{
  "type": "Feature",
  "properties": {
    "addr:full":"311 W Superior Street Chicago IL 60610",
    "addr:housenumber":"311",
    "addr:postcode":"60610",
    "addr:street":"W Superior Street",
    "iso:country":"US",
    "sg:address":"311 W Superior Street",
    "sg:city":"Chicago",
    "sg:classifiers":[
        {
            "category":"Professional",
            "subcategory":"Lawyer & Legal Services",
            "type":"Services"
        },
        {
            "category":"Real Estate",
            "subcategory":"Architect",
            "type":"Services"
        }
    ],
    "sg:phone":"+1 312 642 3344",
    "sg:postcode":"60610",
    "sg:province":"IL",
    "wof:name":"G Goldberg & Associates",
    "wof:placetype":"venue"
},
  "geometry": {"coordinates":[-87.636093,41.895536],"type":"Point"}
}