{
  "type": "Feature",
  "properties": {
    "iso:country":"US",
    "sg:address":"4945 Stone Falls Ctr Ste B",
    "sg:city":"O Fallon",
    "sg:classifiers":[
        {
            "category":"Health Services",
            "subcategory":"Dentist",
            "type":"Services"
        }
    ],
    "sg:phone":"+1 618 622 0212",
    "sg:postcode":"62269",
    "sg:province":"IL",
    "sg:tags":[
        "pediatric"
    ],
    "wof:name":"Rodriguez Francisco DDS",
    "wof:placetype":"venue"
},
  "geometry": {"coordinates":[-89.96268499999999,38.571933],"type":"Point"}
}