{
  "type": "Feature",
  "properties": {
    "iso:country":"US",
    "sg:address":"Damen Ave and 18th St",
    "sg:city":"Chicago",
    "sg:classifiers":[
        {
            "category":"Park",
            "type":"Public Place"
        }
    ],
    "sg:postcode":"60608",
    "sg:province":"IL",
    "wof:name":"Harrison Park",
    "wof:placetype":"venue"
},
  "geometry": {"coordinates":[-87.675974,41.857655],"type":"Point"}
}