{
  "type": "Feature",
  "properties": {
    "addr:full":"951 Creekview Ln Lake In The Hills IL 60156",
    "addr:housenumber":"951",
    "addr:postcode":"60156",
    "addr:street":"Creekview Ln",
    "iso:country":"US",
    "sg:address":"951 Creekview Ln",
    "sg:city":"Lake In The Hills",
    "sg:classifiers":[
        {
            "category":"Wholesale",
            "subcategory":"Chemicals & Plastics",
            "type":"Manufacturing & Wholesale Goods"
        }
    ],
    "sg:phone":"+1 847 878 1994",
    "sg:postcode":"60156",
    "sg:province":"IL",
    "sg:tags":[
        "industrial",
        "solvent"
    ],
    "wof:name":"Solvent Solutions Inc",
    "wof:placetype":"venue"
},
  "geometry": {"coordinates":[-88.310947,42.185383],"type":"Point"}
}