{
  "type": "Feature",
  "properties": {
    "addr:full":"7200 N Clark St Chicago IL 60626",
    "addr:housenumber":"7200",
    "addr:postcode":"60626",
    "addr:street":"N Clark St",
    "iso:country":"US",
    "sg:address":"7200 N Clark St",
    "sg:city":"Chicago",
    "sg:phone":"+1 773 761 4141",
    "sg:postcode":"60626",
    "sg:province":"IL",
    "wof:name":"Romanian Kosher Sausage Co",
    "wof:placetype":"venue"
},
  "geometry": {"coordinates":[-87.674637,42.012642],"type":"Point"}
}