{
  "type": "Feature",
  "properties": {
    "iso:country":"US",
    "sg:address":"1474 E Golf Rd",
    "sg:city":"Schaumburg",
    "sg:classifiers":[
        {
            "category":"Shopping",
            "subcategory":"Clothing, Apparel, & Fashions",
            "type":"Retail Goods"
        },
        {
            "category":"Shopping",
            "subcategory":"Party Supplies",
            "type":"Retail Goods"
        },
        {
            "category":"Shopping",
            "subcategory":"Bridal",
            "type":"Retail Goods"
        }
    ],
    "sg:phone":"+1 847 330 0200",
    "sg:postcode":"60173",
    "sg:province":"IL",
    "sg:tags":[
        "shop",
        "fur",
        "wedding"
    ],
    "wof:name":"Andriana Furs",
    "wof:placetype":"venue"
},
  "geometry": {"coordinates":[-88.041324,42.050611],"type":"Point"}
}