{
  "type": "Feature",
  "properties": {
    "iso:country":"US",
    "sg:address":"5150 W Belmont Avenue",
    "sg:city":"Chicago",
    "sg:classifiers":[
        {
            "category":"Banks & Credit Unions",
            "subcategory":"Financial Services",
            "type":"Services"
        }
    ],
    "sg:phone":"+1 773 202 8311",
    "sg:postcode":"60641",
    "sg:province":"IL",
    "sg:tags":[
        "broker",
        "mortgage"
    ],
    "sg:website":"www.megamortgage.com",
    "wof:name":"Mega Mortgage",
    "wof:placetype":"venue"
},
  "geometry": {"coordinates":[-87.75543,41.93865],"type":"Point"}
}