{
  "type": "Feature",
  "properties": {
    "iso:country":"US",
    "sg:address":"900 N Michigan Ave",
    "sg:city":"Chicago",
    "sg:classifiers":[
        {
            "category":"Shopping",
            "subcategory":"Clothing, Apparel, & Fashions",
            "type":"Retail Goods"
        }
    ],
    "sg:phone":"+1 312 951 7290",
    "sg:postcode":"60611",
    "sg:province":"IL",
    "sg:tags":[
        "lingerie"
    ],
    "wof:name":"Enchante Inc",
    "wof:placetype":"venue"
},
  "geometry": {"coordinates":[-87.624199,41.8992],"type":"Point"}
}