{
  "type": "Feature",
  "properties": {
    "addr:full":"1280 Windham Pkwy Romeoville IL 60446",
    "addr:housenumber":"1280",
    "addr:postcode":"60446",
    "addr:street":"Windham Pkwy",
    "iso:country":"US",
    "sg:address":"1280 Windham Pkwy",
    "sg:city":"Romeoville",
    "sg:classifiers":[
        {
            "category":"Health Services",
            "subcategory":"Doctor",
            "type":"Services"
        }
    ],
    "sg:phone":"+1 630 226 9303",
    "sg:postcode":"60446",
    "sg:province":"IL",
    "sg:tags":[
        "physician",
        "surgeon"
    ],
    "sg:website":"www.ipd.md",
    "wof:name":"Institute For Personal Develop",
    "wof:placetype":"venue"
},
  "geometry": {"coordinates":[-88.121297,41.662273],"type":"Point"}
}