{
  "type": "Feature",
  "properties": {
    "iso:country":"US",
    "sg:address":"1242 E Madison Park",
    "sg:city":"Chicago",
    "sg:classifiers":[
        {
            "category":"Professional",
            "type":"Services"
        }
    ],
    "sg:phone":"+1 773 548 5550",
    "sg:postcode":"60615",
    "sg:province":"IL",
    "sg:tags":[
        "publication",
        "editorial"
    ],
    "sg:website":"http://www.curryyoung.com",
    "wof:name":"Young Curry Consultants",
    "wof:placetype":"venue"
},
  "geometry": {"coordinates":[-87.59654500000001,41.803114],"type":"Point"}
}