{
  "type": "Feature",
  "properties": {
    "iso:country":"US",
    "sg:address":"2863 170th Ave",
    "sg:city":"Sherrard",
    "sg:classifiers":[
        {
            "category":"Professional",
            "subcategory":"Business Services",
            "type":"Services"
        }
    ],
    "sg:phone":"+1 309 283 0857",
    "sg:postcode":"61281",
    "sg:province":"IL",
    "sg:tags":[
        "repossessing"
    ],
    "wof:name":"Twin State Repossessions Inc",
    "wof:placetype":"venue"
},
  "geometry": {"coordinates":[-90.538766,41.312235],"type":"Point"}
}