{
  "type": "Feature",
  "properties": {
    "addr:full":"506 N Chicago St Joliet IL 60432",
    "addr:housenumber":"506",
    "addr:postcode":"60432",
    "addr:street":"N Chicago St",
    "iso:country":"US",
    "sg:address":"506 N Chicago St",
    "sg:city":"Joliet",
    "sg:classifiers":[
        {
            "category":"Science Facility",
            "type":"Public Place"
        }
    ],
    "sg:phone":"+1 815 723 7179",
    "sg:postcode":"60432",
    "sg:province":"IL",
    "sg:tags":[
        "development",
        "laboratories-research"
    ],
    "sg:website":"http://www.instituto-hispano.com",
    "wof:name":"Sugar Cafe",
    "wof:placetype":"venue"
},
  "geometry": {"coordinates":[-88.081833,41.533491],"type":"Point"}
}