{
  "type": "Feature",
  "properties": {
    "addr:full":"5151 Keystone Ct Rolling Meadows IL 60008",
    "addr:housenumber":"5151",
    "addr:postcode":"60008",
    "addr:street":"Keystone Ct",
    "iso:country":"US",
    "sg:address":"5151 Keystone Ct",
    "sg:city":"Rolling Meadows",
    "sg:classifiers":[
        {
            "category":"Retail",
            "subcategory":"Auto Repair",
            "type":"Services"
        }
    ],
    "sg:phone":"+1 847 222 1234",
    "sg:postcode":"60008",
    "sg:province":"IL",
    "sg:tags":[
        "general"
    ],
    "wof:name":"Brandys Automotive",
    "wof:placetype":"venue"
},
  "geometry": {"coordinates":[-88.011269,42.057626],"type":"Point"}
}