{
  "type": "Feature",
  "properties": {
    "addr:full":"1705 E Riverside Blvd Rockford IL 61114",
    "addr:housenumber":"1705",
    "addr:postcode":"61114",
    "addr:street":"E Riverside Blvd",
    "iso:country":"US",
    "sg:address":"1705 E Riverside Blvd",
    "sg:city":"Rockford",
    "sg:classifiers":[
        {
            "category":"Retail",
            "subcategory":"Auto Repair",
            "type":"Services"
        }
    ],
    "sg:phone":"+1 815 282 1010",
    "sg:postcode":"61114",
    "sg:province":"IL",
    "sg:tags":[
        "body",
        "automobile",
        "painting"
    ],
    "wof:name":"All Value Paint & Body",
    "wof:placetype":"venue"
},
  "geometry": {"coordinates":[-89.026674,42.318218],"type":"Point"}
}