{
  "type": "Feature",
  "properties": {
    "iso:country":"US",
    "sg:address":"509 N Locust St",
    "sg:city":"Forreston",
    "sg:classifiers":[
        {
            "category":"Building & Trades",
            "subcategory":"Plumbing",
            "type":"Services"
        }
    ],
    "sg:phone":"+1 815 938 3174",
    "sg:postcode":"61030",
    "sg:province":"IL",
    "sg:tags":[
        "plumbing",
        "contractor"
    ],
    "wof:name":"Rick's Plumbing",
    "wof:placetype":"venue"
},
  "geometry": {"coordinates":[-89.57858400000001,42.133587],"type":"Point"}
}