{
  "type": "Feature",
  "properties": {
    "iso:country":"US",
    "sg:address":"216 N Forest Glen Dr",
    "sg:city":"Hainesville",
    "sg:classifiers":[
        {
            "category":"Retail",
            "subcategory":"Car Wash",
            "type":"Services"
        }
    ],
    "sg:phone":"+1 847 740 1175",
    "sg:postcode":"60073",
    "sg:province":"IL",
    "sg:tags":[
        "automobile",
        "detail",
        "clean"
    ],
    "wof:name":"Rob's Garage",
    "wof:placetype":"venue"
},
  "geometry": {"coordinates":[-88.07562299999999,42.35151],"type":"Point"}
}