{
  "type": "Feature",
  "properties": {
    "iso:country":"US",
    "sg:address":"10750 Co Rd 2",
    "sg:city":"Ipava",
    "sg:classifiers":[
        {
            "category":"Organizations",
            "subcategory":"Religious Organization",
            "type":"Services"
        }
    ],
    "sg:phone":"+1 309 753 8534",
    "sg:postcode":"61441",
    "sg:province":"IL",
    "sg:tags":[
        "church"
    ],
    "wof:name":"Berean Christian Church",
    "wof:placetype":"venue"
},
  "geometry": {"coordinates":[-90.314008,40.350655],"type":"Point"}
}