{
  "type": "Feature",
  "properties": {
    "iso:country":"US",
    "sg:address":"96 River Oaks Center Dr",
    "sg:city":"Calumet City",
    "sg:classifiers":[
        {
            "category":"Ice Cream",
            "type":"Food & Drink"
        }
    ],
    "sg:menulink":"http://www.allmenus.com/il/thornton/243160-baskin-robbins/menu/",
    "sg:phone":"+1 708 862 8610",
    "sg:postcode":"60409",
    "sg:province":"IL",
    "sg:tags":[
        "american"
    ],
    "wof:name":"Baskin-Robbins",
    "wof:placetype":"venue"
},
  "geometry": {"coordinates":[-87.556256,41.59648],"type":"Point"}
}