{
  "type": "Feature",
  "properties": {
    "iso:country":"US",
    "sg:address":"2413 E Martindale Dr",
    "sg:city":"Westchester",
    "sg:classifiers":[
        {
            "category":"Banks & Credit Unions",
            "subcategory":"Investment Brokerage",
            "type":"Services"
        }
    ],
    "sg:phone":"+1 708 562 2570",
    "sg:postcode":"60154",
    "sg:province":"IL",
    "sg:tags":[
        "consultant",
        "planning",
        "financial"
    ],
    "wof:name":"Fiduciary Services Inc",
    "wof:placetype":"venue"
},
  "geometry": {"coordinates":[-87.892404,41.843533],"type":"Point"}
}