{
  "type": "Feature",
  "properties": {
    "iso:country":"US",
    "sg:address":"1507 Fairwood St",
    "sg:city":"Danville",
    "sg:classifiers":[
        {
            "category":"Arts & Performance",
            "subcategory":"Theater",
            "type":"Entertainment"
        }
    ],
    "sg:phone":"+1 217 443 6813",
    "sg:postcode":"61832",
    "sg:province":"IL",
    "sg:tags":[
        "live",
        "music"
    ],
    "wof:name":"M & M Entertainment",
    "wof:placetype":"venue"
},
  "geometry": {"coordinates":[-87.59611,40.145147],"type":"Point"}
}