{
  "type": "Feature",
  "properties": {
    "iso:country":"US",
    "sg:address":"1973 W 111th St",
    "sg:city":"Chicago",
    "sg:classifiers":[
        {
            "category":"Professional",
            "type":"Services"
        }
    ],
    "sg:phone":"+1 773 779 7720",
    "sg:postcode":"60643",
    "sg:province":"IL",
    "sg:tags":[
        "caterer"
    ],
    "wof:name":"Lonigan's Catering",
    "wof:placetype":"venue"
},
  "geometry": {"coordinates":[-87.67130299999999,41.691799],"type":"Point"}
}