{
  "type": "Feature",
  "properties": {
    "iso:country":"US",
    "sg:address":"536 S Clark St",
    "sg:city":"Chicago",
    "sg:classifiers":[
        {
            "category":"Professional",
            "subcategory":"Lawyer & Legal Services",
            "type":"Services"
        }
    ],
    "sg:phone":"+1 312 239 5900",
    "sg:postcode":"60605",
    "sg:province":"IL",
    "sg:tags":[
        "consultant",
        "attorney",
        "law",
        "immigration",
        "naturalization"
    ],
    "wof:name":"U S Citizenship & Immigration Services",
    "wof:placetype":"venue"
},
  "geometry": {"coordinates":[-87.630691,41.875159],"type":"Point"}
}