{
  "type": "Feature",
  "properties": {
    "addr:full":"614 Claridge Cir Hoffman Estates IL 60194",
    "addr:housenumber":"614",
    "addr:postcode":"60194",
    "addr:street":"Claridge Cir",
    "iso:country":"US",
    "sg:address":"614 Claridge Cir",
    "sg:city":"Hoffman Estates",
    "sg:classifiers":[
        {
            "category":"Social Services",
            "type":"Services"
        }
    ],
    "sg:phone":"+1 847 310 4511",
    "sg:postcode":"60194",
    "sg:province":"IL",
    "sg:tags":[
        "counselor",
        "marriage",
        "family"
    ],
    "wof:name":"Comprehensive Counseling Svc",
    "wof:placetype":"venue"
},
  "geometry": {"coordinates":[-88.106106,42.03797],"type":"Point"}
}