{
  "type": "Feature",
  "properties": {
    "iso:country":"US",
    "sg:address":"9340 Skokie Blvd",
    "sg:city":"Skokie",
    "sg:phone":"+1 847 676 0467",
    "sg:postcode":"60077",
    "sg:province":"IL",
    "wof:name":"Turtle Wax Car Wash",
    "wof:placetype":"venue"
},
  "geometry": {"coordinates":[-87.74687400000001,42.050803],"type":"Point"}
}