{
  "type": "Feature",
  "properties": {
    "iso:country":"US",
    "sg:address":"3620 Fairway Pl",
    "sg:city":"Rockford",
    "sg:classifiers":[
        {
            "category":"Food & Beverages",
            "subcategory":"Specialty",
            "type":"Retail Goods"
        }
    ],
    "sg:phone":"+1   ",
    "sg:postcode":"61107",
    "sg:province":"IL",
    "wof:name":"Ed-U-Co Marketing",
    "wof:placetype":"venue"
},
  "geometry": {"coordinates":[-89.032078,42.290419],"type":"Point"}
}