{
  "type": "Feature",
  "properties": {
    "addr:full":"2959 W Belmont Ave Chicago IL 60618",
    "addr:housenumber":"2959",
    "addr:postcode":"60618",
    "addr:street":"W Belmont Ave",
    "iso:country":"US",
    "sg:address":"2959 W Belmont Ave",
    "sg:city":"Chicago",
    "sg:classifiers":[
        {
            "category":"Food & Beverages",
            "subcategory":"Groceries & Convenience Stores",
            "type":"Retail Goods"
        }
    ],
    "sg:phone":"+1 773 865 5982",
    "sg:postcode":"60618",
    "sg:province":"IL",
    "wof:name":"RT Food Mart",
    "wof:placetype":"venue"
},
  "geometry": {"coordinates":[-87.702547,41.939104],"type":"Point"}
}