{
  "type": "Feature",
  "properties": {
    "iso:country":"US",
    "sg:address":"20251 N 1750th St",
    "sg:city":"Chrisman",
    "sg:phone":"+1 217 269 2058",
    "sg:postcode":"61924",
    "sg:province":"IL",
    "sg:tags":[
        "farm",
        "corn",
        "soybean"
    ],
    "wof:name":"E Glithero",
    "wof:placetype":"venue"
},
  "geometry": {"coordinates":[-87.64353300000001,39.76892],"type":"Point"}
}