{
  "type": "Feature",
  "properties": {
    "addr:full":"2950 Kane Rd Leland IL 60531",
    "addr:housenumber":"2950",
    "addr:postcode":"60531",
    "addr:street":"Kane Rd",
    "iso:country":"US",
    "sg:address":"2950 Kane Rd",
    "sg:city":"Leland",
    "sg:classifiers":[
        {
            "category":"Freight",
            "type":"Transportation"
        }
    ],
    "sg:phone":"+1 815 495 9024",
    "sg:postcode":"60531",
    "sg:province":"IL",
    "sg:tags":[
        "operator",
        "trucking"
    ],
    "wof:name":"Wild West Express Inc",
    "wof:placetype":"venue"
},
  "geometry": {"coordinates":[-88.828497,41.669863],"type":"Point"}
}