{
  "type": "Feature",
  "properties": {
    "addr:full":"1201 E Florida Ave Urbana IL 61801",
    "addr:housenumber":"1201",
    "addr:postcode":"61801",
    "addr:street":"E Florida Ave",
    "iso:country":"US",
    "sg:address":"1201 E Florida Ave",
    "sg:city":"Urbana",
    "sg:classifiers":[
        {
            "category":"Building & Trades",
            "subcategory":"Cleaning & Sanitation",
            "type":"Services"
        }
    ],
    "sg:phone":"+1 217 840 1954",
    "sg:postcode":"61801",
    "sg:province":"IL",
    "sg:tags":[
        "apartment",
        "maintenance"
    ],
    "wof:name":"Protective Maintenance Service",
    "wof:placetype":"venue"
},
  "geometry": {"coordinates":[-88.19472,40.098293],"type":"Point"}
}