{
  "type": "Feature",
  "properties": {
    "iso:country":"US",
    "sg:address":"1611 10th St",
    "sg:city":"Silvis",
    "sg:classifiers":[
        {
            "category":"Retail",
            "subcategory":"Auto Repair",
            "type":"Services"
        }
    ],
    "sg:phone":"+1 309 792 0072",
    "sg:postcode":"61282",
    "sg:province":"IL",
    "sg:tags":[
        "muffler",
        "exhaust",
        "system"
    ],
    "wof:name":"Ed's Auto Muffler & Brake",
    "wof:placetype":"venue"
},
  "geometry": {"coordinates":[-90.41557899999999,41.493074],"type":"Point"}
}