{
  "type": "Feature",
  "properties": {
    "addr:full":"1608 N Main St Rockford IL 61103",
    "addr:housenumber":"1608",
    "addr:postcode":"61103",
    "addr:street":"N Main St",
    "iso:country":"US",
    "sg:address":"1608 N Main St",
    "sg:city":"Rockford",
    "sg:classifiers":[
        {
            "category":"Building & Trades",
            "subcategory":"Construction",
            "type":"Services"
        }
    ],
    "sg:phone":"+1 815 623 3131",
    "sg:postcode":"61103",
    "sg:province":"IL",
    "sg:tags":[
        "contractor"
    ],
    "wof:name":"Top Shelf Inc",
    "wof:placetype":"venue"
},
  "geometry": {"coordinates":[-89.079488,42.290535],"type":"Point"}
}