{
  "type": "Feature",
  "properties": {
    "addr:full":"735 N Van Buren Ave Freeport IL 61032",
    "addr:housenumber":"735",
    "addr:postcode":"61032",
    "addr:street":"N Van Buren Ave",
    "iso:country":"US",
    "sg:address":"735 N Van Buren Ave",
    "sg:city":"Freeport",
    "sg:classifiers":[
        {
            "category":"Utilities",
            "subcategory":"Refuse",
            "type":"Services"
        }
    ],
    "sg:phone":"+1 815 233 5644",
    "sg:postcode":"61032",
    "sg:province":"IL",
    "sg:tags":[
        "garbage",
        "collection"
    ],
    "wof:name":"Gill's Freeport Disposal Inc",
    "wof:placetype":"venue"
},
  "geometry": {"coordinates":[-89.62514400000001,42.303363],"type":"Point"}
}