{
  "type": "Feature",
  "properties": {
    "iso:country":"US",
    "sg:address":"8378 Freeport Rd",
    "sg:city":"Durand",
    "sg:classifiers":[
        {
            "category":"Real Estate",
            "subcategory":"Real Estate Agent",
            "type":"Services"
        }
    ],
    "sg:phone":"+1 815 629 2698",
    "sg:postcode":"61024",
    "sg:province":"IL",
    "wof:name":"P M Real Estate LLC",
    "wof:placetype":"venue"
},
  "geometry": {"coordinates":[-89.20191699999999,42.425092],"type":"Point"}
}