{
  "type": "Feature",
  "properties": {
    "addr:full":"2626 N Lakeview Ave Apt 3306 Chicago IL 60614",
    "addr:housenumber":"2626",
    "addr:postcode":"60614",
    "addr:street":"N Lakeview Ave Apt 3306",
    "iso:country":"US",
    "sg:address":"2626 N Lakeview Ave Apt 3306",
    "sg:city":"Chicago",
    "sg:classifiers":[
        {
            "category":"Professional",
            "subcategory":"Employment Agencies",
            "type":"Services"
        }
    ],
    "sg:phone":"+1 773 404 9562",
    "sg:postcode":"60614",
    "sg:province":"IL",
    "wof:name":"Coverage Inc",
    "wof:placetype":"venue"
},
  "geometry": {"coordinates":[-87.639297,41.930099],"type":"Point"}
}