{
  "type": "Feature",
  "properties": {
    "addr:full":"6554 N Mozart St Chicago IL 60645",
    "addr:housenumber":"6554",
    "addr:postcode":"60645",
    "addr:street":"N Mozart St",
    "iso:country":"US",
    "sg:address":"6554 N Mozart St",
    "sg:city":"Chicago",
    "sg:classifiers":[
        {
            "category":"Travel",
            "subcategory":"Hotels & Motels",
            "type":"Entertainment"
        },
        {
            "category":"Personal",
            "type":"Services"
        }
    ],
    "sg:phone":"+1 773 764 3068",
    "sg:postcode":"60645",
    "sg:province":"IL",
    "sg:tags":[
        "assistant",
        "concierge"
    ],
    "wof:name":"Tibetan Healing Arts Center, Nfp",
    "wof:placetype":"venue"
},
  "geometry": {"coordinates":[-87.70093900000001,42.000358],"type":"Point"}
}