{
  "type": "Feature",
  "properties": {
    "iso:country":"US",
    "sg:address":"136 N York St",
    "sg:city":"Elmhurst",
    "sg:classifiers":[
        {
            "category":"Banks & Credit Unions",
            "subcategory":"Bank",
            "type":"Services"
        }
    ],
    "sg:phone":"+1 630 758 1381",
    "sg:postcode":"60126",
    "sg:province":"IL",
    "wof:name":"Citigroup",
    "wof:placetype":"venue"
},
  "geometry": {"coordinates":[-87.93995700000001,41.901081],"type":"Point"}
}