{
  "type": "Feature",
  "properties": {
    "addr:full":"55 E Washington Street Chicago IL 60602",
    "addr:housenumber":"55",
    "addr:postcode":"60602",
    "addr:street":"E Washington Street",
    "iso:country":"US",
    "sg:address":"55 E Washington Street",
    "sg:city":"Chicago",
    "sg:classifiers":[
        {
            "category":"Health Services",
            "subcategory":"Doctor",
            "type":"Services"
        }
    ],
    "sg:phone":"+1 312 553 9620",
    "sg:postcode":"60602",
    "sg:province":"IL",
    "wof:name":"Stefancic Michael F MD",
    "wof:placetype":"venue"
},
  "geometry": {"coordinates":[-87.62562200000001,41.883166],"type":"Point"}
}