{
  "type": "Feature",
  "properties": {
    "addr:full":"122 Hamilton Rd Arlington Heights IL 60005",
    "addr:housenumber":"122",
    "addr:postcode":"60005",
    "addr:street":"Hamilton Rd",
    "iso:country":"US",
    "sg:address":"122 Hamilton Rd",
    "sg:city":"Arlington Heights",
    "sg:classifiers":[
        {
            "category":"Manufacturing",
            "subcategory":"Metals",
            "type":"Manufacturing & Wholesale Goods"
        }
    ],
    "sg:phone":"+1 847 439 5720",
    "sg:postcode":"60005",
    "sg:province":"IL",
    "sg:tags":[
        "machine",
        "screw",
        "product",
        "mfg"
    ],
    "wof:name":"Remco Swiss Ltd",
    "wof:placetype":"venue"
},
  "geometry": {"coordinates":[-87.95027899999999,42.021395],"type":"Point"}
}