{
  "type": "Feature",
  "properties": {
    "iso:country":"US",
    "sg:address":"579 N 1st Bank Dr",
    "sg:city":"Palatine",
    "sg:classifiers":[
        {
            "category":"Education",
            "subcategory":"Vocational School",
            "type":"Public Place"
        }
    ],
    "sg:phone":"+1 847 705 3838",
    "sg:postcode":"60067",
    "sg:province":"IL",
    "sg:tags":[
        "insurance"
    ],
    "wof:name":"Professional Training Services",
    "wof:placetype":"venue"
},
  "geometry": {"coordinates":[-88.035961,42.120854],"type":"Point"}
}