{
  "type": "Feature",
  "properties": {
    "iso:country":"US",
    "sg:address":"7720 Exchange Rd",
    "sg:city":"Texico",
    "sg:classifiers":[
        {
            "category":"Professional",
            "type":"Services"
        }
    ],
    "sg:phone":"+1 618 822 6677",
    "sg:postcode":"62889",
    "sg:province":"IL",
    "wof:name":"Greens Services",
    "wof:placetype":"venue"
},
  "geometry": {"coordinates":[-88.78890800000001,38.482899],"type":"Point"}
}