{
  "type": "Feature",
  "properties": {
    "iso:country":"US",
    "sg:address":"1428 Hamilton Ct",
    "sg:city":"Waukegan",
    "sg:classifiers":[
        {
            "category":"Building & Trades",
            "subcategory":"Landscaping Services",
            "type":"Services"
        }
    ],
    "sg:phone":"+1 847 249 9106",
    "sg:postcode":"60085",
    "sg:province":"IL",
    "wof:name":"Lopez & Lopez Landscaping",
    "wof:placetype":"venue"
},
  "geometry": {"coordinates":[-87.851129,42.360572],"type":"Point"}
}