{
  "type": "Feature",
  "properties": {
    "iso:country":"US",
    "sg:address":"1122 N 4th St",
    "sg:city":"Chillicothe",
    "sg:classifiers":[
        {
            "category":"Restaurant",
            "type":"Food & Drink"
        }
    ],
    "sg:phone":"+1 309 274 5488",
    "sg:postcode":"61523",
    "sg:province":"IL",
    "sg:tags":[
        "eating"
    ],
    "wof:name":"LA Gondola Spaghetti House",
    "wof:placetype":"venue"
},
  "geometry": {"coordinates":[-89.487209,40.919681],"type":"Point"}
}