{
  "type": "Feature",
  "properties": {
    "addr:full":"27781 W Concrete Dr Ingleside IL 60041",
    "addr:housenumber":"27781",
    "addr:postcode":"60041",
    "addr:street":"W Concrete Dr",
    "iso:country":"US",
    "sg:address":"27781 W Concrete Dr",
    "sg:city":"Ingleside",
    "sg:classifiers":[
        {
            "category":"Professional",
            "type":"Services"
        }
    ],
    "sg:phone":"+1 815 759 9273",
    "sg:postcode":"60041",
    "sg:province":"IL",
    "sg:tags":[
        "establishment"
    ],
    "wof:name":"A & D",
    "wof:placetype":"venue"
},
  "geometry": {"coordinates":[-88.175574,42.335038],"type":"Point"}
}