{
  "type": "Feature",
  "properties": {
    "iso:country":"US",
    "sg:address":"309 West Superior",
    "sg:city":"Chicago",
    "sg:classifiers":[
        {
            "category":"Home & Garden",
            "subcategory":"Home Furnishings",
            "type":"Retail Goods"
        },
        {
            "category":"Home & Garden",
            "subcategory":"Furniture",
            "type":"Retail Goods"
        }
    ],
    "sg:phone":"+1 312 664 6190",
    "sg:postcode":"60654",
    "sg:province":"IL",
    "sg:tags":[
        "decor",
        "store"
    ],
    "sg:website":"www.maxalto.it",
    "wof:name":"Maxalto",
    "wof:placetype":"venue"
},
  "geometry": {"coordinates":[-87.63594999999999,41.895326],"type":"Point"}
}