{
  "type": "Feature",
  "properties": {
    "iso:country":"US",
    "sg:address":"8844 W Steger Rd",
    "sg:city":"Frankfort",
    "sg:classifiers":[
        {
            "category":"Manufacturing",
            "subcategory":"Printing",
            "type":"Manufacturing & Wholesale Goods"
        }
    ],
    "sg:phone":"+1 708 333 1516",
    "sg:postcode":"60423",
    "sg:province":"IL",
    "sg:tags":[
        "screen"
    ],
    "wof:name":"B Creative Screen Print Co",
    "wof:placetype":"venue"
},
  "geometry": {"coordinates":[-87.833703,41.470025],"type":"Point"}
}