{
  "type": "Feature",
  "properties": {
    "addr:full":"1001 N Milwaukee Ave Libertyville IL 60048",
    "addr:housenumber":"1001",
    "addr:postcode":"60048",
    "addr:street":"N Milwaukee Ave",
    "iso:country":"US",
    "sg:address":"1001 N Milwaukee Ave",
    "sg:city":"Libertyville",
    "sg:classifiers":[
        {
            "category":"Autos & Motor Vehicles",
            "subcategory":"Auto Supplies",
            "type":"Retail Goods"
        },
        {
            "category":"Retail",
            "subcategory":"Auto Repair",
            "type":"Services"
        }
    ],
    "sg:phone":"+1 847 362 4110",
    "sg:postcode":"60048",
    "sg:province":"IL",
    "sg:tags":[
        "automobile",
        "part",
        "truck"
    ],
    "sg:website":"http://clickserve.dartsearch.net/link/click?lid=43000000313869821&ds_s_kwgid=58000000006820725&ds_e_matchtype={MatchType}&ds_e_kwdid={OrderItemId}&ds_e_adid={AdId}&ds_url_v=2",
    "wof:name":"Berry's Tire Outlet",
    "wof:placetype":"venue"
},
  "geometry": {"coordinates":[-87.94581599999999,42.248146],"type":"Point"}
}