{
  "type": "Feature",
  "properties": {
    "iso:country":"US",
    "sg:address":"672 Cambridge Way",
    "sg:city":"Bolingbrook",
    "sg:classifiers":[
        {
            "category":"Social Services",
            "subcategory":"Child Care",
            "type":"Services"
        }
    ],
    "sg:phone":"+1 630 985 3418",
    "sg:postcode":"60440",
    "sg:province":"IL",
    "sg:tags":[
        "day"
    ],
    "wof:name":"PC Learning Centre",
    "wof:placetype":"venue"
},
  "geometry": {"coordinates":[-88.04079400000001,41.731389],"type":"Point"}
}