{
  "type": "Feature",
  "properties": {
    "iso:country":"US",
    "sg:address":"3354 Windsong",
    "sg:city":"Rockford",
    "sg:classifiers":[
        {
            "category":"Professional",
            "subcategory":"Employment Agencies",
            "type":"Services"
        }
    ],
    "sg:phone":"+1 815 636 9922",
    "sg:postcode":"61114",
    "sg:province":"IL",
    "sg:tags":[
        "help",
        "supply"
    ],
    "wof:name":"Gb Air Inc",
    "wof:placetype":"venue"
},
  "geometry": {"coordinates":[-88.982388,42.308856],"type":"Point"}
}