{
  "type": "Feature",
  "properties": {
    "addr:full":"3344 S Halsted St Chicago IL 60608",
    "addr:housenumber":"3344",
    "addr:postcode":"60608",
    "addr:street":"S Halsted St",
    "iso:country":"US",
    "sg:address":"3344 S Halsted St",
    "sg:city":"Chicago",
    "sg:classifiers":[
        {
            "category":"Health Services",
            "subcategory":"Doctor",
            "type":"Services"
        }
    ],
    "sg:phone":"+1 773 523 9550",
    "sg:postcode":"60608",
    "sg:province":"IL",
    "wof:name":"Nicholas Stiso MD",
    "wof:placetype":"venue"
},
  "geometry": {"coordinates":[-87.64630099999999,41.833401],"type":"Point"}
}