{
  "type": "Feature",
  "properties": {
    "iso:country":"US",
    "sg:address":"725 Kimberly Dr",
    "sg:city":"Carol Stream",
    "sg:classifiers":[
        {
            "category":"Manufacturing",
            "subcategory":"Chemicals & Compounds",
            "type":"Manufacturing & Wholesale Goods"
        }
    ],
    "sg:phone":"+1 630 653 1756",
    "sg:postcode":"60188",
    "sg:province":"IL",
    "sg:tags":[
        "mfg",
        "product",
        "printing",
        "ink"
    ],
    "wof:name":"Valspar Corporation",
    "wof:placetype":"venue"
},
  "geometry": {"coordinates":[-88.112703,41.918487],"type":"Point"}
}