{
  "type": "Feature",
  "properties": {
    "iso:country":"US",
    "sg:address":"1156 Durham Dr",
    "sg:city":"Wheaton",
    "sg:classifiers":[
        {
            "category":"Health Services",
            "subcategory":"Health Practitioner",
            "type":"Services"
        }
    ],
    "sg:phone":"+1 630 690 1462",
    "sg:postcode":"60187",
    "sg:province":"IL",
    "wof:name":"Jesse L Schuttinga Dr",
    "wof:placetype":"venue"
},
  "geometry": {"coordinates":[-88.089608,41.825421],"type":"Point"}
}