{
  "type": "Feature",
  "properties": {
    "addr:full":"418 Davis Rd Batavia IL 60510",
    "addr:housenumber":"418",
    "addr:postcode":"60510",
    "addr:street":"Davis Rd",
    "iso:country":"US",
    "sg:address":"418 Davis Rd",
    "sg:city":"Batavia",
    "sg:classifiers":[
        {
            "category":"Freight",
            "type":"Transportation"
        }
    ],
    "sg:phone":"+1 630 406 6082",
    "sg:postcode":"60510",
    "sg:province":"IL",
    "wof:name":"MAC Logistics",
    "wof:placetype":"venue"
},
  "geometry": {"coordinates":[-88.299277,41.863792],"type":"Point"}
}