{
  "type": "Feature",
  "properties": {
    "addr:full":"1205 N. Dearborn Chicago IL 60610",
    "addr:housenumber":"1205",
    "addr:postcode":"60610",
    "addr:street":"N.",
    "iso:country":"US",
    "sg:address":"1205 N. Dearborn",
    "sg:city":"Chicago",
    "sg:classifiers":[
        {
            "category":"Real Estate",
            "subcategory":"Real Estate Services",
            "type":"Services"
        },
        {
            "category":"Real Estate",
            "subcategory":"Real Estate Agent",
            "type":"Services"
        }
    ],
    "sg:phone":"+1 312 485 9868",
    "sg:postcode":"60610",
    "sg:province":"IL",
    "sg:tags":[
        "management",
        "property"
    ],
    "sg:website":"www.mikekravitzrealtor.com",
    "wof:name":"Mike Kravitz Realtor- Gold Coast Realty",
    "wof:placetype":"venue"
},
  "geometry": {"coordinates":[-87.63069900000001,41.902679],"type":"Point"}
}