{
  "type": "Feature",
  "properties": {
    "iso:country":"US",
    "sg:address":"26888 Shake Rag Rd",
    "sg:city":"Danville",
    "sg:classifiers":[
        {
            "category":"Home & Garden",
            "subcategory":"Building Materials",
            "type":"Retail Goods"
        }
    ],
    "sg:phone":"+1 217 759 7554",
    "sg:postcode":"61834",
    "sg:province":"IL",
    "sg:tags":[
        "windows",
        "door",
        "window",
        "installation"
    ],
    "wof:name":"Bismarck Windows & Doors",
    "wof:placetype":"venue"
},
  "geometry": {"coordinates":[-87.622829,40.252346],"type":"Point"}
}