{
  "type": "Feature",
  "properties": {
    "iso:country":"US",
    "sg:address":"200 W 5th St",
    "sg:city":"Tilton",
    "sg:classifiers":[
        {
            "category":"Restaurant",
            "type":"Food & Drink"
        }
    ],
    "sg:phone":"+1 217 446 5930",
    "sg:postcode":"61833",
    "sg:province":"IL",
    "wof:name":"Whooligan's Restaurant",
    "wof:placetype":"venue"
},
  "geometry": {"coordinates":[-87.653475,40.101577],"type":"Point"}
}