{
  "type": "Feature",
  "properties": {
    "addr:full":"1526 W Nelson St Chicago IL 60657",
    "addr:housenumber":"1526",
    "addr:postcode":"60657",
    "addr:street":"W Nelson St",
    "iso:country":"US",
    "sg:address":"1526 W Nelson St",
    "sg:city":"Chicago",
    "sg:classifiers":[
        {
            "category":"Wholesale",
            "subcategory":"Drugs",
            "type":"Manufacturing & Wholesale Goods"
        }
    ],
    "sg:phone":"+1 773 525 2588",
    "sg:postcode":"60657",
    "sg:province":"IL",
    "sg:tags":[
        "cosmetic"
    ],
    "wof:name":"Aloe Scientific Labs Inc",
    "wof:placetype":"venue"
},
  "geometry": {"coordinates":[-87.667957,41.936963],"type":"Point"}
}