{
  "type": "Feature",
  "properties": {
    "addr:full":"1180 N Arlington Heights Rd Itasca IL 60143",
    "addr:housenumber":"1180",
    "addr:postcode":"60143",
    "addr:street":"N Arlington Heights Rd",
    "iso:country":"US",
    "sg:address":"1180 N Arlington Heights Rd",
    "sg:city":"Itasca",
    "sg:classifiers":[
        {
            "category":"Restaurant",
            "type":"Food & Drink"
        }
    ],
    "sg:phone":"+1 630 773 0722",
    "sg:postcode":"60143",
    "sg:province":"IL",
    "sg:tags":[
        "mexican"
    ],
    "wof:name":"Besa Mi Taco",
    "wof:placetype":"venue"
},
  "geometry": {"coordinates":[-88.003326,41.987108],"type":"Point"}
}