{
  "type": "Feature",
  "properties": {
    "addr:full":"16426 Dorchester Pl Lockport IL 60441",
    "addr:housenumber":"16426",
    "addr:postcode":"60441",
    "addr:street":"Dorchester Pl",
    "iso:country":"US",
    "sg:address":"16426 Dorchester Pl",
    "sg:city":"Lockport",
    "sg:classifiers":[
        {
            "category":"Manufacturing",
            "subcategory":"Apparel",
            "type":"Manufacturing & Wholesale Goods"
        }
    ],
    "sg:phone":"+1 708 301 2892",
    "sg:postcode":"60441",
    "sg:province":"IL",
    "sg:tags":[
        "retail",
        "direct",
        "embroidery",
        "sale"
    ],
    "sg:website":"http://www.momentssewcherished.com",
    "wof:name":"Moments Sew Cherished",
    "wof:placetype":"venue"
},
  "geometry": {"coordinates":[-87.973793,41.588583],"type":"Point"}
}