{
  "type": "Feature",
  "properties": {
    "iso:country":"US",
    "sg:address":"1200 Armstrong St",
    "sg:city":"Algonquin",
    "sg:classifiers":[
        {
            "category":"Autos & Motor Vehicles",
            "subcategory":"Auto Supplies",
            "type":"Retail Goods"
        },
        {
            "category":"Retail",
            "subcategory":"Auto Repair",
            "type":"Services"
        }
    ],
    "sg:phone":"+1 847 658 7700",
    "sg:postcode":"60102",
    "sg:province":"IL",
    "sg:tags":[
        "automobile",
        "part",
        "truck"
    ],
    "sg:website":"http://clickserve.dartsearch.net/link/click?lid=43000000313869374&ds_s_kwgid=58000000006820725&ds_e_matchtype={MatchType}&ds_e_kwdid={OrderItemId}&ds_e_adid={AdId}&ds_url_v=2",
    "wof:name":"Teson Automotive",
    "wof:placetype":"venue"
},
  "geometry": {"coordinates":[-88.30362700000001,42.172131],"type":"Point"}
}