{
  "type": "Feature",
  "properties": {
    "iso:country":"US",
    "sg:address":"1250 E Diehl Rd",
    "sg:city":"Naperville",
    "sg:classifiers":[
        {
            "category":"Professional",
            "subcategory":"Accounting & Tax Preparation",
            "type":"Services"
        },
        {
            "category":"Professional",
            "subcategory":"Lawyer & Legal Services",
            "type":"Services"
        }
    ],
    "sg:phone":"+1 630 505 4696",
    "sg:postcode":"60563",
    "sg:province":"IL",
    "sg:tags":[
        "attorney",
        "trust",
        "return",
        "estate",
        "accountants-certified",
        "corporation",
        "wills",
        "partnership",
        "planning",
        "law",
        "public"
    ],
    "wof:name":"Trauscht Michael R CPA PC",
    "wof:placetype":"venue"
},
  "geometry": {"coordinates":[-88.12284099999999,41.802319],"type":"Point"}
}