{
  "type": "Feature",
  "properties": {
    "iso:country":"US",
    "sg:address":"471 75th St",
    "sg:city":"Naperville",
    "sg:classifiers":[
        {
            "category":"Professional",
            "subcategory":"Advertising",
            "type":"Services"
        },
        {
            "category":"Retail",
            "subcategory":"Veterinary Services",
            "type":"Services"
        },
        {
            "category":"Retail",
            "subcategory":"Pet Boarding",
            "type":"Services"
        }
    ],
    "sg:phone":"+1 630 305 7200",
    "sg:postcode":"60565",
    "sg:province":"IL",
    "sg:tags":[
        "coupon",
        "veterinarian",
        "kennel"
    ],
    "sg:website":"http://www.animalhealthcarepc.com",
    "wof:name":"Animal Health Care PC",
    "wof:placetype":"venue"
},
  "geometry": {"coordinates":[-88.070213,41.749815],"type":"Point"}
}