{
  "type": "Feature",
  "properties": {
    "iso:country":"US",
    "sg:address":"804 W Anthony Dr",
    "sg:city":"Champaign",
    "sg:classifiers":[
        {
            "category":"Home & Garden",
            "subcategory":"Hardware",
            "type":"Retail Goods"
        }
    ],
    "sg:phone":"+1   ",
    "sg:postcode":"61822",
    "sg:province":"IL",
    "sg:tags":[
        "fastener"
    ],
    "wof:name":"Zz Hardware",
    "wof:placetype":"venue"
},
  "geometry": {"coordinates":[-88.25075699999999,40.135034],"type":"Point"}
}