{
  "type": "Feature",
  "properties": {
    "addr:full":"1303 W 3rd St Dixon IL 61021",
    "addr:housenumber":"1303",
    "addr:postcode":"61021",
    "addr:street":"W 3Rd St",
    "iso:country":"US",
    "sg:address":"1303 W 3rd St",
    "sg:city":"Dixon",
    "sg:classifiers":[
        {
            "category":"Building & Trades",
            "subcategory":"Construction",
            "type":"Services"
        }
    ],
    "sg:phone":"+1 815 284 2199",
    "sg:postcode":"61021",
    "sg:province":"IL",
    "sg:tags":[
        "general",
        "contractor"
    ],
    "wof:name":"Remrey Excavating & Carpentry",
    "wof:placetype":"venue"
},
  "geometry": {"coordinates":[-89.496263,41.838181],"type":"Point"}
}