{
  "type": "Feature",
  "properties": {
    "iso:country":"US",
    "sg:address":"1106 Morse Ave",
    "sg:city":"Schaumburg",
    "sg:classifiers":[
        {
            "category":"Building & Trades",
            "subcategory":"Construction",
            "type":"Services"
        }
    ],
    "sg:phone":"+1 847 352 4371",
    "sg:postcode":"60193",
    "sg:province":"IL",
    "sg:tags":[
        "general",
        "contractor"
    ],
    "wof:name":"F J Lawdensky Construction Co",
    "wof:placetype":"venue"
},
  "geometry": {"coordinates":[-88.105086,42.000124],"type":"Point"}
}