{
  "type": "Feature",
  "properties": {
    "iso:country":"US",
    "sg:address":"5973 N Clark St",
    "sg:city":"Chicago",
    "sg:classifiers":[
        {
            "category":"Restaurant",
            "type":"Food & Drink"
        }
    ],
    "sg:menulink":"http://www.allmenus.com/il/chicago/210048-los-perez-restaurante/menu/",
    "sg:phone":"+1 773 728 3066",
    "sg:postcode":"60660",
    "sg:province":"IL",
    "sg:tags":[
        "mexican"
    ],
    "wof:name":"Los Perez Restaurante",
    "wof:placetype":"venue"
},
  "geometry": {"coordinates":[-87.66983500000001,41.990099],"type":"Point"}
}