{
  "type": "Feature",
  "properties": {
    "iso:country":"US",
    "sg:address":"1900 W Field Ct",
    "sg:city":"Lake Forest",
    "sg:classifiers":[
        {
            "category":"Manufacturing",
            "subcategory":"Paper Products",
            "type":"Manufacturing & Wholesale Goods"
        }
    ],
    "sg:phone":"+1 847 482 3000",
    "sg:postcode":"60045",
    "sg:province":"IL",
    "sg:tags":[
        "corrugated",
        "container",
        "mfg"
    ],
    "sg:website":"www.packagingcorp.com",
    "wof:name":"Packaging Corporation America",
    "wof:placetype":"venue"
},
  "geometry": {"coordinates":[-87.89173599999999,42.242399],"type":"Point"}
}