{
  "type": "Feature",
  "properties": {
    "addr:full":"227 Bucklin St La Salle IL 61301",
    "addr:housenumber":"227",
    "addr:postcode":"61301",
    "addr:street":"Bucklin St",
    "iso:country":"US",
    "sg:address":"227 Bucklin St",
    "sg:city":"La Salle",
    "sg:classifiers":[
        {
            "category":"Professional",
            "subcategory":"Computer Services",
            "type":"Services"
        }
    ],
    "sg:phone":"+1 815 223 7953",
    "sg:postcode":"61301",
    "sg:province":"IL",
    "sg:tags":[
        "programing",
        "custom"
    ],
    "sg:website":"www.prokupmedia.com",
    "wof:name":"Prokup Media Inc",
    "wof:placetype":"venue"
},
  "geometry": {"coordinates":[-89.099962,41.329647],"type":"Point"}
}