{
  "type": "Feature",
  "properties": {
    "iso:country":"US",
    "sg:address":"3 Orchard Dr",
    "sg:city":"Camargo",
    "sg:phone":"+1 217 832 9067",
    "sg:postcode":"61919",
    "sg:province":"IL",
    "sg:tags":[
        "farm",
        "corn"
    ],
    "wof:name":"Sigler Farms",
    "wof:placetype":"venue"
},
  "geometry": {"coordinates":[-88.162234,39.795827],"type":"Point"}
}