{
  "type": "Feature",
  "properties": {
    "iso:country":"US",
    "sg:address":"951 Arbor Trl",
    "sg:city":"Decatur",
    "sg:classifiers":[
        {
            "category":"Farming",
            "subcategory":"Farm",
            "type":"Manufacturing & Wholesale Goods"
        }
    ],
    "sg:phone":"+1 217 877 3752",
    "sg:postcode":"62526",
    "sg:province":"IL",
    "wof:name":"Evans Farms",
    "wof:placetype":"venue"
},
  "geometry": {"coordinates":[-88.971675,39.905586],"type":"Point"}
}