{
  "type": "Feature",
  "properties": {
    "iso:country":"US",
    "sg:address":"125 W Macarthur Dr",
    "sg:city":"Cottage Hills",
    "sg:classifiers":[
        {
            "category":"Autos & Motor Vehicles",
            "subcategory":"Automobile Sales",
            "type":"Retail Goods"
        }
    ],
    "sg:phone":"+1 618 258 1640",
    "sg:postcode":"62018",
    "sg:province":"IL",
    "sg:tags":[
        "car",
        "dealer"
    ],
    "wof:name":"Woody's Auto Sales",
    "wof:placetype":"venue"
},
  "geometry": {"coordinates":[-90.071805,38.903329],"type":"Point"}
}