{
  "type": "Feature",
  "properties": {
    "addr:full":"420 Arnold Ave Rockford IL 61108",
    "addr:housenumber":"420",
    "addr:postcode":"61108",
    "addr:street":"Arnold Ave",
    "iso:country":"US",
    "sg:address":"420 Arnold Ave",
    "sg:city":"Rockford",
    "sg:classifiers":[
        {
            "category":"Building & Trades",
            "subcategory":"Cleaning & Sanitation",
            "type":"Services"
        }
    ],
    "sg:phone":"+1 815 399 6900",
    "sg:postcode":"61108",
    "sg:province":"IL",
    "sg:tags":[
        "downspout",
        "gutter"
    ],
    "wof:name":"General Home Svc",
    "wof:placetype":"venue"
},
  "geometry": {"coordinates":[-89.007739,42.264568],"type":"Point"}
}