{
  "type": "Feature",
  "properties": {
    "iso:country":"US",
    "sg:address":"435 S Main St",
    "sg:city":"Princeton",
    "sg:classifiers":[
        {
            "category":"Social Services",
            "type":"Services"
        }
    ],
    "sg:phone":"+1 815 879 5700",
    "sg:postcode":"61356",
    "sg:province":"IL",
    "sg:tags":[
        "youth",
        "organization",
        "center"
    ],
    "wof:name":"Girls Scouts Kickapoo Council",
    "wof:placetype":"venue"
},
  "geometry": {"coordinates":[-89.464963,41.371249],"type":"Point"}
}