{
  "type": "Feature",
  "properties": {
    "addr:full":"200 W Stone Rd Villa Park IL 60181",
    "addr:housenumber":"200",
    "addr:postcode":"60181",
    "addr:street":"W Stone Rd",
    "iso:country":"US",
    "sg:address":"200 W Stone Rd",
    "sg:city":"Villa Park",
    "sg:classifiers":[
        {
            "category":"Home & Garden",
            "subcategory":"Building Materials",
            "type":"Retail Goods"
        },
        {
            "category":"Manufacturing",
            "subcategory":"Building Materials",
            "type":"Manufacturing & Wholesale Goods"
        }
    ],
    "sg:phone":"+1 630 832 5455",
    "sg:postcode":"60181",
    "sg:province":"IL",
    "sg:tags":[
        "mfg"
    ],
    "wof:name":"Dave's Custom Millwork",
    "wof:placetype":"venue"
},
  "geometry": {"coordinates":[-87.98598200000001,41.903848],"type":"Point"}
}