{
  "type": "Feature",
  "properties": {
    "iso:country":"US",
    "sg:address":"1300 19th St",
    "sg:city":"East Moline",
    "sg:classifiers":[
        {
            "category":"Real Estate",
            "subcategory":"Real Estate Agent",
            "type":"Services"
        }
    ],
    "sg:phone":"+1 309 752 7130",
    "sg:postcode":"61244",
    "sg:province":"IL",
    "wof:name":"River Bend Industrial Center",
    "wof:placetype":"venue"
},
  "geometry": {"coordinates":[-90.425467,41.520424],"type":"Point"}
}