{
  "type": "Feature",
  "properties": {
    "addr:full":"534 Dean Ct Canton IL 61520",
    "addr:housenumber":"534",
    "addr:postcode":"61520",
    "addr:street":"Dean Ct",
    "iso:country":"US",
    "sg:address":"534 Dean Ct",
    "sg:city":"Canton",
    "sg:classifiers":[
        {
            "category":"Personal",
            "subcategory":"Beauty Salon",
            "type":"Services"
        }
    ],
    "sg:phone":"+1 309 647 0725",
    "sg:postcode":"61520",
    "sg:province":"IL",
    "sg:tags":[
        "hair"
    ],
    "wof:name":"Hair Zone",
    "wof:placetype":"venue"
},
  "geometry": {"coordinates":[-90.02700299999999,40.562613],"type":"Point"}
}