{
  "type": "Feature",
  "properties": {
    "iso:country":"US",
    "sg:address":"1149 Spring Creek Rd",
    "sg:city":"Elgin",
    "sg:classifiers":[
        {
            "category":"Professional",
            "subcategory":"Employment Agencies",
            "type":"Services"
        }
    ],
    "sg:phone":"+1 847 741 4011",
    "sg:postcode":"60120",
    "sg:province":"IL",
    "sg:tags":[
        "leasing"
    ],
    "wof:name":"At Your Svc Outsourcing Inc",
    "wof:placetype":"venue"
},
  "geometry": {"coordinates":[-88.250946,42.058403],"type":"Point"}
}