{
  "type": "Feature",
  "properties": {
    "addr:full":"10653 W Henry Rd Polo IL 61064",
    "addr:housenumber":"10653",
    "addr:postcode":"61064",
    "addr:street":"W Henry Rd",
    "iso:country":"US",
    "sg:address":"10653 W Henry Rd",
    "sg:city":"Polo",
    "sg:classifiers":[
        {
            "category":"Real Estate",
            "subcategory":"Real Estate Agent",
            "type":"Services"
        }
    ],
    "sg:phone":"+1 815 946 2113",
    "sg:postcode":"61064",
    "sg:province":"IL",
    "wof:name":"Fossler Realty Inc",
    "wof:placetype":"venue"
},
  "geometry": {"coordinates":[-89.541814,41.959606],"type":"Point"}
}