{
  "type": "Feature",
  "properties": {
    "addr:full":"Adams & Clark Chicago IL 60601",
    "addr:postcode":"60601",
    "iso:country":"US",
    "sg:address":"Adams & Clark",
    "sg:city":"Chicago",
    "sg:classifiers":[
        {
            "category":"Communications",
            "subcategory":"Newspaper",
            "type":"Services"
        }
    ],
    "sg:postcode":"60601",
    "sg:province":"IL",
    "sg:tags":[
        "magazine"
    ],
    "wof:name":"NewsStand on corner of Clark and Adams",
    "wof:placetype":"venue"
},
  "geometry": {"coordinates":[-87.630807,41.87941],"type":"Point"}
}