{
  "type": "Feature",
  "properties": {
    "addr:full":"520 N Michigan Ave 5th Fl Chicago IL 60611",
    "addr:housenumber":"520",
    "addr:postcode":"60611",
    "addr:street":"N Michigan Ave",
    "iso:country":"US",
    "sg:address":"520 N Michigan Ave 5th Fl",
    "sg:city":"Chicago",
    "sg:classifiers":[
        {
            "category":"Shopping",
            "subcategory":"Jewelry",
            "type":"Retail Goods"
        }
    ],
    "sg:phone":"+1 312 464 0865",
    "sg:postcode":"60611",
    "sg:province":"IL",
    "wof:name":"Sterling Avenue",
    "wof:placetype":"venue"
},
  "geometry": {"coordinates":[-87.62426600000001,41.891535],"type":"Point"}
}