{
  "type": "Feature",
  "properties": {
    "iso:country":"US",
    "sg:address":"9697 Old River Rd",
    "sg:city":"Roscoe",
    "sg:classifiers":[
        {
            "category":"Utilities",
            "type":"Services"
        }
    ],
    "sg:phone":"+1 815 623 2330",
    "sg:postcode":"61073",
    "sg:province":"IL",
    "sg:tags":[
        "sanitary"
    ],
    "wof:name":"Arthur Peucker",
    "wof:placetype":"venue"
},
  "geometry": {"coordinates":[-89.059402,42.400405],"type":"Point"}
}