{
  "type": "Feature",
  "properties": {
    "iso:country":"US",
    "sg:address":"2368 Corporate Ln",
    "sg:city":"Naperville",
    "sg:classifiers":[
        {
            "category":"Professional",
            "subcategory":"Computer Services",
            "type":"Services"
        }
    ],
    "sg:phone":"+1 630 778 1212",
    "sg:postcode":"60563",
    "sg:province":"IL",
    "sg:tags":[
        "web",
        "isp",
        "site",
        "hosting",
        "design",
        "internet",
        "provider"
    ],
    "sg:website":"http://www.ntsource.com",
    "wof:name":"NetSource",
    "wof:placetype":"venue"
},
  "geometry": {"coordinates":[-88.198764,41.811859],"type":"Point"}
}