{
  "type": "Feature",
  "properties": {
    "addr:full":"2640 North Narragansett Ave Chicago IL 60639",
    "addr:housenumber":"2640",
    "addr:postcode":"60639",
    "addr:street":"North Narragansett Ave",
    "iso:country":"US",
    "sg:address":"2640 North Narragansett Ave",
    "sg:city":"Chicago",
    "sg:classifiers":[
        {
            "category":"Sports & Exercise",
            "subcategory":"Gym",
            "type":"Entertainment"
        }
    ],
    "sg:phone":"+1 773 622 1919",
    "sg:postcode":"60639",
    "sg:province":"IL",
    "sg:website":"www.fitness19.com/",
    "wof:name":"Fitness 19",
    "wof:placetype":"venue"
},
  "geometry": {"coordinates":[-87.785692,41.928092],"type":"Point"}
}