{
  "type": "Feature",
  "properties": {
    "iso:country":"US",
    "sg:address":"3885 Illinois St",
    "sg:city":"Dixon",
    "sg:classifiers":[
        {
            "category":"Banks & Credit Unions",
            "subcategory":"Investment Brokerage",
            "type":"Services"
        }
    ],
    "sg:phone":"+1 815 652 8682",
    "sg:postcode":"61021",
    "sg:province":"IL",
    "sg:tags":[
        "trust"
    ],
    "wof:name":"Ralph Edgar Properties",
    "wof:placetype":"venue"
},
  "geometry": {"coordinates":[-89.417631,41.898012],"type":"Point"}
}