{
  "type": "Feature",
  "properties": {
    "iso:country":"US",
    "sg:address":"515 39th St",
    "sg:city":"Downers Grove",
    "sg:classifiers":[
        {
            "category":"Shopping",
            "subcategory":"Gifts & Souvenirs",
            "type":"Retail Goods"
        }
    ],
    "sg:phone":"+1   ",
    "sg:postcode":"60515",
    "sg:province":"IL",
    "wof:name":"Sports Plaques",
    "wof:placetype":"venue"
},
  "geometry": {"coordinates":[-87.998548,41.816667],"type":"Point"}
}