{
  "type": "Feature",
  "properties": {
    "iso:country":"US",
    "sg:address":"4007 Touhy Ave",
    "sg:city":"Lincolnwood",
    "sg:classifiers":[
        {
            "category":"Retail",
            "subcategory":"Auto Repair",
            "type":"Services"
        }
    ],
    "sg:phone":"+1 847 679 9133",
    "sg:postcode":"60712",
    "sg:province":"IL",
    "sg:tags":[
        "muffler",
        "exhaust",
        "system"
    ],
    "wof:name":"Fair Muffler & Brake Shop",
    "wof:placetype":"venue"
},
  "geometry": {"coordinates":[-87.72977899999999,42.011738],"type":"Point"}
}