{
  "type": "Feature",
  "properties": {
    "addr:full":"345 E 118th St Chicago IL 60628",
    "addr:housenumber":"345",
    "addr:postcode":"60628",
    "addr:street":"E 118Th St",
    "iso:country":"US",
    "sg:address":"345 E 118th St",
    "sg:city":"Chicago",
    "sg:classifiers":[
        {
            "category":"Social Services",
            "subcategory":"Child Care",
            "type":"Services"
        }
    ],
    "sg:phone":"+1 312 747 6284",
    "sg:postcode":"60628",
    "sg:province":"IL",
    "sg:tags":[
        "nursery",
        "day"
    ],
    "wof:name":"Kensington Playground",
    "wof:placetype":"venue"
},
  "geometry": {"coordinates":[-87.61635699999999,41.679935],"type":"Point"}
}