{
  "type": "Feature",
  "properties": {
    "addr:full":"1040 Fairview Ave Lake Forest IL 60045",
    "addr:housenumber":"1040",
    "addr:postcode":"60045",
    "addr:street":"Fairview Ave",
    "iso:country":"US",
    "sg:address":"1040 Fairview Ave",
    "sg:city":"Lake Forest",
    "sg:classifiers":[
        {
            "category":"Shopping",
            "subcategory":"Books",
            "type":"Retail Goods"
        }
    ],
    "sg:phone":"+1   ",
    "sg:postcode":"60045",
    "sg:province":"IL",
    "wof:name":"Chicagoland Bookbuyers Co",
    "wof:placetype":"venue"
},
  "geometry": {"coordinates":[-87.849058,42.220416],"type":"Point"}
}