{
  "type": "Feature",
  "properties": {
    "iso:country":"US",
    "sg:address":"907 Ann St",
    "sg:city":"Batavia",
    "sg:classifiers":[
        {
            "category":"Social Services",
            "subcategory":"Child Care",
            "type":"Services"
        }
    ],
    "sg:phone":"+1 630 406 0622",
    "sg:postcode":"60510",
    "sg:province":"IL",
    "wof:name":"Sheri Flannagan",
    "wof:placetype":"venue"
},
  "geometry": {"coordinates":[-88.304013,41.860693],"type":"Point"}
}