{
  "type": "Feature",
  "properties": {
    "addr:full":"147 Wildflower Ln Round Lake IL 60073",
    "addr:housenumber":"147",
    "addr:postcode":"60073",
    "addr:street":"Wildflower Ln",
    "iso:country":"US",
    "sg:address":"147 Wildflower Ln",
    "sg:city":"Round Lake",
    "sg:classifiers":[
        {
            "category":"Professional",
            "subcategory":"Computer Services",
            "type":"Services"
        }
    ],
    "sg:phone":"+1 847 265 1416",
    "sg:postcode":"60073",
    "sg:province":"IL",
    "sg:tags":[
        "programing",
        "custom"
    ],
    "wof:name":"Futureage Systms Tchnlology",
    "wof:placetype":"venue"
},
  "geometry": {"coordinates":[-88.076871,42.396222],"type":"Point"}
}