{
  "type": "Feature",
  "properties": {
    "addr:full":"724 W Main St Salem IL 62881",
    "addr:housenumber":"724",
    "addr:postcode":"62881",
    "addr:street":"W Main St",
    "iso:country":"US",
    "sg:address":"724 W Main St",
    "sg:city":"Salem",
    "sg:classifiers":[
        {
            "category":"Shopping",
            "type":"Retail Goods"
        }
    ],
    "sg:phone":"+1   ",
    "sg:postcode":"62881",
    "sg:province":"IL",
    "sg:tags":[
        "merchandise"
    ],
    "wof:name":"Stamp Shop",
    "wof:placetype":"venue"
},
  "geometry": {"coordinates":[-88.951994,38.627115],"type":"Point"}
}