{
  "type": "Feature",
  "properties": {
    "iso:country":"US",
    "sg:address":"9033 Ewing Ave",
    "sg:city":"Evanston",
    "sg:classifiers":[
        {
            "category":"Food & Beverages",
            "subcategory":"Specialty",
            "type":"Retail Goods"
        }
    ],
    "sg:phone":"+1   ",
    "sg:postcode":"60203",
    "sg:province":"IL",
    "wof:name":"Gourmet Distribution",
    "wof:placetype":"venue"
},
  "geometry": {"coordinates":[-87.712347,42.045784],"type":"Point"}
}