{
  "type": "Feature",
  "properties": {
    "addr:full":"325 N Park St Kewanee IL 61443",
    "addr:housenumber":"325",
    "addr:postcode":"61443",
    "addr:street":"N Park St",
    "iso:country":"US",
    "sg:address":"325 N Park St",
    "sg:city":"Kewanee",
    "sg:classifiers":[
        {
            "category":"Building & Trades",
            "subcategory":"Plumbing",
            "type":"Services"
        }
    ],
    "sg:phone":"+1 309 853 8534",
    "sg:postcode":"61443",
    "sg:province":"IL",
    "sg:tags":[
        "plumbing",
        "contractor"
    ],
    "wof:name":"Rob's Plumbing & Drain Svc",
    "wof:placetype":"venue"
},
  "geometry": {"coordinates":[-89.930795,41.246797],"type":"Point"}
}