{
  "type": "Feature",
  "properties": {
    "iso:country":"US",
    "sg:address":"4726 Main St",
    "sg:city":"Lisle",
    "sg:classifiers":[
        {
            "category":"Personal",
            "subcategory":"Beauty Salon",
            "type":"Services"
        },
        {
            "category":"Personal",
            "subcategory":"Barber",
            "type":"Services"
        }
    ],
    "sg:phone":"+1 630 968 0137",
    "sg:postcode":"60532",
    "sg:province":"IL",
    "sg:tags":[
        "hair",
        "stylist"
    ],
    "wof:name":"Main Street Hair Company",
    "wof:placetype":"venue"
},
  "geometry": {"coordinates":[-88.074663,41.799999],"type":"Point"}
}