{
  "type": "Feature",
  "properties": {
    "iso:country":"US",
    "sg:address":"965 Lake St",
    "sg:city":"Oak Park",
    "sg:classifiers":[
        {
            "category":"Health Services",
            "subcategory":"Doctor",
            "type":"Services"
        }
    ],
    "sg:phone":"+1 708 386 8600",
    "sg:postcode":"60301",
    "sg:province":"IL",
    "sg:tags":[
        "surgeon",
        "oral"
    ],
    "wof:name":"Politis Constantine L DDS",
    "wof:placetype":"venue"
},
  "geometry": {"coordinates":[-87.797203,41.888599],"type":"Point"}
}