{
  "type": "Feature",
  "properties": {
    "addr:full":"101 N 3rd St Fisher IL 61843",
    "addr:housenumber":"101",
    "addr:postcode":"61843",
    "addr:street":"N 3Rd St",
    "iso:country":"US",
    "sg:address":"101 N 3rd St",
    "sg:city":"Fisher",
    "sg:classifiers":[
        {
            "category":"Professional",
            "subcategory":"Business Services",
            "type":"Services"
        }
    ],
    "sg:phone":"+1 217 897 1294",
    "sg:postcode":"61843",
    "sg:province":"IL",
    "sg:tags":[
        "painter",
        "sign"
    ],
    "wof:name":"Creation Electrical Signs",
    "wof:placetype":"venue"
},
  "geometry": {"coordinates":[-88.34969100000001,40.318413],"type":"Point"}
}