{
  "type": "Feature",
  "properties": {
    "addr:full":"2801 Carl Blvd Elk Grove Vlg IL 60007",
    "addr:housenumber":"2801",
    "addr:postcode":"60007",
    "addr:street":"Carl Blvd",
    "iso:country":"US",
    "sg:address":"2801 Carl Blvd",
    "sg:city":"Elk Grove Vlg",
    "sg:classifiers":[
        {
            "category":"Home & Garden",
            "subcategory":"Building Materials",
            "type":"Retail Goods"
        }
    ],
    "sg:phone":"+1 847 860 8532",
    "sg:postcode":"60007",
    "sg:province":"IL",
    "sg:tags":[
        "door"
    ],
    "wof:name":"Genie Pro Sales Ctr",
    "wof:placetype":"venue"
},
  "geometry": {"coordinates":[-87.973579,41.987325],"type":"Point"}
}