{
  "type": "Feature",
  "properties": {
    "iso:country":"US",
    "sg:address":"1620 Bridle Post Dr",
    "sg:city":"Aurora",
    "sg:classifiers":[
        {
            "category":"Professional",
            "subcategory":"Art Services",
            "type":"Services"
        }
    ],
    "sg:phone":"+1 630 892 7475",
    "sg:postcode":"60506",
    "sg:province":"IL",
    "sg:tags":[
        "photography",
        "commercial"
    ],
    "wof:name":"Staff Davis Photography",
    "wof:placetype":"venue"
},
  "geometry": {"coordinates":[-88.356446,41.78084],"type":"Point"}
}