{
  "type": "Feature",
  "properties": {
    "iso:country":"US",
    "sg:address":"904 W Water St",
    "sg:city":"Teutopolis",
    "sg:classifiers":[
        {
            "category":"Education",
            "subcategory":"School",
            "type":"Public Place"
        }
    ],
    "sg:phone":"+1 217 857 6678",
    "sg:postcode":"62467",
    "sg:province":"IL",
    "wof:name":"Teutopolis Junior High School",
    "wof:placetype":"venue"
},
  "geometry": {"coordinates":[-88.488348,39.13337],"type":"Point"}
}