{
  "type": "Feature",
  "properties": {
    "iso:country":"US",
    "sg:address":"1118 Lunt Ave",
    "sg:city":"Schaumburg",
    "sg:classifiers":[
        {
            "category":"Manufacturing",
            "subcategory":"Metals",
            "type":"Manufacturing & Wholesale Goods"
        }
    ],
    "sg:phone":"+1 847 985 6211",
    "sg:postcode":"60193",
    "sg:province":"IL",
    "sg:tags":[
        "steel",
        "die",
        "tool",
        "mfg"
    ],
    "wof:name":"M-T Tools and Mfg Inc",
    "wof:placetype":"venue"
},
  "geometry": {"coordinates":[-88.104396,42.001419],"type":"Point"}
}