{
  "type": "Feature",
  "properties": {
    "iso:country":"US",
    "sg:address":"649 E 300N Rd",
    "sg:city":"Gibson City",
    "sg:classifiers":[
        {
            "category":"Real Estate",
            "subcategory":"Real Estate Operator",
            "type":"Services"
        }
    ],
    "sg:phone":"+1 217 749 2386",
    "sg:postcode":"60936",
    "sg:province":"IL",
    "sg:tags":[
        "property",
        "lessor"
    ],
    "wof:name":"Buck Verna",
    "wof:placetype":"venue"
},
  "geometry": {"coordinates":[-88.339698,40.442319],"type":"Point"}
}