{
  "type": "Feature",
  "properties": {
    "addr:full":"2201 7th Ave Moline IL 61265",
    "addr:housenumber":"2201",
    "addr:postcode":"61265",
    "addr:street":"7Th Ave",
    "iso:country":"US",
    "sg:address":"2201 7th Ave",
    "sg:city":"Moline",
    "sg:classifiers":[
        {
            "category":"Social Services",
            "type":"Services"
        }
    ],
    "sg:phone":"+1 309 762 5645",
    "sg:postcode":"61265",
    "sg:province":"IL",
    "sg:tags":[
        "agency",
        "adoption"
    ],
    "wof:name":"Lifelink Intl Adoption Svcs",
    "wof:placetype":"venue"
},
  "geometry": {"coordinates":[-90.50566999999999,41.507813],"type":"Point"}
}