{
  "type": "Feature",
  "properties": {
    "addr:full":"900 Camarato Dr Herrin IL 62948",
    "addr:housenumber":"900",
    "addr:postcode":"62948",
    "addr:street":"Camarato Dr",
    "iso:country":"US",
    "sg:address":"900 Camarato Dr",
    "sg:city":"Herrin",
    "sg:classifiers":[
        {
            "category":"Industrial Area",
            "type":"Public Place"
        }
    ],
    "sg:phone":"+1 618 942 4810",
    "sg:postcode":"62948",
    "sg:province":"IL",
    "sg:tags":[
        "development"
    ],
    "sg:website":"http://www.garonfoods.com",
    "wof:name":"Garon Industries, Inc.",
    "wof:placetype":"venue"
},
  "geometry": {"coordinates":[-89.051979,37.810902],"type":"Point"}
}