{
  "type": "Feature",
  "properties": {
    "addr:full":"24714 N Nodding Flower Ct Barrington IL 60010",
    "addr:housenumber":"24714",
    "addr:postcode":"60010",
    "addr:street":"N Nodding Flower Ct",
    "iso:country":"US",
    "sg:address":"24714 N Nodding Flower Ct",
    "sg:city":"Barrington",
    "sg:classifiers":[
        {
            "category":"Real Estate",
            "subcategory":"Real Estate Agent",
            "type":"Services"
        }
    ],
    "sg:phone":"+1 847 526 4196",
    "sg:postcode":"60010",
    "sg:province":"IL",
    "wof:name":"Jordan E Glazov Real Estate",
    "wof:placetype":"venue"
},
  "geometry": {"coordinates":[-88.158362,42.222766],"type":"Point"}
}