{
  "type": "Feature",
  "properties": {
    "iso:country":"US",
    "sg:address":"6751 Alhambra Rd",
    "sg:city":"Alhambra",
    "sg:phone":"+1 618 488 3385",
    "sg:postcode":"62001",
    "sg:province":"IL",
    "sg:tags":[
        "oil"
    ],
    "wof:name":"Alhambra Oil Co",
    "wof:placetype":"venue"
},
  "geometry": {"coordinates":[-89.749679,38.891785],"type":"Point"}
}