{
  "type": "Feature",
  "properties": {
    "iso:country":"US",
    "sg:address":"322 S 4th St",
    "sg:city":"Chillicothe",
    "sg:classifiers":[
        {
            "category":"Personal",
            "subcategory":"Beauty Salon",
            "type":"Services"
        }
    ],
    "sg:phone":"+1 309 274 3934",
    "sg:postcode":"61523",
    "sg:province":"IL",
    "sg:tags":[
        "shop"
    ],
    "wof:name":"Golden Comb Salon",
    "wof:placetype":"venue"
},
  "geometry": {"coordinates":[-89.49328,40.905219],"type":"Point"}
}