{
  "type": "Feature",
  "properties": {
    "addr:full":"1633 River St Des Plaines IL 60016",
    "addr:housenumber":"1633",
    "addr:postcode":"60016",
    "addr:street":"River St",
    "iso:country":"US",
    "sg:address":"1633 River St",
    "sg:city":"Des Plaines",
    "sg:classifiers":[
        {
            "category":"Building & Trades",
            "subcategory":"Construction",
            "type":"Services"
        }
    ],
    "sg:phone":"+1 847 803 2237",
    "sg:postcode":"60016",
    "sg:province":"IL",
    "sg:tags":[
        "house"
    ],
    "wof:name":"J & H Home Repair Inc",
    "wof:placetype":"venue"
},
  "geometry": {"coordinates":[-87.88239900000001,42.041603],"type":"Point"}
}