{
  "type": "Feature",
  "properties": {
    "addr:full":"887 N Brentwood Dr Crystal Lake IL 60014",
    "addr:housenumber":"887",
    "addr:postcode":"60014",
    "addr:street":"N Brentwood Dr",
    "iso:country":"US",
    "sg:address":"887 N Brentwood Dr",
    "sg:city":"Crystal Lake",
    "sg:classifiers":[
        {
            "category":"Building & Trades",
            "subcategory":"Electrical",
            "type":"Services"
        }
    ],
    "sg:phone":"+1 815 455 0071",
    "sg:postcode":"60014",
    "sg:province":"IL",
    "sg:tags":[
        "electric",
        "contractor"
    ],
    "wof:name":"PWR Electric Inc",
    "wof:placetype":"venue"
},
  "geometry": {"coordinates":[-88.344768,42.217329],"type":"Point"}
}