{
  "type": "Feature",
  "properties": {
    "iso:country":"US",
    "sg:address":"239 N Richmond Ave",
    "sg:city":"Clarendon Hills",
    "sg:classifiers":[
        {
            "category":"Freight",
            "type":"Transportation"
        }
    ],
    "sg:phone":"+1 630 325 1520",
    "sg:postcode":"60514",
    "sg:province":"IL",
    "sg:tags":[
        "operator",
        "trucking"
    ],
    "wof:name":"Elite Auto Transport Inc",
    "wof:placetype":"venue"
},
  "geometry": {"coordinates":[-87.966014,41.807189],"type":"Point"}
}