{
  "type": "Feature",
  "properties": {
    "addr:full":"1617 N Cicero Ave Chicago IL 60639",
    "addr:housenumber":"1617",
    "addr:postcode":"60639",
    "addr:street":"N Cicero Ave",
    "iso:country":"US",
    "sg:address":"1617 N Cicero Ave",
    "sg:city":"Chicago",
    "sg:classifiers":[
        {
            "category":"Banks & Credit Unions",
            "subcategory":"Bureau De Change",
            "type":"Services"
        }
    ],
    "sg:phone":"+1 773 276 6688",
    "sg:postcode":"60639",
    "sg:province":"IL",
    "sg:tags":[
        "currency",
        "exchange"
    ],
    "wof:name":"PLS Check Casher",
    "wof:placetype":"venue"
},
  "geometry": {"coordinates":[-87.7458,41.910442],"type":"Point"}
}