{
  "type": "Feature",
  "properties": {
    "addr:full":"18743 E 1400th Ave Teutopolis IL 62467",
    "addr:housenumber":"18743",
    "addr:postcode":"62467",
    "addr:street":"E 1400Th Ave",
    "iso:country":"US",
    "sg:address":"18743 E 1400th Ave",
    "sg:city":"Teutopolis",
    "sg:classifiers":[
        {
            "category":"Farming",
            "subcategory":"Livestock Farm",
            "type":"Manufacturing & Wholesale Goods"
        }
    ],
    "sg:phone":"+1 217 857 3665",
    "sg:postcode":"62467",
    "sg:province":"IL",
    "sg:tags":[
        "hog",
        "corn",
        "or",
        "feedlot"
    ],
    "wof:name":"Willenborg Brothers",
    "wof:placetype":"venue"
},
  "geometry": {"coordinates":[-88.458753,39.118263],"type":"Point"}
}