{
  "type": "Feature",
  "properties": {
    "addr:full":"146 W Northwest Hwy Palatine IL 60067",
    "addr:housenumber":"146",
    "addr:postcode":"60067",
    "addr:street":"W Northwest Hwy",
    "iso:country":"US",
    "sg:address":"146 W Northwest Hwy",
    "sg:city":"Palatine",
    "sg:classifiers":[
        {
            "category":"Food & Beverages",
            "subcategory":"Liquor & Beverages",
            "type":"Retail Goods"
        }
    ],
    "sg:phone":"+1 847 359 1879",
    "sg:postcode":"60067",
    "sg:province":"IL",
    "wof:name":"George's Wine & Spirits",
    "wof:placetype":"venue"
},
  "geometry": {"coordinates":[-88.04744599999999,42.122159],"type":"Point"}
}