{
  "type": "Feature",
  "properties": {
    "iso:country":"US",
    "sg:address":"945 N Shore Dr",
    "sg:city":"Lake Bluff",
    "sg:classifiers":[
        {
            "category":"Recreation",
            "type":"Entertainment"
        }
    ],
    "sg:phone":"+1 847 295 1322",
    "sg:postcode":"60044",
    "sg:province":"IL",
    "sg:tags":[
        "club",
        "membership",
        "tennis"
    ],
    "wof:name":"Raquet Club of Lake Bluff LLC",
    "wof:placetype":"venue"
},
  "geometry": {"coordinates":[-87.872021,42.272644],"type":"Point"}
}