{
  "type": "Feature",
  "properties": {
    "iso:country":"US",
    "sg:address":"12712 25th Street Ct",
    "sg:city":"Milan",
    "sg:classifiers":[
        {
            "category":"Professional",
            "type":"Services"
        }
    ],
    "sg:phone":"+1 309 787 4112",
    "sg:postcode":"61264",
    "sg:province":"IL",
    "wof:name":"Mills Technical Services LLC",
    "wof:placetype":"venue"
},
  "geometry": {"coordinates":[-90.54259500000001,41.389241],"type":"Point"}
}