{
  "type": "Feature",
  "properties": {
    "iso:country":"US",
    "sg:address":"7131 S Jeffery Boulevard",
    "sg:city":"Chicago",
    "sg:classifiers":[
        {
            "category":"Fast Food",
            "type":"Food & Drink"
        },
        {
            "category":"Food & Beverages",
            "subcategory":"Bakery",
            "type":"Retail Goods"
        },
        {
            "category":"Restaurant",
            "type":"Food & Drink"
        }
    ],
    "sg:phone":"+1 773 493 7777",
    "sg:postcode":"60649",
    "sg:province":"IL",
    "sg:tags":[
        "fish",
        "sandwich",
        "chip"
    ],
    "wof:name":"Seashell Fish & Chicken",
    "wof:placetype":"venue"
},
  "geometry": {"coordinates":[-87.576273,41.76542],"type":"Point"}
}