{
  "type": "Feature",
  "properties": {
    "iso:country":"US",
    "sg:address":"1020 Millbrook Dr",
    "sg:city":"Lake Zurich",
    "sg:classifiers":[
        {
            "category":"Shopping",
            "subcategory":"Computers & Home Electronics",
            "type":"Retail Goods"
        }
    ],
    "sg:phone":"+1   ",
    "sg:postcode":"60047",
    "sg:province":"IL",
    "wof:name":"Audio Biz",
    "wof:placetype":"venue"
},
  "geometry": {"coordinates":[-88.068504,42.193301],"type":"Point"}
}