{
  "type": "Feature",
  "properties": {
    "iso:country":"US",
    "sg:address":"3916 W Riverside Blvd",
    "sg:city":"Rockford",
    "sg:classifiers":[
        {
            "category":"Restaurant",
            "type":"Food & Drink"
        }
    ],
    "sg:menulink":"http://www.allmenus.com/il/rockford/159568-arbys/menu/",
    "sg:phone":"+1 815 963 2258",
    "sg:postcode":"61101",
    "sg:province":"IL",
    "sg:tags":[
        "burger",
        "american"
    ],
    "wof:name":"Arby's",
    "wof:placetype":"venue"
},
  "geometry": {"coordinates":[-89.11145,42.315485],"type":"Point"}
}