{
  "type": "Feature",
  "properties": {
    "addr:full":"300 S Riverside Plz Chicago IL 60606",
    "addr:housenumber":"300",
    "addr:postcode":"60606",
    "addr:street":"S Riverside",
    "iso:country":"US",
    "sg:address":"300 S Riverside Plz",
    "sg:city":"Chicago",
    "sg:classifiers":[
        {
            "category":"Government",
            "subcategory":"Office",
            "type":"Public Place"
        }
    ],
    "sg:phone":"+1 312 353 0357",
    "sg:postcode":"60606",
    "sg:province":"IL",
    "sg:tags":[
        "government-united",
        "state"
    ],
    "wof:name":"Us Small Business Admin",
    "wof:placetype":"venue"
},
  "geometry": {"coordinates":[-87.63884,41.878059],"type":"Point"}
}