{
  "type": "Feature",
  "properties": {
    "iso:country":"US",
    "sg:address":"5816 W 118th St",
    "sg:city":"Alsip",
    "sg:classifiers":[
        {
            "category":"Manufacturing",
            "subcategory":"Building Materials",
            "type":"Manufacturing & Wholesale Goods"
        }
    ],
    "sg:phone":"+1 708 489 5958",
    "sg:postcode":"60803",
    "sg:province":"IL",
    "sg:tags":[
        "mfg"
    ],
    "wof:name":"Stoney Creek Hardwoods Inc",
    "wof:placetype":"venue"
},
  "geometry": {"coordinates":[-87.765776,41.677738],"type":"Point"}
}