{
  "type": "Feature",
  "properties": {
    "addr:full":"3488 Milwaukee Ave Northbrook IL 60062",
    "addr:housenumber":"3488",
    "addr:postcode":"60062",
    "addr:street":"Milwaukee Ave",
    "iso:country":"US",
    "sg:address":"3488 Milwaukee Ave",
    "sg:city":"Northbrook",
    "sg:classifiers":[
        {
            "category":"Personal",
            "subcategory":"Beauty Salon",
            "type":"Services"
        }
    ],
    "sg:phone":"+1 847 827 1313",
    "sg:postcode":"60062",
    "sg:province":"IL",
    "sg:tags":[
        "shop"
    ],
    "wof:name":"Madame Joy Hair Salon",
    "wof:placetype":"venue"
},
  "geometry": {"coordinates":[-87.873335,42.090035],"type":"Point"}
}