{
  "type": "Feature",
  "properties": {
    "iso:country":"US",
    "sg:address":"2412 Becker Dr",
    "sg:city":"Peru",
    "sg:classifiers":[
        {
            "category":"Health Services",
            "subcategory":"Nursing And Care Facility",
            "type":"Services"
        }
    ],
    "sg:phone":"+1 815 223 3045",
    "sg:postcode":"61354",
    "sg:province":"IL",
    "sg:tags":[
        "home",
        "retirement",
        "community"
    ],
    "wof:name":"Country Comfort Retirement",
    "wof:placetype":"venue"
},
  "geometry": {"coordinates":[-89.120566,41.344075],"type":"Point"}
}