{
  "type": "Feature",
  "properties": {
    "iso:country":"US",
    "sg:address":"2458 S California Avenue",
    "sg:city":"Chicago",
    "sg:classifiers":[
        {
            "category":"Food & Beverages",
            "subcategory":"Supermarket",
            "type":"Retail Goods"
        },
        {
            "category":"Food & Beverages",
            "subcategory":"Groceries & Convenience Stores",
            "type":"Retail Goods"
        }
    ],
    "sg:phone":"+1 773 523 1859",
    "sg:postcode":"60608",
    "sg:province":"IL",
    "sg:tags":[
        "super"
    ],
    "wof:name":"Makia Foods",
    "wof:placetype":"venue"
},
  "geometry": {"coordinates":[-87.695419,41.846609],"type":"Point"}
}