{
  "type": "Feature",
  "properties": {
    "addr:full":"1420 S Bidwell Ave Freeport IL 61032",
    "addr:housenumber":"1420",
    "addr:postcode":"61032",
    "addr:street":"S Bidwell Ave",
    "iso:country":"US",
    "sg:address":"1420 S Bidwell Ave",
    "sg:city":"Freeport",
    "sg:classifiers":[
        {
            "category":"Organizations",
            "subcategory":"Religious Organization",
            "type":"Services"
        }
    ],
    "sg:phone":"+1 815 235 7544",
    "sg:postcode":"61032",
    "sg:province":"IL",
    "sg:tags":[
        "church"
    ],
    "wof:name":"St Marys Church",
    "wof:placetype":"venue"
},
  "geometry": {"coordinates":[-89.606182,42.284882],"type":"Point"}
}