{
  "type": "Feature",
  "properties": {
    "iso:country":"US",
    "sg:address":"860 Remington Blvd",
    "sg:city":"Bolingbrook",
    "sg:classifiers":[
        {
            "category":"Wholesale",
            "subcategory":"Machinery & Supplies",
            "type":"Manufacturing & Wholesale Goods"
        }
    ],
    "sg:phone":"+1 630 226 4900",
    "sg:postcode":"60440",
    "sg:province":"IL",
    "sg:tags":[
        "valve"
    ],
    "wof:name":"Crane Values",
    "wof:placetype":"venue"
},
  "geometry": {"coordinates":[-88.102206,41.677851],"type":"Point"}
}