{
  "type": "Feature",
  "properties": {
    "iso:country":"US",
    "sg:address":"1219 W 97th St",
    "sg:city":"Chicago",
    "sg:classifiers":[
        {
            "category":"Wholesale",
            "subcategory":"Medical Equipment & Supplies",
            "type":"Manufacturing & Wholesale Goods"
        }
    ],
    "sg:phone":"+1 773 429 0697",
    "sg:postcode":"60643",
    "sg:province":"IL",
    "sg:tags":[
        "physician",
        "surgeon"
    ],
    "wof:name":"Bargain Medical Supplies",
    "wof:placetype":"venue"
},
  "geometry": {"coordinates":[-87.654961,41.718026],"type":"Point"}
}