{
  "type": "Feature",
  "properties": {
    "addr:full":"100 N Seymour Ave Mundelein IL 60060",
    "addr:housenumber":"100",
    "addr:postcode":"60060",
    "addr:street":"N Seymour Ave",
    "iso:country":"US",
    "sg:address":"100 N Seymour Ave",
    "sg:city":"Mundelein",
    "sg:classifiers":[
        {
            "category":"Arts & Performance",
            "subcategory":"Dance",
            "type":"Entertainment"
        }
    ],
    "sg:phone":"+1 847 566 0675",
    "sg:postcode":"60060",
    "sg:province":"IL",
    "sg:tags":[
        "instruction",
        "dancing"
    ],
    "wof:name":"Mundelein Dance Studio",
    "wof:placetype":"venue"
},
  "geometry": {"coordinates":[-88.002647,42.264381],"type":"Point"}
}