{
  "type": "Feature",
  "properties": {
    "iso:country":"US",
    "sg:address":"313 W Blackburn St",
    "sg:city":"Paris",
    "sg:classifiers":[
        {
            "category":"Building & Trades",
            "subcategory":"Cleaning & Sanitation",
            "type":"Services"
        },
        {
            "category":"Retail",
            "subcategory":"Laundry & Dry Cleaning",
            "type":"Services"
        }
    ],
    "sg:phone":"+1 217 463 2735",
    "sg:postcode":"61944",
    "sg:province":"IL",
    "sg:tags":[
        "cleaner",
        "floor",
        "rug",
        "waxing",
        "polishing",
        "janitorial",
        "carpet"
    ],
    "wof:name":"Daves Carpet Cleaning",
    "wof:placetype":"venue"
},
  "geometry": {"coordinates":[-87.69995400000001,39.621783],"type":"Point"}
}