{
  "type": "Feature",
  "properties": {
    "addr:full":"4213 W Madison Street Chicago IL 60624",
    "addr:housenumber":"4213",
    "addr:postcode":"60624",
    "addr:street":"W Madison Street",
    "iso:country":"US",
    "sg:address":"4213 W Madison Street",
    "sg:city":"Chicago",
    "sg:classifiers":[
        {
            "category":"Education",
            "subcategory":"School",
            "type":"Public Place"
        }
    ],
    "sg:phone":"+1 773 533 3500",
    "sg:postcode":"60624",
    "sg:province":"IL",
    "wof:name":"Westside Youth Technical Entrepreneur Center Wytec",
    "wof:placetype":"venue"
},
  "geometry": {"coordinates":[-87.731365,41.880483],"type":"Point"}
}