{
  "type": "Feature",
  "properties": {
    "iso:country":"US",
    "sg:address":"2421 Washington St",
    "sg:city":"Waukegan",
    "sg:classifiers":[
        {
            "category":"Personal",
            "subcategory":"Beauty Salon",
            "type":"Services"
        }
    ],
    "sg:phone":"+1 847 662 1773",
    "sg:postcode":"60085",
    "sg:province":"IL",
    "sg:tags":[
        "shop"
    ],
    "wof:name":"New Image Hair Designs",
    "wof:placetype":"venue"
},
  "geometry": {"coordinates":[-87.864125,42.3594],"type":"Point"}
}