{
  "type": "Feature",
  "properties": {
    "iso:country":"US",
    "sg:address":"1249 W Lincoln Blvd",
    "sg:city":"Freeport",
    "sg:classifiers":[
        {
            "category":"Shopping",
            "subcategory":"Used Merchandise",
            "type":"Retail Goods"
        }
    ],
    "sg:phone":"+1   ",
    "sg:postcode":"61032",
    "sg:province":"IL",
    "wof:name":"James W Sproule",
    "wof:placetype":"venue"
},
  "geometry": {"coordinates":[-89.64299200000001,42.294044],"type":"Point"}
}