{
  "type": "Feature",
  "properties": {
    "iso:country":"US",
    "sg:address":"644 Park Ave",
    "sg:city":"Beloit",
    "sg:classifiers":[
        {
            "category":"Professional",
            "subcategory":"Lawyer & Legal Services",
            "type":"Services"
        }
    ],
    "sg:phone":"+1 608 365 3335",
    "sg:postcode":"53511",
    "sg:province":"IL",
    "wof:name":"Bat Enterprises LLC",
    "wof:placetype":"venue"
},
  "geometry": {"coordinates":[-89.02691299999999,42.502276],"type":"Point"}
}