{
  "type": "Feature",
  "properties": {
    "addr:full":"8556 S Drake Ave Chicago IL 60652",
    "addr:housenumber":"8556",
    "addr:postcode":"60652",
    "addr:street":"S Drake Ave",
    "iso:country":"US",
    "sg:address":"8556 S Drake Ave",
    "sg:city":"Chicago",
    "sg:classifiers":[
        {
            "category":"Social Services",
            "subcategory":"Child Care",
            "type":"Services"
        }
    ],
    "sg:phone":"+1 773 778 6904",
    "sg:postcode":"60652",
    "sg:province":"IL",
    "wof:name":"Brenda Day Care",
    "wof:placetype":"venue"
},
  "geometry": {"coordinates":[-87.711142,41.737609],"type":"Point"}
}