{
  "type": "Feature",
  "properties": {
    "iso:country":"US",
    "sg:address":"3857 W Washington Boulevard",
    "sg:city":"Chicago",
    "sg:classifiers":[
        {
            "category":"Health Services",
            "subcategory":"Dentist",
            "type":"Services"
        }
    ],
    "sg:phone":"+1 773 638 4633",
    "sg:postcode":"60624",
    "sg:province":"IL",
    "wof:name":"Kamdar Harshad DDS",
    "wof:placetype":"venue"
},
  "geometry": {"coordinates":[-87.721969,41.881703],"type":"Point"}
}