{
  "type": "Feature",
  "properties": {
    "iso:country":"US",
    "sg:address":"264 N State Hwy 32",
    "sg:city":"Cerro Gordo",
    "sg:classifiers":[
        {
            "category":"Farming",
            "subcategory":"Farm",
            "type":"Manufacturing & Wholesale Goods"
        }
    ],
    "sg:phone":"+1 217 677 2388",
    "sg:postcode":"61818",
    "sg:province":"IL",
    "sg:tags":[
        "crop",
        "general"
    ],
    "wof:name":"Warren Vanhorn Farm",
    "wof:placetype":"venue"
},
  "geometry": {"coordinates":[-88.726927,39.832277],"type":"Point"}
}