{
  "type": "Feature",
  "properties": {
    "iso:country":"US",
    "sg:address":"18141 Dixie Hwy",
    "sg:city":"Homewood",
    "sg:classifiers":[
        {
            "category":"Insurance",
            "subcategory":"Hazard Insurance",
            "type":"Services"
        },
        {
            "category":"Insurance",
            "subcategory":"Insurance Agent",
            "type":"Services"
        },
        {
            "category":"Insurance",
            "subcategory":"Life Insurance",
            "type":"Services"
        }
    ],
    "sg:phone":"+1 708 798 3687",
    "sg:postcode":"60430",
    "sg:province":"IL",
    "sg:tags":[
        "auto"
    ],
    "sg:website":"http://statefarm.mqgroup.com/url.asp?usr=1395DE",
    "wof:name":"Tzinares, Angelo G - State Farm Insurance Agent",
    "wof:placetype":"venue"
},
  "geometry": {"coordinates":[-87.665384,41.559937],"type":"Point"}
}