{
  "type": "Feature",
  "properties": {
    "addr:full":"1201 Centreville Ave Belleville IL 62220",
    "addr:housenumber":"1201",
    "addr:postcode":"62220",
    "addr:street":"Centreville Ave",
    "iso:country":"US",
    "sg:address":"1201 Centreville Ave",
    "sg:city":"Belleville",
    "sg:classifiers":[
        {
            "category":"Banks & Credit Unions",
            "subcategory":"Investment Brokerage",
            "type":"Services"
        }
    ],
    "sg:phone":"+1 618 234 8239",
    "sg:postcode":"62220",
    "sg:province":"IL",
    "sg:tags":[
        "advisory"
    ],
    "wof:name":"Marco Investment Group",
    "wof:placetype":"venue"
},
  "geometry": {"coordinates":[-89.991676,38.511614],"type":"Point"}
}