{
  "type": "Feature",
  "properties": {
    "iso:country":"US",
    "sg:address":"2400 Home Ave",
    "sg:city":"Berwyn",
    "sg:classifiers":[
        {
            "category":"Social Services",
            "type":"Services"
        }
    ],
    "sg:phone":"+1 708 863 2272",
    "sg:postcode":"60402",
    "sg:province":"IL",
    "wof:name":"Office Rehabilitation Services",
    "wof:placetype":"venue"
},
  "geometry": {"coordinates":[-87.79833600000001,41.845331],"type":"Point"}
}