{
  "type": "Feature",
  "properties": {
    "iso:country":"US",
    "sg:address":"321 N Morton Ave",
    "sg:city":"Morton",
    "sg:classifiers":[
        {
            "category":"Restaurant",
            "type":"Food & Drink"
        }
    ],
    "sg:menulink":"http://www.allmenus.com/il/morton/212485-mcdonalds/menu/",
    "sg:postcode":"61550",
    "sg:province":"IL",
    "sg:tags":[
        "burger",
        "american"
    ],
    "wof:name":"McDonald's",
    "wof:placetype":"venue"
},
  "geometry": {"coordinates":[-89.464412,40.616267],"type":"Point"}
}