{
  "type": "Feature",
  "properties": {
    "iso:country":"US",
    "sg:address":"1390 Howard St",
    "sg:city":"Elk Grove Village",
    "sg:classifiers":[
        {
            "category":"Manufacturing",
            "subcategory":"Signs",
            "type":"Manufacturing & Wholesale Goods"
        }
    ],
    "sg:phone":"+1 847 758 0415",
    "sg:postcode":"60007",
    "sg:province":"IL",
    "sg:tags":[
        "specialty",
        "mfg"
    ],
    "wof:name":"API",
    "wof:placetype":"venue"
},
  "geometry": {"coordinates":[-87.962907,42.016068],"type":"Point"}
}