{
  "type": "Feature",
  "properties": {
    "iso:country":"US",
    "sg:address":"4746 W Peterson Avenue",
    "sg:city":"Chicago",
    "sg:classifiers":[
        {
            "category":"Health Services",
            "subcategory":"Doctor",
            "type":"Services"
        }
    ],
    "sg:phone":"+1 773 685 3338",
    "sg:postcode":"60646",
    "sg:province":"IL",
    "wof:name":"Nelson Carrie DPM",
    "wof:placetype":"venue"
},
  "geometry": {"coordinates":[-87.747587,41.990052],"type":"Point"}
}