{
  "type": "Feature",
  "properties": {
    "iso:country":"US",
    "sg:address":"6325 W Belmont Avenue",
    "sg:city":"Chicago",
    "sg:classifiers":[
        {
            "category":"Health Services",
            "subcategory":"Dentist",
            "type":"Services"
        }
    ],
    "sg:phone":"+1 773 237 8999",
    "sg:postcode":"60634",
    "sg:province":"IL",
    "wof:name":"Wosiek Dental",
    "wof:placetype":"venue"
},
  "geometry": {"coordinates":[-87.78445499999999,41.938151],"type":"Point"}
}