{
  "type": "Feature",
  "properties": {
    "iso:country":"US",
    "sg:address":"122 E Fayette St",
    "sg:city":"Pittsfield",
    "sg:classifiers":[
        {
            "category":"Professional",
            "subcategory":"Computer Services",
            "type":"Services"
        }
    ],
    "sg:phone":"+1 217 285 1323",
    "sg:postcode":"62363",
    "sg:province":"IL",
    "sg:tags":[
        "internet"
    ],
    "wof:name":"Adams Network",
    "wof:placetype":"venue"
},
  "geometry": {"coordinates":[-90.805772,39.605678],"type":"Point"}
}