{
  "type": "Feature",
  "properties": {
    "iso:country":"US",
    "sg:address":"49 1/2 S Washington St # 1",
    "sg:city":"Hinsdale",
    "sg:classifiers":[
        {
            "category":"Real Estate",
            "subcategory":"Real Estate Services",
            "type":"Services"
        },
        {
            "category":"Real Estate",
            "subcategory":"Real Estate Agent",
            "type":"Services"
        }
    ],
    "sg:phone":"+1 630 323 2380",
    "sg:postcode":"60521",
    "sg:province":"IL",
    "sg:tags":[
        "management"
    ],
    "wof:name":"Towne Estates",
    "wof:placetype":"venue"
},
  "geometry": {"coordinates":[-87.929249,41.802056],"type":"Point"}
}