{
  "type": "Feature",
  "properties": {
    "addr:full":"2436 State Rte 116 Benson IL 61516",
    "addr:housenumber":"2436",
    "addr:postcode":"61516",
    "addr:street":"State Rte 116",
    "iso:country":"US",
    "sg:address":"2436 State Rte 116",
    "sg:city":"Benson",
    "sg:classifiers":[
        {
            "category":"Freight",
            "type":"Transportation"
        }
    ],
    "sg:phone":"+1 309 394 2243",
    "sg:postcode":"61516",
    "sg:province":"IL",
    "sg:tags":[
        "trucking"
    ],
    "wof:name":"Hood Trucking Inc",
    "wof:placetype":"venue"
},
  "geometry": {"coordinates":[-89.07814399999999,40.852866],"type":"Point"}
}