{
  "type": "Feature",
  "properties": {
    "addr:full":"996 State Rte 59 Aurora IL 60504",
    "addr:housenumber":"996",
    "addr:postcode":"60504",
    "addr:street":"State Rte 59",
    "iso:country":"US",
    "sg:address":"996 State Rte 59",
    "sg:city":"Aurora",
    "sg:classifiers":[
        {
            "category":"Shopping",
            "subcategory":"Musical Instruments",
            "type":"Retail Goods"
        }
    ],
    "sg:phone":"+1 630 375 1466",
    "sg:postcode":"60504",
    "sg:province":"IL",
    "wof:name":"Guitar Center",
    "wof:placetype":"venue"
},
  "geometry": {"coordinates":[-88.205748,41.783587],"type":"Point"}
}