{
  "type": "Feature",
  "properties": {
    "addr:full":"6851 North Ave Oak Park IL 60302",
    "addr:housenumber":"6851",
    "addr:postcode":"60302",
    "addr:street":"North Ave",
    "iso:country":"US",
    "sg:address":"6851 North Ave",
    "sg:city":"Oak Park",
    "sg:classifiers":[
        {
            "category":"Restaurant",
            "type":"Food & Drink"
        }
    ],
    "sg:phone":"+1   ",
    "sg:postcode":"60302",
    "sg:province":"IL",
    "sg:tags":[
        "eating"
    ],
    "wof:name":"Thais Oak Park Restaurant",
    "wof:placetype":"venue"
},
  "geometry": {"coordinates":[-87.79655099999999,41.909003],"type":"Point"}
}