{
  "type": "Feature",
  "properties": {
    "iso:country":"US",
    "sg:address":"237 W Dundee Rd",
    "sg:city":"Buffalo Grove",
    "sg:classifiers":[
        {
            "category":"Health Services",
            "subcategory":"Chiropractor",
            "type":"Services"
        }
    ],
    "sg:phone":"+1 847 537 4320",
    "sg:postcode":"60089",
    "sg:province":"IL",
    "wof:name":"Family Chiropractic Clinic",
    "wof:placetype":"venue"
},
  "geometry": {"coordinates":[-87.963289,42.138868],"type":"Point"}
}