{
  "type": "Feature",
  "properties": {
    "iso:country":"US",
    "sg:address":"420 N Main St",
    "sg:city":"Rockford",
    "sg:classifiers":[
        {
            "category":"Retail",
            "subcategory":"Funeral Services",
            "type":"Services"
        }
    ],
    "sg:phone":"+1 815 962 3703",
    "sg:postcode":"61103",
    "sg:province":"IL",
    "sg:tags":[
        "home"
    ],
    "wof:name":"Burpee-Wood Funeral Home",
    "wof:placetype":"venue"
},
  "geometry": {"coordinates":[-89.091077,42.276014],"type":"Point"}
}