{
  "type": "Feature",
  "properties": {
    "addr:full":"2750 N Ashland Ave Chicago IL 60614",
    "addr:housenumber":"2750",
    "addr:postcode":"60614",
    "addr:street":"N Ashland Ave",
    "iso:country":"US",
    "sg:address":"2750 N Ashland Ave",
    "sg:city":"Chicago",
    "sg:classifiers":[
        {
            "category":"Shopping",
            "subcategory":"Pets & Pet Supplies",
            "type":"Retail Goods"
        },
        {
            "category":"Retail",
            "subcategory":"Pet Boarding",
            "type":"Services"
        }
    ],
    "sg:phone":"+1 773 698 8731",
    "sg:postcode":"60614",
    "sg:province":"IL",
    "sg:tags":[
        "boarding/pet",
        "store",
        "groomers",
        "sitting"
    ],
    "sg:website":"www.furtastik.com",
    "wof:name":"Furtastik Grooming, Daycare & More!",
    "wof:placetype":"venue"
},
  "geometry": {"coordinates":[-87.66874,41.932079],"type":"Point"}
}