{
  "type": "Feature",
  "properties": {
    "iso:country":"US",
    "sg:address":"4554 N Broadway St Ste 234",
    "sg:city":"Chicago",
    "sg:classifiers":[
        {
            "category":"Professional",
            "subcategory":"Accounting & Tax Preparation",
            "type":"Services"
        }
    ],
    "sg:phone":"+1 773 769 1958",
    "sg:postcode":"60640",
    "sg:province":"IL",
    "sg:tags":[
        "accountant"
    ],
    "wof:name":"Ogele Hardy & Associates",
    "wof:placetype":"venue"
},
  "geometry": {"coordinates":[-87.656998,41.9646],"type":"Point"}
}