{
  "type": "Feature",
  "properties": {
    "iso:country":"US",
    "sg:address":"704 W Springfield Ave",
    "sg:city":"Champaign",
    "sg:classifiers":[
        {
            "category":"Retail",
            "subcategory":"Repair Shop",
            "type":"Services"
        }
    ],
    "sg:phone":"+1 217 637 2352",
    "sg:postcode":"61820",
    "sg:province":"IL",
    "wof:name":"Atkins Restorations",
    "wof:placetype":"venue"
},
  "geometry": {"coordinates":[-88.255397,40.112707],"type":"Point"}
}