{
  "type": "Feature",
  "properties": {
    "addr:full":"1498 E US Hwy 34 Earlville IL 60518",
    "addr:housenumber":"1498",
    "addr:postcode":"60518",
    "addr:street":"E Us Hwy 34",
    "iso:country":"US",
    "sg:address":"1498 E US Hwy 34",
    "sg:city":"Earlville",
    "sg:phone":"+1 815 246 9857",
    "sg:postcode":"60518",
    "sg:province":"IL",
    "sg:tags":[
        "farm",
        "soybean"
    ],
    "wof:name":"Fischer Farms",
    "wof:placetype":"venue"
},
  "geometry": {"coordinates":[-88.86648,41.586471],"type":"Point"}
}