{
  "type": "Feature",
  "properties": {
    "addr:full":"141 Market Pl Fairview Heights IL 62208",
    "addr:housenumber":"141",
    "addr:postcode":"62208",
    "addr:street":"Market Pl",
    "iso:country":"US",
    "sg:address":"141 Market Pl",
    "sg:city":"Fairview Heights",
    "sg:classifiers":[
        {
            "category":"Health Services",
            "subcategory":"Clinic",
            "type":"Services"
        }
    ],
    "sg:phone":"+1 618 394 1022",
    "sg:postcode":"62208",
    "sg:province":"IL",
    "sg:tags":[
        "home"
    ],
    "wof:name":"Addus Healthcare",
    "wof:placetype":"venue"
},
  "geometry": {"coordinates":[-89.99332200000001,38.595241],"type":"Point"}
}