{
  "type": "Feature",
  "properties": {
    "addr:full":"15534 W Idlewood Ln Libertyville IL 60048",
    "addr:housenumber":"15534",
    "addr:postcode":"60048",
    "addr:street":"W Idlewood Ln",
    "iso:country":"US",
    "sg:address":"15534 W Idlewood Ln",
    "sg:city":"Libertyville",
    "sg:classifiers":[
        {
            "category":"Retail",
            "subcategory":"Repair Shop",
            "type":"Services"
        }
    ],
    "sg:phone":"+1 847 362 5232",
    "sg:postcode":"60048",
    "sg:province":"IL",
    "sg:tags":[
        "appliance",
        "electrical"
    ],
    "wof:name":"Micks Appliance Repair Co",
    "wof:placetype":"venue"
},
  "geometry": {"coordinates":[-87.935205,42.303016],"type":"Point"}
}