{
  "type": "Feature",
  "properties": {
    "addr:full":"7201 N Ashland Blvd Chicago IL 60626",
    "addr:housenumber":"7201",
    "addr:postcode":"60626",
    "addr:street":"N Ashland Blvd",
    "iso:country":"US",
    "sg:address":"7201 N Ashland Blvd",
    "sg:city":"Chicago",
    "sg:classifiers":[
        {
            "category":"Place Of Worship",
            "subcategory":"Church",
            "type":"Public Place"
        },
        {
            "category":"Place Of Worship",
            "type":"Public Place"
        }
    ],
    "sg:phone":"+1 773 465 4777",
    "sg:postcode":"60626",
    "sg:province":"IL",
    "sg:tags":[
        "churches-apostolic",
        "churches-pentecostal-apostolic"
    ],
    "wof:name":"Apostolic Catholic Assyrian",
    "wof:placetype":"venue"
},
  "geometry": {"coordinates":[-87.670181,42.01273],"type":"Point"}
}