{
  "type": "Feature",
  "properties": {
    "addr:full":"966 W 21st St Chicago IL 60608",
    "addr:housenumber":"966",
    "addr:postcode":"60608",
    "addr:street":"W 21St St",
    "iso:country":"US",
    "sg:address":"966 W 21st St",
    "sg:city":"Chicago",
    "sg:classifiers":[
        {
            "category":"Health Services",
            "subcategory":"Doctor",
            "type":"Services"
        }
    ],
    "sg:phone":"+1 312 829 6854",
    "sg:postcode":"60608",
    "sg:province":"IL",
    "sg:tags":[
        "physician",
        "surgeon"
    ],
    "wof:name":"Kosanovich, Mark E, Md - Westlake Hosp",
    "wof:placetype":"venue"
},
  "geometry": {"coordinates":[-87.650599,41.853884],"type":"Point"}
}