{
  "type": "Feature",
  "properties": {
    "iso:country":"US",
    "sg:address":"20639 Renwick Rd",
    "sg:city":"Lockport",
    "sg:classifiers":[
        {
            "category":"Building & Trades",
            "subcategory":"Cleaning & Sanitation",
            "type":"Services"
        }
    ],
    "sg:phone":"+1 815 588 0011",
    "sg:postcode":"60441",
    "sg:province":"IL",
    "sg:tags":[
        "cleaning-industrial",
        "contractor"
    ],
    "wof:name":"Less Pay Cleaners",
    "wof:placetype":"venue"
},
  "geometry": {"coordinates":[-88.11947499999999,41.595345],"type":"Point"}
}