{
  "type": "Feature",
  "properties": {
    "addr:full":"1062 W Chicago Ave Fl 2 Chicago IL 60642",
    "addr:housenumber":"1062;2",
    "addr:postcode":"60642",
    "addr:street":"W Chicago Ave Fl",
    "iso:country":"US",
    "sg:address":"1062 W Chicago Ave Fl 2",
    "sg:city":"Chicago",
    "sg:classifiers":[
        {
            "category":"Professional",
            "subcategory":"Engineering",
            "type":"Services"
        }
    ],
    "sg:phone":"+1 312 942 1449",
    "sg:postcode":"60642",
    "sg:province":"IL",
    "sg:tags":[
        "engineer",
        "structural"
    ],
    "wof:name":"Kolbjorn Saether & Associates Inc",
    "wof:placetype":"venue"
},
  "geometry": {"coordinates":[-87.654556,41.896259],"type":"Point"}
}