{
  "type": "Feature",
  "properties": {
    "addr:full":"11217 E Camelot Ave Effingham IL 62401",
    "addr:housenumber":"11217",
    "addr:postcode":"62401",
    "addr:street":"E Camelot Ave",
    "iso:country":"US",
    "sg:address":"11217 E Camelot Ave",
    "sg:city":"Effingham",
    "sg:classifiers":[
        {
            "category":"Building & Trades",
            "subcategory":"Construction",
            "type":"Services"
        }
    ],
    "sg:phone":"+1 217 347 5807",
    "sg:postcode":"62401",
    "sg:province":"IL",
    "sg:tags":[
        "general",
        "contractor"
    ],
    "wof:name":"Crossroads Construction Inc",
    "wof:placetype":"venue"
},
  "geometry": {"coordinates":[-88.591408,39.135374],"type":"Point"}
}