{
  "type": "Feature",
  "properties": {
    "addr:full":"2958 N Milwaukee Ave Chicago IL 60618",
    "addr:housenumber":"2958",
    "addr:postcode":"60618",
    "addr:street":"N Milwaukee Ave",
    "iso:country":"US",
    "sg:address":"2958 N Milwaukee Ave",
    "sg:city":"Chicago",
    "sg:classifiers":[
        {
            "category":"Professional",
            "subcategory":"Lawyer & Legal Services",
            "type":"Services"
        }
    ],
    "sg:phone":"+1 773 770 3700",
    "sg:postcode":"60618",
    "sg:province":"IL",
    "wof:name":"Dymon Consulting",
    "wof:placetype":"venue"
},
  "geometry": {"coordinates":[-87.7174,41.935101],"type":"Point"}
}