{
  "type": "Feature",
  "properties": {
    "addr:full":"4520 N Beacon St Chicago IL 60640",
    "addr:housenumber":"4520",
    "addr:postcode":"60640",
    "addr:street":"N Beacon",
    "iso:country":"US",
    "sg:address":"4520 N Beacon St",
    "sg:city":"Chicago",
    "sg:classifiers":[
        {
            "category":"Social Services",
            "type":"Services"
        }
    ],
    "sg:phone":"+1 773 561 3500",
    "sg:postcode":"60640",
    "sg:province":"IL",
    "sg:tags":[
        "consulting",
        "management"
    ],
    "wof:name":"Uptown Center",
    "wof:placetype":"venue"
},
  "geometry": {"coordinates":[-87.663875,41.964933],"type":"Point"}
}