{
  "type": "Feature",
  "properties": {
    "iso:country":"US",
    "sg:address":"627 Putnam St",
    "sg:city":"Peru",
    "sg:classifiers":[
        {
            "category":"Retail",
            "subcategory":"Repair Shop",
            "type":"Services"
        }
    ],
    "sg:phone":"+1 815 223 1610",
    "sg:postcode":"61354",
    "sg:province":"IL",
    "sg:tags":[
        "portrait",
        "studio",
        "photo"
    ],
    "wof:name":"Video Services",
    "wof:placetype":"venue"
},
  "geometry": {"coordinates":[-89.127746,41.326475],"type":"Point"}
}