{
  "type": "Feature",
  "properties": {
    "iso:country":"US",
    "sg:address":"2551 Allan Dr",
    "sg:city":"Elk Grove Village",
    "sg:classifiers":[
        {
            "category":"Freight",
            "type":"Transportation"
        }
    ],
    "sg:phone":"+1 847 860 8600",
    "sg:postcode":"60007",
    "sg:province":"IL",
    "sg:tags":[
        "special",
        "arrangement"
    ],
    "wof:name":"Systems Transport Inc",
    "wof:placetype":"venue"
},
  "geometry": {"coordinates":[-87.97730799999999,41.988681],"type":"Point"}
}