{
  "type": "Feature",
  "properties": {
    "addr:full":"15395 Jeffrey Ln Brighton IL 62012",
    "addr:housenumber":"15395",
    "addr:postcode":"62012",
    "addr:street":"Jeffrey Ln",
    "iso:country":"US",
    "sg:address":"15395 Jeffrey Ln",
    "sg:city":"Brighton",
    "sg:classifiers":[
        {
            "category":"Professional",
            "subcategory":"Accounting & Tax Preparation",
            "type":"Services"
        }
    ],
    "sg:phone":"+1 618 372 3831",
    "sg:postcode":"62012",
    "sg:province":"IL",
    "sg:tags":[
        "return",
        "filing"
    ],
    "wof:name":"Rhonda Keeney's Income Tax Svc",
    "wof:placetype":"venue"
},
  "geometry": {"coordinates":[-90.15698,39.004562],"type":"Point"}
}