{
  "type": "Feature",
  "properties": {
    "iso:country":"US",
    "sg:address":"8844 Austin Ave",
    "sg:city":"Oak Lawn",
    "sg:classifiers":[
        {
            "category":"Organizations",
            "subcategory":"Religious Organization",
            "type":"Services"
        }
    ],
    "sg:phone":"+1 708 599 3660",
    "sg:postcode":"60453",
    "sg:province":"IL",
    "wof:name":"Wesleyan Community Church",
    "wof:placetype":"venue"
},
  "geometry": {"coordinates":[-87.770554,41.730652],"type":"Point"}
}