{
  "type": "Feature",
  "properties": {
    "addr:full":"6438 W 94th St Oak Lawn IL 60453",
    "addr:housenumber":"6438",
    "addr:postcode":"60453",
    "addr:street":"W 94Th St",
    "iso:country":"US",
    "sg:address":"6438 W 94th St",
    "sg:city":"Oak Lawn",
    "sg:classifiers":[
        {
            "category":"Professional",
            "subcategory":"Computer Services",
            "type":"Services"
        }
    ],
    "sg:phone":"+1 708 599 8345",
    "sg:postcode":"60453",
    "sg:province":"IL",
    "sg:tags":[
        "network"
    ],
    "wof:name":"Jsi",
    "wof:placetype":"venue"
},
  "geometry": {"coordinates":[-87.781229,41.72147],"type":"Point"}
}