{
  "type": "Feature",
  "properties": {
    "iso:country":"US",
    "sg:address":"4525 Barharbor Dr",
    "sg:city":"Lake In The Hills",
    "sg:classifiers":[
        {
            "category":"Bars & Pubs",
            "type":"Food & Drink"
        }
    ],
    "sg:phone":"+1   ",
    "sg:postcode":"60156",
    "sg:province":"IL",
    "sg:tags":[
        "drinking"
    ],
    "wof:name":"Electric Lounge Inc",
    "wof:placetype":"venue"
},
  "geometry": {"coordinates":[-88.380878,42.187372],"type":"Point"}
}