{
  "type": "Feature",
  "properties": {
    "addr:full":"215 E Broadway Trenton IL 62293",
    "addr:housenumber":"215",
    "addr:postcode":"62293",
    "addr:street":"E Broadway",
    "iso:country":"US",
    "sg:address":"215 E Broadway",
    "sg:city":"Trenton",
    "sg:classifiers":[
        {
            "category":"Professional",
            "subcategory":"Lawyer & Legal Services",
            "type":"Services"
        }
    ],
    "sg:phone":"+1 618 224 7882",
    "sg:postcode":"62293",
    "sg:province":"IL",
    "sg:tags":[
        "attorney",
        "practice",
        "plan"
    ],
    "wof:name":"J Patrick Callahan Pc",
    "wof:placetype":"venue"
},
  "geometry": {"coordinates":[-89.679608,38.605607],"type":"Point"}
}