{
  "type": "Feature",
  "properties": {
    "iso:country":"US",
    "sg:address":"1913 W Roosevelt Rd # 1",
    "sg:city":"Broadview",
    "sg:classifiers":[
        {
            "category":"Home & Garden",
            "subcategory":"Building Materials",
            "type":"Retail Goods"
        }
    ],
    "sg:phone":"+1 708 345 4242",
    "sg:postcode":"60155",
    "sg:province":"IL",
    "sg:tags":[
        "equipment",
        "fixture",
        "lighting"
    ],
    "sg:website":"www.gemelectricsupply.com",
    "wof:name":"Gem Electric Supply Inc",
    "wof:placetype":"venue"
},
  "geometry": {"coordinates":[-87.856003,41.8638],"type":"Point"}
}