{
  "type": "Feature",
  "properties": {
    "iso:country":"US",
    "sg:address":"3845 Oakton St",
    "sg:city":"Skokie",
    "sg:classifiers":[
        {
            "category":"Professional",
            "subcategory":"Management & Consulting",
            "type":"Services"
        }
    ],
    "sg:phone":"+1 847 679 0065",
    "sg:postcode":"60076",
    "sg:province":"IL",
    "sg:tags":[
        "access",
        "automation"
    ],
    "wof:name":"Smart Security Solutions Inc",
    "wof:placetype":"venue"
},
  "geometry": {"coordinates":[-87.724836,42.026201],"type":"Point"}
}