{
  "type": "Feature",
  "properties": {
    "iso:country":"US",
    "sg:address":"6805 Old Collinsville Rd",
    "sg:city":"O'Fallon",
    "sg:classifiers":[
        {
            "category":"Restaurant",
            "type":"Food & Drink"
        }
    ],
    "sg:phone":"+1 618 632 4866",
    "sg:postcode":"62269",
    "sg:province":"IL",
    "sg:tags":[
        "steakhouse"
    ],
    "sg:website":"www.andrias.com",
    "wof:name":"Andria's Restaurant",
    "wof:placetype":"venue"
},
  "geometry": {"coordinates":[-89.966304,38.600336],"type":"Point"}
}