{
  "type": "Feature",
  "properties": {
    "addr:full":"7131 S State St Chicago IL 60619",
    "addr:housenumber":"7131",
    "addr:postcode":"60619",
    "addr:street":"S State St",
    "iso:country":"US",
    "sg:address":"7131 S State St",
    "sg:city":"Chicago",
    "sg:classifiers":[
        {
            "category":"Building & Trades",
            "subcategory":"Locksmith",
            "type":"Services"
        }
    ],
    "sg:phone":"+1 773 896 9160",
    "sg:postcode":"60619",
    "sg:province":"IL",
    "sg:tags":[
        "key"
    ],
    "wof:name":"0101 All Chicago Locksmith & Lockout",
    "wof:placetype":"venue"
},
  "geometry": {"coordinates":[-87.624758,41.76435],"type":"Point"}
}