{
  "type": "Feature",
  "properties": {
    "iso:country":"US",
    "sg:address":"625 W Main St",
    "sg:city":"Braidwood",
    "sg:classifiers":[
        {
            "category":"Retail",
            "subcategory":"Auto Repair",
            "type":"Services"
        }
    ],
    "sg:phone":"+1 815 458 2017",
    "sg:postcode":"60408",
    "sg:province":"IL",
    "sg:tags":[
        "general"
    ],
    "wof:name":"Bryans Auto World",
    "wof:placetype":"venue"
},
  "geometry": {"coordinates":[-88.22970599999999,41.264216],"type":"Point"}
}