{
  "type": "Feature",
  "properties": {
    "addr:full":"9015 White Haven Rd Vernon IL 62892",
    "addr:housenumber":"9015",
    "addr:postcode":"62892",
    "addr:street":"White Haven Rd",
    "iso:country":"US",
    "sg:address":"9015 White Haven Rd",
    "sg:city":"Vernon",
    "sg:phone":"+1 618 432 5397",
    "sg:postcode":"62892",
    "sg:province":"IL",
    "sg:tags":[
        "farm",
        "wheat",
        "grain",
        "cash"
    ],
    "wof:name":"Ross Ballance",
    "wof:placetype":"venue"
},
  "geometry": {"coordinates":[-89.12358999999999,38.806789],"type":"Point"}
}