{
  "type": "Feature",
  "properties": {
    "iso:country":"US",
    "sg:address":"4353 W 107th St",
    "sg:city":"Oak Lawn",
    "sg:classifiers":[
        {
            "category":"Shopping",
            "subcategory":"Computers & Home Electronics",
            "type":"Retail Goods"
        }
    ],
    "sg:phone":"+1 708 636 4928",
    "sg:postcode":"60453",
    "sg:province":"IL",
    "wof:name":"K C Audio",
    "wof:placetype":"venue"
},
  "geometry": {"coordinates":[-87.729698,41.698299],"type":"Point"}
}