{
  "type": "Feature",
  "properties": {
    "iso:country":"US",
    "sg:address":"34 Danada Sq W",
    "sg:city":"Wheaton",
    "sg:classifiers":[
        {
            "category":"Shopping",
            "subcategory":"Hobbies, Toys, & Games",
            "type":"Retail Goods"
        }
    ],
    "sg:phone":"+1   ",
    "sg:postcode":"60187",
    "sg:province":"IL",
    "wof:name":"Lane Memorybook Limited",
    "wof:placetype":"venue"
},
  "geometry": {"coordinates":[-88.103773,41.833519],"type":"Point"}
}