{
  "type": "Feature",
  "properties": {
    "addr:full":"6005 Forest View Rd Lisle IL 60532",
    "addr:housenumber":"6005",
    "addr:postcode":"60532",
    "addr:street":"Forest View Rd",
    "iso:country":"US",
    "sg:address":"6005 Forest View Rd",
    "sg:city":"Lisle",
    "sg:classifiers":[
        {
            "category":"Sports & Exercise",
            "subcategory":"Ski Resort",
            "type":"Entertainment"
        }
    ],
    "sg:phone":"+1 630 964 2550",
    "sg:postcode":"60532",
    "sg:province":"IL",
    "wof:name":"Four Lakes Ski Area",
    "wof:placetype":"venue"
},
  "geometry": {"coordinates":[-88.080653,41.774841],"type":"Point"}
}