{
  "type": "Feature",
  "properties": {
    "addr:full":"1000 N Lake Shore Dr # 1902 Chicago IL 60611",
    "addr:housenumber":"1000",
    "addr:postcode":"60611",
    "addr:street":"N Lake Shore Dr # 1902",
    "iso:country":"US",
    "sg:address":"1000 N Lake Shore Dr # 1902",
    "sg:city":"Chicago",
    "sg:classifiers":[
        {
            "category":"Professional",
            "subcategory":"Lawyer & Legal Services",
            "type":"Services"
        }
    ],
    "sg:phone":"+1 312 751 0801",
    "sg:postcode":"60611",
    "sg:province":"IL",
    "sg:tags":[
        "clinic"
    ],
    "wof:name":"Schain Jerome S & Assoc Inc",
    "wof:placetype":"venue"
},
  "geometry": {"coordinates":[-87.614189,41.892355],"type":"Point"}
}