{
  "type": "Feature",
  "properties": {
    "addr:full":"1000 Liberty St Morris IL 60450",
    "addr:housenumber":"1000",
    "addr:postcode":"60450",
    "addr:street":"Liberty St",
    "iso:country":"US",
    "sg:address":"1000 Liberty St",
    "sg:city":"Morris",
    "sg:classifiers":[
        {
            "category":"Utilities",
            "subcategory":"Recycling",
            "type":"Services"
        }
    ],
    "sg:phone":"+1 815 933 0081",
    "sg:postcode":"60450",
    "sg:province":"IL",
    "sg:tags":[
        "rubbish",
        "removal"
    ],
    "wof:name":"United Disposal",
    "wof:placetype":"venue"
},
  "geometry": {"coordinates":[-88.423969,41.365009],"type":"Point"}
}