{
  "type": "Feature",
  "properties": {
    "iso:country":"US",
    "sg:address":"33 Center Dr",
    "sg:city":"Gilberts",
    "sg:classifiers":[
        {
            "category":"Professional",
            "type":"Services"
        }
    ],
    "sg:phone":"+1 847 426 3608",
    "sg:postcode":"60136",
    "sg:province":"IL",
    "wof:name":"James Eaton",
    "wof:placetype":"venue"
},
  "geometry": {"coordinates":[-88.36882799999999,42.102385],"type":"Point"}
}