{
  "type": "Feature",
  "properties": {
    "iso:country":"US",
    "sg:address":"1165 N Clark St",
    "sg:city":"Chicago",
    "sg:classifiers":[
        {
            "category":"Communications",
            "subcategory":"Newspaper",
            "type":"Services"
        }
    ],
    "sg:phone":"+1 312 642 1896",
    "sg:postcode":"60610",
    "sg:province":"IL",
    "sg:tags":[
        "print",
        "medium"
    ],
    "wof:name":"Chicago Family",
    "wof:placetype":"venue"
},
  "geometry": {"coordinates":[-87.631401,41.9034],"type":"Point"}
}