{
  "type": "Feature",
  "properties": {
    "addr:full":"1670 Checker Rd Lake Zurich IL 60047",
    "addr:housenumber":"1670",
    "addr:postcode":"60047",
    "addr:street":"Checker Rd",
    "iso:country":"US",
    "sg:address":"1670 Checker Rd",
    "sg:city":"Lake Zurich",
    "sg:classifiers":[
        {
            "category":"Organizations",
            "subcategory":"Religious Organization",
            "type":"Services"
        }
    ],
    "sg:phone":"+1   ",
    "sg:postcode":"60047",
    "sg:province":"IL",
    "wof:name":"Temple Chai",
    "wof:placetype":"venue"
},
  "geometry": {"coordinates":[-87.989628,42.160911],"type":"Point"}
}