{
  "type": "Feature",
  "properties": {
    "iso:country":"US",
    "sg:address":"1414 Taft Ave",
    "sg:city":"Wheaton",
    "sg:classifiers":[
        {
            "category":"Retail",
            "subcategory":"Repair Shop",
            "type":"Services"
        }
    ],
    "sg:phone":"+1 630 462 5300",
    "sg:postcode":"60187",
    "sg:province":"IL",
    "sg:tags":[
        "electrical"
    ],
    "wof:name":"Installation Department LLC",
    "wof:placetype":"venue"
},
  "geometry": {"coordinates":[-88.08481,41.858129],"type":"Point"}
}