{
  "type": "Feature",
  "properties": {
    "addr:full":"3402 Overlook Dr Richmond IL 60071",
    "addr:housenumber":"3402",
    "addr:postcode":"60071",
    "addr:street":"Overlook Dr",
    "iso:country":"US",
    "sg:address":"3402 Overlook Dr",
    "sg:city":"Richmond",
    "sg:classifiers":[
        {
            "category":"Building & Trades",
            "subcategory":"Landscaping Services",
            "type":"Services"
        }
    ],
    "sg:phone":"+1 815 678 2250",
    "sg:postcode":"60071",
    "sg:province":"IL",
    "sg:tags":[
        "landscape",
        "contractor"
    ],
    "wof:name":"Tree & Timber",
    "wof:placetype":"venue"
},
  "geometry": {"coordinates":[-88.263818,42.489281],"type":"Point"}
}