{
  "type": "Feature",
  "properties": {
    "addr:full":"501 E 3rd St Rock Falls IL 61071",
    "addr:housenumber":"501",
    "addr:postcode":"61071",
    "addr:street":"E 3Rd St",
    "iso:country":"US",
    "sg:address":"501 E 3rd St",
    "sg:city":"Rock Falls",
    "sg:classifiers":[
        {
            "category":"Health Services",
            "subcategory":"Doctor",
            "type":"Services"
        }
    ],
    "sg:phone":"+1 815 626 2157",
    "sg:postcode":"61071",
    "sg:province":"IL",
    "wof:name":"Donald Wilkin DDS",
    "wof:placetype":"venue"
},
  "geometry": {"coordinates":[-89.682406,41.782371],"type":"Point"}
}