{
  "type": "Feature",
  "properties": {
    "iso:country":"US",
    "sg:address":"7352 S Coles Ave",
    "sg:city":"Chicago",
    "sg:classifiers":[
        {
            "category":"Organizations",
            "subcategory":"Membership Organization",
            "type":"Services"
        }
    ],
    "sg:phone":"+1 773 721 7165",
    "sg:postcode":"60649",
    "sg:province":"IL",
    "sg:tags":[
        "religious"
    ],
    "wof:name":"Austrian Cultural Round Table",
    "wof:placetype":"venue"
},
  "geometry": {"coordinates":[-87.56062,41.761903],"type":"Point"}
}