{
  "type": "Feature",
  "properties": {
    "iso:country":"US",
    "sg:address":"2730 W Fargo Ave",
    "sg:city":"Chicago",
    "sg:classifiers":[
        {
            "category":"Professional",
            "subcategory":"Engineering",
            "type":"Services"
        }
    ],
    "sg:phone":"+1 773 465 0641",
    "sg:postcode":"60645",
    "sg:province":"IL",
    "wof:name":"Brenner & Associates",
    "wof:placetype":"venue"
},
  "geometry": {"coordinates":[-87.698345,42.016713],"type":"Point"}
}