{
  "type": "Feature",
  "properties": {
    "addr:full":"909 S Main St Jacksonville IL 62650",
    "addr:housenumber":"909",
    "addr:postcode":"62650",
    "addr:street":"S Main St",
    "iso:country":"US",
    "sg:address":"909 S Main St",
    "sg:city":"Jacksonville",
    "sg:classifiers":[
        {
            "category":"Autos & Motor Vehicles",
            "subcategory":"Automobile Sales",
            "type":"Retail Goods"
        }
    ],
    "sg:phone":"+1 217 243 2013",
    "sg:postcode":"62650",
    "sg:province":"IL",
    "sg:tags":[
        "car",
        "dealer"
    ],
    "wof:name":"Lincoln Land Auto Sales",
    "wof:placetype":"venue"
},
  "geometry": {"coordinates":[-90.22923299999999,39.724396],"type":"Point"}
}