{
  "type": "Feature",
  "properties": {
    "iso:country":"US",
    "sg:address":"261 County Road 150 N",
    "sg:city":"Teutopolis",
    "sg:classifiers":[
        {
            "category":"Farming",
            "subcategory":"Livestock Farm",
            "type":"Manufacturing & Wholesale Goods"
        },
        {
            "category":"Farming",
            "subcategory":"Farm",
            "type":"Manufacturing & Wholesale Goods"
        }
    ],
    "sg:phone":"+1 217 844 2281",
    "sg:postcode":"62467",
    "sg:province":"IL",
    "wof:name":"Steve Holkenbrink",
    "wof:placetype":"venue"
},
  "geometry": {"coordinates":[-88.4212,39.193044],"type":"Point"}
}