{
  "type": "Feature",
  "properties": {
    "addr:full":"2358 Harlem Ave Riverside IL 60546",
    "addr:housenumber":"2358",
    "addr:postcode":"60546",
    "addr:street":"Harlem Ave",
    "iso:country":"US",
    "sg:address":"2358 Harlem Ave",
    "sg:city":"Riverside",
    "sg:classifiers":[
        {
            "category":"Wholesale",
            "subcategory":"Computers",
            "type":"Manufacturing & Wholesale Goods"
        },
        {
            "category":"Shopping",
            "subcategory":"Music",
            "type":"Retail Goods"
        },
        {
            "category":"Home & Garden",
            "subcategory":"Household Appliances",
            "type":"Retail Goods"
        },
        {
            "category":"Professional",
            "subcategory":"Computer Services",
            "type":"Services"
        }
    ],
    "sg:phone":"+1 708 447 2757",
    "sg:postcode":"60546",
    "sg:province":"IL",
    "sg:tags":[
        "repair",
        "dvd's"
    ],
    "wof:name":"Best Buy",
    "wof:placetype":"venue"
},
  "geometry": {"coordinates":[-87.803703,41.8466],"type":"Point"}
}