{
  "type": "Feature",
  "properties": {
    "iso:country":"US",
    "sg:address":"2638 W Pratt Blvd",
    "sg:city":"Chicago",
    "sg:classifiers":[
        {
            "category":"Real Estate",
            "subcategory":"Real Estate Agent",
            "type":"Services"
        }
    ],
    "sg:phone":"+1 773 612 3355",
    "sg:postcode":"60645",
    "sg:province":"IL",
    "sg:tags":[
        "owner",
        "manager",
        "apartment"
    ],
    "wof:name":"Dymand Group Ltd",
    "wof:placetype":"venue"
},
  "geometry": {"coordinates":[-87.695392,42.005016],"type":"Point"}
}