{
  "type": "Feature",
  "properties": {
    "iso:country":"US",
    "sg:address":"22842 State Rte 41",
    "sg:city":"Prairie City",
    "sg:classifiers":[
        {
            "category":"Wholesale",
            "subcategory":"Motor Vehicles",
            "type":"Manufacturing & Wholesale Goods"
        }
    ],
    "sg:phone":"+1 309 775 4512",
    "sg:postcode":"61470",
    "sg:province":"IL",
    "sg:tags":[
        "trailer"
    ],
    "wof:name":"Wilson Trailer Sales Of Il",
    "wof:placetype":"venue"
},
  "geometry": {"coordinates":[-90.465393,40.599377],"type":"Point"}
}