{
  "type": "Feature",
  "properties": {
    "iso:country":"US",
    "sg:address":"2012 de Cook Ave",
    "sg:city":"Park Ridge",
    "sg:classifiers":[
        {
            "category":"Building & Trades",
            "subcategory":"Construction",
            "type":"Services"
        }
    ],
    "sg:phone":"+1 847 384 0465",
    "sg:postcode":"60068",
    "sg:province":"IL",
    "sg:tags":[
        "house"
    ],
    "wof:name":"Jaro Construction",
    "wof:placetype":"venue"
},
  "geometry": {"coordinates":[-87.85505999999999,42.033169],"type":"Point"}
}