{
  "type": "Feature",
  "properties": {
    "iso:country":"US",
    "sg:address":"1912 Heather Rd",
    "sg:city":"Geneva",
    "sg:classifiers":[
        {
            "category":"Real Estate",
            "subcategory":"Real Estate Agent",
            "type":"Services"
        }
    ],
    "sg:phone":"+1 630 232 2500",
    "sg:postcode":"60134",
    "sg:province":"IL",
    "sg:tags":[
        "appraiser"
    ],
    "wof:name":"Bankmann Appraisal Svc",
    "wof:placetype":"venue"
},
  "geometry": {"coordinates":[-88.324309,41.86627],"type":"Point"}
}