{
  "type": "Feature",
  "properties": {
    "addr:full":"2551 Allan Dr Elk Grove Village IL 60007",
    "addr:housenumber":"2551",
    "addr:postcode":"60007",
    "addr:street":"Allan Dr",
    "iso:country":"US",
    "sg:address":"2551 Allan Dr",
    "sg:city":"Elk Grove Village",
    "sg:classifiers":[
        {
            "category":"Wholesale",
            "subcategory":"Books, Periodicals, & Newspapers",
            "type":"Manufacturing & Wholesale Goods"
        }
    ],
    "sg:phone":"+1 630 238 0061",
    "sg:postcode":"60007",
    "sg:province":"IL",
    "wof:name":"Scholastic Book",
    "wof:placetype":"venue"
},
  "geometry": {"coordinates":[-87.97730799999999,41.988681],"type":"Point"}
}