{
  "type": "Feature",
  "properties": {
    "iso:country":"US",
    "sg:address":"3259 S Halsted St",
    "sg:city":"Chicago",
    "sg:classifiers":[
        {
            "category":"Wholesale",
            "subcategory":"Home Furnishings",
            "type":"Manufacturing & Wholesale Goods"
        }
    ],
    "sg:phone":"+1 312 326 5873",
    "sg:postcode":"60608",
    "sg:province":"IL",
    "sg:tags":[
        "blind",
        "shade"
    ],
    "wof:name":"Bertucci's Window Shades",
    "wof:placetype":"venue"
},
  "geometry": {"coordinates":[-87.646202,41.834702],"type":"Point"}
}