{
  "type": "Feature",
  "properties": {
    "iso:country":"US",
    "sg:address":"418 70 St",
    "sg:city":"Roseville",
    "sg:phone":"+1 309 426 2460",
    "sg:postcode":"61473",
    "sg:province":"IL",
    "sg:tags":[
        "farm",
        "corn",
        "beef",
        "feedlot",
        "cattle"
    ],
    "wof:name":"Whiteside Merle",
    "wof:placetype":"venue"
},
  "geometry": {"coordinates":[-90.65548200000001,40.636142],"type":"Point"}
}