{
  "type": "Feature",
  "properties": {
    "addr:full":"21962 Howell Dr New Lenox IL 60451",
    "addr:housenumber":"21962",
    "addr:postcode":"60451",
    "addr:street":"Howell Dr",
    "iso:country":"US",
    "sg:address":"21962 Howell Dr",
    "sg:city":"New Lenox",
    "sg:classifiers":[
        {
            "category":"Building & Trades",
            "subcategory":"Construction",
            "type":"Services"
        }
    ],
    "sg:phone":"+1 815 463 0866",
    "sg:postcode":"60451",
    "sg:province":"IL",
    "sg:tags":[
        "dry wall",
        "contractor"
    ],
    "wof:name":"Gorman Drywall Contractors",
    "wof:placetype":"venue"
},
  "geometry": {"coordinates":[-87.927819,41.489322],"type":"Point"}
}