{
  "type": "Feature",
  "properties": {
    "iso:country":"US",
    "sg:address":"811 W Wellington Avenue",
    "sg:city":"Chicago",
    "sg:classifiers":[
        {
            "category":"Health Services",
            "subcategory":"Doctor",
            "type":"Services"
        },
        {
            "category":"Health Services",
            "subcategory":"Dentist",
            "type":"Services"
        }
    ],
    "sg:phone":"+1 773 871 4964",
    "sg:postcode":"60657",
    "sg:province":"IL",
    "wof:name":"Pasiewicz Richard MD",
    "wof:placetype":"venue"
},
  "geometry": {"coordinates":[-87.64952700000001,41.936263],"type":"Point"}
}