{
  "type": "Feature",
  "properties": {
    "iso:country":"US",
    "sg:address":"3204 Country Bend Ln",
    "sg:city":"Champaign",
    "sg:classifiers":[
        {
            "category":"Arts & Performance",
            "subcategory":"Theater",
            "type":"Entertainment"
        }
    ],
    "sg:phone":"+1 217 356 6372",
    "sg:postcode":"61822",
    "sg:province":"IL",
    "sg:tags":[
        "group"
    ],
    "wof:name":"Interprep Com",
    "wof:placetype":"venue"
},
  "geometry": {"coordinates":[-88.297195,40.079989],"type":"Point"}
}