{
  "type": "Feature",
  "properties": {
    "addr:full":"1835 Apple Valley Rd Bolingbrook IL 60490",
    "addr:housenumber":"1835",
    "addr:postcode":"60490",
    "addr:street":"Apple Valley Rd",
    "iso:country":"US",
    "sg:address":"1835 Apple Valley Rd",
    "sg:city":"Bolingbrook",
    "sg:classifiers":[
        {
            "category":"Education",
            "subcategory":"School",
            "type":"Public Place"
        }
    ],
    "sg:phone":"+1 630 226 4400",
    "sg:postcode":"60490",
    "sg:province":"IL",
    "sg:tags":[
        "elementary"
    ],
    "wof:name":"Wayne Builta Elementary School",
    "wof:placetype":"venue"
},
  "geometry": {"coordinates":[-88.154087,41.690658],"type":"Point"}
}