{
  "type": "Feature",
  "properties": {
    "addr:full":"1527 W 18th St Chicago IL 60608",
    "addr:housenumber":"1527",
    "addr:postcode":"60608",
    "addr:street":"W 18Th St",
    "iso:country":"US",
    "sg:address":"1527 W 18th St",
    "sg:city":"Chicago",
    "sg:classifiers":[
        {
            "category":"Food & Beverages",
            "subcategory":"Liquor & Beverages",
            "type":"Retail Goods"
        }
    ],
    "sg:phone":"+1 312 733 7043",
    "sg:postcode":"60608",
    "sg:province":"IL",
    "sg:tags":[
        "beer",
        "spirit",
        "wine"
    ],
    "wof:name":"Guadalajara Food & Liquors Inc",
    "wof:placetype":"venue"
},
  "geometry": {"coordinates":[-87.665199,41.8577],"type":"Point"}
}