{
  "type": "Feature",
  "properties": {
    "addr:full":"386 Newberry Dr Elk Grove Village IL 60007",
    "addr:housenumber":"386",
    "addr:postcode":"60007",
    "addr:street":"Newberry Dr",
    "iso:country":"US",
    "sg:address":"386 Newberry Dr",
    "sg:city":"Elk Grove Village",
    "sg:classifiers":[
        {
            "category":"Professional",
            "subcategory":"Computer Services",
            "type":"Services"
        }
    ],
    "sg:phone":"+1 847 923 1926",
    "sg:postcode":"60007",
    "sg:province":"IL",
    "sg:tags":[
        "related"
    ],
    "wof:name":"Inovative Data Inc",
    "wof:placetype":"venue"
},
  "geometry": {"coordinates":[-88.057885,42.012796],"type":"Point"}
}