{
  "type": "Feature",
  "properties": {
    "iso:country":"US",
    "sg:address":"3616 W Bloomington Rd",
    "sg:city":"Champaign",
    "sg:classifiers":[
        {
            "category":"Organizations",
            "subcategory":"Community Association",
            "type":"Services"
        }
    ],
    "sg:phone":"+1 217 398 6805",
    "sg:postcode":"61822",
    "sg:province":"IL",
    "sg:tags":[
        "club"
    ],
    "wof:name":"Champaign County Radio Control",
    "wof:placetype":"venue"
},
  "geometry": {"coordinates":[-88.28553599999999,40.141687],"type":"Point"}
}