{
  "type": "Feature",
  "properties": {
    "addr:full":"7209 S Harvard Ave Chicago IL 60621",
    "addr:housenumber":"7209",
    "addr:postcode":"60621",
    "addr:street":"S Harvard Ave",
    "iso:country":"US",
    "sg:address":"7209 S Harvard Ave",
    "sg:city":"Chicago",
    "sg:classifiers":[
        {
            "category":"Shopping",
            "subcategory":"Hobbies, Toys, & Games",
            "type":"Retail Goods"
        },
        {
            "category":"Shopping",
            "subcategory":"Crafts & Fabrics",
            "type":"Retail Goods"
        }
    ],
    "sg:phone":"+1 773 499 1592",
    "sg:postcode":"60621",
    "sg:province":"IL",
    "sg:tags":[
        "shop",
        "hobby",
        "model",
        "supplies-wholesale",
        "manufacturer"
    ],
    "wof:name":"Shavon's Creations",
    "wof:placetype":"venue"
},
  "geometry": {"coordinates":[-87.63338899999999,41.763402],"type":"Point"}
}