{
  "type": "Feature",
  "properties": {
    "iso:country":"US",
    "sg:address":"294 Bristol St",
    "sg:city":"Northfield",
    "sg:classifiers":[
        {
            "category":"Wholesale",
            "subcategory":"Office Equipment",
            "type":"Manufacturing & Wholesale Goods"
        }
    ],
    "sg:phone":"+1 847 441 5926",
    "sg:postcode":"60093",
    "sg:province":"IL",
    "sg:tags":[
        "equipment-installation",
        "furniture"
    ],
    "wof:name":"F F And E Installation",
    "wof:placetype":"venue"
},
  "geometry": {"coordinates":[-87.775316,42.099697],"type":"Point"}
}