{
  "type": "Feature",
  "properties": {
    "iso:country":"US",
    "sg:address":"837 North Milwaukee Ave",
    "sg:city":"Chicago",
    "sg:classifiers":[
        {
            "category":"Real Estate",
            "subcategory":"Real Estate Services",
            "type":"Services"
        },
        {
            "category":"Banks & Credit Unions",
            "subcategory":"Financial Services",
            "type":"Services"
        }
    ],
    "sg:phone":"+1 312 376 3760",
    "sg:postcode":"60642",
    "sg:province":"IL",
    "sg:tags":[
        "broker",
        "mortgage"
    ],
    "sg:website":"www.americanstreet.com",
    "wof:name":"American Street Mortgage Company",
    "wof:placetype":"venue"
},
  "geometry": {"coordinates":[-87.656552,41.897007],"type":"Point"}
}