{
  "type": "Feature",
  "properties": {
    "iso:country":"US",
    "sg:address":"3865 W Columbus Ave",
    "sg:city":"Chicago",
    "sg:classifiers":[
        {
            "category":"Building & Trades",
            "subcategory":"Plumbing",
            "type":"Services"
        }
    ],
    "sg:phone":"+1 773 434 8888",
    "sg:postcode":"60652",
    "sg:province":"IL",
    "sg:tags":[
        "air",
        "heating",
        "conditioning/hvac"
    ],
    "wof:name":"Corner Heating & Cooling Co Inc",
    "wof:placetype":"venue"
},
  "geometry": {"coordinates":[-87.718498,41.737701],"type":"Point"}
}