{
  "type": "Feature",
  "properties": {
    "addr:full":"532 W Mill St Bethalto IL 62010",
    "addr:housenumber":"532",
    "addr:postcode":"62010",
    "addr:street":"W Mill St",
    "iso:country":"US",
    "sg:address":"532 W Mill St",
    "sg:city":"Bethalto",
    "sg:classifiers":[
        {
            "category":"Manufacturing",
            "subcategory":"Tools & Machinery",
            "type":"Manufacturing & Wholesale Goods"
        }
    ],
    "sg:phone":"+1 618 558 2769",
    "sg:postcode":"62010",
    "sg:province":"IL",
    "sg:tags":[
        "mfg"
    ],
    "wof:name":"Air Advantage & More",
    "wof:placetype":"venue"
},
  "geometry": {"coordinates":[-90.04992300000001,38.910813],"type":"Point"}
}