{
  "type": "Feature",
  "properties": {
    "iso:country":"US",
    "sg:address":"930 W Leland Ave",
    "sg:city":"Chicago",
    "sg:classifiers":[
        {
            "category":"Professional",
            "subcategory":"Business Services",
            "type":"Services"
        }
    ],
    "sg:phone":"+1 773 450 0752",
    "sg:postcode":"60640",
    "sg:province":"IL",
    "wof:name":"Thresholds Design Group",
    "wof:placetype":"venue"
},
  "geometry": {"coordinates":[-87.653663,41.967372],"type":"Point"}
}