{
  "type": "Feature",
  "properties": {
    "addr:full":"4179 W Irving Park Road Chicago IL 60641",
    "addr:housenumber":"4179",
    "addr:postcode":"60641",
    "addr:street":"W Irving Park Road",
    "iso:country":"US",
    "sg:address":"4179 W Irving Park Road",
    "sg:city":"Chicago",
    "sg:classifiers":[
        {
            "category":"Building & Trades",
            "subcategory":"Locksmith",
            "type":"Services"
        }
    ],
    "sg:phone":"+1 773 663 4118",
    "sg:postcode":"60641",
    "sg:province":"IL",
    "sg:tags":[
        "key"
    ],
    "wof:name":"Emergency Locksmith",
    "wof:placetype":"venue"
},
  "geometry": {"coordinates":[-87.732231,41.953298],"type":"Point"}
}