{
  "type": "Feature",
  "properties": {
    "iso:country":"US",
    "sg:address":"215 E North St",
    "sg:city":"Bradley",
    "sg:classifiers":[
        {
            "category":"Wholesale",
            "subcategory":"Electrical",
            "type":"Manufacturing & Wholesale Goods"
        }
    ],
    "sg:phone":"+1 815 937 9234",
    "sg:postcode":"60915",
    "sg:province":"IL",
    "sg:tags":[
        "alarm",
        "burglar",
        "system"
    ],
    "wof:name":"Monitronics International",
    "wof:placetype":"venue"
},
  "geometry": {"coordinates":[-87.85687,41.148098],"type":"Point"}
}