{
  "type": "Feature",
  "properties": {
    "iso:country":"US",
    "sg:address":"446 W Diversey Pkwy Frnt",
    "sg:city":"Chicago",
    "sg:classifiers":[
        {
            "category":"Food & Beverages",
            "subcategory":"Liquor & Beverages",
            "type":"Retail Goods"
        }
    ],
    "sg:phone":"+1 773 327 1210",
    "sg:postcode":"60614",
    "sg:province":"IL",
    "sg:tags":[
        "beer",
        "spirit",
        "wine"
    ],
    "wof:name":"Eastgate Wine & Spirits",
    "wof:placetype":"venue"
},
  "geometry": {"coordinates":[-87.640297,41.932899],"type":"Point"}
}