{
  "type": "Feature",
  "properties": {
    "addr:full":"7206 Viscaya Blvd Spring Grove IL 60081",
    "addr:housenumber":"7206",
    "addr:postcode":"60081",
    "addr:street":"Viscaya Blvd",
    "iso:country":"US",
    "sg:address":"7206 Viscaya Blvd",
    "sg:city":"Spring Grove",
    "sg:classifiers":[
        {
            "category":"Building & Trades",
            "subcategory":"Construction",
            "type":"Services"
        }
    ],
    "sg:phone":"+1 847 587 0220",
    "sg:postcode":"60081",
    "sg:province":"IL",
    "sg:tags":[
        "general",
        "contractor"
    ],
    "wof:name":"Longshore/Daly Inc",
    "wof:placetype":"venue"
},
  "geometry": {"coordinates":[-88.17321099999999,42.426993],"type":"Point"}
}