{
  "type": "Feature",
  "properties": {
    "addr:full":"350 E Cermak Rd Chicago IL 60616",
    "addr:housenumber":"350",
    "addr:postcode":"60616",
    "addr:street":"E Cermak Rd",
    "iso:country":"US",
    "sg:address":"350 E Cermak Rd",
    "sg:city":"Chicago",
    "sg:classifiers":[
        {
            "category":"Autos & Motor Vehicles",
            "subcategory":"Auto Supplies",
            "type":"Retail Goods"
        }
    ],
    "sg:phone":"+1 312 674 1346",
    "sg:postcode":"60616",
    "sg:province":"IL",
    "sg:tags":[
        "automobile",
        "accessories-wholesale",
        "parts",
        "manufacturer"
    ],
    "wof:name":"Delphi Automotive",
    "wof:placetype":"venue"
},
  "geometry": {"coordinates":[-87.619011,41.852989],"type":"Point"}
}