{
  "type": "Feature",
  "properties": {
    "addr:full":"900 W Temple Ave Ste 101 Effingham IL 62401",
    "addr:housenumber":"900",
    "addr:postcode":"62401",
    "addr:street":"W Temple Ave Ste 101",
    "iso:country":"US",
    "sg:address":"900 W Temple Ave Ste 101",
    "sg:city":"Effingham",
    "sg:classifiers":[
        {
            "category":"Health Services",
            "subcategory":"Doctor",
            "type":"Services"
        }
    ],
    "sg:phone":"+1 217 342 9774",
    "sg:postcode":"62401",
    "sg:province":"IL",
    "sg:tags":[
        "medicine",
        "physician",
        "practice",
        "surgeons",
        "family"
    ],
    "sg:website":"http://www.effinghamsurgical.com",
    "wof:name":"S C Esa",
    "wof:placetype":"venue"
},
  "geometry": {"coordinates":[-88.552933,39.127541],"type":"Point"}
}