{
  "type": "Feature",
  "properties": {
    "iso:country":"US",
    "sg:address":"5825 S Adams St",
    "sg:city":"Bartonville",
    "sg:classifiers":[
        {
            "category":"Professional",
            "subcategory":"Printing & Photocopies",
            "type":"Services"
        }
    ],
    "sg:phone":"+1 309 697 5296",
    "sg:postcode":"61607",
    "sg:province":"IL",
    "sg:tags":[
        "lithographer"
    ],
    "wof:name":"Kaufmans Printing And Specialt",
    "wof:placetype":"venue"
},
  "geometry": {"coordinates":[-89.651903,40.653328],"type":"Point"}
}