{
  "type": "Feature",
  "properties": {
    "iso:country":"US",
    "sg:address":"1 Twin Lake Dr",
    "sg:city":"East St Louis",
    "sg:classifiers":[
        {
            "category":"Wholesale",
            "subcategory":"Auto Parts",
            "type":"Manufacturing & Wholesale Goods"
        }
    ],
    "sg:phone":"+1 618 398 7109",
    "sg:postcode":"62203",
    "sg:province":"IL",
    "sg:tags":[
        "equipment",
        "truck"
    ],
    "wof:name":"Dynamic Drivetrain Svc",
    "wof:placetype":"venue"
},
  "geometry": {"coordinates":[-90.094608,38.61702],"type":"Point"}
}