{
  "type": "Feature",
  "properties": {
    "addr:full":"550 W Washington Boulevard Chicago IL 60661",
    "addr:housenumber":"550",
    "addr:postcode":"60661",
    "addr:street":"W Washington Boulevard",
    "iso:country":"US",
    "sg:address":"550 W Washington Boulevard",
    "sg:city":"Chicago",
    "sg:classifiers":[
        {
            "category":"Professional",
            "subcategory":"Lawyer & Legal Services",
            "type":"Services"
        }
    ],
    "sg:phone":"+1 312 775 9750",
    "sg:postcode":"60661",
    "sg:province":"IL",
    "wof:name":"Grant Ross & Pittman",
    "wof:placetype":"venue"
},
  "geometry": {"coordinates":[-87.64165199999999,41.883202],"type":"Point"}
}