{
  "type": "Feature",
  "properties": {
    "iso:country":"US",
    "sg:address":"5480 S Kenwood Avenue",
    "sg:city":"Chicago",
    "sg:classifiers":[
        {
            "category":"Social Services",
            "subcategory":"Child Care",
            "type":"Services"
        }
    ],
    "sg:phone":"+1 773 643 4062",
    "sg:postcode":"60615",
    "sg:province":"IL",
    "sg:tags":[
        "day"
    ],
    "wof:name":"Hyde Park Neighborhood Club",
    "wof:placetype":"venue"
},
  "geometry": {"coordinates":[-87.5934,41.79533],"type":"Point"}
}