{
  "type": "Feature",
  "properties": {
    "iso:country":"US",
    "sg:address":"2101 Waukegan Rd",
    "sg:city":"Bannockburn",
    "sg:classifiers":[
        {
            "category":"Personal",
            "subcategory":"Hair Removal",
            "type":"Services"
        }
    ],
    "sg:phone":"+1 847 374 1060",
    "sg:postcode":"60015",
    "sg:province":"IL",
    "sg:tags":[
        "removing"
    ],
    "wof:name":"Advance Laser Clinics",
    "wof:placetype":"venue"
},
  "geometry": {"coordinates":[-87.858436,42.190844],"type":"Point"}
}