{
  "type": "Feature",
  "properties": {
    "addr:full":"1136 W Lawrence Ave Chicago IL 60640",
    "addr:housenumber":"1136",
    "addr:postcode":"60640",
    "addr:street":"W Lawrence Ave",
    "iso:country":"US",
    "sg:address":"1136 W Lawrence Ave",
    "sg:city":"Chicago",
    "sg:classifiers":[
        {
            "category":"Bars & Pubs",
            "subcategory":"Sports Bar",
            "type":"Food & Drink"
        },
        {
            "category":"Bars & Pubs",
            "subcategory":"Lounge",
            "type":"Food & Drink"
        }
    ],
    "sg:phone":"+1 773 878 1136",
    "sg:postcode":"60640",
    "sg:province":"IL",
    "sg:website":"www.uptownlounge.net",
    "wof:name":"Uptown Lounge",
    "wof:placetype":"venue"
},
  "geometry": {"coordinates":[-87.658834,41.969066],"type":"Point"}
}