{
  "type": "Feature",
  "properties": {
    "iso:country":"US",
    "sg:address":"5614 E 825th Ave",
    "sg:city":"Altamont",
    "sg:classifiers":[
        {
            "category":"Retail",
            "subcategory":"Animal Services",
            "type":"Services"
        }
    ],
    "sg:phone":"+1 618 483 5179",
    "sg:postcode":"62411",
    "sg:province":"IL",
    "wof:name":"Heidanes Hidden Timbers",
    "wof:placetype":"venue"
},
  "geometry": {"coordinates":[-88.707743,39.034929],"type":"Point"}
}