{
  "type": "Feature",
  "properties": {
    "iso:country":"US",
    "sg:address":"552 1st St",
    "sg:city":"La Salle",
    "sg:classifiers":[
        {
            "category":"Retail",
            "subcategory":"Auto Repair",
            "type":"Services"
        }
    ],
    "sg:phone":"+1 815 224 1140",
    "sg:postcode":"61301",
    "sg:province":"IL",
    "sg:tags":[
        "repairing",
        "automobile"
    ],
    "wof:name":"Last Muffler & Brake Shop",
    "wof:placetype":"venue"
},
  "geometry": {"coordinates":[-89.09739999999999,41.327836],"type":"Point"}
}