{
  "type": "Feature",
  "properties": {
    "addr:full":"3848 Cahokia Ln Charleston IL 61920",
    "addr:housenumber":"3848",
    "addr:postcode":"61920",
    "addr:street":"Cahokia Ln",
    "iso:country":"US",
    "sg:address":"3848 Cahokia Ln",
    "sg:city":"Charleston",
    "sg:classifiers":[
        {
            "category":"Professional",
            "type":"Services"
        }
    ],
    "sg:phone":"+1 217 345 2534",
    "sg:postcode":"61920",
    "sg:province":"IL",
    "wof:name":"Geology Consultant",
    "wof:placetype":"venue"
},
  "geometry": {"coordinates":[-88.216527,39.429226],"type":"Point"}
}