{
  "type": "Feature",
  "properties": {
    "addr:full":"456 N Main St Sycamore IL 60178",
    "addr:housenumber":"456",
    "addr:postcode":"60178",
    "addr:street":"N Main St",
    "iso:country":"US",
    "sg:address":"456 N Main St",
    "sg:city":"Sycamore",
    "sg:classifiers":[
        {
            "category":"Professional",
            "type":"Services"
        }
    ],
    "sg:phone":"+1 815 899 2333",
    "sg:postcode":"60178",
    "sg:province":"IL",
    "sg:tags":[
        "caterer"
    ],
    "sg:website":"http://www.countrystorecatering.com",
    "wof:name":"Country Store & Catering",
    "wof:placetype":"venue"
},
  "geometry": {"coordinates":[-88.683205,41.994038],"type":"Point"}
}