{
  "type": "Feature",
  "properties": {
    "addr:full":"1800 Hollister Dr Libertyville IL 60048",
    "addr:housenumber":"1800",
    "addr:postcode":"60048",
    "addr:street":"Hollister Dr",
    "iso:country":"US",
    "sg:address":"1800 Hollister Dr",
    "sg:city":"Libertyville",
    "sg:classifiers":[
        {
            "category":"Health Services",
            "subcategory":"Doctor",
            "type":"Services"
        }
    ],
    "sg:phone":"+1 847 367 6781",
    "sg:postcode":"60048",
    "sg:province":"IL",
    "sg:tags":[
        "physician",
        "surgeon"
    ],
    "wof:name":"North Shore Oncology LTD",
    "wof:placetype":"venue"
},
  "geometry": {"coordinates":[-87.94590599999999,42.24884],"type":"Point"}
}