{
  "type": "Feature",
  "properties": {
    "addr:full":"1699 Wall St Mount Prospect IL 60056",
    "addr:housenumber":"1699",
    "addr:postcode":"60056",
    "addr:street":"Wall St",
    "iso:country":"US",
    "sg:address":"1699 Wall St",
    "sg:city":"Mount Prospect",
    "sg:classifiers":[
        {
            "category":"Shopping",
            "subcategory":"Computers & Home Electronics",
            "type":"Retail Goods"
        }
    ],
    "sg:phone":"+1 847 427 9450",
    "sg:postcode":"60056",
    "sg:province":"IL",
    "sg:tags":[
        "related",
        "software"
    ],
    "wof:name":"Business Control Systems Inc",
    "wof:placetype":"venue"
},
  "geometry": {"coordinates":[-87.943552,42.035472],"type":"Point"}
}