{
  "type": "Feature",
  "properties": {
    "iso:country":"US",
    "sg:address":"367 E Potter St",
    "sg:city":"Wood Dale",
    "sg:classifiers":[
        {
            "category":"Manufacturing",
            "subcategory":"Metals",
            "type":"Manufacturing & Wholesale Goods"
        },
        {
            "category":"Manufacturing",
            "subcategory":"Tools & Machinery",
            "type":"Manufacturing & Wholesale Goods"
        }
    ],
    "sg:phone":"+1 630 350 1775",
    "sg:postcode":"60191",
    "sg:province":"IL",
    "sg:tags":[
        "d",
        "mfg",
        "die",
        "supply",
        "trade",
        "equipment",
        "cutting",
        "printing"
    ],
    "sg:website":"www.gardallmfgcorp.com",
    "wof:name":"Gardall Manufacturing Company",
    "wof:placetype":"venue"
},
  "geometry": {"coordinates":[-87.966789,41.960187],"type":"Point"}
}