{
  "type": "Feature",
  "properties": {
    "addr:full":"2312 W Leland Ave Chicago IL 60625",
    "addr:housenumber":"2312",
    "addr:postcode":"60625",
    "addr:street":"W Leland Ave",
    "iso:country":"US",
    "sg:address":"2312 W Leland Ave",
    "sg:city":"Chicago",
    "sg:phone":"+1 773 784 2314",
    "sg:postcode":"60625",
    "sg:province":"IL",
    "wof:name":"Bouffe",
    "wof:placetype":"venue"
},
  "geometry": {"coordinates":[-87.68782400000001,41.966712],"type":"Point"}
}