{
  "type": "Feature",
  "properties": {
    "addr:full":"8303 W Higgins Rd Ste 400 Chicago IL 60631",
    "addr:housenumber":"8303",
    "addr:postcode":"60631",
    "addr:street":"W Higgins Rd Ste 400",
    "iso:country":"US",
    "sg:address":"8303 W Higgins Rd Ste 400",
    "sg:city":"Chicago",
    "sg:classifiers":[
        {
            "category":"Wholesale",
            "subcategory":"Machinery & Supplies",
            "type":"Manufacturing & Wholesale Goods"
        }
    ],
    "sg:phone":"+1 773 864 8000",
    "sg:postcode":"60631",
    "sg:province":"IL",
    "sg:tags":[
        "industrial",
        "equipment",
        "used",
        "machinery-new",
        "supplies-wholesale"
    ],
    "wof:name":"A P V Crepaco",
    "wof:placetype":"venue"
},
  "geometry": {"coordinates":[-87.834818,41.986078],"type":"Point"}
}