{
  "type": "Feature",
  "properties": {
    "addr:full":"7 Ashbury Ln Barrington IL 60010",
    "addr:housenumber":"7",
    "addr:postcode":"60010",
    "addr:street":"Ashbury Ln",
    "iso:country":"US",
    "sg:address":"7 Ashbury Ln",
    "sg:city":"Barrington",
    "sg:classifiers":[
        {
            "category":"Professional",
            "type":"Services"
        }
    ],
    "sg:phone":"+1 847 382 8669",
    "sg:postcode":"60010",
    "sg:province":"IL",
    "sg:tags":[
        "writer"
    ],
    "wof:name":"Wells Communication",
    "wof:placetype":"venue"
},
  "geometry": {"coordinates":[-88.236756,42.155782],"type":"Point"}
}