{
  "type": "Feature",
  "properties": {
    "addr:full":"847 S River St Aurora IL 60506",
    "addr:housenumber":"847",
    "addr:postcode":"60506",
    "addr:street":"S River St",
    "iso:country":"US",
    "sg:address":"847 S River St",
    "sg:city":"Aurora",
    "sg:classifiers":[
        {
            "category":"Building & Trades",
            "subcategory":"Plumbing",
            "type":"Services"
        }
    ],
    "sg:phone":"+1 630 554 8991",
    "sg:postcode":"60506",
    "sg:province":"IL",
    "sg:tags":[
        "plumbing",
        "contractor"
    ],
    "wof:name":"Shank & Sons Plumbing",
    "wof:placetype":"venue"
},
  "geometry": {"coordinates":[-88.329874,41.743588],"type":"Point"}
}