{
  "type": "Feature",
  "properties": {
    "addr:full":"1500 N Cherry St Mount Carmel IL 62863",
    "addr:housenumber":"1500",
    "addr:postcode":"62863",
    "addr:street":"N Cherry St",
    "iso:country":"US",
    "sg:address":"1500 N Cherry St",
    "sg:city":"Mount Carmel",
    "sg:classifiers":[
        {
            "category":"Professional",
            "subcategory":"Accounting & Tax Preparation",
            "type":"Services"
        }
    ],
    "sg:phone":"+1 618 263 3888",
    "sg:postcode":"62863",
    "sg:province":"IL",
    "wof:name":"Kemper CPA Group LLC",
    "wof:placetype":"venue"
},
  "geometry": {"coordinates":[-87.76573500000001,38.425821],"type":"Point"}
}