{
  "type": "Feature",
  "properties": {
    "addr:full":"555 Highgrove Blvd Glendale Heights IL 60139",
    "addr:housenumber":"555",
    "addr:postcode":"60139",
    "addr:street":"Highgrove Blvd",
    "iso:country":"US",
    "sg:address":"555 Highgrove Blvd",
    "sg:city":"Glendale Heights",
    "sg:classifiers":[
        {
            "category":"Local Transit",
            "type":"Transportation"
        }
    ],
    "sg:phone":"+1 630 896 4114",
    "sg:postcode":"60139",
    "sg:province":"IL",
    "sg:tags":[
        "ambulance"
    ],
    "wof:name":"American Medical Response",
    "wof:placetype":"venue"
},
  "geometry": {"coordinates":[-88.06564400000001,41.932621],"type":"Point"}
}