{
  "type": "Feature",
  "properties": {
    "addr:full":"28451 S Rte 45 Peotone IL 60468",
    "addr:housenumber":"28451",
    "addr:postcode":"60468",
    "addr:street":"S Rte 45",
    "iso:country":"US",
    "sg:address":"28451 S Rte 45",
    "sg:city":"Peotone",
    "sg:classifiers":[
        {
            "category":"Freight",
            "type":"Transportation"
        }
    ],
    "sg:phone":"+1 708 258 3268",
    "sg:postcode":"60468",
    "sg:province":"IL",
    "sg:tags":[
        "grain",
        "elevator"
    ],
    "wof:name":"Andres & Wilton Farmers Grain",
    "wof:placetype":"venue"
},
  "geometry": {"coordinates":[-87.882548,41.370912],"type":"Point"}
}