{
  "type": "Feature",
  "properties": {
    "iso:country":"US",
    "sg:address":"222 N Western Ave",
    "sg:city":"Carpentersville",
    "sg:classifiers":[
        {
            "category":"Personal",
            "subcategory":"Beauty Salon",
            "type":"Services"
        }
    ],
    "sg:phone":"+1 847 426 1011",
    "sg:postcode":"60110",
    "sg:province":"IL",
    "sg:tags":[
        "hair"
    ],
    "wof:name":"Opulence Hair Salon Inc",
    "wof:placetype":"venue"
},
  "geometry": {"coordinates":[-88.296463,42.11449],"type":"Point"}
}