{
  "type": "Feature",
  "properties": {
    "addr:full":"379 S Prospect Ave Bartlett IL 60103",
    "addr:housenumber":"379",
    "addr:postcode":"60103",
    "addr:street":"S Prospect Ave",
    "iso:country":"US",
    "sg:address":"379 S Prospect Ave",
    "sg:city":"Bartlett",
    "sg:classifiers":[
        {
            "category":"Personal",
            "subcategory":"Tanning Parlor",
            "type":"Services"
        },
        {
            "category":"Personal",
            "subcategory":"Beauty Salon",
            "type":"Services"
        },
        {
            "category":"Personal",
            "subcategory":"Nail Salon",
            "type":"Services"
        }
    ],
    "sg:phone":"+1 630 830 7191",
    "sg:postcode":"60103",
    "sg:province":"IL",
    "sg:tags":[
        "hair",
        "stylist"
    ],
    "wof:name":"Peacocks Hair Boutique",
    "wof:placetype":"venue"
},
  "geometry": {"coordinates":[-88.174004,41.987999],"type":"Point"}
}