{
  "type": "Feature",
  "properties": {
    "iso:country":"US",
    "sg:address":"3806 E State St",
    "sg:city":"Rockford",
    "sg:classifiers":[
        {
            "category":"Personal",
            "type":"Services"
        }
    ],
    "sg:phone":"+1 815 394 0877",
    "sg:postcode":"61108",
    "sg:province":"IL",
    "wof:name":"Powertan",
    "wof:placetype":"venue"
},
  "geometry": {"coordinates":[-89.041912,42.266151],"type":"Point"}
}