{
  "type": "Feature",
  "properties": {
    "addr:full":"4632 Trevor Cir Apt 4 Rockford IL 61109",
    "addr:housenumber":"4632;4",
    "addr:postcode":"61109",
    "addr:street":"Trevor Cir Apt",
    "iso:country":"US",
    "sg:address":"4632 Trevor Cir Apt 4",
    "sg:city":"Rockford",
    "sg:classifiers":[
        {
            "category":"Restaurant",
            "type":"Food & Drink"
        }
    ],
    "sg:phone":"+1 815 873 9977",
    "sg:postcode":"61109",
    "sg:province":"IL",
    "sg:tags":[
        "style",
        "family"
    ],
    "wof:name":"Red Apple Family Restauran",
    "wof:placetype":"venue"
},
  "geometry": {"coordinates":[-89.028488,42.211479],"type":"Point"}
}