{
  "type": "Feature",
  "properties": {
    "iso:country":"US",
    "sg:address":"10700 S Western Ave",
    "sg:city":"Chicago",
    "sg:classifiers":[
        {
            "category":"Health Services",
            "subcategory":"Chiropractor",
            "type":"Services"
        }
    ],
    "sg:phone":"+1 773 881 7776",
    "sg:postcode":"60643",
    "sg:province":"IL",
    "wof:name":"Elias Chiropractic Clinic",
    "wof:placetype":"venue"
},
  "geometry": {"coordinates":[-87.68139600000001,41.698898],"type":"Point"}
}