{
  "type": "Feature",
  "properties": {
    "iso:country":"US",
    "sg:address":"2901 N Clyborn",
    "sg:city":"Chicago",
    "sg:classifiers":[
        {
            "category":"Real Estate",
            "subcategory":"Real Estate Agent",
            "type":"Services"
        }
    ],
    "sg:phone":"+1 312 342 9333",
    "sg:postcode":"60618",
    "sg:province":"IL",
    "sg:website":"www.therealestatematchmaker.com/",
    "wof:name":"Cecily Crowther - Remax",
    "wof:placetype":"venue"
},
  "geometry": {"coordinates":[-87.681786,41.935071],"type":"Point"}
}