{
  "type": "Feature",
  "properties": {
    "iso:country":"US",
    "sg:address":"2845 Camp Jackson Rd",
    "sg:city":"Cahokia",
    "sg:classifiers":[
        {
            "category":"Restaurant",
            "type":"Food & Drink"
        }
    ],
    "sg:phone":"+1 618 332 2794",
    "sg:postcode":"62206",
    "sg:province":"IL",
    "wof:name":"Derby's Al's Diner",
    "wof:placetype":"venue"
},
  "geometry": {"coordinates":[-90.129229,38.54989],"type":"Point"}
}