{
  "type": "Feature",
  "properties": {
    "addr:full":"1101 Sheila Dr Joliet IL 60435",
    "addr:housenumber":"1101",
    "addr:postcode":"60435",
    "addr:street":"Sheila Dr",
    "iso:country":"US",
    "sg:address":"1101 Sheila Dr",
    "sg:city":"Joliet",
    "sg:classifiers":[
        {
            "category":"Building & Trades",
            "subcategory":"Construction",
            "type":"Services"
        }
    ],
    "sg:phone":"+1 815 730 1303",
    "sg:postcode":"60435",
    "sg:province":"IL",
    "sg:tags":[
        "roofing",
        "contractor"
    ],
    "wof:name":"Mike Collins Roofing",
    "wof:placetype":"venue"
},
  "geometry": {"coordinates":[-88.143646,41.542189],"type":"Point"}
}