{
  "type": "Feature",
  "properties": {
    "iso:country":"US",
    "sg:address":"14712 W Farmington Rd",
    "sg:city":"Hanna City",
    "sg:phone":"+1 309 565 4851",
    "sg:postcode":"61536",
    "sg:province":"IL",
    "sg:tags":[
        "farm",
        "field",
        "crop"
    ],
    "wof:name":"Rosenbohm John",
    "wof:placetype":"venue"
},
  "geometry": {"coordinates":[-89.826729,40.697219],"type":"Point"}
}