{
  "type": "Feature",
  "properties": {
    "addr:full":"650 Deerfield Rd Deerfield IL 60015",
    "addr:housenumber":"650",
    "addr:postcode":"60015",
    "addr:street":"Deerfield Rd",
    "iso:country":"US",
    "sg:address":"650 Deerfield Rd",
    "sg:city":"Deerfield",
    "sg:classifiers":[
        {
            "category":"Retail",
            "subcategory":"Laundry & Dry Cleaning",
            "type":"Services"
        }
    ],
    "sg:phone":"+1 847 948 8100",
    "sg:postcode":"60015",
    "sg:province":"IL",
    "sg:tags":[
        "drycleaning",
        "plant"
    ],
    "wof:name":"Hana Lei Cleaners & Launderers",
    "wof:placetype":"venue"
},
  "geometry": {"coordinates":[-87.845204,42.167375],"type":"Point"}
}