{
  "type": "Feature",
  "properties": {
    "iso:country":"US",
    "sg:address":"1440 21st St",
    "sg:city":"Rockford",
    "sg:classifiers":[
        {
            "category":"Wholesale",
            "subcategory":"Machinery & Supplies",
            "type":"Manufacturing & Wholesale Goods"
        }
    ],
    "sg:phone":"+1 815 399 6573",
    "sg:postcode":"61108",
    "sg:province":"IL",
    "sg:tags":[
        "equipment",
        "canning"
    ],
    "wof:name":"TESTAMERICA",
    "wof:placetype":"venue"
},
  "geometry": {"coordinates":[-89.056137,42.253211],"type":"Point"}
}