{
  "type": "Feature",
  "properties": {
    "addr:full":"1440 21st St Rockford IL 61108",
    "addr:housenumber":"1440",
    "addr:postcode":"61108",
    "addr:street":"21St St",
    "iso:country":"US",
    "sg:address":"1440 21st St",
    "sg:city":"Rockford",
    "sg:classifiers":[
        {
            "category":"Wholesale",
            "subcategory":"Machinery & Supplies",
            "type":"Manufacturing & Wholesale Goods"
        }
    ],
    "sg:phone":"+1 815 399 6573",
    "sg:postcode":"61108",
    "sg:province":"IL",
    "sg:tags":[
        "equipment",
        "canning"
    ],
    "wof:name":"TESTAMERICA",
    "wof:placetype":"venue"
},
  "geometry": {"coordinates":[-89.05613700000001,42.253211],"type":"Point"}
}