{
  "type": "Feature",
  "properties": {
    "iso:country":"US",
    "sg:address":"710 N Church St",
    "sg:city":"Rockford",
    "sg:classifiers":[
        {
            "category":"Real Estate",
            "subcategory":"Architect",
            "type":"Services"
        }
    ],
    "sg:phone":"+1 815 968 7876",
    "sg:postcode":"61103",
    "sg:province":"IL",
    "wof:name":"William J Johannes Architects",
    "wof:placetype":"venue"
},
  "geometry": {"coordinates":[-89.091062,42.277523],"type":"Point"}
}