{
  "type": "Feature",
  "properties": {
    "iso:country":"US",
    "sg:address":"1723 York Rd",
    "sg:city":"Greenup",
    "sg:classifiers":[
        {
            "category":"Manufacturing",
            "subcategory":"Tools & Machinery",
            "type":"Manufacturing & Wholesale Goods"
        }
    ],
    "sg:phone":"+1 217 923 3431",
    "sg:postcode":"62428",
    "sg:province":"IL",
    "sg:tags":[
        "cooler",
        "mfg"
    ],
    "wof:name":"Evapco Midwest Inc",
    "wof:placetype":"venue"
},
  "geometry": {"coordinates":[-88.151291,39.244935],"type":"Point"}
}