{
  "type": "Feature",
  "properties": {
    "iso:country":"US",
    "sg:address":"205 N Broadway",
    "sg:city":"Aurora",
    "sg:classifiers":[
        {
            "category":"Manufacturing",
            "subcategory":"Food",
            "type":"Manufacturing & Wholesale Goods"
        }
    ],
    "sg:phone":"+1 630 859 2710",
    "sg:postcode":"60505",
    "sg:province":"IL",
    "sg:tags":[
        "coffee",
        "tea-wholesale",
        "manufacturer"
    ],
    "wof:name":"Jumpin Java Coffee Co.",
    "wof:placetype":"venue"
},
  "geometry": {"coordinates":[-88.30998599999999,41.760322],"type":"Point"}
}