{
  "type": "Feature",
  "properties": {
    "iso:country":"US",
    "sg:address":"471 Jennings Dr",
    "sg:city":"Lake In The Hls",
    "sg:classifiers":[
        {
            "category":"Building & Trades",
            "subcategory":"Construction",
            "type":"Services"
        },
        {
            "category":"Professional",
            "subcategory":"Management & Consulting",
            "type":"Services"
        }
    ],
    "sg:phone":"+1 815 477 4699",
    "sg:postcode":"60156",
    "sg:province":"IL",
    "sg:tags":[
        "house"
    ],
    "wof:name":"Babineau Construction Corp",
    "wof:placetype":"venue"
},
  "geometry": {"coordinates":[-88.316785,42.21243],"type":"Point"}
}