{
  "type": "Feature",
  "properties": {
    "iso:country":"US",
    "sg:address":"5401 W Devon Ave",
    "sg:city":"Chicago",
    "sg:classifiers":[
        {
            "category":"Personal",
            "subcategory":"Beauty Salon",
            "type":"Services"
        },
        {
            "category":"Personal",
            "subcategory":"Nail Salon",
            "type":"Services"
        }
    ],
    "sg:phone":"+1 773 775 7100",
    "sg:postcode":"60646",
    "sg:province":"IL",
    "sg:tags":[
        "spa"
    ],
    "wof:name":"Lee Nail Salon",
    "wof:placetype":"venue"
},
  "geometry": {"coordinates":[-87.76394999999999,41.99692],"type":"Point"}
}