{
  "type": "Feature",
  "properties": {
    "addr:full":"13725 Main St Lemont IL 60439",
    "addr:housenumber":"13725",
    "addr:postcode":"60439",
    "addr:street":"Main St",
    "iso:country":"US",
    "sg:address":"13725 Main St",
    "sg:city":"Lemont",
    "sg:classifiers":[
        {
            "category":"Manufacturing",
            "subcategory":"Paper Products",
            "type":"Manufacturing & Wholesale Goods"
        }
    ],
    "sg:phone":"+1 630 257 2700",
    "sg:postcode":"60439",
    "sg:province":"IL",
    "sg:tags":[
        "industrial"
    ],
    "wof:name":"Eagle Converting",
    "wof:placetype":"venue"
},
  "geometry": {"coordinates":[-87.95246899999999,41.687105],"type":"Point"}
}