{
  "type": "Feature",
  "properties": {
    "addr:full":"2023 S Ashland Ave Chicago IL 60608",
    "addr:housenumber":"2023",
    "addr:postcode":"60608",
    "addr:street":"S Ashland Ave",
    "iso:country":"US",
    "sg:address":"2023 S Ashland Ave",
    "sg:city":"Chicago",
    "sg:classifiers":[
        {
            "category":"Professional",
            "subcategory":"Detective & Security Services",
            "type":"Services"
        }
    ],
    "sg:phone":"+1 312 492 6666",
    "sg:postcode":"60608",
    "sg:province":"IL",
    "sg:tags":[
        "information",
        "bureau"
    ],
    "wof:name":"America's Tax Svc Inc",
    "wof:placetype":"venue"
},
  "geometry": {"coordinates":[-87.666082,41.854842],"type":"Point"}
}