{
  "type": "Feature",
  "properties": {
    "iso:country":"US",
    "sg:address":"860 W Evergreen Ave",
    "sg:city":"Chicago",
    "sg:classifiers":[
        {
            "category":"Building & Trades",
            "subcategory":"Construction",
            "type":"Services"
        }
    ],
    "sg:phone":"+1 312 587 0982",
    "sg:postcode":"60622",
    "sg:province":"IL",
    "sg:tags":[
        "contractor"
    ],
    "wof:name":"Crown Construction Enterprise Corp",
    "wof:placetype":"venue"
},
  "geometry": {"coordinates":[-87.65010100000001,41.905998],"type":"Point"}
}