{
  "type": "Feature",
  "properties": {
    "iso:country":"US",
    "sg:address":"1491 W King St",
    "sg:city":"Decatur",
    "sg:classifiers":[
        {
            "category":"Restaurant",
            "type":"Food & Drink"
        }
    ],
    "sg:menulink":"http://www.allmenus.com/il/decatur/90850-wingstop/menu/",
    "sg:phone":"+1 217 424 9464",
    "sg:postcode":"62522",
    "sg:province":"IL",
    "sg:tags":[
        "american",
        "wing"
    ],
    "wof:name":"Wingstop",
    "wof:placetype":"venue"
},
  "geometry": {"coordinates":[-88.980255,39.849114],"type":"Point"}
}