{
  "type": "Feature",
  "properties": {
    "iso:country":"US",
    "sg:address":"5320 W Devon Ave",
    "sg:city":"Chicago",
    "sg:classifiers":[
        {
            "category":"Health Services",
            "subcategory":"Medical Lab",
            "type":"Services"
        }
    ],
    "sg:phone":"+1 773 774 6440",
    "sg:postcode":"60646",
    "sg:province":"IL",
    "sg:tags":[
        "x"
    ],
    "wof:name":"Edgebrook Radiology",
    "wof:placetype":"venue"
},
  "geometry": {"coordinates":[-87.761488,41.997399],"type":"Point"}
}