{
  "type": "Feature",
  "properties": {
    "addr:full":"265 E Northwest Hwy Palatine IL 60067",
    "addr:housenumber":"265",
    "addr:postcode":"60067",
    "addr:street":"E Northwest Hwy",
    "iso:country":"US",
    "sg:address":"265 E Northwest Hwy",
    "sg:city":"Palatine",
    "sg:classifiers":[
        {
            "category":"Food & Beverages",
            "subcategory":"Candy",
            "type":"Retail Goods"
        }
    ],
    "sg:phone":"+1 847 358 1596",
    "sg:postcode":"60067",
    "sg:province":"IL",
    "sg:tags":[
        "confectionery"
    ],
    "sg:website":"www.fanniemaycandies.com",
    "wof:name":"Fannie May",
    "wof:placetype":"venue"
},
  "geometry": {"coordinates":[-88.03763499999999,42.119631],"type":"Point"}
}