{
  "type": "Feature",
  "properties": {
    "addr:full":"304 E Rand Rd Arlington Hts IL 60004",
    "addr:housenumber":"304",
    "addr:postcode":"60004",
    "addr:street":"E Rand Rd",
    "iso:country":"US",
    "sg:address":"304 E Rand Rd",
    "sg:city":"Arlington Hts",
    "sg:classifiers":[
        {
            "category":"Health Services",
            "subcategory":"Health Practitioner",
            "type":"Services"
        }
    ],
    "sg:phone":"+1 847 577 4455",
    "sg:postcode":"60004",
    "sg:province":"IL",
    "sg:tags":[
        "nutritionist"
    ],
    "wof:name":"Apple-A-Day Clinic",
    "wof:placetype":"venue"
},
  "geometry": {"coordinates":[-87.97972799999999,42.112398],"type":"Point"}
}