{
  "type": "Feature",
  "properties": {
    "iso:country":"US",
    "sg:address":"3400 W Delmar Ave",
    "sg:city":"Godfrey",
    "sg:classifiers":[
        {
            "category":"Shopping",
            "subcategory":"Party Supplies",
            "type":"Retail Goods"
        },
        {
            "category":"Retail",
            "subcategory":"Auto Rental",
            "type":"Services"
        },
        {
            "category":"Airport",
            "type":"Transportation"
        }
    ],
    "sg:phone":"+1 618 466 7001",
    "sg:postcode":"62035",
    "sg:province":"IL",
    "sg:tags":[
        "limousine",
        "wedding"
    ],
    "sg:website":"http://www.champagnelimos.com",
    "wof:name":"Champagne Limousine",
    "wof:placetype":"venue"
},
  "geometry": {"coordinates":[-90.256897,38.943008],"type":"Point"}
}