{
  "type": "Feature",
  "properties": {
    "addr:full":"7201 N California Ave Chicago IL 60645",
    "addr:housenumber":"7201",
    "addr:postcode":"60645",
    "addr:street":"N California Ave",
    "iso:country":"US",
    "sg:address":"7201 N California Ave",
    "sg:city":"Chicago",
    "sg:classifiers":[
        {
            "category":"Banks & Credit Unions",
            "subcategory":"Bank",
            "type":"Services"
        }
    ],
    "sg:phone":"+1 773 761 2899",
    "sg:postcode":"60645",
    "sg:province":"IL",
    "sg:tags":[
        "currency",
        "exchange"
    ],
    "wof:name":"Cal-Touhy Currency Exchange",
    "wof:placetype":"venue"
},
  "geometry": {"coordinates":[-87.699713,42.012523],"type":"Point"}
}