{
  "type": "Feature",
  "properties": {
    "addr:full":"3629 Sunnyside Ave Rockford IL 61101",
    "addr:housenumber":"3629",
    "addr:postcode":"61101",
    "addr:street":"Sunnyside Ave",
    "iso:country":"US",
    "sg:address":"3629 Sunnyside Ave",
    "sg:city":"Rockford",
    "sg:classifiers":[
        {
            "category":"Autos & Motor Vehicles",
            "subcategory":"Automobile Sales",
            "type":"Retail Goods"
        }
    ],
    "sg:phone":"+1   ",
    "sg:postcode":"61101",
    "sg:province":"IL",
    "sg:tags":[
        "used"
    ],
    "wof:name":"T C Auto Sales",
    "wof:placetype":"venue"
},
  "geometry": {"coordinates":[-89.115047,42.294786],"type":"Point"}
}