{
  "type": "Feature",
  "properties": {
    "addr:full":"8854 W 89th St Hickory Hills IL 60457",
    "addr:housenumber":"8854",
    "addr:postcode":"60457",
    "addr:street":"W 89Th St",
    "iso:country":"US",
    "sg:address":"8854 W 89th St",
    "sg:city":"Hickory Hills",
    "sg:classifiers":[
        {
            "category":"Wholesale",
            "subcategory":"Durable Goods & Equipment",
            "type":"Manufacturing & Wholesale Goods"
        }
    ],
    "sg:phone":"+1 708 599 3787",
    "sg:postcode":"60457",
    "sg:province":"IL",
    "sg:tags":[
        "exporter"
    ],
    "wof:name":"Feniks Commerce Inc",
    "wof:placetype":"venue"
},
  "geometry": {"coordinates":[-87.839438,41.729157],"type":"Point"}
}