{
  "type": "Feature",
  "properties": {
    "addr:full":"57 Waukegan Rd Deerfield IL 60015",
    "addr:housenumber":"57",
    "addr:postcode":"60015",
    "addr:street":"Waukegan Rd",
    "iso:country":"US",
    "sg:address":"57 Waukegan Rd",
    "sg:city":"Deerfield",
    "sg:classifiers":[
        {
            "category":"Sports & Exercise",
            "subcategory":"Gym",
            "type":"Entertainment"
        }
    ],
    "sg:phone":"+1 847 267 4100",
    "sg:postcode":"60015",
    "sg:province":"IL",
    "sg:tags":[
        "club",
        "health",
        "studio",
        "gymnasium"
    ],
    "wof:name":"Fitness Experience",
    "wof:placetype":"venue"
},
  "geometry": {"coordinates":[-87.835866,42.153752],"type":"Point"}
}