{
  "type": "Feature",
  "properties": {
    "iso:country":"US",
    "sg:address":"1178 W Everett Rd",
    "sg:city":"Lake Forest",
    "sg:classifiers":[
        {
            "category":"Real Estate",
            "subcategory":"Architect",
            "type":"Services"
        }
    ],
    "sg:phone":"+1 847 295 5777",
    "sg:postcode":"60045",
    "sg:province":"IL",
    "sg:tags":[
        "architectural"
    ],
    "sg:website":"www.goldbergdowneyarchitects.com",
    "wof:name":"Goldberg Downey Architects Inc",
    "wof:placetype":"venue"
},
  "geometry": {"coordinates":[-87.875047,42.221979],"type":"Point"}
}