{
  "type": "Feature",
  "properties": {
    "iso:country":"US",
    "sg:address":"10936 S Western Ave",
    "sg:city":"Chicago",
    "sg:classifiers":[
        {
            "category":"Professional",
            "subcategory":"Management & Consulting",
            "type":"Services"
        }
    ],
    "sg:phone":"+1 773 238 9500",
    "sg:postcode":"60643",
    "sg:province":"IL",
    "sg:tags":[
        "consultant",
        "co",
        "real estate"
    ],
    "wof:name":"C & A RE Investments Corp",
    "wof:placetype":"venue"
},
  "geometry": {"coordinates":[-87.681327,41.695056],"type":"Point"}
}