{
  "type": "Feature",
  "properties": {
    "iso:country":"US",
    "sg:address":"3245 W 111th St",
    "sg:city":"Chicago",
    "sg:classifiers":[
        {
            "category":"Building & Trades",
            "subcategory":"Construction",
            "type":"Services"
        }
    ],
    "sg:phone":"+1 773 233 8794",
    "sg:postcode":"60655",
    "sg:province":"IL",
    "sg:tags":[
        "contractor"
    ],
    "wof:name":"Einoder Masonry",
    "wof:placetype":"venue"
},
  "geometry": {"coordinates":[-87.703176,41.691457],"type":"Point"}
}