{
  "type": "Feature",
  "properties": {
    "iso:country":"US",
    "sg:address":"6400 Penn Ave",
    "sg:city":"Savanna",
    "sg:classifiers":[
        {
            "category":"Manufacturing",
            "subcategory":"Metals",
            "type":"Manufacturing & Wholesale Goods"
        }
    ],
    "sg:phone":"+1 815 273 7001",
    "sg:postcode":"61074",
    "sg:province":"IL",
    "sg:tags":[
        "plate",
        "mfg",
        "work",
        "fabricated",
        "r",
        "sanitary",
        "ware"
    ],
    "wof:name":"Corly Tempright",
    "wof:placetype":"venue"
},
  "geometry": {"coordinates":[-90.115793,42.082132],"type":"Point"}
}