{
  "type": "Feature",
  "properties": {
    "addr:full":"605 W Baltimore St Wilmington IL 60481",
    "addr:housenumber":"605",
    "addr:postcode":"60481",
    "addr:street":"W Baltimore St",
    "iso:country":"US",
    "sg:address":"605 W Baltimore St",
    "sg:city":"Wilmington",
    "sg:classifiers":[
        {
            "category":"Shopping",
            "subcategory":"Computers & Home Electronics",
            "type":"Retail Goods"
        }
    ],
    "sg:phone":"+1 815 476 7271",
    "sg:postcode":"60481",
    "sg:province":"IL",
    "sg:tags":[
        "equipment",
        "electronic",
        "supply"
    ],
    "wof:name":"Radio Shack",
    "wof:placetype":"venue"
},
  "geometry": {"coordinates":[-88.158051,41.305073],"type":"Point"}
}