{
  "type": "Feature",
  "properties": {
    "iso:country":"US",
    "sg:address":"1319 Blackhawk Ln",
    "sg:city":"Bartlett",
    "sg:classifiers":[
        {
            "category":"Real Estate",
            "subcategory":"Real Estate Services",
            "type":"Services"
        },
        {
            "category":"Real Estate",
            "subcategory":"Real Estate Agent",
            "type":"Services"
        }
    ],
    "sg:phone":"+1 630 837 4044",
    "sg:postcode":"60103",
    "sg:province":"IL",
    "sg:tags":[
        "management"
    ],
    "wof:name":"Pamin Brothers Inc",
    "wof:placetype":"venue"
},
  "geometry": {"coordinates":[-88.17461900000001,41.959286],"type":"Point"}
}