{
  "type": "Feature",
  "properties": {
    "iso:country":"US",
    "sg:address":"4000 Seminary St",
    "sg:city":"Alton",
    "sg:classifiers":[
        {
            "category":"Shopping",
            "type":"Retail Goods"
        }
    ],
    "sg:phone":"+1   ",
    "sg:postcode":"62002",
    "sg:province":"IL",
    "sg:tags":[
        "repair",
        "electrical",
        "merchandise"
    ],
    "wof:name":"Alton Hearing Center",
    "wof:placetype":"venue"
},
  "geometry": {"coordinates":[-90.142356,38.93241],"type":"Point"}
}