{
  "type": "Feature",
  "properties": {
    "addr:full":"7017 North Ave Oak Park IL 60302",
    "addr:housenumber":"7017",
    "addr:postcode":"60302",
    "addr:street":"North Ave",
    "iso:country":"US",
    "sg:address":"7017 North Ave",
    "sg:city":"Oak Park",
    "sg:classifiers":[
        {
            "category":"Personal",
            "subcategory":"Beauty Salon",
            "type":"Services"
        }
    ],
    "sg:phone":"+1 708 383 3644",
    "sg:postcode":"60302",
    "sg:province":"IL",
    "wof:name":"Dream Designs II",
    "wof:placetype":"venue"
},
  "geometry": {"coordinates":[-87.801304,41.908865],"type":"Point"}
}