{
  "type": "Feature",
  "properties": {
    "addr:full":"1531 N Wells Street A Red Orchid Theatre Chicago IL 60610",
    "addr:housenumber":"1531",
    "addr:postcode":"60610",
    "addr:street":"N Wells Street A Red",
    "iso:country":"US",
    "sg:address":"1531 N Wells Street A Red Orchid Theatre",
    "sg:city":"Chicago",
    "sg:classifiers":[
        {
            "category":"Arts & Performance",
            "subcategory":"Arts Center",
            "type":"Entertainment"
        }
    ],
    "sg:phone":"+1 312 943 8722",
    "sg:postcode":"60610",
    "sg:province":"IL",
    "sg:tags":[
        "performing"
    ],
    "wof:name":"The Earl",
    "wof:placetype":"venue"
},
  "geometry": {"coordinates":[-87.63449900000001,41.91],"type":"Point"}
}