{
  "type": "Feature",
  "properties": {
    "iso:country":"US",
    "sg:address":"114 N Orchard Dr",
    "sg:city":"Park Forest",
    "sg:classifiers":[
        {
            "category":"Social Services",
            "subcategory":"Adult Care",
            "type":"Services"
        }
    ],
    "sg:phone":"+1   ",
    "sg:postcode":"60466",
    "sg:province":"IL",
    "sg:tags":[
        "residential"
    ],
    "wof:name":"E Ludeman Developmental Center",
    "wof:placetype":"venue"
},
  "geometry": {"coordinates":[-87.682611,41.493514],"type":"Point"}
}