{
  "type": "Feature",
  "properties": {
    "iso:country":"US",
    "sg:address":"100 W Monroe St Ste 502",
    "sg:city":"Chicago",
    "sg:classifiers":[
        {
            "category":"Transit Center",
            "subcategory":"Freight",
            "type":"Transportation"
        }
    ],
    "sg:phone":"+1 773 525 3590",
    "sg:postcode":"60603",
    "sg:province":"IL",
    "sg:tags":[
        "forwarding"
    ],
    "sg:website":"http://www.theshippingadvisor.com",
    "wof:name":"The Shipping Advisor",
    "wof:placetype":"venue"
},
  "geometry": {"coordinates":[-87.63082900000001,41.880692],"type":"Point"}
}