{
  "type": "Feature",
  "properties": {
    "iso:country":"US",
    "sg:address":"2336 N Co Rd 1700",
    "sg:city":"Dallas City",
    "sg:phone":"+1 217 755 4337",
    "sg:postcode":"62330",
    "sg:province":"IL",
    "sg:tags":[
        "farm"
    ],
    "wof:name":"Don Rings",
    "wof:placetype":"venue"
},
  "geometry": {"coordinates":[-91.176866,40.547762],"type":"Point"}
}