{
  "type": "Feature",
  "properties": {
    "addr:full":"569 Main St NW Bourbonnais IL 60914",
    "addr:housenumber":"569",
    "addr:postcode":"bourbonnais il 60914",
    "addr:street":"Main St Nw",
    "iso:country":"US",
    "sg:address":"569 Main St NW",
    "sg:city":"Bourbonnais",
    "sg:classifiers":[
        {
            "category":"Education",
            "subcategory":"Special Training",
            "type":"Public Place"
        }
    ],
    "sg:phone":"+1 815 929 0426",
    "sg:postcode":"60914",
    "sg:province":"IL",
    "sg:tags":[
        "tutoring"
    ],
    "sg:website":"www.educate.com",
    "wof:name":"Sylvan Learning Ctr",
    "wof:placetype":"venue"
},
  "geometry": {"coordinates":[-87.88788599999999,41.159932],"type":"Point"}
}