{
  "type": "Feature",
  "properties": {
    "addr:full":"3417 N Halsted St Chicago IL 60657",
    "addr:housenumber":"3417",
    "addr:postcode":"60657",
    "addr:street":"N Halsted St",
    "iso:country":"US",
    "sg:address":"3417 N Halsted St",
    "sg:city":"Chicago",
    "sg:classifiers":[
        {
            "category":"Manufacturing",
            "subcategory":"Glass & Minerals",
            "type":"Manufacturing & Wholesale Goods"
        },
        {
            "category":"Retail",
            "subcategory":"Auto Repair",
            "type":"Services"
        }
    ],
    "sg:phone":"+1 630 617 5234",
    "sg:postcode":"60657",
    "sg:province":"IL",
    "sg:tags":[
        "body",
        "repairing",
        "plate",
        "automobile",
        "glass-auto",
        "window",
        "painting"
    ],
    "wof:name":"Gerber Collision & Glass",
    "wof:placetype":"venue"
},
  "geometry": {"coordinates":[-87.64938100000001,41.944101],"type":"Point"}
}