{
  "type": "Feature",
  "properties": {
    "iso:country":"US",
    "sg:address":"445 Cedar Crest Dr",
    "sg:city":"Cedarville",
    "sg:classifiers":[
        {
            "category":"Retail",
            "subcategory":"Portrait Studio",
            "type":"Services"
        }
    ],
    "sg:phone":"+1 815 563 4545",
    "sg:postcode":"61013",
    "sg:province":"IL",
    "sg:tags":[
        "photographer"
    ],
    "wof:name":"Beverley & Beverley",
    "wof:placetype":"venue"
},
  "geometry": {"coordinates":[-89.639382,42.372756],"type":"Point"}
}