{
  "type": "Feature",
  "properties": {
    "addr:full":"440 Challenge St Freeport IL 61032",
    "addr:housenumber":"440",
    "addr:postcode":"61032",
    "addr:street":"Challenge St",
    "iso:country":"US",
    "sg:address":"440 Challenge St",
    "sg:city":"Freeport",
    "sg:classifiers":[
        {
            "category":"Professional",
            "subcategory":"Credit Reporting & Collection",
            "type":"Services"
        }
    ],
    "sg:phone":"+1 815 235 9202",
    "sg:postcode":"61032",
    "sg:province":"IL",
    "sg:tags":[
        "agency"
    ],
    "wof:name":"Tri-State Adjustment Freeport",
    "wof:placetype":"venue"
},
  "geometry": {"coordinates":[-89.611082,42.281503],"type":"Point"}
}