{
  "type": "Feature",
  "properties": {
    "addr:full":"1304 E Indian Trl Rd Aurora IL 60505",
    "addr:housenumber":"1304",
    "addr:postcode":"60505",
    "addr:street":"E Indian Trl Rd",
    "iso:country":"US",
    "sg:address":"1304 E Indian Trl Rd",
    "sg:city":"Aurora",
    "sg:classifiers":[
        {
            "category":"Real Estate",
            "subcategory":"Real Estate Operator",
            "type":"Services"
        }
    ],
    "sg:phone":"+1 630 898 7744",
    "sg:postcode":"60505",
    "sg:province":"IL",
    "sg:tags":[
        "building",
        "apartment"
    ],
    "wof:name":"APT Marketing Center",
    "wof:placetype":"venue"
},
  "geometry": {"coordinates":[-88.287175,41.782401],"type":"Point"}
}