{
  "type": "Feature",
  "properties": {
    "addr:full":"1101 S Canal St Ste 200 Chicago IL 60607",
    "addr:housenumber":"1101",
    "addr:postcode":"60607",
    "addr:street":"S Canal St Ste 200",
    "iso:country":"US",
    "sg:address":"1101 S Canal St Ste 200",
    "sg:city":"Chicago",
    "sg:classifiers":[
        {
            "category":"Shopping",
            "subcategory":"Shoes",
            "type":"Retail Goods"
        }
    ],
    "sg:phone":"+1 312 880 0246",
    "sg:postcode":"60607",
    "sg:province":"IL",
    "sg:tags":[
        "store"
    ],
    "wof:name":"DSW",
    "wof:placetype":"venue"
},
  "geometry": {"coordinates":[-87.63900700000001,41.868225],"type":"Point"}
}