{
  "type": "Feature",
  "properties": {
    "addr:full":"2034 Ridge Rd Fl 2 Homewood IL 60430",
    "addr:housenumber":"2034;2",
    "addr:postcode":"60430",
    "addr:street":"Ridge Rd",
    "iso:country":"US",
    "sg:address":"2034 Ridge Rd Fl 2",
    "sg:city":"Homewood",
    "sg:classifiers":[
        {
            "category":"Insurance",
            "subcategory":"Hazard Insurance",
            "type":"Services"
        }
    ],
    "sg:phone":"+1 708 922 9450",
    "sg:postcode":"60430",
    "sg:province":"IL",
    "sg:tags":[
        "commercial",
        "business"
    ],
    "wof:name":"Alliance Benefit Consultants",
    "wof:placetype":"venue"
},
  "geometry": {"coordinates":[-87.666512,41.56172],"type":"Point"}
}