{
  "type": "Feature",
  "properties": {
    "addr:full":"1014 N Ashland Ave Chicago IL 60622",
    "addr:housenumber":"1014",
    "addr:postcode":"60622",
    "addr:street":"N Ashland Ave",
    "iso:country":"US",
    "sg:address":"1014 N Ashland Ave",
    "sg:city":"Chicago",
    "sg:classifiers":[
        {
            "category":"Building & Trades",
            "subcategory":"Plumbing",
            "type":"Services"
        }
    ],
    "sg:phone":"+1 773 252 6262",
    "sg:postcode":"60622",
    "sg:province":"IL",
    "wof:name":"N B&j Plumbing",
    "wof:placetype":"venue"
},
  "geometry": {"coordinates":[-87.667709,41.90018],"type":"Point"}
}