{
  "type": "Feature",
  "properties": {
    "iso:country":"US",
    "sg:address":"2920 Central St",
    "sg:city":"Evanston",
    "sg:classifiers":[
        {
            "category":"Retail",
            "subcategory":"Laundry & Dry Cleaning",
            "type":"Services"
        }
    ],
    "sg:phone":"+1 847 866 7890",
    "sg:postcode":"60201",
    "sg:province":"IL",
    "sg:tags":[
        "drycleaning",
        "plant"
    ],
    "wof:name":"Swan Lake Cleaners",
    "wof:placetype":"venue"
},
  "geometry": {"coordinates":[-87.71474,42.064464],"type":"Point"}
}