{
  "type": "Feature",
  "properties": {
    "addr:full":"403 Park Ave Clarendon Hills IL 60514",
    "addr:housenumber":"403",
    "addr:postcode":"60514",
    "addr:street":"Park Ave",
    "iso:country":"US",
    "sg:address":"403 Park Ave",
    "sg:city":"Clarendon Hills",
    "sg:classifiers":[
        {
            "category":"Professional",
            "subcategory":"Business Services",
            "type":"Services"
        }
    ],
    "sg:phone":"+1 630 321 0095",
    "sg:postcode":"60514",
    "sg:province":"IL",
    "wof:name":"Park Hill Group Inc",
    "wof:placetype":"venue"
},
  "geometry": {"coordinates":[-87.960573,41.794783],"type":"Point"}
}