{
  "type": "Feature",
  "properties": {
    "addr:full":"2503 184th St Lansing IL 60438",
    "addr:housenumber":"2503",
    "addr:postcode":"60438",
    "addr:street":"184Th St",
    "iso:country":"US",
    "sg:address":"2503 184th St",
    "sg:city":"Lansing",
    "sg:classifiers":[
        {
            "category":"Building & Trades",
            "subcategory":"Construction",
            "type":"Services"
        }
    ],
    "sg:phone":"+1 708 418 8009",
    "sg:postcode":"60438",
    "sg:province":"IL",
    "sg:tags":[
        "contractor"
    ],
    "wof:name":"Done Right Windows",
    "wof:placetype":"venue"
},
  "geometry": {"coordinates":[-87.555149,41.561023],"type":"Point"}
}