{
  "type": "Feature",
  "properties": {
    "addr:full":"720 W Gordon Ter Chicago IL 60613",
    "addr:housenumber":"720",
    "addr:postcode":"60613",
    "addr:street":"W Gordon Ter",
    "iso:country":"US",
    "sg:address":"720 W Gordon Ter",
    "sg:city":"Chicago",
    "sg:classifiers":[
        {
            "category":"Real Estate",
            "subcategory":"Real Estate Operator",
            "type":"Services"
        }
    ],
    "sg:phone":"+1 773 525 8688",
    "sg:postcode":"60613",
    "sg:province":"IL",
    "sg:tags":[
        "apartment"
    ],
    "wof:name":"720 W Gordon Terrace Condominiums",
    "wof:placetype":"venue"
},
  "geometry": {"coordinates":[-87.648399,41.957901],"type":"Point"}
}