{
  "type": "Feature",
  "properties": {
    "iso:country":"US",
    "sg:address":"7300 W 79th St",
    "sg:city":"Bridgeview",
    "sg:classifiers":[
        {
            "category":"Landmark",
            "subcategory":"Historic",
            "type":"Public Place"
        }
    ],
    "sg:phone":"+1 708 496 1254",
    "sg:postcode":"60455",
    "sg:province":"IL",
    "sg:tags":[
        "building",
        "historical"
    ],
    "wof:name":"Bridgeview Park District Landmark",
    "wof:placetype":"venue"
},
  "geometry": {"coordinates":[-87.803061,41.748219],"type":"Point"}
}