{
  "type": "Feature",
  "properties": {
    "iso:country":"US",
    "sg:address":"935 W Rollins Rd",
    "sg:city":"Round Lake Hts",
    "sg:classifiers":[
        {
            "category":"Banks & Credit Unions",
            "subcategory":"Bank",
            "type":"Services"
        }
    ],
    "sg:phone":"+1 847 740 2265",
    "sg:postcode":"60073",
    "sg:province":"IL",
    "sg:tags":[
        "loan",
        "real estate"
    ],
    "wof:name":"Harris Bank",
    "wof:placetype":"venue"
},
  "geometry": {"coordinates":[-88.105766,42.379544],"type":"Point"}
}