{
  "type": "Feature",
  "properties": {
    "iso:country":"US",
    "sg:address":"300 Revere Dr",
    "sg:city":"Northbrook",
    "sg:classifiers":[
        {
            "category":"Social Services",
            "type":"Services"
        }
    ],
    "sg:phone":"+1 847 272 2614",
    "sg:postcode":"60062",
    "sg:province":"IL",
    "wof:name":"Jewish Federation of Metro Chicago",
    "wof:placetype":"venue"
},
  "geometry": {"coordinates":[-87.80463399999999,42.150616],"type":"Point"}
}