{
  "type": "Feature",
  "properties": {
    "iso:country":"US",
    "sg:address":"1750 Maroon Bells Ln",
    "sg:city":"Bolingbrook",
    "sg:classifiers":[
        {
            "category":"Manufacturing",
            "subcategory":"Printing",
            "type":"Manufacturing & Wholesale Goods"
        }
    ],
    "sg:phone":"+1 630 759 7769",
    "sg:postcode":"60490",
    "sg:province":"IL",
    "sg:tags":[
        "multimedia"
    ],
    "wof:name":"S 10 Media Inc",
    "wof:placetype":"venue"
},
  "geometry": {"coordinates":[-88.149154,41.693678],"type":"Point"}
}