{
  "type": "Feature",
  "properties": {
    "addr:full":"304 10th Ave Orion IL 61273",
    "addr:housenumber":"304",
    "addr:postcode":"61273",
    "addr:street":"10Th Ave",
    "iso:country":"US",
    "sg:address":"304 10th Ave",
    "sg:city":"Orion",
    "sg:classifiers":[
        {
            "category":"Bars & Pubs",
            "type":"Food & Drink"
        }
    ],
    "sg:phone":"+1 309 526 3777",
    "sg:postcode":"61273",
    "sg:province":"IL",
    "wof:name":"Sarges Tavern",
    "wof:placetype":"venue"
},
  "geometry": {"coordinates":[-90.38184699999999,41.354734],"type":"Point"}
}