{
  "type": "Feature",
  "properties": {
    "iso:country":"US",
    "sg:address":"1120 S Milwaukee Ave",
    "sg:city":"Vernon Hills",
    "sg:classifiers":[
        {
            "category":"Education",
            "subcategory":"College",
            "type":"Public Place"
        }
    ],
    "sg:phone":"+1 847 433 7884",
    "sg:postcode":"60061",
    "sg:province":"IL",
    "wof:name":"Southlake Educational Center",
    "wof:placetype":"venue"
},
  "geometry": {"coordinates":[-87.945553,42.247585],"type":"Point"}
}