{
  "type": "Feature",
  "properties": {
    "addr:full":"628 Columbus St Ottawa IL 61350",
    "addr:housenumber":"628",
    "addr:postcode":"61350",
    "addr:street":"Columbus St",
    "iso:country":"US",
    "sg:address":"628 Columbus St",
    "sg:city":"Ottawa",
    "sg:classifiers":[
        {
            "category":"Insurance",
            "subcategory":"Hazard Insurance",
            "type":"Services"
        }
    ],
    "sg:phone":"+1 815 434 1128",
    "sg:postcode":"61350",
    "sg:province":"IL",
    "sg:tags":[
        "commercial",
        "business"
    ],
    "wof:name":"Schultz, Kevin",
    "wof:placetype":"venue"
},
  "geometry": {"coordinates":[-88.84118100000001,41.346072],"type":"Point"}
}