{
  "type": "Feature",
  "properties": {
    "addr:full":"2715 23rd Ave Moline IL 61265",
    "addr:housenumber":"2715",
    "addr:postcode":"61265",
    "addr:street":"23Rd Ave",
    "iso:country":"US",
    "sg:address":"2715 23rd Ave",
    "sg:city":"Moline",
    "sg:classifiers":[
        {
            "category":"Restaurant",
            "type":"Food & Drink"
        }
    ],
    "sg:phone":"+1 309 797 8475",
    "sg:postcode":"61265",
    "sg:province":"IL",
    "sg:tags":[
        "mexican"
    ],
    "sg:website":"http://www.elpavito.com",
    "wof:name":"El Pavito",
    "wof:placetype":"venue"
},
  "geometry": {"coordinates":[-90.499047,41.49234],"type":"Point"}
}