{
  "type": "Feature",
  "properties": {
    "iso:country":"US",
    "sg:address":"3340 Oak Park Ave Ste 201",
    "sg:city":"Berwyn",
    "sg:classifiers":[
        {
            "category":"Health Services",
            "subcategory":"Doctor",
            "type":"Services"
        }
    ],
    "sg:phone":"+1 708 795 5502",
    "sg:postcode":"60402",
    "sg:province":"IL",
    "sg:tags":[
        "physician",
        "surgeon",
        "pediatrics",
        "surgeons"
    ],
    "wof:name":"Hathiwala Damayanti S MD",
    "wof:placetype":"venue"
},
  "geometry": {"coordinates":[-87.792801,41.831501],"type":"Point"}
}