{
  "type": "Feature",
  "properties": {
    "iso:country":"US",
    "sg:address":"530 Main St",
    "sg:city":"Warsaw",
    "sg:classifiers":[
        {
            "category":"Building & Trades",
            "subcategory":"Plumbing",
            "type":"Services"
        }
    ],
    "sg:phone":"+1 217 256 4511",
    "sg:postcode":"62379",
    "sg:province":"IL",
    "sg:tags":[
        "conditioning",
        "air",
        "system",
        "contractor"
    ],
    "wof:name":"Jc Heating & Air",
    "wof:placetype":"venue"
},
  "geometry": {"coordinates":[-91.43539,40.359416],"type":"Point"}
}