{
  "type": "Feature",
  "properties": {
    "iso:country":"US",
    "sg:address":"134 N Main St",
    "sg:city":"Rockford",
    "sg:classifiers":[
        {
            "category":"Professional",
            "subcategory":"Lawyer & Legal Services",
            "type":"Services"
        }
    ],
    "sg:phone":"+1 815 965 4878",
    "sg:postcode":"61101",
    "sg:province":"IL",
    "sg:tags":[
        "attorney"
    ],
    "wof:name":"Pete Sullivan & Assoc",
    "wof:placetype":"venue"
},
  "geometry": {"coordinates":[-89.094081,42.271906],"type":"Point"}
}