{
  "type": "Feature",
  "properties": {
    "addr:full":"915 Green Bay Rd Winnetka IL 60093",
    "addr:housenumber":"915",
    "addr:postcode":"60093",
    "addr:street":"Green Bay Rd",
    "iso:country":"US",
    "sg:address":"915 Green Bay Rd",
    "sg:city":"Winnetka",
    "sg:classifiers":[
        {
            "category":"Shopping",
            "subcategory":"Antiques",
            "type":"Retail Goods"
        }
    ],
    "sg:phone":"+1 847 446 0584",
    "sg:postcode":"60093",
    "sg:province":"IL",
    "sg:tags":[
        "dealers-wholesale"
    ],
    "wof:name":"Antique Emporium, The",
    "wof:placetype":"venue"
},
  "geometry": {"coordinates":[-87.743179,42.116165],"type":"Point"}
}