{
  "type": "Feature",
  "properties": {
    "addr:full":"2425 47th Ave Rock Island IL 61201",
    "addr:housenumber":"2425",
    "addr:postcode":"61201",
    "addr:street":"47Th Ave",
    "iso:country":"US",
    "sg:address":"2425 47th Ave",
    "sg:city":"Rock Island",
    "sg:classifiers":[
        {
            "category":"Retail",
            "subcategory":"Repair Shop",
            "type":"Services"
        }
    ],
    "sg:phone":"+1 309 788 0310",
    "sg:postcode":"61201",
    "sg:province":"IL",
    "sg:tags":[
        "repairing",
        "lawn",
        "mower"
    ],
    "wof:name":"Parr's Small Engine Repair",
    "wof:placetype":"venue"
},
  "geometry": {"coordinates":[-90.562563,41.463674],"type":"Point"}
}