{
  "type": "Feature",
  "properties": {
    "iso:country":"US",
    "sg:address":"1242 Manchester Dr",
    "sg:city":"Crystal Lake",
    "sg:classifiers":[
        {
            "category":"Professional",
            "type":"Services"
        }
    ],
    "sg:phone":"+1 815 455 5271",
    "sg:postcode":"60014",
    "sg:province":"IL",
    "sg:tags":[
        "establishment"
    ],
    "wof:name":"Thos Deal",
    "wof:placetype":"venue"
},
  "geometry": {"coordinates":[-88.353073,42.205875],"type":"Point"}
}