{
  "type": "Feature",
  "properties": {
    "addr:full":"1242 Manchester Dr Crystal Lake IL 60014",
    "addr:housenumber":"1242",
    "addr:postcode":"60014",
    "addr:street":"Manchester Dr",
    "iso:country":"US",
    "sg:address":"1242 Manchester Dr",
    "sg:city":"Crystal Lake",
    "sg:classifiers":[
        {
            "category":"Professional",
            "type":"Services"
        }
    ],
    "sg:phone":"+1 815 455 5271",
    "sg:postcode":"60014",
    "sg:province":"IL",
    "sg:tags":[
        "establishment"
    ],
    "wof:name":"Thos Deal",
    "wof:placetype":"venue"
},
  "geometry": {"coordinates":[-88.35307299999999,42.205875],"type":"Point"}
}