{
  "type": "Feature",
  "properties": {
    "addr:full":"327 N Kickapoo St Lincoln IL 62656",
    "addr:housenumber":"327",
    "addr:postcode":"62656",
    "addr:street":"N Kickapoo St",
    "iso:country":"US",
    "sg:address":"327 N Kickapoo St",
    "sg:city":"Lincoln",
    "sg:classifiers":[
        {
            "category":"Banks & Credit Unions",
            "subcategory":"Bank",
            "type":"Services"
        }
    ],
    "sg:phone":"+1 217 732 2201",
    "sg:postcode":"62656",
    "sg:province":"IL",
    "sg:tags":[
        "loan"
    ],
    "wof:name":"Farm Credit Svc",
    "wof:placetype":"venue"
},
  "geometry": {"coordinates":[-89.36006500000001,40.149004],"type":"Point"}
}