{
  "type": "Feature",
  "properties": {
    "addr:city":"Moline",
    "addr:full":"712 18Th Ave Moline, Il 61265",
    "addr:house_number":"712",
    "addr:housenumber":"712",
    "addr:phone":"+1 309-762-0167",
    "addr:postcode":"61265",
    "addr:road":"18Th Ave",
    "addr:state":"IL",
    "addr:street":"18Th Ave",
    "iso:country":"US",
    "sg:address":"712 18th Ave",
    "sg:city":"Moline",
    "sg:classifiers":[
        {
            "category":"Organizations",
            "subcategory":"Community Association",
            "type":"Services"
        }
    ],
    "sg:phone":"+1 309 762 0167",
    "sg:postcode":"61265",
    "sg:province":"IL",
    "sg:tags":[
        "gallery"
    ],
    "wof:airports":[
        102525797,
        102528149
    ],
    "wof:name":"Belgian Culture Center",
    "wof:placetype":"venue"
},
  "geometry": {"coordinates":[-90.52769000000001,41.49691],"type":"Point"}
}