{
  "type": "Feature",
  "properties": {
    "addr:full":"712 18th Ave Moline IL 61265",
    "addr:housenumber":"712",
    "addr:postcode":"61265",
    "addr:street":"18Th Ave",
    "iso:country":"US",
    "sg:address":"712 18th Ave",
    "sg:city":"Moline",
    "sg:classifiers":[
        {
            "category":"Organizations",
            "subcategory":"Community Association",
            "type":"Services"
        }
    ],
    "sg:phone":"+1 309 762 0167",
    "sg:postcode":"61265",
    "sg:province":"IL",
    "sg:tags":[
        "gallery"
    ],
    "wof:name":"Center For Belgian Culture",
    "wof:placetype":"venue"
},
  "geometry": {"coordinates":[-90.52626100000001,41.494998],"type":"Point"}
}