{
  "type": "Feature",
  "properties": {
    "iso:country":"US",
    "sg:address":"1277 Knox Road 1600 N",
    "sg:city":"Knoxville",
    "sg:classifiers":[
        {
            "category":"Building & Trades",
            "subcategory":"Construction",
            "type":"Services"
        }
    ],
    "sg:phone":"+1 309 289 7921",
    "sg:postcode":"61448",
    "sg:province":"IL",
    "sg:tags":[
        "restoration",
        "preservation"
    ],
    "sg:website":"www.trilliumdell.com",
    "wof:name":"Trillium Dell Timber Works",
    "wof:placetype":"venue"
},
  "geometry": {"coordinates":[-90.196348,40.946706],"type":"Point"}
}