{
  "type": "Feature",
  "properties": {
    "addr:full":"261 Planters Row Geneva IL 60134",
    "addr:housenumber":"261",
    "addr:postcode":"60134",
    "addr:street":"Planters Row",
    "iso:country":"US",
    "sg:address":"261 Planters Row",
    "sg:city":"Geneva",
    "sg:classifiers":[
        {
            "category":"Professional",
            "type":"Services"
        }
    ],
    "sg:phone":"+1 630 845 8300",
    "sg:postcode":"60134",
    "sg:province":"IL",
    "sg:tags":[
        "establishment"
    ],
    "wof:name":"Congitive Technologies",
    "wof:placetype":"venue"
},
  "geometry": {"coordinates":[-88.35352399999999,41.888137],"type":"Point"}
}