{
  "type": "Feature",
  "properties": {
    "addr:full":"3021 S Michigan Ave Apt 104 Chicago IL 60616",
    "addr:housenumber":"3021;104",
    "addr:postcode":"60616",
    "addr:street":"S Michigan Ave Apt",
    "iso:country":"US",
    "sg:address":"3021 S Michigan Ave Apt 104",
    "sg:city":"Chicago",
    "sg:classifiers":[
        {
            "category":"Building & Trades",
            "subcategory":"Pest Control",
            "type":"Services"
        }
    ],
    "sg:phone":"+1 312 326 3522",
    "sg:postcode":"60616",
    "sg:province":"IL",
    "wof:name":"Hampton Pestcontrol",
    "wof:placetype":"venue"
},
  "geometry": {"coordinates":[-87.623057,41.839715],"type":"Point"}
}