{
  "type": "Feature",
  "properties": {
    "iso:country":"US",
    "sg:address":"841 Winston Dr",
    "sg:city":"Melrose Park",
    "sg:classifiers":[
        {
            "category":"Building & Trades",
            "subcategory":"Cleaning & Sanitation",
            "type":"Services"
        }
    ],
    "sg:phone":"+1 708 906 5231",
    "sg:postcode":"60160",
    "sg:province":"IL",
    "sg:tags":[
        "carpet"
    ],
    "sg:website":"www.freshcleancarpetcleaning.com",
    "wof:name":"Fresh & Clean Carpet Cleaning",
    "wof:placetype":"venue"
},
  "geometry": {"coordinates":[-87.84428200000001,41.903517],"type":"Point"}
}