{
  "type": "Feature",
  "properties": {
    "iso:country":"US",
    "sg:address":"446 Co Rd 200 N",
    "sg:city":"Sigel",
    "sg:phone":"+1 217 924 4227",
    "sg:postcode":"62462",
    "sg:province":"IL",
    "sg:tags":[
        "farm",
        "soybean",
        "beef",
        "feedlot",
        "cattle"
    ],
    "wof:name":"Kenny Busher",
    "wof:placetype":"venue"
},
  "geometry": {"coordinates":[-88.388054,39.200213],"type":"Point"}
}