{
  "type": "Feature",
  "properties": {
    "iso:country":"US",
    "sg:address":"1100 Gragg St",
    "sg:city":"Centralia",
    "sg:classifiers":[
        {
            "category":"Shopping",
            "subcategory":"Hobbies, Toys, & Games",
            "type":"Retail Goods"
        },
        {
            "category":"Shopping",
            "subcategory":"Crafts & Fabrics",
            "type":"Retail Goods"
        }
    ],
    "sg:phone":"+1 618 532 3865",
    "sg:postcode":"62801",
    "sg:province":"IL",
    "sg:tags":[
        "shop",
        "hobby",
        "model",
        "supply"
    ],
    "wof:name":"Davis Crafts And Creations",
    "wof:placetype":"venue"
},
  "geometry": {"coordinates":[-89.119556,38.53817],"type":"Point"}
}