{
  "type": "Feature",
  "properties": {
    "addr:full":"367 Georgetown Sq Wood Dale IL 60191",
    "addr:housenumber":"367",
    "addr:postcode":"60191",
    "addr:street":"Georgetown Sq",
    "iso:country":"US",
    "sg:address":"367 Georgetown Sq",
    "sg:city":"Wood Dale",
    "sg:classifiers":[
        {
            "category":"Shopping",
            "subcategory":"Hobbies, Toys, & Games",
            "type":"Retail Goods"
        }
    ],
    "sg:phone":"+1   ",
    "sg:postcode":"60191",
    "sg:province":"IL",
    "wof:name":"Across The Trcks Trins Hobbies",
    "wof:placetype":"venue"
},
  "geometry": {"coordinates":[-87.995885,41.964379],"type":"Point"}
}