{
  "type": "Feature",
  "properties": {
    "iso:country":"US",
    "sg:address":"5705 Mill St",
    "sg:city":"Richmond",
    "sg:classifiers":[
        {
            "category":"Retail",
            "subcategory":"Repair Shop",
            "type":"Services"
        }
    ],
    "sg:phone":"+1 815 678 2438",
    "sg:postcode":"60071",
    "sg:province":"IL",
    "sg:tags":[
        "related"
    ],
    "wof:name":"Richmond Auto Repair",
    "wof:placetype":"venue"
},
  "geometry": {"coordinates":[-88.308077,42.476876],"type":"Point"}
}