{
  "type": "Feature",
  "properties": {
    "addr:full":"6134 N Milwaukee Ave Chicago IL 60646",
    "addr:housenumber":"6134",
    "addr:postcode":"60646",
    "addr:street":"N Milwaukee Ave",
    "iso:country":"US",
    "sg:address":"6134 N Milwaukee Ave",
    "sg:city":"Chicago",
    "sg:classifiers":[
        {
            "category":"Real Estate",
            "subcategory":"Real Estate Agent",
            "type":"Services"
        }
    ],
    "sg:phone":"+1 773 792 3906",
    "sg:postcode":"60646",
    "sg:province":"IL",
    "wof:name":"Berger Appraisal Ltd",
    "wof:placetype":"venue"
},
  "geometry": {"coordinates":[-87.78447199999999,41.993649],"type":"Point"}
}