{
  "type": "Feature",
  "properties": {
    "addr:full":"1014 Lois Pl Joliet IL 60435",
    "addr:housenumber":"1014",
    "addr:postcode":"60435",
    "addr:street":"Lois Pl",
    "iso:country":"US",
    "sg:address":"1014 Lois Pl",
    "sg:city":"Joliet",
    "sg:classifiers":[
        {
            "category":"Real Estate",
            "subcategory":"Real Estate Operator",
            "type":"Services"
        }
    ],
    "sg:phone":"+1 815 725 0028",
    "sg:postcode":"60435",
    "sg:province":"IL",
    "sg:tags":[
        "apartment"
    ],
    "wof:name":"Saddle Oak Apartments",
    "wof:placetype":"venue"
},
  "geometry": {"coordinates":[-88.127077,41.539159],"type":"Point"}
}