{
  "type": "Feature",
  "properties": {
    "iso:country":"US",
    "sg:address":"800 E Roosevelt Rd",
    "sg:city":"Glen Ellyn",
    "sg:classifiers":[
        {
            "category":"Professional",
            "subcategory":"Computer Services",
            "type":"Services"
        }
    ],
    "sg:phone":"+1 630 942 1500",
    "sg:postcode":"60137",
    "sg:province":"IL",
    "sg:tags":[
        "prepackaged",
        "software"
    ],
    "wof:name":"Advocate Consulting Group",
    "wof:placetype":"venue"
},
  "geometry": {"coordinates":[-88.052144,41.859466],"type":"Point"}
}