{
  "type": "Feature",
  "properties": {
    "iso:country":"US",
    "sg:address":"2650 W Belden Ave",
    "sg:city":"Chicago",
    "sg:classifiers":[
        {
            "category":"Retail",
            "subcategory":"Portrait Studio",
            "type":"Services"
        }
    ],
    "sg:phone":"+1 773 252 3747",
    "sg:postcode":"60647",
    "sg:province":"IL",
    "sg:tags":[
        "photographer",
        "photography"
    ],
    "wof:name":"Alan Shortall Photography Lmt",
    "wof:placetype":"venue"
},
  "geometry": {"coordinates":[-87.694985,41.92305],"type":"Point"}
}