{
  "type": "Feature",
  "properties": {
    "addr:full":"3105 W 26th Street Chicago IL 60623",
    "addr:housenumber":"3105",
    "addr:postcode":"60623",
    "addr:street":"W 26Th Street",
    "iso:country":"US",
    "sg:address":"3105 W 26th Street",
    "sg:city":"Chicago",
    "sg:classifiers":[
        {
            "category":"Restaurant",
            "type":"Food & Drink"
        }
    ],
    "sg:phone":"+1 773 376 3611",
    "sg:postcode":"60623",
    "sg:province":"IL",
    "sg:tags":[
        "mexican"
    ],
    "sg:website":"www.elpollofelizchicago.com",
    "wof:name":"El Pollo Feliz",
    "wof:placetype":"venue"
},
  "geometry": {"coordinates":[-87.702842,41.844544],"type":"Point"}
}