{
  "type": "Feature",
  "properties": {
    "iso:country":"US",
    "sg:address":"23741 E 200 North Rd",
    "sg:city":"Le Roy",
    "sg:classifiers":[
        {
            "category":"Freight",
            "type":"Transportation"
        }
    ],
    "sg:phone":"+1 309 962 9664",
    "sg:postcode":"61752",
    "sg:province":"IL",
    "sg:tags":[
        "trucking"
    ],
    "wof:name":"Keith Morgan Trucking Inc",
    "wof:placetype":"venue"
},
  "geometry": {"coordinates":[-88.812397,40.311836],"type":"Point"}
}