{
  "type": "Feature",
  "properties": {
    "iso:country":"US",
    "sg:address":"2041 Arrowhead Ct",
    "sg:city":"Geneva",
    "sg:classifiers":[
        {
            "category":"Retail",
            "subcategory":"Portrait Studio",
            "type":"Services"
        }
    ],
    "sg:phone":"+1 630 845 2611",
    "sg:postcode":"60134",
    "sg:province":"IL",
    "sg:tags":[
        "photo"
    ],
    "wof:name":"Jean Whiteside Photography",
    "wof:placetype":"venue"
},
  "geometry": {"coordinates":[-88.337489,41.868629],"type":"Point"}
}