{
  "type": "Feature",
  "properties": {
    "addr:full":"4950 Madison St Skokie IL 60077",
    "addr:housenumber":"4950",
    "addr:postcode":"60077",
    "addr:street":"Madison St",
    "iso:country":"US",
    "sg:address":"4950 Madison St",
    "sg:city":"Skokie",
    "sg:classifiers":[
        {
            "category":"Professional",
            "subcategory":"Business Services",
            "type":"Services"
        },
        {
            "category":"Government",
            "subcategory":"Post Office",
            "type":"Public Place"
        }
    ],
    "sg:phone":"+1 800 275 8777",
    "sg:postcode":"60077",
    "sg:province":"IL",
    "sg:tags":[
        "mail",
        "shipping"
    ],
    "sg:website":"http://www.usps.com",
    "wof:name":"USPS - United States Post Office - Skokie Main Office",
    "wof:placetype":"venue"
},
  "geometry": {"coordinates":[-87.751986,42.03178],"type":"Point"}
}