{
  "type": "Feature",
  "properties": {
    "iso:country":"US",
    "sg:address":"150 River Oaks Center Dr",
    "sg:city":"Calumet City",
    "sg:classifiers":[
        {
            "category":"Communications",
            "subcategory":"Film & Video Production",
            "type":"Services"
        }
    ],
    "sg:phone":"+1 708 862 2480",
    "sg:postcode":"60409",
    "sg:province":"IL",
    "sg:tags":[
        "motion",
        "picture",
        "building",
        "maintenance"
    ],
    "wof:name":"Johnson Controls",
    "wof:placetype":"venue"
},
  "geometry": {"coordinates":[-87.53173700000001,41.596523],"type":"Point"}
}