{
  "type": "Feature",
  "properties": {
    "addr:full":"2000 S Springinsguth Rd Schaumburg IL 60193",
    "addr:housenumber":"2000",
    "addr:postcode":"60193",
    "addr:street":"S Springinsguth Rd",
    "iso:country":"US",
    "sg:address":"2000 S Springinsguth Rd",
    "sg:city":"Schaumburg",
    "sg:classifiers":[
        {
            "category":"Travel",
            "subcategory":"Travel Agent",
            "type":"Entertainment"
        }
    ],
    "sg:phone":"+1 847 895 9260",
    "sg:postcode":"60193",
    "sg:province":"IL",
    "sg:tags":[
        "agency"
    ],
    "wof:name":"Metropolitan Rail",
    "wof:placetype":"venue"
},
  "geometry": {"coordinates":[-88.119304,42.00534],"type":"Point"}
}