{
  "type": "Feature",
  "properties": {
    "addr:full":"35 W Wacker Dr Chicago IL 60601",
    "addr:housenumber":"35",
    "addr:postcode":"60601",
    "addr:street":"W Wacker Dr",
    "iso:country":"US",
    "sg:address":"35 W Wacker Dr",
    "sg:city":"Chicago",
    "sg:classifiers":[
        {
            "category":"Professional",
            "subcategory":"Lawyer & Legal Services",
            "type":"Services"
        }
    ],
    "sg:phone":"+1 312 558 5588",
    "sg:postcode":"60601",
    "sg:province":"IL",
    "wof:name":"Kijowski Lori Ann Lwyr",
    "wof:placetype":"venue"
},
  "geometry": {"coordinates":[-87.628998,41.886799],"type":"Point"}
}