{
  "type": "Feature",
  "properties": {
    "addr:full":"3339 W Columbus Ave Chicago IL 60652",
    "addr:housenumber":"3339",
    "addr:postcode":"60652",
    "addr:street":"W Columbus Ave",
    "iso:country":"US",
    "sg:address":"3339 W Columbus Ave",
    "sg:city":"Chicago",
    "sg:classifiers":[
        {
            "category":"Manufacturing",
            "subcategory":"Glass & Minerals",
            "type":"Manufacturing & Wholesale Goods"
        }
    ],
    "sg:phone":"+1 773 737 7303",
    "sg:postcode":"60652",
    "sg:province":"IL",
    "sg:tags":[
        "lining",
        "material",
        "chimney"
    ],
    "wof:name":"A & C Sheet Metal",
    "wof:placetype":"venue"
},
  "geometry": {"coordinates":[-87.70686000000001,41.747088],"type":"Point"}
}