{
  "type": "Feature",
  "properties": {
    "iso:country":"US",
    "sg:address":"500 Keeney St",
    "sg:city":"Evanston",
    "sg:classifiers":[
        {
            "category":"Utilities",
            "subcategory":"Telephone",
            "type":"Services"
        }
    ],
    "sg:phone":"+1 847 223 7291",
    "sg:postcode":"60202",
    "sg:province":"IL",
    "sg:tags":[
        "communications"
    ],
    "wof:name":"Phil Lindsey",
    "wof:placetype":"venue"
},
  "geometry": {"coordinates":[-87.677656,42.029398],"type":"Point"}
}