{
  "type": "Feature",
  "properties": {
    "iso:country":"US",
    "sg:address":"24785 Lagoon Dr",
    "sg:city":"Cary",
    "sg:classifiers":[
        {
            "category":"Professional",
            "subcategory":"Business Services",
            "type":"Services"
        }
    ],
    "sg:phone":"+1 847 516 2658",
    "sg:postcode":"60013",
    "sg:province":"IL",
    "wof:name":"Automated Control Solutions",
    "wof:placetype":"venue"
},
  "geometry": {"coordinates":[-88.17929700000001,42.222709],"type":"Point"}
}