{
  "type": "Feature",
  "properties": {
    "addr:full":"11110 Revere Rd Mokena IL 60448",
    "addr:housenumber":"11110",
    "addr:postcode":"60448",
    "addr:street":"Revere Rd",
    "iso:country":"US",
    "sg:address":"11110 Revere Rd",
    "sg:city":"Mokena",
    "sg:classifiers":[
        {
            "category":"Professional",
            "subcategory":"Engineering",
            "type":"Services"
        },
        {
            "category":"Manufacturing",
            "subcategory":"Electronics",
            "type":"Manufacturing & Wholesale Goods"
        }
    ],
    "sg:phone":"+1 708 479 9045",
    "sg:postcode":"60448",
    "sg:province":"IL",
    "sg:tags":[
        "control",
        "system",
        "automation",
        "electronic",
        "controls-manufacturers",
        "engineer"
    ],
    "wof:name":"A V I",
    "wof:placetype":"venue"
},
  "geometry": {"coordinates":[-87.888504,41.538747],"type":"Point"}
}