{
  "type": "Feature",
  "properties": {
    "iso:country":"US",
    "sg:address":"1 Bell Rd",
    "sg:city":"Peotone",
    "sg:classifiers":[
        {
            "category":"Education",
            "subcategory":"School",
            "type":"Public Place"
        }
    ],
    "sg:phone":"+1 708 258 3246",
    "sg:postcode":"60447",
    "sg:province":"IL",
    "sg:website":"www.peotone.will.k12.il.us",
    "wof:name":"Peotone Jr High School",
    "wof:placetype":"venue"
},
  "geometry": {"coordinates":[-88.25348,41.49912],"type":"Point"}
}