{
  "type": "Feature",
  "properties": {
    "iso:country":"US",
    "sg:address":"1530 S State Street",
    "sg:city":"Chicago",
    "sg:classifiers":[
        {
            "category":"Retail",
            "subcategory":"Laundry & Dry Cleaning",
            "type":"Services"
        }
    ],
    "sg:phone":"+1 312 225 2545",
    "sg:postcode":"60605",
    "sg:province":"IL",
    "wof:name":"Dearborn Tower Cleaners",
    "wof:placetype":"venue"
},
  "geometry": {"coordinates":[-87.62734399999999,41.861149],"type":"Point"}
}