{
  "type": "Feature",
  "properties": {
    "iso:country":"US",
    "sg:address":"3015 S 25th Ave",
    "sg:city":"Broadview",
    "sg:classifiers":[
        {
            "category":"Building & Trades",
            "subcategory":"Construction",
            "type":"Services"
        }
    ],
    "sg:phone":"+1 708 485 2722",
    "sg:postcode":"60155",
    "sg:province":"IL",
    "sg:tags":[
        "fire",
        "restoration",
        "damage"
    ],
    "wof:name":"Dunne Cleaning Specialists Inc",
    "wof:placetype":"venue"
},
  "geometry": {"coordinates":[-87.86206199999999,41.847901],"type":"Point"}
}