{
  "type": "Feature",
  "properties": {
    "iso:country":"US",
    "sg:address":"35 W Pleasant St",
    "sg:city":"Freeport",
    "sg:classifiers":[
        {
            "category":"Organizations",
            "subcategory":"Religious Organization",
            "type":"Services"
        }
    ],
    "sg:phone":"+1 815 235 4227",
    "sg:postcode":"61032",
    "sg:province":"IL",
    "sg:tags":[
        "clergy"
    ],
    "wof:name":"James Cooley",
    "wof:placetype":"venue"
},
  "geometry": {"coordinates":[-89.618881,42.293436],"type":"Point"}
}