{
  "type": "Feature",
  "properties": {
    "addr:full":"1835 Suffolk Ave Westchester IL 60154",
    "addr:housenumber":"1835",
    "addr:postcode":"60154",
    "addr:street":"Suffolk Ave",
    "iso:country":"US",
    "sg:address":"1835 Suffolk Ave",
    "sg:city":"Westchester",
    "sg:classifiers":[
        {
            "category":"Health Services",
            "subcategory":"Doctor",
            "type":"Services"
        }
    ],
    "sg:phone":"+1 708 343 0668",
    "sg:postcode":"60154",
    "sg:province":"IL",
    "sg:tags":[
        "dental"
    ],
    "wof:name":"DDS Design",
    "wof:placetype":"venue"
},
  "geometry": {"coordinates":[-87.872079,41.853205],"type":"Point"}
}