{
  "type": "Feature",
  "properties": {
    "iso:country":"US",
    "sg:address":"3722 N Southport Ave",
    "sg:city":"Chicago",
    "sg:classifiers":[
        {
            "category":"Shopping",
            "subcategory":"Gifts & Souvenirs",
            "type":"Retail Goods"
        }
    ],
    "sg:phone":"+1 773 549 9300",
    "sg:postcode":"60613",
    "sg:province":"IL",
    "sg:tags":[
        "basket"
    ],
    "sg:website":"http://www.ediblearrangements.com",
    "wof:name":"Edible Arrangements",
    "wof:placetype":"venue"
},
  "geometry": {"coordinates":[-87.663996,41.949306],"type":"Point"}
}