{
  "type": "Feature",
  "properties": {
    "iso:country":"US",
    "sg:address":"3010 N Olcott Ave",
    "sg:city":"Chicago",
    "sg:classifiers":[
        {
            "category":"Wholesale",
            "subcategory":"Computers",
            "type":"Manufacturing & Wholesale Goods"
        }
    ],
    "sg:phone":"+1 773 622 4341",
    "sg:postcode":"60707",
    "sg:province":"IL",
    "sg:tags":[
        "equipment"
    ],
    "wof:name":"Vesa Inc",
    "wof:placetype":"venue"
},
  "geometry": {"coordinates":[-87.81395500000001,41.934565],"type":"Point"}
}