{
  "type": "Feature",
  "properties": {
    "addr:full":"25101 W Mitchell Ct Ingleside IL 60041",
    "addr:housenumber":"25101",
    "addr:postcode":"60041",
    "addr:street":"W Mitchell Ct",
    "iso:country":"US",
    "sg:address":"25101 W Mitchell Ct",
    "sg:city":"Ingleside",
    "sg:classifiers":[
        {
            "category":"Professional",
            "subcategory":"Detective & Security Services",
            "type":"Services"
        }
    ],
    "sg:phone":"+1 847 587 0648",
    "sg:postcode":"60041",
    "sg:province":"IL",
    "sg:tags":[
        "information",
        "bureau"
    ],
    "wof:name":"Allbright Building & Maintenance Services",
    "wof:placetype":"venue"
},
  "geometry": {"coordinates":[-88.122101,42.380051],"type":"Point"}
}