{
  "type": "Feature",
  "properties": {
    "addr:full":"1302 N Prospect Ave Champaign IL 61820",
    "addr:housenumber":"1302",
    "addr:postcode":"61820",
    "addr:street":"N Prospect Ave",
    "iso:country":"US",
    "sg:address":"1302 N Prospect Ave",
    "sg:city":"Champaign",
    "sg:classifiers":[
        {
            "category":"Autos & Motor Vehicles",
            "subcategory":"Fuel & Gas Station",
            "type":"Retail Goods"
        }
    ],
    "sg:phone":"+1   ",
    "sg:postcode":"61820",
    "sg:province":"IL",
    "sg:tags":[
        "station",
        "gasoline"
    ],
    "wof:name":"Mobil",
    "wof:placetype":"venue"
},
  "geometry": {"coordinates":[-88.257897,40.12956],"type":"Point"}
}