{
  "type": "Feature",
  "properties": {
    "iso:country":"US",
    "sg:address":"2801 Civic Circle Blvd Ste 2",
    "sg:city":"Marion",
    "sg:classifiers":[
        {
            "category":"Banks & Credit Unions",
            "subcategory":"Investment Brokerage",
            "type":"Services"
        }
    ],
    "sg:phone":"+1 618 997 5763",
    "sg:postcode":"62959",
    "sg:province":"IL",
    "sg:tags":[
        "investing"
    ],
    "wof:name":"Jones Edward",
    "wof:placetype":"venue"
},
  "geometry": {"coordinates":[-88.975694,37.74964],"type":"Point"}
}