{
  "type": "Feature",
  "properties": {
    "addr:full":"1028 W Hickory St Canton IL 61520",
    "addr:housenumber":"1028",
    "addr:postcode":"61520",
    "addr:street":"W Hickory St",
    "iso:country":"US",
    "sg:address":"1028 W Hickory St",
    "sg:city":"Canton",
    "sg:classifiers":[
        {
            "category":"Autos & Motor Vehicles",
            "subcategory":"Automobile Sales",
            "type":"Retail Goods"
        }
    ],
    "sg:phone":"+1 309 649 9328",
    "sg:postcode":"61520",
    "sg:province":"IL",
    "sg:tags":[
        "car",
        "dealer"
    ],
    "wof:name":"Canton Auto Classics",
    "wof:placetype":"venue"
},
  "geometry": {"coordinates":[-90.056982,40.544736],"type":"Point"}
}