{
  "type": "Feature",
  "properties": {
    "iso:country":"US",
    "sg:address":"2848 W Dickens Ave",
    "sg:city":"Chicago",
    "sg:classifiers":[
        {
            "category":"Professional",
            "subcategory":"Research",
            "type":"Services"
        }
    ],
    "sg:phone":"+1 773 235 4308",
    "sg:postcode":"60647",
    "sg:province":"IL",
    "sg:tags":[
        "nonphysical",
        "commercial"
    ],
    "wof:name":"Benchmark Lab",
    "wof:placetype":"venue"
},
  "geometry": {"coordinates":[-87.699735,41.919645],"type":"Point"}
}