{
  "type": "Feature",
  "properties": {
    "addr:full":"1680 N Ada Street Chicago IL 60622",
    "addr:housenumber":"1680",
    "addr:postcode":"60622",
    "addr:street":"N Ada Street",
    "iso:country":"US",
    "sg:address":"1680 N Ada Street",
    "sg:city":"Chicago",
    "sg:classifiers":[
        {
            "category":"Home & Garden",
            "subcategory":"Furniture",
            "type":"Retail Goods"
        }
    ],
    "sg:phone":"+1 773 384 1770",
    "sg:postcode":"60622",
    "sg:province":"IL",
    "sg:tags":[
        "store"
    ],
    "wof:name":"Krause Eric Furniture",
    "wof:placetype":"venue"
},
  "geometry": {"coordinates":[-87.662218,41.913114],"type":"Point"}
}