{
  "type": "Feature",
  "properties": {
    "addr:full":"945 Wilshire Dr Libertyville IL 60048",
    "addr:housenumber":"945",
    "addr:postcode":"60048",
    "addr:street":"Wilshire Dr",
    "iso:country":"US",
    "sg:address":"945 Wilshire Dr",
    "sg:city":"Libertyville",
    "sg:classifiers":[
        {
            "category":"Professional",
            "type":"Services"
        }
    ],
    "sg:phone":"+1 847 367 7216",
    "sg:postcode":"60048",
    "sg:province":"IL",
    "sg:tags":[
        "establishment"
    ],
    "wof:name":"S As Institute",
    "wof:placetype":"venue"
},
  "geometry": {"coordinates":[-87.96974400000001,42.293251],"type":"Point"}
}