{
  "type": "Feature",
  "properties": {
    "iso:country":"US",
    "sg:address":"945 Wilshire Dr",
    "sg:city":"Libertyville",
    "sg:classifiers":[
        {
            "category":"Professional",
            "type":"Services"
        }
    ],
    "sg:phone":"+1 847 367 7216",
    "sg:postcode":"60048",
    "sg:province":"IL",
    "sg:tags":[
        "establishment"
    ],
    "wof:name":"S As Institute",
    "wof:placetype":"venue"
},
  "geometry": {"coordinates":[-87.969744,42.293251],"type":"Point"}
}