{
  "type": "Feature",
  "properties": {
    "addr:full":"742 Royal Oak Dr Marengo IL 60152",
    "addr:housenumber":"742",
    "addr:postcode":"60152",
    "addr:street":"Royal Oak Dr",
    "iso:country":"US",
    "sg:address":"742 Royal Oak Dr",
    "sg:city":"Marengo",
    "sg:classifiers":[
        {
            "category":"Shopping",
            "subcategory":"Jewelry",
            "type":"Retail Goods"
        }
    ],
    "sg:phone":"+1   ",
    "sg:postcode":"60152",
    "sg:province":"IL",
    "sg:tags":[
        "stone",
        "diamond",
        "setting"
    ],
    "wof:name":"Standleys Jewelry",
    "wof:placetype":"venue"
},
  "geometry": {"coordinates":[-88.610229,42.243836],"type":"Point"}
}