{
  "type": "Feature",
  "properties": {
    "addr:full":"408 Country Club Acres Belleville IL 62223",
    "addr:housenumber":"408",
    "addr:postcode":"62223",
    "addr:street":"Country Club",
    "iso:country":"US",
    "sg:address":"408 Country Club Acres",
    "sg:city":"Belleville",
    "sg:classifiers":[
        {
            "category":"Real Estate",
            "subcategory":"Real Estate Agent",
            "type":"Services"
        }
    ],
    "sg:phone":"+1 618 398 1110",
    "sg:postcode":"62223",
    "sg:province":"IL",
    "wof:name":"Thurlow & Assoc",
    "wof:placetype":"venue"
},
  "geometry": {"coordinates":[-90.04864999999999,38.550455],"type":"Point"}
}