{
  "type": "Feature",
  "properties": {
    "addr:full":"2885 Plainfield Rd Joliet IL 60435",
    "addr:housenumber":"2885",
    "addr:postcode":"60435",
    "addr:street":"Plainfield Rd",
    "iso:country":"US",
    "sg:address":"2885 Plainfield Rd",
    "sg:city":"Joliet",
    "sg:classifiers":[
        {
            "category":"Restaurant",
            "type":"Food & Drink"
        }
    ],
    "sg:menulink":"http://www.allmenus.com/il/plainfield/212422-mcdonalds/menu/",
    "sg:postcode":"60435",
    "sg:province":"IL",
    "sg:tags":[
        "burger",
        "american"
    ],
    "wof:name":"McDonald's",
    "wof:placetype":"venue"
},
  "geometry": {"coordinates":[-88.160882,41.579045],"type":"Point"}
}