{
  "type": "Feature",
  "properties": {
    "iso:country":"US",
    "sg:address":"229 W Galena Blvd",
    "sg:city":"Aurora",
    "sg:classifiers":[
        {
            "category":"Retail",
            "subcategory":"Auto Repair",
            "type":"Services"
        }
    ],
    "sg:phone":"+1 630 844 1666",
    "sg:postcode":"60506",
    "sg:province":"IL",
    "sg:tags":[
        "transmission"
    ],
    "wof:name":"Auto House",
    "wof:placetype":"venue"
},
  "geometry": {"coordinates":[-88.319767,41.760381],"type":"Point"}
}