{
  "type": "Feature",
  "properties": {
    "iso:country":"US",
    "sg:address":"5203 Home Ave",
    "sg:city":"Mc Henry",
    "sg:classifiers":[
        {
            "category":"Building & Trades",
            "subcategory":"Cleaning & Sanitation",
            "type":"Services"
        }
    ],
    "sg:phone":"+1 815 385 8854",
    "sg:postcode":"60050",
    "sg:province":"IL",
    "sg:tags":[
        "maintenance"
    ],
    "wof:name":"Maid E Z Cleaning",
    "wof:placetype":"venue"
},
  "geometry": {"coordinates":[-88.299019,42.35108],"type":"Point"}
}