{
  "type": "Feature",
  "properties": {
    "iso:country":"US",
    "sg:address":"3 Fenview Ct",
    "sg:city":"Bolingbrook",
    "sg:classifiers":[
        {
            "category":"Home & Garden",
            "subcategory":"Building Materials",
            "type":"Retail Goods"
        },
        {
            "category":"Building & Trades",
            "subcategory":"Construction",
            "type":"Services"
        }
    ],
    "sg:phone":"+1 630 739 7715",
    "sg:postcode":"60440",
    "sg:province":"IL",
    "sg:tags":[
        "concrete",
        "staining",
        "contractor"
    ],
    "wof:name":"All Crete Concrete",
    "wof:placetype":"venue"
},
  "geometry": {"coordinates":[-88.045703,41.726492],"type":"Point"}
}