{
  "type": "Feature",
  "properties": {
    "iso:country":"US",
    "sg:address":"140 S Peoria Ave",
    "sg:city":"Dixon",
    "sg:classifiers":[
        {
            "category":"Building & Trades",
            "subcategory":"Construction",
            "type":"Services"
        }
    ],
    "sg:phone":"+1 815 284 6463",
    "sg:postcode":"61021",
    "sg:province":"IL",
    "sg:tags":[
        "contractor"
    ],
    "wof:name":"Roberson Builders Inc",
    "wof:placetype":"venue"
},
  "geometry": {"coordinates":[-89.485046,41.842601],"type":"Point"}
}