{
  "type": "Feature",
  "properties": {
    "addr:full":"119 N Norman Dr Palatine IL 60074",
    "addr:housenumber":"119",
    "addr:postcode":"60074",
    "addr:street":"N Norman Dr",
    "iso:country":"US",
    "sg:address":"119 N Norman Dr",
    "sg:city":"Palatine",
    "sg:classifiers":[
        {
            "category":"Shopping",
            "subcategory":"Crafts & Fabrics",
            "type":"Retail Goods"
        }
    ],
    "sg:phone":"+1   ",
    "sg:postcode":"60074",
    "sg:province":"IL",
    "sg:tags":[
        "sewing"
    ],
    "wof:name":"Sues Sew Unique Embroidery",
    "wof:placetype":"venue"
},
  "geometry": {"coordinates":[-88.00554,42.113391],"type":"Point"}
}