{
  "type": "Feature",
  "properties": {
    "iso:country":"US",
    "sg:address":"1418 W Fayette Ave",
    "sg:city":"Effingham",
    "sg:classifiers":[
        {
            "category":"Wholesale",
            "subcategory":"Groceries",
            "type":"Manufacturing & Wholesale Goods"
        }
    ],
    "sg:phone":"+1 217 857 1414",
    "sg:postcode":"62401",
    "sg:province":"IL",
    "wof:name":"Frito-Lay",
    "wof:placetype":"venue"
},
  "geometry": {"coordinates":[-88.561556,39.12051],"type":"Point"}
}