{
  "type": "Feature",
  "properties": {
    "iso:country":"US",
    "sg:address":"6407 Weaver Rd",
    "sg:city":"Rockford",
    "sg:classifiers":[
        {
            "category":"Bakery",
            "type":"Food & Drink"
        }
    ],
    "sg:phone":"+1 815 633 6914",
    "sg:postcode":"61114",
    "sg:province":"IL",
    "wof:name":"Pepperidge Farms",
    "wof:placetype":"venue"
},
  "geometry": {"coordinates":[-88.991578,42.317323],"type":"Point"}
}