{
  "type": "Feature",
  "properties": {
    "iso:country":"US",
    "sg:address":"34 N Water St",
    "sg:city":"Batavia",
    "sg:classifiers":[
        {
            "category":"Health Services",
            "subcategory":"Doctor",
            "type":"Services"
        }
    ],
    "sg:phone":"+1 630 879 3500",
    "sg:postcode":"60510",
    "sg:province":"IL",
    "sg:tags":[
        "physician",
        "surgeon",
        "medical"
    ],
    "wof:name":"Alexander Delgadillo MD",
    "wof:placetype":"venue"
},
  "geometry": {"coordinates":[-88.310471,41.850776],"type":"Point"}
}