{
  "type": "Feature",
  "properties": {
    "iso:country":"US",
    "sg:address":"4016 Golf Rd",
    "sg:city":"Skokie",
    "sg:classifiers":[
        {
            "category":"Retail",
            "subcategory":"Laundry & Dry Cleaning",
            "type":"Services"
        }
    ],
    "sg:phone":"+1 847 674 8786",
    "sg:postcode":"60076",
    "sg:province":"IL",
    "sg:tags":[
        "cleaners"
    ],
    "wof:name":"K C Cleaners",
    "wof:placetype":"venue"
},
  "geometry": {"coordinates":[-87.728091,42.055325],"type":"Point"}
}