{
  "type": "Feature",
  "properties": {
    "iso:country":"US",
    "sg:address":"303 E Wacker Dr",
    "sg:city":"Chicago",
    "sg:classifiers":[
        {
            "category":"Professional",
            "subcategory":"Business Services",
            "type":"Services"
        }
    ],
    "sg:phone":"+1 312 327 4260",
    "sg:postcode":"60601",
    "sg:province":"IL",
    "sg:tags":[
        "mail",
        "messenger",
        "shipping"
    ],
    "wof:name":"Voicelog",
    "wof:placetype":"venue"
},
  "geometry": {"coordinates":[-87.620605,41.88783],"type":"Point"}
}