{
  "type": "Feature",
  "properties": {
    "iso:country":"US",
    "sg:address":"14738 Innisbrook Ln",
    "sg:city":"Homer Glen",
    "sg:classifiers":[
        {
            "category":"Professional",
            "type":"Services"
        }
    ],
    "sg:phone":"+1 708 301 6783",
    "sg:postcode":"60491",
    "sg:province":"IL",
    "sg:tags":[
        "establishment"
    ],
    "wof:name":"Conco",
    "wof:placetype":"venue"
},
  "geometry": {"coordinates":[-87.960167,41.620229],"type":"Point"}
}