{
  "type": "Feature",
  "properties": {
    "iso:country":"US",
    "sg:address":"4401 W 44th Pl",
    "sg:city":"Chicago",
    "sg:phone":"+1 773 927 7700",
    "sg:postcode":"60632",
    "sg:province":"IL",
    "wof:name":"Randolph Pickle Corp.",
    "wof:placetype":"venue"
},
  "geometry": {"coordinates":[-87.732868,41.813137],"type":"Point"}
}