{
  "type": "Feature",
  "properties": {
    "addr:full":"5400 East Ave Countryside IL 60525",
    "addr:housenumber":"5400",
    "addr:postcode":"60525",
    "addr:street":"East Ave",
    "iso:country":"US",
    "sg:address":"5400 East Ave",
    "sg:city":"Countryside",
    "sg:classifiers":[
        {
            "category":"Sports & Exercise",
            "subcategory":"Sports Center",
            "type":"Entertainment"
        },
        {
            "category":"Sports & Exercise",
            "subcategory":"Playing Field",
            "type":"Entertainment"
        },
        {
            "category":"Community Center",
            "type":"Public Place"
        }
    ],
    "sg:phone":"+1 708 352 3099",
    "sg:postcode":"60525",
    "sg:province":"IL",
    "sg:tags":[
        "recreation",
        "instruction",
        "fitness"
    ],
    "sg:website":"www.flyinghighgym.com",
    "wof:name":"Flying High Sports & Rec Center",
    "wof:placetype":"venue"
},
  "geometry": {"coordinates":[-87.859652,41.792193],"type":"Point"}
}