{
  "type": "Feature",
  "properties": {
    "iso:country":"US",
    "sg:address":"1730 W Fullerton Avenue",
    "sg:city":"Chicago",
    "sg:classifiers":[
        {
            "category":"Retail",
            "subcategory":"Laundry & Dry Cleaning",
            "type":"Services"
        }
    ],
    "sg:phone":"+1 773 862 6000",
    "sg:postcode":"60614",
    "sg:province":"IL",
    "wof:name":"Dolphin Laundry Delivery Service",
    "wof:placetype":"venue"
},
  "geometry": {"coordinates":[-87.672512,41.925087],"type":"Point"}
}