{
  "type": "Feature",
  "properties": {
    "addr:full":"1172 New Trenton Rd Highland IL 62249",
    "addr:housenumber":"1172",
    "addr:postcode":"62249",
    "addr:street":"New Trenton Rd",
    "iso:country":"US",
    "sg:address":"1172 New Trenton Rd",
    "sg:city":"Highland",
    "sg:classifiers":[
        {
            "category":"Autos & Motor Vehicles",
            "subcategory":"Auto Supplies",
            "type":"Retail Goods"
        }
    ],
    "sg:phone":"+1   ",
    "sg:postcode":"62249",
    "sg:province":"IL",
    "sg:tags":[
        "repair",
        "general"
    ],
    "wof:name":"We Auto Care",
    "wof:placetype":"venue"
},
  "geometry": {"coordinates":[-89.68885299999999,38.694047],"type":"Point"}
}