{
  "type": "Feature",
  "properties": {
    "iso:country":"US",
    "sg:address":"5253 W Byron St",
    "sg:city":"Chicago",
    "sg:classifiers":[
        {
            "category":"Organizations",
            "subcategory":"Religious Organization",
            "type":"Services"
        }
    ],
    "sg:phone":"+1 773 685 9736",
    "sg:postcode":"60641",
    "sg:province":"IL",
    "sg:tags":[
        "church"
    ],
    "wof:name":"Fil-American Baptist Church",
    "wof:placetype":"venue"
},
  "geometry": {"coordinates":[-87.7593,41.951199],"type":"Point"}
}