{
  "type": "Feature",
  "properties": {
    "addr:full":"411 W 3rd St Delavan IL 61734",
    "addr:housenumber":"411",
    "addr:postcode":"61734",
    "addr:street":"W 3Rd St",
    "iso:country":"US",
    "sg:address":"411 W 3rd St",
    "sg:city":"Delavan",
    "sg:classifiers":[
        {
            "category":"Building & Trades",
            "subcategory":"Construction",
            "type":"Services"
        }
    ],
    "sg:phone":"+1 309 244 7199",
    "sg:postcode":"61734",
    "sg:province":"IL",
    "sg:tags":[
        "excavation",
        "excavating",
        "contractor"
    ],
    "wof:name":"Tri State Trenching & Drilling",
    "wof:placetype":"venue"
},
  "geometry": {"coordinates":[-89.552256,40.373482],"type":"Point"}
}