{
  "type": "Feature",
  "properties": {
    "addr:full":"2136 W North Ave Chicago IL 60647",
    "addr:housenumber":"2136",
    "addr:postcode":"60647",
    "addr:street":"W North Ave",
    "iso:country":"US",
    "sg:address":"2136 W North Ave",
    "sg:city":"Chicago",
    "sg:classifiers":[
        {
            "category":"Real Estate",
            "subcategory":"Architect",
            "type":"Services"
        }
    ],
    "sg:phone":"+1 773 772 4432",
    "sg:postcode":"60647",
    "sg:province":"IL",
    "wof:name":"Ricchio & Ricchio Architects",
    "wof:placetype":"venue"
},
  "geometry": {"coordinates":[-87.680815,41.910443],"type":"Point"}
}