{
  "type": "Feature",
  "properties": {
    "addr:full":"730 Forest Edge Dr Vernon Hills IL 60061",
    "addr:housenumber":"730",
    "addr:postcode":"60061",
    "addr:street":"Forest Edge Dr",
    "iso:country":"US",
    "sg:address":"730 Forest Edge Dr",
    "sg:city":"Vernon Hills",
    "sg:classifiers":[
        {
            "category":"Wholesale",
            "subcategory":"Hardware",
            "type":"Manufacturing & Wholesale Goods"
        }
    ],
    "sg:phone":"+1 847 427 0055",
    "sg:postcode":"60061",
    "sg:province":"IL",
    "sg:tags":[
        "steam",
        "trap"
    ],
    "sg:website":"www.steamgard.com",
    "wof:name":"Steamgard LLC",
    "wof:placetype":"venue"
},
  "geometry": {"coordinates":[-87.940679,42.210785],"type":"Point"}
}