{
  "type": "Feature",
  "properties": {
    "iso:country":"US",
    "sg:address":"12466 Buckeye Rd",
    "sg:city":"Highland",
    "sg:classifiers":[
        {
            "category":"Government",
            "subcategory":"Office",
            "type":"Public Place"
        }
    ],
    "sg:phone":"+1 618 654 8123",
    "sg:postcode":"62249",
    "sg:province":"IL",
    "sg:tags":[
        "village"
    ],
    "wof:name":"Helvetia Township Shed",
    "wof:placetype":"venue"
},
  "geometry": {"coordinates":[-89.66799399999999,38.691626],"type":"Point"}
}