{
  "type": "Feature",
  "properties": {
    "iso:country":"US",
    "sg:address":"5 E Grand Ave",
    "sg:city":"Fox Lake",
    "sg:classifiers":[
        {
            "category":"Restaurant",
            "type":"Food & Drink"
        }
    ],
    "sg:menulink":"http://www.allmenus.com/il/grant/79974-pizza-hut/menu/",
    "sg:phone":"+1 847 587 7929",
    "sg:postcode":"60020",
    "sg:province":"IL",
    "sg:tags":[
        "american",
        "pizza"
    ],
    "wof:name":"Pizza Hut",
    "wof:placetype":"venue"
},
  "geometry": {"coordinates":[-88.183491,42.396689],"type":"Point"}
}