{
  "type": "Feature",
  "properties": {
    "addr:full":"8124 W 93rd St Hickory Hills IL 60457",
    "addr:housenumber":"8124",
    "addr:postcode":"60457",
    "addr:street":"W 93Rd St",
    "iso:country":"US",
    "sg:address":"8124 W 93rd St",
    "sg:city":"Hickory Hills",
    "sg:classifiers":[
        {
            "category":"Shopping",
            "subcategory":"Computers & Home Electronics",
            "type":"Retail Goods"
        }
    ],
    "sg:phone":"+1 708 599 0015",
    "sg:postcode":"60457",
    "sg:province":"IL",
    "wof:name":"Sound Construction",
    "wof:placetype":"venue"
},
  "geometry": {"coordinates":[-87.821602,41.722099],"type":"Point"}
}