{
  "type": "Feature",
  "properties": {
    "addr:full":"3380 Washington County Line Rd Lenzburg IL 62255",
    "addr:housenumber":"3380",
    "addr:postcode":"62255",
    "addr:street":"Washington County Line Rd",
    "iso:country":"US",
    "sg:address":"3380 Washington County Line Rd",
    "sg:city":"Lenzburg",
    "sg:classifiers":[
        {
            "category":"Real Estate",
            "subcategory":"Real Estate Operator",
            "type":"Services"
        }
    ],
    "sg:phone":"+1 618 768 4335",
    "sg:postcode":"62255",
    "sg:province":"IL",
    "sg:tags":[
        "property",
        "lessor"
    ],
    "wof:name":"Greten Urban",
    "wof:placetype":"venue"
},
  "geometry": {"coordinates":[-89.703746,38.328571],"type":"Point"}
}