{
  "type": "Feature",
  "properties": {
    "addr:full":"10624 S Kolmar Ave Oak Lawn IL 60453",
    "addr:housenumber":"10624",
    "addr:postcode":"60453",
    "addr:street":"S Kolmar Ave",
    "iso:country":"US",
    "sg:address":"10624 S Kolmar Ave",
    "sg:city":"Oak Lawn",
    "sg:classifiers":[
        {
            "category":"Local Transit",
            "type":"Transportation"
        }
    ],
    "sg:phone":"+1 773 927 6450",
    "sg:postcode":"60453",
    "sg:province":"IL",
    "sg:tags":[
        "limousine"
    ],
    "wof:name":"A-Ms Limousine Svc",
    "wof:placetype":"venue"
},
  "geometry": {"coordinates":[-87.73409599999999,41.700631],"type":"Point"}
}