{
  "type": "Feature",
  "properties": {
    "iso:country":"US",
    "sg:address":"212 E Summer St",
    "sg:city":"Hillsboro",
    "sg:classifiers":[
        {
            "category":"Health Services",
            "subcategory":"Doctor",
            "type":"Services"
        },
        {
            "category":"Health Services",
            "subcategory":"Dentist",
            "type":"Services"
        }
    ],
    "sg:phone":"+1 217 532 3333",
    "sg:postcode":"62049",
    "sg:province":"IL",
    "sg:tags":[
        "dentists-oral",
        "physician",
        "maxillofacial",
        "surgeons",
        "surgery",
        "oral"
    ],
    "wof:name":"Hart Kai D Dds",
    "wof:placetype":"venue"
},
  "geometry": {"coordinates":[-89.492048,39.15376],"type":"Point"}
}