{
  "type": "Feature",
  "properties": {
    "addr:full":"4358 W 35th Pl Chicago IL 60632",
    "addr:housenumber":"4358",
    "addr:postcode":"60632",
    "addr:street":"W 35Th Pl",
    "iso:country":"US",
    "sg:address":"4358 W 35th Pl",
    "sg:city":"Chicago",
    "sg:classifiers":[
        {
            "category":"Retail",
            "subcategory":"Auto Repair",
            "type":"Services"
        }
    ],
    "sg:phone":"+1 773 247 7250",
    "sg:postcode":"60632",
    "sg:province":"IL",
    "sg:tags":[
        "trailers-repair"
    ],
    "wof:name":"Intermodal Maintenance Group",
    "wof:placetype":"venue"
},
  "geometry": {"coordinates":[-87.728137,41.830605],"type":"Point"}
}