{
  "type": "Feature",
  "properties": {
    "iso:country":"US",
    "sg:address":"1616 W Glenlake Ave",
    "sg:city":"Chicago",
    "sg:classifiers":[
        {
            "category":"Wholesale",
            "subcategory":"Durable Goods & Equipment",
            "type":"Manufacturing & Wholesale Goods"
        }
    ],
    "sg:phone":"+1 773 274 4114",
    "sg:postcode":"60660",
    "sg:province":"IL",
    "sg:tags":[
        "professional",
        "school",
        "commercial",
        "lithographic",
        "public"
    ],
    "wof:name":"National School Methods Inc",
    "wof:placetype":"venue"
},
  "geometry": {"coordinates":[-87.67045899999999,41.992883],"type":"Point"}
}