{
  "type": "Feature",
  "properties": {
    "iso:country":"US",
    "sg:address":"108 Mc Coy St",
    "sg:city":"Granville",
    "sg:classifiers":[
        {
            "category":"Insurance",
            "subcategory":"Insurance Agent",
            "type":"Services"
        }
    ],
    "sg:phone":"+1 815 339 6136",
    "sg:postcode":"61326",
    "sg:province":"IL",
    "wof:name":"Country Insurance & Financial",
    "wof:placetype":"venue"
},
  "geometry": {"coordinates":[-89.228193,41.262884],"type":"Point"}
}