{
  "type": "Feature",
  "properties": {
    "addr:full":"755 S Milwaukee Ave Libertyville IL 60048",
    "addr:housenumber":"755",
    "addr:postcode":"60048",
    "addr:street":"S Milwaukee Ave",
    "iso:country":"US",
    "sg:address":"755 S Milwaukee Ave",
    "sg:city":"Libertyville",
    "sg:classifiers":[
        {
            "category":"Health Services",
            "subcategory":"Doctor",
            "type":"Services"
        }
    ],
    "sg:phone":"+1 847 573 9031",
    "sg:postcode":"60048",
    "sg:province":"IL",
    "sg:tags":[
        "physician",
        "surgeon"
    ],
    "wof:name":"Chest & Sleep Medicine Assoc",
    "wof:placetype":"venue"
},
  "geometry": {"coordinates":[-87.951812,42.275383],"type":"Point"}
}