{
  "type": "Feature",
  "properties": {
    "addr:full":"1732 N Halsted St Chicago IL 60614",
    "addr:housenumber":"1732",
    "addr:postcode":"60614",
    "addr:street":"N Halsted St",
    "iso:country":"US",
    "sg:address":"1732 N Halsted St",
    "sg:city":"Chicago",
    "sg:classifiers":[
        {
            "category":"Food & Beverages",
            "subcategory":"Specialty",
            "type":"Retail Goods"
        },
        {
            "category":"Restaurant",
            "type":"Food & Drink"
        }
    ],
    "sg:phone":"+1 312 266 1199",
    "sg:postcode":"60614",
    "sg:province":"IL",
    "sg:tags":[
        "gluten-free",
        "italian"
    ],
    "sg:website":"www.vincichicago.com",
    "wof:name":"Vinci Restaurant",
    "wof:placetype":"venue"
},
  "geometry": {"coordinates":[-87.64830000000001,41.911499],"type":"Point"}
}