{
  "type": "Feature",
  "properties": {
    "iso:country":"US",
    "sg:address":"12616 S Harlem Ave",
    "sg:city":"Palos Heights",
    "sg:classifiers":[
        {
            "category":"Professional",
            "subcategory":"Lawyer & Legal Services",
            "type":"Services"
        }
    ],
    "sg:phone":"+1 708 448 0200",
    "sg:postcode":"60463",
    "sg:province":"IL",
    "sg:tags":[
        "personal",
        "injury"
    ],
    "wof:name":"Toscas John Z Atty",
    "wof:placetype":"venue"
},
  "geometry": {"coordinates":[-87.796402,41.661499],"type":"Point"}
}