{
  "type": "Feature",
  "properties": {
    "iso:country":"US",
    "sg:address":"7320 US Hwy 45 S",
    "sg:city":"Carrier Mills",
    "sg:classifiers":[
        {
            "category":"Farming",
            "subcategory":"Farm",
            "type":"Manufacturing & Wholesale Goods"
        }
    ],
    "sg:phone":"+1 618 994 4618",
    "sg:postcode":"62917",
    "sg:province":"IL",
    "wof:name":"Apple Creek Farms",
    "wof:placetype":"venue"
},
  "geometry": {"coordinates":[-88.635014,37.682124],"type":"Point"}
}