{
  "type": "Feature",
  "properties": {
    "iso:country":"US",
    "sg:address":"231 N Randall Rd",
    "sg:city":"Lake In the Hills",
    "sg:classifiers":[
        {
            "category":"Restaurant",
            "type":"Food & Drink"
        }
    ],
    "sg:phone":"+1 847 458 8232",
    "sg:postcode":"60156",
    "sg:province":"IL",
    "sg:website":"www.tacobell.com",
    "wof:name":"Taco Bell",
    "wof:placetype":"venue"
},
  "geometry": {"coordinates":[-88.33560199999999,42.182301],"type":"Point"}
}