{
  "type": "Feature",
  "properties": {
    "addr:full":"288 Wagonwood Rd Round Lake IL 60073",
    "addr:housenumber":"288",
    "addr:postcode":"60073",
    "addr:street":"Wagonwood Rd",
    "iso:country":"US",
    "sg:address":"288 Wagonwood Rd",
    "sg:city":"Round Lake",
    "sg:classifiers":[
        {
            "category":"Professional",
            "subcategory":"Art Services",
            "type":"Services"
        }
    ],
    "sg:phone":"+1 847 740 2214",
    "sg:postcode":"60073",
    "sg:province":"IL",
    "sg:tags":[
        "commercial",
        "design"
    ],
    "wof:name":"Eye Design Graphics",
    "wof:placetype":"venue"
},
  "geometry": {"coordinates":[-88.108891,42.353687],"type":"Point"}
}