{
  "type": "Feature",
  "properties": {
    "iso:country":"US",
    "sg:address":"712A Higgins Rd",
    "sg:city":"Park Ridge",
    "sg:classifiers":[
        {
            "category":"Restaurant",
            "type":"Food & Drink"
        }
    ],
    "sg:phone":"+1 847 698 1168",
    "sg:postcode":"60068",
    "sg:province":"IL",
    "sg:tags":[
        "thai"
    ],
    "wof:name":"Golden Elephant",
    "wof:placetype":"venue"
},
  "geometry": {"coordinates":[-87.833276,41.985862],"type":"Point"}
}