{
  "type": "Feature",
  "properties": {
    "addr:full":"180 E Pearson St Chicago IL 60611",
    "addr:housenumber":"180",
    "addr:postcode":"60611",
    "addr:street":"E Pearson St",
    "iso:country":"US",
    "sg:address":"180 E Pearson St",
    "sg:city":"Chicago",
    "sg:classifiers":[
        {
            "category":"Real Estate",
            "subcategory":"Real Estate Services",
            "type":"Services"
        }
    ],
    "sg:phone":"+1 312 337 7955",
    "sg:postcode":"60611",
    "sg:province":"IL",
    "sg:tags":[
        "management",
        "condominium"
    ],
    "wof:name":"Water Tower Park",
    "wof:placetype":"venue"
},
  "geometry": {"coordinates":[-87.62268299999999,41.897598],"type":"Point"}
}