{
  "type": "Feature",
  "properties": {
    "iso:country":"US",
    "sg:address":"2308 Washington St",
    "sg:city":"Waukegan",
    "sg:classifiers":[
        {
            "category":"Retail",
            "subcategory":"Laundry & Dry Cleaning",
            "type":"Services"
        }
    ],
    "sg:phone":"+1 847 662 3761",
    "sg:postcode":"60085",
    "sg:province":"IL",
    "sg:tags":[
        "cleaners",
        "plant"
    ],
    "wof:name":"Del Mar Cleaners Inc",
    "wof:placetype":"venue"
},
  "geometry": {"coordinates":[-87.86244000000001,42.359568],"type":"Point"}
}