{
  "type": "Feature",
  "properties": {
    "iso:country":"US",
    "sg:address":"1422 S 20th Ave",
    "sg:city":"Maywood",
    "sg:classifiers":[
        {
            "category":"Social Services",
            "subcategory":"Child Care",
            "type":"Services"
        }
    ],
    "sg:phone":"+1 708 865 7648",
    "sg:postcode":"60153",
    "sg:province":"IL",
    "sg:tags":[
        "day"
    ],
    "wof:name":"Jo Ann Montgomery",
    "wof:placetype":"venue"
},
  "geometry": {"coordinates":[-87.857192,41.873823],"type":"Point"}
}