{
  "type": "Feature",
  "properties": {
    "iso:country":"US",
    "sg:address":"2500 Westward Dr",
    "sg:city":"Spring Grove",
    "sg:classifiers":[
        {
            "category":"Retail",
            "subcategory":"Auto Repair",
            "type":"Services"
        }
    ],
    "sg:phone":"+1 815 675 0690",
    "sg:postcode":"60081",
    "sg:province":"IL",
    "sg:tags":[
        "automobile",
        "customizing"
    ],
    "wof:name":"Road Rage Kustoms",
    "wof:placetype":"venue"
},
  "geometry": {"coordinates":[-88.245385,42.43816],"type":"Point"}
}