{
  "type": "Feature",
  "properties": {
    "iso:country":"US",
    "sg:address":"12019 S 72nd Ct",
    "sg:city":"Palos Heights",
    "sg:classifiers":[
        {
            "category":"Building & Trades",
            "subcategory":"Construction",
            "type":"Services"
        }
    ],
    "sg:phone":"+1 708 448 8331",
    "sg:postcode":"60463",
    "sg:province":"IL",
    "sg:tags":[
        "contractor"
    ],
    "wof:name":"Fatima & Farida Inc",
    "wof:placetype":"venue"
},
  "geometry": {"coordinates":[-87.79783,41.67316],"type":"Point"}
}