{
  "type": "Feature",
  "properties": {
    "addr:full":"773 W. Lake Street Chicago IL 60610",
    "addr:housenumber":"773",
    "addr:postcode":"60610",
    "addr:street":"W. Lake Street",
    "iso:country":"US",
    "sg:address":"773 W. Lake Street",
    "sg:city":"Chicago",
    "sg:classifiers":[
        {
            "category":"Museum",
            "type":"Entertainment"
        }
    ],
    "sg:phone":"+1 312 382 0546",
    "sg:postcode":"60610",
    "sg:province":"IL",
    "wof:name":"Galleria 773",
    "wof:placetype":"venue"
},
  "geometry": {"coordinates":[-87.647102,41.885601],"type":"Point"}
}