{
  "type": "Feature",
  "properties": {
    "iso:country":"US",
    "sg:address":"11555 S Harlem Ave",
    "sg:city":"Worth",
    "sg:classifiers":[
        {
            "category":"Health Services",
            "subcategory":"Podiatrist",
            "type":"Services"
        }
    ],
    "sg:phone":"+1 708 361 2323",
    "sg:postcode":"60482",
    "sg:province":"IL",
    "wof:name":"Alex V Stanevich DPM",
    "wof:placetype":"venue"
},
  "geometry": {"coordinates":[-87.797035,41.681035],"type":"Point"}
}