{
  "type": "Feature",
  "properties": {
    "addr:full":"7 Blanchard Cir Wheaton IL 60187",
    "addr:housenumber":"7",
    "addr:postcode":"60187",
    "addr:street":"Blanchard Cir",
    "iso:country":"US",
    "sg:address":"7 Blanchard Cir",
    "sg:city":"Wheaton",
    "sg:classifiers":[
        {
            "category":"Health Services",
            "subcategory":"Dentist",
            "type":"Services"
        }
    ],
    "sg:phone":"+1 630 681 0108",
    "sg:postcode":"60187",
    "sg:province":"IL",
    "wof:name":"Central Dupage Dental Group",
    "wof:placetype":"venue"
},
  "geometry": {"coordinates":[-88.10189800000001,41.836601],"type":"Point"}
}