{
  "type": "Feature",
  "properties": {
    "iso:country":"US",
    "sg:address":"2852 S Farrell St",
    "sg:city":"Chicago",
    "sg:classifiers":[
        {
            "category":"Building & Trades",
            "subcategory":"Construction",
            "type":"Services"
        }
    ],
    "sg:phone":"+1 773 709 3048",
    "sg:postcode":"60608",
    "sg:province":"IL",
    "sg:tags":[
        "carpenter"
    ],
    "wof:name":"Brian Schmitt Carpentry",
    "wof:placetype":"venue"
},
  "geometry": {"coordinates":[-87.654082,41.841972],"type":"Point"}
}