{
  "type": "Feature",
  "properties": {
    "addr:full":"6550 S Cottage Grove Ave Chicago IL 60637",
    "addr:housenumber":"6550",
    "addr:postcode":"60637",
    "addr:street":"S Cottage Grove Ave",
    "iso:country":"US",
    "sg:address":"6550 S Cottage Grove Ave",
    "sg:city":"Chicago",
    "sg:classifiers":[
        {
            "category":"Restaurant",
            "type":"Food & Drink"
        }
    ],
    "sg:phone":"+1 773 469 5909",
    "sg:postcode":"60637",
    "sg:province":"IL",
    "sg:tags":[
        "pizza"
    ],
    "wof:name":"Graffiti Pizza",
    "wof:placetype":"venue"
},
  "geometry": {"coordinates":[-87.60582700000001,41.775841],"type":"Point"}
}