{
  "type": "Feature",
  "properties": {
    "addr:full":"931 Cedar Ave Elgin IL 60120",
    "addr:housenumber":"931",
    "addr:postcode":"60120",
    "addr:street":"Cedar Ave",
    "iso:country":"US",
    "sg:address":"931 Cedar Ave",
    "sg:city":"Elgin",
    "sg:classifiers":[
        {
            "category":"Professional",
            "type":"Services"
        }
    ],
    "sg:phone":"+1 847 697 6387",
    "sg:postcode":"60120",
    "sg:province":"IL",
    "sg:tags":[
        "publication",
        "editorial"
    ],
    "wof:name":"Russell Burkhart Editorial",
    "wof:placetype":"venue"
},
  "geometry": {"coordinates":[-88.274207,42.053828],"type":"Point"}
}