{
  "type": "Feature",
  "properties": {
    "iso:country":"US",
    "sg:address":"101 W Main St",
    "sg:city":"Belleville",
    "sg:classifiers":[
        {
            "category":"Social Services",
            "type":"Services"
        },
        {
            "category":"Professional",
            "subcategory":"Lawyer & Legal Services",
            "type":"Services"
        },
        {
            "category":"Banks & Credit Unions",
            "subcategory":"Financial Services",
            "type":"Services"
        }
    ],
    "sg:phone":"+1 618 233 1103",
    "sg:postcode":"62220",
    "sg:province":"IL",
    "sg:tags":[
        "attorney",
        "law",
        "disability",
        "security",
        "bankruptcy"
    ],
    "sg:website":"http://www.dixonandjohnston.com",
    "wof:name":"Dixon & Johnston Attorneys at Law",
    "wof:placetype":"venue"
},
  "geometry": {"coordinates":[-89.985512,38.513592],"type":"Point"}
}