{
  "type": "Feature",
  "properties": {
    "addr:full":"3109 W Armitage Ave Chicago IL 60647",
    "addr:housenumber":"3109",
    "addr:postcode":"60647",
    "addr:street":"W Armitage Ave",
    "iso:country":"US",
    "sg:address":"3109 W Armitage Ave",
    "sg:city":"Chicago",
    "sg:classifiers":[
        {
            "category":"Health Services",
            "subcategory":"Doctor",
            "type":"Services"
        }
    ],
    "sg:phone":"+1 773 384 4933",
    "sg:postcode":"60647",
    "sg:province":"IL",
    "wof:name":"Antillas Family Medical Center",
    "wof:placetype":"venue"
},
  "geometry": {"coordinates":[-87.705071,41.91742],"type":"Point"}
}