{
  "type": "Feature",
  "properties": {
    "iso:country":"US",
    "sg:address":"205 W Wacker Dr",
    "sg:city":"Chicago",
    "sg:classifiers":[
        {
            "category":"Professional",
            "subcategory":"Management & Consulting",
            "type":"Services"
        },
        {
            "category":"Professional",
            "subcategory":"Advertising",
            "type":"Services"
        }
    ],
    "sg:phone":"+1 312 782 9183",
    "sg:postcode":"60606",
    "sg:province":"IL",
    "sg:tags":[
        "marketing",
        "consultant",
        "program",
        "specialty",
        "internet"
    ],
    "sg:website":"http://www.internetmi.com",
    "wof:name":"Internet Marketing Initiative",
    "wof:placetype":"venue"
},
  "geometry": {"coordinates":[-87.634011,41.886768],"type":"Point"}
}