{
  "type": "Feature",
  "properties": {
    "addr:full":"103 S Main St Orangeville IL 61060",
    "addr:housenumber":"103",
    "addr:postcode":"61060",
    "addr:street":"S Main St",
    "iso:country":"US",
    "sg:address":"103 S Main St",
    "sg:city":"Orangeville",
    "sg:classifiers":[
        {
            "category":"Health Services",
            "subcategory":"Doctor",
            "type":"Services"
        }
    ],
    "sg:phone":"+1 815 789 4611",
    "sg:postcode":"61060",
    "sg:province":"IL",
    "sg:tags":[
        "dentist"
    ],
    "wof:name":"Mark J Maly DDS",
    "wof:placetype":"venue"
},
  "geometry": {"coordinates":[-89.64647100000001,42.46862],"type":"Point"}
}