{
  "type": "Feature",
  "properties": {
    "iso:country":"US",
    "sg:address":"420 Lake Cook Rd",
    "sg:city":"Deerfield",
    "sg:classifiers":[
        {
            "category":"Health Services",
            "subcategory":"Clinic",
            "type":"Services"
        }
    ],
    "sg:phone":"+1 847 457 4948",
    "sg:postcode":"60015",
    "sg:province":"IL",
    "sg:tags":[
        "home",
        "senior",
        "citizen",
        "care"
    ],
    "sg:website":"http://www.SRCarePlus.com",
    "wof:name":"Senior Care Plus",
    "wof:placetype":"venue"
},
  "geometry": {"coordinates":[-87.838442,42.15276],"type":"Point"}
}