{
  "type": "Feature",
  "properties": {
    "iso:country":"US",
    "sg:address":"4848 N Kedzie Ave Ofc",
    "sg:city":"Chicago",
    "sg:classifiers":[
        {
            "category":"Real Estate",
            "subcategory":"Real Estate Operator",
            "type":"Services"
        }
    ],
    "sg:phone":"+1 773 478 0085",
    "sg:postcode":"60625",
    "sg:province":"IL",
    "sg:tags":[
        "apartment"
    ],
    "wof:name":"Moogoong Terrace",
    "wof:placetype":"venue"
},
  "geometry": {"coordinates":[-87.708504,41.969299],"type":"Point"}
}