{
  "type": "Feature",
  "properties": {
    "iso:country":"US",
    "sg:address":"523 Brown St",
    "sg:city":"Wauconda",
    "sg:classifiers":[
        {
            "category":"Building & Trades",
            "subcategory":"Construction",
            "type":"Services"
        }
    ],
    "sg:phone":"+1 847 526 3304",
    "sg:postcode":"60084",
    "sg:province":"IL",
    "sg:tags":[
        "utility",
        "contractor"
    ],
    "wof:name":"Town and Country Utilities",
    "wof:placetype":"venue"
},
  "geometry": {"coordinates":[-88.150429,42.268222],"type":"Point"}
}