{
  "type": "Feature",
  "properties": {
    "iso:country":"US",
    "sg:address":"1800 5th St",
    "sg:city":"Lincoln",
    "sg:classifiers":[
        {
            "category":"Organizations",
            "subcategory":"Non-profit Organization",
            "type":"Services"
        }
    ],
    "sg:phone":"+1 217 732 2159",
    "sg:postcode":"62656",
    "sg:province":"IL",
    "wof:name":"Central Illinois Economic Deve",
    "wof:placetype":"venue"
},
  "geometry": {"coordinates":[-89.387324,40.146939],"type":"Point"}
}