{
  "type": "Feature",
  "properties": {
    "iso:country":"US",
    "sg:address":"2137 Euclid Ave",
    "sg:city":"Berwyn",
    "sg:classifiers":[
        {
            "category":"Banks & Credit Unions",
            "subcategory":"Atm",
            "type":"Services"
        }
    ],
    "sg:phone":"+1 708 795 0880",
    "sg:postcode":"60402",
    "sg:province":"IL",
    "sg:tags":[
        "bankruptcy"
    ],
    "wof:name":"Menachof David M Atty",
    "wof:placetype":"venue"
},
  "geometry": {"coordinates":[-87.792,41.8512],"type":"Point"}
}