{
  "type": "Feature",
  "properties": {
    "addr:full":"1310 N Lewis Ave Waukegan IL 60085",
    "addr:housenumber":"1310",
    "addr:postcode":"60085",
    "addr:street":"N Lewis Ave",
    "iso:country":"US",
    "sg:address":"1310 N Lewis Ave",
    "sg:city":"Waukegan",
    "sg:classifiers":[
        {
            "category":"Restaurant",
            "type":"Food & Drink"
        }
    ],
    "sg:phone":"+1   ",
    "sg:postcode":"60085",
    "sg:province":"IL",
    "sg:tags":[
        "eating"
    ],
    "wof:name":"El Ranchito Michoacano",
    "wof:placetype":"venue"
},
  "geometry": {"coordinates":[-87.855518,42.381817],"type":"Point"}
}