{
  "type": "Feature",
  "properties": {
    "iso:country":"US",
    "sg:address":"768 Birginal Dr",
    "sg:city":"Bensenville",
    "sg:classifiers":[
        {
            "category":"Parking",
            "subcategory":"Garage",
            "type":"Transportation"
        }
    ],
    "sg:phone":"+1 630 350 2470",
    "sg:postcode":"60106",
    "sg:province":"IL",
    "sg:tags":[
        "lot"
    ],
    "wof:name":"Ampco",
    "wof:placetype":"venue"
},
  "geometry": {"coordinates":[-87.955628,41.978802],"type":"Point"}
}