{
  "type": "Feature",
  "properties": {
    "iso:country":"US",
    "sg:address":"7531 S Stony Island Ave",
    "sg:city":"Chicago",
    "sg:classifiers":[
        {
            "category":"Health Services",
            "subcategory":"Doctor",
            "type":"Services"
        }
    ],
    "sg:phone":"+1 773 947 7310",
    "sg:postcode":"60649",
    "sg:province":"IL",
    "sg:tags":[
        "physician",
        "surgeon"
    ],
    "wof:name":"Amer Amin Chughtai MD",
    "wof:placetype":"venue"
},
  "geometry": {"coordinates":[-87.586017,41.757063],"type":"Point"}
}