{
  "type": "Feature",
  "properties": {
    "addr:full":"518 Davis St Evanston IL 60201",
    "addr:housenumber":"518",
    "addr:postcode":"60201",
    "addr:street":"Davis St",
    "iso:country":"US",
    "sg:address":"518 Davis St",
    "sg:city":"Evanston",
    "sg:classifiers":[
        {
            "category":"Real Estate",
            "subcategory":"Architect",
            "type":"Services"
        }
    ],
    "sg:phone":"+1 847 332 2782",
    "sg:postcode":"60201",
    "sg:province":"IL",
    "sg:tags":[
        "architectural"
    ],
    "wof:name":"Thomas N Rajkovich Archtecht",
    "wof:placetype":"venue"
},
  "geometry": {"coordinates":[-87.67862700000001,42.045848],"type":"Point"}
}