{
  "type": "Feature",
  "properties": {
    "iso:country":"US",
    "sg:address":"9333 S Baltimore Ave",
    "sg:city":"Chicago",
    "sg:classifiers":[
        {
            "category":"Autos & Motor Vehicles",
            "subcategory":"Automobile Sales",
            "type":"Retail Goods"
        },
        {
            "category":"Autos & Motor Vehicles",
            "subcategory":"Auto Supplies",
            "type":"Retail Goods"
        },
        {
            "category":"Wholesale",
            "subcategory":"Auto Parts",
            "type":"Manufacturing & Wholesale Goods"
        },
        {
            "category":"Retail",
            "subcategory":"Auto Repair",
            "type":"Services"
        }
    ],
    "sg:phone":"+1 773 978 4600",
    "sg:postcode":"60617",
    "sg:province":"IL",
    "sg:tags":[
        "rebuilt-wholesale",
        "supplies-used",
        "rebuilt",
        "salvage",
        "manufacturer"
    ],
    "wof:name":"Juan's Auto Svc",
    "wof:placetype":"venue"
},
  "geometry": {"coordinates":[-87.548383,41.72589],"type":"Point"}
}