{
  "type": "Feature",
  "properties": {
    "addr:full":"652 East Irving Park Road Roselle IL 60172",
    "addr:housenumber":"652",
    "addr:postcode":"60172",
    "addr:street":"East Irving Park Road",
    "iso:country":"US",
    "sg:address":"652 East Irving Park Road",
    "sg:city":"Roselle",
    "sg:classifiers":[
        {
            "category":"Personal",
            "subcategory":"Massage",
            "type":"Services"
        }
    ],
    "sg:phone":"+1 630 671 1866",
    "sg:postcode":"60172",
    "sg:province":"IL",
    "wof:name":"Ling's Massage Therapy, Inc.",
    "wof:placetype":"venue"
},
  "geometry": {"coordinates":[-88.064511,41.980453],"type":"Point"}
}