{
  "type": "Feature",
  "properties": {
    "addr:full":"1001 Ogden Ave Downers Grove IL 60515",
    "addr:housenumber":"1001",
    "addr:postcode":"60515",
    "addr:street":"Ogden Ave",
    "iso:country":"US",
    "sg:address":"1001 Ogden Ave",
    "sg:city":"Downers Grove",
    "sg:classifiers":[
        {
            "category":"Health Services",
            "subcategory":"Health Practitioner",
            "type":"Services"
        }
    ],
    "sg:phone":"+1 630 852 8442",
    "sg:postcode":"60515",
    "sg:province":"IL",
    "sg:tags":[
        "psychologist"
    ],
    "wof:name":"Kirk Alley PHD",
    "wof:placetype":"venue"
},
  "geometry": {"coordinates":[-88.011076,41.808813],"type":"Point"}
}