{
  "type": "Feature",
  "properties": {
    "iso:country":"US",
    "sg:address":"132 W. Church St",
    "sg:city":"Champaign",
    "sg:classifiers":[
        {
            "category":"Professional",
            "type":"Services"
        },
        {
            "category":"Restaurant",
            "type":"Food & Drink"
        }
    ],
    "sg:phone":"+1 217 356 3366",
    "sg:postcode":"61820",
    "sg:province":"IL",
    "sg:tags":[
        "bar",
        "sushi",
        "japanese",
        "asian",
        "caterer",
        "pan"
    ],
    "wof:name":"Sushi Kame",
    "wof:placetype":"venue"
},
  "geometry": {"coordinates":[-88.24408200000001,40.11829],"type":"Point"}
}