{
  "type": "Feature",
  "properties": {
    "iso:country":"US",
    "sg:address":"566 W Russell St",
    "sg:city":"Barrington",
    "sg:classifiers":[
        {
            "category":"Professional",
            "subcategory":"Management & Consulting",
            "type":"Services"
        }
    ],
    "sg:phone":"+1   ",
    "sg:postcode":"60010",
    "sg:province":"IL",
    "sg:tags":[
        "retail",
        "direct",
        "sales"
    ],
    "wof:name":"E P M Inc",
    "wof:placetype":"venue"
},
  "geometry": {"coordinates":[-88.144594,42.150464],"type":"Point"}
}