{
  "type": "Feature",
  "properties": {
    "iso:country":"US",
    "sg:address":"1032 W. Sheridan Rd.",
    "sg:city":"Chicago",
    "sg:classifiers":[
        {
            "category":"Education",
            "subcategory":"University",
            "type":"Public Place"
        }
    ],
    "sg:phone":"+1 800 262 2373",
    "sg:postcode":"60660",
    "sg:province":"IL",
    "sg:tags":[
        "college"
    ],
    "sg:website":"universalbusinesslisting.org/w/1...",
    "wof:name":"Loyola University Chicago",
    "wof:placetype":"venue"
},
  "geometry": {"coordinates":[-87.65701199999999,41.998251],"type":"Point"}
}