{
  "type": "Feature",
  "properties": {
    "iso:country":"US",
    "sg:address":"35002 N Lake Matthews Trl",
    "sg:city":"Ingleside",
    "sg:classifiers":[
        {
            "category":"Professional",
            "subcategory":"Business Services",
            "type":"Services"
        }
    ],
    "sg:phone":"+1 847 587 2095",
    "sg:postcode":"60041",
    "sg:province":"IL",
    "sg:tags":[
        "auctioneer"
    ],
    "wof:name":"Obenauf Auction Svc",
    "wof:placetype":"venue"
},
  "geometry": {"coordinates":[-88.189245,42.37228],"type":"Point"}
}