{
  "type": "Feature",
  "properties": {
    "iso:country":"US",
    "sg:address":"1119 N Dunton Ave",
    "sg:city":"Arlington Heights",
    "sg:classifiers":[
        {
            "category":"Professional",
            "type":"Services"
        }
    ],
    "sg:phone":"+1 847 253 4818",
    "sg:postcode":"60004",
    "sg:province":"IL",
    "wof:name":"Austin Home Servicesinc",
    "wof:placetype":"venue"
},
  "geometry": {"coordinates":[-87.982804,42.098851],"type":"Point"}
}