{
  "type": "Feature",
  "properties": {
    "iso:country":"US",
    "sg:address":"1955 Overlook Ct",
    "sg:city":"Round Lake",
    "sg:classifiers":[
        {
            "category":"Wholesale",
            "subcategory":"Toys & Hobbies",
            "type":"Manufacturing & Wholesale Goods"
        }
    ],
    "sg:phone":"+1 847 255 3934",
    "sg:postcode":"60073",
    "sg:province":"IL",
    "wof:name":"Birkeland Management Corp",
    "wof:placetype":"venue"
},
  "geometry": {"coordinates":[-88.13004100000001,42.355907],"type":"Point"}
}