{
  "type": "Feature",
  "properties": {
    "addr:full":"5503 N 1350th Ave Orion IL 61273",
    "addr:housenumber":"5503",
    "addr:postcode":"61273",
    "addr:street":"N 1350Th Ave",
    "iso:country":"US",
    "sg:address":"5503 N 1350th Ave",
    "sg:city":"Orion",
    "sg:phone":"+1 309 526 3540",
    "sg:postcode":"61273",
    "sg:province":"IL",
    "sg:tags":[
        "hog",
        "farm",
        "corn",
        "soybean",
        "or",
        "feedlot"
    ],
    "wof:name":"Marcus Westerlund",
    "wof:placetype":"venue"
},
  "geometry": {"coordinates":[-90.330361,41.346308],"type":"Point"}
}