{
  "type": "Feature",
  "properties": {
    "addr:full":"331 Ridge Dr Bethalto IL 62010",
    "addr:housenumber":"331",
    "addr:postcode":"62010",
    "addr:street":"Ridge Dr",
    "iso:country":"US",
    "sg:address":"331 Ridge Dr",
    "sg:city":"Bethalto",
    "sg:classifiers":[
        {
            "category":"Organizations",
            "subcategory":"Religious Organization",
            "type":"Services"
        }
    ],
    "sg:phone":"+1 618 377 3312",
    "sg:postcode":"62010",
    "sg:province":"IL",
    "wof:name":"New Wine Fellowship",
    "wof:placetype":"venue"
},
  "geometry": {"coordinates":[-90.019733,38.894838],"type":"Point"}
}