{
  "type": "Feature",
  "properties": {
    "iso:country":"US",
    "sg:address":"111 N Oak St",
    "sg:city":"Centralia",
    "sg:classifiers":[
        {
            "category":"Restaurant",
            "type":"Food & Drink"
        }
    ],
    "sg:menulink":"http://www.allmenus.com/il/centralia/111219-centralia-house/menu/",
    "sg:phone":"+1 618 532 9754",
    "sg:postcode":"62801",
    "sg:province":"IL",
    "sg:tags":[
        "seafood",
        "american"
    ],
    "wof:name":"Centralia House",
    "wof:placetype":"venue"
},
  "geometry": {"coordinates":[-89.135712,38.528101],"type":"Point"}
}