{
  "type": "Feature",
  "properties": {
    "iso:country":"US",
    "sg:address":"2848 N Broadway St",
    "sg:city":"Chicago",
    "sg:classifiers":[
        {
            "category":"Parking",
            "type":"Transportation"
        }
    ],
    "sg:phone":"+1 773 655 7648",
    "sg:postcode":"60657",
    "sg:province":"IL",
    "sg:tags":[
        "automobile"
    ],
    "wof:name":"Standard Parking Corporation",
    "wof:placetype":"venue"
},
  "geometry": {"coordinates":[-87.64438,41.934173],"type":"Point"}
}