{
  "type": "Feature",
  "properties": {
    "iso:country":"US",
    "sg:address":"1530 6th Ave",
    "sg:city":"Moline",
    "sg:classifiers":[
        {
            "category":"Personal",
            "subcategory":"Beauty Salon",
            "type":"Services"
        }
    ],
    "sg:phone":"+1 309 764 3132",
    "sg:postcode":"61265",
    "sg:province":"IL",
    "sg:tags":[
        "shop"
    ],
    "wof:name":"Car Nan's Hair Designers",
    "wof:placetype":"venue"
},
  "geometry": {"coordinates":[-90.514724,41.50553],"type":"Point"}
}