{
  "type": "Feature",
  "properties": {
    "addr:full":"285 Peterson Rd Libertyville IL 60048",
    "addr:housenumber":"285",
    "addr:postcode":"60048",
    "addr:street":"Peterson Rd",
    "iso:country":"US",
    "sg:address":"285 Peterson Rd",
    "sg:city":"Libertyville",
    "sg:classifiers":[
        {
            "category":"Personal",
            "subcategory":"Beauty Salon",
            "type":"Services"
        }
    ],
    "sg:phone":"+1 847 367 7866",
    "sg:postcode":"60048",
    "sg:province":"IL",
    "sg:tags":[
        "shop"
    ],
    "wof:name":"A C Hair Design",
    "wof:placetype":"venue"
},
  "geometry": {"coordinates":[-87.966869,42.305927],"type":"Point"}
}