{
  "type": "Feature",
  "properties": {
    "addr:full":"831 Locust St Carthage IL 62321",
    "addr:housenumber":"831",
    "addr:postcode":"62321",
    "addr:street":"Locust St",
    "iso:country":"US",
    "sg:address":"831 Locust St",
    "sg:city":"Carthage",
    "sg:phone":"+1 217 357 3449",
    "sg:postcode":"62321",
    "sg:province":"IL",
    "sg:tags":[
        "farm",
        "corn"
    ],
    "wof:name":"Donald Mc Gaughey",
    "wof:placetype":"venue"
},
  "geometry": {"coordinates":[-91.130112,40.409741],"type":"Point"}
}