{
  "type": "Feature",
  "properties": {
    "iso:country":"US",
    "sg:address":"27491 N 1000 E Rd",
    "sg:city":"Cornell",
    "sg:classifiers":[
        {
            "category":"Building & Trades",
            "subcategory":"Construction",
            "type":"Services"
        }
    ],
    "sg:phone":"+1 815 358 2646",
    "sg:postcode":"61319",
    "sg:province":"IL",
    "sg:tags":[
        "woodworker"
    ],
    "wof:name":"Bennett Woodworking",
    "wof:placetype":"venue"
},
  "geometry": {"coordinates":[-88.738675,41.022614],"type":"Point"}
}