{
  "type": "Feature",
  "properties": {
    "iso:country":"US",
    "sg:address":"1560 Burnham Ave",
    "sg:city":"Calumet City",
    "sg:classifiers":[
        {
            "category":"Restaurant",
            "type":"Food & Drink"
        }
    ],
    "sg:phone":"+1 708 868 3532",
    "sg:postcode":"60409",
    "sg:province":"IL",
    "wof:name":"Chef's Table",
    "wof:placetype":"venue"
},
  "geometry": {"coordinates":[-87.539528,41.58693],"type":"Point"}
}