{
  "type": "Feature",
  "properties": {
    "iso:country":"US",
    "sg:address":"517 S Maplewood Dr",
    "sg:city":"Rantoul",
    "sg:classifiers":[
        {
            "category":"Retail",
            "subcategory":"Auto Repair",
            "type":"Services"
        }
    ],
    "sg:phone":"+1 217 892 0572",
    "sg:postcode":"61866",
    "sg:province":"IL",
    "sg:tags":[
        "windshield"
    ],
    "sg:website":"http://www.yext.com/p/superpages/american-eagle-auto-glass-rantoul-illinois.html",
    "wof:name":"American Eagle Auto Glass",
    "wof:placetype":"venue"
},
  "geometry": {"coordinates":[-88.136464,40.307288],"type":"Point"}
}