{
  "type": "Feature",
  "properties": {
    "iso:country":"US",
    "sg:address":"2913 W 63rd St",
    "sg:city":"Chicago",
    "sg:classifiers":[
        {
            "category":"Personal",
            "subcategory":"Massage",
            "type":"Services"
        },
        {
            "category":"Health Services",
            "subcategory":"Clinic",
            "type":"Services"
        },
        {
            "category":"Health Services",
            "subcategory":"Health Practitioner",
            "type":"Services"
        }
    ],
    "sg:phone":"+1 773 778 7137",
    "sg:postcode":"60629",
    "sg:province":"IL",
    "sg:tags":[
        "therapist",
        "therapy",
        "physical"
    ],
    "wof:name":"World Gem Mely",
    "wof:placetype":"venue"
},
  "geometry": {"coordinates":[-87.69635,41.779083],"type":"Point"}
}