{
  "type": "Feature",
  "properties": {
    "iso:country":"US",
    "sg:address":"639 38th St",
    "sg:city":"Rock Island",
    "sg:classifiers":[
        {
            "category":"Arts & Performance",
            "subcategory":"Theater",
            "type":"Entertainment"
        }
    ],
    "sg:phone":"+1 309 794 7233",
    "sg:postcode":"61201",
    "sg:province":"IL",
    "sg:tags":[
        "group"
    ],
    "wof:name":"Depart Music/Augustana College",
    "wof:placetype":"venue"
},
  "geometry": {"coordinates":[-90.547559,41.505325],"type":"Point"}
}