{
  "type": "Feature",
  "properties": {
    "addr:full":"230 Saint Clair Sq Fairview Heights IL 62208",
    "addr:housenumber":"230",
    "addr:postcode":"62208",
    "addr:street":"Saint Clair Sq",
    "iso:country":"US",
    "sg:address":"230 Saint Clair Sq",
    "sg:city":"Fairview Heights",
    "sg:classifiers":[
        {
            "category":"Shopping",
            "subcategory":"Clothing, Apparel, & Fashions",
            "type":"Retail Goods"
        }
    ],
    "sg:phone":"+1 618 628 6948",
    "sg:postcode":"62208",
    "sg:province":"IL",
    "sg:tags":[
        "children's",
        "clothing"
    ],
    "sg:website":"www.childrensplace.com",
    "wof:name":"Children's Place the",
    "wof:placetype":"venue"
},
  "geometry": {"coordinates":[-89.982399,38.5938],"type":"Point"}
}