{
  "type": "Feature",
  "properties": {
    "iso:country":"US",
    "sg:address":"704 N Green Mount Rd",
    "sg:city":"Belleville",
    "sg:classifiers":[
        {
            "category":"Organizations",
            "subcategory":"Religious Organization",
            "type":"Services"
        }
    ],
    "sg:phone":"+1 618 277 0232",
    "sg:postcode":"62221",
    "sg:province":"IL",
    "sg:tags":[
        "church"
    ],
    "wof:name":"Faith Family Church",
    "wof:placetype":"venue"
},
  "geometry": {"coordinates":[-89.92891299999999,38.548478],"type":"Point"}
}