{
  "type": "Feature",
  "properties": {
    "iso:country":"US",
    "sg:address":"755 W. North Ave. #103",
    "sg:city":"Chicago",
    "sg:classifiers":[
        {
            "category":"Home & Garden",
            "subcategory":"Home Furnishings",
            "type":"Retail Goods"
        },
        {
            "category":"Home & Garden",
            "subcategory":"Kitchen Supply",
            "type":"Retail Goods"
        }
    ],
    "sg:phone":"+1 312 787 5111",
    "sg:postcode":"60610",
    "sg:province":"IL",
    "sg:tags":[
        "utensil",
        "cookware",
        "linen",
        "accessory",
        "bath"
    ],
    "sg:website":"www.surlatable.com",
    "wof:name":"Sur La Table",
    "wof:placetype":"venue"
},
  "geometry": {"coordinates":[-87.647102,41.910801],"type":"Point"}
}