{
  "type": "Feature",
  "properties": {
    "addr:full":"447 E. 111th St Chicago IL 60628",
    "addr:housenumber":"447",
    "addr:postcode":"60628",
    "addr:street":"E. 111Th St",
    "iso:country":"US",
    "sg:address":"447 E. 111th St",
    "sg:city":"Chicago",
    "sg:classifiers":[
        {
            "category":"Health Services",
            "subcategory":"Clinic",
            "type":"Services"
        }
    ],
    "sg:phone":"+1 773 928 2908",
    "sg:postcode":"60628",
    "sg:province":"IL",
    "sg:tags":[
        "counseling",
        "mental"
    ],
    "sg:website":"www.ExceptionalProfessionals.com",
    "wof:name":"Exceptional Professionals Inc.",
    "wof:placetype":"venue"
},
  "geometry": {"coordinates":[-87.61145,41.692433],"type":"Point"}
}