{
  "type": "Feature",
  "properties": {
    "iso:country":"US",
    "sg:address":"220 N Randall Rd",
    "sg:city":"Batavia",
    "sg:classifiers":[
        {
            "category":"Restaurant",
            "type":"Food & Drink"
        }
    ],
    "sg:phone":"+1 630 761 3633",
    "sg:postcode":"60510",
    "sg:province":"IL",
    "sg:website":"www.fazolis.com",
    "wof:name":"Fazoli's",
    "wof:placetype":"venue"
},
  "geometry": {"coordinates":[-88.340393,41.854501],"type":"Point"}
}