{
  "type": "Feature",
  "properties": {
    "iso:country":"US",
    "sg:address":"3628 Torrey Pines Pkwy",
    "sg:city":"Northbrook",
    "sg:classifiers":[
        {
            "category":"Building & Trades",
            "subcategory":"Construction",
            "type":"Services"
        }
    ],
    "sg:phone":"+1 847 564 0901",
    "sg:postcode":"60062",
    "sg:province":"IL",
    "sg:tags":[
        "house"
    ],
    "wof:name":"Mosghan & Associates Inc",
    "wof:placetype":"venue"
},
  "geometry": {"coordinates":[-87.868492,42.135919],"type":"Point"}
}