{
  "type": "Feature",
  "properties": {
    "addr:full":"21 E Kenyon Rd Champaign IL 61820",
    "addr:housenumber":"21",
    "addr:postcode":"61820",
    "addr:street":"E Kenyon Rd",
    "iso:country":"US",
    "sg:address":"21 E Kenyon Rd",
    "sg:city":"Champaign",
    "sg:classifiers":[
        {
            "category":"Restaurant",
            "type":"Food & Drink"
        }
    ],
    "sg:phone":"+1 217 366 3210",
    "sg:postcode":"61820",
    "sg:province":"IL",
    "wof:name":"Oakleys",
    "wof:placetype":"venue"
},
  "geometry": {"coordinates":[-88.2435,40.132702],"type":"Point"}
}