{
  "type": "Feature",
  "properties": {
    "iso:country":"US",
    "sg:address":"95 Trade St",
    "sg:city":"Aurora",
    "sg:classifiers":[
        {
            "category":"Health Services",
            "subcategory":"Health Practitioner",
            "type":"Services"
        }
    ],
    "sg:phone":"+1 630 854 7084",
    "sg:postcode":"60504",
    "sg:province":"IL",
    "sg:tags":[
        "acupuncture"
    ],
    "wof:name":"Acupuncture & Massage By Dr Li",
    "wof:placetype":"venue"
},
  "geometry": {"coordinates":[-88.209921,41.75288],"type":"Point"}
}