{
  "type": "Feature",
  "properties": {
    "iso:country":"US",
    "sg:address":"609 1st St",
    "sg:city":"Keyesport",
    "sg:classifiers":[
        {
            "category":"Building & Trades",
            "subcategory":"Plumbing",
            "type":"Services"
        }
    ],
    "sg:phone":"+1 618 749 5900",
    "sg:postcode":"62253",
    "sg:province":"IL",
    "sg:tags":[
        "sewer",
        "cleaning",
        "drain"
    ],
    "wof:name":"Bill's Sewer & Drain Svc",
    "wof:placetype":"venue"
},
  "geometry": {"coordinates":[-89.27869,38.740817],"type":"Point"}
}