{
  "type": "Feature",
  "properties": {
    "addr:full":"1204 E 53rd Street Chicago IL 60615",
    "addr:housenumber":"1204",
    "addr:postcode":"60615",
    "addr:street":"E 53Rd Street",
    "iso:country":"US",
    "sg:address":"1204 E 53rd Street",
    "sg:city":"Chicago",
    "sg:classifiers":[
        {
            "category":"Banks & Credit Unions",
            "subcategory":"Bank",
            "type":"Services"
        }
    ],
    "sg:phone":"+1 773 241 5110",
    "sg:postcode":"60615",
    "sg:province":"IL",
    "wof:name":"Chase",
    "wof:placetype":"venue"
},
  "geometry": {"coordinates":[-87.59637499999999,41.799266],"type":"Point"}
}