{
  "type": "Feature",
  "properties": {
    "addr:full":"3637 Whittier Ln Danville IL 61832",
    "addr:housenumber":"3637",
    "addr:postcode":"61832",
    "addr:street":"Whittier Ln",
    "iso:country":"US",
    "sg:address":"3637 Whittier Ln",
    "sg:city":"Danville",
    "sg:classifiers":[
        {
            "category":"Personal",
            "subcategory":"Barber",
            "type":"Services"
        }
    ],
    "sg:phone":"+1 217 442 0645",
    "sg:postcode":"61832",
    "sg:province":"IL",
    "sg:tags":[
        "shop",
        "beauty"
    ],
    "wof:name":"Bos Place",
    "wof:placetype":"venue"
},
  "geometry": {"coordinates":[-87.634682,40.188774],"type":"Point"}
}