{
  "type": "Feature",
  "properties": {
    "iso:country":"US",
    "sg:address":"2413 183rd St",
    "sg:city":"Homewood",
    "sg:classifiers":[
        {
            "category":"Sports & Exercise",
            "subcategory":"Gym",
            "type":"Entertainment"
        }
    ],
    "sg:phone":"+1 708 957 4770",
    "sg:postcode":"60430",
    "sg:province":"IL",
    "sg:tags":[
        "fitness",
        "physical",
        "facility"
    ],
    "wof:name":"Sweat Equity Ltd",
    "wof:placetype":"venue"
},
  "geometry": {"coordinates":[-87.675752,41.557129],"type":"Point"}
}