{
  "type": "Feature",
  "properties": {
    "iso:country":"US",
    "sg:address":"500 Capitol Way",
    "sg:city":"Jacksonville",
    "sg:classifiers":[
        {
            "category":"Wholesale",
            "subcategory":"Durable Goods & Equipment",
            "type":"Manufacturing & Wholesale Goods"
        }
    ],
    "sg:phone":"+1 217 243 8661",
    "sg:postcode":"62650",
    "sg:province":"IL",
    "wof:name":"Capitol-EMI Music Inc",
    "wof:placetype":"venue"
},
  "geometry": {"coordinates":[-90.271344,39.73768],"type":"Point"}
}