{
  "type": "Feature",
  "properties": {
    "iso:country":"US",
    "sg:address":"754 Essington Rd",
    "sg:city":"Joliet",
    "sg:classifiers":[
        {
            "category":"Health Services",
            "subcategory":"Medical Lab",
            "type":"Services"
        }
    ],
    "sg:phone":"+1 815 741 4100",
    "sg:postcode":"60435",
    "sg:province":"IL",
    "sg:tags":[
        "resonance",
        "magnetic",
        "imaging"
    ],
    "wof:name":"Joliet Open MRI",
    "wof:placetype":"venue"
},
  "geometry": {"coordinates":[-88.160462,41.53467],"type":"Point"}
}