{
  "type": "Feature",
  "properties": {
    "addr:full":"801 S State St Chicago IL 60605",
    "addr:housenumber":"801",
    "addr:postcode":"60605",
    "addr:street":"S State St",
    "iso:country":"US",
    "sg:address":"801 S State St",
    "sg:city":"Chicago",
    "sg:classifiers":[
        {
            "category":"Shopping",
            "subcategory":"Clothing, Apparel, & Fashions",
            "type":"Retail Goods"
        }
    ],
    "sg:phone":"+1 773 598 5507",
    "sg:postcode":"60605",
    "sg:province":"IL",
    "sg:tags":[
        "costume"
    ],
    "sg:website":"www.halloweenhallway.com",
    "wof:name":"Halloween Hallway",
    "wof:placetype":"venue"
},
  "geometry": {"coordinates":[-87.627402,41.870596],"type":"Point"}
}