{
  "type": "Feature",
  "properties": {
    "addr:full":"6124 N Milwaukee Ave Chicago IL 60646",
    "addr:housenumber":"6124",
    "addr:postcode":"60646",
    "addr:street":"N Milwaukee Ave",
    "iso:country":"US",
    "sg:address":"6124 N Milwaukee Ave",
    "sg:city":"Chicago",
    "sg:classifiers":[
        {
            "category":"Manufacturing",
            "subcategory":"Tools & Machinery",
            "type":"Manufacturing & Wholesale Goods"
        }
    ],
    "sg:phone":"+1 773 505 9191",
    "sg:postcode":"60646",
    "sg:province":"IL",
    "sg:tags":[
        "dentist",
        "prosthetics",
        "for",
        "mfg"
    ],
    "wof:name":"Northwest Dental Prosthetics",
    "wof:placetype":"venue"
},
  "geometry": {"coordinates":[-87.78316599999999,41.992284],"type":"Point"}
}