{
  "type": "Feature",
  "properties": {
    "iso:country":"US",
    "sg:address":"418 W Wilmot St",
    "sg:city":"Chillicothe",
    "sg:classifiers":[
        {
            "category":"Organizations",
            "subcategory":"Religious Organization",
            "type":"Services"
        }
    ],
    "sg:phone":"+1 309 274 5420",
    "sg:postcode":"61523",
    "sg:province":"IL",
    "sg:tags":[
        "church"
    ],
    "wof:name":"Jehovah's Witnesses",
    "wof:placetype":"venue"
},
  "geometry": {"coordinates":[-89.486515,40.928125],"type":"Point"}
}