{
  "type": "Feature",
  "properties": {
    "addr:full":"2700 Village Green Dr Aurora IL 60504",
    "addr:housenumber":"2700",
    "addr:postcode":"60504",
    "addr:street":"Village Green Dr",
    "iso:country":"US",
    "sg:address":"2700 Village Green Dr",
    "sg:city":"Aurora",
    "sg:classifiers":[
        {
            "category":"Real Estate",
            "subcategory":"Real Estate Operator",
            "type":"Services"
        }
    ],
    "sg:phone":"+1 630 851 6464",
    "sg:postcode":"60504",
    "sg:province":"IL",
    "sg:tags":[
        "building",
        "apartment"
    ],
    "wof:name":"Fox Valley Villages Apts",
    "wof:placetype":"venue"
},
  "geometry": {"coordinates":[-88.244787,41.74239],"type":"Point"}
}