{
  "type": "Feature",
  "properties": {
    "addr:full":"1559 Kirkwood Dr Geneva IL 60134",
    "addr:housenumber":"1559",
    "addr:postcode":"60134",
    "addr:street":"Kirkwood Dr",
    "iso:country":"US",
    "sg:address":"1559 Kirkwood Dr",
    "sg:city":"Geneva",
    "sg:classifiers":[
        {
            "category":"Wholesale",
            "subcategory":"Machinery & Supplies",
            "type":"Manufacturing & Wholesale Goods"
        }
    ],
    "sg:phone":"+1 630 845 2664",
    "sg:postcode":"60134",
    "sg:province":"IL",
    "sg:tags":[
        "equipment",
        "welding"
    ],
    "wof:name":"Midwest Polymer Extrusion Equi",
    "wof:placetype":"venue"
},
  "geometry": {"coordinates":[-88.280169,41.892118],"type":"Point"}
}