{
  "type": "Feature",
  "properties": {
    "iso:country":"US",
    "sg:address":"3920 W Armitage Ave",
    "sg:city":"Chicago",
    "sg:classifiers":[
        {
            "category":"Manufacturing",
            "subcategory":"Metals",
            "type":"Manufacturing & Wholesale Goods"
        }
    ],
    "sg:phone":"+1 773 227 6200",
    "sg:postcode":"60647",
    "sg:province":"IL",
    "sg:tags":[
        "metalwork",
        "architectural"
    ],
    "wof:name":"Windy Cy Met Fabricators & Sup",
    "wof:placetype":"venue"
},
  "geometry": {"coordinates":[-87.725094,41.91726],"type":"Point"}
}