{
  "type": "Feature",
  "properties": {
    "addr:full":"1920 Cheshire Ln Wheaton IL 60187",
    "addr:housenumber":"1920",
    "addr:postcode":"60187",
    "addr:street":"Cheshire Ln",
    "iso:country":"US",
    "sg:address":"1920 Cheshire Ln",
    "sg:city":"Wheaton",
    "sg:classifiers":[
        {
            "category":"Retail",
            "subcategory":"Funeral Services",
            "type":"Services"
        }
    ],
    "sg:phone":"+1 630 665 8689",
    "sg:postcode":"60187",
    "sg:province":"IL",
    "wof:name":"Alex M Carbonara Funeral Dirs",
    "wof:placetype":"venue"
},
  "geometry": {"coordinates":[-88.083713,41.834214],"type":"Point"}
}