{
  "type": "Feature",
  "properties": {
    "addr:full":"School of Art and Design, Krannert Art Museum 408 E. Peabody Dr Champaign IL 61821",
    "addr:housenumber":"408",
    "addr:postcode":"61821",
    "addr:street":"E. Peabody Dr",
    "iso:country":"US",
    "sg:address":"School of Art and Design, Krannert Art Museum 408 E. Peabody Dr",
    "sg:city":"Champaign",
    "sg:classifiers":[
        {
            "category":"Education",
            "subcategory":"Special Training",
            "type":"Public Place"
        }
    ],
    "sg:phone":"+1 217 333 0855",
    "sg:postcode":"61821",
    "sg:province":"IL",
    "sg:tags":[
        "school",
        "specialty"
    ],
    "sg:website":"www.art.uiuc.edu/groups/satschoo...",
    "wof:name":"Saturday Art School",
    "wof:placetype":"venue"
},
  "geometry": {"coordinates":[-88.233256,40.101478],"type":"Point"}
}