{
  "type": "Feature",
  "properties": {
    "iso:country":"US",
    "sg:address":"2402 N Lincoln Avenue",
    "sg:city":"Chicago",
    "sg:classifiers":[
        {
            "category":"Real Estate",
            "subcategory":"Real Estate Operator",
            "type":"Services"
        }
    ],
    "sg:phone":"+1 773 871 7368",
    "sg:postcode":"60614",
    "sg:province":"IL",
    "sg:tags":[
        "apartment"
    ],
    "wof:name":"Apartment Zone",
    "wof:placetype":"venue"
},
  "geometry": {"coordinates":[-87.64892,41.925715],"type":"Point"}
}