{
  "type": "Feature",
  "properties": {
    "addr:full":"210 E Lincoln Ave Leland IL 60531",
    "addr:housenumber":"210",
    "addr:postcode":"60531",
    "addr:street":"E Lincoln Ave",
    "iso:country":"US",
    "sg:address":"210 E Lincoln Ave",
    "sg:city":"Leland",
    "sg:classifiers":[
        {
            "category":"Manufacturing",
            "subcategory":"Metals",
            "type":"Manufacturing & Wholesale Goods"
        }
    ],
    "sg:phone":"+1 815 495 9227",
    "sg:postcode":"60531",
    "sg:province":"IL",
    "sg:tags":[
        "machine",
        "screw",
        "product"
    ],
    "wof:name":"Calcon Machine Inc",
    "wof:placetype":"venue"
},
  "geometry": {"coordinates":[-88.797483,41.609482],"type":"Point"}
}