{
  "type": "Feature",
  "properties": {
    "iso:country":"US",
    "sg:address":"223 W Main St",
    "sg:city":"Collinsville",
    "sg:classifiers":[
        {
            "category":"Professional",
            "subcategory":"Computer Services",
            "type":"Services"
        }
    ],
    "sg:phone":"+1 618 344 7912",
    "sg:postcode":"62234",
    "sg:province":"IL",
    "sg:tags":[
        "repair"
    ],
    "sg:website":"www.computer-service.com",
    "wof:name":"Computerease",
    "wof:placetype":"venue"
},
  "geometry": {"coordinates":[-89.988297,38.669201],"type":"Point"}
}