{
  "type": "Feature",
  "properties": {
    "iso:country":"US",
    "sg:address":"441 N Marion St",
    "sg:city":"Centralia",
    "sg:classifiers":[
        {
            "category":"Shopping",
            "subcategory":"Florist",
            "type":"Retail Goods"
        }
    ],
    "sg:phone":"+1 618 532 9451",
    "sg:postcode":"62801",
    "sg:province":"IL",
    "wof:name":"Hutchison Greenhouse Florist",
    "wof:placetype":"venue"
},
  "geometry": {"coordinates":[-89.131227,38.554003],"type":"Point"}
}