{
  "type": "Feature",
  "properties": {
    "iso:country":"US",
    "sg:address":"21560 Hampshire Pl",
    "sg:city":"Mundelein",
    "sg:classifiers":[
        {
            "category":"Professional",
            "subcategory":"Research",
            "type":"Services"
        }
    ],
    "sg:phone":"+1 847 566 3330",
    "sg:postcode":"60060",
    "sg:province":"IL",
    "sg:tags":[
        "organization",
        "noncommercial"
    ],
    "wof:name":"Medical Research Group Inc",
    "wof:placetype":"venue"
},
  "geometry": {"coordinates":[-88.053639,42.247031],"type":"Point"}
}