{
  "type": "Feature",
  "properties": {
    "addr:full":"513 Bornman St Belleville IL 62220",
    "addr:housenumber":"513",
    "addr:postcode":"62220",
    "addr:street":"Bornman St",
    "iso:country":"US",
    "sg:address":"513 Bornman St",
    "sg:city":"Belleville",
    "sg:classifiers":[
        {
            "category":"Building & Trades",
            "subcategory":"Construction",
            "type":"Services"
        }
    ],
    "sg:phone":"+1 618 234 0397",
    "sg:postcode":"62220",
    "sg:province":"IL",
    "sg:tags":[
        "siding",
        "contractor"
    ],
    "wof:name":"Gateway Exteriors",
    "wof:placetype":"venue"
},
  "geometry": {"coordinates":[-89.993352,38.508016],"type":"Point"}
}