{
  "type": "Feature",
  "properties": {
    "addr:full":"4840 W North Ave Chicago IL 60639",
    "addr:housenumber":"4840",
    "addr:postcode":"60639",
    "addr:street":"W North Ave",
    "iso:country":"US",
    "sg:address":"4840 W North Ave",
    "sg:city":"Chicago",
    "sg:classifiers":[
        {
            "category":"Professional",
            "subcategory":"Art Services",
            "type":"Services"
        }
    ],
    "sg:phone":"+1 773 237 7755",
    "sg:postcode":"60639",
    "sg:province":"IL",
    "sg:tags":[
        "ornamental",
        "work",
        "metal"
    ],
    "wof:name":"Brass Creations Inc",
    "wof:placetype":"venue"
},
  "geometry": {"coordinates":[-87.74738600000001,41.909607],"type":"Point"}
}