{
  "type": "Feature",
  "properties": {
    "iso:country":"US",
    "sg:address":"519 E Green St",
    "sg:city":"Champaign",
    "sg:classifiers":[
        {
            "category":"Sports & Exercise",
            "subcategory":"Bicycle Rental",
            "type":"Entertainment"
        }
    ],
    "sg:phone":"+1 217 328 7722",
    "sg:postcode":"61820",
    "sg:province":"IL",
    "sg:tags":[
        "wear"
    ],
    "wof:name":"Gameday Sports",
    "wof:placetype":"venue"
},
  "geometry": {"coordinates":[-88.230904,40.1105],"type":"Point"}
}