{
  "type": "Feature",
  "properties": {
    "iso:country":"US",
    "sg:address":"6240 Belmont Rd",
    "sg:city":"Downers Grove",
    "sg:classifiers":[
        {
            "category":"Shopping",
            "subcategory":"Pharmacy",
            "type":"Retail Goods"
        }
    ],
    "sg:phone":"+1   ",
    "sg:postcode":"60516",
    "sg:province":"IL",
    "sg:tags":[
        "store"
    ],
    "wof:name":"Walgreens",
    "wof:placetype":"venue"
},
  "geometry": {"coordinates":[-88.036761,41.772869],"type":"Point"}
}