{
  "type": "Feature",
  "properties": {
    "iso:country":"US",
    "sg:address":"9680 Lyman Rd",
    "sg:city":"Erie",
    "sg:classifiers":[
        {
            "category":"Building & Trades",
            "subcategory":"Construction",
            "type":"Services"
        }
    ],
    "sg:phone":"+1 309 659 2022",
    "sg:postcode":"61250",
    "sg:province":"IL",
    "sg:tags":[
        "house"
    ],
    "wof:name":"Stichter Construction Inc",
    "wof:placetype":"venue"
},
  "geometry": {"coordinates":[-90.067036,41.618875],"type":"Point"}
}