{
  "type": "Feature",
  "properties": {
    "iso:country":"US",
    "sg:address":"8490 Forest Blvd",
    "sg:city":"Caseyville",
    "sg:classifiers":[
        {
            "category":"Farming",
            "subcategory":"Farm",
            "type":"Manufacturing & Wholesale Goods"
        }
    ],
    "sg:phone":"+1 618 398 1001",
    "sg:postcode":"62232",
    "sg:province":"IL",
    "wof:name":"Bluff View Farm",
    "wof:placetype":"venue"
},
  "geometry": {"coordinates":[-90.048433,38.636686],"type":"Point"}
}