{
  "type": "Feature",
  "properties": {
    "addr:full":"724 S 6th St Rockford IL 61104",
    "addr:housenumber":"724",
    "addr:postcode":"61104",
    "addr:street":"S 6Th St",
    "iso:country":"US",
    "sg:address":"724 S 6th St",
    "sg:city":"Rockford",
    "sg:classifiers":[
        {
            "category":"Building & Trades",
            "subcategory":"Construction",
            "type":"Services"
        }
    ],
    "sg:phone":"+1 815 233 1077",
    "sg:postcode":"61104",
    "sg:province":"IL",
    "sg:tags":[
        "roofing",
        "contractor"
    ],
    "wof:name":"A Roofing",
    "wof:placetype":"venue"
},
  "geometry": {"coordinates":[-89.082221,42.259552],"type":"Point"}
}