{
  "type": "Feature",
  "properties": {
    "addr:full":"30 E Belmont Dr Romeoville IL 60446",
    "addr:housenumber":"30",
    "addr:postcode":"60446",
    "addr:street":"E Belmont Dr",
    "iso:country":"US",
    "sg:address":"30 E Belmont Dr",
    "sg:city":"Romeoville",
    "sg:classifiers":[
        {
            "category":"Wholesale",
            "subcategory":"Machinery & Supplies",
            "type":"Manufacturing & Wholesale Goods"
        }
    ],
    "sg:phone":"+1 815 886 0982",
    "sg:postcode":"60446",
    "sg:province":"IL",
    "sg:tags":[
        "contractor"
    ],
    "wof:name":"Mc Carty Brothers Inc",
    "wof:placetype":"venue"
},
  "geometry": {"coordinates":[-88.078188,41.647575],"type":"Point"}
}