{
  "type": "Feature",
  "properties": {
    "iso:country":"US",
    "sg:address":"3511 N Ravenswood Ave",
    "sg:city":"Chicago",
    "sg:classifiers":[
        {
            "category":"Building & Trades",
            "subcategory":"Construction",
            "type":"Services"
        }
    ],
    "sg:phone":"+1 773 880 0431",
    "sg:postcode":"60657",
    "sg:province":"IL",
    "sg:tags":[
        "excavation",
        "contractor"
    ],
    "wof:name":"Taylor Excavating",
    "wof:placetype":"venue"
},
  "geometry": {"coordinates":[-87.67359999999999,41.945178],"type":"Point"}
}