{
  "type": "Feature",
  "properties": {
    "iso:country":"US",
    "sg:address":"2800 Broadway St",
    "sg:city":"Blue Island",
    "sg:classifiers":[
        {
            "category":"Real Estate",
            "subcategory":"Real Estate Operator",
            "type":"Services"
        }
    ],
    "sg:phone":"+1 708 385 5542",
    "sg:postcode":"60406",
    "sg:province":"IL",
    "sg:tags":[
        "mobile",
        "home",
        "community"
    ],
    "wof:name":"Broadway Estates",
    "wof:placetype":"venue"
},
  "geometry": {"coordinates":[-87.688081,41.650128],"type":"Point"}
}