{
  "type": "Feature",
  "properties": {
    "iso:country":"US",
    "sg:address":"500 Forest Ave",
    "sg:city":"River Forest",
    "sg:classifiers":[
        {
            "category":"Professional",
            "subcategory":"Employment Agencies",
            "type":"Services"
        }
    ],
    "sg:phone":"+1 708 366 2161",
    "sg:postcode":"60305",
    "sg:province":"IL",
    "sg:tags":[
        "opportunity"
    ],
    "wof:name":"Chicago Nannies Inc",
    "wof:placetype":"venue"
},
  "geometry": {"coordinates":[-87.821816,41.891816],"type":"Point"}
}