{
  "type": "Feature",
  "properties": {
    "addr:full":"4660 N Broadway St Chicago IL 60640",
    "addr:housenumber":"4660",
    "addr:postcode":"60640",
    "addr:street":"N Broadway St",
    "iso:country":"US",
    "sg:address":"4660 N Broadway St",
    "sg:city":"Chicago",
    "sg:classifiers":[
        {
            "category":"Personal",
            "subcategory":"Beauty Salon",
            "type":"Services"
        }
    ],
    "sg:phone":"+1 773 561 8236",
    "sg:postcode":"60640",
    "sg:province":"IL",
    "sg:tags":[
        "shop"
    ],
    "wof:name":"Adele A Braidi",
    "wof:placetype":"venue"
},
  "geometry": {"coordinates":[-87.65863299999999,41.967212],"type":"Point"}
}