{
  "type": "Feature",
  "properties": {
    "addr:full":"27826 W Belden Ave Spring Grove IL 60081",
    "addr:housenumber":"27826",
    "addr:postcode":"60081",
    "addr:street":"W Belden Ave",
    "iso:country":"US",
    "sg:address":"27826 W Belden Ave",
    "sg:city":"Spring Grove",
    "sg:classifiers":[
        {
            "category":"Professional",
            "subcategory":"Business Services",
            "type":"Services"
        }
    ],
    "sg:phone":"+1 847 973 1641",
    "sg:postcode":"60081",
    "sg:province":"IL",
    "wof:name":"Davis Drafting Service",
    "wof:placetype":"venue"
},
  "geometry": {"coordinates":[-88.175197,42.419159],"type":"Point"}
}