{
  "type": "Feature",
  "properties": {
    "addr:full":"7801 E State St Rockford IL 61108",
    "addr:housenumber":"7801",
    "addr:postcode":"61108",
    "addr:street":"E State St",
    "iso:country":"US",
    "sg:address":"7801 E State St",
    "sg:city":"Rockford",
    "sg:classifiers":[
        {
            "category":"Sports & Exercise",
            "subcategory":"Gym",
            "type":"Entertainment"
        }
    ],
    "sg:phone":"+1 815 398 6177",
    "sg:postcode":"61108",
    "sg:province":"IL",
    "sg:tags":[
        "club",
        "health",
        "studio",
        "gymnasium"
    ],
    "wof:name":"Clock Tower Racquet Club",
    "wof:placetype":"venue"
},
  "geometry": {"coordinates":[-88.96467,42.271126],"type":"Point"}
}