{
  "type": "Feature",
  "properties": {
    "iso:country":"US",
    "sg:address":"5729 S Archer Ave",
    "sg:city":"Chicago",
    "sg:classifiers":[
        {
            "category":"Professional",
            "subcategory":"Printing & Photocopies",
            "type":"Services"
        }
    ],
    "sg:phone":"+1 773 767 7776",
    "sg:postcode":"60638",
    "sg:province":"IL",
    "wof:name":"J & J Printing Inc",
    "wof:placetype":"venue"
},
  "geometry": {"coordinates":[-87.7556,41.796501],"type":"Point"}
}