{
  "type": "Feature",
  "properties": {
    "iso:country":"US",
    "sg:address":"2800 N Sheridan Rd",
    "sg:city":"Chicago",
    "sg:classifiers":[
        {
            "category":"Health Services",
            "subcategory":"Health Practitioner",
            "type":"Services"
        }
    ],
    "sg:phone":"+1 773 404 6133",
    "sg:postcode":"60657",
    "sg:province":"IL",
    "wof:name":"Midwife Assoc",
    "wof:placetype":"venue"
},
  "geometry": {"coordinates":[-87.63933299999999,41.933292],"type":"Point"}
}