{
  "type": "Feature",
  "properties": {
    "addr:full":"13013 Western Ave Blue Island IL 60406",
    "addr:housenumber":"13013",
    "addr:postcode":"60406",
    "addr:street":"Western Ave",
    "iso:country":"US",
    "sg:address":"13013 Western Ave",
    "sg:city":"Blue Island",
    "sg:classifiers":[
        {
            "category":"Freight",
            "type":"Transportation"
        }
    ],
    "sg:phone":"+1 708 371 0729",
    "sg:postcode":"60406",
    "sg:province":"IL",
    "sg:tags":[
        "operator",
        "local",
        "trucking"
    ],
    "wof:name":"Three Way Transport",
    "wof:placetype":"venue"
},
  "geometry": {"coordinates":[-87.680003,41.656758],"type":"Point"}
}