{
  "type": "Feature",
  "properties": {
    "iso:country":"US",
    "sg:address":"6384 Surrey Ridge Rd",
    "sg:city":"Lisle",
    "sg:classifiers":[
        {
            "category":"Shopping",
            "type":"Retail Goods"
        }
    ],
    "sg:phone":"+1   ",
    "sg:postcode":"60532",
    "sg:province":"IL",
    "sg:tags":[
        "merchandise"
    ],
    "wof:name":"Susan Rogan Hearing",
    "wof:placetype":"venue"
},
  "geometry": {"coordinates":[-88.10488,41.769855],"type":"Point"}
}