{
  "type": "Feature",
  "properties": {
    "iso:country":"US",
    "sg:address":"355 Ridge Ave",
    "sg:city":"Evanston",
    "sg:classifiers":[
        {
            "category":"Health Services",
            "subcategory":"Hospital",
            "type":"Services"
        }
    ],
    "sg:phone":"+1 847 492 1334",
    "sg:postcode":"60202",
    "sg:province":"IL",
    "sg:tags":[
        "general"
    ],
    "wof:name":"St Francis Hospital",
    "wof:placetype":"venue"
},
  "geometry": {"coordinates":[-87.685097,42.024068],"type":"Point"}
}