{
  "type": "Feature",
  "properties": {
    "addr:full":"1850 N US Hwy 45 Libertyville IL 60048",
    "addr:housenumber":"1850",
    "addr:postcode":"60048",
    "addr:street":"N Us Hwy 45",
    "iso:country":"US",
    "sg:address":"1850 N US Hwy 45",
    "sg:city":"Libertyville",
    "sg:classifiers":[
        {
            "category":"Recreation",
            "type":"Entertainment"
        }
    ],
    "sg:phone":"+1 847 367 1506",
    "sg:postcode":"60048",
    "sg:province":"IL",
    "sg:tags":[
        "range",
        "practice",
        "golf"
    ],
    "sg:website":"www.libertyvillesportscomplex.com",
    "wof:name":"Libertyville Sports Complex",
    "wof:placetype":"venue"
},
  "geometry": {"coordinates":[-88.004316,42.297755],"type":"Point"}
}