{
  "type": "Feature",
  "properties": {
    "iso:country":"US",
    "sg:address":"525 Martin Cave Ln",
    "sg:city":"Goreville",
    "sg:classifiers":[
        {
            "category":"Social Services",
            "subcategory":"Child Care",
            "type":"Services"
        }
    ],
    "sg:phone":"+1 618 995 9644",
    "sg:postcode":"62939",
    "sg:province":"IL",
    "sg:tags":[
        "day"
    ],
    "wof:name":"Family Care Center",
    "wof:placetype":"venue"
},
  "geometry": {"coordinates":[-89.007717,37.54187],"type":"Point"}
}