{
  "type": "Feature",
  "properties": {
    "addr:full":"1155 W Dundee Rd Arlington Hts IL 60004",
    "addr:housenumber":"1155",
    "addr:postcode":"60004",
    "addr:street":"W Dundee Rd",
    "iso:country":"US",
    "sg:address":"1155 W Dundee Rd",
    "sg:city":"Arlington Hts",
    "sg:classifiers":[
        {
            "category":"Professional",
            "subcategory":"Management & Consulting",
            "type":"Services"
        }
    ],
    "sg:phone":"+1 847 394 8198",
    "sg:postcode":"60004",
    "sg:province":"IL",
    "sg:tags":[
        "fuel"
    ],
    "wof:name":"First American Management",
    "wof:placetype":"venue"
},
  "geometry": {"coordinates":[-87.999156,42.139047],"type":"Point"}
}