{
  "type": "Feature",
  "properties": {
    "iso:country":"US",
    "sg:address":"601 Univ Ave",
    "sg:city":"Champaign",
    "sg:classifiers":[
        {
            "category":"Retail",
            "subcategory":"Auto Repair",
            "type":"Services"
        }
    ],
    "sg:phone":"+1 217 352 0124",
    "sg:postcode":"61820",
    "sg:province":"IL",
    "wof:name":"Car-X Auto Service",
    "wof:placetype":"venue"
},
  "geometry": {"coordinates":[-88.246399,40.111698],"type":"Point"}
}