{
  "type": "Feature",
  "properties": {
    "addr:full":"6920 Ogden Ave Berwyn IL 60402",
    "addr:housenumber":"6920",
    "addr:postcode":"60402",
    "addr:street":"Ogden Ave",
    "iso:country":"US",
    "sg:address":"6920 Ogden Ave",
    "sg:city":"Berwyn",
    "sg:classifiers":[
        {
            "category":"Restaurant",
            "type":"Food & Drink"
        }
    ],
    "sg:menulink":"http://www.allmenus.com/il/berwyn/204560-bacci-pizzeria/menu/",
    "sg:phone":"+1 708 788 1700",
    "sg:postcode":"60402",
    "sg:province":"IL",
    "sg:tags":[
        "american",
        "pizza"
    ],
    "wof:name":"Bacci Pizzeria",
    "wof:placetype":"venue"
},
  "geometry": {"coordinates":[-87.795948,41.825993],"type":"Point"}
}