{
  "type": "Feature",
  "properties": {
    "addr:full":"7530 S South Shore Drive Chicago IL 60649",
    "addr:housenumber":"7530",
    "addr:postcode":"60649",
    "addr:street":"S South Shore Drive",
    "iso:country":"US",
    "sg:address":"7530 S South Shore Drive",
    "sg:city":"Chicago",
    "sg:classifiers":[
        {
            "category":"Education",
            "subcategory":"School",
            "type":"Public Place"
        }
    ],
    "sg:phone":"+1 773 535 6650",
    "sg:postcode":"60649",
    "sg:province":"IL",
    "sg:tags":[
        "high",
        "middle",
        "elementary"
    ],
    "wof:name":"Schools Public",
    "wof:placetype":"venue"
},
  "geometry": {"coordinates":[-87.55662599999999,41.759942],"type":"Point"}
}