{
  "type": "Feature",
  "properties": {
    "iso:country":"US",
    "sg:address":"631 Harlem Rd",
    "sg:city":"Machesney Park",
    "sg:classifiers":[
        {
            "category":"Retail",
            "subcategory":"Laundry & Dry Cleaning",
            "type":"Services"
        }
    ],
    "sg:phone":"+1 815 637 1515",
    "sg:postcode":"61115",
    "sg:province":"IL",
    "sg:tags":[
        "drycleaning",
        "plant",
        "cleaners"
    ],
    "wof:name":"Jim Dandy Discount Dry Cleaner",
    "wof:placetype":"venue"
},
  "geometry": {"coordinates":[-89.052751,42.339353],"type":"Point"}
}