{
  "type": "Feature",
  "properties": {
    "iso:country":"US",
    "sg:address":"416 S 4th St",
    "sg:city":"Quincy",
    "sg:classifiers":[
        {
            "category":"Food & Beverages",
            "subcategory":"Groceries & Convenience Stores",
            "type":"Retail Goods"
        }
    ],
    "sg:phone":"+1   ",
    "sg:postcode":"62301",
    "sg:province":"IL",
    "wof:name":"Winkings Grocery",
    "wof:placetype":"venue"
},
  "geometry": {"coordinates":[-91.410189,39.927964],"type":"Point"}
}