{
  "type": "Feature",
  "properties": {
    "addr:full":"185 Palmer Dr Bolingbrook IL 60490",
    "addr:housenumber":"185",
    "addr:postcode":"60490",
    "addr:street":"Palmer Dr",
    "iso:country":"US",
    "sg:address":"185 Palmer Dr",
    "sg:city":"Bolingbrook",
    "sg:classifiers":[
        {
            "category":"Professional",
            "subcategory":"Management & Consulting",
            "type":"Services"
        }
    ],
    "sg:phone":"+1 630 742 1785",
    "sg:postcode":"60490",
    "sg:province":"IL",
    "wof:name":"Scs Prop Management",
    "wof:placetype":"venue"
},
  "geometry": {"coordinates":[-88.1358,41.692427],"type":"Point"}
}