{
  "type": "Feature",
  "properties": {
    "iso:country":"US",
    "sg:address":"8057 Daniel Dr",
    "sg:city":"Justice",
    "sg:classifiers":[
        {
            "category":"Home & Garden",
            "subcategory":"Building Materials",
            "type":"Retail Goods"
        }
    ],
    "sg:phone":"+1 708 430 2442",
    "sg:postcode":"60458",
    "sg:province":"IL",
    "sg:tags":[
        "door"
    ],
    "wof:name":"Express Garage Door Svc",
    "wof:placetype":"venue"
},
  "geometry": {"coordinates":[-87.821457,41.741607],"type":"Point"}
}