{
  "type": "Feature",
  "properties": {
    "iso:country":"US",
    "sg:address":"1175 Lee St",
    "sg:city":"Des Plaines",
    "sg:classifiers":[
        {
            "category":"Wholesale",
            "subcategory":"Auto Parts",
            "type":"Manufacturing & Wholesale Goods"
        }
    ],
    "sg:phone":"+1 847 297 1888",
    "sg:postcode":"60018",
    "sg:province":"IL",
    "sg:tags":[
        "automotive"
    ],
    "wof:name":"Lee Auto Parts",
    "wof:placetype":"venue"
},
  "geometry": {"coordinates":[-87.89437,42.032092],"type":"Point"}
}