{
  "type": "Feature",
  "properties": {
    "iso:country":"US",
    "sg:address":"201 Houston St",
    "sg:city":"Batavia",
    "sg:classifiers":[
        {
            "category":"Professional",
            "subcategory":"Lawyer & Legal Services",
            "type":"Services"
        }
    ],
    "sg:phone":"+1 630 406 5440",
    "sg:postcode":"60510",
    "sg:province":"IL",
    "sg:tags":[
        "attorney"
    ],
    "wof:name":"Drendel & Drendel PC",
    "wof:placetype":"venue"
},
  "geometry": {"coordinates":[-88.312103,41.851082],"type":"Point"}
}