{
  "type": "Feature",
  "properties": {
    "addr:full":"1622 W Monterey Ave Chicago IL 60643",
    "addr:housenumber":"1622",
    "addr:postcode":"60643",
    "addr:street":"W Monterey Ave",
    "iso:country":"US",
    "sg:address":"1622 W Monterey Ave",
    "sg:city":"Chicago",
    "sg:classifiers":[
        {
            "category":"Food & Beverages",
            "subcategory":"Groceries & Convenience Stores",
            "type":"Retail Goods"
        }
    ],
    "sg:phone":"+1 773 881 8236",
    "sg:postcode":"60643",
    "sg:province":"IL",
    "wof:name":"Stop & Go Food & Liquor",
    "wof:placetype":"venue"
},
  "geometry": {"coordinates":[-87.662102,41.6894],"type":"Point"}
}