{
  "type": "Feature",
  "properties": {
    "iso:country":"US",
    "sg:address":"1601 Parkview Ave",
    "sg:city":"Rockford",
    "sg:classifiers":[
        {
            "category":"Health Services",
            "subcategory":"Doctor",
            "type":"Services"
        }
    ],
    "sg:phone":"+1 815 395 5560",
    "sg:postcode":"61107",
    "sg:province":"IL",
    "sg:tags":[
        "physician",
        "surgeon"
    ],
    "wof:name":"Empedrad, Raquel",
    "wof:placetype":"venue"
},
  "geometry": {"coordinates":[-89.057602,42.28434],"type":"Point"}
}