{
  "type": "Feature",
  "properties": {
    "iso:country":"US",
    "sg:address":"5745 W Addison Street",
    "sg:city":"Chicago",
    "sg:classifiers":[
        {
            "category":"Building & Trades",
            "subcategory":"Plumbing",
            "type":"Services"
        }
    ],
    "sg:phone":"+1 773 205 2300",
    "sg:postcode":"60634",
    "sg:province":"IL",
    "wof:name":"After All Plumbing & Construction",
    "wof:placetype":"venue"
},
  "geometry": {"coordinates":[-87.77109900000001,41.945621],"type":"Point"}
}