{
  "type": "Feature",
  "properties": {
    "iso:country":"US",
    "sg:address":"26137 W Stanton Bay Rd",
    "sg:city":"Ingleside",
    "sg:classifiers":[
        {
            "category":"Banks & Credit Unions",
            "subcategory":"Investment Brokerage",
            "type":"Services"
        }
    ],
    "sg:phone":"+1 847 587 1239",
    "sg:postcode":"60041",
    "sg:province":"IL",
    "sg:tags":[
        "advisory"
    ],
    "wof:name":"Morreale Investments",
    "wof:placetype":"venue"
},
  "geometry": {"coordinates":[-88.14310999999999,42.399955],"type":"Point"}
}