{
  "type": "Feature",
  "properties": {
    "addr:full":"523 W Blackhawk Dr Byron IL 61010",
    "addr:housenumber":"523",
    "addr:postcode":"61010",
    "addr:street":"W Blackhawk Dr",
    "iso:country":"US",
    "sg:address":"523 W Blackhawk Dr",
    "sg:city":"Byron",
    "sg:classifiers":[
        {
            "category":"Restaurant",
            "type":"Food & Drink"
        }
    ],
    "sg:phone":"+1 815 234 4114",
    "sg:postcode":"61010",
    "sg:province":"IL",
    "wof:name":"Charlie's Place",
    "wof:placetype":"venue"
},
  "geometry": {"coordinates":[-89.26195,42.125343],"type":"Point"}
}