{
  "type": "Feature",
  "properties": {
    "iso:country":"US",
    "sg:address":"2767 W Algonquin Rd",
    "sg:city":"Algonquin",
    "sg:classifiers":[
        {
            "category":"Personal",
            "subcategory":"Nail Salon",
            "type":"Services"
        }
    ],
    "sg:phone":"+1 847 854 7736",
    "sg:postcode":"60102",
    "sg:province":"IL",
    "wof:name":"Forever Nails",
    "wof:placetype":"venue"
},
  "geometry": {"coordinates":[-88.32644500000001,42.175556],"type":"Point"}
}