{
  "type": "Feature",
  "properties": {
    "addr:full":"3900 N Bernard St Chicago IL 60618",
    "addr:housenumber":"3900",
    "addr:postcode":"60618",
    "addr:street":"N Bernard St",
    "iso:country":"US",
    "sg:address":"3900 N Bernard St",
    "sg:city":"Chicago",
    "sg:classifiers":[
        {
            "category":"Building & Trades",
            "subcategory":"Cleaning & Sanitation",
            "type":"Services"
        }
    ],
    "sg:phone":"+1 773 758 7847",
    "sg:postcode":"60618",
    "sg:province":"IL",
    "sg:tags":[
        "carpet"
    ],
    "sg:website":"www.ronaldbistry.com",
    "wof:name":"Bistry Ronald",
    "wof:placetype":"venue"
},
  "geometry": {"coordinates":[-87.714224,41.952016],"type":"Point"}
}