{
  "type": "Feature",
  "properties": {
    "iso:country":"US",
    "sg:address":"909 N 2nd St",
    "sg:city":"Chillicothe",
    "sg:classifiers":[
        {
            "category":"Education",
            "subcategory":"Dance Studio",
            "type":"Public Place"
        }
    ],
    "sg:phone":"+1 309 274 4440",
    "sg:postcode":"61523",
    "sg:province":"IL",
    "sg:tags":[
        "instruction",
        "dancing"
    ],
    "wof:name":"Downtown Dance Depot",
    "wof:placetype":"venue"
},
  "geometry": {"coordinates":[-89.485462,40.91712],"type":"Point"}
}