{
  "type": "Feature",
  "properties": {
    "iso:country":"US",
    "sg:address":"119 Fairfield Dr",
    "sg:city":"Island Lake",
    "sg:classifiers":[
        {
            "category":"Organizations",
            "subcategory":"Community Association",
            "type":"Services"
        }
    ],
    "sg:phone":"+1 847 526 3201",
    "sg:postcode":"60042",
    "sg:province":"IL",
    "wof:name":"International Assoc of LI",
    "wof:placetype":"venue"
},
  "geometry": {"coordinates":[-88.197529,42.274346],"type":"Point"}
}