{
  "type": "Feature",
  "properties": {
    "iso:country":"US",
    "sg:address":"627 Sherman Ave",
    "sg:city":"Elgin",
    "sg:classifiers":[
        {
            "category":"Professional",
            "subcategory":"Secretarial Services",
            "type":"Services"
        }
    ],
    "sg:phone":"+1 847 608 0898",
    "sg:postcode":"60120",
    "sg:province":"IL",
    "sg:tags":[
        "convention",
        "reporting",
        "reporters-court"
    ],
    "wof:name":"Sales Innovations",
    "wof:placetype":"venue"
},
  "geometry": {"coordinates":[-88.266915,42.029175],"type":"Point"}
}