{
  "type": "Feature",
  "properties": {
    "iso:country":"US",
    "sg:address":"422 E Evergreen St",
    "sg:city":"Wheaton",
    "sg:classifiers":[
        {
            "category":"Manufacturing",
            "subcategory":"Printing",
            "type":"Manufacturing & Wholesale Goods"
        }
    ],
    "sg:phone":"+1 630 665 4225",
    "sg:postcode":"60187",
    "sg:province":"IL",
    "sg:tags":[
        "commercial"
    ],
    "wof:name":"464 Integrated Graphic Systems",
    "wof:placetype":"venue"
},
  "geometry": {"coordinates":[-88.099028,41.85994],"type":"Point"}
}