{
  "type": "Feature",
  "properties": {
    "addr:full":"435 E 42nd Pl Chicago IL 60653",
    "addr:housenumber":"435",
    "addr:postcode":"60653",
    "addr:street":"E 42Nd Pl",
    "iso:country":"US",
    "sg:address":"435 E 42nd Pl",
    "sg:city":"Chicago",
    "sg:classifiers":[
        {
            "category":"Travel",
            "subcategory":"Travel Agent",
            "type":"Entertainment"
        }
    ],
    "sg:phone":"+1 773 677 6148",
    "sg:postcode":"60653",
    "sg:province":"IL",
    "sg:tags":[
        "agency",
        "services-commercial"
    ],
    "wof:name":"Dabir Travel Group",
    "wof:placetype":"venue"
},
  "geometry": {"coordinates":[-87.615629,41.817537],"type":"Point"}
}