{
  "type": "Feature",
  "properties": {
    "addr:full":"3 First National Plaza Chicago IL 60602",
    "addr:housenumber":"3",
    "addr:postcode":"60602",
    "addr:street":"First National Plaza",
    "iso:country":"US",
    "sg:address":"3 First National Plaza",
    "sg:city":"Chicago",
    "sg:classifiers":[
        {
            "category":"Professional",
            "subcategory":"Lawyer & Legal Services",
            "type":"Services"
        }
    ],
    "sg:phone":"+1 312 263 2300",
    "sg:postcode":"60602",
    "sg:province":"IL",
    "wof:name":"Golan Leonard W",
    "wof:placetype":"venue"
},
  "geometry": {"coordinates":[-87.62940500000001,41.88269],"type":"Point"}
}