{
  "type": "Feature",
  "properties": {
    "iso:country":"US",
    "sg:address":"958 W 69th St",
    "sg:city":"Chicago",
    "sg:phone":"+1 773 994 3977",
    "sg:postcode":"60621",
    "sg:province":"IL",
    "wof:name":"Carribean Lounge",
    "wof:placetype":"venue"
},
  "geometry": {"coordinates":[-87.648612,41.768765],"type":"Point"}
}