{
  "type": "Feature",
  "properties": {
    "iso:country":"US",
    "sg:address":"9150 Crawford Ave",
    "sg:city":"Skokie",
    "sg:classifiers":[
        {
            "category":"Health Services",
            "subcategory":"Doctor",
            "type":"Services"
        }
    ],
    "sg:phone":"+1 847 679 1605",
    "sg:postcode":"60076",
    "sg:province":"IL",
    "sg:tags":[
        "physician"
    ],
    "wof:name":"Alan C Pollack MD",
    "wof:placetype":"venue"
},
  "geometry": {"coordinates":[-87.727706,42.046982],"type":"Point"}
}