{
  "type": "Feature",
  "properties": {
    "iso:country":"US",
    "sg:address":"736 Burnham Ave",
    "sg:city":"Calumet City",
    "sg:classifiers":[
        {
            "category":"Building & Trades",
            "subcategory":"Locksmith",
            "type":"Services"
        }
    ],
    "sg:phone":"+1 708 862 4974",
    "sg:postcode":"60409",
    "sg:province":"IL",
    "sg:tags":[
        "key"
    ],
    "wof:name":"Mika Locksmiths & Hdw",
    "wof:placetype":"venue"
},
  "geometry": {"coordinates":[-87.539497,41.6138],"type":"Point"}
}