{
  "type": "Feature",
  "properties": {
    "iso:country":"US",
    "sg:address":"6 Convenience Center Rd",
    "sg:city":"Champaign",
    "sg:classifiers":[
        {
            "category":"Real Estate",
            "subcategory":"Real Estate Operator",
            "type":"Services"
        }
    ],
    "sg:phone":"+1 217 352 5022",
    "sg:postcode":"61820",
    "sg:province":"IL",
    "sg:tags":[
        "apartment"
    ],
    "wof:name":"Hallmark Real Estate",
    "wof:placetype":"venue"
},
  "geometry": {"coordinates":[-88.243503,40.139144],"type":"Point"}
}