{
  "type": "Feature",
  "properties": {
    "iso:country":"US",
    "sg:address":"315 Lime St",
    "sg:city":"Joliet",
    "sg:classifiers":[
        {
            "category":"Building & Trades",
            "subcategory":"Landscaping Services",
            "type":"Services"
        }
    ],
    "sg:phone":"+1 815 722 4823",
    "sg:postcode":"60435",
    "sg:province":"IL",
    "sg:tags":[
        "lawn",
        "maintenance",
        "grounds"
    ],
    "sg:website":"www.cblcservices.com",
    "wof:name":"Country Boy Lawn Care",
    "wof:placetype":"venue"
},
  "geometry": {"coordinates":[-88.091343,41.536029],"type":"Point"}
}