{
  "type": "Feature",
  "properties": {
    "iso:country":"US",
    "sg:address":"71 S Ottawa Ave",
    "sg:city":"Dixon",
    "sg:classifiers":[
        {
            "category":"Wholesale",
            "subcategory":"Electrical",
            "type":"Manufacturing & Wholesale Goods"
        }
    ],
    "sg:phone":"+1 815 284 0062",
    "sg:postcode":"61021",
    "sg:province":"IL",
    "sg:tags":[
        "electric",
        "motor"
    ],
    "wof:name":"ROGERS Electric Motor Sales",
    "wof:placetype":"venue"
},
  "geometry": {"coordinates":[-89.481605,41.844166],"type":"Point"}
}