{
  "type": "Feature",
  "properties": {
    "iso:country":"US",
    "sg:address":"1342 Chillem Dr",
    "sg:city":"Batavia",
    "sg:classifiers":[
        {
            "category":"Wholesale",
            "subcategory":"Machinery & Supplies",
            "type":"Manufacturing & Wholesale Goods"
        },
        {
            "category":"Retail",
            "subcategory":"Repair Shop",
            "type":"Services"
        }
    ],
    "sg:phone":"+1 630 482 9628",
    "sg:postcode":"60510",
    "sg:province":"IL",
    "sg:tags":[
        "instrument",
        "electronic",
        "marine"
    ],
    "wof:name":"Neptune Marine Electronics Svc",
    "wof:placetype":"venue"
},
  "geometry": {"coordinates":[-88.280394,41.836911],"type":"Point"}
}