{
  "type": "Feature",
  "properties": {
    "iso:country":"US",
    "sg:address":"12N238 Hilltop Rd",
    "sg:city":"Elgin",
    "sg:classifiers":[
        {
            "category":"Real Estate",
            "subcategory":"Real Estate Services",
            "type":"Services"
        }
    ],
    "sg:phone":"+1 847 742 8131",
    "sg:postcode":"60123",
    "sg:province":"IL",
    "wof:name":"Hajner Angie Rl Est",
    "wof:placetype":"venue"
},
  "geometry": {"coordinates":[-88.342697,42.0471],"type":"Point"}
}