{
  "type": "Feature",
  "properties": {
    "iso:country":"US",
    "sg:address":"14825 New Ave",
    "sg:city":"Lockport",
    "sg:classifiers":[
        {
            "category":"Freight",
            "type":"Transportation"
        }
    ],
    "sg:phone":"+1 630 325 9070",
    "sg:postcode":"60441",
    "sg:province":"IL",
    "sg:tags":[
        "operator",
        "local",
        "storage",
        "trucking"
    ],
    "wof:name":"Excel Motor Service",
    "wof:placetype":"venue"
},
  "geometry": {"coordinates":[-88.05116700000001,41.612591],"type":"Point"}
}