{
  "type": "Feature",
  "properties": {
    "iso:country":"US",
    "sg:address":"1904 Round Barn Rd",
    "sg:city":"Champaign",
    "sg:classifiers":[
        {
            "category":"Health Services",
            "subcategory":"Health Practitioner",
            "type":"Services"
        }
    ],
    "sg:phone":"+1 217 355 6240",
    "sg:postcode":"61821",
    "sg:province":"IL",
    "wof:name":"Carle Therapy Services",
    "wof:placetype":"venue"
},
  "geometry": {"coordinates":[-88.282557,40.111201],"type":"Point"}
}