{
  "type": "Feature",
  "properties": {
    "iso:country":"US",
    "sg:address":"7419 E Brick School Rd",
    "sg:city":"Rock City",
    "sg:classifiers":[
        {
            "category":"Organizations",
            "subcategory":"Religious Organization",
            "type":"Services"
        }
    ],
    "sg:phone":"+1 815 449 2890",
    "sg:postcode":"61070",
    "sg:province":"IL",
    "sg:tags":[
        "church"
    ],
    "wof:name":"New Beginnings Church",
    "wof:placetype":"venue"
},
  "geometry": {"coordinates":[-89.469774,42.360709],"type":"Point"}
}