{
  "type": "Feature",
  "properties": {
    "addr:full":"9536 W Foster Avenue Chicago IL 60656",
    "addr:housenumber":"9536",
    "addr:postcode":"60656",
    "addr:street":"W Foster Avenue",
    "iso:country":"US",
    "sg:address":"9536 W Foster Avenue",
    "sg:city":"Chicago",
    "sg:classifiers":[
        {
            "category":"Autos & Motor Vehicles",
            "subcategory":"Automobile Sales",
            "type":"Retail Goods"
        }
    ],
    "sg:phone":"+1 773 992 2404",
    "sg:postcode":"60656",
    "sg:province":"IL",
    "sg:tags":[
        "limo"
    ],
    "wof:name":"Chicago 1 Limo",
    "wof:placetype":"venue"
},
  "geometry": {"coordinates":[-87.852161,41.973464],"type":"Point"}
}