{
  "type": "Feature",
  "properties": {
    "iso:country":"US",
    "sg:address":"14024 S Harrison Ave",
    "sg:city":"Posen",
    "sg:classifiers":[
        {
            "category":"Retail",
            "subcategory":"Auto Repair",
            "type":"Services"
        }
    ],
    "sg:phone":"+1 708 293 8378",
    "sg:postcode":"60469",
    "sg:province":"IL",
    "sg:tags":[
        "body",
        "automobile",
        "painting",
        "repairing"
    ],
    "wof:name":"Ram Auto Body",
    "wof:placetype":"venue"
},
  "geometry": {"coordinates":[-87.687842,41.63846],"type":"Point"}
}