{
  "type": "Feature",
  "properties": {
    "addr:full":"2624 Patriot Blvd Glenview IL 60026",
    "addr:housenumber":"2624",
    "addr:postcode":"60026",
    "addr:street":"Patriot Blvd",
    "iso:country":"US",
    "sg:address":"2624 Patriot Blvd",
    "sg:city":"Glenview",
    "sg:classifiers":[
        {
            "category":"Professional",
            "subcategory":"Computer Services",
            "type":"Services"
        }
    ],
    "sg:phone":"+1 888 623 7189",
    "sg:postcode":"60026",
    "sg:province":"IL",
    "sg:tags":[
        "account-aggregation",
        "data-aggregation",
        "financial-advisors",
        "wealth-managers",
        "financial-planners",
        "ria"
    ],
    "sg:website":"http://www.advisorexchange.com",
    "wof:name":"Advisor Exchange",
    "wof:placetype":"venue"
},
  "geometry": {"coordinates":[-87.824224,42.097947],"type":"Point"}
}