{
  "type": "Feature",
  "properties": {
    "addr:full":"1060 W Addison St Chicago IL 60613",
    "addr:housenumber":"1060",
    "addr:postcode":"60613",
    "addr:street":"W Addison St",
    "iso:country":"US",
    "sg:address":"1060 W Addison St",
    "sg:city":"Chicago",
    "sg:classifiers":[
        {
            "category":"Communications",
            "subcategory":"Television Station",
            "type":"Services"
        }
    ],
    "sg:phone":"+1 773 529 2089",
    "sg:postcode":"60613",
    "sg:province":"IL",
    "sg:tags":[
        "satellite",
        "cable"
    ],
    "wof:name":"Broadcast Comcast Sports",
    "wof:placetype":"venue"
},
  "geometry": {"coordinates":[-87.656479,41.947189],"type":"Point"}
}