{
  "type": "Feature",
  "properties": {
    "iso:country":"US",
    "sg:address":"6809 Stanley Ave",
    "sg:city":"Berwyn",
    "sg:classifiers":[
        {
            "category":"Banks & Credit Unions",
            "subcategory":"Bank",
            "type":"Services"
        }
    ],
    "sg:phone":"+1 708 795 1075",
    "sg:postcode":"60402",
    "sg:province":"IL",
    "sg:tags":[
        "federal",
        "savings",
        "institution"
    ],
    "wof:name":"Harris Trust & Savings Bank",
    "wof:placetype":"venue"
},
  "geometry": {"coordinates":[-87.793645,41.833563],"type":"Point"}
}