{
  "type": "Feature",
  "properties": {
    "iso:country":"US",
    "sg:address":"1401 W North Avenue",
    "sg:city":"Chicago",
    "sg:classifiers":[
        {
            "category":"Food & Beverages",
            "subcategory":"Liquor & Beverages",
            "type":"Retail Goods"
        }
    ],
    "sg:phone":"+1 773 489 2210",
    "sg:postcode":"60622",
    "sg:province":"IL",
    "sg:tags":[
        "beer",
        "spirit",
        "wine"
    ],
    "wof:name":"Miller Brewing Company",
    "wof:placetype":"venue"
},
  "geometry": {"coordinates":[-87.663437,41.910577],"type":"Point"}
}