{
  "type": "Feature",
  "properties": {
    "addr:full":"326 E 18th St Lockport IL 60441",
    "addr:housenumber":"326",
    "addr:postcode":"60441",
    "addr:street":"E 18Th St",
    "iso:country":"US",
    "sg:address":"326 E 18th St",
    "sg:city":"Lockport",
    "sg:classifiers":[
        {
            "category":"Organizations",
            "subcategory":"Religious Organization",
            "type":"Services"
        }
    ],
    "sg:phone":"+1 815 838 1094",
    "sg:postcode":"60441",
    "sg:province":"IL",
    "wof:name":"Calvary Chapel Ministries",
    "wof:placetype":"venue"
},
  "geometry": {"coordinates":[-88.05777399999999,41.579036],"type":"Point"}
}