{
  "type": "Feature",
  "properties": {
    "iso:country":"US",
    "sg:address":"2607 W Peterson Ave",
    "sg:city":"Chicago",
    "sg:classifiers":[
        {
            "category":"Home & Garden",
            "subcategory":"Furniture",
            "type":"Retail Goods"
        }
    ],
    "sg:phone":"+1 773 561 3041",
    "sg:postcode":"60659",
    "sg:province":"IL",
    "sg:tags":[
        "builder",
        "custom"
    ],
    "wof:name":"Dale N Winblad Handcrafted",
    "wof:placetype":"venue"
},
  "geometry": {"coordinates":[-87.695492,41.99039],"type":"Point"}
}