{
  "type": "Feature",
  "properties": {
    "iso:country":"US",
    "sg:address":"3402 Woods Creek Ln",
    "sg:city":"Algonquin",
    "sg:classifiers":[
        {
            "category":"Professional",
            "subcategory":"Art Services",
            "type":"Services"
        }
    ],
    "sg:phone":"+1 847 854 5653",
    "sg:postcode":"60102",
    "sg:province":"IL",
    "sg:tags":[
        "graphic",
        "designer"
    ],
    "sg:website":"http://www.rmgraphicequip.com",
    "wof:name":"Rm Graphics Equipment, Inc",
    "wof:placetype":"venue"
},
  "geometry": {"coordinates":[-88.352248,42.163922],"type":"Point"}
}