{
  "type": "Feature",
  "properties": {
    "iso:country":"US",
    "sg:address":"2466 Washington Rd",
    "sg:city":"Washington",
    "sg:phone":"+1 309 282 4646",
    "sg:postcode":"61571",
    "sg:province":"IL",
    "wof:name":"Lenny's Comedy Cafe",
    "wof:placetype":"venue"
},
  "geometry": {"coordinates":[-89.501017,40.690441],"type":"Point"}
}