{
  "type": "Feature",
  "properties": {
    "addr:full":"501 W Main St Collinsville IL 62234",
    "addr:housenumber":"501",
    "addr:postcode":"62234",
    "addr:street":"W Main St",
    "iso:country":"US",
    "sg:address":"501 W Main St",
    "sg:city":"Collinsville",
    "sg:classifiers":[
        {
            "category":"Retail",
            "subcategory":"Funeral Services",
            "type":"Services"
        }
    ],
    "sg:phone":"+1 618 346 4377",
    "sg:postcode":"62234",
    "sg:province":"IL",
    "sg:tags":[
        "cemetery"
    ],
    "sg:website":"www.herrfuneral.com",
    "wof:name":"Herr Funeral Homes & Cremation Services",
    "wof:placetype":"venue"
},
  "geometry": {"coordinates":[-89.991501,38.668201],"type":"Point"}
}