{
  "type": "Feature",
  "properties": {
    "addr:full":"119 N Peoria St Ste 2A Chicago IL 60607",
    "addr:housenumber":"119",
    "addr:postcode":"60607",
    "addr:street":"N Peoria St Ste 2A",
    "iso:country":"US",
    "sg:address":"119 N Peoria St Ste 2A",
    "sg:city":"Chicago",
    "sg:classifiers":[
        {
            "category":"Arts & Performance",
            "subcategory":"Art Gallery",
            "type":"Entertainment"
        }
    ],
    "sg:phone":"+1 312 480 8390",
    "sg:postcode":"60607",
    "sg:province":"IL",
    "sg:website":"www.westernexhibitions.com",
    "wof:name":"Western Exhibitions",
    "wof:placetype":"venue"
},
  "geometry": {"coordinates":[-87.649157,41.883692],"type":"Point"}
}