{
  "type": "Feature",
  "properties": {
    "addr:full":"106 E Main St La Harpe IL 61450",
    "addr:housenumber":"106",
    "addr:postcode":"61450",
    "addr:street":"E Main St",
    "iso:country":"US",
    "sg:address":"106 E Main St",
    "sg:city":"La Harpe",
    "sg:classifiers":[
        {
            "category":"Professional",
            "subcategory":"Lawyer & Legal Services",
            "type":"Services"
        }
    ],
    "sg:phone":"+1 217 659 3312",
    "sg:postcode":"61450",
    "sg:province":"IL",
    "sg:tags":[
        "attorney"
    ],
    "wof:name":"Richard Rasmussen",
    "wof:placetype":"venue"
},
  "geometry": {"coordinates":[-90.969459,40.583585],"type":"Point"}
}