{
  "type": "Feature",
  "properties": {
    "addr:full":"957 Sioux Dr Round Lake IL 60073",
    "addr:housenumber":"957",
    "addr:postcode":"60073",
    "addr:street":"Sioux Dr",
    "iso:country":"US",
    "sg:address":"957 Sioux Dr",
    "sg:city":"Round Lake",
    "sg:classifiers":[
        {
            "category":"Building & Trades",
            "subcategory":"Construction",
            "type":"Services"
        }
    ],
    "sg:phone":"+1 847 740 3950",
    "sg:postcode":"60073",
    "sg:province":"IL",
    "sg:tags":[
        "house"
    ],
    "wof:name":"Productivity Improvements Inc",
    "wof:placetype":"venue"
},
  "geometry": {"coordinates":[-88.102985,42.387193],"type":"Point"}
}