{
  "type": "Feature",
  "properties": {
    "iso:country":"US",
    "sg:address":"653 Touhy Ave",
    "sg:city":"Elk Grove Village",
    "sg:classifiers":[
        {
            "category":"Building & Trades",
            "subcategory":"Cleaning & Sanitation",
            "type":"Services"
        }
    ],
    "sg:phone":"+1 847 354 8744",
    "sg:postcode":"60007",
    "sg:province":"IL",
    "sg:tags":[
        "fire",
        "restoration"
    ],
    "wof:name":"Fire Clean LLC",
    "wof:placetype":"venue"
},
  "geometry": {"coordinates":[-87.978167,42.006231],"type":"Point"}
}