{
  "type": "Feature",
  "properties": {
    "addr:full":"502 Joliet St La Salle IL 61301",
    "addr:housenumber":"502",
    "addr:postcode":"61301",
    "addr:street":"Joliet St",
    "iso:country":"US",
    "sg:address":"502 Joliet St",
    "sg:city":"La Salle",
    "sg:classifiers":[
        {
            "category":"Organizations",
            "subcategory":"Religious Organization",
            "type":"Services"
        }
    ],
    "sg:phone":"+1 815 223 1286",
    "sg:postcode":"61301",
    "sg:province":"IL",
    "sg:tags":[
        "church"
    ],
    "wof:name":"First Congregational United",
    "wof:placetype":"venue"
},
  "geometry": {"coordinates":[-89.094846,41.333704],"type":"Point"}
}