{
  "type": "Feature",
  "properties": {
    "addr:full":"1420 N Rand Rd Arlington Heights IL 60004",
    "addr:housenumber":"1420",
    "addr:postcode":"60004",
    "addr:street":"N Rand Rd",
    "iso:country":"US",
    "sg:address":"1420 N Rand Rd",
    "sg:city":"Arlington Heights",
    "sg:classifiers":[
        {
            "category":"Deli",
            "type":"Food & Drink"
        }
    ],
    "sg:menulink":"http://www.allmenus.com/il/wheeling/224597-nikkos-drive-in/menu/",
    "sg:phone":"+1 847 870 0180",
    "sg:postcode":"60004",
    "sg:province":"IL",
    "sg:tags":[
        "american"
    ],
    "wof:name":"Nikko's Drive In",
    "wof:placetype":"venue"
},
  "geometry": {"coordinates":[-88.000117,42.126028],"type":"Point"}
}