{
  "type": "Feature",
  "properties": {
    "iso:country":"US",
    "sg:address":"1024 E 9th St",
    "sg:city":"Kewanee",
    "sg:classifiers":[
        {
            "category":"Building & Trades",
            "subcategory":"Construction",
            "type":"Services"
        }
    ],
    "sg:phone":"+1 309 853 8077",
    "sg:postcode":"61443",
    "sg:province":"IL",
    "sg:tags":[
        "excavation",
        "contractor",
        "drainage"
    ],
    "wof:name":"Hayes Farm Draining & Excavtg",
    "wof:placetype":"venue"
},
  "geometry": {"coordinates":[-89.909557,41.253292],"type":"Point"}
}