{
  "type": "Feature",
  "properties": {
    "addr:full":"8750 W Berwyn Ave Ste 700 Chicago IL 60656",
    "addr:housenumber":"8750",
    "addr:postcode":"60656",
    "addr:street":"W Berwyn Ave Ste 700",
    "iso:country":"US",
    "sg:address":"8750 W Berwyn Ave Ste 700",
    "sg:city":"Chicago",
    "sg:classifiers":[
        {
            "category":"Bars & Pubs",
            "type":"Food & Drink"
        }
    ],
    "sg:phone":"+1 773 864 7800",
    "sg:postcode":"60656",
    "sg:province":"IL",
    "sg:tags":[
        "brew"
    ],
    "sg:website":"http://www.collegetalkonline.com",
    "wof:name":"Anheuser-Busch",
    "wof:placetype":"venue"
},
  "geometry": {"coordinates":[-87.84545300000001,41.975105],"type":"Point"}
}