{
  "type": "Feature",
  "properties": {
    "addr:full":"18535 Stockton Ave Homewood IL 60430",
    "addr:housenumber":"18535",
    "addr:postcode":"60430",
    "addr:street":"Stockton Ave",
    "iso:country":"US",
    "sg:address":"18535 Stockton Ave",
    "sg:city":"Homewood",
    "sg:classifiers":[
        {
            "category":"Professional",
            "subcategory":"Business Services",
            "type":"Services"
        }
    ],
    "sg:phone":"+1 708 922 1169",
    "sg:postcode":"60430",
    "sg:province":"IL",
    "sg:tags":[
        "radiology",
        "diagnostic"
    ],
    "wof:name":"Robert L McMiller MD",
    "wof:placetype":"venue"
},
  "geometry": {"coordinates":[-87.693147,41.552466],"type":"Point"}
}