{
  "type": "Feature",
  "properties": {
    "addr:full":"1300 W 127th St Calumet Park IL 60827",
    "addr:housenumber":"1300",
    "addr:postcode":"60827",
    "addr:street":"W 127Th St",
    "iso:country":"US",
    "sg:address":"1300 W 127th St",
    "sg:city":"Calumet Park",
    "sg:classifiers":[
        {
            "category":"Autos & Motor Vehicles",
            "subcategory":"Automobile Sales",
            "type":"Retail Goods"
        }
    ],
    "sg:phone":"+1 708 388 0010",
    "sg:postcode":"60827",
    "sg:province":"IL",
    "sg:tags":[
        "car"
    ],
    "wof:name":"D & A Auto Sales",
    "wof:placetype":"venue"
},
  "geometry": {"coordinates":[-87.653801,41.663101],"type":"Point"}
}