{
  "type": "Feature",
  "properties": {
    "addr:full":"5030 N Marine Dr Chicago IL 60640",
    "addr:housenumber":"5030",
    "addr:postcode":"60640",
    "addr:street":"N Marine Dr",
    "iso:country":"US",
    "sg:address":"5030 N Marine Dr",
    "sg:city":"Chicago",
    "sg:classifiers":[
        {
            "category":"Building & Trades",
            "subcategory":"Cleaning & Sanitation",
            "type":"Services"
        }
    ],
    "sg:phone":"+1 773 784 8196",
    "sg:postcode":"60640",
    "sg:province":"IL",
    "sg:tags":[
        "janitor"
    ],
    "wof:name":"Goldstar Janitorial Svc",
    "wof:placetype":"venue"
},
  "geometry": {"coordinates":[-87.651212,41.973556],"type":"Point"}
}