{
  "type": "Feature",
  "properties": {
    "iso:country":"US",
    "sg:address":"5235 Katrine Ave",
    "sg:city":"Downers Grove",
    "sg:classifiers":[
        {
            "category":"Manufacturing",
            "subcategory":"Tools & Machinery",
            "type":"Manufacturing & Wholesale Goods"
        }
    ],
    "sg:phone":"+1 630 968 2390",
    "sg:postcode":"60515",
    "sg:province":"IL",
    "sg:tags":[
        "control",
        "industrial",
        "or",
        "relay",
        "mfg"
    ],
    "sg:website":"www.controlmasters.com",
    "wof:name":"Control Masters Inc",
    "wof:placetype":"venue"
},
  "geometry": {"coordinates":[-88.047774,41.790028],"type":"Point"}
}