{
  "type": "Feature",
  "properties": {
    "iso:country":"US",
    "sg:address":"1551 N Sheffield Ave",
    "sg:city":"Chicago",
    "sg:classifiers":[
        {
            "category":"Restaurant",
            "type":"Food & Drink"
        }
    ],
    "sg:menulink":"http://www.allmenus.com/il/chicago/22073-north-beach/menu/",
    "sg:phone":"+1 312 266 7842",
    "sg:postcode":"60622",
    "sg:province":"IL",
    "sg:tags":[
        "american"
    ],
    "wof:name":"North Beach",
    "wof:placetype":"venue"
},
  "geometry": {"coordinates":[-87.653122,41.910291],"type":"Point"}
}