{
  "type": "Feature",
  "properties": {
    "addr:full":"2801 Black Rd Joliet IL 60435",
    "addr:housenumber":"2801",
    "addr:postcode":"60435",
    "addr:street":"Black Rd",
    "iso:country":"US",
    "sg:address":"2801 Black Rd",
    "sg:city":"Joliet",
    "sg:classifiers":[
        {
            "category":"Professional",
            "subcategory":"Lawyer & Legal Services",
            "type":"Services"
        }
    ],
    "sg:phone":"+1 815 723 8500",
    "sg:postcode":"60435",
    "sg:province":"IL",
    "sg:tags":[
        "attorney"
    ],
    "wof:name":"Tracy Johnson & Wilson",
    "wof:placetype":"venue"
},
  "geometry": {"coordinates":[-88.149613,41.536683],"type":"Point"}
}