{
  "type": "Feature",
  "properties": {
    "addr:full":"4204 Avenue Of The Cities Moline IL 61265",
    "addr:housenumber":"4204",
    "addr:postcode":"61265",
    "addr:street":"Avenue Of The",
    "iso:country":"US",
    "sg:address":"4204 Avenue Of The Cities",
    "sg:city":"Moline",
    "sg:classifiers":[
        {
            "category":"Shopping",
            "subcategory":"Clothing, Apparel, & Fashions",
            "type":"Retail Goods"
        },
        {
            "category":"Sports & Exercise",
            "subcategory":"Bowling",
            "type":"Entertainment"
        }
    ],
    "sg:phone":"+1 309 743 2664",
    "sg:postcode":"61265",
    "sg:province":"IL",
    "sg:tags":[
        "accessory",
        "equipment",
        "sportswear",
        "apparel",
        "racing",
        "merchandise"
    ],
    "wof:name":"Johnson's Don Pro. Shop",
    "wof:placetype":"venue"
},
  "geometry": {"coordinates":[-90.477834,41.489896],"type":"Point"}
}