{
  "type": "Feature",
  "properties": {
    "addr:full":"2109 Kensington Dr Schaumburg IL 60194",
    "addr:housenumber":"2109",
    "addr:postcode":"60194",
    "addr:street":"Kensington Dr",
    "iso:country":"US",
    "sg:address":"2109 Kensington Dr",
    "sg:city":"Schaumburg",
    "sg:classifiers":[
        {
            "category":"Personal",
            "type":"Services"
        }
    ],
    "sg:phone":"+1 847 885 9847",
    "sg:postcode":"60194",
    "sg:province":"IL",
    "wof:name":"Bedard Services Inc",
    "wof:placetype":"venue"
},
  "geometry": {"coordinates":[-88.13123400000001,42.040656],"type":"Point"}
}