{
  "type": "Feature",
  "properties": {
    "addr:full":"4775 N Linder Ste 2A Chicago IL 60630",
    "addr:housenumber":"4775",
    "addr:postcode":"60630",
    "addr:street":"N Linder Ste 2A",
    "iso:country":"US",
    "sg:address":"4775 N Linder Ste 2A",
    "sg:city":"Chicago",
    "sg:classifiers":[
        {
            "category":"Building & Trades",
            "subcategory":"Construction",
            "type":"Services"
        },
        {
            "category":"Home & Garden",
            "subcategory":"Carpets & Floor Coverings",
            "type":"Retail Goods"
        }
    ],
    "sg:phone":"+1 773 406 5369",
    "sg:postcode":"60630",
    "sg:province":"IL",
    "sg:tags":[
        "interior",
        "design",
        "flooring",
        "contractor"
    ],
    "sg:website":"www.bpremodelers.com",
    "wof:name":"Kitchen Remodelers Elk Grove Village",
    "wof:placetype":"venue"
},
  "geometry": {"coordinates":[-87.764993,41.967565],"type":"Point"}
}