{
  "type": "Feature",
  "properties": {
    "addr:full":"29 Forestwood Dr Romeoville IL 60446",
    "addr:housenumber":"29",
    "addr:postcode":"60446",
    "addr:street":"Forestwood Dr",
    "iso:country":"US",
    "sg:address":"29 Forestwood Dr",
    "sg:city":"Romeoville",
    "sg:classifiers":[
        {
            "category":"Building & Trades",
            "subcategory":"Construction",
            "type":"Services"
        }
    ],
    "sg:phone":"+1 815 886 4600",
    "sg:postcode":"60446",
    "sg:province":"IL",
    "sg:tags":[
        "excavating",
        "contractor"
    ],
    "wof:name":"Morris Excavating Inc",
    "wof:placetype":"venue"
},
  "geometry": {"coordinates":[-88.070656,41.654286],"type":"Point"}
}