{
  "type": "Feature",
  "properties": {
    "iso:country":"US",
    "sg:address":"318 N Lewis Ave",
    "sg:city":"Waukegan",
    "sg:classifiers":[
        {
            "category":"Building & Trades",
            "subcategory":"Landscaping Services",
            "type":"Services"
        }
    ],
    "sg:phone":"+1 847 625 8559",
    "sg:postcode":"60085",
    "sg:province":"IL",
    "wof:name":"Montoya Lanscaping",
    "wof:placetype":"venue"
},
  "geometry": {"coordinates":[-87.855768,42.363316],"type":"Point"}
}