{
  "type": "Feature",
  "properties": {
    "iso:country":"US",
    "sg:address":"201 W Springfield Ave Ste 1005",
    "sg:city":"Champaign",
    "sg:classifiers":[
        {
            "category":"Professional",
            "subcategory":"Lawyer & Legal Services",
            "type":"Services"
        }
    ],
    "sg:phone":"+1 217 351 9969",
    "sg:postcode":"61820",
    "sg:province":"IL",
    "wof:name":"Lawlyes & Lawlyes PC",
    "wof:placetype":"venue"
},
  "geometry": {"coordinates":[-88.24514000000001,40.112443],"type":"Point"}
}