{
  "type": "Feature",
  "properties": {
    "iso:country":"US",
    "sg:address":"601 S Bench St",
    "sg:city":"Galena",
    "sg:classifiers":[
        {
            "category":"Education",
            "subcategory":"Library",
            "type":"Public Place"
        }
    ],
    "sg:phone":"+1 815 777 0200",
    "sg:postcode":"61036",
    "sg:province":"IL",
    "sg:website":"http://www.galenalibrary.org",
    "wof:name":"Galena Public Library",
    "wof:placetype":"venue"
},
  "geometry": {"coordinates":[-90.431648,42.41161],"type":"Point"}
}