{
  "type": "Feature",
  "properties": {
    "addr:full":"304 Walnut St New Windsor IL 61465",
    "addr:housenumber":"304",
    "addr:postcode":"61465",
    "addr:street":"Walnut St",
    "iso:country":"US",
    "sg:address":"304 Walnut St",
    "sg:city":"New Windsor",
    "sg:classifiers":[
        {
            "category":"Organizations",
            "subcategory":"Religious Organization",
            "type":"Services"
        }
    ],
    "sg:phone":"+1 309 667 2115",
    "sg:postcode":"61465",
    "sg:province":"IL",
    "sg:tags":[
        "clergy"
    ],
    "wof:name":"Calvary Lutheran Parsonage",
    "wof:placetype":"venue"
},
  "geometry": {"coordinates":[-90.440742,41.203579],"type":"Point"}
}