{
  "type": "Feature",
  "properties": {
    "addr:full":"6306 N Cicero Avenue Chicago IL 60646",
    "addr:housenumber":"6306",
    "addr:postcode":"60646",
    "addr:street":"N Cicero Avenue",
    "iso:country":"US",
    "sg:address":"6306 N Cicero Avenue",
    "sg:city":"Chicago",
    "sg:classifiers":[
        {
            "category":"Professional",
            "subcategory":"Accounting & Tax Preparation",
            "type":"Services"
        }
    ],
    "sg:phone":"+1 773 736 8800",
    "sg:postcode":"60646",
    "sg:province":"IL",
    "sg:tags":[
        "accountant"
    ],
    "wof:name":"Accurate Computerized Accounting Service",
    "wof:placetype":"venue"
},
  "geometry": {"coordinates":[-87.748127,41.995996],"type":"Point"}
}