{
  "type": "Feature",
  "properties": {
    "addr:full":"7 E 119th Street Chicago IL 60628",
    "addr:housenumber":"7",
    "addr:postcode":"60628",
    "addr:street":"E 119Th Street",
    "iso:country":"US",
    "sg:address":"7 E 119th Street",
    "sg:city":"Chicago",
    "sg:classifiers":[
        {
            "category":"Travel",
            "subcategory":"Hotels & Motels",
            "type":"Entertainment"
        }
    ],
    "sg:phone":"+1 773 291 0826",
    "sg:postcode":"60628",
    "sg:province":"IL",
    "wof:name":"Abraham Lincoln Centre",
    "wof:placetype":"venue"
},
  "geometry": {"coordinates":[-87.62259400000001,41.678138],"type":"Point"}
}