{
  "type": "Feature",
  "properties": {
    "addr:full":"3116 75th St Kenosha IL 53142",
    "addr:housenumber":"3116",
    "addr:postcode":"53142",
    "addr:street":"75Th St",
    "iso:country":"US",
    "sg:address":"3116 75th St",
    "sg:city":"Kenosha",
    "sg:classifiers":[
        {
            "category":"Social Services",
            "type":"Services"
        }
    ],
    "sg:phone":"+1 262 564 0286",
    "sg:postcode":"53142",
    "sg:province":"IL",
    "sg:tags":[
        "organization",
        "welfare"
    ],
    "wof:name":"Salvation Army",
    "wof:placetype":"venue"
},
  "geometry": {"coordinates":[-87.84726999999999,42.566157],"type":"Point"}
}