{
  "type": "Feature",
  "properties": {
    "addr:full":"10829 S 76th Ave Worth IL 60482",
    "addr:housenumber":"10829",
    "addr:postcode":"60482",
    "addr:street":"S 76Th Ave",
    "iso:country":"US",
    "sg:address":"10829 S 76th Ave",
    "sg:city":"Worth",
    "sg:classifiers":[
        {
            "category":"Building & Trades",
            "subcategory":"Plumbing",
            "type":"Services"
        }
    ],
    "sg:phone":"+1 708 923 1868",
    "sg:postcode":"60482",
    "sg:province":"IL",
    "sg:tags":[
        "sheet",
        "work",
        "metal",
        "contractor"
    ],
    "wof:name":"Any Custom Sheet Metal Inc",
    "wof:placetype":"venue"
},
  "geometry": {"coordinates":[-87.807294,41.695032],"type":"Point"}
}