{
  "type": "Feature",
  "properties": {
    "iso:country":"US",
    "sg:address":"4849 W Irving Park Rd",
    "sg:city":"Chicago",
    "sg:classifiers":[
        {
            "category":"Personal",
            "subcategory":"Beauty Salon",
            "type":"Services"
        }
    ],
    "sg:phone":"+1 773 286 4046",
    "sg:postcode":"60641",
    "sg:province":"IL",
    "sg:tags":[
        "shop"
    ],
    "wof:name":"Perfect Nails",
    "wof:placetype":"venue"
},
  "geometry": {"coordinates":[-87.749778,41.953312],"type":"Point"}
}