{
  "type": "Feature",
  "properties": {
    "iso:country":"US",
    "sg:address":"11625 S Ashland Ave",
    "sg:city":"Chicago",
    "sg:classifiers":[
        {
            "category":"Place Of Worship",
            "subcategory":"Church",
            "type":"Public Place"
        },
        {
            "category":"Place Of Worship",
            "type":"Public Place"
        }
    ],
    "sg:phone":"+1 773 568 2299",
    "sg:postcode":"60643",
    "sg:province":"IL",
    "sg:tags":[
        "covenant",
        "churches-evangelical",
        "churches-baptist-general",
        "churches-covenant",
        "churches-baptist"
    ],
    "wof:name":"New Freedom Kingdom Covenant Church",
    "wof:placetype":"venue"
},
  "geometry": {"coordinates":[-87.661537,41.682553],"type":"Point"}
}