{
  "type": "Feature",
  "properties": {
    "iso:country":"US",
    "sg:address":"4600 W 103rd St",
    "sg:city":"Oak Lawn",
    "sg:classifiers":[
        {
            "category":"Health Services",
            "subcategory":"Doctor",
            "type":"Services"
        }
    ],
    "sg:phone":"+1 708 423 8380",
    "sg:postcode":"60453",
    "sg:province":"IL",
    "sg:tags":[
        "surgeon",
        "oral"
    ],
    "wof:name":"Swingler Thomas A DDS",
    "wof:placetype":"venue"
},
  "geometry": {"coordinates":[-87.735497,41.705799],"type":"Point"}
}