{
  "type": "Feature",
  "properties": {
    "addr:full":"109 Melanie Ln Collinsville IL 62234",
    "addr:housenumber":"109",
    "addr:postcode":"62234",
    "addr:street":"Melanie Ln",
    "iso:country":"US",
    "sg:address":"109 Melanie Ln",
    "sg:city":"Collinsville",
    "sg:classifiers":[
        {
            "category":"Building & Trades",
            "subcategory":"Construction",
            "type":"Services"
        }
    ],
    "sg:phone":"+1 618 345 1870",
    "sg:postcode":"62234",
    "sg:province":"IL",
    "sg:tags":[
        "contractor"
    ],
    "wof:name":"R & J Building & Remodeling",
    "wof:placetype":"venue"
},
  "geometry": {"coordinates":[-89.930397,38.7075],"type":"Point"}
}