{
  "type": "Feature",
  "properties": {
    "iso:country":"US",
    "sg:address":"4612 W. Irving Park Road",
    "sg:city":"Chicago",
    "sg:classifiers":[
        {
            "category":"Shopping",
            "subcategory":"Department Store",
            "type":"Retail Goods"
        }
    ],
    "sg:phone":"+1 773 282 0078",
    "sg:postcode":"60641",
    "sg:province":"IL",
    "wof:name":"Marshall's",
    "wof:placetype":"venue"
},
  "geometry": {"coordinates":[-87.742699,41.953602],"type":"Point"}
}