{
  "type": "Feature",
  "properties": {
    "addr:full":"804 N. State Street Chicago IL 60610",
    "addr:housenumber":"804",
    "addr:postcode":"60610",
    "addr:street":"N. State Street",
    "iso:country":"US",
    "sg:address":"804 N. State Street",
    "sg:city":"Chicago",
    "sg:classifiers":[
        {
            "category":"Restaurant",
            "type":"Food & Drink"
        }
    ],
    "sg:phone":"+1 312 951 9030",
    "sg:postcode":"60610",
    "sg:province":"IL",
    "sg:tags":[
        "thai",
        "vietnamese"
    ],
    "wof:name":"Quang Noodle Vietnamese and Thai Cuisine",
    "wof:placetype":"venue"
},
  "geometry": {"coordinates":[-87.62840300000001,41.8969],"type":"Point"}
}