{
  "type": "Feature",
  "properties": {
    "iso:country":"US",
    "sg:address":"611 N 4th St",
    "sg:city":"Chillicothe",
    "sg:classifiers":[
        {
            "category":"Manufacturing",
            "subcategory":"Jewelry",
            "type":"Manufacturing & Wholesale Goods"
        }
    ],
    "sg:phone":"+1 309 274 8860",
    "sg:postcode":"61523",
    "sg:province":"IL",
    "wof:name":"Hoppler's Jewelry",
    "wof:placetype":"venue"
},
  "geometry": {"coordinates":[-89.489637,40.914686],"type":"Point"}
}