{
  "type": "Feature",
  "properties": {
    "iso:country":"US",
    "sg:address":"2310 W Ainslie Street",
    "sg:city":"Chicago",
    "sg:classifiers":[
        {
            "category":"Organizations",
            "subcategory":"Religious Organization",
            "type":"Services"
        }
    ],
    "sg:phone":"+1 773 506 2191",
    "sg:postcode":"60625",
    "sg:province":"IL",
    "wof:name":"St Matthias Church",
    "wof:placetype":"venue"
},
  "geometry": {"coordinates":[-87.686942,41.970565],"type":"Point"}
}