{
  "type": "Feature",
  "properties": {
    "addr:full":"2502 Galen Dr Ste 102 Champaign IL 61821",
    "addr:housenumber":"2502",
    "addr:postcode":"61821",
    "addr:street":"Galen Dr Ste 102",
    "iso:country":"US",
    "sg:address":"2502 Galen Dr Ste 102",
    "sg:city":"Champaign",
    "sg:classifiers":[
        {
            "category":"Banks & Credit Unions",
            "subcategory":"Investment Brokerage",
            "type":"Services"
        },
        {
            "category":"Banks & Credit Unions",
            "subcategory":"Bank",
            "type":"Services"
        },
        {
            "category":"Banks & Credit Unions",
            "subcategory":"Financial Services",
            "type":"Services"
        }
    ],
    "sg:phone":"+1 217 359 4686",
    "sg:postcode":"61821",
    "sg:province":"IL",
    "sg:tags":[
        "management",
        "transfer",
        "broker",
        "agent",
        "security",
        "stock",
        "bond"
    ],
    "sg:website":"http://www.stefel.com",
    "wof:name":"Stifel, Nicolaus & Company Incorporated",
    "wof:placetype":"venue"
},
  "geometry": {"coordinates":[-88.262867,40.082066],"type":"Point"}
}