{
  "type": "Feature",
  "properties": {
    "iso:country":"US",
    "sg:address":"400 W Huron Street",
    "sg:city":"Chicago",
    "sg:classifiers":[
        {
            "category":"Building & Trades",
            "subcategory":"Construction",
            "type":"Services"
        }
    ],
    "sg:phone":"+1 312 587 1023",
    "sg:postcode":"60610",
    "sg:province":"IL",
    "sg:tags":[
        "contractor"
    ],
    "wof:name":"Smithfield Properties Xxvii",
    "wof:placetype":"venue"
},
  "geometry": {"coordinates":[-87.63883300000001,41.89483],"type":"Point"}
}