{
  "type": "Feature",
  "properties": {
    "addr:full":"854 N Central Ave Chicago IL 60651",
    "addr:housenumber":"854",
    "addr:postcode":"60651",
    "addr:street":"N Central Ave",
    "iso:country":"US",
    "sg:address":"854 N Central Ave",
    "sg:city":"Chicago",
    "sg:classifiers":[
        {
            "category":"Organizations",
            "subcategory":"Religious Organization",
            "type":"Services"
        }
    ],
    "sg:phone":"+1 773 921 2554",
    "sg:postcode":"60651",
    "sg:province":"IL",
    "sg:tags":[
        "church"
    ],
    "wof:name":"Christ Tabernacle Church",
    "wof:placetype":"venue"
},
  "geometry": {"coordinates":[-87.765523,41.896351],"type":"Point"}
}