{
  "type": "Feature",
  "properties": {
    "iso:country":"US",
    "sg:address":"4330 S Champlain Avenue",
    "sg:city":"Chicago",
    "sg:classifiers":[
        {
            "category":"Real Estate",
            "subcategory":"Real Estate Services",
            "type":"Services"
        },
        {
            "category":"Real Estate",
            "subcategory":"Real Estate Operator",
            "type":"Services"
        }
    ],
    "sg:phone":"+1 773 268 3049",
    "sg:postcode":"60653",
    "sg:province":"IL",
    "sg:tags":[
        "apartment",
        "vacancy",
        "management",
        "listing",
        "rental",
        "finder"
    ],
    "wof:name":"Leontyne Apartments",
    "wof:placetype":"venue"
},
  "geometry": {"coordinates":[-87.610405,41.816155],"type":"Point"}
}