{
  "type": "Feature",
  "properties": {
    "addr:full":"548 Heritage Dr Mackinaw IL 61755",
    "addr:housenumber":"548",
    "addr:postcode":"61755",
    "addr:street":"Heritage Dr",
    "iso:country":"US",
    "sg:address":"548 Heritage Dr",
    "sg:city":"Mackinaw",
    "sg:classifiers":[
        {
            "category":"Professional",
            "subcategory":"Printing & Photocopies",
            "type":"Services"
        }
    ],
    "sg:phone":"+1 309 359 3333",
    "sg:postcode":"61755",
    "sg:province":"IL",
    "sg:tags":[
        "photocopying"
    ],
    "wof:name":"Lenski Copy & Editing",
    "wof:placetype":"venue"
},
  "geometry": {"coordinates":[-89.326723,40.552861],"type":"Point"}
}