{
  "type": "Feature",
  "properties": {
    "addr:full":"1875 Big Timber Rd Elgin IL 60123",
    "addr:housenumber":"1875",
    "addr:postcode":"60123",
    "addr:street":"Big Timber Rd",
    "iso:country":"US",
    "sg:address":"1875 Big Timber Rd",
    "sg:city":"Elgin",
    "sg:classifiers":[
        {
            "category":"Manufacturing",
            "subcategory":"Tools & Machinery",
            "type":"Manufacturing & Wholesale Goods"
        }
    ],
    "sg:phone":"+1 847 695 1000",
    "sg:postcode":"60123",
    "sg:province":"IL",
    "sg:tags":[
        "machine",
        "mfg"
    ],
    "sg:website":"www.harigproducts.com",
    "wof:name":"Harig Products Inc",
    "wof:placetype":"venue"
},
  "geometry": {"coordinates":[-88.32223399999999,42.059029],"type":"Point"}
}