{
  "type": "Feature",
  "properties": {
    "iso:country":"US",
    "sg:address":"115 S La Salle Street",
    "sg:city":"Chicago",
    "sg:classifiers":[
        {
            "category":"Banks & Credit Unions",
            "subcategory":"Investment Brokerage",
            "type":"Services"
        }
    ],
    "sg:phone":"+1 312 368 0066",
    "sg:postcode":"60603",
    "sg:province":"IL",
    "sg:tags":[
        "investing"
    ],
    "wof:name":"The Burridge Group",
    "wof:placetype":"venue"
},
  "geometry": {"coordinates":[-87.63228100000001,41.880562],"type":"Point"}
}