{
  "type": "Feature",
  "properties": {
    "iso:country":"US",
    "sg:address":"216 W Madison St",
    "sg:city":"Rushville",
    "sg:classifiers":[
        {
            "category":"Retail",
            "subcategory":"Auto Repair",
            "type":"Services"
        }
    ],
    "sg:phone":"+1   ",
    "sg:postcode":"62681",
    "sg:province":"IL",
    "sg:tags":[
        "glass",
        "replacement",
        "supply"
    ],
    "wof:name":"Auto Glass Systems",
    "wof:placetype":"venue"
},
  "geometry": {"coordinates":[-90.564377,40.119029],"type":"Point"}
}