{
  "type": "Feature",
  "properties": {
    "iso:country":"US",
    "sg:address":"617 Arlington Heights Rd",
    "sg:city":"Arlington Heights",
    "sg:classifiers":[
        {
            "category":"Professional",
            "subcategory":"Accounting & Tax Preparation",
            "type":"Services"
        }
    ],
    "sg:phone":"+1 847 228 6977",
    "sg:postcode":"60005",
    "sg:province":"IL",
    "wof:name":"D Varey & Co",
    "wof:placetype":"venue"
},
  "geometry": {"coordinates":[-87.980442,42.072227],"type":"Point"}
}