{
  "type": "Feature",
  "properties": {
    "iso:country":"US",
    "sg:address":"1567 E Algonquin Rd",
    "sg:city":"Des Plaines",
    "sg:classifiers":[
        {
            "category":"Professional",
            "type":"Services"
        }
    ],
    "sg:phone":"+1 847 635 0375",
    "sg:postcode":"60016",
    "sg:province":"IL",
    "wof:name":"Eclectic Media Services",
    "wof:placetype":"venue"
},
  "geometry": {"coordinates":[-87.885909,42.031577],"type":"Point"}
}