{
  "type": "Feature",
  "properties": {
    "addr:full":"1011 E Touhy Ave Des Plaines IL 60018",
    "addr:housenumber":"1011",
    "addr:postcode":"60018",
    "addr:street":"E Touhy Ave",
    "iso:country":"US",
    "sg:address":"1011 E Touhy Ave",
    "sg:city":"Des Plaines",
    "sg:classifiers":[
        {
            "category":"Professional",
            "subcategory":"Computer Services",
            "type":"Services"
        }
    ],
    "sg:phone":"+1 847 699 9960",
    "sg:postcode":"60018",
    "sg:province":"IL",
    "sg:tags":[
        "reseller",
        "com",
        "system",
        "value",
        "integration"
    ],
    "wof:name":"Decision Systems Plus Inc",
    "wof:placetype":"venue"
},
  "geometry": {"coordinates":[-87.897307,42.009178],"type":"Point"}
}