{
  "type": "Feature",
  "properties": {
    "iso:country":"US",
    "sg:address":"1525 E 53rd St Ste 810",
    "sg:city":"Chicago",
    "sg:classifiers":[
        {
            "category":"Personal",
            "subcategory":"Massage",
            "type":"Services"
        }
    ],
    "sg:phone":"+1 773 719 7273",
    "sg:postcode":"60615",
    "sg:province":"IL",
    "sg:website":"www.kimosha.com",
    "wof:name":"Ki Massage & Bodywork",
    "wof:placetype":"venue"
},
  "geometry": {"coordinates":[-87.58817500000001,41.799309],"type":"Point"}
}