{
  "type": "Feature",
  "properties": {
    "iso:country":"US",
    "sg:address":"1431 N 2250th Rd",
    "sg:city":"Ottawa",
    "sg:classifiers":[
        {
            "category":"Manufacturing",
            "subcategory":"Food",
            "type":"Manufacturing & Wholesale Goods"
        },
        {
            "category":"Farming",
            "subcategory":"Farm",
            "type":"Manufacturing & Wholesale Goods"
        }
    ],
    "sg:phone":"+1 815 249 5021",
    "sg:postcode":"61350",
    "sg:province":"IL",
    "sg:tags":[
        "corn",
        "product"
    ],
    "wof:name":"Thomas Brothers",
    "wof:placetype":"venue"
},
  "geometry": {"coordinates":[-88.89191,41.258441],"type":"Point"}
}