{
  "type": "Feature",
  "properties": {
    "addr:full":"213 Hazel Ave Glencoe IL 60022",
    "addr:housenumber":"213",
    "addr:postcode":"60022",
    "addr:street":"Hazel Ave",
    "iso:country":"US",
    "sg:address":"213 Hazel Ave",
    "sg:city":"Glencoe",
    "sg:classifiers":[
        {
            "category":"Place Of Worship",
            "subcategory":"Church",
            "type":"Public Place"
        },
        {
            "category":"Place Of Worship",
            "type":"Public Place"
        }
    ],
    "sg:phone":"+1 847 835 1227",
    "sg:postcode":"60022",
    "sg:province":"IL",
    "sg:tags":[
        "churches-methodist"
    ],
    "wof:name":"North Shore United Methodist Church",
    "wof:placetype":"venue"
},
  "geometry": {"coordinates":[-87.754414,42.134816],"type":"Point"}
}