{
  "type": "Feature",
  "properties": {
    "iso:country":"US",
    "sg:address":"4514 S Western Ave",
    "sg:city":"Chicago",
    "sg:phone":"+1 773 927 2055",
    "sg:postcode":"60609",
    "sg:province":"IL",
    "wof:name":"Ancor Professional Upholstery",
    "wof:placetype":"venue"
},
  "geometry": {"coordinates":[-87.68450900000001,41.811615],"type":"Point"}
}