{
  "type": "Feature",
  "properties": {
    "addr:full":"5113 159th St Oak Forest IL 60452",
    "addr:housenumber":"5113",
    "addr:postcode":"60452",
    "addr:street":"159Th St",
    "iso:country":"US",
    "sg:address":"5113 159th St",
    "sg:city":"Oak Forest",
    "sg:classifiers":[
        {
            "category":"Retail",
            "subcategory":"Auto Repair",
            "type":"Services"
        }
    ],
    "sg:phone":"+1 708 687 1500",
    "sg:postcode":"60452",
    "sg:province":"IL",
    "wof:name":"Multistate Transmissions",
    "wof:placetype":"venue"
},
  "geometry": {"coordinates":[-87.744698,41.603001],"type":"Point"}
}