{
  "type": "Feature",
  "properties": {
    "addr:full":"1090 Sweetwater Trl New Lenox IL 60451",
    "addr:housenumber":"1090",
    "addr:postcode":"60451",
    "addr:street":"Sweetwater Trl",
    "iso:country":"US",
    "sg:address":"1090 Sweetwater Trl",
    "sg:city":"New Lenox",
    "sg:classifiers":[
        {
            "category":"Building & Trades",
            "subcategory":"Landscaping Services",
            "type":"Services"
        }
    ],
    "sg:phone":"+1 815 462 0675",
    "sg:postcode":"60451",
    "sg:province":"IL",
    "wof:name":"Jtc Lawn Maintenance",
    "wof:placetype":"venue"
},
  "geometry": {"coordinates":[-87.986616,41.480481],"type":"Point"}
}