{
  "type": "Feature",
  "properties": {
    "iso:country":"US",
    "sg:address":"185 Olive St",
    "sg:city":"Elmhurst",
    "sg:classifiers":[
        {
            "category":"Professional",
            "subcategory":"Business Services",
            "type":"Services"
        }
    ],
    "sg:phone":"+1 630 833 1521",
    "sg:postcode":"60126",
    "sg:province":"IL",
    "sg:tags":[
        "interior",
        "design"
    ],
    "wof:name":"Donoghue Consulting Service",
    "wof:placetype":"venue"
},
  "geometry": {"coordinates":[-87.944592,41.889496],"type":"Point"}
}