{
  "type": "Feature",
  "properties": {
    "iso:country":"US",
    "sg:address":"7501 N Waukegan Rd",
    "sg:city":"Niles",
    "sg:classifiers":[
        {
            "category":"Utilities",
            "subcategory":"Electric",
            "type":"Services"
        },
        {
            "category":"Manufacturing",
            "subcategory":"Electronics",
            "type":"Manufacturing & Wholesale Goods"
        },
        {
            "category":"Building & Trades",
            "subcategory":"Construction",
            "type":"Services"
        },
        {
            "category":"Building & Trades",
            "subcategory":"Electrical",
            "type":"Services"
        }
    ],
    "sg:phone":"+1 847 588 2533",
    "sg:postcode":"60714",
    "sg:province":"IL",
    "sg:tags":[
        "industrial",
        "electrician",
        "specialty",
        "equipment-testing",
        "system",
        "heating",
        "contractors-commercial",
        "contractor",
        "air conditioning"
    ],
    "wof:name":"Electrical Services Group",
    "wof:placetype":"venue"
},
  "geometry": {"coordinates":[-87.80262,42.01701],"type":"Point"}
}