{
  "type": "Feature",
  "properties": {
    "addr:full":"721 10th St North Chicago IL 60064",
    "addr:housenumber":"721",
    "addr:postcode":"60064",
    "addr:street":"10Th St",
    "iso:country":"US",
    "sg:address":"721 10th St",
    "sg:city":"North Chicago",
    "sg:classifiers":[
        {
            "category":"Insurance",
            "subcategory":"Insurance Agent",
            "type":"Services"
        }
    ],
    "sg:phone":"+1 847 887 9650",
    "sg:postcode":"60064",
    "sg:province":"IL",
    "wof:name":"Mex American Insurance",
    "wof:placetype":"venue"
},
  "geometry": {"coordinates":[-87.840496,42.341223],"type":"Point"}
}