{
  "type": "Feature",
  "properties": {
    "addr:full":"5148 US Hwy 20 Galena IL 61036",
    "addr:housenumber":"5148",
    "addr:postcode":"61036",
    "addr:street":"Us Hwy 20",
    "iso:country":"US",
    "sg:address":"5148 US Hwy 20",
    "sg:city":"Galena",
    "sg:classifiers":[
        {
            "category":"Travel",
            "subcategory":"Hotels & Motels",
            "type":"Entertainment"
        },
        {
            "category":"Real Estate",
            "subcategory":"Real Estate Operator",
            "type":"Services"
        }
    ],
    "sg:phone":"+1 815 777 9320",
    "sg:postcode":"61036",
    "sg:province":"IL",
    "sg:tags":[
        "residential",
        "manager",
        "property",
        "resort"
    ],
    "sg:website":"www.ambercreek.com",
    "wof:name":"Amber Creek",
    "wof:placetype":"venue"
},
  "geometry": {"coordinates":[-90.45520500000001,42.446691],"type":"Point"}
}