{
  "type": "Feature",
  "properties": {
    "addr:full":"411 W Ontario Street Ofc Chicago IL 60610",
    "addr:housenumber":"411",
    "addr:postcode":"60610",
    "addr:street":"W Ontario Street",
    "iso:country":"US",
    "sg:address":"411 W Ontario Street Ofc",
    "sg:city":"Chicago",
    "sg:classifiers":[
        {
            "category":"Professional",
            "subcategory":"Lawyer & Legal Services",
            "type":"Services"
        }
    ],
    "sg:phone":"+1 312 943 1707",
    "sg:postcode":"60610",
    "sg:province":"IL",
    "wof:name":"Young Donald W",
    "wof:placetype":"venue"
},
  "geometry": {"coordinates":[-87.638918,41.893107],"type":"Point"}
}