{
  "type": "Feature",
  "properties": {
    "iso:country":"US",
    "sg:address":"1851 W Grand Ave",
    "sg:city":"Chicago",
    "sg:classifiers":[
        {
            "category":"Shopping",
            "subcategory":"Beauty & Cosmetics",
            "type":"Retail Goods"
        },
        {
            "category":"Personal",
            "subcategory":"Hair Removal",
            "type":"Services"
        },
        {
            "category":"Personal",
            "subcategory":"Day Spa",
            "type":"Services"
        },
        {
            "category":"Personal",
            "subcategory":"Skin Care",
            "type":"Services"
        },
        {
            "category":"Personal",
            "subcategory":"Beauty Salon",
            "type":"Services"
        }
    ],
    "sg:phone":"+1 312 226 1851",
    "sg:postcode":"60622",
    "sg:province":"IL",
    "sg:tags":[
        "perfume"
    ],
    "wof:name":"Jeta Skin Care Inc",
    "wof:placetype":"venue"
},
  "geometry": {"coordinates":[-87.67326199999999,41.890899],"type":"Point"}
}