{
  "type": "Feature",
  "properties": {
    "iso:country":"US",
    "sg:address":"313 N Naperville Rd",
    "sg:city":"Bolingbrook",
    "sg:classifiers":[
        {
            "category":"Retail",
            "subcategory":"Repair Shop",
            "type":"Services"
        }
    ],
    "sg:phone":"+1 630 759 3335",
    "sg:postcode":"60490",
    "sg:province":"IL",
    "sg:tags":[
        "electrical"
    ],
    "wof:name":"Lens Appliance Repair",
    "wof:placetype":"venue"
},
  "geometry": {"coordinates":[-88.12620800000001,41.704911],"type":"Point"}
}