{
  "type": "Feature",
  "properties": {
    "addr:full":"2011 2nd Ave Rock Island IL 61201",
    "addr:housenumber":"2011",
    "addr:postcode":"61201",
    "addr:street":"2Nd Ave",
    "iso:country":"US",
    "sg:address":"2011 2nd Ave",
    "sg:city":"Rock Island",
    "sg:classifiers":[
        {
            "category":"Social Services",
            "type":"Services"
        }
    ],
    "sg:phone":"+1 309 788 0833",
    "sg:postcode":"61201",
    "sg:province":"IL",
    "sg:tags":[
        "youth",
        "organization",
        "center"
    ],
    "sg:website":"www.girlscouts-mvc.org",
    "wof:name":"Girl Scouts Mississippi Valley",
    "wof:placetype":"venue"
},
  "geometry": {"coordinates":[-90.570365,41.511093],"type":"Point"}
}