{
  "type": "Feature",
  "properties": {
    "iso:country":"US",
    "sg:address":"6139 W Cermak Rd",
    "sg:city":"Cicero",
    "sg:classifiers":[
        {
            "category":"Restaurant",
            "type":"Food & Drink"
        }
    ],
    "sg:phone":"+1 708 652 0888",
    "sg:postcode":"60804",
    "sg:province":"IL",
    "sg:tags":[
        "thai"
    ],
    "wof:name":"So Full Thai Restaurant",
    "wof:placetype":"venue"
},
  "geometry": {"coordinates":[-87.778053,41.850426],"type":"Point"}
}