{
  "type": "Feature",
  "properties": {
    "iso:country":"US",
    "sg:address":"2140 N Lincoln Ave",
    "sg:city":"Chicago",
    "sg:classifiers":[
        {
            "category":"Building & Trades",
            "subcategory":"Equipment Rental",
            "type":"Services"
        }
    ],
    "sg:phone":"+1 773 477 8336",
    "sg:postcode":"60614",
    "sg:province":"IL",
    "sg:tags":[
        "supplies-renting",
        "hospital",
        "wheelchairs-rental"
    ],
    "wof:name":"Suburban Home Respiratory Care Serv Inc",
    "wof:placetype":"venue"
},
  "geometry": {"coordinates":[-87.642306,41.920816],"type":"Point"}
}