{
  "type": "Feature",
  "properties": {
    "addr:full":"5059 Ace Ln Naperville IL 60564",
    "addr:housenumber":"5059",
    "addr:postcode":"60564",
    "addr:street":"Ace Ln",
    "iso:country":"US",
    "sg:address":"5059 Ace Ln",
    "sg:city":"Naperville",
    "sg:classifiers":[
        {
            "category":"Restaurant",
            "type":"Food & Drink"
        }
    ],
    "sg:menulink":"http://www.allmenus.com/il/wheatland/159541-arbys/menu/",
    "sg:phone":"+1 630 922 4277",
    "sg:postcode":"60564",
    "sg:province":"IL",
    "sg:tags":[
        "burger",
        "american"
    ],
    "wof:name":"Arby's",
    "wof:placetype":"venue"
},
  "geometry": {"coordinates":[-88.205763,41.678667],"type":"Point"}
}