{
  "type": "Feature",
  "properties": {
    "iso:country":"US",
    "sg:address":"211 N Pleasant St",
    "sg:city":"Princeton",
    "sg:classifiers":[
        {
            "category":"Organizations",
            "subcategory":"Religious Organization",
            "type":"Services"
        }
    ],
    "sg:phone":"+1 815 872 7871",
    "sg:postcode":"61356",
    "sg:province":"IL",
    "sg:tags":[
        "church"
    ],
    "wof:name":"Church Of Christ",
    "wof:placetype":"venue"
},
  "geometry": {"coordinates":[-89.46627100000001,41.377942],"type":"Point"}
}