{
  "type": "Feature",
  "properties": {
    "addr:full":"505 E Saint Charles Rd Villa Park IL 60181",
    "addr:housenumber":"505",
    "addr:postcode":"60181",
    "addr:street":"E Saint Charles Rd",
    "iso:country":"US",
    "sg:address":"505 E Saint Charles Rd",
    "sg:city":"Villa Park",
    "sg:classifiers":[
        {
            "category":"Home & Garden",
            "subcategory":"Furniture",
            "type":"Retail Goods"
        }
    ],
    "sg:phone":"+1 630 832 0047",
    "sg:postcode":"60181",
    "sg:province":"IL",
    "wof:name":"Classic Oak Designs Inc",
    "wof:placetype":"venue"
},
  "geometry": {"coordinates":[-87.96544,41.890098],"type":"Point"}
}