{
  "type": "Feature",
  "properties": {
    "iso:country":"US",
    "sg:address":"210 8th Ave",
    "sg:city":"Mendota",
    "sg:classifiers":[
        {
            "category":"Professional",
            "type":"Services"
        }
    ],
    "sg:phone":"+1 815 539 5220",
    "sg:postcode":"61342",
    "sg:province":"IL",
    "wof:name":"Sally A Hedgspeth",
    "wof:placetype":"venue"
},
  "geometry": {"coordinates":[-89.11993699999999,41.542622],"type":"Point"}
}