{
  "type": "Feature",
  "properties": {
    "iso:country":"US",
    "sg:address":"631 S Burno Dr",
    "sg:city":"Palatine",
    "sg:classifiers":[
        {
            "category":"Banks & Credit Unions",
            "subcategory":"Financial Services",
            "type":"Services"
        }
    ],
    "sg:phone":"+1 847 359 1115",
    "sg:postcode":"60067",
    "sg:province":"IL",
    "sg:tags":[
        "company",
        "holding"
    ],
    "wof:name":"John & Anne Lichner Foundation",
    "wof:placetype":"venue"
},
  "geometry": {"coordinates":[-88.05457800000001,42.101482],"type":"Point"}
}