{
  "type": "Feature",
  "properties": {
    "addr:full":"2130 N Cicero Ave Chicago IL 60639",
    "addr:housenumber":"2130",
    "addr:postcode":"60639",
    "addr:street":"N Cicero Ave",
    "iso:country":"US",
    "sg:address":"2130 N Cicero Ave",
    "sg:city":"Chicago",
    "sg:classifiers":[
        {
            "category":"Building & Trades",
            "subcategory":"Locksmith",
            "type":"Services"
        }
    ],
    "sg:phone":"+1 773 797 5668",
    "sg:postcode":"60639",
    "sg:province":"IL",
    "sg:tags":[
        "key"
    ],
    "wof:name":"A 1 Emergency Locksmith",
    "wof:placetype":"venue"
},
  "geometry": {"coordinates":[-87.746414,41.919632],"type":"Point"}
}