{
  "type": "Feature",
  "properties": {
    "addr:full":"800 Ogden Ave Downers Grove IL 60515",
    "addr:housenumber":"800",
    "addr:postcode":"60515",
    "addr:street":"Ogden Ave",
    "iso:country":"US",
    "sg:address":"800 Ogden Ave",
    "sg:city":"Downers Grove",
    "sg:classifiers":[
        {
            "category":"Shopping",
            "type":"Retail Goods"
        }
    ],
    "sg:phone":"+1   ",
    "sg:postcode":"60515",
    "sg:province":"IL",
    "sg:tags":[
        "merchandise"
    ],
    "wof:name":"Cofax Business Systems",
    "wof:placetype":"venue"
},
  "geometry": {"coordinates":[-88.006671,41.809073],"type":"Point"}
}