{
  "type": "Feature",
  "properties": {
    "iso:country":"US",
    "sg:address":"115 W Central Rd",
    "sg:city":"Mount Prospect",
    "sg:classifiers":[
        {
            "category":"Food & Beverages",
            "subcategory":"Groceries & Convenience Stores",
            "type":"Retail Goods"
        }
    ],
    "sg:phone":"+1   ",
    "sg:postcode":"60056",
    "sg:province":"IL",
    "wof:name":"Around The Corner Market Inc",
    "wof:placetype":"venue"
},
  "geometry": {"coordinates":[-87.939458,42.066212],"type":"Point"}
}