{
  "type": "Feature",
  "properties": {
    "iso:country":"US",
    "sg:address":"101 N Skokie Hwy",
    "sg:city":"Lake Bluff",
    "sg:classifiers":[
        {
            "category":"Building & Trades",
            "subcategory":"Construction",
            "type":"Services"
        }
    ],
    "sg:phone":"+1 847 295 0415",
    "sg:postcode":"60044",
    "sg:province":"IL",
    "sg:tags":[
        "roofing",
        "contractor"
    ],
    "wof:name":"RCE Roofing",
    "wof:placetype":"venue"
},
  "geometry": {"coordinates":[-87.870504,42.282902],"type":"Point"}
}