{
  "type": "Feature",
  "properties": {
    "addr:full":"700 N Lake St Mundelein IL 60060",
    "addr:housenumber":"700",
    "addr:postcode":"60060",
    "addr:street":"N Lake St",
    "iso:country":"US",
    "sg:address":"700 N Lake St",
    "sg:city":"Mundelein",
    "sg:classifiers":[
        {
            "category":"Social Services",
            "type":"Services"
        },
        {
            "category":"Personal",
            "type":"Services"
        }
    ],
    "sg:phone":"+1 847 949 0063",
    "sg:postcode":"60060",
    "sg:province":"IL",
    "sg:tags":[
        "family",
        "counselors-licensed",
        "individual",
        "marriage",
        "child",
        "professional",
        "counselor"
    ],
    "sg:website":"http://www.melaniedillon.com",
    "wof:name":"Life Coach 4 Change",
    "wof:placetype":"venue"
},
  "geometry": {"coordinates":[-88.00402099999999,42.273762],"type":"Point"}
}