{
  "type": "Feature",
  "properties": {
    "addr:full":"615 Winnebago Trl Batavia IL 60510",
    "addr:housenumber":"615",
    "addr:postcode":"60510",
    "addr:street":"Winnebago Trl",
    "iso:country":"US",
    "sg:address":"615 Winnebago Trl",
    "sg:city":"Batavia",
    "sg:classifiers":[
        {
            "category":"Professional",
            "subcategory":"Lawyer & Legal Services",
            "type":"Services"
        }
    ],
    "sg:phone":"+1 630 406 8320",
    "sg:postcode":"60510",
    "sg:province":"IL",
    "sg:tags":[
        "attorney"
    ],
    "wof:name":"Helen M Bus",
    "wof:placetype":"venue"
},
  "geometry": {"coordinates":[-88.32913499999999,41.861344],"type":"Point"}
}