{
  "type": "Feature",
  "properties": {
    "addr:full":"3233 Broadway St Quincy IL 62301",
    "addr:housenumber":"3233",
    "addr:postcode":"62301",
    "addr:street":"Broadway St",
    "iso:country":"US",
    "sg:address":"3233 Broadway St",
    "sg:city":"Quincy",
    "sg:classifiers":[
        {
            "category":"Banks & Credit Unions",
            "subcategory":"Bank",
            "type":"Services"
        }
    ],
    "sg:phone":"+1 217 224 5700",
    "sg:postcode":"62301",
    "sg:province":"IL",
    "sg:tags":[
        "state"
    ],
    "wof:name":"First Bank",
    "wof:placetype":"venue"
},
  "geometry": {"coordinates":[-91.364525,39.935329],"type":"Point"}
}