{
  "type": "Feature",
  "properties": {
    "iso:country":"US",
    "sg:address":"100 E Central St",
    "sg:city":"Bethalto",
    "sg:classifiers":[
        {
            "category":"Social Services",
            "type":"Services"
        }
    ],
    "sg:phone":"+1 618 377 5263",
    "sg:postcode":"62010",
    "sg:province":"IL",
    "sg:tags":[
        "senior",
        "citizen"
    ],
    "wof:name":"Bethalto Senior Citizens Ctr",
    "wof:placetype":"venue"
},
  "geometry": {"coordinates":[-90.039639,38.911244],"type":"Point"}
}