{
  "type": "Feature",
  "properties": {
    "iso:country":"US",
    "sg:address":"5937 Sandy Hollow Rd",
    "sg:city":"Rockford",
    "sg:classifiers":[
        {
            "category":"Wholesale",
            "subcategory":"Motor Vehicles",
            "type":"Manufacturing & Wholesale Goods"
        }
    ],
    "sg:phone":"+1 815 874 7800",
    "sg:postcode":"61109",
    "sg:province":"IL",
    "sg:tags":[
        "auction",
        "automobile"
    ],
    "sg:website":"www.graa.net",
    "wof:name":"Greater Rockford Auto Auction",
    "wof:placetype":"venue"
},
  "geometry": {"coordinates":[-88.99986,42.22418],"type":"Point"}
}