{
  "type": "Feature",
  "properties": {
    "addr:full":"608 Breen Dr Champaign IL 61820",
    "addr:housenumber":"608",
    "addr:postcode":"61820",
    "addr:street":"Breen Dr",
    "iso:country":"US",
    "sg:address":"608 Breen Dr",
    "sg:city":"Champaign",
    "sg:classifiers":[
        {
            "category":"Shopping",
            "subcategory":"Clothing, Apparel, & Fashions",
            "type":"Retail Goods"
        }
    ],
    "sg:phone":"+1   ",
    "sg:postcode":"61820",
    "sg:province":"IL",
    "wof:name":"Made For You",
    "wof:placetype":"venue"
},
  "geometry": {"coordinates":[-88.25335,40.094135],"type":"Point"}
}