{
  "type": "Feature",
  "properties": {
    "iso:country":"US",
    "sg:address":"806 W George St",
    "sg:city":"Chicago",
    "sg:classifiers":[
        {
            "category":"Professional",
            "subcategory":"Management & Consulting",
            "type":"Services"
        }
    ],
    "sg:phone":"+1 312 420 5447",
    "sg:postcode":"60657",
    "sg:province":"IL",
    "wof:name":"J R Logan",
    "wof:placetype":"venue"
},
  "geometry": {"coordinates":[-87.649546,41.93461],"type":"Point"}
}