{
  "type": "Feature",
  "properties": {
    "iso:country":"US",
    "sg:address":"4907 Oakton St",
    "sg:city":"Skokie",
    "sg:classifiers":[
        {
            "category":"Restaurant",
            "type":"Food & Drink"
        }
    ],
    "sg:phone":"+1 847 674 5446",
    "sg:postcode":"60077",
    "sg:province":"IL",
    "sg:tags":[
        "italian"
    ],
    "wof:name":"Toscana Restaurant Inc",
    "wof:placetype":"venue"
},
  "geometry": {"coordinates":[-87.750103,42.026292],"type":"Point"}
}