{
  "type": "Feature",
  "properties": {
    "iso:country":"US",
    "sg:address":"1610 N Broadway Ave",
    "sg:city":"Salem",
    "sg:classifiers":[
        {
            "category":"Health Services",
            "subcategory":"Doctor",
            "type":"Services"
        }
    ],
    "sg:phone":"+1 618 548 4613",
    "sg:postcode":"62881",
    "sg:province":"IL",
    "sg:tags":[
        "physician",
        "family",
        "practice",
        "surgeons",
        "medicine"
    ],
    "wof:name":"Salem Family & Allergy Care",
    "wof:placetype":"venue"
},
  "geometry": {"coordinates":[-88.942943,38.643773],"type":"Point"}
}