{
  "type": "Feature",
  "properties": {
    "iso:country":"US",
    "sg:address":"850 Biesterfield Rd",
    "sg:city":"Elk Grove Village",
    "sg:classifiers":[
        {
            "category":"Health Services",
            "subcategory":"Doctor",
            "type":"Services"
        }
    ],
    "sg:phone":"+1 847 437 0061",
    "sg:postcode":"60007",
    "sg:province":"IL",
    "wof:name":"John L Gorny MD Ltd",
    "wof:placetype":"venue"
},
  "geometry": {"coordinates":[-88.017939,42.003529],"type":"Point"}
}