{
  "type": "Feature",
  "properties": {
    "iso:country":"US",
    "sg:address":"16970 US Hwy 150",
    "sg:city":"Orion",
    "sg:classifiers":[
        {
            "category":"Autos & Motor Vehicles",
            "subcategory":"Automobile Sales",
            "type":"Retail Goods"
        }
    ],
    "sg:phone":"+1   ",
    "sg:postcode":"61273",
    "sg:province":"IL",
    "sg:tags":[
        "supply"
    ],
    "wof:name":"MGF",
    "wof:placetype":"venue"
},
  "geometry": {"coordinates":[-90.415342,41.398174],"type":"Point"}
}