{
  "type": "Feature",
  "properties": {
    "iso:country":"US",
    "sg:address":"7548 S Halsted Street",
    "sg:city":"Chicago",
    "sg:classifiers":[
        {
            "category":"Home & Garden",
            "subcategory":"Furniture",
            "type":"Retail Goods"
        }
    ],
    "sg:phone":"+1 773 892 1808",
    "sg:postcode":"60620",
    "sg:province":"IL",
    "sg:tags":[
        "store"
    ],
    "wof:name":"Comfort Plus",
    "wof:placetype":"venue"
},
  "geometry": {"coordinates":[-87.644251,41.756208],"type":"Point"}
}