{
  "type": "Feature",
  "properties": {
    "iso:country":"US",
    "sg:address":"4325 Alby St",
    "sg:city":"Alton",
    "sg:classifiers":[
        {
            "category":"Professional",
            "subcategory":"Accounting & Tax Preparation",
            "type":"Services"
        }
    ],
    "sg:phone":"+1 618 462 0499",
    "sg:postcode":"62002",
    "sg:province":"IL",
    "sg:tags":[
        "billing"
    ],
    "wof:name":"Compas Central Billing Office",
    "wof:placetype":"venue"
},
  "geometry": {"coordinates":[-90.178531,38.923217],"type":"Point"}
}