{
  "type": "Feature",
  "properties": {
    "addr:full":"4887 Prestwick Pl Barrington IL 60010",
    "addr:housenumber":"4887",
    "addr:postcode":"60010",
    "addr:street":"Prestwick Pl",
    "iso:country":"US",
    "sg:address":"4887 Prestwick Pl",
    "sg:city":"Barrington",
    "sg:classifiers":[
        {
            "category":"Professional",
            "subcategory":"Management & Consulting",
            "type":"Services"
        }
    ],
    "sg:phone":"+1 847 776 0101",
    "sg:postcode":"60010",
    "sg:province":"IL",
    "sg:tags":[
        "business"
    ],
    "wof:name":"Tower Performance Group",
    "wof:placetype":"venue"
},
  "geometry": {"coordinates":[-88.115083,42.112329],"type":"Point"}
}