{
  "type": "Feature",
  "properties": {
    "iso:country":"US",
    "sg:address":"2334 Squaw Prairie Rd",
    "sg:city":"Belvidere",
    "sg:classifiers":[
        {
            "category":"Building & Trades",
            "subcategory":"Construction",
            "type":"Services"
        }
    ],
    "sg:phone":"+1 815 544 4272",
    "sg:postcode":"61008",
    "sg:province":"IL",
    "sg:tags":[
        "product",
        "asphalt"
    ],
    "wof:name":"A & G Blacktop Inc",
    "wof:placetype":"venue"
},
  "geometry": {"coordinates":[-88.895122,42.290914],"type":"Point"}
}