{
  "type": "Feature",
  "properties": {
    "addr:full":"152 S Waukegan Rd Deerfield IL 60015",
    "addr:housenumber":"152",
    "addr:postcode":"60015",
    "addr:street":"S Waukegan Rd",
    "iso:country":"US",
    "sg:address":"152 S Waukegan Rd",
    "sg:city":"Deerfield",
    "sg:classifiers":[
        {
            "category":"Shopping",
            "subcategory":"Clothing, Apparel, & Fashions",
            "type":"Retail Goods"
        },
        {
            "category":"Shopping",
            "subcategory":"Department Store",
            "type":"Retail Goods"
        },
        {
            "category":"Shopping",
            "subcategory":"Discount & Variety Stores",
            "type":"Retail Goods"
        }
    ],
    "sg:phone":"+1 847 562 4369",
    "sg:postcode":"60015",
    "sg:province":"IL",
    "sg:tags":[
        "apparel",
        "clothing",
        "women's"
    ],
    "sg:website":"http://www.tjx.com",
    "wof:name":"Tj Maxx",
    "wof:placetype":"venue"
},
  "geometry": {"coordinates":[-87.833686,42.150141],"type":"Point"}
}