{
  "type": "Feature",
  "properties": {
    "iso:country":"US",
    "sg:address":"427 W 2nd St",
    "sg:city":"Kewanee",
    "sg:classifiers":[
        {
            "category":"Retail",
            "subcategory":"Auto Repair",
            "type":"Services"
        }
    ],
    "sg:phone":"+1 309 852 2940",
    "sg:postcode":"61443",
    "sg:province":"IL",
    "sg:tags":[
        "general"
    ],
    "wof:name":"Car Care Plus",
    "wof:placetype":"venue"
},
  "geometry": {"coordinates":[-89.930357,41.244431],"type":"Point"}
}