{
  "type": "Feature",
  "properties": {
    "iso:country":"US",
    "sg:address":"3137 N Ayp Rd",
    "sg:city":"Lena",
    "sg:classifiers":[
        {
            "category":"Manufacturing",
            "subcategory":"Pet Food",
            "type":"Manufacturing & Wholesale Goods"
        },
        {
            "category":"Farming",
            "subcategory":"Farm",
            "type":"Manufacturing & Wholesale Goods"
        }
    ],
    "sg:phone":"+1 815 563 4561",
    "sg:postcode":"61048",
    "sg:province":"IL",
    "sg:tags":[
        "hay"
    ],
    "wof:name":"Leroy Jensen",
    "wof:placetype":"venue"
},
  "geometry": {"coordinates":[-89.71506100000001,42.344548],"type":"Point"}
}