{
  "type": "Feature",
  "properties": {
    "iso:country":"US",
    "sg:address":"1400 N 30th St",
    "sg:city":"Quincy",
    "sg:classifiers":[
        {
            "category":"Real Estate",
            "subcategory":"Real Estate Operator",
            "type":"Services"
        }
    ],
    "sg:phone":"+1 217 222 2725",
    "sg:postcode":"62301",
    "sg:province":"IL",
    "sg:tags":[
        "building",
        "nonresidential"
    ],
    "wof:name":"Quincy Development Center",
    "wof:placetype":"venue"
},
  "geometry": {"coordinates":[-91.36756200000001,39.948915],"type":"Point"}
}