{
  "type": "Feature",
  "properties": {
    "addr:full":"284 S Weber Rd Bolingbrook IL 60490",
    "addr:housenumber":"284",
    "addr:postcode":"60490",
    "addr:street":"S Weber Rd",
    "iso:country":"US",
    "sg:address":"284 S Weber Rd",
    "sg:city":"Bolingbrook",
    "sg:classifiers":[
        {
            "category":"Restaurant",
            "type":"Food & Drink"
        }
    ],
    "sg:phone":"+1 630 759 8022",
    "sg:postcode":"60490",
    "sg:province":"IL",
    "wof:name":"Aurelios Family Pizzeria",
    "wof:placetype":"venue"
},
  "geometry": {"coordinates":[-88.12579700000001,41.688422],"type":"Point"}
}