{
  "type": "Feature",
  "properties": {
    "iso:country":"US",
    "sg:address":"550 8th St",
    "sg:city":"Carlyle",
    "sg:classifiers":[
        {
            "category":"Health Services",
            "subcategory":"Doctor",
            "type":"Services"
        }
    ],
    "sg:phone":"+1 618 594 3361",
    "sg:postcode":"62231",
    "sg:province":"IL",
    "wof:name":"Sidney D Wessol DDS",
    "wof:placetype":"venue"
},
  "geometry": {"coordinates":[-89.36761799999999,38.610672],"type":"Point"}
}