{
  "type": "Feature",
  "properties": {
    "addr:full":"15090 N 225th St Brocton IL 61917",
    "addr:housenumber":"15090",
    "addr:postcode":"61917",
    "addr:street":"N 225Th St",
    "iso:country":"US",
    "sg:address":"15090 N 225th St",
    "sg:city":"Brocton",
    "sg:phone":"+1 217 385 2278",
    "sg:postcode":"61917",
    "sg:province":"IL",
    "sg:tags":[
        "farm",
        "corn",
        "soybean"
    ],
    "wof:name":"Ruth McGinness",
    "wof:placetype":"venue"
},
  "geometry": {"coordinates":[-87.923663,39.702471],"type":"Point"}
}