{
  "type": "Feature",
  "properties": {
    "iso:country":"US",
    "sg:address":"930 N Range Ln",
    "sg:city":"Peoria",
    "sg:classifiers":[
        {
            "category":"Place Of Worship",
            "subcategory":"Church",
            "type":"Public Place"
        },
        {
            "category":"Place Of Worship",
            "type":"Public Place"
        }
    ],
    "sg:phone":"+1 309 674 0500",
    "sg:postcode":"61604",
    "sg:province":"IL",
    "sg:tags":[
        "churches-methodist"
    ],
    "wof:name":"Bethel Free Methodist Church Thats My School",
    "wof:placetype":"venue"
},
  "geometry": {"coordinates":[-89.68155,40.697951],"type":"Point"}
}