{
  "type": "Feature",
  "properties": {
    "addr:full":"8504 S Stony Island Avenue Chicago IL 60617",
    "addr:housenumber":"8504",
    "addr:postcode":"60617",
    "addr:street":"S Stony Island Avenue",
    "iso:country":"US",
    "sg:address":"8504 S Stony Island Avenue",
    "sg:city":"Chicago",
    "sg:classifiers":[
        {
            "category":"Food & Beverages",
            "subcategory":"Specialty",
            "type":"Retail Goods"
        },
        {
            "category":"Insurance",
            "subcategory":"Health Insurance",
            "type":"Services"
        }
    ],
    "sg:phone":"+1 773 721 6611",
    "sg:postcode":"60617",
    "sg:province":"IL",
    "sg:tags":[
        "product",
        "market",
        "diet"
    ],
    "wof:name":"Natures Way Health Food Store",
    "wof:placetype":"venue"
},
  "geometry": {"coordinates":[-87.585855,41.740241],"type":"Point"}
}