{
  "type": "Feature",
  "properties": {
    "iso:country":"US",
    "sg:address":"2970 N Lake Shore Dr W",
    "sg:city":"Chicago",
    "sg:classifiers":[
        {
            "category":"Professional",
            "subcategory":"Business Services",
            "type":"Services"
        }
    ],
    "sg:phone":"+1 773 348 1972",
    "sg:postcode":"60657",
    "sg:province":"IL",
    "sg:tags":[
        "management",
        "electronic",
        "document"
    ],
    "wof:name":"LTI Consulting",
    "wof:placetype":"venue"
},
  "geometry": {"coordinates":[-87.63685099999999,41.936617],"type":"Point"}
}