{
  "type": "Feature",
  "properties": {
    "addr:full":"309 S 1st St Pinckneyville IL 62274",
    "addr:housenumber":"309",
    "addr:postcode":"62274",
    "addr:street":"S 1St St",
    "iso:country":"US",
    "sg:address":"309 S 1st St",
    "sg:city":"Pinckneyville",
    "sg:classifiers":[
        {
            "category":"Banks & Credit Unions",
            "subcategory":"Investment Brokerage",
            "type":"Services"
        },
        {
            "category":"Insurance",
            "subcategory":"Hazard Insurance",
            "type":"Services"
        },
        {
            "category":"Banks & Credit Unions",
            "subcategory":"Financial Services",
            "type":"Services"
        },
        {
            "category":"Insurance",
            "subcategory":"Life Insurance",
            "type":"Services"
        }
    ],
    "sg:phone":"+1 618 357 2124",
    "sg:postcode":"62274",
    "sg:province":"IL",
    "sg:website":"http://national.citysearch.com/profile/external/629339390/pinckneyville_il/country_financial_larry_woodside.html?publisher=yellowpages&reference_id=1&placement=ypwebsitemip",
    "wof:name":"COUNTRY Financial - Larry Woodside",
    "wof:placetype":"venue"
},
  "geometry": {"coordinates":[-89.379651,38.077331],"type":"Point"}
}