{
  "type": "Feature",
  "properties": {
    "iso:country":"US",
    "sg:address":"150 S Gary Ave",
    "sg:city":"Carol Stream",
    "sg:classifiers":[
        {
            "category":"Restaurant",
            "type":"Food & Drink"
        }
    ],
    "sg:phone":"+1 630 665 8300",
    "sg:postcode":"60188",
    "sg:province":"IL",
    "wof:name":"Fitzgerald's Tavern",
    "wof:placetype":"venue"
},
  "geometry": {"coordinates":[-88.120598,41.903099],"type":"Point"}
}