{
  "type": "Feature",
  "properties": {
    "iso:country":"US",
    "sg:address":"1620 25th St",
    "sg:city":"Highland",
    "sg:classifiers":[
        {
            "category":"Professional",
            "subcategory":"Business Services",
            "type":"Services"
        }
    ],
    "sg:phone":"+1 618 654 3147",
    "sg:postcode":"62249",
    "sg:province":"IL",
    "sg:tags":[
        "shop",
        "lettering",
        "painting",
        "sign"
    ],
    "wof:name":"Cindys Signs",
    "wof:placetype":"venue"
},
  "geometry": {"coordinates":[-89.670936,38.727305],"type":"Point"}
}