{
  "type": "Feature",
  "properties": {
    "iso:country":"US",
    "sg:address":"4554 N Broadway St",
    "sg:city":"Chicago",
    "sg:classifiers":[
        {
            "category":"Health Services",
            "subcategory":"Clinic",
            "type":"Services"
        }
    ],
    "sg:phone":"+1 773 784 8717",
    "sg:postcode":"60640",
    "sg:province":"IL",
    "sg:tags":[
        "home",
        "care"
    ],
    "wof:name":"Carepaks Health Services Inc",
    "wof:placetype":"venue"
},
  "geometry": {"coordinates":[-87.656182,41.963381],"type":"Point"}
}