{
  "type": "Feature",
  "properties": {
    "addr:full":"546 E Burnett Rd Island Lake IL 60042",
    "addr:housenumber":"546",
    "addr:postcode":"60042",
    "addr:street":"E Burnett Rd",
    "iso:country":"US",
    "sg:address":"546 E Burnett Rd",
    "sg:city":"Island Lake",
    "sg:classifiers":[
        {
            "category":"Retail",
            "subcategory":"Auto Repair",
            "type":"Services"
        }
    ],
    "sg:phone":"+1 847 487 7278",
    "sg:postcode":"60042",
    "sg:province":"IL",
    "sg:tags":[
        "body"
    ],
    "wof:name":"Unforgotten Past",
    "wof:placetype":"venue"
},
  "geometry": {"coordinates":[-88.19009200000001,42.285035],"type":"Point"}
}