{
  "type": "Feature",
  "properties": {
    "iso:country":"US",
    "sg:address":"5240 N. Pulaski Road",
    "sg:city":"Chicago",
    "sg:classifiers":[
        {
            "category":"Restaurant",
            "type":"Food & Drink"
        }
    ],
    "sg:phone":"+1 773 866 2868",
    "sg:postcode":"60686",
    "sg:province":"IL",
    "sg:tags":[
        "chinese"
    ],
    "wof:name":"May Flower",
    "wof:placetype":"venue"
},
  "geometry": {"coordinates":[-87.7285,41.976501],"type":"Point"}
}