{
  "type": "Feature",
  "properties": {
    "iso:country":"US",
    "sg:address":"900 Peale Ave",
    "sg:city":"Park Ridge",
    "sg:classifiers":[
        {
            "category":"Manufacturing",
            "subcategory":"Printing",
            "type":"Manufacturing & Wholesale Goods"
        }
    ],
    "sg:phone":"+1 847 692 2788",
    "sg:postcode":"60068",
    "sg:province":"IL",
    "sg:tags":[
        "lithographic",
        "commercial"
    ],
    "wof:name":"Graphic Impressions Too",
    "wof:placetype":"venue"
},
  "geometry": {"coordinates":[-87.825052,41.998574],"type":"Point"}
}