{
  "type": "Feature",
  "properties": {
    "iso:country":"US",
    "sg:address":"2144 Maple Rd",
    "sg:city":"Homewood",
    "sg:classifiers":[
        {
            "category":"Building & Trades",
            "subcategory":"Construction",
            "type":"Services"
        }
    ],
    "sg:phone":"+1 708 798 7889",
    "sg:postcode":"60430",
    "sg:province":"IL",
    "sg:tags":[
        "siding",
        "contractor"
    ],
    "wof:name":"Craftsmen Aluminum",
    "wof:placetype":"venue"
},
  "geometry": {"coordinates":[-87.667418,41.567501],"type":"Point"}
}