{
  "type": "Feature",
  "properties": {
    "iso:country":"US",
    "sg:address":"5220 Douglas Rd",
    "sg:city":"Oswego",
    "sg:classifiers":[
        {
            "category":"Animal Shelter",
            "type":"Public Place"
        },
        {
            "category":"Retail",
            "subcategory":"Pet Boarding",
            "type":"Services"
        }
    ],
    "sg:phone":"+1 630 551 1628",
    "sg:postcode":"60543",
    "sg:province":"IL",
    "sg:tags":[
        "kennel"
    ],
    "wof:name":"Dymondee Kennels",
    "wof:placetype":"venue"
},
  "geometry": {"coordinates":[-88.307877,41.646049],"type":"Point"}
}