{
  "type": "Feature",
  "properties": {
    "iso:country":"US",
    "sg:address":"28W140 High Lake Rd",
    "sg:city":"Winfield",
    "sg:classifiers":[
        {
            "category":"Home & Garden",
            "subcategory":"Garden Supply",
            "type":"Retail Goods"
        }
    ],
    "sg:phone":"+1 630 231 4992",
    "sg:postcode":"60190",
    "sg:province":"IL",
    "sg:tags":[
        "nursery",
        "gardening"
    ],
    "wof:name":"Prosek Greenhouses",
    "wof:placetype":"venue"
},
  "geometry": {"coordinates":[-88.158401,41.871399],"type":"Point"}
}