{
  "type": "Feature",
  "properties": {
    "iso:country":"US",
    "sg:address":"7719 W 60th Pl",
    "sg:city":"Summit Argo",
    "sg:classifiers":[
        {
            "category":"Wholesale",
            "subcategory":"Stationery",
            "type":"Manufacturing & Wholesale Goods"
        }
    ],
    "sg:phone":"+1 708 361 5987",
    "sg:postcode":"60501",
    "sg:province":"IL",
    "sg:tags":[
        "drum",
        "pail",
        "material",
        "packaging",
        "can",
        "container"
    ],
    "wof:name":"Chicago Can Company",
    "wof:placetype":"venue"
},
  "geometry": {"coordinates":[-87.813175,41.781567],"type":"Point"}
}