{
  "type": "Feature",
  "properties": {
    "iso:country":"US",
    "sg:address":"300 W Golf Rd",
    "sg:city":"Mount Prospect",
    "sg:classifiers":[
        {
            "category":"Insurance",
            "subcategory":"Insurance Agent",
            "type":"Services"
        }
    ],
    "sg:phone":"+1 847 259 4150",
    "sg:postcode":"60056",
    "sg:province":"IL",
    "wof:name":"State Farm Insurance",
    "wof:placetype":"venue"
},
  "geometry": {"coordinates":[-87.942138,42.047556],"type":"Point"}
}