{
  "type": "Feature",
  "properties": {
    "iso:country":"US",
    "sg:address":"2501 W Lawrence Avenue",
    "sg:city":"Chicago",
    "sg:classifiers":[
        {
            "category":"Health Services",
            "subcategory":"Doctor",
            "type":"Services"
        },
        {
            "category":"Community Center",
            "type":"Public Place"
        }
    ],
    "sg:phone":"+1 773 989 3344",
    "sg:postcode":"60625",
    "sg:province":"IL",
    "sg:tags":[
        "medical"
    ],
    "wof:name":"Lincoln Square Medical Center",
    "wof:placetype":"venue"
},
  "geometry": {"coordinates":[-87.69139,41.968561],"type":"Point"}
}