{
  "type": "Feature",
  "properties": {
    "iso:country":"US",
    "sg:address":"444 Pennsylvania Ave",
    "sg:city":"Glen Ellyn",
    "sg:classifiers":[
        {
            "category":"Wholesale",
            "subcategory":"Computers",
            "type":"Manufacturing & Wholesale Goods"
        }
    ],
    "sg:phone":"+1 630 545 9590",
    "sg:postcode":"60137",
    "sg:province":"IL",
    "wof:name":"Barcode Source Inc",
    "wof:placetype":"venue"
},
  "geometry": {"coordinates":[-88.071409,41.8768],"type":"Point"}
}