{
  "type": "Feature",
  "properties": {
    "iso:country":"US",
    "sg:address":"1275 W Galena Ave",
    "sg:city":"Freeport",
    "sg:classifiers":[
        {
            "category":"Shopping",
            "subcategory":"Discount & Variety Stores",
            "type":"Retail Goods"
        }
    ],
    "sg:phone":"+1   ",
    "sg:postcode":"61032",
    "sg:province":"IL",
    "wof:name":"Dollar General",
    "wof:placetype":"venue"
},
  "geometry": {"coordinates":[-89.643753,42.30157],"type":"Point"}
}