{
  "type": "Feature",
  "properties": {
    "iso:country":"US",
    "sg:address":"610 W Roosevelt Rd Ste B2",
    "sg:city":"Wheaton",
    "sg:classifiers":[
        {
            "category":"Professional",
            "subcategory":"Lawyer & Legal Services",
            "type":"Services"
        }
    ],
    "sg:phone":"+1 630 653 7710",
    "sg:postcode":"60187",
    "sg:province":"IL",
    "wof:name":"Didzerekis Paul P Atty",
    "wof:placetype":"venue"
},
  "geometry": {"coordinates":[-88.115402,41.858601],"type":"Point"}
}