{
  "type": "Feature",
  "properties": {
    "addr:full":"10720 1st Ct Mokena IL 60448",
    "addr:housenumber":"10720",
    "addr:postcode":"60448",
    "addr:street":"1St Ct",
    "iso:country":"US",
    "sg:address":"10720 1st Ct",
    "sg:city":"Mokena",
    "sg:classifiers":[
        {
            "category":"Social Services",
            "subcategory":"Child Care",
            "type":"Services"
        }
    ],
    "sg:phone":"+1 708 535 2342",
    "sg:postcode":"60448",
    "sg:province":"IL",
    "sg:tags":[
        "day"
    ],
    "wof:name":"Dawn Collins",
    "wof:placetype":"venue"
},
  "geometry": {"coordinates":[-87.878214,41.535851],"type":"Point"}
}