{
  "type": "Feature",
  "properties": {
    "iso:country":"US",
    "sg:address":"717 S Vermont St",
    "sg:city":"Palatine",
    "sg:classifiers":[
        {
            "category":"Wholesale",
            "subcategory":"Electrical",
            "type":"Manufacturing & Wholesale Goods"
        }
    ],
    "sg:phone":"+1 847 934 4975",
    "sg:postcode":"60067",
    "sg:province":"IL",
    "sg:tags":[
        "distributor",
        "computer",
        "component"
    ],
    "wof:name":"Neosong Usa Inc",
    "wof:placetype":"venue"
},
  "geometry": {"coordinates":[-88.037385,42.100615],"type":"Point"}
}