{
  "type": "Feature",
  "properties": {
    "addr:full":"2193 Old State Rd Jacksonville IL 62650",
    "addr:housenumber":"2193",
    "addr:postcode":"62650",
    "addr:street":"Old State Rd",
    "iso:country":"US",
    "sg:address":"2193 Old State Rd",
    "sg:city":"Jacksonville",
    "sg:classifiers":[
        {
            "category":"Manufacturing",
            "subcategory":"Rubber & Plastics",
            "type":"Manufacturing & Wholesale Goods"
        }
    ],
    "sg:phone":"+1 217 479 8200",
    "sg:postcode":"62650",
    "sg:province":"IL",
    "sg:tags":[
        "product",
        "m",
        "mfg"
    ],
    "wof:name":"Northernaire Manufacturing Co",
    "wof:placetype":"venue"
},
  "geometry": {"coordinates":[-90.185756,39.73563],"type":"Point"}
}