{
  "type": "Feature",
  "properties": {
    "iso:country":"US",
    "sg:address":"200 Water St",
    "sg:city":"Cahokia",
    "sg:classifiers":[
        {
            "category":"Organizations",
            "subcategory":"Religious Organization",
            "type":"Services"
        }
    ],
    "sg:phone":"+1 618 332 6534",
    "sg:postcode":"62206",
    "sg:province":"IL",
    "sg:tags":[
        "church"
    ],
    "wof:name":"Apostolic Pentecostal Church",
    "wof:placetype":"venue"
},
  "geometry": {"coordinates":[-90.190422,38.568687],"type":"Point"}
}