{
  "type": "Feature",
  "properties": {
    "addr:full":"9300 Weber Park Pl Skokie IL 60077",
    "addr:housenumber":"9300",
    "addr:postcode":"60077",
    "addr:street":"Weber Park Pl",
    "iso:country":"US",
    "sg:address":"9300 Weber Park Pl",
    "sg:city":"Skokie",
    "sg:classifiers":[
        {
            "category":"Recreation",
            "type":"Entertainment"
        }
    ],
    "sg:phone":"+1 847 674 1510",
    "sg:postcode":"60077",
    "sg:province":"IL",
    "wof:name":"Skatium",
    "wof:placetype":"venue"
},
  "geometry": {"coordinates":[-87.750641,42.048251],"type":"Point"}
}