{
  "type": "Feature",
  "properties": {
    "addr:full":"1370 Gateway Dr Elgin IL 60124",
    "addr:housenumber":"1370",
    "addr:postcode":"60124",
    "addr:street":"Gateway Dr",
    "iso:country":"US",
    "sg:address":"1370 Gateway Dr",
    "sg:city":"Elgin",
    "sg:classifiers":[
        {
            "category":"Wholesale",
            "subcategory":"Construction Materials",
            "type":"Manufacturing & Wholesale Goods"
        }
    ],
    "sg:phone":"+1 847 717 4920",
    "sg:postcode":"60124",
    "sg:province":"IL",
    "wof:name":"F H Premier Plywood",
    "wof:placetype":"venue"
},
  "geometry": {"coordinates":[-88.343283,42.067266],"type":"Point"}
}