{
  "type": "Feature",
  "properties": {
    "addr:full":"1311 S 6th St Springfield IL 62703",
    "addr:housenumber":"1311",
    "addr:postcode":"62703",
    "addr:street":"S 6Th St",
    "iso:country":"US",
    "sg:address":"1311 S 6th St",
    "sg:city":"Springfield",
    "sg:classifiers":[
        {
            "category":"Utilities",
            "subcategory":"Mobile Phone",
            "type":"Services"
        },
        {
            "category":"Shopping",
            "subcategory":"Mobile Phones",
            "type":"Retail Goods"
        },
        {
            "category":"Communications",
            "type":"Services"
        },
        {
            "category":"Internet Cafe",
            "subcategory":"None",
            "type":"Food & Drink"
        }
    ],
    "sg:phone":"+1 217 528 1800",
    "sg:postcode":"62703",
    "sg:province":"IL",
    "sg:tags":[
        "supply",
        "telephone",
        "wireless",
        "equipment",
        "paging",
        "signaling",
        "cellular",
        "provider"
    ],
    "sg:website":"http://www.att.com",
    "wof:name":"AT&T",
    "wof:placetype":"venue"
},
  "geometry": {"coordinates":[-89.648267,39.788106],"type":"Point"}
}