{
  "type": "Feature",
  "properties": {
    "iso:country":"US",
    "sg:address":"911 N Central Ave",
    "sg:city":"Wood Dale",
    "sg:classifiers":[
        {
            "category":"Organizations",
            "subcategory":"Community Association",
            "type":"Services"
        }
    ],
    "sg:phone":"+1 630 766 8340",
    "sg:postcode":"60191",
    "sg:province":"IL",
    "wof:name":"National 4-H Supply",
    "wof:placetype":"venue"
},
  "geometry": {"coordinates":[-87.976945,41.984097],"type":"Point"}
}