{
  "type": "Feature",
  "properties": {
    "iso:country":"US",
    "sg:address":"5955 W Walton St",
    "sg:city":"Chicago",
    "sg:classifiers":[
        {
            "category":"Retail",
            "subcategory":"Repair Shop",
            "type":"Services"
        }
    ],
    "sg:phone":"+1 773 921 8905",
    "sg:postcode":"60651",
    "sg:province":"IL",
    "sg:tags":[
        "repairing",
        "piano",
        "refinishing"
    ],
    "wof:name":"Frank Edwards Piano & Organ",
    "wof:placetype":"venue"
},
  "geometry": {"coordinates":[-87.773913,41.897391],"type":"Point"}
}