{
  "type": "Feature",
  "properties": {
    "iso:country":"US",
    "sg:address":"506 N Frontage Rd",
    "sg:city":"Bolingbrook",
    "sg:phone":"+1 630 783 1239",
    "sg:postcode":"60440",
    "sg:province":"IL",
    "sg:tags":[
        "equipment",
        "supply"
    ],
    "wof:name":"Zepole Restaurant Supply",
    "wof:placetype":"venue"
},
  "geometry": {"coordinates":[-88.088843,41.674814],"type":"Point"}
}