{
  "type": "Feature",
  "properties": {
    "iso:country":"US",
    "sg:address":"10412 S Kedzie Avenue",
    "sg:city":"Chicago",
    "sg:classifiers":[
        {
            "category":"Health Services",
            "subcategory":"Dentist",
            "type":"Services"
        }
    ],
    "sg:phone":"+1 773 233 1900",
    "sg:postcode":"60655",
    "sg:province":"IL",
    "wof:name":"Timeless Smiles Dental PC",
    "wof:placetype":"venue"
},
  "geometry": {"coordinates":[-87.70132099999999,41.703374],"type":"Point"}
}