{
  "type": "Feature",
  "properties": {
    "addr:full":"149 W Division St Chicago IL 60610",
    "addr:housenumber":"149",
    "addr:postcode":"60610",
    "addr:street":"W Division St",
    "iso:country":"US",
    "sg:address":"149 W Division St",
    "sg:city":"Chicago",
    "sg:classifiers":[
        {
            "category":"Retail",
            "subcategory":"Laundry & Dry Cleaning",
            "type":"Services"
        }
    ],
    "sg:phone":"+1 312 337 3390",
    "sg:postcode":"60610",
    "sg:province":"IL",
    "wof:name":"Best Cleaners",
    "wof:placetype":"venue"
},
  "geometry": {"coordinates":[-87.63400300000001,41.903702],"type":"Point"}
}