{
  "type": "Feature",
  "properties": {
    "addr:full":"2165 75th St Darien IL 60561",
    "addr:housenumber":"2165",
    "addr:postcode":"60561",
    "addr:street":"75Th St",
    "iso:country":"US",
    "sg:address":"2165 75th St",
    "sg:city":"Darien",
    "sg:classifiers":[
        {
            "category":"Bakery",
            "type":"Food & Drink"
        }
    ],
    "sg:menulink":"http://www.allmenus.com/il/downers-grove/103347-panera-bread/menu/",
    "sg:phone":"+1 630 824 4000",
    "sg:postcode":"60561",
    "sg:province":"IL",
    "sg:tags":[
        "american",
        "sandwich",
        "pastry"
    ],
    "wof:name":"Panera Bread",
    "wof:placetype":"venue"
},
  "geometry": {"coordinates":[-87.998722,41.751151],"type":"Point"}
}