{
  "type": "Feature",
  "properties": {
    "addr:full":"16909 S Gougar Rd Lockport IL 60441",
    "addr:housenumber":"16909",
    "addr:postcode":"60441",
    "addr:street":"S Gougar Rd",
    "iso:country":"US",
    "sg:address":"16909 S Gougar Rd",
    "sg:city":"Lockport",
    "sg:classifiers":[
        {
            "category":"Shopping",
            "subcategory":"Used Merchandise",
            "type":"Retail Goods"
        }
    ],
    "sg:phone":"+1   ",
    "sg:postcode":"60441",
    "sg:province":"IL",
    "wof:name":"Recollections",
    "wof:placetype":"venue"
},
  "geometry": {"coordinates":[-88.00672,41.58139],"type":"Point"}
}