{
  "type": "Feature",
  "properties": {
    "iso:country":"US",
    "sg:address":"1048 N Briegel St",
    "sg:city":"Columbia",
    "sg:classifiers":[
        {
            "category":"Education",
            "subcategory":"Special Training",
            "type":"Public Place"
        }
    ],
    "sg:phone":"+1 618 281 5543",
    "sg:postcode":"62236",
    "sg:province":"IL",
    "sg:tags":[
        "school",
        "music"
    ],
    "wof:name":"S Cullen Music Studio",
    "wof:placetype":"venue"
},
  "geometry": {"coordinates":[-90.20874999999999,38.454902],"type":"Point"}
}