{
  "type": "Feature",
  "properties": {
    "addr:full":"616 W Fulton St Chicago IL 60661",
    "addr:housenumber":"616",
    "addr:postcode":"60661",
    "addr:street":"W Fulton St",
    "iso:country":"US",
    "sg:address":"616 W Fulton St",
    "sg:city":"Chicago",
    "sg:classifiers":[
        {
            "category":"Professional",
            "subcategory":"Computer Services",
            "type":"Services"
        }
    ],
    "sg:phone":"+1 312 930 0383",
    "sg:postcode":"60661",
    "sg:province":"IL",
    "sg:tags":[
        "related"
    ],
    "wof:name":"Schaffner Interactive",
    "wof:placetype":"venue"
},
  "geometry": {"coordinates":[-87.64280599999999,41.886811],"type":"Point"}
}