{
  "type": "Feature",
  "properties": {
    "iso:country":"US",
    "sg:address":"203 W Main St",
    "sg:city":"Olney",
    "sg:classifiers":[
        {
            "category":"Retail",
            "subcategory":"Car Wash",
            "type":"Services"
        }
    ],
    "sg:phone":"+1 618 395 7019",
    "sg:postcode":"62450",
    "sg:province":"IL",
    "wof:name":"Kerr's Auto Shine",
    "wof:placetype":"venue"
},
  "geometry": {"coordinates":[-88.086065,38.731091],"type":"Point"}
}