{
  "type": "Feature",
  "properties": {
    "addr:full":"241 55th St Clarendon Hills IL 60514",
    "addr:housenumber":"241",
    "addr:postcode":"60514",
    "addr:street":"55Th St",
    "iso:country":"US",
    "sg:address":"241 55th St",
    "sg:city":"Clarendon Hills",
    "sg:classifiers":[
        {
            "category":"Restaurant",
            "type":"Food & Drink"
        }
    ],
    "sg:phone":"+1 630 325 1444",
    "sg:postcode":"60514",
    "sg:province":"IL",
    "sg:website":"www.burgerone.com",
    "wof:name":"Country House",
    "wof:placetype":"venue"
},
  "geometry": {"coordinates":[-87.955158,41.788695],"type":"Point"}
}