{
  "type": "Feature",
  "properties": {
    "iso:country":"US",
    "sg:address":"13814 S State St",
    "sg:city":"Riverdale",
    "sg:classifiers":[
        {
            "category":"Social Services",
            "subcategory":"Child Care",
            "type":"Services"
        }
    ],
    "sg:phone":"+1 708 841 0742",
    "sg:postcode":"60827",
    "sg:province":"IL",
    "sg:tags":[
        "day"
    ],
    "wof:name":"Sherry Little",
    "wof:placetype":"venue"
},
  "geometry": {"coordinates":[-87.622156,41.644406],"type":"Point"}
}