{
  "type": "Feature",
  "properties": {
    "iso:country":"US",
    "sg:address":"2718 Salisbury St",
    "sg:city":"Champaign",
    "sg:classifiers":[
        {
            "category":"Communications",
            "subcategory":"Film & Video Production",
            "type":"Services"
        }
    ],
    "sg:phone":"+1 217 403 0239",
    "sg:postcode":"61821",
    "sg:province":"IL",
    "sg:tags":[
        "motion",
        "electronic"
    ],
    "wof:name":"Viscog Productions Inc",
    "wof:placetype":"venue"
},
  "geometry": {"coordinates":[-88.258175,40.078938],"type":"Point"}
}