{
  "type": "Feature",
  "properties": {
    "iso:country":"US",
    "sg:address":"400 N 4th St Ofc 106",
    "sg:city":"Saint Louis",
    "sg:classifiers":[
        {
            "category":"Real Estate",
            "subcategory":"Real Estate Operator",
            "type":"Services"
        }
    ],
    "sg:phone":"+1 314 231 5444",
    "sg:postcode":"63102",
    "sg:province":"MO",
    "sg:tags":[
        "apartment"
    ],
    "sg:website":"www.gentryslanding.com",
    "wof:name":"Gentry's Landing Apartments",
    "wof:placetype":"venue"
},
  "geometry": {"coordinates":[-90.18710299999999,38.629299],"type":"Point"}
}