{
  "type": "Feature",
  "properties": {
    "iso:country":"US",
    "sg:address":"2751 Old Higgins Rd",
    "sg:city":"Elk Grove Village",
    "sg:classifiers":[
        {
            "category":"Freight",
            "type":"Transportation"
        }
    ],
    "sg:phone":"+1 847 427 8387",
    "sg:postcode":"60007",
    "sg:province":"IL",
    "sg:tags":[
        "forwarding"
    ],
    "wof:name":"Pilot Air Freight",
    "wof:placetype":"venue"
},
  "geometry": {"coordinates":[-87.940233,42.007094],"type":"Point"}
}