{
  "type": "Feature",
  "properties": {
    "addr:full":"2751 Old Higgins Rd Elk Grove Village IL 60007",
    "addr:housenumber":"2751",
    "addr:postcode":"60007",
    "addr:street":"Old Higgins Rd",
    "iso:country":"US",
    "sg:address":"2751 Old Higgins Rd",
    "sg:city":"Elk Grove Village",
    "sg:classifiers":[
        {
            "category":"Freight",
            "type":"Transportation"
        }
    ],
    "sg:phone":"+1 847 427 8387",
    "sg:postcode":"60007",
    "sg:province":"IL",
    "sg:tags":[
        "forwarding"
    ],
    "wof:name":"Pilot Air Freight",
    "wof:placetype":"venue"
},
  "geometry": {"coordinates":[-87.94023300000001,42.007094],"type":"Point"}
}