{
  "type": "Feature",
  "properties": {
    "addr:full":"1135 W Catalpa Ave Chicago IL 60640",
    "addr:housenumber":"1135",
    "addr:postcode":"60640",
    "addr:street":"W Catalpa Ave",
    "iso:country":"US",
    "sg:address":"1135 W Catalpa Ave",
    "sg:city":"Chicago",
    "sg:classifiers":[
        {
            "category":"Retail",
            "subcategory":"Auto Repair",
            "type":"Services"
        }
    ],
    "sg:phone":"+1 773 728 4367",
    "sg:postcode":"60640",
    "sg:province":"IL",
    "sg:tags":[
        "general"
    ],
    "wof:name":"Asian Complete Auto Repair",
    "wof:placetype":"venue"
},
  "geometry": {"coordinates":[-87.659052,41.981737],"type":"Point"}
}