{
  "type": "Feature",
  "properties": {
    "iso:country":"US",
    "sg:address":"346 N West St",
    "sg:city":"Jacksonville",
    "sg:classifiers":[
        {
            "category":"Professional",
            "subcategory":"Employment Agencies",
            "type":"Services"
        }
    ],
    "sg:phone":"+1 217 243 9675",
    "sg:postcode":"62650",
    "sg:province":"IL",
    "sg:tags":[
        "help",
        "contractor"
    ],
    "wof:name":"Workforce Solutions",
    "wof:placetype":"venue"
},
  "geometry": {"coordinates":[-90.23145,39.73609],"type":"Point"}
}