{
  "type": "Feature",
  "properties": {
    "iso:country":"US",
    "sg:address":"3945 W Grand Avenue",
    "sg:city":"Chicago",
    "sg:classifiers":[
        {
            "category":"Retail",
            "subcategory":"Auto Repair",
            "type":"Services"
        }
    ],
    "sg:phone":"+1 773 384 8743",
    "sg:postcode":"60651",
    "sg:province":"IL",
    "wof:name":"Natl Transmission Center",
    "wof:placetype":"venue"
},
  "geometry": {"coordinates":[-87.72545599999999,41.905631],"type":"Point"}
}