{
  "type": "Feature",
  "properties": {
    "addr:full":"1819 Spruce Hill Dr Belleville IL 62221",
    "addr:housenumber":"1819",
    "addr:postcode":"62221",
    "addr:street":"Spruce Hill Dr",
    "iso:country":"US",
    "sg:address":"1819 Spruce Hill Dr",
    "sg:city":"Belleville",
    "sg:classifiers":[
        {
            "category":"Freight",
            "type":"Transportation"
        }
    ],
    "sg:phone":"+1 618 277 5620",
    "sg:postcode":"62221",
    "sg:province":"IL",
    "sg:tags":[
        "operator",
        "trucking"
    ],
    "wof:name":"Bill and Billie Express",
    "wof:placetype":"venue"
},
  "geometry": {"coordinates":[-89.950074,38.527681],"type":"Point"}
}