{
  "type": "Feature",
  "properties": {
    "addr:full":"2366 Sunrise Cir Aurora IL 60503",
    "addr:housenumber":"2366",
    "addr:postcode":"60503",
    "addr:street":"Sunrise Cir",
    "iso:country":"US",
    "sg:address":"2366 Sunrise Cir",
    "sg:city":"Aurora",
    "sg:classifiers":[
        {
            "category":"Freight",
            "type":"Transportation"
        }
    ],
    "sg:phone":"+1 630 803 3338",
    "sg:postcode":"60503",
    "sg:province":"IL",
    "sg:tags":[
        "trucking"
    ],
    "wof:name":"All State Transport",
    "wof:placetype":"venue"
},
  "geometry": {"coordinates":[-88.255517,41.710666],"type":"Point"}
}