{
  "type": "Feature",
  "properties": {
    "iso:country":"US",
    "sg:address":"6323 E Riverside Blvd",
    "sg:city":"Rockford",
    "sg:classifiers":[
        {
            "category":"Professional",
            "subcategory":"Lawyer & Legal Services",
            "type":"Services"
        }
    ],
    "sg:phone":"+1 815 226 7700",
    "sg:postcode":"61114",
    "sg:province":"IL",
    "sg:tags":[
        "attorney"
    ],
    "wof:name":"Cicero & France P C",
    "wof:placetype":"venue"
},
  "geometry": {"coordinates":[-88.992391,42.31853],"type":"Point"}
}