{
  "type": "Feature",
  "properties": {
    "iso:country":"US",
    "sg:address":"1832 Vandalia St",
    "sg:city":"Collinsville",
    "sg:classifiers":[
        {
            "category":"Wholesale",
            "subcategory":"Medical Equipment & Supplies",
            "type":"Manufacturing & Wholesale Goods"
        },
        {
            "category":"Health Services",
            "subcategory":"Hospital",
            "type":"Services"
        },
        {
            "category":"Building & Trades",
            "subcategory":"Construction",
            "type":"Services"
        }
    ],
    "sg:phone":"+1 618 345 0649",
    "sg:postcode":"62234",
    "sg:province":"IL",
    "sg:tags":[
        "wheelchair",
        "lift",
        "ramp",
        "oxygen"
    ],
    "sg:website":"http://www.foxmed-equip.com",
    "wof:name":"Fox Med-Equip Services Inc.",
    "wof:placetype":"venue"
},
  "geometry": {"coordinates":[-89.970779,38.692799],"type":"Point"}
}