{
  "type": "Feature",
  "properties": {
    "addr:full":"3445 Lonergan Dr Rockford IL 61109",
    "addr:housenumber":"3445",
    "addr:postcode":"61109",
    "addr:street":"Lonergan Dr",
    "iso:country":"US",
    "sg:address":"3445 Lonergan Dr",
    "sg:city":"Rockford",
    "sg:classifiers":[
        {
            "category":"Manufacturing",
            "subcategory":"Tools & Machinery",
            "type":"Manufacturing & Wholesale Goods"
        }
    ],
    "sg:phone":"+1 815 874 9421",
    "sg:postcode":"61109",
    "sg:province":"IL",
    "sg:tags":[
        "head",
        "drill"
    ],
    "sg:website":"www.rockforddrillhead.com",
    "wof:name":"Rockford Drill Head",
    "wof:placetype":"venue"
},
  "geometry": {"coordinates":[-89.02715000000001,42.22566],"type":"Point"}
}