{
  "type": "Feature",
  "properties": {
    "iso:country":"US",
    "sg:address":"9721 Grand Ave",
    "sg:city":"Franklin Park",
    "sg:classifiers":[
        {
            "category":"Restaurant",
            "type":"Food & Drink"
        }
    ],
    "sg:phone":"+1   ",
    "sg:postcode":"60131",
    "sg:province":"IL",
    "wof:name":"Gallery Restaurant & Bar Inc",
    "wof:placetype":"venue"
},
  "geometry": {"coordinates":[-87.868177,41.929698],"type":"Point"}
}