{
  "type": "Feature",
  "properties": {
    "addr:full":"7173 W Grand Ave Chicago IL 60707",
    "addr:housenumber":"7173",
    "addr:postcode":"60707",
    "addr:street":"W Grand Ave",
    "iso:country":"US",
    "sg:address":"7173 W Grand Ave",
    "sg:city":"Chicago",
    "sg:classifiers":[
        {
            "category":"Bars & Pubs",
            "subcategory":"Sports Bar",
            "type":"Food & Drink"
        }
    ],
    "sg:phone":"+1 773 622 3556",
    "sg:postcode":"60707",
    "sg:province":"IL",
    "wof:name":"Eva's Sports Bar",
    "wof:placetype":"venue"
},
  "geometry": {"coordinates":[-87.80529900000001,41.923798],"type":"Point"}
}