{
  "type": "Feature",
  "properties": {
    "addr:full":"1323 Golf Rd Rolling Meadows IL 60008",
    "addr:housenumber":"1323",
    "addr:postcode":"60008",
    "addr:street":"Golf Rd",
    "iso:country":"US",
    "sg:address":"1323 Golf Rd",
    "sg:city":"Rolling Meadows",
    "sg:classifiers":[
        {
            "category":"Restaurant",
            "type":"Food & Drink"
        }
    ],
    "sg:menulink":"http://www.allmenus.com/il/elk-grove/152336-honeybaked-ham/menu/",
    "sg:phone":"+1 847 981 9790",
    "sg:postcode":"60008",
    "sg:province":"IL",
    "sg:tags":[
        "american"
    ],
    "wof:name":"The HoneyBaked Ham Company",
    "wof:placetype":"venue"
},
  "geometry": {"coordinates":[-87.995788,42.051286],"type":"Point"}
}