{
  "type": "Feature",
  "properties": {
    "iso:country":"US",
    "sg:address":"100 W Monroe Street Suite 400",
    "sg:city":"Chicago",
    "sg:classifiers":[
        {
            "category":"Banks & Credit Unions",
            "subcategory":"Financial Services",
            "type":"Services"
        }
    ],
    "sg:phone":"+1 312 220 0001",
    "sg:postcode":"60603",
    "sg:province":"IL",
    "sg:website":"www.kensington-research.com",
    "wof:name":"Kensington Research & Recovery",
    "wof:placetype":"venue"
},
  "geometry": {"coordinates":[-87.63111600000001,41.880759],"type":"Point"}
}