{
  "type": "Feature",
  "properties": {
    "iso:country":"US",
    "sg:address":"1005 Alexander Ct",
    "sg:city":"Cary",
    "sg:classifiers":[
        {
            "category":"Health Services",
            "subcategory":"Clinic",
            "type":"Services"
        },
        {
            "category":"Health Services",
            "subcategory":"Doctor",
            "type":"Services"
        }
    ],
    "sg:phone":"+1 847 462 0589",
    "sg:postcode":"60013",
    "sg:province":"IL",
    "sg:tags":[
        "physician",
        "medical",
        "group"
    ],
    "wof:name":"McHenry County Physicians Ctr",
    "wof:placetype":"venue"
},
  "geometry": {"coordinates":[-88.273535,42.221617],"type":"Point"}
}