{
  "type": "Feature",
  "properties": {
    "iso:country":"US",
    "sg:address":"848 E Anderson Dr",
    "sg:city":"Palatine",
    "sg:classifiers":[
        {
            "category":"Professional",
            "subcategory":"Secretarial Services",
            "type":"Services"
        }
    ],
    "sg:phone":"+1 847 991 5353",
    "sg:postcode":"60074",
    "sg:province":"IL",
    "sg:tags":[
        "reporting"
    ],
    "wof:name":"Axelson Communications",
    "wof:placetype":"venue"
},
  "geometry": {"coordinates":[-88.020393,42.119641],"type":"Point"}
}