{
  "type": "Feature",
  "properties": {
    "addr:full":"10203 Klenke Rd Alhambra IL 62001",
    "addr:housenumber":"10203",
    "addr:postcode":"62001",
    "addr:street":"Klenke Rd",
    "iso:country":"US",
    "sg:address":"10203 Klenke Rd",
    "sg:city":"Alhambra",
    "sg:phone":"+1 618 488 7931",
    "sg:postcode":"62001",
    "sg:province":"IL",
    "sg:tags":[
        "farm",
        "corn",
        "beef",
        "feedlot",
        "cattle"
    ],
    "wof:name":"George Sconyers",
    "wof:placetype":"venue"
},
  "geometry": {"coordinates":[-89.792748,38.852107],"type":"Point"}
}