{
  "type": "Feature",
  "properties": {
    "iso:country":"US",
    "sg:address":"5757 S Woodlawn Ave",
    "sg:city":"Chicago",
    "sg:classifiers":[
        {
            "category":"Landmark",
            "subcategory":"Historic",
            "type":"Public Place"
        }
    ],
    "sg:phone":"+1 708 848 1976",
    "sg:postcode":"60607",
    "sg:province":"IL",
    "sg:tags":[
        "building",
        "historical"
    ],
    "sg:website":"www.wrightplus.org/robiehouse/ro...",
    "wof:name":"Frederick C. Robie House",
    "wof:placetype":"venue"
},
  "geometry": {"coordinates":[-87.59593599999999,41.789937],"type":"Point"}
}