{
  "type": "Feature",
  "properties": {
    "iso:country":"US",
    "sg:address":"224 Stratford Square Mall Ste B24",
    "sg:city":"Bloomingdale",
    "sg:classifiers":[
        {
            "category":"Shopping",
            "subcategory":"Clothing, Apparel, & Fashions",
            "type":"Retail Goods"
        },
        {
            "category":"Shopping",
            "subcategory":"Shoes",
            "type":"Retail Goods"
        }
    ],
    "sg:phone":"+1 630 307 6271",
    "sg:postcode":"60108",
    "sg:province":"IL",
    "sg:tags":[
        "accessory",
        "store",
        "women's"
    ],
    "sg:website":"http://www.paylessshoesource.com",
    "wof:name":"Payless ShoeSource",
    "wof:placetype":"venue"
},
  "geometry": {"coordinates":[-88.114216,41.951456],"type":"Point"}
}