{
  "type": "Feature",
  "properties": {
    "iso:country":"US",
    "sg:address":"17625 Torrence Ave",
    "sg:city":"Lansing",
    "sg:classifiers":[
        {
            "category":"Shopping",
            "subcategory":"Stationery & Office Supplies",
            "type":"Retail Goods"
        }
    ],
    "sg:phone":"+1 708 895 2119",
    "sg:postcode":"60438",
    "sg:province":"IL",
    "sg:tags":[
        "equipment"
    ],
    "wof:name":"Furnituremax",
    "wof:placetype":"venue"
},
  "geometry": {"coordinates":[-87.558701,41.574299],"type":"Point"}
}