{
  "type": "Feature",
  "properties": {
    "iso:country":"US",
    "sg:address":"400 E Gregory St",
    "sg:city":"Mount Prospect",
    "sg:classifiers":[
        {
            "category":"Organizations",
            "subcategory":"Religious Organization",
            "type":"Services"
        }
    ],
    "sg:phone":"+1 847 590 1925",
    "sg:postcode":"60056",
    "sg:province":"IL",
    "wof:name":"Agfg Chicago School Theology",
    "wof:placetype":"venue"
},
  "geometry": {"coordinates":[-87.929954,42.073485],"type":"Point"}
}