{
  "type": "Feature",
  "properties": {
    "addr:full":"1677 Elmhurst Rd Elk Grove Village IL 60007",
    "addr:housenumber":"1677",
    "addr:postcode":"60007",
    "addr:street":"Elmhurst Rd",
    "iso:country":"US",
    "sg:address":"1677 Elmhurst Rd",
    "sg:city":"Elk Grove Village",
    "sg:classifiers":[
        {
            "category":"Wholesale",
            "subcategory":"Apparel",
            "type":"Manufacturing & Wholesale Goods"
        }
    ],
    "sg:phone":"+1 847 981 1816",
    "sg:postcode":"60007",
    "sg:province":"IL",
    "sg:tags":[
        "piece"
    ],
    "wof:name":"Wisconsin Drapery Supply Inc",
    "wof:placetype":"venue"
},
  "geometry": {"coordinates":[-87.94004099999999,42.00167],"type":"Point"}
}