{
  "type": "Feature",
  "properties": {
    "iso:country":"US",
    "sg:address":"920 Lindeman Ave",
    "sg:city":"Dupo",
    "sg:classifiers":[
        {
            "category":"Utilities",
            "subcategory":"Refuse",
            "type":"Services"
        }
    ],
    "sg:phone":"+1 618 286 6732",
    "sg:postcode":"62239",
    "sg:province":"IL",
    "sg:tags":[
        "system"
    ],
    "wof:name":"Patriot Waste Inc",
    "wof:placetype":"venue"
},
  "geometry": {"coordinates":[-90.201728,38.516808],"type":"Point"}
}