{
  "type": "Feature",
  "properties": {
    "addr:full":"7303 Northgate Way Downers Grove IL 60516",
    "addr:housenumber":"7303",
    "addr:postcode":"60516",
    "addr:street":"Northgate Way",
    "iso:country":"US",
    "sg:address":"7303 Northgate Way",
    "sg:city":"Downers Grove",
    "sg:classifiers":[
        {
            "category":"Wholesale",
            "subcategory":"Non-durable Goods",
            "type":"Manufacturing & Wholesale Goods"
        }
    ],
    "sg:phone":"+1 630 435 0520",
    "sg:postcode":"60516",
    "sg:province":"IL",
    "wof:name":"7 Seas Imports",
    "wof:placetype":"venue"
},
  "geometry": {"coordinates":[-87.99951,41.754613],"type":"Point"}
}