{
  "type": "Feature",
  "properties": {
    "iso:country":"US",
    "sg:address":"115 N Clinton St",
    "sg:city":"Breese",
    "sg:classifiers":[
        {
            "category":"Professional",
            "subcategory":"Accounting & Tax Preparation",
            "type":"Services"
        }
    ],
    "sg:phone":"+1 618 526 2233",
    "sg:postcode":"62230",
    "sg:province":"IL",
    "wof:name":"Rickhoff & Associates",
    "wof:placetype":"venue"
},
  "geometry": {"coordinates":[-89.528953,38.608612],"type":"Point"}
}