{
  "type": "Feature",
  "properties": {
    "iso:country":"US",
    "sg:address":"580 Peachtree Ln",
    "sg:city":"Lake Zurich",
    "sg:classifiers":[
        {
            "category":"Professional",
            "subcategory":"Accounting & Tax Preparation",
            "type":"Services"
        }
    ],
    "sg:phone":"+1 847 540 0068",
    "sg:postcode":"60047",
    "sg:province":"IL",
    "sg:tags":[
        "accountant"
    ],
    "wof:name":"Fine Roth & Co",
    "wof:placetype":"venue"
},
  "geometry": {"coordinates":[-88.109248,42.18406],"type":"Point"}
}