{
  "type": "Feature",
  "properties": {
    "iso:country":"US",
    "sg:address":"1 Old Barn Rd",
    "sg:city":"Lake Zurich",
    "sg:classifiers":[
        {
            "category":"Real Estate",
            "subcategory":"Real Estate Operator",
            "type":"Services"
        }
    ],
    "sg:phone":"+1 847 550 5403",
    "sg:postcode":"60047",
    "sg:province":"IL",
    "sg:tags":[
        "building",
        "nonresidential"
    ],
    "wof:name":"Agarwal Properties",
    "wof:placetype":"venue"
},
  "geometry": {"coordinates":[-88.027985,42.210727],"type":"Point"}
}