{
  "type": "Feature",
  "properties": {
    "iso:country":"US",
    "sg:address":"7550 Kostner Ave",
    "sg:city":"Skokie",
    "sg:classifiers":[
        {
            "category":"Social Services",
            "subcategory":"Adult Care",
            "type":"Services"
        },
        {
            "category":"Health Services",
            "subcategory":"Nursing And Care Facility",
            "type":"Services"
        }
    ],
    "sg:phone":"+1 847 675 8580",
    "sg:postcode":"60076",
    "sg:province":"IL",
    "sg:tags":[
        "skilled",
        "residential",
        "retirement",
        "community",
        "home"
    ],
    "wof:name":"Council For The Jewish Elderly",
    "wof:placetype":"venue"
},
  "geometry": {"coordinates":[-87.738146,42.017635],"type":"Point"}
}