{
  "type": "Feature",
  "properties": {
    "iso:country":"US",
    "sg:address":"1202 E State St",
    "sg:city":"Rockford",
    "sg:classifiers":[
        {
            "category":"Building & Trades",
            "subcategory":"Construction",
            "type":"Services"
        }
    ],
    "sg:phone":"+1 815 633 3333",
    "sg:postcode":"61104",
    "sg:province":"IL",
    "sg:tags":[
        "siding",
        "contractor"
    ],
    "wof:name":"Littlefield Siding",
    "wof:placetype":"venue"
},
  "geometry": {"coordinates":[-89.074648,42.267005],"type":"Point"}
}