{
  "type": "Feature",
  "properties": {
    "iso:country":"US",
    "sg:address":"2619 W Pearl City Rd",
    "sg:city":"Freeport",
    "sg:classifiers":[
        {
            "category":"Real Estate",
            "subcategory":"Developer",
            "type":"Services"
        }
    ],
    "sg:phone":"+1 815 297 9999",
    "sg:postcode":"61032",
    "sg:province":"IL",
    "sg:tags":[
        "cemetery",
        "association"
    ],
    "wof:name":"Oakland Cemetery Assn Freeport",
    "wof:placetype":"venue"
},
  "geometry": {"coordinates":[-89.66310799999999,42.28382],"type":"Point"}
}