{
  "type": "Feature",
  "properties": {
    "iso:country":"US",
    "sg:address":"3612 W Chicago Ave",
    "sg:city":"Chicago",
    "sg:classifiers":[
        {
            "category":"Place Of Worship",
            "subcategory":"Church",
            "type":"Public Place"
        },
        {
            "category":"Place Of Worship",
            "type":"Public Place"
        },
        {
            "category":"Organizations",
            "subcategory":"Religious Organization",
            "type":"Services"
        }
    ],
    "sg:phone":"+1 773 384 4266",
    "sg:postcode":"60651",
    "sg:province":"IL",
    "sg:tags":[
        "god",
        "churches-church",
        "churches-pentecostal"
    ],
    "wof:name":"Sanctuary Of Faith Church-God",
    "wof:placetype":"venue"
},
  "geometry": {"coordinates":[-87.71682300000001,41.895492],"type":"Point"}
}