{
  "type": "Feature",
  "properties": {
    "addr:full":"5225 N Oriole Ave Chicago IL 60656",
    "addr:housenumber":"5225",
    "addr:postcode":"60656",
    "addr:street":"N Oriole Ave",
    "iso:country":"US",
    "sg:address":"5225 N Oriole Ave",
    "sg:city":"Chicago",
    "sg:classifiers":[
        {
            "category":"Sports & Exercise",
            "subcategory":"Gym",
            "type":"Entertainment"
        }
    ],
    "sg:phone":"+1 773 631 7425",
    "sg:postcode":"60656",
    "sg:province":"IL",
    "sg:tags":[
        "instruction",
        "gymnastics"
    ],
    "wof:name":"Gymnastics Stars Academy Inc",
    "wof:placetype":"venue"
},
  "geometry": {"coordinates":[-87.816906,41.974745],"type":"Point"}
}