{
  "type": "Feature",
  "properties": {
    "iso:country":"US",
    "sg:address":"7241 Roosevelt Rd",
    "sg:city":"Forest Park",
    "sg:phone":"+1 312 243 3720",
    "sg:postcode":"60130",
    "sg:province":"IL",
    "sg:tags":[
        "repair",
        "industrial",
        "scale",
        "lease"
    ],
    "wof:name":"C & M Scale Co",
    "wof:placetype":"venue"
},
  "geometry": {"coordinates":[-87.80593,41.865041],"type":"Point"}
}