{
  "type": "Feature",
  "properties": {
    "iso:country":"US",
    "sg:address":"1065 S Washington Ave",
    "sg:city":"Kankakee",
    "sg:classifiers":[
        {
            "category":"Social Services",
            "type":"Services"
        }
    ],
    "sg:phone":"+1 815 937 9199",
    "sg:postcode":"60901",
    "sg:province":"IL",
    "sg:tags":[
        "organization",
        "welfare"
    ],
    "wof:name":"K C C Parent Program",
    "wof:placetype":"venue"
},
  "geometry": {"coordinates":[-87.869909,41.108844],"type":"Point"}
}