{
  "type": "Feature",
  "properties": {
    "addr:full":"205 Dulles Rd Des Plaines IL 60016",
    "addr:housenumber":"205",
    "addr:postcode":"60016",
    "addr:street":"Dulles Rd Des",
    "iso:country":"US",
    "sg:address":"205 Dulles Rd",
    "sg:city":"Des Plaines",
    "sg:classifiers":[
        {
            "category":"Wholesale",
            "subcategory":"Toys & Hobbies",
            "type":"Manufacturing & Wholesale Goods"
        }
    ],
    "sg:phone":"+1 847 893 7546",
    "sg:postcode":"60016",
    "sg:province":"IL",
    "sg:tags":[
        "consulting"
    ],
    "wof:name":"International Trading",
    "wof:placetype":"venue"
},
  "geometry": {"coordinates":[-87.924977,42.044832],"type":"Point"}
}