{
  "type": "Feature",
  "properties": {
    "addr:full":"119 W 3rd St Beardstown IL 62618",
    "addr:housenumber":"119",
    "addr:postcode":"62618",
    "addr:street":"W 3Rd St",
    "iso:country":"US",
    "sg:address":"119 W 3rd St",
    "sg:city":"Beardstown",
    "sg:classifiers":[
        {
            "category":"Place Of Worship",
            "subcategory":"Church",
            "type":"Public Place"
        },
        {
            "category":"Place Of Worship",
            "type":"Public Place"
        }
    ],
    "sg:phone":"+1 217 323 1457",
    "sg:postcode":"62618",
    "sg:province":"IL",
    "sg:tags":[
        "christ",
        "denomination",
        "testament",
        "churches-church",
        "churches-interdenominational",
        "christ-new",
        "churches-various"
    ],
    "wof:name":"First Cngregational Untd Ch Ch",
    "wof:placetype":"venue"
},
  "geometry": {"coordinates":[-90.433967,40.016511],"type":"Point"}
}