{
  "type": "Feature",
  "properties": {
    "iso:country":"US",
    "sg:address":"1397 Schrader Ln",
    "sg:city":"New Boston",
    "sg:classifiers":[
        {
            "category":"Real Estate",
            "subcategory":"Real Estate Operator",
            "type":"Services"
        }
    ],
    "sg:phone":"+1 309 537 3326",
    "sg:postcode":"61272",
    "sg:province":"IL",
    "sg:tags":[
        "property",
        "lessor"
    ],
    "wof:name":"Walter Marshall",
    "wof:placetype":"venue"
},
  "geometry": {"coordinates":[-90.97207,41.263382],"type":"Point"}
}