{
  "type": "Feature",
  "properties": {
    "addr:full":"4222 N Ashland Ave Chicago IL 60613",
    "addr:housenumber":"4222",
    "addr:postcode":"60613",
    "addr:street":"N Ashland Ave",
    "iso:country":"US",
    "sg:address":"4222 N Ashland Ave",
    "sg:city":"Chicago",
    "sg:classifiers":[
        {
            "category":"Real Estate",
            "subcategory":"Real Estate Operator",
            "type":"Services"
        }
    ],
    "sg:phone":"+1 773 477 3487",
    "sg:postcode":"60613",
    "sg:province":"IL",
    "sg:tags":[
        "apartment"
    ],
    "wof:name":"Drw Holdings",
    "wof:placetype":"venue"
},
  "geometry": {"coordinates":[-87.669388,41.958364],"type":"Point"}
}