{
  "type": "Feature",
  "properties": {
    "iso:country":"US",
    "sg:address":"808 Villa St",
    "sg:city":"Elgin",
    "sg:classifiers":[
        {
            "category":"Sports & Exercise",
            "subcategory":"Bowling",
            "type":"Entertainment"
        }
    ],
    "sg:phone":"+1   ",
    "sg:postcode":"60120",
    "sg:province":"IL",
    "sg:tags":[
        "lounge",
        "alley"
    ],
    "wof:name":"Bowlway Enterprises Inc",
    "wof:placetype":"venue"
},
  "geometry": {"coordinates":[-88.258893,42.027547],"type":"Point"}
}