{
  "type": "Feature",
  "properties": {
    "iso:country":"US",
    "sg:address":"1704 Broadway St",
    "sg:city":"Quincy",
    "sg:classifiers":[
        {
            "category":"Health Services",
            "subcategory":"Optometrist",
            "type":"Services"
        },
        {
            "category":"Shopping",
            "subcategory":"Optical Goods",
            "type":"Retail Goods"
        },
        {
            "category":"Shopping",
            "subcategory":"Optician",
            "type":"Retail Goods"
        }
    ],
    "sg:phone":"+1 217 222 2020",
    "sg:postcode":"62301",
    "sg:province":"IL",
    "sg:tags":[
        "lens",
        "contact"
    ],
    "sg:website":"http://www.2020eyecareinc.com",
    "wof:name":"20/20 EyeCare Inc",
    "wof:placetype":"venue"
},
  "geometry": {"coordinates":[-91.38870300000001,39.935531],"type":"Point"}
}