{
  "type": "Feature",
  "properties": {
    "iso:country":"US",
    "sg:address":"2918 Becket Ave",
    "sg:city":"Westchester",
    "sg:classifiers":[
        {
            "category":"Organizations",
            "subcategory":"Professional Association",
            "type":"Services"
        }
    ],
    "sg:phone":"+1 630 771 6166",
    "sg:postcode":"60154",
    "sg:province":"IL",
    "sg:tags":[
        "mail-order",
        "fulfillment"
    ],
    "wof:name":"Innotrac Corp",
    "wof:placetype":"venue"
},
  "geometry": {"coordinates":[-87.893263,41.836882],"type":"Point"}
}