{
  "type": "Feature",
  "properties": {
    "iso:country":"US",
    "sg:address":"4554 N Broadway St",
    "sg:city":"Chicago",
    "sg:classifiers":[
        {
            "category":"Professional",
            "subcategory":"Accounting & Tax Preparation",
            "type":"Services"
        }
    ],
    "sg:phone":"+1 773 506 6630",
    "sg:postcode":"60640",
    "sg:province":"IL",
    "wof:name":"Adjetey & Bell Ltd",
    "wof:placetype":"venue"
},
  "geometry": {"coordinates":[-87.656182,41.963381],"type":"Point"}
}