{
  "type": "Feature",
  "properties": {
    "addr:full":"1023 W Fairfield Ct Waukegan IL 60085",
    "addr:housenumber":"1023",
    "addr:postcode":"60085",
    "addr:street":"W Fairfield Ct",
    "iso:country":"US",
    "sg:address":"1023 W Fairfield Ct",
    "sg:city":"Waukegan",
    "sg:classifiers":[
        {
            "category":"Wholesale",
            "subcategory":"Hardware",
            "type":"Manufacturing & Wholesale Goods"
        }
    ],
    "sg:phone":"+1 847 336 0461",
    "sg:postcode":"60085",
    "sg:province":"IL",
    "sg:tags":[
        "refrigerating"
    ],
    "wof:name":"Refrigeration & Air Cond Svc",
    "wof:placetype":"venue"
},
  "geometry": {"coordinates":[-87.84472599999999,42.374697],"type":"Point"}
}