{
  "type": "Feature",
  "properties": {
    "iso:country":"US",
    "sg:address":"1023 W Fairfield Ct",
    "sg:city":"Waukegan",
    "sg:classifiers":[
        {
            "category":"Wholesale",
            "subcategory":"Hardware",
            "type":"Manufacturing & Wholesale Goods"
        }
    ],
    "sg:phone":"+1 847 336 0461",
    "sg:postcode":"60085",
    "sg:province":"IL",
    "sg:tags":[
        "refrigerating"
    ],
    "wof:name":"Refrigeration & Air Cond Svc",
    "wof:placetype":"venue"
},
  "geometry": {"coordinates":[-87.844726,42.374697],"type":"Point"}
}