{
  "type": "Feature",
  "properties": {
    "addr:full":"237 N Northwest Hwy Park Ridge IL 60068",
    "addr:housenumber":"237",
    "addr:postcode":"60068",
    "addr:street":"N Northwest Hwy",
    "iso:country":"US",
    "sg:address":"237 N Northwest Hwy",
    "sg:city":"Park Ridge",
    "sg:classifiers":[
        {
            "category":"Health Services",
            "subcategory":"Health Practitioner",
            "type":"Services"
        }
    ],
    "sg:phone":"+1 847 692 3458",
    "sg:postcode":"60068",
    "sg:province":"IL",
    "wof:name":"Patricia Gerrity PHD",
    "wof:placetype":"venue"
},
  "geometry": {"coordinates":[-87.834391,42.014321],"type":"Point"}
}