{
  "type": "Feature",
  "properties": {
    "iso:country":"US",
    "sg:address":"558 Shellview Dr",
    "sg:city":"Bethalto",
    "sg:classifiers":[
        {
            "category":"Food & Beverages",
            "subcategory":"Specialty",
            "type":"Retail Goods"
        }
    ],
    "sg:phone":"+1 618 377 8415",
    "sg:postcode":"62010",
    "sg:province":"IL",
    "sg:tags":[
        "spice"
    ],
    "wof:name":"Watkins Quality Products",
    "wof:placetype":"venue"
},
  "geometry": {"coordinates":[-90.03681,38.902526],"type":"Point"}
}