{
  "type": "Feature",
  "properties": {
    "iso:country":"US",
    "sg:address":"10455 5th Ave Cut Off",
    "sg:city":"Countryside",
    "sg:classifiers":[
        {
            "category":"Home & Garden",
            "subcategory":"Building Materials",
            "type":"Retail Goods"
        },
        {
            "category":"Building & Trades",
            "subcategory":"Construction",
            "type":"Services"
        }
    ],
    "sg:phone":"+1 708 579 1966",
    "sg:postcode":"60525",
    "sg:province":"IL",
    "sg:tags":[
        "industrial",
        "contractor",
        "concrete",
        "contractors-commercial",
        "staining",
        "masonry",
        "mason"
    ],
    "wof:name":"Koranda Masonry",
    "wof:placetype":"venue"
},
  "geometry": {"coordinates":[-87.88026600000001,41.757424],"type":"Point"}
}