{
  "type": "Feature",
  "properties": {
    "addr:full":"125 W Wilson St Batavia IL 60510",
    "addr:housenumber":"125",
    "addr:postcode":"60510",
    "addr:street":"W Wilson St",
    "iso:country":"US",
    "sg:address":"125 W Wilson St",
    "sg:city":"Batavia",
    "sg:classifiers":[
        {
            "category":"Restaurant",
            "type":"Food & Drink"
        }
    ],
    "sg:phone":"+1   ",
    "sg:postcode":"60510",
    "sg:province":"IL",
    "sg:tags":[
        "eating"
    ],
    "wof:name":"McDonalds",
    "wof:placetype":"venue"
},
  "geometry": {"coordinates":[-88.30900699999999,41.849979],"type":"Point"}
}