{
  "type": "Feature",
  "properties": {
    "iso:country":"US",
    "sg:address":"2010 Big Oak Ln",
    "sg:city":"Northbrook",
    "sg:classifiers":[
        {
            "category":"Shopping",
            "subcategory":"Computers & Home Electronics",
            "type":"Retail Goods"
        }
    ],
    "sg:phone":"+1 847 446 6020",
    "sg:postcode":"60062",
    "sg:province":"IL",
    "sg:tags":[
        "television",
        "radio"
    ],
    "wof:name":"Avery-Murphy Television",
    "wof:placetype":"venue"
},
  "geometry": {"coordinates":[-87.82716000000001,42.137289],"type":"Point"}
}