{
  "type": "Feature",
  "properties": {
    "iso:country":"US",
    "sg:address":"103 W Woodland Rd",
    "sg:city":"Oakwood Hills",
    "sg:classifiers":[
        {
            "category":"Government",
            "subcategory":"Office",
            "type":"Public Place"
        }
    ],
    "sg:phone":"+1 847 639 4941",
    "sg:postcode":"60013",
    "sg:province":"IL",
    "sg:tags":[
        "village"
    ],
    "wof:name":"Oakwood Hills Building Dept",
    "wof:placetype":"venue"
},
  "geometry": {"coordinates":[-88.251355,42.241699],"type":"Point"}
}