{
  "type": "Feature",
  "properties": {
    "iso:country":"US",
    "sg:address":"4705 Roberts Rd",
    "sg:city":"Island Lake",
    "sg:classifiers":[
        {
            "category":"Building & Trades",
            "subcategory":"Landscaping Services",
            "type":"Services"
        }
    ],
    "sg:phone":"+1 847 639 9321",
    "sg:postcode":"60042",
    "sg:province":"IL",
    "sg:tags":[
        "landscape",
        "contractor"
    ],
    "sg:website":"www.jmpesz.com",
    "wof:name":"Joe M Pesz Landscaping & Exc",
    "wof:placetype":"venue"
},
  "geometry": {"coordinates":[-88.200697,42.26035],"type":"Point"}
}