{
  "type": "Feature",
  "properties": {
    "addr:full":"2294 N Milwaukee Ave Chicago IL 60647",
    "addr:housenumber":"2294",
    "addr:postcode":"60647",
    "addr:street":"N Milwaukee Ave",
    "iso:country":"US",
    "sg:address":"2294 N Milwaukee Ave",
    "sg:city":"Chicago",
    "sg:classifiers":[
        {
            "category":"Restaurant",
            "type":"Food & Drink"
        }
    ],
    "sg:phone":"+1 773 276 2215",
    "sg:postcode":"60647",
    "sg:province":"IL",
    "sg:tags":[
        "traditional",
        "american",
        "brunch",
        "diner",
        "breakfast"
    ],
    "wof:name":"Cozy Corner Diner & Pancake House",
    "wof:placetype":"venue"
},
  "geometry": {"coordinates":[-87.696899,41.922798],"type":"Point"}
}