{
  "type": "Feature",
  "properties": {
    "addr:full":"315 E 47th St Chicago IL 60653",
    "addr:housenumber":"315",
    "addr:postcode":"60653",
    "addr:street":"E 47Th St",
    "iso:country":"US",
    "sg:address":"315 E 47th St",
    "sg:city":"Chicago",
    "sg:classifiers":[
        {
            "category":"Food & Beverages",
            "subcategory":"Groceries & Convenience Stores",
            "type":"Retail Goods"
        }
    ],
    "sg:phone":"+1 773 924 1629",
    "sg:postcode":"60653",
    "sg:province":"IL",
    "wof:name":"Aristo Food & Liquors Inc",
    "wof:placetype":"venue"
},
  "geometry": {"coordinates":[-87.618103,41.810398],"type":"Point"}
}