{
  "type": "Feature",
  "properties": {
    "iso:country":"US",
    "sg:address":"11737 Blackburn Dr",
    "sg:city":"Orland Park",
    "sg:classifiers":[
        {
            "category":"Retail",
            "subcategory":"Repair Shop",
            "type":"Services"
        }
    ],
    "sg:phone":"+1 708 460 9360",
    "sg:postcode":"60467",
    "sg:province":"IL",
    "wof:name":"Powerwash On Wheels Inc",
    "wof:placetype":"venue"
},
  "geometry": {"coordinates":[-87.903185,41.630739],"type":"Point"}
}