{
  "type": "Feature",
  "properties": {
    "addr:full":"2434 N Spaulding Ave Chicago IL 60647",
    "addr:housenumber":"2434",
    "addr:postcode":"60647",
    "addr:street":"N Spaulding Ave",
    "iso:country":"US",
    "sg:address":"2434 N Spaulding Ave",
    "sg:city":"Chicago",
    "sg:classifiers":[
        {
            "category":"Professional",
            "subcategory":"Computer Services",
            "type":"Services"
        }
    ],
    "sg:phone":"+1 773 366 0652",
    "sg:postcode":"60647",
    "sg:province":"IL",
    "sg:tags":[
        "beer",
        "reviews",
        "travel",
        "brewery",
        "brewpub",
        "bar"
    ],
    "sg:website":"http://beermapping.com",
    "wof:name":"The Beer Mapping Project",
    "wof:placetype":"venue"
},
  "geometry": {"coordinates":[-87.710854,41.925475],"type":"Point"}
}