{
  "type": "Feature",
  "properties": {
    "addr:full":"101 E Main Cross St Taylorville IL 62568",
    "addr:housenumber":"101",
    "addr:postcode":"62568",
    "addr:street":"E Main Cross St",
    "iso:country":"US",
    "sg:address":"101 E Main Cross St",
    "sg:city":"Taylorville",
    "sg:classifiers":[
        {
            "category":"Shopping",
            "subcategory":"Stationery & Office Supplies",
            "type":"Retail Goods"
        },
        {
            "category":"Wholesale",
            "subcategory":"Office Equipment",
            "type":"Manufacturing & Wholesale Goods"
        },
        {
            "category":"Manufacturing",
            "subcategory":"Electronics",
            "type":"Manufacturing & Wholesale Goods"
        },
        {
            "category":"Professional",
            "subcategory":"Printing & Photocopies",
            "type":"Services"
        },
        {
            "category":"Shopping",
            "subcategory":"Computers & Home Electronics",
            "type":"Retail Goods"
        }
    ],
    "sg:phone":"+1 217 287 7311",
    "sg:postcode":"62568",
    "sg:province":"IL",
    "sg:tags":[
        "scanning",
        "printer",
        "envelope",
        "services-commercial",
        "duplicating",
        "copying",
        "printers-equipment",
        "plotting",
        "store"
    ],
    "sg:website":"http://www.psprinting.com",
    "wof:name":"Ps Printing",
    "wof:placetype":"venue"
},
  "geometry": {"coordinates":[-89.29492999999999,39.54937],"type":"Point"}
}