{
  "type": "Feature",
  "properties": {
    "addr:full":"742 N Galena Ave Dixon IL 61021",
    "addr:housenumber":"742",
    "addr:postcode":"61021",
    "addr:street":"N Galena Ave",
    "iso:country":"US",
    "sg:address":"742 N Galena Ave",
    "sg:city":"Dixon",
    "sg:classifiers":[
        {
            "category":"Personal",
            "type":"Services"
        },
        {
            "category":"Professional",
            "subcategory":"Art Services",
            "type":"Services"
        }
    ],
    "sg:phone":"+1 815 284 3686",
    "sg:postcode":"61021",
    "sg:province":"IL",
    "sg:tags":[
        "photography",
        "videography",
        "wedding"
    ],
    "wof:name":"The Photo Corner",
    "wof:placetype":"venue"
},
  "geometry": {"coordinates":[-89.487065,41.853597],"type":"Point"}
}