{
  "type": "Feature",
  "properties": {
    "iso:country":"US",
    "sg:address":"1250 S Michigan Ave # 2604",
    "sg:city":"Chicago",
    "sg:classifiers":[
        {
            "category":"Banks & Credit Unions",
            "subcategory":"Investment Brokerage",
            "type":"Services"
        },
        {
            "category":"Real Estate",
            "subcategory":"Developer",
            "type":"Services"
        }
    ],
    "sg:phone":"+1 312 765 0173",
    "sg:postcode":"60605",
    "sg:province":"IL",
    "sg:tags":[
        "investing"
    ],
    "wof:name":"Dcr Partners",
    "wof:placetype":"venue"
},
  "geometry": {"coordinates":[-87.62413100000001,41.86655],"type":"Point"}
}