{
  "type": "Feature",
  "properties": {
    "addr:full":"526 N Stewart St Geneseo IL 61254",
    "addr:housenumber":"526",
    "addr:postcode":"61254",
    "addr:street":"N Stewart St",
    "iso:country":"US",
    "sg:address":"526 N Stewart St",
    "sg:city":"Geneseo",
    "sg:classifiers":[
        {
            "category":"Organizations",
            "subcategory":"Community Association",
            "type":"Services"
        }
    ],
    "sg:phone":"+1 309 944 2449",
    "sg:postcode":"61254",
    "sg:province":"IL",
    "wof:name":"Kiwanis International",
    "wof:placetype":"venue"
},
  "geometry": {"coordinates":[-90.163202,41.45917],"type":"Point"}
}