{
  "type": "Feature",
  "properties": {
    "iso:country":"US",
    "sg:address":"7052 171st St",
    "sg:city":"Tinley Park",
    "sg:classifiers":[
        {
            "category":"Manufacturing",
            "subcategory":"Apparel",
            "type":"Manufacturing & Wholesale Goods"
        }
    ],
    "sg:phone":"+1 708 429 2262",
    "sg:postcode":"60477",
    "sg:province":"IL",
    "wof:name":"Maks",
    "wof:placetype":"venue"
},
  "geometry": {"coordinates":[-87.792646,41.580544],"type":"Point"}
}