{
  "type": "Feature",
  "properties": {
    "addr:full":"575 W Madison St Chicago IL 60661",
    "addr:housenumber":"575",
    "addr:postcode":"60661",
    "addr:street":"W Madison St",
    "iso:country":"US",
    "sg:address":"575 W Madison St",
    "sg:city":"Chicago",
    "sg:classifiers":[
        {
            "category":"Professional",
            "subcategory":"Business Services",
            "type":"Services"
        }
    ],
    "sg:phone":"+1 312 902 8717",
    "sg:postcode":"60661",
    "sg:province":"IL",
    "wof:name":"Haggai Group Inc",
    "wof:placetype":"venue"
},
  "geometry": {"coordinates":[-87.641914,41.881773],"type":"Point"}
}