{
  "type": "Feature",
  "properties": {
    "iso:country":"US",
    "sg:address":"216 N Sangamon Ave",
    "sg:city":"Gibson City",
    "sg:classifiers":[
        {
            "category":"Social Services",
            "type":"Services"
        }
    ],
    "sg:phone":"+1 217 784 8321",
    "sg:postcode":"60936",
    "sg:province":"IL",
    "sg:tags":[
        "youth",
        "organization",
        "center"
    ],
    "wof:name":"GCMS Community Youth Ctr",
    "wof:placetype":"venue"
},
  "geometry": {"coordinates":[-88.375273,40.467059],"type":"Point"}
}