{
  "type": "Feature",
  "properties": {
    "addr:full":"112 S Seeser St Joliet IL 60436",
    "addr:housenumber":"112",
    "addr:postcode":"60436",
    "addr:street":"S Seeser St",
    "iso:country":"US",
    "sg:address":"112 S Seeser St",
    "sg:city":"Joliet",
    "sg:classifiers":[
        {
            "category":"Social Services",
            "subcategory":"Child Care",
            "type":"Services"
        }
    ],
    "sg:phone":"+1 815 260 3895",
    "sg:postcode":"60436",
    "sg:province":"IL",
    "wof:name":"Velia's Sunshine Daycare",
    "wof:placetype":"venue"
},
  "geometry": {"coordinates":[-88.096816,41.520118],"type":"Point"}
}