{
  "type": "Feature",
  "properties": {
    "iso:country":"US",
    "sg:address":"6825 Hobson Valley Dr",
    "sg:city":"Woodridge",
    "sg:classifiers":[
        {
            "category":"Building & Trades",
            "subcategory":"Construction",
            "type":"Services"
        }
    ],
    "sg:phone":"+1 630 960 1212",
    "sg:postcode":"60517",
    "sg:province":"IL",
    "sg:tags":[
        "nonresidential"
    ],
    "wof:name":"Wojcik Robt J",
    "wof:placetype":"venue"
},
  "geometry": {"coordinates":[-88.067648,41.760959],"type":"Point"}
}