{
  "type": "Feature",
  "properties": {
    "addr:full":"200 E Willow Ave Wheaton IL 60187",
    "addr:housenumber":"200",
    "addr:postcode":"60187",
    "addr:street":"E Willow Ave",
    "iso:country":"US",
    "sg:address":"200 E Willow Ave",
    "sg:city":"Wheaton",
    "sg:classifiers":[
        {
            "category":"Health Services",
            "subcategory":"Clinic",
            "type":"Services"
        }
    ],
    "sg:phone":"+1 630 871 8100",
    "sg:postcode":"60187",
    "sg:province":"IL",
    "wof:name":"Oaktree Wellness Center",
    "wof:placetype":"venue"
},
  "geometry": {"coordinates":[-88.10435099999999,41.86324],"type":"Point"}
}