{
  "type": "Feature",
  "properties": {
    "addr:full":"1220 37th St Peru IL 61354",
    "addr:housenumber":"1220",
    "addr:postcode":"61354",
    "addr:street":"37Th St",
    "iso:country":"US",
    "sg:address":"1220 37th St",
    "sg:city":"Peru",
    "sg:classifiers":[
        {
            "category":"Shopping",
            "type":"Retail Goods"
        }
    ],
    "sg:phone":"+1 815 224 8126",
    "sg:postcode":"61354",
    "sg:province":"IL",
    "sg:tags":[
        "craft",
        "gallery",
        "dealer"
    ],
    "wof:name":"Crafters' Village Inc",
    "wof:placetype":"venue"
},
  "geometry": {"coordinates":[-89.122675,41.356527],"type":"Point"}
}