{
  "type": "Feature",
  "properties": {
    "iso:country":"US",
    "sg:address":"7550 Roosevelt Rd",
    "sg:city":"Forest Park",
    "sg:classifiers":[
        {
            "category":"Restaurant",
            "type":"Food & Drink"
        }
    ],
    "sg:phone":"+1   ",
    "sg:postcode":"60130",
    "sg:province":"IL",
    "sg:tags":[
        "eating"
    ],
    "wof:name":"Taco Bell",
    "wof:placetype":"venue"
},
  "geometry": {"coordinates":[-87.81353799999999,41.864739],"type":"Point"}
}