{
  "type": "Feature",
  "properties": {
    "iso:country":"US",
    "sg:address":"24 N Batavia Ave",
    "sg:city":"Batavia",
    "sg:classifiers":[
        {
            "category":"Home & Garden",
            "subcategory":"Furniture",
            "type":"Retail Goods"
        }
    ],
    "sg:phone":"+1 630 879 7377",
    "sg:postcode":"60510",
    "sg:province":"IL",
    "wof:name":"Furniture Rep's Warehouse",
    "wof:placetype":"venue"
},
  "geometry": {"coordinates":[-88.31201,41.850828],"type":"Point"}
}