{
  "type": "Feature",
  "properties": {
    "iso:country":"US",
    "sg:address":"1708 Bentbrook Dr",
    "sg:city":"Champaign",
    "sg:classifiers":[
        {
            "category":"Professional",
            "subcategory":"Lawyer & Legal Services",
            "type":"Services"
        }
    ],
    "sg:phone":"+1 217 352 2418",
    "sg:postcode":"61822",
    "sg:province":"IL",
    "wof:name":"Craver Middleton",
    "wof:placetype":"venue"
},
  "geometry": {"coordinates":[-88.307971,40.097395],"type":"Point"}
}