{
  "type": "Feature",
  "properties": {
    "addr:full":"1005 W Laraway Rd New Lenox IL 60451",
    "addr:housenumber":"1005",
    "addr:postcode":"60451",
    "addr:street":"W Laraway Rd",
    "iso:country":"US",
    "sg:address":"1005 W Laraway Rd",
    "sg:city":"New Lenox",
    "sg:classifiers":[
        {
            "category":"Cinema",
            "subcategory":"Movie Rental",
            "type":"Entertainment"
        }
    ],
    "sg:phone":"+1 815 485 7141",
    "sg:postcode":"60451",
    "sg:province":"IL",
    "sg:tags":[
        "tape",
        "video",
        "disc",
        "leasing",
        "sales"
    ],
    "wof:name":"Video Vista",
    "wof:placetype":"venue"
},
  "geometry": {"coordinates":[-87.95268,41.483309],"type":"Point"}
}