{
  "type": "Feature",
  "properties": {
    "addr:full":"628 Meadow Ln Le Roy IL 61752",
    "addr:housenumber":"628",
    "addr:postcode":"61752",
    "addr:street":"Meadow Ln",
    "iso:country":"US",
    "sg:address":"628 Meadow Ln",
    "sg:city":"Le Roy",
    "sg:classifiers":[
        {
            "category":"Building & Trades",
            "subcategory":"Landscaping Services",
            "type":"Services"
        }
    ],
    "sg:phone":"+1 309 962 2036",
    "sg:postcode":"61752",
    "sg:province":"IL",
    "sg:tags":[
        "landscape",
        "contractor"
    ],
    "wof:name":"Poppe Land Svc",
    "wof:placetype":"venue"
},
  "geometry": {"coordinates":[-88.75557499999999,40.353226],"type":"Point"}
}