{
  "type": "Feature",
  "properties": {
    "iso:country":"US",
    "sg:address":"1931 N State St",
    "sg:city":"Belvidere",
    "sg:classifiers":[
        {
            "category":"Health Services",
            "subcategory":"Doctor",
            "type":"Services"
        }
    ],
    "sg:phone":"+1 815 544 3426",
    "sg:postcode":"61008",
    "sg:province":"IL",
    "sg:tags":[
        "dentist"
    ],
    "wof:name":"Belvidere Family Dental Care",
    "wof:placetype":"venue"
},
  "geometry": {"coordinates":[-88.86145500000001,42.272465],"type":"Point"}
}