{
  "type": "Feature",
  "properties": {
    "iso:country":"US",
    "sg:address":"1217 Palmyra St",
    "sg:city":"Dixon",
    "sg:classifiers":[
        {
            "category":"Retail",
            "subcategory":"Auto Repair",
            "type":"Services"
        }
    ],
    "sg:phone":"+1 815 288 5444",
    "sg:postcode":"61021",
    "sg:province":"IL",
    "sg:tags":[
        "repairing",
        "automobile",
        "general",
        "supply"
    ],
    "wof:name":"Ron's Automotive",
    "wof:placetype":"venue"
},
  "geometry": {"coordinates":[-89.502115,41.847697],"type":"Point"}
}