{
  "type": "Feature",
  "properties": {
    "iso:country":"US",
    "sg:address":"165 Kenilworth Ave",
    "sg:city":"Glen Ellyn",
    "sg:classifiers":[
        {
            "category":"Building & Trades",
            "subcategory":"Electrical",
            "type":"Services"
        }
    ],
    "sg:phone":"+1 630 858 0810",
    "sg:postcode":"60137",
    "sg:province":"IL",
    "sg:tags":[
        "electrician"
    ],
    "wof:name":"S R Electrical",
    "wof:placetype":"venue"
},
  "geometry": {"coordinates":[-88.077698,41.865398],"type":"Point"}
}