{
  "type": "Feature",
  "properties": {
    "iso:country":"US",
    "sg:address":"1326 N Larkspur Ln",
    "sg:city":"Palatine",
    "sg:classifiers":[
        {
            "category":"Retail",
            "subcategory":"Laundry & Dry Cleaning",
            "type":"Services"
        }
    ],
    "sg:phone":"+1 847 991 7551",
    "sg:postcode":"60074",
    "sg:province":"IL",
    "sg:tags":[
        "cleaners",
        "rug",
        "carpet"
    ],
    "wof:name":"American Experts Carpet Rug &",
    "wof:placetype":"venue"
},
  "geometry": {"coordinates":[-88.026523,42.13402],"type":"Point"}
}