{
  "type": "Feature",
  "properties": {
    "addr:full":"6831 Sunset Ave Countryside IL 60525",
    "addr:housenumber":"6831",
    "addr:postcode":"60525",
    "addr:street":"Sunset Ave",
    "iso:country":"US",
    "sg:address":"6831 Sunset Ave",
    "sg:city":"Countryside",
    "sg:classifiers":[
        {
            "category":"Building & Trades",
            "subcategory":"Construction",
            "type":"Services"
        }
    ],
    "sg:phone":"+1 708 354 3995",
    "sg:postcode":"60525",
    "sg:province":"IL",
    "sg:tags":[
        "roofing",
        "industrial",
        "contractors-commercial",
        "contractor"
    ],
    "wof:name":"Schuler Roofing Co",
    "wof:placetype":"venue"
},
  "geometry": {"coordinates":[-87.882108,41.765666],"type":"Point"}
}