{
  "type": "Feature",
  "properties": {
    "addr:full":"3865 N Mulford Rd Rockford IL 61114",
    "addr:housenumber":"3865",
    "addr:postcode":"61114",
    "addr:street":"N Mulford Rd",
    "iso:country":"US",
    "sg:address":"3865 N Mulford Rd",
    "sg:city":"Rockford",
    "sg:classifiers":[
        {
            "category":"Health Services",
            "subcategory":"Doctor",
            "type":"Services"
        },
        {
            "category":"Health Services",
            "subcategory":"Health Practitioner",
            "type":"Services"
        }
    ],
    "sg:phone":"+1 815 399 2190",
    "sg:postcode":"61114",
    "sg:province":"IL",
    "sg:tags":[
        "physician",
        "ophthalmology",
        "surgeons",
        "surgeon"
    ],
    "sg:website":"http://www.815laser.com",
    "wof:name":"Malik Masud MD",
    "wof:placetype":"venue"
},
  "geometry": {"coordinates":[-88.99954200000001,42.317266],"type":"Point"}
}