{
  "type": "Feature",
  "properties": {
    "iso:country":"US",
    "sg:address":"2121 S Goebbert Rd",
    "sg:city":"Arlington Heights",
    "sg:classifiers":[
        {
            "category":"Education",
            "subcategory":"School",
            "type":"Public Place"
        }
    ],
    "sg:phone":"+1 847 718 7771",
    "sg:postcode":"60005",
    "sg:province":"IL",
    "sg:tags":[
        "management"
    ],
    "wof:name":"Township High School Dst 214",
    "wof:placetype":"venue"
},
  "geometry": {"coordinates":[-87.974801,42.046185],"type":"Point"}
}