{
  "type": "Feature",
  "properties": {
    "addr:full":"305 W Woodbury St Danville IL 61832",
    "addr:housenumber":"305",
    "addr:postcode":"61832",
    "addr:street":"W Woodbury St",
    "iso:country":"US",
    "sg:address":"305 W Woodbury St",
    "sg:city":"Danville",
    "sg:classifiers":[
        {
            "category":"Social Services",
            "type":"Services"
        }
    ],
    "sg:phone":"+1 217 442 0869",
    "sg:postcode":"61832",
    "sg:province":"IL",
    "sg:tags":[
        "youth",
        "organization",
        "center"
    ],
    "wof:name":"Boy Scouts Of America",
    "wof:placetype":"venue"
},
  "geometry": {"coordinates":[-87.63478499999999,40.137254],"type":"Point"}
}