{
  "type": "Feature",
  "properties": {
    "iso:country":"US",
    "sg:address":"3533 Rose St",
    "sg:city":"Franklin Park",
    "sg:classifiers":[
        {
            "category":"Shopping",
            "subcategory":"Clothing, Apparel, & Fashions",
            "type":"Retail Goods"
        }
    ],
    "sg:phone":"+1   ",
    "sg:postcode":"60131",
    "sg:province":"IL",
    "sg:tags":[
        "shop",
        "barber"
    ],
    "wof:name":"Preiti Salon For Men",
    "wof:placetype":"venue"
},
  "geometry": {"coordinates":[-87.865781,41.94381],"type":"Point"}
}