{
  "type": "Feature",
  "properties": {
    "addr:full":"100 Lincolnwood Ct Spring Grove IL 60081",
    "addr:housenumber":"100",
    "addr:postcode":"60081",
    "addr:street":"Lincolnwood Ct",
    "iso:country":"US",
    "sg:address":"100 Lincolnwood Ct",
    "sg:city":"Spring Grove",
    "sg:classifiers":[
        {
            "category":"Retail",
            "subcategory":"Portrait Studio",
            "type":"Services"
        }
    ],
    "sg:phone":"+1 847 973 9240",
    "sg:postcode":"60081",
    "sg:province":"IL",
    "sg:tags":[
        "identification",
        "card"
    ],
    "wof:name":"Smart Kid Card",
    "wof:placetype":"venue"
},
  "geometry": {"coordinates":[-88.176892,42.425191],"type":"Point"}
}