{
  "type": "Feature",
  "properties": {
    "addr:full":"625 N Cicero Ave Chicago IL 60644",
    "addr:housenumber":"625",
    "addr:postcode":"60644",
    "addr:street":"N Cicero Ave",
    "iso:country":"US",
    "sg:address":"625 N Cicero Ave",
    "sg:city":"Chicago",
    "sg:classifiers":[
        {
            "category":"Autos & Motor Vehicles",
            "subcategory":"Automobile Sales",
            "type":"Retail Goods"
        }
    ],
    "sg:phone":"+1 773 626 4440",
    "sg:postcode":"60644",
    "sg:province":"IL",
    "sg:tags":[
        "used"
    ],
    "wof:name":"Cairo Auto Wholesaler",
    "wof:placetype":"venue"
},
  "geometry": {"coordinates":[-87.74562400000001,41.891845],"type":"Point"}
}