{
  "type": "Feature",
  "properties": {
    "iso:country":"US",
    "sg:address":"1212 S Division St",
    "sg:city":"Carterville",
    "sg:classifiers":[
        {
            "category":"Real Estate",
            "subcategory":"Real Estate Services",
            "type":"Services"
        }
    ],
    "sg:phone":"+1 618 985 3900",
    "sg:postcode":"62918",
    "sg:province":"IL",
    "sg:tags":[
        "management",
        "property"
    ],
    "wof:name":"House of Rentals",
    "wof:placetype":"venue"
},
  "geometry": {"coordinates":[-89.077306,37.750206],"type":"Point"}
}