{
  "type": "Feature",
  "properties": {
    "addr:full":"1503 Kingshighway East Saint Louis IL 62204",
    "addr:housenumber":"1503",
    "addr:postcode":"62204",
    "addr:street":"Kingshighway East",
    "iso:country":"US",
    "sg:address":"1503 Kingshighway",
    "sg:city":"East Saint Louis",
    "sg:classifiers":[
        {
            "category":"Food & Beverages",
            "subcategory":"Groceries & Convenience Stores",
            "type":"Retail Goods"
        }
    ],
    "sg:phone":"+1   ",
    "sg:postcode":"62204",
    "sg:province":"IL",
    "wof:name":"Family Matters & More",
    "wof:placetype":"venue"
},
  "geometry": {"coordinates":[-90.09312300000001,38.629072],"type":"Point"}
}