{
  "type": "Feature",
  "properties": {
    "iso:country":"US",
    "sg:address":"12142 Kickapoo Park Rd",
    "sg:city":"Oakwood",
    "sg:classifiers":[
        {
            "category":"Utilities",
            "subcategory":"Mobile Phone",
            "type":"Services"
        }
    ],
    "sg:phone":"+1 217 431 0225",
    "sg:postcode":"61858",
    "sg:province":"IL",
    "sg:tags":[
        "telephone",
        "cellular"
    ],
    "wof:name":"Verizon Wireless Messaging Svc",
    "wof:placetype":"venue"
},
  "geometry": {"coordinates":[-87.71055200000001,40.15252],"type":"Point"}
}