{
  "type": "Feature",
  "properties": {
    "iso:country":"US",
    "sg:address":"4955 W Washington Blvd",
    "sg:city":"Chicago",
    "sg:classifiers":[
        {
            "category":"Real Estate",
            "subcategory":"Real Estate Agent",
            "type":"Services"
        }
    ],
    "sg:phone":"+1 773 626 6610",
    "sg:postcode":"60644",
    "sg:province":"IL",
    "wof:name":"Ativie Property Management",
    "wof:placetype":"venue"
},
  "geometry": {"coordinates":[-87.74899499999999,41.881696],"type":"Point"}
}