{
  "type": "Feature",
  "properties": {
    "iso:country":"US",
    "sg:address":"103 16th Ave",
    "sg:city":"Rock Island",
    "sg:classifiers":[
        {
            "category":"Manufacturing",
            "subcategory":"Tools & Machinery",
            "type":"Manufacturing & Wholesale Goods"
        }
    ],
    "sg:phone":"+1 309 786 6463",
    "sg:postcode":"61201",
    "sg:province":"IL",
    "sg:tags":[
        "shop",
        "job"
    ],
    "wof:name":"Sparks Fiberglass Inc",
    "wof:placetype":"venue"
},
  "geometry": {"coordinates":[-90.593955,41.496606],"type":"Point"}
}