{
  "type": "Feature",
  "properties": {
    "iso:country":"US",
    "sg:address":"1226 Lencioni Ct",
    "sg:city":"Geneva",
    "sg:classifiers":[
        {
            "category":"Professional",
            "subcategory":"Business Services",
            "type":"Services"
        }
    ],
    "sg:phone":"+1 630 262 9298",
    "sg:postcode":"60134",
    "sg:province":"IL",
    "sg:tags":[
        "building",
        "distributor",
        "construction"
    ],
    "wof:name":"Dng Building Distributors",
    "wof:placetype":"venue"
},
  "geometry": {"coordinates":[-88.282794,41.894082],"type":"Point"}
}