{
  "type": "Feature",
  "properties": {
    "iso:country":"US",
    "sg:address":"56 W Maple St",
    "sg:city":"Chicago",
    "sg:classifiers":[
        {
            "category":"Shopping",
            "subcategory":"Books",
            "type":"Retail Goods"
        }
    ],
    "sg:phone":"+1 312 988 7246",
    "sg:postcode":"60610",
    "sg:province":"IL",
    "sg:tags":[
        "store"
    ],
    "wof:name":"Chicago Rare Book Center Inc",
    "wof:placetype":"venue"
},
  "geometry": {"coordinates":[-87.630289,41.901877],"type":"Point"}
}