{
  "type": "Feature",
  "properties": {
    "iso:country":"US",
    "sg:address":"2832 W 24th Blvd",
    "sg:city":"Chicago",
    "sg:classifiers":[
        {
            "category":"Education",
            "subcategory":"School",
            "type":"Public Place"
        }
    ],
    "sg:phone":"+1 773 534 1403",
    "sg:postcode":"60623",
    "sg:province":"IL",
    "sg:website":"http://www.ywlcs.org",
    "wof:name":"Telpochcalli Elementary School",
    "wof:placetype":"venue"
},
  "geometry": {"coordinates":[-87.695938,41.847877],"type":"Point"}
}