{
  "type": "Feature",
  "properties": {
    "iso:country":"US",
    "sg:address":"814 Thunderbird Trl",
    "sg:city":"Carol Stream",
    "sg:classifiers":[
        {
            "category":"Professional",
            "subcategory":"Art Services",
            "type":"Services"
        }
    ],
    "sg:phone":"+1 630 217 3598",
    "sg:postcode":"60188",
    "sg:province":"IL",
    "sg:tags":[
        "commercial",
        "design"
    ],
    "wof:name":"Dupage Millennium Medium",
    "wof:placetype":"venue"
},
  "geometry": {"coordinates":[-88.149764,41.911268],"type":"Point"}
}