{
  "type": "Feature",
  "properties": {
    "iso:country":"US",
    "sg:address":"1232 N Milwaukee Ave",
    "sg:city":"Chicago",
    "sg:classifiers":[
        {
            "category":"Shopping",
            "subcategory":"Shoes",
            "type":"Retail Goods"
        }
    ],
    "sg:phone":"+1 773 384 2201",
    "sg:postcode":"60622",
    "sg:province":"IL",
    "sg:tags":[
        "store"
    ],
    "sg:website":"www.altshoes.com",
    "wof:name":"Alternatives Shoe Outlet",
    "wof:placetype":"venue"
},
  "geometry": {"coordinates":[-87.668237,41.904189],"type":"Point"}
}