{
  "type": "Feature",
  "properties": {
    "iso:country":"US",
    "sg:address":"3017 W 26th Street",
    "sg:city":"Chicago",
    "sg:classifiers":[
        {
            "category":"Retail",
            "subcategory":"Auto Repair",
            "type":"Services"
        }
    ],
    "sg:phone":"+1 773 579 0118",
    "sg:postcode":"60623",
    "sg:province":"IL",
    "wof:name":"Technicentro Automotriz",
    "wof:placetype":"venue"
},
  "geometry": {"coordinates":[-87.700576,41.844486],"type":"Point"}
}