{
  "type": "Feature",
  "properties": {
    "iso:country":"US",
    "sg:address":"3129 W Logan Blvd",
    "sg:city":"Chicago",
    "sg:classifiers":[
        {
            "category":"Professional",
            "subcategory":"Lawyer & Legal Services",
            "type":"Services"
        }
    ],
    "sg:phone":"+1 773 395 2233",
    "sg:postcode":"60647",
    "sg:province":"IL",
    "wof:name":"Vazquez Felix A Atty",
    "wof:placetype":"venue"
},
  "geometry": {"coordinates":[-87.7052,41.928001],"type":"Point"}
}