{
  "type": "Feature",
  "properties": {
    "addr:full":"2522 W Chicago Ave Chicago IL 60622",
    "addr:housenumber":"2522",
    "addr:postcode":"60622",
    "addr:street":"W Chicago Ave",
    "iso:country":"US",
    "sg:address":"2522 W Chicago Ave",
    "sg:city":"Chicago",
    "sg:classifiers":[
        {
            "category":"Personal",
            "subcategory":"Beauty Salon",
            "type":"Services"
        },
        {
            "category":"Personal",
            "subcategory":"Hair Removal",
            "type":"Services"
        },
        {
            "category":"Personal",
            "subcategory":"Nail Salon",
            "type":"Services"
        }
    ],
    "sg:phone":"+1 773 342 6333",
    "sg:postcode":"60622",
    "sg:province":"IL",
    "sg:website":"www.connectionsalon.com/",
    "wof:name":"Connection Salon",
    "wof:placetype":"venue"
},
  "geometry": {"coordinates":[-87.69035100000001,41.895977],"type":"Point"}
}