{
  "type": "Feature",
  "properties": {
    "iso:country":"US",
    "sg:address":"991 Aurora Ave",
    "sg:city":"Aurora",
    "sg:classifiers":[
        {
            "category":"Shopping",
            "subcategory":"Clothing, Apparel, & Fashions",
            "type":"Retail Goods"
        }
    ],
    "sg:phone":"+1 630 844 9071",
    "sg:postcode":"60505",
    "sg:province":"IL",
    "sg:tags":[
        "designer"
    ],
    "wof:name":"KIF Industries",
    "wof:placetype":"venue"
},
  "geometry": {"coordinates":[-88.307912,41.776407],"type":"Point"}
}