{
  "type": "Feature",
  "properties": {
    "addr:full":"301 Swan Ave Centralia IL 62801",
    "addr:housenumber":"301",
    "addr:postcode":"62801",
    "addr:street":"Swan Ave",
    "iso:country":"US",
    "sg:address":"301 Swan Ave",
    "sg:city":"Centralia",
    "sg:classifiers":[
        {
            "category":"Wholesale",
            "subcategory":"Machinery & Supplies",
            "type":"Manufacturing & Wholesale Goods"
        }
    ],
    "sg:phone":"+1 618 532 1163",
    "sg:postcode":"62801",
    "sg:province":"IL",
    "sg:tags":[
        "fastener",
        "industrial"
    ],
    "wof:name":"Fastenal Company",
    "wof:placetype":"venue"
},
  "geometry": {"coordinates":[-89.137838,38.497718],"type":"Point"}
}