{
  "type": "Feature",
  "properties": {
    "addr:full":"213 Ernest St Washington IL 61571",
    "addr:housenumber":"213",
    "addr:postcode":"61571",
    "addr:street":"Ernest St",
    "iso:country":"US",
    "sg:address":"213 Ernest St",
    "sg:city":"Washington",
    "sg:classifiers":[
        {
            "category":"Building & Trades",
            "subcategory":"Construction",
            "type":"Services"
        }
    ],
    "sg:phone":"+1 309 745 9754",
    "sg:postcode":"61571",
    "sg:province":"IL",
    "sg:tags":[
        "altering",
        "remodeling",
        "contractor"
    ],
    "wof:name":"Aschenbrenner Construction",
    "wof:placetype":"venue"
},
  "geometry": {"coordinates":[-89.464681,40.697432],"type":"Point"}
}