{
  "type": "Feature",
  "properties": {
    "iso:country":"US",
    "sg:address":"4923 N Kruger Ave",
    "sg:city":"Chicago",
    "sg:classifiers":[
        {
            "category":"Professional",
            "subcategory":"Employment Agencies",
            "type":"Services"
        }
    ],
    "sg:phone":"+1 773 736 9378",
    "sg:postcode":"60630",
    "sg:province":"IL",
    "wof:name":"Best Personal Services",
    "wof:placetype":"venue"
},
  "geometry": {"coordinates":[-87.745003,41.970699],"type":"Point"}
}