{
  "type": "Feature",
  "properties": {
    "addr:full":"750 Toledo Cemetery Rd Cobden IL 62920",
    "addr:housenumber":"750",
    "addr:postcode":"62920",
    "addr:street":"Toledo Cemetery Rd",
    "iso:country":"US",
    "sg:address":"750 Toledo Cemetery Rd",
    "sg:city":"Cobden",
    "sg:classifiers":[
        {
            "category":"Building & Trades",
            "subcategory":"Construction",
            "type":"Services"
        }
    ],
    "sg:phone":"+1 618 893 2698",
    "sg:postcode":"62920",
    "sg:province":"IL",
    "sg:tags":[
        "hanging",
        "painter",
        "contractor"
    ],
    "wof:name":"Dent Austin Painting",
    "wof:placetype":"venue"
},
  "geometry": {"coordinates":[-89.25658900000001,37.564111],"type":"Point"}
}