{
  "type": "Feature",
  "properties": {
    "iso:country":"US",
    "sg:address":"8516 W Winona St",
    "sg:city":"Chicago",
    "sg:classifiers":[
        {
            "category":"Local Transit",
            "type":"Transportation"
        }
    ],
    "sg:phone":"+1 773 625 0400",
    "sg:postcode":"60656",
    "sg:province":"IL",
    "sg:tags":[
        "limousine"
    ],
    "wof:name":"AAA Airport Limo",
    "wof:placetype":"venue"
},
  "geometry": {"coordinates":[-87.840718,41.972419],"type":"Point"}
}