{
  "type": "Feature",
  "properties": {
    "addr:full":"4719 N Beacon St Chicago IL 60640",
    "addr:housenumber":"4719",
    "addr:postcode":"60640",
    "addr:street":"N Beacon",
    "iso:country":"US",
    "sg:address":"4719 N Beacon St",
    "sg:city":"Chicago",
    "sg:classifiers":[
        {
            "category":"Real Estate",
            "subcategory":"Real Estate Operator",
            "type":"Services"
        }
    ],
    "sg:phone":"+1 773 878 6417",
    "sg:postcode":"60640",
    "sg:province":"IL",
    "sg:tags":[
        "condominium"
    ],
    "wof:name":"Beacon Hills Condo Assoc",
    "wof:placetype":"venue"
},
  "geometry": {"coordinates":[-87.664314,41.968627],"type":"Point"}
}