{
  "type": "Feature",
  "properties": {
    "iso:country":"US",
    "sg:address":"598 Lindgren Ln",
    "sg:city":"Belvidere",
    "sg:classifiers":[
        {
            "category":"Building & Trades",
            "subcategory":"Construction",
            "type":"Services"
        }
    ],
    "sg:phone":"+1 815 332 9840",
    "sg:postcode":"61008",
    "sg:province":"IL",
    "sg:tags":[
        "home",
        "contractor"
    ],
    "wof:name":"J P Vyborny Construction Co",
    "wof:placetype":"venue"
},
  "geometry": {"coordinates":[-88.925989,42.296468],"type":"Point"}
}