{
  "type": "Feature",
  "properties": {
    "iso:country":"US",
    "sg:address":"3533 S Archer Ave",
    "sg:city":"Chicago",
    "sg:classifiers":[
        {
            "category":"Communications",
            "subcategory":"Film & Video Production",
            "type":"Services"
        }
    ],
    "sg:phone":"+1 773 927 9091",
    "sg:postcode":"60609",
    "sg:province":"IL",
    "sg:tags":[
        "dvd",
        "cassette",
        "duplicating",
        "cd"
    ],
    "sg:website":"http://www.intervideoduplication.com/",
    "wof:name":"Intervideo Duplication Services",
    "wof:placetype":"venue"
},
  "geometry": {"coordinates":[-87.678583,41.829817],"type":"Point"}
}