{
  "type": "Feature",
  "properties": {
    "addr:full":"101 Southpointe Suite B Edwardsville IL 62025",
    "addr:housenumber":"101;suite b",
    "addr:postcode":"62025",
    "addr:street":"Southpointe",
    "iso:country":"US",
    "sg:address":"101 Southpointe Suite B",
    "sg:city":"Edwardsville",
    "sg:classifiers":[
        {
            "category":"Professional",
            "subcategory":"Lawyer & Legal Services",
            "type":"Services"
        }
    ],
    "sg:phone":"+1 618 659 9292",
    "sg:postcode":"62025",
    "sg:province":"IL",
    "sg:tags":[
        "attorney",
        "law",
        "estate",
        "wills",
        "elder",
        "planning",
        "trust"
    ],
    "sg:website":"http://qualityforbenefits.com",
    "wof:name":"Coulson Elder Law",
    "wof:placetype":"venue"
},
  "geometry": {"coordinates":[-89.978989,38.781879],"type":"Point"}
}