{
  "type": "Feature",
  "properties": {
    "iso:country":"US",
    "sg:address":"1180 E Lincoln St",
    "sg:city":"Riverton",
    "sg:classifiers":[
        {
            "category":"Shopping",
            "subcategory":"Party Supplies",
            "type":"Retail Goods"
        },
        {
            "category":"Farming",
            "subcategory":"Orchard",
            "type":"Manufacturing & Wholesale Goods"
        }
    ],
    "sg:phone":"+1 217 629 7000",
    "sg:postcode":"62561",
    "sg:province":"IL",
    "sg:tags":[
        "flowers-preserved",
        "wedding"
    ],
    "wof:name":"Beautiful Keepsakes",
    "wof:placetype":"venue"
},
  "geometry": {"coordinates":[-89.52462,39.844372],"type":"Point"}
}