{
  "type": "Feature",
  "properties": {
    "addr:full":"325 Main St Batavia IL 60510",
    "addr:housenumber":"325",
    "addr:postcode":"60510",
    "addr:street":"Main St",
    "iso:country":"US",
    "sg:address":"325 Main St",
    "sg:city":"Batavia",
    "sg:classifiers":[
        {
            "category":"Education",
            "subcategory":"School",
            "type":"Public Place"
        }
    ],
    "sg:phone":"+1 630 879 2359",
    "sg:postcode":"60510",
    "sg:province":"IL",
    "wof:name":"Valley Sheltered Workshop",
    "wof:placetype":"venue"
},
  "geometry": {"coordinates":[-88.382257,41.84608],"type":"Point"}
}