{
  "type": "Feature",
  "properties": {
    "addr:full":"2700 S Loomis St Chicago IL 60686",
    "addr:housenumber":"2700",
    "addr:postcode":"60686",
    "addr:street":"S Loomis St",
    "iso:country":"US",
    "sg:address":"2700 S Loomis St",
    "sg:city":"Chicago",
    "sg:classifiers":[
        {
            "category":"Bars & Pubs",
            "type":"Food & Drink"
        }
    ],
    "sg:phone":"+1 773 847 8140",
    "sg:postcode":"60686",
    "sg:province":"IL",
    "wof:name":"Gem Bar",
    "wof:placetype":"venue"
},
  "geometry": {"coordinates":[-87.66011399999999,41.844641],"type":"Point"}
}