{
  "type": "Feature",
  "properties": {
    "iso:country":"US",
    "sg:address":"228 N Main St",
    "sg:city":"Galena",
    "sg:classifiers":[
        {
            "category":"Shopping",
            "subcategory":"Clothing, Apparel, & Fashions",
            "type":"Retail Goods"
        }
    ],
    "sg:phone":"+1   ",
    "sg:postcode":"61036",
    "sg:province":"IL",
    "sg:tags":[
        "boutique",
        "lady"
    ],
    "wof:name":"Simply Elegant Boutique",
    "wof:placetype":"venue"
},
  "geometry": {"coordinates":[-90.42580700000001,42.417237],"type":"Point"}
}