{
  "type": "Feature",
  "properties": {
    "addr:full":"2001 S Mount Prospect Rd Des Plaines IL 60018",
    "addr:housenumber":"2001",
    "addr:postcode":"60018",
    "addr:street":"S Mount Prospect Rd Des",
    "iso:country":"US",
    "sg:address":"2001 S Mount Prospect Rd",
    "sg:city":"Des Plaines",
    "sg:classifiers":[
        {
            "category":"Manufacturing",
            "subcategory":"Metals",
            "type":"Manufacturing & Wholesale Goods"
        }
    ],
    "sg:phone":"+1 847 813 4040",
    "sg:postcode":"60018",
    "sg:province":"IL",
    "sg:tags":[
        "mfg",
        "s",
        "computer",
        "stampings"
    ],
    "wof:name":"Pentair Electronic Packaging",
    "wof:placetype":"venue"
},
  "geometry": {"coordinates":[-87.920762,42.016904],"type":"Point"}
}