{
  "type": "Feature",
  "properties": {
    "iso:country":"US",
    "sg:address":"814 Race Track Rd",
    "sg:city":"Centralia",
    "sg:classifiers":[
        {
            "category":"Wholesale",
            "subcategory":"Durable Goods & Equipment",
            "type":"Manufacturing & Wholesale Goods"
        }
    ],
    "sg:phone":"+1 618 532 6922",
    "sg:postcode":"62801",
    "sg:province":"IL",
    "sg:tags":[
        "fire",
        "extinguisher"
    ],
    "wof:name":"Dorco Distributing Co",
    "wof:placetype":"venue"
},
  "geometry": {"coordinates":[-89.03269400000001,38.503871],"type":"Point"}
}