{
  "type": "Feature",
  "properties": {
    "iso:country":"US",
    "sg:address":"294 Spring Ave",
    "sg:city":"Glen Ellyn",
    "sg:classifiers":[
        {
            "category":"Manufacturing",
            "subcategory":"Printing",
            "type":"Manufacturing & Wholesale Goods"
        }
    ],
    "sg:phone":"+1 630 790 8093",
    "sg:postcode":"60137",
    "sg:province":"IL",
    "sg:tags":[
        "printer"
    ],
    "wof:name":"American Printing Svc",
    "wof:placetype":"venue"
},
  "geometry": {"coordinates":[-88.048115,41.868315],"type":"Point"}
}