{
  "type": "Feature",
  "properties": {
    "iso:country":"US",
    "sg:address":"310 S Michigan Ave # 1",
    "sg:city":"Chicago",
    "sg:classifiers":[
        {
            "category":"Real Estate",
            "subcategory":"Real Estate Services",
            "type":"Services"
        },
        {
            "category":"Real Estate",
            "subcategory":"Real Estate Agent",
            "type":"Services"
        }
    ],
    "sg:phone":"+1 312 922 1310",
    "sg:postcode":"60604",
    "sg:province":"IL",
    "sg:tags":[
        "buyer",
        "management",
        "broker"
    ],
    "wof:name":"Metropolitian Tower",
    "wof:placetype":"venue"
},
  "geometry": {"coordinates":[-87.624396,41.87814],"type":"Point"}
}