{
  "type": "Feature",
  "properties": {
    "iso:country":"US",
    "sg:address":"20 S Clark Street Suite 500",
    "sg:city":"Chicago",
    "sg:classifiers":[
        {
            "category":"Professional",
            "subcategory":"Lawyer & Legal Services",
            "type":"Services"
        }
    ],
    "sg:phone":"+1 312 372 7075",
    "sg:postcode":"60603",
    "sg:province":"IL",
    "wof:name":"Richardson Stasko Boyd & Mack",
    "wof:placetype":"venue"
},
  "geometry": {"coordinates":[-87.630875,41.881728],"type":"Point"}
}