{
  "type": "Feature",
  "properties": {
    "iso:country":"US",
    "sg:address":"602 17th Ave",
    "sg:city":"East Moline",
    "sg:classifiers":[
        {
            "category":"Organizations",
            "subcategory":"Religious Organization",
            "type":"Services"
        }
    ],
    "sg:phone":"+1 309 755 5704",
    "sg:postcode":"61244",
    "sg:province":"IL",
    "sg:website":"www.olgca.us",
    "wof:name":"Our Lady of Grace Catholic Academy",
    "wof:placetype":"venue"
},
  "geometry": {"coordinates":[-90.44722400000001,41.513727],"type":"Point"}
}