{
  "type": "Feature",
  "properties": {
    "iso:country":"US",
    "sg:address":"1525 W Belmont Avenue",
    "sg:city":"Chicago",
    "sg:classifiers":[
        {
            "category":"Health Services",
            "subcategory":"Doctor",
            "type":"Services"
        },
        {
            "category":"Health Services",
            "subcategory":"Health Practitioner",
            "type":"Services"
        }
    ],
    "sg:phone":"+1 773 525 7868",
    "sg:postcode":"60657",
    "sg:province":"IL",
    "sg:tags":[
        "medicine",
        "internal",
        "therapy",
        "physical"
    ],
    "wof:name":"Saint Joseph Health Center",
    "wof:placetype":"venue"
},
  "geometry": {"coordinates":[-87.66676,41.939723],"type":"Point"}
}