{
  "type": "Feature",
  "properties": {
    "addr:full":"237 E Greenwood St Bourbonnais IL 60914",
    "addr:housenumber":"237",
    "addr:postcode":"60914",
    "addr:street":"E Greenwood St",
    "iso:country":"US",
    "sg:address":"237 E Greenwood St",
    "sg:city":"Bourbonnais",
    "sg:classifiers":[
        {
            "category":"Retail",
            "subcategory":"Auto Repair",
            "type":"Services"
        }
    ],
    "sg:phone":"+1 815 939 4395",
    "sg:postcode":"60914",
    "sg:province":"IL",
    "sg:tags":[
        "body",
        "automobile",
        "painting"
    ],
    "wof:name":"High Proformance Auto Body",
    "wof:placetype":"venue"
},
  "geometry": {"coordinates":[-87.877579,41.158495],"type":"Point"}
}