{
  "type": "Feature",
  "properties": {
    "iso:country":"US",
    "sg:address":"1600 N Harlem Ave",
    "sg:city":"Elmwood Park",
    "sg:classifiers":[
        {
            "category":"Shopping",
            "subcategory":"Pharmacy",
            "type":"Retail Goods"
        }
    ],
    "sg:phone":"+1 708 456 8810",
    "sg:postcode":"60707",
    "sg:province":"IL",
    "sg:tags":[
        "drugstore"
    ],
    "sg:website":"www.walgreens.com",
    "wof:name":"Walgreen Drug Stores",
    "wof:placetype":"venue"
},
  "geometry": {"coordinates":[-87.805397,41.908798],"type":"Point"}
}