{
  "type": "Feature",
  "properties": {
    "addr:full":"7870 Lincoln Ave Skokie IL 60077",
    "addr:housenumber":"7870",
    "addr:postcode":"60077",
    "addr:street":"Lincoln Ave",
    "iso:country":"US",
    "sg:address":"7870 Lincoln Ave",
    "sg:city":"Skokie",
    "sg:classifiers":[
        {
            "category":"Insurance",
            "subcategory":"Insurance Agent",
            "type":"Services"
        }
    ],
    "sg:phone":"+1 847 679 5200",
    "sg:postcode":"60077",
    "sg:province":"IL",
    "wof:name":"T & H Insurance Center",
    "wof:placetype":"venue"
},
  "geometry": {"coordinates":[-87.75417299999999,42.023493],"type":"Point"}
}