{
  "type": "Feature",
  "properties": {
    "addr:full":"2400 178th St Lansing IL 60438",
    "addr:housenumber":"2400",
    "addr:postcode":"60438",
    "addr:street":"178Th St",
    "iso:country":"US",
    "sg:address":"2400 178th St",
    "sg:city":"Lansing",
    "sg:classifiers":[
        {
            "category":"Professional",
            "subcategory":"Computer Services",
            "type":"Services"
        }
    ],
    "sg:phone":"+1 708 785 8085",
    "sg:postcode":"60438",
    "sg:province":"IL",
    "wof:name":"Elite-PC Computer Svc",
    "wof:placetype":"venue"
},
  "geometry": {"coordinates":[-87.55820799999999,41.571949],"type":"Point"}
}