{
  "type": "Feature",
  "properties": {
    "iso:country":"US",
    "sg:address":"7408 Archer Ave",
    "sg:city":"Summit Argo",
    "sg:classifiers":[
        {
            "category":"Retail",
            "subcategory":"Laundry & Dry Cleaning",
            "type":"Services"
        }
    ],
    "sg:phone":"+1 708 563 0781",
    "sg:postcode":"60501",
    "sg:province":"IL",
    "sg:tags":[
        "drycleaning",
        "plant"
    ],
    "wof:name":"Village Dry Cleaners",
    "wof:placetype":"venue"
},
  "geometry": {"coordinates":[-87.80730200000001,41.791801],"type":"Point"}
}