{
  "type": "Feature",
  "properties": {
    "iso:country":"US",
    "sg:address":"2200 S Wolf Rd",
    "sg:city":"Des Plaines",
    "sg:classifiers":[
        {
            "category":"Manufacturing",
            "subcategory":"Printing",
            "type":"Manufacturing & Wholesale Goods"
        }
    ],
    "sg:phone":"+1 847 803 2200",
    "sg:postcode":"60018",
    "sg:province":"IL",
    "wof:name":"Pamco Printed Tape & Label Co",
    "wof:placetype":"venue"
},
  "geometry": {"coordinates":[-87.908912,42.010296],"type":"Point"}
}