{
  "type": "Feature",
  "properties": {
    "iso:country":"US",
    "sg:address":"564 W Stratford Pl",
    "sg:city":"Chicago",
    "sg:classifiers":[
        {
            "category":"Home & Garden",
            "subcategory":"Furniture",
            "type":"Retail Goods"
        }
    ],
    "sg:phone":"+1 773 525 6060",
    "sg:postcode":"60657",
    "sg:province":"IL",
    "sg:tags":[
        "pottery",
        "household",
        "mfg"
    ],
    "wof:name":"Bradley Lippitz Ltd",
    "wof:placetype":"venue"
},
  "geometry": {"coordinates":[-87.645675,41.944953],"type":"Point"}
}