{
  "type": "Feature",
  "properties": {
    "addr:full":"1142 W Thorndale Ave Chicago IL 60660",
    "addr:housenumber":"1142",
    "addr:postcode":"60660",
    "addr:street":"W Thorndale Ave",
    "iso:country":"US",
    "sg:address":"1142 W Thorndale Ave",
    "sg:city":"Chicago",
    "sg:classifiers":[
        {
            "category":"Shopping",
            "subcategory":"Jewelry",
            "type":"Retail Goods"
        }
    ],
    "sg:phone":"+1 773 516 0647",
    "sg:postcode":"60660",
    "sg:province":"IL",
    "wof:name":"Armen's Jewelry",
    "wof:placetype":"venue"
},
  "geometry": {"coordinates":[-87.65967499999999,41.990043],"type":"Point"}
}