{
  "type": "Feature",
  "properties": {
    "iso:country":"US",
    "sg:address":"2864 River Rd",
    "sg:city":"Kankakee",
    "sg:classifiers":[
        {
            "category":"Professional",
            "subcategory":"Business Services",
            "type":"Services"
        }
    ],
    "sg:phone":"+1 815 939 7372",
    "sg:postcode":"60901",
    "sg:province":"IL",
    "sg:tags":[
        "messenger"
    ],
    "wof:name":"Mary Weeks Message Therapist",
    "wof:placetype":"venue"
},
  "geometry": {"coordinates":[-87.821169,41.079169],"type":"Point"}
}