{
  "type": "Feature",
  "properties": {
    "iso:country":"US",
    "sg:address":"1320 38th St",
    "sg:city":"Peru",
    "sg:classifiers":[
        {
            "category":"Shopping",
            "subcategory":"Clothing, Apparel, & Fashions",
            "type":"Retail Goods"
        }
    ],
    "sg:phone":"+1   ",
    "sg:postcode":"61354",
    "sg:province":"IL",
    "sg:tags":[
        "western",
        "wear"
    ],
    "wof:name":"Western Cattle Company",
    "wof:placetype":"venue"
},
  "geometry": {"coordinates":[-89.123299,41.358624],"type":"Point"}
}