{
  "type": "Feature",
  "properties": {
    "addr:full":"2613 S Rising Rd Champaign IL 61822",
    "addr:housenumber":"2613",
    "addr:postcode":"61822",
    "addr:street":"S Rising Rd",
    "iso:country":"US",
    "sg:address":"2613 S Rising Rd",
    "sg:city":"Champaign",
    "sg:classifiers":[
        {
            "category":"Building & Trades",
            "subcategory":"Landscaping Services",
            "type":"Services"
        }
    ],
    "sg:phone":"+1 217 863 2500",
    "sg:postcode":"61822",
    "sg:province":"IL",
    "sg:tags":[
        "designer",
        "landscape"
    ],
    "wof:name":"Brown Woods & Assoc",
    "wof:placetype":"venue"
},
  "geometry": {"coordinates":[-88.333789,40.141375],"type":"Point"}
}