{
  "type": "Feature",
  "properties": {
    "addr:full":"5837 Park Dr Charleston IL 61920",
    "addr:housenumber":"5837",
    "addr:postcode":"61920",
    "addr:street":"Park Dr",
    "iso:country":"US",
    "sg:address":"5837 Park Dr",
    "sg:city":"Charleston",
    "sg:classifiers":[
        {
            "category":"Banks & Credit Unions",
            "subcategory":"Investment Brokerage",
            "type":"Services"
        }
    ],
    "sg:phone":"+1 217 235 2212",
    "sg:postcode":"61920",
    "sg:province":"IL",
    "sg:tags":[
        "security"
    ],
    "wof:name":"A G Edwards & Sons Inc",
    "wof:placetype":"venue"
},
  "geometry": {"coordinates":[-88.265568,39.485511],"type":"Point"}
}