{
  "type": "Feature",
  "properties": {
    "addr:full":"3340 Mall Loop Dr Joliet IL 60431",
    "addr:housenumber":"3340",
    "addr:postcode":"60431",
    "addr:street":"Mall Loop Dr",
    "iso:country":"US",
    "sg:address":"3340 Mall Loop Dr",
    "sg:city":"Joliet",
    "sg:classifiers":[
        {
            "category":"Restaurant",
            "type":"Food & Drink"
        }
    ],
    "sg:menulink":"http://www.allmenus.com/il/plainfield/181121-great-wraps/menu/",
    "sg:phone":"+1 815 267 8764",
    "sg:postcode":"60431",
    "sg:province":"IL",
    "sg:tags":[
        "wrap",
        "american",
        "sandwich"
    ],
    "wof:name":"Great Wraps",
    "wof:placetype":"venue"
},
  "geometry": {"coordinates":[-88.165058,41.57939],"type":"Point"}
}