{
  "type": "Feature",
  "properties": {
    "iso:country":"US",
    "sg:address":"514 Navajo Ct",
    "sg:city":"New Lenox",
    "sg:classifiers":[
        {
            "category":"Building & Trades",
            "subcategory":"Construction",
            "type":"Services"
        }
    ],
    "sg:phone":"+1 815 530 3905",
    "sg:postcode":"60451",
    "sg:province":"IL",
    "sg:tags":[
        "general",
        "contractor"
    ],
    "wof:name":"Graystone Construction Inc",
    "wof:placetype":"venue"
},
  "geometry": {"coordinates":[-88.001349,41.53603],"type":"Point"}
}