{
  "type": "Feature",
  "properties": {
    "iso:country":"US",
    "sg:address":"39 S La Salle St Ste 915",
    "sg:city":"Chicago",
    "sg:classifiers":[
        {
            "category":"Professional",
            "subcategory":"Lawyer & Legal Services",
            "type":"Services"
        }
    ],
    "sg:phone":"+1 312 634 6900",
    "sg:postcode":"60603",
    "sg:province":"IL",
    "wof:name":"Kedzie & Svanascini",
    "wof:placetype":"venue"
},
  "geometry": {"coordinates":[-87.632301,41.881199],"type":"Point"}
}