{
  "type": "Feature",
  "properties": {
    "iso:country":"US",
    "sg:address":"14029 Newgate Ct",
    "sg:city":"Orland Park",
    "sg:classifiers":[
        {
            "category":"Professional",
            "subcategory":"Employment Agencies",
            "type":"Services"
        }
    ],
    "sg:phone":"+1 708 460 9532",
    "sg:postcode":"60462",
    "sg:province":"IL",
    "sg:tags":[
        "help",
        "supply"
    ],
    "wof:name":"Terrys Cleaning Service",
    "wof:placetype":"venue"
},
  "geometry": {"coordinates":[-87.82165999999999,41.636366],"type":"Point"}
}