{
  "type": "Feature",
  "properties": {
    "addr:full":"1645 S West Ave Freeport IL 61032",
    "addr:housenumber":"1645",
    "addr:postcode":"61032",
    "addr:street":"S West Ave",
    "iso:country":"US",
    "sg:address":"1645 S West Ave",
    "sg:city":"Freeport",
    "sg:classifiers":[
        {
            "category":"Restaurant",
            "type":"Food & Drink"
        }
    ],
    "sg:phone":"+1 815 235 5200",
    "sg:postcode":"61032",
    "sg:province":"IL",
    "wof:name":"El Tapatio",
    "wof:placetype":"venue"
},
  "geometry": {"coordinates":[-89.631578,42.281453],"type":"Point"}
}