{
  "type": "Feature",
  "properties": {
    "addr:full":"7454 N Hoyne Ave Apt 2N Chicago IL 60645",
    "addr:housenumber":"7454",
    "addr:postcode":"60645",
    "addr:street":"N Hoyne Ave Apt 2N",
    "iso:country":"US",
    "sg:address":"7454 N Hoyne Ave Apt 2N",
    "sg:city":"Chicago",
    "sg:classifiers":[
        {
            "category":"Real Estate",
            "subcategory":"Real Estate Services",
            "type":"Services"
        },
        {
            "category":"Real Estate",
            "subcategory":"Surveying",
            "type":"Services"
        }
    ],
    "sg:phone":"+1 773 262 1840",
    "sg:postcode":"60645",
    "sg:province":"IL",
    "sg:tags":[
        "industrial",
        "appraisers-commercial",
        "appraiser"
    ],
    "wof:name":"Esc America, Inc.",
    "wof:placetype":"venue"
},
  "geometry": {"coordinates":[-87.682981,42.017132],"type":"Point"}
}