{
  "type": "Feature",
  "properties": {
    "addr:full":"8020 Commercial Ave Loves Park IL 61111",
    "addr:housenumber":"8020",
    "addr:postcode":"61111",
    "addr:street":"Commercial Ave",
    "iso:country":"US",
    "sg:address":"8020 Commercial Ave",
    "sg:city":"Loves Park",
    "sg:classifiers":[
        {
            "category":"Manufacturing",
            "subcategory":"Tools & Machinery",
            "type":"Manufacturing & Wholesale Goods"
        }
    ],
    "sg:phone":"+1 815 877 1634",
    "sg:postcode":"61111",
    "sg:province":"IL",
    "sg:tags":[
        "machine",
        "repair",
        "tooling"
    ],
    "wof:name":"Lake Machine",
    "wof:placetype":"venue"
},
  "geometry": {"coordinates":[-89.019839,42.342231],"type":"Point"}
}