{
  "type": "Feature",
  "properties": {
    "iso:country":"US",
    "sg:address":"22 S 1st St",
    "sg:city":"Geneva",
    "sg:classifiers":[
        {
            "category":"Government",
            "subcategory":"Office",
            "type":"Public Place"
        }
    ],
    "sg:phone":"+1 630 232 7494",
    "sg:postcode":"60134",
    "sg:province":"IL",
    "sg:tags":[
        "city"
    ],
    "wof:name":"Geneva Mayor's Office",
    "wof:placetype":"venue"
},
  "geometry": {"coordinates":[-88.30540000000001,41.886733],"type":"Point"}
}