{
  "type": "Feature",
  "properties": {
    "iso:country":"US",
    "sg:address":"8079 E 450th St",
    "sg:city":"Colchester",
    "sg:classifiers":[
        {
            "category":"Farming",
            "subcategory":"Farm",
            "type":"Manufacturing & Wholesale Goods"
        }
    ],
    "sg:phone":"+1 309 776 3320",
    "sg:postcode":"62326",
    "sg:province":"IL",
    "wof:name":"K Enterprises",
    "wof:placetype":"venue"
},
  "geometry": {"coordinates":[-90.820403,40.398538],"type":"Point"}
}