{
  "type": "Feature",
  "properties": {
    "iso:country":"US",
    "sg:address":"951 N Old Rand Rd",
    "sg:city":"Wauconda",
    "sg:classifiers":[
        {
            "category":"Building & Trades",
            "subcategory":"Construction",
            "type":"Services"
        }
    ],
    "sg:phone":"+1 847 487 7900",
    "sg:postcode":"60084",
    "sg:province":"IL",
    "sg:tags":[
        "porch",
        "enclosure",
        "patio",
        "deck"
    ],
    "wof:name":"Armcor Design & Build",
    "wof:placetype":"venue"
},
  "geometry": {"coordinates":[-88.146542,42.274402],"type":"Point"}
}