{
  "type": "Feature",
  "properties": {
    "addr:full":"509 W Colfax St Palatine IL 60067",
    "addr:housenumber":"509",
    "addr:postcode":"60067",
    "addr:street":"W Colfax St",
    "iso:country":"US",
    "sg:address":"509 W Colfax St",
    "sg:city":"Palatine",
    "sg:classifiers":[
        {
            "category":"Freight",
            "type":"Transportation"
        }
    ],
    "sg:phone":"+1 847 358 2466",
    "sg:postcode":"60067",
    "sg:province":"IL",
    "sg:tags":[
        "warehouse",
        "self",
        "storage"
    ],
    "wof:name":"Colfax 24 Hr Self Storage",
    "wof:placetype":"venue"
},
  "geometry": {"coordinates":[-88.055511,42.116563],"type":"Point"}
}