{
  "type": "Feature",
  "properties": {
    "addr:full":"1114 Cassie Dr Joliet IL 60435",
    "addr:housenumber":"1114",
    "addr:postcode":"60435",
    "addr:street":"Cassie Dr",
    "iso:country":"US",
    "sg:address":"1114 Cassie Dr",
    "sg:city":"Joliet",
    "sg:phone":"+1 815 725 5787",
    "sg:postcode":"60435",
    "sg:province":"IL",
    "sg:tags":[
        "farm",
        "corn",
        "grain",
        "cash"
    ],
    "wof:name":"David Cattron",
    "wof:placetype":"venue"
},
  "geometry": {"coordinates":[-88.155402,41.543625],"type":"Point"}
}