{
  "type": "Feature",
  "properties": {
    "addr:full":"647 N Independence Blvd Romeoville IL 60446",
    "addr:housenumber":"647",
    "addr:postcode":"60446",
    "addr:street":"N Independence Blvd",
    "iso:country":"US",
    "sg:address":"647 N Independence Blvd",
    "sg:city":"Romeoville",
    "sg:classifiers":[
        {
            "category":"Food & Beverages",
            "subcategory":"Groceries & Convenience Stores",
            "type":"Retail Goods"
        }
    ],
    "sg:phone":"+1 815 293 3836",
    "sg:postcode":"60446",
    "sg:province":"IL",
    "sg:tags":[
        "grocer"
    ],
    "wof:name":"Super Mercado Don Augustine",
    "wof:placetype":"venue"
},
  "geometry": {"coordinates":[-88.080517,41.652163],"type":"Point"}
}