{
  "type": "Feature",
  "properties": {
    "iso:country":"US",
    "sg:address":"3515 N 1300E Rd",
    "sg:city":"Kempton",
    "sg:classifiers":[
        {
            "category":"Manufacturing",
            "subcategory":"Food",
            "type":"Manufacturing & Wholesale Goods"
        },
        {
            "category":"Farming",
            "subcategory":"Farm",
            "type":"Manufacturing & Wholesale Goods"
        }
    ],
    "sg:phone":"+1 815 253 6418",
    "sg:postcode":"60946",
    "sg:province":"IL",
    "sg:tags":[
        "corn",
        "product"
    ],
    "wof:name":"Travis Farley",
    "wof:placetype":"venue"
},
  "geometry": {"coordinates":[-88.22575399999999,40.909931],"type":"Point"}
}