{
  "type": "Feature",
  "properties": {
    "iso:country":"US",
    "sg:address":"1 E Saint Charles Rd",
    "sg:city":"Lombard",
    "sg:classifiers":[
        {
            "category":"Bakery",
            "type":"Food & Drink"
        },
        {
            "category":"Coffee & Tea",
            "type":"Food & Drink"
        },
        {
            "category":"Bagels",
            "type":"Food & Drink"
        },
        {
            "category":"Donuts",
            "type":"Food & Drink"
        }
    ],
    "sg:menulink":"http://www.allmenus.com/il/york/135217-dunkin-donuts/menu/",
    "sg:phone":"+1 630 620 9744",
    "sg:postcode":"60148",
    "sg:province":"IL",
    "sg:tags":[
        "american",
        "pastry"
    ],
    "wof:name":"Dunkin' Donuts",
    "wof:placetype":"venue"
},
  "geometry": {"coordinates":[-88.01827900000001,41.887254],"type":"Point"}
}