{
  "type": "Feature",
  "properties": {
    "iso:country":"US",
    "sg:address":"757 Stuffishook Rd",
    "sg:city":"Addieville",
    "sg:phone":"+1 618 824 6421",
    "sg:postcode":"62214",
    "sg:province":"IL",
    "sg:tags":[
        "farm",
        "corn",
        "wheat",
        "soybean"
    ],
    "wof:name":"Lohman Farms",
    "wof:placetype":"venue"
},
  "geometry": {"coordinates":[-89.69018800000001,38.41197],"type":"Point"}
}