{
  "type": "Feature",
  "properties": {
    "addr:full":"2020 Balmoral Ave Chicago IL 60625",
    "addr:housenumber":"2020",
    "addr:postcode":"60625",
    "addr:street":"Balmoral Ave",
    "iso:country":"US",
    "sg:address":"2020 Balmoral Ave",
    "sg:city":"Chicago",
    "sg:classifiers":[
        {
            "category":"Wholesale",
            "subcategory":"Scrap",
            "type":"Manufacturing & Wholesale Goods"
        }
    ],
    "sg:phone":"+1 773 310 9500",
    "sg:postcode":"60625",
    "sg:province":"IL",
    "sg:tags":[
        "junk",
        "hauling",
        "removal"
    ],
    "sg:website":"atozhauling.com",
    "wof:name":"A To Z Hauling",
    "wof:placetype":"venue"
},
  "geometry": {"coordinates":[-87.68044500000001,41.979917],"type":"Point"}
}