{
  "type": "Feature",
  "properties": {
    "addr:full":"416 N 1st St Rochelle IL 61068",
    "addr:housenumber":"416",
    "addr:postcode":"61068",
    "addr:street":"N 1St St",
    "iso:country":"US",
    "sg:address":"416 N 1st St",
    "sg:city":"Rochelle",
    "sg:classifiers":[
        {
            "category":"Retail",
            "subcategory":"Auto Repair",
            "type":"Services"
        }
    ],
    "sg:phone":"+1 815 562 5919",
    "sg:postcode":"61068",
    "sg:province":"IL",
    "sg:tags":[
        "exchanging",
        "engine"
    ],
    "wof:name":"J & M Small Engine Repair",
    "wof:placetype":"venue"
},
  "geometry": {"coordinates":[-89.062145,41.92306],"type":"Point"}
}