{
  "type": "Feature",
  "properties": {
    "addr:full":"802 W University Ave Champaign IL 61820",
    "addr:housenumber":"802",
    "addr:postcode":"61820",
    "addr:street":"W University Ave",
    "iso:country":"US",
    "sg:address":"802 W University Ave",
    "sg:city":"Champaign",
    "sg:classifiers":[
        {
            "category":"Travel",
            "subcategory":"Bed & Breakfast",
            "type":"Entertainment"
        }
    ],
    "sg:phone":"+1 217 390 9830",
    "sg:postcode":"61820",
    "sg:province":"IL",
    "sg:website":"champaignilbedandbreakfast.com",
    "wof:name":"The Avenue Bed & Breakfast",
    "wof:placetype":"venue"
},
  "geometry": {"coordinates":[-88.25598100000001,40.116603],"type":"Point"}
}