{
  "type": "Feature",
  "properties": {
    "iso:country":"US",
    "sg:address":"4300 W Grand Ave",
    "sg:city":"Chicago",
    "sg:classifiers":[
        {
            "category":"Retail",
            "subcategory":"Auto Repair",
            "type":"Services"
        }
    ],
    "sg:phone":"+1 773 235 9394",
    "sg:postcode":"60651",
    "sg:province":"IL",
    "sg:tags":[
        "general"
    ],
    "wof:name":"Sistema Mufflers Inc",
    "wof:placetype":"venue"
},
  "geometry": {"coordinates":[-87.73386000000001,41.909112],"type":"Point"}
}