{
  "type": "Feature",
  "properties": {
    "iso:country":"US",
    "sg:address":"590 N McLean Blvd",
    "sg:city":"Elgin",
    "sg:classifiers":[
        {
            "category":"Banks & Credit Unions",
            "subcategory":"Bank",
            "type":"Services"
        }
    ],
    "sg:phone":"+1 847 888 7985",
    "sg:postcode":"60123",
    "sg:province":"IL",
    "wof:name":"Elgin State Bank",
    "wof:placetype":"venue"
},
  "geometry": {"coordinates":[-88.314432,42.016143],"type":"Point"}
}