{
  "type": "Feature",
  "properties": {
    "iso:country":"US",
    "sg:address":"413 Fairmont Dr",
    "sg:city":"Dekalb",
    "sg:classifiers":[
        {
            "category":"Communications",
            "subcategory":"Film & Video Production",
            "type":"Services"
        }
    ],
    "sg:phone":"+1 815 758 5149",
    "sg:postcode":"60115",
    "sg:province":"IL",
    "sg:tags":[
        "motion",
        "picture",
        "studio",
        "producer"
    ],
    "wof:name":"Even Productions",
    "wof:placetype":"venue"
},
  "geometry": {"coordinates":[-88.75549599999999,41.941704],"type":"Point"}
}