{
  "type": "Feature",
  "properties": {
    "iso:country":"US",
    "sg:address":"321 W Main St",
    "sg:city":"Ottawa",
    "sg:classifiers":[
        {
            "category":"Banks & Credit Unions",
            "subcategory":"Bank",
            "type":"Services"
        }
    ],
    "sg:phone":"+1 815 431 9250",
    "sg:postcode":"61350",
    "sg:province":"IL",
    "sg:tags":[
        "financing"
    ],
    "wof:name":"Upper Illinois River Valley",
    "wof:placetype":"venue"
},
  "geometry": {"coordinates":[-88.84532299999999,41.345654],"type":"Point"}
}