{
  "type": "Feature",
  "properties": {
    "addr:full":"4650 Western Ave Lisle IL 60532",
    "addr:housenumber":"4650",
    "addr:postcode":"60532",
    "addr:street":"Western Ave",
    "iso:country":"US",
    "sg:address":"4650 Western Ave",
    "sg:city":"Lisle",
    "sg:classifiers":[
        {
            "category":"Manufacturing",
            "subcategory":"Apparel",
            "type":"Manufacturing & Wholesale Goods"
        }
    ],
    "sg:phone":"+1 630 663 1000",
    "sg:postcode":"60532",
    "sg:province":"IL",
    "sg:tags":[
        "dress"
    ],
    "sg:website":"www.cassandrastone.com",
    "wof:name":"Creative Imports",
    "wof:placetype":"venue"
},
  "geometry": {"coordinates":[-88.09642599999999,41.799812],"type":"Point"}
}