{
  "type": "Feature",
  "properties": {
    "addr:full":"3614 Waukegan Rd Mc Henry IL 60050",
    "addr:housenumber":"3614",
    "addr:postcode":"60050",
    "addr:street":"Waukegan Rd",
    "iso:country":"US",
    "sg:address":"3614 Waukegan Rd",
    "sg:city":"Mc Henry",
    "sg:classifiers":[
        {
            "category":"Education",
            "subcategory":"School",
            "type":"Public Place"
        }
    ],
    "sg:phone":"+1 815 385 8120",
    "sg:postcode":"60050",
    "sg:province":"IL",
    "wof:name":"Landmark Elementary School",
    "wof:placetype":"venue"
},
  "geometry": {"coordinates":[-88.267366,42.343042],"type":"Point"}
}