{
  "type": "Feature",
  "properties": {
    "addr:full":"3412 W 183rd St Hazel Crest IL 60429",
    "addr:housenumber":"3412",
    "addr:postcode":"60429",
    "addr:street":"W 183Rd St",
    "iso:country":"US",
    "sg:address":"3412 W 183rd St",
    "sg:city":"Hazel Crest",
    "sg:classifiers":[
        {
            "category":"Restaurant",
            "type":"Food & Drink"
        }
    ],
    "sg:menulink":"http://www.allmenus.com/il/bremen/23440-kennys-ribs--chicken/menu/",
    "sg:phone":"+1 708 206 1500",
    "sg:postcode":"60429",
    "sg:province":"IL",
    "sg:tags":[
        "american",
        "southern"
    ],
    "wof:name":"Kenny's Ribs & Chicken",
    "wof:placetype":"venue"
},
  "geometry": {"coordinates":[-87.698584,41.557218],"type":"Point"}
}