{
  "type": "Feature",
  "properties": {
    "addr:full":"2303 Charles St Rockford IL 61104",
    "addr:housenumber":"2303",
    "addr:postcode":"61104",
    "addr:street":"Charles St",
    "iso:country":"US",
    "sg:address":"2303 Charles St",
    "sg:city":"Rockford",
    "sg:classifiers":[
        {
            "category":"Shopping",
            "subcategory":"Computers & Home Electronics",
            "type":"Retail Goods"
        }
    ],
    "sg:phone":"+1 815 227 1437",
    "sg:postcode":"61104",
    "sg:province":"IL",
    "sg:tags":[
        "equipment",
        "dealer"
    ],
    "wof:name":"Gemini Computer Systems Inc",
    "wof:placetype":"venue"
},
  "geometry": {"coordinates":[-89.06027899999999,42.260887],"type":"Point"}
}