{
  "type": "Feature",
  "properties": {
    "addr:full":"30223 N Park Ln Libertyville IL 60048",
    "addr:housenumber":"30223",
    "addr:postcode":"60048",
    "addr:street":"N Park Ln",
    "iso:country":"US",
    "sg:address":"30223 N Park Ln",
    "sg:city":"Libertyville",
    "sg:classifiers":[
        {
            "category":"Manufacturing",
            "subcategory":"Metals",
            "type":"Manufacturing & Wholesale Goods"
        }
    ],
    "sg:phone":"+1 847 367 5718",
    "sg:postcode":"60048",
    "sg:province":"IL",
    "sg:tags":[
        "steel",
        "product",
        "stampings",
        "mfg"
    ],
    "wof:name":"McCarthy Enterprises Inc",
    "wof:placetype":"venue"
},
  "geometry": {"coordinates":[-87.930392,42.300338],"type":"Point"}
}