{
  "type": "Feature",
  "properties": {
    "addr:full":"204 N Walnut St De Soto IL 62924",
    "addr:housenumber":"204",
    "addr:postcode":"62924",
    "addr:street":"N Walnut St",
    "iso:country":"US",
    "sg:address":"204 N Walnut St",
    "sg:city":"De Soto",
    "sg:classifiers":[
        {
            "category":"Professional",
            "subcategory":"Advertising",
            "type":"Services"
        }
    ],
    "sg:phone":"+1 618 867 3613",
    "sg:postcode":"62924",
    "sg:province":"IL",
    "wof:name":"Riverfront Online",
    "wof:placetype":"venue"
},
  "geometry": {"coordinates":[-89.229406,37.818774],"type":"Point"}
}