{
  "type": "Feature",
  "properties": {
    "addr:full":"77 W Wacker Drive Lbby Chicago IL 60601",
    "addr:housenumber":"77",
    "addr:postcode":"60601",
    "addr:street":"W Wacker Drive",
    "iso:country":"US",
    "sg:address":"77 W Wacker Drive Lbby",
    "sg:city":"Chicago",
    "sg:classifiers":[
        {
            "category":"Professional",
            "subcategory":"Lawyer & Legal Services",
            "type":"Services"
        }
    ],
    "sg:phone":"+1 312 456 8400",
    "sg:postcode":"60601",
    "sg:province":"IL",
    "wof:name":"McGaugh Raymond S",
    "wof:placetype":"venue"
},
  "geometry": {"coordinates":[-87.62998,41.886755],"type":"Point"}
}