{
  "type": "Feature",
  "properties": {
    "iso:country":"US",
    "sg:address":"834 S 12th St",
    "sg:city":"Quincy",
    "sg:classifiers":[
        {
            "category":"Restaurant",
            "type":"Food & Drink"
        }
    ],
    "sg:phone":"+1   ",
    "sg:postcode":"62301",
    "sg:province":"IL",
    "sg:tags":[
        "eating"
    ],
    "wof:name":"Hardees",
    "wof:placetype":"venue"
},
  "geometry": {"coordinates":[-91.396478,39.921948],"type":"Point"}
}