{
  "type": "Feature",
  "properties": {
    "iso:country":"US",
    "sg:address":"180 W Ogden Ave",
    "sg:city":"Westmont",
    "sg:classifiers":[
        {
            "category":"Fast Food",
            "type":"Food & Drink"
        },
        {
            "category":"Restaurant",
            "type":"Food & Drink"
        },
        {
            "category":"Food & Beverages",
            "subcategory":"Groceries & Convenience Stores",
            "type":"Retail Goods"
        }
    ],
    "sg:phone":"+1 630 968 5533",
    "sg:postcode":"60559",
    "sg:province":"IL",
    "sg:tags":[
        "shop",
        "american",
        "sandwich"
    ],
    "sg:website":"http://www.arbys.com",
    "wof:name":"Arby's",
    "wof:placetype":"venue"
},
  "geometry": {"coordinates":[-87.98049,41.809943],"type":"Point"}
}