{
  "type": "Feature",
  "properties": {
    "iso:country":"US",
    "sg:address":"625 N Maple Ave",
    "sg:city":"Palatine",
    "sg:classifiers":[
        {
            "category":"Autos & Motor Vehicles",
            "subcategory":"Fuel & Gas Station",
            "type":"Retail Goods"
        }
    ],
    "sg:phone":"+1   ",
    "sg:postcode":"60067",
    "sg:province":"IL",
    "sg:tags":[
        "operation",
        "store"
    ],
    "wof:name":"Sandhu Petroleum Inc",
    "wof:placetype":"venue"
},
  "geometry": {"coordinates":[-88.066305,42.122925],"type":"Point"}
}