{
  "type": "Feature",
  "properties": {
    "addr:full":"103 5th St Peru IL 61354",
    "addr:housenumber":"103",
    "addr:postcode":"61354",
    "addr:street":"5Th St",
    "iso:country":"US",
    "sg:address":"103 5th St",
    "sg:city":"Peru",
    "sg:classifiers":[
        {
            "category":"Banks & Credit Unions",
            "subcategory":"Bank",
            "type":"Services"
        }
    ],
    "sg:phone":"+1 815 220 8200",
    "sg:postcode":"61354",
    "sg:province":"IL",
    "sg:tags":[
        "loan",
        "real estate"
    ],
    "wof:name":"Mortgage Shoppe Inc",
    "wof:placetype":"venue"
},
  "geometry": {"coordinates":[-89.205044,41.177901],"type":"Point"}
}