{
  "type": "Feature",
  "properties": {
    "iso:country":"US",
    "sg:address":"2645 W Monroe St",
    "sg:city":"Chicago",
    "sg:classifiers":[
        {
            "category":"Home & Garden",
            "subcategory":"Furniture",
            "type":"Retail Goods"
        },
        {
            "category":"Home & Garden",
            "subcategory":"Building Materials",
            "type":"Retail Goods"
        },
        {
            "category":"Building & Trades",
            "subcategory":"Construction",
            "type":"Services"
        },
        {
            "category":"Manufacturing",
            "subcategory":"Building Materials",
            "type":"Manufacturing & Wholesale Goods"
        },
        {
            "category":"Train Station",
            "subcategory":"Rail",
            "type":"Transportation"
        }
    ],
    "sg:phone":"+1 866 977 8694",
    "sg:postcode":"60612",
    "sg:province":"IL",
    "sg:tags":[
        "stairway",
        "cabinet",
        "counter",
        "sheet",
        "top",
        "work",
        "metal",
        "rails",
        "accessory",
        "railing",
        "contractor",
        "welder",
        "equipment-household",
        "kitchen"
    ],
    "wof:name":"C & B Welders, Inc.",
    "wof:placetype":"venue"
},
  "geometry": {"coordinates":[-87.69241,41.880211],"type":"Point"}
}