{
  "type": "Feature",
  "properties": {
    "addr:full":"5507 N Cumberland Ave Ste 409 Chicago IL 60656",
    "addr:housenumber":"5507",
    "addr:postcode":"60656",
    "addr:street":"N Cumberland Ave Ste 409",
    "iso:country":"US",
    "sg:address":"5507 N Cumberland Ave Ste 409",
    "sg:city":"Chicago",
    "sg:classifiers":[
        {
            "category":"Professional",
            "subcategory":"Lawyer & Legal Services",
            "type":"Services"
        }
    ],
    "sg:phone":"+1 773 631 9215",
    "sg:postcode":"60656",
    "sg:province":"IL",
    "wof:name":"Strzalka Mary Alice Attorney At Law",
    "wof:placetype":"venue"
},
  "geometry": {"coordinates":[-87.83626599999999,41.97937],"type":"Point"}
}