{
  "type": "Feature",
  "properties": {
    "iso:country":"US",
    "sg:address":"250 W Hawley St",
    "sg:city":"Amboy",
    "sg:classifiers":[
        {
            "category":"Professional",
            "type":"Services"
        }
    ],
    "sg:phone":"+1 815 288 6691",
    "sg:postcode":"61310",
    "sg:province":"IL",
    "wof:name":"Kreider Services",
    "wof:placetype":"venue"
},
  "geometry": {"coordinates":[-89.337407,41.720491],"type":"Point"}
}