{
  "type": "Feature",
  "properties": {
    "addr:full":"2323 N Damen Ave Chicago IL 60647",
    "addr:housenumber":"2323",
    "addr:postcode":"60647",
    "addr:street":"N Damen Ave",
    "iso:country":"US",
    "sg:address":"2323 N Damen Ave",
    "sg:city":"Chicago",
    "sg:classifiers":[
        {
            "category":"Freight",
            "type":"Transportation"
        }
    ],
    "sg:phone":"+1 773 235 0495",
    "sg:postcode":"60647",
    "sg:province":"IL",
    "sg:tags":[
        "specializing",
        "distance",
        "long",
        "trucking",
        "mover",
        "local"
    ],
    "sg:website":"www.tandjmovers.com",
    "wof:name":"T & J Movers",
    "wof:placetype":"venue"
},
  "geometry": {"coordinates":[-87.677902,41.923],"type":"Point"}
}