{
  "type": "Feature",
  "properties": {
    "iso:country":"US",
    "sg:address":"546 N Western Ave",
    "sg:city":"Lake Forest",
    "sg:classifiers":[
        {
            "category":"Shopping",
            "subcategory":"Florist",
            "type":"Retail Goods"
        }
    ],
    "sg:phone":"+1 847 234 0017",
    "sg:postcode":"60045",
    "sg:province":"IL",
    "sg:website":"www.lakeforestflowers.com",
    "wof:name":"Lake Forest Florist",
    "wof:placetype":"venue"
},
  "geometry": {"coordinates":[-87.839031,42.24844],"type":"Point"}
}