{
  "type": "Feature",
  "properties": {
    "iso:country":"US",
    "sg:address":"6327 John St",
    "sg:city":"Loves Park",
    "sg:classifiers":[
        {
            "category":"Building & Trades",
            "subcategory":"Cleaning & Sanitation",
            "type":"Services"
        }
    ],
    "sg:phone":"+1 815 636 1565",
    "sg:postcode":"61111",
    "sg:province":"IL",
    "sg:tags":[
        "maintenance"
    ],
    "wof:name":"Nos Cleaning Service",
    "wof:placetype":"venue"
},
  "geometry": {"coordinates":[-89.04714300000001,42.323104],"type":"Point"}
}