{
  "type": "Feature",
  "properties": {
    "iso:country":"US",
    "sg:address":"727 Tarbat Ct",
    "sg:city":"Inverness",
    "sg:classifiers":[
        {
            "category":"Professional",
            "subcategory":"Art Services",
            "type":"Services"
        }
    ],
    "sg:phone":"+1 847 842 9651",
    "sg:postcode":"60010",
    "sg:province":"IL",
    "sg:tags":[
        "graphic",
        "designer"
    ],
    "wof:name":"Infinity Marketing",
    "wof:placetype":"venue"
},
  "geometry": {"coordinates":[-88.113551,42.122131],"type":"Point"}
}