{
  "type": "Feature",
  "properties": {
    "addr:full":"2817 Flossmoor Rd Flossmoor IL 60422",
    "addr:housenumber":"2817",
    "addr:postcode":"60422",
    "addr:street":"Flossmoor Rd",
    "iso:country":"US",
    "sg:address":"2817 Flossmoor Rd",
    "sg:city":"Flossmoor",
    "sg:classifiers":[
        {
            "category":"Health Services",
            "subcategory":"Chiropractor",
            "type":"Services"
        }
    ],
    "sg:phone":"+1 708 798 5290",
    "sg:postcode":"60422",
    "sg:province":"IL",
    "wof:name":"Demko Chiropractic Svc",
    "wof:placetype":"venue"
},
  "geometry": {"coordinates":[-87.685659,41.542642],"type":"Point"}
}