{
  "type": "Feature",
  "properties": {
    "iso:country":"US",
    "sg:address":"67 E Cermak Rd",
    "sg:city":"Chicago",
    "sg:classifiers":[
        {
            "category":"Bars & Pubs",
            "type":"Food & Drink"
        },
        {
            "category":"Restaurant",
            "type":"Food & Drink"
        },
        {
            "category":"Arts & Performance",
            "subcategory":"Jazz & Blues",
            "type":"Entertainment"
        },
        {
            "category":"Bars & Pubs",
            "subcategory":"Lounge",
            "type":"Food & Drink"
        }
    ],
    "sg:phone":"+1 312 791 9050",
    "sg:postcode":"60616",
    "sg:province":"IL",
    "sg:tags":[
        "brew",
        "grill",
        "cocktail"
    ],
    "sg:website":"www.velvetlounge.net",
    "wof:name":"Velvet Lounge",
    "wof:placetype":"venue"
},
  "geometry": {"coordinates":[-87.624381,41.852765],"type":"Point"}
}