{
  "type": "Feature",
  "properties": {
    "addr:full":"8501 Bailey Rd Darien IL 60561",
    "addr:housenumber":"8501",
    "addr:postcode":"60561",
    "addr:street":"Bailey Rd",
    "iso:country":"US",
    "sg:address":"8501 Bailey Rd",
    "sg:city":"Darien",
    "sg:classifiers":[
        {
            "category":"Shopping",
            "type":"Retail Goods"
        }
    ],
    "sg:phone":"+1 630 969 0001",
    "sg:postcode":"60561",
    "sg:province":"IL",
    "sg:tags":[
        "religious"
    ],
    "sg:website":"http://carmelitegifts.com",
    "wof:name":"Carmelite Gift Shop",
    "wof:placetype":"venue"
},
  "geometry": {"coordinates":[-87.97756200000001,41.733227],"type":"Point"}
}