{
  "type": "Feature",
  "properties": {
    "addr:full":"1301 N Dearborn Street Chicago IL 60610",
    "addr:housenumber":"1301",
    "addr:postcode":"60610",
    "addr:street":"N Dearborn Street",
    "iso:country":"US",
    "sg:address":"1301 N Dearborn Street",
    "sg:city":"Chicago",
    "sg:classifiers":[
        {
            "category":"Real Estate",
            "subcategory":"Real Estate Operator",
            "type":"Services"
        }
    ],
    "sg:phone":"+1 312 654 9080",
    "sg:postcode":"60610",
    "sg:province":"IL",
    "sg:tags":[
        "apartment"
    ],
    "wof:name":"Whitney Condiminum Assn",
    "wof:placetype":"venue"
},
  "geometry": {"coordinates":[-87.630036,41.905792],"type":"Point"}
}