{
  "type": "Feature",
  "properties": {
    "iso:country":"US",
    "sg:address":"5581 Northwest Hwy",
    "sg:city":"Chicago",
    "sg:classifiers":[
        {
            "category":"Bars & Pubs",
            "subcategory":"Dive Bar",
            "type":"Food & Drink"
        }
    ],
    "sg:phone":"+1 773 837 5309",
    "sg:postcode":"60630",
    "sg:province":"IL",
    "wof:name":"Jimmy Mac's",
    "wof:placetype":"venue"
},
  "geometry": {"coordinates":[-87.781149,41.982591],"type":"Point"}
}