{
  "type": "Feature",
  "properties": {
    "iso:country":"US",
    "sg:address":"1406 Niedringhaus Ave",
    "sg:city":"Granite City",
    "sg:classifiers":[
        {
            "category":"Professional",
            "subcategory":"Lawyer & Legal Services",
            "type":"Services"
        }
    ],
    "sg:phone":"+1 618 452 3110",
    "sg:postcode":"62040",
    "sg:province":"IL",
    "wof:name":"Bosslet Robert W Jr Atty",
    "wof:placetype":"venue"
},
  "geometry": {"coordinates":[-90.147003,38.701401],"type":"Point"}
}