{
  "type": "Feature",
  "properties": {
    "addr:full":"689 Deerpath Dr Deerfield IL 60015",
    "addr:housenumber":"689",
    "addr:postcode":"60015",
    "addr:street":"Deerpath Dr",
    "iso:country":"US",
    "sg:address":"689 Deerpath Dr",
    "sg:city":"Deerfield",
    "sg:classifiers":[
        {
            "category":"Building & Trades",
            "subcategory":"Construction",
            "type":"Services"
        }
    ],
    "sg:phone":"+1 847 945 4022",
    "sg:postcode":"60015",
    "sg:province":"IL",
    "sg:tags":[
        "concrete",
        "contractor",
        "sanitary"
    ],
    "wof:name":"Meintzer Snow Removal",
    "wof:placetype":"venue"
},
  "geometry": {"coordinates":[-87.857934,42.163946],"type":"Point"}
}