{
  "type": "Feature",
  "properties": {
    "iso:country":"US",
    "sg:address":"836 2nd St",
    "sg:city":"La Salle",
    "sg:classifiers":[
        {
            "category":"Food & Beverages",
            "subcategory":"Bakery",
            "type":"Retail Goods"
        }
    ],
    "sg:phone":"+1 815 224 4010",
    "sg:postcode":"61301",
    "sg:province":"IL",
    "sg:tags":[
        "baker"
    ],
    "wof:name":"Continental Baking Co",
    "wof:placetype":"venue"
},
  "geometry": {"coordinates":[-89.093281,41.329341],"type":"Point"}
}