{
  "type": "Feature",
  "properties": {
    "iso:country":"US",
    "sg:address":"517 E Main St",
    "sg:city":"Danville",
    "sg:classifiers":[
        {
            "category":"Building & Trades",
            "subcategory":"Construction",
            "type":"Services"
        }
    ],
    "sg:phone":"+1 217 442 6899",
    "sg:postcode":"61832",
    "sg:province":"IL",
    "sg:tags":[
        "home",
        "light",
        "commercial",
        "contractor"
    ],
    "wof:name":"Progressive Builders",
    "wof:placetype":"venue"
},
  "geometry": {"coordinates":[-87.61887,40.12452],"type":"Point"}
}