{
  "type": "Feature",
  "properties": {
    "addr:full":"6566 Erin Way Roscoe IL 61073",
    "addr:housenumber":"6566",
    "addr:postcode":"61073",
    "addr:street":"Erin Way",
    "iso:country":"US",
    "sg:address":"6566 Erin Way",
    "sg:city":"Roscoe",
    "sg:classifiers":[
        {
            "category":"Professional",
            "subcategory":"Printing & Photocopies",
            "type":"Services"
        }
    ],
    "sg:phone":"+1 815 623 8142",
    "sg:postcode":"61073",
    "sg:province":"IL",
    "sg:tags":[
        "screen"
    ],
    "wof:name":"Roscoe Silkscreening",
    "wof:placetype":"venue"
},
  "geometry": {"coordinates":[-88.988923,42.423111],"type":"Point"}
}