{
  "type": "Feature",
  "properties": {
    "addr:full":"1950 W 13th St Chicago IL 60608",
    "addr:housenumber":"1950",
    "addr:postcode":"60608",
    "addr:street":"W 13Th St",
    "iso:country":"US",
    "sg:address":"1950 W 13th St",
    "sg:city":"Chicago",
    "sg:classifiers":[
        {
            "category":"Social Services",
            "subcategory":"Child Care",
            "type":"Services"
        }
    ],
    "sg:phone":"+1 773 733 1263",
    "sg:postcode":"60608",
    "sg:province":"IL",
    "sg:tags":[
        "day"
    ],
    "sg:website":"www.banquets.newzionmbc.com",
    "wof:name":"New Zion",
    "wof:placetype":"venue"
},
  "geometry": {"coordinates":[-87.674958,41.865165],"type":"Point"}
}