{
  "type": "Feature",
  "properties": {
    "addr:full":"200 E 14th St Danville IL 61832",
    "addr:housenumber":"200",
    "addr:postcode":"61832",
    "addr:street":"E 14Th St",
    "iso:country":"US",
    "sg:address":"200 E 14th St",
    "sg:city":"Danville",
    "sg:classifiers":[
        {
            "category":"Freight",
            "type":"Transportation"
        }
    ],
    "sg:phone":"+1 800 742 5877",
    "sg:postcode":"61832",
    "sg:province":"IL",
    "sg:tags":[
        "delivery",
        "parcel"
    ],
    "wof:name":"UPS",
    "wof:placetype":"venue"
},
  "geometry": {"coordinates":[-87.63045,40.1018],"type":"Point"}
}