{
  "type": "Feature",
  "properties": {
    "iso:country":"US",
    "sg:address":"403 Farmhill Cir",
    "sg:city":"Wauconda",
    "sg:classifiers":[
        {
            "category":"Organizations",
            "subcategory":"Religious Organization",
            "type":"Services"
        }
    ],
    "sg:phone":"+1 847 526 7696",
    "sg:postcode":"60084",
    "sg:province":"IL",
    "wof:name":"Fusion Church Inc",
    "wof:placetype":"venue"
},
  "geometry": {"coordinates":[-88.153729,42.267592],"type":"Point"}
}