{
  "type": "Feature",
  "properties": {
    "iso:country":"US",
    "sg:address":"8765 S Kildare Ave",
    "sg:city":"Oak Lawn",
    "sg:classifiers":[
        {
            "category":"Freight",
            "type":"Transportation"
        }
    ],
    "sg:phone":"+1 708 422 7530",
    "sg:postcode":"60456",
    "sg:province":"IL",
    "wof:name":"South Side Transport",
    "wof:placetype":"venue"
},
  "geometry": {"coordinates":[-87.73004899999999,41.73172],"type":"Point"}
}