{
  "type": "Feature",
  "properties": {
    "addr:full":"157 Nanti St Park Forest IL 60466",
    "addr:housenumber":"157",
    "addr:postcode":"60466",
    "addr:street":"Nanti St",
    "iso:country":"US",
    "sg:address":"157 Nanti St",
    "sg:city":"Park Forest",
    "sg:classifiers":[
        {
            "category":"Building & Trades",
            "subcategory":"Construction",
            "type":"Services"
        }
    ],
    "sg:phone":"+1 708 748 9141",
    "sg:postcode":"60466",
    "sg:province":"IL",
    "sg:tags":[
        "restoration",
        "cleaning",
        "patio",
        "deck"
    ],
    "wof:name":"Exteriors Bright Power Washing",
    "wof:placetype":"venue"
},
  "geometry": {"coordinates":[-87.68962399999999,41.466897],"type":"Point"}
}