{
  "type": "Feature",
  "properties": {
    "iso:country":"US",
    "sg:address":"207 Luce St",
    "sg:city":"Dalzell",
    "sg:classifiers":[
        {
            "category":"Real Estate",
            "subcategory":"Real Estate Agent",
            "type":"Services"
        }
    ],
    "sg:phone":"+1 815 663 0062",
    "sg:postcode":"61320",
    "sg:province":"IL",
    "wof:name":"Macleod Property",
    "wof:placetype":"venue"
},
  "geometry": {"coordinates":[-89.17059,41.356612],"type":"Point"}
}