{
  "type": "Feature",
  "properties": {
    "iso:country":"US",
    "sg:address":"116 Emma Ave",
    "sg:city":"Dupo",
    "sg:classifiers":[
        {
            "category":"Banks & Credit Unions",
            "subcategory":"Bank",
            "type":"Services"
        }
    ],
    "sg:phone":"+1 618 286 7677",
    "sg:postcode":"62239",
    "sg:province":"IL",
    "sg:tags":[
        "loan",
        "real estate"
    ],
    "wof:name":"Creative Mortgage Concepts",
    "wof:placetype":"venue"
},
  "geometry": {"coordinates":[-90.209243,38.520299],"type":"Point"}
}