{
  "type": "Feature",
  "properties": {
    "iso:country":"US",
    "sg:address":"411 N Division St",
    "sg:city":"Pontiac",
    "sg:classifiers":[
        {
            "category":"Personal",
            "subcategory":"Beauty Salon",
            "type":"Services"
        }
    ],
    "sg:phone":"+1 815 842 2926",
    "sg:postcode":"61764",
    "sg:province":"IL",
    "wof:name":"Marianne Arnolts",
    "wof:placetype":"venue"
},
  "geometry": {"coordinates":[-88.633241,40.881229],"type":"Point"}
}