{
  "type": "Feature",
  "properties": {
    "iso:country":"US",
    "sg:address":"4215 E State St",
    "sg:city":"Rockford",
    "sg:classifiers":[
        {
            "category":"Sports & Exercise",
            "subcategory":"Gym",
            "type":"Entertainment"
        }
    ],
    "sg:phone":"+1 815 399 5303",
    "sg:postcode":"61108",
    "sg:province":"IL",
    "sg:tags":[
        "club",
        "health",
        "studio",
        "gymnasium"
    ],
    "wof:name":"Rockford VIG Health Spa",
    "wof:placetype":"venue"
},
  "geometry": {"coordinates":[-89.034944,42.265192],"type":"Point"}
}