{
  "type": "Feature",
  "properties": {
    "addr:full":"9341 Springfield Ave Evanston IL 60203",
    "addr:housenumber":"9341",
    "addr:postcode":"60203",
    "addr:street":"Springfield Ave",
    "iso:country":"US",
    "sg:address":"9341 Springfield Ave",
    "sg:city":"Evanston",
    "sg:classifiers":[
        {
            "category":"Professional",
            "type":"Services"
        }
    ],
    "sg:phone":"+1 847 673 3804",
    "sg:postcode":"60203",
    "sg:province":"IL",
    "wof:name":"Media Masters Inc",
    "wof:placetype":"venue"
},
  "geometry": {"coordinates":[-87.725066,42.050918],"type":"Point"}
}