{
  "type": "Feature",
  "properties": {
    "iso:country":"US",
    "sg:address":"137 W Acton Ave",
    "sg:city":"Wood River",
    "sg:classifiers":[
        {
            "category":"Retail",
            "subcategory":"Laundry & Dry Cleaning",
            "type":"Services"
        }
    ],
    "sg:phone":"+1 618 254 2900",
    "sg:postcode":"62095",
    "sg:province":"IL",
    "wof:name":"Panyiks Prof Crpt & Upholster",
    "wof:placetype":"venue"
},
  "geometry": {"coordinates":[-90.100459,38.862717],"type":"Point"}
}