{
  "type": "Feature",
  "properties": {
    "addr:full":"10001 Grand Ave Franklin Park IL 60131",
    "addr:housenumber":"10001",
    "addr:postcode":"60131",
    "addr:street":"Grand Ave",
    "iso:country":"US",
    "sg:address":"10001 Grand Ave",
    "sg:city":"Franklin Park",
    "sg:classifiers":[
        {
            "category":"Health Services",
            "subcategory":"Clinic",
            "type":"Services"
        }
    ],
    "sg:phone":"+1 847 451 0330",
    "sg:postcode":"60131",
    "sg:province":"IL",
    "sg:tags":[
        "specialty",
        "outpatient"
    ],
    "wof:name":"The Share Program",
    "wof:placetype":"venue"
},
  "geometry": {"coordinates":[-87.87617299999999,41.930042],"type":"Point"}
}