{
  "type": "Feature",
  "properties": {
    "iso:country":"US",
    "sg:address":"33 N Dearborn Street",
    "sg:city":"Chicago",
    "sg:classifiers":[
        {
            "category":"Professional",
            "subcategory":"Accounting & Tax Preparation",
            "type":"Services"
        }
    ],
    "sg:phone":"+1 312 251 4500",
    "sg:postcode":"60602",
    "sg:province":"IL",
    "sg:tags":[
        "accountant"
    ],
    "wof:name":"R G L Gallagher",
    "wof:placetype":"venue"
},
  "geometry": {"coordinates":[-87.629385,41.882691],"type":"Point"}
}