{
  "type": "Feature",
  "properties": {
    "iso:country":"US",
    "sg:address":"1590 S Milwaukee Ave",
    "sg:city":"Libertyville",
    "sg:classifiers":[
        {
            "category":"Professional",
            "subcategory":"Accounting & Tax Preparation",
            "type":"Services"
        }
    ],
    "sg:phone":"+1 847 549 1776",
    "sg:postcode":"60048",
    "sg:province":"IL",
    "sg:tags":[
        "accountant"
    ],
    "wof:name":"Thomas E Drennan CPA",
    "wof:placetype":"venue"
},
  "geometry": {"coordinates":[-87.94797699999999,42.25851],"type":"Point"}
}