{
  "type": "Feature",
  "properties": {
    "addr:full":"318 E Crescent St Gilman IL 60938",
    "addr:housenumber":"318",
    "addr:postcode":"60938",
    "addr:street":"E Crescent St",
    "iso:country":"US",
    "sg:address":"318 E Crescent St",
    "sg:city":"Gilman",
    "sg:classifiers":[
        {
            "category":"Government",
            "subcategory":"Office",
            "type":"Public Place"
        }
    ],
    "sg:phone":"+1 815 265 4516",
    "sg:postcode":"60938",
    "sg:province":"IL",
    "sg:tags":[
        "village"
    ],
    "wof:name":"Pump Station",
    "wof:placetype":"venue"
},
  "geometry": {"coordinates":[-87.988921,40.766471],"type":"Point"}
}