{
  "type": "Feature",
  "properties": {
    "iso:country":"US",
    "sg:address":"980 W South St",
    "sg:city":"Freeport",
    "sg:classifiers":[
        {
            "category":"Health Services",
            "subcategory":"Optometrist",
            "type":"Services"
        }
    ],
    "sg:phone":"+1 815 235 3466",
    "sg:postcode":"61032",
    "sg:province":"IL",
    "wof:name":"Best Insight",
    "wof:placetype":"venue"
},
  "geometry": {"coordinates":[-89.632721,42.280355],"type":"Point"}
}