{
  "type": "Feature",
  "properties": {
    "addr:full":"1115 Howard Dr West Chicago IL 60185",
    "addr:housenumber":"1115",
    "addr:postcode":"60185",
    "addr:street":"Howard Dr West",
    "iso:country":"US",
    "sg:address":"1115 Howard Dr",
    "sg:city":"West Chicago",
    "sg:classifiers":[
        {
            "category":"Professional",
            "subcategory":"Business Services",
            "type":"Services"
        }
    ],
    "sg:phone":"+1 630 293 1200",
    "sg:postcode":"60185",
    "sg:province":"IL",
    "wof:name":"Roadway Express",
    "wof:placetype":"venue"
},
  "geometry": {"coordinates":[-88.241792,41.907399],"type":"Point"}
}