{
  "type": "Feature",
  "properties": {
    "addr:full":"187 N North St Argenta IL 62501",
    "addr:housenumber":"187",
    "addr:postcode":"62501",
    "addr:street":"N North St",
    "iso:country":"US",
    "sg:address":"187 N North St",
    "sg:city":"Argenta",
    "sg:classifiers":[
        {
            "category":"Government",
            "subcategory":"Post Office",
            "type":"Public Place"
        }
    ],
    "sg:phone":"+1 217 795 2065",
    "sg:postcode":"62501",
    "sg:province":"IL",
    "wof:name":"US Post Office",
    "wof:placetype":"venue"
},
  "geometry": {"coordinates":[-89.061616,39.9331],"type":"Point"}
}