{
  "type": "Feature",
  "properties": {
    "addr:full":"4600 Main St Skokie IL 60076",
    "addr:housenumber":"4600",
    "addr:postcode":"60076",
    "addr:street":"Main St",
    "iso:country":"US",
    "sg:address":"4600 Main St",
    "sg:city":"Skokie",
    "sg:classifiers":[
        {
            "category":"Education",
            "subcategory":"School",
            "type":"Public Place"
        }
    ],
    "sg:phone":"+1 847 982 9191",
    "sg:postcode":"60076",
    "sg:province":"IL",
    "sg:tags":[
        "elementary"
    ],
    "wof:name":"Arie Crown Hebrew Day School",
    "wof:placetype":"venue"
},
  "geometry": {"coordinates":[-87.744885,42.033508],"type":"Point"}
}