{
  "type": "Feature",
  "properties": {
    "iso:country":"US",
    "sg:address":"1059 N Old Rand Rd",
    "sg:city":"Wauconda",
    "sg:classifiers":[
        {
            "category":"Home & Garden",
            "subcategory":"Building Materials",
            "type":"Retail Goods"
        },
        {
            "category":"Building & Trades",
            "subcategory":"Construction",
            "type":"Services"
        }
    ],
    "sg:phone":"+1 847 487 6500",
    "sg:postcode":"60084",
    "sg:province":"IL",
    "sg:tags":[
        "shower",
        "door",
        "contractor",
        "glass-wholesale",
        "enclosure",
        "manufacturer"
    ],
    "sg:website":"www.heightsglass.com",
    "wof:name":"Heights Glass & Mirror Co.",
    "wof:placetype":"venue"
},
  "geometry": {"coordinates":[-88.147974,42.275849],"type":"Point"}
}