{
  "type": "Feature",
  "properties": {
    "iso:country":"US",
    "sg:address":"1255 Chapel Hill Rd",
    "sg:city":"Cypress",
    "sg:classifiers":[
        {
            "category":"Health Services",
            "subcategory":"Dentist",
            "type":"Services"
        }
    ],
    "sg:phone":"+1 618 657 2378",
    "sg:postcode":"62923",
    "sg:province":"IL",
    "wof:name":"Wayne Dunn",
    "wof:placetype":"venue"
},
  "geometry": {"coordinates":[-89.042433,37.374067],"type":"Point"}
}