{
  "type": "Feature",
  "properties": {
    "iso:country":"US",
    "sg:address":"250 S Gary Ave Ste 102",
    "sg:city":"Bloomingdale",
    "sg:classifiers":[
        {
            "category":"Retail",
            "subcategory":"Auto Repair",
            "type":"Services"
        }
    ],
    "sg:phone":"+1 630 894 1100",
    "sg:postcode":"60108",
    "sg:province":"IL",
    "wof:name":"Sam's Automotive",
    "wof:placetype":"venue"
},
  "geometry": {"coordinates":[-88.115402,41.952202],"type":"Point"}
}