{
  "type": "Feature",
  "properties": {
    "iso:country":"US",
    "sg:address":"36802 Buck Ct",
    "sg:city":"Lake Villa",
    "sg:classifiers":[
        {
            "category":"Organizations",
            "subcategory":"Religious Organization",
            "type":"Services"
        }
    ],
    "sg:phone":"+1 847 356 0441",
    "sg:postcode":"60046",
    "sg:province":"IL",
    "sg:tags":[
        "music",
        "ministry"
    ],
    "wof:name":"Good News Singing Ministry",
    "wof:placetype":"venue"
},
  "geometry": {"coordinates":[-88.00278400000001,42.397674],"type":"Point"}
}