{
  "type": "Feature",
  "properties": {
    "addr:full":"936 W Castlewood Ter Chicago IL 60640",
    "addr:housenumber":"936",
    "addr:postcode":"60640",
    "addr:street":"W Castlewood Ter",
    "iso:country":"US",
    "sg:address":"936 W Castlewood Ter",
    "sg:city":"Chicago",
    "sg:classifiers":[
        {
            "category":"Professional",
            "subcategory":"Advertising",
            "type":"Services"
        }
    ],
    "sg:phone":"+1 773 878 2720",
    "sg:postcode":"60640",
    "sg:province":"IL",
    "sg:tags":[
        "distributing",
        "sample",
        "service-circular"
    ],
    "wof:name":"K & S Demon Limited Inc",
    "wof:placetype":"venue"
},
  "geometry": {"coordinates":[-87.653254,41.970832],"type":"Point"}
}