{
  "type": "Feature",
  "properties": {
    "addr:full":"2026 N Main St Princeton IL 61356",
    "addr:housenumber":"2026",
    "addr:postcode":"61356",
    "addr:street":"N Main St",
    "iso:country":"US",
    "sg:address":"2026 N Main St",
    "sg:city":"Princeton",
    "sg:classifiers":[
        {
            "category":"Shopping",
            "subcategory":"Used Merchandise",
            "type":"Retail Goods"
        }
    ],
    "sg:phone":"+1   ",
    "sg:postcode":"61356",
    "sg:province":"IL",
    "wof:name":"Closet",
    "wof:placetype":"venue"
},
  "geometry": {"coordinates":[-89.46744,41.394036],"type":"Point"}
}