{
  "type": "Feature",
  "properties": {
    "addr:full":"733 N 965 East Rd Palmer IL 62556",
    "addr:housenumber":"733",
    "addr:postcode":"62556",
    "addr:street":"N 965 East Rd",
    "iso:country":"US",
    "sg:address":"733 N 965 East Rd",
    "sg:city":"Palmer",
    "sg:classifiers":[
        {
            "category":"Farming",
            "subcategory":"Livestock Farm",
            "type":"Manufacturing & Wholesale Goods"
        },
        {
            "category":"Farming",
            "subcategory":"Farm",
            "type":"Manufacturing & Wholesale Goods"
        }
    ],
    "sg:phone":"+1 217 526 3859",
    "sg:postcode":"62556",
    "sg:province":"IL",
    "wof:name":"Larry Weber",
    "wof:placetype":"venue"
},
  "geometry": {"coordinates":[-89.353493,39.447787],"type":"Point"}
}