{
  "type": "Feature",
  "properties": {
    "iso:country":"US",
    "sg:address":"24606 Sassafras Rd",
    "sg:city":"Centralia",
    "sg:phone":"+1 618 493 7553",
    "sg:postcode":"62801",
    "sg:province":"IL",
    "sg:tags":[
        "farm",
        "grain",
        "cash"
    ],
    "wof:name":"Silger Farms",
    "wof:placetype":"venue"
},
  "geometry": {"coordinates":[-89.244411,38.493228],"type":"Point"}
}