{
  "type": "Feature",
  "properties": {
    "addr:full":"1301 N Alpine Rd Rockford IL 61107",
    "addr:housenumber":"1301",
    "addr:postcode":"61107",
    "addr:street":"N Alpine Rd",
    "iso:country":"US",
    "sg:address":"1301 N Alpine Rd",
    "sg:city":"Rockford",
    "sg:classifiers":[
        {
            "category":"Health Services",
            "subcategory":"Dentist",
            "type":"Services"
        }
    ],
    "sg:phone":"+1 815 397 4280",
    "sg:postcode":"61107",
    "sg:province":"IL",
    "sg:tags":[
        "dentists-oral",
        "surgery",
        "maxillofacial"
    ],
    "sg:website":"http://www.rockforddental.net",
    "wof:name":"Rockford Dental Care, P.C.",
    "wof:placetype":"venue"
},
  "geometry": {"coordinates":[-89.029068,42.280756],"type":"Point"}
}