{
  "type": "Feature",
  "properties": {
    "iso:country":"US",
    "sg:address":"401 N Mulberry St",
    "sg:city":"Effingham",
    "sg:classifiers":[
        {
            "category":"Social Services",
            "type":"Services"
        }
    ],
    "sg:phone":"+1 217 347 7200",
    "sg:postcode":"62401",
    "sg:province":"IL",
    "wof:name":"Red Cross",
    "wof:placetype":"venue"
},
  "geometry": {"coordinates":[-88.55148699999999,39.125811],"type":"Point"}
}