{
  "type": "Feature",
  "properties": {
    "iso:country":"US",
    "sg:address":"3143 W Jefferson St",
    "sg:city":"Joliet",
    "sg:classifiers":[
        {
            "category":"Wholesale",
            "subcategory":"Durable Goods & Equipment",
            "type":"Manufacturing & Wholesale Goods"
        }
    ],
    "sg:phone":"+1 815 744 5142",
    "sg:postcode":"60435",
    "sg:province":"IL",
    "sg:tags":[
        "laboratory",
        "supply"
    ],
    "wof:name":"Quest Diagnostics Inc",
    "wof:placetype":"venue"
},
  "geometry": {"coordinates":[-88.157732,41.521895],"type":"Point"}
}