{
  "type": "Feature",
  "properties": {
    "addr:full":"824 S 3 Willow Ct Palatine IL 60067",
    "addr:housenumber":"824;3",
    "addr:postcode":"60067",
    "addr:street":"S;Willow Ct",
    "iso:country":"US",
    "sg:address":"824 S 3 Willow Ct",
    "sg:city":"Palatine",
    "sg:classifiers":[
        {
            "category":"Professional",
            "subcategory":"Accounting & Tax Preparation",
            "type":"Services"
        }
    ],
    "sg:phone":"+1 847 358 3922",
    "sg:postcode":"60067",
    "sg:province":"IL",
    "wof:name":"Ddk Financial Services Inc",
    "wof:placetype":"venue"
},
  "geometry": {"coordinates":[-88.07579,42.0945],"type":"Point"}
}