{
  "type": "Feature",
  "properties": {
    "iso:country":"US",
    "sg:address":"9325 Starboard Dr",
    "sg:city":"Roscoe",
    "sg:classifiers":[
        {
            "category":"Building & Trades",
            "subcategory":"Plumbing",
            "type":"Services"
        }
    ],
    "sg:phone":"+1 815 654 1456",
    "sg:postcode":"61073",
    "sg:province":"IL",
    "sg:tags":[
        "heating",
        "contractor"
    ],
    "wof:name":"Crain Co",
    "wof:placetype":"venue"
},
  "geometry": {"coordinates":[-89.01061900000001,42.395207],"type":"Point"}
}