{
  "type": "Feature",
  "properties": {
    "iso:country":"US",
    "sg:address":"19900 Governors Dr",
    "sg:city":"Olympia Fields",
    "sg:classifiers":[
        {
            "category":"Health Services",
            "subcategory":"Health Practitioner",
            "type":"Services"
        }
    ],
    "sg:phone":"+1 708 283 8700",
    "sg:postcode":"60461",
    "sg:province":"IL",
    "wof:name":"Vorwerk Susan Mat CCC Clp",
    "wof:placetype":"venue"
},
  "geometry": {"coordinates":[-87.70095,41.527131],"type":"Point"}
}