{
  "type": "Feature",
  "properties": {
    "addr:full":"19900 Governors Dr Olympia Fields IL 60461",
    "addr:housenumber":"19900",
    "addr:postcode":"60461",
    "addr:street":"Governors Dr",
    "iso:country":"US",
    "sg:address":"19900 Governors Dr",
    "sg:city":"Olympia Fields",
    "sg:classifiers":[
        {
            "category":"Health Services",
            "subcategory":"Health Practitioner",
            "type":"Services"
        }
    ],
    "sg:phone":"+1 708 283 8700",
    "sg:postcode":"60461",
    "sg:province":"IL",
    "wof:name":"Vorwerk Susan Mat CCC Clp",
    "wof:placetype":"venue"
},
  "geometry": {"coordinates":[-87.70095000000001,41.527131],"type":"Point"}
}