{
  "type": "Feature",
  "properties": {
    "iso:country":"US",
    "sg:address":"19907 N 400th St",
    "sg:city":"Annapolis",
    "sg:phone":"+1 618 569 5028",
    "sg:postcode":"62413",
    "sg:province":"IL",
    "sg:tags":[
        "farm",
        "corn",
        "rice",
        "wheat",
        "soybean"
    ],
    "wof:name":"Lee Bline",
    "wof:placetype":"venue"
},
  "geometry": {"coordinates":[-87.872805,39.130591],"type":"Point"}
}