{
  "type": "Feature",
  "properties": {
    "iso:country":"US",
    "sg:address":"2100 Huffman Blvd",
    "sg:city":"Rockford",
    "sg:classifiers":[
        {
            "category":"Education",
            "subcategory":"School",
            "type":"Public Place"
        }
    ],
    "sg:phone":"+1 815 966 3260",
    "sg:postcode":"61103",
    "sg:province":"IL",
    "wof:name":"R K Welsh Elementary School",
    "wof:placetype":"venue"
},
  "geometry": {"coordinates":[-89.08688600000001,42.295822],"type":"Point"}
}