{
  "type": "Feature",
  "properties": {
    "iso:country":"US",
    "sg:address":"3735 65th St",
    "sg:city":"Kenosha",
    "sg:classifiers":[
        {
            "category":"Government",
            "subcategory":"Office",
            "type":"Public Place"
        }
    ],
    "sg:phone":"+1 262 653 4290",
    "sg:postcode":"53142",
    "sg:province":"IL",
    "sg:tags":[
        "city"
    ],
    "wof:name":"Transit Department",
    "wof:placetype":"venue"
},
  "geometry": {"coordinates":[-87.853382,42.575635],"type":"Point"}
}