{
  "type": "Feature",
  "properties": {
    "addr:full":"5610 W. 63rd St. Chicago IL 60638",
    "addr:housenumber":"5610",
    "addr:postcode":"60638",
    "addr:street":"W. 63Rd St.",
    "iso:country":"US",
    "sg:address":"5610 W. 63rd St.",
    "sg:city":"Chicago",
    "sg:classifiers":[
        {
            "category":"Bakery",
            "type":"Food & Drink"
        }
    ],
    "sg:phone":"+1 773 735 1732",
    "sg:postcode":"60638",
    "sg:province":"IL",
    "sg:website":"www.lapetitepastry.com/",
    "wof:name":"La Petite Pastry",
    "wof:placetype":"venue"
},
  "geometry": {"coordinates":[-87.762186,41.778243],"type":"Point"}
}