{
  "type": "Feature",
  "properties": {
    "iso:country":"US",
    "sg:address":"82 N Main St",
    "sg:city":"Lenzburg",
    "sg:classifiers":[
        {
            "category":"Bars & Pubs",
            "type":"Food & Drink"
        }
    ],
    "sg:phone":"+1 618 475 9670",
    "sg:postcode":"62255",
    "sg:province":"IL",
    "sg:tags":[
        "drinking"
    ],
    "wof:name":"Babe's Tavern",
    "wof:placetype":"venue"
},
  "geometry": {"coordinates":[-89.817227,38.287452],"type":"Point"}
}