{
  "type": "Feature",
  "properties": {
    "iso:country":"US",
    "sg:address":"7247 Kingery Hwy",
    "sg:city":"Willowbrook",
    "sg:classifiers":[
        {
            "category":"Bakery",
            "type":"Food & Drink"
        },
        {
            "category":"Coffee & Tea",
            "type":"Food & Drink"
        },
        {
            "category":"Bagels",
            "type":"Food & Drink"
        },
        {
            "category":"Donuts",
            "type":"Food & Drink"
        }
    ],
    "sg:menulink":"http://www.allmenus.com/il/downers-grove/135322-dunkin-donuts/menu/",
    "sg:phone":"+1 630 323 5205",
    "sg:postcode":"60527",
    "sg:province":"IL",
    "sg:tags":[
        "american",
        "pastry"
    ],
    "wof:name":"Dunkin' Donuts",
    "wof:placetype":"venue"
},
  "geometry": {"coordinates":[-87.94449,41.756292],"type":"Point"}
}