{
  "type": "Feature",
  "properties": {
    "addr:full":"7500 S Pulaski Road Chicago IL 60652",
    "addr:housenumber":"7500",
    "addr:postcode":"60652",
    "addr:street":"S Pulaski Road",
    "iso:country":"US",
    "sg:address":"7500 S Pulaski Road",
    "sg:city":"Chicago",
    "sg:classifiers":[
        {
            "category":"Education",
            "subcategory":"University",
            "type":"Public Place"
        }
    ],
    "sg:phone":"+1 773 838 7500",
    "sg:postcode":"60652",
    "sg:province":"IL",
    "sg:tags":[
        "college"
    ],
    "wof:name":"City Colleges of Chicago",
    "wof:placetype":"venue"
},
  "geometry": {"coordinates":[-87.729178,41.753196],"type":"Point"}
}