{
  "type": "Feature",
  "properties": {
    "addr:full":"810 Morse Ave Schaumburg IL 60193",
    "addr:housenumber":"810",
    "addr:postcode":"60193",
    "addr:street":"Morse Ave",
    "iso:country":"US",
    "sg:address":"810 Morse Ave",
    "sg:city":"Schaumburg",
    "sg:classifiers":[
        {
            "category":"Local Transit",
            "type":"Transportation"
        }
    ],
    "sg:phone":"+1 630 894 8731",
    "sg:postcode":"60193",
    "sg:province":"IL",
    "sg:tags":[
        "ambulance"
    ],
    "wof:name":"Advantage Ambulance Inc",
    "wof:placetype":"venue"
},
  "geometry": {"coordinates":[-88.093523,42.0005],"type":"Point"}
}