{
  "type": "Feature",
  "properties": {
    "addr:full":"511 Rita Ct Prophetstown IL 61277",
    "addr:housenumber":"511",
    "addr:postcode":"61277",
    "addr:street":"Rita Ct",
    "iso:country":"US",
    "sg:address":"511 Rita Ct",
    "sg:city":"Prophetstown",
    "sg:classifiers":[
        {
            "category":"Shopping",
            "subcategory":"Gifts & Souvenirs",
            "type":"Retail Goods"
        }
    ],
    "sg:phone":"+1   ",
    "sg:postcode":"61277",
    "sg:province":"IL",
    "wof:name":"Generations Antiques & Gifts",
    "wof:placetype":"venue"
},
  "geometry": {"coordinates":[-89.929214,41.667733],"type":"Point"}
}