{
  "type": "Feature",
  "properties": {
    "addr:full":"76 S Grove Ave Elgin IL 60120",
    "addr:housenumber":"76",
    "addr:postcode":"60120",
    "addr:street":"S Grove Ave",
    "iso:country":"US",
    "sg:address":"76 S Grove Ave",
    "sg:city":"Elgin",
    "sg:classifiers":[
        {
            "category":"Professional",
            "subcategory":"Lawyer & Legal Services",
            "type":"Services"
        }
    ],
    "sg:phone":"+1 847 717 0906",
    "sg:postcode":"60120",
    "sg:province":"IL",
    "sg:tags":[
        "attorney"
    ],
    "wof:name":"Emilio Moretti Law Offices",
    "wof:placetype":"venue"
},
  "geometry": {"coordinates":[-88.28342000000001,42.03621],"type":"Point"}
}