{
  "type": "Feature",
  "properties": {
    "addr:full":"4128 Hale Ln Island Lake IL 60042",
    "addr:housenumber":"4128",
    "addr:postcode":"60042",
    "addr:street":"Hale Ln",
    "iso:country":"US",
    "sg:address":"4128 Hale Ln",
    "sg:city":"Island Lake",
    "sg:classifiers":[
        {
            "category":"Building & Trades",
            "subcategory":"Construction",
            "type":"Services"
        }
    ],
    "sg:phone":"+1 847 526 2304",
    "sg:postcode":"60042",
    "sg:province":"IL",
    "sg:tags":[
        "contractor"
    ],
    "wof:name":"Svaras Installation",
    "wof:placetype":"venue"
},
  "geometry": {"coordinates":[-88.21621,42.267986],"type":"Point"}
}