{
  "type": "Feature",
  "properties": {
    "iso:country":"US",
    "sg:address":"218 E Main St",
    "sg:city":"West Frankfort",
    "sg:classifiers":[
        {
            "category":"Real Estate",
            "subcategory":"Real Estate Agent",
            "type":"Services"
        }
    ],
    "sg:phone":"+1 618 932 3888",
    "sg:postcode":"62896",
    "sg:province":"IL",
    "wof:name":"Starr Realty",
    "wof:placetype":"venue"
},
  "geometry": {"coordinates":[-88.926514,37.897891],"type":"Point"}
}