{
  "type": "Feature",
  "properties": {
    "iso:country":"US",
    "sg:address":"619 S Wabash Ave",
    "sg:city":"Chicago",
    "sg:classifiers":[
        {
            "category":"Education",
            "subcategory":"School",
            "type":"Public Place"
        }
    ],
    "sg:phone":"+1 312 369 6400",
    "sg:postcode":"60605",
    "sg:province":"IL",
    "sg:website":"www.newstips.org",
    "wof:name":"Community Media Workshop",
    "wof:placetype":"venue"
},
  "geometry": {"coordinates":[-87.625984,41.873925],"type":"Point"}
}