{
  "type": "Feature",
  "properties": {
    "iso:country":"US",
    "sg:address":"102 Easthaven Dr",
    "sg:city":"Carbondale",
    "sg:classifiers":[
        {
            "category":"Building & Trades",
            "subcategory":"Landscaping Services",
            "type":"Services"
        }
    ],
    "sg:phone":"+1 618 549 8233",
    "sg:postcode":"62901",
    "sg:province":"IL",
    "sg:tags":[
        "landscape",
        "contractor"
    ],
    "wof:name":"Clean Cut Lawn Care",
    "wof:placetype":"venue"
},
  "geometry": {"coordinates":[-89.152482,37.768675],"type":"Point"}
}