{
  "type": "Feature",
  "properties": {
    "addr:full":"298 High Line St Belvidere IL 61008",
    "addr:housenumber":"298",
    "addr:postcode":"61008",
    "addr:street":"High Line St",
    "iso:country":"US",
    "sg:address":"298 High Line St",
    "sg:city":"Belvidere",
    "sg:classifiers":[
        {
            "category":"Real Estate",
            "subcategory":"Real Estate Operator",
            "type":"Services"
        }
    ],
    "sg:phone":"+1 815 547 5535",
    "sg:postcode":"61008",
    "sg:province":"IL",
    "sg:tags":[
        "apartment"
    ],
    "wof:name":"Coachlite Apartments",
    "wof:placetype":"venue"
},
  "geometry": {"coordinates":[-88.866514,42.270848],"type":"Point"}
}