{
  "type": "Feature",
  "properties": {
    "iso:country":"US",
    "sg:address":"9905 S Sangamon St",
    "sg:city":"Chicago",
    "sg:classifiers":[
        {
            "category":"Professional",
            "subcategory":"Management & Consulting",
            "type":"Services"
        },
        {
            "category":"Professional",
            "subcategory":"Advertising",
            "type":"Services"
        }
    ],
    "sg:phone":"+1 312 307 4840",
    "sg:postcode":"60643",
    "sg:province":"IL",
    "sg:tags":[
        "agency",
        "specialty",
        "relation",
        "counselor",
        "public"
    ],
    "wof:name":"Favor Consulting Group",
    "wof:placetype":"venue"
},
  "geometry": {"coordinates":[-87.64664999999999,41.714087],"type":"Point"}
}