{
  "type": "Feature",
  "properties": {
    "iso:country":"US",
    "sg:address":"6666 N Western Ave",
    "sg:city":"Chicago",
    "sg:classifiers":[
        {
            "category":"Real Estate",
            "subcategory":"Real Estate Agent",
            "type":"Services"
        }
    ],
    "sg:phone":"+1 773 381 9690",
    "sg:postcode":"60645",
    "sg:province":"IL",
    "wof:name":"Feiner Investment",
    "wof:placetype":"venue"
},
  "geometry": {"coordinates":[-87.690072,42.001961],"type":"Point"}
}