{
  "type": "Feature",
  "properties": {
    "addr:full":"524 W Mondamin St Minooka IL 60447",
    "addr:housenumber":"524",
    "addr:postcode":"60447",
    "addr:street":"W Mondamin St",
    "iso:country":"US",
    "sg:address":"524 W Mondamin St",
    "sg:city":"Minooka",
    "sg:classifiers":[
        {
            "category":"Restaurant",
            "type":"Food & Drink"
        }
    ],
    "sg:phone":"+1 815 467 7373",
    "sg:postcode":"60447",
    "sg:province":"IL",
    "wof:name":"Jrajas Inc",
    "wof:placetype":"venue"
},
  "geometry": {"coordinates":[-88.272797,41.454899],"type":"Point"}
}