{
  "type": "Feature",
  "properties": {
    "iso:country":"US",
    "sg:address":"281 N Seymour Ave",
    "sg:city":"Mundelein",
    "sg:classifiers":[
        {
            "category":"Insurance",
            "subcategory":"Hazard Insurance",
            "type":"Services"
        },
        {
            "category":"Insurance",
            "subcategory":"Insurance Agent",
            "type":"Services"
        },
        {
            "category":"Insurance",
            "subcategory":"Life Insurance",
            "type":"Services"
        },
        {
            "category":"Insurance",
            "subcategory":"Title Insurance",
            "type":"Services"
        }
    ],
    "sg:phone":"+1 847 837 0555",
    "sg:postcode":"60060",
    "sg:province":"IL",
    "sg:tags":[
        "auto",
        "commercial",
        "business",
        "homeowner"
    ],
    "sg:website":"http://www.farmersagent.com/drasmussen3/",
    "wof:name":"Diana Rasmussen - Farmers Insurance",
    "wof:placetype":"venue"
},
  "geometry": {"coordinates":[-88.002521,42.267879],"type":"Point"}
}