{
  "type": "Feature",
  "properties": {
    "addr:full":"838 W Lincoln Hwy Dekalb IL 60115",
    "addr:housenumber":"838",
    "addr:postcode":"60115",
    "addr:street":"W Lincoln Hwy",
    "iso:country":"US",
    "sg:address":"838 W Lincoln Hwy",
    "sg:city":"Dekalb",
    "sg:classifiers":[
        {
            "category":"Personal",
            "type":"Services"
        },
        {
            "category":"Sports & Exercise",
            "subcategory":"Gym",
            "type":"Entertainment"
        },
        {
            "category":"Health Services",
            "subcategory":"Health Practitioner",
            "type":"Services"
        },
        {
            "category":"Arena",
            "subcategory":"Sports Club",
            "type":"Entertainment"
        }
    ],
    "sg:phone":"+1 815 758 2244",
    "sg:postcode":"60115",
    "sg:province":"IL",
    "sg:tags":[
        "control",
        "weight",
        "consultant",
        "program",
        "fitness",
        "physical"
    ],
    "sg:website":"http://www.curves.com",
    "wof:name":"Curves",
    "wof:placetype":"venue"
},
  "geometry": {"coordinates":[-88.769869,41.93111],"type":"Point"}
}