{
  "type": "Feature",
  "properties": {
    "iso:country":"US",
    "sg:address":"256 W Roosevelt Rd",
    "sg:city":"Lombard",
    "sg:classifiers":[
        {
            "category":"Restaurant",
            "type":"Food & Drink"
        }
    ],
    "sg:phone":"+1 630 889 0889",
    "sg:postcode":"60148",
    "sg:province":"IL",
    "sg:tags":[
        "mexican"
    ],
    "sg:website":"http://www.elfamousburritolombard.com",
    "wof:name":"El Famous Burrito",
    "wof:placetype":"venue"
},
  "geometry": {"coordinates":[-88.021665,41.859969],"type":"Point"}
}