{
  "type": "Feature",
  "properties": {
    "addr:full":"1547 W Belmont Ave Chicago IL 60657",
    "addr:housenumber":"1547",
    "addr:postcode":"60657",
    "addr:street":"W Belmont Ave",
    "iso:country":"US",
    "sg:address":"1547 W Belmont Ave",
    "sg:city":"Chicago",
    "sg:classifiers":[
        {
            "category":"Government",
            "subcategory":"Court House",
            "type":"Public Place"
        }
    ],
    "sg:phone":"+1 312 201 2923",
    "sg:postcode":"60657",
    "sg:province":"IL",
    "sg:tags":[
        "legislator"
    ],
    "wof:name":"House Of Representatives, Illinois",
    "wof:placetype":"venue"
},
  "geometry": {"coordinates":[-87.66819,41.939709],"type":"Point"}
}