{
  "type": "Feature",
  "properties": {
    "addr:full":"1756 N Clybourn Ave Chicago IL 60614",
    "addr:housenumber":"1756",
    "addr:postcode":"60614",
    "addr:street":"N Clybourn Ave",
    "iso:country":"US",
    "sg:address":"1756 N Clybourn Ave",
    "sg:city":"Chicago",
    "sg:classifiers":[
        {
            "category":"Professional",
            "subcategory":"Lawyer & Legal Services",
            "type":"Services"
        }
    ],
    "sg:phone":"+1 312 642 0559",
    "sg:postcode":"60614",
    "sg:province":"IL",
    "wof:name":"Gigi Gilbert Attorney At Law",
    "wof:placetype":"venue"
},
  "geometry": {"coordinates":[-87.652603,41.9133],"type":"Point"}
}