{
  "type": "Feature",
  "properties": {
    "iso:country":"US",
    "sg:address":"719 Jenkisson Ave",
    "sg:city":"Lake Bluff",
    "sg:classifiers":[
        {
            "category":"Government",
            "subcategory":"Office",
            "type":"Public Place"
        }
    ],
    "sg:phone":"+1 847 234 0888",
    "sg:postcode":"60044",
    "sg:province":"IL",
    "sg:tags":[
        "village"
    ],
    "wof:name":"Shields Twp Road Commissioner",
    "wof:placetype":"venue"
},
  "geometry": {"coordinates":[-87.878128,42.285509],"type":"Point"}
}