{
  "type": "Feature",
  "properties": {
    "iso:country":"US",
    "sg:address":"82 N Main St",
    "sg:city":"Canton",
    "sg:classifiers":[
        {
            "category":"Social Services",
            "type":"Services"
        }
    ],
    "sg:phone":"+1   ",
    "sg:postcode":"61520",
    "sg:province":"IL",
    "sg:tags":[
        "clothing"
    ],
    "wof:name":"Mens Scial Svc Rhblitation Ctr",
    "wof:placetype":"venue"
},
  "geometry": {"coordinates":[-90.035205,40.55658],"type":"Point"}
}