{
  "type": "Feature",
  "properties": {
    "iso:country":"US",
    "sg:address":"1201 Arthur Ave",
    "sg:city":"Elk Grove Village",
    "sg:classifiers":[
        {
            "category":"Freight",
            "type":"Transportation"
        }
    ],
    "sg:phone":"+1 847 437 7050",
    "sg:postcode":"60007",
    "sg:province":"IL",
    "sg:tags":[
        "operator",
        "local",
        "storage",
        "trucking"
    ],
    "wof:name":"Atlas Van Lines Agent",
    "wof:placetype":"venue"
},
  "geometry": {"coordinates":[-87.960817,41.995548],"type":"Point"}
}