{
  "type": "Feature",
  "properties": {
    "addr:full":"1910 Saint Clair Ave Granite City IL 62040",
    "addr:housenumber":"1910",
    "addr:postcode":"62040",
    "addr:street":"Saint Clair Ave",
    "iso:country":"US",
    "sg:address":"1910 Saint Clair Ave",
    "sg:city":"Granite City",
    "sg:classifiers":[
        {
            "category":"Education",
            "subcategory":"School",
            "type":"Public Place"
        }
    ],
    "sg:phone":"+1 618 877 0001",
    "sg:postcode":"62040",
    "sg:province":"IL",
    "sg:tags":[
        "high",
        "middle",
        "elementary"
    ],
    "wof:name":"Holy Family Learning Center For Pre-Scho",
    "wof:placetype":"venue"
},
  "geometry": {"coordinates":[-90.116501,38.716801],"type":"Point"}
}