{
  "type": "Feature",
  "properties": {
    "iso:country":"US",
    "sg:address":"1140 E 103rd St Ste D",
    "sg:city":"Chicago",
    "sg:classifiers":[
        {
            "category":"Manufacturing",
            "subcategory":"Chemicals & Compounds",
            "type":"Manufacturing & Wholesale Goods"
        }
    ],
    "sg:phone":"+1 773 785 2300",
    "sg:postcode":"60628",
    "sg:province":"IL",
    "sg:tags":[
        "chemicals-wholesale",
        "manufacturer"
    ],
    "wof:name":"Nuance Solutions",
    "wof:placetype":"venue"
},
  "geometry": {"coordinates":[-87.595428,41.707618],"type":"Point"}
}