{
  "type": "Feature",
  "properties": {
    "addr:full":"1310 N Cicero Ave Chicago IL 60651",
    "addr:housenumber":"1310",
    "addr:postcode":"60651",
    "addr:street":"N Cicero Ave",
    "iso:country":"US",
    "sg:address":"1310 N Cicero Ave",
    "sg:city":"Chicago",
    "sg:classifiers":[
        {
            "category":"Building & Trades",
            "subcategory":"Plumbing",
            "type":"Services"
        }
    ],
    "sg:phone":"+1 773 626 5144",
    "sg:postcode":"60651",
    "sg:province":"IL",
    "wof:name":"Member Mechanical Inc",
    "wof:placetype":"venue"
},
  "geometry": {"coordinates":[-87.745796,41.904301],"type":"Point"}
}