{
  "type": "Feature",
  "properties": {
    "addr:full":"411 Illinois Ave Glenwood IL 60425",
    "addr:housenumber":"411",
    "addr:postcode":"60425",
    "addr:street":"Illinois Ave",
    "iso:country":"US",
    "sg:address":"411 Illinois Ave",
    "sg:city":"Glenwood",
    "sg:classifiers":[
        {
            "category":"Wholesale",
            "subcategory":"Electrical",
            "type":"Manufacturing & Wholesale Goods"
        }
    ],
    "sg:phone":"+1 773 776 5400",
    "sg:postcode":"60425",
    "sg:province":"IL",
    "sg:tags":[
        "equipment"
    ],
    "wof:name":"CSC Alarm Syst",
    "wof:placetype":"venue"
},
  "geometry": {"coordinates":[-87.640415,41.553422],"type":"Point"}
}