{
  "type": "Feature",
  "properties": {
    "iso:country":"US",
    "sg:address":"1234 15th Ave",
    "sg:city":"East Moline",
    "sg:classifiers":[
        {
            "category":"Building & Trades",
            "subcategory":"Plumbing",
            "type":"Services"
        }
    ],
    "sg:phone":"+1 309 755 9412",
    "sg:postcode":"61244",
    "sg:province":"IL",
    "sg:tags":[
        "septic"
    ],
    "wof:name":"Otis Surratt & Sons",
    "wof:placetype":"venue"
},
  "geometry": {"coordinates":[-90.433897,41.516825],"type":"Point"}
}