{
  "type": "Feature",
  "properties": {
    "addr:full":"300 E Plymouth St Villa Park IL 60181",
    "addr:housenumber":"300",
    "addr:postcode":"60181",
    "addr:street":"E Plymouth St",
    "iso:country":"US",
    "sg:address":"300 E Plymouth St",
    "sg:city":"Villa Park",
    "sg:classifiers":[
        {
            "category":"Building & Trades",
            "subcategory":"Construction",
            "type":"Services"
        }
    ],
    "sg:phone":"+1 630 964 8708",
    "sg:postcode":"60181",
    "sg:province":"IL",
    "sg:tags":[
        "heavy"
    ],
    "wof:name":"Adept Construction",
    "wof:placetype":"venue"
},
  "geometry": {"coordinates":[-87.97009799999999,41.899395],"type":"Point"}
}