{
  "type": "Feature",
  "properties": {
    "iso:country":"US",
    "sg:address":"400 Duane St",
    "sg:city":"Glen Ellyn",
    "sg:classifiers":[
        {
            "category":"Education",
            "subcategory":"Library",
            "type":"Public Place"
        }
    ],
    "sg:phone":"+1 630 469 0879",
    "sg:postcode":"60137",
    "sg:province":"IL",
    "sg:website":"www.gepl.org",
    "wof:name":"Glen Ellyn Public Library",
    "wof:placetype":"venue"
},
  "geometry": {"coordinates":[-88.070999,41.875401],"type":"Point"}
}