{
  "type": "Feature",
  "properties": {
    "addr:full":"119 E 23rd Ave Coal Valley IL 61240",
    "addr:housenumber":"119",
    "addr:postcode":"61240",
    "addr:street":"E 23Rd Ave",
    "iso:country":"US",
    "sg:address":"119 E 23rd Ave",
    "sg:city":"Coal Valley",
    "sg:classifiers":[
        {
            "category":"Autos & Motor Vehicles",
            "subcategory":"Fuel & Gas Station",
            "type":"Retail Goods"
        },
        {
            "category":"Personal",
            "type":"Services"
        },
        {
            "category":"Retail",
            "subcategory":"Auto Repair",
            "type":"Services"
        }
    ],
    "sg:phone":"+1 309 799 5362",
    "sg:postcode":"61240",
    "sg:province":"IL",
    "sg:tags":[
        "towing"
    ],
    "wof:name":"G & L Auto Care Cntr",
    "wof:placetype":"venue"
},
  "geometry": {"coordinates":[-90.460999,41.4286],"type":"Point"}
}