{
  "type": "Feature",
  "properties": {
    "iso:country":"US",
    "sg:address":"2129 E Waverly Ln",
    "sg:city":"Arlington Heights",
    "sg:classifiers":[
        {
            "category":"Building & Trades",
            "subcategory":"Construction",
            "type":"Services"
        }
    ],
    "sg:phone":"+1 847 398 7546",
    "sg:postcode":"60004",
    "sg:province":"IL",
    "sg:tags":[
        "carpet",
        "installation",
        "contractor"
    ],
    "wof:name":"Kovanda Carpets",
    "wof:placetype":"venue"
},
  "geometry": {"coordinates":[-87.958458,42.120286],"type":"Point"}
}