{
  "type": "Feature",
  "properties": {
    "addr:full":"3429 Freedom Dr Springfield IL 62704",
    "addr:housenumber":"3429",
    "addr:postcode":"62704",
    "addr:street":"Freedom Dr",
    "iso:country":"US",
    "sg:address":"3429 Freedom Dr",
    "sg:city":"Springfield",
    "sg:classifiers":[
        {
            "category":"Bakery",
            "type":"Food & Drink"
        }
    ],
    "sg:menulink":"http://www.allmenus.com/il/capital/102042-perkins-restaurant--bakery/menu/",
    "sg:phone":"+1 217 787 3535",
    "sg:postcode":"62704",
    "sg:province":"IL",
    "sg:tags":[
        "sandwich",
        "salad",
        "soup",
        "american",
        "pastry",
        "wrap"
    ],
    "wof:name":"Perkins Restaurant & Bakery",
    "wof:placetype":"venue"
},
  "geometry": {"coordinates":[-89.707885,39.75189],"type":"Point"}
}