{
  "type": "Feature",
  "properties": {
    "addr:full":"1422 W Main St Belleville IL 62220",
    "addr:housenumber":"1422",
    "addr:postcode":"62220",
    "addr:street":"W Main St",
    "iso:country":"US",
    "sg:address":"1422 W Main St",
    "sg:city":"Belleville",
    "sg:classifiers":[
        {
            "category":"Home & Garden",
            "subcategory":"Household Appliances",
            "type":"Retail Goods"
        }
    ],
    "sg:phone":"+1   ",
    "sg:postcode":"62220",
    "sg:province":"IL",
    "wof:name":"West Main Bargain Store",
    "wof:placetype":"venue"
},
  "geometry": {"coordinates":[-90.001406,38.517186],"type":"Point"}
}