{
  "type": "Feature",
  "properties": {
    "iso:country":"US",
    "sg:address":"563 N Williams St",
    "sg:city":"Thornton",
    "sg:classifiers":[
        {
            "category":"Wholesale",
            "subcategory":"Machinery & Supplies",
            "type":"Manufacturing & Wholesale Goods"
        }
    ],
    "sg:phone":"+1 708 877 6550",
    "sg:postcode":"60476",
    "sg:province":"IL",
    "sg:tags":[
        "fire",
        "department",
        "equipment"
    ],
    "wof:name":"Dolton Fire Equipment Sales",
    "wof:placetype":"venue"
},
  "geometry": {"coordinates":[-87.613445,41.57736],"type":"Point"}
}