{
  "type": "Feature",
  "properties": {
    "iso:country":"US",
    "sg:address":"17033 Torrence Ave",
    "sg:city":"Lansing",
    "sg:classifiers":[
        {
            "category":"Restaurant",
            "type":"Food & Drink"
        }
    ],
    "sg:phone":"+1 708 474 5015",
    "sg:postcode":"60438",
    "sg:province":"IL",
    "sg:tags":[
        "seafood"
    ],
    "sg:website":"www.nawlinscrabhouse.com",
    "wof:name":"N'awlins Crab House",
    "wof:placetype":"venue"
},
  "geometry": {"coordinates":[-87.558849,41.585754],"type":"Point"}
}