{
  "type": "Feature",
  "properties": {
    "addr:full":"1201 Pine St Eldorado IL 62930",
    "addr:housenumber":"1201",
    "addr:postcode":"62930",
    "addr:street":"Pine St",
    "iso:country":"US",
    "sg:address":"1201 Pine St",
    "sg:city":"Eldorado",
    "sg:classifiers":[
        {
            "category":"Health Services",
            "subcategory":"Clinic",
            "type":"Services"
        }
    ],
    "sg:phone":"+1 618 273 3361",
    "sg:postcode":"62930",
    "sg:province":"IL",
    "sg:tags":[
        "medical"
    ],
    "wof:name":"4th St Clinic",
    "wof:placetype":"venue"
},
  "geometry": {"coordinates":[-88.44148300000001,37.815189],"type":"Point"}
}