{
  "type": "Feature",
  "properties": {
    "iso:country":"US",
    "sg:address":"280 Old Gary Ave",
    "sg:city":"Bloomingdale",
    "sg:classifiers":[
        {
            "category":"Education",
            "subcategory":"School",
            "type":"Public Place"
        }
    ],
    "sg:phone":"+1 630 539 4653",
    "sg:postcode":"60108",
    "sg:province":"IL",
    "wof:name":"Bloomingdale School District 93",
    "wof:placetype":"venue"
},
  "geometry": {"coordinates":[-88.12071400000001,41.94147],"type":"Point"}
}