{
  "type": "Feature",
  "properties": {
    "iso:country":"US",
    "sg:address":"13952 W 7000S Rd",
    "sg:city":"Herscher",
    "sg:phone":"+1 815 426 2633",
    "sg:postcode":"60922",
    "sg:province":"IL",
    "sg:tags":[
        "farm",
        "corn",
        "soybean"
    ],
    "wof:name":"David Winterroth",
    "wof:placetype":"venue"
},
  "geometry": {"coordinates":[-88.13137999999999,41.012414],"type":"Point"}
}