{
  "type": "Feature",
  "properties": {
    "addr:full":"162 US Hwy 36 Lovington IL 61937",
    "addr:housenumber":"162",
    "addr:postcode":"61937",
    "addr:street":"Us Hwy 36",
    "iso:country":"US",
    "sg:address":"162 US Hwy 36",
    "sg:city":"Lovington",
    "sg:classifiers":[
        {
            "category":"Farming",
            "subcategory":"Farm",
            "type":"Manufacturing & Wholesale Goods"
        }
    ],
    "sg:phone":"+1 217 677 2354",
    "sg:postcode":"61937",
    "sg:province":"IL",
    "sg:tags":[
        "crop",
        "general"
    ],
    "wof:name":"E & T Hoffman Farms",
    "wof:placetype":"venue"
},
  "geometry": {"coordinates":[-88.482377,39.79179],"type":"Point"}
}