{
  "type": "Feature",
  "properties": {
    "iso:country":"US",
    "sg:address":"2361 N Clark St",
    "sg:city":"Chicago",
    "sg:classifiers":[
        {
            "category":"Personal",
            "subcategory":"Shoe Repair & Shine",
            "type":"Services"
        }
    ],
    "sg:phone":"+1 773 525 0133",
    "sg:postcode":"60614",
    "sg:province":"IL",
    "wof:name":"Gus's Shoe Repair",
    "wof:placetype":"venue"
},
  "geometry": {"coordinates":[-87.640503,41.925301],"type":"Point"}
}