{
  "type": "Feature",
  "properties": {
    "addr:full":"8380 W Dublin Rd Pearl City IL 61062",
    "addr:housenumber":"8380",
    "addr:postcode":"61062",
    "addr:street":"W Dublin Rd",
    "iso:country":"US",
    "sg:address":"8380 W Dublin Rd",
    "sg:city":"Pearl City",
    "sg:classifiers":[
        {
            "category":"Farming",
            "subcategory":"Farm",
            "type":"Manufacturing & Wholesale Goods"
        }
    ],
    "sg:phone":"+1 815 235 3715",
    "sg:postcode":"61062",
    "sg:province":"IL",
    "wof:name":"Dar She Farms Inc",
    "wof:placetype":"venue"
},
  "geometry": {"coordinates":[-89.768823,42.294733],"type":"Point"}
}