{
  "type": "Feature",
  "properties": {
    "iso:country":"US",
    "sg:address":"3637 W Division St",
    "sg:city":"Chicago",
    "sg:classifiers":[
        {
            "category":"Food & Beverages",
            "subcategory":"Liquor & Beverages",
            "type":"Retail Goods"
        }
    ],
    "sg:phone":"+1   ",
    "sg:postcode":"60651",
    "sg:province":"IL",
    "sg:tags":[
        "alcoholic"
    ],
    "wof:name":"Nickel Liquors Inc",
    "wof:placetype":"venue"
},
  "geometry": {"coordinates":[-87.718827,41.902661],"type":"Point"}
}