{
  "type": "Feature",
  "properties": {
    "iso:country":"US",
    "sg:address":"309 Nicholson St",
    "sg:city":"Joliet",
    "sg:classifiers":[
        {
            "category":"Home & Garden",
            "subcategory":"Home Furnishings",
            "type":"Retail Goods"
        }
    ],
    "sg:phone":"+1 630 399 2414",
    "sg:postcode":"60435",
    "sg:province":"IL",
    "sg:tags":[
        "managing"
    ],
    "wof:name":"Homes For Humanity",
    "wof:placetype":"venue"
},
  "geometry": {"coordinates":[-88.09377000000001,41.528791],"type":"Point"}
}