{
  "type": "Feature",
  "properties": {
    "addr:full":"1009 N 500 East Rd Buckley IL 60918",
    "addr:housenumber":"1009",
    "addr:postcode":"60918",
    "addr:street":"N 500 East Rd",
    "iso:country":"US",
    "sg:address":"1009 N 500 East Rd",
    "sg:city":"Buckley",
    "sg:phone":"+1 217 394 2409",
    "sg:postcode":"60918",
    "sg:province":"IL",
    "sg:tags":[
        "farm",
        "corn",
        "soybean"
    ],
    "wof:name":"Myron Rust",
    "wof:placetype":"venue"
},
  "geometry": {"coordinates":[-88.02567999999999,40.644206],"type":"Point"}
}