{
  "type": "Feature",
  "properties": {
    "addr:full":"241 3rd St Crystal Lake IL 60014",
    "addr:housenumber":"241",
    "addr:postcode":"60014",
    "addr:street":"3Rd St",
    "iso:country":"US",
    "sg:address":"241 3rd St",
    "sg:city":"Crystal Lake",
    "sg:classifiers":[
        {
            "category":"Professional",
            "subcategory":"Management & Consulting",
            "type":"Services"
        }
    ],
    "sg:phone":"+1 815 477 1392",
    "sg:postcode":"60014",
    "sg:province":"IL",
    "sg:tags":[
        "construction"
    ],
    "wof:name":"Babineau Construction",
    "wof:placetype":"venue"
},
  "geometry": {"coordinates":[-88.319897,42.248034],"type":"Point"}
}