{
  "type": "Feature",
  "properties": {
    "addr:full":"1810 W Irving Park Rd Chicago IL 60613",
    "addr:housenumber":"1810",
    "addr:postcode":"60613",
    "addr:street":"W Irving Park Rd",
    "iso:country":"US",
    "sg:address":"1810 W Irving Park Rd",
    "sg:city":"Chicago",
    "sg:classifiers":[
        {
            "category":"Professional",
            "subcategory":"Employment Agencies",
            "type":"Services"
        }
    ],
    "sg:phone":"+1 773 472 1919",
    "sg:postcode":"60613",
    "sg:province":"IL",
    "wof:name":"Adecco Employment Services",
    "wof:placetype":"venue"
},
  "geometry": {"coordinates":[-87.67449999999999,41.954399],"type":"Point"}
}