{
  "type": "Feature",
  "properties": {
    "iso:country":"US",
    "sg:address":"255 W 111th St",
    "sg:city":"Chicago",
    "sg:classifiers":[
        {
            "category":"Social Services",
            "subcategory":"Child Care",
            "type":"Services"
        }
    ],
    "sg:phone":"+1 773 928 5612",
    "sg:postcode":"60628",
    "sg:province":"IL",
    "sg:tags":[
        "day"
    ],
    "wof:name":"Linda's Daycare",
    "wof:placetype":"venue"
},
  "geometry": {"coordinates":[-87.629226,41.692372],"type":"Point"}
}