{
  "type": "Feature",
  "properties": {
    "iso:country":"US",
    "sg:address":"106 N Main St",
    "sg:city":"Albany",
    "sg:classifiers":[
        {
            "category":"Autos & Motor Vehicles",
            "subcategory":"Boat Sales",
            "type":"Retail Goods"
        }
    ],
    "sg:phone":"+1 309 887 4804",
    "sg:postcode":"61270",
    "sg:province":"IL",
    "sg:tags":[
        "outboard"
    ],
    "wof:name":"Bitler Marine",
    "wof:placetype":"venue"
},
  "geometry": {"coordinates":[-90.22074499999999,41.78958],"type":"Point"}
}