{
  "type": "Feature",
  "properties": {
    "iso:country":"US",
    "sg:address":"542 S Rosewood Ave",
    "sg:city":"Kankakee",
    "sg:classifiers":[
        {
            "category":"Shopping",
            "subcategory":"Computers & Home Electronics",
            "type":"Retail Goods"
        }
    ],
    "sg:phone":"+1   ",
    "sg:postcode":"60901",
    "sg:province":"IL",
    "wof:name":"Nelson Car Stereo",
    "wof:placetype":"venue"
},
  "geometry": {"coordinates":[-87.856562,41.113539],"type":"Point"}
}