{
  "type": "Feature",
  "properties": {
    "iso:country":"US",
    "sg:address":"440 S la Salle St Ste 960",
    "sg:city":"Chicago",
    "sg:classifiers":[
        {
            "category":"Professional",
            "subcategory":"Engineering",
            "type":"Services"
        }
    ],
    "sg:phone":"+1 312 260 5188",
    "sg:postcode":"60605",
    "sg:province":"IL",
    "sg:tags":[
        "consulting",
        "engineer"
    ],
    "wof:name":"Zydeco Asset Partners",
    "wof:placetype":"venue"
},
  "geometry": {"coordinates":[-87.63175200000001,41.876371],"type":"Point"}
}