{
  "type": "Feature",
  "properties": {
    "iso:country":"US",
    "sg:address":"37 S Main St",
    "sg:city":"Harrisburg",
    "sg:classifiers":[
        {
            "category":"Banks & Credit Unions",
            "subcategory":"Investment Brokerage",
            "type":"Services"
        },
        {
            "category":"Banks & Credit Unions",
            "subcategory":"Bank",
            "type":"Services"
        },
        {
            "category":"Banks & Credit Unions",
            "subcategory":"Financial Services",
            "type":"Services"
        }
    ],
    "sg:phone":"+1 618 253 4444",
    "sg:postcode":"62946",
    "sg:province":"IL",
    "sg:tags":[
        "advisory",
        "mutual",
        "consultant",
        "broker",
        "fund",
        "planning",
        "bond",
        "stock"
    ],
    "sg:website":"http://www.tisonfinancialgroup.com",
    "wof:name":"Raymond James Financial Services",
    "wof:placetype":"venue"
},
  "geometry": {"coordinates":[-88.540274,37.737886],"type":"Point"}
}