{
  "type": "Feature",
  "properties": {
    "addr:full":"1246 Camp Jackson Rd Cahokia IL 62206",
    "addr:housenumber":"1246",
    "addr:postcode":"62206",
    "addr:street":"Camp Jackson Rd",
    "iso:country":"US",
    "sg:address":"1246 Camp Jackson Rd",
    "sg:city":"Cahokia",
    "sg:classifiers":[
        {
            "category":"Restaurant",
            "type":"Food & Drink"
        }
    ],
    "sg:phone":"+1 618 332 1909",
    "sg:postcode":"62206",
    "sg:province":"IL",
    "wof:name":"Subway Sandwiches & Salads",
    "wof:placetype":"venue"
},
  "geometry": {"coordinates":[-90.174042,38.560695],"type":"Point"}
}