{
  "type": "Feature",
  "properties": {
    "iso:country":"US",
    "sg:address":"1655 W Division St",
    "sg:city":"Chicago",
    "sg:classifiers":[
        {
            "category":"Shopping",
            "subcategory":"Crafts & Fabrics",
            "type":"Retail Goods"
        }
    ],
    "sg:phone":"+1 773 486 8996",
    "sg:postcode":"60622",
    "sg:province":"IL",
    "sg:tags":[
        "knitting",
        "supply"
    ],
    "sg:website":"www.ninachicago.com",
    "wof:name":"Nina",
    "wof:placetype":"venue"
},
  "geometry": {"coordinates":[-87.66909099999999,41.903314],"type":"Point"}
}