{
  "type": "Feature",
  "properties": {
    "addr:full":"4657 Puffer Rd Downers Grove IL 60515",
    "addr:housenumber":"4657",
    "addr:postcode":"60515",
    "addr:street":"Puffer Rd",
    "iso:country":"US",
    "sg:address":"4657 Puffer Rd",
    "sg:city":"Downers Grove",
    "sg:classifiers":[
        {
            "category":"Professional",
            "subcategory":"Accounting & Tax Preparation",
            "type":"Services"
        }
    ],
    "sg:phone":"+1 630 969 1867",
    "sg:postcode":"60515",
    "sg:province":"IL",
    "sg:tags":[
        "return"
    ],
    "wof:name":"Hilda M Schultz",
    "wof:placetype":"venue"
},
  "geometry": {"coordinates":[-88.03910500000001,41.80201],"type":"Point"}
}