{
  "type": "Feature",
  "properties": {
    "iso:country":"US",
    "sg:address":"3100 Golf Rd",
    "sg:city":"Rolling Meadows",
    "sg:classifiers":[
        {
            "category":"Professional",
            "subcategory":"Management & Consulting",
            "type":"Services"
        }
    ],
    "sg:phone":"+1 847 734 3810",
    "sg:postcode":"60008",
    "sg:province":"IL",
    "wof:name":"Helene Curtis New Dimensions",
    "wof:placetype":"venue"
},
  "geometry": {"coordinates":[-88.020342,42.051137],"type":"Point"}
}