{
  "type": "Feature",
  "properties": {
    "addr:full":"91 Fairfield Ln Cary IL 60013",
    "addr:housenumber":"91",
    "addr:postcode":"60013",
    "addr:street":"Fairfield Ln",
    "iso:country":"US",
    "sg:address":"91 Fairfield Ln",
    "sg:city":"Cary",
    "sg:classifiers":[
        {
            "category":"Manufacturing",
            "subcategory":"Retail Goods",
            "type":"Manufacturing & Wholesale Goods"
        }
    ],
    "sg:phone":"+1 847 639 1691",
    "sg:postcode":"60013",
    "sg:province":"IL",
    "sg:tags":[
        "manufacturer"
    ],
    "wof:name":"LGB Industries",
    "wof:placetype":"venue"
},
  "geometry": {"coordinates":[-88.26521099999999,42.209459],"type":"Point"}
}