{
  "type": "Feature",
  "properties": {
    "addr:full":"8240 Archer Ave Willow Springs IL 60480",
    "addr:housenumber":"8240",
    "addr:postcode":"60480",
    "addr:street":"Archer Ave",
    "iso:country":"US",
    "sg:address":"8240 Archer Ave",
    "sg:city":"Willow Springs",
    "sg:classifiers":[
        {
            "category":"Restaurant",
            "type":"Food & Drink"
        }
    ],
    "sg:phone":"+1   ",
    "sg:postcode":"60480",
    "sg:province":"IL",
    "sg:tags":[
        "drinking",
        "eating"
    ],
    "wof:name":"Willow Springs Friendly Tap",
    "wof:placetype":"venue"
},
  "geometry": {"coordinates":[-87.861678,41.740518],"type":"Point"}
}