{
  "type": "Feature",
  "properties": {
    "addr:full":"1423 Lundvall Ave Rockford IL 61107",
    "addr:housenumber":"1423",
    "addr:postcode":"61107",
    "addr:street":"Lundvall Ave",
    "iso:country":"US",
    "sg:address":"1423 Lundvall Ave",
    "sg:city":"Rockford",
    "sg:classifiers":[
        {
            "category":"Health Services",
            "subcategory":"Hospital",
            "type":"Services"
        }
    ],
    "sg:phone":"+1 815 398 1960",
    "sg:postcode":"61107",
    "sg:province":"IL",
    "sg:tags":[
        "specialty"
    ],
    "wof:name":"McAren Acupuncture & Herbs Ctr",
    "wof:placetype":"venue"
},
  "geometry": {"coordinates":[-89.051458,42.279461],"type":"Point"}
}