{
  "type": "Feature",
  "properties": {
    "iso:country":"US",
    "sg:address":"14135 Scott Ln",
    "sg:city":"Orland Park",
    "sg:classifiers":[
        {
            "category":"Banks & Credit Unions",
            "subcategory":"Investment Brokerage",
            "type":"Services"
        }
    ],
    "sg:phone":"+1 708 873 0202",
    "sg:postcode":"60462",
    "sg:province":"IL",
    "sg:tags":[
        "commodity",
        "contract"
    ],
    "wof:name":"Lawrence G Pietrzak Jr Inc",
    "wof:placetype":"venue"
},
  "geometry": {"coordinates":[-87.810598,41.63354],"type":"Point"}
}