{
  "type": "Feature",
  "properties": {
    "iso:country":"US",
    "sg:address":"511 Vfw St",
    "sg:city":"Coulterville",
    "sg:classifiers":[
        {
            "category":"Organizations",
            "subcategory":"Community Association",
            "type":"Services"
        }
    ],
    "sg:phone":"+1 618 758 9009",
    "sg:postcode":"62237",
    "sg:province":"IL",
    "sg:tags":[
        "military"
    ],
    "wof:name":"Veterans Of Foreign Wars",
    "wof:placetype":"venue"
},
  "geometry": {"coordinates":[-89.600962,38.193213],"type":"Point"}
}