{
  "type": "Feature",
  "properties": {
    "addr:full":"600 E Main St Knoxville IL 61448",
    "addr:housenumber":"600",
    "addr:postcode":"61448",
    "addr:street":"E Main St",
    "iso:country":"US",
    "sg:address":"600 E Main St",
    "sg:city":"Knoxville",
    "sg:classifiers":[
        {
            "category":"Education",
            "subcategory":"School",
            "type":"Public Place"
        }
    ],
    "sg:phone":"+1 309 289 2324",
    "sg:postcode":"61448",
    "sg:province":"IL",
    "wof:name":"School District 202",
    "wof:placetype":"venue"
},
  "geometry": {"coordinates":[-90.276399,40.908073],"type":"Point"}
}