{
  "type": "Feature",
  "properties": {
    "addr:full":"120 Carlyle Plaza Dr Belleville IL 62221",
    "addr:housenumber":"120",
    "addr:postcode":"62221",
    "addr:street":"Carlyle Plaza Dr",
    "iso:country":"US",
    "sg:address":"120 Carlyle Plaza Dr",
    "sg:city":"Belleville",
    "sg:classifiers":[
        {
            "category":"Professional",
            "subcategory":"Accounting & Tax Preparation",
            "type":"Services"
        }
    ],
    "sg:phone":"+1 618 239 6787",
    "sg:postcode":"62221",
    "sg:province":"IL",
    "sg:tags":[
        "return",
        "filing"
    ],
    "wof:name":"H & R Block Tax Svc",
    "wof:placetype":"venue"
},
  "geometry": {"coordinates":[-89.95304299999999,38.514143],"type":"Point"}
}