{
  "type": "Feature",
  "properties": {
    "addr:full":"513 E 8th St Dixon IL 61021",
    "addr:housenumber":"513",
    "addr:postcode":"61021",
    "addr:street":"E 8Th St",
    "iso:country":"US",
    "sg:address":"513 E 8th St",
    "sg:city":"Dixon",
    "sg:classifiers":[
        {
            "category":"Personal",
            "subcategory":"Beauty Salon",
            "type":"Services"
        }
    ],
    "sg:phone":"+1 815 284 6341",
    "sg:postcode":"61021",
    "sg:province":"IL",
    "sg:tags":[
        "shop"
    ],
    "wof:name":"Shear Delight",
    "wof:placetype":"venue"
},
  "geometry": {"coordinates":[-89.473975,41.838498],"type":"Point"}
}