{
  "type": "Feature",
  "properties": {
    "iso:country":"US",
    "sg:address":"7545 N Winchester Ave",
    "sg:city":"Chicago",
    "sg:classifiers":[
        {
            "category":"Autos & Motor Vehicles",
            "subcategory":"Automobile Sales",
            "type":"Retail Goods"
        }
    ],
    "sg:phone":"+1 773 381 1569",
    "sg:postcode":"60626",
    "sg:province":"IL",
    "sg:tags":[
        "equipment",
        "truck",
        "air conditioning"
    ],
    "wof:name":"Smith, Bill Jr General Truck Sa",
    "wof:placetype":"venue"
},
  "geometry": {"coordinates":[-87.679039,42.018592],"type":"Point"}
}