{
  "type": "Feature",
  "properties": {
    "addr:full":"1201 Park Ave River Forest IL 60305",
    "addr:housenumber":"1201",
    "addr:postcode":"60305",
    "addr:street":"Park Ave",
    "iso:country":"US",
    "sg:address":"1201 Park Ave",
    "sg:city":"River Forest",
    "sg:classifiers":[
        {
            "category":"Home & Garden",
            "subcategory":"Furniture",
            "type":"Retail Goods"
        }
    ],
    "sg:phone":"+1   ",
    "sg:postcode":"60305",
    "sg:province":"IL",
    "wof:name":"Comfort Zone",
    "wof:placetype":"venue"
},
  "geometry": {"coordinates":[-87.820223,41.90433],"type":"Point"}
}