{
  "type": "Feature",
  "properties": {
    "iso:country":"US",
    "sg:address":"8825 S Calumet Ave",
    "sg:city":"Chicago",
    "sg:classifiers":[
        {
            "category":"Organizations",
            "subcategory":"Religious Organization",
            "type":"Services"
        }
    ],
    "sg:phone":"+1 773 874 5291",
    "sg:postcode":"60619",
    "sg:province":"IL",
    "wof:name":"Impact Ministries",
    "wof:placetype":"venue"
},
  "geometry": {"coordinates":[-87.615898,41.733898],"type":"Point"}
}