{
  "type": "Feature",
  "properties": {
    "addr:full":"42701 N Deep Lake Rd Antioch IL 60002",
    "addr:housenumber":"42701",
    "addr:postcode":"60002",
    "addr:street":"N Deep Lake Rd",
    "iso:country":"US",
    "sg:address":"42701 N Deep Lake Rd",
    "sg:city":"Antioch",
    "sg:classifiers":[
        {
            "category":"Freight",
            "type":"Transportation"
        }
    ],
    "sg:phone":"+1 847 395 4908",
    "sg:postcode":"60002",
    "sg:province":"IL",
    "sg:tags":[
        "building",
        "house",
        "mover"
    ],
    "wof:name":"Eddy's House Raising & Bldg",
    "wof:placetype":"venue"
},
  "geometry": {"coordinates":[-88.062124,42.481402],"type":"Point"}
}