{
  "type": "Feature",
  "properties": {
    "iso:country":"US",
    "sg:address":"3130 N Elston Ave",
    "sg:city":"Chicago",
    "sg:classifiers":[
        {
            "category":"Home & Garden",
            "subcategory":"Carpets & Floor Coverings",
            "type":"Retail Goods"
        }
    ],
    "sg:phone":"+1 773 463 9405",
    "sg:postcode":"60618",
    "sg:province":"IL",
    "sg:tags":[
        "material",
        "carpeting",
        "flooring",
        "contractor"
    ],
    "sg:website":"http://www.gabesinstallation.com",
    "wof:name":"Gabe's Installation Service Inc",
    "wof:placetype":"venue"
},
  "geometry": {"coordinates":[-87.69609800000001,41.938],"type":"Point"}
}