{
  "type": "Feature",
  "properties": {
    "addr:full":"106 N 6th St Quincy IL 62301",
    "addr:housenumber":"106",
    "addr:postcode":"62301",
    "addr:street":"N 6Th St",
    "iso:country":"US",
    "sg:address":"106 N 6th St",
    "sg:city":"Quincy",
    "sg:classifiers":[
        {
            "category":"Shopping",
            "subcategory":"Used Merchandise",
            "type":"Retail Goods"
        }
    ],
    "sg:phone":"+1 217 222 7001",
    "sg:postcode":"62301",
    "sg:province":"IL",
    "sg:tags":[
        "resale",
        "shop"
    ],
    "wof:name":"Jeanne's Shoppe",
    "wof:placetype":"venue"
},
  "geometry": {"coordinates":[-91.40675400000001,39.931973],"type":"Point"}
}