{
  "type": "Feature",
  "properties": {
    "iso:country":"US",
    "sg:address":"208 S Chestnut St",
    "sg:city":"Champaign",
    "sg:classifiers":[
        {
            "category":"Building & Trades",
            "subcategory":"Electrical",
            "type":"Services"
        }
    ],
    "sg:phone":"+1 217 359 3914",
    "sg:postcode":"61820",
    "sg:province":"IL",
    "sg:tags":[
        "security",
        "electrical",
        "system",
        "contractor"
    ],
    "wof:name":"A-1 Alarm Service Inc",
    "wof:placetype":"venue"
},
  "geometry": {"coordinates":[-88.242121,40.113798],"type":"Point"}
}