{
  "type": "Feature",
  "properties": {
    "addr:full":"3304 Prairie Dell Rd Shipman IL 62685",
    "addr:housenumber":"3304",
    "addr:postcode":"62685",
    "addr:street":"Prairie Dell Rd",
    "iso:country":"US",
    "sg:address":"3304 Prairie Dell Rd",
    "sg:city":"Shipman",
    "sg:classifiers":[
        {
            "category":"Real Estate",
            "subcategory":"Real Estate Operator",
            "type":"Services"
        }
    ],
    "sg:phone":"+1 618 729 4476",
    "sg:postcode":"62685",
    "sg:province":"IL",
    "sg:tags":[
        "property",
        "lessor"
    ],
    "wof:name":"Irma Stone",
    "wof:placetype":"venue"
},
  "geometry": {"coordinates":[-90.080316,39.102175],"type":"Point"}
}