{
  "type": "Feature",
  "properties": {
    "iso:country":"US",
    "sg:address":"5331 W 65th St",
    "sg:city":"Chicago",
    "sg:classifiers":[
        {
            "category":"Manufacturing",
            "subcategory":"Furniture",
            "type":"Manufacturing & Wholesale Goods"
        }
    ],
    "sg:phone":"+1 708 594 6712",
    "sg:postcode":"60638",
    "sg:province":"IL",
    "sg:tags":[
        "builder",
        "designer",
        "custom"
    ],
    "wof:name":"K -A Cabinets Inc.",
    "wof:placetype":"venue"
},
  "geometry": {"coordinates":[-87.755883,41.774479],"type":"Point"}
}