{
  "type": "Feature",
  "properties": {
    "iso:country":"US",
    "sg:address":"8644 S 86th Ave",
    "sg:city":"Bedford Park",
    "sg:classifiers":[
        {
            "category":"Retail",
            "subcategory":"Laundry & Dry Cleaning",
            "type":"Services"
        }
    ],
    "sg:phone":"+1 708 728 0229",
    "sg:postcode":"60458",
    "sg:province":"IL",
    "wof:name":"Unique Floor Maintenance",
    "wof:placetype":"venue"
},
  "geometry": {"coordinates":[-87.833493,41.735632],"type":"Point"}
}