{
  "type": "Feature",
  "properties": {
    "addr:full":"1300 Jefferson St Des Plaines IL 60016",
    "addr:housenumber":"1300",
    "addr:postcode":"60016",
    "addr:street":"Jefferson St",
    "iso:country":"US",
    "sg:address":"1300 Jefferson St",
    "sg:city":"Des Plaines",
    "sg:classifiers":[
        {
            "category":"Wholesale",
            "subcategory":"Durable Goods & Equipment",
            "type":"Manufacturing & Wholesale Goods"
        }
    ],
    "sg:phone":"+1 847 759 1100",
    "sg:postcode":"60016",
    "sg:province":"IL",
    "sg:tags":[
        "representative",
        "manufacturer"
    ],
    "wof:name":"Four Seasons Sales & Marketing",
    "wof:placetype":"venue"
},
  "geometry": {"coordinates":[-87.88996899999999,42.043236],"type":"Point"}
}