{
  "type": "Feature",
  "properties": {
    "addr:full":"1111 W Pershing Rd Chicago IL 60609",
    "addr:housenumber":"1111",
    "addr:postcode":"60609",
    "addr:street":"W Pershing Rd",
    "iso:country":"US",
    "sg:address":"1111 W Pershing Rd",
    "sg:city":"Chicago",
    "sg:classifiers":[
        {
            "category":"Professional",
            "subcategory":"Business Services",
            "type":"Services"
        }
    ],
    "sg:phone":"+1 773 376 1668",
    "sg:postcode":"60609",
    "sg:province":"IL",
    "sg:tags":[
        "holding"
    ],
    "wof:name":"Wong Associates Holding",
    "wof:placetype":"venue"
},
  "geometry": {"coordinates":[-87.654162,41.823294],"type":"Point"}
}