{
  "type": "Feature",
  "properties": {
    "iso:country":"US",
    "sg:address":"11058 Addison Ave",
    "sg:city":"Franklin Park",
    "sg:classifiers":[
        {
            "category":"Wholesale",
            "subcategory":"Stationery",
            "type":"Manufacturing & Wholesale Goods"
        }
    ],
    "sg:phone":"+1 847 349 1500",
    "sg:postcode":"60131",
    "sg:province":"IL",
    "sg:tags":[
        "a",
        "container",
        "supply",
        "food",
        "disposable",
        "equipment",
        "sanitary"
    ],
    "sg:website":"www.allpfs.com",
    "wof:name":"Alliance Paper & Food Service",
    "wof:placetype":"venue"
},
  "geometry": {"coordinates":[-87.903251,41.942271],"type":"Point"}
}