{
  "type": "Feature",
  "properties": {
    "addr:full":"2206 Downing Ave Westchester IL 60154",
    "addr:housenumber":"2206",
    "addr:postcode":"60154",
    "addr:street":"Downing Ave",
    "iso:country":"US",
    "sg:address":"2206 Downing Ave",
    "sg:city":"Westchester",
    "sg:classifiers":[
        {
            "category":"Professional",
            "subcategory":"Engineering",
            "type":"Services"
        }
    ],
    "sg:phone":"+1 708 836 9910",
    "sg:postcode":"60154",
    "sg:province":"IL",
    "wof:name":"Cavanaugh General Contractors",
    "wof:placetype":"venue"
},
  "geometry": {"coordinates":[-87.88903500000001,41.844927],"type":"Point"}
}