{
  "type": "Feature",
  "properties": {
    "addr:full":"207 N Center St Durand IL 61024",
    "addr:housenumber":"207",
    "addr:postcode":"61024",
    "addr:street":"N Center St",
    "iso:country":"US",
    "sg:address":"207 N Center St",
    "sg:city":"Durand",
    "sg:classifiers":[
        {
            "category":"Retail",
            "subcategory":"Laundry & Dry Cleaning",
            "type":"Services"
        }
    ],
    "sg:phone":"+1 815 248 4430",
    "sg:postcode":"61024",
    "sg:province":"IL",
    "wof:name":"Center Street Laundry",
    "wof:placetype":"venue"
},
  "geometry": {"coordinates":[-89.331833,42.434902],"type":"Point"}
}