{
  "type": "Feature",
  "properties": {
    "addr:full":"706 Sunset Ln Shorewood IL 60404",
    "addr:housenumber":"706",
    "addr:postcode":"60404",
    "addr:street":"Sunset Ln",
    "iso:country":"US",
    "sg:address":"706 Sunset Ln",
    "sg:city":"Shorewood",
    "sg:classifiers":[
        {
            "category":"Building & Trades",
            "subcategory":"Cleaning & Sanitation",
            "type":"Services"
        }
    ],
    "sg:phone":"+1 815 725 7280",
    "sg:postcode":"60404",
    "sg:province":"IL",
    "sg:tags":[
        "janitor"
    ],
    "wof:name":"Golden Touch-Ceiling Pro Clng",
    "wof:placetype":"venue"
},
  "geometry": {"coordinates":[-88.200722,41.514829],"type":"Point"}
}