{
  "type": "Feature",
  "properties": {
    "addr:full":"1955 W Field Ct Lake Forest IL 60045",
    "addr:housenumber":"1955",
    "addr:postcode":"60045",
    "addr:street":"W Field Ct",
    "iso:country":"US",
    "sg:address":"1955 W Field Ct",
    "sg:city":"Lake Forest",
    "sg:classifiers":[
        {
            "category":"Manufacturing",
            "subcategory":"Tools & Machinery",
            "type":"Manufacturing & Wholesale Goods"
        }
    ],
    "sg:phone":"+1 847 803 4600",
    "sg:postcode":"60045",
    "sg:province":"IL",
    "sg:tags":[
        "mfg",
        "personal",
        "chi",
        "appliance",
        "clocks",
        "small",
        "kitchen",
        "care"
    ],
    "sg:website":"www.saltonglobal.com",
    "wof:name":"Salton Inc",
    "wof:placetype":"venue"
},
  "geometry": {"coordinates":[-87.890216,42.24112],"type":"Point"}
}