{
  "type": "Feature",
  "properties": {
    "iso:country":"US",
    "sg:address":"3541 W Peterson Ave",
    "sg:city":"Chicago",
    "sg:classifiers":[
        {
            "category":"Place Of Worship",
            "subcategory":"Synagogue",
            "type":"Public Place"
        }
    ],
    "sg:phone":"+1 773 588 0021",
    "sg:postcode":"60659",
    "sg:province":"IL",
    "wof:name":"Agudath Israel-Warsaw Bickur Cholin Congrtn",
    "wof:placetype":"venue"
},
  "geometry": {"coordinates":[-87.71790300000001,41.990002],"type":"Point"}
}