{
  "type": "Feature",
  "properties": {
    "iso:country":"US",
    "sg:address":"5832 E State Rte 15",
    "sg:city":"Woodlawn",
    "sg:classifiers":[
        {
            "category":"Bars & Pubs",
            "type":"Food & Drink"
        }
    ],
    "sg:phone":"+1 618 735 9969",
    "sg:postcode":"62898",
    "sg:province":"IL",
    "wof:name":"Woodlawn Bar",
    "wof:placetype":"venue"
},
  "geometry": {"coordinates":[-89.038602,38.307305],"type":"Point"}
}