{
  "type": "Feature",
  "properties": {
    "iso:country":"US",
    "sg:address":"294 Evergreen Dr",
    "sg:city":"Vernon Hills",
    "sg:classifiers":[
        {
            "category":"Organizations",
            "subcategory":"Religious Organization",
            "type":"Services"
        }
    ],
    "sg:phone":"+1 847 549 8538",
    "sg:postcode":"60061",
    "sg:province":"IL",
    "sg:tags":[
        "church"
    ],
    "wof:name":"New Life Fellowship",
    "wof:placetype":"venue"
},
  "geometry": {"coordinates":[-87.971047,42.221428],"type":"Point"}
}