{
  "type": "Feature",
  "properties": {
    "addr:full":"2523 N Lawndale Ave Chicago IL 60647",
    "addr:housenumber":"2523",
    "addr:postcode":"60647",
    "addr:street":"N Lawndale Ave",
    "iso:country":"US",
    "sg:address":"2523 N Lawndale Ave",
    "sg:city":"Chicago",
    "sg:classifiers":[
        {
            "category":"Professional",
            "subcategory":"Computer Services",
            "type":"Services"
        }
    ],
    "sg:phone":"+1 773 433 0191",
    "sg:postcode":"60647",
    "sg:province":"IL",
    "sg:tags":[
        "repair"
    ],
    "sg:website":"editchicago.net",
    "wof:name":"edIT",
    "wof:placetype":"venue"
},
  "geometry": {"coordinates":[-87.71946800000001,41.927085],"type":"Point"}
}