{
  "type": "Feature",
  "properties": {
    "addr:full":"6187 S Archer Ave Chicago IL 60638",
    "addr:housenumber":"6187",
    "addr:postcode":"60638",
    "addr:street":"S Archer Ave",
    "iso:country":"US",
    "sg:address":"6187 S Archer Ave",
    "sg:city":"Chicago",
    "sg:classifiers":[
        {
            "category":"Health Services",
            "subcategory":"Optometrist",
            "type":"Services"
        }
    ],
    "sg:phone":"+1 773 581 2000",
    "sg:postcode":"60638",
    "sg:province":"IL",
    "sg:tags":[
        "ophthalmologist"
    ],
    "wof:name":"Mizen Thomas R MD",
    "wof:placetype":"venue"
},
  "geometry": {"coordinates":[-87.773201,41.7939],"type":"Point"}
}