{
  "type": "Feature",
  "properties": {
    "iso:country":"US",
    "sg:address":"336 Ruby St",
    "sg:city":"Joliet",
    "sg:classifiers":[
        {
            "category":"Building & Trades",
            "subcategory":"Plumbing",
            "type":"Services"
        }
    ],
    "sg:phone":"+1 815 722 4088",
    "sg:postcode":"60435",
    "sg:province":"IL",
    "sg:tags":[
        "heating",
        "contractor"
    ],
    "wof:name":"Bedolla Heating & Cooling",
    "wof:placetype":"venue"
},
  "geometry": {"coordinates":[-88.090466,41.538039],"type":"Point"}
}