{
  "type": "Feature",
  "properties": {
    "addr:full":"336 Ruby St Joliet IL 60435",
    "addr:housenumber":"336",
    "addr:postcode":"60435",
    "addr:street":"Ruby St",
    "iso:country":"US",
    "sg:address":"336 Ruby St",
    "sg:city":"Joliet",
    "sg:classifiers":[
        {
            "category":"Building & Trades",
            "subcategory":"Plumbing",
            "type":"Services"
        }
    ],
    "sg:phone":"+1 815 722 4088",
    "sg:postcode":"60435",
    "sg:province":"IL",
    "sg:tags":[
        "heating",
        "contractor"
    ],
    "wof:name":"Bedolla Heating & Cooling",
    "wof:placetype":"venue"
},
  "geometry": {"coordinates":[-88.09046600000001,41.538039],"type":"Point"}
}