{
  "type": "Feature",
  "properties": {
    "addr:full":"1709 Delrose St Joliet IL 60435",
    "addr:housenumber":"1709",
    "addr:postcode":"60435",
    "addr:street":"Delrose St",
    "iso:country":"US",
    "sg:address":"1709 Delrose St",
    "sg:city":"Joliet",
    "sg:classifiers":[
        {
            "category":"Real Estate",
            "subcategory":"Real Estate Services",
            "type":"Services"
        },
        {
            "category":"Real Estate",
            "subcategory":"Real Estate Agent",
            "type":"Services"
        }
    ],
    "sg:phone":"+1 815 546 9771",
    "sg:postcode":"60435",
    "sg:province":"IL",
    "sg:tags":[
        "buyer",
        "broker"
    ],
    "wof:name":"Accurate Realty",
    "wof:placetype":"venue"
},
  "geometry": {"coordinates":[-88.155682,41.553802],"type":"Point"}
}