{
  "type": "Feature",
  "properties": {
    "iso:country":"US",
    "sg:address":"108 E University Ave",
    "sg:city":"Champaign",
    "sg:classifiers":[
        {
            "category":"Banks & Credit Unions",
            "subcategory":"Bank",
            "type":"Services"
        }
    ],
    "sg:phone":"+1 217 352 6922",
    "sg:postcode":"61820",
    "sg:province":"IL",
    "sg:tags":[
        "personal"
    ],
    "wof:name":"Security Finance Corp of Ill",
    "wof:placetype":"venue"
},
  "geometry": {"coordinates":[-88.237183,40.116407],"type":"Point"}
}