{
  "type": "Feature",
  "properties": {
    "addr:full":"2403 S Blue Island Ave Chicago IL 60608",
    "addr:housenumber":"2403",
    "addr:postcode":"60608",
    "addr:street":"S Blue Island Ave",
    "iso:country":"US",
    "sg:address":"2403 S Blue Island Ave",
    "sg:city":"Chicago",
    "sg:classifiers":[
        {
            "category":"Autos & Motor Vehicles",
            "subcategory":"Fuel & Gas Station",
            "type":"Retail Goods"
        }
    ],
    "sg:phone":"+1 773 376 9726",
    "sg:postcode":"60608",
    "sg:province":"IL",
    "wof:name":"M & B Inc",
    "wof:placetype":"venue"
},
  "geometry": {"coordinates":[-87.67582899999999,41.848515],"type":"Point"}
}