{
  "type": "Feature",
  "properties": {
    "addr:full":"528 W Grand Ave Elmhurst IL 60126",
    "addr:housenumber":"528",
    "addr:postcode":"60126",
    "addr:street":"W Grand Ave",
    "iso:country":"US",
    "sg:address":"528 W Grand Ave",
    "sg:city":"Elmhurst",
    "sg:classifiers":[
        {
            "category":"Retail",
            "subcategory":"Auto Rental",
            "type":"Services"
        }
    ],
    "sg:phone":"+1 630 279 5675",
    "sg:postcode":"60126",
    "sg:province":"IL",
    "sg:tags":[
        "renting",
        "automobile"
    ],
    "wof:name":"Avis Rent A Car",
    "wof:placetype":"venue"
},
  "geometry": {"coordinates":[-87.959883,41.927064],"type":"Point"}
}