{
  "type": "Feature",
  "properties": {
    "iso:country":"US",
    "sg:address":"1648 E New York St",
    "sg:city":"Aurora",
    "sg:classifiers":[
        {
            "category":"Real Estate",
            "subcategory":"Real Estate Agent",
            "type":"Services"
        }
    ],
    "sg:phone":"+1 630 820 3300",
    "sg:postcode":"60505",
    "sg:province":"IL",
    "wof:name":"Desmond Services Inc.",
    "wof:placetype":"venue"
},
  "geometry": {"coordinates":[-88.273239,41.758381],"type":"Point"}
}