{
  "type": "Feature",
  "properties": {
    "iso:country":"US",
    "sg:address":"1632 W Hollywood Ave",
    "sg:city":"Chicago",
    "sg:classifiers":[
        {
            "category":"Retail",
            "subcategory":"Repair Shop",
            "type":"Services"
        },
        {
            "category":"Wholesale",
            "subcategory":"Construction Materials",
            "type":"Manufacturing & Wholesale Goods"
        },
        {
            "category":"Building & Trades",
            "subcategory":"Construction",
            "type":"Services"
        }
    ],
    "sg:phone":"+1 773 989 0432",
    "sg:postcode":"60660",
    "sg:province":"IL",
    "sg:tags":[
        "major",
        "refinishing",
        "appliance",
        "specialty",
        "system",
        "systems-wholesale",
        "equipment",
        "heating",
        "contractor",
        "air conditioning"
    ],
    "wof:name":"Service Air",
    "wof:placetype":"venue"
},
  "geometry": {"coordinates":[-87.67075699999999,41.985107],"type":"Point"}
}