{
  "type": "Feature",
  "properties": {
    "iso:country":"US",
    "sg:address":"17 River Oaks Dr",
    "sg:city":"Calumet City",
    "sg:classifiers":[
        {
            "category":"Utilities",
            "subcategory":"Mobile Phone",
            "type":"Services"
        }
    ],
    "sg:phone":"+1 708 868 9000",
    "sg:postcode":"60409",
    "sg:province":"IL",
    "sg:tags":[
        "equipment",
        "paging",
        "signaling",
        "system"
    ],
    "wof:name":"ABC Cellular",
    "wof:placetype":"venue"
},
  "geometry": {"coordinates":[-87.525778,41.595825],"type":"Point"}
}