{
  "type": "Feature",
  "properties": {
    "iso:country":"US",
    "sg:address":"1575 1600th Ave",
    "sg:city":"Lincoln",
    "sg:phone":"+1 217 732 9878",
    "sg:postcode":"62656",
    "sg:province":"IL",
    "sg:tags":[
        "farm",
        "corn",
        "soybean"
    ],
    "wof:name":"Sandel John",
    "wof:placetype":"venue"
},
  "geometry": {"coordinates":[-89.291842,40.146883],"type":"Point"}
}