{
  "type": "Feature",
  "properties": {
    "addr:full":"3907 Howard St Skokie IL 60076",
    "addr:housenumber":"3907",
    "addr:postcode":"60076",
    "addr:street":"Howard St",
    "iso:country":"US",
    "sg:address":"3907 Howard St",
    "sg:city":"Skokie",
    "sg:classifiers":[
        {
            "category":"Restaurant",
            "type":"Food & Drink"
        }
    ],
    "sg:phone":"+1 847 677 7883",
    "sg:postcode":"60076",
    "sg:province":"IL",
    "sg:tags":[
        "caterer"
    ],
    "wof:name":"Cortes Catering",
    "wof:placetype":"venue"
},
  "geometry": {"coordinates":[-87.72831100000001,42.018916],"type":"Point"}
}