{
  "type": "Feature",
  "properties": {
    "iso:country":"US",
    "sg:address":"1233 Central St",
    "sg:city":"Evanston",
    "sg:classifiers":[
        {
            "category":"Professional",
            "subcategory":"Business Services",
            "type":"Services"
        }
    ],
    "sg:phone":"+1   ",
    "sg:postcode":"60201",
    "sg:province":"IL",
    "sg:tags":[
        "automobile",
        "used"
    ],
    "wof:name":"TI Enterprise",
    "wof:placetype":"venue"
},
  "geometry": {"coordinates":[-87.688611,42.064297],"type":"Point"}
}