{
  "type": "Feature",
  "properties": {
    "iso:country":"US",
    "sg:address":"309 E Jefferson St",
    "sg:city":"Gardner",
    "sg:classifiers":[
        {
            "category":"Organizations",
            "subcategory":"Religious Organization",
            "type":"Services"
        }
    ],
    "sg:phone":"+1 815 237 2227",
    "sg:postcode":"60424",
    "sg:province":"IL",
    "sg:tags":[
        "church"
    ],
    "wof:name":"United Lutheran Church",
    "wof:placetype":"venue"
},
  "geometry": {"coordinates":[-88.30436,41.187595],"type":"Point"}
}