{
  "type": "Feature",
  "properties": {
    "addr:full":"974 Main St Antioch IL 60002",
    "addr:housenumber":"974",
    "addr:postcode":"60002",
    "addr:street":"Main St",
    "iso:country":"US",
    "sg:address":"974 Main St",
    "sg:city":"Antioch",
    "sg:classifiers":[
        {
            "category":"Real Estate",
            "subcategory":"Real Estate Agent",
            "type":"Services"
        }
    ],
    "sg:phone":"+1 847 395 7575",
    "sg:postcode":"60002",
    "sg:province":"IL",
    "wof:name":"Coldwell Banker Hometrust",
    "wof:placetype":"venue"
},
  "geometry": {"coordinates":[-88.09552600000001,42.476536],"type":"Point"}
}