{
  "type": "Feature",
  "properties": {
    "iso:country":"US",
    "sg:address":"18531 Spring Creek Dr",
    "sg:city":"Tinley Park",
    "sg:classifiers":[
        {
            "category":"Manufacturing",
            "subcategory":"Electronics",
            "type":"Manufacturing & Wholesale Goods"
        }
    ],
    "sg:phone":"+1 708 633 5000",
    "sg:postcode":"60477",
    "sg:province":"IL",
    "sg:tags":[
        "par",
        "mfg",
        "electronic",
        "motor",
        "vehicle"
    ],
    "wof:name":"ITW Filtration Products",
    "wof:placetype":"venue"
},
  "geometry": {"coordinates":[-87.797357,41.555515],"type":"Point"}
}