{
  "type": "Feature",
  "properties": {
    "addr:full":"2347 W Marquette Rd Chicago IL 60636",
    "addr:housenumber":"2347",
    "addr:postcode":"60636",
    "addr:street":"W Marquette Rd",
    "iso:country":"US",
    "sg:address":"2347 W Marquette Rd",
    "sg:city":"Chicago",
    "sg:classifiers":[
        {
            "category":"Shopping",
            "subcategory":"Florist",
            "type":"Retail Goods"
        }
    ],
    "sg:phone":"+1 773 471 3000",
    "sg:postcode":"60636",
    "sg:province":"IL",
    "wof:name":"W & L Floristry",
    "wof:placetype":"venue"
},
  "geometry": {"coordinates":[-87.682292,41.771886],"type":"Point"}
}