{
  "type": "Feature",
  "properties": {
    "addr:full":"5241 W Chicago Avenue Chicago IL 60651",
    "addr:housenumber":"5241",
    "addr:postcode":"60651",
    "addr:street":"W Chicago Avenue",
    "iso:country":"US",
    "sg:address":"5241 W Chicago Avenue",
    "sg:city":"Chicago",
    "sg:classifiers":[
        {
            "category":"Restaurant",
            "type":"Food & Drink"
        }
    ],
    "sg:phone":"+1 773 378 0700",
    "sg:postcode":"60651",
    "sg:province":"IL",
    "wof:name":"Vo's Place",
    "wof:placetype":"venue"
},
  "geometry": {"coordinates":[-87.757048,41.89474],"type":"Point"}
}