{
  "type": "Feature",
  "properties": {
    "iso:country":"US",
    "sg:address":"651 Railroad Ave",
    "sg:city":"Round Lake",
    "sg:classifiers":[
        {
            "category":"Restaurant",
            "type":"Food & Drink"
        }
    ],
    "sg:phone":"+1 847 740 3540",
    "sg:postcode":"60073",
    "sg:province":"IL",
    "wof:name":"Nanuco's Cafe",
    "wof:placetype":"venue"
},
  "geometry": {"coordinates":[-88.095747,42.355208],"type":"Point"}
}