{
  "type": "Feature",
  "properties": {
    "addr:full":"843 W Armitage Ave Chicago IL 60614",
    "addr:housenumber":"843",
    "addr:postcode":"60614",
    "addr:street":"W Armitage Ave",
    "iso:country":"US",
    "sg:address":"843 W Armitage Ave",
    "sg:city":"Chicago",
    "sg:classifiers":[
        {
            "category":"Shopping",
            "subcategory":"Clothing, Apparel, & Fashions",
            "type":"Retail Goods"
        },
        {
            "category":"Wholesale",
            "subcategory":"Apparel",
            "type":"Manufacturing & Wholesale Goods"
        }
    ],
    "sg:phone":"+1 734 930 9909",
    "sg:postcode":"60614",
    "sg:province":"IL",
    "sg:tags":[
        "sportswear-wholesale",
        "sportswear",
        "manufacturer"
    ],
    "wof:name":"Clue Sports",
    "wof:placetype":"venue"
},
  "geometry": {"coordinates":[-87.649933,41.918166],"type":"Point"}
}