{
  "type": "Feature",
  "properties": {
    "iso:country":"US",
    "sg:address":"5021 W Erie St",
    "sg:city":"Chicago",
    "sg:classifiers":[
        {
            "category":"Social Services",
            "subcategory":"Adult Care",
            "type":"Services"
        },
        {
            "category":"Social Services",
            "subcategory":"Child Care",
            "type":"Services"
        }
    ],
    "sg:phone":"+1 773 378 3773",
    "sg:postcode":"60644",
    "sg:province":"IL",
    "sg:tags":[
        "home",
        "day",
        "residential"
    ],
    "wof:name":"Godfrey Jernigan Care Center",
    "wof:placetype":"venue"
},
  "geometry": {"coordinates":[-87.752556,41.892132],"type":"Point"}
}