{
  "type": "Feature",
  "properties": {
    "iso:country":"US",
    "sg:address":"156 S Bloomingdale Rd",
    "sg:city":"Bloomingdale",
    "sg:classifiers":[
        {
            "category":"Personal",
            "subcategory":"Beauty Salon",
            "type":"Services"
        },
        {
            "category":"Personal",
            "subcategory":"Nail Salon",
            "type":"Services"
        }
    ],
    "sg:phone":"+1 630 295 5999",
    "sg:postcode":"60108",
    "sg:province":"IL",
    "wof:name":"Americi's Salon",
    "wof:placetype":"venue"
},
  "geometry": {"coordinates":[-88.081001,41.9529],"type":"Point"}
}