{
  "type": "Feature",
  "properties": {
    "iso:country":"US",
    "sg:address":"9450 Bryn Mawr Ave",
    "sg:city":"Des Plaines",
    "sg:classifiers":[
        {
            "category":"Banks & Credit Unions",
            "subcategory":"Financial Services",
            "type":"Services"
        }
    ],
    "sg:phone":"+1 847 671 1616",
    "sg:postcode":"60018",
    "sg:province":"IL",
    "sg:tags":[
        "box",
        "spring",
        "mattress",
        "for",
        "manufacturer"
    ],
    "wof:name":"RMC",
    "wof:placetype":"venue"
},
  "geometry": {"coordinates":[-87.858058,41.980763],"type":"Point"}
}