{
  "type": "Feature",
  "properties": {
    "addr:full":"2400 E Devon Ave Des Plaines IL 60018",
    "addr:housenumber":"2400",
    "addr:postcode":"60018",
    "addr:street":"E Devon Ave",
    "iso:country":"US",
    "sg:address":"2400 E Devon Ave",
    "sg:city":"Des Plaines",
    "sg:classifiers":[
        {
            "category":"Professional",
            "subcategory":"Management & Consulting",
            "type":"Services"
        }
    ],
    "sg:phone":"+1 847 699 6310",
    "sg:postcode":"60018",
    "sg:province":"IL",
    "sg:tags":[
        "marketing",
        "program"
    ],
    "wof:name":"G B Marketing",
    "wof:placetype":"venue"
},
  "geometry": {"coordinates":[-87.87327500000001,41.995442],"type":"Point"}
}