{
  "type": "Feature",
  "properties": {
    "iso:country":"US",
    "sg:address":"3217 Lake Ave",
    "sg:city":"Wilmette",
    "sg:phone":"+1 847 251 9301",
    "sg:postcode":"60091",
    "sg:province":"IL",
    "wof:name":"Chick N Rib Joynt",
    "wof:placetype":"venue"
},
  "geometry": {"coordinates":[-87.75511899999999,42.079498],"type":"Point"}
}