{
  "type": "Feature",
  "properties": {
    "iso:country":"US",
    "sg:address":"7501 Lemont Rd",
    "sg:city":"Woodridge",
    "sg:classifiers":[
        {
            "category":"Professional",
            "subcategory":"Lawyer & Legal Services",
            "type":"Services"
        }
    ],
    "sg:phone":"+1 630 910 9300",
    "sg:postcode":"60517",
    "sg:province":"IL",
    "sg:tags":[
        "attorney"
    ],
    "wof:name":"Alan C Hruby Attorney At Law",
    "wof:placetype":"venue"
},
  "geometry": {"coordinates":[-88.012653,41.749693],"type":"Point"}
}