{
  "type": "Feature",
  "properties": {
    "addr:full":"1047 Parkview Cir Carol Stream IL 60188",
    "addr:housenumber":"1047",
    "addr:postcode":"60188",
    "addr:street":"Parkview Cir",
    "iso:country":"US",
    "sg:address":"1047 Parkview Cir",
    "sg:city":"Carol Stream",
    "sg:classifiers":[
        {
            "category":"Building & Trades",
            "subcategory":"Electrical",
            "type":"Services"
        }
    ],
    "sg:phone":"+1 630 289 1715",
    "sg:postcode":"60188",
    "sg:province":"IL",
    "sg:tags":[
        "electrical",
        "electric",
        "contractor"
    ],
    "wof:name":"Ashley Electric Inc",
    "wof:placetype":"venue"
},
  "geometry": {"coordinates":[-88.15736699999999,41.933933],"type":"Point"}
}