{
  "type": "Feature",
  "properties": {
    "iso:country":"US",
    "sg:address":"4630 S Cottage Grove Ave",
    "sg:city":"Chicago",
    "sg:classifiers":[
        {
            "category":"Wholesale",
            "subcategory":"Construction Materials",
            "type":"Manufacturing & Wholesale Goods"
        }
    ],
    "sg:phone":"+1 773 268 5000",
    "sg:postcode":"60653",
    "sg:province":"IL",
    "sg:tags":[
        "building",
        "retail",
        "supply"
    ],
    "wof:name":"Hyde Park Building Mtl Sups",
    "wof:placetype":"venue"
},
  "geometry": {"coordinates":[-87.60666,41.810634],"type":"Point"}
}