{
  "type": "Feature",
  "properties": {
    "addr:full":"2844 N Laramie Ave Chicago IL 60641",
    "addr:housenumber":"2844",
    "addr:postcode":"60641",
    "addr:street":"N Laramie Ave",
    "iso:country":"US",
    "sg:address":"2844 N Laramie Ave",
    "sg:city":"Chicago",
    "sg:classifiers":[
        {
            "category":"Shopping",
            "subcategory":"Florist",
            "type":"Retail Goods"
        }
    ],
    "sg:phone":"+1 773 725 4600",
    "sg:postcode":"60641",
    "sg:province":"IL",
    "sg:tags":[
        "basket",
        "gift"
    ],
    "wof:name":"Anna & Tom's Flowers",
    "wof:placetype":"venue"
},
  "geometry": {"coordinates":[-87.75630200000001,41.932701],"type":"Point"}
}