{
  "type": "Feature",
  "properties": {
    "iso:country":"US",
    "sg:address":"1714 N Damen Ave",
    "sg:city":"Chicago",
    "sg:classifiers":[
        {
            "category":"Professional",
            "subcategory":"Management & Consulting",
            "type":"Services"
        }
    ],
    "sg:phone":"+1 773 227 0000",
    "sg:postcode":"60647",
    "sg:province":"IL",
    "sg:tags":[
        "product",
        "business",
        "mfg"
    ],
    "wof:name":"Meyer Glass Design Inc",
    "wof:placetype":"venue"
},
  "geometry": {"coordinates":[-87.677588,41.912585],"type":"Point"}
}