{
  "type": "Feature",
  "properties": {
    "iso:country":"US",
    "sg:address":"5319 S Archer Ave",
    "sg:city":"Chicago",
    "sg:classifiers":[
        {
            "category":"Retail",
            "subcategory":"Auto Repair",
            "type":"Services"
        }
    ],
    "sg:phone":"+1 773 284 5900",
    "sg:postcode":"60632",
    "sg:province":"IL",
    "wof:name":"Waratek Auto Service",
    "wof:placetype":"venue"
},
  "geometry": {"coordinates":[-87.740099,41.798947],"type":"Point"}
}