{
  "type": "Feature",
  "properties": {
    "iso:country":"US",
    "sg:address":"800 Lake St Ste 122",
    "sg:city":"Roselle",
    "sg:classifiers":[
        {
            "category":"Building & Trades",
            "subcategory":"Locksmith",
            "type":"Services"
        }
    ],
    "sg:phone":"+1 630 894 0041",
    "sg:postcode":"60172",
    "sg:province":"IL",
    "sg:tags":[
        "key"
    ],
    "wof:name":"A L K Contractors Supply Corp",
    "wof:placetype":"venue"
},
  "geometry": {"coordinates":[-88.106903,41.966202],"type":"Point"}
}