{
  "type": "Feature",
  "properties": {
    "iso:country":"US",
    "sg:address":"2128 E Grand Ave",
    "sg:city":"Lindenhurst",
    "sg:classifiers":[
        {
            "category":"Insurance",
            "subcategory":"Hazard Insurance",
            "type":"Services"
        }
    ],
    "sg:phone":"+1 847 356 2954",
    "sg:postcode":"60046",
    "sg:province":"IL",
    "wof:name":"Country Financial",
    "wof:placetype":"venue"
},
  "geometry": {"coordinates":[-88.030789,42.408453],"type":"Point"}
}