{
  "type": "Feature",
  "properties": {
    "iso:country":"US",
    "sg:address":"4433 Harlem Ave",
    "sg:city":"Berwyn",
    "sg:classifiers":[
        {
            "category":"Building & Trades",
            "subcategory":"Plumbing",
            "type":"Services"
        }
    ],
    "sg:phone":"+1 773 585 5585",
    "sg:postcode":"60402",
    "sg:province":"IL",
    "sg:tags":[
        "plumbing",
        "contractor"
    ],
    "wof:name":"Ace Plumbing & Heating",
    "wof:placetype":"venue"
},
  "geometry": {"coordinates":[-87.802043,41.810621],"type":"Point"}
}