{
  "type": "Feature",
  "properties": {
    "iso:country":"US",
    "sg:address":"20W041 101st St",
    "sg:city":"Lemont",
    "sg:classifiers":[
        {
            "category":"Professional",
            "subcategory":"Management & Consulting",
            "type":"Services"
        }
    ],
    "sg:phone":"+1 630 972 1400",
    "sg:postcode":"60439",
    "sg:province":"IL",
    "sg:tags":[
        "food",
        "consultant",
        "beverage",
        "facility"
    ],
    "wof:name":"Brandt Cellars Intl.",
    "wof:placetype":"venue"
},
  "geometry": {"coordinates":[-88.017735,41.70343],"type":"Point"}
}