{
  "type": "Feature",
  "properties": {
    "iso:country":"US",
    "sg:address":"202 E Peabody Dr",
    "sg:city":"Champaign",
    "sg:classifiers":[
        {
            "category":"Professional",
            "type":"Services"
        }
    ],
    "sg:phone":"+1 217 337 0142",
    "sg:postcode":"61820",
    "sg:province":"IL",
    "sg:tags":[
        "establishment"
    ],
    "sg:website":"www.demaco.com",
    "wof:name":"Demaco",
    "wof:placetype":"venue"
},
  "geometry": {"coordinates":[-88.235985,40.101523],"type":"Point"}
}