{
  "type": "Feature",
  "properties": {
    "addr:full":"1640 W Kennedy Rd Lake Forest IL 60045",
    "addr:housenumber":"1640",
    "addr:postcode":"60045",
    "addr:street":"W Kennedy Rd",
    "iso:country":"US",
    "sg:address":"1640 W Kennedy Rd",
    "sg:city":"Lake Forest",
    "sg:classifiers":[
        {
            "category":"Professional",
            "subcategory":"Management & Consulting",
            "type":"Services"
        }
    ],
    "sg:phone":"+1 847 295 1040",
    "sg:postcode":"60045",
    "sg:province":"IL",
    "sg:tags":[
        "consultant",
        "business"
    ],
    "wof:name":"National Family Business Cncl",
    "wof:placetype":"venue"
},
  "geometry": {"coordinates":[-87.886093,42.24011],"type":"Point"}
}