{
  "type": "Feature",
  "properties": {
    "addr:full":"386 S 6th St Dundee IL 60118",
    "addr:housenumber":"386",
    "addr:postcode":"60118",
    "addr:street":"S 6Th St",
    "iso:country":"US",
    "sg:address":"386 S 6th St",
    "sg:city":"Dundee",
    "sg:classifiers":[
        {
            "category":"Restaurant",
            "type":"Food & Drink"
        }
    ],
    "sg:phone":"+1 847 426 8929",
    "sg:postcode":"60118",
    "sg:province":"IL",
    "wof:name":"Mc Donald's Restaurants",
    "wof:placetype":"venue"
},
  "geometry": {"coordinates":[-88.283908,42.095219],"type":"Point"}
}