{
  "type": "Feature",
  "properties": {
    "addr:full":"24981 N 1400 E Rd Cornell IL 61319",
    "addr:housenumber":"24981;1400",
    "addr:postcode":"61319",
    "addr:street":"N;E Rd",
    "iso:country":"US",
    "sg:address":"24981 N 1400 E Rd",
    "sg:city":"Cornell",
    "sg:classifiers":[
        {
            "category":"Manufacturing",
            "subcategory":"Pet Food",
            "type":"Manufacturing & Wholesale Goods"
        }
    ],
    "sg:phone":"+1 815 358 2301",
    "sg:postcode":"61319",
    "sg:province":"IL",
    "sg:tags":[
        "feed",
        "bird"
    ],
    "sg:website":"www.lafeber.com",
    "wof:name":"Lafeber Co",
    "wof:placetype":"venue"
},
  "geometry": {"coordinates":[-88.662977,40.986124],"type":"Point"}
}