{
  "type": "Feature",
  "properties": {
    "iso:country":"US",
    "sg:address":"4400 S Honore Street",
    "sg:city":"Chicago",
    "sg:classifiers":[
        {
            "category":"Food & Beverages",
            "subcategory":"Groceries & Convenience Stores",
            "type":"Retail Goods"
        }
    ],
    "sg:phone":"+1 773 247 3331",
    "sg:postcode":"60609",
    "sg:province":"IL",
    "wof:name":"De La Luz",
    "wof:placetype":"venue"
},
  "geometry": {"coordinates":[-87.67125299999999,41.813799],"type":"Point"}
}