{
  "type": "Feature",
  "properties": {
    "iso:country":"US",
    "sg:address":"109 N Main St",
    "sg:city":"Benld",
    "sg:classifiers":[
        {
            "category":"Government",
            "subcategory":"Post Office",
            "type":"Public Place"
        }
    ],
    "sg:phone":"+1 217 835 4525",
    "sg:postcode":"62009",
    "sg:province":"IL",
    "sg:tags":[
        "postal",
        "us"
    ],
    "wof:name":"US Post Office",
    "wof:placetype":"venue"
},
  "geometry": {"coordinates":[-89.80364899999999,39.093466],"type":"Point"}
}