{
  "type": "Feature",
  "properties": {
    "iso:country":"US",
    "sg:address":"4276 N Winnebago Rd",
    "sg:city":"Winnebago",
    "sg:classifiers":[
        {
            "category":"Personal",
            "type":"Services"
        },
        {
            "category":"Professional",
            "subcategory":"Art Services",
            "type":"Services"
        }
    ],
    "sg:phone":"+1 815 335 1317",
    "sg:postcode":"61088",
    "sg:province":"IL",
    "sg:tags":[
        "photography",
        "videography",
        "wedding"
    ],
    "wof:name":"Photo S Of The Heart",
    "wof:placetype":"venue"
},
  "geometry": {"coordinates":[-89.243394,42.312218],"type":"Point"}
}