{
  "type": "Feature",
  "properties": {
    "iso:country":"US",
    "sg:address":"1186 Dresden Dr",
    "sg:city":"Schaumburg",
    "sg:classifiers":[
        {
            "category":"Professional",
            "subcategory":"Computer Services",
            "type":"Services"
        }
    ],
    "sg:phone":"+1 847 496 5276",
    "sg:postcode":"60192",
    "sg:province":"IL",
    "sg:tags":[
        "consulting",
        "technology"
    ],
    "wof:name":"Nextek Systems Inc",
    "wof:placetype":"venue"
},
  "geometry": {"coordinates":[-88.10890000000001,42.099927],"type":"Point"}
}