{
  "type": "Feature",
  "properties": {
    "iso:country":"US",
    "sg:address":"926 N Shore Dr",
    "sg:city":"Lake Bluff",
    "sg:classifiers":[
        {
            "category":"Building & Trades",
            "subcategory":"Construction",
            "type":"Services"
        }
    ],
    "sg:phone":"+1 847 457 3909",
    "sg:postcode":"60044",
    "sg:province":"IL",
    "sg:tags":[
        "general",
        "contractor"
    ],
    "wof:name":"Riley Construction Co Inc",
    "wof:placetype":"venue"
},
  "geometry": {"coordinates":[-87.87284,42.272797],"type":"Point"}
}