{
  "type": "Feature",
  "properties": {
    "iso:country":"US",
    "sg:address":"1502 N Western Ave",
    "sg:city":"Chicago",
    "sg:classifiers":[
        {
            "category":"Restaurant",
            "type":"Food & Drink"
        }
    ],
    "sg:phone":"+1 773 486 4195",
    "sg:postcode":"60622",
    "sg:province":"IL",
    "sg:tags":[
        "mexican"
    ],
    "wof:name":"Taqueria Super Burrito",
    "wof:placetype":"venue"
},
  "geometry": {"coordinates":[-87.68724400000001,41.908535],"type":"Point"}
}