{
  "type": "Feature",
  "properties": {
    "iso:country":"US",
    "sg:address":"28835 N Herky Dr",
    "sg:city":"Lake Bluff",
    "sg:classifiers":[
        {
            "category":"Wholesale",
            "subcategory":"Hardware",
            "type":"Manufacturing & Wholesale Goods"
        }
    ],
    "sg:phone":"+1 847 362 9660",
    "sg:postcode":"60044",
    "sg:province":"IL",
    "sg:tags":[
        "purifying",
        "cleaning",
        "air"
    ],
    "wof:name":"Hastings Air Energy Control",
    "wof:placetype":"venue"
},
  "geometry": {"coordinates":[-87.904031,42.28188],"type":"Point"}
}