{
  "type": "Feature",
  "properties": {
    "addr:full":"4214 W Montrose Ave Chicago IL 60641",
    "addr:housenumber":"4214",
    "addr:postcode":"60641",
    "addr:street":"W Montrose Ave",
    "iso:country":"US",
    "sg:address":"4214 W Montrose Ave",
    "sg:city":"Chicago",
    "sg:classifiers":[
        {
            "category":"Insurance",
            "subcategory":"Insurance Agent",
            "type":"Services"
        }
    ],
    "sg:phone":"+1 773 545 2555",
    "sg:postcode":"60641",
    "sg:province":"IL",
    "wof:name":"Prudential",
    "wof:placetype":"venue"
},
  "geometry": {"coordinates":[-87.732721,41.960892],"type":"Point"}
}