{
  "type": "Feature",
  "properties": {
    "addr:full":"1117 S Hamlin Ave Park Ridge IL 60068",
    "addr:housenumber":"1117",
    "addr:postcode":"60068",
    "addr:street":"S Hamlin Ave",
    "iso:country":"US",
    "sg:address":"1117 S Hamlin Ave",
    "sg:city":"Park Ridge",
    "sg:classifiers":[
        {
            "category":"Professional",
            "subcategory":"Research",
            "type":"Services"
        }
    ],
    "sg:phone":"+1 847 825 4398",
    "sg:postcode":"60068",
    "sg:province":"IL",
    "sg:tags":[
        "firm",
        "marketing"
    ],
    "wof:name":"Chicago Document Company",
    "wof:placetype":"venue"
},
  "geometry": {"coordinates":[-87.850455,41.997612],"type":"Point"}
}