{
  "type": "Feature",
  "properties": {
    "addr:full":"5480 W 159th St Oak Forest IL 60452",
    "addr:housenumber":"5480",
    "addr:postcode":"60452",
    "addr:street":"W 159Th St",
    "iso:country":"US",
    "sg:address":"5480 W 159th St",
    "sg:city":"Oak Forest",
    "sg:classifiers":[
        {
            "category":"Insurance",
            "subcategory":"Health Insurance",
            "type":"Services"
        }
    ],
    "sg:phone":"+1 708 535 7600",
    "sg:postcode":"60452",
    "sg:province":"IL",
    "sg:tags":[
        "market"
    ],
    "sg:website":"www.capitolnutrition.com",
    "wof:name":"Capitol Discount Nutrition",
    "wof:placetype":"venue"
},
  "geometry": {"coordinates":[-87.753687,41.602917],"type":"Point"}
}