{
  "type": "Feature",
  "properties": {
    "addr:full":"310 Melvin Dr Northbrook IL 60062",
    "addr:housenumber":"310",
    "addr:postcode":"60062",
    "addr:street":"Melvin Dr",
    "iso:country":"US",
    "sg:address":"310 Melvin Dr",
    "sg:city":"Northbrook",
    "sg:classifiers":[
        {
            "category":"Real Estate",
            "subcategory":"Real Estate Services",
            "type":"Services"
        }
    ],
    "sg:phone":"+1 847 559 1581",
    "sg:postcode":"60062",
    "sg:province":"IL",
    "sg:tags":[
        "vacancy",
        "apartment",
        "rental",
        "finder",
        "listing"
    ],
    "wof:name":"Sanimar Decor Studio",
    "wof:placetype":"venue"
},
  "geometry": {"coordinates":[-87.850785,42.146738],"type":"Point"}
}