{
  "type": "Feature",
  "properties": {
    "iso:country":"US",
    "sg:address":"8102 W 119th St",
    "sg:city":"Palos Park",
    "sg:classifiers":[
        {
            "category":"Building & Trades",
            "subcategory":"Plumbing",
            "type":"Services"
        }
    ],
    "sg:phone":"+1 708 361 4490",
    "sg:postcode":"60464",
    "sg:province":"IL",
    "sg:tags":[
        "plumbing",
        "contractor"
    ],
    "wof:name":"R J OSullivan Plumbing Co",
    "wof:placetype":"venue"
},
  "geometry": {"coordinates":[-87.818335,41.674942],"type":"Point"}
}