{
  "type": "Feature",
  "properties": {
    "addr:full":"1275 N Prairie St Galesburg IL 61401",
    "addr:housenumber":"1275",
    "addr:postcode":"61401",
    "addr:street":"N Prairie St",
    "iso:country":"US",
    "sg:address":"1275 N Prairie St",
    "sg:city":"Galesburg",
    "sg:classifiers":[
        {
            "category":"Organizations",
            "subcategory":"Religious Organization",
            "type":"Services"
        }
    ],
    "sg:phone":"+1 309 341 3065",
    "sg:postcode":"61401",
    "sg:province":"IL",
    "sg:tags":[
        "clergy"
    ],
    "wof:name":"Siems Daniel Rev",
    "wof:placetype":"venue"
},
  "geometry": {"coordinates":[-90.36778099999999,40.963001],"type":"Point"}
}