{
  "type": "Feature",
  "properties": {
    "iso:country":"US",
    "sg:address":"101 S Hough St",
    "sg:city":"Barrington",
    "sg:classifiers":[
        {
            "category":"Professional",
            "subcategory":"Business Services",
            "type":"Services"
        }
    ],
    "sg:phone":"+1 847 382 7108",
    "sg:postcode":"60010",
    "sg:province":"IL",
    "wof:name":"Business Process Solutions",
    "wof:placetype":"venue"
},
  "geometry": {"coordinates":[-88.136038,42.153302],"type":"Point"}
}