{
  "type": "Feature",
  "properties": {
    "addr:full":"1456 W Elmdale Ave Chicago IL 60660",
    "addr:housenumber":"1456",
    "addr:postcode":"60660",
    "addr:street":"W Elmdale Ave",
    "iso:country":"US",
    "sg:address":"1456 W Elmdale Ave",
    "sg:city":"Chicago",
    "sg:classifiers":[
        {
            "category":"Wholesale",
            "subcategory":"Groceries",
            "type":"Manufacturing & Wholesale Goods"
        }
    ],
    "sg:phone":"+1 773 274 0958",
    "sg:postcode":"60660",
    "sg:province":"IL",
    "sg:tags":[
        "food",
        "product",
        "health"
    ],
    "wof:name":"American Herbal Products",
    "wof:placetype":"venue"
},
  "geometry": {"coordinates":[-87.66644100000001,41.990918],"type":"Point"}
}