{
  "type": "Feature",
  "properties": {
    "addr:full":"2219 Evergreen Ln Woodridge IL 60517",
    "addr:housenumber":"2219",
    "addr:postcode":"60517",
    "addr:street":"Evergreen Ln",
    "iso:country":"US",
    "sg:address":"2219 Evergreen Ln",
    "sg:city":"Woodridge",
    "sg:classifiers":[
        {
            "category":"Organizations",
            "subcategory":"Community Association",
            "type":"Services"
        }
    ],
    "sg:phone":"+1 630 985 7646",
    "sg:postcode":"60517",
    "sg:province":"IL",
    "wof:name":"Alpha Sigma Alpha Sororit",
    "wof:placetype":"venue"
},
  "geometry": {"coordinates":[-88.037278,41.744155],"type":"Point"}
}