{
  "type": "Feature",
  "properties": {
    "addr:full":"816 Randall Dr Donnellson IL 62012",
    "addr:housenumber":"816",
    "addr:postcode":"62012",
    "addr:street":"Randall Dr",
    "iso:country":"US",
    "sg:address":"816 Randall Dr",
    "sg:city":"Donnellson",
    "sg:classifiers":[
        {
            "category":"Building & Trades",
            "subcategory":"Construction",
            "type":"Services"
        }
    ],
    "sg:phone":"+1 217 537 3577",
    "sg:postcode":"62012",
    "sg:province":"IL",
    "sg:tags":[
        "contracting",
        "excavating",
        "general"
    ],
    "wof:name":"Alco Epuipment Rental Inc",
    "wof:placetype":"venue"
},
  "geometry": {"coordinates":[-90.14722999999999,39.033217],"type":"Point"}
}