{
  "type": "Feature",
  "properties": {
    "iso:country":"US",
    "sg:address":"1790 Westfield Plaza Pkwy",
    "sg:city":"Belleville",
    "sg:classifiers":[
        {
            "category":"Real Estate",
            "subcategory":"Real Estate Agent",
            "type":"Services"
        }
    ],
    "sg:phone":"+1 618 277 8261",
    "sg:postcode":"62223",
    "sg:province":"IL",
    "sg:tags":[
        "authorities",
        "housing"
    ],
    "wof:name":"St Clair Housing Auth Offices",
    "wof:placetype":"venue"
},
  "geometry": {"coordinates":[-90.05426199999999,38.539198],"type":"Point"}
}