{
  "type": "Feature",
  "properties": {
    "addr:full":"439 E State St Sycamore IL 60178",
    "addr:housenumber":"439",
    "addr:postcode":"60178",
    "addr:street":"E State St",
    "iso:country":"US",
    "sg:address":"439 E State St",
    "sg:city":"Sycamore",
    "sg:classifiers":[
        {
            "category":"Restaurant",
            "type":"Food & Drink"
        }
    ],
    "sg:menulink":"http://www.allmenus.com/il/sycamore/181092-wendys/menu/",
    "sg:phone":"+1 815 895 4855",
    "sg:postcode":"60178",
    "sg:province":"IL",
    "sg:tags":[
        "burger",
        "american",
        "soup"
    ],
    "wof:name":"Wendy's",
    "wof:placetype":"venue"
},
  "geometry": {"coordinates":[-88.678769,41.987649],"type":"Point"}
}