{
  "type": "Feature",
  "properties": {
    "iso:country":"US",
    "sg:address":"8702 S Roberts Rd",
    "sg:city":"Hickory Hills",
    "sg:classifiers":[
        {
            "category":"Autos & Motor Vehicles",
            "subcategory":"Fuel & Gas Station",
            "type":"Retail Goods"
        },
        {
            "category":"Personal",
            "type":"Services"
        }
    ],
    "sg:phone":"+1 708 599 8484",
    "sg:postcode":"60457",
    "sg:province":"IL",
    "sg:tags":[
        "towing"
    ],
    "sg:website":"www.marathon.com",
    "wof:name":"Alex's Marathon Full Service Station",
    "wof:placetype":"venue"
},
  "geometry": {"coordinates":[-87.81860399999999,41.7327],"type":"Point"}
}