{
  "type": "Feature",
  "properties": {
    "iso:country":"US",
    "sg:address":"6450 S Stony Island Ave",
    "sg:city":"Chicago",
    "sg:classifiers":[
        {
            "category":"Organizations",
            "subcategory":"Community Association",
            "type":"Services"
        }
    ],
    "sg:phone":"+1 773 288 3000",
    "sg:postcode":"60637",
    "sg:province":"IL",
    "wof:name":"We Can",
    "wof:placetype":"venue"
},
  "geometry": {"coordinates":[-87.586371,41.777836],"type":"Point"}
}