{
  "type": "Feature",
  "properties": {
    "addr:full":"206 Bright Ridge Dr Schaumburg IL 60194",
    "addr:housenumber":"206",
    "addr:postcode":"60194",
    "addr:street":"Bright Ridge Dr",
    "iso:country":"US",
    "sg:address":"206 Bright Ridge Dr",
    "sg:city":"Schaumburg",
    "sg:classifiers":[
        {
            "category":"Professional",
            "subcategory":"Accounting & Tax Preparation",
            "type":"Services"
        }
    ],
    "sg:phone":"+1 847 781 1606",
    "sg:postcode":"60194",
    "sg:province":"IL",
    "wof:name":"Professional Office Services I",
    "wof:placetype":"venue"
},
  "geometry": {"coordinates":[-88.068348,42.028757],"type":"Point"}
}