{
  "type": "Feature",
  "properties": {
    "iso:country":"US",
    "sg:address":"7150 S Halsted St",
    "sg:city":"Chicago",
    "sg:classifiers":[
        {
            "category":"Personal",
            "type":"Services"
        }
    ],
    "sg:phone":"+1 773 874 1616",
    "sg:postcode":"60621",
    "sg:province":"IL",
    "sg:tags":[
        "mover"
    ],
    "wof:name":"Smith Movers Inc",
    "wof:placetype":"venue"
},
  "geometry": {"coordinates":[-87.644402,41.763699],"type":"Point"}
}