{
  "type": "Feature",
  "properties": {
    "addr:full":"3055 W Lawrence Ave Chicago IL 60625",
    "addr:housenumber":"3055",
    "addr:postcode":"60625",
    "addr:street":"W Lawrence Ave",
    "iso:country":"US",
    "sg:address":"3055 W Lawrence Ave",
    "sg:city":"Chicago",
    "sg:classifiers":[
        {
            "category":"Food & Beverages",
            "subcategory":"Meat & Fish",
            "type":"Retail Goods"
        }
    ],
    "sg:phone":"+1 773 866 2980",
    "sg:postcode":"60625",
    "sg:province":"IL",
    "sg:tags":[
        "seafood",
        "market"
    ],
    "wof:name":"Lee Sea Food Company",
    "wof:placetype":"venue"
},
  "geometry": {"coordinates":[-87.705704,41.968399],"type":"Point"}
}