{
  "type": "Feature",
  "properties": {
    "addr:full":"221 Turner Ln Wilmington IL 60481",
    "addr:housenumber":"221",
    "addr:postcode":"60481",
    "addr:street":"Turner Ln",
    "iso:country":"US",
    "sg:address":"221 Turner Ln",
    "sg:city":"Wilmington",
    "sg:classifiers":[
        {
            "category":"Shopping",
            "subcategory":"Gifts & Souvenirs",
            "type":"Retail Goods"
        }
    ],
    "sg:phone":"+1   ",
    "sg:postcode":"60481",
    "sg:province":"IL",
    "wof:name":"K & D Ceramics",
    "wof:placetype":"venue"
},
  "geometry": {"coordinates":[-88.13695800000001,41.308404],"type":"Point"}
}