{
  "type": "Feature",
  "properties": {
    "addr:full":"1709 W Roosevelt Rd Broadview IL 60155",
    "addr:housenumber":"1709",
    "addr:postcode":"60155",
    "addr:street":"W Roosevelt Rd",
    "iso:country":"US",
    "sg:address":"1709 W Roosevelt Rd",
    "sg:city":"Broadview",
    "sg:classifiers":[
        {
            "category":"Shopping",
            "subcategory":"Clothing, Apparel, & Fashions",
            "type":"Retail Goods"
        }
    ],
    "sg:phone":"+1 708 865 8177",
    "sg:postcode":"60155",
    "sg:province":"IL",
    "sg:tags":[
        "accessory"
    ],
    "wof:name":"Fashion Ebonie",
    "wof:placetype":"venue"
},
  "geometry": {"coordinates":[-87.8535,41.863899],"type":"Point"}
}