{
  "type": "Feature",
  "properties": {
    "addr:full":"400 Mix St Oregon IL 61061",
    "addr:housenumber":"400",
    "addr:postcode":"61061",
    "addr:street":"Mix St",
    "iso:country":"US",
    "sg:address":"400 Mix St",
    "sg:city":"Oregon",
    "sg:classifiers":[
        {
            "category":"Travel",
            "subcategory":"Hotels & Motels",
            "type":"Entertainment"
        }
    ],
    "sg:phone":"+1 815 732 2067",
    "sg:postcode":"61061",
    "sg:province":"IL",
    "sg:tags":[
        "breakfast",
        "accommodation",
        "bed"
    ],
    "sg:website":"www.pinehillbb.com",
    "wof:name":"Pinehill Inn",
    "wof:placetype":"venue"
},
  "geometry": {"coordinates":[-89.339996,42.017362],"type":"Point"}
}