{
  "type": "Feature",
  "properties": {
    "iso:country":"US",
    "sg:address":"703 S Neil St",
    "sg:city":"Champaign",
    "sg:classifiers":[
        {
            "category":"Restaurant",
            "type":"Food & Drink"
        }
    ],
    "sg:menulink":"http://www.allmenus.com/il/champaign-city/124617-quiznos-sub/menu/",
    "sg:phone":"+1 217 355 5750",
    "sg:postcode":"61820",
    "sg:province":"IL",
    "sg:tags":[
        "sandwich",
        "salad",
        "soup",
        "american",
        "wrap",
        "chicken",
        "hoagy"
    ],
    "wof:name":"Quiznos Sub",
    "wof:placetype":"venue"
},
  "geometry": {"coordinates":[-88.24351,40.10895],"type":"Point"}
}