{
  "type": "Feature",
  "properties": {
    "iso:country":"US",
    "sg:address":"17060 S Park Ave",
    "sg:city":"Harvey",
    "sg:classifiers":[
        {
            "category":"Health Services",
            "subcategory":"Doctor",
            "type":"Services"
        }
    ],
    "sg:phone":"+1 708 331 9200",
    "sg:postcode":"60426",
    "sg:province":"IL",
    "sg:tags":[
        "practice",
        "family"
    ],
    "wof:name":"Advocate Health Centers",
    "wof:placetype":"venue"
},
  "geometry": {"coordinates":[-87.663101,41.6119],"type":"Point"}
}