{
  "type": "Feature",
  "properties": {
    "iso:country":"US",
    "sg:address":"2301 James St",
    "sg:city":"Lawrenceville",
    "sg:classifiers":[
        {
            "category":"Shopping",
            "subcategory":"Discount & Variety Stores",
            "type":"Retail Goods"
        }
    ],
    "sg:phone":"+1   ",
    "sg:postcode":"62439",
    "sg:province":"IL",
    "wof:name":"Dollar General",
    "wof:placetype":"venue"
},
  "geometry": {"coordinates":[-87.69837099999999,38.726196],"type":"Point"}
}