{
  "type": "Feature",
  "properties": {
    "iso:country":"US",
    "sg:address":"101 W 2nd St",
    "sg:city":"Dixon",
    "sg:classifiers":[
        {
            "category":"Organizations",
            "subcategory":"Professional Association",
            "type":"Services"
        }
    ],
    "sg:phone":"+1 815 284 3361",
    "sg:postcode":"61021",
    "sg:province":"IL",
    "sg:tags":[
        "chambers",
        "commerce"
    ],
    "wof:name":"Chamber Of Commerce",
    "wof:placetype":"venue"
},
  "geometry": {"coordinates":[-89.482275,41.842658],"type":"Point"}
}