{
  "type": "Feature",
  "properties": {
    "addr:full":"14315 108th Ave Orland Park IL 60467",
    "addr:housenumber":"14315",
    "addr:postcode":"60467",
    "addr:street":"108Th Ave",
    "iso:country":"US",
    "sg:address":"14315 108th Ave",
    "sg:city":"Orland Park",
    "sg:classifiers":[
        {
            "category":"Professional",
            "subcategory":"Lawyer & Legal Services",
            "type":"Services"
        }
    ],
    "sg:phone":"+1 708 403 4900",
    "sg:postcode":"60467",
    "sg:province":"IL",
    "sg:tags":[
        "attorney",
        "practice",
        "general"
    ],
    "wof:name":"Brunell Alan Atty At Law",
    "wof:placetype":"venue"
},
  "geometry": {"coordinates":[-87.88260200000001,41.628772],"type":"Point"}
}