{
  "type": "Feature",
  "properties": {
    "iso:country":"US",
    "sg:address":"750 S Blackhawk Blvd",
    "sg:city":"Rockton",
    "sg:classifiers":[
        {
            "category":"Professional",
            "subcategory":"Computer Services",
            "type":"Services"
        },
        {
            "category":"Wholesale",
            "subcategory":"Computers",
            "type":"Manufacturing & Wholesale Goods"
        }
    ],
    "sg:phone":"+1 815 624 4748",
    "sg:postcode":"61072",
    "sg:province":"IL",
    "sg:tags":[
        "equipment",
        "software"
    ],
    "wof:name":"Hill Technical Service",
    "wof:placetype":"venue"
},
  "geometry": {"coordinates":[-89.078829,42.445298],"type":"Point"}
}