{
  "type": "Feature",
  "properties": {
    "iso:country":"US",
    "sg:address":"6135 N Meade Ave Apt 1",
    "sg:city":"Chicago",
    "sg:classifiers":[
        {
            "category":"Transit Center",
            "subcategory":"Freight",
            "type":"Transportation"
        },
        {
            "category":"Freight",
            "type":"Transportation"
        }
    ],
    "sg:phone":"+1 773 858 2524",
    "sg:postcode":"60646",
    "sg:province":"IL",
    "sg:tags":[
        "local",
        "trucking-motor",
        "trucking"
    ],
    "wof:name":"Otfinow Trans Inc",
    "wof:placetype":"venue"
},
  "geometry": {"coordinates":[-87.780355,41.992704],"type":"Point"}
}