{
  "type": "Feature",
  "properties": {
    "iso:country":"US",
    "sg:address":"112 W 87th Street",
    "sg:city":"Chicago",
    "sg:classifiers":[
        {
            "category":"Shopping",
            "subcategory":"Hobbies, Toys, & Games",
            "type":"Retail Goods"
        },
        {
            "category":"Cinema",
            "subcategory":"Movie Rental",
            "type":"Entertainment"
        }
    ],
    "sg:phone":"+1 773 487 6960",
    "sg:postcode":"60620",
    "sg:province":"IL",
    "sg:tags":[
        "video",
        "supply"
    ],
    "sg:website":"www.gamestop.com",
    "wof:name":"Gamestop",
    "wof:placetype":"venue"
},
  "geometry": {"coordinates":[-87.62742799999999,41.736304],"type":"Point"}
}