{
  "type": "Feature",
  "properties": {
    "addr:full":"716 N Wells St Chicago IL 60610",
    "addr:housenumber":"716",
    "addr:postcode":"60610",
    "addr:street":"N Wells St",
    "iso:country":"US",
    "sg:address":"716 N Wells St",
    "sg:city":"Chicago",
    "sg:classifiers":[
        {
            "category":"Real Estate",
            "subcategory":"Architect",
            "type":"Services"
        }
    ],
    "sg:phone":"+1 312 943 7300",
    "sg:postcode":"60610",
    "sg:province":"IL",
    "wof:name":"Clark John W Arch",
    "wof:placetype":"venue"
},
  "geometry": {"coordinates":[-87.63400300000001,41.8955],"type":"Point"}
}