{
  "type": "Feature",
  "properties": {
    "addr:full":"1550 Glen Rock Ave Waukegan IL 60085",
    "addr:housenumber":"1550",
    "addr:postcode":"60085",
    "addr:street":"Glen Rock Ave",
    "iso:country":"US",
    "sg:address":"1550 Glen Rock Ave",
    "sg:city":"Waukegan",
    "sg:classifiers":[
        {
            "category":"Autos & Motor Vehicles",
            "subcategory":"Fuel & Gas Station",
            "type":"Retail Goods"
        }
    ],
    "sg:phone":"+1   ",
    "sg:postcode":"60085",
    "sg:province":"IL",
    "sg:tags":[
        "grocery",
        "station",
        "gasoline"
    ],
    "wof:name":"Speedway Superamerica LLC",
    "wof:placetype":"venue"
},
  "geometry": {"coordinates":[-87.850595,42.351556],"type":"Point"}
}