{
  "type": "Feature",
  "properties": {
    "iso:country":"US",
    "sg:address":"6342 Shuler Rd",
    "sg:city":"Salem",
    "sg:classifiers":[
        {
            "category":"Retail",
            "subcategory":"Animal Services",
            "type":"Services"
        }
    ],
    "sg:phone":"+1 618 548 0303",
    "sg:postcode":"62881",
    "sg:province":"IL",
    "sg:tags":[
        "breeder",
        "bloodhound"
    ],
    "wof:name":"Shuler Bloodhounds",
    "wof:placetype":"venue"
},
  "geometry": {"coordinates":[-88.99104,38.692732],"type":"Point"}
}