{
  "type": "Feature",
  "properties": {
    "addr:full":"750 S Halsted Chicago IL 60607",
    "addr:housenumber":"750",
    "addr:postcode":"60607",
    "addr:street":"S Halsted",
    "iso:country":"US",
    "sg:address":"750 S Halsted",
    "sg:city":"Chicago",
    "sg:classifiers":[
        {
            "category":"Restaurant",
            "type":"Food & Drink"
        }
    ],
    "sg:postcode":"60607",
    "sg:province":"IL",
    "wof:name":"Burrito Bravo",
    "wof:placetype":"venue"
},
  "geometry": {"coordinates":[-87.64751,41.871914],"type":"Point"}
}