{
  "type": "Feature",
  "properties": {
    "iso:country":"US",
    "sg:address":"907 W Marketview Dr Ste 10",
    "sg:city":"Champaign",
    "sg:classifiers":[
        {
            "category":"Professional",
            "subcategory":"Computer Services",
            "type":"Services"
        }
    ],
    "sg:phone":"+1 217 778 8203",
    "sg:postcode":"61822",
    "sg:province":"IL",
    "sg:tags":[
        "repair"
    ],
    "sg:website":"www.doctormicro.com",
    "wof:name":"Doctor Micro",
    "wof:placetype":"venue"
},
  "geometry": {"coordinates":[-88.25807,40.137883],"type":"Point"}
}