{
  "type": "Feature",
  "properties": {
    "iso:country":"US",
    "sg:address":"3650 N Recreation Dr",
    "sg:city":"Chicago",
    "sg:classifiers":[
        {
            "category":"Shopping",
            "subcategory":"Bicycles & Sporting Goods",
            "type":"Retail Goods"
        },
        {
            "category":"Sports & Exercise",
            "subcategory":"Bicycle Rental",
            "type":"Entertainment"
        }
    ],
    "sg:phone":"+1 630 886 6188",
    "sg:postcode":"60613",
    "sg:province":"IL",
    "sg:tags":[
        "bike"
    ],
    "sg:website":"www.lakeshorebike.com",
    "wof:name":"Lakeshore Bike",
    "wof:placetype":"venue"
},
  "geometry": {"coordinates":[-87.64435,41.95288],"type":"Point"}
}