{
  "type": "Feature",
  "properties": {
    "iso:country":"US",
    "sg:address":"2400 Owens Ln",
    "sg:city":"Brighton",
    "sg:classifiers":[
        {
            "category":"Retail",
            "subcategory":"Animal Services",
            "type":"Services"
        }
    ],
    "sg:phone":"+1 618 372 3837",
    "sg:postcode":"62012",
    "sg:province":"IL",
    "sg:tags":[
        "boarding",
        "training",
        "pet",
        "s",
        "grooming",
        "kennel"
    ],
    "wof:name":"Rowens Kennels",
    "wof:placetype":"venue"
},
  "geometry": {"coordinates":[-90.121059,39.034137],"type":"Point"}
}