{
  "type": "Feature",
  "properties": {
    "addr:full":"510 N Arbor Dr Round Lake IL 60073",
    "addr:housenumber":"510",
    "addr:postcode":"60073",
    "addr:street":"N Arbor Dr",
    "iso:country":"US",
    "sg:address":"510 N Arbor Dr",
    "sg:city":"Round Lake",
    "sg:classifiers":[
        {
            "category":"Building & Trades",
            "subcategory":"Construction",
            "type":"Services"
        }
    ],
    "sg:phone":"+1 847 740 2606",
    "sg:postcode":"60073",
    "sg:province":"IL",
    "sg:tags":[
        "contractor"
    ],
    "wof:name":"Strictly Stone",
    "wof:placetype":"venue"
},
  "geometry": {"coordinates":[-88.07237499999999,42.357715],"type":"Point"}
}