{
  "type": "Feature",
  "properties": {
    "iso:country":"US",
    "sg:address":"5717 W 120th St",
    "sg:city":"Alsip",
    "sg:classifiers":[
        {
            "category":"Building & Trades",
            "subcategory":"Plumbing",
            "type":"Services"
        }
    ],
    "sg:phone":"+1 708 597 9663",
    "sg:postcode":"60803",
    "sg:province":"IL",
    "sg:tags":[
        "contractor"
    ],
    "sg:website":"www.birkplumbinginc.com",
    "wof:name":"Birk Plumbing Inc",
    "wof:placetype":"venue"
},
  "geometry": {"coordinates":[-87.76067999999999,41.675034],"type":"Point"}
}