{
  "type": "Feature",
  "properties": {
    "addr:full":"1250 N Convent St Bourbonnais IL 60914",
    "addr:housenumber":"1250",
    "addr:postcode":"60914",
    "addr:street":"N Convent St",
    "iso:country":"US",
    "sg:address":"1250 N Convent St",
    "sg:city":"Bourbonnais",
    "sg:classifiers":[
        {
            "category":"Building & Trades",
            "subcategory":"Construction",
            "type":"Services"
        }
    ],
    "sg:phone":"+1 815 802 0433",
    "sg:postcode":"60914",
    "sg:province":"IL",
    "sg:tags":[
        "general",
        "contractor"
    ],
    "wof:name":"Don Daly Construction Co",
    "wof:placetype":"venue"
},
  "geometry": {"coordinates":[-87.87542500000001,41.175431],"type":"Point"}
}