{
  "type": "Feature",
  "properties": {
    "addr:full":"1108 Main St Carterville IL 62918",
    "addr:housenumber":"1108",
    "addr:postcode":"62918",
    "addr:street":"Main St",
    "iso:country":"US",
    "sg:address":"1108 Main St",
    "sg:city":"Carterville",
    "sg:classifiers":[
        {
            "category":"Farming",
            "subcategory":"Farm",
            "type":"Manufacturing & Wholesale Goods"
        }
    ],
    "sg:phone":"+1 618 985 9904",
    "sg:postcode":"62918",
    "sg:province":"IL",
    "sg:tags":[
        "crop",
        "general"
    ],
    "wof:name":"McDannel Farms",
    "wof:placetype":"venue"
},
  "geometry": {"coordinates":[-89.06775500000001,37.75105],"type":"Point"}
}