{
  "type": "Feature",
  "properties": {
    "addr:full":"4315 E State St Rockford IL 61108",
    "addr:housenumber":"4315",
    "addr:postcode":"61108",
    "addr:street":"E State St",
    "iso:country":"US",
    "sg:address":"4315 E State St",
    "sg:city":"Rockford",
    "sg:classifiers":[
        {
            "category":"Manufacturing",
            "subcategory":"Printing",
            "type":"Manufacturing & Wholesale Goods"
        }
    ],
    "sg:phone":"+1 815 395 8393",
    "sg:postcode":"61108",
    "sg:province":"IL",
    "sg:tags":[
        "newspaper"
    ],
    "wof:name":"American Classifieds",
    "wof:placetype":"venue"
},
  "geometry": {"coordinates":[-89.036214,42.265499],"type":"Point"}
}