{
  "type": "Feature",
  "properties": {
    "iso:country":"US",
    "sg:address":"11 Bowlby Rd",
    "sg:city":"De Soto",
    "sg:phone":"+1 618 867 2208",
    "sg:postcode":"62924",
    "sg:province":"IL",
    "sg:tags":[
        "farm",
        "grain"
    ],
    "wof:name":"Robert G Bowlby",
    "wof:placetype":"venue"
},
  "geometry": {"coordinates":[-89.25429099999999,37.804266],"type":"Point"}
}