{
  "type": "Feature",
  "properties": {
    "iso:country":"US",
    "sg:address":"1107 Asbury Farms Cc Ct",
    "sg:city":"Normal",
    "sg:classifiers":[
        {
            "category":"Professional",
            "subcategory":"Art Services",
            "type":"Services"
        }
    ],
    "sg:phone":"+1 309 452 7772",
    "sg:postcode":"61761",
    "sg:province":"IL",
    "sg:tags":[
        "interior",
        "designer",
        "decorator"
    ],
    "wof:name":"Pamela S Interior",
    "wof:placetype":"venue"
},
  "geometry": {"coordinates":[-88.96433500000001,40.543415],"type":"Point"}
}