{
  "type": "Feature",
  "properties": {
    "iso:country":"US",
    "sg:address":"11 E Golf Rd",
    "sg:city":"Des Plaines",
    "sg:classifiers":[
        {
            "category":"Retail",
            "subcategory":"Veterinary Services",
            "type":"Services"
        }
    ],
    "sg:phone":"+1 847 699 8387",
    "sg:postcode":"60016",
    "sg:province":"IL",
    "sg:tags":[
        "hospital",
        "veterinarian"
    ],
    "wof:name":"Aberdeen Animal Hospital PC",
    "wof:placetype":"venue"
},
  "geometry": {"coordinates":[-87.91943499999999,42.049038],"type":"Point"}
}