{
  "type": "Feature",
  "properties": {
    "addr:full":"2950 Commerce St Franklin Park IL 60131",
    "addr:housenumber":"2950",
    "addr:postcode":"60131",
    "addr:street":"Commerce St",
    "iso:country":"US",
    "sg:address":"2950 Commerce St",
    "sg:city":"Franklin Park",
    "sg:classifiers":[
        {
            "category":"Manufacturing",
            "subcategory":"Metals",
            "type":"Manufacturing & Wholesale Goods"
        }
    ],
    "sg:phone":"+1 847 455 9030",
    "sg:postcode":"60131",
    "sg:province":"IL",
    "sg:tags":[
        "mfg",
        "repair",
        "metalwork",
        "sheet",
        "welding"
    ],
    "wof:name":"Allrite Sheetmetal Inc",
    "wof:placetype":"venue"
},
  "geometry": {"coordinates":[-87.85844299999999,41.931666],"type":"Point"}
}