{
  "type": "Feature",
  "properties": {
    "addr:full":"1711 Creve Coeur St La Salle IL 61301",
    "addr:housenumber":"1711",
    "addr:postcode":"61301",
    "addr:street":"Creve Coeur St",
    "iso:country":"US",
    "sg:address":"1711 Creve Coeur St",
    "sg:city":"La Salle",
    "sg:classifiers":[
        {
            "category":"Shopping",
            "subcategory":"Gifts & Souvenirs",
            "type":"Retail Goods"
        }
    ],
    "sg:phone":"+1   ",
    "sg:postcode":"61301",
    "sg:province":"IL",
    "wof:name":"The Wedding Chapel",
    "wof:placetype":"venue"
},
  "geometry": {"coordinates":[-89.10478500000001,41.345981],"type":"Point"}
}