{
  "type": "Feature",
  "properties": {
    "iso:country":"US",
    "sg:address":"254 May Ave",
    "sg:city":"Glen Ellyn",
    "sg:classifiers":[
        {
            "category":"Professional",
            "subcategory":"Management & Consulting",
            "type":"Services"
        }
    ],
    "sg:phone":"+1 630 790 3817",
    "sg:postcode":"60137",
    "sg:province":"IL",
    "sg:tags":[
        "business"
    ],
    "wof:name":"Impact Solutions",
    "wof:placetype":"venue"
},
  "geometry": {"coordinates":[-88.051467,41.869259],"type":"Point"}
}