{
  "type": "Feature",
  "properties": {
    "addr:full":"1181 N Raddant Rd Batavia IL 60510",
    "addr:housenumber":"1181",
    "addr:postcode":"60510",
    "addr:street":"N Raddant Rd",
    "iso:country":"US",
    "sg:address":"1181 N Raddant Rd",
    "sg:city":"Batavia",
    "sg:classifiers":[
        {
            "category":"Manufacturing",
            "subcategory":"Tools & Machinery",
            "type":"Manufacturing & Wholesale Goods"
        }
    ],
    "sg:phone":"+1 630 879 2400",
    "sg:postcode":"60510",
    "sg:province":"IL",
    "sg:tags":[
        "assembly",
        "mfg"
    ],
    "sg:website":"www.schaffertool.com",
    "wof:name":"Schaffer Tool & Design Inc",
    "wof:placetype":"venue"
},
  "geometry": {"coordinates":[-88.293176,41.862578],"type":"Point"}
}