{
  "type": "Feature",
  "properties": {
    "iso:country":"US",
    "sg:address":"5248 Wilcox Lake Rd",
    "sg:city":"Chandlerville",
    "sg:classifiers":[
        {
            "category":"Farming",
            "subcategory":"Farm",
            "type":"Manufacturing & Wholesale Goods"
        }
    ],
    "sg:phone":"+1 217 458 2826",
    "sg:postcode":"62627",
    "sg:province":"IL",
    "wof:name":"Wilcox Farm Partners",
    "wof:placetype":"venue"
},
  "geometry": {"coordinates":[-90.250767,40.072479],"type":"Point"}
}