{
  "type": "Feature",
  "properties": {
    "iso:country":"US",
    "sg:address":"2334 W Lawrence Avenue",
    "sg:city":"Chicago",
    "sg:classifiers":[
        {
            "category":"Health Services",
            "subcategory":"Health Practitioner",
            "type":"Services"
        }
    ],
    "sg:phone":"+1 773 769 6102",
    "sg:postcode":"60625",
    "sg:province":"IL",
    "sg:tags":[
        "therapy",
        "physical"
    ],
    "wof:name":"Integrative Therapy",
    "wof:placetype":"venue"
},
  "geometry": {"coordinates":[-87.68750900000001,41.968626],"type":"Point"}
}