{
  "type": "Feature",
  "properties": {
    "iso:country":"US",
    "sg:address":"15760 Willow Brook Rd",
    "sg:city":"South Beloit",
    "sg:classifiers":[
        {
            "category":"Manufacturing",
            "subcategory":"Tools & Machinery",
            "type":"Manufacturing & Wholesale Goods"
        }
    ],
    "sg:phone":"+1 815 389 4000",
    "sg:postcode":"61080",
    "sg:province":"WI",
    "sg:tags":[
        "machine",
        "shop"
    ],
    "sg:website":"www.vibracraft.com",
    "wof:name":"Vibracraft",
    "wof:placetype":"venue"
},
  "geometry": {"coordinates":[-89.00027,42.491647],"type":"Point"}
}