{
  "type": "Feature",
  "properties": {
    "addr:full":"1218 W Williams St Danville IL 61832",
    "addr:housenumber":"1218",
    "addr:postcode":"61832",
    "addr:street":"W Williams St",
    "iso:country":"US",
    "sg:address":"1218 W Williams St",
    "sg:city":"Danville",
    "sg:classifiers":[
        {
            "category":"Organizations",
            "subcategory":"Religious Organization",
            "type":"Services"
        }
    ],
    "sg:phone":"+1 217 446 5591",
    "sg:postcode":"61832",
    "sg:province":"IL",
    "sg:tags":[
        "church"
    ],
    "wof:name":"Evangelical Church",
    "wof:placetype":"venue"
},
  "geometry": {"coordinates":[-87.64743900000001,40.134475],"type":"Point"}
}