{
  "type": "Feature",
  "properties": {
    "iso:country":"US",
    "sg:address":"2409 Belvidere Rd",
    "sg:city":"Waukegan",
    "sg:classifiers":[
        {
            "category":"Recreation",
            "type":"Entertainment"
        }
    ],
    "sg:phone":"+1 847 249 5043",
    "sg:postcode":"60085",
    "sg:province":"IL",
    "sg:tags":[
        "park",
        "amusement"
    ],
    "wof:name":"Belvidere Arcade",
    "wof:placetype":"venue"
},
  "geometry": {"coordinates":[-87.857357,42.350633],"type":"Point"}
}