{
  "type": "Feature",
  "properties": {
    "iso:country":"US",
    "sg:address":"1450 30th Ave",
    "sg:city":"East Moline",
    "sg:classifiers":[
        {
            "category":"Education",
            "subcategory":"Preschool",
            "type":"Public Place"
        },
        {
            "category":"Education",
            "subcategory":"School",
            "type":"Public Place"
        }
    ],
    "sg:phone":"+1 309 792 0755",
    "sg:postcode":"61244",
    "sg:province":"IL",
    "sg:tags":[
        "elementary"
    ],
    "sg:website":"www.stjohnsem.org",
    "wof:name":"St John's Lutheran Church & Ctr For Early Learning",
    "wof:placetype":"venue"
},
  "geometry": {"coordinates":[-90.4282,41.500599],"type":"Point"}
}