{
  "type": "Feature",
  "properties": {
    "addr:full":"9270 Joliet Rd Ste 600 Hodgkins IL 60525",
    "addr:housenumber":"9270",
    "addr:postcode":"60525",
    "addr:street":"Joliet Rd Ste 600",
    "iso:country":"US",
    "sg:address":"9270 Joliet Rd Ste 600",
    "sg:city":"Hodgkins",
    "sg:classifiers":[
        {
            "category":"Cinema",
            "subcategory":"Movie Rental",
            "type":"Entertainment"
        }
    ],
    "sg:phone":"+1 708 485 9400",
    "sg:postcode":"60525",
    "sg:province":"IL",
    "sg:tags":[
        "game",
        "video"
    ],
    "wof:name":"Play N Trade",
    "wof:placetype":"venue"
},
  "geometry": {"coordinates":[-87.854215,41.784862],"type":"Point"}
}