{
  "type": "Feature",
  "properties": {
    "iso:country":"US",
    "sg:address":"429 Texas Blvd",
    "sg:city":"Bethalto",
    "sg:classifiers":[
        {
            "category":"Building & Trades",
            "subcategory":"Cleaning & Sanitation",
            "type":"Services"
        },
        {
            "category":"Retail",
            "subcategory":"Repair Shop",
            "type":"Services"
        }
    ],
    "sg:phone":"+1 618 377 0219",
    "sg:postcode":"62010",
    "sg:province":"IL",
    "sg:tags":[
        "janitor"
    ],
    "wof:name":"All Star Cleaning Team",
    "wof:placetype":"venue"
},
  "geometry": {"coordinates":[-90.046373,38.905607],"type":"Point"}
}