{
  "type": "Feature",
  "properties": {
    "addr:full":"521 Lincoln Ave Calumet City IL 60409",
    "addr:housenumber":"521",
    "addr:postcode":"60409",
    "addr:street":"Lincoln Ave",
    "iso:country":"US",
    "sg:address":"521 Lincoln Ave",
    "sg:city":"Calumet City",
    "sg:classifiers":[
        {
            "category":"Food & Beverages",
            "subcategory":"Groceries & Convenience Stores",
            "type":"Retail Goods"
        }
    ],
    "sg:phone":"+1 708 832 0258",
    "sg:postcode":"60409",
    "sg:province":"IL",
    "wof:name":"Humberto Orozco",
    "wof:placetype":"venue"
},
  "geometry": {"coordinates":[-87.53218699999999,41.621333],"type":"Point"}
}