{
  "type": "Feature",
  "properties": {
    "iso:country":"US",
    "sg:address":"2820 State St",
    "sg:city":"Chester",
    "sg:classifiers":[
        {
            "category":"Travel",
            "subcategory":"Bed & Breakfast",
            "type":"Entertainment"
        }
    ],
    "sg:phone":"+1 618 826 3677",
    "sg:postcode":"62233",
    "sg:province":"IL",
    "sg:tags":[
        "house"
    ],
    "wof:name":"Stephanie A Lockhart",
    "wof:placetype":"venue"
},
  "geometry": {"coordinates":[-89.79446299999999,37.935688],"type":"Point"}
}