{
  "type": "Feature",
  "properties": {
    "iso:country":"US",
    "sg:address":"112 E Main St",
    "sg:city":"Belleville",
    "sg:classifiers":[
        {
            "category":"Shopping",
            "subcategory":"Hobbies, Toys, & Games",
            "type":"Retail Goods"
        }
    ],
    "sg:phone":"+1 618 277 9278",
    "sg:postcode":"62220",
    "sg:province":"IL",
    "sg:tags":[
        "craft",
        "supply"
    ],
    "wof:name":"Ben's Floral & Crafts",
    "wof:placetype":"venue"
},
  "geometry": {"coordinates":[-89.981618,38.513536],"type":"Point"}
}