{
  "type": "Feature",
  "properties": {
    "addr:full":"2101 E 71st Chicago IL 60607",
    "addr:housenumber":"2101",
    "addr:postcode":"60607",
    "addr:street":"E 71St",
    "iso:country":"US",
    "sg:address":"2101 E 71st",
    "sg:city":"Chicago",
    "sg:classifiers":[
        {
            "category":"Home & Garden",
            "subcategory":"Hardware",
            "type":"Retail Goods"
        }
    ],
    "sg:phone":"+1 773 955 9600",
    "sg:postcode":"60607",
    "sg:province":"IL",
    "sg:tags":[
        "store"
    ],
    "wof:name":"Ace Hardware Stores",
    "wof:placetype":"venue"
},
  "geometry": {"coordinates":[-87.656932,41.873792],"type":"Point"}
}