{
  "type": "Feature",
  "properties": {
    "addr:full":"6956 Ogden Ave Berwyn IL 60402",
    "addr:housenumber":"6956",
    "addr:postcode":"60402",
    "addr:street":"Ogden Ave",
    "iso:country":"US",
    "sg:address":"6956 Ogden Ave",
    "sg:city":"Berwyn",
    "sg:classifiers":[
        {
            "category":"Fast Food",
            "type":"Food & Drink"
        },
        {
            "category":"Restaurant",
            "type":"Food & Drink"
        }
    ],
    "sg:phone":"+1 708 749 4747",
    "sg:postcode":"60402",
    "sg:province":"IL",
    "sg:tags":[
        "mexican"
    ],
    "sg:website":"www.tacobell.com",
    "wof:name":"Taco Bell",
    "wof:placetype":"venue"
},
  "geometry": {"coordinates":[-87.797096,41.825699],"type":"Point"}
}