{
  "type": "Feature",
  "properties": {
    "iso:country":"US",
    "sg:address":"546 W 80th St",
    "sg:city":"Chicago",
    "sg:classifiers":[
        {
            "category":"Train Station",
            "subcategory":"Rail",
            "type":"Transportation"
        }
    ],
    "sg:phone":"+1 773 224 1258",
    "sg:postcode":"60620",
    "sg:province":"IL",
    "sg:tags":[
        "railroad"
    ],
    "wof:name":"Belt Railway Co",
    "wof:placetype":"venue"
},
  "geometry": {"coordinates":[-87.63779700000001,41.748904],"type":"Point"}
}