{
  "type": "Feature",
  "properties": {
    "iso:country":"US",
    "sg:address":"1608 W Main St",
    "sg:city":"Teutopolis",
    "sg:classifiers":[
        {
            "category":"Retail",
            "subcategory":"Auto Repair",
            "type":"Services"
        }
    ],
    "sg:phone":"+1 217 857 3196",
    "sg:postcode":"62467",
    "sg:province":"IL",
    "sg:tags":[
        "truck"
    ],
    "sg:website":"www.ddssales.com",
    "wof:name":"Dale's Diesel Svc",
    "wof:placetype":"venue"
},
  "geometry": {"coordinates":[-88.490862,39.128902],"type":"Point"}
}