{
  "type": "Feature",
  "properties": {
    "addr:full":"5 Cambridge Ln Lincolnshire IL 60069",
    "addr:housenumber":"5",
    "addr:postcode":"60069",
    "addr:street":"Cambridge Ln",
    "iso:country":"US",
    "sg:address":"5 Cambridge Ln",
    "sg:city":"Lincolnshire",
    "sg:classifiers":[
        {
            "category":"Recreation",
            "type":"Entertainment"
        }
    ],
    "sg:phone":"+1 773 388 8766",
    "sg:postcode":"60069",
    "sg:province":"IL",
    "sg:tags":[
        "charter",
        "boat"
    ],
    "wof:name":"Confusion Fishing Charters",
    "wof:placetype":"venue"
},
  "geometry": {"coordinates":[-87.90777,42.190613],"type":"Point"}
}