{
  "type": "Feature",
  "properties": {
    "addr:full":"9131 Belleforte Ave Morton Grove IL 60053",
    "addr:housenumber":"9131",
    "addr:postcode":"60053",
    "addr:street":"Belleforte Ave",
    "iso:country":"US",
    "sg:address":"9131 Belleforte Ave",
    "sg:city":"Morton Grove",
    "sg:classifiers":[
        {
            "category":"Professional",
            "subcategory":"Business Services",
            "type":"Services"
        }
    ],
    "sg:phone":"+1 866 580 7640",
    "sg:postcode":"60053",
    "sg:province":"IL",
    "wof:name":"Enhancing Sight Solution",
    "wof:placetype":"venue"
},
  "geometry": {"coordinates":[-87.803348,42.046547],"type":"Point"}
}