{
  "type": "Feature",
  "properties": {
    "addr:full":"2924 W Chase Ave Chicago IL 60645",
    "addr:housenumber":"2924",
    "addr:postcode":"60645",
    "addr:street":"W Chase Ave",
    "iso:country":"US",
    "sg:address":"2924 W Chase Ave",
    "sg:city":"Chicago",
    "sg:classifiers":[
        {
            "category":"Building & Trades",
            "subcategory":"Construction",
            "type":"Services"
        }
    ],
    "sg:phone":"+1 773 491 4191",
    "sg:postcode":"60645",
    "sg:province":"IL",
    "sg:tags":[
        "roofing",
        "contractor"
    ],
    "wof:name":"Absolute Comfort Systems Inc",
    "wof:placetype":"venue"
},
  "geometry": {"coordinates":[-87.703864,42.013865],"type":"Point"}
}