{
  "type": "Feature",
  "properties": {
    "addr:full":"1 IBM Plaza Chicago IL 60611",
    "addr:housenumber":"1",
    "addr:postcode":"60611",
    "addr:street":"Ibm Plaza",
    "iso:country":"US",
    "sg:address":"1 IBM Plaza",
    "sg:city":"Chicago",
    "sg:classifiers":[
        {
            "category":"Professional",
            "subcategory":"Lawyer & Legal Services",
            "type":"Services"
        }
    ],
    "sg:phone":"+1 312 222 9350",
    "sg:postcode":"60611",
    "sg:province":"IL",
    "wof:name":"Dickinson Christopher C Atty",
    "wof:placetype":"venue"
},
  "geometry": {"coordinates":[-87.620244,41.892018],"type":"Point"}
}