{
  "type": "Feature",
  "properties": {
    "addr:full":"211 W Wacker Dr Chicago IL 60606",
    "addr:housenumber":"211",
    "addr:postcode":"60606",
    "addr:street":"W;Dr",
    "iso:country":"US",
    "sg:address":"211 W Wacker Dr",
    "sg:city":"Chicago",
    "sg:classifiers":[
        {
            "category":"Professional",
            "subcategory":"Lawyer & Legal Services",
            "type":"Services"
        }
    ],
    "sg:phone":"+1 312 456 6900",
    "sg:postcode":"60606",
    "sg:province":"IL",
    "sg:tags":[
        "attorney"
    ],
    "sg:website":"http://stearneylaw.com/",
    "wof:name":"Law Offices of Ronald A. Stearney LLC",
    "wof:placetype":"venue"
},
  "geometry": {"coordinates":[-87.63411499999999,41.886768],"type":"Point"}
}