{
  "type": "Feature",
  "properties": {
    "iso:country":"US",
    "sg:address":"1301 Industrial Dr",
    "sg:city":"Lake In The Hls",
    "sg:classifiers":[
        {
            "category":"Freight",
            "type":"Transportation"
        }
    ],
    "sg:phone":"+1 847 658 2570",
    "sg:postcode":"60156",
    "sg:province":"IL",
    "sg:tags":[
        "trucking"
    ],
    "sg:website":"www.eprod.com",
    "wof:name":"Enterprise Transportation",
    "wof:placetype":"venue"
},
  "geometry": {"coordinates":[-88.30536499999999,42.191798],"type":"Point"}
}