{
  "type": "Feature",
  "properties": {
    "iso:country":"US",
    "sg:address":"445 Arlington Heights Rd",
    "sg:city":"Arlington Heights",
    "sg:classifiers":[
        {
            "category":"Retail",
            "subcategory":"Auto Repair",
            "type":"Services"
        }
    ],
    "sg:phone":"+1 847 394 2666",
    "sg:postcode":"60005",
    "sg:province":"IL",
    "sg:tags":[
        "automotive",
        "general"
    ],
    "wof:name":"Scarsdale Automotive",
    "wof:placetype":"venue"
},
  "geometry": {"coordinates":[-87.980461,42.076375],"type":"Point"}
}