{
  "type": "Feature",
  "properties": {
    "iso:country":"US",
    "sg:address":"10910 S Eastwood Dr",
    "sg:city":"Palos Hills",
    "sg:classifiers":[
        {
            "category":"Building & Trades",
            "subcategory":"Construction",
            "type":"Services"
        }
    ],
    "sg:phone":"+1 708 974 0368",
    "sg:postcode":"60465",
    "sg:province":"IL",
    "sg:tags":[
        "excavating",
        "contractor"
    ],
    "wof:name":"M & K Excavating Inc",
    "wof:placetype":"venue"
},
  "geometry": {"coordinates":[-87.811186,41.689812],"type":"Point"}
}