{
  "type": "Feature",
  "properties": {
    "addr:full":"5958 W Addison Chicago IL 60634",
    "addr:housenumber":"5958",
    "addr:postcode":"60634",
    "addr:street":"W Addison",
    "iso:country":"US",
    "sg:address":"5958 W Addison",
    "sg:city":"Chicago",
    "sg:classifiers":[
        {
            "category":"Communications",
            "subcategory":"Television Station",
            "type":"Services"
        }
    ],
    "sg:phone":"+1 773 725 6004",
    "sg:postcode":"60634",
    "sg:province":"IL",
    "sg:website":"www.directv.com",
    "wof:name":"DirecTV Satellite Systems",
    "wof:placetype":"venue"
},
  "geometry": {"coordinates":[-87.776258,41.945819],"type":"Point"}
}