{
  "type": "Feature",
  "properties": {
    "addr:full":"1450 W Lake St Addison IL 60101",
    "addr:housenumber":"1450",
    "addr:postcode":"60101",
    "addr:street":"W Lake St",
    "iso:country":"US",
    "sg:address":"1450 W Lake St",
    "sg:city":"Addison",
    "sg:classifiers":[
        {
            "category":"Restaurant",
            "type":"Food & Drink"
        }
    ],
    "sg:menulink":"http://www.allmenus.com/il/addison/124134-quiznos-sub/menu/",
    "sg:phone":"+1 630 250 0414",
    "sg:postcode":"60101",
    "sg:province":"IL",
    "sg:tags":[
        "wrap",
        "american",
        "sandwich"
    ],
    "wof:name":"Quiznos Sub",
    "wof:placetype":"venue"
},
  "geometry": {"coordinates":[-88.023132,41.946818],"type":"Point"}
}