{
  "type": "Feature",
  "properties": {
    "iso:country":"US",
    "sg:address":"2650 Duffy Ln",
    "sg:city":"Riverwoods",
    "sg:classifiers":[
        {
            "category":"Professional",
            "subcategory":"Engineering",
            "type":"Services"
        }
    ],
    "sg:phone":"+1 847 948 9322",
    "sg:postcode":"60015",
    "sg:province":"IL",
    "sg:tags":[
        "engineer"
    ],
    "wof:name":"Lucole Consulting Engineering",
    "wof:placetype":"venue"
},
  "geometry": {"coordinates":[-87.891673,42.189282],"type":"Point"}
}