{
  "type": "Feature",
  "properties": {
    "iso:country":"US",
    "sg:address":"70 W Roberta St",
    "sg:city":"Lemont",
    "sg:classifiers":[
        {
            "category":"Building & Trades",
            "subcategory":"Plumbing",
            "type":"Services"
        }
    ],
    "sg:phone":"+1 630 243 0469",
    "sg:postcode":"60439",
    "sg:province":"IL",
    "sg:tags":[
        "air",
        "warm",
        "refrigeration",
        "conditioning",
        "he"
    ],
    "wof:name":"Evergreen Service Co of Ill",
    "wof:placetype":"venue"
},
  "geometry": {"coordinates":[-88.014461,41.660396],"type":"Point"}
}