{
  "type": "Feature",
  "properties": {
    "iso:country":"US",
    "sg:address":"8480 W Golf Rd",
    "sg:city":"Niles",
    "sg:classifiers":[
        {
            "category":"Restaurant",
            "type":"Food & Drink"
        }
    ],
    "sg:menulink":"http://www.allmenus.com/il/maine/91494-bennigans-grill--tavern/menu/",
    "sg:phone":"+1 847 965 4644",
    "sg:postcode":"60714",
    "sg:province":"IL",
    "sg:tags":[
        "sandwich",
        "salad",
        "burger",
        "pub",
        "soup",
        "american",
        "wrap"
    ],
    "wof:name":"Bennigan's Grill & Tavern",
    "wof:placetype":"venue"
},
  "geometry": {"coordinates":[-87.83772500000001,42.054679],"type":"Point"}
}