{
  "type": "Feature",
  "properties": {
    "iso:country":"US",
    "sg:address":"4755 N Lincoln Ave",
    "sg:city":"Chicago",
    "sg:classifiers":[
        {
            "category":"Personal",
            "subcategory":"Beauty Salon",
            "type":"Services"
        }
    ],
    "sg:phone":"+1 773 506 7870",
    "sg:postcode":"60625",
    "sg:province":"IL",
    "sg:tags":[
        "hair",
        "spa"
    ],
    "sg:website":"www.tigerlilie.com",
    "wof:name":"Tigerlilie Salon",
    "wof:placetype":"venue"
},
  "geometry": {"coordinates":[-87.687836,41.967892],"type":"Point"}
}