{
  "type": "Feature",
  "properties": {
    "iso:country":"US",
    "sg:address":"3000 W Deyoung St Ste 800B",
    "sg:city":"Marion",
    "sg:classifiers":[
        {
            "category":"Professional",
            "subcategory":"Employment Agencies",
            "type":"Services"
        }
    ],
    "sg:phone":"+1 618 998 0970",
    "sg:postcode":"62959",
    "sg:province":"IL",
    "wof:name":"Man-Tra-Con Corp",
    "wof:placetype":"venue"
},
  "geometry": {"coordinates":[-88.977885,37.747406],"type":"Point"}
}