{
  "type": "Feature",
  "properties": {
    "iso:country":"US",
    "sg:address":"2500 Helm Rd",
    "sg:city":"Carpentersville",
    "sg:classifiers":[
        {
            "category":"Education",
            "subcategory":"School",
            "type":"Public Place"
        }
    ],
    "sg:phone":"+1 847 426 4232",
    "sg:postcode":"60110",
    "sg:province":"IL",
    "wof:name":"Sunnyhill Schl",
    "wof:placetype":"venue"
},
  "geometry": {"coordinates":[-88.25299800000001,42.132301],"type":"Point"}
}