{
  "type": "Feature",
  "properties": {
    "iso:country":"US",
    "sg:address":"425 S Edgewood Ave",
    "sg:city":"Wood Dale",
    "sg:classifiers":[
        {
            "category":"Wholesale",
            "subcategory":"Electrical",
            "type":"Manufacturing & Wholesale Goods"
        }
    ],
    "sg:phone":"+1 630 860 2020",
    "sg:postcode":"60191",
    "sg:province":"IL",
    "sg:tags":[
        "equipment"
    ],
    "wof:name":"Phase Industries",
    "wof:placetype":"venue"
},
  "geometry": {"coordinates":[-87.96645100000001,41.948541],"type":"Point"}
}