{
  "type": "Feature",
  "properties": {
    "iso:country":"US",
    "sg:address":"2451 Lively Blvd",
    "sg:city":"Elk Grove Village",
    "sg:classifiers":[
        {
            "category":"Professional",
            "subcategory":"Advertising",
            "type":"Services"
        }
    ],
    "sg:phone":"+1 847 238 5400",
    "sg:postcode":"60007",
    "sg:province":"IL",
    "sg:tags":[
        "mail",
        "direct"
    ],
    "wof:name":"Paw Print Direct Marketing",
    "wof:placetype":"venue"
},
  "geometry": {"coordinates":[-87.970532,41.990332],"type":"Point"}
}