{
  "type": "Feature",
  "properties": {
    "iso:country":"US",
    "sg:address":"4385 S Archer Ave",
    "sg:city":"Chicago",
    "sg:classifiers":[
        {
            "category":"Retail",
            "subcategory":"Portrait Studio",
            "type":"Services"
        },
        {
            "category":"Shopping",
            "subcategory":"Pharmacy",
            "type":"Retail Goods"
        }
    ],
    "sg:phone":"+1 773 247 6252",
    "sg:postcode":"60632",
    "sg:province":"IL",
    "sg:tags":[
        "photography",
        "drugstore",
        "store"
    ],
    "wof:name":"Walgreen Drug Stores",
    "wof:placetype":"venue"
},
  "geometry": {"coordinates":[-87.705101,41.813301],"type":"Point"}
}