{
  "type": "Feature",
  "properties": {
    "iso:country":"US",
    "sg:address":"210 Moen Ave",
    "sg:city":"Rockdale",
    "sg:classifiers":[
        {
            "category":"Building & Trades",
            "subcategory":"Construction",
            "type":"Services"
        }
    ],
    "sg:phone":"+1 815 553 4822",
    "sg:postcode":"60436",
    "sg:province":"IL",
    "sg:tags":[
        "system",
        "specialty",
        "heating",
        "contractor",
        "air conditioning"
    ],
    "wof:name":"Jerico Services Etc.",
    "wof:placetype":"venue"
},
  "geometry": {"coordinates":[-88.109855,41.505276],"type":"Point"}
}