{
  "type": "Feature",
  "properties": {
    "iso:country":"US",
    "sg:address":"5439 W Lawrence Ave",
    "sg:city":"Chicago",
    "sg:classifiers":[
        {
            "category":"Autos & Motor Vehicles",
            "subcategory":"Automobile Sales",
            "type":"Retail Goods"
        }
    ],
    "sg:phone":"+1 773 286 7896",
    "sg:postcode":"60630",
    "sg:province":"IL",
    "sg:tags":[
        "limo"
    ],
    "wof:name":"Pronto",
    "wof:placetype":"venue"
},
  "geometry": {"coordinates":[-87.763901,41.967602],"type":"Point"}
}