{
  "type": "Feature",
  "properties": {
    "iso:country":"US",
    "sg:address":"3708 River Rd",
    "sg:city":"Franklin Park",
    "sg:classifiers":[
        {
            "category":"Wholesale",
            "subcategory":"Non-durable Goods",
            "type":"Manufacturing & Wholesale Goods"
        }
    ],
    "sg:phone":"+1 847 233 9757",
    "sg:postcode":"60131",
    "sg:province":"IL",
    "sg:tags":[
        "to",
        "only",
        "importer",
        "gift",
        "trade"
    ],
    "wof:name":"Primark International Ltd",
    "wof:placetype":"venue"
},
  "geometry": {"coordinates":[-87.854496,41.943578],"type":"Point"}
}