{
  "type": "Feature",
  "properties": {
    "iso:country":"US",
    "sg:address":"431 Holiday Dr",
    "sg:city":"Somonauk",
    "sg:classifiers":[
        {
            "category":"Shopping",
            "subcategory":"Catalog Store",
            "type":"Retail Goods"
        }
    ],
    "sg:phone":"+1 815 498 9805",
    "sg:postcode":"60552",
    "sg:province":"IL",
    "sg:tags":[
        "mail",
        "order",
        "online"
    ],
    "wof:name":"Char-Lee Originals Crafts",
    "wof:placetype":"venue"
},
  "geometry": {"coordinates":[-88.67004300000001,41.619237],"type":"Point"}
}