{
  "type": "Feature",
  "properties": {
    "iso:country":"US",
    "sg:address":"2812 1/2 W Devon Ave",
    "sg:city":"Chicago",
    "sg:classifiers":[
        {
            "category":"Food & Beverages",
            "subcategory":"Groceries & Convenience Stores",
            "type":"Retail Goods"
        }
    ],
    "sg:phone":"+1 773 338 9893",
    "sg:postcode":"60659",
    "sg:province":"IL",
    "wof:name":"Yonan Bushra",
    "wof:placetype":"venue"
},
  "geometry": {"coordinates":[-87.700141,41.997679],"type":"Point"}
}