{
  "type": "Feature",
  "properties": {
    "iso:country":"US",
    "sg:address":"11 Jackson St",
    "sg:city":"East Dundee",
    "sg:classifiers":[
        {
            "category":"Shopping",
            "subcategory":"Bicycles & Sporting Goods",
            "type":"Retail Goods"
        }
    ],
    "sg:phone":"+1 847 428 2600",
    "sg:postcode":"60118",
    "sg:province":"IL",
    "sg:tags":[
        "bike"
    ],
    "wof:name":"Bicycle Garage",
    "wof:placetype":"venue"
},
  "geometry": {"coordinates":[-88.275002,42.0993],"type":"Point"}
}