{
  "type": "Feature",
  "properties": {
    "iso:country":"US",
    "sg:address":"806 S Jasper St",
    "sg:city":"Decatur",
    "sg:classifiers":[
        {
            "category":"Banks & Credit Unions",
            "subcategory":"Investment Brokerage",
            "type":"Services"
        },
        {
            "category":"Shopping",
            "subcategory":"Computers & Home Electronics",
            "type":"Retail Goods"
        }
    ],
    "sg:phone":"+1 217 422 3011",
    "sg:postcode":"62521",
    "sg:province":"IL",
    "sg:tags":[
        "television",
        "theater",
        "system",
        "sale",
        "dvds-rental",
        "video",
        "radio",
        "store",
        "tape"
    ],
    "sg:website":"http://www.bandctvyp.com",
    "wof:name":"B & C TV Service, Inc.",
    "wof:placetype":"venue"
},
  "geometry": {"coordinates":[-88.940192,39.833289],"type":"Point"}
}