{
  "type": "Feature",
  "properties": {
    "addr:full":"1858 N State Rte 50 Bourbonnais IL 60914",
    "addr:housenumber":"1858",
    "addr:postcode":"60914",
    "addr:street":"N State Rte 50 Bourbonnais",
    "iso:country":"US",
    "sg:address":"1858 N State Rte 50",
    "sg:city":"Bourbonnais",
    "sg:classifiers":[
        {
            "category":"Shopping",
            "subcategory":"Hobbies, Toys, & Games",
            "type":"Retail Goods"
        }
    ],
    "sg:phone":"+1   ",
    "sg:postcode":"60914",
    "sg:province":"IL",
    "sg:tags":[
        "collectible"
    ],
    "wof:name":"Legends of Racing",
    "wof:placetype":"venue"
},
  "geometry": {"coordinates":[-87.850971,41.163829],"type":"Point"}
}