{
  "type": "Feature",
  "properties": {
    "addr:full":"15935 Le Claire Ave Ste 1A Oak Forest IL 60452",
    "addr:housenumber":"15935",
    "addr:postcode":"60452",
    "addr:street":"Le Claire Ave Ste 1A",
    "iso:country":"US",
    "sg:address":"15935 Le Claire Ave Ste 1A",
    "sg:city":"Oak Forest",
    "sg:classifiers":[
        {
            "category":"Real Estate",
            "subcategory":"Real Estate Operator",
            "type":"Services"
        }
    ],
    "sg:phone":"+1 708 687 9640",
    "sg:postcode":"60452",
    "sg:province":"IL",
    "sg:tags":[
        "apartment"
    ],
    "wof:name":"Rustic Oaks Apartments",
    "wof:placetype":"venue"
},
  "geometry": {"coordinates":[-87.7435,41.6026],"type":"Point"}
}