{
  "type": "Feature",
  "properties": {
    "addr:full":"2348 W Cermak Rd Chicago IL 60608",
    "addr:housenumber":"2348",
    "addr:postcode":"60608",
    "addr:street":"W Cermak Rd",
    "iso:country":"US",
    "sg:address":"2348 W Cermak Rd",
    "sg:city":"Chicago",
    "sg:classifiers":[
        {
            "category":"Home & Garden",
            "subcategory":"Home Furnishings",
            "type":"Retail Goods"
        }
    ],
    "sg:phone":"+1 773 247 0578",
    "sg:postcode":"60608",
    "sg:province":"IL",
    "sg:tags":[
        "draperies",
        "bedding",
        "linen",
        "window",
        "treatment",
        "curtain"
    ],
    "wof:name":"Mr. Dollar's Bedding, Inc",
    "wof:placetype":"venue"
},
  "geometry": {"coordinates":[-87.68499,41.852016],"type":"Point"}
}