{
  "type": "Feature",
  "properties": {
    "addr:full":"1405 State St East St Louis IL 62205",
    "addr:housenumber":"1405",
    "addr:postcode":"62205",
    "addr:street":"State St",
    "iso:country":"US",
    "sg:address":"1405 State St",
    "sg:city":"East St Louis",
    "sg:classifiers":[
        {
            "category":"Education",
            "subcategory":"Vocational School",
            "type":"Public Place"
        }
    ],
    "sg:phone":"+1 618 874 1671",
    "sg:postcode":"62205",
    "sg:province":"IL",
    "sg:tags":[
        "technical",
        "trade"
    ],
    "wof:name":"Emerson Park Development Corp",
    "wof:placetype":"venue"
},
  "geometry": {"coordinates":[-90.143299,38.622061],"type":"Point"}
}