{
  "type": "Feature",
  "properties": {
    "addr:full":"967 N Green Bay Rd Waukegan IL 60085",
    "addr:housenumber":"967",
    "addr:postcode":"60085",
    "addr:street":"N Green Bay Rd",
    "iso:country":"US",
    "sg:address":"967 N Green Bay Rd",
    "sg:city":"Waukegan",
    "sg:classifiers":[
        {
            "category":"Restaurant",
            "type":"Food & Drink"
        }
    ],
    "sg:phone":"+1   ",
    "sg:postcode":"60085",
    "sg:province":"IL",
    "sg:tags":[
        "fast"
    ],
    "wof:name":"Rallys Hamburgers",
    "wof:placetype":"venue"
},
  "geometry": {"coordinates":[-87.882431,42.373166],"type":"Point"}
}