{
  "type": "Feature",
  "properties": {
    "iso:country":"US",
    "sg:address":"692 Lee St",
    "sg:city":"Des Plaines",
    "sg:classifiers":[
        {
            "category":"Sports & Exercise",
            "subcategory":"Gym",
            "type":"Entertainment"
        }
    ],
    "sg:phone":"+1 847 827 3333",
    "sg:postcode":"60016",
    "sg:province":"IL",
    "sg:tags":[
        "club",
        "health",
        "studio",
        "gymnasium"
    ],
    "wof:name":"Curves For Women",
    "wof:placetype":"venue"
},
  "geometry": {"coordinates":[-87.88825199999999,42.040993],"type":"Point"}
}