{
  "type": "Feature",
  "properties": {
    "addr:full":"6071 N Milwaukee Ave Chicago IL 60646",
    "addr:housenumber":"6071",
    "addr:postcode":"60646",
    "addr:street":"N Milwaukee Ave",
    "iso:country":"US",
    "sg:address":"6071 N Milwaukee Ave",
    "sg:city":"Chicago",
    "sg:classifiers":[
        {
            "category":"Building & Trades",
            "subcategory":"Equipment Rental",
            "type":"Services"
        }
    ],
    "sg:phone":"+1 773 631 2424",
    "sg:postcode":"60646",
    "sg:province":"IL",
    "sg:tags":[
        "heavy",
        "construction",
        "real estate"
    ],
    "wof:name":"Schmid Management Inc",
    "wof:placetype":"venue"
},
  "geometry": {"coordinates":[-87.783573,41.992909],"type":"Point"}
}