{
  "type": "Feature",
  "properties": {
    "addr:full":"2113 Rivington Rd Loves Park IL 61111",
    "addr:housenumber":"2113",
    "addr:postcode":"61111",
    "addr:street":"Rivington Rd",
    "iso:country":"US",
    "sg:address":"2113 Rivington Rd",
    "sg:city":"Loves Park",
    "sg:classifiers":[
        {
            "category":"Real Estate",
            "subcategory":"Real Estate Operator",
            "type":"Services"
        }
    ],
    "sg:phone":"+1 815 877 2020",
    "sg:postcode":"61111",
    "sg:province":"IL",
    "sg:tags":[
        "apartment"
    ],
    "wof:name":"D C Properties",
    "wof:placetype":"venue"
},
  "geometry": {"coordinates":[-89.022564,42.327125],"type":"Point"}
}