{
  "type": "Feature",
  "properties": {
    "addr:full":"1918 W Irving Park Rd Chicago IL 60613",
    "addr:housenumber":"1918",
    "addr:postcode":"60613",
    "addr:street":"W Irving Park Rd",
    "iso:country":"US",
    "sg:address":"1918 W Irving Park Rd",
    "sg:city":"Chicago",
    "sg:classifiers":[
        {
            "category":"Retail",
            "subcategory":"Repair Shop",
            "type":"Services"
        }
    ],
    "sg:phone":"+1 773 348 9240",
    "sg:postcode":"60613",
    "sg:province":"IL",
    "sg:tags":[
        "reupholstery",
        "furniture"
    ],
    "wof:name":"Star Upholstery",
    "wof:placetype":"venue"
},
  "geometry": {"coordinates":[-87.6772,41.9543],"type":"Point"}
}