{
  "type": "Feature",
  "properties": {
    "iso:country":"US",
    "sg:address":"9611 Grand Ave",
    "sg:city":"Franklin Park",
    "sg:classifiers":[
        {
            "category":"Professional",
            "subcategory":"Employment Agencies",
            "type":"Services"
        }
    ],
    "sg:phone":"+1 847 455 3101",
    "sg:postcode":"60131",
    "sg:province":"IL",
    "sg:tags":[
        "opportunity"
    ],
    "sg:website":"www.flexicorps.com",
    "wof:name":"Alpha Temporary Svc",
    "wof:placetype":"venue"
},
  "geometry": {"coordinates":[-87.866072,41.929647],"type":"Point"}
}