{
  "type": "Feature",
  "properties": {
    "iso:country":"US",
    "sg:address":"1600 W Walnut St",
    "sg:city":"Jacksonville",
    "sg:classifiers":[
        {
            "category":"Health Services",
            "subcategory":"Doctor",
            "type":"Services"
        }
    ],
    "sg:phone":"+1 217 479 0107",
    "sg:postcode":"62650",
    "sg:province":"IL",
    "sg:tags":[
        "medical"
    ],
    "wof:name":"Mark A Savage MD",
    "wof:placetype":"venue"
},
  "geometry": {"coordinates":[-90.260671,39.745354],"type":"Point"}
}