{
  "type": "Feature",
  "properties": {
    "iso:country":"US",
    "sg:address":"4820 Wright Ter",
    "sg:city":"Skokie",
    "sg:classifiers":[
        {
            "category":"Professional",
            "subcategory":"Art Services",
            "type":"Services"
        }
    ],
    "sg:phone":"+1 847 982 1446",
    "sg:postcode":"60077",
    "sg:province":"IL",
    "sg:tags":[
        "commercial",
        "design"
    ],
    "wof:name":"Akins Aesthetic Design",
    "wof:placetype":"venue"
},
  "geometry": {"coordinates":[-87.74721599999999,42.036221],"type":"Point"}
}