{
  "type": "Feature",
  "properties": {
    "iso:country":"US",
    "sg:address":"2501 S Christiana Ave",
    "sg:city":"Chicago",
    "sg:classifiers":[
        {
            "category":"Retail",
            "subcategory":"Laundry & Dry Cleaning",
            "type":"Services"
        }
    ],
    "sg:phone":"+1 773 521 5480",
    "sg:postcode":"60623",
    "sg:province":"IL",
    "sg:tags":[
        "operated",
        "dryer",
        "laundries-self",
        "washer",
        "coin"
    ],
    "wof:name":"Little Village Laundromat",
    "wof:placetype":"venue"
},
  "geometry": {"coordinates":[-87.70871699999999,41.846272],"type":"Point"}
}