{
  "type": "Feature",
  "properties": {
    "addr:full":"6001 Dempster St Morton Grove IL 60053",
    "addr:housenumber":"6001",
    "addr:postcode":"60053",
    "addr:street":"Dempster St",
    "iso:country":"US",
    "sg:address":"6001 Dempster St",
    "sg:city":"Morton Grove",
    "sg:classifiers":[
        {
            "category":"Shopping",
            "type":"Retail Goods"
        }
    ],
    "sg:phone":"+1   ",
    "sg:postcode":"60053",
    "sg:province":"IL",
    "sg:tags":[
        "equipment",
        "medical"
    ],
    "wof:name":"Mobility Plus of Illinois Inc",
    "wof:placetype":"venue"
},
  "geometry": {"coordinates":[-87.77731799999999,42.040921],"type":"Point"}
}