{
  "type": "Feature",
  "properties": {
    "addr:full":"7446 N Clark St Chicago IL 60626",
    "addr:housenumber":"7446",
    "addr:postcode":"60626",
    "addr:street":"N Clark St",
    "iso:country":"US",
    "sg:address":"7446 N Clark St",
    "sg:city":"Chicago",
    "sg:classifiers":[
        {
            "category":"Autos & Motor Vehicles",
            "subcategory":"Automobile Sales",
            "type":"Retail Goods"
        },
        {
            "category":"Autos & Motor Vehicles",
            "subcategory":"Motorcycle Sales",
            "type":"Retail Goods"
        },
        {
            "category":"Autos & Motor Vehicles",
            "subcategory":"Recreational Vehicle Sales",
            "type":"Retail Goods"
        }
    ],
    "sg:phone":"+1 866 974 7281",
    "sg:postcode":"60626",
    "sg:province":"IL",
    "sg:tags":[
        "antique",
        "car",
        "used",
        "appraiser",
        "classic"
    ],
    "sg:website":"http://www.howardlautosales.com",
    "wof:name":"Howard L Auto Sales",
    "wof:placetype":"venue"
},
  "geometry": {"coordinates":[-87.67533899999999,42.016836],"type":"Point"}
}