{
  "type": "Feature",
  "properties": {
    "addr:full":"32401 S State Rte 53 Wilmington IL 60481",
    "addr:housenumber":"32401",
    "addr:postcode":"60481",
    "addr:street":"S State Rte 53",
    "iso:country":"US",
    "sg:address":"32401 S State Rte 53",
    "sg:city":"Wilmington",
    "sg:classifiers":[
        {
            "category":"Communications",
            "subcategory":"Radio Station",
            "type":"Services"
        }
    ],
    "sg:phone":"+1 815 476 5855",
    "sg:postcode":"60481",
    "sg:province":"IL",
    "sg:tags":[
        "company",
        "broadcasting"
    ],
    "wof:name":"Pride Communications",
    "wof:placetype":"venue"
},
  "geometry": {"coordinates":[-88.169528,41.297195],"type":"Point"}
}