{
  "type": "Feature",
  "properties": {
    "iso:country":"US",
    "sg:address":"2405 Hamilton Rd",
    "sg:city":"Arlington Hts",
    "sg:classifiers":[
        {
            "category":"Wholesale",
            "subcategory":"Machinery & Supplies",
            "type":"Manufacturing & Wholesale Goods"
        }
    ],
    "sg:phone":"+1 847 640 9400",
    "sg:postcode":"60005",
    "sg:province":"IL",
    "sg:tags":[
        "truck"
    ],
    "sg:website":"www.uslist.com",
    "wof:name":"Budgetlift Forklift & Aerial",
    "wof:placetype":"venue"
},
  "geometry": {"coordinates":[-87.948528,42.021016],"type":"Point"}
}