{
  "type": "Feature",
  "properties": {
    "iso:country":"US",
    "sg:address":"3833 N Tripp Ave",
    "sg:city":"Chicago",
    "sg:classifiers":[
        {
            "category":"Professional",
            "type":"Services"
        }
    ],
    "sg:phone":"+1 773 481 2776",
    "sg:postcode":"60641",
    "sg:province":"IL",
    "sg:tags":[
        "literary",
        "writer",
        "agent"
    ],
    "wof:name":"Craig A Shutt",
    "wof:placetype":"venue"
},
  "geometry": {"coordinates":[-87.73386600000001,41.950545],"type":"Point"}
}