{
  "type": "Feature",
  "properties": {
    "iso:country":"US",
    "sg:address":"700 W 55th St",
    "sg:city":"La Grange",
    "sg:classifiers":[
        {
            "category":"Education",
            "subcategory":"School",
            "type":"Public Place"
        }
    ],
    "sg:phone":"+1 708 352 4820",
    "sg:postcode":"60525",
    "sg:province":"IL",
    "sg:website":"www.stcletusparish.com/school/",
    "wof:name":"St Cletus School",
    "wof:placetype":"venue"
},
  "geometry": {"coordinates":[-87.877403,41.790401],"type":"Point"}
}