{
  "type": "Feature",
  "properties": {
    "iso:country":"US",
    "sg:address":"1505 S Main St",
    "sg:city":"Rockford",
    "sg:classifiers":[
        {
            "category":"Social Services",
            "type":"Services"
        }
    ],
    "sg:phone":"+1 815 965 6993",
    "sg:postcode":"61102",
    "sg:province":"IL",
    "sg:tags":[
        "care",
        "community",
        "child"
    ],
    "wof:name":"Adult Building",
    "wof:placetype":"venue"
},
  "geometry": {"coordinates":[-89.10145199999999,42.257116],"type":"Point"}
}