{
  "type": "Feature",
  "properties": {
    "iso:country":"US",
    "sg:address":"100 E Plaza Dr",
    "sg:city":"Carterville",
    "sg:classifiers":[
        {
            "category":"Autos & Motor Vehicles",
            "subcategory":"Fuel & Gas Station",
            "type":"Retail Goods"
        }
    ],
    "sg:phone":"+1 618 985 4015",
    "sg:postcode":"62918",
    "sg:province":"IL",
    "wof:name":"Fkg Oil",
    "wof:placetype":"venue"
},
  "geometry": {"coordinates":[-89.076797,37.745499],"type":"Point"}
}