{
  "type": "Feature",
  "properties": {
    "addr:full":"9806 S Turner Ave Evergreen Park IL 60805",
    "addr:housenumber":"9806",
    "addr:postcode":"60805",
    "addr:street":"S Turner Ave",
    "iso:country":"US",
    "sg:address":"9806 S Turner Ave",
    "sg:city":"Evergreen Park",
    "sg:classifiers":[
        {
            "category":"Shopping",
            "subcategory":"Jewelry",
            "type":"Retail Goods"
        }
    ],
    "sg:phone":"+1   ",
    "sg:postcode":"60805",
    "sg:province":"IL",
    "sg:tags":[
        "store"
    ],
    "wof:name":"Coren Jewelers",
    "wof:placetype":"venue"
},
  "geometry": {"coordinates":[-87.705326,41.715914],"type":"Point"}
}