{
  "type": "Feature",
  "properties": {
    "iso:country":"US",
    "sg:address":"602 E Newton St",
    "sg:city":"Heyworth",
    "sg:classifiers":[
        {
            "category":"Building & Trades",
            "subcategory":"Construction",
            "type":"Services"
        }
    ],
    "sg:phone":"+1 309 473 3703",
    "sg:postcode":"61745",
    "sg:province":"IL",
    "sg:tags":[
        "house"
    ],
    "wof:name":"Bell Construction",
    "wof:placetype":"venue"
},
  "geometry": {"coordinates":[-88.970347,40.315234],"type":"Point"}
}