{
  "type": "Feature",
  "properties": {
    "iso:country":"US",
    "sg:address":"25 S Northwest Hwy",
    "sg:city":"Park Ridge",
    "sg:classifiers":[
        {
            "category":"Home & Garden",
            "subcategory":"Furniture",
            "type":"Retail Goods"
        }
    ],
    "sg:phone":"+1   ",
    "sg:postcode":"60068",
    "sg:province":"IL",
    "sg:tags":[
        "store"
    ],
    "wof:name":"Walter E Smithe Furniture",
    "wof:placetype":"venue"
},
  "geometry": {"coordinates":[-87.82831899999999,42.010574],"type":"Point"}
}