{
  "type": "Feature",
  "properties": {
    "addr:full":"6121 S Archer Rd Summit IL 60501",
    "addr:housenumber":"6121",
    "addr:postcode":"60501",
    "addr:street":"S Archer Rd",
    "iso:country":"US",
    "sg:address":"6121 S Archer Rd",
    "sg:city":"Summit",
    "sg:classifiers":[
        {
            "category":"Restaurant",
            "type":"Food & Drink"
        }
    ],
    "sg:phone":"+1 708 924 5167",
    "sg:postcode":"60501",
    "sg:province":"IL",
    "sg:tags":[
        "american",
        "latin",
        "mexican"
    ],
    "wof:name":"Antojitos Dona Maria",
    "wof:placetype":"venue"
},
  "geometry": {"coordinates":[-87.81257600000001,41.780073],"type":"Point"}
}