{
  "type": "Feature",
  "properties": {
    "addr:full":"977 Lakeview Pkwy Vernon Hills IL 60061",
    "addr:housenumber":"977",
    "addr:postcode":"60061",
    "addr:street":"Lakeview Pkwy",
    "iso:country":"US",
    "sg:address":"977 Lakeview Pkwy",
    "sg:city":"Vernon Hills",
    "sg:classifiers":[
        {
            "category":"Insurance",
            "subcategory":"Insurance Agent",
            "type":"Services"
        }
    ],
    "sg:phone":"+1 847 367 2633",
    "sg:postcode":"60061",
    "sg:province":"IL",
    "wof:name":"Rand-Tec Insurance Inc",
    "wof:placetype":"venue"
},
  "geometry": {"coordinates":[-87.95926799999999,42.242339],"type":"Point"}
}