{
  "type": "Feature",
  "properties": {
    "iso:country":"US",
    "sg:address":"306 W 23rd Pl",
    "sg:city":"Chicago",
    "sg:classifiers":[
        {
            "category":"Personal",
            "type":"Services"
        },
        {
            "category":"Home & Garden",
            "subcategory":"Hardware",
            "type":"Retail Goods"
        }
    ],
    "sg:phone":"+1 312 225 9123",
    "sg:postcode":"60616",
    "sg:province":"IL",
    "sg:tags":[
        "designing",
        "remodeling",
        "closet",
        "accessory"
    ],
    "wof:name":"Changsheng Trading Inc",
    "wof:placetype":"venue"
},
  "geometry": {"coordinates":[-87.634974,41.850027],"type":"Point"}
}