{
  "type": "Feature",
  "properties": {
    "addr:full":"2425 Charles St Rockford IL 61108",
    "addr:housenumber":"2425",
    "addr:postcode":"61108",
    "addr:street":"Charles St",
    "iso:country":"US",
    "sg:address":"2425 Charles St",
    "sg:city":"Rockford",
    "sg:classifiers":[
        {
            "category":"Wholesale",
            "subcategory":"Office Equipment",
            "type":"Manufacturing & Wholesale Goods"
        }
    ],
    "sg:phone":"+1 815 226 1066",
    "sg:postcode":"61108",
    "sg:province":"IL",
    "sg:tags":[
        "register",
        "cash",
        "supply"
    ],
    "wof:name":"Cash Register Systems",
    "wof:placetype":"venue"
},
  "geometry": {"coordinates":[-89.056522,42.259917],"type":"Point"}
}