{
  "type": "Feature",
  "properties": {
    "addr:full":"1050 N Milwaukee Ave Chicago IL 60642",
    "addr:housenumber":"1050",
    "addr:postcode":"60642",
    "addr:street":"N Milwaukee Ave",
    "iso:country":"US",
    "sg:address":"1050 N Milwaukee Ave",
    "sg:city":"Chicago",
    "sg:classifiers":[
        {
            "category":"Autos & Motor Vehicles",
            "subcategory":"Automobile Sales",
            "type":"Retail Goods"
        }
    ],
    "sg:phone":"+1 773 603 8865",
    "sg:postcode":"60642",
    "sg:province":"IL",
    "sg:tags":[
        "limo"
    ],
    "wof:name":"Chicago Limo",
    "wof:placetype":"venue"
},
  "geometry": {"coordinates":[-87.66278699999999,41.900968],"type":"Point"}
}