{
  "type": "Feature",
  "properties": {
    "addr:full":"312 N Washington St Bethany IL 61914",
    "addr:housenumber":"312",
    "addr:postcode":"61914",
    "addr:street":"N Washington St",
    "iso:country":"US",
    "sg:address":"312 N Washington St",
    "sg:city":"Bethany",
    "sg:classifiers":[
        {
            "category":"Organizations",
            "subcategory":"Religious Organization",
            "type":"Services"
        }
    ],
    "sg:phone":"+1 217 665 3353",
    "sg:postcode":"61914",
    "sg:province":"IL",
    "sg:tags":[
        "church"
    ],
    "wof:name":"United Methodist Church",
    "wof:placetype":"venue"
},
  "geometry": {"coordinates":[-88.73957299999999,39.64821],"type":"Point"}
}