{
  "type": "Feature",
  "properties": {
    "addr:full":"330 N Westmore Ave Villa Park IL 60181",
    "addr:housenumber":"330",
    "addr:postcode":"60181",
    "addr:street":"N Westmore Ave",
    "iso:country":"US",
    "sg:address":"330 N Westmore Ave",
    "sg:city":"Villa Park",
    "sg:classifiers":[
        {
            "category":"Education",
            "subcategory":"School",
            "type":"Public Place"
        }
    ],
    "sg:phone":"+1 630 279 7404",
    "sg:postcode":"60181",
    "sg:province":"IL",
    "wof:name":"St John Apostle",
    "wof:placetype":"venue"
},
  "geometry": {"coordinates":[-87.99359200000001,41.896594],"type":"Point"}
}