{
  "type": "Feature",
  "properties": {
    "iso:country":"US",
    "sg:address":"2929 N Main St",
    "sg:city":"Rockford",
    "sg:classifiers":[
        {
            "category":"Banks & Credit Unions",
            "subcategory":"Bank",
            "type":"Services"
        }
    ],
    "sg:phone":"+1 815 636 3291",
    "sg:postcode":"61103",
    "sg:province":"IL",
    "wof:name":"Atwood Credit Union",
    "wof:placetype":"venue"
},
  "geometry": {"coordinates":[-89.077063,42.306161],"type":"Point"}
}