{
  "type": "Feature",
  "properties": {
    "iso:country":"US",
    "sg:address":"3321 W Pratt Ave",
    "sg:city":"Lincolnwood",
    "sg:classifiers":[
        {
            "category":"Building & Trades",
            "subcategory":"Construction",
            "type":"Services"
        }
    ],
    "sg:phone":"+1 847 673 1017",
    "sg:postcode":"60712",
    "sg:province":"IL",
    "sg:tags":[
        "hanging",
        "contractor"
    ],
    "wof:name":"Baze Painting",
    "wof:placetype":"venue"
},
  "geometry": {"coordinates":[-87.71368099999999,42.004541],"type":"Point"}
}