{
  "type": "Feature",
  "properties": {
    "iso:country":"US",
    "sg:address":"727 Oriole Ave",
    "sg:city":"Park Ridge",
    "sg:classifiers":[
        {
            "category":"Building & Trades",
            "subcategory":"Plumbing",
            "type":"Services"
        }
    ],
    "sg:phone":"+1 847 698 1422",
    "sg:postcode":"60068",
    "sg:province":"IL",
    "sg:tags":[
        "contractor"
    ],
    "wof:name":"Ridge Htg Cooling & Mechanical",
    "wof:placetype":"venue"
},
  "geometry": {"coordinates":[-87.816402,42.021886],"type":"Point"}
}