{
  "type": "Feature",
  "properties": {
    "addr:full":"307 N Clinton St Collinsville IL 62234",
    "addr:housenumber":"307",
    "addr:postcode":"62234",
    "addr:street":"N Clinton St",
    "iso:country":"US",
    "sg:address":"307 N Clinton St",
    "sg:city":"Collinsville",
    "sg:classifiers":[
        {
            "category":"Retail",
            "subcategory":"Repair Shop",
            "type":"Services"
        }
    ],
    "sg:phone":"+1 618 345 0593",
    "sg:postcode":"62234",
    "sg:province":"IL",
    "sg:tags":[
        "jewelry"
    ],
    "wof:name":"Adams Jewelers",
    "wof:placetype":"venue"
},
  "geometry": {"coordinates":[-89.988367,38.673606],"type":"Point"}
}