{
  "type": "Feature",
  "properties": {
    "addr:full":"7301 W Palos Ave Palos Heights IL 60463",
    "addr:housenumber":"7301",
    "addr:postcode":"60463",
    "addr:street":"W Palos Ave",
    "iso:country":"US",
    "sg:address":"7301 W Palos Ave",
    "sg:city":"Palos Heights",
    "sg:classifiers":[
        {
            "category":"Health Services",
            "subcategory":"Doctor",
            "type":"Services"
        }
    ],
    "sg:phone":"+1 708 448 3355",
    "sg:postcode":"60463",
    "sg:province":"IL",
    "wof:name":"Robert Adlfinger DDS",
    "wof:placetype":"venue"
},
  "geometry": {"coordinates":[-87.799702,41.659584],"type":"Point"}
}