{
  "type": "Feature",
  "properties": {
    "addr:full":"213 S Katie Ln Mc Henry IL 60050",
    "addr:housenumber":"213",
    "addr:postcode":"60050",
    "addr:street":"S Katie Ln Mc Henry",
    "iso:country":"US",
    "sg:address":"213 S Katie Ln",
    "sg:city":"Mc Henry",
    "sg:classifiers":[
        {
            "category":"Health Services",
            "subcategory":"Medical Lab",
            "type":"Services"
        }
    ],
    "sg:phone":"+1 815 344 4512",
    "sg:postcode":"60050",
    "sg:province":"IL",
    "sg:tags":[
        "laboratory",
        "dental"
    ],
    "wof:name":"Raabe Dental Lab",
    "wof:placetype":"venue"
},
  "geometry": {"coordinates":[-88.258724,42.32635],"type":"Point"}
}