{
  "type": "Feature",
  "properties": {
    "iso:country":"US",
    "sg:address":"209 Cleveland St",
    "sg:city":"Cary",
    "sg:classifiers":[
        {
            "category":"Manufacturing",
            "subcategory":"Building Materials",
            "type":"Manufacturing & Wholesale Goods"
        }
    ],
    "sg:phone":"+1 847 639 1323",
    "sg:postcode":"60013",
    "sg:province":"IL",
    "sg:tags":[
        "mfg",
        "household",
        "wood",
        "furniture",
        "cabinet"
    ],
    "wof:name":"Master Cabinets",
    "wof:placetype":"venue"
},
  "geometry": {"coordinates":[-88.22980699999999,42.201664],"type":"Point"}
}