{
  "type": "Feature",
  "properties": {
    "addr:full":"1314 Adirondack Dr Northbrook IL 60062",
    "addr:housenumber":"1314",
    "addr:postcode":"60062",
    "addr:street":"Adirondack Dr",
    "iso:country":"US",
    "sg:address":"1314 Adirondack Dr",
    "sg:city":"Northbrook",
    "sg:classifiers":[
        {
            "category":"Manufacturing",
            "subcategory":"Apparel",
            "type":"Manufacturing & Wholesale Goods"
        }
    ],
    "sg:phone":"+1 847 715 1042",
    "sg:postcode":"60062",
    "sg:province":"IL",
    "sg:tags":[
        "product",
        "mfg"
    ],
    "wof:name":"Avamt Garden Canvas Gallery",
    "wof:placetype":"venue"
},
  "geometry": {"coordinates":[-87.85710400000001,42.128529],"type":"Point"}
}