{
  "type": "Feature",
  "properties": {
    "iso:country":"US",
    "sg:address":"105 E 9th St",
    "sg:city":"Gibson City",
    "sg:classifiers":[
        {
            "category":"Wholesale",
            "subcategory":"Groceries",
            "type":"Manufacturing & Wholesale Goods"
        }
    ],
    "sg:phone":"+1 217 784 4500",
    "sg:postcode":"60936",
    "sg:province":"IL",
    "wof:name":"Cutting Edge",
    "wof:placetype":"venue"
},
  "geometry": {"coordinates":[-88.375302,40.466086],"type":"Point"}
}