{
  "type": "Feature",
  "properties": {
    "iso:country":"US",
    "sg:address":"6464 N Clark St",
    "sg:city":"Chicago",
    "sg:classifiers":[
        {
            "category":"Government",
            "subcategory":"Police Station",
            "type":"Public Place"
        }
    ],
    "sg:phone":"+1 312 744 5907",
    "sg:postcode":"60626",
    "sg:province":"IL",
    "sg:tags":[
        "department"
    ],
    "wof:name":"Chicago Police Dept",
    "wof:placetype":"venue"
},
  "geometry": {"coordinates":[-87.67112299999999,41.999664],"type":"Point"}
}