{
  "type": "Feature",
  "properties": {
    "iso:country":"US",
    "sg:address":"1435 Maple Ave",
    "sg:city":"Berwyn",
    "sg:classifiers":[
        {
            "category":"Organizations",
            "subcategory":"Membership Organization",
            "type":"Services"
        }
    ],
    "sg:phone":"+1 708 788 0168",
    "sg:postcode":"60402",
    "sg:province":"IL",
    "wof:name":"Dekovens Social Club",
    "wof:placetype":"venue"
},
  "geometry": {"coordinates":[-87.80265,41.860181],"type":"Point"}
}