{
  "type": "Feature",
  "properties": {
    "iso:country":"US",
    "sg:address":"735 N Taylor Ave",
    "sg:city":"Oak Park",
    "sg:classifiers":[
        {
            "category":"Education",
            "subcategory":"Vocational School",
            "type":"Public Place"
        }
    ],
    "sg:phone":"+1 708 383 7397",
    "sg:postcode":"60302",
    "sg:province":"IL",
    "wof:name":"Ozark Ultraflight Inc",
    "wof:placetype":"venue"
},
  "geometry": {"coordinates":[-87.77779700000001,41.899505],"type":"Point"}
}