{
  "type": "Feature",
  "properties": {
    "addr:full":"1205 N Blackhawk Blvd Rockton IL 61072",
    "addr:housenumber":"1205",
    "addr:postcode":"61072",
    "addr:street":"N Blackhawk Blvd",
    "iso:country":"US",
    "sg:address":"1205 N Blackhawk Blvd",
    "sg:city":"Rockton",
    "sg:classifiers":[
        {
            "category":"Organizations",
            "subcategory":"Religious Organization",
            "type":"Services"
        }
    ],
    "sg:phone":"+1 815 623 3775",
    "sg:postcode":"61072",
    "sg:province":"IL",
    "sg:tags":[
        "church"
    ],
    "wof:name":"Amazing Grace Lutheran Chr",
    "wof:placetype":"venue"
},
  "geometry": {"coordinates":[-89.06388699999999,42.465419],"type":"Point"}
}