{
  "type": "Feature",
  "properties": {
    "iso:country":"US",
    "sg:address":"645 Keep Ave",
    "sg:city":"Elgin",
    "sg:classifiers":[
        {
            "category":"Professional",
            "type":"Services"
        }
    ],
    "sg:phone":"+1 847 468 7016",
    "sg:postcode":"60120",
    "sg:province":"IL",
    "wof:name":"Rosso Technical Services",
    "wof:placetype":"venue"
},
  "geometry": {"coordinates":[-88.26686100000001,42.056002],"type":"Point"}
}