{
  "type": "Feature",
  "properties": {
    "addr:full":"185 Cypress Dr Bolingbrook IL 60440",
    "addr:housenumber":"185",
    "addr:postcode":"60440",
    "addr:street":"Cypress Dr",
    "iso:country":"US",
    "sg:address":"185 Cypress Dr",
    "sg:city":"Bolingbrook",
    "sg:classifiers":[
        {
            "category":"Retail",
            "subcategory":"Laundry & Dry Cleaning",
            "type":"Services"
        }
    ],
    "sg:phone":"+1 630 759 4210",
    "sg:postcode":"60440",
    "sg:province":"IL",
    "sg:tags":[
        "cleaners"
    ],
    "wof:name":"Lucier Maintenance & Repair",
    "wof:placetype":"venue"
},
  "geometry": {"coordinates":[-88.06927399999999,41.69757],"type":"Point"}
}