{
  "type": "Feature",
  "properties": {
    "iso:country":"US",
    "sg:address":"406 Kerry Ct",
    "sg:city":"Prospect Heights",
    "sg:classifiers":[
        {
            "category":"Professional",
            "subcategory":"Computer Services",
            "type":"Services"
        }
    ],
    "sg:phone":"+1 847 788 1175",
    "sg:postcode":"60070",
    "sg:province":"IL",
    "sg:tags":[
        "information",
        "retrieval"
    ],
    "wof:name":"Chicago Technologies",
    "wof:placetype":"venue"
},
  "geometry": {"coordinates":[-87.948946,42.12374],"type":"Point"}
}