{
  "type": "Feature",
  "properties": {
    "iso:country":"US",
    "sg:address":"104 E 4th St",
    "sg:city":"Norris City",
    "sg:classifiers":[
        {
            "category":"Autos & Motor Vehicles",
            "subcategory":"Fuel & Gas Station",
            "type":"Retail Goods"
        }
    ],
    "sg:phone":"+1 618 378 3410",
    "sg:postcode":"62869",
    "sg:province":"IL",
    "sg:tags":[
        "oil"
    ],
    "wof:name":"Bartley's Bp Convenience Store",
    "wof:placetype":"venue"
},
  "geometry": {"coordinates":[-88.328437,37.977985],"type":"Point"}
}