{
  "type": "Feature",
  "properties": {
    "addr:full":"111 E Church St Libertyville IL 60048",
    "addr:housenumber":"111",
    "addr:postcode":"60048",
    "addr:street":"E Church St",
    "iso:country":"US",
    "sg:address":"111 E Church St",
    "sg:city":"Libertyville",
    "sg:classifiers":[
        {
            "category":"Utilities",
            "subcategory":"Telephone",
            "type":"Services"
        },
        {
            "category":"Professional",
            "subcategory":"Computer Services",
            "type":"Services"
        }
    ],
    "sg:phone":"+1 847 996 0001",
    "sg:postcode":"60048",
    "sg:province":"IL",
    "sg:tags":[
        "communications",
        "internet"
    ],
    "wof:name":"Tri Media Inc",
    "wof:placetype":"venue"
},
  "geometry": {"coordinates":[-87.952507,42.286862],"type":"Point"}
}