{
  "type": "Feature",
  "properties": {
    "addr:full":"1155 N Howe St Chicago IL 60610",
    "addr:housenumber":"1155",
    "addr:postcode":"60610",
    "addr:street":"N Howe St",
    "iso:country":"US",
    "sg:address":"1155 N Howe St",
    "sg:city":"Chicago",
    "sg:classifiers":[
        {
            "category":"Home & Garden",
            "subcategory":"Furniture",
            "type":"Retail Goods"
        },
        {
            "category":"Building & Trades",
            "subcategory":"Construction",
            "type":"Services"
        },
        {
            "category":"Manufacturing",
            "subcategory":"Building Materials",
            "type":"Manufacturing & Wholesale Goods"
        },
        {
            "category":"Wholesale",
            "subcategory":"Home Furnishings",
            "type":"Manufacturing & Wholesale Goods"
        }
    ],
    "sg:phone":"+1 312 654 1400",
    "sg:postcode":"60610",
    "sg:province":"IL",
    "sg:tags":[
        "industrial",
        "equipment-wholesale",
        "cabinetmakers-commercial",
        "kitchen",
        "equipment-household",
        "cabinet",
        "maker",
        "manufacturer"
    ],
    "sg:website":"http://www.spaceorganization.net",
    "wof:name":"Space Organization, Ltd",
    "wof:placetype":"venue"
},
  "geometry": {"coordinates":[-87.644452,41.903215],"type":"Point"}
}