{
  "type": "Feature",
  "properties": {
    "iso:country":"US",
    "sg:address":"9 Gateway Dr",
    "sg:city":"Collinsville",
    "sg:classifiers":[
        {
            "category":"Restaurant",
            "type":"Food & Drink"
        }
    ],
    "sg:phone":"+1 618 346 2600",
    "sg:postcode":"62234",
    "sg:province":"IL",
    "wof:name":"Ponderosa Steakhouse",
    "wof:placetype":"venue"
},
  "geometry": {"coordinates":[-90.020826,38.682376],"type":"Point"}
}