{
  "type": "Feature",
  "properties": {
    "addr:full":"5212 W Agatite Ave Chicago IL 60630",
    "addr:housenumber":"5212",
    "addr:postcode":"60630",
    "addr:street":"W Agatite Ave",
    "iso:country":"US",
    "sg:address":"5212 W Agatite Ave",
    "sg:city":"Chicago",
    "sg:classifiers":[
        {
            "category":"Organizations",
            "subcategory":"Religious Organization",
            "type":"Services"
        }
    ],
    "sg:phone":"+1 773 286 2950",
    "sg:postcode":"60630",
    "sg:province":"IL",
    "wof:name":"Our Lady of Victory Church",
    "wof:placetype":"venue"
},
  "geometry": {"coordinates":[-87.757772,41.961512],"type":"Point"}
}