{
  "type": "Feature",
  "properties": {
    "addr:full":"620 W Liberty St Wauconda IL 60084",
    "addr:housenumber":"620",
    "addr:postcode":"60084",
    "addr:street":"W Liberty St",
    "iso:country":"US",
    "sg:address":"620 W Liberty St",
    "sg:city":"Wauconda",
    "sg:classifiers":[
        {
            "category":"Autos & Motor Vehicles",
            "subcategory":"Auto Supplies",
            "type":"Retail Goods"
        },
        {
            "category":"Wholesale",
            "subcategory":"Electrical",
            "type":"Manufacturing & Wholesale Goods"
        },
        {
            "category":"Wholesale",
            "subcategory":"Auto Parts",
            "type":"Manufacturing & Wholesale Goods"
        }
    ],
    "sg:phone":"+1 847 526 7592",
    "sg:postcode":"60084",
    "sg:province":"IL",
    "sg:tags":[
        "body",
        "battery",
        "automobile",
        "accessory",
        "equipment",
        "truck"
    ],
    "sg:website":"http://www.oreillyauto.com?utm_source=yellowpages&utm_medium=iyp&utm_campaign=3425",
    "wof:name":"O'Reilly Auto Parts",
    "wof:placetype":"venue"
},
  "geometry": {"coordinates":[-88.157021,42.258911],"type":"Point"}
}