{
  "type": "Feature",
  "properties": {
    "iso:country":"US",
    "sg:address":"4816 W 92nd St",
    "sg:city":"Oak Lawn",
    "sg:classifiers":[
        {
            "category":"Building & Trades",
            "subcategory":"Landscaping Services",
            "type":"Services"
        }
    ],
    "sg:phone":"+1 708 423 5346",
    "sg:postcode":"60453",
    "sg:province":"IL",
    "sg:tags":[
        "landscape",
        "business"
    ],
    "wof:name":"Arquilla Designs Inc",
    "wof:placetype":"venue"
},
  "geometry": {"coordinates":[-87.741514,41.725601],"type":"Point"}
}