{
  "type": "Feature",
  "properties": {
    "iso:country":"US",
    "sg:address":"4442 N Ashland Ave",
    "sg:city":"Chicago",
    "sg:classifiers":[
        {
            "category":"Building & Trades",
            "subcategory":"Construction",
            "type":"Services"
        }
    ],
    "sg:phone":"+1 773 271 3972",
    "sg:postcode":"60640",
    "sg:province":"IL",
    "sg:tags":[
        "home",
        "improvement"
    ],
    "wof:name":"Grace Full Home Improvement",
    "wof:placetype":"venue"
},
  "geometry": {"coordinates":[-87.66937299999999,41.963116],"type":"Point"}
}