{
  "type": "Feature",
  "properties": {
    "iso:country":"US",
    "sg:address":"4913 W Montrose Ave",
    "sg:city":"Chicago",
    "sg:classifiers":[
        {
            "category":"Building & Trades",
            "subcategory":"Construction",
            "type":"Services"
        }
    ],
    "sg:phone":"+1 847 275 3933",
    "sg:postcode":"60641",
    "sg:province":"IL",
    "sg:tags":[
        "painter"
    ],
    "sg:website":"www.shamrock-services.com",
    "wof:name":"Shamrock Painting & Handy Services Inc",
    "wof:placetype":"venue"
},
  "geometry": {"coordinates":[-87.75040300000001,41.960292],"type":"Point"}
}