{
  "type": "Feature",
  "properties": {
    "iso:country":"US",
    "sg:address":"25922 S Chestnut Rd",
    "sg:city":"Monee",
    "sg:classifiers":[
        {
            "category":"Personal",
            "type":"Services"
        }
    ],
    "sg:phone":"+1 708 235 0345",
    "sg:postcode":"60449",
    "sg:province":"IL",
    "wof:name":"Voodo Tattoo",
    "wof:placetype":"venue"
},
  "geometry": {"coordinates":[-87.745136,41.419087],"type":"Point"}
}