{
  "type": "Feature",
  "properties": {
    "iso:country":"US",
    "sg:address":"340 W Palatine Rd",
    "sg:city":"Arlington Heights",
    "sg:classifiers":[
        {
            "category":"Building & Trades",
            "subcategory":"Construction",
            "type":"Services"
        }
    ],
    "sg:phone":"+1 847 394 1587",
    "sg:postcode":"60004",
    "sg:province":"IL",
    "sg:tags":[
        "carpentry",
        "general",
        "contractor"
    ],
    "wof:name":"Wolchuk Construction Inc",
    "wof:placetype":"venue"
},
  "geometry": {"coordinates":[-87.989626,42.11016],"type":"Point"}
}