{
  "type": "Feature",
  "properties": {
    "addr:full":"30 N Michigan Ave Ste 726 Chicago IL 60602",
    "addr:housenumber":"30",
    "addr:postcode":"60602",
    "addr:street":"N Michigan Ave Ste 726",
    "iso:country":"US",
    "sg:address":"30 N Michigan Ave Ste 726",
    "sg:city":"Chicago",
    "sg:classifiers":[
        {
            "category":"Health Services",
            "subcategory":"Clinic",
            "type":"Services"
        }
    ],
    "sg:phone":"+1 312 236 7320",
    "sg:postcode":"60602",
    "sg:province":"IL",
    "sg:tags":[
        "medical"
    ],
    "wof:name":"Icon Inc",
    "wof:placetype":"venue"
},
  "geometry": {"coordinates":[-87.624515,41.882504],"type":"Point"}
}