{
  "type": "Feature",
  "properties": {
    "iso:country":"US",
    "sg:address":"530 N Bradley Ave",
    "sg:city":"Chillicothe",
    "sg:classifiers":[
        {
            "category":"Building & Trades",
            "subcategory":"Plumbing",
            "type":"Services"
        }
    ],
    "sg:phone":"+1 309 274 3448",
    "sg:postcode":"61523",
    "sg:province":"IL",
    "sg:tags":[
        "contractor"
    ],
    "wof:name":"Gary Crull Plumbing",
    "wof:placetype":"venue"
},
  "geometry": {"coordinates":[-89.50069000000001,40.915153],"type":"Point"}
}