{
  "type": "Feature",
  "properties": {
    "addr:full":"323 Front St Mc Henry IL 60050",
    "addr:housenumber":"323",
    "addr:postcode":"60050",
    "addr:street":"Front St Mc Henry",
    "iso:country":"US",
    "sg:address":"323 Front St",
    "sg:city":"Mc Henry",
    "sg:classifiers":[
        {
            "category":"Shopping",
            "subcategory":"Florist",
            "type":"Retail Goods"
        }
    ],
    "sg:phone":"+1 815 759 0075",
    "sg:postcode":"60050",
    "sg:province":"IL",
    "wof:name":"Heavenly Scents Flowers & Gift",
    "wof:placetype":"venue"
},
  "geometry": {"coordinates":[-88.27448800000001,42.331346],"type":"Point"}
}