{
  "type": "Feature",
  "properties": {
    "addr:full":"4690 E 3090 N Rd Potomac IL 61865",
    "addr:housenumber":"4690",
    "addr:postcode":"61865",
    "addr:street":"E 3090 N Rd",
    "iso:country":"US",
    "sg:address":"4690 E 3090 N Rd",
    "sg:city":"Potomac",
    "sg:phone":"+1 217 987 6388",
    "sg:postcode":"61865",
    "sg:province":"IL",
    "sg:tags":[
        "beef",
        "farm",
        "corn",
        "soybean",
        "cattle",
        "feedlot"
    ],
    "wof:name":"Jeffery Blackford",
    "wof:placetype":"venue"
},
  "geometry": {"coordinates":[-87.844779,40.31105],"type":"Point"}
}