{
  "type": "Feature",
  "properties": {
    "addr:full":"28 Muirwood Dr Glen Ellyn IL 60137",
    "addr:housenumber":"28",
    "addr:postcode":"60137",
    "addr:street":"Muirwood Dr",
    "iso:country":"US",
    "sg:address":"28 Muirwood Dr",
    "sg:city":"Glen Ellyn",
    "sg:classifiers":[
        {
            "category":"Professional",
            "subcategory":"Management & Consulting",
            "type":"Services"
        }
    ],
    "sg:phone":"+1 630 790 9564",
    "sg:postcode":"60137",
    "sg:province":"IL",
    "sg:tags":[
        "independent",
        "consultant"
    ],
    "wof:name":"William S Aldrich",
    "wof:placetype":"venue"
},
  "geometry": {"coordinates":[-88.06010499999999,41.888977],"type":"Point"}
}