{
  "type": "Feature",
  "properties": {
    "addr:full":"4073 W Algonquin Rd Algonquin IL 60102",
    "addr:housenumber":"4073",
    "addr:postcode":"60102",
    "addr:street":"W Algonquin Rd",
    "iso:country":"US",
    "sg:address":"4073 W Algonquin Rd",
    "sg:city":"Algonquin",
    "sg:classifiers":[
        {
            "category":"Personal",
            "subcategory":"Massage",
            "type":"Services"
        },
        {
            "category":"Personal",
            "subcategory":"Nail Salon",
            "type":"Services"
        }
    ],
    "sg:phone":"+1 847 669 4786",
    "sg:postcode":"60102",
    "sg:province":"IL",
    "wof:name":"Creative Nail Too",
    "wof:placetype":"venue"
},
  "geometry": {"coordinates":[-88.37329800000001,42.175671],"type":"Point"}
}