{
  "type": "Feature",
  "properties": {
    "addr:full":"8623 Wayne Rd Breese IL 62230",
    "addr:housenumber":"8623",
    "addr:postcode":"62230",
    "addr:street":"Wayne Rd",
    "iso:country":"US",
    "sg:address":"8623 Wayne Rd",
    "sg:city":"Breese",
    "sg:classifiers":[
        {
            "category":"Building & Trades",
            "subcategory":"Construction",
            "type":"Services"
        }
    ],
    "sg:phone":"+1 618 526 0014",
    "sg:postcode":"62230",
    "sg:province":"IL",
    "sg:tags":[
        "downspouts",
        "gutter"
    ],
    "wof:name":"Affordable Seamless Gutt",
    "wof:placetype":"venue"
},
  "geometry": {"coordinates":[-89.54365,38.669264],"type":"Point"}
}