{
  "type": "Feature",
  "properties": {
    "iso:country":"US",
    "sg:address":"686 W Boughton Rd",
    "sg:city":"Bolingbrook",
    "sg:classifiers":[
        {
            "category":"Health Services",
            "subcategory":"Doctor",
            "type":"Services"
        }
    ],
    "sg:phone":"+1 630 378 1234",
    "sg:postcode":"60440",
    "sg:province":"IL",
    "sg:tags":[
        "clinic"
    ],
    "wof:name":"Naperbrook Medical Ctr",
    "wof:placetype":"venue"
},
  "geometry": {"coordinates":[-88.091559,41.707162],"type":"Point"}
}