{
  "type": "Feature",
  "properties": {
    "addr:full":"4422 Roosevelt Rd Hillside IL 60162",
    "addr:housenumber":"4422",
    "addr:postcode":"60162",
    "addr:street":"Roosevelt Rd",
    "iso:country":"US",
    "sg:address":"4422 Roosevelt Rd",
    "sg:city":"Hillside",
    "sg:classifiers":[
        {
            "category":"Shopping",
            "subcategory":"Stationery & Office Supplies",
            "type":"Retail Goods"
        },
        {
            "category":"Banks & Credit Unions",
            "subcategory":"Financial Services",
            "type":"Services"
        }
    ],
    "sg:phone":"+1 708 449 6650",
    "sg:postcode":"60162",
    "sg:province":"IL",
    "sg:tags":[
        "register",
        "plans-equipment",
        "cash",
        "card"
    ],
    "sg:website":"http://www.merchants-solutions.com",
    "wof:name":"Merchant Solutions",
    "wof:placetype":"venue"
},
  "geometry": {"coordinates":[-87.892105,41.862996],"type":"Point"}
}