{
  "type": "Feature",
  "properties": {
    "addr:full":"27268 US Hwy 6 Princeton IL 61356",
    "addr:postcode":"27268;61356",
    "addr:street":"Us Hwy 6",
    "iso:country":"US",
    "sg:address":"27268 US Hwy 6",
    "sg:city":"Princeton",
    "sg:classifiers":[
        {
            "category":"Farming",
            "subcategory":"Farm",
            "type":"Manufacturing & Wholesale Goods"
        }
    ],
    "sg:phone":"+1 815 875 4436",
    "sg:postcode":"61356",
    "sg:province":"IL",
    "sg:tags":[
        "mushroom"
    ],
    "wof:name":"Monterey Mushrooms",
    "wof:placetype":"venue"
},
  "geometry": {"coordinates":[-89.325772,41.363417],"type":"Point"}
}