{
  "type": "Feature",
  "properties": {
    "iso:country":"US",
    "sg:address":"5137 W School St",
    "sg:city":"Chicago",
    "sg:classifiers":[
        {
            "category":"Freight",
            "type":"Transportation"
        }
    ],
    "sg:phone":"+1 773 545 6519",
    "sg:postcode":"60641",
    "sg:province":"IL",
    "sg:tags":[
        "operator",
        "local",
        "trucking"
    ],
    "wof:name":"S Arroyo Trucking Inc",
    "wof:placetype":"venue"
},
  "geometry": {"coordinates":[-87.755954,41.940461],"type":"Point"}
}