{
  "type": "Feature",
  "properties": {
    "iso:country":"US",
    "sg:address":"526 Vine St",
    "sg:city":"New Haven",
    "sg:classifiers":[
        {
            "category":"Government",
            "subcategory":"Post Office",
            "type":"Public Place"
        }
    ],
    "sg:phone":"+1 618 265 3293",
    "sg:postcode":"62867",
    "sg:province":"IL",
    "sg:tags":[
        "postal",
        "us"
    ],
    "wof:name":"US Post Office",
    "wof:placetype":"venue"
},
  "geometry": {"coordinates":[-88.12529000000001,37.906724],"type":"Point"}
}