{
  "type": "Feature",
  "properties": {
    "addr:full":"6058 W 63rd St Chicago IL 60638",
    "addr:housenumber":"6058",
    "addr:postcode":"60638",
    "addr:street":"W 63Rd St",
    "iso:country":"US",
    "sg:address":"6058 W 63rd St",
    "sg:city":"Chicago",
    "sg:classifiers":[
        {
            "category":"Bars & Pubs",
            "type":"Food & Drink"
        },
        {
            "category":"Bars & Pubs",
            "subcategory":"Dive Bar",
            "type":"Food & Drink"
        },
        {
            "category":"Bars & Pubs",
            "subcategory":"Lounge",
            "type":"Food & Drink"
        }
    ],
    "sg:phone":"+1 773 586 8177",
    "sg:postcode":"60638",
    "sg:province":"IL",
    "sg:tags":[
        "tavern",
        "cocktail"
    ],
    "wof:name":"Touch of Class Lounge",
    "wof:placetype":"venue"
},
  "geometry": {"coordinates":[-87.77359800000001,41.777901],"type":"Point"}
}