{
  "type": "Feature",
  "properties": {
    "iso:country":"US",
    "sg:address":"604 S Main St",
    "sg:city":"Wilmington",
    "sg:classifiers":[
        {
            "category":"Organizations",
            "subcategory":"Non-profit Organization",
            "type":"Services"
        }
    ],
    "sg:phone":"+1 815 476 7694",
    "sg:postcode":"60481",
    "sg:province":"IL",
    "sg:tags":[
        "charity",
        "foundations-educational",
        "philanthropic",
        "research"
    ],
    "wof:name":"Sister's of Charity",
    "wof:placetype":"venue"
},
  "geometry": {"coordinates":[-88.143602,41.304097],"type":"Point"}
}