{
  "type": "Feature",
  "properties": {
    "addr:full":"3510 W Franklin Blvd Chicago IL 60624",
    "addr:housenumber":"3510",
    "addr:postcode":"60624",
    "addr:street":"W Franklin Blvd",
    "iso:country":"US",
    "sg:address":"3510 W Franklin Blvd",
    "sg:city":"Chicago",
    "sg:classifiers":[
        {
            "category":"Professional",
            "subcategory":"Lawyer & Legal Services",
            "type":"Services"
        }
    ],
    "sg:phone":"+1 773 533 0243",
    "sg:postcode":"60624",
    "sg:province":"IL",
    "sg:tags":[
        "living",
        "estate",
        "planning",
        "trust",
        "probate"
    ],
    "wof:name":"Smart Money Foundation",
    "wof:placetype":"venue"
},
  "geometry": {"coordinates":[-87.71413800000001,41.890233],"type":"Point"}
}