{
  "type": "Feature",
  "properties": {
    "iso:country":"US",
    "sg:address":"114 N Emmett St",
    "sg:city":"Genoa",
    "sg:classifiers":[
        {
            "category":"Retail",
            "subcategory":"Auto Repair",
            "type":"Services"
        }
    ],
    "sg:phone":"+1 815 784 3400",
    "sg:postcode":"60135",
    "sg:province":"IL",
    "sg:tags":[
        "body",
        "automobile",
        "painting"
    ],
    "wof:name":"Genoa Auto Body",
    "wof:placetype":"venue"
},
  "geometry": {"coordinates":[-88.694086,42.098303],"type":"Point"}
}