{
  "type": "Feature",
  "properties": {
    "iso:country":"US",
    "sg:address":"12215 Cashlenan Ln",
    "sg:city":"New Lenox",
    "sg:classifiers":[
        {
            "category":"Professional",
            "subcategory":"Advertising",
            "type":"Services"
        }
    ],
    "sg:phone":"+1 815 463 9229",
    "sg:postcode":"60451",
    "sg:province":"IL",
    "sg:tags":[
        "representative"
    ],
    "wof:name":"Natco Assoc",
    "wof:placetype":"venue"
},
  "geometry": {"coordinates":[-87.912959,41.470188],"type":"Point"}
}