{
  "type": "Feature",
  "properties": {
    "iso:country":"US",
    "sg:address":"5752 W Belmont Avenue",
    "sg:city":"Chicago",
    "sg:classifiers":[
        {
            "category":"Insurance",
            "subcategory":"Health Insurance",
            "type":"Services"
        }
    ],
    "sg:phone":"+1 773 777 6151",
    "sg:postcode":"60634",
    "sg:province":"IL",
    "sg:tags":[
        "market"
    ],
    "wof:name":"Health Through Nature",
    "wof:placetype":"venue"
},
  "geometry": {"coordinates":[-87.7709,41.938538],"type":"Point"}
}