{
  "type": "Feature",
  "properties": {
    "addr:full":"9424 Kilbourn Ave Skokie IL 60076",
    "addr:housenumber":"9424",
    "addr:postcode":"60076",
    "addr:street":"Kilbourn Ave",
    "iso:country":"US",
    "sg:address":"9424 Kilbourn Ave",
    "sg:city":"Skokie",
    "sg:classifiers":[
        {
            "category":"Building & Trades",
            "subcategory":"Electrical",
            "type":"Services"
        }
    ],
    "sg:phone":"+1 847 983 0306",
    "sg:postcode":"60076",
    "sg:province":"IL",
    "sg:tags":[
        "school",
        "processing",
        "datum",
        "contractor",
        "computer",
        "electrical",
        "r"
    ],
    "wof:name":"AB Computer Consultant",
    "wof:placetype":"venue"
},
  "geometry": {"coordinates":[-87.73945399999999,42.052075],"type":"Point"}
}