{
  "type": "Feature",
  "properties": {
    "iso:country":"US",
    "sg:address":"675 N Saint Clair St",
    "sg:city":"Chicago",
    "sg:classifiers":[
        {
            "category":"Health Services",
            "subcategory":"Doctor",
            "type":"Services"
        }
    ],
    "sg:phone":"+1 312 695 8628",
    "sg:postcode":"60611",
    "sg:province":"IL",
    "wof:name":"Sharma Leena MD",
    "wof:placetype":"venue"
},
  "geometry": {"coordinates":[-87.622704,41.894199],"type":"Point"}
}