{
  "type": "Feature",
  "properties": {
    "iso:country":"US",
    "sg:address":"1317 W Taylor St",
    "sg:city":"Chicago",
    "sg:classifiers":[
        {
            "category":"Banks & Credit Unions",
            "subcategory":"Financial Services",
            "type":"Services"
        }
    ],
    "sg:phone":"+1 312 421 0011",
    "sg:postcode":"60607",
    "sg:province":"IL",
    "sg:tags":[
        "broker",
        "mortgage"
    ],
    "wof:name":"Park Place Financial",
    "wof:placetype":"venue"
},
  "geometry": {"coordinates":[-87.65969800000001,41.869301],"type":"Point"}
}