{
  "type": "Feature",
  "properties": {
    "addr:full":"122 S Michigan Avenue Lbby 6 Chicago IL 60603",
    "addr:housenumber":"122;6",
    "addr:postcode":"60603",
    "addr:street":"S Michigan Avenue Lbby",
    "iso:country":"US",
    "sg:address":"122 S Michigan Avenue Lbby 6",
    "sg:city":"Chicago",
    "sg:classifiers":[
        {
            "category":"Professional",
            "subcategory":"Lawyer & Legal Services",
            "type":"Services"
        },
        {
            "category":"Building & Trades",
            "subcategory":"Construction",
            "type":"Services"
        }
    ],
    "sg:phone":"+1 312 663 4631",
    "sg:postcode":"60603",
    "sg:province":"IL",
    "sg:tags":[
        "interior",
        "design"
    ],
    "wof:name":"Nakamon Design",
    "wof:placetype":"venue"
},
  "geometry": {"coordinates":[-87.62444499999999,41.880523],"type":"Point"}
}