{
  "type": "Feature",
  "properties": {
    "iso:country":"US",
    "sg:address":"5000 38th Ave",
    "sg:city":"Moline",
    "sg:classifiers":[
        {
            "category":"Sports & Exercise",
            "subcategory":"Golf",
            "type":"Entertainment"
        }
    ],
    "sg:phone":"+1 309 762 7160",
    "sg:postcode":"61265",
    "sg:province":"IL",
    "sg:tags":[
        "mini"
    ],
    "wof:name":"River Valley Golf",
    "wof:placetype":"venue"
},
  "geometry": {"coordinates":[-90.493599,41.487499],"type":"Point"}
}