{
  "type": "Feature",
  "properties": {
    "iso:country":"US",
    "sg:address":"1108 N 14th Ave",
    "sg:city":"Melrose Park",
    "sg:classifiers":[
        {
            "category":"Building & Trades",
            "subcategory":"Construction",
            "type":"Services"
        }
    ],
    "sg:phone":"+1 708 344 0190",
    "sg:postcode":"60160",
    "sg:province":"IL",
    "sg:tags":[
        "contractor"
    ],
    "wof:name":"A & B Environmental Construction",
    "wof:placetype":"venue"
},
  "geometry": {"coordinates":[-87.85079500000001,41.897043],"type":"Point"}
}