{
  "type": "Feature",
  "properties": {
    "iso:country":"US",
    "sg:address":"531 W Independence Ave",
    "sg:city":"Jacksonville",
    "sg:classifiers":[
        {
            "category":"Manufacturing",
            "subcategory":"Tools & Machinery",
            "type":"Manufacturing & Wholesale Goods"
        }
    ],
    "sg:phone":"+1 217 243 5849",
    "sg:postcode":"62650",
    "sg:province":"IL",
    "sg:tags":[
        "machine",
        "shop"
    ],
    "wof:name":"Birdsell's Machine Shop",
    "wof:placetype":"venue"
},
  "geometry": {"coordinates":[-90.237415,39.741541],"type":"Point"}
}