{
  "type": "Feature",
  "properties": {
    "iso:country":"US",
    "sg:address":"315 N Rand Rd",
    "sg:city":"Lake Zurich",
    "sg:classifiers":[
        {
            "category":"Shopping",
            "subcategory":"Hobbies, Toys, & Games",
            "type":"Retail Goods"
        }
    ],
    "sg:phone":"+1   ",
    "sg:postcode":"60047",
    "sg:province":"IL",
    "sg:website":"www.learningexpress.com",
    "wof:name":"Learning Express",
    "wof:placetype":"venue"
},
  "geometry": {"coordinates":[-88.108118,42.191749],"type":"Point"}
}