{
  "type": "Feature",
  "properties": {
    "addr:full":"1654 Elevator Rd Sorento IL 62086",
    "addr:housenumber":"1654",
    "addr:postcode":"62086",
    "addr:street":"Elevator Rd",
    "iso:country":"US",
    "sg:address":"1654 Elevator Rd",
    "sg:city":"Sorento",
    "sg:classifiers":[
        {
            "category":"Education",
            "subcategory":"School",
            "type":"Public Place"
        }
    ],
    "sg:phone":"+1 217 272 4639",
    "sg:postcode":"62086",
    "sg:province":"IL",
    "wof:name":"Metro Christian Academy",
    "wof:placetype":"venue"
},
  "geometry": {"coordinates":[-89.615458,38.992361],"type":"Point"}
}