{
  "type": "Feature",
  "properties": {
    "iso:country":"US",
    "sg:address":"608 E Golf Rd",
    "sg:city":"Arlington Hts",
    "sg:classifiers":[
        {
            "category":"Personal",
            "subcategory":"Beauty Salon",
            "type":"Services"
        }
    ],
    "sg:phone":"+1 847 593 9003",
    "sg:postcode":"60005",
    "sg:province":"IL",
    "sg:tags":[
        "manicuring"
    ],
    "wof:name":"American Nails",
    "wof:placetype":"venue"
},
  "geometry": {"coordinates":[-87.972825,42.051465],"type":"Point"}
}