{
  "type": "Feature",
  "properties": {
    "iso:country":"US",
    "sg:address":"719 Arlington Heights Rd",
    "sg:city":"Arlington Heights",
    "sg:classifiers":[
        {
            "category":"Shopping",
            "subcategory":"Computers & Home Electronics",
            "type":"Retail Goods"
        }
    ],
    "sg:phone":"+1   ",
    "sg:postcode":"60005",
    "sg:province":"IL",
    "sg:tags":[
        "machine",
        "fax",
        "copier"
    ],
    "wof:name":"Advanced Business Tech Inc",
    "wof:placetype":"venue"
},
  "geometry": {"coordinates":[-87.980399,42.070455],"type":"Point"}
}