{
  "type": "Feature",
  "properties": {
    "addr:full":"399 Wall St Ste N Glendale Heights IL 60139",
    "addr:housenumber":"399",
    "addr:postcode":"60139",
    "addr:street":"Wall St Ste N",
    "iso:country":"US",
    "sg:address":"399 Wall St Ste N",
    "sg:city":"Glendale Heights",
    "sg:classifiers":[
        {
            "category":"Building & Trades",
            "subcategory":"Construction",
            "type":"Services"
        }
    ],
    "sg:phone":"+1 630 980 4364",
    "sg:postcode":"60139",
    "sg:province":"IL",
    "sg:tags":[
        "contractor"
    ],
    "sg:website":"www.nittidevelopment.com",
    "wof:name":"Nitti Custom Builders",
    "wof:placetype":"venue"
},
  "geometry": {"coordinates":[-88.097729,41.935069],"type":"Point"}
}