{
  "type": "Feature",
  "properties": {
    "addr:full":"180 Southgate Dr Vernon Hills IL 60061",
    "addr:housenumber":"180",
    "addr:postcode":"60061",
    "addr:street":"Southgate Dr",
    "iso:country":"US",
    "sg:address":"180 Southgate Dr",
    "sg:city":"Vernon Hills",
    "sg:classifiers":[
        {
            "category":"Professional",
            "subcategory":"Management & Consulting",
            "type":"Services"
        }
    ],
    "sg:phone":"+1 847 549 6247",
    "sg:postcode":"60061",
    "sg:province":"IL",
    "wof:name":"Pine Consulting Group Inc",
    "wof:placetype":"venue"
},
  "geometry": {"coordinates":[-87.974209,42.221692],"type":"Point"}
}