{
  "type": "Feature",
  "properties": {
    "iso:country":"US",
    "sg:address":"601 S Main St",
    "sg:city":"Buffalo",
    "sg:phone":"+1 217 364 4994",
    "sg:postcode":"62515",
    "sg:province":"IL",
    "sg:tags":[
        "farm",
        "corn",
        "soybean"
    ],
    "wof:name":"George Leka",
    "wof:placetype":"venue"
},
  "geometry": {"coordinates":[-89.40606699999999,39.847166],"type":"Point"}
}