{
  "type": "Feature",
  "properties": {
    "iso:country":"US",
    "sg:address":"5043 W Eddy St",
    "sg:city":"Chicago",
    "sg:classifiers":[
        {
            "category":"Building & Trades",
            "subcategory":"Electrical",
            "type":"Services"
        }
    ],
    "sg:phone":"+1 773 286 9532",
    "sg:postcode":"60641",
    "sg:province":"IL",
    "sg:tags":[
        "electrical",
        "contractor"
    ],
    "wof:name":"Arad Electric Inc",
    "wof:placetype":"venue"
},
  "geometry": {"coordinates":[-87.755864,41.945082],"type":"Point"}
}