{
  "type": "Feature",
  "properties": {
    "iso:country":"US",
    "sg:address":"607 S Wright St",
    "sg:city":"Champaign",
    "sg:classifiers":[
        {
            "category":"Restaurant",
            "type":"Food & Drink"
        }
    ],
    "sg:phone":"+1 217 355 5569",
    "sg:postcode":"61820",
    "sg:province":"IL",
    "sg:tags":[
        "korean"
    ],
    "wof:name":"A-Rl-Rang",
    "wof:placetype":"venue"
},
  "geometry": {"coordinates":[-88.228798,40.111401],"type":"Point"}
}