{
  "type": "Feature",
  "properties": {
    "iso:country":"US",
    "sg:address":"1260 W Northwest Hwy # 900",
    "sg:city":"Palatine",
    "sg:classifiers":[
        {
            "category":"Insurance",
            "subcategory":"Hazard Insurance",
            "type":"Services"
        }
    ],
    "sg:phone":"+1 630 324 2500",
    "sg:postcode":"60067",
    "sg:province":"IL",
    "wof:name":"Hilb Rogal & Hobbs Of Illinois, Inc.",
    "wof:placetype":"venue"
},
  "geometry": {"coordinates":[-88.074674,42.125085],"type":"Point"}
}