{
  "type": "Feature",
  "properties": {
    "addr:full":"1157 Rovey Ave Farmersville IL 62533",
    "addr:housenumber":"1157",
    "addr:postcode":"62533",
    "addr:street":"Rovey Ave",
    "iso:country":"US",
    "sg:address":"1157 Rovey Ave",
    "sg:city":"Farmersville",
    "sg:classifiers":[
        {
            "category":"Home & Garden",
            "subcategory":"Garden Supply",
            "type":"Retail Goods"
        },
        {
            "category":"Food & Beverages",
            "subcategory":"Farmers Market",
            "type":"Retail Goods"
        },
        {
            "category":"Farming",
            "subcategory":"Nursery",
            "type":"Manufacturing & Wholesale Goods"
        }
    ],
    "sg:phone":"+1 217 227 4541",
    "sg:postcode":"62533",
    "sg:province":"IL",
    "sg:tags":[
        "bulbs-wholesale",
        "equipment",
        "seed",
        "grower",
        "bulb",
        "growers'"
    ],
    "wof:name":"Rovey Seed Co",
    "wof:placetype":"venue"
},
  "geometry": {"coordinates":[-89.681331,39.472341],"type":"Point"}
}