{
  "type": "Feature",
  "properties": {
    "iso:country":"US",
    "sg:address":"209 Kingspoint Dr",
    "sg:city":"Sherman",
    "sg:classifiers":[
        {
            "category":"Real Estate",
            "subcategory":"Real Estate Agent",
            "type":"Services"
        }
    ],
    "sg:phone":"+1 217 496 3238",
    "sg:postcode":"62684",
    "sg:province":"IL",
    "wof:name":"H&S Partnership",
    "wof:placetype":"venue"
},
  "geometry": {"coordinates":[-89.61113,39.89911],"type":"Point"}
}