{
  "type": "Feature",
  "properties": {
    "iso:country":"US",
    "sg:address":"1 N Walnut St",
    "sg:city":"Danville",
    "sg:classifiers":[
        {
            "category":"Organizations",
            "subcategory":"Membership Organization",
            "type":"Services"
        }
    ],
    "sg:phone":"+1 217 431 0285",
    "sg:postcode":"61832",
    "sg:province":"IL",
    "sg:tags":[
        "club",
        "auto",
        "carrier",
        "insurance"
    ],
    "wof:name":"AAA Danville",
    "wof:placetype":"venue"
},
  "geometry": {"coordinates":[-87.631329,40.12634],"type":"Point"}
}