{
  "type": "Feature",
  "properties": {
    "iso:country":"US",
    "sg:address":"3414 Clinton Ave",
    "sg:city":"Berwyn",
    "sg:classifiers":[
        {
            "category":"Shopping",
            "subcategory":"Bicycles & Sporting Goods",
            "type":"Retail Goods"
        }
    ],
    "sg:phone":"+1   ",
    "sg:postcode":"60402",
    "sg:province":"IL",
    "wof:name":"Jj Custom Guns",
    "wof:placetype":"venue"
},
  "geometry": {"coordinates":[-87.796444,41.830206],"type":"Point"}
}