{
  "type": "Feature",
  "properties": {
    "addr:full":"115 Kansas St Frankfort IL 60423",
    "addr:postcode":"60423",
    "addr:street":"115 Kansas St",
    "iso:country":"US",
    "sg:address":"115 Kansas St",
    "sg:city":"Frankfort",
    "sg:classifiers":[
        {
            "category":"Shopping",
            "subcategory":"Gifts & Souvenirs",
            "type":"Retail Goods"
        }
    ],
    "sg:phone":"+1 815 806 1807",
    "sg:postcode":"60423",
    "sg:province":"IL",
    "wof:name":"Comfort Crafts",
    "wof:placetype":"venue"
},
  "geometry": {"coordinates":[-87.852116,41.498532],"type":"Point"}
}