{
  "type": "Feature",
  "properties": {
    "addr:full":"6509 1/2 W Archer Ave Chicago IL 60638",
    "addr:housenumber":"6509 1 / 2",
    "addr:postcode":"60638",
    "addr:street":"W Archer Ave",
    "iso:country":"US",
    "sg:address":"6509 1/2 W Archer Ave",
    "sg:city":"Chicago",
    "sg:classifiers":[
        {
            "category":"Personal",
            "subcategory":"Beauty Salon",
            "type":"Services"
        },
        {
            "category":"Personal",
            "subcategory":"Barber",
            "type":"Services"
        }
    ],
    "sg:phone":"+1 773 586 7814",
    "sg:postcode":"60638",
    "sg:province":"IL",
    "sg:tags":[
        "hair",
        "stylist"
    ],
    "wof:name":"Andy's Barber Shop",
    "wof:placetype":"venue"
},
  "geometry": {"coordinates":[-87.784689,41.792269],"type":"Point"}
}