{
  "type": "Feature",
  "properties": {
    "iso:country":"US",
    "sg:address":"14831 Pine Tree Rd",
    "sg:city":"Orland Park",
    "sg:classifiers":[
        {
            "category":"Health Services",
            "subcategory":"Clinic",
            "type":"Services"
        }
    ],
    "sg:phone":"+1 708 349 7106",
    "sg:postcode":"60462",
    "sg:province":"IL",
    "wof:name":"Complete Wellness Center SC",
    "wof:placetype":"venue"
},
  "geometry": {"coordinates":[-87.880003,41.620553],"type":"Point"}
}