{
  "type": "Feature",
  "properties": {
    "iso:country":"US",
    "sg:address":"115 Campbell St",
    "sg:city":"Geneva",
    "sg:classifiers":[
        {
            "category":"Shopping",
            "subcategory":"Computers & Home Electronics",
            "type":"Retail Goods"
        }
    ],
    "sg:phone":"+1 630 845 9416",
    "sg:postcode":"60134",
    "sg:province":"IL",
    "sg:tags":[
        "software"
    ],
    "wof:name":"W S Packaging",
    "wof:placetype":"venue"
},
  "geometry": {"coordinates":[-88.306821,41.885695],"type":"Point"}
}