{
  "type": "Feature",
  "properties": {
    "iso:country":"US",
    "sg:address":"304 W Kimball Rd",
    "sg:city":"Tampico",
    "sg:classifiers":[
        {
            "category":"Education",
            "subcategory":"School",
            "type":"Public Place"
        }
    ],
    "sg:phone":"+1 815 438 3085",
    "sg:postcode":"61283",
    "sg:province":"IL",
    "wof:name":"Tampico Middle School",
    "wof:placetype":"venue"
},
  "geometry": {"coordinates":[-89.788653,41.627587],"type":"Point"}
}