{
  "type": "Feature",
  "properties": {
    "iso:country":"US",
    "sg:address":"201 W Main St",
    "sg:city":"West Frankfort",
    "sg:classifiers":[
        {
            "category":"Retail",
            "subcategory":"Auto Repair",
            "type":"Services"
        }
    ],
    "sg:phone":"+1 618 937 4515",
    "sg:postcode":"62896",
    "sg:province":"IL",
    "sg:tags":[
        "automotive"
    ],
    "wof:name":"Neibch Towing Service",
    "wof:placetype":"venue"
},
  "geometry": {"coordinates":[-88.929867,37.897948],"type":"Point"}
}