{
  "type": "Feature",
  "properties": {
    "addr:full":"9831 Sussex Ct Mokena IL 60448",
    "addr:housenumber":"9831",
    "addr:postcode":"60448",
    "addr:street":"Sussex Ct",
    "iso:country":"US",
    "sg:address":"9831 Sussex Ct",
    "sg:city":"Mokena",
    "sg:classifiers":[
        {
            "category":"Wholesale",
            "subcategory":"Vending Machines",
            "type":"Manufacturing & Wholesale Goods"
        }
    ],
    "sg:phone":"+1   ",
    "sg:postcode":"60448",
    "sg:province":"IL",
    "sg:tags":[
        "operator"
    ],
    "wof:name":"J&K Vending Inc",
    "wof:placetype":"venue"
},
  "geometry": {"coordinates":[-87.85798200000001,41.533463],"type":"Point"}
}