{
  "type": "Feature",
  "properties": {
    "addr:full":"5110 Oakton St Skokie IL 60077",
    "addr:housenumber":"5110",
    "addr:postcode":"60077",
    "addr:street":"Oakton St",
    "iso:country":"US",
    "sg:address":"5110 Oakton St",
    "sg:city":"Skokie",
    "sg:classifiers":[
        {
            "category":"Banks & Credit Unions",
            "subcategory":"Bank",
            "type":"Services"
        }
    ],
    "sg:phone":"+1 847 673 4497",
    "sg:postcode":"60077",
    "sg:province":"IL",
    "sg:tags":[
        "currency",
        "exchange"
    ],
    "wof:name":"Lincoln Okton Crrency Exch Inc",
    "wof:placetype":"venue"
},
  "geometry": {"coordinates":[-87.755621,42.026407],"type":"Point"}
}