{
  "type": "Feature",
  "properties": {
    "iso:country":"US",
    "sg:address":"9636 W 143rd St",
    "sg:city":"Orland Park",
    "sg:classifiers":[
        {
            "category":"Shopping",
            "subcategory":"Florist",
            "type":"Retail Goods"
        }
    ],
    "sg:phone":"+1 708 349 3200",
    "sg:postcode":"60462",
    "sg:province":"IL",
    "wof:name":"Bloomingfields Florist",
    "wof:placetype":"venue"
},
  "geometry": {"coordinates":[-87.854459,41.630552],"type":"Point"}
}