{
  "type": "Feature",
  "properties": {
    "iso:country":"US",
    "sg:address":"4320 W Madison St",
    "sg:city":"Chicago",
    "sg:classifiers":[
        {
            "category":"Community Center",
            "type":"Public Place"
        }
    ],
    "sg:phone":"+1 773 921 3632",
    "sg:postcode":"60624",
    "sg:province":"IL",
    "sg:tags":[
        "medical"
    ],
    "wof:name":"Family Wellness Center",
    "wof:placetype":"venue"
},
  "geometry": {"coordinates":[-87.7341,41.880699],"type":"Point"}
}