{
  "type": "Feature",
  "properties": {
    "iso:country":"US",
    "sg:address":"1046 McDonough Lake Rd",
    "sg:city":"Collinsville",
    "sg:classifiers":[
        {
            "category":"Arena",
            "subcategory":"Sports Club",
            "type":"Entertainment"
        }
    ],
    "sg:phone":"+1 618 346 2559",
    "sg:postcode":"62234",
    "sg:province":"IL",
    "sg:tags":[
        "soccer"
    ],
    "wof:name":"Metro FC",
    "wof:placetype":"venue"
},
  "geometry": {"coordinates":[-90.018248,38.695154],"type":"Point"}
}