{
  "type": "Feature",
  "properties": {
    "iso:country":"US",
    "sg:address":"1802 Washington Ave",
    "sg:city":"Alton",
    "sg:classifiers":[
        {
            "category":"Wholesale",
            "subcategory":"Machinery & Supplies",
            "type":"Manufacturing & Wholesale Goods"
        }
    ],
    "sg:phone":"+1 618 465 7230",
    "sg:postcode":"62002",
    "sg:province":"IL",
    "sg:tags":[
        "equipment",
        "establishment"
    ],
    "wof:name":"Tomorrows Beauty Sup & Fashion",
    "wof:placetype":"venue"
},
  "geometry": {"coordinates":[-90.149907,38.905645],"type":"Point"}
}