{
  "type": "Feature",
  "properties": {
    "iso:country":"US",
    "sg:address":"413 Green Haven Dr",
    "sg:city":"Swansea",
    "sg:classifiers":[
        {
            "category":"Shopping",
            "subcategory":"Bicycles & Sporting Goods",
            "type":"Retail Goods"
        }
    ],
    "sg:phone":"+1 618 257 9540",
    "sg:postcode":"62226",
    "sg:province":"IL",
    "wof:name":"Open Season Inc",
    "wof:placetype":"venue"
},
  "geometry": {"coordinates":[-89.988201,38.564058],"type":"Point"}
}