{
  "type": "Feature",
  "properties": {
    "iso:country":"US",
    "sg:address":"6048 N Francisco Ave 2",
    "sg:city":"Chicago",
    "sg:classifiers":[
        {
            "category":"Real Estate",
            "subcategory":"Real Estate Services",
            "type":"Services"
        },
        {
            "category":"Banks & Credit Unions",
            "subcategory":"Financial Services",
            "type":"Services"
        }
    ],
    "sg:phone":"+1 773 338 0554",
    "sg:postcode":"60659",
    "sg:province":"IL",
    "sg:tags":[
        "loan",
        "processing"
    ],
    "wof:name":"Express Mortage Ci",
    "wof:placetype":"venue"
},
  "geometry": {"coordinates":[-87.701847,41.991293],"type":"Point"}
}