{
  "type": "Feature",
  "properties": {
    "addr:full":"2700 Touhy Ave Elk Grove Vlg IL 60007",
    "addr:housenumber":"2700",
    "addr:postcode":"60007",
    "addr:street":"Touhy Ave",
    "iso:country":"US",
    "sg:address":"2700 Touhy Ave",
    "sg:city":"Elk Grove Vlg",
    "sg:classifiers":[
        {
            "category":"Manufacturing",
            "subcategory":"Electronics",
            "type":"Manufacturing & Wholesale Goods"
        }
    ],
    "sg:phone":"+1 847 364 4848",
    "sg:postcode":"60007",
    "sg:province":"IL",
    "sg:tags":[
        "printed",
        "mfg",
        "boards",
        "circuit",
        "etched"
    ],
    "sg:website":"www.pcb.com",
    "wof:name":"Electronic Interconnect Corp",
    "wof:placetype":"venue"
},
  "geometry": {"coordinates":[-87.93832,42.008193],"type":"Point"}
}