{
  "type": "Feature",
  "properties": {
    "addr:full":"7344 W 90th St Bridgeview IL 60455",
    "addr:housenumber":"7344",
    "addr:postcode":"60455",
    "addr:street":"W 90Th St",
    "iso:country":"US",
    "sg:address":"7344 W 90th St",
    "sg:city":"Bridgeview",
    "sg:classifiers":[
        {
            "category":"Building & Trades",
            "subcategory":"Electrical",
            "type":"Services"
        }
    ],
    "sg:phone":"+1 708 430 4130",
    "sg:postcode":"60455",
    "sg:province":"IL",
    "sg:tags":[
        "electrician",
        "contractor"
    ],
    "wof:name":"Arcore Electric",
    "wof:placetype":"venue"
},
  "geometry": {"coordinates":[-87.802299,41.728001],"type":"Point"}
}