{
  "type": "Feature",
  "properties": {
    "iso:country":"US",
    "sg:address":"1335 W 90th St",
    "sg:city":"Chicago",
    "sg:classifiers":[
        {
            "category":"Social Services",
            "subcategory":"Child Care",
            "type":"Services"
        }
    ],
    "sg:phone":"+1 773 881 0840",
    "sg:postcode":"60620",
    "sg:province":"IL",
    "sg:tags":[
        "day"
    ],
    "wof:name":"Irene's Quality Day Care",
    "wof:placetype":"venue"
},
  "geometry": {"coordinates":[-87.65720399999999,41.730301],"type":"Point"}
}