{
  "type": "Feature",
  "properties": {
    "iso:country":"US",
    "sg:address":"613 N 7th St",
    "sg:city":"Springfield",
    "sg:classifiers":[
        {
            "category":"Health Services",
            "subcategory":"Dentist",
            "type":"Services"
        }
    ],
    "sg:phone":"+1 217 525 6980",
    "sg:postcode":"62702",
    "sg:province":"IL",
    "sg:tags":[
        "denture",
        "dentists-prosthodontists"
    ],
    "sg:website":"http://www.keithcummins.com",
    "wof:name":"Cummins Keith C Dmd",
    "wof:placetype":"venue"
},
  "geometry": {"coordinates":[-89.646277,39.80741],"type":"Point"}
}