{
  "type": "Feature",
  "properties": {
    "iso:country":"US",
    "sg:address":"419 S Sangamon Ave",
    "sg:city":"Gibson City",
    "sg:classifiers":[
        {
            "category":"Wholesale",
            "subcategory":"Farm Supplies",
            "type":"Manufacturing & Wholesale Goods"
        }
    ],
    "sg:phone":"+1 217 784 8693",
    "sg:postcode":"60936",
    "sg:province":"IL",
    "sg:tags":[
        "grain"
    ],
    "wof:name":"Cargill Inc",
    "wof:placetype":"venue"
},
  "geometry": {"coordinates":[-88.375394,40.461067],"type":"Point"}
}