{
  "type": "Feature",
  "properties": {
    "iso:country":"US",
    "sg:address":"115 N 1st St",
    "sg:city":"Girard",
    "sg:classifiers":[
        {
            "category":"Government",
            "subcategory":"Fire Station",
            "type":"Public Place"
        }
    ],
    "sg:phone":"+1 217 627 2345",
    "sg:postcode":"62640",
    "sg:province":"IL",
    "sg:tags":[
        "department"
    ],
    "wof:name":"Girard Fire Protection Dist",
    "wof:placetype":"venue"
},
  "geometry": {"coordinates":[-89.77764999999999,39.446724],"type":"Point"}
}