{
  "type": "Feature",
  "properties": {
    "iso:country":"US",
    "sg:address":"427 Sheridan Rd",
    "sg:city":"Kenilworth",
    "sg:classifiers":[
        {
            "category":"Professional",
            "subcategory":"Management & Consulting",
            "type":"Services"
        }
    ],
    "sg:phone":"+1 847 251 4388",
    "sg:postcode":"60043",
    "sg:province":"IL",
    "sg:tags":[
        "business"
    ],
    "wof:name":"Haynes Wj & Co",
    "wof:placetype":"venue"
},
  "geometry": {"coordinates":[-87.711205,42.093571],"type":"Point"}
}