{
  "type": "Feature",
  "properties": {
    "addr:full":"202 N Cherry St Morrison IL 61270",
    "addr:housenumber":"202",
    "addr:postcode":"61270",
    "addr:street":"N Cherry St",
    "iso:country":"US",
    "sg:address":"202 N Cherry St",
    "sg:city":"Morrison",
    "sg:classifiers":[
        {
            "category":"Personal",
            "subcategory":"Beauty Salon",
            "type":"Services"
        }
    ],
    "sg:phone":"+1 815 772 4441",
    "sg:postcode":"61270",
    "sg:province":"IL",
    "wof:name":"Design Line Connection",
    "wof:placetype":"venue"
},
  "geometry": {"coordinates":[-89.96615199999999,41.807571],"type":"Point"}
}