{
  "type": "Feature",
  "properties": {
    "iso:country":"US",
    "sg:address":"9 Western Dr",
    "sg:city":"Decatur",
    "sg:classifiers":[
        {
            "category":"Manufacturing",
            "subcategory":"Buildings",
            "type":"Manufacturing & Wholesale Goods"
        },
        {
            "category":"Building & Trades",
            "subcategory":"Construction",
            "type":"Services"
        }
    ],
    "sg:phone":"+1 217 429 2138",
    "sg:postcode":"62521",
    "sg:province":"IL",
    "sg:tags":[
        "home",
        "builder",
        "contractor"
    ],
    "wof:name":"Cherry Builders",
    "wof:placetype":"venue"
},
  "geometry": {"coordinates":[-88.914871,39.81752],"type":"Point"}
}