{
  "type": "Feature",
  "properties": {
    "iso:country":"US",
    "sg:address":"415 Whitney Ave",
    "sg:city":"Joliet",
    "sg:classifiers":[
        {
            "category":"Shopping",
            "subcategory":"Computers & Home Electronics",
            "type":"Retail Goods"
        }
    ],
    "sg:phone":"+1 815 727 9498",
    "sg:postcode":"60435",
    "sg:province":"IL",
    "sg:tags":[
        "publishing"
    ],
    "wof:name":"Creative Image",
    "wof:placetype":"venue"
},
  "geometry": {"coordinates":[-88.09734400000001,41.531675],"type":"Point"}
}