{
  "type": "Feature",
  "properties": {
    "addr:full":"4884 S Archer Avenue Chicago IL 60632",
    "addr:housenumber":"4884",
    "addr:postcode":"60632",
    "addr:street":"S Archer Avenue",
    "iso:country":"US",
    "sg:address":"4884 S Archer Avenue",
    "sg:city":"Chicago",
    "sg:classifiers":[
        {
            "category":"Food & Beverages",
            "subcategory":"Groceries & Convenience Stores",
            "type":"Retail Goods"
        }
    ],
    "sg:phone":"+1 773 847 4660",
    "sg:postcode":"60632",
    "sg:province":"IL",
    "wof:name":"7-9-11 Food Mart",
    "wof:placetype":"venue"
},
  "geometry": {"coordinates":[-87.72027199999999,41.804287],"type":"Point"}
}