{
  "type": "Feature",
  "properties": {
    "addr:full":"219 W McGaughey St Worden IL 62097",
    "addr:housenumber":"219",
    "addr:postcode":"62097",
    "addr:street":"W Mcgaughey St",
    "iso:country":"US",
    "sg:address":"219 W McGaughey St",
    "sg:city":"Worden",
    "sg:classifiers":[
        {
            "category":"Education",
            "subcategory":"School",
            "type":"Public Place"
        }
    ],
    "sg:phone":"+1 618 459 3621",
    "sg:postcode":"62097",
    "sg:province":"IL",
    "wof:name":"Trinity St Paul Lutheran",
    "wof:placetype":"venue"
},
  "geometry": {"coordinates":[-89.844458,38.928796],"type":"Point"}
}