{
  "type": "Feature",
  "properties": {
    "iso:country":"US",
    "sg:address":"150 S Gary Ave",
    "sg:city":"Carol Stream",
    "sg:classifiers":[
        {
            "category":"Retail",
            "subcategory":"Auto Rental",
            "type":"Services"
        }
    ],
    "sg:phone":"+1 630 221 9800",
    "sg:postcode":"60188",
    "sg:province":"IL",
    "sg:tags":[
        "car"
    ],
    "wof:name":"Avis",
    "wof:placetype":"venue"
},
  "geometry": {"coordinates":[-88.120823,41.901638],"type":"Point"}
}