{
  "type": "Feature",
  "properties": {
    "addr:full":"1 Wood Ct Bolingbrook IL 60440",
    "addr:housenumber":"1",
    "addr:postcode":"60440",
    "addr:street":"Wood Ct",
    "iso:country":"US",
    "sg:address":"1 Wood Ct",
    "sg:city":"Bolingbrook",
    "sg:classifiers":[
        {
            "category":"Insurance",
            "subcategory":"Insurance Agent",
            "type":"Services"
        }
    ],
    "sg:phone":"+1 630 759 1331",
    "sg:postcode":"60440",
    "sg:province":"IL",
    "wof:name":"State Farm Insurance",
    "wof:placetype":"venue"
},
  "geometry": {"coordinates":[-88.11703799999999,41.703352],"type":"Point"}
}