{
  "type": "Feature",
  "properties": {
    "iso:country":"US",
    "sg:address":"3916 5th Ave",
    "sg:city":"Rock Island",
    "sg:classifiers":[
        {
            "category":"Autos & Motor Vehicles",
            "subcategory":"Motorcycle Sales",
            "type":"Retail Goods"
        }
    ],
    "sg:phone":"+1 309 786 3605",
    "sg:postcode":"61201",
    "sg:province":"IL",
    "sg:tags":[
        "scooter"
    ],
    "wof:name":"Payne's Cycle Ctr",
    "wof:placetype":"venue"
},
  "geometry": {"coordinates":[-90.545157,41.507467],"type":"Point"}
}