{
  "type": "Feature",
  "properties": {
    "iso:country":"US",
    "sg:address":"218 S Wabash Ave Ste 600",
    "sg:city":"Chicago",
    "sg:classifiers":[
        {
            "category":"Community Center",
            "subcategory":"Youth",
            "type":"Public Place"
        }
    ],
    "sg:phone":"+1 312 913 1700",
    "sg:postcode":"60604",
    "sg:province":"IL",
    "wof:name":"Cyc",
    "wof:placetype":"venue"
},
  "geometry": {"coordinates":[-87.626099,41.879284],"type":"Point"}
}