{
  "type": "Feature",
  "properties": {
    "iso:country":"US",
    "sg:address":"10117 S Trumbull Ave",
    "sg:city":"Evergreen Park",
    "sg:classifiers":[
        {
            "category":"Professional",
            "subcategory":"Business Services",
            "type":"Services"
        }
    ],
    "sg:phone":"+1 708 424 5153",
    "sg:postcode":"60805",
    "sg:province":"IL",
    "wof:name":"Commercial Building Solutions",
    "wof:placetype":"venue"
},
  "geometry": {"coordinates":[-87.707448,41.708202],"type":"Point"}
}