{
  "type": "Feature",
  "properties": {
    "addr:full":"875 North Michigan Chicago IL 60686",
    "addr:housenumber":"875",
    "addr:postcode":"60686",
    "addr:street":"North",
    "iso:country":"US",
    "sg:address":"875 North Michigan",
    "sg:city":"Chicago",
    "sg:classifiers":[
        {
            "category":"Shopping",
            "subcategory":"Clothing, Apparel, & Fashions",
            "type":"Retail Goods"
        }
    ],
    "sg:postcode":"60686",
    "sg:province":"IL",
    "sg:tags":[
        "clothing",
        "women's"
    ],
    "wof:name":"Ann Taylor",
    "wof:placetype":"venue"
},
  "geometry": {"coordinates":[-87.624055,41.898772],"type":"Point"}
}