{
  "type": "Feature",
  "properties": {
    "iso:country":"US",
    "sg:address":"580 E Merchant St",
    "sg:city":"Kankakee",
    "sg:classifiers":[
        {
            "category":"Professional",
            "subcategory":"Lawyer & Legal Services",
            "type":"Services"
        }
    ],
    "sg:phone":"+1 815 426 2578",
    "sg:postcode":"60901",
    "sg:province":"IL",
    "sg:tags":[
        "attorney"
    ],
    "wof:name":"Grotevant & Huber",
    "wof:placetype":"venue"
},
  "geometry": {"coordinates":[-87.859701,41.118436],"type":"Point"}
}