{
  "type": "Feature",
  "properties": {
    "iso:country":"US",
    "sg:address":"1305 Maple Ave",
    "sg:city":"Lisle",
    "sg:classifiers":[
        {
            "category":"Professional",
            "subcategory":"Computer Services",
            "type":"Services"
        }
    ],
    "sg:phone":"+1 630 963 5381",
    "sg:postcode":"60532",
    "sg:province":"IL",
    "sg:tags":[
        "prepackaged",
        "software"
    ],
    "wof:name":"Risingsoft Software Svcs LLC",
    "wof:placetype":"venue"
},
  "geometry": {"coordinates":[-88.07637800000001,41.786183],"type":"Point"}
}