{
  "type": "Feature",
  "properties": {
    "addr:full":"6257 Dayton Corner A St Colona IL 61241",
    "addr:housenumber":"6257",
    "addr:postcode":"61241",
    "addr:street":"Dayton Corner A St",
    "iso:country":"US",
    "sg:address":"6257 Dayton Corner A St",
    "sg:city":"Colona",
    "sg:classifiers":[
        {
            "category":"Wholesale",
            "subcategory":"Auto Parts",
            "type":"Manufacturing & Wholesale Goods"
        }
    ],
    "sg:phone":"+1 309 792 3205",
    "sg:postcode":"61241",
    "sg:province":"IL",
    "sg:tags":[
        "automobile",
        "rebuilt"
    ],
    "wof:name":"Horn's Used Parts & Cars",
    "wof:placetype":"venue"
},
  "geometry": {"coordinates":[-90.299644,41.488081],"type":"Point"}
}