{
  "type": "Feature",
  "properties": {
    "addr:full":"1116 S Humphrey Ave Oak Park IL 60304",
    "addr:housenumber":"1116",
    "addr:postcode":"60304",
    "addr:street":"S Humphrey Ave",
    "iso:country":"US",
    "sg:address":"1116 S Humphrey Ave",
    "sg:city":"Oak Park",
    "sg:classifiers":[
        {
            "category":"Professional",
            "subcategory":"Business Services",
            "type":"Services"
        },
        {
            "category":"Home & Garden",
            "subcategory":"Home Furnishings",
            "type":"Retail Goods"
        }
    ],
    "sg:phone":"+1 708 660 9118",
    "sg:postcode":"60304",
    "sg:province":"IL",
    "sg:tags":[
        "window",
        "treatment"
    ],
    "sg:website":"www.davidwayneinteriors.com",
    "wof:name":"Wayne David Interiors",
    "wof:placetype":"venue"
},
  "geometry": {"coordinates":[-87.775368,41.867883],"type":"Point"}
}