{
  "type": "Feature",
  "properties": {
    "addr:full":"507 E University Ave Champaign IL 61820",
    "addr:housenumber":"507",
    "addr:postcode":"61820",
    "addr:street":"E University Ave",
    "iso:country":"US",
    "sg:address":"507 E University Ave",
    "sg:city":"Champaign",
    "sg:classifiers":[
        {
            "category":"Health Services",
            "subcategory":"Doctor",
            "type":"Services"
        }
    ],
    "sg:phone":"+1 217 378 7800",
    "sg:postcode":"61820",
    "sg:province":"IL",
    "sg:tags":[
        "clinic"
    ],
    "sg:website":"www.gambrohealthcare.com",
    "wof:name":"Gambro Healthcare",
    "wof:placetype":"venue"
},
  "geometry": {"coordinates":[-88.230509,40.116289],"type":"Point"}
}