{
  "type": "Feature",
  "properties": {
    "iso:country":"US",
    "sg:address":"14962 W Abbey Ln",
    "sg:city":"Lockport",
    "sg:phone":"+1 815 836 8573",
    "sg:postcode":"60441",
    "sg:province":"IL",
    "wof:name":"J & K Elite Cheerleading",
    "wof:placetype":"venue"
},
  "geometry": {"coordinates":[-88.024986,41.585089],"type":"Point"}
}