{
  "type": "Feature",
  "properties": {
    "addr:full":"231 S Lake St Aurora IL 60506",
    "addr:housenumber":"231",
    "addr:postcode":"60506",
    "addr:street":"S Lake St",
    "iso:country":"US",
    "sg:address":"231 S Lake St",
    "sg:city":"Aurora",
    "sg:classifiers":[
        {
            "category":"Retail",
            "subcategory":"Repair Shop",
            "type":"Services"
        }
    ],
    "sg:phone":"+1 630 896 6161",
    "sg:postcode":"60506",
    "sg:province":"IL",
    "wof:name":"Van Dorn Upholstery",
    "wof:placetype":"venue"
},
  "geometry": {"coordinates":[-88.324107,41.755859],"type":"Point"}
}