{
  "type": "Feature",
  "properties": {
    "iso:country":"US",
    "sg:address":"626 E Church St",
    "sg:city":"Libertyville",
    "sg:classifiers":[
        {
            "category":"Building & Trades",
            "subcategory":"Construction",
            "type":"Services"
        }
    ],
    "sg:phone":"+1 847 362 3160",
    "sg:postcode":"60048",
    "sg:province":"IL",
    "sg:tags":[
        "course",
        "excavating",
        "golf",
        "contractor"
    ],
    "wof:name":"Koelper Brothers Inc",
    "wof:placetype":"venue"
},
  "geometry": {"coordinates":[-87.945112,42.28649],"type":"Point"}
}