{
  "type": "Feature",
  "properties": {
    "iso:country":"US",
    "sg:address":"4228 Newburg Rd",
    "sg:city":"Rockford",
    "sg:classifiers":[
        {
            "category":"Cinema",
            "subcategory":"Drive-in Theater",
            "type":"Entertainment"
        }
    ],
    "sg:phone":"+1 815 229 0536",
    "sg:postcode":"61108",
    "sg:province":"IL",
    "sg:tags":[
        "drive"
    ],
    "wof:name":"Colonial Village Cinem",
    "wof:placetype":"venue"
},
  "geometry": {"coordinates":[-89.026534,42.252712],"type":"Point"}
}