{
  "type": "Feature",
  "properties": {
    "iso:country":"US",
    "sg:address":"9400 Forest Hills Rd",
    "sg:city":"Loves Park",
    "sg:classifiers":[
        {
            "category":"Recreation",
            "type":"Entertainment"
        }
    ],
    "sg:phone":"+1 815 637 8748",
    "sg:postcode":"61111",
    "sg:province":"IL",
    "sg:tags":[
        "hall",
        "auditorium"
    ],
    "wof:name":"Harlem Community Ctr",
    "wof:placetype":"venue"
},
  "geometry": {"coordinates":[-89.01467100000001,42.359054],"type":"Point"}
}