{
  "type": "Feature",
  "properties": {
    "addr:full":"3224 Ridge Rd Lansing IL 60438",
    "addr:housenumber":"3224",
    "addr:postcode":"60438",
    "addr:street":"Ridge Rd",
    "iso:country":"US",
    "sg:address":"3224 Ridge Rd",
    "sg:city":"Lansing",
    "sg:classifiers":[
        {
            "category":"Professional",
            "subcategory":"Management & Consulting",
            "type":"Services"
        }
    ],
    "sg:phone":"+1 708 418 8790",
    "sg:postcode":"60438",
    "sg:province":"IL",
    "sg:tags":[
        "business"
    ],
    "wof:name":"Bankhead Group Inc",
    "wof:placetype":"venue"
},
  "geometry": {"coordinates":[-87.538749,41.564902],"type":"Point"}
}