{
  "type": "Feature",
  "properties": {
    "addr:full":"4037 N Oriole Ave Norridge IL 60706",
    "addr:housenumber":"4037",
    "addr:postcode":"60706",
    "addr:street":"N Oriole Ave",
    "iso:country":"US",
    "sg:address":"4037 N Oriole Ave",
    "sg:city":"Norridge",
    "sg:classifiers":[
        {
            "category":"Building & Trades",
            "subcategory":"Pest Control",
            "type":"Services"
        }
    ],
    "sg:phone":"+1 773 587 8365",
    "sg:postcode":"60706",
    "sg:province":"IL",
    "sg:website":"www.pestcontrolexpertschicago.com",
    "wof:name":"Pest Control Norridge",
    "wof:placetype":"venue"
},
  "geometry": {"coordinates":[-87.81667400000001,41.953943],"type":"Point"}
}