{
  "type": "Feature",
  "properties": {
    "iso:country":"US",
    "sg:address":"404 S Route 59",
    "sg:city":"Naperville",
    "sg:classifiers":[
        {
            "category":"Home & Garden",
            "subcategory":"Home Furnishings",
            "type":"Retail Goods"
        },
        {
            "category":"Home & Garden",
            "subcategory":"Furniture",
            "type":"Retail Goods"
        }
    ],
    "sg:phone":"+1 888 897 0504",
    "sg:postcode":"60540",
    "sg:province":"IL",
    "sg:tags":[
        "furniture-children's",
        "store"
    ],
    "sg:website":"http://cribstocollegebedroo.reachlocal.com/?scid=1886115",
    "wof:name":"Cribs To College Bedrooms",
    "wof:placetype":"venue"
},
  "geometry": {"coordinates":[-88.20580099999999,41.763226],"type":"Point"}
}