{
  "type": "Feature",
  "properties": {
    "iso:country":"US",
    "sg:address":"1762 Dr Springs Rd",
    "sg:city":"Carterville",
    "sg:classifiers":[
        {
            "category":"Arts & Performance",
            "subcategory":"Theater",
            "type":"Entertainment"
        }
    ],
    "sg:phone":"+1 618 987 2647",
    "sg:postcode":"62918",
    "sg:province":"IL",
    "sg:tags":[
        "group"
    ],
    "wof:name":"Heartland Mobile Entertainment",
    "wof:placetype":"venue"
},
  "geometry": {"coordinates":[-89.12858199999999,37.803472],"type":"Point"}
}