{
  "type": "Feature",
  "properties": {
    "addr:full":"5520 E Goodfarm Rd Gardner IL 60424",
    "addr:housenumber":"5520",
    "addr:postcode":"60424",
    "addr:street":"E Goodfarm Rd",
    "iso:country":"US",
    "sg:address":"5520 E Goodfarm Rd",
    "sg:city":"Gardner",
    "sg:phone":"+1 815 237 8642",
    "sg:postcode":"60424",
    "sg:province":"IL",
    "sg:tags":[
        "farm",
        "corn",
        "soybean"
    ],
    "wof:name":"Margie Storm",
    "wof:placetype":"venue"
},
  "geometry": {"coordinates":[-88.309234,41.156784],"type":"Point"}
}