{
  "type": "Feature",
  "properties": {
    "iso:country":"US",
    "sg:address":"491 S Weber Rd",
    "sg:city":"Bolingbrook",
    "sg:classifiers":[
        {
            "category":"Sports & Exercise",
            "subcategory":"Gym",
            "type":"Entertainment"
        }
    ],
    "sg:phone":"+1 630 378 9740",
    "sg:postcode":"60490",
    "sg:province":"IL",
    "sg:tags":[
        "club",
        "health",
        "studio",
        "gymnasium"
    ],
    "wof:name":"Ladies Workout Express",
    "wof:placetype":"venue"
},
  "geometry": {"coordinates":[-88.125778,41.682667],"type":"Point"}
}