{
  "type": "Feature",
  "properties": {
    "addr:full":"1141 N Raddant Rd Batavia IL 60510",
    "addr:housenumber":"1141",
    "addr:postcode":"60510",
    "addr:street":"N Raddant Rd",
    "iso:country":"US",
    "sg:address":"1141 N Raddant Rd",
    "sg:city":"Batavia",
    "sg:classifiers":[
        {
            "category":"Manufacturing",
            "subcategory":"Food",
            "type":"Manufacturing & Wholesale Goods"
        }
    ],
    "sg:phone":"+1 630 406 1100",
    "sg:postcode":"60510",
    "sg:province":"IL",
    "sg:tags":[
        "coffee"
    ],
    "wof:name":"Papanicholas Coffee Company",
    "wof:placetype":"venue"
},
  "geometry": {"coordinates":[-88.293115,41.862192],"type":"Point"}
}