{
  "type": "Feature",
  "properties": {
    "addr:full":"1648 Marquette Rd Joliet IL 60435",
    "addr:housenumber":"1648",
    "addr:postcode":"60435",
    "addr:street":"Marquette Rd",
    "iso:country":"US",
    "sg:address":"1648 Marquette Rd",
    "sg:city":"Joliet",
    "sg:classifiers":[
        {
            "category":"Building & Trades",
            "subcategory":"Construction",
            "type":"Services"
        }
    ],
    "sg:phone":"+1 815 726 1040",
    "sg:postcode":"60435",
    "sg:province":"IL",
    "sg:tags":[
        "painter"
    ],
    "wof:name":"Over All Painting & Decorating",
    "wof:placetype":"venue"
},
  "geometry": {"coordinates":[-88.123093,41.529931],"type":"Point"}
}