{
  "type": "Feature",
  "properties": {
    "addr:full":"1812 NE Wilmar Ct Quincy IL 62301",
    "addr:housenumber":"1812",
    "addr:postcode":"62301",
    "addr:street":"Ne Wilmar Ct",
    "iso:country":"US",
    "sg:address":"1812 NE Wilmar Ct",
    "sg:city":"Quincy",
    "sg:classifiers":[
        {
            "category":"Organizations",
            "subcategory":"Membership Organization",
            "type":"Services"
        }
    ],
    "sg:phone":"+1 217 223 0669",
    "sg:postcode":"62301",
    "sg:province":"IL",
    "wof:name":"Student Foundation of Illinois",
    "wof:placetype":"venue"
},
  "geometry": {"coordinates":[-91.37880800000001,39.909322],"type":"Point"}
}