{
  "type": "Feature",
  "properties": {
    "addr:full":"1181 Furlong Dr Libertyville IL 60048",
    "addr:housenumber":"1181",
    "addr:postcode":"60048",
    "addr:street":"Furlong Dr",
    "iso:country":"US",
    "sg:address":"1181 Furlong Dr",
    "sg:city":"Libertyville",
    "sg:classifiers":[
        {
            "category":"Wholesale",
            "subcategory":"Apparel",
            "type":"Manufacturing & Wholesale Goods"
        }
    ],
    "sg:phone":"+1 847 367 7954",
    "sg:postcode":"60048",
    "sg:province":"IL",
    "sg:tags":[
        "clothing"
    ],
    "wof:name":"Msr Collectibles Inc",
    "wof:placetype":"venue"
},
  "geometry": {"coordinates":[-87.94703699999999,42.26577],"type":"Point"}
}