{
  "type": "Feature",
  "properties": {
    "addr:full":"11113 S Western Ave Chicago IL 60643",
    "addr:housenumber":"11113",
    "addr:postcode":"60643",
    "addr:street":"S Western Ave",
    "iso:country":"US",
    "sg:address":"11113 S Western Ave",
    "sg:city":"Chicago",
    "sg:classifiers":[
        {
            "category":"Insurance",
            "subcategory":"Insurance Agent",
            "type":"Services"
        }
    ],
    "sg:phone":"+1 773 779 0100",
    "sg:postcode":"60643",
    "sg:province":"IL",
    "wof:name":"Hallberg Insurance Co Agency",
    "wof:placetype":"venue"
},
  "geometry": {"coordinates":[-87.68106,41.691188],"type":"Point"}
}