{
  "type": "Feature",
  "properties": {
    "iso:country":"US",
    "sg:address":"775 E Belvidere Rd",
    "sg:city":"Grayslake",
    "sg:classifiers":[
        {
            "category":"Coffee & Tea",
            "type":"Food & Drink"
        }
    ],
    "sg:menulink":"http://www.allmenus.com/il/avon/112497-starbucks-coffee/menu/",
    "sg:phone":"+1 847 548 0916",
    "sg:postcode":"60030",
    "sg:province":"IL",
    "sg:tags":[
        "american"
    ],
    "wof:name":"Starbucks Coffee",
    "wof:placetype":"venue"
},
  "geometry": {"coordinates":[-88.03272699999999,42.336602],"type":"Point"}
}