{
  "type": "Feature",
  "properties": {
    "iso:country":"US",
    "sg:address":"1911 Elmore Ave",
    "sg:city":"Downers Grove",
    "sg:classifiers":[
        {
            "category":"Professional",
            "subcategory":"Research",
            "type":"Services"
        }
    ],
    "sg:phone":"+1 630 241 2292",
    "sg:postcode":"60515",
    "sg:province":"IL",
    "sg:tags":[
        "business"
    ],
    "wof:name":"Advantage Capital Partners",
    "wof:placetype":"venue"
},
  "geometry": {"coordinates":[-88.02757,41.789624],"type":"Point"}
}