{
  "type": "Feature",
  "properties": {
    "addr:full":"7924 W 26th St Riverside IL 60546",
    "addr:housenumber":"7924",
    "addr:postcode":"60546",
    "addr:street":"W 26Th St",
    "iso:country":"US",
    "sg:address":"7924 W 26th St",
    "sg:city":"Riverside",
    "sg:classifiers":[
        {
            "category":"Personal",
            "subcategory":"Beauty Salon",
            "type":"Services"
        },
        {
            "category":"Personal",
            "subcategory":"Barber",
            "type":"Services"
        },
        {
            "category":"Shopping",
            "subcategory":"Beauty & Cosmetics",
            "type":"Retail Goods"
        }
    ],
    "sg:phone":"+1 708 447 5150",
    "sg:postcode":"60546",
    "sg:province":"IL",
    "sg:tags":[
        "supply"
    ],
    "wof:name":"Mombo Hair Art Studio",
    "wof:placetype":"venue"
},
  "geometry": {"coordinates":[-87.821602,41.8428],"type":"Point"}
}