{
  "type": "Feature",
  "properties": {
    "iso:country":"US",
    "sg:address":"704 W Eleanor Pl",
    "sg:city":"Peoria",
    "sg:classifiers":[
        {
            "category":"Real Estate",
            "subcategory":"Real Estate Operator",
            "type":"Services"
        }
    ],
    "sg:phone":"+1 309 682 5517",
    "sg:postcode":"61604",
    "sg:province":"IL",
    "sg:tags":[
        "apartment"
    ],
    "wof:name":"Deborah B Landers",
    "wof:placetype":"venue"
},
  "geometry": {"coordinates":[-89.603647,40.711786],"type":"Point"}
}