{
  "type": "Feature",
  "properties": {
    "iso:country":"US",
    "sg:address":"715 E Golf Rd",
    "sg:city":"Schaumburg",
    "sg:phone":"+1 847 884 6840",
    "sg:postcode":"60173",
    "sg:province":"IL",
    "wof:name":"Versailes Village Center",
    "wof:placetype":"venue"
},
  "geometry": {"coordinates":[-88.06200200000001,42.049985],"type":"Point"}
}