{
  "type": "Feature",
  "properties": {
    "iso:country":"US",
    "sg:address":"33 W Illinois St",
    "sg:city":"Chicago",
    "sg:classifiers":[
        {
            "category":"Shopping",
            "subcategory":"Gifts & Souvenirs",
            "type":"Retail Goods"
        }
    ],
    "sg:phone":"+1 312 494 1657",
    "sg:postcode":"60654",
    "sg:province":"IL",
    "sg:tags":[
        "shop"
    ],
    "wof:name":"Am Lobby Shops Inc",
    "wof:placetype":"venue"
},
  "geometry": {"coordinates":[-87.629372,41.890842],"type":"Point"}
}