{
  "type": "Feature",
  "properties": {
    "iso:country":"US",
    "sg:address":"417 31st St",
    "sg:city":"Cairo",
    "sg:classifiers":[
        {
            "category":"Restaurant",
            "type":"Food & Drink"
        }
    ],
    "sg:phone":"+1 618 734 1836",
    "sg:postcode":"62914",
    "sg:province":"IL",
    "sg:tags":[
        "house",
        "steak",
        "barbecue"
    ],
    "wof:name":"We Do Butts Bar B Que",
    "wof:placetype":"venue"
},
  "geometry": {"coordinates":[-89.181258,37.012484],"type":"Point"}
}