{
  "type": "Feature",
  "properties": {
    "iso:country":"US",
    "sg:address":"50 E Bellevue Place",
    "sg:city":"Chicago",
    "sg:classifiers":[
        {
            "category":"Parking",
            "type":"Transportation"
        }
    ],
    "sg:phone":"+1 312 642 7780",
    "sg:postcode":"60611",
    "sg:province":"IL",
    "sg:website":"www.abm.com",
    "wof:name":"Ampco System Parking",
    "wof:placetype":"venue"
},
  "geometry": {"coordinates":[-87.62714699999999,41.901586],"type":"Point"}
}