{
  "type": "Feature",
  "properties": {
    "addr:full":"2001 S Raney St Effingham IL 62401",
    "addr:housenumber":"2001",
    "addr:postcode":"62401",
    "addr:street":"S Raney St",
    "iso:country":"US",
    "sg:address":"2001 S Raney St",
    "sg:city":"Effingham",
    "sg:phone":"+1 217 342 4359",
    "sg:postcode":"62401",
    "sg:province":"IL",
    "sg:tags":[
        "farm",
        "corn"
    ],
    "wof:name":"Ralph Bourgeois",
    "wof:placetype":"venue"
},
  "geometry": {"coordinates":[-88.561053,39.103913],"type":"Point"}
}