{
  "type": "Feature",
  "properties": {
    "iso:country":"US",
    "sg:address":"110 S Alpine Rd",
    "sg:city":"Rockford",
    "sg:classifiers":[
        {
            "category":"Wholesale",
            "subcategory":"Electrical",
            "type":"Manufacturing & Wholesale Goods"
        }
    ],
    "sg:phone":"+1 815 229 0225",
    "sg:postcode":"61108",
    "sg:province":"IL",
    "sg:tags":[
        "electronic"
    ],
    "wof:name":"Newark Electronics 71",
    "wof:placetype":"venue"
},
  "geometry": {"coordinates":[-89.028957,42.263013],"type":"Point"}
}