{
  "type": "Feature",
  "properties": {
    "addr:full":"1750 N Wells St Apt 306 Chicago IL 60614",
    "addr:housenumber":"1750;306",
    "addr:postcode":"60614",
    "addr:street":"N Wells St Apt",
    "iso:country":"US",
    "sg:address":"1750 N Wells St Apt 306",
    "sg:city":"Chicago",
    "sg:classifiers":[
        {
            "category":"Retail",
            "subcategory":"Photofinishing",
            "type":"Services"
        }
    ],
    "sg:phone":"+1 312 944 1940",
    "sg:postcode":"60614",
    "sg:province":"IL",
    "sg:tags":[
        "photo",
        "restoration",
        "retouching"
    ],
    "wof:name":"Rjd Photo",
    "wof:placetype":"venue"
},
  "geometry": {"coordinates":[-87.634804,41.914009],"type":"Point"}
}