{
  "type": "Feature",
  "properties": {
    "iso:country":"US",
    "sg:address":"7431 W Isham Ave",
    "sg:city":"Chicago",
    "sg:classifiers":[
        {
            "category":"Building & Trades",
            "subcategory":"Construction",
            "type":"Services"
        }
    ],
    "sg:phone":"+1 773 631 4136",
    "sg:postcode":"60631",
    "sg:province":"IL",
    "sg:tags":[
        "painting",
        "contractor"
    ],
    "wof:name":"M Ecker Co",
    "wof:placetype":"venue"
},
  "geometry": {"coordinates":[-87.812459,41.997997],"type":"Point"}
}