{
  "type": "Feature",
  "properties": {
    "iso:country":"US",
    "sg:address":"2500 N Main St",
    "sg:city":"Rockford",
    "sg:classifiers":[
        {
            "category":"Retail",
            "subcategory":"Repair Shop",
            "type":"Services"
        }
    ],
    "sg:phone":"+1 815 963 3321",
    "sg:postcode":"61103",
    "sg:province":"IL",
    "sg:tags":[
        "equipment",
        "industrial"
    ],
    "wof:name":"Jacobson Industrials Inc",
    "wof:placetype":"venue"
},
  "geometry": {"coordinates":[-89.07713200000001,42.298007],"type":"Point"}
}