{
  "type": "Feature",
  "properties": {
    "addr:full":"1401 Golden Bell Ct Downers Grove IL 60515",
    "addr:housenumber":"1401",
    "addr:postcode":"60515",
    "addr:street":"Golden Bell Ct",
    "iso:country":"US",
    "sg:address":"1401 Golden Bell Ct",
    "sg:city":"Downers Grove",
    "sg:classifiers":[
        {
            "category":"Professional",
            "subcategory":"Detective & Security Services",
            "type":"Services"
        }
    ],
    "sg:phone":"+1 630 795 1981",
    "sg:postcode":"60515",
    "sg:province":"IL",
    "sg:tags":[
        "system"
    ],
    "wof:name":"Opening Solutions",
    "wof:placetype":"venue"
},
  "geometry": {"coordinates":[-88.02140199999999,41.818737],"type":"Point"}
}