{
  "type": "Feature",
  "properties": {
    "addr:full":"736 Roger Ave Kenilworth IL 60043",
    "addr:housenumber":"736",
    "addr:postcode":"60043",
    "addr:street":"Roger Ave",
    "iso:country":"US",
    "sg:address":"736 Roger Ave",
    "sg:city":"Kenilworth",
    "sg:classifiers":[
        {
            "category":"Building & Trades",
            "subcategory":"Landscaping Services",
            "type":"Services"
        }
    ],
    "sg:phone":"+1 847 256 5341",
    "sg:postcode":"60043",
    "sg:province":"IL",
    "wof:name":"Ostrowski Landscaping",
    "wof:placetype":"venue"
},
  "geometry": {"coordinates":[-87.724431,42.089417],"type":"Point"}
}