{
  "type": "Feature",
  "properties": {
    "addr:full":"950 N Villa Ave Villa Park IL 60181",
    "addr:housenumber":"950",
    "addr:postcode":"60181",
    "addr:street":"N Villa Ave",
    "iso:country":"US",
    "sg:address":"950 N Villa Ave",
    "sg:city":"Villa Park",
    "sg:classifiers":[
        {
            "category":"Building & Trades",
            "subcategory":"Construction",
            "type":"Services"
        }
    ],
    "sg:phone":"+1 630 941 0125",
    "sg:postcode":"60181",
    "sg:province":"IL",
    "sg:tags":[
        "contractor"
    ],
    "wof:name":"Chicago Land",
    "wof:placetype":"venue"
},
  "geometry": {"coordinates":[-87.97106100000001,41.911652],"type":"Point"}
}