{
  "type": "Feature",
  "properties": {
    "iso:country":"US",
    "sg:address":"6199 N Lincoln Ave",
    "sg:city":"Chicago",
    "sg:classifiers":[
        {
            "category":"Organizations",
            "subcategory":"Political Organization",
            "type":"Services"
        }
    ],
    "sg:phone":"+1 773 764 5050",
    "sg:postcode":"60659",
    "sg:province":"IL",
    "wof:name":"Alderman Bernard L Stone",
    "wof:placetype":"venue"
},
  "geometry": {"coordinates":[-87.712521,41.993545],"type":"Point"}
}