{
  "type": "Feature",
  "properties": {
    "iso:country":"US",
    "sg:address":"515 E Golf Rd",
    "sg:city":"Arlington Hts",
    "sg:classifiers":[
        {
            "category":"Building & Trades",
            "subcategory":"Construction",
            "type":"Services"
        }
    ],
    "sg:phone":"+1 847 806 8040",
    "sg:postcode":"60005",
    "sg:province":"IL",
    "sg:tags":[
        "general",
        "contractor"
    ],
    "wof:name":"Construction Morning Dew",
    "wof:placetype":"venue"
},
  "geometry": {"coordinates":[-87.980934,42.051363],"type":"Point"}
}