{
  "type": "Feature",
  "properties": {
    "iso:country":"US",
    "sg:address":"1914 E Grand Ave",
    "sg:city":"Lindenhurst",
    "sg:classifiers":[
        {
            "category":"Professional",
            "subcategory":"Engineering",
            "type":"Services"
        },
        {
            "category":"Banks & Credit Unions",
            "subcategory":"Financial Services",
            "type":"Services"
        }
    ],
    "sg:phone":"+1 847 662 4863",
    "sg:postcode":"60046",
    "sg:province":"IL",
    "sg:tags":[
        "vice",
        "patent",
        "processing",
        "owner",
        "technology",
        "engineer"
    ],
    "sg:website":"www.theisresearch.com",
    "wof:name":"Theis Research Inc",
    "wof:placetype":"venue"
},
  "geometry": {"coordinates":[-88.033928,42.410481],"type":"Point"}
}