{
  "type": "Feature",
  "properties": {
    "addr:full":"1612 W Irving Park Rd Chicago IL 60613",
    "addr:housenumber":"1612",
    "addr:postcode":"60613",
    "addr:street":"W Irving Park Rd",
    "iso:country":"US",
    "sg:address":"1612 W Irving Park Rd",
    "sg:city":"Chicago",
    "sg:classifiers":[
        {
            "category":"Bars & Pubs",
            "type":"Food & Drink"
        }
    ],
    "sg:phone":"+1 773 665 4500",
    "sg:postcode":"60613",
    "sg:province":"IL",
    "sg:website":"longroomchicago.com",
    "wof:name":"The Long Room",
    "wof:placetype":"venue"
},
  "geometry": {"coordinates":[-87.669899,41.954498],"type":"Point"}
}