{
  "type": "Feature",
  "properties": {
    "iso:country":"US",
    "sg:address":"1657 Hill Dr",
    "sg:city":"Dixon",
    "sg:classifiers":[
        {
            "category":"Building & Trades",
            "subcategory":"Construction",
            "type":"Services"
        }
    ],
    "sg:phone":"+1 815 284 8929",
    "sg:postcode":"61021",
    "sg:province":"IL",
    "sg:tags":[
        "general",
        "contractor"
    ],
    "wof:name":"Jacobs Construction",
    "wof:placetype":"venue"
},
  "geometry": {"coordinates":[-89.578188,41.823606],"type":"Point"}
}