{
  "type": "Feature",
  "properties": {
    "iso:country":"US",
    "sg:address":"401 Orchard St",
    "sg:city":"Fox River Grove",
    "sg:classifiers":[
        {
            "category":"Education",
            "subcategory":"School",
            "type":"Public Place"
        }
    ],
    "sg:phone":"+1 847 516 5105",
    "sg:postcode":"60021",
    "sg:province":"IL",
    "sg:tags":[
        "high",
        "middle",
        "elementary"
    ],
    "wof:name":"Schools Public",
    "wof:placetype":"venue"
},
  "geometry": {"coordinates":[-88.213795,42.197247],"type":"Point"}
}