{
  "type": "Feature",
  "properties": {
    "iso:country":"US",
    "sg:address":"3003 183rd St",
    "sg:city":"Homewood",
    "sg:classifiers":[
        {
            "category":"Bagels",
            "type":"Food & Drink"
        }
    ],
    "sg:menulink":"http://www.allmenus.com/il/bremen/235799-the-great-american-bagel/menu/",
    "sg:phone":"+1 708 957 0125",
    "sg:postcode":"60430",
    "sg:province":"IL",
    "sg:tags":[
        "wrap",
        "american",
        "sandwich"
    ],
    "wof:name":"The Great American Bagel",
    "wof:placetype":"venue"
},
  "geometry": {"coordinates":[-87.689537,41.557135],"type":"Point"}
}