{
  "type": "Feature",
  "properties": {
    "iso:country":"US",
    "sg:address":"1112 Rd 1150 N",
    "sg:city":"Homer",
    "sg:classifiers":[
        {
            "category":"Farming",
            "subcategory":"Livestock Farm",
            "type":"Manufacturing & Wholesale Goods"
        }
    ],
    "sg:phone":"+1 217 896 2388",
    "sg:postcode":"61849",
    "sg:province":"IL",
    "sg:tags":[
        "general"
    ],
    "wof:name":"Bruce Bryan",
    "wof:placetype":"venue"
},
  "geometry": {"coordinates":[-87.919363,40.032661],"type":"Point"}
}