{
  "type": "Feature",
  "properties": {
    "addr:full":"402 E Roosevelt Rd Wheaton IL 60187",
    "addr:housenumber":"402",
    "addr:postcode":"60187",
    "addr:street":"E Roosevelt Rd",
    "iso:country":"US",
    "sg:address":"402 E Roosevelt Rd",
    "sg:city":"Wheaton",
    "sg:classifiers":[
        {
            "category":"Health Services",
            "subcategory":"Health Practitioner",
            "type":"Services"
        }
    ],
    "sg:phone":"+1 630 469 7476",
    "sg:postcode":"60187",
    "sg:province":"IL",
    "wof:name":"Athletic & Therapeutic Massage",
    "wof:placetype":"venue"
},
  "geometry": {"coordinates":[-88.09869999999999,41.858822],"type":"Point"}
}