{
  "type": "Feature",
  "properties": {
    "addr:full":"6316 N Lincoln Ave Chicago IL 60659",
    "addr:housenumber":"6316",
    "addr:postcode":"60659",
    "addr:street":"N Lincoln Ave",
    "iso:country":"US",
    "sg:address":"6316 N Lincoln Ave",
    "sg:city":"Chicago",
    "sg:classifiers":[
        {
            "category":"Professional",
            "subcategory":"Lawyer & Legal Services",
            "type":"Services"
        }
    ],
    "sg:phone":"+1 773 583 6300",
    "sg:postcode":"60659",
    "sg:province":"IL",
    "sg:tags":[
        "plan"
    ],
    "sg:website":"http://www.visaprofessional.com",
    "wof:name":"Shah-Khan, Mazher M, Law Offices Of",
    "wof:placetype":"venue"
},
  "geometry": {"coordinates":[-87.716696,41.996132],"type":"Point"}
}