{
  "type": "Feature",
  "properties": {
    "iso:country":"US",
    "sg:address":"801 Sanders St",
    "sg:city":"Bethalto",
    "sg:classifiers":[
        {
            "category":"Shopping",
            "subcategory":"Computers & Home Electronics",
            "type":"Retail Goods"
        }
    ],
    "sg:phone":"+1 618 377 6570",
    "sg:postcode":"62010",
    "sg:province":"IL",
    "sg:tags":[
        "software"
    ],
    "wof:name":"Christos-Rhema Software",
    "wof:placetype":"venue"
},
  "geometry": {"coordinates":[-90.042873,38.898686],"type":"Point"}
}