{
  "type": "Feature",
  "properties": {
    "addr:full":"39090 N US Hwy 41 Wadsworth IL 60083",
    "addr:housenumber":"39090",
    "addr:postcode":"60083",
    "addr:street":"N Us Hwy 41",
    "iso:country":"US",
    "sg:address":"39090 N US Hwy 41",
    "sg:city":"Wadsworth",
    "sg:classifiers":[
        {
            "category":"Food & Beverages",
            "subcategory":"Groceries & Convenience Stores",
            "type":"Retail Goods"
        }
    ],
    "sg:phone":"+1 847 336 5016",
    "sg:postcode":"60083",
    "sg:province":"IL",
    "wof:name":"Tri Star Gas & Food Mart Inc",
    "wof:placetype":"venue"
},
  "geometry": {"coordinates":[-87.938183,42.429229],"type":"Point"}
}