{
  "type": "Feature",
  "properties": {
    "iso:country":"US",
    "sg:address":"9405 Champion Ct",
    "sg:city":"Spring Grove",
    "sg:classifiers":[
        {
            "category":"Building & Trades",
            "subcategory":"Construction",
            "type":"Services"
        }
    ],
    "sg:phone":"+1 815 675 0515",
    "sg:postcode":"60081",
    "sg:province":"IL",
    "sg:tags":[
        "hanging",
        "contractor"
    ],
    "wof:name":"Cedergren Decorating",
    "wof:placetype":"venue"
},
  "geometry": {"coordinates":[-88.254081,42.46275],"type":"Point"}
}