{
  "type": "Feature",
  "properties": {
    "iso:country":"US",
    "sg:address":"102 N Poplar St",
    "sg:city":"De Soto",
    "sg:classifiers":[
        {
            "category":"Shopping",
            "subcategory":"Hobbies, Toys, & Games",
            "type":"Retail Goods"
        }
    ],
    "sg:phone":"+1   ",
    "sg:postcode":"62924",
    "sg:province":"IL",
    "wof:name":"M G Squared",
    "wof:placetype":"venue"
},
  "geometry": {"coordinates":[-89.223973,37.816382],"type":"Point"}
}