{
  "type": "Feature",
  "properties": {
    "addr:full":"2516-2518 W 63rd St Chicago IL 60629",
    "addr:housenumber":"2516-2518",
    "addr:postcode":"60629",
    "addr:street":"W 63Rd St",
    "iso:country":"US",
    "sg:address":"2516-2518 W 63rd St",
    "sg:city":"Chicago",
    "sg:classifiers":[
        {
            "category":"Restaurant",
            "type":"Food & Drink"
        }
    ],
    "sg:phone":"+1 773 776 7440",
    "sg:postcode":"60629",
    "sg:province":"IL",
    "sg:tags":[
        "caribbean"
    ],
    "wof:name":"Garifuna Flava",
    "wof:placetype":"venue"
},
  "geometry": {"coordinates":[-87.686926,41.779342],"type":"Point"}
}