{
  "type": "Feature",
  "properties": {
    "iso:country":"US",
    "sg:address":"6520 S Cicero Avenue",
    "sg:city":"Chicago",
    "sg:classifiers":[
        {
            "category":"Professional",
            "type":"Services"
        },
        {
            "category":"Travel",
            "subcategory":"Hotels & Motels",
            "type":"Entertainment"
        }
    ],
    "sg:phone":"+1 708 594 5500",
    "sg:postcode":"60638",
    "sg:province":"IL",
    "sg:tags":[
        "caterer"
    ],
    "wof:name":"Holiday Inn Select Chicago Midway Airport",
    "wof:placetype":"venue"
},
  "geometry": {"coordinates":[-87.74218500000001,41.773847],"type":"Point"}
}