{
  "type": "Feature",
  "properties": {
    "addr:full":"201 S Alpine Rd Rockford IL 61108",
    "addr:housenumber":"201",
    "addr:postcode":"61108",
    "addr:street":"S Alpine Rd",
    "iso:country":"US",
    "sg:address":"201 S Alpine Rd",
    "sg:city":"Rockford",
    "sg:classifiers":[
        {
            "category":"Autos & Motor Vehicles",
            "subcategory":"Auto Supplies",
            "type":"Retail Goods"
        }
    ],
    "sg:phone":"+1 815 398 3749",
    "sg:postcode":"61108",
    "sg:province":"IL",
    "sg:tags":[
        "automobile",
        "parts"
    ],
    "wof:name":"Autozone",
    "wof:placetype":"venue"
},
  "geometry": {"coordinates":[-89.02902899999999,42.261496],"type":"Point"}
}