{
  "type": "Feature",
  "properties": {
    "iso:country":"US",
    "sg:address":"3940 11th St",
    "sg:city":"Rock Island",
    "sg:classifiers":[
        {
            "category":"Home & Garden",
            "subcategory":"Hardware",
            "type":"Retail Goods"
        }
    ],
    "sg:phone":"+1 309 786 0500",
    "sg:postcode":"61201",
    "sg:province":"IL",
    "sg:tags":[
        "wholesale",
        "tool"
    ],
    "wof:name":"Midwest Tool",
    "wof:placetype":"venue"
},
  "geometry": {"coordinates":[-90.58378999999999,41.470941],"type":"Point"}
}