{
  "type": "Feature",
  "properties": {
    "iso:country":"US",
    "sg:address":"2222 Benderwirt Ave",
    "sg:city":"Rockford",
    "sg:classifiers":[
        {
            "category":"Sports & Exercise",
            "subcategory":"Gym",
            "type":"Entertainment"
        }
    ],
    "sg:phone":"+1 815 636 9455",
    "sg:postcode":"61103",
    "sg:province":"IL",
    "sg:tags":[
        "club",
        "health",
        "studio",
        "gymnasium"
    ],
    "sg:website":"www.ladyofamerica.com",
    "wof:name":"Tana Inc",
    "wof:placetype":"venue"
},
  "geometry": {"coordinates":[-89.09240699999999,42.287486],"type":"Point"}
}