{
  "type": "Feature",
  "properties": {
    "addr:full":"720 N Edwardsville St Staunton IL 62088",
    "addr:housenumber":"720",
    "addr:postcode":"62088",
    "addr:street":"N Edwardsville St",
    "iso:country":"US",
    "sg:address":"720 N Edwardsville St",
    "sg:city":"Staunton",
    "sg:classifiers":[
        {
            "category":"Retail",
            "subcategory":"Auto Repair",
            "type":"Services"
        }
    ],
    "sg:phone":"+1 618 635 2400",
    "sg:postcode":"62088",
    "sg:province":"IL",
    "sg:tags":[
        "repairing",
        "automobile"
    ],
    "wof:name":"Bud's Service Ctr",
    "wof:placetype":"venue"
},
  "geometry": {"coordinates":[-89.790584,39.018903],"type":"Point"}
}