{
  "type": "Feature",
  "properties": {
    "iso:country":"US",
    "sg:address":"4316 N Freedom Rd",
    "sg:city":"Noble",
    "sg:classifiers":[
        {
            "category":"Real Estate",
            "subcategory":"Real Estate Operator",
            "type":"Services"
        }
    ],
    "sg:phone":"+1 618 723 2468",
    "sg:postcode":"62868",
    "sg:province":"IL",
    "sg:tags":[
        "property",
        "lessor"
    ],
    "wof:name":"Miller Ek",
    "wof:placetype":"venue"
},
  "geometry": {"coordinates":[-88.237653,38.730054],"type":"Point"}
}