{
  "type": "Feature",
  "properties": {
    "addr:full":"5458 N Ashland Ave Chicago IL 60640",
    "addr:housenumber":"5458",
    "addr:postcode":"60640",
    "addr:street":"N Ashland Ave",
    "iso:country":"US",
    "sg:address":"5458 N Ashland Ave",
    "sg:city":"Chicago",
    "sg:classifiers":[
        {
            "category":"Banks & Credit Unions",
            "subcategory":"Bank",
            "type":"Services"
        }
    ],
    "sg:phone":"+1 773 561 4335",
    "sg:postcode":"60640",
    "sg:province":"IL",
    "wof:name":"State Farm Bank",
    "wof:placetype":"venue"
},
  "geometry": {"coordinates":[-87.669701,41.980598],"type":"Point"}
}