{
  "type": "Feature",
  "properties": {
    "iso:country":"US",
    "sg:address":"24664 Wildwood Trl",
    "sg:city":"Crete",
    "sg:classifiers":[
        {
            "category":"Personal",
            "subcategory":"Beauty Salon",
            "type":"Services"
        }
    ],
    "sg:phone":"+1 708 672 4032",
    "sg:postcode":"60417",
    "sg:province":"IL",
    "sg:tags":[
        "shop"
    ],
    "wof:name":"Two Sisters Inc",
    "wof:placetype":"venue"
},
  "geometry": {"coordinates":[-87.538153,41.443909],"type":"Point"}
}