{
  "type": "Feature",
  "properties": {
    "iso:country":"US",
    "sg:address":"20972 E 450th St",
    "sg:city":"Colona",
    "sg:classifiers":[
        {
            "category":"Retail",
            "subcategory":"Veterinary Services",
            "type":"Services"
        }
    ],
    "sg:phone":"+1 309 949 2144",
    "sg:postcode":"61241",
    "sg:province":"IL",
    "sg:tags":[
        "pet",
        "veterinarian",
        "boarding/pet",
        "sitting"
    ],
    "sg:website":"www.oakwoodvets.com",
    "wof:name":"Oakwood Veterinary Service",
    "wof:placetype":"venue"
},
  "geometry": {"coordinates":[-90.34834600000001,41.452802],"type":"Point"}
}