{
  "type": "Feature",
  "properties": {
    "addr:full":"1900 S Clark St Chicago IL 60616",
    "addr:housenumber":"1900",
    "addr:postcode":"60616",
    "addr:street":"S Clark St",
    "iso:country":"US",
    "sg:address":"1900 S Clark St",
    "sg:city":"Chicago",
    "sg:classifiers":[
        {
            "category":"Restaurant",
            "type":"Food & Drink"
        }
    ],
    "sg:phone":"+1 312 225 0831",
    "sg:postcode":"60616",
    "sg:province":"IL",
    "wof:name":"Big Daddys Vending",
    "wof:placetype":"venue"
},
  "geometry": {"coordinates":[-87.630188,41.85659],"type":"Point"}
}