{
  "type": "Feature",
  "properties": {
    "iso:country":"US",
    "sg:address":"1162 Aura Dr",
    "sg:city":"Rockford",
    "sg:classifiers":[
        {
            "category":"Banks & Credit Unions",
            "subcategory":"Investment Brokerage",
            "type":"Services"
        }
    ],
    "sg:phone":"+1 815 226 4563",
    "sg:postcode":"61108",
    "sg:province":"IL",
    "sg:tags":[
        "tape",
        "video",
        "sale",
        "dvds-rental"
    ],
    "wof:name":"D & D Amusements",
    "wof:placetype":"venue"
},
  "geometry": {"coordinates":[-88.978831,42.257863],"type":"Point"}
}