{
  "type": "Feature",
  "properties": {
    "addr:full":"2835 N 10000W Rd Bonfield IL 60913",
    "addr:housenumber":"2835",
    "addr:postcode":"60913",
    "addr:street":"N 10000W Rd",
    "iso:country":"US",
    "sg:address":"2835 N 10000W Rd",
    "sg:city":"Bonfield",
    "sg:classifiers":[
        {
            "category":"Freight",
            "type":"Transportation"
        }
    ],
    "sg:phone":"+1 815 936 1415",
    "sg:postcode":"60913",
    "sg:province":"IL",
    "sg:tags":[
        "trucking"
    ],
    "wof:name":"Bauer Transport Inc",
    "wof:placetype":"venue"
},
  "geometry": {"coordinates":[-88.06887999999999,41.155988],"type":"Point"}
}