{
  "type": "Feature",
  "properties": {
    "iso:country":"US",
    "sg:address":"2434 Orchard St",
    "sg:city":"Blue Island",
    "sg:classifiers":[
        {
            "category":"Building & Trades",
            "subcategory":"Cleaning & Sanitation",
            "type":"Services"
        }
    ],
    "sg:phone":"+1 708 371 3572",
    "sg:postcode":"60406",
    "sg:province":"IL",
    "sg:tags":[
        "carpet"
    ],
    "wof:name":"Mike's Special Service Carpet Cleaning",
    "wof:placetype":"venue"
},
  "geometry": {"coordinates":[-87.682098,41.668201],"type":"Point"}
}