{
  "type": "Feature",
  "properties": {
    "iso:country":"US",
    "sg:address":"736 N Western Ave",
    "sg:city":"Lake Forest",
    "sg:classifiers":[
        {
            "category":"Wholesale",
            "subcategory":"Construction Materials",
            "type":"Manufacturing & Wholesale Goods"
        },
        {
            "category":"Building & Trades",
            "subcategory":"Construction",
            "type":"Services"
        }
    ],
    "sg:phone":"+1 847 295 9900",
    "sg:postcode":"60045",
    "sg:province":"IL",
    "sg:tags":[
        "granite",
        "marble",
        "contractor"
    ],
    "sg:website":"www.mastercraftmarble.com",
    "wof:name":"Mastercraft Marble and Granite",
    "wof:placetype":"venue"
},
  "geometry": {"coordinates":[-87.840228,42.252685],"type":"Point"}
}