{
  "type": "Feature",
  "properties": {
    "iso:country":"US",
    "sg:address":"2925 200th Pl",
    "sg:city":"Lynwood",
    "sg:classifiers":[
        {
            "category":"Real Estate",
            "subcategory":"Real Estate Services",
            "type":"Services"
        }
    ],
    "sg:phone":"+1 708 889 9102",
    "sg:postcode":"60411",
    "sg:province":"IL",
    "sg:tags":[
        "consultant"
    ],
    "wof:name":"Oynxx Development Consultant, Inc",
    "wof:placetype":"venue"
},
  "geometry": {"coordinates":[-87.545649,41.532172],"type":"Point"}
}