{
  "type": "Feature",
  "properties": {
    "addr:full":"222 S Riverside Plz 29th FL Chicago IL 60606",
    "addr:housenumber":"222",
    "addr:postcode":"60606",
    "addr:street":"S Riverside Plz 29Th Fl",
    "iso:country":"US",
    "sg:address":"222 S Riverside Plz 29th FL",
    "sg:city":"Chicago",
    "sg:classifiers":[
        {
            "category":"Professional",
            "type":"Services"
        }
    ],
    "sg:phone":"+1 877 800 0604",
    "sg:postcode":"60606",
    "sg:province":"IL",
    "sg:website":"www.emeraldoffice.com",
    "wof:name":"Emerald Office",
    "wof:placetype":"venue"
},
  "geometry": {"coordinates":[-87.638808,41.87874],"type":"Point"}
}