{
  "type": "Feature",
  "properties": {
    "iso:country":"US",
    "sg:address":"7456 Lake St",
    "sg:city":"Moro",
    "sg:classifiers":[
        {
            "category":"Place Of Worship",
            "subcategory":"Church",
            "type":"Public Place"
        },
        {
            "category":"Place Of Worship",
            "type":"Public Place"
        }
    ],
    "sg:phone":"+1 618 377 9288",
    "sg:postcode":"62067",
    "sg:province":"IL",
    "sg:tags":[
        "testament",
        "christ-new",
        "churches-church",
        "christ"
    ],
    "wof:name":"Saint John United Church Of Christ",
    "wof:placetype":"venue"
},
  "geometry": {"coordinates":[-89.967918,38.929741],"type":"Point"}
}