{
  "type": "Feature",
  "properties": {
    "iso:country":"US",
    "sg:address":"400 Melissa Cir",
    "sg:city":"Romeoville",
    "sg:classifiers":[
        {
            "category":"Building & Trades",
            "subcategory":"Construction",
            "type":"Services"
        }
    ],
    "sg:phone":"+1 815 609 1736",
    "sg:postcode":"60446",
    "sg:province":"IL",
    "sg:tags":[
        "hanging",
        "contractor"
    ],
    "wof:name":"Paul Fanara Decorating Inc",
    "wof:placetype":"venue"
},
  "geometry": {"coordinates":[-88.144188,41.608717],"type":"Point"}
}