{
  "type": "Feature",
  "properties": {
    "addr:full":"9915 S 81st Ave Palos Hills IL 60465",
    "addr:housenumber":"9915",
    "addr:postcode":"60465",
    "addr:street":"S 81St Ave",
    "iso:country":"US",
    "sg:address":"9915 S 81st Ave",
    "sg:city":"Palos Hills",
    "sg:classifiers":[
        {
            "category":"Professional",
            "subcategory":"Advertising",
            "type":"Services"
        }
    ],
    "sg:phone":"+1 708 598 0255",
    "sg:postcode":"60465",
    "sg:province":"IL",
    "sg:tags":[
        "agency"
    ],
    "wof:name":"AC Media Representatives LLC",
    "wof:placetype":"venue"
},
  "geometry": {"coordinates":[-87.819883,41.709669],"type":"Point"}
}