{
  "type": "Feature",
  "properties": {
    "iso:country":"US",
    "sg:address":"5005 Newport Dr",
    "sg:city":"Rolling Meadows",
    "sg:classifiers":[
        {
            "category":"Professional",
            "subcategory":"Lawyer & Legal Services",
            "type":"Services"
        }
    ],
    "sg:phone":"+1 847 818 9166",
    "sg:postcode":"60008",
    "sg:province":"IL",
    "wof:name":"Belconis David Law Office",
    "wof:placetype":"venue"
},
  "geometry": {"coordinates":[-88.01732199999999,42.058022],"type":"Point"}
}