{
  "type": "Feature",
  "properties": {
    "iso:country":"US",
    "sg:address":"110 Brandywine Ct",
    "sg:city":"Vernon Hills",
    "sg:classifiers":[
        {
            "category":"Real Estate",
            "subcategory":"Real Estate Agent",
            "type":"Services"
        }
    ],
    "sg:phone":"+1 847 327 9092",
    "sg:postcode":"60061",
    "sg:province":"IL",
    "sg:tags":[
        "inspection"
    ],
    "wof:name":"Advanced Appliance Repair Svc",
    "wof:placetype":"venue"
},
  "geometry": {"coordinates":[-87.968157,42.244174],"type":"Point"}
}