{
  "type": "Feature",
  "properties": {
    "iso:country":"US",
    "sg:address":"17 Crescent Dr",
    "sg:city":"Mundelein",
    "sg:classifiers":[
        {
            "category":"Retail",
            "subcategory":"Repair Shop",
            "type":"Services"
        }
    ],
    "sg:phone":"+1 847 970 9353",
    "sg:postcode":"60060",
    "sg:province":"IL",
    "sg:tags":[
        "commercial",
        "welding"
    ],
    "wof:name":"Welding Consultant Services",
    "wof:placetype":"venue"
},
  "geometry": {"coordinates":[-88.053403,42.24189],"type":"Point"}
}