{
  "type": "Feature",
  "properties": {
    "iso:country":"US",
    "sg:address":"1007 Longaker Rd",
    "sg:city":"Northbrook",
    "sg:classifiers":[
        {
            "category":"Building & Trades",
            "subcategory":"Construction",
            "type":"Services"
        }
    ],
    "sg:phone":"+1 847 291 6936",
    "sg:postcode":"60062",
    "sg:province":"IL",
    "sg:tags":[
        "home",
        "improvement"
    ],
    "wof:name":"Allstar Construction",
    "wof:placetype":"venue"
},
  "geometry": {"coordinates":[-87.793325,42.135076],"type":"Point"}
}