{
  "type": "Feature",
  "properties": {
    "addr:full":"632 Kennedy Rd Carbondale IL 62902",
    "addr:housenumber":"632",
    "addr:postcode":"62902",
    "addr:street":"Kennedy Rd",
    "iso:country":"US",
    "sg:address":"632 Kennedy Rd",
    "sg:city":"Carbondale",
    "sg:classifiers":[
        {
            "category":"Travel",
            "subcategory":"Hotels & Motels",
            "type":"Entertainment"
        }
    ],
    "sg:phone":"+1 618 457 7400",
    "sg:postcode":"62902",
    "sg:province":"IL",
    "sg:website":"www.woodlandcabins.net",
    "wof:name":"Woodland Cabins",
    "wof:placetype":"venue"
},
  "geometry": {"coordinates":[-89.26565100000001,37.686729],"type":"Point"}
}