{
  "type": "Feature",
  "properties": {
    "addr:full":"120 W Madison Street Chicago IL 60602",
    "addr:housenumber":"120",
    "addr:postcode":"60602",
    "addr:street":"W Madison Street",
    "iso:country":"US",
    "sg:address":"120 W Madison Street",
    "sg:city":"Chicago",
    "sg:classifiers":[
        {
            "category":"Professional",
            "subcategory":"Accounting & Tax Preparation",
            "type":"Services"
        }
    ],
    "sg:phone":"+1 312 425 0001",
    "sg:postcode":"60602",
    "sg:province":"IL",
    "sg:tags":[
        "accountant"
    ],
    "wof:name":"Forde Jack CPA",
    "wof:placetype":"venue"
},
  "geometry": {"coordinates":[-87.631496,41.881978],"type":"Point"}
}