{
  "type": "Feature",
  "properties": {
    "iso:country":"US",
    "sg:address":"1468 Townline Rd",
    "sg:city":"Mundelein",
    "sg:classifiers":[
        {
            "category":"Shopping",
            "type":"Retail Goods"
        }
    ],
    "sg:phone":"+1   ",
    "sg:postcode":"60060",
    "sg:province":"IL",
    "sg:tags":[
        "communication",
        "product",
        "cellular"
    ],
    "wof:name":"Commone",
    "wof:placetype":"venue"
},
  "geometry": {"coordinates":[-87.99029,42.240531],"type":"Point"}
}