{
  "type": "Feature",
  "properties": {
    "iso:country":"US",
    "sg:address":"1255 Pleasant Ridge Rd",
    "sg:city":"Collinsville",
    "sg:classifiers":[
        {
            "category":"Sports & Exercise",
            "subcategory":"Race Track",
            "type":"Entertainment"
        }
    ],
    "sg:phone":"+1 618 345 0240",
    "sg:postcode":"62234",
    "sg:province":"IL",
    "sg:tags":[
        "operation",
        "racing",
        "or"
    ],
    "wof:name":"Wilborn Racing Stable Inc",
    "wof:placetype":"venue"
},
  "geometry": {"coordinates":[-89.97110499999999,38.704249],"type":"Point"}
}