{
  "type": "Feature",
  "properties": {
    "addr:full":"3300 W Armitage Ave Chicago IL 60647",
    "addr:housenumber":"3300",
    "addr:postcode":"60647",
    "addr:street":"W Armitage Ave",
    "iso:country":"US",
    "sg:address":"3300 W Armitage Ave",
    "sg:city":"Chicago",
    "sg:classifiers":[
        {
            "category":"Food & Beverages",
            "subcategory":"Groceries & Convenience Stores",
            "type":"Retail Goods"
        }
    ],
    "sg:phone":"+1   ",
    "sg:postcode":"60647",
    "sg:province":"IL",
    "wof:name":"San Lorenzo Foodmart",
    "wof:placetype":"venue"
},
  "geometry": {"coordinates":[-87.711905,41.917342],"type":"Point"}
}