{
  "type": "Feature",
  "properties": {
    "addr:full":"9748 S Vanderpoel Ave Chicago IL 60643",
    "addr:housenumber":"9748",
    "addr:postcode":"60643",
    "addr:street":"S Vanderpoel Ave",
    "iso:country":"US",
    "sg:address":"9748 S Vanderpoel Ave",
    "sg:city":"Chicago",
    "sg:classifiers":[
        {
            "category":"Wholesale",
            "subcategory":"Non-durable Goods",
            "type":"Manufacturing & Wholesale Goods"
        },
        {
            "category":"Professional",
            "subcategory":"Business Services",
            "type":"Services"
        }
    ],
    "sg:phone":"+1 773 238 1865",
    "sg:postcode":"60643",
    "sg:province":"IL",
    "sg:tags":[
        "broker",
        "merchandise",
        "merchandise-wholesale"
    ],
    "wof:name":"Dek Company",
    "wof:placetype":"venue"
},
  "geometry": {"coordinates":[-87.66577700000001,41.716629],"type":"Point"}
}