{
  "type": "Feature",
  "properties": {
    "addr:full":"1108 Olive St Saint Louis MO 63101",
    "addr:housenumber":"1108",
    "addr:postcode":"63101",
    "addr:street":"Olive St",
    "iso:country":"US",
    "sg:address":"1108 Olive St",
    "sg:city":"Saint Louis",
    "sg:classifiers":[
        {
            "category":"Professional",
            "subcategory":"Lawyer & Legal Services",
            "type":"Services"
        }
    ],
    "sg:phone":"+1 314 621 1701",
    "sg:postcode":"63101",
    "sg:province":"MO",
    "wof:name":"Mandel Alan S Atty",
    "wof:placetype":"venue"
},
  "geometry": {"coordinates":[-90.195801,38.629398],"type":"Point"}
}