{
  "type": "Feature",
  "properties": {
    "iso:country":"US",
    "sg:address":"1000 Criss Cir",
    "sg:city":"Elk Grove Village",
    "sg:classifiers":[
        {
            "category":"Building & Trades",
            "subcategory":"Plumbing",
            "type":"Services"
        }
    ],
    "sg:phone":"+1 847 640 0880",
    "sg:postcode":"60007",
    "sg:province":"IL",
    "sg:tags":[
        "plumbing",
        "contractor"
    ],
    "wof:name":"F Robert Phillips Company",
    "wof:placetype":"venue"
},
  "geometry": {"coordinates":[-87.974749,42.031465],"type":"Point"}
}