{
  "type": "Feature",
  "properties": {
    "iso:country":"US",
    "sg:address":"1144 W Diversey Pkwy",
    "sg:city":"Chicago",
    "sg:classifiers":[
        {
            "category":"Personal",
            "subcategory":"Day Spa",
            "type":"Services"
        }
    ],
    "sg:phone":"+1 773 880 0858",
    "sg:postcode":"60614",
    "sg:province":"IL",
    "wof:name":"A New Life Spa",
    "wof:placetype":"venue"
},
  "geometry": {"coordinates":[-87.657653,41.932722],"type":"Point"}
}