{
  "type": "Feature",
  "properties": {
    "iso:country":"US",
    "sg:address":"112 Allison Ct",
    "sg:city":"Bolingbrook",
    "sg:classifiers":[
        {
            "category":"Building & Trades",
            "subcategory":"Construction",
            "type":"Services"
        }
    ],
    "sg:phone":"+1 630 783 4077",
    "sg:postcode":"60440",
    "sg:province":"IL",
    "sg:tags":[
        "concrete",
        "contractor"
    ],
    "wof:name":"Residential Concrete Svc",
    "wof:placetype":"venue"
},
  "geometry": {"coordinates":[-88.050921,41.700776],"type":"Point"}
}