{
  "type": "Feature",
  "properties": {
    "iso:country":"US",
    "sg:address":"93 Kensington Cir",
    "sg:city":"Wheaton",
    "sg:classifiers":[
        {
            "category":"Professional",
            "subcategory":"Lawyer & Legal Services",
            "type":"Services"
        }
    ],
    "sg:phone":"+1 630 653 7339",
    "sg:postcode":"60187",
    "sg:province":"IL",
    "sg:tags":[
        "attorney"
    ],
    "wof:name":"Carol A Coon",
    "wof:placetype":"venue"
},
  "geometry": {"coordinates":[-88.095605,41.834725],"type":"Point"}
}