{
  "type": "Feature",
  "properties": {
    "iso:country":"US",
    "sg:address":"2910 Fawn Trail Ct",
    "sg:city":"Crystal Lake",
    "sg:classifiers":[
        {
            "category":"Professional",
            "subcategory":"Computer Services",
            "type":"Services"
        }
    ],
    "sg:phone":"+1 815 477 2967",
    "sg:postcode":"60012",
    "sg:province":"IL",
    "sg:tags":[
        "related"
    ],
    "wof:name":"Mike Shedlock Inc",
    "wof:placetype":"venue"
},
  "geometry": {"coordinates":[-88.254168,42.275344],"type":"Point"}
}