{
  "type": "Feature",
  "properties": {
    "iso:country":"US",
    "sg:address":"703 N 6th St",
    "sg:city":"Vandalia",
    "sg:classifiers":[
        {
            "category":"Building & Trades",
            "subcategory":"Construction",
            "type":"Services"
        }
    ],
    "sg:phone":"+1 618 283 2303",
    "sg:postcode":"62471",
    "sg:province":"IL",
    "sg:tags":[
        "roofing",
        "contractor"
    ],
    "wof:name":"Cox Roofing",
    "wof:placetype":"venue"
},
  "geometry": {"coordinates":[-89.097534,38.968639],"type":"Point"}
}