{
  "type": "Feature",
  "properties": {
    "addr:full":"108 E Poplar St Robinson IL 62454",
    "addr:housenumber":"108",
    "addr:postcode":"62454",
    "addr:street":"E Poplar St",
    "iso:country":"US",
    "sg:address":"108 E Poplar St",
    "sg:city":"Robinson",
    "sg:classifiers":[
        {
            "category":"Utilities",
            "subcategory":"Water",
            "type":"Services"
        }
    ],
    "sg:phone":"+1 618 544 3188",
    "sg:postcode":"62454",
    "sg:province":"IL",
    "sg:tags":[
        "company-utility",
        "system",
        "supply"
    ],
    "wof:name":"Robinson-Palestine Water Commission",
    "wof:placetype":"venue"
},
  "geometry": {"coordinates":[-87.73918399999999,39.00129],"type":"Point"}
}