{
  "type": "Feature",
  "properties": {
    "addr:full":"11137 Northwest Rd Palos Hills IL 60465",
    "addr:housenumber":"11137",
    "addr:postcode":"60465",
    "addr:street":"Northwest Rd",
    "iso:country":"US",
    "sg:address":"11137 Northwest Rd",
    "sg:city":"Palos Hills",
    "sg:classifiers":[
        {
            "category":"Building & Trades",
            "subcategory":"Plumbing",
            "type":"Services"
        }
    ],
    "sg:phone":"+1 708 974 2845",
    "sg:postcode":"60465",
    "sg:province":"IL",
    "sg:tags":[
        "contractor"
    ],
    "wof:name":"C&G Heating & Cooling Inc",
    "wof:placetype":"venue"
},
  "geometry": {"coordinates":[-87.843991,41.687544],"type":"Point"}
}