{
  "type": "Feature",
  "properties": {
    "iso:country":"US",
    "sg:address":"5539 N Austin Ave",
    "sg:city":"Chicago",
    "sg:classifiers":[
        {
            "category":"Building & Trades",
            "subcategory":"Construction",
            "type":"Services"
        }
    ],
    "sg:phone":"+1 773 218 1694",
    "sg:postcode":"60630",
    "sg:province":"IL",
    "sg:tags":[
        "excavation",
        "contractor"
    ],
    "wof:name":"Premier Excavation Inc",
    "wof:placetype":"venue"
},
  "geometry": {"coordinates":[-87.77803299999999,41.981797],"type":"Point"}
}