{
  "type": "Feature",
  "properties": {
    "addr:full":"1835 Waukegan Rd Techny IL 60062",
    "addr:housenumber":"1835",
    "addr:postcode":"60062",
    "addr:street":"Waukegan Rd",
    "iso:country":"US",
    "sg:address":"1835 Waukegan Rd",
    "sg:city":"Techny",
    "sg:classifiers":[
        {
            "category":"Professional",
            "subcategory":"Management & Consulting",
            "type":"Services"
        }
    ],
    "sg:phone":"+1 847 272 7600",
    "sg:postcode":"60062",
    "sg:province":"IL",
    "sg:tags":[
        "marketing",
        "program"
    ],
    "sg:website":"www.divinewordmissionaries.org",
    "wof:name":"Divine Word Missionaries",
    "wof:placetype":"venue"
},
  "geometry": {"coordinates":[-87.80708199999999,42.116417],"type":"Point"}
}