{
  "type": "Feature",
  "properties": {
    "iso:country":"US",
    "sg:address":"201 S 17th Ave",
    "sg:city":"Maywood",
    "sg:classifiers":[
        {
            "category":"Professional",
            "subcategory":"Accounting & Tax Preparation",
            "type":"Services"
        }
    ],
    "sg:phone":"+1 708 344 2177",
    "sg:postcode":"60153",
    "sg:province":"IL",
    "sg:tags":[
        "auditing",
        "bookkeeping"
    ],
    "wof:name":"Small Business Matters",
    "wof:placetype":"venue"
},
  "geometry": {"coordinates":[-87.853991,41.884071],"type":"Point"}
}