{
  "type": "Feature",
  "properties": {
    "addr:full":"243 E 147th St Harvey IL 60426",
    "addr:housenumber":"243",
    "addr:postcode":"60426",
    "addr:street":"E 147Th St",
    "iso:country":"US",
    "sg:address":"243 E 147th St",
    "sg:city":"Harvey",
    "sg:classifiers":[
        {
            "category":"Restaurant",
            "type":"Food & Drink"
        }
    ],
    "sg:phone":"+1 708 596 3663",
    "sg:postcode":"60426",
    "sg:province":"IL",
    "wof:name":"Shark's Fish & Chicken",
    "wof:placetype":"venue"
},
  "geometry": {"coordinates":[-87.643204,41.6227],"type":"Point"}
}