{
  "type": "Feature",
  "properties": {
    "iso:country":"US",
    "sg:address":"1215 E 87th St",
    "sg:city":"Chicago",
    "sg:phone":"+1 773 768 8000",
    "sg:postcode":"60619",
    "sg:province":"IL",
    "wof:name":"Payday Loan Store",
    "wof:placetype":"venue"
},
  "geometry": {"coordinates":[-87.59438,41.736791],"type":"Point"}
}