{
  "type": "Feature",
  "properties": {
    "addr:full":"789 McMullin Dr Kankakee IL 60901",
    "addr:housenumber":"789",
    "addr:postcode":"60901",
    "addr:street":"Mcmullin Dr",
    "iso:country":"US",
    "sg:address":"789 McMullin Dr",
    "sg:city":"Kankakee",
    "sg:classifiers":[
        {
            "category":"Wholesale",
            "subcategory":"Non-durable Goods",
            "type":"Manufacturing & Wholesale Goods"
        }
    ],
    "sg:phone":"+1 815 939 8822",
    "sg:postcode":"60901",
    "sg:province":"IL",
    "sg:tags":[
        "public",
        "relations"
    ],
    "sg:website":"www.premiumspecialties.com",
    "wof:name":"Premium Specialties",
    "wof:placetype":"venue"
},
  "geometry": {"coordinates":[-87.86891300000001,41.112642],"type":"Point"}
}