{
  "type": "Feature",
  "properties": {
    "iso:country":"US",
    "sg:address":"152 Baker Rd",
    "sg:city":"Lake Bluff",
    "sg:classifiers":[
        {
            "category":"Shopping",
            "subcategory":"Florist",
            "type":"Retail Goods"
        }
    ],
    "sg:phone":"+1   ",
    "sg:postcode":"60044",
    "sg:province":"IL",
    "wof:name":"Designs By Jody Inc",
    "wof:placetype":"venue"
},
  "geometry": {"coordinates":[-87.901152,42.281619],"type":"Point"}
}