{
  "type": "Feature",
  "properties": {
    "addr:full":"616 E Green St Champaign IL 61820",
    "addr:housenumber":"616",
    "addr:postcode":"61820",
    "addr:street":"E Green St",
    "iso:country":"US",
    "sg:address":"616 E Green St",
    "sg:city":"Champaign",
    "sg:classifiers":[
        {
            "category":"Insurance",
            "subcategory":"Health Insurance",
            "type":"Services"
        }
    ],
    "sg:phone":"+1 217 337 5555",
    "sg:postcode":"61820",
    "sg:province":"IL",
    "sg:tags":[
        "market"
    ],
    "wof:name":"Smoothie King",
    "wof:placetype":"venue"
},
  "geometry": {"coordinates":[-88.23020200000001,40.110401],"type":"Point"}
}