{
  "type": "Feature",
  "properties": {
    "addr:full":"109 Cypress Dr Bolingbrook IL 60440",
    "addr:housenumber":"109",
    "addr:postcode":"60440",
    "addr:street":"Cypress Dr",
    "iso:country":"US",
    "sg:address":"109 Cypress Dr",
    "sg:city":"Bolingbrook",
    "sg:classifiers":[
        {
            "category":"Shopping",
            "subcategory":"Pharmacy",
            "type":"Retail Goods"
        }
    ],
    "sg:phone":"+1 630 759 0360",
    "sg:postcode":"60440",
    "sg:province":"IL",
    "wof:name":"Prescription Information Card",
    "wof:placetype":"venue"
},
  "geometry": {"coordinates":[-88.073702,41.697486],"type":"Point"}
}