{
  "type": "Feature",
  "properties": {
    "addr:full":"1500 North Wells 2nd Floor Chicago IL 60686",
    "addr:housenumber":"1500;2nd floor",
    "addr:postcode":"60686",
    "addr:street":"North Wells",
    "iso:country":"US",
    "sg:address":"1500 North Wells 2nd Floor",
    "sg:city":"Chicago",
    "sg:classifiers":[
        {
            "category":"Personal",
            "subcategory":"Beauty Salon",
            "type":"Services"
        }
    ],
    "sg:phone":"+1 312 944 6747",
    "sg:postcode":"60686",
    "sg:province":"IL",
    "sg:tags":[
        "spa"
    ],
    "wof:name":"Campagnia della Bellezza",
    "wof:placetype":"venue"
},
  "geometry": {"coordinates":[-87.63499899999999,41.909222],"type":"Point"}
}