{
  "type": "Feature",
  "properties": {
    "addr:full":"390 S 8th St Fl 2 West Dundee IL 60118",
    "addr:housenumber":"390;2",
    "addr:postcode":"60118",
    "addr:street":"S 8Th St",
    "iso:country":"US",
    "sg:address":"390 S 8th St Fl 2",
    "sg:city":"West Dundee",
    "sg:classifiers":[
        {
            "category":"Banks & Credit Unions",
            "subcategory":"Financial Services",
            "type":"Services"
        }
    ],
    "sg:phone":"+1 847 426 8500",
    "sg:postcode":"60118",
    "sg:province":"IL",
    "sg:tags":[
        "broker",
        "mortgage"
    ],
    "wof:name":"Illinois Lending Commission Inc",
    "wof:placetype":"venue"
},
  "geometry": {"coordinates":[-88.287201,42.095299],"type":"Point"}
}