{
  "type": "Feature",
  "properties": {
    "iso:country":"US",
    "sg:address":"104 Village Sq",
    "sg:city":"Bradley",
    "sg:classifiers":[
        {
            "category":"Personal",
            "subcategory":"Nail Salon",
            "type":"Services"
        }
    ],
    "sg:phone":"+1 815 937 9777",
    "sg:postcode":"60915",
    "sg:province":"IL",
    "wof:name":"United States Nail",
    "wof:placetype":"venue"
},
  "geometry": {"coordinates":[-87.85281999999999,41.148671],"type":"Point"}
}