{
  "type": "Feature",
  "properties": {
    "iso:country":"US",
    "sg:address":"40338 N Deep Lake Rd",
    "sg:city":"Antioch",
    "sg:classifiers":[
        {
            "category":"Restaurant",
            "type":"Food & Drink"
        },
        {
            "category":"Manufacturing",
            "subcategory":"Pet Food",
            "type":"Manufacturing & Wholesale Goods"
        }
    ],
    "sg:phone":"+1 847 395 5005",
    "sg:postcode":"60002",
    "sg:province":"IL",
    "sg:tags":[
        "mill",
        "pizza",
        "eating",
        "mfg"
    ],
    "wof:name":"Ron & Pat's Pizza Shack",
    "wof:placetype":"venue"
},
  "geometry": {"coordinates":[-88.06253100000001,42.449243],"type":"Point"}
}