{
  "type": "Feature",
  "properties": {
    "addr:full":"1917 Wright Blvd Schaumburg IL 60193",
    "addr:housenumber":"1917",
    "addr:postcode":"60193",
    "addr:street":"Wright Blvd",
    "iso:country":"US",
    "sg:address":"1917 Wright Blvd",
    "sg:city":"Schaumburg",
    "sg:classifiers":[
        {
            "category":"Building & Trades",
            "subcategory":"Construction",
            "type":"Services"
        }
    ],
    "sg:phone":"+1 847 584 4545",
    "sg:postcode":"60193",
    "sg:province":"IL",
    "sg:tags":[
        "industrial",
        "mate"
    ],
    "wof:name":"Panels Plus Inc",
    "wof:placetype":"venue"
},
  "geometry": {"coordinates":[-88.101732,41.992995],"type":"Point"}
}