{
  "type": "Feature",
  "properties": {
    "addr:full":"330 N Gilbert St Danville IL 61832",
    "addr:housenumber":"330",
    "addr:postcode":"61832",
    "addr:street":"N Gilbert St",
    "iso:country":"US",
    "sg:address":"330 N Gilbert St",
    "sg:city":"Danville",
    "sg:classifiers":[
        {
            "category":"Real Estate",
            "subcategory":"Real Estate Services",
            "type":"Services"
        }
    ],
    "sg:phone":"+1 217 446 8339",
    "sg:postcode":"61832",
    "sg:province":"IL",
    "sg:tags":[
        "company",
        "title"
    ],
    "wof:name":"Midwest Title Loans",
    "wof:placetype":"venue"
},
  "geometry": {"coordinates":[-87.635654,40.130008],"type":"Point"}
}