{
  "type": "Feature",
  "properties": {
    "iso:country":"US",
    "sg:address":"6118 N Lincoln Ave",
    "sg:city":"Chicago",
    "sg:classifiers":[
        {
            "category":"Personal",
            "subcategory":"Beauty Salon",
            "type":"Services"
        }
    ],
    "sg:phone":"+1 773 588 4600",
    "sg:postcode":"60659",
    "sg:province":"IL",
    "wof:name":"Dieter Denmar",
    "wof:placetype":"venue"
},
  "geometry": {"coordinates":[-87.712119,41.993157],"type":"Point"}
}