{
  "type": "Feature",
  "properties": {
    "iso:country":"US",
    "sg:address":"5600 N Menard Ave",
    "sg:city":"Chicago",
    "sg:classifiers":[
        {
            "category":"Manufacturing",
            "subcategory":"Aerospace",
            "type":"Manufacturing & Wholesale Goods"
        }
    ],
    "sg:phone":"+1 773 894 8940",
    "sg:postcode":"60646",
    "sg:province":"IL",
    "sg:tags":[
        "instrument",
        "aircraft",
        "avionics"
    ],
    "wof:name":"Swissport Cargo Services, L. P.",
    "wof:placetype":"venue"
},
  "geometry": {"coordinates":[-87.773178,41.98291],"type":"Point"}
}