{
  "type": "Feature",
  "properties": {
    "iso:country":"US",
    "sg:address":"2103 E Lillian Ln",
    "sg:city":"Arlington Hts",
    "sg:classifiers":[
        {
            "category":"Professional",
            "subcategory":"Lawyer & Legal Services",
            "type":"Services"
        }
    ],
    "sg:phone":"+1 847 255 0550",
    "sg:postcode":"60004",
    "sg:province":"IL",
    "sg:tags":[
        "attorney"
    ],
    "wof:name":"Francine Schwartz PC",
    "wof:placetype":"venue"
},
  "geometry": {"coordinates":[-87.959064,42.108377],"type":"Point"}
}