{
  "type": "Feature",
  "properties": {
    "addr:full":"7562 N Western Ave Chicago IL 60645",
    "addr:housenumber":"7562",
    "addr:postcode":"60645",
    "addr:street":"N Western Ave",
    "iso:country":"US",
    "sg:address":"7562 N Western Ave",
    "sg:city":"Chicago",
    "sg:classifiers":[
        {
            "category":"Shopping",
            "subcategory":"Clothing, Apparel, & Fashions",
            "type":"Retail Goods"
        }
    ],
    "sg:phone":"+1 773 764 2879",
    "sg:postcode":"60645",
    "sg:province":"IL",
    "wof:name":"Dots Inc",
    "wof:placetype":"venue"
},
  "geometry": {"coordinates":[-87.69026599999999,42.017977],"type":"Point"}
}