{
  "type": "Feature",
  "properties": {
    "addr:full":"2500 N Main St Rockford IL 61103",
    "addr:housenumber":"2500",
    "addr:postcode":"61103",
    "addr:street":"N Main St",
    "iso:country":"US",
    "sg:address":"2500 N Main St",
    "sg:city":"Rockford",
    "sg:classifiers":[
        {
            "category":"Building & Trades",
            "subcategory":"Electrical",
            "type":"Services"
        }
    ],
    "sg:phone":"+1 815 963 1275",
    "sg:postcode":"61103",
    "sg:province":"IL",
    "sg:tags":[
        "industrial",
        "electrician",
        "contractors-commercial",
        "electric"
    ],
    "wof:name":"Garwic Electric Inc.",
    "wof:placetype":"venue"
},
  "geometry": {"coordinates":[-89.077141,42.29953],"type":"Point"}
}