{
  "type": "Feature",
  "properties": {
    "iso:country":"US",
    "sg:address":"320 N Galena Ave",
    "sg:city":"Freeport",
    "sg:classifiers":[
        {
            "category":"Real Estate",
            "subcategory":"Real Estate Agent",
            "type":"Services"
        }
    ],
    "sg:phone":"+1 815 235 3100",
    "sg:postcode":"61032",
    "sg:province":"IL",
    "wof:name":"Ohlinger Realty",
    "wof:placetype":"venue"
},
  "geometry": {"coordinates":[-89.623493,42.299735],"type":"Point"}
}