{
  "type": "Feature",
  "properties": {
    "iso:country":"US",
    "sg:address":"5304 N Clark St",
    "sg:city":"Chicago",
    "sg:classifiers":[
        {
            "category":"Food & Beverages",
            "subcategory":"Bakery",
            "type":"Retail Goods"
        }
    ],
    "sg:postcode":"60640",
    "sg:province":"IL",
    "sg:tags":[
        "sandwich"
    ],
    "sg:website":"www.potbelly.com/",
    "wof:name":"Potbelly's Sandwich Works",
    "wof:placetype":"venue"
},
  "geometry": {"coordinates":[-87.668362,41.978196],"type":"Point"}
}