{
  "type": "Feature",
  "properties": {
    "addr:full":"1701 N Ashland Avenue Chicago IL 60622",
    "addr:housenumber":"1701",
    "addr:postcode":"60622",
    "addr:street":"N Ashland Avenue",
    "iso:country":"US",
    "sg:address":"1701 N Ashland Avenue",
    "sg:city":"Chicago",
    "sg:classifiers":[
        {
            "category":"Banks & Credit Unions",
            "subcategory":"Financial Services",
            "type":"Services"
        }
    ],
    "sg:phone":"+1 773 584 6315",
    "sg:postcode":"60622",
    "sg:province":"IL",
    "sg:tags":[
        "broker",
        "mortgage"
    ],
    "wof:name":"Nasa Financial Services",
    "wof:placetype":"venue"
},
  "geometry": {"coordinates":[-87.66781899999999,41.912594],"type":"Point"}
}