{
  "type": "Feature",
  "properties": {
    "addr:full":"3150 W Salt Creek Ln Arlington Hts IL 60005",
    "addr:housenumber":"3150",
    "addr:postcode":"60005",
    "addr:street":"W Salt Creek Ln",
    "iso:country":"US",
    "sg:address":"3150 W Salt Creek Ln",
    "sg:city":"Arlington Hts",
    "sg:classifiers":[
        {
            "category":"Professional",
            "type":"Services"
        }
    ],
    "sg:phone":"+1 847 342 7499",
    "sg:postcode":"60005",
    "sg:province":"IL",
    "sg:tags":[
        "establishment"
    ],
    "wof:name":"C Tca",
    "wof:placetype":"venue"
},
  "geometry": {"coordinates":[-88.021101,42.092189],"type":"Point"}
}