{
  "type": "Feature",
  "properties": {
    "addr:full":"112 E Grand Ave Elmhurst IL 60126",
    "addr:housenumber":"112",
    "addr:postcode":"60126",
    "addr:street":"E Grand Ave",
    "iso:country":"US",
    "sg:address":"112 E Grand Ave",
    "sg:city":"Elmhurst",
    "sg:classifiers":[
        {
            "category":"Utilities",
            "subcategory":"Mobile Phone",
            "type":"Services"
        }
    ],
    "sg:phone":"+1 630 833 2704",
    "sg:postcode":"60126",
    "sg:province":"IL",
    "sg:tags":[
        "communication",
        "radiotelephone"
    ],
    "wof:name":"Brience",
    "wof:placetype":"venue"
},
  "geometry": {"coordinates":[-87.936294,41.931486],"type":"Point"}
}