{
  "type": "Feature",
  "properties": {
    "iso:country":"US",
    "sg:address":"3239 N Oriole Ave",
    "sg:city":"Chicago",
    "sg:classifiers":[
        {
            "category":"Building & Trades",
            "subcategory":"Electrical",
            "type":"Services"
        }
    ],
    "sg:phone":"+1 312 415 2803",
    "sg:postcode":"60634",
    "sg:province":"IL",
    "sg:tags":[
        "electrician"
    ],
    "wof:name":"Industrial and Testing Electricians",
    "wof:placetype":"venue"
},
  "geometry": {"coordinates":[-87.81619000000001,41.939123],"type":"Point"}
}