{
  "type": "Feature",
  "properties": {
    "iso:country":"US",
    "sg:address":"38788 N Broadway Ave",
    "sg:city":"Antioch",
    "sg:classifiers":[
        {
            "category":"Autos & Motor Vehicles",
            "subcategory":"Boat Sales",
            "type":"Retail Goods"
        }
    ],
    "sg:phone":"+1 847 395 8110",
    "sg:postcode":"60002",
    "sg:province":"IL",
    "sg:tags":[
        "repair",
        "maintenance"
    ],
    "wof:name":"Tradewinds Marine Center Inc",
    "wof:placetype":"venue"
},
  "geometry": {"coordinates":[-88.14241,42.425986],"type":"Point"}
}