{
  "type": "Feature",
  "properties": {
    "addr:full":"502 270th Ave Little York IL 61453",
    "addr:housenumber":"502",
    "addr:postcode":"61453",
    "addr:street":"270Th Ave",
    "iso:country":"US",
    "sg:address":"502 270th Ave",
    "sg:city":"Little York",
    "sg:classifiers":[
        {
            "category":"Farming",
            "subcategory":"Livestock Farm",
            "type":"Manufacturing & Wholesale Goods"
        }
    ],
    "sg:phone":"+1 309 729 5531",
    "sg:postcode":"61453",
    "sg:province":"IL",
    "sg:tags":[
        "hog",
        "or",
        "feedlot"
    ],
    "wof:name":"Bob Brownlee",
    "wof:placetype":"venue"
},
  "geometry": {"coordinates":[-90.687528,41.023917],"type":"Point"}
}