{
  "type": "Feature",
  "properties": {
    "iso:country":"US",
    "sg:address":"15138 Station Rd",
    "sg:city":"East Dubuque",
    "sg:classifiers":[
        {
            "category":"Building & Trades",
            "subcategory":"Landscaping Services",
            "type":"Services"
        }
    ],
    "sg:phone":"+1 815 747 3866",
    "sg:postcode":"61025",
    "sg:province":"IL",
    "wof:name":"Woodsmen",
    "wof:placetype":"venue"
},
  "geometry": {"coordinates":[-90.517211,42.428708],"type":"Point"}
}