{
  "type": "Feature",
  "properties": {
    "iso:country":"US",
    "sg:address":"1056 E 162nd St",
    "sg:city":"South Holland",
    "sg:classifiers":[
        {
            "category":"Shopping",
            "subcategory":"Mobile Phones",
            "type":"Retail Goods"
        }
    ],
    "sg:phone":"+1 708 596 4900",
    "sg:postcode":"60473",
    "sg:province":"IL",
    "wof:name":"Wireless Central",
    "wof:placetype":"venue"
},
  "geometry": {"coordinates":[-87.591014,41.600967],"type":"Point"}
}