{
  "type": "Feature",
  "properties": {
    "iso:country":"US",
    "sg:address":"515 E 29th St",
    "sg:city":"Chicago",
    "sg:classifiers":[
        {
            "category":"Health Services",
            "subcategory":"Clinic",
            "type":"Services"
        }
    ],
    "sg:phone":"+1 312 791 2181",
    "sg:postcode":"60616",
    "sg:province":"IL",
    "sg:tags":[
        "welfare"
    ],
    "wof:name":"Midwest Health Plus Ltd",
    "wof:placetype":"venue"
},
  "geometry": {"coordinates":[-87.61406700000001,41.842097],"type":"Point"}
}