{
  "type": "Feature",
  "properties": {
    "iso:country":"US",
    "sg:address":"2549 N Southport Avenue",
    "sg:city":"Chicago",
    "sg:classifiers":[
        {
            "category":"Retail",
            "subcategory":"Laundry & Dry Cleaning",
            "type":"Services"
        }
    ],
    "sg:phone":"+1 773 281 7202",
    "sg:postcode":"60614",
    "sg:province":"IL",
    "wof:name":"4U Cleaners",
    "wof:placetype":"venue"
},
  "geometry": {"coordinates":[-87.66340599999999,41.928174],"type":"Point"}
}