{
  "type": "Feature",
  "properties": {
    "iso:country":"US",
    "sg:address":"611 Lunt Ave",
    "sg:city":"Schaumburg",
    "sg:classifiers":[
        {
            "category":"Organizations",
            "subcategory":"Membership Organization",
            "type":"Services"
        }
    ],
    "sg:phone":"+1 847 352 7422",
    "sg:postcode":"60193",
    "sg:province":"IL",
    "wof:name":"Schaumburg Athletic Assn",
    "wof:placetype":"venue"
},
  "geometry": {"coordinates":[-88.097487,42.001492],"type":"Point"}
}