{
  "type": "Feature",
  "properties": {
    "iso:country":"US",
    "sg:address":"1100 Madison St",
    "sg:city":"Maywood",
    "sg:classifiers":[
        {
            "category":"Social Services",
            "type":"Services"
        }
    ],
    "sg:phone":"+1 708 865 0605",
    "sg:postcode":"60153",
    "sg:province":"IL",
    "wof:name":"Headstart",
    "wof:placetype":"venue"
},
  "geometry": {"coordinates":[-87.847507,41.878789],"type":"Point"}
}