{
  "type": "Feature",
  "properties": {
    "iso:country":"US",
    "sg:address":"3012 W 111th St",
    "sg:city":"Chicago",
    "sg:classifiers":[
        {
            "category":"Utilities",
            "subcategory":"Telephone",
            "type":"Services"
        }
    ],
    "sg:phone":"+1 847 266 9900",
    "sg:postcode":"60655",
    "sg:province":"IL",
    "sg:tags":[
        "communications"
    ],
    "wof:name":"Insnet",
    "wof:placetype":"venue"
},
  "geometry": {"coordinates":[-87.696738,41.691691],"type":"Point"}
}