{
  "type": "Feature",
  "properties": {
    "addr:full":"12299 N State Hwy 49 Casey IL 62420",
    "addr:housenumber":"12299",
    "addr:postcode":"62420",
    "addr:street":"N State Hwy 49",
    "iso:country":"US",
    "sg:address":"12299 N State Hwy 49",
    "sg:city":"Casey",
    "sg:phone":"+1 217 932 2076",
    "sg:postcode":"62420",
    "sg:province":"IL",
    "sg:tags":[
        "farm",
        "corn",
        "soybean"
    ],
    "wof:name":"Eddie Allen",
    "wof:placetype":"venue"
},
  "geometry": {"coordinates":[-87.984292,39.327962],"type":"Point"}
}