{
  "type": "Feature",
  "properties": {
    "iso:country":"US",
    "sg:address":"5405 W Madison St",
    "sg:city":"Chicago",
    "sg:classifiers":[
        {
            "category":"Retail",
            "subcategory":"Laundry & Dry Cleaning",
            "type":"Services"
        }
    ],
    "sg:phone":"+1 773 261 1346",
    "sg:postcode":"60644",
    "sg:province":"IL",
    "sg:tags":[
        "drycleaning",
        "plant"
    ],
    "wof:name":"Rose Cleaners",
    "wof:placetype":"venue"
},
  "geometry": {"coordinates":[-87.761002,41.8801],"type":"Point"}
}