{
  "type": "Feature",
  "properties": {
    "iso:country":"US",
    "sg:address":"8919 Moore Dr",
    "sg:city":"Bridgeview",
    "sg:classifiers":[
        {
            "category":"Autos & Motor Vehicles",
            "subcategory":"Motorcycle Sales",
            "type":"Retail Goods"
        }
    ],
    "sg:phone":"+1 708 430 4457",
    "sg:postcode":"60455",
    "sg:province":"IL",
    "wof:name":"South Side Cycles",
    "wof:placetype":"venue"
},
  "geometry": {"coordinates":[-87.801697,41.728901],"type":"Point"}
}