{
  "type": "Feature",
  "properties": {
    "iso:country":"US",
    "sg:address":"824 Clark St",
    "sg:city":"Evanston",
    "sg:classifiers":[
        {
            "category":"Fast Food",
            "type":"Food & Drink"
        },
        {
            "category":"Restaurant",
            "type":"Food & Drink"
        },
        {
            "category":"Food & Beverages",
            "subcategory":"Groceries & Convenience Stores",
            "type":"Retail Goods"
        }
    ],
    "sg:phone":"+1 847 328 8858",
    "sg:postcode":"60201",
    "sg:province":"IL",
    "sg:tags":[
        "shop",
        "sandwich",
        "take"
    ],
    "sg:website":"http://www.jimmyjohns.com",
    "wof:name":"Jimmy John's",
    "wof:placetype":"venue"
},
  "geometry": {"coordinates":[-87.682151,42.049983],"type":"Point"}
}