{
  "type": "Feature",
  "properties": {
    "addr:full":"1030 E Central Rd Arlington Heights IL 60005",
    "addr:housenumber":"1030",
    "addr:postcode":"60005",
    "addr:street":"E Central Rd",
    "iso:country":"US",
    "sg:address":"1030 E Central Rd",
    "sg:city":"Arlington Heights",
    "sg:classifiers":[
        {
            "category":"Home & Garden",
            "subcategory":"Household Appliances",
            "type":"Retail Goods"
        }
    ],
    "sg:phone":"+1   ",
    "sg:postcode":"60005",
    "sg:province":"IL",
    "sg:tags":[
        "machine",
        "sewing",
        "fabric",
        "w",
        "supply"
    ],
    "wof:name":"Linda ZS Sewing Center",
    "wof:placetype":"venue"
},
  "geometry": {"coordinates":[-87.96974400000001,42.066536],"type":"Point"}
}