{
  "type": "Feature",
  "properties": {
    "addr:full":"833 Tam O Shanter Cir Bolingbrook IL 60440",
    "addr:housenumber":"833",
    "addr:postcode":"60440",
    "addr:street":"Tam O Shanter Cir",
    "iso:country":"US",
    "sg:address":"833 Tam O Shanter Cir",
    "sg:city":"Bolingbrook",
    "sg:classifiers":[
        {
            "category":"Structure",
            "subcategory":"Office Building",
            "type":"Public Place"
        }
    ],
    "sg:phone":"+1 630 739 6317",
    "sg:postcode":"60440",
    "sg:province":"IL",
    "sg:tags":[
        "park"
    ],
    "wof:name":"Vgsa Properties",
    "wof:placetype":"venue"
},
  "geometry": {"coordinates":[-88.05797699999999,41.725155],"type":"Point"}
}