{
  "type": "Feature",
  "properties": {
    "iso:country":"US",
    "sg:address":"302 E Broadway",
    "sg:city":"Centralia",
    "sg:classifiers":[
        {
            "category":"Personal",
            "subcategory":"Beauty Salon",
            "type":"Services"
        }
    ],
    "sg:phone":"+1 618 532 7740",
    "sg:postcode":"62801",
    "sg:province":"IL",
    "sg:tags":[
        "school"
    ],
    "wof:name":"Centralia Academy-Hair Design",
    "wof:placetype":"venue"
},
  "geometry": {"coordinates":[-89.132796,38.527448],"type":"Point"}
}