{
  "type": "Feature",
  "properties": {
    "iso:country":"US",
    "sg:address":"3861 Cutty Sark Rd",
    "sg:city":"Cherry Valley",
    "sg:classifiers":[
        {
            "category":"Professional",
            "subcategory":"Business Services",
            "type":"Services"
        }
    ],
    "sg:phone":"+1 815 332 5394",
    "sg:postcode":"61016",
    "sg:province":"IL",
    "sg:tags":[
        "roofing",
        "material"
    ],
    "wof:name":"Dalco Exteriors",
    "wof:placetype":"venue"
},
  "geometry": {"coordinates":[-88.94350799999999,42.227387],"type":"Point"}
}