{
  "type": "Feature",
  "properties": {
    "addr:full":"2451 W Cuyler Ave Chicago IL 60618",
    "addr:housenumber":"2451",
    "addr:postcode":"60618",
    "addr:street":"W Cuyler Ave",
    "iso:country":"US",
    "sg:address":"2451 W Cuyler Ave",
    "sg:city":"Chicago",
    "sg:classifiers":[
        {
            "category":"Building & Trades",
            "subcategory":"Construction",
            "type":"Services"
        }
    ],
    "sg:phone":"+1 773 478 7577",
    "sg:postcode":"60618",
    "sg:province":"IL",
    "sg:tags":[
        "system",
        "specialty",
        "heating",
        "contractor",
        "air conditioning"
    ],
    "wof:name":"P E M Heating & Cooling, Inc",
    "wof:placetype":"venue"
},
  "geometry": {"coordinates":[-87.68973,41.95491],"type":"Point"}
}