{
  "type": "Feature",
  "properties": {
    "iso:country":"US",
    "sg:address":"300 S Oakland Ave",
    "sg:city":"Carbondale",
    "sg:classifiers":[
        {
            "category":"Government",
            "subcategory":"Office",
            "type":"Public Place"
        }
    ],
    "sg:phone":"+1   ",
    "sg:postcode":"62901",
    "sg:province":"IL",
    "sg:tags":[
        "legislative",
        "body",
        "religious",
        "organization"
    ],
    "wof:name":"City Carbondale Fire Stn 2",
    "wof:placetype":"venue"
},
  "geometry": {"coordinates":[-89.22787,37.724336],"type":"Point"}
}