{
  "type": "Feature",
  "properties": {
    "addr:full":"404 E Green St Champaign IL 61820",
    "addr:housenumber":"404",
    "addr:postcode":"61820",
    "addr:street":"E Green St",
    "iso:country":"US",
    "sg:address":"404 E Green St",
    "sg:city":"Champaign",
    "sg:classifiers":[
        {
            "category":"Restaurant",
            "type":"Food & Drink"
        }
    ],
    "sg:phone":"+1 217 337 7300",
    "sg:postcode":"61820",
    "sg:province":"IL",
    "sg:tags":[
        "mexican"
    ],
    "wof:name":"Los Amigos",
    "wof:placetype":"venue"
},
  "geometry": {"coordinates":[-88.23348,40.110267],"type":"Point"}
}