{
  "type": "Feature",
  "properties": {
    "addr:full":"9628 S Central Park Ave Evergreen Park IL 60805",
    "addr:housenumber":"9628",
    "addr:postcode":"60805",
    "addr:street":"S Central Park Ave",
    "iso:country":"US",
    "sg:address":"9628 S Central Park Ave",
    "sg:city":"Evergreen Park",
    "sg:classifiers":[
        {
            "category":"Real Estate",
            "subcategory":"Real Estate Operator",
            "type":"Services"
        }
    ],
    "sg:phone":"+1 708 423 9712",
    "sg:postcode":"60805",
    "sg:province":"IL",
    "sg:tags":[
        "building",
        "nonresidential"
    ],
    "wof:name":"Jbr Properties Inc",
    "wof:placetype":"venue"
},
  "geometry": {"coordinates":[-87.711552,41.717063],"type":"Point"}
}