{
  "type": "Feature",
  "properties": {
    "iso:country":"US",
    "sg:address":"1173 E Algonquin Rd",
    "sg:city":"Des Plaines",
    "sg:classifiers":[
        {
            "category":"Health Services",
            "subcategory":"Doctor",
            "type":"Services"
        }
    ],
    "sg:phone":"+1 847 827 2784",
    "sg:postcode":"60016",
    "sg:province":"IL",
    "wof:name":"Gary R Kuntz DDS",
    "wof:placetype":"venue"
},
  "geometry": {"coordinates":[-87.895214,42.031185],"type":"Point"}
}