{
  "type": "Feature",
  "properties": {
    "addr:full":"720 Cherry Cir Itasca IL 60143",
    "addr:housenumber":"720",
    "addr:postcode":"60143",
    "addr:street":"Cherry Cir",
    "iso:country":"US",
    "sg:address":"720 Cherry Cir",
    "sg:city":"Itasca",
    "sg:classifiers":[
        {
            "category":"Professional",
            "subcategory":"Detective & Security Services",
            "type":"Services"
        }
    ],
    "sg:phone":"+1 630 250 9525",
    "sg:postcode":"60143",
    "sg:province":"IL",
    "sg:tags":[
        "information",
        "bureau"
    ],
    "wof:name":"Tom Landers Accounting Servic",
    "wof:placetype":"venue"
},
  "geometry": {"coordinates":[-88.00824,41.979599],"type":"Point"}
}