{
  "type": "Feature",
  "properties": {
    "iso:country":"US",
    "sg:address":"909 E Coach Rd",
    "sg:city":"Palatine",
    "sg:classifiers":[
        {
            "category":"Professional",
            "subcategory":"Business Services",
            "type":"Services"
        }
    ],
    "sg:phone":"+1 847 963 9353",
    "sg:postcode":"60074",
    "sg:province":"IL",
    "wof:name":"Innovision Consulting Inc",
    "wof:placetype":"venue"
},
  "geometry": {"coordinates":[-88.023399,42.15066],"type":"Point"}
}