{
  "type": "Feature",
  "properties": {
    "addr:full":"2861 Coastal Dr Aurora IL 60503",
    "addr:housenumber":"2861",
    "addr:postcode":"60503",
    "addr:street":"Coastal Dr",
    "iso:country":"US",
    "sg:address":"2861 Coastal Dr",
    "sg:city":"Aurora",
    "sg:classifiers":[
        {
            "category":"Insurance",
            "subcategory":"Insurance Agent",
            "type":"Services"
        }
    ],
    "sg:phone":"+1 630 375 9431",
    "sg:postcode":"60503",
    "sg:province":"IL",
    "wof:name":"Geico Insurance",
    "wof:placetype":"venue"
},
  "geometry": {"coordinates":[-88.243488,41.72418],"type":"Point"}
}