{
  "type": "Feature",
  "properties": {
    "iso:country":"US",
    "sg:address":"1810 Jarvis Ave",
    "sg:city":"Elk Grove Village",
    "sg:classifiers":[
        {
            "category":"Wholesale",
            "subcategory":"Machinery & Supplies",
            "type":"Manufacturing & Wholesale Goods"
        }
    ],
    "sg:phone":"+1 847 427 1234",
    "sg:postcode":"60007",
    "sg:province":"IL",
    "sg:tags":[
        "hardware",
        "equipment",
        "industrial",
        "mfg"
    ],
    "wof:name":"Pascal Engineering Inc",
    "wof:placetype":"venue"
},
  "geometry": {"coordinates":[-87.967784,42.013215],"type":"Point"}
}