{
  "type": "Feature",
  "properties": {
    "addr:full":"222 3rd St La Salle IL 61301",
    "addr:housenumber":"222",
    "addr:postcode":"61301",
    "addr:street":"3Rd St",
    "iso:country":"US",
    "sg:address":"222 3rd St",
    "sg:city":"La Salle",
    "sg:classifiers":[
        {
            "category":"Personal",
            "type":"Services"
        }
    ],
    "sg:phone":"+1 815 223 8005",
    "sg:postcode":"61301",
    "sg:province":"IL",
    "wof:name":"Seno Formal Wear",
    "wof:placetype":"venue"
},
  "geometry": {"coordinates":[-89.10163799999999,41.329723],"type":"Point"}
}