{
  "type": "Feature",
  "properties": {
    "iso:country":"US",
    "sg:address":"18221 Crawford Ave",
    "sg:city":"Country Club Hills",
    "sg:classifiers":[
        {
            "category":"Bars & Pubs",
            "type":"Food & Drink"
        }
    ],
    "sg:phone":"+1   ",
    "sg:postcode":"60478",
    "sg:province":"IL",
    "sg:tags":[
        "bar"
    ],
    "wof:name":"Mick Shanes II Inc",
    "wof:placetype":"venue"
},
  "geometry": {"coordinates":[-87.713653,41.559294],"type":"Point"}
}