{
  "type": "Feature",
  "properties": {
    "addr:full":"930 N Villa Ave Villa Park IL 60181",
    "addr:housenumber":"930",
    "addr:postcode":"60181",
    "addr:street":"N Villa Ave",
    "iso:country":"US",
    "sg:address":"930 N Villa Ave",
    "sg:city":"Villa Park",
    "sg:classifiers":[
        {
            "category":"Manufacturing",
            "subcategory":"Tools & Machinery",
            "type":"Manufacturing & Wholesale Goods"
        }
    ],
    "sg:phone":"+1 847 488 9700",
    "sg:postcode":"60181",
    "sg:province":"IL",
    "sg:tags":[
        "forming",
        "metal"
    ],
    "wof:name":"Formtek Metalforming Intgrtn",
    "wof:placetype":"venue"
},
  "geometry": {"coordinates":[-87.971036,41.911553],"type":"Point"}
}