{
  "type": "Feature",
  "properties": {
    "iso:country":"US",
    "sg:address":"301 N Harlem Ave",
    "sg:city":"Oak Park",
    "sg:classifiers":[
        {
            "category":"Professional",
            "subcategory":"Accounting & Tax Preparation",
            "type":"Services"
        }
    ],
    "sg:phone":"+1 708 358 0699",
    "sg:postcode":"60302",
    "sg:province":"IL",
    "sg:tags":[
        "return",
        "filing"
    ],
    "wof:name":"Comprehansive Business",
    "wof:placetype":"venue"
},
  "geometry": {"coordinates":[-87.804929,41.885401],"type":"Point"}
}