{
  "type": "Feature",
  "properties": {
    "addr:full":"5250 W Waveland Ave Chicago IL 60641",
    "addr:housenumber":"5250",
    "addr:postcode":"60641",
    "addr:street":"W Waveland Ave",
    "iso:country":"US",
    "sg:address":"5250 W Waveland Ave",
    "sg:city":"Chicago",
    "sg:classifiers":[
        {
            "category":"Building & Trades",
            "subcategory":"Construction",
            "type":"Services"
        }
    ],
    "sg:phone":"+1 773 205 3180",
    "sg:postcode":"60641",
    "sg:province":"IL",
    "sg:tags":[
        "house",
        "hanging"
    ],
    "wof:name":"Accurate Painting & Remodeling",
    "wof:placetype":"venue"
},
  "geometry": {"coordinates":[-87.75837799999999,41.947891],"type":"Point"}
}