{
  "type": "Feature",
  "properties": {
    "addr:full":"3210 N Vermilion St Danville IL 61832",
    "addr:housenumber":"3210",
    "addr:postcode":"61832",
    "addr:street":"N Vermilion St",
    "iso:country":"US",
    "sg:address":"3210 N Vermilion St",
    "sg:city":"Danville",
    "sg:classifiers":[
        {
            "category":"Restaurant",
            "type":"Food & Drink"
        }
    ],
    "sg:menulink":"http://www.allmenus.com/il/newell/121678-fazolis/menu/",
    "sg:phone":"+1 217 442 8340",
    "sg:postcode":"61832",
    "sg:province":"IL",
    "sg:tags":[
        "italian"
    ],
    "wof:name":"Fazoli's",
    "wof:placetype":"venue"
},
  "geometry": {"coordinates":[-87.63036200000001,40.17531],"type":"Point"}
}