{
  "type": "Feature",
  "properties": {
    "iso:country":"US",
    "sg:address":"1832 W Montrose Ave",
    "sg:city":"Chicago",
    "sg:classifiers":[
        {
            "category":"Food & Beverages",
            "subcategory":"Liquor & Beverages",
            "type":"Retail Goods"
        },
        {
            "category":"Food & Beverages",
            "subcategory":"Groceries & Convenience Stores",
            "type":"Retail Goods"
        }
    ],
    "sg:phone":"+1 773 271 3442",
    "sg:postcode":"60613",
    "sg:province":"IL",
    "sg:tags":[
        "beer",
        "spirit",
        "wine"
    ],
    "wof:name":"Best Buy Food & Liquors",
    "wof:placetype":"venue"
},
  "geometry": {"coordinates":[-87.675786,41.961666],"type":"Point"}
}