{
  "type": "Feature",
  "properties": {
    "addr:full":"59 W Hubbard St Chicago IL 60610",
    "addr:housenumber":"59",
    "addr:postcode":"60610",
    "addr:street":"W Hubbard St",
    "iso:country":"US",
    "sg:address":"59 W Hubbard St",
    "sg:city":"Chicago",
    "sg:classifiers":[
        {
            "category":"Restaurant",
            "type":"Food & Drink"
        }
    ],
    "sg:menulink":"http://www.allmenus.com/il/chicago/185544-brasserie-jo/menu/",
    "sg:phone":"+1 312 595 0800",
    "sg:postcode":"60610",
    "sg:province":"IL",
    "sg:tags":[
        "french"
    ],
    "wof:name":"Brasserie Jo",
    "wof:placetype":"venue"
},
  "geometry": {"coordinates":[-87.630037,41.890031],"type":"Point"}
}