{
  "type": "Feature",
  "properties": {
    "iso:country":"US",
    "sg:address":"1047 Cannell Ct Ste A",
    "sg:city":"Rockton",
    "sg:classifiers":[
        {
            "category":"Arts & Performance",
            "subcategory":"Dance",
            "type":"Entertainment"
        }
    ],
    "sg:phone":"+1 815 624 8855",
    "sg:postcode":"61072",
    "sg:province":"IL",
    "sg:tags":[
        "instruction",
        "dancing"
    ],
    "wof:name":"Andreas Dance Factory",
    "wof:placetype":"venue"
},
  "geometry": {"coordinates":[-89.061193,42.465904],"type":"Point"}
}