{
  "type": "Feature",
  "properties": {
    "iso:country":"US",
    "sg:address":"1616 5th Ave",
    "sg:city":"Moline",
    "sg:classifiers":[
        {
            "category":"Personal",
            "subcategory":"Beauty Salon",
            "type":"Services"
        }
    ],
    "sg:phone":"+1 309 736 9282",
    "sg:postcode":"61265",
    "sg:province":"IL",
    "sg:tags":[
        "shop"
    ],
    "wof:name":"J Michael's Salon",
    "wof:placetype":"venue"
},
  "geometry": {"coordinates":[-90.513762,41.507032],"type":"Point"}
}