{
  "type": "Feature",
  "properties": {
    "iso:country":"US",
    "sg:address":"581 Belt Line Rd",
    "sg:city":"Collinsville",
    "sg:classifiers":[
        {
            "category":"Shopping",
            "subcategory":"Clothing, Apparel, & Fashions",
            "type":"Retail Goods"
        },
        {
            "category":"Shopping",
            "subcategory":"Bicycles & Sporting Goods",
            "type":"Retail Goods"
        },
        {
            "category":"Shopping",
            "subcategory":"Shoes",
            "type":"Retail Goods"
        }
    ],
    "sg:phone":"+1 618 346 8355",
    "sg:postcode":"62234",
    "sg:province":"IL",
    "sg:tags":[
        "accessory",
        "clothing",
        "store",
        "women's"
    ],
    "wof:name":"Supermarket of Shoes",
    "wof:placetype":"venue"
},
  "geometry": {"coordinates":[-89.977501,38.690899],"type":"Point"}
}