{
  "type": "Feature",
  "properties": {
    "iso:country":"US",
    "sg:address":"38 Talcott Ave",
    "sg:city":"Crystal Lake",
    "sg:classifiers":[
        {
            "category":"Shopping",
            "type":"Retail Goods"
        }
    ],
    "sg:phone":"+1 815 455 7888",
    "sg:postcode":"60014",
    "sg:province":"IL",
    "sg:tags":[
        "spa",
        "company",
        "pool"
    ],
    "wof:name":"Precision Pool & Spa Inc",
    "wof:placetype":"venue"
},
  "geometry": {"coordinates":[-88.302601,42.241559],"type":"Point"}
}