{
  "type": "Feature",
  "properties": {
    "iso:country":"US",
    "sg:address":"2343 E 71st Street",
    "sg:city":"Chicago",
    "sg:classifiers":[
        {
            "category":"Food & Beverages",
            "subcategory":"Ethnic Foods",
            "type":"Retail Goods"
        }
    ],
    "sg:phone":"+1 773 891 2889",
    "sg:postcode":"60649",
    "sg:province":"IL",
    "sg:tags":[
        "soul"
    ],
    "wof:name":"5 Loaves Eatery",
    "wof:placetype":"venue"
},
  "geometry": {"coordinates":[-87.567245,41.766085],"type":"Point"}
}