{
  "type": "Feature",
  "properties": {
    "addr:full":"2709 Madison Ave Granite City IL 62040",
    "addr:housenumber":"2709",
    "addr:postcode":"62040",
    "addr:street":"Madison Ave",
    "iso:country":"US",
    "sg:address":"2709 Madison Ave",
    "sg:city":"Granite City",
    "sg:classifiers":[
        {
            "category":"Professional",
            "subcategory":"Lawyer & Legal Services",
            "type":"Services"
        }
    ],
    "sg:phone":"+1 618 877 5471",
    "sg:postcode":"62040",
    "sg:province":"IL",
    "wof:name":"Hildebrand Thomas E Atty",
    "wof:placetype":"venue"
},
  "geometry": {"coordinates":[-90.1315,38.7117],"type":"Point"}
}