{
  "type": "Feature",
  "properties": {
    "iso:country":"US",
    "sg:address":"18117 Gumtown Rd",
    "sg:city":"Virginia",
    "sg:phone":"+1 217 458 2244",
    "sg:postcode":"62691",
    "sg:province":"IL",
    "sg:tags":[
        "farm",
        "grain",
        "cash"
    ],
    "wof:name":"Wessel Farms",
    "wof:placetype":"venue"
},
  "geometry": {"coordinates":[-90.25161900000001,40.040712],"type":"Point"}
}