{
  "type": "Feature",
  "properties": {
    "iso:country":"US",
    "sg:address":"102 W Rock Falls Rd",
    "sg:city":"Rock Falls",
    "sg:classifiers":[
        {
            "category":"Health Services",
            "subcategory":"Optometrist",
            "type":"Services"
        }
    ],
    "sg:phone":"+1 815 626 7700",
    "sg:postcode":"61071",
    "sg:province":"IL",
    "wof:name":"Rock Falls Eye Care",
    "wof:placetype":"venue"
},
  "geometry": {"coordinates":[-89.689854,41.765644],"type":"Point"}
}