{
  "type": "Feature",
  "properties": {
    "addr:full":"7648 W 159th St Orland Park IL 60462",
    "addr:housenumber":"7648",
    "addr:postcode":"60462",
    "addr:street":"W 159Th St",
    "iso:country":"US",
    "sg:address":"7648 W 159th St",
    "sg:city":"Orland Park",
    "sg:classifiers":[
        {
            "category":"Home & Garden",
            "subcategory":"Garden Supply",
            "type":"Retail Goods"
        }
    ],
    "sg:phone":"+1 708 429 1950",
    "sg:postcode":"60462",
    "sg:province":"IL",
    "sg:tags":[
        "center"
    ],
    "wof:name":"Every Bloomin' Thing",
    "wof:placetype":"venue"
},
  "geometry": {"coordinates":[-87.804879,41.602179],"type":"Point"}
}