{
  "type": "Feature",
  "properties": {
    "addr:full":"10210 Washington Ave Oak Lawn IL 60453",
    "addr:housenumber":"10210",
    "addr:postcode":"60453",
    "addr:street":"Washington Ave",
    "iso:country":"US",
    "sg:address":"10210 Washington Ave",
    "sg:city":"Oak Lawn",
    "sg:classifiers":[
        {
            "category":"Organizations",
            "subcategory":"Community Association",
            "type":"Services"
        }
    ],
    "sg:phone":"+1 708 425 8700",
    "sg:postcode":"60453",
    "sg:province":"IL",
    "wof:name":"West Edge Condo Association",
    "wof:placetype":"venue"
},
  "geometry": {"coordinates":[-87.75868199999999,41.706266],"type":"Point"}
}