{
  "type": "Feature",
  "properties": {
    "iso:country":"US",
    "sg:address":"2121 W Army Trl Rd Ste 108",
    "sg:city":"Addison",
    "sg:classifiers":[
        {
            "category":"Professional",
            "subcategory":"Computer Services",
            "type":"Services"
        }
    ],
    "sg:phone":"+1 630 563 0151",
    "sg:postcode":"60101",
    "sg:province":"IL",
    "sg:tags":[
        "repair"
    ],
    "wof:name":"Blue Collar Computing",
    "wof:placetype":"venue"
},
  "geometry": {"coordinates":[-88.043668,41.932218],"type":"Point"}
}