{
  "type": "Feature",
  "properties": {
    "addr:full":"1450 N Evergreen Ln Columbia IL 62236",
    "addr:housenumber":"1450",
    "addr:postcode":"62236",
    "addr:street":"N Evergreen Ln",
    "iso:country":"US",
    "sg:address":"1450 N Evergreen Ln",
    "sg:city":"Columbia",
    "sg:classifiers":[
        {
            "category":"Restaurant",
            "type":"Food & Drink"
        }
    ],
    "sg:phone":"+1   ",
    "sg:postcode":"62236",
    "sg:province":"IL",
    "sg:tags":[
        "pizza"
    ],
    "wof:name":"Columbia",
    "wof:placetype":"venue"
},
  "geometry": {"coordinates":[-90.218547,38.451753],"type":"Point"}
}