{
  "type": "Feature",
  "properties": {
    "iso:country":"US",
    "sg:address":"4125 W Belle Plaine Ave",
    "sg:city":"Chicago",
    "sg:classifiers":[
        {
            "category":"Professional",
            "subcategory":"Advertising",
            "type":"Services"
        },
        {
            "category":"Professional",
            "subcategory":"Business Services",
            "type":"Services"
        }
    ],
    "sg:phone":"+1 312 805 1858",
    "sg:postcode":"60641",
    "sg:province":"IL",
    "sg:tags":[
        "marketing",
        "relation",
        "public"
    ],
    "sg:website":"www.inkmeansbusiness.com",
    "wof:name":",Ink. Commercial Writing Services",
    "wof:placetype":"venue"
},
  "geometry": {"coordinates":[-87.73178299999999,41.955415],"type":"Point"}
}