{
  "type": "Feature",
  "properties": {
    "iso:country":"US",
    "sg:address":"744 Ogden Ave",
    "sg:city":"Downers Grove",
    "sg:classifiers":[
        {
            "category":"Food & Beverages",
            "subcategory":"Bakery",
            "type":"Retail Goods"
        }
    ],
    "sg:phone":"+1   ",
    "sg:postcode":"60515",
    "sg:province":"IL",
    "sg:tags":[
        "baked"
    ],
    "wof:name":"Pepperidge Farm Incorporated",
    "wof:placetype":"venue"
},
  "geometry": {"coordinates":[-88.004486,41.809259],"type":"Point"}
}