{
  "type": "Feature",
  "properties": {
    "iso:country":"US",
    "sg:address":"1206 W Lawrence Ave",
    "sg:city":"Chicago",
    "sg:classifiers":[
        {
            "category":"Restaurant",
            "type":"Food & Drink"
        }
    ],
    "sg:phone":"+1 773 275 5321",
    "sg:postcode":"60640",
    "sg:province":"IL",
    "sg:tags":[
        "mexican"
    ],
    "wof:name":"Carmela's Taqueria",
    "wof:placetype":"venue"
},
  "geometry": {"coordinates":[-87.659994,41.969023],"type":"Point"}
}