{
  "type": "Feature",
  "properties": {
    "iso:country":"US",
    "sg:address":"15161 S Gougar Rd",
    "sg:city":"Homer Glen",
    "sg:classifiers":[
        {
            "category":"Education",
            "subcategory":"School",
            "type":"Public Place"
        }
    ],
    "sg:phone":"+1 815 836 2724",
    "sg:postcode":"60491",
    "sg:province":"IL",
    "sg:website":"www.d92.org",
    "wof:name":"Oak Prairie Junior High School",
    "wof:placetype":"venue"
},
  "geometry": {"coordinates":[-88.007448,41.605718],"type":"Point"}
}