{
  "type": "Feature",
  "properties": {
    "addr:full":"1700 E Court St Kankakee IL 60901",
    "addr:housenumber":"1700",
    "addr:postcode":"60901",
    "addr:street":"E Court St",
    "iso:country":"US",
    "sg:address":"1700 E Court St",
    "sg:city":"Kankakee",
    "sg:classifiers":[
        {
            "category":"Shopping",
            "subcategory":"Pharmacy",
            "type":"Retail Goods"
        }
    ],
    "sg:phone":"+1   ",
    "sg:postcode":"60901",
    "sg:province":"IL",
    "sg:website":"www.walgreens.com",
    "wof:name":"Walgreens",
    "wof:placetype":"venue"
},
  "geometry": {"coordinates":[-87.84265499999999,41.118932],"type":"Point"}
}