{
  "type": "Feature",
  "properties": {
    "iso:country":"US",
    "sg:address":"316 Mc Coy St",
    "sg:city":"Granville",
    "sg:classifiers":[
        {
            "category":"Government",
            "subcategory":"Police Station",
            "type":"Public Place"
        }
    ],
    "sg:phone":"+1 815 339 2514",
    "sg:postcode":"61326",
    "sg:province":"IL",
    "sg:tags":[
        "department"
    ],
    "wof:name":"Granville Village Police Dept",
    "wof:placetype":"venue"
},
  "geometry": {"coordinates":[-89.22815,41.260942],"type":"Point"}
}