{
  "type": "Feature",
  "properties": {
    "addr:full":"950 Warrenville Rd Lisle IL 60532",
    "addr:housenumber":"950",
    "addr:postcode":"60532",
    "addr:street":"Warrenville Rd",
    "iso:country":"US",
    "sg:address":"950 Warrenville Rd",
    "sg:city":"Lisle",
    "sg:classifiers":[
        {
            "category":"Retail",
            "subcategory":"Auto Rental",
            "type":"Services"
        }
    ],
    "sg:phone":"+1 630 572 2801",
    "sg:postcode":"60532",
    "sg:province":"IL",
    "sg:tags":[
        "repair",
        "truck",
        "general"
    ],
    "wof:name":"Primms",
    "wof:placetype":"venue"
},
  "geometry": {"coordinates":[-88.069213,41.808691],"type":"Point"}
}