{
  "type": "Feature",
  "properties": {
    "addr:full":"8989 Potter Rd Des Plaines IL 60016",
    "addr:housenumber":"8989",
    "addr:postcode":"60016",
    "addr:street":"Potter Rd",
    "iso:country":"US",
    "sg:address":"8989 Potter Rd",
    "sg:city":"Des Plaines",
    "sg:classifiers":[
        {
            "category":"Shopping",
            "type":"Retail Goods"
        }
    ],
    "sg:phone":"+1 847 824 8989",
    "sg:postcode":"60016",
    "sg:province":"IL",
    "sg:tags":[
        "merchandise",
        "animal"
    ],
    "wof:name":"Maine Pet Supplies & Grooming",
    "wof:placetype":"venue"
},
  "geometry": {"coordinates":[-87.859921,42.065877],"type":"Point"}
}