{
  "type": "Feature",
  "properties": {
    "addr:full":"10768 Main St Roscoe IL 61073",
    "addr:housenumber":"10768",
    "addr:postcode":"61073",
    "addr:street":"Main St",
    "iso:country":"US",
    "sg:address":"10768 Main St",
    "sg:city":"Roscoe",
    "sg:classifiers":[
        {
            "category":"Insurance",
            "subcategory":"Insurance Agent",
            "type":"Services"
        }
    ],
    "sg:phone":"+1 815 623 6506",
    "sg:postcode":"61073",
    "sg:province":"IL",
    "wof:name":"James D Shaver Agency",
    "wof:placetype":"venue"
},
  "geometry": {"coordinates":[-89.009608,42.417002],"type":"Point"}
}