{
  "type": "Feature",
  "properties": {
    "iso:country":"US",
    "sg:address":"904 N Sunset Ave",
    "sg:city":"Rockford",
    "sg:classifiers":[
        {
            "category":"Shopping",
            "subcategory":"Clothing, Apparel, & Fashions",
            "type":"Retail Goods"
        }
    ],
    "sg:phone":"+1 815 962 4699",
    "sg:postcode":"61101",
    "sg:province":"IL",
    "sg:tags":[
        "item",
        "boutique"
    ],
    "wof:name":"Lace Boutique",
    "wof:placetype":"venue"
},
  "geometry": {"coordinates":[-89.11846799999999,42.286707],"type":"Point"}
}