{
  "type": "Feature",
  "properties": {
    "iso:country":"US",
    "sg:address":"1125 Harvard Ter",
    "sg:city":"Evanston",
    "sg:classifiers":[
        {
            "category":"Education",
            "subcategory":"Special Training",
            "type":"Public Place"
        }
    ],
    "sg:phone":"+1 847 864 3512",
    "sg:postcode":"60202",
    "sg:province":"IL",
    "wof:name":"Academics Plus",
    "wof:placetype":"venue"
},
  "geometry": {"coordinates":[-87.686995,42.022654],"type":"Point"}
}