{
  "type": "Feature",
  "properties": {
    "iso:country":"US",
    "sg:address":"4203 Oakton St",
    "sg:city":"Skokie",
    "sg:classifiers":[
        {
            "category":"Home & Garden",
            "subcategory":"Household Appliances",
            "type":"Retail Goods"
        }
    ],
    "sg:phone":"+1   ",
    "sg:postcode":"60076",
    "sg:province":"IL",
    "wof:name":"Sewing Machines Inc",
    "wof:placetype":"venue"
},
  "geometry": {"coordinates":[-87.73415900000001,42.026169],"type":"Point"}
}