{
  "type": "Feature",
  "properties": {
    "iso:country":"US",
    "sg:address":"660 Collins St",
    "sg:city":"Joliet",
    "sg:classifiers":[
        {
            "category":"Professional",
            "subcategory":"Business Services",
            "type":"Services"
        }
    ],
    "sg:phone":"+1 815 740 1121",
    "sg:postcode":"60432",
    "sg:province":"IL",
    "sg:tags":[
        "packaging",
        "manufacturing",
        "assembly",
        "contract"
    ],
    "sg:website":"www.roselab.com",
    "wof:name":"Rose Laboratories Inc",
    "wof:placetype":"venue"
},
  "geometry": {"coordinates":[-88.072658,41.53712],"type":"Point"}
}