{
  "type": "Feature",
  "properties": {
    "addr:full":"4105 Fieldstone Rd Champaign IL 61822",
    "addr:housenumber":"4105",
    "addr:postcode":"61822",
    "addr:street":"Fieldstone Rd",
    "iso:country":"US",
    "sg:address":"4105 Fieldstone Rd",
    "sg:city":"Champaign",
    "sg:classifiers":[
        {
            "category":"Shopping",
            "subcategory":"Hobbies, Toys, & Games",
            "type":"Retail Goods"
        }
    ],
    "sg:phone":"+1 217 355 9511",
    "sg:postcode":"61822",
    "sg:province":"IL",
    "sg:tags":[
        "toy",
        "store"
    ],
    "wof:name":"Jr Service America",
    "wof:placetype":"venue"
},
  "geometry": {"coordinates":[-88.311401,40.115002],"type":"Point"}
}