{
  "type": "Feature",
  "properties": {
    "iso:country":"US",
    "sg:address":"5817 W Newport Ave",
    "sg:city":"Chicago",
    "sg:classifiers":[
        {
            "category":"Retail",
            "subcategory":"Repair Shop",
            "type":"Services"
        }
    ],
    "sg:phone":"+1 773 286 5484",
    "sg:postcode":"60634",
    "sg:province":"IL",
    "sg:tags":[
        "machine"
    ],
    "wof:name":"Quality Machine Weks",
    "wof:placetype":"venue"
},
  "geometry": {"coordinates":[-87.77191999999999,41.943076],"type":"Point"}
}