{
  "type": "Feature",
  "properties": {
    "addr:full":"6415 E Riverside Blvd Rockford IL 61114",
    "addr:housenumber":"6415",
    "addr:postcode":"61114",
    "addr:street":"E Riverside Blvd",
    "iso:country":"US",
    "sg:address":"6415 E Riverside Blvd",
    "sg:city":"Rockford",
    "sg:classifiers":[
        {
            "category":"Shopping",
            "subcategory":"Gifts & Souvenirs",
            "type":"Retail Goods"
        },
        {
            "category":"Food & Beverages",
            "subcategory":"Bakery",
            "type":"Retail Goods"
        },
        {
            "category":"Bakery",
            "type":"Food & Drink"
        },
        {
            "category":"Shopping",
            "subcategory":"Florist",
            "type":"Retail Goods"
        }
    ],
    "sg:phone":"+1 815 282 5400",
    "sg:postcode":"61114",
    "sg:province":"IL",
    "sg:tags":[
        "shop",
        "cracker",
        "cooky",
        "basket"
    ],
    "sg:website":"http://www.cookiesbydesign.com",
    "wof:name":"Cookies By Design",
    "wof:placetype":"venue"
},
  "geometry": {"coordinates":[-88.991569,42.318669],"type":"Point"}
}