{
  "type": "Feature",
  "properties": {
    "addr:full":"1117 E Valley Ln Arlington Heights IL 60004",
    "addr:housenumber":"1117",
    "addr:postcode":"60004",
    "addr:street":"E Valley Ln",
    "iso:country":"US",
    "sg:address":"1117 E Valley Ln",
    "sg:city":"Arlington Heights",
    "sg:classifiers":[
        {
            "category":"Professional",
            "subcategory":"Computer Services",
            "type":"Services"
        }
    ],
    "sg:phone":"+1 847 577 0929",
    "sg:postcode":"60004",
    "sg:province":"IL",
    "sg:tags":[
        "design",
        "system"
    ],
    "wof:name":"Lorenzo De Leon",
    "wof:placetype":"venue"
},
  "geometry": {"coordinates":[-87.967341,42.115332],"type":"Point"}
}