{
  "type": "Feature",
  "properties": {
    "iso:country":"US",
    "sg:address":"5647 N Menard Ave",
    "sg:city":"Chicago",
    "sg:classifiers":[
        {
            "category":"Building & Trades",
            "subcategory":"Construction",
            "type":"Services"
        }
    ],
    "sg:phone":"+1 773 631 6598",
    "sg:postcode":"60646",
    "sg:province":"IL",
    "sg:tags":[
        "contractor"
    ],
    "wof:name":"Waj Construction Inc",
    "wof:placetype":"venue"
},
  "geometry": {"coordinates":[-87.773201,41.984402],"type":"Point"}
}