{
  "type": "Feature",
  "properties": {
    "iso:country":"US",
    "sg:address":"24777 Star Rd",
    "sg:city":"Tampico",
    "sg:classifiers":[
        {
            "category":"Farming",
            "subcategory":"Livestock Farm",
            "type":"Manufacturing & Wholesale Goods"
        }
    ],
    "sg:phone":"+1 815 438 3213",
    "sg:postcode":"61283",
    "sg:province":"IL",
    "sg:tags":[
        "feeding"
    ],
    "wof:name":"Art Wetzell",
    "wof:placetype":"venue"
},
  "geometry": {"coordinates":[-89.76900500000001,41.685571],"type":"Point"}
}