{
  "type": "Feature",
  "properties": {
    "addr:full":"270 Country Commons Rd Cary IL 60013",
    "addr:housenumber":"270",
    "addr:postcode":"60013",
    "addr:street":"Country Commons Rd",
    "iso:country":"US",
    "sg:address":"270 Country Commons Rd",
    "sg:city":"Cary",
    "sg:classifiers":[
        {
            "category":"Social Services",
            "subcategory":"Child Care",
            "type":"Services"
        },
        {
            "category":"Education",
            "subcategory":"School",
            "type":"Public Place"
        }
    ],
    "sg:phone":"+1 847 639 3977",
    "sg:postcode":"60013",
    "sg:province":"IL",
    "wof:name":"Cary Country Pre School",
    "wof:placetype":"venue"
},
  "geometry": {"coordinates":[-88.25714499999999,42.203352],"type":"Point"}
}