{
  "type": "Feature",
  "properties": {
    "addr:full":"9201 Starboard Dr Roscoe IL 61073",
    "addr:housenumber":"9201",
    "addr:postcode":"61073",
    "addr:street":"Starboard Dr",
    "iso:country":"US",
    "sg:address":"9201 Starboard Dr",
    "sg:city":"Roscoe",
    "sg:classifiers":[
        {
            "category":"Manufacturing",
            "subcategory":"Rubber & Plastics",
            "type":"Manufacturing & Wholesale Goods"
        }
    ],
    "sg:phone":"+1 815 636 9982",
    "sg:postcode":"61073",
    "sg:province":"IL",
    "sg:tags":[
        "product"
    ],
    "sg:website":"www.gtflowtech.com",
    "wof:name":"G T Flow Technology Inc",
    "wof:placetype":"venue"
},
  "geometry": {"coordinates":[-89.010678,42.393744],"type":"Point"}
}