{
  "type": "Feature",
  "properties": {
    "iso:country":"US",
    "sg:address":"579 Cress Creek Ln",
    "sg:city":"Crystal Lake",
    "sg:classifiers":[
        {
            "category":"Retail",
            "subcategory":"Repair Shop",
            "type":"Services"
        },
        {
            "category":"Professional",
            "subcategory":"Management & Consulting",
            "type":"Services"
        }
    ],
    "sg:phone":"+1 815 455 5589",
    "sg:postcode":"60014",
    "sg:province":"IL",
    "sg:tags":[
        "measuring",
        "educational",
        "industrial",
        "testing"
    ],
    "wof:name":"Ogden Power Inc",
    "wof:placetype":"venue"
},
  "geometry": {"coordinates":[-88.34048,42.221039],"type":"Point"}
}