{
  "type": "Feature",
  "properties": {
    "addr:full":"1024 Beech St Highland IL 62249",
    "addr:housenumber":"1024",
    "addr:postcode":"62249",
    "addr:street":"Beech St",
    "iso:country":"US",
    "sg:address":"1024 Beech St",
    "sg:city":"Highland",
    "sg:classifiers":[
        {
            "category":"Building & Trades",
            "subcategory":"Landscaping Services",
            "type":"Services"
        }
    ],
    "sg:phone":"+1 618 651 0120",
    "sg:postcode":"62249",
    "sg:province":"IL",
    "sg:tags":[
        "landscape",
        "contractor"
    ],
    "wof:name":"Ray's Landscaping",
    "wof:placetype":"venue"
},
  "geometry": {"coordinates":[-89.68811100000001,38.738934],"type":"Point"}
}