{
  "type": "Feature",
  "properties": {
    "addr:full":"28490 280th St Barry IL 62312",
    "addr:housenumber":"28490",
    "addr:postcode":"62312",
    "addr:street":"280Th St",
    "iso:country":"US",
    "sg:address":"28490 280th St",
    "sg:city":"Barry",
    "sg:classifiers":[
        {
            "category":"Personal",
            "type":"Services"
        },
        {
            "category":"Retail",
            "subcategory":"Portrait Studio",
            "type":"Services"
        },
        {
            "category":"Professional",
            "subcategory":"Art Services",
            "type":"Services"
        }
    ],
    "sg:phone":"+1 217 335 3439",
    "sg:postcode":"62312",
    "sg:province":"IL",
    "sg:tags":[
        "photographers-portrait",
        "videography",
        "darkroom",
        "rental",
        "photography",
        "wedding",
        "photographic"
    ],
    "wof:name":"Dutch Creek Photography",
    "wof:placetype":"venue"
},
  "geometry": {"coordinates":[-91.00641,39.675362],"type":"Point"}
}