{
  "type": "Feature",
  "properties": {
    "iso:country":"US",
    "sg:address":"2714 W North Ave",
    "sg:city":"Chicago",
    "sg:classifiers":[
        {
            "category":"Health Services",
            "subcategory":"Doctor",
            "type":"Services"
        }
    ],
    "sg:phone":"+1 773 278 2600",
    "sg:postcode":"60647",
    "sg:province":"IL",
    "sg:tags":[
        "medical"
    ],
    "wof:name":"Carlos Pedrera MD SC",
    "wof:placetype":"venue"
},
  "geometry": {"coordinates":[-87.69524699999999,41.91038],"type":"Point"}
}