{
  "type": "Feature",
  "properties": {
    "iso:country":"US",
    "sg:address":"715 Meadow Ave",
    "sg:city":"Rockdale",
    "sg:classifiers":[
        {
            "category":"Health Services",
            "subcategory":"Doctor",
            "type":"Services"
        }
    ],
    "sg:phone":"+1 815 744 9699",
    "sg:postcode":"60436",
    "sg:province":"IL",
    "sg:tags":[
        "physician",
        "surgeon",
        "psychologist"
    ],
    "wof:name":"Diane Kleckler Phd",
    "wof:placetype":"venue"
},
  "geometry": {"coordinates":[-88.116399,41.506961],"type":"Point"}
}