{
  "type": "Feature",
  "properties": {
    "addr:full":"3457 N Milwaukee Ave Chicago IL 60641",
    "addr:housenumber":"3457",
    "addr:postcode":"60641",
    "addr:street":"N Milwaukee Ave",
    "iso:country":"US",
    "sg:address":"3457 N Milwaukee Ave",
    "sg:city":"Chicago",
    "sg:classifiers":[
        {
            "category":"Restaurant",
            "type":"Food & Drink"
        }
    ],
    "sg:phone":"+1 773 685 6676",
    "sg:postcode":"60641",
    "sg:province":"IL",
    "wof:name":"Janina's Tavern & Banquet Hall",
    "wof:placetype":"venue"
},
  "geometry": {"coordinates":[-87.731903,41.943901],"type":"Point"}
}