{
  "type": "Feature",
  "properties": {
    "addr:full":"1081 Caton Farm Rd Lockport IL 60441",
    "addr:housenumber":"1081",
    "addr:postcode":"60441",
    "addr:street":"Caton Farm Rd",
    "iso:country":"US",
    "sg:address":"1081 Caton Farm Rd",
    "sg:city":"Lockport",
    "sg:classifiers":[
        {
            "category":"Building & Trades",
            "subcategory":"Construction",
            "type":"Services"
        }
    ],
    "sg:phone":"+1 815 723 9728",
    "sg:postcode":"60441",
    "sg:province":"IL",
    "sg:tags":[
        "flooring",
        "contractor"
    ],
    "wof:name":"Flooring Resolutions Inc",
    "wof:placetype":"venue"
},
  "geometry": {"coordinates":[-88.115398,41.566379],"type":"Point"}
}