{
  "type": "Feature",
  "properties": {
    "iso:country":"US",
    "sg:address":"135 Prospect Ave",
    "sg:city":"Wood Dale",
    "sg:classifiers":[
        {
            "category":"Building & Trades",
            "subcategory":"Construction",
            "type":"Services"
        }
    ],
    "sg:phone":"+1 630 595 1611",
    "sg:postcode":"60191",
    "sg:province":"IL",
    "sg:tags":[
        "concrete",
        "contractor"
    ],
    "wof:name":"Lawrence Concrete Specialists",
    "wof:placetype":"venue"
},
  "geometry": {"coordinates":[-87.998283,41.957667],"type":"Point"}
}