{
  "type": "Feature",
  "properties": {
    "iso:country":"US",
    "sg:address":"1401 Windsor Rd",
    "sg:city":"Loves Park",
    "sg:classifiers":[
        {
            "category":"Freight",
            "type":"Transportation"
        }
    ],
    "sg:phone":"+1 815 633 2333",
    "sg:postcode":"61111",
    "sg:province":"IL",
    "sg:tags":[
        "special"
    ],
    "wof:name":"Midwest Self Storage",
    "wof:placetype":"venue"
},
  "geometry": {"coordinates":[-89.039191,42.325257],"type":"Point"}
}