{
  "type": "Feature",
  "properties": {
    "addr:full":"3532 W North Ave Chicago IL 60647",
    "addr:housenumber":"3532",
    "addr:postcode":"60647",
    "addr:street":"W North Ave",
    "iso:country":"US",
    "sg:address":"3532 W North Ave",
    "sg:city":"Chicago",
    "sg:classifiers":[
        {
            "category":"Education",
            "subcategory":"School",
            "type":"Public Place"
        }
    ],
    "sg:phone":"+1 773 276 7097",
    "sg:postcode":"60647",
    "sg:province":"IL",
    "wof:name":"Ebenezer Bible Institute",
    "wof:placetype":"venue"
},
  "geometry": {"coordinates":[-87.716483,41.910128],"type":"Point"}
}