{
  "type": "Feature",
  "properties": {
    "iso:country":"US",
    "sg:address":"707 E 93rd Street",
    "sg:city":"Chicago",
    "sg:classifiers":[
        {
            "category":"Social Services",
            "subcategory":"Child Care",
            "type":"Services"
        }
    ],
    "sg:phone":"+1 773 723 0628",
    "sg:postcode":"60619",
    "sg:province":"IL",
    "sg:tags":[
        "day"
    ],
    "wof:name":"Hayes Home Daycare",
    "wof:placetype":"venue"
},
  "geometry": {"coordinates":[-87.606157,41.725763],"type":"Point"}
}