{
  "type": "Feature",
  "properties": {
    "iso:country":"US",
    "sg:address":"3359 N Vermilion St",
    "sg:city":"Danville",
    "sg:classifiers":[
        {
            "category":"Restaurant",
            "type":"Food & Drink"
        }
    ],
    "sg:menulink":"http://www.allmenus.com/il/newell/124396-quiznos-sub/menu/",
    "sg:phone":"+1 217 431 8807",
    "sg:postcode":"61832",
    "sg:province":"IL",
    "sg:tags":[
        "wrap",
        "american",
        "sandwich"
    ],
    "wof:name":"Quiznos Sub",
    "wof:placetype":"venue"
},
  "geometry": {"coordinates":[-87.629936,40.177154],"type":"Point"}
}