{
  "type": "Feature",
  "properties": {
    "iso:country":"US",
    "sg:address":"801 N Lombard Ave",
    "sg:city":"Oak Park",
    "sg:classifiers":[
        {
            "category":"Building & Trades",
            "subcategory":"Construction",
            "type":"Services"
        }
    ],
    "sg:phone":"+1 708 358 1096",
    "sg:postcode":"60302",
    "sg:province":"IL",
    "sg:tags":[
        "repairing",
        "remodeling",
        "contractor"
    ],
    "wof:name":"Father & Son Remodeling Inc",
    "wof:placetype":"venue"
},
  "geometry": {"coordinates":[-87.78017,41.900103],"type":"Point"}
}