{
  "type": "Feature",
  "properties": {
    "addr:full":"9211 S Commercial Ave Chicago IL 60617",
    "addr:housenumber":"9211",
    "addr:postcode":"60617",
    "addr:street":"S Commercial Ave",
    "iso:country":"US",
    "sg:address":"9211 S Commercial Ave",
    "sg:city":"Chicago",
    "sg:classifiers":[
        {
            "category":"Fast Food",
            "type":"Food & Drink"
        },
        {
            "category":"Restaurant",
            "type":"Food & Drink"
        }
    ],
    "sg:phone":"+1 773 375 7700",
    "sg:postcode":"60617",
    "sg:province":"IL",
    "sg:tags":[
        "hamburger",
        "dog",
        "burger",
        "hot",
        "take",
        "american",
        "chicken"
    ],
    "sg:website":"www.mcdonalds.com",
    "wof:name":"McDonald's",
    "wof:placetype":"venue"
},
  "geometry": {"coordinates":[-87.551174,41.727909],"type":"Point"}
}