{
  "type": "Feature",
  "properties": {
    "iso:country":"US",
    "sg:address":"222 Merchandise Mart Plz",
    "sg:city":"Chicago",
    "sg:classifiers":[
        {
            "category":"Insurance",
            "subcategory":"Health Insurance",
            "type":"Services"
        }
    ],
    "sg:phone":"+1 312 832 6990",
    "sg:postcode":"60654",
    "sg:province":"IL",
    "sg:tags":[
        "market"
    ],
    "wof:name":"General Nutrition Center",
    "wof:placetype":"venue"
},
  "geometry": {"coordinates":[-87.634399,41.888],"type":"Point"}
}