{
  "type": "Feature",
  "properties": {
    "addr:full":"18411 Miller Dr Lansing IL 60438",
    "addr:housenumber":"18411",
    "addr:postcode":"60438",
    "addr:street":"Miller Dr",
    "iso:country":"US",
    "sg:address":"18411 Miller Dr",
    "sg:city":"Lansing",
    "sg:classifiers":[
        {
            "category":"Building & Trades",
            "subcategory":"Construction",
            "type":"Services"
        }
    ],
    "sg:phone":"+1 708 895 5860",
    "sg:postcode":"60438",
    "sg:province":"IL",
    "sg:tags":[
        "residential"
    ],
    "wof:name":"Kalco",
    "wof:placetype":"venue"
},
  "geometry": {"coordinates":[-87.53114100000001,41.559792],"type":"Point"}
}