{
  "type": "Feature",
  "properties": {
    "iso:country":"US",
    "sg:address":"18501 Meadow Ln",
    "sg:city":"Hazel Crest",
    "sg:classifiers":[
        {
            "category":"Banks & Credit Unions",
            "subcategory":"Financial Services",
            "type":"Services"
        }
    ],
    "sg:phone":"+1 708 922 9069",
    "sg:postcode":"60429",
    "sg:province":"IL",
    "sg:tags":[
        "investor"
    ],
    "wof:name":"No Regrets Investment Assoc",
    "wof:placetype":"venue"
},
  "geometry": {"coordinates":[-87.699427,41.554038],"type":"Point"}
}