{
  "type": "Feature",
  "properties": {
    "addr:full":"2615 W Main St Belleville IL 62226",
    "addr:housenumber":"2615",
    "addr:postcode":"62226",
    "addr:street":"W Main St",
    "iso:country":"US",
    "sg:address":"2615 W Main St",
    "sg:city":"Belleville",
    "sg:classifiers":[
        {
            "category":"Building & Trades",
            "subcategory":"Construction",
            "type":"Services"
        }
    ],
    "sg:phone":"+1 618 277 2207",
    "sg:postcode":"62226",
    "sg:province":"IL",
    "sg:tags":[
        "home",
        "improvement"
    ],
    "wof:name":"Hagler & Son Inc",
    "wof:placetype":"venue"
},
  "geometry": {"coordinates":[-90.011605,38.525681],"type":"Point"}
}