{
  "type": "Feature",
  "properties": {
    "iso:country":"US",
    "sg:address":"4401 Wildwood Ln",
    "sg:city":"Rockford",
    "sg:classifiers":[
        {
            "category":"Wholesale",
            "subcategory":"Machinery & Supplies",
            "type":"Manufacturing & Wholesale Goods"
        }
    ],
    "sg:phone":"+1 815 963 3373",
    "sg:postcode":"61101",
    "sg:province":"IL",
    "sg:tags":[
        "machine",
        "tool"
    ],
    "wof:name":"Consep Industrial",
    "wof:placetype":"venue"
},
  "geometry": {"coordinates":[-89.137794,42.321713],"type":"Point"}
}