{
  "type": "Feature",
  "properties": {
    "addr:full":"136 10th St Carmi IL 62821",
    "addr:housenumber":"136",
    "addr:postcode":"62821",
    "addr:street":"10Th St",
    "iso:country":"US",
    "sg:address":"136 10th St",
    "sg:city":"Carmi",
    "sg:classifiers":[
        {
            "category":"Professional",
            "subcategory":"Management & Consulting",
            "type":"Services"
        }
    ],
    "sg:phone":"+1 618 382 4084",
    "sg:postcode":"62821",
    "sg:province":"IL",
    "sg:tags":[
        "farm"
    ],
    "wof:name":"Glenn Kallenbach",
    "wof:placetype":"venue"
},
  "geometry": {"coordinates":[-88.173777,38.083057],"type":"Point"}
}