{
  "type": "Feature",
  "properties": {
    "addr:full":"460 Raintree Ct Glen Ellyn IL 60137",
    "addr:housenumber":"460",
    "addr:postcode":"60137",
    "addr:street":"Raintree Ct",
    "iso:country":"US",
    "sg:address":"460 Raintree Ct",
    "sg:city":"Glen Ellyn",
    "sg:classifiers":[
        {
            "category":"Shopping",
            "subcategory":"Gifts & Souvenirs",
            "type":"Retail Goods"
        }
    ],
    "sg:phone":"+1   ",
    "sg:postcode":"60137",
    "sg:province":"IL",
    "sg:tags":[
        "cards"
    ],
    "wof:name":"Hanover Cards & Gifts Inc",
    "wof:placetype":"venue"
},
  "geometry": {"coordinates":[-88.07149099999999,41.847046],"type":"Point"}
}