{
  "type": "Feature",
  "properties": {
    "addr:full":"205 N Michigan Ave Ste 3300 Chicago IL 60601",
    "addr:housenumber":"205",
    "addr:postcode":"60601",
    "addr:street":"N Michigan Ave Ste 3300",
    "iso:country":"US",
    "sg:address":"205 N Michigan Ave Ste 3300",
    "sg:city":"Chicago",
    "sg:classifiers":[
        {
            "category":"Professional",
            "subcategory":"Employment Agencies",
            "type":"Services"
        }
    ],
    "sg:phone":"+1 312 616 8367",
    "sg:postcode":"60601",
    "sg:province":"IL",
    "wof:name":"Accountants Are At Accountemps",
    "wof:placetype":"venue"
},
  "geometry": {"coordinates":[-87.624397,41.885799],"type":"Point"}
}