{
  "type": "Feature",
  "properties": {
    "iso:country":"US",
    "sg:address":"2436 N Lincoln Avenue",
    "sg:city":"Chicago",
    "sg:classifiers":[
        {
            "category":"Restaurant",
            "type":"Food & Drink"
        }
    ],
    "sg:phone":"+1 773 880 6666",
    "sg:postcode":"60614",
    "sg:province":"IL",
    "sg:tags":[
        "mexican"
    ],
    "wof:name":"Atolito Mexican Kitchen",
    "wof:placetype":"venue"
},
  "geometry": {"coordinates":[-87.64972400000001,41.926293],"type":"Point"}
}