{
  "type": "Feature",
  "properties": {
    "iso:country":"US",
    "sg:address":"213 N Morgan Ste 3C",
    "sg:city":"Chicago",
    "sg:classifiers":[
        {
            "category":"Arts & Performance",
            "subcategory":"Art Gallery",
            "type":"Entertainment"
        }
    ],
    "sg:phone":"+1 312 772 3021",
    "sg:postcode":"60607",
    "sg:province":"IL",
    "sg:website":"ebersmoore.com/",
    "wof:name":"Ebersmoore",
    "wof:placetype":"venue"
},
  "geometry": {"coordinates":[-87.652023,41.886181],"type":"Point"}
}