{
  "type": "Feature",
  "properties": {
    "addr:full":"4325 Lincoln Ave Lisle IL 60532",
    "addr:housenumber":"4325",
    "addr:postcode":"60532",
    "addr:street":"Lincoln Ave",
    "iso:country":"US",
    "sg:address":"4325 Lincoln Ave",
    "sg:city":"Lisle",
    "sg:classifiers":[
        {
            "category":"Autos & Motor Vehicles",
            "subcategory":"Automobile Sales",
            "type":"Retail Goods"
        },
        {
            "category":"Retail",
            "subcategory":"Auto Repair",
            "type":"Services"
        }
    ],
    "sg:phone":"+1 630 241 3000",
    "sg:postcode":"60532",
    "sg:province":"IL",
    "sg:tags":[
        "new",
        "used",
        "leasing",
        "car"
    ],
    "sg:website":"http://www.infinitioflisle.com/",
    "wof:name":"Infiniti Of Lisle",
    "wof:placetype":"venue"
},
  "geometry": {"coordinates":[-88.075923,41.807819],"type":"Point"}
}