{
  "type": "Feature",
  "properties": {
    "iso:country":"US",
    "sg:address":"207 W Orchard Pl",
    "sg:city":"Mount Prospect",
    "sg:classifiers":[
        {
            "category":"Insurance",
            "subcategory":"Insurance Agent",
            "type":"Services"
        }
    ],
    "sg:phone":"+1 847 670 8268",
    "sg:postcode":"60056",
    "sg:province":"IL",
    "wof:name":"Dennis Goszczynski",
    "wof:placetype":"venue"
},
  "geometry": {"coordinates":[-87.938456,42.050894],"type":"Point"}
}