{
  "type": "Feature",
  "properties": {
    "iso:country":"US",
    "sg:address":"32 W Streamwood Blvd",
    "sg:city":"Streamwood",
    "sg:classifiers":[
        {
            "category":"Insurance",
            "subcategory":"Hazard Insurance",
            "type":"Services"
        },
        {
            "category":"Insurance",
            "subcategory":"Insurance Agent",
            "type":"Services"
        },
        {
            "category":"Insurance",
            "subcategory":"Life Insurance",
            "type":"Services"
        },
        {
            "category":"Insurance",
            "subcategory":"Title Insurance",
            "type":"Services"
        }
    ],
    "sg:phone":"+1 630 540 1931",
    "sg:postcode":"60107",
    "sg:province":"IL",
    "sg:tags":[
        "auto",
        "homeowner"
    ],
    "sg:website":"http://www.nationwide.com/agent/Streamwood-ILLINOIS-insurance-agent/joseph-karl/office.html",
    "wof:name":"Joseph A Karl - Nationwide Insurance",
    "wof:placetype":"venue"
},
  "geometry": {"coordinates":[-88.18418,42.021895],"type":"Point"}
}