{
  "type": "Feature",
  "properties": {
    "addr:full":"712 W South 3rd St Shelbyville IL 62565",
    "addr:housenumber":"712",
    "addr:postcode":"62565",
    "addr:street":"W South 3Rd St",
    "iso:country":"US",
    "sg:address":"712 W South 3rd St",
    "sg:city":"Shelbyville",
    "sg:classifiers":[
        {
            "category":"Wholesale",
            "subcategory":"Poultry",
            "type":"Manufacturing & Wholesale Goods"
        },
        {
            "category":"Farming",
            "subcategory":"Livestock Farm",
            "type":"Manufacturing & Wholesale Goods"
        }
    ],
    "sg:phone":"+1 217 774 2645",
    "sg:postcode":"62565",
    "sg:province":"IL",
    "sg:tags":[
        "auction",
        "market"
    ],
    "wof:name":"Hog S Helton Shelbyville Jfl",
    "wof:placetype":"venue"
},
  "geometry": {"coordinates":[-88.800827,39.403743],"type":"Point"}
}