{
  "type": "Feature",
  "properties": {
    "addr:full":"4021 167th St Country Club Hills IL 60478",
    "addr:housenumber":"4021",
    "addr:postcode":"60478",
    "addr:street":"167Th St",
    "iso:country":"US",
    "sg:address":"4021 167th St",
    "sg:city":"Country Club Hills",
    "sg:classifiers":[
        {
            "category":"Shopping",
            "subcategory":"Mobile Phones",
            "type":"Retail Goods"
        }
    ],
    "sg:phone":"+1 708 798 6802",
    "sg:postcode":"60478",
    "sg:province":"IL",
    "sg:website":"www.t-mobile.com",
    "wof:name":"T-Mobile",
    "wof:placetype":"venue"
},
  "geometry": {"coordinates":[-87.71465600000001,41.586003],"type":"Point"}
}