{
  "type": "Feature",
  "properties": {
    "iso:country":"US",
    "sg:address":"8522 S Pulaski Rd",
    "sg:city":"Chicago",
    "sg:classifiers":[
        {
            "category":"Building & Trades",
            "subcategory":"Equipment Rental",
            "type":"Services"
        }
    ],
    "sg:phone":"+1 773 284 0680",
    "sg:postcode":"60652",
    "sg:province":"IL",
    "sg:tags":[
        "renting",
        "leasing",
        "furniture"
    ],
    "wof:name":"Chicago Equipment Rental",
    "wof:placetype":"venue"
},
  "geometry": {"coordinates":[-87.72152800000001,41.73779],"type":"Point"}
}