{
  "type": "Feature",
  "properties": {
    "iso:country":"US",
    "sg:address":"214 E 1700 North Rd",
    "sg:city":"Cisco",
    "sg:phone":"+1 217 669 2192",
    "sg:postcode":"61830",
    "sg:province":"IL",
    "sg:tags":[
        "farm",
        "corn",
        "soybean"
    ],
    "wof:name":"Gucker Farm Inc",
    "wof:placetype":"venue"
},
  "geometry": {"coordinates":[-88.705,40.040365],"type":"Point"}
}