{
  "type": "Feature",
  "properties": {
    "iso:country":"US",
    "sg:address":"1108 N Allen St",
    "sg:city":"Robinson",
    "sg:classifiers":[
        {
            "category":"Health Services",
            "subcategory":"Doctor",
            "type":"Services"
        }
    ],
    "sg:phone":"+1 618 546 5464",
    "sg:postcode":"62454",
    "sg:province":"IL",
    "sg:tags":[
        "medicine",
        "physician",
        "surgeon",
        "internal",
        "surgeons"
    ],
    "wof:name":"Crafort Memorial Hosp.",
    "wof:placetype":"venue"
},
  "geometry": {"coordinates":[-87.750153,39.013173],"type":"Point"}
}