{
  "type": "Feature",
  "properties": {
    "iso:country":"US",
    "sg:address":"410 N Broadway St",
    "sg:city":"Sandoval",
    "sg:classifiers":[
        {
            "category":"Organizations",
            "subcategory":"Religious Organization",
            "type":"Services"
        }
    ],
    "sg:phone":"+1 618 247 3859",
    "sg:postcode":"62882",
    "sg:province":"IL",
    "sg:tags":[
        "church"
    ],
    "wof:name":"First United Meth Parsonage",
    "wof:placetype":"venue"
},
  "geometry": {"coordinates":[-89.117878,38.616365],"type":"Point"}
}