{
  "type": "Feature",
  "properties": {
    "iso:country":"US",
    "sg:address":"1635 W Wise Rd",
    "sg:city":"Schaumburg",
    "sg:classifiers":[
        {
            "category":"Manufacturing",
            "subcategory":"Printing",
            "type":"Manufacturing & Wholesale Goods"
        }
    ],
    "sg:phone":"+1 847 895 3322",
    "sg:postcode":"60193",
    "sg:province":"IL",
    "sg:tags":[
        "print",
        "lithographic",
        "typesetting"
    ],
    "wof:name":"S & S Printing Inc",
    "wof:placetype":"venue"
},
  "geometry": {"coordinates":[-88.121822,42.003663],"type":"Point"}
}