{
  "type": "Feature",
  "properties": {
    "iso:country":"US",
    "sg:address":"6754 Barrington Rd",
    "sg:city":"Bartlett",
    "sg:classifiers":[
        {
            "category":"Shopping",
            "subcategory":"Crafts & Fabrics",
            "type":"Retail Goods"
        }
    ],
    "sg:phone":"+1   ",
    "sg:postcode":"60133",
    "sg:province":"IL",
    "sg:tags":[
        "sewing"
    ],
    "wof:name":"Fabric Mart Inc",
    "wof:placetype":"venue"
},
  "geometry": {"coordinates":[-88.144938,41.994447],"type":"Point"}
}