{
  "type": "Feature",
  "properties": {
    "iso:country":"US",
    "sg:address":"4600 N Ravenswood Ave",
    "sg:city":"Chicago",
    "sg:classifiers":[
        {
            "category":"Health Services",
            "subcategory":"Health Practitioner",
            "type":"Services"
        },
        {
            "category":"Health Services",
            "subcategory":"Doctor",
            "type":"Services"
        }
    ],
    "sg:phone":"+1 773 989 3900",
    "sg:postcode":"60640",
    "sg:province":"IL",
    "sg:tags":[
        "physician",
        "surgeon",
        "therapist",
        "physical"
    ],
    "sg:website":"www.advocatehealth.com",
    "wof:name":"Advocate Illinois Masonic Hlth",
    "wof:placetype":"venue"
},
  "geometry": {"coordinates":[-87.674664,41.966985],"type":"Point"}
}