{
  "type": "Feature",
  "properties": {
    "addr:full":"511 N Jackson St Robinson IL 62454",
    "addr:housenumber":"511",
    "addr:postcode":"62454",
    "addr:street":"N Jackson St",
    "iso:country":"US",
    "sg:address":"511 N Jackson St",
    "sg:city":"Robinson",
    "sg:classifiers":[
        {
            "category":"Autos & Motor Vehicles",
            "subcategory":"Automobile Sales",
            "type":"Retail Goods"
        }
    ],
    "sg:phone":"+1 618 544 7212",
    "sg:postcode":"62454",
    "sg:province":"IL",
    "sg:tags":[
        "new",
        "car"
    ],
    "sg:website":"http://www.terrywiseman.com",
    "wof:name":"Terry Wiseman Buick",
    "wof:placetype":"venue"
},
  "geometry": {"coordinates":[-87.732193,39.002135],"type":"Point"}
}