{
  "type": "Feature",
  "properties": {
    "addr:full":"7225 Springside Ave Downers Grove IL 60516",
    "addr:housenumber":"7225",
    "addr:postcode":"60516",
    "addr:street":"Springside Ave",
    "iso:country":"US",
    "sg:address":"7225 Springside Ave",
    "sg:city":"Downers Grove",
    "sg:classifiers":[
        {
            "category":"Professional",
            "subcategory":"Management & Consulting",
            "type":"Services"
        }
    ],
    "sg:phone":"+1   ",
    "sg:postcode":"60516",
    "sg:province":"IL",
    "sg:tags":[
        "product",
        "quality",
        "kitchen"
    ],
    "wof:name":"Pampered Chef Ltd",
    "wof:placetype":"venue"
},
  "geometry": {"coordinates":[-88.021953,41.756601],"type":"Point"}
}