{
  "type": "Feature",
  "properties": {
    "iso:country":"US",
    "sg:address":"2009 N Western Ave",
    "sg:city":"Chicago",
    "sg:classifiers":[
        {
            "category":"Restaurant",
            "type":"Food & Drink"
        }
    ],
    "sg:phone":"+1 773 486 3303",
    "sg:postcode":"60647",
    "sg:province":"IL",
    "sg:tags":[
        "mexican"
    ],
    "wof:name":"Lazo's Tacos",
    "wof:placetype":"venue"
},
  "geometry": {"coordinates":[-87.6875,41.917702],"type":"Point"}
}