{
  "type": "Feature",
  "properties": {
    "addr:full":"706 Main St Evanston IL 60202",
    "addr:housenumber":"706",
    "addr:postcode":"60202",
    "addr:street":"Main St",
    "iso:country":"US",
    "sg:address":"706 Main St",
    "sg:city":"Evanston",
    "sg:classifiers":[
        {
            "category":"Wholesale",
            "subcategory":"Groceries",
            "type":"Manufacturing & Wholesale Goods"
        }
    ],
    "sg:phone":"+1 847 475 6565",
    "sg:postcode":"60202",
    "sg:province":"IL",
    "sg:tags":[
        "bakery"
    ],
    "wof:name":"Thompson Bakery of Evanston",
    "wof:placetype":"venue"
},
  "geometry": {"coordinates":[-87.682103,42.033894],"type":"Point"}
}