{
  "type": "Feature",
  "properties": {
    "addr:full":"3238 W Wilson Ave Chicago IL 60625",
    "addr:housenumber":"3238",
    "addr:postcode":"60625",
    "addr:street":"W Wilson Ave",
    "iso:country":"US",
    "sg:address":"3238 W Wilson Ave",
    "sg:city":"Chicago",
    "sg:classifiers":[
        {
            "category":"Home & Garden",
            "subcategory":"Building Materials",
            "type":"Retail Goods"
        },
        {
            "category":"Building & Trades",
            "subcategory":"Construction",
            "type":"Services"
        }
    ],
    "sg:phone":"+1 773 583 8948",
    "sg:postcode":"60625",
    "sg:province":"IL",
    "sg:tags":[
        "altering",
        "improvement",
        "remodeling",
        "carpenter",
        "contractor"
    ],
    "wof:name":"Aj Carpentry",
    "wof:placetype":"venue"
},
  "geometry": {"coordinates":[-87.709321,41.964695],"type":"Point"}
}