{
  "type": "Feature",
  "properties": {
    "addr:full":"14204 W Sterling Rd Polo IL 61064",
    "addr:housenumber":"14204",
    "addr:postcode":"61064",
    "addr:street":"W Sterling Rd",
    "iso:country":"US",
    "sg:address":"14204 W Sterling Rd",
    "sg:city":"Polo",
    "sg:classifiers":[
        {
            "category":"Farming",
            "subcategory":"Livestock Farm",
            "type":"Manufacturing & Wholesale Goods"
        }
    ],
    "sg:phone":"+1 815 946 3283",
    "sg:postcode":"61064",
    "sg:province":"IL",
    "sg:tags":[
        "implement",
        "grain",
        "cattle"
    ],
    "wof:name":"Scholl Farms of Illinois Ltd",
    "wof:placetype":"venue"
},
  "geometry": {"coordinates":[-89.60041200000001,41.916421],"type":"Point"}
}