{
  "type": "Feature",
  "properties": {
    "addr:full":"1422 Washington Ave Alton IL 62002",
    "addr:housenumber":"1422",
    "addr:postcode":"62002",
    "addr:street":"Washington Ave",
    "iso:country":"US",
    "sg:address":"1422 Washington Ave",
    "sg:city":"Alton",
    "sg:classifiers":[
        {
            "category":"Organizations",
            "subcategory":"Religious Organization",
            "type":"Services"
        }
    ],
    "sg:phone":"+1 618 462 8816",
    "sg:postcode":"62002",
    "sg:province":"IL",
    "sg:website":"www.calbap.org",
    "wof:name":"Calvary Baptist Church",
    "wof:placetype":"venue"
},
  "geometry": {"coordinates":[-90.14962199999999,38.899501],"type":"Point"}
}