{
  "type": "Feature",
  "properties": {
    "addr:full":"16052 Debra Dr Oak Forest IL 60452",
    "addr:housenumber":"16052",
    "addr:postcode":"60452",
    "addr:street":"Debra Dr",
    "iso:country":"US",
    "sg:address":"16052 Debra Dr",
    "sg:city":"Oak Forest",
    "sg:classifiers":[
        {
            "category":"Utilities",
            "subcategory":"Refuse",
            "type":"Services"
        }
    ],
    "sg:phone":"+1 708 687 6778",
    "sg:postcode":"60452",
    "sg:province":"IL",
    "sg:tags":[
        "operator",
        "local",
        "system",
        "trucking"
    ],
    "wof:name":"KAL Trucking Inc",
    "wof:placetype":"venue"
},
  "geometry": {"coordinates":[-87.753142,41.597578],"type":"Point"}
}