{
  "type": "Feature",
  "properties": {
    "addr:full":"1523 Marquette Rd Joliet IL 60435",
    "addr:housenumber":"1523",
    "addr:postcode":"60435",
    "addr:street":"Marquette Rd",
    "iso:country":"US",
    "sg:address":"1523 Marquette Rd",
    "sg:city":"Joliet",
    "sg:classifiers":[
        {
            "category":"Manufacturing",
            "subcategory":"Musical Instruments",
            "type":"Manufacturing & Wholesale Goods"
        }
    ],
    "sg:phone":"+1 815 741 3989",
    "sg:postcode":"60435",
    "sg:province":"IL",
    "wof:name":"Kradl Inc",
    "wof:placetype":"venue"
},
  "geometry": {"coordinates":[-88.118483,41.527619],"type":"Point"}
}