{
  "type": "Feature",
  "properties": {
    "iso:country":"US",
    "sg:address":"5319 N Wayne Ave",
    "sg:city":"Chicago",
    "sg:classifiers":[
        {
            "category":"Professional",
            "subcategory":"Management & Consulting",
            "type":"Services"
        }
    ],
    "sg:phone":"+1 773 334 6383",
    "sg:postcode":"60640",
    "sg:province":"IL",
    "sg:tags":[
        "consultant",
        "business"
    ],
    "wof:name":"Gordon Group",
    "wof:placetype":"venue"
},
  "geometry": {"coordinates":[-87.663575,41.979581],"type":"Point"}
}