{
  "type": "Feature",
  "properties": {
    "iso:country":"US",
    "sg:address":"1715 N Wells St Apt 34",
    "sg:city":"Chicago",
    "sg:classifiers":[
        {
            "category":"Professional",
            "subcategory":"Business Services",
            "type":"Services"
        }
    ],
    "sg:phone":"+1 312 504 3159",
    "sg:postcode":"60614",
    "sg:province":"IL",
    "sg:tags":[
        "medical",
        "administration"
    ],
    "wof:name":"E I Medical Management In",
    "wof:placetype":"venue"
},
  "geometry": {"coordinates":[-87.63476199999999,41.913047],"type":"Point"}
}