{
  "type": "Feature",
  "properties": {
    "iso:country":"US",
    "sg:address":"440 N Wabash Ave",
    "sg:city":"Chicago",
    "sg:classifiers":[
        {
            "category":"Retail",
            "subcategory":"Repair Shop",
            "type":"Services"
        }
    ],
    "sg:phone":"+1 312 276 0246",
    "sg:postcode":"60611",
    "sg:province":"IL",
    "sg:tags":[
        "mending",
        "weaving"
    ],
    "wof:name":"M Dc",
    "wof:placetype":"venue"
},
  "geometry": {"coordinates":[-87.62664700000001,41.890055],"type":"Point"}
}