{
  "type": "Feature",
  "properties": {
    "iso:country":"US",
    "sg:address":"810 Walnut Ave",
    "sg:city":"Elgin",
    "sg:classifiers":[
        {
            "category":"Retail",
            "subcategory":"Auto Repair",
            "type":"Services"
        }
    ],
    "sg:phone":"+1 847 741 1492",
    "sg:postcode":"60123",
    "sg:province":"IL",
    "sg:tags":[
        "repairing",
        "automobile"
    ],
    "wof:name":"Gary's Automotive Svc",
    "wof:placetype":"venue"
},
  "geometry": {"coordinates":[-88.299944,42.028614],"type":"Point"}
}