{
  "type": "Feature",
  "properties": {
    "iso:country":"US",
    "sg:address":"3364 Commercial Ave",
    "sg:city":"Northbrook",
    "sg:classifiers":[
        {
            "category":"Manufacturing",
            "subcategory":"Printing",
            "type":"Manufacturing & Wholesale Goods"
        }
    ],
    "sg:phone":"+1 847 272 5560",
    "sg:postcode":"60062",
    "sg:province":"IL",
    "sg:tags":[
        "lithographic",
        "b",
        "commercial",
        "typesetting"
    ],
    "wof:name":"PIP Printing",
    "wof:placetype":"venue"
},
  "geometry": {"coordinates":[-87.859994,42.146569],"type":"Point"}
}