{
  "type": "Feature",
  "properties": {
    "iso:country":"US",
    "sg:address":"1030 N Clark St Fl 5",
    "sg:city":"Chicago",
    "sg:classifiers":[
        {
            "category":"Health Services",
            "subcategory":"Clinic",
            "type":"Services"
        }
    ],
    "sg:phone":"+1 312 274 0680",
    "sg:postcode":"60610",
    "sg:province":"IL",
    "sg:tags":[
        "medical"
    ],
    "sg:website":"www.ric.org/",
    "wof:name":"Rehabilitation Institute of Chicago",
    "wof:placetype":"venue"
},
  "geometry": {"coordinates":[-87.631401,41.900902],"type":"Point"}
}