{
  "type": "Feature",
  "properties": {
    "addr:full":"550 S Green Bay Rd Waukegan IL 60085",
    "addr:housenumber":"550",
    "addr:postcode":"60085",
    "addr:street":"S Green Bay Rd",
    "iso:country":"US",
    "sg:address":"550 S Green Bay Rd",
    "sg:city":"Waukegan",
    "sg:classifiers":[
        {
            "category":"Retail",
            "subcategory":"Auto Repair",
            "type":"Services"
        }
    ],
    "sg:phone":"+1 847 662 2220",
    "sg:postcode":"60085",
    "sg:province":"IL",
    "wof:name":"Meineke Discount Mufflers",
    "wof:placetype":"venue"
},
  "geometry": {"coordinates":[-87.874047,42.352773],"type":"Point"}
}