{
  "type": "Feature",
  "properties": {
    "iso:country":"US",
    "sg:address":"245 Sundew Dr",
    "sg:city":"Belleville",
    "sg:classifiers":[
        {
            "category":"Home & Garden",
            "subcategory":"Building Materials",
            "type":"Retail Goods"
        }
    ],
    "sg:phone":"+1   ",
    "sg:postcode":"62221",
    "sg:province":"IL",
    "wof:name":"Si Corporation",
    "wof:placetype":"venue"
},
  "geometry": {"coordinates":[-89.940071,38.528495],"type":"Point"}
}