{
  "type": "Feature",
  "properties": {
    "iso:country":"US",
    "sg:address":"867 N Addison Ave",
    "sg:city":"Elmhurst",
    "sg:classifiers":[
        {
            "category":"Professional",
            "subcategory":"Business Services",
            "type":"Services"
        }
    ],
    "sg:phone":"+1 630 834 8257",
    "sg:postcode":"60126",
    "sg:province":"IL",
    "wof:name":"Ill Prfessional Festival Assoc",
    "wof:placetype":"venue"
},
  "geometry": {"coordinates":[-87.94136,41.926244],"type":"Point"}
}