{
  "type": "Feature",
  "properties": {
    "iso:country":"US",
    "sg:address":"323 N Harlem Ave",
    "sg:city":"Peotone",
    "sg:classifiers":[
        {
            "category":"Food & Beverages",
            "subcategory":"Groceries & Convenience Stores",
            "type":"Retail Goods"
        }
    ],
    "sg:phone":"+1 708 258 3510",
    "sg:postcode":"60468",
    "sg:province":"IL",
    "sg:tags":[
        "station",
        "gasoline",
        "trailer",
        "utility"
    ],
    "wof:name":"U-Haul",
    "wof:placetype":"venue"
},
  "geometry": {"coordinates":[-87.785368,41.339068],"type":"Point"}
}