{
  "type": "Feature",
  "properties": {
    "iso:country":"US",
    "sg:address":"4898 Wildwood Ln",
    "sg:city":"Brighton",
    "sg:classifiers":[
        {
            "category":"Retail",
            "subcategory":"Repair Shop",
            "type":"Services"
        },
        {
            "category":"Building & Trades",
            "subcategory":"Plumbing",
            "type":"Services"
        }
    ],
    "sg:phone":"+1 618 372 7116",
    "sg:postcode":"62012",
    "sg:province":"IL",
    "sg:tags":[
        "conditioning",
        "air",
        "refrigeration",
        "system",
        "contractor"
    ],
    "wof:name":"Dale Plumbing Heating & Coolg",
    "wof:placetype":"venue"
},
  "geometry": {"coordinates":[-90.06004900000001,39.056376],"type":"Point"}
}