{
  "type": "Feature",
  "properties": {
    "iso:country":"US",
    "sg:address":"4377 W 26th St",
    "sg:city":"Chicago",
    "sg:classifiers":[
        {
            "category":"Restaurant",
            "type":"Food & Drink"
        }
    ],
    "sg:phone":"+1 773 522 2050",
    "sg:postcode":"60640",
    "sg:province":"IL",
    "sg:tags":[
        "american",
        "latin"
    ],
    "wof:name":"Izalco Restaurant",
    "wof:placetype":"venue"
},
  "geometry": {"coordinates":[-87.733885,41.843765],"type":"Point"}
}