{
  "type": "Feature",
  "properties": {
    "iso:country":"US",
    "sg:address":"212 SW Water St",
    "sg:city":"Peoria",
    "sg:classifiers":[
        {
            "category":"Professional",
            "type":"Services"
        },
        {
            "category":"Shopping",
            "subcategory":"Party Supplies",
            "type":"Retail Goods"
        },
        {
            "category":"Restaurant",
            "type":"Food & Drink"
        },
        {
            "category":"Retail",
            "subcategory":"Event Space",
            "type":"Services"
        },
        {
            "category":"Personal",
            "type":"Services"
        }
    ],
    "sg:phone":"+1 309 671 7000",
    "sg:postcode":"61602",
    "sg:province":"IL",
    "sg:tags":[
        "facility",
        "wedding",
        "hall",
        "planning",
        "reception",
        "caterer",
        "meeting",
        "banquet"
    ],
    "wof:name":"River Station",
    "wof:placetype":"venue"
},
  "geometry": {"coordinates":[-89.588964,40.689003],"type":"Point"}
}