{
  "type": "Feature",
  "properties": {
    "addr:full":"2606 S State St Lockport IL 60441",
    "addr:housenumber":"2606",
    "addr:postcode":"60441",
    "addr:street":"S State St",
    "iso:country":"US",
    "sg:address":"2606 S State St",
    "sg:city":"Lockport",
    "sg:classifiers":[
        {
            "category":"Retail",
            "subcategory":"Auto Repair",
            "type":"Services"
        }
    ],
    "sg:phone":"+1   ",
    "sg:postcode":"60441",
    "sg:province":"IL",
    "sg:tags":[
        "general",
        "supply"
    ],
    "wof:name":"Gombosi Tire & Automotive",
    "wof:placetype":"venue"
},
  "geometry": {"coordinates":[-88.067859,41.569658],"type":"Point"}
}