{
  "type": "Feature",
  "properties": {
    "iso:country":"US",
    "sg:address":"400 E 41st St",
    "sg:city":"Chicago",
    "sg:classifiers":[
        {
            "category":"Professional",
            "subcategory":"Accounting & Tax Preparation",
            "type":"Services"
        }
    ],
    "sg:phone":"+1 773 924 2556",
    "sg:postcode":"60653",
    "sg:province":"IL",
    "sg:tags":[
        "return"
    ],
    "wof:name":"Davis Bedenfield Associates",
    "wof:placetype":"venue"
},
  "geometry": {"coordinates":[-87.61586699999999,41.82025],"type":"Point"}
}