{
  "type": "Feature",
  "properties": {
    "addr:full":"9121 159th St Tinley Park IL 60487",
    "addr:housenumber":"9121",
    "addr:postcode":"60487",
    "addr:street":"159Th St",
    "iso:country":"US",
    "sg:address":"9121 159th St",
    "sg:city":"Tinley Park",
    "sg:classifiers":[
        {
            "category":"Personal",
            "type":"Services"
        }
    ],
    "sg:phone":"+1 708 364 8267",
    "sg:postcode":"60487",
    "sg:province":"IL",
    "wof:name":"Executive Tans",
    "wof:placetype":"venue"
},
  "geometry": {"coordinates":[-87.843988,41.601437],"type":"Point"}
}