{
  "type": "Feature",
  "properties": {
    "addr:full":"8055 Lamon Ave Bedford Park IL 60459",
    "addr:postcode":"8055;60459",
    "addr:street":"Lamon Ave",
    "iso:country":"US",
    "sg:address":"8055 Lamon Ave",
    "sg:city":"Bedford Park",
    "sg:classifiers":[
        {
            "category":"Professional",
            "subcategory":"Business Services",
            "type":"Services"
        }
    ],
    "sg:phone":"+1 708 346 6165",
    "sg:postcode":"60459",
    "sg:province":"IL",
    "wof:name":"Mrl Enterprises Inc",
    "wof:placetype":"venue"
},
  "geometry": {"coordinates":[-87.743686,41.74841],"type":"Point"}
}