{
  "type": "Feature",
  "properties": {
    "iso:country":"US",
    "sg:address":"5449 W 79th St",
    "sg:city":"Burbank",
    "sg:classifiers":[
        {
            "category":"Shopping",
            "subcategory":"Florist",
            "type":"Retail Goods"
        }
    ],
    "sg:phone":"+1 708 424 2335",
    "sg:postcode":"60459",
    "sg:province":"IL",
    "wof:name":"Flower Hill",
    "wof:placetype":"venue"
},
  "geometry": {"coordinates":[-87.758698,41.748699],"type":"Point"}
}