{
  "type": "Feature",
  "properties": {
    "addr:full":"14946 Mission Ave Oak Forest IL 60452",
    "addr:housenumber":"14946",
    "addr:postcode":"60452",
    "addr:street":"Mission Ave",
    "iso:country":"US",
    "sg:address":"14946 Mission Ave",
    "sg:city":"Oak Forest",
    "sg:classifiers":[
        {
            "category":"Building & Trades",
            "subcategory":"Electrical",
            "type":"Services"
        }
    ],
    "sg:phone":"+1 708 535 9630",
    "sg:postcode":"60452",
    "sg:province":"IL",
    "sg:tags":[
        "electrical",
        "contractor"
    ],
    "wof:name":"Mission Electric Inc",
    "wof:placetype":"venue"
},
  "geometry": {"coordinates":[-87.752392,41.619832],"type":"Point"}
}