{
  "type": "Feature",
  "properties": {
    "iso:country":"US",
    "sg:address":"320 Reber St",
    "sg:city":"Wheaton",
    "sg:classifiers":[
        {
            "category":"Real Estate",
            "subcategory":"Surveying",
            "type":"Services"
        }
    ],
    "sg:phone":"+1 630 653 6331",
    "sg:postcode":"60187",
    "sg:province":"IL",
    "wof:name":"Lambert & Assoc",
    "wof:placetype":"venue"
},
  "geometry": {"coordinates":[-88.104309,41.86272],"type":"Point"}
}