{
  "type": "Feature",
  "properties": {
    "iso:country":"US",
    "sg:address":"7224 W Palos Ave",
    "sg:city":"Palos Heights",
    "sg:classifiers":[
        {
            "category":"Insurance",
            "subcategory":"Insurance Agent",
            "type":"Services"
        }
    ],
    "sg:phone":"+1 708 923 1800",
    "sg:postcode":"60463",
    "sg:province":"IL",
    "wof:name":"AFLAC",
    "wof:placetype":"venue"
},
  "geometry": {"coordinates":[-87.80074500000001,41.659395],"type":"Point"}
}