{
  "type": "Feature",
  "properties": {
    "iso:country":"US",
    "sg:address":"321 S Buesching Rd",
    "sg:city":"Lake Zurich",
    "sg:classifiers":[
        {
            "category":"Government",
            "subcategory":"Fire Station",
            "type":"Public Place"
        }
    ],
    "sg:phone":"+1 847 540 5070",
    "sg:postcode":"60047",
    "sg:province":"IL",
    "sg:tags":[
        "department",
        "protection"
    ],
    "sg:website":"www.lzfirerescue.org",
    "wof:name":"Lake Zurich Fire & Rescue",
    "wof:placetype":"venue"
},
  "geometry": {"coordinates":[-88.082214,42.192755],"type":"Point"}
}