{
  "type": "Feature",
  "properties": {
    "addr:full":"1680 W Station St Kankakee IL 60901",
    "addr:housenumber":"1680",
    "addr:postcode":"60901",
    "addr:street":"W Station St",
    "iso:country":"US",
    "sg:address":"1680 W Station St",
    "sg:city":"Kankakee",
    "sg:classifiers":[
        {
            "category":"Food & Beverages",
            "subcategory":"Liquor & Beverages",
            "type":"Retail Goods"
        }
    ],
    "sg:phone":"+1   ",
    "sg:postcode":"60901",
    "sg:province":"IL",
    "sg:tags":[
        "packaged"
    ],
    "wof:name":"Kankakee Liquor Store Ltd",
    "wof:placetype":"venue"
},
  "geometry": {"coordinates":[-87.90058000000001,41.118652],"type":"Point"}
}