{
  "type": "Feature",
  "properties": {
    "addr:full":"2020 Morcambe Bay Dr New Lenox IL 60451",
    "addr:housenumber":"2020",
    "addr:postcode":"60451",
    "addr:street":"Morcambe Bay Dr",
    "iso:country":"US",
    "sg:address":"2020 Morcambe Bay Dr",
    "sg:city":"New Lenox",
    "sg:classifiers":[
        {
            "category":"Restaurant",
            "type":"Food & Drink"
        }
    ],
    "sg:phone":"+1   ",
    "sg:postcode":"60451",
    "sg:province":"IL",
    "sg:tags":[
        "eating"
    ],
    "wof:name":"Kitchen Vision",
    "wof:placetype":"venue"
},
  "geometry": {"coordinates":[-87.92254800000001,41.472169],"type":"Point"}
}