{
  "type": "Feature",
  "properties": {
    "addr:full":"312 Eureka St Genoa IL 60135",
    "addr:housenumber":"312",
    "addr:postcode":"60135",
    "addr:street":"Eureka St",
    "iso:country":"US",
    "sg:address":"312 Eureka St",
    "sg:city":"Genoa",
    "sg:classifiers":[
        {
            "category":"Shopping",
            "subcategory":"Department Store",
            "type":"Retail Goods"
        },
        {
            "category":"Home & Garden",
            "subcategory":"Building Materials",
            "type":"Retail Goods"
        },
        {
            "category":"Manufacturing",
            "subcategory":"Building Materials",
            "type":"Manufacturing & Wholesale Goods"
        }
    ],
    "sg:phone":"+1 815 784 4165",
    "sg:postcode":"60135",
    "sg:province":"IL",
    "sg:tags":[
        "product",
        "aluminum"
    ],
    "sg:website":"http://www.custom-aluminum.com",
    "wof:name":"Custom Aluminum Products Incorporated",
    "wof:placetype":"venue"
},
  "geometry": {"coordinates":[-88.687659,42.099487],"type":"Point"}
}