{
  "type": "Feature",
  "properties": {
    "iso:country":"US",
    "sg:address":"131 N Normal St",
    "sg:city":"Macomb",
    "sg:classifiers":[
        {
            "category":"Shopping",
            "subcategory":"Music",
            "type":"Retail Goods"
        }
    ],
    "sg:phone":"+1   ",
    "sg:postcode":"61455",
    "sg:province":"IL",
    "wof:name":"Disc & Dat",
    "wof:placetype":"venue"
},
  "geometry": {"coordinates":[-90.686518,40.459724],"type":"Point"}
}