{
  "type": "Feature",
  "properties": {
    "addr:full":"13449 S Crawford Ave Robbins IL 60472",
    "addr:housenumber":"13449",
    "addr:postcode":"60472",
    "addr:street":"S Crawford Ave",
    "iso:country":"US",
    "sg:address":"13449 S Crawford Ave",
    "sg:city":"Robbins",
    "sg:classifiers":[
        {
            "category":"Autos & Motor Vehicles",
            "subcategory":"Automobile Sales",
            "type":"Retail Goods"
        }
    ],
    "sg:phone":"+1   ",
    "sg:postcode":"60472",
    "sg:province":"IL",
    "sg:tags":[
        "used"
    ],
    "wof:name":"A G F Auto Sales",
    "wof:placetype":"venue"
},
  "geometry": {"coordinates":[-87.71858899999999,41.648728],"type":"Point"}
}