{
  "type": "Feature",
  "properties": {
    "addr:full":"4701 Auvergne Ave Lisle IL 60532",
    "addr:postcode":"4701;60532",
    "addr:street":"Auvergne Ave",
    "iso:country":"US",
    "sg:address":"4701 Auvergne Ave",
    "sg:city":"Lisle",
    "sg:classifiers":[
        {
            "category":"Professional",
            "subcategory":"Management & Consulting",
            "type":"Services"
        }
    ],
    "sg:phone":"+1 630 852 3400",
    "sg:postcode":"60532",
    "sg:province":"IL",
    "sg:tags":[
        "personnel",
        "consultant"
    ],
    "sg:website":"www.aggressivecorp.com",
    "wof:name":"Aggressive Partners",
    "wof:placetype":"venue"
},
  "geometry": {"coordinates":[-88.06101099999999,41.7997],"type":"Point"}
}