{
  "type": "Feature",
  "properties": {
    "addr:full":"1220 Crosby St Rockford IL 61107",
    "addr:housenumber":"1220",
    "addr:postcode":"61107",
    "addr:street":"Crosby St",
    "iso:country":"US",
    "sg:address":"1220 Crosby St",
    "sg:city":"Rockford",
    "sg:classifiers":[
        {
            "category":"Manufacturing",
            "subcategory":"Textiles",
            "type":"Manufacturing & Wholesale Goods"
        }
    ],
    "sg:phone":"+1 815 963 1375",
    "sg:postcode":"61107",
    "sg:province":"IL",
    "sg:tags":[
        "mill",
        "narrow",
        "fabric"
    ],
    "wof:name":"James Ribbon Service",
    "wof:placetype":"venue"
},
  "geometry": {"coordinates":[-89.076177,42.269355],"type":"Point"}
}