{
  "type": "Feature",
  "properties": {
    "iso:country":"US",
    "sg:address":"10935 S Artesian Ave",
    "sg:city":"Chicago",
    "sg:classifiers":[
        {
            "category":"Retail",
            "subcategory":"Auto Repair",
            "type":"Services"
        }
    ],
    "sg:phone":"+1 773 881 8575",
    "sg:postcode":"60655",
    "sg:province":"IL",
    "sg:tags":[
        "general"
    ],
    "wof:name":"Patton Motor Service",
    "wof:placetype":"venue"
},
  "geometry": {"coordinates":[-87.682433,41.694249],"type":"Point"}
}