{
  "type": "Feature",
  "properties": {
    "iso:country":"US",
    "sg:address":"1177 Furlong Dr",
    "sg:city":"Libertyville",
    "sg:classifiers":[
        {
            "category":"Banks & Credit Unions",
            "subcategory":"Financial Services",
            "type":"Services"
        },
        {
            "category":"Professional",
            "subcategory":"Business Services",
            "type":"Services"
        }
    ],
    "sg:phone":"+1 847 680 7716",
    "sg:postcode":"60048",
    "sg:province":"IL",
    "sg:tags":[
        "management"
    ],
    "wof:name":"Saratoga Capital Company Inc",
    "wof:placetype":"venue"
},
  "geometry": {"coordinates":[-87.94535999999999,42.264173],"type":"Point"}
}