{
  "type": "Feature",
  "properties": {
    "iso:country":"US",
    "sg:address":"588 E Court St",
    "sg:city":"Kankakee",
    "sg:classifiers":[
        {
            "category":"Banks & Credit Unions",
            "subcategory":"Investment Brokerage",
            "type":"Services"
        },
        {
            "category":"Insurance",
            "subcategory":"Hazard Insurance",
            "type":"Services"
        }
    ],
    "sg:phone":"+1 815 932 7411",
    "sg:postcode":"60901",
    "sg:province":"IL",
    "sg:tags":[
        "commercial",
        "agent",
        "business",
        "resume"
    ],
    "wof:name":"Deuschle-Gilmore Insurance Agency, Inc.",
    "wof:placetype":"venue"
},
  "geometry": {"coordinates":[-87.827415,41.118805],"type":"Point"}
}