{
  "type": "Feature",
  "properties": {
    "addr:full":"949 Harlem Ave Forest Park IL 60130",
    "addr:housenumber":"949",
    "addr:postcode":"60130",
    "addr:street":"Harlem Ave",
    "iso:country":"US",
    "sg:address":"949 Harlem Ave",
    "sg:city":"Forest Park",
    "sg:classifiers":[
        {
            "category":"Food & Beverages",
            "subcategory":"Groceries & Convenience Stores",
            "type":"Retail Goods"
        }
    ],
    "sg:phone":"+1   ",
    "sg:postcode":"60130",
    "sg:province":"IL",
    "wof:name":"Go Mart",
    "wof:placetype":"venue"
},
  "geometry": {"coordinates":[-87.804434,41.86956],"type":"Point"}
}