{
  "type": "Feature",
  "properties": {
    "addr:full":"5113 N Ravenswood Ave Chicago IL 60640",
    "addr:housenumber":"5113",
    "addr:postcode":"60640",
    "addr:street":"N Ravenswood Ave",
    "iso:country":"US",
    "sg:address":"5113 N Ravenswood Ave",
    "sg:city":"Chicago",
    "sg:classifiers":[
        {
            "category":"Recreation",
            "subcategory":"Marina",
            "type":"Entertainment"
        }
    ],
    "sg:phone":"+1 773 561 0691",
    "sg:postcode":"60640",
    "sg:province":"IL",
    "sg:tags":[
        "storage",
        "boat"
    ],
    "wof:name":"Drydock Inc",
    "wof:placetype":"venue"
},
  "geometry": {"coordinates":[-87.674299,41.974797],"type":"Point"}
}