{
  "type": "Feature",
  "properties": {
    "addr:full":"105 E High St Colona IL 61241",
    "addr:housenumber":"105",
    "addr:postcode":"61241",
    "addr:street":"E High St",
    "iso:country":"US",
    "sg:address":"105 E High St",
    "sg:city":"Colona",
    "sg:classifiers":[
        {
            "category":"Personal",
            "type":"Services"
        }
    ],
    "sg:phone":"+1 309 792 2682",
    "sg:postcode":"61241",
    "sg:province":"IL",
    "wof:name":"Dan Carpenter",
    "wof:placetype":"venue"
},
  "geometry": {"coordinates":[-90.319248,41.498432],"type":"Point"}
}