{
  "type": "Feature",
  "properties": {
    "addr:full":"445 W Erie St Chicago IL 60654",
    "addr:housenumber":"445",
    "addr:postcode":"60654",
    "addr:street":"W Erie St",
    "iso:country":"US",
    "sg:address":"445 W Erie St",
    "sg:city":"Chicago",
    "sg:classifiers":[
        {
            "category":"Professional",
            "subcategory":"Computer Services",
            "type":"Services"
        },
        {
            "category":"Wholesale",
            "subcategory":"Computers",
            "type":"Manufacturing & Wholesale Goods"
        }
    ],
    "sg:phone":"+1 312 229 7800",
    "sg:postcode":"60654",
    "sg:province":"IL",
    "sg:tags":[
        "equipment",
        "cd-rom",
        "software"
    ],
    "wof:name":"B2p Commerce Corp",
    "wof:placetype":"venue"
},
  "geometry": {"coordinates":[-87.640258,41.893917],"type":"Point"}
}