{
  "type": "Feature",
  "properties": {
    "addr:full":"2100 Manchester Rd Wheaton IL 60187",
    "addr:housenumber":"2100",
    "addr:postcode":"60187",
    "addr:street":"Manchester Rd",
    "iso:country":"US",
    "sg:address":"2100 Manchester Rd",
    "sg:city":"Wheaton",
    "sg:classifiers":[
        {
            "category":"Organizations",
            "subcategory":"Non-profit Organization",
            "type":"Services"
        }
    ],
    "sg:phone":"+1 630 690 7800",
    "sg:postcode":"60187",
    "sg:province":"IL",
    "sg:tags":[
        "information",
        "alcoholism",
        "treatment"
    ],
    "wof:name":"Associates In Alcohol & Drug",
    "wof:placetype":"venue"
},
  "geometry": {"coordinates":[-88.13596200000001,41.865567],"type":"Point"}
}