{
  "type": "Feature",
  "properties": {
    "iso:country":"US",
    "sg:address":"2111 Boeger Ave",
    "sg:city":"Westchester",
    "sg:classifiers":[
        {
            "category":"Personal",
            "subcategory":"Beauty Salon",
            "type":"Services"
        }
    ],
    "sg:phone":"+1 773 935 7006",
    "sg:postcode":"60154",
    "sg:province":"IL",
    "wof:name":"Carissima Italy Salon",
    "wof:placetype":"venue"
},
  "geometry": {"coordinates":[-87.895262,41.849334],"type":"Point"}
}