{
  "type": "Feature",
  "properties": {
    "iso:country":"US",
    "sg:address":"2274 Robin Rd",
    "sg:city":"Washington",
    "sg:classifiers":[
        {
            "category":"Building & Trades",
            "subcategory":"Cleaning & Sanitation",
            "type":"Services"
        }
    ],
    "sg:phone":"+1 309 745 3648",
    "sg:postcode":"61571",
    "sg:province":"IL",
    "sg:tags":[
        "janitorial"
    ],
    "sg:website":"http://www.ingoliasjanitorservice.com",
    "wof:name":"Ingolia's Janitor Service & Supplies Inc",
    "wof:placetype":"venue"
},
  "geometry": {"coordinates":[-89.48240699999999,40.68745],"type":"Point"}
}