{
  "type": "Feature",
  "properties": {
    "iso:country":"US",
    "sg:address":"22240 Governors Hwy",
    "sg:city":"Richton Park",
    "sg:classifiers":[
        {
            "category":"Food & Beverages",
            "subcategory":"Groceries & Convenience Stores",
            "type":"Retail Goods"
        }
    ],
    "sg:phone":"+1   ",
    "sg:postcode":"60471",
    "sg:province":"IL",
    "wof:name":"Valley Fresh Market Inc",
    "wof:placetype":"venue"
},
  "geometry": {"coordinates":[-87.712888,41.485396],"type":"Point"}
}