{
  "type": "Feature",
  "properties": {
    "addr:full":"3642 S Kedzie Avenue Chicago IL 60632",
    "addr:housenumber":"3642",
    "addr:postcode":"60632",
    "addr:street":"S Kedzie Avenue",
    "iso:country":"US",
    "sg:address":"3642 S Kedzie Avenue",
    "sg:city":"Chicago",
    "sg:classifiers":[
        {
            "category":"Food & Beverages",
            "subcategory":"Candy",
            "type":"Retail Goods"
        }
    ],
    "sg:phone":"+1 773 843 1905",
    "sg:postcode":"60632",
    "sg:province":"IL",
    "sg:tags":[
        "store"
    ],
    "wof:name":"Royal Candy and Nut Company",
    "wof:placetype":"venue"
},
  "geometry": {"coordinates":[-87.70465799999999,41.827352],"type":"Point"}
}