{
  "type": "Feature",
  "properties": {
    "iso:country":"US",
    "sg:address":"3242 W Foster Ave",
    "sg:city":"Chicago",
    "sg:classifiers":[
        {
            "category":"Insurance",
            "subcategory":"Health Insurance",
            "type":"Services"
        }
    ],
    "sg:phone":"+1 773 267 0808",
    "sg:postcode":"60625",
    "sg:province":"IL",
    "sg:tags":[
        "market"
    ],
    "wof:name":"Leo Naturals",
    "wof:placetype":"venue"
},
  "geometry": {"coordinates":[-87.710297,41.9758],"type":"Point"}
}