{
  "type": "Feature",
  "properties": {
    "iso:country":"US",
    "sg:address":"2607 Chestnut St",
    "sg:city":"Quincy",
    "sg:classifiers":[
        {
            "category":"Building & Trades",
            "subcategory":"Landscaping Services",
            "type":"Services"
        }
    ],
    "sg:phone":"+1 217 224 0649",
    "sg:postcode":"62301",
    "sg:province":"IL",
    "sg:tags":[
        "tree"
    ],
    "wof:name":"Mathews Tree Service",
    "wof:placetype":"venue"
},
  "geometry": {"coordinates":[-91.374256,39.942791],"type":"Point"}
}