{
  "type": "Feature",
  "properties": {
    "iso:country":"US",
    "sg:address":"513 Phelps Ave",
    "sg:city":"Rockford",
    "sg:classifiers":[
        {
            "category":"Social Services",
            "subcategory":"Child Care",
            "type":"Services"
        }
    ],
    "sg:phone":"+1 815 229 3513",
    "sg:postcode":"61108",
    "sg:province":"IL",
    "wof:name":"New Horizons Day Care",
    "wof:placetype":"venue"
},
  "geometry": {"coordinates":[-89.004835,42.266088],"type":"Point"}
}