{
  "type": "Feature",
  "properties": {
    "addr:full":"180 N Jefferson Street Unit 2303 Chicago IL 60661",
    "addr:housenumber":"180;2303",
    "addr:postcode":"60661",
    "addr:street":"N Jefferson Street",
    "iso:country":"US",
    "sg:address":"180 N Jefferson Street Unit 2303",
    "sg:city":"Chicago",
    "sg:classifiers":[
        {
            "category":"Real Estate",
            "subcategory":"Real Estate Operator",
            "type":"Services"
        }
    ],
    "sg:phone":"+1 312 207 1500",
    "sg:postcode":"60661",
    "sg:province":"IL",
    "sg:tags":[
        "apartment"
    ],
    "wof:name":"180 N Jefferson",
    "wof:placetype":"venue"
},
  "geometry": {"coordinates":[-87.64277,41.885564],"type":"Point"}
}