{
  "type": "Feature",
  "properties": {
    "iso:country":"US",
    "sg:address":"1909 W 103rd St",
    "sg:city":"Chicago",
    "sg:classifiers":[
        {
            "category":"Shopping",
            "subcategory":"Gifts & Souvenirs",
            "type":"Retail Goods"
        }
    ],
    "sg:phone":"+1   ",
    "sg:postcode":"60643",
    "sg:province":"IL",
    "wof:name":"Simply Stated",
    "wof:placetype":"venue"
},
  "geometry": {"coordinates":[-87.670505,41.706489],"type":"Point"}
}