{
  "type": "Feature",
  "properties": {
    "iso:country":"US",
    "sg:address":"10000 Woodward Ave",
    "sg:city":"Woodridge",
    "sg:phone":"+1 630 972 1640",
    "sg:postcode":"60517",
    "sg:province":"IL",
    "sg:website":"http://www.amctheatres.com",
    "wof:name":"AMC Loews Woodridge 18",
    "wof:placetype":"venue"
},
  "geometry": {"coordinates":[-88.021584,41.703331],"type":"Point"}
}