{
  "type": "Feature",
  "properties": {
    "iso:country":"US",
    "sg:address":"5688 Northridge Dr",
    "sg:city":"Gurnee",
    "sg:phone":"+1 847 662 7600",
    "sg:postcode":"60031",
    "sg:province":"IL",
    "sg:website":"http://redirect.searchignite.com/si/cm/tracking/DGTrackingRedirect.aspx?siclientid=2537&siredirect=http://www.lq.com/lq/properties/propertyProfile.do%3Fident%3DLQ1016%26IATA%3D99020726%26WT.srch%3D1&sisearchengine=155&siproduct=LQ+Chicago+Gurnee",
    "wof:name":"La Quinta Inn & Suites Chicago - Gurnee",
    "wof:placetype":"venue"
},
  "geometry": {"coordinates":[-87.94309800000001,42.37816],"type":"Point"}
}