{
  "type": "Feature",
  "properties": {
    "addr:full":"328 S Johnson St Macomb IL 61455",
    "addr:housenumber":"328",
    "addr:postcode":"61455",
    "addr:street":"S Johnson St",
    "iso:country":"US",
    "sg:address":"328 S Johnson St",
    "sg:city":"Macomb",
    "sg:classifiers":[
        {
            "category":"Professional",
            "subcategory":"Computer Services",
            "type":"Services"
        }
    ],
    "sg:phone":"+1 309 333 1500",
    "sg:postcode":"61455",
    "sg:province":"IL",
    "sg:tags":[
        "related"
    ],
    "wof:name":"One Web Place",
    "wof:placetype":"venue"
},
  "geometry": {"coordinates":[-90.674914,40.45608],"type":"Point"}
}