{
  "type": "Feature",
  "properties": {
    "iso:country":"US",
    "sg:address":"7642 N Oleander Ave",
    "sg:city":"Niles",
    "sg:classifiers":[
        {
            "category":"Professional",
            "subcategory":"Management & Consulting",
            "type":"Services"
        },
        {
            "category":"Banks & Credit Unions",
            "subcategory":"Financial Services",
            "type":"Services"
        }
    ],
    "sg:phone":"+1 847 966 2243",
    "sg:postcode":"60714",
    "sg:province":"IL",
    "sg:tags":[
        "consultant",
        "financing",
        "planning"
    ],
    "wof:name":"Prowealth(Tm)",
    "wof:placetype":"venue"
},
  "geometry": {"coordinates":[-87.815083,42.019543],"type":"Point"}
}