{
  "type": "Feature",
  "properties": {
    "iso:country":"US",
    "sg:address":"1144 W Fulton Market # 100",
    "sg:city":"Chicago",
    "sg:classifiers":[
        {
            "category":"Manufacturing",
            "subcategory":"Buildings",
            "type":"Manufacturing & Wholesale Goods"
        },
        {
            "category":"Building & Trades",
            "subcategory":"Construction",
            "type":"Services"
        }
    ],
    "sg:phone":"+1 312 829 1144",
    "sg:postcode":"60607",
    "sg:province":"IL",
    "sg:tags":[
        "industrial",
        "altering",
        "builder",
        "contractor",
        "contractors-commercial",
        "home",
        "remodeling"
    ],
    "wof:name":"Prairie Construction Group, Inc",
    "wof:placetype":"venue"
},
  "geometry": {"coordinates":[-87.655914,41.886687],"type":"Point"}
}