{
  "type": "Feature",
  "properties": {
    "addr:full":"2390 Legends Ct Deerfield IL 60015",
    "addr:housenumber":"2390",
    "addr:postcode":"60015",
    "addr:street":"Legends Ct",
    "iso:country":"US",
    "sg:address":"2390 Legends Ct",
    "sg:city":"Deerfield",
    "sg:classifiers":[
        {
            "category":"Real Estate",
            "subcategory":"Real Estate Operator",
            "type":"Services"
        }
    ],
    "sg:phone":"+1 847 606 9226",
    "sg:postcode":"60015",
    "sg:province":"IL",
    "sg:tags":[
        "building",
        "apartment"
    ],
    "wof:name":"Allegro Apts LLC",
    "wof:placetype":"venue"
},
  "geometry": {"coordinates":[-87.88619,42.160032],"type":"Point"}
}