{
  "type": "Feature",
  "properties": {
    "iso:country":"US",
    "sg:address":"3574 Milwaukee Ave",
    "sg:city":"Northbrook",
    "sg:classifiers":[
        {
            "category":"Personal",
            "subcategory":"Beauty Salon",
            "type":"Services"
        }
    ],
    "sg:phone":"+1 847 299 4546",
    "sg:postcode":"60062",
    "sg:province":"IL",
    "sg:tags":[
        "shop"
    ],
    "wof:name":"Unique Wave Hair Salon",
    "wof:placetype":"venue"
},
  "geometry": {"coordinates":[-87.872676,42.089444],"type":"Point"}
}