{
  "type": "Feature",
  "properties": {
    "iso:country":"US",
    "sg:address":"28841 W Roberts Rd",
    "sg:city":"Barrington",
    "sg:classifiers":[
        {
            "category":"Retail",
            "subcategory":"Auto Repair",
            "type":"Services"
        }
    ],
    "sg:phone":"+1   ",
    "sg:postcode":"60010",
    "sg:province":"IL",
    "sg:tags":[
        "automotive",
        "gasoline"
    ],
    "wof:name":"Snyder Service",
    "wof:placetype":"venue"
},
  "geometry": {"coordinates":[-88.196012,42.248779],"type":"Point"}
}