{
  "type": "Feature",
  "properties": {
    "addr:full":"1356 E 2900N Rd Clifton IL 60927",
    "addr:housenumber":"1356",
    "addr:postcode":"60927",
    "addr:street":"E 2900N Rd",
    "iso:country":"US",
    "sg:address":"1356 E 2900N Rd",
    "sg:city":"Clifton",
    "sg:phone":"+1 815 694 2666",
    "sg:postcode":"60927",
    "sg:province":"IL",
    "sg:tags":[
        "farm",
        "corn",
        "soybean"
    ],
    "wof:name":"Cnudde Merton",
    "wof:placetype":"venue"
},
  "geometry": {"coordinates":[-87.867932,40.930975],"type":"Point"}
}