{
  "type": "Feature",
  "properties": {
    "iso:country":"US",
    "sg:address":"13909 W Eagle Point Rd",
    "sg:city":"Polo",
    "sg:classifiers":[
        {
            "category":"Farming",
            "subcategory":"Livestock Farm",
            "type":"Manufacturing & Wholesale Goods"
        }
    ],
    "sg:phone":"+1 815 946 2062",
    "sg:postcode":"61064",
    "sg:province":"IL",
    "sg:tags":[
        "hog",
        "corn",
        "or",
        "feedlot"
    ],
    "wof:name":"Dave Sherrick",
    "wof:placetype":"venue"
},
  "geometry": {"coordinates":[-89.611344,41.991183],"type":"Point"}
}