{
  "type": "Feature",
  "properties": {
    "addr:full":"1323 W Main St Belleville IL 62220",
    "addr:housenumber":"1323",
    "addr:postcode":"62220",
    "addr:street":"W Main St",
    "iso:country":"US",
    "sg:address":"1323 W Main St",
    "sg:city":"Belleville",
    "sg:classifiers":[
        {
            "category":"Shopping",
            "subcategory":"Used Merchandise",
            "type":"Retail Goods"
        }
    ],
    "sg:phone":"+1 618 239 6574",
    "sg:postcode":"62220",
    "sg:province":"IL",
    "sg:tags":[
        "shop",
        "consignment"
    ],
    "wof:name":"Trunks Housewares & Cllctbls",
    "wof:placetype":"venue"
},
  "geometry": {"coordinates":[-89.99987400000001,38.516619],"type":"Point"}
}