{
  "type": "Feature",
  "properties": {
    "addr:full":"1312 Marquette Dr Romeoville IL 60446",
    "addr:housenumber":"1312",
    "addr:postcode":"60446",
    "addr:street":"Marquette Dr",
    "iso:country":"US",
    "sg:address":"1312 Marquette Dr",
    "sg:city":"Romeoville",
    "sg:classifiers":[
        {
            "category":"Health Services",
            "subcategory":"Optometrist",
            "type":"Services"
        }
    ],
    "sg:phone":"+1 630 759 7666",
    "sg:postcode":"60446",
    "sg:province":"IL",
    "sg:tags":[
        "good",
        "optical"
    ],
    "wof:name":"Lombart-Midwest Instruments",
    "wof:placetype":"venue"
},
  "geometry": {"coordinates":[-88.06949400000001,41.671686],"type":"Point"}
}