{
  "type": "Feature",
  "properties": {
    "addr:full":"34 N Bennett St Geneva IL 60134",
    "addr:housenumber":"34",
    "addr:postcode":"60134",
    "addr:street":"N Bennett St",
    "iso:country":"US",
    "sg:address":"34 N Bennett St",
    "sg:city":"Geneva",
    "sg:classifiers":[
        {
            "category":"Recreation",
            "type":"Entertainment"
        }
    ],
    "sg:phone":"+1 630 232 0320",
    "sg:postcode":"60134",
    "sg:province":"IL",
    "sg:tags":[
        "amusement"
    ],
    "wof:name":"Geneva Kayak Ctr",
    "wof:placetype":"venue"
},
  "geometry": {"coordinates":[-88.30043499999999,41.886953],"type":"Point"}
}