{
  "type": "Feature",
  "properties": {
    "iso:country":"US",
    "sg:address":"501 N Grove St",
    "sg:city":"Waverly",
    "sg:classifiers":[
        {
            "category":"Home & Garden",
            "subcategory":"Garden Supply",
            "type":"Retail Goods"
        }
    ],
    "sg:phone":"+1 217 435 5241",
    "sg:postcode":"62692",
    "sg:province":"IL",
    "sg:tags":[
        "fertilizer"
    ],
    "wof:name":"Brandt Consolidated Inc",
    "wof:placetype":"venue"
},
  "geometry": {"coordinates":[-89.951532,39.594916],"type":"Point"}
}