{
  "type": "Feature",
  "properties": {
    "iso:country":"US",
    "sg:address":"4909 W Division Street",
    "sg:city":"Chicago",
    "sg:classifiers":[
        {
            "category":"Community Center",
            "type":"Public Place"
        }
    ],
    "sg:phone":"+1 773 921 8100",
    "sg:postcode":"60651",
    "sg:province":"IL",
    "sg:tags":[
        "medical"
    ],
    "sg:website":"www.cfhcn.org",
    "wof:name":"Chicago City of",
    "wof:placetype":"venue"
},
  "geometry": {"coordinates":[-87.74853299999999,41.90222],"type":"Point"}
}