{
  "type": "Feature",
  "properties": {
    "iso:country":"US",
    "sg:address":"91 N Randall Rd",
    "sg:city":"Lake In the Hills",
    "sg:classifiers":[
        {
            "category":"Insurance",
            "subcategory":"Health Insurance",
            "type":"Services"
        }
    ],
    "sg:phone":"+1 847 458 7200",
    "sg:postcode":"60156",
    "sg:province":"IL",
    "sg:tags":[
        "market"
    ],
    "sg:website":"www.gnc.com",
    "wof:name":"General Nutrition Center",
    "wof:placetype":"venue"
},
  "geometry": {"coordinates":[-88.335503,42.178299],"type":"Point"}
}