{
  "type": "Feature",
  "properties": {
    "addr:full":"14124 S Bell Rd Homer Glen IL 60491",
    "addr:housenumber":"14124",
    "addr:postcode":"60491",
    "addr:street":"S Bell Rd",
    "iso:country":"US",
    "sg:address":"14124 S Bell Rd",
    "sg:city":"Homer Glen",
    "sg:classifiers":[
        {
            "category":"Restaurant",
            "type":"Food & Drink"
        }
    ],
    "sg:phone":"+1 708 301 4950",
    "sg:postcode":"60491",
    "sg:province":"IL",
    "sg:tags":[
        "shop",
        "coffee"
    ],
    "wof:name":"Starbucks",
    "wof:placetype":"venue"
},
  "geometry": {"coordinates":[-87.931173,41.630589],"type":"Point"}
}