{
  "type": "Feature",
  "properties": {
    "addr:full":"6203 Material Ave Loves Park IL 61111",
    "addr:postcode":"6203;61111",
    "addr:street":"Material Ave",
    "iso:country":"US",
    "sg:address":"6203 Material Ave",
    "sg:city":"Loves Park",
    "sg:classifiers":[
        {
            "category":"Retail",
            "subcategory":"Animal Services",
            "type":"Services"
        }
    ],
    "sg:phone":"+1 815 633 2350",
    "sg:postcode":"61111",
    "sg:province":"IL",
    "sg:tags":[
        "pet",
        "training"
    ],
    "wof:name":"Forest City Dog Training Club",
    "wof:placetype":"venue"
},
  "geometry": {"coordinates":[-89.038028,42.322188],"type":"Point"}
}