{
  "type": "Feature",
  "properties": {
    "iso:country":"US",
    "sg:address":"1000 N Halsted St Ste 204",
    "sg:city":"Chicago",
    "sg:classifiers":[
        {
            "category":"Professional",
            "subcategory":"Business Services",
            "type":"Services"
        },
        {
            "category":"Real Estate",
            "subcategory":"Architect",
            "type":"Services"
        }
    ],
    "sg:phone":"+1 312 649 1650",
    "sg:postcode":"60642",
    "sg:province":"IL",
    "sg:tags":[
        "architects'",
        "development",
        "product",
        "designers-industrial",
        "marketing",
        "specification",
        "commercial",
        "builders'",
        "construction",
        "design",
        "architectural"
    ],
    "wof:name":"Johnson Design Group, Inc.",
    "wof:placetype":"venue"
},
  "geometry": {"coordinates":[-87.647919,41.899899],"type":"Point"}
}