{
  "type": "Feature",
  "properties": {
    "addr:full":"6116 N Western Ave Chicago IL 60659",
    "addr:housenumber":"6116",
    "addr:postcode":"60659",
    "addr:street":"N Western Ave",
    "iso:country":"US",
    "sg:address":"6116 N Western Ave",
    "sg:city":"Chicago",
    "sg:classifiers":[
        {
            "category":"Autos & Motor Vehicles",
            "subcategory":"Automobile Sales",
            "type":"Retail Goods"
        }
    ],
    "sg:phone":"+1 773 508 5800",
    "sg:postcode":"60659",
    "sg:province":"IL",
    "sg:tags":[
        "car",
        "dealer"
    ],
    "wof:name":"Champion Dodge KIA Of Chicago",
    "wof:placetype":"venue"
},
  "geometry": {"coordinates":[-87.689832,41.993793],"type":"Point"}
}