{
  "type": "Feature",
  "properties": {
    "addr:full":"3321 W Riverside Blvd Rockford IL 61101",
    "addr:housenumber":"3321",
    "addr:postcode":"61101",
    "addr:street":"W Riverside Blvd",
    "iso:country":"US",
    "sg:address":"3321 W Riverside Blvd",
    "sg:city":"Rockford",
    "sg:classifiers":[
        {
            "category":"Social Services",
            "subcategory":"Adult Care",
            "type":"Services"
        }
    ],
    "sg:phone":"+1 815 636 4422",
    "sg:postcode":"61101",
    "sg:province":"IL",
    "sg:tags":[
        "home",
        "group"
    ],
    "wof:name":"Milestone Inc",
    "wof:placetype":"venue"
},
  "geometry": {"coordinates":[-89.10471800000001,42.315671],"type":"Point"}
}