{
  "type": "Feature",
  "properties": {
    "iso:country":"US",
    "sg:address":"216 S Jefferson St",
    "sg:city":"Chicago",
    "sg:classifiers":[
        {
            "category":"Professional",
            "subcategory":"Engineering",
            "type":"Services"
        }
    ],
    "sg:phone":"+1 312 466 1540",
    "sg:postcode":"60661",
    "sg:province":"IL",
    "sg:tags":[
        "consulting",
        "engineer"
    ],
    "wof:name":"Power Engineer Collaborative",
    "wof:placetype":"venue"
},
  "geometry": {"coordinates":[-87.642546,41.878771],"type":"Point"}
}