{
  "type": "Feature",
  "properties": {
    "iso:country":"US",
    "sg:address":"106 N Front St",
    "sg:city":"Cobden",
    "sg:classifiers":[
        {
            "category":"Bars & Pubs",
            "type":"Food & Drink"
        }
    ],
    "sg:phone":"+1 618 893 2814",
    "sg:postcode":"62901",
    "sg:province":"IL",
    "sg:tags":[
        "tavern"
    ],
    "wof:name":"Fuzzy's Tavern",
    "wof:placetype":"venue"
},
  "geometry": {"coordinates":[-89.253475,37.533049],"type":"Point"}
}