{
  "type": "Feature",
  "properties": {
    "iso:country":"US",
    "sg:address":"38580 Chicago Ave",
    "sg:city":"Wadsworth",
    "sg:classifiers":[
        {
            "category":"Food & Beverages",
            "subcategory":"Specialty",
            "type":"Retail Goods"
        }
    ],
    "sg:phone":"+1 847 599 8760",
    "sg:postcode":"60083",
    "sg:province":"IL",
    "sg:tags":[
        "equipment",
        "coffee",
        "handling",
        "roasting"
    ],
    "wof:name":"Dupre Denice",
    "wof:placetype":"venue"
},
  "geometry": {"coordinates":[-87.923697,42.422672],"type":"Point"}
}