{
  "type": "Feature",
  "properties": {
    "addr:full":"200 N Dearborn St Unit 4006 Chicago IL 60601",
    "addr:housenumber":"200",
    "addr:postcode":"60601",
    "addr:street":"N Dearborn St Unit 4006",
    "iso:country":"US",
    "sg:address":"200 N Dearborn St Unit 4006",
    "sg:city":"Chicago",
    "sg:classifiers":[
        {
            "category":"Professional",
            "subcategory":"Employment Agencies",
            "type":"Services"
        }
    ],
    "sg:phone":"+1 312 201 1171",
    "sg:postcode":"60601",
    "sg:province":"IL",
    "wof:name":"Wordspeed Inc",
    "wof:placetype":"venue"
},
  "geometry": {"coordinates":[-87.629542,41.886276],"type":"Point"}
}