{
  "type": "Feature",
  "properties": {
    "iso:country":"US",
    "sg:address":"12350 S 114th Ave",
    "sg:city":"Palos Park",
    "sg:classifiers":[
        {
            "category":"Shopping",
            "subcategory":"Gifts & Souvenirs",
            "type":"Retail Goods"
        }
    ],
    "sg:phone":"+1   ",
    "sg:postcode":"60464",
    "sg:province":"IL",
    "wof:name":"It All About Plaisure Ltd",
    "wof:placetype":"venue"
},
  "geometry": {"coordinates":[-87.898161,41.665889],"type":"Point"}
}