{
  "type": "Feature",
  "properties": {
    "iso:country":"US",
    "sg:address":"10890 Lincoln Trl",
    "sg:city":"Fairview Heights",
    "sg:classifiers":[
        {
            "category":"Utilities",
            "subcategory":"Mobile Phone",
            "type":"Services"
        }
    ],
    "sg:phone":"+1 618 397 4700",
    "sg:postcode":"62208",
    "sg:province":"IL",
    "sg:tags":[
        "communication",
        "telephone",
        "cellular",
        "radiotelephone"
    ],
    "sg:website":"www.cingular.com",
    "wof:name":"Cingular Wireless LLC",
    "wof:placetype":"venue"
},
  "geometry": {"coordinates":[-89.988082,38.592721],"type":"Point"}
}