{
  "type": "Feature",
  "properties": {
    "addr:full":"1031 W Bryn Mawr Ave Chicago IL 60660",
    "addr:housenumber":"1031",
    "addr:postcode":"60660",
    "addr:street":"W Bryn Mawr Ave",
    "iso:country":"US",
    "sg:address":"1031 W Bryn Mawr Ave",
    "sg:city":"Chicago",
    "sg:classifiers":[
        {
            "category":"Professional",
            "subcategory":"Business Services",
            "type":"Services"
        }
    ],
    "sg:phone":"+1 773 728 6380",
    "sg:postcode":"60660",
    "sg:province":"IL",
    "sg:tags":[
        "interior",
        "design"
    ],
    "wof:name":"Smithfield Associates",
    "wof:placetype":"venue"
},
  "geometry": {"coordinates":[-87.656502,41.983601],"type":"Point"}
}