{
  "type": "Feature",
  "properties": {
    "addr:full":"158 N Chicago St Joliet IL 60432",
    "addr:housenumber":"158",
    "addr:postcode":"60432",
    "addr:street":"N Chicago St",
    "iso:country":"US",
    "sg:address":"158 N Chicago St",
    "sg:city":"Joliet",
    "sg:classifiers":[
        {
            "category":"Restaurant",
            "type":"Food & Drink"
        }
    ],
    "sg:phone":"+1 815 722 1744",
    "sg:postcode":"60432",
    "sg:province":"IL",
    "wof:name":"Barolo Restaurant",
    "wof:placetype":"venue"
},
  "geometry": {"coordinates":[-88.081608,41.527662],"type":"Point"}
}