{
  "type": "Feature",
  "properties": {
    "addr:full":"640 W Irving Park Road Chicago IL 60613",
    "addr:housenumber":"640",
    "addr:postcode":"60613",
    "addr:street":"W Irving Park Road",
    "iso:country":"US",
    "sg:address":"640 W Irving Park Road",
    "sg:city":"Chicago",
    "sg:classifiers":[
        {
            "category":"Education",
            "subcategory":"School",
            "type":"Public Place"
        }
    ],
    "sg:phone":"+1 773 935 9925",
    "sg:postcode":"60613",
    "sg:province":"IL",
    "sg:tags":[
        "high",
        "middle",
        "elementary"
    ],
    "wof:name":"Prologue Alternative High School",
    "wof:placetype":"venue"
},
  "geometry": {"coordinates":[-87.64664999999999,41.954712],"type":"Point"}
}