{
  "type": "Feature",
  "properties": {
    "iso:country":"US",
    "sg:address":"8417 Latrobe Ave",
    "sg:city":"Skokie",
    "sg:classifiers":[
        {
            "category":"Building & Trades",
            "subcategory":"Construction",
            "type":"Services"
        }
    ],
    "sg:phone":"+1 847 676 3703",
    "sg:postcode":"60077",
    "sg:province":"IL",
    "sg:tags":[
        "system",
        "contractor",
        "air conditioning"
    ],
    "wof:name":"U S Air Flow Systems Co",
    "wof:placetype":"venue"
},
  "geometry": {"coordinates":[-87.75825399999999,42.033968],"type":"Point"}
}