{
  "type": "Feature",
  "properties": {
    "addr:full":"363 Aaron Ln Bolingbrook IL 60440",
    "addr:housenumber":"363",
    "addr:postcode":"60440",
    "addr:street":"Aaron Ln",
    "iso:country":"US",
    "sg:address":"363 Aaron Ln",
    "sg:city":"Bolingbrook",
    "sg:classifiers":[
        {
            "category":"Professional",
            "subcategory":"Management & Consulting",
            "type":"Services"
        }
    ],
    "sg:phone":"+1 630 783 0020",
    "sg:postcode":"60440",
    "sg:province":"IL",
    "sg:tags":[
        "consultant",
        "engineering"
    ],
    "wof:name":"Edes Converting Inc",
    "wof:placetype":"venue"
},
  "geometry": {"coordinates":[-88.055012,41.715715],"type":"Point"}
}