{
  "type": "Feature",
  "properties": {
    "iso:country":"US",
    "sg:address":"16 Dogwood Dr",
    "sg:city":"Bristol",
    "sg:classifiers":[
        {
            "category":"Local Transit",
            "type":"Transportation"
        }
    ],
    "sg:phone":"+1 630 553 6644",
    "sg:postcode":"60512",
    "sg:province":"IL",
    "sg:tags":[
        "limousine"
    ],
    "wof:name":"United Limousine",
    "wof:placetype":"venue"
},
  "geometry": {"coordinates":[-88.407386,41.705404],"type":"Point"}
}