{
  "type": "Feature",
  "properties": {
    "iso:country":"US",
    "sg:address":"1020 Nerge Rd",
    "sg:city":"Elk Grove Village",
    "sg:classifiers":[
        {
            "category":"Building & Trades",
            "subcategory":"Construction",
            "type":"Services"
        }
    ],
    "sg:phone":"+1 847 923 5600",
    "sg:postcode":"60007",
    "sg:province":"IL",
    "sg:tags":[
        "concrete",
        "contractor"
    ],
    "wof:name":"Litgen Cutting Supply",
    "wof:placetype":"venue"
},
  "geometry": {"coordinates":[-88.02826399999999,41.994465],"type":"Point"}
}