{
  "type": "Feature",
  "properties": {
    "iso:country":"US",
    "sg:address":"2408 Country Club Dr",
    "sg:city":"Springfield",
    "sg:classifiers":[
        {
            "category":"Professional",
            "subcategory":"Lawyer & Legal Services",
            "type":"Services"
        }
    ],
    "sg:phone":"+1 217 787 7451",
    "sg:postcode":"62704",
    "sg:province":"IL",
    "sg:tags":[
        "attorney",
        "practice"
    ],
    "wof:name":"Gary L Borah",
    "wof:placetype":"venue"
},
  "geometry": {"coordinates":[-89.697266,39.781692],"type":"Point"}
}