{
  "type": "Feature",
  "properties": {
    "addr:full":"1073 Paradise Acres Galesburg IL 61401",
    "addr:housenumber":"1073",
    "addr:postcode":"61401",
    "addr:street":"Paradise Acres",
    "iso:country":"US",
    "sg:address":"1073 Paradise Acres",
    "sg:city":"Galesburg",
    "sg:classifiers":[
        {
            "category":"Professional",
            "subcategory":"Accounting & Tax Preparation",
            "type":"Services"
        }
    ],
    "sg:phone":"+1 309 342 7723",
    "sg:postcode":"61401",
    "sg:province":"IL",
    "sg:tags":[
        "public",
        "accountants-certified"
    ],
    "wof:name":"Dale Blucker & Sandra A",
    "wof:placetype":"venue"
},
  "geometry": {"coordinates":[-90.362999,40.871375],"type":"Point"}
}