{
  "type": "Feature",
  "properties": {
    "iso:country":"US",
    "sg:address":"225 Canal St",
    "sg:city":"Lemont",
    "sg:classifiers":[
        {
            "category":"Home & Garden",
            "subcategory":"Hardware",
            "type":"Retail Goods"
        }
    ],
    "sg:phone":"+1 630 257 2258",
    "sg:postcode":"60439",
    "sg:province":"IL",
    "wof:name":"Arthur Peterson Inc",
    "wof:placetype":"venue"
},
  "geometry": {"coordinates":[-88.00075699999999,41.674445],"type":"Point"}
}