{
  "type": "Feature",
  "properties": {
    "addr:full":"1 N Halsted St Chicago IL 60661",
    "addr:housenumber":"1",
    "addr:postcode":"60661",
    "addr:street":"N Halsted St",
    "iso:country":"US",
    "sg:address":"1 N Halsted St",
    "sg:city":"Chicago",
    "sg:classifiers":[
        {
            "category":"Parking",
            "type":"Transportation"
        }
    ],
    "sg:phone":"+1 312 559 1845",
    "sg:postcode":"60661",
    "sg:province":"IL",
    "wof:name":"Skybridge",
    "wof:placetype":"venue"
},
  "geometry": {"coordinates":[-87.647499,41.882],"type":"Point"}
}