{
  "type": "Feature",
  "properties": {
    "iso:country":"US",
    "sg:address":"11817 N State Rte 2",
    "sg:city":"Rockford",
    "sg:classifiers":[
        {
            "category":"Real Estate",
            "subcategory":"Real Estate Operator",
            "type":"Services"
        }
    ],
    "sg:phone":"+1 815 967 0822",
    "sg:postcode":"61102",
    "sg:province":"IL",
    "sg:tags":[
        "building",
        "apartment"
    ],
    "wof:name":"Harry Schelling",
    "wof:placetype":"venue"
},
  "geometry": {"coordinates":[-89.175515,42.182373],"type":"Point"}
}