{
  "type": "Feature",
  "properties": {
    "iso:country":"US",
    "sg:address":"4300 Church Rd",
    "sg:city":"Alorton",
    "sg:classifiers":[
        {
            "category":"Freight",
            "type":"Transportation"
        }
    ],
    "sg:phone":"+1 618 271 5500",
    "sg:postcode":"62207",
    "sg:province":"IL",
    "sg:tags":[
        "warehouse",
        "self",
        "storage"
    ],
    "wof:name":"M J Resurrection",
    "wof:placetype":"venue"
},
  "geometry": {"coordinates":[-90.129003,38.575683],"type":"Point"}
}