{
  "type": "Feature",
  "properties": {
    "iso:country":"US",
    "sg:address":"626 George St",
    "sg:city":"Wood Dale",
    "sg:classifiers":[
        {
            "category":"Professional",
            "subcategory":"Business Services",
            "type":"Services"
        }
    ],
    "sg:phone":"+1 630 350 1677",
    "sg:postcode":"60191",
    "sg:province":"IL",
    "wof:name":"CK Express Inc",
    "wof:placetype":"venue"
},
  "geometry": {"coordinates":[-88.002143,41.963504],"type":"Point"}
}