{
  "type": "Feature",
  "properties": {
    "addr:full":"26481 W Grand Ave Ingleside IL 60041",
    "addr:housenumber":"26481",
    "addr:postcode":"60041",
    "addr:street":"W Grand Ave",
    "iso:country":"US",
    "sg:address":"26481 W Grand Ave",
    "sg:city":"Ingleside",
    "sg:classifiers":[
        {
            "category":"Manufacturing",
            "subcategory":"Tools & Machinery",
            "type":"Manufacturing & Wholesale Goods"
        }
    ],
    "sg:phone":"+1 847 587 2842",
    "sg:postcode":"60041",
    "sg:province":"IL",
    "sg:tags":[
        "industrial",
        "mfg"
    ],
    "wof:name":"Propaholics",
    "wof:placetype":"venue"
},
  "geometry": {"coordinates":[-88.148565,42.393992],"type":"Point"}
}