{
  "type": "Feature",
  "properties": {
    "addr:full":"404 Marquette Ave Cary IL 60013",
    "addr:housenumber":"404",
    "addr:postcode":"60013",
    "addr:street":"Marquette Ave",
    "iso:country":"US",
    "sg:address":"404 Marquette Ave",
    "sg:city":"Cary",
    "sg:classifiers":[
        {
            "category":"Personal",
            "type":"Services"
        }
    ],
    "sg:phone":"+1 847 639 8282",
    "sg:postcode":"60013",
    "sg:province":"IL",
    "wof:name":"Fox Valley Tattoo",
    "wof:placetype":"venue"
},
  "geometry": {"coordinates":[-88.228154,42.201167],"type":"Point"}
}