{
  "type": "Feature",
  "properties": {
    "addr:full":"1811 N Rockwell St Chicago IL 60647",
    "addr:housenumber":"1811",
    "addr:postcode":"60647",
    "addr:street":"N Rockwell St",
    "iso:country":"US",
    "sg:address":"1811 N Rockwell St",
    "sg:city":"Chicago",
    "sg:classifiers":[
        {
            "category":"Professional",
            "type":"Services"
        }
    ],
    "sg:phone":"+1 773 252 4001",
    "sg:postcode":"60647",
    "sg:province":"IL",
    "wof:name":"Demontech",
    "wof:placetype":"venue"
},
  "geometry": {"coordinates":[-87.692142,41.914505],"type":"Point"}
}