{
  "type": "Feature",
  "properties": {
    "addr:full":"731 N McAree Rd Waukegan IL 60085",
    "addr:housenumber":"731",
    "addr:postcode":"60085",
    "addr:street":"N Mcaree Rd",
    "iso:country":"US",
    "sg:address":"731 N McAree Rd",
    "sg:city":"Waukegan",
    "sg:classifiers":[
        {
            "category":"Personal",
            "subcategory":"Barber",
            "type":"Services"
        }
    ],
    "sg:phone":"+1 847 244 8287",
    "sg:postcode":"60085",
    "sg:province":"IL",
    "wof:name":"Cal's Barber Shop",
    "wof:placetype":"venue"
},
  "geometry": {"coordinates":[-87.865301,42.37104],"type":"Point"}
}