{
  "type": "Feature",
  "properties": {
    "iso:country":"US",
    "sg:address":"15520 E 300th Ave",
    "sg:city":"West Liberty",
    "sg:classifiers":[
        {
            "category":"Freight",
            "type":"Transportation"
        }
    ],
    "sg:phone":"+1 618 783 2184",
    "sg:postcode":"62475",
    "sg:province":"IL",
    "wof:name":"Urfer Transportation Inc",
    "wof:placetype":"venue"
},
  "geometry": {"coordinates":[-88.07733500000001,38.893035],"type":"Point"}
}