{
  "type": "Feature",
  "properties": {
    "iso:country":"US",
    "sg:address":"675 N North Ct",
    "sg:city":"Palatine",
    "sg:classifiers":[
        {
            "category":"Banks & Credit Unions",
            "subcategory":"Investment Brokerage",
            "type":"Services"
        }
    ],
    "sg:phone":"+1 847 359 7388",
    "sg:postcode":"60067",
    "sg:province":"IL",
    "sg:tags":[
        "advisory"
    ],
    "wof:name":"Axa Network",
    "wof:placetype":"venue"
},
  "geometry": {"coordinates":[-88.03828300000001,42.1218],"type":"Point"}
}