{
  "type": "Feature",
  "properties": {
    "iso:country":"US",
    "sg:address":"87 N Airlite St",
    "sg:city":"Elgin",
    "sg:classifiers":[
        {
            "category":"Health Services",
            "subcategory":"Doctor",
            "type":"Services"
        }
    ],
    "sg:phone":"+1 847 695 5333",
    "sg:postcode":"60123",
    "sg:province":"IL",
    "sg:tags":[
        "physician"
    ],
    "wof:name":"Cavallo Charles A MD",
    "wof:placetype":"venue"
},
  "geometry": {"coordinates":[-88.327825,42.036312],"type":"Point"}
}