{
  "type": "Feature",
  "properties": {
    "iso:country":"US",
    "sg:address":"3303 N 1800th St",
    "sg:city":"Dieterich",
    "sg:phone":"+1 217 739 2261",
    "sg:postcode":"62424",
    "sg:province":"IL",
    "sg:tags":[
        "farm",
        "corn",
        "soybean"
    ],
    "wof:name":"Lyle Ohnesorge",
    "wof:placetype":"venue"
},
  "geometry": {"coordinates":[-88.469268,38.961798],"type":"Point"}
}