{
  "type": "Feature",
  "properties": {
    "iso:country":"US",
    "sg:address":"12211 S Lagrange Rd",
    "sg:city":"Palos Hills",
    "sg:classifiers":[
        {
            "category":"Recreation",
            "type":"Entertainment"
        }
    ],
    "sg:phone":"+1 708 361 7977",
    "sg:postcode":"60465",
    "sg:province":"IL",
    "sg:tags":[
        "active",
        "life"
    ],
    "sg:website":"www.fitzjoyfarm.com",
    "wof:name":"Fitzjoy Farm Riding Academy",
    "wof:placetype":"venue"
},
  "geometry": {"coordinates":[-87.821899,41.699001],"type":"Point"}
}