{
  "type": "Feature",
  "properties": {
    "addr:full":"2342 N Clark St Chicago IL 60614",
    "addr:housenumber":"2342",
    "addr:postcode":"60614",
    "addr:street":"N Clark St",
    "iso:country":"US",
    "sg:address":"2342 N Clark St",
    "sg:city":"Chicago",
    "sg:classifiers":[
        {
            "category":"Shopping",
            "subcategory":"Pharmacy",
            "type":"Retail Goods"
        }
    ],
    "sg:phone":"+1 773 549 2720",
    "sg:postcode":"60614",
    "sg:province":"IL",
    "sg:tags":[
        "drugstore"
    ],
    "wof:name":"Parkway Drugs",
    "wof:placetype":"venue"
},
  "geometry": {"coordinates":[-87.640332,41.924739],"type":"Point"}
}