{
  "type": "Feature",
  "properties": {
    "iso:country":"US",
    "sg:address":"2001 5th St",
    "sg:city":"Silvis",
    "sg:classifiers":[
        {
            "category":"Banks & Credit Unions",
            "subcategory":"Bank",
            "type":"Services"
        }
    ],
    "sg:phone":"+1 309 792 0004",
    "sg:postcode":"61282",
    "sg:province":"IL",
    "wof:name":"Wells Fargo Bank Illinois Na",
    "wof:placetype":"venue"
},
  "geometry": {"coordinates":[-90.424896,41.493301],"type":"Point"}
}