{
  "type": "Feature",
  "properties": {
    "iso:country":"US",
    "sg:address":"520 N Michigan Ave",
    "sg:city":"Chicago",
    "sg:classifiers":[
        {
            "category":"Shopping",
            "subcategory":"Hobbies, Toys, & Games",
            "type":"Retail Goods"
        }
    ],
    "sg:phone":"+1 312 494 0760",
    "sg:postcode":"60611",
    "sg:province":"IL",
    "sg:tags":[
        "toy",
        "store"
    ],
    "wof:name":"Lego the Store",
    "wof:placetype":"venue"
},
  "geometry": {"coordinates":[-87.624298,41.891602],"type":"Point"}
}