{
  "type": "Feature",
  "properties": {
    "iso:country":"US",
    "sg:address":"20 E Russet Way",
    "sg:city":"Palatine",
    "sg:classifiers":[
        {
            "category":"Professional",
            "subcategory":"Computer Services",
            "type":"Services"
        }
    ],
    "sg:phone":"+1 847 358 8353",
    "sg:postcode":"60067",
    "sg:province":"IL",
    "sg:tags":[
        "design",
        "system"
    ],
    "wof:name":"Kk Engineering",
    "wof:placetype":"venue"
},
  "geometry": {"coordinates":[-88.038293,42.1289],"type":"Point"}
}