{
  "type": "Feature",
  "properties": {
    "iso:country":"US",
    "sg:address":"301 Warren St",
    "sg:city":"Campbell Hill",
    "sg:classifiers":[
        {
            "category":"Retail",
            "subcategory":"Funeral Services",
            "type":"Services"
        }
    ],
    "sg:phone":"+1 618 426 3122",
    "sg:postcode":"62906",
    "sg:province":"IL",
    "sg:tags":[
        "director"
    ],
    "wof:name":"Wilson's Funeral Homes",
    "wof:placetype":"venue"
},
  "geometry": {"coordinates":[-89.24775099999999,37.46795],"type":"Point"}
}