{
  "type": "Feature",
  "properties": {
    "iso:country":"US",
    "sg:address":"955 E Algonquin Rd",
    "sg:city":"Arlington Hts",
    "sg:classifiers":[
        {
            "category":"Wholesale",
            "subcategory":"Furniture",
            "type":"Manufacturing & Wholesale Goods"
        }
    ],
    "sg:phone":"+1 847 981 1451",
    "sg:postcode":"60005",
    "sg:province":"IL",
    "sg:website":"www.cort1.com",
    "wof:name":"Cort Furniture Rental",
    "wof:placetype":"venue"
},
  "geometry": {"coordinates":[-87.970612,42.039478],"type":"Point"}
}