{
  "type": "Feature",
  "properties": {
    "iso:country":"US",
    "sg:address":"265 N Jackson St",
    "sg:city":"Elgin",
    "sg:classifiers":[
        {
            "category":"Education",
            "subcategory":"School",
            "type":"Public Place"
        }
    ],
    "sg:phone":"+1 847 888 5199",
    "sg:postcode":"60123",
    "sg:province":"IL",
    "wof:name":"Grant Elementary School",
    "wof:placetype":"venue"
},
  "geometry": {"coordinates":[-88.29342,42.040138],"type":"Point"}
}