{
  "type": "Feature",
  "properties": {
    "iso:country":"US",
    "sg:address":"60 Revere Dr",
    "sg:city":"Northbrook",
    "sg:classifiers":[
        {
            "category":"Organizations",
            "subcategory":"Non-profit Organization",
            "type":"Services"
        }
    ],
    "sg:phone":"+1 847 656 8880",
    "sg:postcode":"60062",
    "sg:province":"IL",
    "sg:tags":[
        "social"
    ],
    "wof:name":"Jewish National Fund",
    "wof:placetype":"venue"
},
  "geometry": {"coordinates":[-87.80521899999999,42.150843],"type":"Point"}
}