{
  "type": "Feature",
  "properties": {
    "iso:country":"US",
    "sg:address":"622 Tay St",
    "sg:city":"Rockford",
    "sg:classifiers":[
        {
            "category":"Autos & Motor Vehicles",
            "subcategory":"Fuel & Gas Station",
            "type":"Retail Goods"
        }
    ],
    "sg:phone":"+1 815 965 6765",
    "sg:postcode":"61102",
    "sg:province":"IL",
    "sg:tags":[
        "oil"
    ],
    "wof:name":"Kelley Williamson Mobil",
    "wof:placetype":"venue"
},
  "geometry": {"coordinates":[-89.109743,42.269578],"type":"Point"}
}