{
  "type": "Feature",
  "properties": {
    "addr:full":"425 Huehl Rd Northbrook IL 60062",
    "addr:housenumber":"425",
    "addr:postcode":"60062",
    "addr:street":"Huehl Rd",
    "iso:country":"US",
    "sg:address":"425 Huehl Rd",
    "sg:city":"Northbrook",
    "sg:classifiers":[
        {
            "category":"Building & Trades",
            "subcategory":"Construction",
            "type":"Services"
        }
    ],
    "sg:phone":"+1 847 291 1512",
    "sg:postcode":"60062",
    "sg:province":"IL",
    "sg:tags":[
        "home",
        "contractor",
        "general",
        "new"
    ],
    "wof:name":"Court Gardent III Inc",
    "wof:placetype":"venue"
},
  "geometry": {"coordinates":[-87.86293000000001,42.145275],"type":"Point"}
}