{
  "type": "Feature",
  "properties": {
    "addr:full":"108 E Main St Industry IL 61440",
    "addr:housenumber":"108",
    "addr:postcode":"61440",
    "addr:street":"E Main St",
    "iso:country":"US",
    "sg:address":"108 E Main St",
    "sg:city":"Industry",
    "sg:classifiers":[
        {
            "category":"Food & Beverages",
            "subcategory":"Groceries & Convenience Stores",
            "type":"Retail Goods"
        }
    ],
    "sg:phone":"+1 309 254 3595",
    "sg:postcode":"61440",
    "sg:province":"IL",
    "wof:name":"Suzy-Q's Convenience Store",
    "wof:placetype":"venue"
},
  "geometry": {"coordinates":[-90.60714900000001,40.327597],"type":"Point"}
}