{
  "type": "Feature",
  "properties": {
    "addr:full":"19615 Governors Hwy Flossmoor IL 60422",
    "addr:housenumber":"19615",
    "addr:postcode":"60422",
    "addr:street":"Governors Hwy",
    "iso:country":"US",
    "sg:address":"19615 Governors Hwy",
    "sg:city":"Flossmoor",
    "sg:classifiers":[
        {
            "category":"Health Services",
            "subcategory":"Doctor",
            "type":"Services"
        },
        {
            "category":"Health Services",
            "subcategory":"Dentist",
            "type":"Services"
        }
    ],
    "sg:phone":"+1 708 647 6453",
    "sg:postcode":"60422",
    "sg:province":"IL",
    "sg:tags":[
        "dentists-oral",
        "physician",
        "maxillofacial",
        "denture",
        "dental",
        "surgeons",
        "dentists-prosthodontists",
        "clinic",
        "dentistry",
        "implant",
        "oral",
        "surgery",
        "dentists-orthodontists",
        "dentists-implantology"
    ],
    "sg:website":"http://www.flossmoordental.com",
    "wof:name":"Greenebaum, Charles J, Dds - Center For Dental Excellence",
    "wof:placetype":"venue"
},
  "geometry": {"coordinates":[-87.69607499999999,41.532584],"type":"Point"}
}