{
  "type": "Feature",
  "properties": {
    "iso:country":"US",
    "sg:address":"20W267 101st St",
    "sg:city":"Lemont",
    "sg:classifiers":[
        {
            "category":"Wholesale",
            "subcategory":"Office Equipment",
            "type":"Manufacturing & Wholesale Goods"
        },
        {
            "category":"Wholesale",
            "subcategory":"Machinery & Supplies",
            "type":"Manufacturing & Wholesale Goods"
        },
        {
            "category":"Wholesale",
            "subcategory":"Furniture",
            "type":"Manufacturing & Wholesale Goods"
        }
    ],
    "sg:phone":"+1 630 972 1266",
    "sg:postcode":"60439",
    "sg:province":"IL",
    "sg:tags":[
        "industrial",
        "furniture-wholesale",
        "manufacturer"
    ],
    "wof:name":"J & A Sales, Inc.",
    "wof:placetype":"venue"
},
  "geometry": {"coordinates":[-88.017735,41.70343],"type":"Point"}
}