{
  "type": "Feature",
  "properties": {
    "iso:country":"US",
    "sg:address":"205 Wheeler St",
    "sg:city":"Paw Paw",
    "sg:classifiers":[
        {
            "category":"Sports & Exercise",
            "subcategory":"Golf",
            "type":"Entertainment"
        }
    ],
    "sg:phone":"+1 815 627 9222",
    "sg:postcode":"61353",
    "sg:province":"IL",
    "sg:tags":[
        "course"
    ],
    "wof:name":"Trestle Creek Golf & Country",
    "wof:placetype":"venue"
},
  "geometry": {"coordinates":[-88.979697,41.685663],"type":"Point"}
}