{
  "type": "Feature",
  "properties": {
    "iso:country":"US",
    "sg:address":"807 W Williams St",
    "sg:city":"Danville",
    "sg:classifiers":[
        {
            "category":"Retail",
            "subcategory":"Photofinishing",
            "type":"Services"
        }
    ],
    "sg:phone":"+1   ",
    "sg:postcode":"61832",
    "sg:province":"IL",
    "sg:tags":[
        "photo",
        "finishing",
        "camera"
    ],
    "wof:name":"Cunningham Photo Service",
    "wof:placetype":"venue"
},
  "geometry": {"coordinates":[-87.641441,40.134014],"type":"Point"}
}