{
  "type": "Feature",
  "properties": {
    "addr:full":"1523 Elliott St Park Ridge IL 60068",
    "addr:housenumber":"1523",
    "addr:postcode":"60068",
    "addr:street":"Elliott St",
    "iso:country":"US",
    "sg:address":"1523 Elliott St",
    "sg:city":"Park Ridge",
    "sg:classifiers":[
        {
            "category":"Building & Trades",
            "subcategory":"Construction",
            "type":"Services"
        }
    ],
    "sg:phone":"+1 847 518 0231",
    "sg:postcode":"60068",
    "sg:province":"IL",
    "sg:tags":[
        "hanging",
        "contractor"
    ],
    "wof:name":"Wesleys Painting",
    "wof:placetype":"venue"
},
  "geometry": {"coordinates":[-87.86358300000001,42.035204],"type":"Point"}
}