{
  "type": "Feature",
  "properties": {
    "iso:country":"US",
    "sg:address":"1405 Walnut St",
    "sg:city":"Highland",
    "sg:classifiers":[
        {
            "category":"Wholesale",
            "subcategory":"Apparel",
            "type":"Manufacturing & Wholesale Goods"
        }
    ],
    "sg:phone":"+1 618 654 2113",
    "sg:postcode":"62249",
    "sg:province":"IL",
    "sg:tags":[
        "textile",
        "converting"
    ],
    "sg:website":"www.artex-int.com",
    "wof:name":"Artex International Inc",
    "wof:placetype":"venue"
},
  "geometry": {"coordinates":[-89.681428,38.736908],"type":"Point"}
}