{
  "type": "Feature",
  "properties": {
    "addr:full":"1422 W Willow St Chicago IL 60642",
    "addr:housenumber":"1422",
    "addr:postcode":"60642",
    "addr:street":"W Willow St",
    "iso:country":"US",
    "sg:address":"1422 W Willow St",
    "sg:city":"Chicago",
    "sg:classifiers":[
        {
            "category":"Transit Center",
            "subcategory":"Freight",
            "type":"Transportation"
        }
    ],
    "sg:phone":"+1 773 661 5044",
    "sg:postcode":"60642",
    "sg:province":"IL",
    "sg:tags":[
        "container",
        "broker"
    ],
    "sg:website":"http://www.clservicesinc.com",
    "wof:name":"C.L. Services, Inc.",
    "wof:placetype":"venue"
},
  "geometry": {"coordinates":[-87.662525,41.91452],"type":"Point"}
}