{
  "type": "Feature",
  "properties": {
    "iso:country":"US",
    "sg:address":"18329 State Hwy 1",
    "sg:city":"Hutsonville",
    "sg:classifiers":[
        {
            "category":"Real Estate",
            "subcategory":"Real Estate Operator",
            "type":"Services"
        }
    ],
    "sg:phone":"+1 618 563 4768",
    "sg:postcode":"62433",
    "sg:province":"IL",
    "sg:tags":[
        "property",
        "lessor"
    ],
    "wof:name":"Joe Griffith",
    "wof:placetype":"venue"
},
  "geometry": {"coordinates":[-87.681961,39.120615],"type":"Point"}
}