{
  "type": "Feature",
  "properties": {
    "addr:full":"800 Brickville Rd Sycamore IL 60178",
    "addr:housenumber":"800",
    "addr:postcode":"60178",
    "addr:street":"Brickville Rd",
    "iso:country":"US",
    "sg:address":"800 Brickville Rd",
    "sg:city":"Sycamore",
    "sg:classifiers":[
        {
            "category":"Autos & Motor Vehicles",
            "subcategory":"Automobile Sales",
            "type":"Retail Goods"
        },
        {
            "category":"Autos & Motor Vehicles",
            "subcategory":"Auto Supplies",
            "type":"Retail Goods"
        },
        {
            "category":"Utilities",
            "subcategory":"Recycling",
            "type":"Services"
        },
        {
            "category":"Wholesale",
            "subcategory":"Scrap",
            "type":"Manufacturing & Wholesale Goods"
        }
    ],
    "sg:phone":"+1 815 895 6744",
    "sg:postcode":"60178",
    "sg:province":"IL",
    "sg:tags":[
        "supplies-used",
        "rebuilt",
        "part",
        "metal",
        "salvage"
    ],
    "wof:name":"B & O Used Auto Parts",
    "wof:placetype":"venue"
},
  "geometry": {"coordinates":[-88.68937699999999,41.998662],"type":"Point"}
}