{
  "type": "Feature",
  "properties": {
    "addr:full":"1650 Lake Cook Rd Deerfield IL 60015",
    "addr:housenumber":"1650",
    "addr:postcode":"60015",
    "addr:street":"Lake Cook Rd",
    "iso:country":"US",
    "sg:address":"1650 Lake Cook Rd",
    "sg:city":"Deerfield",
    "sg:classifiers":[
        {
            "category":"Manufacturing",
            "subcategory":"Paper Products",
            "type":"Manufacturing & Wholesale Goods"
        }
    ],
    "sg:phone":"+1 847 317 5000",
    "sg:postcode":"60015",
    "sg:province":"IL",
    "sg:tags":[
        "consumer",
        "marketer",
        "mfg"
    ],
    "wof:name":"Fort James Corporation",
    "wof:placetype":"venue"
},
  "geometry": {"coordinates":[-87.870102,42.153014],"type":"Point"}
}