{
  "type": "Feature",
  "properties": {
    "iso:country":"US",
    "sg:address":"250 N Monroe St",
    "sg:city":"Rushville",
    "sg:classifiers":[
        {
            "category":"Social Services",
            "subcategory":"Adult Care",
            "type":"Services"
        },
        {
            "category":"Social Services",
            "type":"Services"
        }
    ],
    "sg:phone":"+1 217 322 6430",
    "sg:postcode":"62681",
    "sg:province":"IL",
    "sg:tags":[
        "organization",
        "senior",
        "citizen"
    ],
    "wof:name":"Senior Citizens Schuyler Cnty",
    "wof:placetype":"venue"
},
  "geometry": {"coordinates":[-90.565094,40.12301],"type":"Point"}
}