{
  "type": "Feature",
  "properties": {
    "iso:country":"US",
    "sg:address":"100 7th Pl",
    "sg:city":"Geneva",
    "sg:classifiers":[
        {
            "category":"Professional",
            "subcategory":"Computer Services",
            "type":"Services"
        }
    ],
    "sg:phone":"+1 630 232 0631",
    "sg:postcode":"60134",
    "sg:province":"IL",
    "sg:tags":[
        "consultant",
        "designer"
    ],
    "sg:website":"www.ewfoster.com",
    "wof:name":"Edward Foster & Co",
    "wof:placetype":"venue"
},
  "geometry": {"coordinates":[-88.313863,41.887611],"type":"Point"}
}