{
  "type": "Feature",
  "properties": {
    "addr:full":"222 Merchandise Mart Plz Chicago IL 60654",
    "addr:housenumber":"222",
    "addr:postcode":"60654",
    "addr:street":"Merchandise Mart Plz",
    "iso:country":"US",
    "sg:address":"222 Merchandise Mart Plz",
    "sg:city":"Chicago",
    "sg:classifiers":[
        {
            "category":"Restaurant",
            "type":"Food & Drink"
        }
    ],
    "sg:menulink":"http://www.allmenus.com/il/chicago/268679-bluprint/menu/",
    "sg:phone":"+1 312 410 9800",
    "sg:postcode":"60654",
    "sg:province":"IL",
    "sg:tags":[
        "american"
    ],
    "wof:name":"bluprint",
    "wof:placetype":"venue"
},
  "geometry": {"coordinates":[-87.635392,41.887901],"type":"Point"}
}