{
  "type": "Feature",
  "properties": {
    "iso:country":"US",
    "sg:address":"2310 W Fisher Ln",
    "sg:city":"Royalton",
    "sg:classifiers":[
        {
            "category":"Farming",
            "subcategory":"Livestock Farm",
            "type":"Manufacturing & Wholesale Goods"
        },
        {
            "category":"Farming",
            "subcategory":"Farm",
            "type":"Manufacturing & Wholesale Goods"
        }
    ],
    "sg:phone":"+1 618 984 2340",
    "sg:postcode":"62983",
    "sg:province":"IL",
    "wof:name":"Thomas Fisher",
    "wof:placetype":"venue"
},
  "geometry": {"coordinates":[-89.111256,37.893158],"type":"Point"}
}