{
  "type": "Feature",
  "properties": {
    "addr:full":"1930 W Division St Chicago IL 60622",
    "addr:housenumber":"1930",
    "addr:postcode":"60622",
    "addr:street":"W Division St",
    "iso:country":"US",
    "sg:address":"1930 W Division St",
    "sg:city":"Chicago",
    "sg:classifiers":[
        {
            "category":"Real Estate",
            "subcategory":"Real Estate Services",
            "type":"Services"
        }
    ],
    "sg:phone":"+1 773 342 0706",
    "sg:postcode":"60622",
    "sg:province":"IL",
    "sg:tags":[
        "management",
        "property"
    ],
    "wof:name":"Rowstar",
    "wof:placetype":"venue"
},
  "geometry": {"coordinates":[-87.676102,41.903301],"type":"Point"}
}