{
  "type": "Feature",
  "properties": {
    "iso:country":"US",
    "sg:address":"21629 W Morningdove Ct",
    "sg:city":"Kildeer",
    "sg:classifiers":[
        {
            "category":"Professional",
            "type":"Services"
        }
    ],
    "sg:phone":"+1 847 726 8707",
    "sg:postcode":"60047",
    "sg:province":"IL",
    "sg:tags":[
        "establishment"
    ],
    "wof:name":"Pax Clearing Co",
    "wof:placetype":"venue"
},
  "geometry": {"coordinates":[-88.054639,42.17987],"type":"Point"}
}