{
  "type": "Feature",
  "properties": {
    "iso:country":"US",
    "sg:address":"1200 S Dunton Ave",
    "sg:city":"Arlington Heights",
    "sg:classifiers":[
        {
            "category":"Education",
            "subcategory":"School",
            "type":"Public Place"
        }
    ],
    "sg:phone":"+1 847 758 4900",
    "sg:postcode":"60005",
    "sg:province":"IL",
    "sg:tags":[
        "management"
    ],
    "wof:name":"Arlington Hts Schl Dst No 25",
    "wof:placetype":"venue"
},
  "geometry": {"coordinates":[-87.98233399999999,42.060572],"type":"Point"}
}