{
  "type": "Feature",
  "properties": {
    "addr:full":"6343 26th St Berwyn IL 60402",
    "addr:housenumber":"6343",
    "addr:postcode":"60402",
    "addr:street":"26Th St",
    "iso:country":"US",
    "sg:address":"6343 26th St",
    "sg:city":"Berwyn",
    "sg:classifiers":[
        {
            "category":"Food & Beverages",
            "subcategory":"Groceries & Convenience Stores",
            "type":"Retail Goods"
        }
    ],
    "sg:phone":"+1 708 795 5474",
    "sg:postcode":"60402",
    "sg:province":"IL",
    "wof:name":"Friends Mini Mart Inc",
    "wof:placetype":"venue"
},
  "geometry": {"coordinates":[-87.783058,41.843475],"type":"Point"}
}