{
  "type": "Feature",
  "properties": {
    "iso:country":"US",
    "sg:address":"2320 Green Bay Rd",
    "sg:city":"North Chicago",
    "sg:classifiers":[
        {
            "category":"Restaurant",
            "type":"Food & Drink"
        }
    ],
    "sg:menulink":"http://www.allmenus.com/il/shields/167185-burger-king/menu/",
    "sg:phone":"+1 847 689 4703",
    "sg:postcode":"60064",
    "sg:province":"IL",
    "sg:tags":[
        "burger",
        "american"
    ],
    "wof:name":"Burger King",
    "wof:placetype":"venue"
},
  "geometry": {"coordinates":[-87.865587,42.316474],"type":"Point"}
}