{
  "type": "Feature",
  "properties": {
    "iso:country":"US",
    "sg:address":"611B S Illinois Ave",
    "sg:city":"Carbondale",
    "sg:classifiers":[
        {
            "category":"Fast Food",
            "type":"Food & Drink"
        },
        {
            "category":"Restaurant",
            "type":"Food & Drink"
        }
    ],
    "sg:phone":"+1 618 529 3287",
    "sg:postcode":"62901",
    "sg:province":"IL",
    "sg:tags":[
        "hamburger",
        "hot",
        "dog",
        "american",
        "take"
    ],
    "sg:website":"http://www.campusspecial.com",
    "wof:name":"Fat Patties",
    "wof:placetype":"venue"
},
  "geometry": {"coordinates":[-89.216258,37.721674],"type":"Point"}
}