{
  "type": "Feature",
  "properties": {
    "addr:full":"4747 S King Dr Chicago IL 60615",
    "addr:housenumber":"4747",
    "addr:postcode":"60615",
    "addr:street":"S King Dr",
    "iso:country":"US",
    "sg:address":"4747 S King Dr",
    "sg:city":"Chicago",
    "sg:classifiers":[
        {
            "category":"Real Estate",
            "subcategory":"Real Estate Operator",
            "type":"Services"
        }
    ],
    "sg:phone":"+1 773 624 0747",
    "sg:postcode":"60615",
    "sg:province":"IL",
    "sg:tags":[
        "apartment"
    ],
    "wof:name":"Luther Terrace Apartments Senior Center",
    "wof:placetype":"venue"
},
  "geometry": {"coordinates":[-87.616203,41.808399],"type":"Point"}
}