{
  "type": "Feature",
  "properties": {
    "addr:full":"1884 Tweed Rd Inverness IL 60067",
    "addr:housenumber":"1884",
    "addr:postcode":"60067",
    "addr:street":"Tweed Rd",
    "iso:country":"US",
    "sg:address":"1884 Tweed Rd",
    "sg:city":"Inverness",
    "sg:classifiers":[
        {
            "category":"Building & Trades",
            "subcategory":"Plumbing",
            "type":"Services"
        }
    ],
    "sg:phone":"+1 847 991 1442",
    "sg:postcode":"60067",
    "sg:province":"IL",
    "sg:tags":[
        "plumbing",
        "contractor"
    ],
    "wof:name":"Envirotech Mechanical Inc",
    "wof:placetype":"venue"
},
  "geometry": {"coordinates":[-88.09138400000001,42.130548],"type":"Point"}
}