{
  "type": "Feature",
  "properties": {
    "addr:full":"1401 N Cicero Ave Chicago IL 60651",
    "addr:housenumber":"1401",
    "addr:postcode":"60651",
    "addr:street":"N Cicero Ave",
    "iso:country":"US",
    "sg:address":"1401 N Cicero Ave",
    "sg:city":"Chicago",
    "sg:classifiers":[
        {
            "category":"Wholesale",
            "subcategory":"Hardware",
            "type":"Manufacturing & Wholesale Goods"
        }
    ],
    "sg:phone":"+1 773 292 1531",
    "sg:postcode":"60651",
    "sg:province":"IL",
    "sg:tags":[
        "plumbing",
        "fixture",
        "supply"
    ],
    "wof:name":"Ferguson Enterprises Inc",
    "wof:placetype":"venue"
},
  "geometry": {"coordinates":[-87.74605,41.907078],"type":"Point"}
}