{
  "type": "Feature",
  "properties": {
    "addr:full":"3440 S Ashland Ave Chicago IL 60608",
    "addr:housenumber":"3440",
    "addr:postcode":"60608",
    "addr:street":"S Ashland Ave",
    "iso:country":"US",
    "sg:address":"3440 S Ashland Ave",
    "sg:city":"Chicago",
    "sg:classifiers":[
        {
            "category":"Retail",
            "subcategory":"Auto Repair",
            "type":"Services"
        }
    ],
    "sg:phone":"+1 773 254 0416",
    "sg:postcode":"60608",
    "sg:province":"IL",
    "wof:name":"Auto Mex Inc",
    "wof:placetype":"venue"
},
  "geometry": {"coordinates":[-87.665854,41.831663],"type":"Point"}
}