{
  "type": "Feature",
  "properties": {
    "addr:full":"901 W Jackson Blvd Ste 300 Chicago IL 60607",
    "addr:housenumber":"901",
    "addr:postcode":"60607",
    "addr:street":"W Jackson Blvd Ste 300",
    "iso:country":"US",
    "sg:address":"901 W Jackson Blvd Ste 300",
    "sg:city":"Chicago",
    "sg:classifiers":[
        {
            "category":"Professional",
            "subcategory":"Employment Agencies",
            "type":"Services"
        }
    ],
    "sg:phone":"+1 312 243 0311",
    "sg:postcode":"60607",
    "sg:province":"IL",
    "wof:name":"Platinum Executive Recriters Inc",
    "wof:placetype":"venue"
},
  "geometry": {"coordinates":[-87.64957699999999,41.877803],"type":"Point"}
}