{
  "type": "Feature",
  "properties": {
    "iso:country":"US",
    "sg:address":"841 Mill Race Ln",
    "sg:city":"Naperville",
    "sg:classifiers":[
        {
            "category":"Science Facility",
            "type":"Public Place"
        }
    ],
    "sg:phone":"+1 630 983 5381",
    "sg:postcode":"60565",
    "sg:province":"IL",
    "sg:tags":[
        "development",
        "laboratories-research"
    ],
    "wof:name":"Roche Palo Alto",
    "wof:placetype":"venue"
},
  "geometry": {"coordinates":[-88.112936,41.737439],"type":"Point"}
}