{
  "type": "Feature",
  "properties": {
    "iso:country":"US",
    "sg:address":"4655 W Arthington St",
    "sg:city":"Chicago",
    "sg:classifiers":[
        {
            "category":"Building & Trades",
            "subcategory":"Construction",
            "type":"Services"
        }
    ],
    "sg:phone":"+1 773 626 4122",
    "sg:postcode":"60644",
    "sg:province":"IL",
    "sg:tags":[
        "general",
        "contractor"
    ],
    "wof:name":"GF Structures Corporation",
    "wof:placetype":"venue"
},
  "geometry": {"coordinates":[-87.741315,41.869525],"type":"Point"}
}