{
  "type": "Feature",
  "properties": {
    "addr:full":"4015 N Pulaski Road Chicago IL 60641",
    "addr:housenumber":"4015",
    "addr:postcode":"60641",
    "addr:street":"N Pulaski Road",
    "iso:country":"US",
    "sg:address":"4015 N Pulaski Road",
    "sg:city":"Chicago",
    "sg:classifiers":[
        {
            "category":"Health Services",
            "subcategory":"Doctor",
            "type":"Services"
        }
    ],
    "sg:phone":"+1 773 588 8855",
    "sg:postcode":"60641",
    "sg:province":"IL",
    "wof:name":"Merrin Claude MD",
    "wof:placetype":"venue"
},
  "geometry": {"coordinates":[-87.727621,41.95378],"type":"Point"}
}