{
  "type": "Feature",
  "properties": {
    "addr:full":"99 W Van Buren St Chicago IL 60605",
    "addr:housenumber":"99",
    "addr:postcode":"60605",
    "addr:street":"W Van Buren St",
    "iso:country":"US",
    "sg:address":"99 W Van Buren St",
    "sg:city":"Chicago",
    "sg:classifiers":[
        {
            "category":"Building & Trades",
            "subcategory":"Locksmith",
            "type":"Services"
        }
    ],
    "sg:phone":"+1 312 267 0701",
    "sg:postcode":"60605",
    "sg:province":"IL",
    "sg:tags":[
        "key"
    ],
    "sg:website":"fastchicagolocksmith.com/",
    "wof:name":"Chicago Locksmith",
    "wof:placetype":"venue"
},
  "geometry": {"coordinates":[-87.63072,41.876865],"type":"Point"}
}