{
  "type": "Feature",
  "properties": {
    "addr:full":"1418 Charleston Ct Geneva IL 60134",
    "addr:housenumber":"1418",
    "addr:postcode":"60134",
    "addr:street":"Charleston Ct",
    "iso:country":"US",
    "sg:address":"1418 Charleston Ct",
    "sg:city":"Geneva",
    "sg:classifiers":[
        {
            "category":"Professional",
            "subcategory":"Business Services",
            "type":"Services"
        }
    ],
    "sg:phone":"+1 630 208 7861",
    "sg:postcode":"60134",
    "sg:province":"IL",
    "wof:name":"Termondt Technology Innovation",
    "wof:placetype":"venue"
},
  "geometry": {"coordinates":[-88.280404,41.893009],"type":"Point"}
}