{
  "type": "Feature",
  "properties": {
    "addr:full":"202 S Main St Fairmount IL 61841",
    "addr:housenumber":"202",
    "addr:postcode":"61841",
    "addr:street":"S Main St",
    "iso:country":"US",
    "sg:address":"202 S Main St",
    "sg:city":"Fairmount",
    "sg:classifiers":[
        {
            "category":"Organizations",
            "subcategory":"Religious Organization",
            "type":"Services"
        }
    ],
    "sg:phone":"+1 217 733 2382",
    "sg:postcode":"61841",
    "sg:province":"IL",
    "sg:tags":[
        "church"
    ],
    "wof:name":"First Baptist Church",
    "wof:placetype":"venue"
},
  "geometry": {"coordinates":[-87.830433,40.04551],"type":"Point"}
}