{
  "type": "Feature",
  "properties": {
    "addr:full":"1000 Woodbine Ave Oak Park IL 60302",
    "addr:housenumber":"1000",
    "addr:postcode":"60302",
    "addr:street":"Woodbine Ave",
    "iso:country":"US",
    "sg:address":"1000 Woodbine Ave",
    "sg:city":"Oak Park",
    "sg:classifiers":[
        {
            "category":"Real Estate",
            "subcategory":"Architect",
            "type":"Services"
        }
    ],
    "sg:phone":"+1 708 660 0315",
    "sg:postcode":"60302",
    "sg:province":"IL",
    "wof:name":"Eakin Garret",
    "wof:placetype":"venue"
},
  "geometry": {"coordinates":[-87.79920199999999,41.903599],"type":"Point"}
}