{
  "type": "Feature",
  "properties": {
    "addr:full":"953 Howard St Evanston IL 60202",
    "addr:housenumber":"953",
    "addr:postcode":"60202",
    "addr:street":"Howard St",
    "iso:country":"US",
    "sg:address":"953 Howard St",
    "sg:city":"Evanston",
    "sg:classifiers":[
        {
            "category":"Personal",
            "subcategory":"Beauty Salon",
            "type":"Services"
        }
    ],
    "sg:phone":"+1 847 491 9557",
    "sg:postcode":"60202",
    "sg:province":"IL",
    "sg:tags":[
        "shop"
    ],
    "wof:name":"Lovely Nails",
    "wof:placetype":"venue"
},
  "geometry": {"coordinates":[-87.686487,42.019582],"type":"Point"}
}