{
  "type": "Feature",
  "properties": {
    "addr:full":"355 N Lavergne Ave Chicago IL 60644",
    "addr:housenumber":"355",
    "addr:postcode":"60644",
    "addr:street":"N Lavergne Ave",
    "iso:country":"US",
    "sg:address":"355 N Lavergne Ave",
    "sg:city":"Chicago",
    "sg:classifiers":[
        {
            "category":"Wholesale",
            "subcategory":"Metals & Minerals",
            "type":"Manufacturing & Wholesale Goods"
        }
    ],
    "sg:phone":"+1 773 626 4747",
    "sg:postcode":"60644",
    "sg:province":"IL",
    "sg:tags":[
        "pipe"
    ],
    "sg:website":"www.addisonpipe.com",
    "wof:name":"Addison Pipe & Tube Co",
    "wof:placetype":"venue"
},
  "geometry": {"coordinates":[-87.750339,41.887315],"type":"Point"}
}