{
  "type": "Feature",
  "properties": {
    "addr:full":"19747 Wolf Rd Mokena IL 60448",
    "addr:housenumber":"19747",
    "addr:postcode":"60448",
    "addr:street":"Wolf Rd",
    "iso:country":"US",
    "sg:address":"19747 Wolf Rd",
    "sg:city":"Mokena",
    "sg:classifiers":[
        {
            "category":"Social Services",
            "type":"Services"
        }
    ],
    "sg:phone":"+1 708 478 8260",
    "sg:postcode":"60448",
    "sg:province":"IL",
    "wof:name":"Kathleen Carlson Msw Lcsw",
    "wof:placetype":"venue"
},
  "geometry": {"coordinates":[-87.889293,41.53065],"type":"Point"}
}