{
  "type": "Feature",
  "properties": {
    "addr:full":"225 Rice Rd South Wilmington IL 60474",
    "addr:housenumber":"225",
    "addr:postcode":"60474",
    "addr:street":"Rice Rd",
    "iso:country":"US",
    "sg:address":"225 Rice Rd",
    "sg:city":"South Wilmington",
    "sg:classifiers":[
        {
            "category":"Organizations",
            "subcategory":"Religious Organization",
            "type":"Services"
        }
    ],
    "sg:phone":"+1 815 237 2573",
    "sg:postcode":"60474",
    "sg:province":"IL",
    "sg:tags":[
        "church"
    ],
    "wof:name":"South Wilmington United Mthdst",
    "wof:placetype":"venue"
},
  "geometry": {"coordinates":[-88.252578,41.172427],"type":"Point"}
}