{
  "type": "Feature",
  "properties": {
    "iso:country":"US",
    "sg:address":"418 S Lincoln Blvd",
    "sg:city":"Centralia",
    "sg:classifiers":[
        {
            "category":"Home & Garden",
            "subcategory":"Home Furnishings",
            "type":"Retail Goods"
        }
    ],
    "sg:phone":"+1 618 545 0320",
    "sg:postcode":"62801",
    "sg:province":"IL",
    "sg:tags":[
        "curtain",
        "made",
        "drapery"
    ],
    "wof:name":"Lea's Custom Draperies",
    "wof:placetype":"venue"
},
  "geometry": {"coordinates":[-89.125658,38.521791],"type":"Point"}
}