{
  "type": "Feature",
  "properties": {
    "addr:full":"5547 W Van Buren St Chicago IL 60644",
    "addr:housenumber":"5547",
    "addr:postcode":"60644",
    "addr:street":"W Van Buren St",
    "iso:country":"US",
    "sg:address":"5547 W Van Buren St",
    "sg:city":"Chicago",
    "sg:classifiers":[
        {
            "category":"Building & Trades",
            "subcategory":"Plumbing",
            "type":"Services"
        }
    ],
    "sg:phone":"+1 773 921 4593",
    "sg:postcode":"60644",
    "sg:province":"IL",
    "sg:tags":[
        "plumbing",
        "contractor"
    ],
    "wof:name":"All Around Sewers & Plumbing",
    "wof:placetype":"venue"
},
  "geometry": {"coordinates":[-87.76344,41.874671],"type":"Point"}
}