{
  "type": "Feature",
  "properties": {
    "iso:country":"US",
    "sg:address":"114 S Illinois Ave",
    "sg:city":"Carbondale",
    "sg:classifiers":[
        {
            "category":"Restaurant",
            "type":"Food & Drink"
        }
    ],
    "sg:phone":"+1 618 457 5084",
    "sg:postcode":"62901",
    "sg:province":"IL",
    "wof:name":"Mary Lou's Grill",
    "wof:placetype":"venue"
},
  "geometry": {"coordinates":[-89.216904,37.7271],"type":"Point"}
}