{
  "type": "Feature",
  "properties": {
    "iso:country":"US",
    "sg:address":"1835 W School St",
    "sg:city":"Chicago",
    "sg:classifiers":[
        {
            "category":"Personal",
            "type":"Services"
        },
        {
            "category":"Education",
            "subcategory":"Special Training",
            "type":"Public Place"
        }
    ],
    "sg:phone":"+1 773 477 6482",
    "sg:postcode":"60657",
    "sg:province":"IL",
    "sg:tags":[
        "home",
        "school",
        "specialty"
    ],
    "sg:website":"www.woodsmythschicago.com/",
    "wof:name":"Woodsmyths Woodworking",
    "wof:placetype":"venue"
},
  "geometry": {"coordinates":[-87.675359,41.941178],"type":"Point"}
}