{
  "type": "Feature",
  "properties": {
    "iso:country":"US",
    "sg:address":"12941 California Ave",
    "sg:city":"Blue Island",
    "sg:classifiers":[
        {
            "category":"Building & Trades",
            "subcategory":"Construction",
            "type":"Services"
        }
    ],
    "sg:phone":"+1 708 385 8277",
    "sg:postcode":"60406",
    "sg:province":"IL",
    "sg:tags":[
        "siding",
        "contractor"
    ],
    "wof:name":"DNR Construction Inc",
    "wof:placetype":"venue"
},
  "geometry": {"coordinates":[-87.689798,41.657062],"type":"Point"}
}