{
  "type": "Feature",
  "properties": {
    "iso:country":"US",
    "sg:address":"1276 State St",
    "sg:city":"Lemont",
    "sg:classifiers":[
        {
            "category":"Restaurant",
            "type":"Food & Drink"
        }
    ],
    "sg:menulink":"http://www.allmenus.com/il/lemont/167138-burger-king/menu/",
    "sg:phone":"+1 630 243 6142",
    "sg:postcode":"60439",
    "sg:province":"IL",
    "sg:tags":[
        "burger",
        "american"
    ],
    "wof:name":"Burger King",
    "wof:placetype":"venue"
},
  "geometry": {"coordinates":[-88.00019399999999,41.654154],"type":"Point"}
}