{
  "type": "Feature",
  "properties": {
    "addr:full":"119 W Church St Champaign IL 61820",
    "addr:housenumber":"119",
    "addr:postcode":"61820",
    "addr:street":"W Church St",
    "iso:country":"US",
    "sg:address":"119 W Church St",
    "sg:city":"Champaign",
    "sg:classifiers":[
        {
            "category":"Communications",
            "subcategory":"Television Station",
            "type":"Services"
        }
    ],
    "sg:phone":"+1 217 403 9927",
    "sg:postcode":"61820",
    "sg:province":"IL",
    "wof:name":"Fox 55 27 Illinois",
    "wof:placetype":"venue"
},
  "geometry": {"coordinates":[-88.243837,40.11815],"type":"Point"}
}