{
  "type": "Feature",
  "properties": {
    "iso:country":"US",
    "sg:address":"3048 W Diversey Ave",
    "sg:city":"Chicago",
    "sg:classifiers":[
        {
            "category":"Banks & Credit Unions",
            "subcategory":"Bank",
            "type":"Services"
        }
    ],
    "sg:phone":"+1 773 486 4064",
    "sg:postcode":"60647",
    "sg:province":"IL",
    "sg:tags":[
        "broker",
        "mortgage"
    ],
    "sg:website":"www.capital-source.info",
    "wof:name":"Capital Sources LTD",
    "wof:placetype":"venue"
},
  "geometry": {"coordinates":[-87.704676,41.932117],"type":"Point"}
}