{
  "type": "Feature",
  "properties": {
    "iso:country":"US",
    "sg:address":"5030 Imperial Dr",
    "sg:city":"Richton Park",
    "sg:classifiers":[
        {
            "category":"Education",
            "subcategory":"School",
            "type":"Public Place"
        }
    ],
    "sg:phone":"+1 708 481 7424",
    "sg:postcode":"60471",
    "sg:province":"IL",
    "wof:name":"Neil Armstrong Elementary",
    "wof:placetype":"venue"
},
  "geometry": {"coordinates":[-87.739898,41.477549],"type":"Point"}
}