{
  "type": "Feature",
  "properties": {
    "iso:country":"US",
    "sg:address":"500 N Michigan Ave, Ste 330",
    "sg:city":"Chicago",
    "sg:classifiers":[
        {
            "category":"Communications",
            "subcategory":"Newspaper",
            "type":"Services"
        },
        {
            "category":"Professional",
            "subcategory":"Art Services",
            "type":"Services"
        },
        {
            "category":"Communications",
            "type":"Services"
        }
    ],
    "sg:phone":"+1 312 893 9608",
    "sg:postcode":"60611",
    "sg:province":"IL",
    "sg:tags":[
        "web",
        "graphic",
        "design",
        "advertising"
    ],
    "sg:website":"www.growclicks.com",
    "wof:name":"Grow Clicks",
    "wof:placetype":"venue"
},
  "geometry": {"coordinates":[-87.624484,41.891105],"type":"Point"}
}