{
  "type": "Feature",
  "properties": {
    "addr:full":"3727 N Ventura Dr Arlington Heights IL 60004",
    "addr:housenumber":"3727",
    "addr:postcode":"60004",
    "addr:street":"N Ventura Dr",
    "iso:country":"US",
    "sg:address":"3727 N Ventura Dr",
    "sg:city":"Arlington Heights",
    "sg:classifiers":[
        {
            "category":"Professional",
            "subcategory":"Art Services",
            "type":"Services"
        }
    ],
    "sg:phone":"+1 847 577 9550",
    "sg:postcode":"60004",
    "sg:province":"IL",
    "sg:tags":[
        "photography",
        "commercial"
    ],
    "wof:name":"Norikane Studios",
    "wof:placetype":"venue"
},
  "geometry": {"coordinates":[-88.003781,42.143579],"type":"Point"}
}