{
  "type": "Feature",
  "properties": {
    "addr:full":"1287 W Wabash Ave Effingham IL 62401",
    "addr:housenumber":"1287",
    "addr:postcode":"62401",
    "addr:street":"W Wabash Ave",
    "iso:country":"US",
    "sg:address":"1287 W Wabash Ave",
    "sg:city":"Effingham",
    "sg:classifiers":[
        {
            "category":"Shopping",
            "subcategory":"Computers & Home Electronics",
            "type":"Retail Goods"
        }
    ],
    "sg:phone":"+1 217 787 4756",
    "sg:postcode":"62401",
    "sg:province":"IL",
    "sg:tags":[
        "audio"
    ],
    "wof:name":"Beatty Televisual Inc",
    "wof:placetype":"venue"
},
  "geometry": {"coordinates":[-88.55699300000001,39.11302],"type":"Point"}
}