{
  "type": "Feature",
  "properties": {
    "iso:country":"US",
    "sg:address":"3155 W Lawrence Ave",
    "sg:city":"Chicago",
    "sg:classifiers":[
        {
            "category":"Health Services",
            "subcategory":"Clinic",
            "type":"Services"
        }
    ],
    "sg:phone":"+1 773 283 3131",
    "sg:postcode":"60625",
    "sg:province":"IL",
    "sg:tags":[
        "medical"
    ],
    "wof:name":"Neck & Back Clinic Ltd",
    "wof:placetype":"venue"
},
  "geometry": {"coordinates":[-87.707898,41.96846],"type":"Point"}
}