{
  "type": "Feature",
  "properties": {
    "addr:full":"290 Meadowview Ln Aurora IL 60502",
    "addr:housenumber":"290",
    "addr:postcode":"60502",
    "addr:street":"Meadowview Ln",
    "iso:country":"US",
    "sg:address":"290 Meadowview Ln",
    "sg:city":"Aurora",
    "sg:classifiers":[
        {
            "category":"Home & Garden",
            "subcategory":"Garden Supply",
            "type":"Retail Goods"
        }
    ],
    "sg:phone":"+1   ",
    "sg:postcode":"60502",
    "sg:province":"IL",
    "wof:name":"Lebanon Chemical Corporation",
    "wof:placetype":"venue"
},
  "geometry": {"coordinates":[-88.261218,41.748423],"type":"Point"}
}