{
  "type": "Feature",
  "properties": {
    "iso:country":"US",
    "sg:address":"617 S 4th Ave",
    "sg:city":"Libertyville",
    "sg:classifiers":[
        {
            "category":"Building & Trades",
            "subcategory":"Construction",
            "type":"Services"
        }
    ],
    "sg:phone":"+1 847 367 6931",
    "sg:postcode":"60048",
    "sg:province":"IL",
    "sg:tags":[
        "restoration",
        "cleaning",
        "patio",
        "deck"
    ],
    "wof:name":"Complete Deck Care",
    "wof:placetype":"venue"
},
  "geometry": {"coordinates":[-87.94714500000001,42.276321],"type":"Point"}
}