{
  "type": "Feature",
  "properties": {
    "iso:country":"US",
    "sg:address":"6935 11th St",
    "sg:city":"Rockford",
    "sg:classifiers":[
        {
            "category":"Restaurant",
            "type":"Food & Drink"
        }
    ],
    "sg:phone":"+1 815 874 6888",
    "sg:postcode":"61109",
    "sg:province":"IL",
    "wof:name":"Bino's Italian Restaurant",
    "wof:placetype":"venue"
},
  "geometry": {"coordinates":[-89.07207200000001,42.185054],"type":"Point"}
}