{
  "type": "Feature",
  "properties": {
    "addr:full":"1824 Michigan Ave Rockford IL 61102",
    "addr:housenumber":"1824",
    "addr:postcode":"61102",
    "addr:street":"Michigan Ave",
    "iso:country":"US",
    "sg:address":"1824 Michigan Ave",
    "sg:city":"Rockford",
    "sg:classifiers":[
        {
            "category":"Freight",
            "type":"Transportation"
        }
    ],
    "sg:phone":"+1 815 962 3750",
    "sg:postcode":"61102",
    "sg:province":"IL",
    "sg:tags":[
        "operator",
        "trucking"
    ],
    "wof:name":"Andrea Trucking Inc",
    "wof:placetype":"venue"
},
  "geometry": {"coordinates":[-89.12886399999999,42.251904],"type":"Point"}
}