{
  "type": "Feature",
  "properties": {
    "addr:full":"1701 E Riverside Blvd Rockford IL 61114",
    "addr:housenumber":"1701",
    "addr:postcode":"61114",
    "addr:street":"E Riverside Blvd",
    "iso:country":"US",
    "sg:address":"1701 E Riverside Blvd",
    "sg:city":"Rockford",
    "sg:classifiers":[
        {
            "category":"Retail",
            "subcategory":"Auto Repair",
            "type":"Services"
        }
    ],
    "sg:phone":"+1 815 654 1002",
    "sg:postcode":"61114",
    "sg:province":"IL",
    "sg:tags":[
        "automobile",
        "lubrication",
        "automotive"
    ],
    "wof:name":"Lubepro's 10 Minute Oil Change",
    "wof:placetype":"venue"
},
  "geometry": {"coordinates":[-89.026629,42.318294],"type":"Point"}
}