{
  "type": "Feature",
  "properties": {
    "addr:full":"4300 E New York St Aurora IL 60504",
    "addr:housenumber":"4300",
    "addr:postcode":"60504",
    "addr:street":"E New York St",
    "iso:country":"US",
    "sg:address":"4300 E New York St",
    "sg:city":"Aurora",
    "sg:classifiers":[
        {
            "category":"Education",
            "subcategory":"Special Training",
            "type":"Public Place"
        }
    ],
    "sg:phone":"+1 630 236 5563",
    "sg:postcode":"60504",
    "sg:province":"IL",
    "sg:tags":[
        "school",
        "instruction",
        "art"
    ],
    "wof:name":"Gymboree Play & Music Ctr",
    "wof:placetype":"venue"
},
  "geometry": {"coordinates":[-88.212861,41.761664],"type":"Point"}
}