{
  "type": "Feature",
  "properties": {
    "iso:country":"US",
    "sg:address":"2470 Hayloft Ln",
    "sg:city":"Elgin",
    "sg:classifiers":[
        {
            "category":"Building & Trades",
            "subcategory":"Cleaning & Sanitation",
            "type":"Services"
        }
    ],
    "sg:phone":"+1 847 695 6587",
    "sg:postcode":"60124",
    "sg:province":"IL",
    "sg:tags":[
        "janitor"
    ],
    "wof:name":"Accent Janitorial Svc",
    "wof:placetype":"venue"
},
  "geometry": {"coordinates":[-88.339762,42.018394],"type":"Point"}
}