{
  "type": "Feature",
  "properties": {
    "addr:full":"14492 Dorr Rd South Beloit WI 61080",
    "addr:housenumber":"14492",
    "addr:postcode":"61080",
    "addr:street":"Dorr Rd",
    "iso:country":"US",
    "sg:address":"14492 Dorr Rd",
    "sg:city":"South Beloit",
    "sg:classifiers":[
        {
            "category":"Autos & Motor Vehicles",
            "subcategory":"Auto Supplies",
            "type":"Retail Goods"
        },
        {
            "category":"Wholesale",
            "subcategory":"Auto Parts",
            "type":"Manufacturing & Wholesale Goods"
        }
    ],
    "sg:phone":"+1 815 624 4046",
    "sg:postcode":"61080",
    "sg:province":"WI",
    "sg:tags":[
        "body",
        "truck",
        "accessory"
    ],
    "wof:name":"Specialty Coatings Accesories",
    "wof:placetype":"venue"
},
  "geometry": {"coordinates":[-89.03962199999999,42.470287],"type":"Point"}
}