{
  "type": "Feature",
  "properties": {
    "iso:country":"US",
    "sg:address":"243 W Northwest Hwy",
    "sg:city":"Barrington",
    "sg:classifiers":[
        {
            "category":"Restaurant",
            "type":"Food & Drink"
        }
    ],
    "sg:phone":"+1 847 277 9636",
    "sg:postcode":"60010",
    "sg:province":"IL",
    "wof:name":"LA Mesa Restaurant",
    "wof:placetype":"venue"
},
  "geometry": {"coordinates":[-88.138452,42.161488],"type":"Point"}
}