{
  "type": "Feature",
  "properties": {
    "iso:country":"US",
    "sg:address":"9140 Broadway Ave",
    "sg:city":"Brookfield",
    "sg:classifiers":[
        {
            "category":"Real Estate",
            "subcategory":"Real Estate Agent",
            "type":"Services"
        }
    ],
    "sg:phone":"+1 708 485 6606",
    "sg:postcode":"60513",
    "sg:province":"IL",
    "sg:website":"www.failla.com",
    "wof:name":"Failla Realty",
    "wof:placetype":"venue"
},
  "geometry": {"coordinates":[-87.84988,41.829061],"type":"Point"}
}