{
  "type": "Feature",
  "properties": {
    "addr:full":"108 W Mississippi St Elwood IL 60421",
    "addr:housenumber":"108",
    "addr:postcode":"60421",
    "addr:street":"W Mississippi St",
    "iso:country":"US",
    "sg:address":"108 W Mississippi St",
    "sg:city":"Elwood",
    "sg:classifiers":[
        {
            "category":"Restaurant",
            "type":"Food & Drink"
        }
    ],
    "sg:phone":"+1 815 424 0160",
    "sg:postcode":"60421",
    "sg:province":"IL",
    "wof:name":"Lazy Dog",
    "wof:placetype":"venue"
},
  "geometry": {"coordinates":[-88.111861,41.403979],"type":"Point"}
}