{
  "type": "Feature",
  "properties": {
    "addr:full":"1653 W. Congress Chicago IL 60612",
    "addr:housenumber":"1653",
    "addr:postcode":"60612",
    "addr:street":"W.",
    "iso:country":"US",
    "sg:address":"1653 W. Congress",
    "sg:city":"Chicago",
    "sg:classifiers":[
        {
            "category":"Health Services",
            "subcategory":"Hospital",
            "type":"Services"
        }
    ],
    "sg:phone":"+1 312 942 6428",
    "sg:postcode":"60612",
    "sg:province":"IL",
    "sg:website":"www.rush.edu/rumc/page-109961155...",
    "wof:name":"Rush University Medical Center Emergency Room",
    "wof:placetype":"venue"
},
  "geometry": {"coordinates":[-87.667984,41.875156],"type":"Point"}
}