{
  "type": "Feature",
  "properties": {
    "iso:country":"US",
    "sg:address":"5851 S Kedzie Ave",
    "sg:city":"Chicago",
    "sg:classifiers":[
        {
            "category":"Banks & Credit Unions",
            "subcategory":"Financial Services",
            "type":"Services"
        }
    ],
    "sg:phone":"+1 773 737 1562",
    "sg:postcode":"60629",
    "sg:province":"IL",
    "sg:tags":[
        "cashing",
        "loan",
        "payday",
        "check"
    ],
    "sg:website":"http://www.checkintocash.com",
    "wof:name":"Check Into Cash",
    "wof:placetype":"venue"
},
  "geometry": {"coordinates":[-87.70336500000001,41.787142],"type":"Point"}
}