{
  "type": "Feature",
  "properties": {
    "addr:full":"503 Cypress Dr Effingham IL 62401",
    "addr:housenumber":"503",
    "addr:postcode":"62401",
    "addr:street":"Cypress Dr",
    "iso:country":"US",
    "sg:address":"503 Cypress Dr",
    "sg:city":"Effingham",
    "sg:classifiers":[
        {
            "category":"Sports & Exercise",
            "subcategory":"Gym",
            "type":"Entertainment"
        }
    ],
    "sg:phone":"+1 217 342 3390",
    "sg:postcode":"62401",
    "sg:province":"IL",
    "sg:tags":[
        "fitness",
        "physical",
        "facility"
    ],
    "wof:name":"Zone Enterprises Inc",
    "wof:placetype":"venue"
},
  "geometry": {"coordinates":[-88.536145,39.100596],"type":"Point"}
}