{
  "type": "Feature",
  "properties": {
    "addr:full":"3270 W Dickens Ave Chicago IL 60647",
    "addr:housenumber":"3270",
    "addr:postcode":"60647",
    "addr:street":"W Dickens Ave",
    "iso:country":"US",
    "sg:address":"3270 W Dickens Ave",
    "sg:city":"Chicago",
    "sg:classifiers":[
        {
            "category":"Building & Trades",
            "subcategory":"Locksmith",
            "type":"Services"
        }
    ],
    "sg:phone":"+1 773 829 4842",
    "sg:postcode":"60647",
    "sg:province":"IL",
    "sg:tags":[
        "key"
    ],
    "wof:name":"Always Affective Available Emergency",
    "wof:placetype":"venue"
},
  "geometry": {"coordinates":[-87.709611,41.919337],"type":"Point"}
}