{
  "type": "Feature",
  "properties": {
    "addr:full":"622 E Main St Carbondale IL 62902",
    "addr:housenumber":"622",
    "addr:postcode":"62902",
    "addr:street":"E Main St",
    "iso:country":"US",
    "sg:address":"622 E Main St",
    "sg:city":"Carbondale",
    "sg:classifiers":[
        {
            "category":"Retail",
            "subcategory":"Auto Repair",
            "type":"Services"
        }
    ],
    "sg:phone":"+1 618 549 6120",
    "sg:postcode":"62902",
    "sg:province":"IL",
    "sg:tags":[
        "automobile",
        "lubrication"
    ],
    "wof:name":"Pro Lube",
    "wof:placetype":"venue"
},
  "geometry": {"coordinates":[-89.20337000000001,37.728289],"type":"Point"}
}