{
  "type": "Feature",
  "properties": {
    "addr:full":"3135 N Lewis Ave Waukegan IL 60087",
    "addr:housenumber":"3135",
    "addr:postcode":"60087",
    "addr:street":"N Lewis Ave",
    "iso:country":"US",
    "sg:address":"3135 N Lewis Ave",
    "sg:city":"Waukegan",
    "sg:classifiers":[
        {
            "category":"Personal",
            "subcategory":"Beauty Salon",
            "type":"Services"
        }
    ],
    "sg:phone":"+1 847 623 3322",
    "sg:postcode":"60087",
    "sg:province":"IL",
    "wof:name":"Sheer Magic Beauty Salon",
    "wof:placetype":"venue"
},
  "geometry": {"coordinates":[-87.855001,42.408991],"type":"Point"}
}