{
  "type": "Feature",
  "properties": {
    "addr:full":"10810 Oxford Ave Chicago Ridge IL 60415",
    "addr:housenumber":"10810",
    "addr:postcode":"60415",
    "addr:street":"Oxford Ave",
    "iso:country":"US",
    "sg:address":"10810 Oxford Ave",
    "sg:city":"Chicago Ridge",
    "sg:classifiers":[
        {
            "category":"Education",
            "subcategory":"School",
            "type":"Public Place"
        }
    ],
    "sg:phone":"+1 708 425 0250",
    "sg:postcode":"60415",
    "sg:province":"IL",
    "sg:tags":[
        "high",
        "middle",
        "elementary"
    ],
    "wof:name":"Our Lady of the Ridge",
    "wof:placetype":"venue"
},
  "geometry": {"coordinates":[-87.777975,41.695687],"type":"Point"}
}