{
  "type": "Feature",
  "properties": {
    "iso:country":"US",
    "sg:address":"105 S 5th St",
    "sg:city":"Vandalia",
    "sg:classifiers":[
        {
            "category":"Shopping",
            "subcategory":"Computers & Home Electronics",
            "type":"Retail Goods"
        }
    ],
    "sg:phone":"+1 618 283 1420",
    "sg:postcode":"62471",
    "sg:province":"IL",
    "sg:tags":[
        "software"
    ],
    "wof:name":"Opportunities Unlimited",
    "wof:placetype":"venue"
},
  "geometry": {"coordinates":[-89.096181,38.961559],"type":"Point"}
}