{
  "type": "Feature",
  "properties": {
    "iso:country":"US",
    "sg:address":"500 W Irving Park Rd",
    "sg:city":"Bensenville",
    "sg:classifiers":[
        {
            "category":"Wholesale",
            "subcategory":"Furniture",
            "type":"Manufacturing & Wholesale Goods"
        }
    ],
    "sg:phone":"+1 630 766 7766",
    "sg:postcode":"60106",
    "sg:province":"IL",
    "sg:tags":[
        "furniture-wholesale",
        "manufacturer"
    ],
    "wof:name":"Vertical Blinds Factory Outlet",
    "wof:placetype":"venue"
},
  "geometry": {"coordinates":[-87.94710499999999,41.960921],"type":"Point"}
}