{
  "type": "Feature",
  "properties": {
    "iso:country":"US",
    "sg:address":"109 S Dunlap Ave",
    "sg:city":"Savoy",
    "sg:classifiers":[
        {
            "category":"Home & Garden",
            "subcategory":"Garden Supply",
            "type":"Retail Goods"
        }
    ],
    "sg:phone":"+1 217 352 0622",
    "sg:postcode":"61874",
    "sg:province":"IL",
    "sg:tags":[
        "nursery",
        "gardening"
    ],
    "sg:website":"www.awesomemachines.net",
    "wof:name":"Awesome Machines Sales & Rental",
    "wof:placetype":"venue"
},
  "geometry": {"coordinates":[-88.25158399999999,40.054487],"type":"Point"}
}