{
  "type": "Feature",
  "properties": {
    "addr:full":"104 W Main St Peotone IL 60468",
    "addr:housenumber":"104",
    "addr:postcode":"60468",
    "addr:street":"W Main St",
    "iso:country":"US",
    "sg:address":"104 W Main St",
    "sg:city":"Peotone",
    "sg:classifiers":[
        {
            "category":"Organizations",
            "subcategory":"Professional Association",
            "type":"Services"
        }
    ],
    "sg:phone":"+1 708 258 9450",
    "sg:postcode":"60468",
    "sg:province":"IL",
    "sg:tags":[
        "chambers",
        "commerce"
    ],
    "wof:name":"Peotone Chamber Of Commerce",
    "wof:placetype":"venue"
},
  "geometry": {"coordinates":[-87.790848,41.333184],"type":"Point"}
}