{
  "type": "Feature",
  "properties": {
    "iso:country":"US",
    "sg:address":"1229 N Monticello Ave",
    "sg:city":"Chicago",
    "sg:classifiers":[
        {
            "category":"Building & Trades",
            "subcategory":"Construction",
            "type":"Services"
        }
    ],
    "sg:phone":"+1 773 342 6488",
    "sg:postcode":"60651",
    "sg:province":"IL",
    "sg:tags":[
        "roofing",
        "general"
    ],
    "wof:name":"Tri Star Roofing",
    "wof:placetype":"venue"
},
  "geometry": {"coordinates":[-87.717781,41.902744],"type":"Point"}
}