{
  "type": "Feature",
  "properties": {
    "addr:full":"733 NE Holcomb Dr Mundelein IL 60060",
    "addr:housenumber":"733",
    "addr:postcode":"60060",
    "addr:street":"Ne Holcomb Dr",
    "iso:country":"US",
    "sg:address":"733 NE Holcomb Dr",
    "sg:city":"Mundelein",
    "sg:classifiers":[
        {
            "category":"Shopping",
            "subcategory":"Clothing, Apparel, & Fashions",
            "type":"Retail Goods"
        }
    ],
    "sg:phone":"+1   ",
    "sg:postcode":"60060",
    "sg:province":"IL",
    "wof:name":"Legends In Time",
    "wof:placetype":"venue"
},
  "geometry": {"coordinates":[-87.999313,42.273925],"type":"Point"}
}