{
  "type": "Feature",
  "properties": {
    "addr:full":"454 N Columbus Dr Chicago IL 60611",
    "addr:housenumber":"454",
    "addr:postcode":"60611",
    "addr:street":"N Columbus Dr",
    "iso:country":"US",
    "sg:address":"454 N Columbus Dr",
    "sg:city":"Chicago",
    "sg:classifiers":[
        {
            "category":"Communications",
            "subcategory":"Television Station",
            "type":"Services"
        }
    ],
    "sg:phone":"+1 312 836 9400",
    "sg:postcode":"60611",
    "sg:province":"IL",
    "sg:tags":[
        "distributor",
        "program",
        "producer"
    ],
    "sg:website":"http://www.oceanic.com",
    "wof:name":"Time Warner",
    "wof:placetype":"venue"
},
  "geometry": {"coordinates":[-87.620327,41.89027],"type":"Point"}
}