{
  "type": "Feature",
  "properties": {
    "iso:country":"US",
    "sg:address":"2618 W Peterson Ave",
    "sg:city":"Chicago",
    "sg:classifiers":[
        {
            "category":"Personal",
            "type":"Services"
        }
    ],
    "sg:phone":"+1 773 508 1500",
    "sg:postcode":"60659",
    "sg:province":"IL",
    "sg:tags":[
        "electrolysis"
    ],
    "wof:name":"Body Works Electrolysis & Skin",
    "wof:placetype":"venue"
},
  "geometry": {"coordinates":[-87.695106,41.990543],"type":"Point"}
}