{
  "type": "Feature",
  "properties": {
    "iso:country":"US",
    "sg:address":"9338 Kilbourn Ave",
    "sg:city":"Skokie",
    "sg:classifiers":[
        {
            "category":"Wholesale",
            "subcategory":"Auto Parts",
            "type":"Manufacturing & Wholesale Goods"
        }
    ],
    "sg:phone":"+1 847 675 0998",
    "sg:postcode":"60076",
    "sg:province":"IL",
    "sg:tags":[
        "repair",
        "brake"
    ],
    "wof:name":"Northside Auto Brake Parts Inc",
    "wof:placetype":"venue"
},
  "geometry": {"coordinates":[-87.73939900000001,42.050507],"type":"Point"}
}