{
  "type": "Feature",
  "properties": {
    "iso:country":"US",
    "sg:address":"2 E 2nd St",
    "sg:city":"Danville",
    "sg:classifiers":[
        {
            "category":"Government",
            "subcategory":"Police Station",
            "type":"Public Place"
        }
    ],
    "sg:phone":"+1 217 431 2250",
    "sg:postcode":"61832",
    "sg:province":"IL",
    "sg:tags":[
        "department",
        "protection"
    ],
    "wof:name":"Danville Police Department",
    "wof:placetype":"venue"
},
  "geometry": {"coordinates":[-87.635579,40.1152],"type":"Point"}
}