{
  "type": "Feature",
  "properties": {
    "addr:full":"2711 Killarney Dr Cary IL 60013",
    "addr:housenumber":"2711",
    "addr:postcode":"60013",
    "addr:street":"Killarney Dr",
    "iso:country":"US",
    "sg:address":"2711 Killarney Dr",
    "sg:city":"Cary",
    "sg:classifiers":[
        {
            "category":"Building & Trades",
            "subcategory":"Construction",
            "type":"Services"
        }
    ],
    "sg:phone":"+1 847 639 0701",
    "sg:postcode":"60013",
    "sg:province":"IL",
    "sg:tags":[
        "house"
    ],
    "wof:name":"Wilson Hill Home Renovations",
    "wof:placetype":"venue"
},
  "geometry": {"coordinates":[-88.249137,42.234383],"type":"Point"}
}