{
  "type": "Feature",
  "properties": {
    "addr:full":"205 W Broadway St Bradley IL 60915",
    "addr:housenumber":"205",
    "addr:postcode":"60915",
    "addr:street":"W Broadway St",
    "iso:country":"US",
    "sg:address":"205 W Broadway St",
    "sg:city":"Bradley",
    "sg:classifiers":[
        {
            "category":"Organizations",
            "subcategory":"Religious Organization",
            "type":"Services"
        }
    ],
    "sg:phone":"+1 815 937 0720",
    "sg:postcode":"60915",
    "sg:province":"IL",
    "wof:name":"Evangelical Church Alliance",
    "wof:placetype":"venue"
},
  "geometry": {"coordinates":[-87.864867,41.14245],"type":"Point"}
}