{
  "type": "Feature",
  "properties": {
    "addr:full":"1850 Oak St Northfield IL 60093",
    "addr:housenumber":"1850",
    "addr:postcode":"60093",
    "addr:street":"Oak St",
    "iso:country":"US",
    "sg:address":"1850 Oak St",
    "sg:city":"Northfield",
    "sg:classifiers":[
        {
            "category":"Health Services",
            "subcategory":"Clinic",
            "type":"Services"
        }
    ],
    "sg:phone":"+1 847 441 9330",
    "sg:postcode":"60093",
    "sg:province":"IL",
    "sg:tags":[
        "spa",
        "medical"
    ],
    "wof:name":"Medispa",
    "wof:placetype":"venue"
},
  "geometry": {"coordinates":[-87.771565,42.105005],"type":"Point"}
}