{
  "type": "Feature",
  "properties": {
    "iso:country":"US",
    "sg:address":"3517 Main St",
    "sg:city":"Skokie",
    "sg:classifiers":[
        {
            "category":"Professional",
            "subcategory":"Business Services",
            "type":"Services"
        }
    ],
    "sg:phone":"+1 847 673 5261",
    "sg:postcode":"60076",
    "sg:province":"IL",
    "sg:tags":[
        "operator",
        "trucking"
    ],
    "wof:name":"Calovic Express Inc",
    "wof:placetype":"venue"
},
  "geometry": {"coordinates":[-87.716571,42.033548],"type":"Point"}
}