{
  "type": "Feature",
  "properties": {
    "iso:country":"US",
    "sg:address":"255 Oak St",
    "sg:city":"Frankfort",
    "sg:classifiers":[
        {
            "category":"Real Estate",
            "subcategory":"Real Estate Operator",
            "type":"Services"
        }
    ],
    "sg:phone":"+1 815 469 2151",
    "sg:postcode":"60423",
    "sg:province":"IL",
    "wof:name":"M & C Development & Inv Co",
    "wof:placetype":"venue"
},
  "geometry": {"coordinates":[-87.850927,41.494806],"type":"Point"}
}