{
  "type": "Feature",
  "properties": {
    "iso:country":"US",
    "sg:address":"5904 162nd Ave",
    "sg:city":"Milan",
    "sg:classifiers":[
        {
            "category":"Professional",
            "subcategory":"Management & Consulting",
            "type":"Services"
        }
    ],
    "sg:phone":"+1 309 756 2280",
    "sg:postcode":"61264",
    "sg:province":"IL",
    "sg:tags":[
        "social"
    ],
    "wof:name":"Mosaic",
    "wof:placetype":"venue"
},
  "geometry": {"coordinates":[-90.521164,41.35546],"type":"Point"}
}