{
  "type": "Feature",
  "properties": {
    "addr:full":"520 N 30th St Quincy IL 62301",
    "addr:housenumber":"520",
    "addr:postcode":"62301",
    "addr:street":"N 30Th St",
    "iso:country":"US",
    "sg:address":"520 N 30th St",
    "sg:city":"Quincy",
    "sg:classifiers":[
        {
            "category":"Professional",
            "subcategory":"Lawyer & Legal Services",
            "type":"Services"
        }
    ],
    "sg:phone":"+1 217 224 4020",
    "sg:postcode":"62301",
    "sg:province":"IL",
    "sg:tags":[
        "attorney"
    ],
    "wof:name":"Cashman & Kuhlman",
    "wof:placetype":"venue"
},
  "geometry": {"coordinates":[-91.367659,39.937722],"type":"Point"}
}