{
  "type": "Feature",
  "properties": {
    "addr:full":"5525 W Roosevelt Rd Cicero IL 60804",
    "addr:housenumber":"5525",
    "addr:postcode":"60804",
    "addr:street":"W Roosevelt Rd",
    "iso:country":"US",
    "sg:address":"5525 W Roosevelt Rd",
    "sg:city":"Cicero",
    "sg:classifiers":[
        {
            "category":"Building & Trades",
            "subcategory":"Construction",
            "type":"Services"
        }
    ],
    "sg:phone":"+1 708 222 0747",
    "sg:postcode":"60804",
    "sg:province":"IL",
    "sg:tags":[
        "general",
        "contractor"
    ],
    "wof:name":"D & L Construction",
    "wof:placetype":"venue"
},
  "geometry": {"coordinates":[-87.763479,41.865542],"type":"Point"}
}