{
  "type": "Feature",
  "properties": {
    "iso:country":"US",
    "sg:address":"1424 Sherman Rd",
    "sg:city":"Romeoville",
    "sg:classifiers":[
        {
            "category":"Wholesale",
            "subcategory":"Construction Materials",
            "type":"Manufacturing & Wholesale Goods"
        }
    ],
    "sg:phone":"+1 630 739 5252",
    "sg:postcode":"60446",
    "sg:province":"IL",
    "sg:tags":[
        "mfg"
    ],
    "sg:website":"www.customwoodstairs.com",
    "wof:name":"Customwood Stairs Inc",
    "wof:placetype":"venue"
},
  "geometry": {"coordinates":[-88.056631,41.678456],"type":"Point"}
}