{
  "type": "Feature",
  "properties": {
    "addr:full":"441 E Willow St Carbondale IL 62901",
    "addr:housenumber":"441",
    "addr:postcode":"62901",
    "addr:street":"E Willow St",
    "iso:country":"US",
    "sg:address":"441 E Willow St",
    "sg:city":"Carbondale",
    "sg:classifiers":[
        {
            "category":"Government",
            "subcategory":"Jail",
            "type":"Public Place"
        }
    ],
    "sg:phone":"+1   ",
    "sg:postcode":"62901",
    "sg:province":"IL",
    "sg:tags":[
        "correctional",
        "institution"
    ],
    "wof:name":"Corrections Illinois Dept",
    "wof:placetype":"venue"
},
  "geometry": {"coordinates":[-89.21230199999999,37.734211],"type":"Point"}
}