{
  "type": "Feature",
  "properties": {
    "iso:country":"US",
    "sg:address":"3625 215th St",
    "sg:city":"Matteson",
    "sg:classifiers":[
        {
            "category":"Education",
            "subcategory":"School",
            "type":"Public Place"
        }
    ],
    "sg:phone":"+1 708 748 0100",
    "sg:postcode":"60443",
    "sg:province":"IL",
    "sg:tags":[
        "district"
    ],
    "wof:name":"Matteson Elmntary Schl Dst 162",
    "wof:placetype":"venue"
},
  "geometry": {"coordinates":[-87.70479400000001,41.498316],"type":"Point"}
}