{
  "type": "Feature",
  "properties": {
    "addr:full":"8100 W 111th St Palos Hills IL 60465",
    "addr:housenumber":"8100",
    "addr:postcode":"60465",
    "addr:street":"W 111Th St",
    "iso:country":"US",
    "sg:address":"8100 W 111th St",
    "sg:city":"Palos Hills",
    "sg:classifiers":[
        {
            "category":"Food & Beverages",
            "subcategory":"Groceries & Convenience Stores",
            "type":"Retail Goods"
        }
    ],
    "sg:phone":"+1 708 974 3802",
    "sg:postcode":"60465",
    "sg:province":"IL",
    "sg:website":"www.newenglandpantry.com",
    "wof:name":"White Hen Pantry",
    "wof:placetype":"venue"
},
  "geometry": {"coordinates":[-87.818963,41.689614],"type":"Point"}
}