{
  "type": "Feature",
  "properties": {
    "addr:full":"1074 Louise Ln Joliet IL 60431",
    "addr:housenumber":"1074",
    "addr:postcode":"60431",
    "addr:street":"Louise Ln",
    "iso:country":"US",
    "sg:address":"1074 Louise Ln",
    "sg:city":"Joliet",
    "sg:classifiers":[
        {
            "category":"Personal",
            "type":"Services"
        }
    ],
    "sg:phone":"+1   ",
    "sg:postcode":"60431",
    "sg:province":"IL",
    "sg:tags":[
        "tuxedo",
        "rental"
    ],
    "wof:name":"Gingiss Formal Wear Louis Jlt",
    "wof:placetype":"venue"
},
  "geometry": {"coordinates":[-88.168109,41.502861],"type":"Point"}
}