{
  "type": "Feature",
  "properties": {
    "iso:country":"US",
    "sg:address":"1260 W Washington St",
    "sg:city":"Pittsfield",
    "sg:classifiers":[
        {
            "category":"Communications",
            "subcategory":"Radio Station",
            "type":"Services"
        }
    ],
    "sg:phone":"+1 217 285 5975",
    "sg:postcode":"62363",
    "sg:province":"IL",
    "sg:tags":[
        "company",
        "broadcasting"
    ],
    "wof:name":"WBBA",
    "wof:placetype":"venue"
},
  "geometry": {"coordinates":[-90.827282,39.604634],"type":"Point"}
}