{
  "type": "Feature",
  "properties": {
    "iso:country":"US",
    "sg:address":"1439 N Evergreen Ln",
    "sg:city":"Columbia",
    "sg:classifiers":[
        {
            "category":"Real Estate",
            "subcategory":"Real Estate Agent",
            "type":"Services"
        }
    ],
    "sg:phone":"+1 618 281 4880",
    "sg:postcode":"62236",
    "sg:province":"IL",
    "sg:tags":[
        "finding",
        "apartment",
        "rental"
    ],
    "wof:name":"Hawthorn Place Apartments",
    "wof:placetype":"venue"
},
  "geometry": {"coordinates":[-90.21874,38.451796],"type":"Point"}
}