{
  "type": "Feature",
  "properties": {
    "iso:country":"US",
    "sg:address":"2619 W Springfield Ave",
    "sg:city":"Champaign",
    "sg:classifiers":[
        {
            "category":"Retail",
            "subcategory":"Veterinary Services",
            "type":"Services"
        },
        {
            "category":"Retail",
            "subcategory":"Pet Boarding",
            "type":"Services"
        }
    ],
    "sg:phone":"+1 217 356 6481",
    "sg:postcode":"61821",
    "sg:province":"IL",
    "sg:tags":[
        "veterinarian",
        "boarding/pet",
        "sitting"
    ],
    "wof:name":"Country View Veterinary Clinic",
    "wof:placetype":"venue"
},
  "geometry": {"coordinates":[-88.290001,40.112701],"type":"Point"}
}