{
  "type": "Feature",
  "properties": {
    "iso:country":"US",
    "sg:address":"87 Golfview Dr",
    "sg:city":"Glendale Heights",
    "sg:classifiers":[
        {
            "category":"Professional",
            "subcategory":"Accounting & Tax Preparation",
            "type":"Services"
        }
    ],
    "sg:phone":"+1 630 510 8631",
    "sg:postcode":"60139",
    "sg:province":"IL",
    "wof:name":"Metz Assoc",
    "wof:placetype":"venue"
},
  "geometry": {"coordinates":[-88.0962,41.91129],"type":"Point"}
}