{
  "type": "Feature",
  "properties": {
    "iso:country":"US",
    "sg:address":"20727 Cattail Rd",
    "sg:city":"Fulton",
    "sg:classifiers":[
        {
            "category":"Organizations",
            "subcategory":"Community Association",
            "type":"Services"
        }
    ],
    "sg:phone":"+1 815 589 2440",
    "sg:postcode":"61252",
    "sg:province":"IL",
    "sg:tags":[
        "club"
    ],
    "wof:name":"Fulton Country Club",
    "wof:placetype":"venue"
},
  "geometry": {"coordinates":[-90.143382,41.878319],"type":"Point"}
}