{
  "type": "Feature",
  "properties": {
    "addr:full":"25092 Crabtree Ln Ingleside IL 60041",
    "addr:housenumber":"25092",
    "addr:postcode":"60041",
    "addr:street":"Crabtree Ln",
    "iso:country":"US",
    "sg:address":"25092 Crabtree Ln",
    "sg:city":"Ingleside",
    "sg:classifiers":[
        {
            "category":"Insurance",
            "subcategory":"Insurance Agent",
            "type":"Services"
        }
    ],
    "sg:phone":"+1 847 838 4740",
    "sg:postcode":"60041",
    "sg:province":"IL",
    "wof:name":"New York Life Insurance Co",
    "wof:placetype":"venue"
},
  "geometry": {"coordinates":[-88.12207100000001,42.390339],"type":"Point"}
}