{
  "type": "Feature",
  "properties": {
    "addr:full":"5311 S Harlem Ave Chicago IL 60638",
    "addr:housenumber":"5311",
    "addr:postcode":"60638",
    "addr:street":"S Harlem Ave",
    "iso:country":"US",
    "sg:address":"5311 S Harlem Ave",
    "sg:city":"Chicago",
    "sg:classifiers":[
        {
            "category":"Health Services",
            "subcategory":"Doctor",
            "type":"Services"
        }
    ],
    "sg:phone":"+1 773 586 0076",
    "sg:postcode":"60638",
    "sg:province":"IL",
    "wof:name":"Woman's Health Care",
    "wof:placetype":"venue"
},
  "geometry": {"coordinates":[-87.801399,41.795601],"type":"Point"}
}