{
  "type": "Feature",
  "properties": {
    "iso:country":"US",
    "sg:address":"302 S Superior St",
    "sg:city":"Ramsey",
    "sg:classifiers":[
        {
            "category":"Restaurant",
            "type":"Food & Drink"
        }
    ],
    "sg:menulink":"http://www.allmenus.com/il/ramsey/226401-caseys-general-store/menu/",
    "sg:phone":"+1 618 423 9328",
    "sg:postcode":"62080",
    "sg:province":"IL",
    "sg:tags":[
        "american",
        "pizza"
    ],
    "wof:name":"Casey's General Store",
    "wof:placetype":"venue"
},
  "geometry": {"coordinates":[-89.108298,39.142188],"type":"Point"}
}