{
  "type": "Feature",
  "properties": {
    "iso:country":"US",
    "sg:address":"12350 Waverly Rd",
    "sg:city":"Waverly",
    "sg:classifiers":[
        {
            "category":"Building & Trades",
            "subcategory":"Construction",
            "type":"Services"
        }
    ],
    "sg:phone":"+1 217 435 9021",
    "sg:postcode":"62692",
    "sg:province":"IL",
    "sg:tags":[
        "garden"
    ],
    "wof:name":"Contain A Pet",
    "wof:placetype":"venue"
},
  "geometry": {"coordinates":[-89.926867,39.618782],"type":"Point"}
}