{
  "type": "Feature",
  "properties": {
    "iso:country":"US",
    "sg:address":"1043 Abbot Ln",
    "sg:city":"Park Forest",
    "sg:classifiers":[
        {
            "category":"Social Services",
            "subcategory":"Child Care",
            "type":"Services"
        }
    ],
    "sg:phone":"+1 708 534 8737",
    "sg:postcode":"60466",
    "sg:province":"IL",
    "sg:tags":[
        "day"
    ],
    "wof:name":"Cathy Hudson",
    "wof:placetype":"venue"
},
  "geometry": {"coordinates":[-87.6738,41.433468],"type":"Point"}
}