{
  "type": "Feature",
  "properties": {
    "iso:country":"US",
    "sg:address":"927 4th St",
    "sg:city":"Beloit",
    "sg:classifiers":[
        {
            "category":"Retail",
            "subcategory":"Auto Rental",
            "type":"Services"
        }
    ],
    "sg:phone":"+1 608 363 0055",
    "sg:postcode":"53511",
    "sg:province":"IL",
    "sg:tags":[
        "renting",
        "automobile",
        "car"
    ],
    "wof:name":"Enterprise Rent-A-Car Company",
    "wof:placetype":"venue"
},
  "geometry": {"coordinates":[-89.03780999999999,42.50859],"type":"Point"}
}