{
  "type": "Feature",
  "properties": {
    "iso:country":"US",
    "sg:address":"2215 York Road Suite 414",
    "sg:city":"Oak Brook",
    "sg:classifiers":[
        {
            "category":"Professional",
            "subcategory":"Computer Services",
            "type":"Services"
        }
    ],
    "sg:phone":"+1 480 557 8000",
    "sg:postcode":"60523",
    "sg:province":"IL",
    "sg:website":"http://www.itracs.com/",
    "wof:name":"iTracs",
    "wof:placetype":"venue"
},
  "geometry": {"coordinates":[-87.929096,41.845966],"type":"Point"}
}