{
  "type": "Feature",
  "properties": {
    "addr:full":"4201 Shabbona Grove Rd Shabbona IL 60550",
    "addr:housenumber":"4201",
    "addr:postcode":"60550",
    "addr:street":"Shabbona Grove Rd",
    "iso:country":"US",
    "sg:address":"4201 Shabbona Grove Rd",
    "sg:city":"Shabbona",
    "sg:classifiers":[
        {
            "category":"Restaurant",
            "type":"Food & Drink"
        }
    ],
    "sg:phone":"+1 815 824 2481",
    "sg:postcode":"60550",
    "sg:province":"IL",
    "sg:tags":[
        "style",
        "family"
    ],
    "wof:name":"Pokanoka's Restaurant",
    "wof:placetype":"venue"
},
  "geometry": {"coordinates":[-88.86528800000001,41.732208],"type":"Point"}
}