{
  "type": "Feature",
  "properties": {
    "iso:country":"US",
    "sg:address":"5 E Van Buren St",
    "sg:city":"Joliet",
    "sg:classifiers":[
        {
            "category":"Organizations",
            "subcategory":"Non-profit Organization",
            "type":"Services"
        }
    ],
    "sg:phone":"+1 815 483 2090",
    "sg:postcode":"60432",
    "sg:province":"IL",
    "sg:tags":[
        "charity"
    ],
    "wof:name":"Charity Splits",
    "wof:placetype":"venue"
},
  "geometry": {"coordinates":[-88.081411,41.525931],"type":"Point"}
}