{
  "type": "Feature",
  "properties": {
    "iso:country":"US",
    "sg:address":"226 Westgate Dr",
    "sg:city":"Carol Stream",
    "sg:classifiers":[
        {
            "category":"Building & Trades",
            "subcategory":"Plumbing",
            "type":"Services"
        }
    ],
    "sg:phone":"+1 630 665 6620",
    "sg:postcode":"60188",
    "sg:province":"IL",
    "sg:tags":[
        "air",
        "heating",
        "conditioning",
        "contractor"
    ],
    "wof:name":"Ram Mechanical Services Inc",
    "wof:placetype":"venue"
},
  "geometry": {"coordinates":[-88.1281,41.899698],"type":"Point"}
}