{
  "type": "Feature",
  "properties": {
    "iso:country":"US",
    "sg:address":"5850 N State Rte 2",
    "sg:city":"Oregon",
    "sg:classifiers":[
        {
            "category":"Home & Garden",
            "subcategory":"Garden Supply",
            "type":"Retail Goods"
        }
    ],
    "sg:phone":"+1   ",
    "sg:postcode":"61061",
    "sg:province":"IL",
    "wof:name":"Fawn Madow Nurs Tree Spade Svc",
    "wof:placetype":"venue"
},
  "geometry": {"coordinates":[-89.327021,42.092998],"type":"Point"}
}