{
  "type": "Feature",
  "properties": {
    "iso:country":"US",
    "sg:address":"630 N Addison Rd",
    "sg:city":"Villa Park",
    "sg:classifiers":[
        {
            "category":"Food & Beverages",
            "subcategory":"Groceries & Convenience Stores",
            "type":"Retail Goods"
        }
    ],
    "sg:phone":"+1   ",
    "sg:postcode":"60181",
    "sg:province":"IL",
    "wof:name":"Kothari Foods",
    "wof:placetype":"venue"
},
  "geometry": {"coordinates":[-87.988536,41.902489],"type":"Point"}
}