{
  "type": "Feature",
  "properties": {
    "iso:country":"US",
    "sg:address":"309 E Railroad Ave",
    "sg:city":"Genoa",
    "sg:classifiers":[
        {
            "category":"Local Transit",
            "type":"Transportation"
        }
    ],
    "sg:phone":"+1 815 784 2300",
    "sg:postcode":"60135",
    "sg:province":"IL",
    "sg:tags":[
        "passenger"
    ],
    "wof:name":"Genoa-Kingston Resue Squad",
    "wof:placetype":"venue"
},
  "geometry": {"coordinates":[-88.687746,42.098601],"type":"Point"}
}