{
  "type": "Feature",
  "properties": {
    "iso:country":"US",
    "sg:address":"1108 Wembley Dr",
    "sg:city":"Island Lake",
    "sg:classifiers":[
        {
            "category":"Building & Trades",
            "subcategory":"Construction",
            "type":"Services"
        }
    ],
    "sg:phone":"+1 847 526 4564",
    "sg:postcode":"60042",
    "sg:province":"IL",
    "sg:tags":[
        "floor",
        "laying",
        "contractor"
    ],
    "wof:name":"Hometown Flooring Designs Inc",
    "wof:placetype":"venue"
},
  "geometry": {"coordinates":[-88.219275,42.273929],"type":"Point"}
}