{
  "type": "Feature",
  "properties": {
    "addr:full":"2126 W Van Buren St Chicago IL 60612",
    "addr:housenumber":"2126",
    "addr:postcode":"60612",
    "addr:street":"W Van Buren St",
    "iso:country":"US",
    "sg:address":"2126 W Van Buren St",
    "sg:city":"Chicago",
    "sg:classifiers":[
        {
            "category":"Building & Trades",
            "subcategory":"Construction",
            "type":"Services"
        }
    ],
    "sg:phone":"+1 312 666 2323",
    "sg:postcode":"60612",
    "sg:province":"IL",
    "sg:tags":[
        "contractor"
    ],
    "sg:website":"www.mcvandevelopment.com",
    "wof:name":"McVan Development General Contractor",
    "wof:placetype":"venue"
},
  "geometry": {"coordinates":[-87.680054,41.876328],"type":"Point"}
}