{
  "type": "Feature",
  "properties": {
    "iso:country":"US",
    "sg:address":"305 N Easton St",
    "sg:city":"Staunton",
    "sg:classifiers":[
        {
            "category":"Building & Trades",
            "subcategory":"Construction",
            "type":"Services"
        }
    ],
    "sg:phone":"+1 618 635 3121",
    "sg:postcode":"62088",
    "sg:province":"IL",
    "sg:tags":[
        "general",
        "contractor"
    ],
    "wof:name":"Feldmann Construction",
    "wof:placetype":"venue"
},
  "geometry": {"coordinates":[-89.781842,39.014998],"type":"Point"}
}