{
  "type": "Feature",
  "properties": {
    "iso:country":"US",
    "sg:address":"530 W 10th St",
    "sg:city":"Rock Falls",
    "sg:classifiers":[
        {
            "category":"Professional",
            "subcategory":"Business Services",
            "type":"Services"
        }
    ],
    "sg:phone":"+1 815 625 4766",
    "sg:postcode":"61071",
    "sg:province":"IL",
    "sg:tags":[
        "appraiser"
    ],
    "wof:name":"Herb Beveroth Realtors",
    "wof:placetype":"venue"
},
  "geometry": {"coordinates":[-89.696434,41.772546],"type":"Point"}
}