{
  "type": "Feature",
  "properties": {
    "addr:full":"110 E Jackson St Joliet IL 60432",
    "addr:housenumber":"110",
    "addr:postcode":"60432",
    "addr:street":"E Jackson St",
    "iso:country":"US",
    "sg:address":"110 E Jackson St",
    "sg:city":"Joliet",
    "sg:classifiers":[
        {
            "category":"Food & Beverages",
            "subcategory":"Liquor & Beverages",
            "type":"Retail Goods"
        }
    ],
    "sg:phone":"+1   ",
    "sg:postcode":"60432",
    "sg:province":"IL",
    "sg:tags":[
        "alcoholic"
    ],
    "wof:name":"Aa",
    "wof:placetype":"venue"
},
  "geometry": {"coordinates":[-88.07898900000001,41.531503],"type":"Point"}
}