{
  "type": "Feature",
  "properties": {
    "iso:country":"US",
    "sg:address":"720 N Larrabee St",
    "sg:city":"Chicago",
    "sg:classifiers":[
        {
            "category":"Real Estate",
            "subcategory":"Real Estate Services",
            "type":"Services"
        }
    ],
    "sg:phone":"+1 312 836 1235",
    "sg:postcode":"60654",
    "sg:province":"IL",
    "sg:tags":[
        "management",
        "condominium"
    ],
    "wof:name":"Two River Place Condo Assoc",
    "wof:placetype":"venue"
},
  "geometry": {"coordinates":[-87.64294599999999,41.895276],"type":"Point"}
}