{
  "type": "Feature",
  "properties": {
    "iso:country":"US",
    "sg:address":"7501 Industrial Dr",
    "sg:city":"Forest Park",
    "sg:classifiers":[
        {
            "category":"Food & Beverages",
            "subcategory":"Meat & Fish",
            "type":"Retail Goods"
        }
    ],
    "sg:phone":"+1 708 488 6001",
    "sg:postcode":"60130",
    "sg:province":"IL",
    "sg:tags":[
        "shop"
    ],
    "wof:name":"Weinstein Wholesale Meats",
    "wof:placetype":"venue"
},
  "geometry": {"coordinates":[-87.81125299999999,41.855215],"type":"Point"}
}