{
  "type": "Feature",
  "properties": {
    "addr:full":"2107 Belvidere Rd Waukegan IL 60085",
    "addr:housenumber":"2107",
    "addr:postcode":"60085",
    "addr:street":"Belvidere Rd",
    "iso:country":"US",
    "sg:address":"2107 Belvidere Rd",
    "sg:city":"Waukegan",
    "sg:classifiers":[
        {
            "category":"Shopping",
            "subcategory":"Shoes",
            "type":"Retail Goods"
        }
    ],
    "sg:phone":"+1   ",
    "sg:postcode":"60085",
    "sg:province":"IL",
    "wof:name":"Josefina Esparza",
    "wof:placetype":"venue"
},
  "geometry": {"coordinates":[-87.86224799999999,42.350275],"type":"Point"}
}