{
  "type": "Feature",
  "properties": {
    "addr:full":"11950 S Cicero Ave Alsip IL 60803",
    "addr:housenumber":"11950",
    "addr:postcode":"60803",
    "addr:street":"S Cicero Ave",
    "iso:country":"US",
    "sg:address":"11950 S Cicero Ave",
    "sg:city":"Alsip",
    "sg:classifiers":[
        {
            "category":"Food & Beverages",
            "subcategory":"Groceries & Convenience Stores",
            "type":"Retail Goods"
        }
    ],
    "sg:phone":"+1 708 389 0387",
    "sg:postcode":"60803",
    "sg:province":"IL",
    "sg:website":"www.7-eleven.com",
    "wof:name":"7-Eleven",
    "wof:placetype":"venue"
},
  "geometry": {"coordinates":[-87.739197,41.6754],"type":"Point"}
}