{
  "type": "Feature",
  "properties": {
    "addr:full":"7353 S Cicero Ave Chicago IL 60629",
    "addr:housenumber":"7353",
    "addr:postcode":"60629",
    "addr:street":"S Cicero Ave",
    "iso:country":"US",
    "sg:address":"7353 S Cicero Ave",
    "sg:city":"Chicago",
    "sg:classifiers":[
        {
            "category":"Airline",
            "type":"Transportation"
        }
    ],
    "sg:phone":"+1 800 433 7300",
    "sg:postcode":"60629",
    "sg:province":"IL",
    "sg:website":"http://chicago.citysearch.com/profile/external/603442272/chicago_il/american_airlines.html?publisher=yellowpages&reference_id=1&placement=ypwebsitemip",
    "wof:name":"American Airlines",
    "wof:placetype":"venue"
},
  "geometry": {"coordinates":[-87.74172,41.759509],"type":"Point"}
}