{
  "type": "Feature",
  "properties": {
    "iso:country":"US",
    "sg:address":"5991 Karl Rd",
    "sg:city":"Decatur",
    "sg:classifiers":[
        {
            "category":"Manufacturing",
            "subcategory":"Food",
            "type":"Manufacturing & Wholesale Goods"
        },
        {
            "category":"Farming",
            "subcategory":"Farm",
            "type":"Manufacturing & Wholesale Goods"
        }
    ],
    "sg:phone":"+1 217 864 3335",
    "sg:postcode":"62521",
    "sg:province":"IL",
    "sg:tags":[
        "corn",
        "product"
    ],
    "wof:name":"William White",
    "wof:placetype":"venue"
},
  "geometry": {"coordinates":[-88.908891,39.767812],"type":"Point"}
}