{
  "type": "Feature",
  "properties": {
    "addr:full":"214 N Ottawa St Joliet IL 60432",
    "addr:housenumber":"214",
    "addr:postcode":"60432",
    "addr:street":"N Ottawa St",
    "iso:country":"US",
    "sg:address":"214 N Ottawa St",
    "sg:city":"Joliet",
    "sg:classifiers":[
        {
            "category":"Education",
            "subcategory":"Special Training",
            "type":"Public Place"
        }
    ],
    "sg:phone":"+1 815 727 2714",
    "sg:postcode":"60432",
    "sg:province":"IL",
    "sg:tags":[
        "organization",
        "educational",
        "cooperative"
    ],
    "wof:name":"Three Rivers Education",
    "wof:placetype":"venue"
},
  "geometry": {"coordinates":[-88.083016,41.528465],"type":"Point"}
}