{
  "type": "Feature",
  "properties": {
    "addr:full":"636 Hampshire St Quincy IL 62301",
    "addr:housenumber":"636",
    "addr:postcode":"62301",
    "addr:street":"Hampshire St",
    "iso:country":"US",
    "sg:address":"636 Hampshire St",
    "sg:city":"Quincy",
    "sg:classifiers":[
        {
            "category":"Real Estate",
            "subcategory":"Real Estate Services",
            "type":"Services"
        }
    ],
    "sg:phone":"+1 217 222 6109",
    "sg:postcode":"62301",
    "sg:province":"IL",
    "sg:tags":[
        "abstract",
        "insurance",
        "title"
    ],
    "wof:name":"Midwest Abstract Co",
    "wof:placetype":"venue"
},
  "geometry": {"coordinates":[-91.406176,39.933131],"type":"Point"}
}