{
  "type": "Feature",
  "properties": {
    "iso:country":"US",
    "sg:address":"204 E 3rd St",
    "sg:city":"Dixon",
    "sg:classifiers":[
        {
            "category":"Travel",
            "subcategory":"Hotels & Motels",
            "type":"Entertainment"
        }
    ],
    "sg:phone":"+1 815 288 3351",
    "sg:postcode":"61021",
    "sg:province":"IL",
    "sg:tags":[
        "operation"
    ],
    "wof:name":"Crawford House Inn",
    "wof:placetype":"venue"
},
  "geometry": {"coordinates":[-89.47929600000001,41.842263],"type":"Point"}
}