{
  "type": "Feature",
  "properties": {
    "addr:full":"117 E Main St Camargo IL 61913",
    "addr:housenumber":"117",
    "addr:postcode":"61913",
    "addr:street":"E Main St",
    "iso:country":"US",
    "sg:address":"117 E Main St",
    "sg:city":"Camargo",
    "sg:classifiers":[
        {
            "category":"Health Services",
            "subcategory":"Clinic",
            "type":"Services"
        }
    ],
    "sg:phone":"+1 217 832 2602",
    "sg:postcode":"61913",
    "sg:province":"IL",
    "wof:name":"Family Health Ctr",
    "wof:placetype":"venue"
},
  "geometry": {"coordinates":[-88.163741,39.79992],"type":"Point"}
}