{
  "type": "Feature",
  "properties": {
    "iso:country":"US",
    "sg:address":"18165 N 4th Ave",
    "sg:city":"Coffeen",
    "sg:classifiers":[
        {
            "category":"Farming",
            "subcategory":"Livestock Farm",
            "type":"Manufacturing & Wholesale Goods"
        }
    ],
    "sg:phone":"+1 217 534 6347",
    "sg:postcode":"62017",
    "sg:province":"IL",
    "sg:tags":[
        "beef",
        "feedlot",
        "cattle"
    ],
    "wof:name":"Forsee Stock Farm",
    "wof:placetype":"venue"
},
  "geometry": {"coordinates":[-89.357616,39.056859],"type":"Point"}
}