{
  "type": "Feature",
  "properties": {
    "iso:country":"US",
    "sg:address":"1100 Alexander St",
    "sg:city":"Eldorado",
    "sg:classifiers":[
        {
            "category":"Education",
            "subcategory":"School",
            "type":"Public Place"
        }
    ],
    "sg:phone":"+1 618 273 9324",
    "sg:postcode":"62930",
    "sg:province":"IL",
    "sg:website":"www.eldorado.k12.il.us",
    "wof:name":"Eldorado Elementary School",
    "wof:placetype":"venue"
},
  "geometry": {"coordinates":[-88.437516,37.827047],"type":"Point"}
}