{
  "type": "Feature",
  "properties": {
    "addr:full":"300 Ravinia Pl Orland Park IL 60462",
    "addr:housenumber":"300",
    "addr:postcode":"60462",
    "addr:street":"Ravinia Pl",
    "iso:country":"US",
    "sg:address":"300 Ravinia Pl",
    "sg:city":"Orland Park",
    "sg:classifiers":[
        {
            "category":"Retail",
            "subcategory":"Repair Shop",
            "type":"Services"
        }
    ],
    "sg:phone":"+1 708 460 2555",
    "sg:postcode":"60462",
    "sg:province":"IL",
    "sg:tags":[
        "appliance"
    ],
    "wof:name":"United Refrigeration",
    "wof:placetype":"venue"
},
  "geometry": {"coordinates":[-87.853498,41.61534],"type":"Point"}
}