{
  "type": "Feature",
  "properties": {
    "iso:country":"US",
    "sg:address":"6655 N Avondale Ave Ste 5",
    "sg:city":"Chicago",
    "sg:classifiers":[
        {
            "category":"Building & Trades",
            "subcategory":"Construction",
            "type":"Services"
        }
    ],
    "sg:phone":"+1 773 631 1555",
    "sg:postcode":"60631",
    "sg:province":"IL",
    "sg:tags":[
        "windows-repair",
        "siding",
        "replacement",
        "installation",
        "contractor"
    ],
    "wof:name":"Norwood Siding Installation Co Inc",
    "wof:placetype":"venue"
},
  "geometry": {"coordinates":[-87.81713999999999,42.000946],"type":"Point"}
}