{
  "type": "Feature",
  "properties": {
    "iso:country":"US",
    "sg:address":"2635 Broadway St",
    "sg:city":"Quincy",
    "sg:classifiers":[
        {
            "category":"Restaurant",
            "type":"Food & Drink"
        }
    ],
    "sg:phone":"+1   ",
    "sg:postcode":"62301",
    "sg:province":"IL",
    "sg:tags":[
        "eating"
    ],
    "wof:name":"Tower of Pizza & Mexican",
    "wof:placetype":"venue"
},
  "geometry": {"coordinates":[-91.373129,39.935404],"type":"Point"}
}