{
  "type": "Feature",
  "properties": {
    "iso:country":"US",
    "sg:address":"5247 S Keeler Ave",
    "sg:city":"Chicago",
    "sg:classifiers":[
        {
            "category":"Banks & Credit Unions",
            "subcategory":"Bank",
            "type":"Services"
        }
    ],
    "sg:phone":"+1 773 582 2262",
    "sg:postcode":"60632",
    "sg:province":"IL",
    "wof:name":"Yale Polishers & Platers Incorporated",
    "wof:placetype":"venue"
},
  "geometry": {"coordinates":[-87.727997,41.7976],"type":"Point"}
}