{
  "type": "Feature",
  "properties": {
    "addr:full":"1008 E Geneva Rd Wheaton IL 60187",
    "addr:housenumber":"1008",
    "addr:postcode":"60187",
    "addr:street":"E Geneva Rd",
    "iso:country":"US",
    "sg:address":"1008 E Geneva Rd",
    "sg:city":"Wheaton",
    "sg:classifiers":[
        {
            "category":"Professional",
            "subcategory":"Accounting & Tax Preparation",
            "type":"Services"
        }
    ],
    "sg:phone":"+1 630 752 1410",
    "sg:postcode":"60187",
    "sg:province":"IL",
    "sg:tags":[
        "accountant"
    ],
    "wof:name":"AAA American Accounting & Tax Services",
    "wof:placetype":"venue"
},
  "geometry": {"coordinates":[-88.09169799999999,41.888302],"type":"Point"}
}