{
  "type": "Feature",
  "properties": {
    "iso:country":"US",
    "sg:address":"1600 W 103rd St",
    "sg:city":"Chicago",
    "sg:classifiers":[
        {
            "category":"Professional",
            "type":"Services"
        }
    ],
    "sg:phone":"+1 773 429 9890",
    "sg:postcode":"60643",
    "sg:province":"IL",
    "sg:tags":[
        "relocation"
    ],
    "wof:name":"Anita Green Relocation Managem",
    "wof:placetype":"venue"
},
  "geometry": {"coordinates":[-87.662064,41.706699],"type":"Point"}
}