{
  "type": "Feature",
  "properties": {
    "addr:full":"6316 N Cicero Ave Chicago IL 60646",
    "addr:housenumber":"6316",
    "addr:postcode":"60646",
    "addr:street":"N Cicero Ave",
    "iso:country":"US",
    "sg:address":"6316 N Cicero Ave",
    "sg:city":"Chicago",
    "sg:classifiers":[
        {
            "category":"Professional",
            "subcategory":"Accounting & Tax Preparation",
            "type":"Services"
        }
    ],
    "sg:phone":"+1 773 725 6800",
    "sg:postcode":"60646",
    "sg:province":"IL",
    "wof:name":"S K Associates",
    "wof:placetype":"venue"
},
  "geometry": {"coordinates":[-87.748409,41.993075],"type":"Point"}
}