{
  "type": "Feature",
  "properties": {
    "iso:country":"US",
    "sg:address":"2637 N Central Ave",
    "sg:city":"Chicago",
    "sg:classifiers":[
        {
            "category":"Restaurant",
            "type":"Food & Drink"
        }
    ],
    "sg:phone":"+1 773 836 8009",
    "sg:postcode":"60639",
    "sg:province":"IL",
    "sg:tags":[
        "chinese"
    ],
    "wof:name":"Chinese Chef's Kitchen",
    "wof:placetype":"venue"
},
  "geometry": {"coordinates":[-87.766037,41.928732],"type":"Point"}
}