{
  "type": "Feature",
  "properties": {
    "addr:full":"5900 N Milwaukee Ave Chicago IL 60646",
    "addr:housenumber":"5900",
    "addr:postcode":"60646",
    "addr:street":"N Milwaukee Ave",
    "iso:country":"US",
    "sg:address":"5900 N Milwaukee Ave",
    "sg:city":"Chicago",
    "sg:classifiers":[
        {
            "category":"Education",
            "subcategory":"Vocational School",
            "type":"Public Place"
        },
        {
            "category":"Education",
            "subcategory":"University",
            "type":"Public Place"
        }
    ],
    "sg:phone":"+1 773 594 7729",
    "sg:postcode":"60646",
    "sg:province":"IL",
    "sg:tags":[
        "technical",
        "industrial",
        "college",
        "business",
        "trade"
    ],
    "wof:name":"American Academy Of Massage",
    "wof:placetype":"venue"
},
  "geometry": {"coordinates":[-87.77961000000001,41.98864],"type":"Point"}
}