{
  "type": "Feature",
  "properties": {
    "iso:country":"US",
    "sg:address":"55 W Monroe St Suite 900",
    "sg:city":"Chicago",
    "sg:classifiers":[
        {
            "category":"Professional",
            "subcategory":"Lawyer & Legal Services",
            "type":"Services"
        }
    ],
    "sg:phone":"+1 312 346 6444",
    "sg:postcode":"60603",
    "sg:province":"IL",
    "sg:website":"www.capronlaw.com",
    "wof:name":"Capron & Avgerinos",
    "wof:placetype":"venue"
},
  "geometry": {"coordinates":[-87.630144,41.880356],"type":"Point"}
}