{
  "type": "Feature",
  "properties": {
    "addr:full":"175 S Wall St Kankakee IL 60901",
    "addr:housenumber":"175",
    "addr:postcode":"60901",
    "addr:street":"S Wall St",
    "iso:country":"US",
    "sg:address":"175 S Wall St",
    "sg:city":"Kankakee",
    "sg:classifiers":[
        {
            "category":"Health Services",
            "subcategory":"Health Practitioner",
            "type":"Services"
        }
    ],
    "sg:phone":"+1 815 935 3007",
    "sg:postcode":"60901",
    "sg:province":"IL",
    "sg:tags":[
        "worker",
        "psychiatric",
        "social"
    ],
    "wof:name":"Stress Management Workshop",
    "wof:placetype":"venue"
},
  "geometry": {"coordinates":[-87.880672,41.12101],"type":"Point"}
}