{
  "type": "Feature",
  "properties": {
    "iso:country":"US",
    "sg:address":"RR 31",
    "sg:city":"Carpentersville",
    "sg:classifiers":[
        {
            "category":"Restaurant",
            "type":"Food & Drink"
        }
    ],
    "sg:phone":"+1 847 426 3446",
    "sg:postcode":"60110",
    "sg:province":"IL",
    "wof:name":"Floyd's Restaurant Inc",
    "wof:placetype":"venue"
},
  "geometry": {"coordinates":[-88.267899,42.1227],"type":"Point"}
}