{
  "type": "Feature",
  "properties": {
    "iso:country":"US",
    "sg:address":"7014 Tall Grass Ct",
    "sg:city":"Spring Grove",
    "sg:classifiers":[
        {
            "category":"Building & Trades",
            "subcategory":"Construction",
            "type":"Services"
        }
    ],
    "sg:phone":"+1 815 675 1494",
    "sg:postcode":"60081",
    "sg:province":"IL",
    "sg:tags":[
        "home",
        "builder"
    ],
    "wof:name":"Mainstay Home Builders Corp",
    "wof:placetype":"venue"
},
  "geometry": {"coordinates":[-88.27146999999999,42.42767],"type":"Point"}
}