{
  "type": "Feature",
  "properties": {
    "iso:country":"US",
    "sg:address":"100 S 2nd St",
    "sg:city":"Oregon",
    "sg:classifiers":[
        {
            "category":"Bars & Pubs",
            "type":"Food & Drink"
        }
    ],
    "sg:phone":"+1 815 732 3319",
    "sg:postcode":"61061",
    "sg:province":"IL",
    "wof:name":"Breakers Saloon & Eatery",
    "wof:placetype":"venue"
},
  "geometry": {"coordinates":[-89.32999700000001,42.014542],"type":"Point"}
}