{
  "type": "Feature",
  "properties": {
    "iso:country":"US",
    "sg:address":"6333 N Clark St",
    "sg:city":"Chicago",
    "sg:classifiers":[
        {
            "category":"Professional",
            "subcategory":"Management & Consulting",
            "type":"Services"
        },
        {
            "category":"Professional",
            "subcategory":"Advertising",
            "type":"Services"
        },
        {
            "category":"Professional",
            "subcategory":"Business Services",
            "type":"Services"
        },
        {
            "category":"Professional",
            "subcategory":"Art Services",
            "type":"Services"
        }
    ],
    "sg:phone":"+1 773 465 9958",
    "sg:postcode":"60660",
    "sg:province":"IL",
    "sg:tags":[
        "development",
        "product",
        "graphic",
        "marketing",
        "designer",
        "program",
        "design",
        "consultant"
    ],
    "sg:website":"http://www.edlgraphics.com",
    "wof:name":"Edl Marketing Graphics",
    "wof:placetype":"venue"
},
  "geometry": {"coordinates":[-87.670334,41.997386],"type":"Point"}
}