{
  "type": "Feature",
  "properties": {
    "addr:full":"105 White Clover Dr Chillicothe IL 61523",
    "addr:housenumber":"105",
    "addr:postcode":"61523",
    "addr:street":"White Clover Dr",
    "iso:country":"US",
    "sg:address":"105 White Clover Dr",
    "sg:city":"Chillicothe",
    "sg:phone":"+1 309 274 3795",
    "sg:postcode":"61523",
    "sg:province":"IL",
    "sg:tags":[
        "food",
        "farm",
        "product",
        "corn",
        "soybean"
    ],
    "wof:name":"Russell Jackson",
    "wof:placetype":"venue"
},
  "geometry": {"coordinates":[-89.51445,40.907611],"type":"Point"}
}