{
  "type": "Feature",
  "properties": {
    "iso:country":"US",
    "sg:address":"1835 Oak Park Ave",
    "sg:city":"Berwyn",
    "sg:classifiers":[
        {
            "category":"Building & Trades",
            "subcategory":"Construction",
            "type":"Services"
        }
    ],
    "sg:phone":"+1 312 525 9866",
    "sg:postcode":"60402",
    "sg:province":"IL",
    "sg:tags":[
        "road",
        "contractor"
    ],
    "wof:name":"J & G Construction",
    "wof:placetype":"venue"
},
  "geometry": {"coordinates":[-87.793459,41.854771],"type":"Point"}
}