{
  "type": "Feature",
  "properties": {
    "iso:country":"US",
    "sg:address":"1201 Tuscola Blvd",
    "sg:city":"Tuscola",
    "sg:classifiers":[
        {
            "category":"Travel",
            "subcategory":"Hotels & Motels",
            "type":"Entertainment"
        },
        {
            "category":"Retail",
            "subcategory":"Event Space",
            "type":"Services"
        }
    ],
    "sg:phone":"+1 800 345 8082",
    "sg:postcode":"61953",
    "sg:province":"IL",
    "sg:tags":[
        "facility",
        "banquet",
        "reception",
        "lodging",
        "corporate",
        "hall"
    ],
    "sg:website":"http://ad.doubleclick.net/clk;222816988;46581822;v?http://www.hiexpress.com/redirect?path=hd&brandCode=ex&hotelCode=tsctb&_PMID=99601036&cm_mmc=mdpr-_-yellowpages-_-ex-_-tsctb",
    "wof:name":"Holiday Inn Express Tuscola",
    "wof:placetype":"venue"
},
  "geometry": {"coordinates":[-88.269514,39.790354],"type":"Point"}
}