{
  "type": "Feature",
  "properties": {
    "iso:country":"US",
    "sg:address":"11030 S Breuning Rd",
    "sg:city":"Elizabeth",
    "sg:classifiers":[
        {
            "category":"Real Estate",
            "subcategory":"Real Estate Operator",
            "type":"Services"
        }
    ],
    "sg:phone":"+1 815 598 3386",
    "sg:postcode":"61028",
    "sg:province":"IL",
    "sg:tags":[
        "property",
        "lessor"
    ],
    "wof:name":"Allen Van Brocklin",
    "wof:placetype":"venue"
},
  "geometry": {"coordinates":[-90.096254,42.208703],"type":"Point"}
}