{
  "type": "Feature",
  "properties": {
    "iso:country":"US",
    "sg:address":"5 Darby Ln",
    "sg:city":"Lincolnshire",
    "sg:classifiers":[
        {
            "category":"Professional",
            "subcategory":"Management & Consulting",
            "type":"Services"
        }
    ],
    "sg:phone":"+1 847 948 5656",
    "sg:postcode":"60069",
    "sg:province":"IL",
    "sg:tags":[
        "consultant",
        "training"
    ],
    "wof:name":"Lyerly Seminars Inc",
    "wof:placetype":"venue"
},
  "geometry": {"coordinates":[-87.913864,42.192859],"type":"Point"}
}