{
  "type": "Feature",
  "properties": {
    "addr:full":"234 N Northwest Hwy Palatine IL 60067",
    "addr:housenumber":"234",
    "addr:postcode":"60067",
    "addr:street":"N Northwest Hwy",
    "iso:country":"US",
    "sg:address":"234 N Northwest Hwy",
    "sg:city":"Palatine",
    "sg:classifiers":[
        {
            "category":"Recreation",
            "type":"Entertainment"
        }
    ],
    "sg:phone":"+1   ",
    "sg:postcode":"60067",
    "sg:province":"IL",
    "sg:tags":[
        "frame",
        "art",
        "gallery"
    ],
    "wof:name":"Gallery NW Lampshades & Things",
    "wof:placetype":"venue"
},
  "geometry": {"coordinates":[-88.03398300000001,42.116785],"type":"Point"}
}