{
  "type": "Feature",
  "properties": {
    "iso:country":"US",
    "sg:address":"1055 W Argyle Street",
    "sg:city":"Chicago",
    "sg:classifiers":[
        {
            "category":"Restaurant",
            "type":"Food & Drink"
        }
    ],
    "sg:phone":"+1 773 561 4077",
    "sg:postcode":"60640",
    "sg:province":"IL",
    "sg:tags":[
        "chinese",
        "vietnamese"
    ],
    "sg:website":"www.haiyenrestaurant.com/",
    "wof:name":"Hai Yen Restaurant",
    "wof:placetype":"venue"
},
  "geometry": {"coordinates":[-87.6567,41.973301],"type":"Point"}
}