{
  "type": "Feature",
  "properties": {
    "iso:country":"US",
    "sg:address":"6718 Cermak Rd",
    "sg:city":"Berwyn",
    "sg:classifiers":[
        {
            "category":"Health Services",
            "subcategory":"Doctor",
            "type":"Services"
        }
    ],
    "sg:phone":"+1 707 484 4404",
    "sg:postcode":"60402",
    "sg:province":"IL",
    "sg:tags":[
        "dentist"
    ],
    "wof:name":"Berwyn Dental Center",
    "wof:placetype":"venue"
},
  "geometry": {"coordinates":[-87.791397,41.850601],"type":"Point"}
}