{
  "type": "Feature",
  "properties": {
    "iso:country":"US",
    "sg:address":"316 S Oakwood Ave",
    "sg:city":"Geneseo",
    "sg:classifiers":[
        {
            "category":"Organizations",
            "subcategory":"Religious Organization",
            "type":"Services"
        }
    ],
    "sg:phone":"+1 309 944 3993",
    "sg:postcode":"61254",
    "sg:province":"IL",
    "sg:website":"www.geneseolutheranchurch.com",
    "wof:name":"Concordia Lutheran Church",
    "wof:placetype":"venue"
},
  "geometry": {"coordinates":[-90.153893,41.450396],"type":"Point"}
}