{
  "type": "Feature",
  "properties": {
    "iso:country":"US",
    "sg:address":"538 S Diamond St",
    "sg:city":"Jacksonville",
    "sg:classifiers":[
        {
            "category":"Bars & Pubs",
            "type":"Food & Drink"
        }
    ],
    "sg:phone":"+1   ",
    "sg:postcode":"62650",
    "sg:province":"IL",
    "sg:tags":[
        "drinking"
    ],
    "wof:name":"Danielle Sound Inc",
    "wof:placetype":"venue"
},
  "geometry": {"coordinates":[-90.238541,39.730069],"type":"Point"}
}