{
  "type": "Feature",
  "properties": {
    "addr:full":"5400 W 95th St Oak Lawn IL 60453",
    "addr:housenumber":"5400",
    "addr:postcode":"60453",
    "addr:street":"W 95Th St",
    "iso:country":"US",
    "sg:address":"5400 W 95th St",
    "sg:city":"Oak Lawn",
    "sg:classifiers":[
        {
            "category":"Banks & Credit Unions",
            "subcategory":"Bank",
            "type":"Services"
        }
    ],
    "sg:phone":"+1 708 907 7440",
    "sg:postcode":"60453",
    "sg:province":"IL",
    "wof:name":"Archer Bank",
    "wof:placetype":"venue"
},
  "geometry": {"coordinates":[-87.755494,41.720017],"type":"Point"}
}