{
  "type": "Feature",
  "properties": {
    "addr:full":"305 Arrowhead Dr Shorewood IL 60404",
    "addr:housenumber":"305",
    "addr:postcode":"60404",
    "addr:street":"Arrowhead Dr",
    "iso:country":"US",
    "sg:address":"305 Arrowhead Dr",
    "sg:city":"Shorewood",
    "sg:classifiers":[
        {
            "category":"Arts & Performance",
            "subcategory":"Theater",
            "type":"Entertainment"
        }
    ],
    "sg:phone":"+1 815 725 2461",
    "sg:postcode":"60404",
    "sg:province":"IL",
    "sg:tags":[
        "magician"
    ],
    "wof:name":"Magic & Illusion",
    "wof:placetype":"venue"
},
  "geometry": {"coordinates":[-88.207859,41.524441],"type":"Point"}
}