{
  "type": "Feature",
  "properties": {
    "addr:full":"1934 W Chicago Ave Chicago IL 60622",
    "addr:housenumber":"1934",
    "addr:postcode":"60622",
    "addr:street":"W Chicago Ave",
    "iso:country":"US",
    "sg:address":"1934 W Chicago Ave",
    "sg:city":"Chicago",
    "sg:classifiers":[
        {
            "category":"Food & Beverages",
            "subcategory":"Liquor & Beverages",
            "type":"Retail Goods"
        }
    ],
    "sg:phone":"+1 773 489 6758",
    "sg:postcode":"60622",
    "sg:province":"IL",
    "sg:tags":[
        "beer",
        "spirit",
        "wine"
    ],
    "wof:name":"Jalisco Liquor",
    "wof:placetype":"venue"
},
  "geometry": {"coordinates":[-87.67600299999999,41.896],"type":"Point"}
}