{
  "type": "Feature",
  "properties": {
    "addr:full":"505 E Grant St Macomb IL 61455",
    "addr:housenumber":"505",
    "addr:postcode":"61455",
    "addr:street":"E Grant St",
    "iso:country":"US",
    "sg:address":"505 E Grant St",
    "sg:city":"Macomb",
    "sg:classifiers":[
        {
            "category":"Health Services",
            "subcategory":"Doctor",
            "type":"Services"
        }
    ],
    "sg:phone":"+1 309 837 9985",
    "sg:postcode":"61455",
    "sg:province":"IL",
    "wof:name":"Bobofchak Bruce J DDS",
    "wof:placetype":"venue"
},
  "geometry": {"coordinates":[-90.66615899999999,40.447855],"type":"Point"}
}