{
  "type": "Feature",
  "properties": {
    "iso:country":"US",
    "sg:address":"505 E Grant St",
    "sg:city":"Macomb",
    "sg:classifiers":[
        {
            "category":"Health Services",
            "subcategory":"Doctor",
            "type":"Services"
        }
    ],
    "sg:phone":"+1 309 837 9985",
    "sg:postcode":"61455",
    "sg:province":"IL",
    "wof:name":"Bobofchak Bruce J DDS",
    "wof:placetype":"venue"
},
  "geometry": {"coordinates":[-90.666159,40.447855],"type":"Point"}
}