{
  "type": "Feature",
  "properties": {
    "iso:country":"US",
    "sg:address":"W Suburban Hospital Me",
    "sg:city":"Oak Park",
    "sg:classifiers":[
        {
            "category":"Health Services",
            "subcategory":"Doctor",
            "type":"Services"
        },
        {
            "category":"Health Services",
            "subcategory":"Hospital",
            "type":"Services"
        }
    ],
    "sg:phone":"+1 773 880 3570",
    "sg:postcode":"60301",
    "sg:province":"IL",
    "wof:name":"Children's Memorial Hospital",
    "wof:placetype":"venue"
},
  "geometry": {"coordinates":[-87.796997,41.8885],"type":"Point"}
}