{
  "type": "Feature",
  "properties": {
    "iso:country":"US",
    "sg:address":"1006 Maple St",
    "sg:city":"Lawrenceville",
    "sg:classifiers":[
        {
            "category":"Place Of Worship",
            "subcategory":"Church",
            "type":"Public Place"
        },
        {
            "category":"Place Of Worship",
            "type":"Public Place"
        },
        {
            "category":"Organizations",
            "subcategory":"Religious Organization",
            "type":"Services"
        }
    ],
    "sg:phone":"+1 618 943 5812",
    "sg:postcode":"62439",
    "sg:province":"IL",
    "sg:tags":[
        "churches-methodist",
        "clergy"
    ],
    "wof:name":"Free Methodist Church",
    "wof:placetype":"venue"
},
  "geometry": {"coordinates":[-87.681073,38.72616],"type":"Point"}
}