{
  "type": "Feature",
  "properties": {
    "addr:full":"11610 S Austin Ave Alsip IL 60803",
    "addr:housenumber":"11610",
    "addr:postcode":"60803",
    "addr:street":"S Austin Ave",
    "iso:country":"US",
    "sg:address":"11610 S Austin Ave",
    "sg:city":"Alsip",
    "sg:classifiers":[
        {
            "category":"Wholesale",
            "subcategory":"Hardware",
            "type":"Manufacturing & Wholesale Goods"
        }
    ],
    "sg:phone":"+1 708 371 0747",
    "sg:postcode":"60803",
    "sg:province":"IL",
    "sg:tags":[
        "fastener",
        "metal"
    ],
    "sg:website":"www.fascofasteners.com",
    "wof:name":"Fasco Inc",
    "wof:placetype":"venue"
},
  "geometry": {"coordinates":[-87.76865100000001,41.679638],"type":"Point"}
}