{
  "type": "Feature",
  "properties": {
    "iso:country":"US",
    "sg:address":"2320 20th Ave",
    "sg:city":"Rockford",
    "sg:classifiers":[
        {
            "category":"Building & Trades",
            "subcategory":"Plumbing",
            "type":"Services"
        }
    ],
    "sg:phone":"+1 815 965 7450",
    "sg:postcode":"61104",
    "sg:province":"IL",
    "sg:tags":[
        "plumbing",
        "contractor"
    ],
    "wof:name":"Elmer Carlson & Sons",
    "wof:placetype":"venue"
},
  "geometry": {"coordinates":[-89.060799,42.245847],"type":"Point"}
}