{
  "type": "Feature",
  "properties": {
    "addr:full":"1204 E Central Rd Arlington Heights IL 60005",
    "addr:housenumber":"1204",
    "addr:postcode":"60005",
    "addr:street":"E Central Rd",
    "iso:country":"US",
    "sg:address":"1204 E Central Rd",
    "sg:city":"Arlington Heights",
    "sg:classifiers":[
        {
            "category":"Professional",
            "subcategory":"Accounting & Tax Preparation",
            "type":"Services"
        }
    ],
    "sg:phone":"+1 847 670 3562",
    "sg:postcode":"60005",
    "sg:province":"IL",
    "wof:name":"Hollinger & Assoc",
    "wof:placetype":"venue"
},
  "geometry": {"coordinates":[-87.96773399999999,42.066451],"type":"Point"}
}