{
  "type": "Feature",
  "properties": {
    "iso:country":"US",
    "sg:address":"7240 Westfield Plaza Dr",
    "sg:city":"Belleville",
    "sg:classifiers":[
        {
            "category":"Shopping",
            "subcategory":"Shoes",
            "type":"Retail Goods"
        }
    ],
    "sg:phone":"+1 618 277 5458",
    "sg:postcode":"62223",
    "sg:province":"IL",
    "wof:name":"Payless Shoe Source",
    "wof:placetype":"venue"
},
  "geometry": {"coordinates":[-90.052241,38.545054],"type":"Point"}
}