{
  "type": "Feature",
  "properties": {
    "iso:country":"US",
    "sg:address":"9312 Clark Rd",
    "sg:city":"Richmond",
    "sg:classifiers":[
        {
            "category":"Retail",
            "subcategory":"Auto Repair",
            "type":"Services"
        }
    ],
    "sg:phone":"+1 815 675 6810",
    "sg:postcode":"60071",
    "sg:province":"IL",
    "sg:tags":[
        "body"
    ],
    "wof:name":"Restorations By Greg",
    "wof:placetype":"venue"
},
  "geometry": {"coordinates":[-88.26219500000001,42.462805],"type":"Point"}
}