{
  "type": "Feature",
  "properties": {
    "iso:country":"US",
    "sg:address":"510 Columbia St",
    "sg:city":"Joliet",
    "sg:classifiers":[
        {
            "category":"Education",
            "subcategory":"School",
            "type":"Public Place"
        }
    ],
    "sg:phone":"+1 815 727 7806",
    "sg:postcode":"60432",
    "sg:province":"IL",
    "wof:name":"St Thaddeus School",
    "wof:placetype":"venue"
},
  "geometry": {"coordinates":[-88.069242,41.536363],"type":"Point"}
}