{
  "type": "Feature",
  "properties": {
    "addr:full":"322 Piasa St Alton IL 62002",
    "addr:housenumber":"322",
    "addr:postcode":"62002",
    "addr:street":"Piasa St",
    "iso:country":"US",
    "sg:address":"322 Piasa St",
    "sg:city":"Alton",
    "sg:classifiers":[
        {
            "category":"Professional",
            "subcategory":"Computer Services",
            "type":"Services"
        }
    ],
    "sg:phone":"+1 618 462 4911",
    "sg:postcode":"62002",
    "sg:province":"IL",
    "sg:tags":[
        "programing",
        "custom"
    ],
    "wof:name":"Piasa Computers",
    "wof:placetype":"venue"
},
  "geometry": {"coordinates":[-90.18651199999999,38.891804],"type":"Point"}
}