{
  "type": "Feature",
  "properties": {
    "iso:country":"US",
    "sg:address":"14 N Sangamon Street",
    "sg:city":"Chicago",
    "sg:classifiers":[
        {
            "category":"Building & Trades",
            "subcategory":"Construction",
            "type":"Services"
        }
    ],
    "sg:phone":"+1 312 226 5265",
    "sg:postcode":"60607",
    "sg:province":"IL",
    "sg:tags":[
        "contractor"
    ],
    "wof:name":"Art House Lost Condiminium Assoc",
    "wof:placetype":"venue"
},
  "geometry": {"coordinates":[-87.65086599999999,41.881884],"type":"Point"}
}