{
  "type": "Feature",
  "properties": {
    "iso:country":"US",
    "sg:address":"315 Salem Pl",
    "sg:city":"Fairview Heights",
    "sg:classifiers":[
        {
            "category":"Shopping",
            "subcategory":"Used Merchandise",
            "type":"Retail Goods"
        }
    ],
    "sg:phone":"+1 618 628 1650",
    "sg:postcode":"62208",
    "sg:province":"IL",
    "sg:tags":[
        "antique"
    ],
    "wof:name":"St Clair Antique Mall",
    "wof:placetype":"venue"
},
  "geometry": {"coordinates":[-89.983299,38.602001],"type":"Point"}
}