{
  "type": "Feature",
  "properties": {
    "addr:full":"920 N Franklin St Ste 205 Chicago IL 60610",
    "addr:housenumber":"920",
    "addr:postcode":"60610",
    "addr:street":"N Franklin St Ste 205",
    "iso:country":"US",
    "sg:address":"920 N Franklin St Ste 205",
    "sg:city":"Chicago",
    "sg:classifiers":[
        {
            "category":"Health Services",
            "subcategory":"Hospital",
            "type":"Services"
        }
    ],
    "sg:phone":"+1 312 988 4500",
    "sg:postcode":"60610",
    "sg:province":"IL",
    "wof:name":"Illinois Center For Clinical Trials",
    "wof:placetype":"venue"
},
  "geometry": {"coordinates":[-87.63579,41.898876],"type":"Point"}
}