{
  "type": "Feature",
  "properties": {
    "iso:country":"US",
    "sg:address":"77 W Jackson Blvd",
    "sg:city":"Chicago",
    "sg:classifiers":[
        {
            "category":"Government",
            "subcategory":"Office",
            "type":"Public Place"
        }
    ],
    "sg:phone":"+1   ",
    "sg:postcode":"60661",
    "sg:province":"IL",
    "sg:tags":[
        "agency"
    ],
    "wof:name":"Foster Grandparent Program",
    "wof:placetype":"venue"
},
  "geometry": {"coordinates":[-87.629714,41.878161],"type":"Point"}
}