{
  "type": "Feature",
  "properties": {
    "addr:full":"2525 W Jefferson St Joliet IL 60435",
    "addr:housenumber":"2525",
    "addr:postcode":"60435",
    "addr:street":"W Jefferson St",
    "iso:country":"US",
    "sg:address":"2525 W Jefferson St",
    "sg:city":"Joliet",
    "sg:classifiers":[
        {
            "category":"Autos & Motor Vehicles",
            "subcategory":"Automobile Sales",
            "type":"Retail Goods"
        }
    ],
    "sg:phone":"+1 815 725 2575",
    "sg:postcode":"60435",
    "sg:province":"IL",
    "sg:tags":[
        "car",
        "dealer"
    ],
    "wof:name":"Bill Jacobs Joliet",
    "wof:placetype":"venue"
},
  "geometry": {"coordinates":[-88.149648,41.522121],"type":"Point"}
}