{
  "type": "Feature",
  "properties": {
    "addr:full":"5418 W Gale St Chicago IL 60630",
    "addr:housenumber":"5418",
    "addr:postcode":"60630",
    "addr:street":"W Gale St",
    "iso:country":"US",
    "sg:address":"5418 W Gale St",
    "sg:city":"Chicago",
    "sg:classifiers":[
        {
            "category":"Education",
            "subcategory":"College",
            "type":"Public Place"
        },
        {
            "category":"Organizations",
            "subcategory":"Membership Organization",
            "type":"Services"
        }
    ],
    "sg:phone":"+1 773 282 4747",
    "sg:postcode":"60630",
    "sg:province":"IL",
    "sg:tags":[
        "student",
        "housing",
        "fraternity",
        "sorority",
        "fraternal"
    ],
    "wof:name":"K Ing Oscar Lodge 855 Af Am",
    "wof:placetype":"venue"
},
  "geometry": {"coordinates":[-87.76464,41.969861],"type":"Point"}
}