{
  "type": "Feature",
  "properties": {
    "iso:country":"US",
    "sg:address":"1603 State Hwy 78",
    "sg:city":"Jacksonville",
    "sg:classifiers":[
        {
            "category":"Freight",
            "type":"Transportation"
        }
    ],
    "sg:phone":"+1 217 243 6053",
    "sg:postcode":"62650",
    "sg:province":"IL",
    "sg:tags":[
        "operator",
        "refuse",
        "local",
        "system",
        "trucking"
    ],
    "wof:name":"Angelos Trash Service",
    "wof:placetype":"venue"
},
  "geometry": {"coordinates":[-90.26062400000001,39.745204],"type":"Point"}
}