{
  "type": "Feature",
  "properties": {
    "addr:full":"1014 S Oakley Boulevard Apt 3 Chicago IL 60612",
    "addr:housenumber":"1014;3",
    "addr:postcode":"60612",
    "addr:street":"S Oakley Boulevard Apt",
    "iso:country":"US",
    "sg:address":"1014 S Oakley Boulevard Apt 3",
    "sg:city":"Chicago",
    "sg:classifiers":[
        {
            "category":"Building & Trades",
            "subcategory":"Plumbing",
            "type":"Services"
        }
    ],
    "sg:phone":"+1 312 421 8891",
    "sg:postcode":"60612",
    "sg:province":"IL",
    "wof:name":"Baca Plumbing Corporation",
    "wof:placetype":"venue"
},
  "geometry": {"coordinates":[-87.683769,41.868559],"type":"Point"}
}