{
  "type": "Feature",
  "properties": {
    "addr:full":"119 E 22nd Avenue A Coal Valley IL 61240",
    "addr:housenumber":"119",
    "addr:postcode":"61240",
    "addr:street":"E 22Nd Avenue A Coal",
    "iso:country":"US",
    "sg:address":"119 E 22nd Avenue A",
    "sg:city":"Coal Valley",
    "sg:classifiers":[
        {
            "category":"Restaurant",
            "type":"Food & Drink"
        }
    ],
    "sg:phone":"+1 309 799 7411",
    "sg:postcode":"61240",
    "sg:province":"IL",
    "sg:tags":[
        "pizza"
    ],
    "wof:name":"Headquarters Bar & Grill",
    "wof:placetype":"venue"
},
  "geometry": {"coordinates":[-90.4533,41.433701],"type":"Point"}
}