{
  "type": "Feature",
  "properties": {
    "addr:full":"2237 S Archer Ave Apt 2 Chicago IL 60616",
    "addr:housenumber":"2237;2",
    "addr:postcode":"60616",
    "addr:street":"S Archer Ave Apt",
    "iso:country":"US",
    "sg:address":"2237 S Archer Ave Apt 2",
    "sg:city":"Chicago",
    "sg:classifiers":[
        {
            "category":"Wholesale",
            "subcategory":"Groceries",
            "type":"Manufacturing & Wholesale Goods"
        }
    ],
    "sg:phone":"+1 312 731 4855",
    "sg:postcode":"60616",
    "sg:province":"IL",
    "sg:tags":[
        "grocers-wholesale"
    ],
    "wof:name":"E-Shops, Inc.",
    "wof:placetype":"venue"
},
  "geometry": {"coordinates":[-87.63654200000001,41.851998],"type":"Point"}
}