{
  "type": "Feature",
  "properties": {
    "addr:full":"700 W Irving Park Rd Streamwood IL 60107",
    "addr:housenumber":"700",
    "addr:postcode":"60107",
    "addr:street":"W Irving Park Rd",
    "iso:country":"US",
    "sg:address":"700 W Irving Park Rd",
    "sg:city":"Streamwood",
    "sg:classifiers":[
        {
            "category":"Community Center",
            "type":"Public Place"
        }
    ],
    "sg:phone":"+1 630 550 5269",
    "sg:postcode":"60107",
    "sg:province":"IL",
    "sg:tags":[
        "recreation"
    ],
    "wof:name":"Streamwood Park District",
    "wof:placetype":"venue"
},
  "geometry": {"coordinates":[-88.195351,42.017712],"type":"Point"}
}