{
  "type": "Feature",
  "properties": {
    "iso:country":"US",
    "sg:address":"107 W Main St 109",
    "sg:city":"Streator",
    "sg:classifiers":[
        {
            "category":"Organizations",
            "subcategory":"Membership Organization",
            "type":"Services"
        }
    ],
    "sg:phone":"+1 815 673 3708",
    "sg:postcode":"61364",
    "sg:province":"IL",
    "sg:tags":[
        "fraternal"
    ],
    "sg:website":"http://www.foe.com/",
    "wof:name":"Foe 645",
    "wof:placetype":"venue"
},
  "geometry": {"coordinates":[-88.835589,41.120908],"type":"Point"}
}