{
  "type": "Feature",
  "properties": {
    "iso:country":"US",
    "sg:address":"350 Circle Ave",
    "sg:city":"Forest Park",
    "sg:classifiers":[
        {
            "category":"Communications",
            "subcategory":"Newspaper",
            "type":"Services"
        }
    ],
    "sg:phone":"+1 708 366 8947",
    "sg:postcode":"60130",
    "sg:province":"IL",
    "sg:tags":[
        "print",
        "medium"
    ],
    "wof:name":"34 Publishing Inc",
    "wof:placetype":"venue"
},
  "geometry": {"coordinates":[-87.808381,41.880227],"type":"Point"}
}