{
  "type": "Feature",
  "properties": {
    "addr:full":"2600 Fremont St Rolling Meadows IL 60008",
    "addr:housenumber":"2600",
    "addr:postcode":"60008",
    "addr:street":"Fremont St",
    "iso:country":"US",
    "sg:address":"2600 Fremont St",
    "sg:city":"Rolling Meadows",
    "sg:classifiers":[
        {
            "category":"Arts & Performance",
            "subcategory":"Theater",
            "type":"Entertainment"
        }
    ],
    "sg:phone":"+1 847 670 7933",
    "sg:postcode":"60008",
    "sg:province":"IL",
    "sg:tags":[
        "theatrical"
    ],
    "wof:name":"Cross Country Production",
    "wof:placetype":"venue"
},
  "geometry": {"coordinates":[-88.016139,42.087434],"type":"Point"}
}