{
  "type": "Feature",
  "properties": {
    "iso:country":"US",
    "sg:address":"728 Fairfield Ave",
    "sg:city":"Elmhurst",
    "sg:classifiers":[
        {
            "category":"Wholesale",
            "subcategory":"Machinery & Supplies",
            "type":"Manufacturing & Wholesale Goods"
        }
    ],
    "sg:phone":"+1 630 834 7242",
    "sg:postcode":"60126",
    "sg:province":"IL",
    "sg:tags":[
        "equipment",
        "establishment"
    ],
    "wof:name":"B & F Power Washing",
    "wof:placetype":"venue"
},
  "geometry": {"coordinates":[-87.952001,41.876059],"type":"Point"}
}