{
  "type": "Feature",
  "properties": {
    "iso:country":"US",
    "sg:address":"1474 Sandypoint Dr",
    "sg:city":"Rockford",
    "sg:classifiers":[
        {
            "category":"Building & Trades",
            "subcategory":"Construction",
            "type":"Services"
        }
    ],
    "sg:phone":"+1 815 654 1901",
    "sg:postcode":"61103",
    "sg:province":"IL",
    "sg:tags":[
        "carpentry",
        "contractor"
    ],
    "wof:name":"Roys Construction Inc",
    "wof:placetype":"venue"
},
  "geometry": {"coordinates":[-89.067312,42.357488],"type":"Point"}
}