{
  "type": "Feature",
  "properties": {
    "iso:country":"US",
    "sg:address":"1000 Van Buren St",
    "sg:city":"Maywood",
    "sg:classifiers":[
        {
            "category":"Professional",
            "subcategory":"Management & Consulting",
            "type":"Services"
        },
        {
            "category":"Education",
            "subcategory":"Special Training",
            "type":"Public Place"
        },
        {
            "category":"Education",
            "subcategory":"School",
            "type":"Public Place"
        }
    ],
    "sg:phone":"+1 708 450 2100",
    "sg:postcode":"60153",
    "sg:province":"IL",
    "sg:tags":[
        "consultant",
        "educational",
        "tutoring"
    ],
    "wof:name":"Proviso Area-Exceptional Child",
    "wof:placetype":"venue"
},
  "geometry": {"coordinates":[-87.844803,41.873371],"type":"Point"}
}