{
  "type": "Feature",
  "properties": {
    "iso:country":"US",
    "sg:address":"1211 Forest Ave",
    "sg:city":"Oak Park",
    "sg:classifiers":[
        {
            "category":"Professional",
            "subcategory":"Management & Consulting",
            "type":"Services"
        }
    ],
    "sg:phone":"+1 708 383 4884",
    "sg:postcode":"60302",
    "sg:province":"IL",
    "sg:tags":[
        "outplacing",
        "resource",
        "outsourcing",
        "human"
    ],
    "wof:name":"Joseph Bucolo Associates LLC",
    "wof:placetype":"venue"
},
  "geometry": {"coordinates":[-87.80123399999999,41.90824],"type":"Point"}
}