{
  "type": "Feature",
  "properties": {
    "iso:country":"US",
    "sg:address":"3546 W 98th Pl",
    "sg:city":"Evergreen Park",
    "sg:classifiers":[
        {
            "category":"Autos & Motor Vehicles",
            "subcategory":"Automobile Sales",
            "type":"Retail Goods"
        }
    ],
    "sg:phone":"+1 708 425 7300",
    "sg:postcode":"60805",
    "sg:province":"IL",
    "sg:tags":[
        "limo"
    ],
    "wof:name":"Bylak Limousine Service",
    "wof:placetype":"venue"
},
  "geometry": {"coordinates":[-87.71075,41.714333],"type":"Point"}
}