{
  "type": "Feature",
  "properties": {
    "addr:full":"W Chicago Lakeshore 644 N Lake Shore Dr Chicago IL 60611",
    "addr:housenumber":"644",
    "addr:postcode":"60611",
    "addr:street":"W;Lakeshore;N Lake Shore Dr",
    "iso:country":"US",
    "sg:address":"W Chicago Lakeshore 644 N Lake Shore Dr",
    "sg:city":"Chicago",
    "sg:classifiers":[
        {
            "category":"Retail",
            "subcategory":"Event Space",
            "type":"Services"
        }
    ],
    "sg:postcode":"60611",
    "sg:province":"IL",
    "sg:tags":[
        "venue"
    ],
    "wof:name":"The Altitude Room",
    "wof:placetype":"venue"
},
  "geometry": {"coordinates":[-87.615577,41.89387],"type":"Point"}
}