{
  "type": "Feature",
  "properties": {
    "iso:country":"US",
    "sg:address":"738 S Buffalo Grove Rd",
    "sg:city":"Buffalo Grove",
    "sg:classifiers":[
        {
            "category":"Wholesale",
            "subcategory":"Medical Equipment & Supplies",
            "type":"Manufacturing & Wholesale Goods"
        }
    ],
    "sg:phone":"+1 847 520 4901",
    "sg:postcode":"60089",
    "sg:province":"IL",
    "wof:name":"Laima Medical Supplies Ltd",
    "wof:placetype":"venue"
},
  "geometry": {"coordinates":[-87.958618,42.141161],"type":"Point"}
}