{
  "type": "Feature",
  "properties": {
    "addr:full":"2701 Glenwood Ave Joliet IL 60435",
    "addr:housenumber":"2701",
    "addr:postcode":"60435",
    "addr:street":"Glenwood Ave",
    "iso:country":"US",
    "sg:address":"2701 Glenwood Ave",
    "sg:city":"Joliet",
    "sg:classifiers":[
        {
            "category":"Building & Trades",
            "subcategory":"Construction",
            "type":"Services"
        }
    ],
    "sg:phone":"+1 815 744 2223",
    "sg:postcode":"60435",
    "sg:province":"IL",
    "sg:tags":[
        "masonry",
        "contractor"
    ],
    "wof:name":"Barello Masonary Inc",
    "wof:placetype":"venue"
},
  "geometry": {"coordinates":[-88.150088,41.529333],"type":"Point"}
}