{
  "type": "Feature",
  "properties": {
    "iso:country":"US",
    "sg:address":"1035 Broadway St",
    "sg:city":"Hamilton",
    "sg:classifiers":[
        {
            "category":"Banks & Credit Unions",
            "subcategory":"Bank",
            "type":"Services"
        }
    ],
    "sg:phone":"+1 217 847 6675",
    "sg:postcode":"62341",
    "sg:province":"IL",
    "sg:tags":[
        "state",
        "commercial"
    ],
    "wof:name":"First State Bank",
    "wof:placetype":"venue"
},
  "geometry": {"coordinates":[-91.345056,40.393172],"type":"Point"}
}