{
  "type": "Feature",
  "properties": {
    "iso:country":"US",
    "sg:address":"1150 Davis Rd",
    "sg:city":"Elgin",
    "sg:classifiers":[
        {
            "category":"Manufacturing",
            "subcategory":"Food",
            "type":"Manufacturing & Wholesale Goods"
        }
    ],
    "sg:phone":"+1 847 608 7332",
    "sg:postcode":"60123",
    "sg:province":"IL",
    "sg:tags":[
        "product",
        "mfg"
    ],
    "wof:name":"Decadent Chocolates",
    "wof:placetype":"venue"
},
  "geometry": {"coordinates":[-88.303759,42.068185],"type":"Point"}
}