{
  "type": "Feature",
  "properties": {
    "addr:full":"239 E Randolph Chicago IL 60601",
    "addr:housenumber":"239",
    "addr:postcode":"60601",
    "addr:street":"E Randolph",
    "iso:country":"US",
    "sg:address":"239 E Randolph",
    "sg:city":"Chicago",
    "sg:classifiers":[
        {
            "category":"Sports & Exercise",
            "subcategory":"Bicycle Rental",
            "type":"Entertainment"
        },
        {
            "category":"Landmark",
            "subcategory":"Tourist Information",
            "type":"Public Place"
        }
    ],
    "sg:phone":"+1 312 729 1000",
    "sg:postcode":"60601",
    "sg:province":"IL",
    "sg:tags":[
        "tour",
        "bike"
    ],
    "sg:website":"www.bikechicago.com",
    "wof:name":"Bike and Roll Chicago",
    "wof:placetype":"venue"
},
  "geometry": {"coordinates":[-87.621117,41.8841],"type":"Point"}
}