{
  "type": "Feature",
  "properties": {
    "iso:country":"US",
    "sg:address":"4054 N Troy St",
    "sg:city":"Chicago",
    "sg:classifiers":[
        {
            "category":"Place Of Worship",
            "subcategory":"Church",
            "type":"Public Place"
        },
        {
            "category":"Place Of Worship",
            "type":"Public Place"
        }
    ],
    "sg:phone":"+1 773 267 2589",
    "sg:postcode":"60618",
    "sg:province":"IL",
    "sg:tags":[
        "testament",
        "churches-church",
        "christ",
        "christ-new"
    ],
    "wof:name":"Christ Church Of Rigelyveal",
    "wof:placetype":"venue"
},
  "geometry": {"coordinates":[-87.706813,41.954944],"type":"Point"}
}