{
  "type": "Feature",
  "properties": {
    "iso:country":"US",
    "sg:address":"7724 W 93rd St",
    "sg:city":"Oak Lawn",
    "sg:classifiers":[
        {
            "category":"Building & Trades",
            "subcategory":"Construction",
            "type":"Services"
        }
    ],
    "sg:phone":"+1 708 233 1647",
    "sg:postcode":"60457",
    "sg:province":"IL",
    "sg:tags":[
        "concrete",
        "contractor"
    ],
    "wof:name":"Westcoast Concrete Inc",
    "wof:placetype":"venue"
},
  "geometry": {"coordinates":[-87.81169300000001,41.722381],"type":"Point"}
}