{
  "type": "Feature",
  "properties": {
    "iso:country":"US",
    "sg:address":"5763 W 95th St",
    "sg:city":"Oak Lawn",
    "sg:classifiers":[
        {
            "category":"Bars & Pubs",
            "subcategory":"Nightclub",
            "type":"Food & Drink"
        }
    ],
    "sg:phone":"+1 708 636 1293",
    "sg:postcode":"60453",
    "sg:province":"IL",
    "sg:tags":[
        "nightlife"
    ],
    "wof:name":"Rusty Nail Lounge",
    "wof:placetype":"venue"
},
  "geometry": {"coordinates":[-87.76460299999999,41.719501],"type":"Point"}
}