{
  "type": "Feature",
  "properties": {
    "addr:full":"101 Griffin Pl SW Poplar Grove IL 61065",
    "addr:housenumber":"101",
    "addr:postcode":"61065",
    "addr:street":"Griffin Pl Sw",
    "iso:country":"US",
    "sg:address":"101 Griffin Pl SW",
    "sg:city":"Poplar Grove",
    "sg:classifiers":[
        {
            "category":"Building & Trades",
            "subcategory":"Construction",
            "type":"Services"
        }
    ],
    "sg:phone":"+1 815 243 2631",
    "sg:postcode":"61065",
    "sg:province":"IL",
    "sg:tags":[
        "contractor"
    ],
    "wof:name":"Ian Robbins Construction",
    "wof:placetype":"venue"
},
  "geometry": {"coordinates":[-88.87071899999999,42.347922],"type":"Point"}
}