{
  "type": "Feature",
  "properties": {
    "iso:country":"US",
    "sg:address":"2318 Cherry Hill Rd",
    "sg:city":"Joliet",
    "sg:classifiers":[
        {
            "category":"Professional",
            "type":"Services"
        }
    ],
    "sg:phone":"+1 815 723 1140",
    "sg:postcode":"60433",
    "sg:province":"IL",
    "sg:tags":[
        "establishment"
    ],
    "wof:name":"Green Glen Inc",
    "wof:placetype":"venue"
},
  "geometry": {"coordinates":[-88.02252799999999,41.484482],"type":"Point"}
}