{
  "type": "Feature",
  "properties": {
    "iso:country":"US",
    "sg:address":"7269 Harlem Rd",
    "sg:city":"Caledonia",
    "sg:classifiers":[
        {
            "category":"Building & Trades",
            "subcategory":"Construction",
            "type":"Services"
        }
    ],
    "sg:phone":"+1 815 885 4191",
    "sg:postcode":"61011",
    "sg:province":"IL",
    "sg:tags":[
        "general",
        "contractor"
    ],
    "wof:name":"Goebel Construction Co",
    "wof:placetype":"venue"
},
  "geometry": {"coordinates":[-88.97516,42.340864],"type":"Point"}
}