{
  "type": "Feature",
  "properties": {
    "addr:full":"9 N Vail Ave Arlington Hts IL 60005",
    "addr:housenumber":"9",
    "addr:postcode":"60005",
    "addr:street":"N Vail Ave",
    "iso:country":"US",
    "sg:address":"9 N Vail Ave",
    "sg:city":"Arlington Hts",
    "sg:classifiers":[
        {
            "category":"Wholesale",
            "subcategory":"Metals & Minerals",
            "type":"Manufacturing & Wholesale Goods"
        }
    ],
    "sg:phone":"+1 847 670 4326",
    "sg:postcode":"60005",
    "sg:province":"IL",
    "sg:tags":[
        "copper",
        "product"
    ],
    "wof:name":"Ecomold Products",
    "wof:placetype":"venue"
},
  "geometry": {"coordinates":[-87.984054,42.083691],"type":"Point"}
}