{
  "type": "Feature",
  "properties": {
    "addr:full":"307 W Court St Kankakee IL 60901",
    "addr:housenumber":"307",
    "addr:postcode":"60901",
    "addr:street":"W Court St",
    "iso:country":"US",
    "sg:address":"307 W Court St",
    "sg:city":"Kankakee",
    "sg:classifiers":[
        {
            "category":"Shopping",
            "type":"Retail Goods"
        }
    ],
    "sg:phone":"+1 815 939 4318",
    "sg:postcode":"60901",
    "sg:province":"IL",
    "sg:tags":[
        "cards",
        "sport",
        "baseball",
        "memorabilia"
    ],
    "wof:name":"Court Street Cards",
    "wof:placetype":"venue"
},
  "geometry": {"coordinates":[-87.870289,41.121087],"type":"Point"}
}