{
  "type": "Feature",
  "properties": {
    "addr:full":"4460 W Diversey Avenue Chicago IL 60639",
    "addr:housenumber":"4460",
    "addr:postcode":"60639",
    "addr:street":"W Diversey Avenue",
    "iso:country":"US",
    "sg:address":"4460 W Diversey Avenue",
    "sg:city":"Chicago",
    "sg:classifiers":[
        {
            "category":"Restaurant",
            "type":"Food & Drink"
        }
    ],
    "sg:phone":"+1 773 685 1162",
    "sg:postcode":"60639",
    "sg:province":"IL",
    "wof:name":"Poncitlan Jalisco Taqueria",
    "wof:placetype":"venue"
},
  "geometry": {"coordinates":[-87.739009,41.931646],"type":"Point"}
}