{
  "type": "Feature",
  "properties": {
    "iso:country":"US",
    "sg:address":"1920 N Keeler Ave",
    "sg:city":"Chicago",
    "sg:classifiers":[
        {
            "category":"Wholesale",
            "subcategory":"Books, Periodicals, & Newspapers",
            "type":"Manufacturing & Wholesale Goods"
        }
    ],
    "sg:phone":"+1 773 227 5340",
    "sg:postcode":"60639",
    "sg:province":"IL",
    "sg:tags":[
        "publishers-periodical"
    ],
    "sg:website":"http://www.microcapgems.com",
    "wof:name":"Microcap Gems",
    "wof:placetype":"venue"
},
  "geometry": {"coordinates":[-87.731371,41.91564],"type":"Point"}
}