{
  "type": "Feature",
  "properties": {
    "addr:full":"2309 3rd Ave Rock Island IL 61201",
    "addr:housenumber":"2309",
    "addr:postcode":"61201",
    "addr:street":"3Rd Ave",
    "iso:country":"US",
    "sg:address":"2309 3rd Ave",
    "sg:city":"Rock Island",
    "sg:classifiers":[
        {
            "category":"Building & Trades",
            "subcategory":"Construction",
            "type":"Services"
        }
    ],
    "sg:phone":"+1 309 786 3698",
    "sg:postcode":"61201",
    "sg:province":"IL",
    "sg:tags":[
        "downspouts",
        "gutter"
    ],
    "wof:name":"A-1 Heating & Gutters",
    "wof:placetype":"venue"
},
  "geometry": {"coordinates":[-90.566885,41.509971],"type":"Point"}
}