{
  "type": "Feature",
  "properties": {
    "iso:country":"US",
    "sg:address":"135 S La Salle Street",
    "sg:city":"Chicago",
    "sg:classifiers":[
        {
            "category":"Professional",
            "subcategory":"Lawyer & Legal Services",
            "type":"Services"
        }
    ],
    "sg:phone":"+1 312 782 1403",
    "sg:postcode":"60603",
    "sg:province":"IL",
    "wof:name":"Marsh D A Jr & Associates",
    "wof:placetype":"venue"
},
  "geometry": {"coordinates":[-87.632277,41.880345],"type":"Point"}
}