{
  "type": "Feature",
  "properties": {
    "iso:country":"US",
    "sg:address":"10601 Seymour Ave",
    "sg:city":"Franklin Park",
    "sg:classifiers":[
        {
            "category":"Professional",
            "subcategory":"Management & Consulting",
            "type":"Services"
        }
    ],
    "sg:phone":"+1 847 928 0428",
    "sg:postcode":"60131",
    "sg:province":"IL",
    "sg:tags":[
        "logistics"
    ],
    "sg:website":"www.apx.com",
    "wof:name":"Apx Logistics",
    "wof:placetype":"venue"
},
  "geometry": {"coordinates":[-87.891339,41.950663],"type":"Point"}
}