{
  "type": "Feature",
  "properties": {
    "addr:full":"7659 S Euclid Ave Chicago IL 60649",
    "addr:housenumber":"7659",
    "addr:postcode":"60649",
    "addr:street":"S Euclid Ave",
    "iso:country":"US",
    "sg:address":"7659 S Euclid Ave",
    "sg:city":"Chicago",
    "sg:classifiers":[
        {
            "category":"Professional",
            "subcategory":"Business Services",
            "type":"Services"
        }
    ],
    "sg:phone":"+1 773 221 4767",
    "sg:postcode":"60649",
    "sg:province":"IL",
    "wof:name":"Jupiter PC Solutions",
    "wof:placetype":"venue"
},
  "geometry": {"coordinates":[-87.577231,41.756304],"type":"Point"}
}