{
  "type": "Feature",
  "properties": {
    "addr:full":"105 May St West Chicago IL 60185",
    "addr:housenumber":"105",
    "addr:postcode":"60185",
    "addr:street":"May St",
    "iso:country":"US",
    "sg:address":"105 May St",
    "sg:city":"West Chicago",
    "sg:classifiers":[
        {
            "category":"Retail",
            "subcategory":"Repair Shop",
            "type":"Services"
        }
    ],
    "sg:phone":"+1 630 231 2418",
    "sg:postcode":"60185",
    "sg:province":"IL",
    "sg:tags":[
        "hardware",
        "electrical"
    ],
    "wof:name":"Phils Home Appliance Inc",
    "wof:placetype":"venue"
},
  "geometry": {"coordinates":[-88.20689900000001,41.863879],"type":"Point"}
}