{
  "type": "Feature",
  "properties": {
    "addr:full":"1 N State St Fl 16 Chicago IL 60602",
    "addr:housenumber":"1;16",
    "addr:postcode":"60602",
    "addr:street":"N State St Fl",
    "iso:country":"US",
    "sg:address":"1 N State St Fl 16",
    "sg:city":"Chicago",
    "sg:classifiers":[
        {
            "category":"Professional",
            "subcategory":"Research",
            "type":"Services"
        }
    ],
    "sg:phone":"+1 312 759 5200",
    "sg:postcode":"60602",
    "sg:province":"IL",
    "sg:tags":[
        "analysis",
        "market"
    ],
    "wof:name":"N O R C",
    "wof:placetype":"venue"
},
  "geometry": {"coordinates":[-87.62779999999999,41.882061],"type":"Point"}
}