{
  "type": "Feature",
  "properties": {
    "iso:country":"US",
    "sg:address":"4200 N Ashland Ave",
    "sg:city":"Chicago",
    "sg:classifiers":[
        {
            "category":"Banks & Credit Unions",
            "subcategory":"Bank",
            "type":"Services"
        }
    ],
    "sg:phone":"+1 773 847 6748",
    "sg:postcode":"60613",
    "sg:province":"IL",
    "sg:tags":[
        "saving",
        "commercial"
    ],
    "wof:name":"Lasalle Bank",
    "wof:placetype":"venue"
},
  "geometry": {"coordinates":[-87.669151,41.957958],"type":"Point"}
}