{
  "type": "Feature",
  "properties": {
    "iso:country":"US",
    "sg:address":"432 Florine Ct",
    "sg:city":"Cary",
    "sg:classifiers":[
        {
            "category":"Building & Trades",
            "subcategory":"Construction",
            "type":"Services"
        }
    ],
    "sg:phone":"+1 847 829 4353",
    "sg:postcode":"60013",
    "sg:province":"IL",
    "sg:tags":[
        "wallcoverings-installation",
        "wallpaper",
        "painting",
        "contractor"
    ],
    "wof:name":"Terence Lee Painting Inc",
    "wof:placetype":"venue"
},
  "geometry": {"coordinates":[-88.24674400000001,42.227572],"type":"Point"}
}