{
  "type": "Feature",
  "properties": {
    "addr:full":"564 Ryan Pl Lake Forest IL 60045",
    "addr:housenumber":"564",
    "addr:postcode":"60045",
    "addr:street":"Ryan Pl",
    "iso:country":"US",
    "sg:address":"564 Ryan Pl",
    "sg:city":"Lake Forest",
    "sg:classifiers":[
        {
            "category":"Real Estate",
            "subcategory":"Real Estate Operator",
            "type":"Services"
        }
    ],
    "sg:phone":"+1 847 234 6915",
    "sg:postcode":"60045",
    "sg:province":"IL",
    "sg:tags":[
        "owner",
        "industrial"
    ],
    "wof:name":"Leahy Realty Corporation",
    "wof:placetype":"venue"
},
  "geometry": {"coordinates":[-87.834435,42.24105],"type":"Point"}
}