{
  "type": "Feature",
  "properties": {
    "addr:full":"398 Church Rd Compton IL 61318",
    "addr:housenumber":"398",
    "addr:postcode":"61318",
    "addr:street":"Church Rd",
    "iso:country":"US",
    "sg:address":"398 Church Rd",
    "sg:city":"Compton",
    "sg:classifiers":[
        {
            "category":"Organizations",
            "subcategory":"Religious Organization",
            "type":"Services"
        }
    ],
    "sg:phone":"+1 815 539 6567",
    "sg:postcode":"61318",
    "sg:province":"IL",
    "sg:tags":[
        "church"
    ],
    "wof:name":"Immanuel Lutheran Church",
    "wof:placetype":"venue"
},
  "geometry": {"coordinates":[-89.090756,41.639897],"type":"Point"}
}