{
  "type": "Feature",
  "properties": {
    "addr:full":"2010 N Lincoln Ave Urbana IL 61801",
    "addr:housenumber":"2010",
    "addr:postcode":"61801",
    "addr:street":"N Lincoln Ave",
    "iso:country":"US",
    "sg:address":"2010 N Lincoln Ave",
    "sg:city":"Urbana",
    "sg:classifiers":[
        {
            "category":"Autos & Motor Vehicles",
            "subcategory":"Motorcycle Sales",
            "type":"Retail Goods"
        }
    ],
    "sg:phone":"+1 217 328 2092",
    "sg:postcode":"61801",
    "sg:province":"IL",
    "sg:website":"www.harley-davidson.com",
    "wof:name":"Andrae's Harley-Davidson Sales & Serv",
    "wof:placetype":"venue"
},
  "geometry": {"coordinates":[-88.219398,40.132401],"type":"Point"}
}