{
  "type": "Feature",
  "properties": {
    "addr:full":"2591 N Mulford Rd Rockford IL 61114",
    "addr:housenumber":"2591",
    "addr:postcode":"61114",
    "addr:street":"N Mulford Rd",
    "iso:country":"US",
    "sg:address":"2591 N Mulford Rd",
    "sg:city":"Rockford",
    "sg:classifiers":[
        {
            "category":"Shopping",
            "type":"Retail Goods"
        }
    ],
    "sg:phone":"+1 815 639 9251",
    "sg:postcode":"61114",
    "sg:province":"IL",
    "sg:tags":[
        "limb",
        "artificial"
    ],
    "wof:name":"Inspiration For Inner & Outer",
    "wof:placetype":"venue"
},
  "geometry": {"coordinates":[-88.999487,42.299944],"type":"Point"}
}