{
  "type": "Feature",
  "properties": {
    "iso:country":"US",
    "sg:address":"7566 S South Shore Dr",
    "sg:city":"Chicago",
    "sg:classifiers":[
        {
            "category":"Organizations",
            "subcategory":"Religious Organization",
            "type":"Services"
        }
    ],
    "sg:phone":"+1 773 785 7476",
    "sg:postcode":"60649",
    "sg:province":"IL",
    "sg:tags":[
        "church"
    ],
    "wof:name":"CCAP Associated Urban Mnstr",
    "wof:placetype":"venue"
},
  "geometry": {"coordinates":[-87.555511,41.759068],"type":"Point"}
}