{
  "type": "Feature",
  "properties": {
    "addr:full":"505 Drummond Dr Bourbonnais IL 60914",
    "addr:housenumber":"505",
    "addr:postcode":"60914",
    "addr:street":"Drummond Dr",
    "iso:country":"US",
    "sg:address":"505 Drummond Dr",
    "sg:city":"Bourbonnais",
    "sg:classifiers":[
        {
            "category":"Professional",
            "subcategory":"Computer Services",
            "type":"Services"
        }
    ],
    "sg:phone":"+1 815 937 5035",
    "sg:postcode":"60914",
    "sg:province":"IL",
    "sg:tags":[
        "website",
        "design"
    ],
    "wof:name":"Quality Custom Webs",
    "wof:placetype":"venue"
},
  "geometry": {"coordinates":[-87.88252,41.151461],"type":"Point"}
}