{
  "type": "Feature",
  "properties": {
    "iso:country":"US",
    "sg:address":"2658 W Van Buren St",
    "sg:city":"Chicago",
    "sg:classifiers":[
        {
            "category":"Building & Trades",
            "subcategory":"Cleaning & Sanitation",
            "type":"Services"
        },
        {
            "category":"Home & Garden",
            "subcategory":"Building Materials",
            "type":"Retail Goods"
        },
        {
            "category":"Building & Trades",
            "subcategory":"Construction",
            "type":"Services"
        }
    ],
    "sg:phone":"+1 773 638 5206",
    "sg:postcode":"60612",
    "sg:province":"IL",
    "sg:tags":[
        "industrial",
        "waterproofing",
        "contractor",
        "concrete",
        "restoration",
        "contractors-commercial",
        "masonry",
        "sealing"
    ],
    "sg:website":"http://www.westerngroup.com",
    "wof:name":"Western Waterproofing",
    "wof:placetype":"venue"
},
  "geometry": {"coordinates":[-87.69286,41.876031],"type":"Point"}
}