{
  "type": "Feature",
  "properties": {
    "iso:country":"US",
    "sg:address":"910 Jungles Ave",
    "sg:city":"Aurora",
    "sg:classifiers":[
        {
            "category":"Education",
            "subcategory":"Dance Studio",
            "type":"Public Place"
        }
    ],
    "sg:phone":"+1 630 978 0979",
    "sg:postcode":"60505",
    "sg:province":"IL",
    "sg:tags":[
        "instruction",
        "dancing"
    ],
    "wof:name":"Shiloh Studio Of Dance",
    "wof:placetype":"venue"
},
  "geometry": {"coordinates":[-88.292618,41.777152],"type":"Point"}
}