{
  "type": "Feature",
  "properties": {
    "addr:full":"1659 Missouri Dr Elk Grove Village IL 60007",
    "addr:housenumber":"1659",
    "addr:postcode":"60007",
    "addr:street":"Missouri Dr",
    "iso:country":"US",
    "sg:address":"1659 Missouri Dr",
    "sg:city":"Elk Grove Village",
    "sg:classifiers":[
        {
            "category":"Manufacturing",
            "subcategory":"Retail Goods",
            "type":"Manufacturing & Wholesale Goods"
        }
    ],
    "sg:phone":"+1 847 891 2637",
    "sg:postcode":"60007",
    "sg:province":"IL",
    "sg:tags":[
        "product",
        "mfg"
    ],
    "wof:name":"Bighead Industries Ltd",
    "wof:placetype":"venue"
},
  "geometry": {"coordinates":[-88.04838100000001,41.998627],"type":"Point"}
}