{
  "type": "Feature",
  "properties": {
    "iso:country":"US",
    "sg:address":"11157 S Green Bay Ave",
    "sg:city":"Chicago",
    "sg:classifiers":[
        {
            "category":"Building & Trades",
            "subcategory":"Construction",
            "type":"Services"
        }
    ],
    "sg:phone":"+1 773 721 3028",
    "sg:postcode":"60617",
    "sg:province":"IL",
    "sg:tags":[
        "system",
        "specialty",
        "heating",
        "contractor",
        "air conditioning"
    ],
    "wof:name":"Sam Rosados Cooling & Heating",
    "wof:placetype":"venue"
},
  "geometry": {"coordinates":[-87.541313,41.692618],"type":"Point"}
}