{
  "type": "Feature",
  "properties": {
    "iso:country":"US",
    "sg:address":"309 Market Ave",
    "sg:city":"East St Louis",
    "sg:classifiers":[
        {
            "category":"Shopping",
            "subcategory":"Bicycles & Sporting Goods",
            "type":"Retail Goods"
        }
    ],
    "sg:phone":"+1 618 394 0344",
    "sg:postcode":"62201",
    "sg:province":"IL",
    "sg:tags":[
        "equipment",
        "exercise"
    ],
    "wof:name":"Fitness Experience",
    "wof:placetype":"venue"
},
  "geometry": {"coordinates":[-90.167142,38.62136],"type":"Point"}
}