{
  "type": "Feature",
  "properties": {
    "iso:country":"US",
    "sg:address":"2100 Manchester Rd",
    "sg:city":"Wheaton",
    "sg:classifiers":[
        {
            "category":"Manufacturing",
            "subcategory":"Tools & Machinery",
            "type":"Manufacturing & Wholesale Goods"
        }
    ],
    "sg:phone":"+1 630 690 7805",
    "sg:postcode":"60187",
    "sg:province":"IL",
    "sg:tags":[
        "pipe",
        "mills",
        "tube",
        "component"
    ],
    "wof:name":"Oto Mills USA Inc",
    "wof:placetype":"venue"
},
  "geometry": {"coordinates":[-88.13596200000001,41.865567],"type":"Point"}
}