{
  "type": "Feature",
  "properties": {
    "addr:full":"440 W Boughton Rd Bolingbrook IL 60440",
    "addr:housenumber":"440",
    "addr:postcode":"60440",
    "addr:street":"W Boughton Rd",
    "iso:country":"US",
    "sg:address":"440 W Boughton Rd",
    "sg:city":"Bolingbrook",
    "sg:classifiers":[
        {
            "category":"Real Estate",
            "subcategory":"Real Estate Services",
            "type":"Services"
        }
    ],
    "sg:phone":"+1 630 759 0968",
    "sg:postcode":"60440",
    "sg:province":"IL",
    "sg:tags":[
        "company",
        "title"
    ],
    "wof:name":"Professional Title Co LLC",
    "wof:placetype":"venue"
},
  "geometry": {"coordinates":[-88.084875,41.708016],"type":"Point"}
}