{
  "type": "Feature",
  "properties": {
    "addr:full":"6755 State St East Saint Louis IL 62203",
    "addr:housenumber":"6755",
    "addr:postcode":"62203",
    "addr:street":"State St East",
    "iso:country":"US",
    "sg:address":"6755 State St",
    "sg:city":"East Saint Louis",
    "sg:classifiers":[
        {
            "category":"Social Services",
            "type":"Services"
        }
    ],
    "sg:phone":"+1 618 274 4710",
    "sg:postcode":"62203",
    "sg:province":"IL",
    "sg:tags":[
        "center"
    ],
    "wof:name":"Senior Citizens Activities of",
    "wof:placetype":"venue"
},
  "geometry": {"coordinates":[-90.083061,38.601709],"type":"Point"}
}