{
  "type": "Feature",
  "properties": {
    "iso:country":"US",
    "sg:address":"509 E Clark St",
    "sg:city":"Champaign",
    "sg:classifiers":[
        {
            "category":"Banks & Credit Unions",
            "subcategory":"Financial Services",
            "type":"Services"
        }
    ],
    "sg:phone":"+1 217 384 0789",
    "sg:postcode":"61820",
    "sg:province":"IL",
    "sg:tags":[
        "real estate",
        "investment",
        "closed"
    ],
    "wof:name":"Security Realty Mgmt",
    "wof:placetype":"venue"
},
  "geometry": {"coordinates":[-88.230538,40.115315],"type":"Point"}
}