{
  "type": "Feature",
  "properties": {
    "iso:country":"US",
    "sg:address":"215 Columbine St",
    "sg:city":"Crystal Lake",
    "sg:classifiers":[
        {
            "category":"Shopping",
            "type":"Retail Goods"
        }
    ],
    "sg:phone":"+1 815 477 1056",
    "sg:postcode":"60014",
    "sg:province":"IL",
    "sg:tags":[
        "material",
        "artist",
        "supply"
    ],
    "wof:name":"Coyote Forge",
    "wof:placetype":"venue"
},
  "geometry": {"coordinates":[-88.376565,42.229912],"type":"Point"}
}