{
  "type": "Feature",
  "properties": {
    "addr:full":"1000 Johnson Dr Buffalo Grove IL 60089",
    "addr:housenumber":"1000",
    "addr:postcode":"60089",
    "addr:street":"Johnson Dr",
    "iso:country":"US",
    "sg:address":"1000 Johnson Dr",
    "sg:city":"Buffalo Grove",
    "sg:classifiers":[
        {
            "category":"Government",
            "subcategory":"Office",
            "type":"Public Place"
        }
    ],
    "sg:phone":"+1   ",
    "sg:postcode":"60089",
    "sg:province":"IL",
    "sg:tags":[
        "facility"
    ],
    "wof:name":"Wheeling Park District",
    "wof:placetype":"venue"
},
  "geometry": {"coordinates":[-87.928923,42.153991],"type":"Point"}
}