{
  "type": "Feature",
  "properties": {
    "addr:full":"4941 173rd St Country Club Hills IL 60478",
    "addr:housenumber":"4941",
    "addr:postcode":"60478",
    "addr:street":"173Rd St",
    "iso:country":"US",
    "sg:address":"4941 173rd St",
    "sg:city":"Country Club Hills",
    "sg:classifiers":[
        {
            "category":"Manufacturing",
            "subcategory":"Furniture",
            "type":"Manufacturing & Wholesale Goods"
        }
    ],
    "sg:phone":"+1 708 957 4666",
    "sg:postcode":"60478",
    "sg:province":"IL",
    "sg:tags":[
        "carpentry",
        "cabinetry",
        "contractor"
    ],
    "wof:name":"Harts Top Shop",
    "wof:placetype":"venue"
},
  "geometry": {"coordinates":[-87.73680299999999,41.576412],"type":"Point"}
}