{
  "type": "Feature",
  "properties": {
    "addr:full":"1322 Milton Rd Alton IL 62002",
    "addr:housenumber":"1322",
    "addr:postcode":"62002",
    "addr:street":"Milton Rd",
    "iso:country":"US",
    "sg:address":"1322 Milton Rd",
    "sg:city":"Alton",
    "sg:classifiers":[
        {
            "category":"Retail",
            "subcategory":"Auto Repair",
            "type":"Services"
        }
    ],
    "sg:phone":"+1 618 465 5591",
    "sg:postcode":"62002",
    "sg:province":"IL",
    "sg:tags":[
        "transmission",
        "automobile",
        "equipment",
        "air conditioning"
    ],
    "sg:website":"http://www.napaautocare.com/",
    "wof:name":"Rister's Automotive & Transmissions",
    "wof:placetype":"venue"
},
  "geometry": {"coordinates":[-90.13543,38.897627],"type":"Point"}
}