{
  "type": "Feature",
  "properties": {
    "addr:full":"5197 Torque Rd Loves Park IL 61111",
    "addr:housenumber":"5197",
    "addr:postcode":"61111",
    "addr:street":"Torque Rd",
    "iso:country":"US",
    "sg:address":"5197 Torque Rd",
    "sg:city":"Loves Park",
    "sg:classifiers":[
        {
            "category":"Professional",
            "type":"Services"
        }
    ],
    "sg:phone":"+1 815 877 9114",
    "sg:postcode":"61111",
    "sg:province":"IL",
    "wof:name":"Denny Lemonds",
    "wof:placetype":"venue"
},
  "geometry": {"coordinates":[-89.01972000000001,42.361013],"type":"Point"}
}