{
  "type": "Feature",
  "properties": {
    "addr:full":"3553 S Winchester Ave Chicago IL 60609",
    "addr:housenumber":"3553",
    "addr:postcode":"60609",
    "addr:street":"S Winchester Ave",
    "iso:country":"US",
    "sg:address":"3553 S Winchester Ave",
    "sg:city":"Chicago",
    "sg:classifiers":[
        {
            "category":"Building & Trades",
            "subcategory":"Construction",
            "type":"Services"
        }
    ],
    "sg:phone":"+1 773 847 3695",
    "sg:postcode":"60609",
    "sg:province":"IL",
    "sg:tags":[
        "contractor"
    ],
    "wof:name":"Triple T Mechanical Heat and Airconditioning",
    "wof:placetype":"venue"
},
  "geometry": {"coordinates":[-87.67384300000001,41.82947],"type":"Point"}
}