{
  "type": "Feature",
  "properties": {
    "iso:country":"US",
    "sg:address":"2807 N 3501st Rd",
    "sg:city":"Seneca",
    "sg:classifiers":[
        {
            "category":"Home & Garden",
            "subcategory":"Building Materials",
            "type":"Retail Goods"
        },
        {
            "category":"Building & Trades",
            "subcategory":"Construction",
            "type":"Services"
        }
    ],
    "sg:phone":"+1 815 695 5054",
    "sg:postcode":"61360",
    "sg:province":"IL",
    "sg:tags":[
        "concrete",
        "staining",
        "contractor"
    ],
    "wof:name":"Hawley Concrete",
    "wof:placetype":"venue"
},
  "geometry": {"coordinates":[-88.63432400000001,41.451076],"type":"Point"}
}