{
  "type": "Feature",
  "properties": {
    "iso:country":"US",
    "sg:address":"4102 Rock Creek Blvd",
    "sg:city":"Joliet",
    "sg:classifiers":[
        {
            "category":"Real Estate",
            "subcategory":"Architect",
            "type":"Services"
        }
    ],
    "sg:phone":"+1 815 730 8025",
    "sg:postcode":"60431",
    "sg:province":"IL",
    "sg:tags":[
        "estimate",
        "construction"
    ],
    "wof:name":"Kajima Construction Svc",
    "wof:placetype":"venue"
},
  "geometry": {"coordinates":[-88.176894,41.490503],"type":"Point"}
}