{
  "type": "Feature",
  "properties": {
    "iso:country":"US",
    "sg:address":"906 Olive St Ph 19",
    "sg:city":"Saint Louis",
    "sg:classifiers":[
        {
            "category":"Professional",
            "subcategory":"Lawyer & Legal Services",
            "type":"Services"
        }
    ],
    "sg:phone":"+1 314 241 2441",
    "sg:postcode":"63101",
    "sg:province":"MO",
    "wof:name":"Walker & Williams PC",
    "wof:placetype":"venue"
},
  "geometry": {"coordinates":[-90.19360500000001,38.62872],"type":"Point"}
}