{
  "type": "Feature",
  "properties": {
    "iso:country":"US",
    "sg:address":"10311 Grand Ave",
    "sg:city":"Franklin Park",
    "sg:classifiers":[
        {
            "category":"Education",
            "subcategory":"Library",
            "type":"Public Place"
        }
    ],
    "sg:phone":"+1 847 455 6016",
    "sg:postcode":"60131",
    "sg:province":"IL",
    "sg:website":"www.franklinparklibrary.org",
    "wof:name":"Franklin Park Public Lib Dst",
    "wof:placetype":"venue"
},
  "geometry": {"coordinates":[-87.882998,41.930154],"type":"Point"}
}