{
  "type": "Feature",
  "properties": {
    "iso:country":"US",
    "sg:address":"1935 York St",
    "sg:city":"Blue Island",
    "sg:classifiers":[
        {
            "category":"Building & Trades",
            "subcategory":"Construction",
            "type":"Services"
        }
    ],
    "sg:phone":"+1 708 396 1051",
    "sg:postcode":"60406",
    "sg:province":"IL",
    "sg:tags":[
        "plastering",
        "contractor"
    ],
    "wof:name":"Dorados Plastering",
    "wof:placetype":"venue"
},
  "geometry": {"coordinates":[-87.669122,41.657327],"type":"Point"}
}