{
  "type": "Feature",
  "properties": {
    "iso:country":"US",
    "sg:address":"1921 Union Ave",
    "sg:city":"Belvidere",
    "sg:classifiers":[
        {
            "category":"Personal",
            "subcategory":"Beauty Salon",
            "type":"Services"
        }
    ],
    "sg:phone":"+1 815 547 3555",
    "sg:postcode":"61008",
    "sg:province":"IL",
    "sg:tags":[
        "shop"
    ],
    "wof:name":"Hair For ME",
    "wof:placetype":"venue"
},
  "geometry": {"coordinates":[-88.842841,42.243329],"type":"Point"}
}