{
  "type": "Feature",
  "properties": {
    "addr:full":"1085 Willow Bay Elgin IL 60123",
    "addr:housenumber":"1085",
    "addr:postcode":"60123",
    "addr:street":"Willow Bay",
    "iso:country":"US",
    "sg:address":"1085 Willow Bay",
    "sg:city":"Elgin",
    "sg:classifiers":[
        {
            "category":"Freight",
            "type":"Transportation"
        }
    ],
    "sg:phone":"+1 847 697 2559",
    "sg:postcode":"60123",
    "sg:province":"IL",
    "sg:tags":[
        "operator",
        "local",
        "trucking"
    ],
    "wof:name":"Montes Trucking",
    "wof:placetype":"venue"
},
  "geometry": {"coordinates":[-88.328075,42.004532],"type":"Point"}
}