{
  "type": "Feature",
  "properties": {
    "addr:full":"1601 Feehanville Dr Mount Prospect IL 60056",
    "addr:housenumber":"1601",
    "addr:postcode":"60056",
    "addr:street":"Feehanville Dr",
    "iso:country":"US",
    "sg:address":"1601 Feehanville Dr",
    "sg:city":"Mount Prospect",
    "sg:classifiers":[
        {
            "category":"Professional",
            "subcategory":"Management & Consulting",
            "type":"Services"
        }
    ],
    "sg:phone":"+1 847 297 0900",
    "sg:postcode":"60056",
    "sg:province":"IL",
    "sg:tags":[
        "canned",
        "promotion",
        "good",
        "sales"
    ],
    "wof:name":"Campbell Soup",
    "wof:placetype":"venue"
},
  "geometry": {"coordinates":[-87.909987,42.077168],"type":"Point"}
}