{
  "type": "Feature",
  "properties": {
    "iso:country":"US",
    "sg:address":"2661 N Illinois St",
    "sg:city":"Belleville",
    "sg:classifiers":[
        {
            "category":"Freight",
            "type":"Transportation"
        }
    ],
    "sg:phone":"+1 618 277 4884",
    "sg:postcode":"62226",
    "sg:province":"IL",
    "sg:tags":[
        "business",
        "arrangement"
    ],
    "wof:name":"Pak Mail",
    "wof:placetype":"venue"
},
  "geometry": {"coordinates":[-89.983948,38.544177],"type":"Point"}
}