{
  "type": "Feature",
  "properties": {
    "iso:country":"US",
    "sg:address":"307 Walnut St",
    "sg:city":"Carthage",
    "sg:classifiers":[
        {
            "category":"Organizations",
            "subcategory":"Religious Organization",
            "type":"Services"
        }
    ],
    "sg:phone":"+1 217 357 2989",
    "sg:postcode":"62321",
    "sg:province":"IL",
    "sg:tags":[
        "church"
    ],
    "wof:name":"Carthage Visitors Ctr",
    "wof:placetype":"venue"
},
  "geometry": {"coordinates":[-91.139602,40.415119],"type":"Point"}
}