{
  "type": "Feature",
  "properties": {
    "iso:country":"US",
    "sg:address":"1360 Sleepy Hollow Rd",
    "sg:city":"Amboy",
    "sg:classifiers":[
        {
            "category":"Professional",
            "subcategory":"Lawyer & Legal Services",
            "type":"Services"
        }
    ],
    "sg:phone":"+1 815 857 2663",
    "sg:postcode":"61310",
    "sg:province":"IL",
    "sg:tags":[
        "plan"
    ],
    "wof:name":"Law Office Of Richard Geiger",
    "wof:placetype":"venue"
},
  "geometry": {"coordinates":[-89.372888,41.682329],"type":"Point"}
}