{
  "type": "Feature",
  "properties": {
    "addr:full":"1813 Moen Ave Rockdale IL 60436",
    "addr:postcode":"1813;60436",
    "addr:street":"Moen Ave",
    "iso:country":"US",
    "sg:address":"1813 Moen Ave",
    "sg:city":"Rockdale",
    "sg:classifiers":[
        {
            "category":"Building & Trades",
            "subcategory":"Plumbing",
            "type":"Services"
        }
    ],
    "sg:phone":"+1 815 744 0836",
    "sg:postcode":"60436",
    "sg:province":"IL",
    "sg:tags":[
        "plumbing",
        "contractor"
    ],
    "wof:name":"M & M Affordable Plumbing",
    "wof:placetype":"venue"
},
  "geometry": {"coordinates":[-88.125232,41.504919],"type":"Point"}
}