{
  "type": "Feature",
  "properties": {
    "addr:full":"10 Sussex Ct Mackinaw IL 61755",
    "addr:housenumber":"10",
    "addr:postcode":"61755",
    "addr:street":"Sussex Ct",
    "iso:country":"US",
    "sg:address":"10 Sussex Ct",
    "sg:city":"Mackinaw",
    "sg:classifiers":[
        {
            "category":"Home & Garden",
            "subcategory":"Furniture",
            "type":"Retail Goods"
        }
    ],
    "sg:phone":"+1   ",
    "sg:postcode":"61755",
    "sg:province":"IL",
    "sg:tags":[
        "mattress"
    ],
    "wof:name":"Mattress Doctor",
    "wof:placetype":"venue"
},
  "geometry": {"coordinates":[-89.32207,40.543531],"type":"Point"}
}