{
  "type": "Feature",
  "properties": {
    "addr:full":"4843 Cal Sag Rd Crestwood IL 60445",
    "addr:housenumber":"4843",
    "addr:postcode":"60445",
    "addr:street":"Cal Sag Rd",
    "iso:country":"US",
    "sg:address":"4843 Cal Sag Rd",
    "sg:city":"Crestwood",
    "sg:classifiers":[
        {
            "category":"Insurance",
            "subcategory":"Health Insurance",
            "type":"Services"
        }
    ],
    "sg:phone":"+1 708 489 2313",
    "sg:postcode":"60445",
    "sg:province":"IL",
    "sg:tags":[
        "market"
    ],
    "sg:website":"www.gnc.com",
    "wof:name":"General Nutrition Center",
    "wof:placetype":"venue"
},
  "geometry": {"coordinates":[-87.74009700000001,41.654099],"type":"Point"}
}