{
  "type": "Feature",
  "properties": {
    "iso:country":"US",
    "sg:address":"1986 Harrison Ave",
    "sg:city":"Beloit",
    "sg:classifiers":[
        {
            "category":"Building & Trades",
            "subcategory":"Construction",
            "type":"Services"
        }
    ],
    "sg:phone":"+1 608 362 3795",
    "sg:postcode":"53511",
    "sg:province":"IL",
    "sg:tags":[
        "contractor"
    ],
    "wof:name":"Johnson Jim Rofg Insul Contrac",
    "wof:placetype":"venue"
},
  "geometry": {"coordinates":[-89.02552900000001,42.52571],"type":"Point"}
}