{
  "type": "Feature",
  "properties": {
    "iso:country":"US",
    "sg:address":"3482 Milwaukee Ave",
    "sg:city":"Northbrook",
    "sg:classifiers":[
        {
            "category":"Health Services",
            "subcategory":"Doctor",
            "type":"Services"
        }
    ],
    "sg:phone":"+1 773 248 3680",
    "sg:postcode":"60062",
    "sg:province":"IL",
    "sg:tags":[
        "dentist"
    ],
    "wof:name":"Michael R Feldman DDS",
    "wof:placetype":"venue"
},
  "geometry": {"coordinates":[-87.873303,42.089992],"type":"Point"}
}