{
  "type": "Feature",
  "properties": {
    "iso:country":"US",
    "sg:address":"11437 S Magnolia Ln",
    "sg:city":"Alsip",
    "sg:classifiers":[
        {
            "category":"Banks & Credit Unions",
            "subcategory":"Investment Brokerage",
            "type":"Services"
        },
        {
            "category":"Banks & Credit Unions",
            "subcategory":"Financial Services",
            "type":"Services"
        }
    ],
    "sg:phone":"+1 708 389 6105",
    "sg:postcode":"60803",
    "sg:province":"IL",
    "sg:tags":[
        "advisory",
        "management"
    ],
    "sg:website":"http://www.manhattancalumet.com",
    "wof:name":"Manhattan Calumet",
    "wof:placetype":"venue"
},
  "geometry": {"coordinates":[-87.75350899999999,41.684129],"type":"Point"}
}