{
  "type": "Feature",
  "properties": {
    "addr:full":"609 S Linden Ave Elmhurst IL 60126",
    "addr:housenumber":"609",
    "addr:postcode":"60126",
    "addr:street":"S Linden Ave",
    "iso:country":"US",
    "sg:address":"609 S Linden Ave",
    "sg:city":"Elmhurst",
    "sg:classifiers":[
        {
            "category":"Organizations",
            "subcategory":"Religious Organization",
            "type":"Services"
        }
    ],
    "sg:phone":"+1 630 782 5882",
    "sg:postcode":"60126",
    "sg:province":"IL",
    "wof:name":"Vineyards of True Life In God",
    "wof:placetype":"venue"
},
  "geometry": {"coordinates":[-87.928724,41.880498],"type":"Point"}
}