{
  "type": "Feature",
  "properties": {
    "iso:country":"US",
    "sg:address":"200 E. Chestnut Street",
    "sg:city":"Chicago",
    "sg:classifiers":[
        {
            "category":"Restaurant",
            "type":"Food & Drink"
        },
        {
            "category":"Bars & Pubs",
            "subcategory":"Wine Bar",
            "type":"Food & Drink"
        }
    ],
    "sg:phone":"+1 312 266 4500",
    "sg:postcode":"60611",
    "sg:province":"IL",
    "wof:name":"Chestnut Grill & Wine Bar",
    "wof:placetype":"venue"
},
  "geometry": {"coordinates":[-87.621696,41.898499],"type":"Point"}
}