{
  "type": "Feature",
  "properties": {
    "iso:country":"US",
    "sg:address":"120 N Monroe Ave",
    "sg:city":"Bradley",
    "sg:classifiers":[
        {
            "category":"Organizations",
            "subcategory":"Religious Organization",
            "type":"Services"
        }
    ],
    "sg:phone":"+1 815 932 1600",
    "sg:postcode":"60915",
    "sg:province":"IL",
    "sg:tags":[
        "church"
    ],
    "wof:name":"Christ Temple Apostolic Church",
    "wof:placetype":"venue"
},
  "geometry": {"coordinates":[-87.843999,41.146048],"type":"Point"}
}