{
  "type": "Feature",
  "properties": {
    "iso:country":"US",
    "sg:address":"332 W Marion Ave",
    "sg:city":"Forsyth",
    "sg:classifiers":[
        {
            "category":"Insurance",
            "subcategory":"Hazard Insurance",
            "type":"Services"
        },
        {
            "category":"Banks & Credit Unions",
            "subcategory":"Investment Brokerage",
            "type":"Services"
        },
        {
            "category":"Insurance",
            "subcategory":"Life Insurance",
            "type":"Services"
        },
        {
            "category":"Banks & Credit Unions",
            "subcategory":"Financial Services",
            "type":"Services"
        }
    ],
    "sg:phone":"+1 918 258 5155",
    "sg:postcode":"62535",
    "sg:province":"IL",
    "sg:website":"http://national.citysearch.com/profile/external/43626047/forsyth_il/country_financial_doug_alford.html?publisher=yellowpages&reference_id=1&placement=ypwebsitemip",
    "wof:name":"COUNTRY Financial - Doug Alford",
    "wof:placetype":"venue"
},
  "geometry": {"coordinates":[-88.957131,39.92159],"type":"Point"}
}