{
  "type": "Feature",
  "properties": {
    "iso:country":"US",
    "sg:address":"1416 North Ave",
    "sg:city":"Rockford",
    "sg:classifiers":[
        {
            "category":"Building & Trades",
            "subcategory":"Construction",
            "type":"Services"
        }
    ],
    "sg:phone":"+1 815 963 1091",
    "sg:postcode":"61103",
    "sg:province":"IL",
    "sg:tags":[
        "altering",
        "industrial",
        "remodeling",
        "contractors-commercial",
        "contractor"
    ],
    "wof:name":"Advantage Construction",
    "wof:placetype":"venue"
},
  "geometry": {"coordinates":[-89.086941,42.287415],"type":"Point"}
}