{
  "type": "Feature",
  "properties": {
    "addr:full":"3824 W Montrose Ave Chicago IL 60618",
    "addr:housenumber":"3824",
    "addr:postcode":"60618",
    "addr:street":"W Montrose Ave",
    "iso:country":"US",
    "sg:address":"3824 W Montrose Ave",
    "sg:city":"Chicago",
    "sg:classifiers":[
        {
            "category":"Retail",
            "subcategory":"Repair Shop",
            "type":"Services"
        }
    ],
    "sg:phone":"+1 773 463 5414",
    "sg:postcode":"60618",
    "sg:province":"IL",
    "sg:tags":[
        "reupholstery",
        "furniture"
    ],
    "wof:name":"Lucy Interiors",
    "wof:placetype":"venue"
},
  "geometry": {"coordinates":[-87.72370100000001,41.960999],"type":"Point"}
}