{
  "type": "Feature",
  "properties": {
    "addr:full":"914 W Madison St Chicago IL 60607",
    "addr:housenumber":"914",
    "addr:postcode":"60607",
    "addr:street":"W Madison St",
    "iso:country":"US",
    "sg:address":"914 W Madison St",
    "sg:city":"Chicago",
    "sg:classifiers":[
        {
            "category":"Food & Beverages",
            "subcategory":"Groceries & Convenience Stores",
            "type":"Retail Goods"
        }
    ],
    "sg:phone":"+1 312 455 2873",
    "sg:postcode":"60607",
    "sg:province":"IL",
    "wof:name":"Anshiv International Inc",
    "wof:placetype":"venue"
},
  "geometry": {"coordinates":[-87.650683,41.881924],"type":"Point"}
}