{
  "type": "Feature",
  "properties": {
    "addr:full":"3225 W 26th St Chicago IL 60623",
    "addr:housenumber":"3225",
    "addr:postcode":"60623",
    "addr:street":"W 26Th St",
    "iso:country":"US",
    "sg:address":"3225 W 26th St",
    "sg:city":"Chicago",
    "sg:classifiers":[
        {
            "category":"Health Services",
            "subcategory":"Chiropractor",
            "type":"Services"
        }
    ],
    "sg:phone":"+1 773 376 0600",
    "sg:postcode":"60623",
    "sg:province":"IL",
    "sg:tags":[
        "chiropractic"
    ],
    "wof:name":"Los Quiropracticos",
    "wof:placetype":"venue"
},
  "geometry": {"coordinates":[-87.70605999999999,41.844512],"type":"Point"}
}