{
  "type": "Feature",
  "properties": {
    "iso:country":"US",
    "sg:address":"145 S Randall Rd",
    "sg:city":"Batavia",
    "sg:classifiers":[
        {
            "category":"Shopping",
            "subcategory":"Gifts & Souvenirs",
            "type":"Retail Goods"
        }
    ],
    "sg:phone":"+1   ",
    "sg:postcode":"60510",
    "sg:province":"IL",
    "wof:name":"Legends Collectibles",
    "wof:placetype":"venue"
},
  "geometry": {"coordinates":[-88.340166,41.847935],"type":"Point"}
}