{
  "type": "Feature",
  "properties": {
    "iso:country":"US",
    "sg:address":"855 Arlington Heights Rd",
    "sg:city":"Arlington Heights",
    "sg:classifiers":[
        {
            "category":"Professional",
            "subcategory":"Lawyer & Legal Services",
            "type":"Services"
        }
    ],
    "sg:phone":"+1 847 437 4197",
    "sg:postcode":"60005",
    "sg:province":"IL",
    "wof:name":"Thomas J Organ",
    "wof:placetype":"venue"
},
  "geometry": {"coordinates":[-87.980365,42.069355],"type":"Point"}
}