{
  "type": "Feature",
  "properties": {
    "iso:country":"US",
    "sg:address":"4329 W 26th St",
    "sg:city":"Chicago",
    "sg:classifiers":[
        {
            "category":"Building & Trades",
            "subcategory":"Locksmith",
            "type":"Services"
        }
    ],
    "sg:phone":"+1 773 277 5625",
    "sg:postcode":"60623",
    "sg:province":"IL",
    "sg:tags":[
        "key"
    ],
    "sg:website":"www.omegalocksmith.com/",
    "wof:name":"Omega Locksmith",
    "wof:placetype":"venue"
},
  "geometry": {"coordinates":[-87.732125,41.843831],"type":"Point"}
}