{
  "type": "Feature",
  "properties": {
    "iso:country":"US",
    "sg:address":"20282 N 500 E Rd",
    "sg:city":"Flanagan",
    "sg:classifiers":[
        {
            "category":"Farming",
            "subcategory":"Farm",
            "type":"Manufacturing & Wholesale Goods"
        }
    ],
    "sg:phone":"+1 815 796 2747",
    "sg:postcode":"61740",
    "sg:province":"IL",
    "sg:tags":[
        "crop",
        "general"
    ],
    "wof:name":"Keith Iverson",
    "wof:placetype":"venue"
},
  "geometry": {"coordinates":[-88.835583,40.929673],"type":"Point"}
}