{
  "type": "Feature",
  "properties": {
    "addr:full":"1200 Central Ave Bartlett IL 60133",
    "addr:housenumber":"1200",
    "addr:postcode":"60133",
    "addr:street":"Central Ave",
    "iso:country":"US",
    "sg:address":"1200 Central Ave",
    "sg:city":"Bartlett",
    "sg:classifiers":[
        {
            "category":"Wholesale",
            "subcategory":"Electrical",
            "type":"Manufacturing & Wholesale Goods"
        }
    ],
    "sg:phone":"+1 630 697 2888",
    "sg:postcode":"60133",
    "sg:province":"IL",
    "sg:tags":[
        "fixture",
        "lighting",
        "apparatus"
    ],
    "wof:name":"Bell & Gustus Inc",
    "wof:placetype":"venue"
},
  "geometry": {"coordinates":[-88.12778299999999,41.982099],"type":"Point"}
}