{
  "type": "Feature",
  "properties": {
    "addr:full":"220 E Chicago Ave Chicago IL 60611",
    "addr:housenumber":"220",
    "addr:postcode":"60611",
    "addr:street":"E Chicago Ave",
    "iso:country":"US",
    "sg:address":"220 E Chicago Ave",
    "sg:city":"Chicago",
    "sg:classifiers":[
        {
            "category":"Arts & Performance",
            "subcategory":"Art Gallery",
            "type":"Entertainment"
        },
        {
            "category":"Landmark",
            "subcategory":"Tourist Information",
            "type":"Public Place"
        },
        {
            "category":"Museum",
            "type":"Entertainment"
        }
    ],
    "sg:phone":"+1 312 280 2660",
    "sg:postcode":"60611",
    "sg:province":"IL",
    "sg:tags":[
        "consultant",
        "galleries",
        "attraction"
    ],
    "sg:website":"www.mcachicago.org",
    "wof:name":"Museum Of Contemporary Art",
    "wof:placetype":"venue"
},
  "geometry": {"coordinates":[-87.622603,41.897069],"type":"Point"}
}