{
  "type": "Feature",
  "properties": {
    "iso:country":"US",
    "sg:address":"12258 S Peoria St",
    "sg:city":"Chicago",
    "sg:classifiers":[
        {
            "category":"Social Services",
            "subcategory":"Child Care",
            "type":"Services"
        }
    ],
    "sg:phone":"+1 773 264 4558",
    "sg:postcode":"60643",
    "sg:province":"IL",
    "wof:name":"Tiny Footprint Daycare",
    "wof:placetype":"venue"
},
  "geometry": {"coordinates":[-87.644207,41.671576],"type":"Point"}
}