{
  "type": "Feature",
  "properties": {
    "iso:country":"US",
    "sg:address":"229 N Leamington Ave",
    "sg:city":"Chicago",
    "sg:classifiers":[
        {
            "category":"Arts & Performance",
            "subcategory":"Theater",
            "type":"Entertainment"
        }
    ],
    "sg:phone":"+1 773 287 5681",
    "sg:postcode":"60644",
    "sg:province":"IL",
    "sg:tags":[
        "group"
    ],
    "wof:name":"Big City Entertainment Inc",
    "wof:placetype":"venue"
},
  "geometry": {"coordinates":[-87.753953,41.885282],"type":"Point"}
}