{
  "type": "Feature",
  "properties": {
    "iso:country":"US",
    "sg:address":"9414 S Champlain Ave",
    "sg:city":"Chicago",
    "sg:classifiers":[
        {
            "category":"Shopping",
            "type":"Retail Goods"
        }
    ],
    "sg:phone":"+1 773 679 8960",
    "sg:postcode":"60619",
    "sg:province":"IL",
    "sg:tags":[
        "item",
        "boutique"
    ],
    "wof:name":"Sassy Boutique",
    "wof:placetype":"venue"
},
  "geometry": {"coordinates":[-87.608135,41.723601],"type":"Point"}
}