{
  "type": "Feature",
  "properties": {
    "addr:full":"1231 S Pulaski Road Chicago IL 60623",
    "addr:housenumber":"1231",
    "addr:postcode":"60623",
    "addr:street":"S Pulaski Road",
    "iso:country":"US",
    "sg:address":"1231 S Pulaski Road",
    "sg:city":"Chicago",
    "sg:classifiers":[
        {
            "category":"Education",
            "subcategory":"School",
            "type":"Public Place"
        }
    ],
    "sg:phone":"+1 773 762 2272",
    "sg:postcode":"60623",
    "sg:province":"IL",
    "sg:tags":[
        "high",
        "middle",
        "elementary"
    ],
    "wof:name":"C C A Academy",
    "wof:placetype":"venue"
},
  "geometry": {"coordinates":[-87.724889,41.865754],"type":"Point"}
}