{
  "type": "Feature",
  "properties": {
    "iso:country":"US",
    "sg:address":"6619 Cermak Rd",
    "sg:city":"Berwyn",
    "sg:classifiers":[
        {
            "category":"Retail",
            "subcategory":"Auto Repair",
            "type":"Services"
        }
    ],
    "sg:phone":"+1 708 749 7449",
    "sg:postcode":"60402",
    "sg:province":"IL",
    "wof:name":"Karco",
    "wof:placetype":"venue"
},
  "geometry": {"coordinates":[-87.788803,41.850601],"type":"Point"}
}