{
  "type": "Feature",
  "properties": {
    "iso:country":"US",
    "sg:address":"14962 W Abbey Ln",
    "sg:city":"Lockport",
    "sg:classifiers":[
        {
            "category":"Recreation",
            "type":"Entertainment"
        }
    ],
    "sg:phone":"+1 815 836 8573",
    "sg:postcode":"60441",
    "sg:province":"IL",
    "sg:tags":[
        "amusement"
    ],
    "wof:name":"J & K Elite Cheerleading",
    "wof:placetype":"venue"
},
  "geometry": {"coordinates":[-87.982899,41.586691],"type":"Point"}
}