{
  "type": "Feature",
  "properties": {
    "addr:full":"4913 W Glenbrook Trl Mc Henry IL 60050",
    "addr:housenumber":"4913",
    "addr:postcode":"60050",
    "addr:street":"W Glenbrook Trl Mc Henry",
    "iso:country":"US",
    "sg:address":"4913 W Glenbrook Trl",
    "sg:city":"Mc Henry",
    "sg:classifiers":[
        {
            "category":"Retail",
            "subcategory":"Repair Shop",
            "type":"Services"
        }
    ],
    "sg:phone":"+1 815 759 0570",
    "sg:postcode":"60050",
    "sg:province":"IL",
    "wof:name":"Lhb Communications",
    "wof:placetype":"venue"
},
  "geometry": {"coordinates":[-88.294811,42.323112],"type":"Point"}
}