{
  "type": "Feature",
  "properties": {
    "addr:full":"17951 Chappel Ave Lansing IL 60438",
    "addr:postcode":"17951;60438",
    "addr:street":"Chappel Ave",
    "iso:country":"US",
    "sg:address":"17951 Chappel Ave",
    "sg:city":"Lansing",
    "sg:classifiers":[
        {
            "category":"Building & Trades",
            "subcategory":"Construction",
            "type":"Services"
        }
    ],
    "sg:phone":"+1 708 474 4037",
    "sg:postcode":"60438",
    "sg:province":"IL",
    "sg:tags":[
        "painter"
    ],
    "wof:name":"Hicks Decorating Inc",
    "wof:placetype":"venue"
},
  "geometry": {"coordinates":[-87.570801,41.57],"type":"Point"}
}