{
  "type": "Feature",
  "properties": {
    "iso:country":"US",
    "sg:address":"201 N Morrison Ave",
    "sg:city":"Collinsville",
    "sg:classifiers":[
        {
            "category":"Travel",
            "subcategory":"Travel Agent",
            "type":"Entertainment"
        }
    ],
    "sg:phone":"+1 618 345 2043",
    "sg:postcode":"62234",
    "sg:province":"IL",
    "sg:tags":[
        "agency",
        "bureau"
    ],
    "wof:name":"Pic-A-Place Travel Inc",
    "wof:placetype":"venue"
},
  "geometry": {"coordinates":[-89.986058,38.672944],"type":"Point"}
}