{
  "type": "Feature",
  "properties": {
    "iso:country":"US",
    "sg:address":"2901 W Armitage Ave",
    "sg:city":"Chicago",
    "sg:classifiers":[
        {
            "category":"Professional",
            "subcategory":"Business Services",
            "type":"Services"
        },
        {
            "category":"Government",
            "subcategory":"Post Office",
            "type":"Public Place"
        }
    ],
    "sg:phone":"+1 800 275 8777",
    "sg:postcode":"60647",
    "sg:province":"IL",
    "sg:tags":[
        "mail",
        "shipping"
    ],
    "sg:website":"http://www.usps.com",
    "wof:name":"USPS - United States Post Office - CPU Foodsmart",
    "wof:placetype":"venue"
},
  "geometry": {"coordinates":[-87.69931,41.917461],"type":"Point"}
}