{
  "type": "Feature",
  "properties": {
    "iso:country":"US",
    "sg:address":"3853 W North Ave",
    "sg:city":"Chicago",
    "sg:classifiers":[
        {
            "category":"Manufacturing",
            "subcategory":"Printing",
            "type":"Manufacturing & Wholesale Goods"
        }
    ],
    "sg:phone":"+1 773 772 2383",
    "sg:postcode":"60647",
    "sg:province":"IL",
    "sg:tags":[
        "commercial",
        "c",
        "lithographic",
        "typesetting"
    ],
    "wof:name":"Bcs Graphics Printing Inc",
    "wof:placetype":"venue"
},
  "geometry": {"coordinates":[-87.724123,41.909885],"type":"Point"}
}