{
  "type": "Feature",
  "properties": {
    "addr:full":"7901 S Cottage Grove Ave Chicago IL 60619",
    "addr:housenumber":"7901",
    "addr:postcode":"60619",
    "addr:street":"S Cottage Grove Ave",
    "iso:country":"US",
    "sg:address":"7901 S Cottage Grove Ave",
    "sg:city":"Chicago",
    "sg:classifiers":[
        {
            "category":"Food & Beverages",
            "subcategory":"Groceries & Convenience Stores",
            "type":"Retail Goods"
        }
    ],
    "sg:phone":"+1 773 783 5846",
    "sg:postcode":"60619",
    "sg:province":"IL",
    "wof:name":"Happy Foods",
    "wof:placetype":"venue"
},
  "geometry": {"coordinates":[-87.60497599999999,41.751274],"type":"Point"}
}