{
  "type": "Feature",
  "properties": {
    "addr:full":"6321 N Avondale Ave Chicago IL 60631",
    "addr:housenumber":"6321",
    "addr:postcode":"60631",
    "addr:street":"N Avondale Ave",
    "iso:country":"US",
    "sg:address":"6321 N Avondale Ave",
    "sg:city":"Chicago",
    "sg:classifiers":[
        {
            "category":"Autos & Motor Vehicles",
            "subcategory":"Automobile Sales",
            "type":"Retail Goods"
        }
    ],
    "sg:phone":"+1 800 848 2888",
    "sg:postcode":"60631",
    "sg:province":"IL",
    "sg:tags":[
        "limo"
    ],
    "wof:name":"Presidential Limousine",
    "wof:placetype":"venue"
},
  "geometry": {"coordinates":[-87.808104,41.996012],"type":"Point"}
}