{
  "type": "Feature",
  "properties": {
    "addr:full":"1300 W Normantown Rd Romeoville IL 60446",
    "addr:housenumber":"1300",
    "addr:postcode":"60446",
    "addr:street":"W Normantown Rd",
    "iso:country":"US",
    "sg:address":"1300 W Normantown Rd",
    "sg:city":"Romeoville",
    "sg:classifiers":[
        {
            "category":"Autos & Motor Vehicles",
            "subcategory":"Fuel & Gas Station",
            "type":"Retail Goods"
        }
    ],
    "sg:phone":"+1 815 293 2738",
    "sg:postcode":"60446",
    "sg:province":"IL",
    "sg:tags":[
        "oil"
    ],
    "wof:name":"Gas City Offices",
    "wof:placetype":"venue"
},
  "geometry": {"coordinates":[-88.09778799999999,41.654033],"type":"Point"}
}