{
  "type": "Feature",
  "properties": {
    "iso:country":"US",
    "sg:address":"9473 Scenic Bluff Rd",
    "sg:city":"Savanna",
    "sg:classifiers":[
        {
            "category":"Freight",
            "type":"Transportation"
        }
    ],
    "sg:phone":"+1 815 273 4660",
    "sg:postcode":"61074",
    "sg:province":"IL",
    "sg:tags":[
        "trucking"
    ],
    "wof:name":"Myrick Trucking",
    "wof:placetype":"venue"
},
  "geometry": {"coordinates":[-90.091142,42.068895],"type":"Point"}
}