{
  "type": "Feature",
  "properties": {
    "addr:full":"3045 N Elston Ave Chicago IL 60618",
    "addr:housenumber":"3045",
    "addr:postcode":"60618",
    "addr:street":"N Elston Ave",
    "iso:country":"US",
    "sg:address":"3045 N Elston Ave",
    "sg:city":"Chicago",
    "sg:classifiers":[
        {
            "category":"Retail",
            "subcategory":"Auto Repair",
            "type":"Services"
        }
    ],
    "sg:phone":"+1 773 267 5400",
    "sg:postcode":"60618",
    "sg:province":"IL",
    "sg:website":"www.RNBMW.com",
    "wof:name":"R & N Bavarian Motors",
    "wof:placetype":"venue"
},
  "geometry": {"coordinates":[-87.694237,41.936616],"type":"Point"}
}