{
  "type": "Feature",
  "properties": {
    "addr:full":"2353 S Laramie Ave Cicero IL 60804",
    "addr:housenumber":"2353",
    "addr:postcode":"60804",
    "addr:street":"S Laramie Ave",
    "iso:country":"US",
    "sg:address":"2353 S Laramie Ave",
    "sg:city":"Cicero",
    "sg:classifiers":[
        {
            "category":"Restaurant",
            "type":"Food & Drink"
        },
        {
            "category":"Ice Cream",
            "type":"Food & Drink"
        }
    ],
    "sg:phone":"+1 708 683 5111",
    "sg:postcode":"60804",
    "sg:province":"IL",
    "sg:tags":[
        "frozen",
        "yogurt",
        "flavor",
        "local"
    ],
    "sg:website":"www.lindyschili.com",
    "wof:name":"Lindy's Chilli & Gertie's Ice Cream",
    "wof:placetype":"venue"
},
  "geometry": {"coordinates":[-87.75395399999999,41.847978],"type":"Point"}
}