{
  "type": "Feature",
  "properties": {
    "addr:full":"3100 S Raney St Effingham IL 62401",
    "addr:housenumber":"3100",
    "addr:postcode":"62401",
    "addr:street":"S Raney St",
    "iso:country":"US",
    "sg:address":"3100 S Raney St",
    "sg:city":"Effingham",
    "sg:classifiers":[
        {
            "category":"Manufacturing",
            "subcategory":"Pet Food",
            "type":"Manufacturing & Wholesale Goods"
        },
        {
            "category":"Farming",
            "subcategory":"Farm",
            "type":"Manufacturing & Wholesale Goods"
        }
    ],
    "sg:phone":"+1 217 342 6689",
    "sg:postcode":"62401",
    "sg:province":"IL",
    "sg:tags":[
        "hay"
    ],
    "wof:name":"Haarmann Brothers",
    "wof:placetype":"venue"
},
  "geometry": {"coordinates":[-88.561741,39.092007],"type":"Point"}
}