{
  "type": "Feature",
  "properties": {
    "addr:full":"2828 Broadway St Quincy IL 62301",
    "addr:housenumber":"2828",
    "addr:postcode":"62301",
    "addr:street":"Broadway St",
    "iso:country":"US",
    "sg:address":"2828 Broadway St",
    "sg:city":"Quincy",
    "sg:classifiers":[
        {
            "category":"Shopping",
            "subcategory":"Catalog Store",
            "type":"Retail Goods"
        }
    ],
    "sg:phone":"+1 217 224 8500",
    "sg:postcode":"62301",
    "sg:province":"IL",
    "sg:tags":[
        "mail",
        "order"
    ],
    "sg:website":"www.4electronicwarehouse.com",
    "wof:name":"Electronic Warehouse",
    "wof:placetype":"venue"
},
  "geometry": {"coordinates":[-91.36988700000001,39.935126],"type":"Point"}
}