{
  "type": "Feature",
  "properties": {
    "addr:full":"680 N Lake Shore Dr Chicago IL 60611",
    "addr:housenumber":"680",
    "addr:postcode":"60611",
    "addr:street":"N Lake Shore Dr",
    "iso:country":"US",
    "sg:address":"680 N Lake Shore Dr",
    "sg:city":"Chicago",
    "sg:phone":"+1 312 302 9900",
    "sg:postcode":"60611",
    "sg:province":"IL",
    "sg:website":"http://marcelflorist.com",
    "wof:name":"Marcel Florist Inc",
    "wof:placetype":"venue"
},
  "geometry": {"coordinates":[-87.615621,41.894691],"type":"Point"}
}