{
  "type": "Feature",
  "properties": {
    "iso:country":"US",
    "sg:address":"9800 Joliet Rd",
    "sg:city":"Countryside",
    "sg:classifiers":[
        {
            "category":"Building & Trades",
            "subcategory":"Construction",
            "type":"Services"
        },
        {
            "category":"Real Estate",
            "subcategory":"Real Estate Agent",
            "type":"Services"
        }
    ],
    "sg:phone":"+1 708 352 2043",
    "sg:postcode":"60525",
    "sg:province":"IL",
    "sg:tags":[
        "manufactured",
        "housing-communities"
    ],
    "sg:website":"http://www.cambonihomes.com",
    "wof:name":"Country Club Park",
    "wof:placetype":"venue"
},
  "geometry": {"coordinates":[-87.865752,41.779633],"type":"Point"}
}