{
  "type": "Feature",
  "properties": {
    "iso:country":"US",
    "sg:address":"7337 S Yates Blvd",
    "sg:city":"Chicago",
    "sg:classifiers":[
        {
            "category":"Social Services",
            "subcategory":"Child Care",
            "type":"Services"
        }
    ],
    "sg:phone":"+1 773 768 2829",
    "sg:postcode":"60649",
    "sg:province":"IL",
    "wof:name":"Clemcares",
    "wof:placetype":"venue"
},
  "geometry": {"coordinates":[-87.566349,41.761471],"type":"Point"}
}