{
  "type": "Feature",
  "properties": {
    "addr:full":"950 Collins St Joliet IL 60432",
    "addr:housenumber":"950",
    "addr:postcode":"60432",
    "addr:street":"Collins St",
    "iso:country":"US",
    "sg:address":"950 Collins St",
    "sg:city":"Joliet",
    "sg:classifiers":[
        {
            "category":"Bars & Pubs",
            "type":"Food & Drink"
        }
    ],
    "sg:phone":"+1 815 722 7463",
    "sg:postcode":"60432",
    "sg:province":"IL",
    "wof:name":"Sam's Place",
    "wof:placetype":"venue"
},
  "geometry": {"coordinates":[-88.07253300000001,41.542338],"type":"Point"}
}