{
  "type": "Feature",
  "properties": {
    "iso:country":"US",
    "sg:address":"1 Columbus Plz",
    "sg:city":"Collinsville",
    "sg:classifiers":[
        {
            "category":"Organizations",
            "subcategory":"Community Association",
            "type":"Services"
        }
    ],
    "sg:phone":"+1 618 345 1492",
    "sg:postcode":"62234",
    "sg:province":"IL",
    "sg:tags":[
        "fraternal"
    ],
    "wof:name":"Knights Of Columbus",
    "wof:placetype":"venue"
},
  "geometry": {"coordinates":[-90.01570599999999,38.666934],"type":"Point"}
}