{
  "type": "Feature",
  "properties": {
    "iso:country":"US",
    "sg:address":"420 E Higgins Rd",
    "sg:city":"Elk Grove Village",
    "sg:classifiers":[
        {
            "category":"Retail",
            "subcategory":"Auto Repair",
            "type":"Services"
        }
    ],
    "sg:phone":"+1 847 437 4700",
    "sg:postcode":"60007",
    "sg:province":"IL",
    "sg:tags":[
        "transmission"
    ],
    "wof:name":"Higgins Transmission",
    "wof:placetype":"venue"
},
  "geometry": {"coordinates":[-87.982479,42.027935],"type":"Point"}
}