{
  "type": "Feature",
  "properties": {
    "iso:country":"US",
    "sg:address":"934 S State St",
    "sg:city":"Lockport",
    "sg:classifiers":[
        {
            "category":"Professional",
            "subcategory":"Management & Consulting",
            "type":"Services"
        }
    ],
    "sg:phone":"+1 815 836 8500",
    "sg:postcode":"60441",
    "sg:province":"IL",
    "sg:tags":[
        "consultant",
        "security",
        "system"
    ],
    "wof:name":"Terra Security Systems",
    "wof:placetype":"venue"
},
  "geometry": {"coordinates":[-88.057724,41.588661],"type":"Point"}
}