{
  "type": "Feature",
  "properties": {
    "addr:full":"520 Gary Dr Bolingbrook IL 60440",
    "addr:housenumber":"520",
    "addr:postcode":"60440",
    "addr:street":"Gary Dr",
    "iso:country":"US",
    "sg:address":"520 Gary Dr",
    "sg:city":"Bolingbrook",
    "sg:classifiers":[
        {
            "category":"Education",
            "subcategory":"School",
            "type":"Public Place"
        }
    ],
    "sg:phone":"+1 630 739 3603",
    "sg:postcode":"60440",
    "sg:province":"IL",
    "sg:tags":[
        "elementary"
    ],
    "wof:name":"Schools Pub Bolingbrook Vly View Cmnty Unit Schl",
    "wof:placetype":"venue"
},
  "geometry": {"coordinates":[-88.047594,41.703144],"type":"Point"}
}