{
  "type": "Feature",
  "properties": {
    "iso:country":"US",
    "sg:address":"17316 Marengo Rd",
    "sg:city":"Union",
    "sg:classifiers":[
        {
            "category":"Manufacturing",
            "subcategory":"Buildings",
            "type":"Manufacturing & Wholesale Goods"
        },
        {
            "category":"Building & Trades",
            "subcategory":"Construction",
            "type":"Services"
        }
    ],
    "sg:phone":"+1 815 923 2613",
    "sg:postcode":"60180",
    "sg:province":"IL",
    "sg:tags":[
        "industrial",
        "system",
        "specialty",
        "builder",
        "heating",
        "contractor",
        "contractors-commercial",
        "home",
        "air conditioning"
    ],
    "wof:name":"Light Center Foundation",
    "wof:placetype":"venue"
},
  "geometry": {"coordinates":[-88.533396,42.200311],"type":"Point"}
}