{
  "type": "Feature",
  "properties": {
    "addr:full":"432 Hillside Ave Glen Ellyn IL 60137",
    "addr:housenumber":"432",
    "addr:postcode":"60137",
    "addr:street":"Hillside Ave",
    "iso:country":"US",
    "sg:address":"432 Hillside Ave",
    "sg:city":"Glen Ellyn",
    "sg:classifiers":[
        {
            "category":"Professional",
            "subcategory":"Engineering",
            "type":"Services"
        }
    ],
    "sg:phone":"+1 630 790 9054",
    "sg:postcode":"60137",
    "sg:province":"IL",
    "wof:name":"Scribner Design Group",
    "wof:placetype":"venue"
},
  "geometry": {"coordinates":[-88.07265599999999,41.874035],"type":"Point"}
}