{
  "type": "Feature",
  "properties": {
    "iso:country":"US",
    "sg:address":"1002 E Laurel Ave",
    "sg:city":"Havana",
    "sg:classifiers":[
        {
            "category":"Government",
            "subcategory":"Office",
            "type":"Public Place"
        }
    ],
    "sg:phone":"+1 309 543 2201",
    "sg:postcode":"62644",
    "sg:province":"IL",
    "sg:tags":[
        "county",
        "program",
        "health"
    ],
    "wof:name":"Mason County Health Dept",
    "wof:placetype":"venue"
},
  "geometry": {"coordinates":[-90.04871300000001,40.29705],"type":"Point"}
}