{
  "type": "Feature",
  "properties": {
    "addr:full":"12815 Model Ct Midlothian IL 60445",
    "addr:housenumber":"12815",
    "addr:postcode":"60445",
    "addr:street":"Model Ct",
    "iso:country":"US",
    "sg:address":"12815 Model Ct",
    "sg:city":"Midlothian",
    "sg:classifiers":[
        {
            "category":"Real Estate",
            "subcategory":"Real Estate Operator",
            "type":"Services"
        }
    ],
    "sg:phone":"+1 708 389 4484",
    "sg:postcode":"60445",
    "sg:province":"IL",
    "sg:tags":[
        "property",
        "lessor"
    ],
    "wof:name":"Jnj Management",
    "wof:placetype":"venue"
},
  "geometry": {"coordinates":[-87.750314,41.658753],"type":"Point"}
}