{
  "type": "Feature",
  "properties": {
    "iso:country":"US",
    "sg:address":"1701 Golfview Dr",
    "sg:city":"Collinsville",
    "sg:classifiers":[
        {
            "category":"Wholesale",
            "subcategory":"Construction Materials",
            "type":"Manufacturing & Wholesale Goods"
        }
    ],
    "sg:phone":"+1 618 346 9186",
    "sg:postcode":"62234",
    "sg:province":"IL",
    "sg:tags":[
        "frame",
        "door"
    ],
    "wof:name":"Builders Specialties Hardware",
    "wof:placetype":"venue"
},
  "geometry": {"coordinates":[-89.975365,38.693795],"type":"Point"}
}