{
  "type": "Feature",
  "properties": {
    "iso:country":"US",
    "sg:address":"835 E Wilson St",
    "sg:city":"Batavia",
    "sg:classifiers":[
        {
            "category":"Retail",
            "subcategory":"Repair Shop",
            "type":"Services"
        }
    ],
    "sg:phone":"+1 630 879 2626",
    "sg:postcode":"60510",
    "sg:province":"IL",
    "sg:tags":[
        "mfg"
    ],
    "wof:name":"Valley Upholstery",
    "wof:placetype":"venue"
},
  "geometry": {"coordinates":[-88.291257,41.851634],"type":"Point"}
}