{
  "type": "Feature",
  "properties": {
    "addr:full":"4863 N Winthrop Ave Chicago IL 60640",
    "addr:housenumber":"4863",
    "addr:postcode":"60640",
    "addr:street":"N Winthrop Ave",
    "iso:country":"US",
    "sg:address":"4863 N Winthrop Ave",
    "sg:city":"Chicago",
    "sg:classifiers":[
        {
            "category":"Personal",
            "subcategory":"Nail Salon",
            "type":"Services"
        }
    ],
    "sg:phone":"+1 773 744 1842",
    "sg:postcode":"60640",
    "sg:province":"IL",
    "wof:name":"3 D Nails",
    "wof:placetype":"venue"
},
  "geometry": {"coordinates":[-87.65754699999999,41.970623],"type":"Point"}
}