{
  "type": "Feature",
  "properties": {
    "addr:full":"100 W. Higgins Suite 1-15 South Barrington IL 60010",
    "addr:housenumber":"100",
    "addr:postcode":"60010",
    "addr:street":"W. Higgins Suite 1-15",
    "iso:country":"US",
    "sg:address":"100 W. Higgins Suite 1-15",
    "sg:city":"South Barrington",
    "sg:classifiers":[
        {
            "category":"Sports & Exercise",
            "subcategory":"Gym",
            "type":"Entertainment"
        }
    ],
    "sg:phone":"+1 847 551 8800",
    "sg:postcode":"60010",
    "sg:province":"IL",
    "sg:website":"www.xsportfitness.com",
    "wof:name":"XSport Fitness",
    "wof:placetype":"venue"
},
  "geometry": {"coordinates":[-88.18418,42.073571],"type":"Point"}
}