{
  "type": "Feature",
  "properties": {
    "iso:country":"US",
    "sg:address":"4055 N Milwaukee Ave",
    "sg:city":"Chicago",
    "sg:classifiers":[
        {
            "category":"Wholesale",
            "subcategory":"Stationery",
            "type":"Manufacturing & Wholesale Goods"
        }
    ],
    "sg:phone":"+1 773 282 6771",
    "sg:postcode":"60641",
    "sg:province":"IL",
    "sg:tags":[
        "card"
    ],
    "wof:name":"Crown Card & Gift Shop",
    "wof:placetype":"venue"
},
  "geometry": {"coordinates":[-87.749397,41.954498],"type":"Point"}
}