{
  "type": "Feature",
  "properties": {
    "addr:full":"300 Fox Glen Ct Barrington IL 60010",
    "addr:housenumber":"300",
    "addr:postcode":"60010",
    "addr:street":"Fox Glen Ct",
    "iso:country":"US",
    "sg:address":"300 Fox Glen Ct",
    "sg:city":"Barrington",
    "sg:classifiers":[
        {
            "category":"Health Services",
            "subcategory":"Doctor",
            "type":"Services"
        }
    ],
    "sg:phone":"+1 847 382 6070",
    "sg:postcode":"60010",
    "sg:province":"IL",
    "sg:website":"www.drminithakkarmd.com",
    "wof:name":"Thakker Padmini Mini MD Sc",
    "wof:placetype":"venue"
},
  "geometry": {"coordinates":[-88.19828,42.193207],"type":"Point"}
}