{
  "type": "Feature",
  "properties": {
    "iso:country":"US",
    "sg:address":"11638 Il Route 125",
    "sg:city":"Beardstown",
    "sg:classifiers":[
        {
            "category":"Manufacturing",
            "subcategory":"Food",
            "type":"Manufacturing & Wholesale Goods"
        },
        {
            "category":"Farming",
            "subcategory":"Farm",
            "type":"Manufacturing & Wholesale Goods"
        }
    ],
    "sg:phone":"+1 217 323 4321",
    "sg:postcode":"62618",
    "sg:province":"IL",
    "sg:tags":[
        "corn",
        "product"
    ],
    "wof:name":"Richard Jokisch",
    "wof:placetype":"venue"
},
  "geometry": {"coordinates":[-90.36895,39.992485],"type":"Point"}
}