{
  "type": "Feature",
  "properties": {
    "addr:full":"2901 Plainfield Rd Joliet IL 60435",
    "addr:housenumber":"2901",
    "addr:postcode":"60435",
    "addr:street":"Plainfield Rd",
    "iso:country":"US",
    "sg:address":"2901 Plainfield Rd",
    "sg:city":"Joliet",
    "sg:classifiers":[
        {
            "category":"Restaurant",
            "type":"Food & Drink"
        }
    ],
    "sg:menulink":"http://www.allmenus.com/il/plainfield/79873-pizza-hut/menu/",
    "sg:phone":"+1 815 436 4166",
    "sg:postcode":"60435",
    "sg:province":"IL",
    "sg:tags":[
        "american",
        "pizza"
    ],
    "wof:name":"Pizza Hut",
    "wof:placetype":"venue"
},
  "geometry": {"coordinates":[-88.16106600000001,41.579174],"type":"Point"}
}