{
  "type": "Feature",
  "properties": {
    "iso:country":"US",
    "sg:address":"1327 Danhof Dr",
    "sg:city":"Bolingbrook",
    "sg:classifiers":[
        {
            "category":"Professional",
            "subcategory":"Accounting & Tax Preparation",
            "type":"Services"
        }
    ],
    "sg:phone":"+1 815 577 1677",
    "sg:postcode":"60490",
    "sg:province":"IL",
    "sg:tags":[
        "return",
        "filing"
    ],
    "wof:name":"Mohammed Account Tax Bus Svc",
    "wof:placetype":"venue"
},
  "geometry": {"coordinates":[-88.1694,41.650823],"type":"Point"}
}