{
  "type": "Feature",
  "properties": {
    "iso:country":"US",
    "sg:address":"3450 Ridge Rd",
    "sg:city":"Lansing",
    "sg:classifiers":[
        {
            "category":"Building & Trades",
            "subcategory":"Construction",
            "type":"Services"
        }
    ],
    "sg:phone":"+1 708 889 0940",
    "sg:postcode":"60438",
    "sg:province":"IL",
    "sg:tags":[
        "contractor"
    ],
    "wof:name":"Steppo Supply & Construction",
    "wof:placetype":"venue"
},
  "geometry": {"coordinates":[-87.533044,41.564611],"type":"Point"}
}