{
  "type": "Feature",
  "properties": {
    "addr:full":"1428 N Western Ave Chicago IL 60622",
    "addr:housenumber":"1428",
    "addr:postcode":"60622",
    "addr:street":"N Western Ave",
    "iso:country":"US",
    "sg:address":"1428 N Western Ave",
    "sg:city":"Chicago",
    "sg:classifiers":[
        {
            "category":"Personal",
            "subcategory":"Beauty Salon",
            "type":"Services"
        },
        {
            "category":"Personal",
            "subcategory":"Day Spa",
            "type":"Services"
        }
    ],
    "sg:phone":"+1 773 276 0672",
    "sg:postcode":"60622",
    "sg:province":"IL",
    "wof:name":"Tropical S P A",
    "wof:placetype":"venue"
},
  "geometry": {"coordinates":[-87.687364,41.907192],"type":"Point"}
}