{
  "type": "Feature",
  "properties": {
    "iso:country":"US",
    "sg:address":"840 W Chalmers Place",
    "sg:city":"Chicago",
    "sg:classifiers":[
        {
            "category":"Health Services",
            "subcategory":"Doctor",
            "type":"Services"
        }
    ],
    "sg:phone":"+1 773 525 1858",
    "sg:postcode":"60614",
    "sg:province":"IL",
    "wof:name":"Freed Harvey M MD",
    "wof:placetype":"venue"
},
  "geometry": {"coordinates":[-87.65027499999999,41.924716],"type":"Point"}
}