{
  "type": "Feature",
  "properties": {
    "iso:country":"US",
    "sg:address":"4010 E State St",
    "sg:city":"Rockford",
    "sg:classifiers":[
        {
            "category":"Wholesale",
            "subcategory":"Machinery & Supplies",
            "type":"Manufacturing & Wholesale Goods"
        }
    ],
    "sg:phone":"+1 815 226 0900",
    "sg:postcode":"61108",
    "sg:province":"IL",
    "sg:tags":[
        "salon",
        "beauty"
    ],
    "wof:name":"State Beauty Supply",
    "wof:placetype":"venue"
},
  "geometry": {"coordinates":[-89.031557,42.264593],"type":"Point"}
}