{
  "type": "Feature",
  "properties": {
    "addr:full":"6500 W Archer Ave Chicago IL 60638",
    "addr:housenumber":"6500",
    "addr:postcode":"60638",
    "addr:street":"W Archer Ave",
    "iso:country":"US",
    "sg:address":"6500 W Archer Ave",
    "sg:city":"Chicago",
    "sg:classifiers":[
        {
            "category":"Travel",
            "subcategory":"Travel Agent",
            "type":"Entertainment"
        }
    ],
    "sg:phone":"+1 708 594 3685",
    "sg:postcode":"60638",
    "sg:province":"IL",
    "sg:tags":[
        "consultant",
        "transportation"
    ],
    "wof:name":"Bulkmatic Inc",
    "wof:placetype":"venue"
},
  "geometry": {"coordinates":[-87.784233,41.79232],"type":"Point"}
}