{
  "type": "Feature",
  "properties": {
    "iso:country":"US",
    "sg:address":"5630 W Cermak Rd",
    "sg:city":"Cicero",
    "sg:classifiers":[
        {
            "category":"Restaurant",
            "type":"Food & Drink"
        }
    ],
    "sg:phone":"+1 708 656 8984",
    "sg:postcode":"60804",
    "sg:province":"IL",
    "sg:tags":[
        "mexican"
    ],
    "wof:name":"Taqueria & Birreria Tototlan",
    "wof:placetype":"venue"
},
  "geometry": {"coordinates":[-87.765146,41.851167],"type":"Point"}
}