{
  "type": "Feature",
  "properties": {
    "iso:country":"US",
    "sg:address":"614 E Eureka St",
    "sg:city":"Eureka",
    "sg:classifiers":[
        {
            "category":"Freight",
            "type":"Transportation"
        }
    ],
    "sg:phone":"+1 309 467 4003",
    "sg:postcode":"61530",
    "sg:province":"IL",
    "sg:tags":[
        "operator",
        "local",
        "trucking"
    ],
    "wof:name":"Fly By Night Operations",
    "wof:placetype":"venue"
},
  "geometry": {"coordinates":[-89.264165,40.720386],"type":"Point"}
}