{
  "type": "Feature",
  "properties": {
    "addr:full":"606 N Obannon St Raymond IL 62560",
    "addr:housenumber":"606",
    "addr:postcode":"62560",
    "addr:street":"N Obannon St",
    "iso:country":"US",
    "sg:address":"606 N Obannon St",
    "sg:city":"Raymond",
    "sg:classifiers":[
        {
            "category":"Autos & Motor Vehicles",
            "subcategory":"Boat Sales",
            "type":"Retail Goods"
        }
    ],
    "sg:phone":"+1 217 229 3012",
    "sg:postcode":"62560",
    "sg:province":"IL",
    "sg:website":"http://www.hanksboats.com",
    "wof:name":"Hank's Sales & Service Incorporated",
    "wof:placetype":"venue"
},
  "geometry": {"coordinates":[-89.570053,39.325119],"type":"Point"}
}