{
  "type": "Feature",
  "properties": {
    "iso:country":"US",
    "sg:address":"250 E Main St Ste 307",
    "sg:city":"Galesburg",
    "sg:classifiers":[
        {
            "category":"Professional",
            "type":"Services"
        }
    ],
    "sg:phone":"+1 309 342 2415",
    "sg:postcode":"61401",
    "sg:province":"IL",
    "sg:tags":[
        "processing",
        "data"
    ],
    "wof:name":"Eichhorn Jewelers Inc",
    "wof:placetype":"venue"
},
  "geometry": {"coordinates":[-90.36712,40.94746],"type":"Point"}
}