{
  "type": "Feature",
  "properties": {
    "addr:full":"205 E Washington St Le Roy IL 61752",
    "addr:housenumber":"205",
    "addr:postcode":"61752",
    "addr:street":"E Washington St",
    "iso:country":"US",
    "sg:address":"205 E Washington St",
    "sg:city":"Le Roy",
    "sg:classifiers":[
        {
            "category":"Building & Trades",
            "subcategory":"Landscaping Services",
            "type":"Services"
        }
    ],
    "sg:phone":"+1 309 962 5005",
    "sg:postcode":"61752",
    "sg:province":"IL",
    "sg:tags":[
        "landscape"
    ],
    "wof:name":"Prices Landscape Design",
    "wof:placetype":"venue"
},
  "geometry": {"coordinates":[-88.760563,40.351591],"type":"Point"}
}