{
  "type": "Feature",
  "properties": {
    "iso:country":"US",
    "sg:address":"21 Roberta Dr",
    "sg:city":"Caseyville",
    "sg:classifiers":[
        {
            "category":"Real Estate",
            "subcategory":"Real Estate Operator",
            "type":"Services"
        }
    ],
    "sg:phone":"+1 618 344 7980",
    "sg:postcode":"62232",
    "sg:province":"IL",
    "sg:tags":[
        "mobile",
        "home",
        "community"
    ],
    "wof:name":"Rock Springs LLC",
    "wof:placetype":"venue"
},
  "geometry": {"coordinates":[-89.978919,38.640106],"type":"Point"}
}