{
  "type": "Feature",
  "properties": {
    "addr:full":"35 N River Ln Geneva IL 60134",
    "addr:housenumber":"35",
    "addr:postcode":"60134",
    "addr:street":"N River Ln",
    "iso:country":"US",
    "sg:address":"35 N River Ln",
    "sg:city":"Geneva",
    "sg:classifiers":[
        {
            "category":"Restaurant",
            "type":"Food & Drink"
        }
    ],
    "sg:phone":"+1 630 262 8371",
    "sg:postcode":"60134",
    "sg:province":"IL",
    "sg:tags":[
        "banquet",
        "rooms"
    ],
    "sg:website":"www.riversidereceptions.com",
    "wof:name":"Riverside Reception & Confrnc",
    "wof:placetype":"venue"
},
  "geometry": {"coordinates":[-88.303505,41.88807],"type":"Point"}
}