{
  "type": "Feature",
  "properties": {
    "iso:country":"US",
    "sg:address":"500 W Barry Ave",
    "sg:city":"Chicago",
    "sg:classifiers":[
        {
            "category":"Manufacturing",
            "subcategory":"Retail Goods",
            "type":"Manufacturing & Wholesale Goods"
        }
    ],
    "sg:phone":"+1 773 472 0658",
    "sg:postcode":"60657",
    "sg:province":"IL",
    "sg:tags":[
        "product",
        "mfg"
    ],
    "wof:name":"Gurney Co Inc",
    "wof:placetype":"venue"
},
  "geometry": {"coordinates":[-87.643109,41.937675],"type":"Point"}
}