{
  "type": "Feature",
  "properties": {
    "iso:country":"US",
    "sg:address":"901 W Morton Ave Frnt",
    "sg:city":"Jacksonville",
    "sg:classifiers":[
        {
            "category":"Bars & Pubs",
            "type":"Food & Drink"
        },
        {
            "category":"Restaurant",
            "type":"Food & Drink"
        },
        {
            "category":"Bars & Pubs",
            "subcategory":"Lounge",
            "type":"Food & Drink"
        }
    ],
    "sg:phone":"+1 217 245 5845",
    "sg:postcode":"62650",
    "sg:province":"IL",
    "sg:tags":[
        "tavern",
        "cocktail"
    ],
    "wof:name":"Kuhl Time Corner",
    "wof:placetype":"venue"
},
  "geometry": {"coordinates":[-90.24095199999999,39.723221],"type":"Point"}
}