{
  "type": "Feature",
  "properties": {
    "addr:full":"641 N Clark Street Chicago IL 60610",
    "addr:housenumber":"641",
    "addr:postcode":"60610",
    "addr:street":"N Clark Street",
    "iso:country":"US",
    "sg:address":"641 N Clark Street",
    "sg:city":"Chicago",
    "sg:classifiers":[
        {
            "category":"Shopping",
            "subcategory":"Pharmacy",
            "type":"Retail Goods"
        }
    ],
    "sg:phone":"+1 312 587 1416",
    "sg:postcode":"60610",
    "sg:province":"IL",
    "sg:tags":[
        "drugstore"
    ],
    "wof:name":"Walgreens",
    "wof:placetype":"venue"
},
  "geometry": {"coordinates":[-87.631315,41.893621],"type":"Point"}
}