{
  "type": "Feature",
  "properties": {
    "iso:country":"US",
    "sg:address":"414 S Oak Park Ave Ste 2",
    "sg:city":"Oak Park",
    "sg:classifiers":[
        {
            "category":"Health Services",
            "subcategory":"Dentist",
            "type":"Services"
        }
    ],
    "sg:phone":"+1 708 524 4628",
    "sg:postcode":"60302",
    "sg:province":"IL",
    "wof:name":"Galic Michael M DDS",
    "wof:placetype":"venue"
},
  "geometry": {"coordinates":[-87.794016,41.881322],"type":"Point"}
}