{
  "type": "Feature",
  "properties": {
    "addr:full":"220 Bond St Elk Grove Vlg IL 60007",
    "addr:housenumber":"220",
    "addr:postcode":"60007",
    "addr:street":"Bond St",
    "iso:country":"US",
    "sg:address":"220 Bond St",
    "sg:city":"Elk Grove Vlg",
    "sg:classifiers":[
        {
            "category":"Manufacturing",
            "subcategory":"Printing",
            "type":"Manufacturing & Wholesale Goods"
        }
    ],
    "sg:phone":"+1 847 357 9870",
    "sg:postcode":"60007",
    "sg:province":"IL",
    "sg:tags":[
        "printer"
    ],
    "wof:name":"Graphic Industries Inc",
    "wof:placetype":"venue"
},
  "geometry": {"coordinates":[-87.9748,42.028192],"type":"Point"}
}