{
  "type": "Feature",
  "properties": {
    "addr:full":"4825 S Pulaski Road Chicago IL 60632",
    "addr:housenumber":"4825",
    "addr:postcode":"60632",
    "addr:street":"S Pulaski Road",
    "iso:country":"US",
    "sg:address":"4825 S Pulaski Road",
    "sg:city":"Chicago",
    "sg:classifiers":[
        {
            "category":"Autos & Motor Vehicles",
            "subcategory":"Automobile Sales",
            "type":"Retail Goods"
        },
        {
            "category":"Retail",
            "subcategory":"Auto Rental",
            "type":"Services"
        }
    ],
    "sg:phone":"+1 773 579 6800",
    "sg:postcode":"60632",
    "sg:province":"IL",
    "sg:tags":[
        "car",
        "leasing",
        "truck"
    ],
    "sg:website":"www.enterprise.com",
    "wof:name":"Enterprise Rent-A-Car",
    "wof:placetype":"venue"
},
  "geometry": {"coordinates":[-87.723298,41.804741],"type":"Point"}
}