{
  "type": "Feature",
  "properties": {
    "iso:country":"US",
    "sg:address":"8935 Skokie Blvd",
    "sg:city":"Skokie",
    "sg:classifiers":[
        {
            "category":"Building & Trades",
            "subcategory":"Cleaning & Sanitation",
            "type":"Services"
        }
    ],
    "sg:phone":"+1 312 363 8714",
    "sg:postcode":"60077",
    "sg:province":"IL",
    "sg:tags":[
        "butler",
        "maid"
    ],
    "sg:website":"www.accessmaids.com",
    "wof:name":"ACCESSMAIDS.COM",
    "wof:placetype":"venue"
},
  "geometry": {"coordinates":[-87.746968,42.042673],"type":"Point"}
}