{
  "type": "Feature",
  "properties": {
    "addr:full":"2936 Wireton Rd Blue Island IL 60406",
    "addr:postcode":"2936;60406",
    "addr:street":"Wireton Rd",
    "iso:country":"US",
    "sg:address":"2936 Wireton Rd",
    "sg:city":"Blue Island",
    "sg:classifiers":[
        {
            "category":"Home & Garden",
            "subcategory":"Furniture",
            "type":"Retail Goods"
        }
    ],
    "sg:phone":"+1 708 597 4766",
    "sg:postcode":"60406",
    "sg:province":"IL",
    "sg:tags":[
        "store"
    ],
    "wof:name":"Wright's Furniture Warehouse",
    "wof:placetype":"venue"
},
  "geometry": {"coordinates":[-87.69454,41.657071],"type":"Point"}
}