{
  "type": "Feature",
  "properties": {
    "iso:country":"US",
    "sg:address":"11427 S Central Park Ave",
    "sg:city":"Chicago",
    "sg:classifiers":[
        {
            "category":"Shopping",
            "subcategory":"Bicycles & Sporting Goods",
            "type":"Retail Goods"
        }
    ],
    "sg:phone":"+1   ",
    "sg:postcode":"60655",
    "sg:province":"IL",
    "wof:name":"All Type Sporting Enterprises",
    "wof:placetype":"venue"
},
  "geometry": {"coordinates":[-87.71022600000001,41.684489],"type":"Point"}
}