{
  "type": "Feature",
  "properties": {
    "addr:full":"712 Morse Ave Schaumburg IL 60193",
    "addr:housenumber":"712",
    "addr:postcode":"60193",
    "addr:street":"Morse Ave",
    "iso:country":"US",
    "sg:address":"712 Morse Ave",
    "sg:city":"Schaumburg",
    "sg:classifiers":[
        {
            "category":"Wholesale",
            "subcategory":"Machinery & Supplies",
            "type":"Manufacturing & Wholesale Goods"
        }
    ],
    "sg:phone":"+1 847 891 6994",
    "sg:postcode":"60193",
    "sg:province":"IL",
    "sg:tags":[
        "cleaning"
    ],
    "wof:name":"Cleaning Service Systems",
    "wof:placetype":"venue"
},
  "geometry": {"coordinates":[-88.096327,42.000431],"type":"Point"}
}