{
  "type": "Feature",
  "properties": {
    "iso:country":"US",
    "sg:address":"625 E Monroe St",
    "sg:city":"Cuba",
    "sg:classifiers":[
        {
            "category":"Social Services",
            "subcategory":"Retirement Home",
            "type":"Services"
        },
        {
            "category":"Social Services",
            "subcategory":"Adult Care",
            "type":"Services"
        }
    ],
    "sg:phone":"+1 309 785 5012",
    "sg:postcode":"61427",
    "sg:province":"IL",
    "sg:tags":[
        "living",
        "assisted",
        "nurses-home",
        "facility"
    ],
    "sg:website":"http://www.fultoncountyhealth.com",
    "wof:name":"The Clayberg",
    "wof:placetype":"venue"
},
  "geometry": {"coordinates":[-90.190724,40.488446],"type":"Point"}
}