{
  "type": "Feature",
  "properties": {
    "iso:country":"US",
    "sg:address":"6216 Lakeview Dr",
    "sg:city":"Huntley",
    "sg:classifiers":[
        {
            "category":"Professional",
            "subcategory":"Lawyer & Legal Services",
            "type":"Services"
        }
    ],
    "sg:phone":"+1 847 669 3124",
    "sg:postcode":"60142",
    "sg:province":"IL",
    "sg:tags":[
        "attorney",
        "practice"
    ],
    "wof:name":"Richard Stopka & Associates",
    "wof:placetype":"venue"
},
  "geometry": {"coordinates":[-88.439601,42.239102],"type":"Point"}
}