{
  "type": "Feature",
  "properties": {
    "addr:full":"107 Bent Tree Ln Schaumburg IL 60195",
    "addr:housenumber":"107",
    "addr:postcode":"60195",
    "addr:street":"Bent Tree Ln",
    "iso:country":"US",
    "sg:address":"107 Bent Tree Ln",
    "sg:city":"Schaumburg",
    "sg:classifiers":[
        {
            "category":"Building & Trades",
            "subcategory":"Electrical",
            "type":"Services"
        }
    ],
    "sg:phone":"+1 847 885 6043",
    "sg:postcode":"60195",
    "sg:province":"IL",
    "sg:tags":[
        "electric",
        "contractor"
    ],
    "wof:name":"Elston Electric",
    "wof:placetype":"venue"
},
  "geometry": {"coordinates":[-88.08269199999999,42.05317],"type":"Point"}
}