{
  "type": "Feature",
  "properties": {
    "addr:full":"77 W Jackson Blvd Chicago IL 60661",
    "addr:housenumber":"77",
    "addr:postcode":"60661",
    "addr:street":"W Jackson Blvd",
    "iso:country":"US",
    "sg:address":"77 W Jackson Blvd",
    "sg:city":"Chicago",
    "sg:classifiers":[
        {
            "category":"Restaurant",
            "type":"Food & Drink"
        }
    ],
    "sg:phone":"+1   ",
    "sg:postcode":"60661",
    "sg:province":"IL",
    "sg:tags":[
        "eating"
    ],
    "wof:name":"Popeyes Chicken & Biscuits",
    "wof:placetype":"venue"
},
  "geometry": {"coordinates":[-87.62971400000001,41.878161],"type":"Point"}
}