{
  "type": "Feature",
  "properties": {
    "iso:country":"US",
    "sg:address":"122 W Main St",
    "sg:city":"Mount Sterling",
    "sg:classifiers":[
        {
            "category":"Personal",
            "subcategory":"Beauty Salon",
            "type":"Services"
        }
    ],
    "sg:phone":"+1 217 773 2046",
    "sg:postcode":"62353",
    "sg:province":"IL",
    "sg:tags":[
        "shop"
    ],
    "wof:name":"Inez Beauty Bar",
    "wof:placetype":"venue"
},
  "geometry": {"coordinates":[-90.766755,39.986086],"type":"Point"}
}