{
  "type": "Feature",
  "properties": {
    "iso:country":"US",
    "sg:address":"12054 S State St",
    "sg:city":"Chicago",
    "sg:classifiers":[
        {
            "category":"Building & Trades",
            "subcategory":"Plumbing",
            "type":"Services"
        }
    ],
    "sg:phone":"+1 773 660 8860",
    "sg:postcode":"60628",
    "sg:province":"IL",
    "wof:name":"Universal C & M Plumbing Service",
    "wof:placetype":"venue"
},
  "geometry": {"coordinates":[-87.622736,41.674799],"type":"Point"}
}