{
  "type": "Feature",
  "properties": {
    "iso:country":"US",
    "sg:address":"389 Sola Dr",
    "sg:city":"Gilberts",
    "sg:classifiers":[
        {
            "category":"Manufacturing",
            "subcategory":"Buildings",
            "type":"Manufacturing & Wholesale Goods"
        },
        {
            "category":"Building & Trades",
            "subcategory":"Construction",
            "type":"Services"
        }
    ],
    "sg:phone":"+1 847 844 1453",
    "sg:postcode":"60136",
    "sg:province":"IL",
    "sg:tags":[
        "industrial",
        "consultant",
        "builder",
        "contractor",
        "contractors-commercial",
        "home"
    ],
    "wof:name":"Brigantine Construction Consultants",
    "wof:placetype":"venue"
},
  "geometry": {"coordinates":[-88.36591799999999,42.100496],"type":"Point"}
}