{
  "type": "Feature",
  "properties": {
    "iso:country":"US",
    "sg:address":"3922 Main St",
    "sg:city":"Mc Henry",
    "sg:classifiers":[
        {
            "category":"Professional",
            "subcategory":"Engineering",
            "type":"Services"
        }
    ],
    "sg:phone":"+1 815 363 9200",
    "sg:postcode":"60050",
    "sg:province":"IL",
    "wof:name":"Land Technology Inc",
    "wof:placetype":"venue"
},
  "geometry": {"coordinates":[-88.274114,42.343592],"type":"Point"}
}