{
  "type": "Feature",
  "properties": {
    "addr:full":"1205C E Florida Ave Urbana IL 61801",
    "addr:housenumber":"1205c",
    "addr:postcode":"61801",
    "addr:street":"E Florida Ave",
    "iso:country":"US",
    "sg:address":"1205C E Florida Ave",
    "sg:city":"Urbana",
    "sg:classifiers":[
        {
            "category":"Real Estate",
            "subcategory":"Real Estate Operator",
            "type":"Services"
        }
    ],
    "sg:phone":"+1 217 344 2072",
    "sg:postcode":"61801",
    "sg:province":"IL",
    "sg:tags":[
        "apartment"
    ],
    "wof:name":"Florida Avenue Apartments",
    "wof:placetype":"venue"
},
  "geometry": {"coordinates":[-88.194058,40.098378],"type":"Point"}
}