{
  "type": "Feature",
  "properties": {
    "addr:full":"414 Grouse Ln Deerfield IL 60015",
    "addr:housenumber":"414",
    "addr:postcode":"60015",
    "addr:street":"Grouse Ln",
    "iso:country":"US",
    "sg:address":"414 Grouse Ln",
    "sg:city":"Deerfield",
    "sg:classifiers":[
        {
            "category":"Social Services",
            "subcategory":"Child Care",
            "type":"Services"
        }
    ],
    "sg:phone":"+1 847 459 3315",
    "sg:postcode":"60015",
    "sg:province":"IL",
    "sg:tags":[
        "day"
    ],
    "wof:name":"Pathways To Learning",
    "wof:placetype":"venue"
},
  "geometry": {"coordinates":[-87.93252699999999,42.16137],"type":"Point"}
}