{
  "type": "Feature",
  "properties": {
    "addr:full":"9409 Schiller Blvd Franklin Park IL 60131",
    "addr:housenumber":"9409",
    "addr:postcode":"60131",
    "addr:street":"Schiller Blvd",
    "iso:country":"US",
    "sg:address":"9409 Schiller Blvd",
    "sg:city":"Franklin Park",
    "sg:classifiers":[
        {
            "category":"Manufacturing",
            "subcategory":"Motor Vehicles & Parts",
            "type":"Manufacturing & Wholesale Goods"
        }
    ],
    "sg:phone":"+1 847 455 8654",
    "sg:postcode":"60131",
    "sg:province":"IL",
    "sg:tags":[
        "heater",
        "motorized",
        "for",
        "mfg"
    ],
    "wof:name":"Polly Heaters Inc",
    "wof:placetype":"venue"
},
  "geometry": {"coordinates":[-87.862853,41.933138],"type":"Point"}
}