{
  "type": "Feature",
  "properties": {
    "addr:full":"3840 Harvard Ter Skokie IL 60076",
    "addr:housenumber":"3840",
    "addr:postcode":"60076",
    "addr:street":"Harvard Ter",
    "iso:country":"US",
    "sg:address":"3840 Harvard Ter",
    "sg:city":"Skokie",
    "sg:classifiers":[
        {
            "category":"Building & Trades",
            "subcategory":"Cleaning & Sanitation",
            "type":"Services"
        }
    ],
    "sg:phone":"+1 847 677 8113",
    "sg:postcode":"60076",
    "sg:province":"IL",
    "sg:tags":[
        "janitorial"
    ],
    "wof:name":"Metro Maintenance Service",
    "wof:placetype":"venue"
},
  "geometry": {"coordinates":[-87.725066,42.02181],"type":"Point"}
}