{
  "type": "Feature",
  "properties": {
    "iso:country":"US",
    "sg:address":"2200 E Devon Ave",
    "sg:city":"Des Plaines",
    "sg:classifiers":[
        {
            "category":"Manufacturing",
            "subcategory":"Wood Products",
            "type":"Manufacturing & Wholesale Goods"
        }
    ],
    "sg:phone":"+1 847 803 4500",
    "sg:postcode":"60018",
    "sg:province":"IL",
    "sg:tags":[
        "mfg",
        "plastic"
    ],
    "wof:name":"Nu-Dell Plastics",
    "wof:placetype":"venue"
},
  "geometry": {"coordinates":[-87.870676,41.995532],"type":"Point"}
}