{
  "type": "Feature",
  "properties": {
    "iso:country":"US",
    "sg:address":"2055 Walnut Cir",
    "sg:city":"Northbrook",
    "sg:classifiers":[
        {
            "category":"Building & Trades",
            "subcategory":"Landscaping Services",
            "type":"Services"
        }
    ],
    "sg:phone":"+1 847 835 1195",
    "sg:postcode":"60062",
    "sg:province":"IL",
    "sg:tags":[
        "removal",
        "firewood",
        "tree",
        "retail"
    ],
    "wof:name":"Firewood King",
    "wof:placetype":"venue"
},
  "geometry": {"coordinates":[-87.82986699999999,42.148804],"type":"Point"}
}