{
  "type": "Feature",
  "properties": {
    "iso:country":"US",
    "sg:address":"855 E Roxanna Cir",
    "sg:city":"Kankakee",
    "sg:classifiers":[
        {
            "category":"Building & Trades",
            "subcategory":"Landscaping Services",
            "type":"Services"
        }
    ],
    "sg:phone":"+1 815 939 7831",
    "sg:postcode":"60901",
    "sg:province":"IL",
    "wof:name":"Larrys Landscape & Lawn Svc",
    "wof:placetype":"venue"
},
  "geometry": {"coordinates":[-87.851391,41.05986],"type":"Point"}
}