{
  "type": "Feature",
  "properties": {
    "addr:full":"3820 N. Cicero Ave Chicago IL 60641",
    "addr:housenumber":"3820",
    "addr:postcode":"60641",
    "addr:street":"N. Cicero Ave",
    "iso:country":"US",
    "sg:address":"3820 N. Cicero Ave",
    "sg:city":"Chicago",
    "sg:classifiers":[
        {
            "category":"Retail",
            "subcategory":"Auto Repair",
            "type":"Services"
        }
    ],
    "sg:phone":"+1 773 283 3999",
    "sg:postcode":"60641",
    "sg:province":"IL",
    "wof:name":"Millenium Auto Repair",
    "wof:placetype":"venue"
},
  "geometry": {"coordinates":[-87.747536,41.950301],"type":"Point"}
}