{
  "type": "Feature",
  "properties": {
    "iso:country":"US",
    "sg:address":"1133 W Madison St",
    "sg:city":"Chicago",
    "sg:classifiers":[
        {
            "category":"Bars & Pubs",
            "type":"Food & Drink"
        }
    ],
    "sg:phone":"+1 312 432 9107",
    "sg:postcode":"60607",
    "sg:province":"IL",
    "sg:website":"www.thirdrailtavern.com/",
    "wof:name":"Third Rail Tavern",
    "wof:placetype":"venue"
},
  "geometry": {"coordinates":[-87.655739,41.881604],"type":"Point"}
}