{
  "type": "Feature",
  "properties": {
    "iso:country":"US",
    "sg:address":"PO Box 60",
    "sg:city":"Palos Park",
    "sg:classifiers":[
        {
            "category":"Professional",
            "subcategory":"Lawyer & Legal Services",
            "type":"Services"
        }
    ],
    "sg:phone":"+1 708 923 9735",
    "sg:postcode":"60464",
    "sg:province":"IL",
    "wof:name":"Gordan Elias M Attorney At Law",
    "wof:placetype":"venue"
},
  "geometry": {"coordinates":[-87.854401,41.657799],"type":"Point"}
}