{
  "type": "Feature",
  "properties": {
    "addr:full":"13016 N 1500th Ave Cambridge IL 61238",
    "addr:housenumber":"13016",
    "addr:postcode":"61238",
    "addr:street":"N 1500Th Ave",
    "iso:country":"US",
    "sg:address":"13016 N 1500th Ave",
    "sg:city":"Cambridge",
    "sg:classifiers":[
        {
            "category":"Building & Trades",
            "subcategory":"Construction",
            "type":"Services"
        }
    ],
    "sg:phone":"+1 309 944 4294",
    "sg:postcode":"61238",
    "sg:province":"IL",
    "sg:tags":[
        "contractor"
    ],
    "wof:name":"Clarence A Johnson & Sons Co",
    "wof:placetype":"venue"
},
  "geometry": {"coordinates":[-90.185141,41.368475],"type":"Point"}
}