{
  "type": "Feature",
  "properties": {
    "iso:country":"US",
    "sg:address":"303 Gray St",
    "sg:city":"Sidell",
    "sg:classifiers":[
        {
            "category":"Professional",
            "subcategory":"Art Services",
            "type":"Services"
        }
    ],
    "sg:phone":"+1 217 288 9477",
    "sg:postcode":"61876",
    "sg:province":"IL",
    "sg:tags":[
        "graphic",
        "designer"
    ],
    "sg:website":"www.alphaadvertising.com",
    "wof:name":"Alpha Advertising",
    "wof:placetype":"venue"
},
  "geometry": {"coordinates":[-87.82137899999999,39.91289],"type":"Point"}
}