{
  "type": "Feature",
  "properties": {
    "addr:full":"37635 N State Rte 59 Lake Villa IL 60046",
    "addr:housenumber":"37635",
    "addr:postcode":"60046",
    "addr:street":"N State Rte 59",
    "iso:country":"US",
    "sg:address":"37635 N State Rte 59",
    "sg:city":"Lake Villa",
    "sg:classifiers":[
        {
            "category":"Autos & Motor Vehicles",
            "subcategory":"Automobile Sales",
            "type":"Retail Goods"
        }
    ],
    "sg:phone":"+1 847 587 7800",
    "sg:postcode":"60046",
    "sg:province":"IL",
    "sg:tags":[
        "used",
        "classic"
    ],
    "sg:website":"www.rosemotorsports.com",
    "wof:name":"Rose Motorsports Inc",
    "wof:placetype":"venue"
},
  "geometry": {"coordinates":[-88.125857,42.41036],"type":"Point"}
}