{
  "type": "Feature",
  "properties": {
    "iso:country":"US",
    "sg:address":"1123 Emerson St Ste 203",
    "sg:city":"Evanston",
    "sg:classifiers":[
        {
            "category":"Professional",
            "subcategory":"Lawyer & Legal Services",
            "type":"Services"
        }
    ],
    "sg:phone":"+1 847 492 1410",
    "sg:postcode":"60201",
    "sg:province":"IL",
    "sg:tags":[
        "information",
        "attorney",
        "referral"
    ],
    "wof:name":"Evanston Community Defender Inc",
    "wof:placetype":"venue"
},
  "geometry": {"coordinates":[-87.68670400000001,42.052133],"type":"Point"}
}