{
  "type": "Feature",
  "properties": {
    "addr:full":"4057 Old Orchard Rd Skokie IL 60076",
    "addr:housenumber":"4057",
    "addr:postcode":"60076",
    "addr:street":"Old Orchard Rd",
    "iso:country":"US",
    "sg:address":"4057 Old Orchard Rd",
    "sg:city":"Skokie",
    "sg:classifiers":[
        {
            "category":"Health Services",
            "subcategory":"Doctor",
            "type":"Services"
        }
    ],
    "sg:phone":"+1 847 329 1314",
    "sg:postcode":"60076",
    "sg:province":"IL",
    "wof:name":"David P Kaplan DDS",
    "wof:placetype":"venue"
},
  "geometry": {"coordinates":[-87.72857399999999,42.062483],"type":"Point"}
}