{
  "type": "Feature",
  "properties": {
    "addr:full":"5617 Marietta Dr Crystal Lake IL 60014",
    "addr:housenumber":"5617",
    "addr:postcode":"60014",
    "addr:street":"Marietta Dr",
    "iso:country":"US",
    "sg:address":"5617 Marietta Dr",
    "sg:city":"Crystal Lake",
    "sg:classifiers":[
        {
            "category":"Freight",
            "type":"Transportation"
        }
    ],
    "sg:phone":"+1 815 455 1960",
    "sg:postcode":"60014",
    "sg:province":"IL",
    "sg:tags":[
        "trucking"
    ],
    "wof:name":"Beirau Trucking",
    "wof:placetype":"venue"
},
  "geometry": {"coordinates":[-88.283073,42.24869],"type":"Point"}
}