{
  "type": "Feature",
  "properties": {
    "iso:country":"US",
    "sg:address":"1415 Arlington Heights Rd",
    "sg:city":"Arlington Heights",
    "sg:classifiers":[
        {
            "category":"Professional",
            "subcategory":"Management & Consulting",
            "type":"Services"
        }
    ],
    "sg:phone":"+1 847 577 6887",
    "sg:postcode":"60005",
    "sg:province":"IL",
    "sg:tags":[
        "business"
    ],
    "wof:name":"Design Builders Inc",
    "wof:placetype":"venue"
},
  "geometry": {"coordinates":[-87.98057799999999,42.057649],"type":"Point"}
}