{
  "type": "Feature",
  "properties": {
    "iso:country":"US",
    "sg:address":"540 Lake Cook Rd",
    "sg:city":"Deerfield",
    "sg:classifiers":[
        {
            "category":"Insurance",
            "subcategory":"Insurance Agent",
            "type":"Services"
        }
    ],
    "sg:phone":"+1 847 374 2400",
    "sg:postcode":"60015",
    "sg:province":"IL",
    "wof:name":"M M I Cos",
    "wof:placetype":"venue"
},
  "geometry": {"coordinates":[-87.841216,42.152852],"type":"Point"}
}