{
  "type": "Feature",
  "properties": {
    "iso:country":"US",
    "sg:address":"951 N Main St",
    "sg:city":"Lombard",
    "sg:classifiers":[
        {
            "category":"Professional",
            "type":"Services"
        },
        {
            "category":"Personal",
            "type":"Services"
        }
    ],
    "sg:phone":"+1 866 761 6402",
    "sg:postcode":"60148",
    "sg:province":"IL",
    "sg:tags":[
        "industrial",
        "organ",
        "material",
        "storage",
        "movers-commercial",
        "full",
        "moving",
        "services-labor",
        "mover",
        "piano"
    ],
    "sg:website":"https://ecom-bekins-com.netsolads.com/householdmove/action/autoSelectAgent.do?leadSourceCode=35&_nsag=31476",
    "wof:name":"Bekins Agent - Century Moving, Inc.",
    "wof:placetype":"venue"
},
  "geometry": {"coordinates":[-88.017624,41.907215],"type":"Point"}
}