{
  "type": "Feature",
  "properties": {
    "addr:full":"1575 N Green Mount Rd O Fallon IL 62269",
    "addr:housenumber":"1575",
    "addr:postcode":"62269",
    "addr:street":"N Green Mount Rd",
    "iso:country":"US",
    "sg:address":"1575 N Green Mount Rd",
    "sg:city":"O Fallon",
    "sg:classifiers":[
        {
            "category":"Banks & Credit Unions",
            "subcategory":"Bank",
            "type":"Services"
        }
    ],
    "sg:phone":"+1 618 622 3636",
    "sg:postcode":"62269",
    "sg:province":"IL",
    "wof:name":"Reliance Bank",
    "wof:placetype":"venue"
},
  "geometry": {"coordinates":[-89.92904,38.587522],"type":"Point"}
}