{
  "type": "Feature",
  "properties": {
    "iso:country":"US",
    "sg:address":"770 Beloit Rd",
    "sg:city":"Belvidere",
    "sg:classifiers":[
        {
            "category":"Personal",
            "subcategory":"Beauty Salon",
            "type":"Services"
        },
        {
            "category":"Personal",
            "subcategory":"Barber",
            "type":"Services"
        }
    ],
    "sg:phone":"+1 815 544 6363",
    "sg:postcode":"61008",
    "sg:province":"IL",
    "sg:tags":[
        "hair",
        "stylist"
    ],
    "sg:website":"http://www.dukesandlordsfamilyhaircutting.com",
    "wof:name":"Dukes & Lords Family Haircutting Centers",
    "wof:placetype":"venue"
},
  "geometry": {"coordinates":[-88.880745,42.316515],"type":"Point"}
}