{
  "type": "Feature",
  "properties": {
    "addr:full":"210-209 W Main St Carpentersville IL 60110",
    "addr:housenumber":"210-209",
    "addr:postcode":"60110",
    "addr:street":"W Main St",
    "iso:country":"US",
    "sg:address":"210-209 W Main St",
    "sg:city":"Carpentersville",
    "sg:classifiers":[
        {
            "category":"Shopping",
            "subcategory":"Department Store",
            "type":"Retail Goods"
        }
    ],
    "sg:phone":"+1 847 426 4970",
    "sg:postcode":"60110",
    "sg:province":"IL",
    "wof:name":"Tuesday Morning",
    "wof:placetype":"venue"
},
  "geometry": {"coordinates":[-88.29398500000001,42.107884],"type":"Point"}
}