{
  "type": "Feature",
  "properties": {
    "iso:country":"US",
    "sg:address":"1437 Bucklin St",
    "sg:city":"La Salle",
    "sg:classifiers":[
        {
            "category":"Building & Trades",
            "subcategory":"Construction",
            "type":"Services"
        }
    ],
    "sg:phone":"+1 815 223 4053",
    "sg:postcode":"61301",
    "sg:province":"IL",
    "sg:tags":[
        "general",
        "contractor"
    ],
    "wof:name":"Practical Builders Constr Co",
    "wof:placetype":"venue"
},
  "geometry": {"coordinates":[-89.101885,41.343374],"type":"Point"}
}