{
  "type": "Feature",
  "properties": {
    "iso:country":"US",
    "sg:address":"3501 Lake Ave",
    "sg:city":"Wilmette",
    "sg:classifiers":[
        {
            "category":"Shopping",
            "type":"Retail Goods"
        }
    ],
    "sg:phone":"+1 847 256 1462",
    "sg:postcode":"60091",
    "sg:province":"IL",
    "sg:tags":[
        "merchandise"
    ],
    "wof:name":"Waukegan Shell Mart Inc",
    "wof:placetype":"venue"
},
  "geometry": {"coordinates":[-87.76148999999999,42.079571],"type":"Point"}
}