{
  "type": "Feature",
  "properties": {
    "addr:full":"7026 S Western Ave Chicago IL 60636",
    "addr:housenumber":"7026",
    "addr:postcode":"60636",
    "addr:street":"S Western Ave",
    "iso:country":"US",
    "sg:address":"7026 S Western Ave",
    "sg:city":"Chicago",
    "sg:classifiers":[
        {
            "category":"Wholesale",
            "subcategory":"Medical Equipment & Supplies",
            "type":"Manufacturing & Wholesale Goods"
        }
    ],
    "sg:phone":"+1 773 952 7723",
    "sg:postcode":"60636",
    "sg:province":"IL",
    "sg:tags":[
        "soundproofing"
    ],
    "wof:name":"BigDog TV & Electronics, A & A",
    "wof:placetype":"venue"
},
  "geometry": {"coordinates":[-87.683273,41.765682],"type":"Point"}
}