{
  "type": "Feature",
  "properties": {
    "iso:country":"US",
    "sg:address":"136 McKinstry Dr",
    "sg:city":"Elgin",
    "sg:classifiers":[
        {
            "category":"Social Services",
            "type":"Services"
        }
    ],
    "sg:phone":"+1 847 622 8597",
    "sg:postcode":"60123",
    "sg:province":"IL",
    "wof:name":"Sherk Ed",
    "wof:placetype":"venue"
},
  "geometry": {"coordinates":[-88.328997,42.037648],"type":"Point"}
}