{
  "type": "Feature",
  "properties": {
    "iso:country":"US",
    "sg:address":"615 St Johns Dr",
    "sg:city":"Sherman",
    "sg:classifiers":[
        {
            "category":"Social Services",
            "subcategory":"Child Care",
            "type":"Services"
        }
    ],
    "sg:phone":"+1 217 496 2798",
    "sg:postcode":"62684",
    "sg:province":"IL",
    "sg:tags":[
        "day"
    ],
    "wof:name":"All His Children",
    "wof:placetype":"venue"
},
  "geometry": {"coordinates":[-89.612386,39.888646],"type":"Point"}
}