{
  "type": "Feature",
  "properties": {
    "iso:country":"US",
    "sg:address":"971 Autumn Dr",
    "sg:city":"Antioch",
    "sg:classifiers":[
        {
            "category":"Insurance",
            "subcategory":"Insurance Agent",
            "type":"Services"
        }
    ],
    "sg:phone":"+1 847 838 1075",
    "sg:postcode":"60002",
    "sg:province":"IL",
    "sg:tags":[
        "processing"
    ],
    "wof:name":"C Pt Health Care Billing Svc",
    "wof:placetype":"venue"
},
  "geometry": {"coordinates":[-88.067935,42.476189],"type":"Point"}
}