{
  "type": "Feature",
  "properties": {
    "addr:full":"109 S Garrard St Rantoul IL 61866",
    "addr:housenumber":"109",
    "addr:postcode":"61866",
    "addr:street":"S Garrard St",
    "iso:country":"US",
    "sg:address":"109 S Garrard St",
    "sg:city":"Rantoul",
    "sg:classifiers":[
        {
            "category":"Banks & Credit Unions",
            "subcategory":"Investment Brokerage",
            "type":"Services"
        }
    ],
    "sg:phone":"+1 217 893 8171",
    "sg:postcode":"61866",
    "sg:province":"IL",
    "sg:tags":[
        "security"
    ],
    "wof:name":"Edward Jones 02207",
    "wof:placetype":"venue"
},
  "geometry": {"coordinates":[-88.157296,40.310105],"type":"Point"}
}