{
  "type": "Feature",
  "properties": {
    "iso:country":"US",
    "sg:address":"214 E Grand Prairie St",
    "sg:city":"Palestine",
    "sg:classifiers":[
        {
            "category":"Place Of Worship",
            "subcategory":"Church",
            "type":"Public Place"
        },
        {
            "category":"Place Of Worship",
            "type":"Public Place"
        },
        {
            "category":"Organizations",
            "subcategory":"Religious Organization",
            "type":"Services"
        }
    ],
    "sg:phone":"+1 618 586 2768",
    "sg:postcode":"62451",
    "sg:province":"IL",
    "sg:tags":[
        "churches-interdenominational",
        "churches-various",
        "denomination"
    ],
    "sg:website":"http://www.fcc-online.org",
    "wof:name":"First Christian Church",
    "wof:placetype":"venue"
},
  "geometry": {"coordinates":[-87.611324,39.001785],"type":"Point"}
}