{
  "type": "Feature",
  "properties": {
    "iso:country":"US",
    "sg:address":"335 E Glenwood Lansing Rd",
    "sg:city":"Glenwood",
    "sg:classifiers":[
        {
            "category":"Food & Beverages",
            "subcategory":"Liquor & Beverages",
            "type":"Retail Goods"
        }
    ],
    "sg:phone":"+1 708 758 2444",
    "sg:postcode":"60425",
    "sg:province":"IL",
    "sg:tags":[
        "beer",
        "spirit",
        "wine"
    ],
    "wof:name":"Glenwood Liquors",
    "wof:placetype":"venue"
},
  "geometry": {"coordinates":[-87.603104,41.542702],"type":"Point"}
}