{
  "type": "Feature",
  "properties": {
    "addr:full":"4230 N Pulaski Road Chicago IL 60641",
    "addr:housenumber":"4230",
    "addr:postcode":"60641",
    "addr:street":"N Pulaski Road",
    "iso:country":"US",
    "sg:address":"4230 N Pulaski Road",
    "sg:city":"Chicago",
    "sg:classifiers":[
        {
            "category":"Retail",
            "subcategory":"Auto Repair",
            "type":"Services"
        }
    ],
    "sg:phone":"+1 773 427 5211",
    "sg:postcode":"60641",
    "sg:province":"IL",
    "wof:name":"R Auto Center",
    "wof:placetype":"venue"
},
  "geometry": {"coordinates":[-87.72744299999999,41.958106],"type":"Point"}
}