{
  "type": "Feature",
  "properties": {
    "iso:country":"US",
    "sg:address":"115 S La Salle St",
    "sg:city":"Chicago",
    "sg:classifiers":[
        {
            "category":"Professional",
            "subcategory":"Lawyer & Legal Services",
            "type":"Services"
        }
    ],
    "sg:phone":"+1 312 443 0667",
    "sg:postcode":"60603",
    "sg:province":"IL",
    "wof:name":"Snider Rowe W Lwyr",
    "wof:placetype":"venue"
},
  "geometry": {"coordinates":[-87.632301,41.880199],"type":"Point"}
}