{
  "type": "Feature",
  "properties": {
    "iso:country":"US",
    "sg:address":"1479 Keokuk St",
    "sg:city":"Hamilton",
    "sg:classifiers":[
        {
            "category":"Manufacturing",
            "subcategory":"Printing",
            "type":"Manufacturing & Wholesale Goods"
        }
    ],
    "sg:phone":"+1 217 847 2244",
    "sg:postcode":"62341",
    "sg:province":"IL",
    "sg:tags":[
        "commercial",
        "b",
        "printer",
        "lithographic",
        "typesetting"
    ],
    "wof:name":"Great River Printing Co",
    "wof:placetype":"venue"
},
  "geometry": {"coordinates":[-91.338035,40.39654],"type":"Point"}
}