{
  "type": "Feature",
  "properties": {
    "iso:country":"US",
    "sg:address":"502 Webster St",
    "sg:city":"Batavia",
    "sg:classifiers":[
        {
            "category":"Structure",
            "subcategory":"Office Building",
            "type":"Public Place"
        }
    ],
    "sg:phone":"+1 630 879 6162",
    "sg:postcode":"60510",
    "sg:province":"IL",
    "sg:tags":[
        "park"
    ],
    "wof:name":"Killian Properties",
    "wof:placetype":"venue"
},
  "geometry": {"coordinates":[-88.30087,41.848854],"type":"Point"}
}