{
  "type": "Feature",
  "properties": {
    "iso:country":"US",
    "sg:address":"505 Davis Rd",
    "sg:city":"Elgin",
    "sg:classifiers":[
        {
            "category":"Professional",
            "subcategory":"Business Services",
            "type":"Services"
        }
    ],
    "sg:phone":"+1 847 697 1711",
    "sg:postcode":"60123",
    "sg:province":"IL",
    "wof:name":"Assessment Services Ltd",
    "wof:placetype":"venue"
},
  "geometry": {"coordinates":[-88.292922,42.06305],"type":"Point"}
}