{
  "type": "Feature",
  "properties": {
    "addr:full":"3317 N Clark Street Chicago IL 60657",
    "addr:housenumber":"3317",
    "addr:postcode":"60657",
    "addr:street":"N Clark Street",
    "iso:country":"US",
    "sg:address":"3317 N Clark Street",
    "sg:city":"Chicago",
    "sg:classifiers":[
        {
            "category":"Shopping",
            "subcategory":"Bicycles & Sporting Goods",
            "type":"Retail Goods"
        }
    ],
    "sg:phone":"+1 773 248 4970",
    "sg:postcode":"60657",
    "sg:province":"IL",
    "wof:name":"Airtime Snow & Skateboards-Windward Sports",
    "wof:placetype":"venue"
},
  "geometry": {"coordinates":[-87.65266800000001,41.942226],"type":"Point"}
}