{
  "type": "Feature",
  "properties": {
    "addr:full":"3 Walter Ct Lake In The Hills IL 60156",
    "addr:housenumber":"3",
    "addr:postcode":"60156",
    "addr:street":"Walter Ct",
    "iso:country":"US",
    "sg:address":"3 Walter Ct",
    "sg:city":"Lake In The Hills",
    "sg:classifiers":[
        {
            "category":"Freight",
            "type":"Transportation"
        }
    ],
    "sg:phone":"+1 847 658 2633",
    "sg:postcode":"60156",
    "sg:province":"IL",
    "sg:tags":[
        "general"
    ],
    "wof:name":"RES-Com",
    "wof:placetype":"venue"
},
  "geometry": {"coordinates":[-88.305013,42.191326],"type":"Point"}
}