{
  "type": "Feature",
  "properties": {
    "iso:country":"US",
    "sg:address":"210 Hartman Ln Ste 400",
    "sg:city":"O Fallon",
    "sg:classifiers":[
        {
            "category":"Shopping",
            "subcategory":"Clothing, Apparel, & Fashions",
            "type":"Retail Goods"
        }
    ],
    "sg:phone":"+1 618 624 8010",
    "sg:postcode":"62269",
    "sg:province":"IL",
    "sg:tags":[
        "lingerie"
    ],
    "sg:website":"www.brashop.com",
    "wof:name":"Ann's Bra Shop",
    "wof:placetype":"venue"
},
  "geometry": {"coordinates":[-89.947389,38.591159],"type":"Point"}
}