{
  "type": "Feature",
  "properties": {
    "iso:country":"US",
    "sg:address":"1613 Beechwood Dr",
    "sg:city":"Danville",
    "sg:classifiers":[
        {
            "category":"Social Services",
            "subcategory":"Child Care",
            "type":"Services"
        }
    ],
    "sg:phone":"+1 217 443 8210",
    "sg:postcode":"61832",
    "sg:province":"IL",
    "wof:name":"Kenyata's Day Care",
    "wof:placetype":"venue"
},
  "geometry": {"coordinates":[-87.592681,40.143429],"type":"Point"}
}