{
  "type": "Feature",
  "properties": {
    "iso:country":"US",
    "sg:address":"4300 N Hermitage Ave",
    "sg:city":"Chicago",
    "sg:classifiers":[
        {
            "category":"Place Of Worship",
            "subcategory":"Church",
            "type":"Public Place"
        },
        {
            "category":"Place Of Worship",
            "type":"Public Place"
        }
    ],
    "sg:phone":"+1 773 281 8172",
    "sg:postcode":"60613",
    "sg:province":"IL",
    "sg:tags":[
        "churches-presbyterian-arp",
        "churches-presbyterian"
    ],
    "wof:name":"Ravenswood Presbyterian Church",
    "wof:placetype":"venue"
},
  "geometry": {"coordinates":[-87.67234000000001,41.959721],"type":"Point"}
}