{
  "type": "Feature",
  "properties": {
    "iso:country":"US",
    "sg:address":"12113 Cedar Hills Dr",
    "sg:city":"Highland",
    "sg:classifiers":[
        {
            "category":"Real Estate",
            "subcategory":"Real Estate Agent",
            "type":"Services"
        }
    ],
    "sg:phone":"+1 618 651 9822",
    "sg:postcode":"62249",
    "sg:province":"IL",
    "sg:tags":[
        "inspection"
    ],
    "wof:name":"World Inspection Network",
    "wof:placetype":"venue"
},
  "geometry": {"coordinates":[-89.70454700000001,38.753192],"type":"Point"}
}