{
  "type": "Feature",
  "properties": {
    "addr:full":"2668 E 875th Rd Oglesby IL 61348",
    "addr:housenumber":"2668",
    "addr:postcode":"61348",
    "addr:street":"E 875Th Rd",
    "iso:country":"US",
    "sg:address":"2668 E 875th Rd",
    "sg:city":"Oglesby",
    "sg:classifiers":[
        {
            "category":"Restaurant",
            "type":"Food & Drink"
        }
    ],
    "sg:phone":"+1 815 667 4211",
    "sg:postcode":"61348",
    "sg:province":"IL",
    "wof:name":"Starved Rock Lodge & Conf Ctr",
    "wof:placetype":"venue"
},
  "geometry": {"coordinates":[-88.994787,41.315833],"type":"Point"}
}