{
  "type": "Feature",
  "properties": {
    "iso:country":"US",
    "sg:address":"611 Lake Shore Blvd",
    "sg:city":"Wauconda",
    "sg:classifiers":[
        {
            "category":"Professional",
            "subcategory":"Business Services",
            "type":"Services"
        },
        {
            "category":"Utilities",
            "subcategory":"Refuse",
            "type":"Services"
        }
    ],
    "sg:phone":"+1 847 526 7643",
    "sg:postcode":"60084",
    "sg:province":"IL",
    "sg:tags":[
        "garbage",
        "collection",
        "system"
    ],
    "wof:name":"ARS American Roll-Off System",
    "wof:placetype":"venue"
},
  "geometry": {"coordinates":[-88.123073,42.266938],"type":"Point"}
}