{
  "type": "Feature",
  "properties": {
    "addr:full":"102 N Front St Danforth IL 60930",
    "addr:housenumber":"102",
    "addr:postcode":"60930",
    "addr:street":"N Front St",
    "iso:country":"US",
    "sg:address":"102 N Front St",
    "sg:city":"Danforth",
    "sg:classifiers":[
        {
            "category":"Freight",
            "type":"Transportation"
        }
    ],
    "sg:phone":"+1 815 269 2710",
    "sg:postcode":"60930",
    "sg:province":"IL",
    "sg:tags":[
        "trucking"
    ],
    "wof:name":"B & K Inc",
    "wof:placetype":"venue"
},
  "geometry": {"coordinates":[-87.97865299999999,40.821344],"type":"Point"}
}