{
  "type": "Feature",
  "properties": {
    "iso:country":"US",
    "sg:address":"308 S Main St",
    "sg:city":"Homer",
    "sg:classifiers":[
        {
            "category":"Retail",
            "subcategory":"Portrait Studio",
            "type":"Services"
        }
    ],
    "sg:phone":"+1 217 896 2529",
    "sg:postcode":"61849",
    "sg:province":"IL",
    "sg:tags":[
        "photo"
    ],
    "wof:name":"Cotton Papa Photographers",
    "wof:placetype":"venue"
},
  "geometry": {"coordinates":[-87.958116,40.033296],"type":"Point"}
}