{
  "type": "Feature",
  "properties": {
    "iso:country":"US",
    "sg:address":"116 Edwards Ave",
    "sg:city":"La Salle",
    "sg:classifiers":[
        {
            "category":"Personal",
            "subcategory":"Beauty Salon",
            "type":"Services"
        }
    ],
    "sg:phone":"+1 815 223 2020",
    "sg:postcode":"61301",
    "sg:province":"IL",
    "wof:name":"Carolyn's Beauty Salon",
    "wof:placetype":"venue"
},
  "geometry": {"coordinates":[-89.104679,41.350443],"type":"Point"}
}