{
  "type": "Feature",
  "properties": {
    "iso:country":"US",
    "sg:address":"5813 W Cermak Rd",
    "sg:city":"Cicero",
    "sg:classifiers":[
        {
            "category":"Banks & Credit Unions",
            "subcategory":"Bank",
            "type":"Services"
        }
    ],
    "sg:phone":"+1 708 780 9070",
    "sg:postcode":"60804",
    "sg:province":"IL",
    "sg:tags":[
        "mortgage",
        "loan",
        "broker",
        "real estate"
    ],
    "wof:name":"Assured Home Mortgage",
    "wof:placetype":"venue"
},
  "geometry": {"coordinates":[-87.769096,41.8507],"type":"Point"}
}