{
  "type": "Feature",
  "properties": {
    "iso:country":"US",
    "sg:address":"7607 N Sheridan Rd",
    "sg:city":"Chicago",
    "sg:classifiers":[
        {
            "category":"Professional",
            "type":"Services"
        }
    ],
    "sg:phone":"+1 773 761 6516",
    "sg:postcode":"60626",
    "sg:province":"IL",
    "sg:tags":[
        "motion",
        "technician",
        "picture"
    ],
    "wof:name":"Art Film Music & More",
    "wof:placetype":"venue"
},
  "geometry": {"coordinates":[-87.666112,42.019429],"type":"Point"}
}