{
  "type": "Feature",
  "properties": {
    "addr:full":"1537 W 79th St Chicago IL 60620",
    "addr:housenumber":"1537",
    "addr:postcode":"60620",
    "addr:street":"W 79Th St",
    "iso:country":"US",
    "sg:address":"1537 W 79th St",
    "sg:city":"Chicago",
    "sg:classifiers":[
        {
            "category":"Shopping",
            "subcategory":"Clothing, Apparel, & Fashions",
            "type":"Retail Goods"
        }
    ],
    "sg:phone":"+1 773 729 4840",
    "sg:postcode":"60620",
    "sg:province":"IL",
    "sg:tags":[
        "apparel",
        "women's"
    ],
    "wof:name":"Wild N Sexy Fashions",
    "wof:placetype":"venue"
},
  "geometry": {"coordinates":[-87.66253399999999,41.750384],"type":"Point"}
}