{
  "type": "Feature",
  "properties": {
    "iso:country":"US",
    "sg:address":"1841 W Chicago Avenue",
    "sg:city":"Chicago",
    "sg:classifiers":[
        {
            "category":"Shopping",
            "subcategory":"Antiques",
            "type":"Retail Goods"
        }
    ],
    "sg:phone":"+1 312 226 8200",
    "sg:postcode":"60622",
    "sg:province":"IL",
    "wof:name":"Broken Art Porcelain Restoration",
    "wof:placetype":"venue"
},
  "geometry": {"coordinates":[-87.673681,41.89585],"type":"Point"}
}