{
  "type": "Feature",
  "properties": {
    "addr:full":"8725 W 95th St Hickory Hills IL 60457",
    "addr:housenumber":"8725",
    "addr:postcode":"60457",
    "addr:street":"W 95Th St",
    "iso:country":"US",
    "sg:address":"8725 W 95th St",
    "sg:city":"Hickory Hills",
    "sg:classifiers":[
        {
            "category":"Sports & Exercise",
            "subcategory":"Gym",
            "type":"Entertainment"
        }
    ],
    "sg:phone":"+1 708 599 5102",
    "sg:postcode":"60457",
    "sg:province":"IL",
    "sg:tags":[
        "trainer"
    ],
    "sg:website":"www.curves.com",
    "wof:name":"Curves",
    "wof:placetype":"venue"
},
  "geometry": {"coordinates":[-87.83398699999999,41.718078],"type":"Point"}
}