{
  "type": "Feature",
  "properties": {
    "iso:country":"US",
    "sg:address":"1429 S Main St",
    "sg:city":"Jacksonville",
    "sg:classifiers":[
        {
            "category":"Personal",
            "subcategory":"Tanning Parlor",
            "type":"Services"
        },
        {
            "category":"Personal",
            "type":"Services"
        }
    ],
    "sg:phone":"+1 217 243 3041",
    "sg:postcode":"62650",
    "sg:province":"IL",
    "sg:tags":[
        "salon"
    ],
    "wof:name":"Tanning Connection",
    "wof:placetype":"venue"
},
  "geometry": {"coordinates":[-90.22930100000001,39.715355],"type":"Point"}
}