{
  "type": "Feature",
  "properties": {
    "iso:country":"US",
    "sg:address":"19 W US Hwy 6",
    "sg:city":"Peru",
    "sg:classifiers":[
        {
            "category":"Wholesale",
            "subcategory":"Machinery & Supplies",
            "type":"Manufacturing & Wholesale Goods"
        },
        {
            "category":"Building & Trades",
            "subcategory":"Equipment Rental",
            "type":"Services"
        }
    ],
    "sg:phone":"+1 815 223 3522",
    "sg:postcode":"61354",
    "sg:province":"IL",
    "sg:tags":[
        "contractor"
    ],
    "wof:name":"Snook Equipment Rental Inc",
    "wof:placetype":"venue"
},
  "geometry": {"coordinates":[-89.106027,41.329444],"type":"Point"}
}