{
  "type": "Feature",
  "properties": {
    "addr:full":"2124 W 21st Pl # 1 Chicago IL 60608",
    "addr:housenumber":"2124",
    "addr:postcode":"60608",
    "addr:street":"W 21St Pl # 1",
    "iso:country":"US",
    "sg:address":"2124 W 21st Pl # 1",
    "sg:city":"Chicago",
    "sg:classifiers":[
        {
            "category":"Social Services",
            "type":"Services"
        },
        {
            "category":"Personal",
            "type":"Services"
        }
    ],
    "sg:phone":"+1 773 890 7676",
    "sg:postcode":"60608",
    "sg:province":"IL",
    "sg:tags":[
        "counseling"
    ],
    "wof:name":"Mujeres Latinas En Accion Inc",
    "wof:placetype":"venue"
},
  "geometry": {"coordinates":[-87.678899,41.853054],"type":"Point"}
}