{
  "type": "Feature",
  "properties": {
    "addr:full":"2045 E Algonquin Rd Algonquin IL 60102",
    "addr:housenumber":"2045",
    "addr:postcode":"60102",
    "addr:street":"E Algonquin Rd",
    "iso:country":"US",
    "sg:address":"2045 E Algonquin Rd",
    "sg:city":"Algonquin",
    "sg:classifiers":[
        {
            "category":"Banks & Credit Unions",
            "subcategory":"Bank",
            "type":"Services"
        }
    ],
    "sg:phone":"+1 847 854 4100",
    "sg:postcode":"60102",
    "sg:province":"IL",
    "sg:website":"www.midwestbank.com",
    "wof:name":"Midwest Bank and Trust Company",
    "wof:placetype":"venue"
},
  "geometry": {"coordinates":[-88.26619700000001,42.155998],"type":"Point"}
}