{
  "type": "Feature",
  "properties": {
    "iso:country":"US",
    "sg:address":"1584 S Busse Rd",
    "sg:city":"Mount Prospect",
    "sg:classifiers":[
        {
            "category":"Restaurant",
            "type":"Food & Drink"
        }
    ],
    "sg:phone":"+1   ",
    "sg:postcode":"60056",
    "sg:province":"IL",
    "sg:tags":[
        "japanese"
    ],
    "wof:name":"Torishin Japanese Restaurant",
    "wof:placetype":"venue"
},
  "geometry": {"coordinates":[-87.960743,42.037592],"type":"Point"}
}