{
  "type": "Feature",
  "properties": {
    "addr:full":"124 E Sangamon Ave Rantoul IL 61866",
    "addr:housenumber":"124",
    "addr:postcode":"61866",
    "addr:street":"E Sangamon Ave",
    "iso:country":"US",
    "sg:address":"124 E Sangamon Ave",
    "sg:city":"Rantoul",
    "sg:classifiers":[
        {
            "category":"Restaurant",
            "type":"Food & Drink"
        }
    ],
    "sg:phone":"+1 217 892 4100",
    "sg:postcode":"61866",
    "sg:province":"IL",
    "wof:name":"Kevin M Polito",
    "wof:placetype":"venue"
},
  "geometry": {"coordinates":[-88.158535,40.310592],"type":"Point"}
}