{
  "type": "Feature",
  "properties": {
    "iso:country":"US",
    "sg:address":"710 S 1st St",
    "sg:city":"Oregon",
    "sg:classifiers":[
        {
            "category":"Professional",
            "subcategory":"Accounting & Tax Preparation",
            "type":"Services"
        }
    ],
    "sg:phone":"+1 815 732 6732",
    "sg:postcode":"61061",
    "sg:province":"IL",
    "sg:tags":[
        "bookkeeping"
    ],
    "wof:name":"De'neau Bookkeeping",
    "wof:placetype":"venue"
},
  "geometry": {"coordinates":[-89.32894899999999,42.005779],"type":"Point"}
}