{
  "type": "Feature",
  "properties": {
    "iso:country":"US",
    "sg:address":"2984 W Wadsworth Rd",
    "sg:city":"Waukegan",
    "sg:classifiers":[
        {
            "category":"Manufacturing",
            "subcategory":"Motor Vehicles & Parts",
            "type":"Manufacturing & Wholesale Goods"
        }
    ],
    "sg:phone":"+1 847 336 2305",
    "sg:postcode":"60087",
    "sg:province":"IL",
    "sg:tags":[
        "car",
        "race",
        "mfg"
    ],
    "wof:name":"Chassis Service Unlimited",
    "wof:placetype":"venue"
},
  "geometry": {"coordinates":[-87.87392199999999,42.428479],"type":"Point"}
}