{
  "type": "Feature",
  "properties": {
    "addr:full":"3755 N. Southport Ave Chicago IL 60613",
    "addr:housenumber":"3755",
    "addr:postcode":"60613",
    "addr:street":"N. Southport Ave",
    "iso:country":"US",
    "sg:address":"3755 N. Southport Ave",
    "sg:city":"Chicago",
    "sg:classifiers":[
        {
            "category":"Restaurant",
            "type":"Food & Drink"
        }
    ],
    "sg:phone":"+1 773 935 2330",
    "sg:postcode":"60613",
    "sg:province":"IL",
    "sg:tags":[
        "mexican"
    ],
    "wof:name":"Frida's",
    "wof:placetype":"venue"
},
  "geometry": {"coordinates":[-87.66385200000001,41.950562],"type":"Point"}
}