{
  "type": "Feature",
  "properties": {
    "iso:country":"US",
    "sg:address":"120 N Main St Rm 212",
    "sg:city":"Hillsboro",
    "sg:classifiers":[
        {
            "category":"Government",
            "subcategory":"Court House",
            "type":"Public Place"
        }
    ],
    "sg:phone":"+1 217 532 9540",
    "sg:postcode":"62049",
    "sg:province":"IL",
    "sg:tags":[
        "justice"
    ],
    "wof:name":"Montgomery Cnty Curcuit Clerk",
    "wof:placetype":"venue"
},
  "geometry": {"coordinates":[-89.493382,39.161715],"type":"Point"}
}