{
  "type": "Feature",
  "properties": {
    "iso:country":"US",
    "sg:address":"204 N Main St",
    "sg:city":"Chana",
    "sg:classifiers":[
        {
            "category":"Education",
            "subcategory":"School",
            "type":"Public Place"
        }
    ],
    "sg:phone":"+1 815 732 4664",
    "sg:postcode":"61015",
    "sg:province":"IL",
    "wof:name":"Chana Education Ctr",
    "wof:placetype":"venue"
},
  "geometry": {"coordinates":[-89.221454,41.980988],"type":"Point"}
}