{
  "type": "Feature",
  "properties": {
    "iso:country":"US",
    "sg:address":"121 N Hudson St",
    "sg:city":"Vandalia",
    "sg:classifiers":[
        {
            "category":"Building & Trades",
            "subcategory":"Construction",
            "type":"Services"
        }
    ],
    "sg:phone":"+1 618 283 1252",
    "sg:postcode":"62471",
    "sg:province":"IL",
    "sg:tags":[
        "general",
        "contractor"
    ],
    "wof:name":"Vaughn's General Contracting",
    "wof:placetype":"venue"
},
  "geometry": {"coordinates":[-89.111428,38.962674],"type":"Point"}
}