{
  "type": "Feature",
  "properties": {
    "addr:full":"620 Buckthorn Ter Buffalo Grove IL 60089",
    "addr:housenumber":"620",
    "addr:postcode":"60089",
    "addr:street":"Buckthorn Ter",
    "iso:country":"US",
    "sg:address":"620 Buckthorn Ter",
    "sg:city":"Buffalo Grove",
    "sg:classifiers":[
        {
            "category":"Professional",
            "subcategory":"Computer Services",
            "type":"Services"
        }
    ],
    "sg:phone":"+1   ",
    "sg:postcode":"60089",
    "sg:province":"IL",
    "sg:tags":[
        "related"
    ],
    "wof:name":"Beatrice and Gofman Cons",
    "wof:placetype":"venue"
},
  "geometry": {"coordinates":[-87.94533300000001,42.157865],"type":"Point"}
}