{
  "type": "Feature",
  "properties": {
    "iso:country":"US",
    "sg:address":"1724 W Bradley Ave",
    "sg:city":"Champaign",
    "sg:classifiers":[
        {
            "category":"Banks & Credit Unions",
            "subcategory":"Bank",
            "type":"Services"
        }
    ],
    "sg:phone":"+1 217 359 2274",
    "sg:postcode":"61821",
    "sg:province":"IL",
    "sg:tags":[
        "institution",
        "business"
    ],
    "wof:name":"Heights Finance Corporation",
    "wof:placetype":"venue"
},
  "geometry": {"coordinates":[-88.275435,40.127479],"type":"Point"}
}