{
  "type": "Feature",
  "properties": {
    "addr:full":"4187 183rd St Country Club Hls IL 60478",
    "addr:housenumber":"4187",
    "addr:postcode":"60478",
    "addr:street":"183Rd St",
    "iso:country":"US",
    "sg:address":"4187 183rd St",
    "sg:city":"Country Club Hls",
    "sg:classifiers":[
        {
            "category":"Education",
            "subcategory":"School",
            "type":"Public Place"
        }
    ],
    "sg:phone":"+1 708 798 9542",
    "sg:postcode":"60478",
    "sg:province":"IL",
    "sg:website":"www.menta.com",
    "wof:name":"Country Club Hills Tech-Trade",
    "wof:placetype":"venue"
},
  "geometry": {"coordinates":[-87.718159,41.557048],"type":"Point"}
}