{
  "type": "Feature",
  "properties": {
    "iso:country":"US",
    "sg:address":"3030 N Tripp Ave",
    "sg:city":"Chicago",
    "sg:classifiers":[
        {
            "category":"Wholesale",
            "subcategory":"Scrap",
            "type":"Manufacturing & Wholesale Goods"
        }
    ],
    "sg:phone":"+1 773 539 5500",
    "sg:postcode":"60641",
    "sg:province":"IL",
    "sg:tags":[
        "metal",
        "nonferrous"
    ],
    "wof:name":"Midwest Industrial Metals Corp",
    "wof:placetype":"venue"
},
  "geometry": {"coordinates":[-87.73294,41.93674],"type":"Point"}
}