{
  "type": "Feature",
  "properties": {
    "iso:country":"US",
    "sg:address":"1022 E Liberty Dr",
    "sg:city":"Wheaton",
    "sg:classifiers":[
        {
            "category":"Building & Trades",
            "subcategory":"Construction",
            "type":"Services"
        }
    ],
    "sg:phone":"+1 630 653 7748",
    "sg:postcode":"60187",
    "sg:province":"IL",
    "sg:tags":[
        "carpentry",
        "contractor"
    ],
    "wof:name":"Kramer Carpentry",
    "wof:placetype":"venue"
},
  "geometry": {"coordinates":[-88.090565,41.864472],"type":"Point"}
}