{
  "type": "Feature",
  "properties": {
    "addr:full":"126 S State St Belvidere IL 61008",
    "addr:housenumber":"126",
    "addr:postcode":"61008",
    "addr:street":"S State St",
    "iso:country":"US",
    "sg:address":"126 S State St",
    "sg:city":"Belvidere",
    "sg:classifiers":[
        {
            "category":"Shopping",
            "subcategory":"Music",
            "type":"Retail Goods"
        }
    ],
    "sg:phone":"+1   ",
    "sg:postcode":"61008",
    "sg:province":"IL",
    "wof:name":"Video Goldmine",
    "wof:placetype":"venue"
},
  "geometry": {"coordinates":[-88.842251,42.258549],"type":"Point"}
}