{
  "type": "Feature",
  "properties": {
    "addr:full":"5864 N Northwest Hwy Chicago IL 60631",
    "addr:housenumber":"5864",
    "addr:postcode":"60631",
    "addr:street":"N Northwest Hwy",
    "iso:country":"US",
    "sg:address":"5864 N Northwest Hwy",
    "sg:city":"Chicago",
    "sg:classifiers":[
        {
            "category":"Manufacturing",
            "subcategory":"Tools & Machinery",
            "type":"Manufacturing & Wholesale Goods"
        }
    ],
    "sg:phone":"+1 773 334 5000",
    "sg:postcode":"60631",
    "sg:province":"IL",
    "sg:tags":[
        "machine"
    ],
    "sg:website":"http://www.americanmachinetools.com/",
    "wof:name":"American Machine Tools Inc",
    "wof:placetype":"venue"
},
  "geometry": {"coordinates":[-87.791405,41.988017],"type":"Point"}
}