{
  "type": "Feature",
  "properties": {
    "addr:full":"1901 W George St Chicago IL 60657",
    "addr:housenumber":"1901",
    "addr:postcode":"60657",
    "addr:street":"W George St",
    "iso:country":"US",
    "sg:address":"1901 W George St",
    "sg:city":"Chicago",
    "sg:classifiers":[
        {
            "category":"Bars & Pubs",
            "type":"Food & Drink"
        }
    ],
    "sg:phone":"+1 773 929 2391",
    "sg:postcode":"60657",
    "sg:province":"IL",
    "wof:name":"H & P Lounge LTD",
    "wof:placetype":"venue"
},
  "geometry": {"coordinates":[-87.677571,41.934115],"type":"Point"}
}