{
  "type": "Feature",
  "properties": {
    "addr:full":"16335 Harlem Ave Tinley Park IL 60477",
    "addr:housenumber":"16335",
    "addr:postcode":"60477",
    "addr:street":"Harlem Ave",
    "iso:country":"US",
    "sg:address":"16335 Harlem Ave",
    "sg:city":"Tinley Park",
    "sg:classifiers":[
        {
            "category":"Banks & Credit Unions",
            "subcategory":"Bank",
            "type":"Services"
        }
    ],
    "sg:phone":"+1 708 633 6319",
    "sg:postcode":"60477",
    "sg:province":"IL",
    "sg:tags":[
        "loan",
        "real estate"
    ],
    "wof:name":"American Mortgage",
    "wof:placetype":"venue"
},
  "geometry": {"coordinates":[-87.79373,41.592329],"type":"Point"}
}