{
  "type": "Feature",
  "properties": {
    "addr:full":"1182 Northbrook Ct Northbrook IL 60062",
    "addr:housenumber":"1182",
    "addr:postcode":"60062",
    "addr:street":"Northbrook Ct",
    "iso:country":"US",
    "sg:address":"1182 Northbrook Ct",
    "sg:city":"Northbrook",
    "sg:classifiers":[
        {
            "category":"Health Services",
            "subcategory":"Doctor",
            "type":"Services"
        },
        {
            "category":"Community Center",
            "type":"Public Place"
        },
        {
            "category":"Health Services",
            "subcategory":"Dentist",
            "type":"Services"
        }
    ],
    "sg:phone":"+1 847 509 1818",
    "sg:postcode":"60062",
    "sg:province":"IL",
    "sg:tags":[
        "laboratories-medical",
        "radiology",
        "physician",
        "dental",
        "surgeons",
        "mri",
        "resonance",
        "magnetic",
        "x-ray",
        "imaging"
    ],
    "sg:website":"http://www.medimageofnbc.com",
    "wof:name":"Medical Imaging Of Northbrook Court LLC",
    "wof:placetype":"venue"
},
  "geometry": {"coordinates":[-87.81712400000001,42.151871],"type":"Point"}
}