{
  "type": "Feature",
  "properties": {
    "iso:country":"US",
    "sg:address":"3965 Old Freeburg Rd",
    "sg:city":"Freeburg",
    "sg:classifiers":[
        {
            "category":"Retail",
            "subcategory":"Auto Repair",
            "type":"Services"
        }
    ],
    "sg:phone":"+1 618 539 5042",
    "sg:postcode":"62243",
    "sg:province":"IL",
    "sg:tags":[
        "truck"
    ],
    "wof:name":"Parco Maintenance Co",
    "wof:placetype":"venue"
},
  "geometry": {"coordinates":[-89.921694,38.444772],"type":"Point"}
}