{
  "type": "Feature",
  "properties": {
    "addr:full":"2317 N Clark St Chicago IL 60614",
    "addr:housenumber":"2317",
    "addr:postcode":"60614",
    "addr:street":"N Clark St",
    "iso:country":"US",
    "sg:address":"2317 N Clark St",
    "sg:city":"Chicago",
    "sg:classifiers":[
        {
            "category":"Shopping",
            "subcategory":"Pharmacy",
            "type":"Retail Goods"
        }
    ],
    "sg:phone":"+1 773 929 7488",
    "sg:postcode":"60614",
    "sg:province":"IL",
    "sg:tags":[
        "drugstore"
    ],
    "sg:website":"www.walgreens.com",
    "wof:name":"Walgreens",
    "wof:placetype":"venue"
},
  "geometry": {"coordinates":[-87.639264,41.924352],"type":"Point"}
}