{
  "type": "Feature",
  "properties": {
    "addr:full":"6243 State Rte 40 Buda IL 61314",
    "addr:housenumber":"6243",
    "addr:postcode":"61314",
    "addr:street":"State Rte 40",
    "iso:country":"US",
    "sg:address":"6243 State Rte 40",
    "sg:city":"Buda",
    "sg:classifiers":[
        {
            "category":"Farming",
            "subcategory":"Farm",
            "type":"Manufacturing & Wholesale Goods"
        }
    ],
    "sg:phone":"+1 309 897 8106",
    "sg:postcode":"61314",
    "sg:province":"IL",
    "sg:tags":[
        "industrial",
        "merchandise",
        "build",
        "crop",
        "general"
    ],
    "wof:name":"Endress Equipt Co",
    "wof:placetype":"venue"
},
  "geometry": {"coordinates":[-89.683587,41.244904],"type":"Point"}
}