{
  "type": "Feature",
  "properties": {
    "iso:country":"US",
    "sg:address":"107 Melanie Ln",
    "sg:city":"Collinsville",
    "sg:classifiers":[
        {
            "category":"Professional",
            "type":"Services"
        }
    ],
    "sg:phone":"+1 618 344 0816",
    "sg:postcode":"62234",
    "sg:province":"IL",
    "wof:name":"Bali Co The",
    "wof:placetype":"venue"
},
  "geometry": {"coordinates":[-89.932233,38.707468],"type":"Point"}
}