{
  "type": "Feature",
  "properties": {
    "iso:country":"US",
    "sg:address":"2156 W Montrose Ave",
    "sg:city":"Chicago",
    "sg:classifiers":[
        {
            "category":"Real Estate",
            "subcategory":"Real Estate Agent",
            "type":"Services"
        }
    ],
    "sg:phone":"+1 773 502 1673",
    "sg:postcode":"60625",
    "sg:province":"IL",
    "sg:website":"www.movewithmaggie.com",
    "wof:name":"Maggie Finegan - Keller Williams Lincoln Square",
    "wof:placetype":"venue"
},
  "geometry": {"coordinates":[-87.683677,41.96167],"type":"Point"}
}