{
  "type": "Feature",
  "properties": {
    "iso:country":"US",
    "sg:address":"1845 E Rand Rd",
    "sg:city":"Arlington Hts",
    "sg:classifiers":[
        {
            "category":"Banks & Credit Unions",
            "subcategory":"Bank",
            "type":"Services"
        }
    ],
    "sg:phone":"+1 847 590 1990",
    "sg:postcode":"60004",
    "sg:province":"IL",
    "sg:tags":[
        "financing"
    ],
    "wof:name":"First America Financial Corp",
    "wof:placetype":"venue"
},
  "geometry": {"coordinates":[-87.957391,42.097175],"type":"Point"}
}