{
  "type": "Feature",
  "properties": {
    "iso:country":"US",
    "sg:address":"17 N Ayer St",
    "sg:city":"Harvard",
    "sg:classifiers":[
        {
            "category":"Restaurant",
            "type":"Food & Drink"
        }
    ],
    "sg:phone":"+1 815 943 6606",
    "sg:postcode":"60033",
    "sg:province":"IL",
    "sg:tags":[
        "style",
        "family"
    ],
    "wof:name":"Town & Country Restaurant",
    "wof:placetype":"venue"
},
  "geometry": {"coordinates":[-88.615949,42.419854],"type":"Point"}
}