{
  "type": "Feature",
  "properties": {
    "iso:country":"US",
    "sg:address":"3923 Vogel School Rd",
    "sg:city":"Waterloo",
    "sg:classifiers":[
        {
            "category":"Manufacturing",
            "subcategory":"Food",
            "type":"Manufacturing & Wholesale Goods"
        },
        {
            "category":"Farming",
            "subcategory":"Farm",
            "type":"Manufacturing & Wholesale Goods"
        }
    ],
    "sg:phone":"+1 618 473 2659",
    "sg:postcode":"62298",
    "sg:province":"IL",
    "sg:tags":[
        "corn",
        "product"
    ],
    "wof:name":"James Probst",
    "wof:placetype":"venue"
},
  "geometry": {"coordinates":[-90.07261699999999,38.387539],"type":"Point"}
}