{
  "type": "Feature",
  "properties": {
    "iso:country":"US",
    "sg:address":"1813 16th Ave",
    "sg:city":"Viola",
    "sg:classifiers":[
        {
            "category":"Government",
            "subcategory":"Police Station",
            "type":"Public Place"
        }
    ],
    "sg:phone":"+1 309 000 1111",
    "sg:postcode":"61486",
    "sg:province":"IL",
    "sg:tags":[
        "department"
    ],
    "wof:name":"Viola Police Dept",
    "wof:placetype":"venue"
},
  "geometry": {"coordinates":[-90.58026,41.20363],"type":"Point"}
}