{
  "type": "Feature",
  "properties": {
    "addr:full":"2110 W Greenleaf Ave Chicago IL 60645",
    "addr:housenumber":"2110",
    "addr:postcode":"60645",
    "addr:street":"W Greenleaf Ave",
    "iso:country":"US",
    "sg:address":"2110 W Greenleaf Ave",
    "sg:city":"Chicago",
    "sg:classifiers":[
        {
            "category":"Education",
            "subcategory":"School",
            "type":"Public Place"
        }
    ],
    "sg:phone":"+1 773 534 2150",
    "sg:postcode":"60645",
    "sg:province":"IL",
    "sg:website":"www.armstrongschool.org",
    "wof:name":"George Armstrong Elem School",
    "wof:placetype":"venue"
},
  "geometry": {"coordinates":[-87.68349499999999,42.010186],"type":"Point"}
}