{
  "type": "Feature",
  "properties": {
    "addr:full":"216 W 2nd St Kewanee IL 61443",
    "addr:housenumber":"216",
    "addr:postcode":"61443",
    "addr:street":"W 2Nd St",
    "iso:country":"US",
    "sg:address":"216 W 2nd St",
    "sg:city":"Kewanee",
    "sg:classifiers":[
        {
            "category":"Personal",
            "subcategory":"Beauty Salon",
            "type":"Services"
        }
    ],
    "sg:phone":"+1 309 852 5208",
    "sg:postcode":"61443",
    "sg:province":"IL",
    "sg:tags":[
        "treatment",
        "skin"
    ],
    "wof:name":"Body Logics",
    "wof:placetype":"venue"
},
  "geometry": {"coordinates":[-89.92763100000001,41.244595],"type":"Point"}
}