{
  "type": "Feature",
  "properties": {
    "iso:country":"US",
    "sg:address":"1555 Sherman Ave",
    "sg:city":"Evanston",
    "sg:classifiers":[
        {
            "category":"Professional",
            "subcategory":"Management & Consulting",
            "type":"Services"
        }
    ],
    "sg:phone":"+1 847 491 6700",
    "sg:postcode":"60201",
    "sg:province":"IL",
    "sg:tags":[
        "business"
    ],
    "wof:name":"Strothman & Assocs",
    "wof:placetype":"venue"
},
  "geometry": {"coordinates":[-87.68181,42.045629],"type":"Point"}
}