{
  "type": "Feature",
  "properties": {
    "addr:full":"417 S Western Ave Rear Peoria IL 61605",
    "addr:housenumber":"417",
    "addr:postcode":"61605",
    "addr:street":"S Western Ave",
    "iso:country":"US",
    "sg:address":"417 S Western Ave Rear",
    "sg:city":"Peoria",
    "sg:classifiers":[
        {
            "category":"Personal",
            "type":"Services"
        },
        {
            "category":"Professional",
            "subcategory":"Business Services",
            "type":"Services"
        }
    ],
    "sg:phone":"+1 309 686 0558",
    "sg:postcode":"61605",
    "sg:province":"IL",
    "sg:tags":[
        "estates-sales",
        "liquidation",
        "appraisal",
        "auctioneer"
    ],
    "sg:website":"http://cottenauctions.com",
    "wof:name":"Cotten Commercial Auctioneers Inc",
    "wof:placetype":"venue"
},
  "geometry": {"coordinates":[-89.622969,40.684267],"type":"Point"}
}