{
  "type": "Feature",
  "properties": {
    "addr:full":"107 W Van Buren Ste 201 Chicago IL 60605",
    "addr:housenumber":"107;ste 201",
    "addr:postcode":"60605",
    "addr:street":"W Van",
    "iso:country":"US",
    "sg:address":"107 W Van Buren Ste 201",
    "sg:city":"Chicago",
    "sg:classifiers":[
        {
            "category":"Professional",
            "subcategory":"Advertising",
            "type":"Services"
        },
        {
            "category":"Communications",
            "subcategory":"Newspaper",
            "type":"Services"
        }
    ],
    "sg:phone":"+1 773 722 2339",
    "sg:postcode":"60605",
    "sg:province":"IL",
    "sg:tags":[
        "marketing"
    ],
    "sg:website":"www.hilltopstudios.net",
    "wof:name":"Hilltop Studio",
    "wof:placetype":"venue"
},
  "geometry": {"coordinates":[-87.631078,41.87686],"type":"Point"}
}