{
  "type": "Feature",
  "properties": {
    "iso:country":"US",
    "sg:address":"1111 N Vermilion St",
    "sg:city":"Danville",
    "sg:classifiers":[
        {
            "category":"Organizations",
            "subcategory":"Community Association",
            "type":"Services"
        }
    ],
    "sg:phone":"+1 217 442 0563",
    "sg:postcode":"61832",
    "sg:province":"IL",
    "sg:website":"www.danvilleymca.org",
    "wof:name":"YMCA",
    "wof:placetype":"venue"
},
  "geometry": {"coordinates":[-87.63019,40.14215],"type":"Point"}
}