{
  "type": "Feature",
  "properties": {
    "addr:full":"9120 Delphia Ave Des Plaines IL 60016",
    "addr:postcode":"9120;60016",
    "addr:street":"Delphia Ave",
    "iso:country":"US",
    "sg:address":"9120 Delphia Ave",
    "sg:city":"Des Plaines",
    "sg:classifiers":[
        {
            "category":"Building & Trades",
            "subcategory":"Construction",
            "type":"Services"
        }
    ],
    "sg:phone":"+1 847 299 5348",
    "sg:postcode":"60016",
    "sg:province":"IL",
    "sg:tags":[
        "contractor"
    ],
    "wof:name":"Safeway Tuckpointing",
    "wof:placetype":"venue"
},
  "geometry": {"coordinates":[-87.84161400000001,42.046883],"type":"Point"}
}