{
  "type": "Feature",
  "properties": {
    "iso:country":"US",
    "sg:address":"419 W Superior St",
    "sg:city":"Chicago",
    "sg:classifiers":[
        {
            "category":"Restaurant",
            "type":"Food & Drink"
        }
    ],
    "sg:phone":"+1 312 475 9112",
    "sg:postcode":"60610",
    "sg:province":"IL",
    "sg:tags":[
        "new",
        "american"
    ],
    "sg:website":"www.zealousrestaurant.com/home/i...",
    "wof:name":"Zealous Restaurant",
    "wof:placetype":"venue"
},
  "geometry": {"coordinates":[-87.639313,41.895297],"type":"Point"}
}