{
  "type": "Feature",
  "properties": {
    "iso:country":"US",
    "sg:address":"701 Ridge Rd",
    "sg:city":"Homewood",
    "sg:classifiers":[
        {
            "category":"Retail",
            "subcategory":"Funeral Services",
            "type":"Services"
        }
    ],
    "sg:phone":"+1 708 798 0645",
    "sg:postcode":"60430",
    "sg:province":"IL",
    "sg:tags":[
        "cemetery"
    ],
    "sg:website":"http://www.washingtoncemetery.com",
    "wof:name":"Washington Memory Gardens Inc",
    "wof:placetype":"venue"
},
  "geometry": {"coordinates":[-87.633163,41.564041],"type":"Point"}
}