{
  "type": "Feature",
  "properties": {
    "iso:country":"US",
    "sg:address":"10603 Lincoln Trl",
    "sg:city":"Fairview Heights",
    "sg:classifiers":[
        {
            "category":"Wholesale",
            "subcategory":"Painting Supplies",
            "type":"Manufacturing & Wholesale Goods"
        }
    ],
    "sg:phone":"+1 618 397 4100",
    "sg:postcode":"62208",
    "sg:province":"IL",
    "wof:name":"M A B Paint 840",
    "wof:placetype":"venue"
},
  "geometry": {"coordinates":[-89.99427799999999,38.59296],"type":"Point"}
}