{
  "type": "Feature",
  "properties": {
    "addr:full":"2626 N Clark St Chicago IL 60614",
    "addr:housenumber":"2626",
    "addr:postcode":"60614",
    "addr:street":"N Clark St",
    "iso:country":"US",
    "sg:address":"2626 N Clark St",
    "sg:city":"Chicago",
    "sg:classifiers":[
        {
            "category":"Banks & Credit Unions",
            "subcategory":"Financial Services",
            "type":"Services"
        },
        {
            "category":"Shopping",
            "subcategory":"Jewelry",
            "type":"Retail Goods"
        },
        {
            "category":"Manufacturing",
            "subcategory":"Jewelry",
            "type":"Manufacturing & Wholesale Goods"
        },
        {
            "category":"Shopping",
            "subcategory":"Pawn Shop",
            "type":"Retail Goods"
        }
    ],
    "sg:phone":"+1 773 528 7900",
    "sg:postcode":"60614",
    "sg:province":"IL",
    "sg:tags":[
        "platinum",
        "gold",
        "loan",
        "jeweler",
        "pawnbroker",
        "buyer",
        "silver"
    ],
    "sg:website":"www.clarkpawners.com",
    "wof:name":"Clark Pawners & Jewelers",
    "wof:placetype":"venue"
},
  "geometry": {"coordinates":[-87.643984,41.930221],"type":"Point"}
}