{
  "type": "Feature",
  "properties": {
    "iso:country":"US",
    "sg:address":"2515 Driftwood Ln",
    "sg:city":"Rockford",
    "sg:classifiers":[
        {
            "category":"Insurance",
            "subcategory":"Insurance Agent",
            "type":"Services"
        }
    ],
    "sg:phone":"+1 815 636 1135",
    "sg:postcode":"61107",
    "sg:province":"IL",
    "wof:name":"Horace Mann",
    "wof:placetype":"venue"
},
  "geometry": {"coordinates":[-89.03945899999999,42.295077],"type":"Point"}
}