{
  "type": "Feature",
  "properties": {
    "addr:full":"5304 N Milwaukee Ave Chicago IL 60630",
    "addr:housenumber":"5304",
    "addr:postcode":"60630",
    "addr:street":"N Milwaukee Ave",
    "iso:country":"US",
    "sg:address":"5304 N Milwaukee Ave",
    "sg:city":"Chicago",
    "sg:classifiers":[
        {
            "category":"Home & Garden",
            "subcategory":"Building Materials",
            "type":"Retail Goods"
        }
    ],
    "sg:phone":"+1 773 774 3131",
    "sg:postcode":"60630",
    "sg:province":"IL",
    "sg:tags":[
        "supply"
    ],
    "wof:name":"American Thermal Window Products Inc",
    "wof:placetype":"venue"
},
  "geometry": {"coordinates":[-87.76860000000001,41.976799],"type":"Point"}
}