{
  "type": "Feature",
  "properties": {
    "addr:full":"91 Plaza Dr Beardstown IL 62618",
    "addr:housenumber":"91",
    "addr:postcode":"62618",
    "addr:street":"Plaza Dr",
    "iso:country":"US",
    "sg:address":"91 Plaza Dr",
    "sg:city":"Beardstown",
    "sg:classifiers":[
        {
            "category":"Restaurant",
            "type":"Food & Drink"
        }
    ],
    "sg:menulink":"http://www.allmenus.com/il/beardstown/127658-subway/menu/",
    "sg:phone":"+1 217 323 5551",
    "sg:postcode":"62618",
    "sg:province":"IL",
    "sg:tags":[
        "american",
        "sandwich"
    ],
    "wof:name":"Subway",
    "wof:placetype":"venue"
},
  "geometry": {"coordinates":[-90.437667,40.002704],"type":"Point"}
}