{
  "type": "Feature",
  "properties": {
    "addr:full":"720 Industrial Dr Cary IL 60013",
    "addr:housenumber":"720",
    "addr:postcode":"60013",
    "addr:street":"Industrial Dr",
    "iso:country":"US",
    "sg:address":"720 Industrial Dr",
    "sg:city":"Cary",
    "sg:classifiers":[
        {
            "category":"Manufacturing",
            "subcategory":"Tools & Machinery",
            "type":"Manufacturing & Wholesale Goods"
        }
    ],
    "sg:phone":"+1 847 462 8485",
    "sg:postcode":"60013",
    "sg:province":"IL",
    "wof:name":"Cigar Club",
    "wof:placetype":"venue"
},
  "geometry": {"coordinates":[-88.255591,42.214829],"type":"Point"}
}