{
  "type": "Feature",
  "properties": {
    "iso:country":"US",
    "sg:address":"2138 S 61st Ct",
    "sg:city":"Cicero",
    "sg:classifiers":[
        {
            "category":"Professional",
            "subcategory":"Employment Agencies",
            "type":"Services"
        }
    ],
    "sg:phone":"+1 708 222 3100",
    "sg:postcode":"60804",
    "sg:province":"IL",
    "wof:name":"Illinois Employment Training Center",
    "wof:placetype":"venue"
},
  "geometry": {"coordinates":[-87.777298,41.851299],"type":"Point"}
}