{
  "type": "Feature",
  "properties": {
    "addr:full":"1440 N Lake Shore Dr Chicago IL 60610",
    "addr:housenumber":"1440",
    "addr:postcode":"60610",
    "addr:street":"N Lake Shore Dr",
    "iso:country":"US",
    "sg:address":"1440 N Lake Shore Dr",
    "sg:city":"Chicago",
    "sg:classifiers":[
        {
            "category":"Real Estate",
            "subcategory":"Real Estate Operator",
            "type":"Services"
        }
    ],
    "sg:phone":"+1 312 664 2428",
    "sg:postcode":"60610",
    "sg:province":"IL",
    "sg:tags":[
        "apartment"
    ],
    "wof:name":"1440 Lake Shore Dr Bldg",
    "wof:placetype":"venue"
},
  "geometry": {"coordinates":[-87.62599899999999,41.908501],"type":"Point"}
}