{
  "type": "Feature",
  "properties": {
    "addr:full":"1915 University Press Dr Carbondale IL 62901",
    "addr:housenumber":"1915",
    "addr:postcode":"62901",
    "addr:street":"University Press Dr",
    "iso:country":"US",
    "sg:address":"1915 University Press Dr",
    "sg:city":"Carbondale",
    "sg:classifiers":[
        {
            "category":"Education",
            "subcategory":"University",
            "type":"Public Place"
        }
    ],
    "sg:phone":"+1 618 453 2281",
    "sg:postcode":"62901",
    "sg:province":"IL",
    "sg:tags":[
        "college"
    ],
    "sg:website":"www.siuc.edu",
    "wof:name":"Southern Illinois University Carbondale",
    "wof:placetype":"venue"
},
  "geometry": {"coordinates":[-89.239216,37.709986],"type":"Point"}
}