{
  "type": "Feature",
  "properties": {
    "addr:full":"3050 N Greenview Ave Chicago IL 60657",
    "addr:housenumber":"3050",
    "addr:postcode":"60657",
    "addr:street":"N Greenview Ave",
    "iso:country":"US",
    "sg:address":"3050 N Greenview Ave",
    "sg:city":"Chicago",
    "sg:classifiers":[
        {
            "category":"Personal",
            "subcategory":"Beauty Salon",
            "type":"Services"
        }
    ],
    "sg:phone":"+1 773 929 7060",
    "sg:postcode":"60657",
    "sg:province":"IL",
    "wof:name":"Iris Beauty Salon",
    "wof:placetype":"venue"
},
  "geometry": {"coordinates":[-87.666246,41.937751],"type":"Point"}
}