{
  "type": "Feature",
  "properties": {
    "iso:country":"US",
    "sg:address":"1 Williams Ln",
    "sg:city":"Ava",
    "sg:classifiers":[
        {
            "category":"Building & Trades",
            "subcategory":"Plumbing",
            "type":"Services"
        }
    ],
    "sg:phone":"+1 618 457 7422",
    "sg:postcode":"62907",
    "sg:province":"IL",
    "sg:tags":[
        "plumbing",
        "contractor"
    ],
    "wof:name":"Charles T Williams Plumbing",
    "wof:placetype":"venue"
},
  "geometry": {"coordinates":[-89.429794,37.862744],"type":"Point"}
}