{
  "type": "Feature",
  "properties": {
    "iso:country":"US",
    "sg:address":"335 Quadrangle Dr",
    "sg:city":"Bolingbrook",
    "sg:classifiers":[
        {
            "category":"Insurance",
            "subcategory":"Insurance Agent",
            "type":"Services"
        }
    ],
    "sg:phone":"+1 630 759 8582",
    "sg:postcode":"60440",
    "sg:province":"IL",
    "wof:name":"RCR Assocciates Insurance",
    "wof:placetype":"venue"
},
  "geometry": {"coordinates":[-88.075482,41.689271],"type":"Point"}
}