{
  "type": "Feature",
  "properties": {
    "iso:country":"US",
    "sg:address":"916 Viaduct Rd",
    "sg:city":"Savanna",
    "sg:classifiers":[
        {
            "category":"Organizations",
            "subcategory":"Religious Organization",
            "type":"Services"
        }
    ],
    "sg:phone":"+1 815 273 2893",
    "sg:postcode":"61074",
    "sg:province":"IL",
    "sg:tags":[
        "church"
    ],
    "wof:name":"Calvary Baptist Church",
    "wof:placetype":"venue"
},
  "geometry": {"coordinates":[-90.126339,42.07848],"type":"Point"}
}