{
  "type": "Feature",
  "properties": {
    "iso:country":"US",
    "sg:address":"618 Clinton St",
    "sg:city":"Ottawa",
    "sg:classifiers":[
        {
            "category":"Restaurant",
            "type":"Food & Drink"
        }
    ],
    "sg:phone":"+1 815 434 6890",
    "sg:postcode":"61350",
    "sg:province":"IL",
    "sg:tags":[
        "eating",
        "pizza"
    ],
    "wof:name":"Bianchi's Pizza",
    "wof:placetype":"venue"
},
  "geometry": {"coordinates":[-88.844045,41.346631],"type":"Point"}
}