{
  "type": "Feature",
  "properties": {
    "iso:country":"US",
    "sg:address":"7 Dogwood Rd",
    "sg:city":"Rolling Meadows",
    "sg:classifiers":[
        {
            "category":"Utilities",
            "subcategory":"Telephone",
            "type":"Services"
        }
    ],
    "sg:phone":"+1 847 303 9300",
    "sg:postcode":"60008",
    "sg:province":"IL",
    "sg:tags":[
        "communications"
    ],
    "wof:name":"Bishop Partners Inc",
    "wof:placetype":"venue"
},
  "geometry": {"coordinates":[-88.034984,42.075697],"type":"Point"}
}