{
  "type": "Feature",
  "properties": {
    "addr:full":"2641 Northtown Way Highland IL 62249",
    "addr:housenumber":"2641",
    "addr:postcode":"62249",
    "addr:street":"Northtown Way",
    "iso:country":"US",
    "sg:address":"2641 Northtown Way",
    "sg:city":"Highland",
    "sg:classifiers":[
        {
            "category":"Home & Garden",
            "subcategory":"Home Furnishings",
            "type":"Retail Goods"
        },
        {
            "category":"Shopping",
            "subcategory":"Crafts & Fabrics",
            "type":"Retail Goods"
        }
    ],
    "sg:phone":"+1 618 654 3583",
    "sg:postcode":"62249",
    "sg:province":"IL",
    "sg:tags":[
        "curtain",
        "made",
        "drapery",
        "sewing"
    ],
    "wof:name":"Artist's Touch",
    "wof:placetype":"venue"
},
  "geometry": {"coordinates":[-89.68230200000001,38.752262],"type":"Point"}
}