{
  "type": "Feature",
  "properties": {
    "addr:full":"10458 S Ewing Ave Chicago IL 60617",
    "addr:housenumber":"10458",
    "addr:postcode":"60617",
    "addr:street":"S Ewing Ave",
    "iso:country":"US",
    "sg:address":"10458 S Ewing Ave",
    "sg:city":"Chicago",
    "sg:classifiers":[
        {
            "category":"Autos & Motor Vehicles",
            "subcategory":"Auto Supplies",
            "type":"Retail Goods"
        }
    ],
    "sg:phone":"+1 773 221 5100",
    "sg:postcode":"60617",
    "sg:province":"IL",
    "sg:tags":[
        "automobile",
        "parts",
        "accessory",
        "part",
        "accessories-wholesale",
        "manufacturer"
    ],
    "wof:name":"Skyway Auto Parts",
    "wof:placetype":"venue"
},
  "geometry": {"coordinates":[-87.535263,41.705353],"type":"Point"}
}