{
  "type": "Feature",
  "properties": {
    "iso:country":"US",
    "sg:address":"34740 N US Hwy 45",
    "sg:city":"Lake Villa",
    "sg:classifiers":[
        {
            "category":"Health Services",
            "subcategory":"Doctor",
            "type":"Services"
        }
    ],
    "sg:phone":"+1 847 986 3644",
    "sg:postcode":"60046",
    "sg:province":"IL",
    "sg:tags":[
        "medicine",
        "injury",
        "sport"
    ],
    "wof:name":"Canine Sports Medicine Ctr",
    "wof:placetype":"venue"
},
  "geometry": {"coordinates":[-87.997963,42.366978],"type":"Point"}
}