{
  "type": "Feature",
  "properties": {
    "iso:country":"US",
    "sg:address":"2 River Pl Ste I",
    "sg:city":"Lansing",
    "sg:classifiers":[
        {
            "category":"Banks & Credit Unions",
            "subcategory":"Financial Services",
            "type":"Services"
        }
    ],
    "sg:phone":"+1 708 895 8252",
    "sg:postcode":"60438",
    "sg:province":"IL",
    "sg:tags":[
        "broker",
        "mortgage"
    ],
    "wof:name":"Beneficial Illinois Inc",
    "wof:placetype":"venue"
},
  "geometry": {"coordinates":[-87.560997,41.586399],"type":"Point"}
}