{
  "type": "Feature",
  "properties": {
    "addr:full":"26 Wedgewood Rd Matteson IL 60443",
    "addr:housenumber":"26",
    "addr:postcode":"60443",
    "addr:street":"Wedgewood Rd",
    "iso:country":"US",
    "sg:address":"26 Wedgewood Rd",
    "sg:city":"Matteson",
    "sg:classifiers":[
        {
            "category":"Professional",
            "subcategory":"Employment Agencies",
            "type":"Services"
        }
    ],
    "sg:phone":"+1 708 720 3158",
    "sg:postcode":"60443",
    "sg:province":"IL",
    "wof:name":"T & T Nursing Agency Inc",
    "wof:placetype":"venue"
},
  "geometry": {"coordinates":[-87.76495199999999,41.5271],"type":"Point"}
}