{
  "type": "Feature",
  "properties": {
    "iso:country":"US",
    "sg:address":"105 S Vermilion St",
    "sg:city":"Potomac",
    "sg:classifiers":[
        {
            "category":"Banks & Credit Unions",
            "subcategory":"Bank",
            "type":"Services"
        }
    ],
    "sg:phone":"+1 217 987 6107",
    "sg:postcode":"61865",
    "sg:province":"IL",
    "wof:name":"United Community Bank",
    "wof:placetype":"venue"
},
  "geometry": {"coordinates":[-87.800555,40.30525],"type":"Point"}
}