{
  "type": "Feature",
  "properties": {
    "addr:full":"909 N Logan Ave Danville IL 61832",
    "addr:housenumber":"909",
    "addr:postcode":"61832",
    "addr:street":"N Logan Ave",
    "iso:country":"US",
    "sg:address":"909 N Logan Ave",
    "sg:city":"Danville",
    "sg:classifiers":[
        {
            "category":"Health Services",
            "subcategory":"Doctor",
            "type":"Services"
        }
    ],
    "sg:phone":"+1 217 431 8133",
    "sg:postcode":"61832",
    "sg:province":"IL",
    "sg:tags":[
        "medical"
    ],
    "wof:name":"Yeonsuk Koo MD",
    "wof:placetype":"venue"
},
  "geometry": {"coordinates":[-87.644835,40.138664],"type":"Point"}
}