{
  "type": "Feature",
  "properties": {
    "addr:full":"890 Longwood Dr Lake Forest IL 60045",
    "addr:housenumber":"890",
    "addr:postcode":"60045",
    "addr:street":"Longwood Dr",
    "iso:country":"US",
    "sg:address":"890 Longwood Dr",
    "sg:city":"Lake Forest",
    "sg:classifiers":[
        {
            "category":"Professional",
            "type":"Services"
        }
    ],
    "sg:phone":"+1 847 735 8895",
    "sg:postcode":"60045",
    "sg:province":"IL",
    "sg:tags":[
        "development",
        "technology"
    ],
    "wof:name":"Faspay Technologies Inc",
    "wof:placetype":"venue"
},
  "geometry": {"coordinates":[-87.82499300000001,42.220893],"type":"Point"}
}