{
  "type": "Feature",
  "properties": {
    "iso:country":"US",
    "sg:address":"1485 Commerce Dr",
    "sg:city":"Algonquin",
    "sg:classifiers":[
        {
            "category":"Professional",
            "subcategory":"Lawyer & Legal Services",
            "type":"Services"
        }
    ],
    "sg:phone":"+1 847 658 9100",
    "sg:postcode":"60102",
    "sg:province":"IL",
    "wof:name":"Mohr Bruce Hirsh & Hill PC",
    "wof:placetype":"venue"
},
  "geometry": {"coordinates":[-88.334857,42.156507],"type":"Point"}
}