{
  "type": "Feature",
  "properties": {
    "iso:country":"US",
    "sg:address":"225 W Benton St",
    "sg:city":"Aurora",
    "sg:classifiers":[
        {
            "category":"Building & Trades",
            "subcategory":"Construction",
            "type":"Services"
        }
    ],
    "sg:phone":"+1 630 844 2262",
    "sg:postcode":"60506",
    "sg:province":"IL",
    "sg:tags":[
        "elevator"
    ],
    "wof:name":"Advanced Elevator Corp",
    "wof:placetype":"venue"
},
  "geometry": {"coordinates":[-88.32087199999999,41.758354],"type":"Point"}
}