{
  "type": "Feature",
  "properties": {
    "iso:country":"US",
    "sg:address":"17195 Apple Tree Dr",
    "sg:city":"Country Club Hls",
    "sg:classifiers":[
        {
            "category":"Organizations",
            "subcategory":"Non-profit Organization",
            "type":"Services"
        }
    ],
    "sg:phone":"+1 708 647 9880",
    "sg:postcode":"60478",
    "sg:province":"IL",
    "wof:name":"African Projects For Peace",
    "wof:placetype":"venue"
},
  "geometry": {"coordinates":[-87.707116,41.576845],"type":"Point"}
}