{
  "type": "Feature",
  "properties": {
    "addr:full":"4214 7th St East Moline IL 61244",
    "addr:housenumber":"4214",
    "addr:postcode":"61244",
    "addr:street":"7Th St",
    "iso:country":"US",
    "sg:address":"4214 7th St",
    "sg:city":"East Moline",
    "sg:classifiers":[
        {
            "category":"Personal",
            "subcategory":"Nail Salon",
            "type":"Services"
        }
    ],
    "sg:phone":"+1 309 792 2130",
    "sg:postcode":"61244",
    "sg:province":"IL",
    "wof:name":"Bloomingnails",
    "wof:placetype":"venue"
},
  "geometry": {"coordinates":[-90.44450399999999,41.488602],"type":"Point"}
}