{
  "type": "Feature",
  "properties": {
    "addr:full":"209 Peterson Rd Libertyville IL 60048",
    "addr:housenumber":"209",
    "addr:postcode":"60048",
    "addr:street":"Peterson Rd",
    "iso:country":"US",
    "sg:address":"209 Peterson Rd",
    "sg:city":"Libertyville",
    "sg:classifiers":[
        {
            "category":"Health Services",
            "subcategory":"Doctor",
            "type":"Services"
        }
    ],
    "sg:phone":"+1 847 362 1800",
    "sg:postcode":"60048",
    "sg:province":"IL",
    "sg:tags":[
        "clinic",
        "medical"
    ],
    "wof:name":"Lake County Radiology Assoc SC",
    "wof:placetype":"venue"
},
  "geometry": {"coordinates":[-87.96513400000001,42.305907],"type":"Point"}
}