{
  "type": "Feature",
  "properties": {
    "iso:country":"US",
    "sg:address":"6229 Ogden Ave",
    "sg:city":"Berwyn",
    "sg:classifiers":[
        {
            "category":"Retail",
            "subcategory":"Auto Repair",
            "type":"Services"
        }
    ],
    "sg:phone":"+1 708 652 5838",
    "sg:postcode":"60402",
    "sg:province":"IL",
    "wof:name":"Avery's Services",
    "wof:placetype":"venue"
},
  "geometry": {"coordinates":[-87.779602,41.831501],"type":"Point"}
}