{
  "type": "Feature",
  "properties": {
    "iso:country":"US",
    "sg:address":"2758 N Ashland Ave",
    "sg:city":"Chicago",
    "sg:classifiers":[
        {
            "category":"Bars & Pubs",
            "type":"Food & Drink"
        },
        {
            "category":"Bars & Pubs",
            "subcategory":"Nightclub",
            "type":"Food & Drink"
        },
        {
            "category":"Bars & Pubs",
            "subcategory":"Sports Bar",
            "type":"Food & Drink"
        }
    ],
    "sg:phone":"+1 773 248 9160",
    "sg:postcode":"60614",
    "sg:province":"IL",
    "sg:tags":[
        "club",
        "tavern",
        "night"
    ],
    "sg:website":"www.fourshadows.net/",
    "wof:name":"Four Shadows",
    "wof:placetype":"venue"
},
  "geometry": {"coordinates":[-87.668747,41.932283],"type":"Point"}
}