{
  "type": "Feature",
  "properties": {
    "iso:country":"US",
    "sg:address":"123 Des Plaines Ave",
    "sg:city":"Forest Park",
    "sg:classifiers":[
        {
            "category":"Communications",
            "subcategory":"Film & Video Production",
            "type":"Services"
        }
    ],
    "sg:phone":"+1 708 488 9670",
    "sg:postcode":"60130",
    "sg:province":"IL",
    "sg:tags":[
        "motion"
    ],
    "wof:name":"Video Production Services",
    "wof:placetype":"venue"
},
  "geometry": {"coordinates":[-87.81204200000001,41.885186],"type":"Point"}
}