{
  "type": "Feature",
  "properties": {
    "addr:full":"450 E Court St Kankakee IL 60901",
    "addr:housenumber":"450",
    "addr:postcode":"60901",
    "addr:street":"E Court St",
    "iso:country":"US",
    "sg:address":"450 E Court St",
    "sg:city":"Kankakee",
    "sg:classifiers":[
        {
            "category":"Government",
            "subcategory":"Office",
            "type":"Public Place"
        }
    ],
    "sg:phone":"+1   ",
    "sg:postcode":"60901",
    "sg:province":"IL",
    "sg:tags":[
        "executive"
    ],
    "wof:name":"Dept States Attorneys Office",
    "wof:placetype":"venue"
},
  "geometry": {"coordinates":[-87.86033,41.119849],"type":"Point"}
}