{
  "type": "Feature",
  "properties": {
    "addr:full":"101 W Washington St Millstadt IL 62260",
    "addr:housenumber":"101",
    "addr:postcode":"62260",
    "addr:street":"W Washington St",
    "iso:country":"US",
    "sg:address":"101 W Washington St",
    "sg:city":"Millstadt",
    "sg:classifiers":[
        {
            "category":"Restaurant",
            "type":"Food & Drink"
        }
    ],
    "sg:menulink":"http://www.allmenus.com/il/millstadt/126804-subway/menu/",
    "sg:phone":"+1 618 476 1884",
    "sg:postcode":"62260",
    "sg:province":"IL",
    "sg:tags":[
        "american",
        "sandwich"
    ],
    "wof:name":"Subway",
    "wof:placetype":"venue"
},
  "geometry": {"coordinates":[-90.092941,38.461649],"type":"Point"}
}