{
  "type": "Feature",
  "properties": {
    "iso:country":"US",
    "sg:address":"1013 Spring Rd",
    "sg:city":"Elmhurst",
    "sg:classifiers":[
        {
            "category":"Food & Beverages",
            "subcategory":"Groceries & Convenience Stores",
            "type":"Retail Goods"
        }
    ],
    "sg:phone":"+1   ",
    "sg:postcode":"60126",
    "sg:province":"IL",
    "wof:name":"Northern Illinois Food Service",
    "wof:placetype":"venue"
},
  "geometry": {"coordinates":[-87.94887,41.867151],"type":"Point"}
}