{
  "type": "Feature",
  "properties": {
    "iso:country":"US",
    "sg:address":"539 Margate Ter",
    "sg:city":"Deerfield",
    "sg:classifiers":[
        {
            "category":"Wholesale",
            "subcategory":"Groceries",
            "type":"Manufacturing & Wholesale Goods"
        }
    ],
    "sg:phone":"+1 847 940 7251",
    "sg:postcode":"60015",
    "sg:province":"IL",
    "wof:name":"Liquid Asset",
    "wof:placetype":"venue"
},
  "geometry": {"coordinates":[-87.841859,42.170372],"type":"Point"}
}