{
  "type": "Feature",
  "properties": {
    "addr:full":"2550 W Lexington St Chicago IL 60612",
    "addr:housenumber":"2550",
    "addr:postcode":"60612",
    "addr:street":"W Lexington St",
    "iso:country":"US",
    "sg:address":"2550 W Lexington St",
    "sg:city":"Chicago",
    "sg:classifiers":[
        {
            "category":"Retail",
            "subcategory":"Auto Repair",
            "type":"Services"
        }
    ],
    "sg:phone":"+1 312 666 1100",
    "sg:postcode":"60612",
    "sg:province":"IL",
    "wof:name":"Chicagoland Auto Repairs & Body Shop",
    "wof:placetype":"venue"
},
  "geometry": {"coordinates":[-87.69061499999999,41.872313],"type":"Point"}
}