{
  "type": "Feature",
  "properties": {
    "iso:country":"US",
    "sg:address":"1905 W Chicago Avenue",
    "sg:city":"Chicago",
    "sg:classifiers":[
        {
            "category":"Real Estate",
            "subcategory":"Real Estate Services",
            "type":"Services"
        }
    ],
    "sg:phone":"+1 312 850 2620",
    "sg:postcode":"60622",
    "sg:province":"IL",
    "sg:website":"www.questchicago.com",
    "wof:name":"Quest Realty Group",
    "wof:placetype":"venue"
},
  "geometry": {"coordinates":[-87.674763,41.895942],"type":"Point"}
}