{
  "type": "Feature",
  "properties": {
    "iso:country":"US",
    "sg:address":"4825 W Pensacola Ave",
    "sg:city":"Chicago",
    "sg:classifiers":[
        {
            "category":"Building & Trades",
            "subcategory":"Construction",
            "type":"Services"
        }
    ],
    "sg:phone":"+1 773 282 6517",
    "sg:postcode":"60641",
    "sg:province":"IL",
    "sg:tags":[
        "house",
        "nonresidential"
    ],
    "wof:name":"B Brant Constr Co Inc",
    "wof:placetype":"venue"
},
  "geometry": {"coordinates":[-87.74767199999999,41.959734],"type":"Point"}
}