{
  "type": "Feature",
  "properties": {
    "iso:country":"US",
    "sg:address":"6539 26th St",
    "sg:city":"Berwyn",
    "sg:classifiers":[
        {
            "category":"Education",
            "subcategory":"School",
            "type":"Public Place"
        }
    ],
    "sg:phone":"+1 708 795 2327",
    "sg:postcode":"60402",
    "sg:province":"IL",
    "sg:tags":[
        "high",
        "middle",
        "elementary"
    ],
    "wof:name":"Schools Public",
    "wof:placetype":"venue"
},
  "geometry": {"coordinates":[-87.787165,41.843485],"type":"Point"}
}