{
  "type": "Feature",
  "properties": {
    "iso:country":"US",
    "sg:address":"3350 W 95th St",
    "sg:city":"Evergreen Park",
    "sg:classifiers":[
        {
            "category":"Real Estate",
            "subcategory":"Architect",
            "type":"Services"
        }
    ],
    "sg:phone":"+1 708 636 9960",
    "sg:postcode":"60805",
    "sg:province":"IL",
    "sg:tags":[
        "building",
        "construction"
    ],
    "wof:name":"All Maintenance Construction",
    "wof:placetype":"venue"
},
  "geometry": {"coordinates":[-87.706471,41.720759],"type":"Point"}
}