{
  "type": "Feature",
  "properties": {
    "addr:full":"600 W Main St Ste 2 Carbondale IL 62901",
    "addr:housenumber":"600",
    "addr:postcode":"62901",
    "addr:street":"W Main St Ste 2",
    "iso:country":"US",
    "sg:address":"600 W Main St Ste 2",
    "sg:city":"Carbondale",
    "sg:classifiers":[
        {
            "category":"Real Estate",
            "subcategory":"Architect",
            "type":"Services"
        }
    ],
    "sg:phone":"+1 618 457 5709",
    "sg:postcode":"62901",
    "sg:province":"IL",
    "wof:name":"Bohnsack H Michael Architects",
    "wof:placetype":"venue"
},
  "geometry": {"coordinates":[-89.22339599999999,37.726799],"type":"Point"}
}