{
  "type": "Feature",
  "properties": {
    "iso:country":"US",
    "sg:address":"2325 177th St",
    "sg:city":"Lansing",
    "sg:classifiers":[
        {
            "category":"Place Of Worship",
            "subcategory":"Church",
            "type":"Public Place"
        },
        {
            "category":"Place Of Worship",
            "type":"Public Place"
        },
        {
            "category":"Organizations",
            "subcategory":"Religious Organization",
            "type":"Services"
        }
    ],
    "sg:phone":"+1 708 895 7310",
    "sg:postcode":"60438",
    "sg:province":"IL",
    "sg:tags":[
        "god",
        "churches-church",
        "churches-pentecostal"
    ],
    "sg:website":"http://www.newleafresources.org",
    "wof:name":"New Leaf Resources",
    "wof:placetype":"venue"
},
  "geometry": {"coordinates":[-87.560641,41.573872],"type":"Point"}
}