{
  "type": "Feature",
  "properties": {
    "iso:country":"US",
    "sg:address":"7501 S Pulaski Rd",
    "sg:city":"Chicago",
    "sg:classifiers":[
        {
            "category":"Freight",
            "type":"Transportation"
        }
    ],
    "sg:phone":"+1 773 735 3554",
    "sg:postcode":"60652",
    "sg:province":"IL",
    "sg:tags":[
        "trucking"
    ],
    "wof:name":"Erick's Express Inc",
    "wof:placetype":"venue"
},
  "geometry": {"coordinates":[-87.72218599999999,41.755662],"type":"Point"}
}