{
  "type": "Feature",
  "properties": {
    "addr:full":"3100 Collinsville Rd East Saint Louis IL 62201",
    "addr:postcode":"3100;62201",
    "addr:street":"Collinsville Rd",
    "iso:country":"US",
    "sg:address":"3100 Collinsville Rd",
    "sg:city":"East Saint Louis",
    "sg:classifiers":[
        {
            "category":"Building & Trades",
            "subcategory":"Construction",
            "type":"Services"
        }
    ],
    "sg:phone":"+1 618 875 3565",
    "sg:postcode":"62201",
    "sg:province":"IL",
    "sg:tags":[
        "stonework",
        "masonry",
        "other"
    ],
    "wof:name":"Maranatha Masonry",
    "wof:placetype":"venue"
},
  "geometry": {"coordinates":[-90.114952,38.644554],"type":"Point"}
}