{
  "type": "Feature",
  "properties": {
    "addr:full":"7847 W Monee Manhattan Rd Monee IL 60449",
    "addr:housenumber":"7847",
    "addr:postcode":"60449",
    "addr:street":"W Monee Manhattan Rd",
    "iso:country":"US",
    "sg:address":"7847 W Monee Manhattan Rd",
    "sg:city":"Monee",
    "sg:classifiers":[
        {
            "category":"Professional",
            "subcategory":"Computer Services",
            "type":"Services"
        }
    ],
    "sg:phone":"+1 708 534 0961",
    "sg:postcode":"60449",
    "sg:province":"IL",
    "sg:tags":[
        "repair",
        "equipment-service"
    ],
    "sg:website":"http://www.rhubarbsystems.com",
    "wof:name":"Rhubarb Systems",
    "wof:placetype":"venue"
},
  "geometry": {"coordinates":[-87.803918,41.42648],"type":"Point"}
}