{
  "type": "Feature",
  "properties": {
    "addr:full":"930 175th St Homewood IL 60430",
    "addr:housenumber":"930",
    "addr:postcode":"60430",
    "addr:street":"175Th St",
    "iso:country":"US",
    "sg:address":"930 175th St",
    "sg:city":"Homewood",
    "sg:classifiers":[
        {
            "category":"Insurance",
            "subcategory":"Insurance Agent",
            "type":"Services"
        }
    ],
    "sg:phone":"+1 708 798 1972",
    "sg:postcode":"60430",
    "sg:province":"IL",
    "wof:name":"Allstate",
    "wof:placetype":"venue"
},
  "geometry": {"coordinates":[-87.640306,41.571873],"type":"Point"}
}