{
  "type": "Feature",
  "properties": {
    "iso:country":"US",
    "sg:address":"7228 W Palos Ave",
    "sg:city":"Palos Heights",
    "sg:classifiers":[
        {
            "category":"Food & Beverages",
            "subcategory":"Specialty",
            "type":"Retail Goods"
        }
    ],
    "sg:phone":"+1   ",
    "sg:postcode":"60463",
    "sg:province":"IL",
    "sg:tags":[
        "health"
    ],
    "wof:name":"Pass Health Foods",
    "wof:placetype":"venue"
},
  "geometry": {"coordinates":[-87.800699,41.659398],"type":"Point"}
}