{
  "type": "Feature",
  "properties": {
    "iso:country":"US",
    "sg:address":"1801 S 55th Ave",
    "sg:city":"Cicero",
    "sg:classifiers":[
        {
            "category":"Education",
            "subcategory":"Special Training",
            "type":"Public Place"
        }
    ],
    "sg:phone":"+1 708 863 2200",
    "sg:postcode":"60804",
    "sg:province":"IL",
    "sg:tags":[
        "school",
        "specialty"
    ],
    "wof:name":"Morton Freshman Center",
    "wof:placetype":"venue"
},
  "geometry": {"coordinates":[-87.761464,41.856529],"type":"Point"}
}