{
  "type": "Feature",
  "properties": {
    "iso:country":"US",
    "sg:address":"1524 St Louis Ave",
    "sg:city":"East St Louis",
    "sg:classifiers":[
        {
            "category":"Organizations",
            "subcategory":"Religious Organization",
            "type":"Services"
        }
    ],
    "sg:phone":"+1 618 482 2543",
    "sg:postcode":"62201",
    "sg:province":"IL",
    "sg:tags":[
        "church"
    ],
    "wof:name":"Eastside Church Of Christ",
    "wof:placetype":"venue"
},
  "geometry": {"coordinates":[-90.144963,38.617034],"type":"Point"}
}