{
  "type": "Feature",
  "properties": {
    "iso:country":"US",
    "sg:address":"4903 Main St",
    "sg:city":"Lisle",
    "sg:classifiers":[
        {
            "category":"Autos & Motor Vehicles",
            "subcategory":"Automobile Sales",
            "type":"Retail Goods"
        },
        {
            "category":"Autos & Motor Vehicles",
            "subcategory":"Auto Supplies",
            "type":"Retail Goods"
        },
        {
            "category":"Retail",
            "subcategory":"Auto Repair",
            "type":"Services"
        }
    ],
    "sg:phone":"+1 630 968 8473",
    "sg:postcode":"60532",
    "sg:province":"IL",
    "sg:tags":[
        "tire",
        "equipment",
        "brake",
        "air conditioning"
    ],
    "wof:name":"V & R Tire & Alignment Specialists Inc",
    "wof:placetype":"venue"
},
  "geometry": {"coordinates":[-88.074434,41.796928],"type":"Point"}
}