{
  "type": "Feature",
  "properties": {
    "iso:country":"US",
    "sg:address":"192 Dunteman Dr",
    "sg:city":"Glendale Heights",
    "sg:classifiers":[
        {
            "category":"Wholesale",
            "subcategory":"Computers",
            "type":"Manufacturing & Wholesale Goods"
        }
    ],
    "sg:phone":"+1 630 894 1947",
    "sg:postcode":"60139",
    "sg:province":"IL",
    "wof:name":"R Qyx",
    "wof:placetype":"venue"
},
  "geometry": {"coordinates":[-88.083905,41.942358],"type":"Point"}
}