{
  "type": "Feature",
  "properties": {
    "iso:country":"US",
    "sg:address":"217 Main St",
    "sg:city":"New Windsor",
    "sg:classifiers":[
        {
            "category":"Retail",
            "subcategory":"Auto Repair",
            "type":"Services"
        }
    ],
    "sg:phone":"+1 309 667 2757",
    "sg:postcode":"61465",
    "sg:province":"IL",
    "sg:tags":[
        "body",
        "automotive",
        "painting"
    ],
    "wof:name":"Davisons Auto Body & Repair",
    "wof:placetype":"venue"
},
  "geometry": {"coordinates":[-90.43834699999999,41.202344],"type":"Point"}
}