{
  "type": "Feature",
  "properties": {
    "iso:country":"US",
    "sg:address":"1246 N Pulaski Rd",
    "sg:city":"Chicago",
    "sg:classifiers":[
        {
            "category":"Retail",
            "subcategory":"Auto Repair",
            "type":"Services"
        }
    ],
    "sg:phone":"+1 773 342 4390",
    "sg:postcode":"60651",
    "sg:province":"IL",
    "sg:tags":[
        "repairing",
        "automobile",
        "general"
    ],
    "wof:name":"G & G Auto Repair",
    "wof:placetype":"venue"
},
  "geometry": {"coordinates":[-87.726414,41.90423],"type":"Point"}
}