{
  "type": "Feature",
  "properties": {
    "iso:country":"US",
    "sg:address":"118 W Ferguson Ave",
    "sg:city":"Wood River",
    "sg:classifiers":[
        {
            "category":"Personal",
            "subcategory":"Beauty Salon",
            "type":"Services"
        }
    ],
    "sg:phone":"+1 618 254 3989",
    "sg:postcode":"62095",
    "sg:province":"IL",
    "sg:tags":[
        "shop"
    ],
    "wof:name":"Your House Hair Care",
    "wof:placetype":"venue"
},
  "geometry": {"coordinates":[-90.100538,38.860826],"type":"Point"}
}