{
  "type": "Feature",
  "properties": {
    "addr:full":"1469 Rand Rd Des Plaines IL 60016",
    "addr:housenumber":"1469",
    "addr:postcode":"60016",
    "addr:street":"Rand Rd",
    "iso:country":"US",
    "sg:address":"1469 Rand Rd",
    "sg:city":"Des Plaines",
    "sg:classifiers":[
        {
            "category":"Retail",
            "subcategory":"Auto Rental",
            "type":"Services"
        }
    ],
    "sg:phone":"+1 847 699 7368",
    "sg:postcode":"60016",
    "sg:province":"IL",
    "sg:tags":[
        "truck"
    ],
    "wof:name":"Pride Car & Truck Rental Inc",
    "wof:placetype":"venue"
},
  "geometry": {"coordinates":[-87.88594000000001,42.047551],"type":"Point"}
}