{
  "type": "Feature",
  "properties": {
    "iso:country":"US",
    "sg:address":"109 W Union St",
    "sg:city":"Mount Sterling",
    "sg:classifiers":[
        {
            "category":"Professional",
            "subcategory":"Accounting & Tax Preparation",
            "type":"Services"
        }
    ],
    "sg:phone":"+1 217 773 9186",
    "sg:postcode":"62353",
    "sg:province":"IL",
    "sg:tags":[
        "return"
    ],
    "wof:name":"Greg McKennan",
    "wof:placetype":"venue"
},
  "geometry": {"coordinates":[-90.767252,39.983514],"type":"Point"}
}