{
  "type": "Feature",
  "properties": {
    "iso:country":"US",
    "sg:address":"2 Park Pl",
    "sg:city":"Swansea",
    "sg:classifiers":[
        {
            "category":"Real Estate",
            "subcategory":"Real Estate Agent",
            "type":"Services"
        }
    ],
    "sg:phone":"+1 618 233 4990",
    "sg:postcode":"62226",
    "sg:province":"IL",
    "wof:name":"Beyond Housing NHS",
    "wof:placetype":"venue"
},
  "geometry": {"coordinates":[-89.984296,38.539944],"type":"Point"}
}