{
  "type": "Feature",
  "properties": {
    "addr:full":"3696 Burwood Dr Waukegan IL 60085",
    "addr:housenumber":"3696",
    "addr:postcode":"60085",
    "addr:street":"Burwood Dr",
    "iso:country":"US",
    "sg:address":"3696 Burwood Dr",
    "sg:city":"Waukegan",
    "sg:classifiers":[
        {
            "category":"Wholesale",
            "subcategory":"Durable Goods & Equipment",
            "type":"Manufacturing & Wholesale Goods"
        }
    ],
    "sg:phone":"+1 847 473 2149",
    "sg:postcode":"60085",
    "sg:province":"IL",
    "sg:tags":[
        "representative",
        "manufacturer"
    ],
    "sg:website":"www.derse.com",
    "wof:name":"Derse Exhibits",
    "wof:placetype":"venue"
},
  "geometry": {"coordinates":[-87.892191,42.32469],"type":"Point"}
}