{
  "type": "Feature",
  "properties": {
    "addr:full":"16421 Whipple Rd Sycamore IL 60178",
    "addr:housenumber":"16421",
    "addr:postcode":"60178",
    "addr:street":"Whipple Rd",
    "iso:country":"US",
    "sg:address":"16421 Whipple Rd",
    "sg:city":"Sycamore",
    "sg:classifiers":[
        {
            "category":"Professional",
            "subcategory":"Advertising",
            "type":"Services"
        },
        {
            "category":"Professional",
            "subcategory":"Art Services",
            "type":"Services"
        }
    ],
    "sg:phone":"+1 815 899 3699",
    "sg:postcode":"60178",
    "sg:province":"IL",
    "sg:tags":[
        "designer",
        "agency",
        "producer",
        "display"
    ],
    "wof:name":"Design Discovery Ltd",
    "wof:placetype":"venue"
},
  "geometry": {"coordinates":[-88.63453,42.037784],"type":"Point"}
}