{
  "type": "Feature",
  "properties": {
    "addr:full":"125 Old Orchard Shopping Ctr Skokie IL 60077",
    "addr:housenumber":"125",
    "addr:postcode":"60077",
    "addr:street":"Old Orchard Shopping Ctr",
    "iso:country":"US",
    "sg:address":"125 Old Orchard Shopping Ctr",
    "sg:city":"Skokie",
    "sg:classifiers":[
        {
            "category":"Bakery",
            "type":"Food & Drink"
        }
    ],
    "sg:menulink":"http://www.allmenus.com/il/niles/219905-auntie-annes-pretzels/menu/",
    "sg:phone":"+1 847 677 1077",
    "sg:postcode":"60077",
    "sg:province":"IL",
    "sg:tags":[
        "american",
        "pastry"
    ],
    "wof:name":"Auntie Anne's Pretzels",
    "wof:placetype":"venue"
},
  "geometry": {"coordinates":[-87.749084,42.055867],"type":"Point"}
}