{
  "type": "Feature",
  "properties": {
    "addr:full":"970 Chateau Ave Aurora IL 60505",
    "addr:housenumber":"970",
    "addr:postcode":"60505",
    "addr:street":"Chateau Ave",
    "iso:country":"US",
    "sg:address":"970 Chateau Ave",
    "sg:city":"Aurora",
    "sg:classifiers":[
        {
            "category":"Building & Trades",
            "subcategory":"Construction",
            "type":"Services"
        }
    ],
    "sg:phone":"+1 630 585 7975",
    "sg:postcode":"60505",
    "sg:province":"IL",
    "sg:tags":[
        "contractor"
    ],
    "wof:name":"Chateau Drywall Inc",
    "wof:placetype":"venue"
},
  "geometry": {"coordinates":[-88.292365,41.780298],"type":"Point"}
}