{
  "type": "Feature",
  "properties": {
    "addr:full":"1105 W Argyle Street Chicago IL 60640",
    "addr:housenumber":"1105",
    "addr:postcode":"60640",
    "addr:street":"W Argyle Street",
    "iso:country":"US",
    "sg:address":"1105 W Argyle Street",
    "sg:city":"Chicago",
    "sg:classifiers":[
        {
            "category":"Shopping",
            "subcategory":"Jewelry",
            "type":"Retail Goods"
        }
    ],
    "sg:phone":"+1 773 769 6190",
    "sg:postcode":"60640",
    "sg:province":"IL",
    "wof:name":"Kim Hout Jewelry",
    "wof:placetype":"venue"
},
  "geometry": {"coordinates":[-87.65810999999999,41.973035],"type":"Point"}
}