{
  "type": "Feature",
  "properties": {
    "addr:full":"1256 W Palmer St Freeport IL 61032",
    "addr:housenumber":"1256",
    "addr:postcode":"61032",
    "addr:street":"W Palmer St",
    "iso:country":"US",
    "sg:address":"1256 W Palmer St",
    "sg:city":"Freeport",
    "sg:classifiers":[
        {
            "category":"Personal",
            "subcategory":"Beauty Salon",
            "type":"Services"
        }
    ],
    "sg:phone":"+1 815 233 4794",
    "sg:postcode":"61032",
    "sg:province":"IL",
    "wof:name":"Angels Touch Beauty Salon",
    "wof:placetype":"venue"
},
  "geometry": {"coordinates":[-89.643388,42.288928],"type":"Point"}
}