{
  "type": "Feature",
  "properties": {
    "iso:country":"US",
    "sg:address":"1784 E 25th Rd",
    "sg:city":"Ransom",
    "sg:classifiers":[
        {
            "category":"Farming",
            "subcategory":"Farm",
            "type":"Manufacturing & Wholesale Goods"
        }
    ],
    "sg:phone":"+1 815 586 4203",
    "sg:postcode":"60470",
    "sg:province":"IL",
    "wof:name":"Bergeson Farms",
    "wof:placetype":"venue"
},
  "geometry": {"coordinates":[-88.683339,41.182177],"type":"Point"}
}