{
  "type": "Feature",
  "properties": {
    "iso:country":"US",
    "sg:address":"17895 State Rte 37",
    "sg:city":"West Frankfort",
    "sg:classifiers":[
        {
            "category":"Professional",
            "subcategory":"Business Services",
            "type":"Services"
        }
    ],
    "sg:phone":"+1 618 937 3895",
    "sg:postcode":"62896",
    "sg:province":"IL",
    "wof:name":"PI Group of Southern Illinois",
    "wof:placetype":"venue"
},
  "geometry": {"coordinates":[-88.95606,37.896828],"type":"Point"}
}