{
  "type": "Feature",
  "properties": {
    "iso:country":"US",
    "sg:address":"112 W 87th St Ste F1A",
    "sg:city":"Chicago",
    "sg:classifiers":[
        {
            "category":"Shopping",
            "subcategory":"Discount & Variety Stores",
            "type":"Retail Goods"
        }
    ],
    "sg:postcode":"60620",
    "sg:province":"IL",
    "sg:tags":[
        "outlet"
    ],
    "sg:website":"www.dollartree.com",
    "wof:name":"Dollar Tree",
    "wof:placetype":"venue"
},
  "geometry": {"coordinates":[-87.63174600000001,41.73602],"type":"Point"}
}