{
  "type": "Feature",
  "properties": {
    "addr:full":"1910 E 95th Street Chicago IL 60617",
    "addr:housenumber":"1910",
    "addr:postcode":"60617",
    "addr:street":"E 95Th Street",
    "iso:country":"US",
    "sg:address":"1910 E 95th Street",
    "sg:city":"Chicago",
    "sg:classifiers":[
        {
            "category":"Banks & Credit Unions",
            "subcategory":"Bank",
            "type":"Services"
        }
    ],
    "sg:phone":"+1 773 356 5790",
    "sg:postcode":"60617",
    "sg:province":"IL",
    "wof:name":"Chase",
    "wof:placetype":"venue"
},
  "geometry": {"coordinates":[-87.577664,41.722331],"type":"Point"}
}