{
  "type": "Feature",
  "properties": {
    "iso:country":"US",
    "sg:address":"1040 W Huron St",
    "sg:city":"Chicago",
    "sg:classifiers":[
        {
            "category":"Professional",
            "subcategory":"Research",
            "type":"Services"
        }
    ],
    "sg:phone":"+1 773 525 4691",
    "sg:postcode":"60642",
    "sg:province":"IL",
    "wof:name":"Sheskin Research",
    "wof:placetype":"venue"
},
  "geometry": {"coordinates":[-87.653966,41.894394],"type":"Point"}
}