{
  "type": "Feature",
  "properties": {
    "addr:full":"10 Executive Ct Barrington IL 60010",
    "addr:housenumber":"10",
    "addr:postcode":"60010",
    "addr:street":"Executive Ct",
    "iso:country":"US",
    "sg:address":"10 Executive Ct",
    "sg:city":"Barrington",
    "sg:classifiers":[
        {
            "category":"Real Estate",
            "subcategory":"Architect",
            "type":"Services"
        }
    ],
    "sg:phone":"+1 847 438 5454",
    "sg:postcode":"60010",
    "sg:province":"IL",
    "sg:tags":[
        "architectural"
    ],
    "wof:name":"Muran Nowak Architects",
    "wof:placetype":"venue"
},
  "geometry": {"coordinates":[-88.142078,42.079583],"type":"Point"}
}