{
  "type": "Feature",
  "properties": {
    "addr:full":"619 S Gilbert St Danville IL 61832",
    "addr:housenumber":"619",
    "addr:postcode":"61832",
    "addr:street":"S Gilbert St",
    "iso:country":"US",
    "sg:address":"619 S Gilbert St",
    "sg:city":"Danville",
    "sg:classifiers":[
        {
            "category":"Restaurant",
            "type":"Food & Drink"
        }
    ],
    "sg:menulink":"http://www.allmenus.com/il/danville/281893-el-toro/menu/",
    "sg:phone":"+1 217 446 3090",
    "sg:postcode":"61832",
    "sg:province":"IL",
    "sg:tags":[
        "mexican"
    ],
    "wof:name":"El Toro",
    "wof:placetype":"venue"
},
  "geometry": {"coordinates":[-87.636112,40.11294],"type":"Point"}
}