{
  "type": "Feature",
  "properties": {
    "iso:country":"US",
    "sg:address":"907 1st Ave",
    "sg:city":"Rock Falls",
    "sg:classifiers":[
        {
            "category":"Autos & Motor Vehicles",
            "subcategory":"Auto Supplies",
            "type":"Retail Goods"
        }
    ],
    "sg:phone":"+1 815 622 4990",
    "sg:postcode":"61071",
    "sg:province":"IL",
    "sg:tags":[
        "automobile",
        "parts"
    ],
    "wof:name":"O'REILLY Auto Parts",
    "wof:placetype":"venue"
},
  "geometry": {"coordinates":[-89.689311,41.774454],"type":"Point"}
}