{
  "type": "Feature",
  "properties": {
    "iso:country":"US",
    "sg:address":"206 N Elmhurst Ave",
    "sg:city":"Mount Prospect",
    "sg:classifiers":[
        {
            "category":"Professional",
            "subcategory":"Management & Consulting",
            "type":"Services"
        }
    ],
    "sg:phone":"+1 847 253 9268",
    "sg:postcode":"60056",
    "sg:province":"IL",
    "sg:tags":[
        "property"
    ],
    "wof:name":"A & R Maintenance Inc",
    "wof:placetype":"venue"
},
  "geometry": {"coordinates":[-87.94179699999999,42.071619],"type":"Point"}
}