{
  "type": "Feature",
  "properties": {
    "iso:country":"US",
    "sg:address":"28 N Bennett St",
    "sg:city":"Geneva",
    "sg:classifiers":[
        {
            "category":"Insurance",
            "subcategory":"Insurance Agent",
            "type":"Services"
        }
    ],
    "sg:phone":"+1 630 232 4188",
    "sg:postcode":"60134",
    "sg:province":"IL",
    "wof:name":"Robert Geiken CLU",
    "wof:placetype":"venue"
},
  "geometry": {"coordinates":[-88.300349,41.887827],"type":"Point"}
}