{
  "type": "Feature",
  "properties": {
    "addr:full":"1401 W Hollywood Ave Chicago IL 60660",
    "addr:housenumber":"1401",
    "addr:postcode":"60660",
    "addr:street":"W Hollywood Ave",
    "iso:country":"US",
    "sg:address":"1401 W Hollywood Ave",
    "sg:city":"Chicago",
    "sg:classifiers":[
        {
            "category":"Organizations",
            "subcategory":"Religious Organization",
            "type":"Services"
        }
    ],
    "sg:phone":"+1 773 784 3040",
    "sg:postcode":"60660",
    "sg:province":"IL",
    "sg:website":"www.edgebapt.com",
    "wof:name":"Edgewater Baptist Church",
    "wof:placetype":"venue"
},
  "geometry": {"coordinates":[-87.66857899999999,41.985442],"type":"Point"}
}