{
  "type": "Feature",
  "properties": {
    "iso:country":"US",
    "sg:address":"3512 Caton Farm Rd",
    "sg:city":"Joliet",
    "sg:classifiers":[
        {
            "category":"Building & Trades",
            "subcategory":"Construction",
            "type":"Services"
        }
    ],
    "sg:phone":"+1 815 609 8210",
    "sg:postcode":"60431",
    "sg:province":"IL",
    "sg:tags":[
        "floor",
        "laying",
        "contractor"
    ],
    "wof:name":"Desire Hardwood Floors",
    "wof:placetype":"venue"
},
  "geometry": {"coordinates":[-88.168103,41.565364],"type":"Point"}
}