{
  "type": "Feature",
  "properties": {
    "addr:full":"102 E Plumb St Ransom IL 60470",
    "addr:housenumber":"102",
    "addr:postcode":"60470",
    "addr:street":"E Plumb St",
    "iso:country":"US",
    "sg:address":"102 E Plumb St",
    "sg:city":"Ransom",
    "sg:classifiers":[
        {
            "category":"Place Of Worship",
            "subcategory":"Church",
            "type":"Public Place"
        },
        {
            "category":"Place Of Worship",
            "type":"Public Place"
        }
    ],
    "sg:phone":"+1 815 586 4504",
    "sg:postcode":"60470",
    "sg:province":"IL",
    "sg:tags":[
        "churches-methodist"
    ],
    "sg:website":"http://www.umc.org",
    "wof:name":"United Methodist Church",
    "wof:placetype":"venue"
},
  "geometry": {"coordinates":[-88.654123,41.156712],"type":"Point"}
}