{
  "type": "Feature",
  "properties": {
    "iso:country":"US",
    "sg:address":"567 Meadow Ln",
    "sg:city":"Dixon",
    "sg:phone":"+1 815 288 4050",
    "sg:postcode":"61021",
    "sg:province":"IL",
    "sg:tags":[
        "farm",
        "grain",
        "cash"
    ],
    "wof:name":"Frederick Zbinden",
    "wof:placetype":"venue"
},
  "geometry": {"coordinates":[-89.522316,41.835817],"type":"Point"}
}