{
  "type": "Feature",
  "properties": {
    "addr:full":"929 E 103rd Street Chicago IL 60628",
    "addr:housenumber":"929",
    "addr:postcode":"60628",
    "addr:street":"E 103Rd Street",
    "iso:country":"US",
    "sg:address":"929 E 103rd Street",
    "sg:city":"Chicago",
    "sg:classifiers":[
        {
            "category":"Organizations",
            "subcategory":"Religious Organization",
            "type":"Services"
        }
    ],
    "sg:phone":"+1 773 785 1700",
    "sg:postcode":"60628",
    "sg:province":"IL",
    "wof:name":"Chicagoland Christian Center",
    "wof:placetype":"venue"
},
  "geometry": {"coordinates":[-87.59750699999999,41.707685],"type":"Point"}
}