{
  "type": "Feature",
  "properties": {
    "iso:country":"US",
    "sg:address":"9516 S Kildare Ave",
    "sg:city":"Oak Lawn",
    "sg:classifiers":[
        {
            "category":"Building & Trades",
            "subcategory":"Electrical",
            "type":"Services"
        }
    ],
    "sg:phone":"+1 708 636 8886",
    "sg:postcode":"60453",
    "sg:province":"IL",
    "sg:tags":[
        "electric",
        "contractor"
    ],
    "wof:name":"B & M Electric",
    "wof:placetype":"venue"
},
  "geometry": {"coordinates":[-87.728715,41.720121],"type":"Point"}
}