{
  "type": "Feature",
  "properties": {
    "addr:full":"1155 Peachtree Ct Naperville IL 60540",
    "addr:housenumber":"1155",
    "addr:postcode":"60540",
    "addr:street":"Peachtree Ct",
    "iso:country":"US",
    "sg:address":"1155 Peachtree Ct",
    "sg:city":"Naperville",
    "sg:classifiers":[
        {
            "category":"Wholesale",
            "subcategory":"Computers",
            "type":"Manufacturing & Wholesale Goods"
        }
    ],
    "sg:phone":"+1 630 355 0024",
    "sg:postcode":"60540",
    "sg:province":"IL",
    "sg:tags":[
        "equipment"
    ],
    "wof:name":"Norco Systems Integration",
    "wof:placetype":"venue"
},
  "geometry": {"coordinates":[-88.12905600000001,41.776085],"type":"Point"}
}