{
  "type": "Feature",
  "properties": {
    "addr:full":"5 Woodfield Mall Schaumburg IL 60173",
    "addr:housenumber":"5",
    "addr:postcode":"60173",
    "addr:street":"Woodfield Mall",
    "iso:country":"US",
    "sg:address":"5 Woodfield Mall",
    "sg:city":"Schaumburg",
    "sg:classifiers":[
        {
            "category":"Coffee & Tea",
            "type":"Food & Drink"
        }
    ],
    "sg:menulink":"http://www.allmenus.com/il/schaumburg/112616-starbucks-coffee/menu/",
    "sg:phone":"+1 847 517 1081",
    "sg:postcode":"60173",
    "sg:province":"IL",
    "sg:tags":[
        "american"
    ],
    "wof:name":"Starbucks Coffee",
    "wof:placetype":"venue"
},
  "geometry": {"coordinates":[-88.037722,42.049374],"type":"Point"}
}