{
  "type": "Feature",
  "properties": {
    "iso:country":"US",
    "sg:address":"6353 S Sacramento Ave",
    "sg:city":"Chicago",
    "sg:classifiers":[
        {
            "category":"Retail",
            "subcategory":"Auto Repair",
            "type":"Services"
        }
    ],
    "sg:phone":"+1 312 666 6621",
    "sg:postcode":"60629",
    "sg:province":"IL",
    "wof:name":"Big Apple Auto Tech",
    "wof:placetype":"venue"
},
  "geometry": {"coordinates":[-87.697868,41.777497],"type":"Point"}
}