{
  "type": "Feature",
  "properties": {
    "addr:full":"1914 Clover Ln Champaign IL 61821",
    "addr:housenumber":"1914",
    "addr:postcode":"61821",
    "addr:street":"Clover Ln",
    "iso:country":"US",
    "sg:address":"1914 Clover Ln",
    "sg:city":"Champaign",
    "sg:classifiers":[
        {
            "category":"Organizations",
            "subcategory":"Religious Organization",
            "type":"Services"
        }
    ],
    "sg:phone":"+1 217 359 1313",
    "sg:postcode":"61821",
    "sg:province":"IL",
    "wof:name":"Baha I Faith of Champaign",
    "wof:placetype":"venue"
},
  "geometry": {"coordinates":[-88.27939000000001,40.089995],"type":"Point"}
}