{
  "type": "Feature",
  "properties": {
    "iso:country":"US",
    "sg:address":"4136 Aberdeen Ave",
    "sg:city":"Alton",
    "sg:classifiers":[
        {
            "category":"Retail",
            "subcategory":"Auto Repair",
            "type":"Services"
        }
    ],
    "sg:phone":"+1 618 465 4334",
    "sg:postcode":"62002",
    "sg:province":"IL",
    "sg:tags":[
        "repairing",
        "automobile"
    ],
    "wof:name":"Rogers Performance",
    "wof:placetype":"venue"
},
  "geometry": {"coordinates":[-90.120383,38.891242],"type":"Point"}
}