{
  "type": "Feature",
  "properties": {
    "addr:full":"115 W 1st St Dixon IL 61021",
    "addr:housenumber":"115",
    "addr:postcode":"61021",
    "addr:street":"W 1St St",
    "iso:country":"US",
    "sg:address":"115 W 1st St",
    "sg:city":"Dixon",
    "sg:classifiers":[
        {
            "category":"Health Services",
            "subcategory":"Health Practitioner",
            "type":"Services"
        }
    ],
    "sg:phone":"+1 815 285 8394",
    "sg:postcode":"61021",
    "sg:province":"IL",
    "sg:tags":[
        "psychologist"
    ],
    "wof:name":"Elaine M Bochenek",
    "wof:placetype":"venue"
},
  "geometry": {"coordinates":[-89.482843,41.843617],"type":"Point"}
}