{
  "type": "Feature",
  "properties": {
    "addr:full":"7050 171st St Tinley Park IL 60477",
    "addr:housenumber":"7050",
    "addr:postcode":"60477",
    "addr:street":"171St St",
    "iso:country":"US",
    "sg:address":"7050 171st St",
    "sg:city":"Tinley Park",
    "sg:classifiers":[
        {
            "category":"Food & Beverages",
            "subcategory":"Liquor & Beverages",
            "type":"Retail Goods"
        }
    ],
    "sg:phone":"+1 708 802 9140",
    "sg:postcode":"60477",
    "sg:province":"IL",
    "wof:name":"Country Lane Liquor",
    "wof:placetype":"venue"
},
  "geometry": {"coordinates":[-87.792666,41.580544],"type":"Point"}
}