{
  "type": "Feature",
  "properties": {
    "addr:full":"3352 W Foster Ave Chicago IL 60625",
    "addr:housenumber":"3352",
    "addr:postcode":"60625",
    "addr:street":"W Foster Ave",
    "iso:country":"US",
    "sg:address":"3352 W Foster Ave",
    "sg:city":"Chicago",
    "sg:classifiers":[
        {
            "category":"Restaurant",
            "type":"Food & Drink"
        }
    ],
    "sg:phone":"+1 773 267 4455",
    "sg:postcode":"60625",
    "sg:province":"IL",
    "sg:tags":[
        "pizza"
    ],
    "wof:name":"North Park Village Pizza",
    "wof:placetype":"venue"
},
  "geometry": {"coordinates":[-87.71318100000001,41.975952],"type":"Point"}
}