{
  "type": "Feature",
  "properties": {
    "addr:full":"7828 S Western Avenue Chicago IL 60620",
    "addr:housenumber":"7828",
    "addr:postcode":"60620",
    "addr:street":"S Western Avenue",
    "iso:country":"US",
    "sg:address":"7828 S Western Avenue",
    "sg:city":"Chicago",
    "sg:classifiers":[
        {
            "category":"Restaurant",
            "type":"Food & Drink"
        }
    ],
    "sg:phone":"+1 773 918 9999",
    "sg:postcode":"60620",
    "sg:province":"IL",
    "wof:name":"Sharks Fish & Chicken",
    "wof:placetype":"venue"
},
  "geometry": {"coordinates":[-87.68292599999999,41.750874],"type":"Point"}
}