{
  "type": "Feature",
  "properties": {
    "addr:full":"4510 W Irving Park Rd Chicago IL 60641",
    "addr:housenumber":"4510",
    "addr:postcode":"60641",
    "addr:street":"W Irving Park Rd",
    "iso:country":"US",
    "sg:address":"4510 W Irving Park Rd",
    "sg:city":"Chicago",
    "sg:classifiers":[
        {
            "category":"Professional",
            "subcategory":"Credit Reporting & Collection",
            "type":"Services"
        }
    ],
    "sg:phone":"+1 773 685 1706",
    "sg:postcode":"60641",
    "sg:province":"IL",
    "wof:name":"Monumental III",
    "wof:placetype":"venue"
},
  "geometry": {"coordinates":[-87.74163799999999,41.953558],"type":"Point"}
}