{
  "type": "Feature",
  "properties": {
    "iso:country":"US",
    "sg:address":"3743 Prairie Ave",
    "sg:city":"Brookfield",
    "sg:classifiers":[
        {
            "category":"Insurance",
            "subcategory":"Insurance Agent",
            "type":"Services"
        },
        {
            "category":"Insurance",
            "subcategory":"Hazard Insurance",
            "type":"Services"
        },
        {
            "category":"Insurance",
            "subcategory":"Title Insurance",
            "type":"Services"
        }
    ],
    "sg:phone":"+1 708 485 7212",
    "sg:postcode":"60513",
    "sg:province":"IL",
    "sg:tags":[
        "auto",
        "homeowner"
    ],
    "sg:website":"http://apps.amfam.com/agentlocator/AGRINKEV?sourceid=yp3",
    "wof:name":"American Family Insurance- Alina Grinkevicius",
    "wof:placetype":"venue"
},
  "geometry": {"coordinates":[-87.84401699999999,41.823316],"type":"Point"}
}