{
  "type": "Feature",
  "properties": {
    "iso:country":"US",
    "sg:address":"215 S Schuyler Ave",
    "sg:city":"Kankakee",
    "sg:classifiers":[
        {
            "category":"Insurance",
            "subcategory":"Title Insurance",
            "type":"Services"
        }
    ],
    "sg:phone":"+1 815 933 5100",
    "sg:postcode":"60901",
    "sg:province":"IL",
    "wof:name":"Standard Title Guaranty Company",
    "wof:placetype":"venue"
},
  "geometry": {"coordinates":[-87.864187,41.118846],"type":"Point"}
}