{
  "type": "Feature",
  "properties": {
    "iso:country":"US",
    "sg:address":"126 S Northwest Hwy",
    "sg:city":"Barrington",
    "sg:classifiers":[
        {
            "category":"Professional",
            "subcategory":"Lawyer & Legal Services",
            "type":"Services"
        }
    ],
    "sg:phone":"+1 847 381 7555",
    "sg:postcode":"60010",
    "sg:province":"IL",
    "sg:tags":[
        "attorney"
    ],
    "sg:website":"http://www.curielli.com",
    "wof:name":"John Peter Curielli Pc, Law Office Of",
    "wof:placetype":"venue"
},
  "geometry": {"coordinates":[-88.128311,42.153427],"type":"Point"}
}