{
  "type": "Feature",
  "properties": {
    "iso:country":"US",
    "sg:address":"2801 Ridge Ave",
    "sg:city":"Rockford",
    "sg:classifiers":[
        {
            "category":"Shopping",
            "subcategory":"Computers & Home Electronics",
            "type":"Retail Goods"
        }
    ],
    "sg:phone":"+1 815 963 1760",
    "sg:postcode":"61103",
    "sg:province":"IL",
    "sg:tags":[
        "software"
    ],
    "sg:website":"www.sofengsvc.com",
    "wof:name":"Software Engineering Svc",
    "wof:placetype":"venue"
},
  "geometry": {"coordinates":[-89.091094,42.302113],"type":"Point"}
}