{
  "type": "Feature",
  "properties": {
    "iso:country":"US",
    "sg:address":"549 S Route 59",
    "sg:city":"Aurora",
    "sg:classifiers":[
        {
            "category":"Fast Food",
            "type":"Food & Drink"
        },
        {
            "category":"Restaurant",
            "type":"Food & Drink"
        },
        {
            "category":"Food & Beverages",
            "subcategory":"Groceries & Convenience Stores",
            "type":"Retail Goods"
        }
    ],
    "sg:phone":"+1 630 236 9990",
    "sg:postcode":"60504",
    "sg:province":"IL",
    "sg:tags":[
        "shop",
        "sandwich",
        "take"
    ],
    "sg:website":"http://www.jimmyjohns.com",
    "wof:name":"Jimmy John's",
    "wof:placetype":"venue"
},
  "geometry": {"coordinates":[-88.206074,41.761687],"type":"Point"}
}