{
  "type": "Feature",
  "properties": {
    "iso:country":"US",
    "sg:address":"9253 W Cermak Rd",
    "sg:city":"Riverside",
    "sg:classifiers":[
        {
            "category":"Restaurant",
            "type":"Food & Drink"
        }
    ],
    "sg:phone":"+1 708 443 0000",
    "sg:postcode":"60546",
    "sg:province":"IL",
    "sg:tags":[
        "pizza"
    ],
    "sg:website":"www.alsrestaurant.com",
    "wof:name":"Al's Restaurant",
    "wof:placetype":"venue"
},
  "geometry": {"coordinates":[-87.85382799999999,41.849233],"type":"Point"}
}