{
  "type": "Feature",
  "properties": {
    "iso:country":"US",
    "sg:address":"511 E Walnut St",
    "sg:city":"Carbondale",
    "sg:classifiers":[
        {
            "category":"Autos & Motor Vehicles",
            "subcategory":"Fuel & Gas Station",
            "type":"Retail Goods"
        }
    ],
    "sg:phone":"+1   ",
    "sg:postcode":"62901",
    "sg:province":"IL",
    "sg:tags":[
        "station",
        "gasoline"
    ],
    "wof:name":"Wareco",
    "wof:placetype":"venue"
},
  "geometry": {"coordinates":[-89.208731,37.725855],"type":"Point"}
}