{
  "type": "Feature",
  "properties": {
    "iso:country":"US",
    "sg:address":"2824 S 16th St",
    "sg:city":"Springfield",
    "sg:classifiers":[
        {
            "category":"Retail",
            "subcategory":"Laundry & Dry Cleaning",
            "type":"Services"
        },
        {
            "category":"Building & Trades",
            "subcategory":"Cleaning & Sanitation",
            "type":"Services"
        }
    ],
    "sg:phone":"+1 217 529 2233",
    "sg:postcode":"62703",
    "sg:province":"IL",
    "sg:tags":[
        "cleaner",
        "house"
    ],
    "wof:name":"Clc Cleaners",
    "wof:placetype":"venue"
},
  "geometry": {"coordinates":[-89.633707,39.764582],"type":"Point"}
}