{
  "type": "Feature",
  "properties": {
    "addr:full":"802 S Buchanan Dr Monticello IL 61856",
    "addr:housenumber":"802",
    "addr:postcode":"61856",
    "addr:street":"S Buchanan Dr",
    "iso:country":"US",
    "sg:address":"802 S Buchanan Dr",
    "sg:city":"Monticello",
    "sg:classifiers":[
        {
            "category":"Social Services",
            "subcategory":"Child Care",
            "type":"Services"
        }
    ],
    "sg:phone":"+1 217 762 7431",
    "sg:postcode":"61856",
    "sg:province":"IL",
    "sg:tags":[
        "day"
    ],
    "wof:name":"Kristi Hicks",
    "wof:placetype":"venue"
},
  "geometry": {"coordinates":[-88.569956,40.018976],"type":"Point"}
}