{
  "type": "Feature",
  "properties": {
    "iso:country":"US",
    "sg:address":"682 S Main St",
    "sg:city":"Virginia",
    "sg:phone":"+1 217 452 7270",
    "sg:postcode":"62691",
    "sg:province":"IL",
    "sg:tags":[
        "farm",
        "corn"
    ],
    "wof:name":"Roger Sweatman",
    "wof:placetype":"venue"
},
  "geometry": {"coordinates":[-90.215529,39.943128],"type":"Point"}
}