{
  "type": "Feature",
  "properties": {
    "addr:full":"5727 Strathmoor Dr Rockford IL 61107",
    "addr:housenumber":"5727",
    "addr:postcode":"61107",
    "addr:street":"Strathmoor Dr",
    "iso:country":"US",
    "sg:address":"5727 Strathmoor Dr",
    "sg:city":"Rockford",
    "sg:classifiers":[
        {
            "category":"Health Services",
            "subcategory":"Doctor",
            "type":"Services"
        }
    ],
    "sg:phone":"+1 815 381 1004",
    "sg:postcode":"61107",
    "sg:province":"IL",
    "sg:tags":[
        "physician",
        "surgeon"
    ],
    "wof:name":"Allison Benthal DO",
    "wof:placetype":"venue"
},
  "geometry": {"coordinates":[-89.005859,42.271071],"type":"Point"}
}