{
  "type": "Feature",
  "properties": {
    "addr:full":"2352 E 75th St Chicago IL 60649",
    "addr:housenumber":"2352",
    "addr:postcode":"60649",
    "addr:street":"E 75Th St",
    "iso:country":"US",
    "sg:address":"2352 E 75th St",
    "sg:city":"Chicago",
    "sg:classifiers":[
        {
            "category":"Food & Beverages",
            "subcategory":"Groceries & Convenience Stores",
            "type":"Retail Goods"
        }
    ],
    "sg:phone":"+1   ",
    "sg:postcode":"60649",
    "sg:province":"IL",
    "sg:tags":[
        "station",
        "gasoline"
    ],
    "wof:name":"Amoco",
    "wof:placetype":"venue"
},
  "geometry": {"coordinates":[-87.566711,41.759058],"type":"Point"}
}