{
  "type": "Feature",
  "properties": {
    "iso:country":"US",
    "sg:address":"1724 E Riverside Blvd",
    "sg:city":"Loves Park",
    "sg:classifiers":[
        {
            "category":"Shopping",
            "type":"Retail Goods"
        }
    ],
    "sg:phone":"+1 815 395 1055",
    "sg:postcode":"61111",
    "sg:province":"IL",
    "sg:tags":[
        "telephone",
        "cellular"
    ],
    "wof:name":"Forest City Communications",
    "wof:placetype":"venue"
},
  "geometry": {"coordinates":[-89.026914,42.318361],"type":"Point"}
}