{
  "type": "Feature",
  "properties": {
    "addr:full":"1025 Peoria St Peru IL 61354",
    "addr:housenumber":"1025",
    "addr:postcode":"61354",
    "addr:street":"Peoria St",
    "iso:country":"US",
    "sg:address":"1025 Peoria St",
    "sg:city":"Peru",
    "sg:classifiers":[
        {
            "category":"Insurance",
            "subcategory":"Insurance Agent",
            "type":"Services"
        }
    ],
    "sg:phone":"+1 815 223 0510",
    "sg:postcode":"61354",
    "sg:province":"IL",
    "wof:name":"Metropolitan Insurance",
    "wof:placetype":"venue"
},
  "geometry": {"coordinates":[-89.129108,41.330118],"type":"Point"}
}