{
  "type": "Feature",
  "properties": {
    "iso:country":"US",
    "sg:address":"1300 S White Oak Dr",
    "sg:city":"Waukegan",
    "sg:classifiers":[
        {
            "category":"Wholesale",
            "subcategory":"Apparel",
            "type":"Manufacturing & Wholesale Goods"
        }
    ],
    "sg:phone":"+1 847 689 1405",
    "sg:postcode":"60085",
    "sg:province":"IL",
    "wof:name":"Grafton Street Clothing Co",
    "wof:placetype":"venue"
},
  "geometry": {"coordinates":[-87.89358799999999,42.334097],"type":"Point"}
}