{
  "type": "Feature",
  "properties": {
    "iso:country":"US",
    "sg:address":"5720 N Belt W Ste #26",
    "sg:city":"Belleville",
    "sg:classifiers":[
        {
            "category":"Shopping",
            "subcategory":"Beauty & Cosmetics",
            "type":"Retail Goods"
        },
        {
            "category":"Personal",
            "subcategory":"Beauty Salon",
            "type":"Services"
        }
    ],
    "sg:phone":"+1 618 235 1653",
    "sg:postcode":"62226",
    "sg:province":"IL",
    "sg:tags":[
        "supply",
        "perfume",
        "hair",
        "equipment",
        "salons-equipment",
        "accessory"
    ],
    "sg:website":"http://www.sallybeauty.com/",
    "wof:name":"Sally Beauty Supply",
    "wof:placetype":"venue"
},
  "geometry": {"coordinates":[-90.033744,38.54164],"type":"Point"}
}