{
  "type": "Feature",
  "properties": {
    "addr:full":"3510 N University St Peoria IL 61604",
    "addr:housenumber":"3510",
    "addr:postcode":"61604",
    "addr:street":"N University St",
    "iso:country":"US",
    "sg:address":"3510 N University St",
    "sg:city":"Peoria",
    "sg:classifiers":[
        {
            "category":"Restaurant",
            "type":"Food & Drink"
        }
    ],
    "sg:phone":"+1 309 688 0418",
    "sg:postcode":"61604",
    "sg:province":"IL",
    "sg:tags":[
        "chinese"
    ],
    "sg:website":"http://www.mingshee.com",
    "wof:name":"Ming Shee Restaurant",
    "wof:placetype":"venue"
},
  "geometry": {"coordinates":[-89.612701,40.730572],"type":"Point"}
}