{
  "type": "Feature",
  "properties": {
    "addr:full":"108 E Superior St Chicago IL 60611",
    "addr:housenumber":"108",
    "addr:postcode":"60611",
    "addr:street":"E Superior St",
    "iso:country":"US",
    "sg:address":"108 E Superior St",
    "sg:city":"Chicago",
    "sg:classifiers":[
        {
            "category":"Restaurant",
            "type":"Food & Drink"
        }
    ],
    "sg:menulink":"http://www.allmenus.com/il/chicago/267041-the-lobby/menu/",
    "sg:phone":"+1 312 573 6760",
    "sg:postcode":"60611",
    "sg:province":"IL",
    "sg:tags":[
        "american"
    ],
    "wof:name":"The Lobby",
    "wof:placetype":"venue"
},
  "geometry": {"coordinates":[-87.62492899999999,41.895722],"type":"Point"}
}