{
  "type": "Feature",
  "properties": {
    "addr:full":"13161 W 143rd St Homer Glen IL 60441",
    "addr:housenumber":"13161",
    "addr:postcode":"60441",
    "addr:street":"W 143Rd St",
    "iso:country":"US",
    "sg:address":"13161 W 143rd St",
    "sg:city":"Homer Glen",
    "sg:classifiers":[
        {
            "category":"Manufacturing",
            "subcategory":"Printing",
            "type":"Manufacturing & Wholesale Goods"
        }
    ],
    "sg:phone":"+1 708 301 4900",
    "sg:postcode":"60441",
    "sg:province":"IL",
    "sg:tags":[
        "newspaper",
        "publishing"
    ],
    "wof:name":"Homerian",
    "wof:placetype":"venue"
},
  "geometry": {"coordinates":[-87.938316,41.628868],"type":"Point"}
}