{
  "type": "Feature",
  "properties": {
    "addr:full":"103 Haven Rd Elmhurst IL 60126",
    "addr:housenumber":"103",
    "addr:postcode":"60126",
    "addr:street":"Haven Rd",
    "iso:country":"US",
    "sg:address":"103 Haven Rd",
    "sg:city":"Elmhurst",
    "sg:classifiers":[
        {
            "category":"Health Services",
            "subcategory":"Doctor",
            "type":"Services"
        }
    ],
    "sg:phone":"+1 630 832 1865",
    "sg:postcode":"60126",
    "sg:province":"IL",
    "sg:tags":[
        "osteopathic"
    ],
    "wof:name":"Barbara Heller Do",
    "wof:placetype":"venue"
},
  "geometry": {"coordinates":[-87.936285,41.901083],"type":"Point"}
}