{
  "type": "Feature",
  "properties": {
    "addr:full":"5339 Maxey Rd Salem IL 62881",
    "addr:housenumber":"5339",
    "addr:postcode":"62881",
    "addr:street":"Maxey Rd",
    "iso:country":"US",
    "sg:address":"5339 Maxey Rd",
    "sg:city":"Salem",
    "sg:phone":"+1 618 548 3576",
    "sg:postcode":"62881",
    "sg:province":"IL",
    "sg:tags":[
        "farm",
        "soybean"
    ],
    "wof:name":"Maxey Loyd",
    "wof:placetype":"venue"
},
  "geometry": {"coordinates":[-88.981725,38.668194],"type":"Point"}
}