{
  "type": "Feature",
  "properties": {
    "addr:full":"2477 Eastrock Dr Rockford IL 61108",
    "addr:housenumber":"2477",
    "addr:postcode":"61108",
    "addr:street":"Eastrock Dr",
    "iso:country":"US",
    "sg:address":"2477 Eastrock Dr",
    "sg:city":"Rockford",
    "sg:classifiers":[
        {
            "category":"Home & Garden",
            "subcategory":"Building Materials",
            "type":"Retail Goods"
        }
    ],
    "sg:phone":"+1 815 398 6585",
    "sg:postcode":"61108",
    "sg:province":"IL",
    "sg:tags":[
        "equipment",
        "electric",
        "supply"
    ],
    "wof:name":"Eaton Cutler-Hammer",
    "wof:placetype":"venue"
},
  "geometry": {"coordinates":[-89.01345499999999,42.239409],"type":"Point"}
}