{
  "type": "Feature",
  "properties": {
    "addr:full":"14928 E Eddy Rd Davis Junction IL 61020",
    "addr:housenumber":"14928",
    "addr:postcode":"61020",
    "addr:street":"E Eddy Rd",
    "iso:country":"US",
    "sg:address":"14928 E Eddy Rd",
    "sg:city":"Davis Junction",
    "sg:classifiers":[
        {
            "category":"Farming",
            "subcategory":"Livestock Farm",
            "type":"Manufacturing & Wholesale Goods"
        }
    ],
    "sg:phone":"+1 815 393 4988",
    "sg:postcode":"61020",
    "sg:province":"IL",
    "sg:tags":[
        "hog",
        "beef",
        "corn",
        "cattle",
        "or",
        "feedlot"
    ],
    "wof:name":"Bruce Batty",
    "wof:placetype":"venue"
},
  "geometry": {"coordinates":[-89.074686,42.107405],"type":"Point"}
}