{
  "type": "Feature",
  "properties": {
    "iso:country":"US",
    "sg:address":"2220 E Stonewall Rd",
    "sg:city":"Gardner",
    "sg:classifiers":[
        {
            "category":"Farming",
            "subcategory":"Farm",
            "type":"Manufacturing & Wholesale Goods"
        }
    ],
    "sg:phone":"+1 815 584 1012",
    "sg:postcode":"60424",
    "sg:province":"IL",
    "sg:tags":[
        "crop",
        "general"
    ],
    "wof:name":"F & F Farms",
    "wof:placetype":"venue"
},
  "geometry": {"coordinates":[-88.380563,41.140281],"type":"Point"}
}