{
  "type": "Feature",
  "properties": {
    "iso:country":"US",
    "sg:address":"407 NW 3rd St",
    "sg:city":"Casey",
    "sg:classifiers":[
        {
            "category":"Organizations",
            "subcategory":"Non-profit Organization",
            "type":"Services"
        }
    ],
    "sg:phone":"+1 217 932 5900",
    "sg:postcode":"62420",
    "sg:province":"IL",
    "sg:tags":[
        "alternative",
        "abortion"
    ],
    "wof:name":"Crisis Pregnancy Ctr Of E Il",
    "wof:placetype":"venue"
},
  "geometry": {"coordinates":[-87.997149,39.30292],"type":"Point"}
}