{
  "type": "Feature",
  "properties": {
    "iso:country":"US",
    "sg:address":"211 S Quincy Ave",
    "sg:city":"Bradley",
    "sg:classifiers":[
        {
            "category":"Shopping",
            "type":"Retail Goods"
        }
    ],
    "sg:phone":"+1   ",
    "sg:postcode":"60915",
    "sg:province":"IL",
    "sg:tags":[
        "merchandise"
    ],
    "wof:name":"Jackson Fish & Pet Supplies",
    "wof:placetype":"venue"
},
  "geometry": {"coordinates":[-87.849599,41.141029],"type":"Point"}
}