{
  "type": "Feature",
  "properties": {
    "iso:country":"US",
    "sg:address":"2850 W 95th St",
    "sg:city":"Evergreen Park",
    "sg:classifiers":[
        {
            "category":"Shopping",
            "subcategory":"Pharmacy",
            "type":"Retail Goods"
        }
    ],
    "sg:phone":"+1   ",
    "sg:postcode":"60805",
    "sg:province":"IL",
    "sg:tags":[
        "drug",
        "store"
    ],
    "wof:name":"Jerozal Pharmacy",
    "wof:placetype":"venue"
},
  "geometry": {"coordinates":[-87.69409400000001,41.720893],"type":"Point"}
}