{
  "type": "Feature",
  "properties": {
    "iso:country":"US",
    "sg:address":"1501 S Blue Island Avenue",
    "sg:city":"Chicago",
    "sg:classifiers":[
        {
            "category":"Wholesale",
            "subcategory":"Fruits & Vegetables",
            "type":"Manufacturing & Wholesale Goods"
        }
    ],
    "sg:phone":"+1 312 455 0078",
    "sg:postcode":"60608",
    "sg:province":"IL",
    "sg:tags":[
        "veggie"
    ],
    "wof:name":"Capitol Wholesale Produce",
    "wof:placetype":"venue"
},
  "geometry": {"coordinates":[-87.658423,41.860871],"type":"Point"}
}