{
  "type": "Feature",
  "properties": {
    "addr:full":"9440 W Foster Ave Chicago IL 60656",
    "addr:housenumber":"9440",
    "addr:postcode":"60656",
    "addr:street":"W Foster Ave",
    "iso:country":"US",
    "sg:address":"9440 W Foster Ave",
    "sg:city":"Chicago",
    "sg:classifiers":[
        {
            "category":"Restaurant",
            "type":"Food & Drink"
        }
    ],
    "sg:phone":"+1   ",
    "sg:postcode":"60656",
    "sg:province":"IL",
    "wof:name":"Marias Mexican Restaurant",
    "wof:placetype":"venue"
},
  "geometry": {"coordinates":[-87.86227700000001,41.97331],"type":"Point"}
}