{
  "type": "Feature",
  "properties": {
    "addr:full":"19896 E 2400 N Rd Odell IL 60460",
    "addr:housenumber":"19896",
    "addr:postcode":"60460",
    "addr:street":"E 2400 N Rd",
    "iso:country":"US",
    "sg:address":"19896 E 2400 N Rd",
    "sg:city":"Odell",
    "sg:phone":"+1 815 998 2094",
    "sg:postcode":"60460",
    "sg:province":"IL",
    "sg:tags":[
        "farm",
        "corn"
    ],
    "wof:name":"Gary Fosen",
    "wof:placetype":"venue"
},
  "geometry": {"coordinates":[-88.56682499999999,40.976249],"type":"Point"}
}