{
  "type": "Feature",
  "properties": {
    "iso:country":"US",
    "sg:address":"1300 S Grove Ave",
    "sg:city":"Barrington",
    "sg:classifiers":[
        {
            "category":"Wholesale",
            "subcategory":"Machinery & Supplies",
            "type":"Manufacturing & Wholesale Goods"
        }
    ],
    "sg:phone":"+1 847 277 0508",
    "sg:postcode":"60010",
    "sg:province":"IL",
    "sg:tags":[
        "packaging"
    ],
    "wof:name":"Packagingpricecom Inc",
    "wof:placetype":"venue"
},
  "geometry": {"coordinates":[-88.130815,42.133392],"type":"Point"}
}