{
  "type": "Feature",
  "properties": {
    "addr:full":"105 E Franklin St Sesser IL 62884",
    "addr:housenumber":"105",
    "addr:postcode":"62884",
    "addr:street":"E Franklin St",
    "iso:country":"US",
    "sg:address":"105 E Franklin St",
    "sg:city":"Sesser",
    "sg:classifiers":[
        {
            "category":"Bars & Pubs",
            "type":"Food & Drink"
        }
    ],
    "sg:phone":"+1 618 625 5803",
    "sg:postcode":"62884",
    "sg:province":"IL",
    "sg:tags":[
        "drinking"
    ],
    "wof:name":"Cliff's Coal Inn",
    "wof:placetype":"venue"
},
  "geometry": {"coordinates":[-89.049001,38.091726],"type":"Point"}
}