{
  "type": "Feature",
  "properties": {
    "iso:country":"US",
    "sg:address":"14700 Wood St",
    "sg:city":"Harvey",
    "sg:classifiers":[
        {
            "category":"Shopping",
            "subcategory":"Mobile Phones",
            "type":"Retail Goods"
        }
    ],
    "sg:phone":"+1 708 331 7411",
    "sg:postcode":"60426",
    "sg:province":"IL",
    "wof:name":"B Known Services",
    "wof:placetype":"venue"
},
  "geometry": {"coordinates":[-87.661013,41.62264],"type":"Point"}
}