{
  "type": "Feature",
  "properties": {
    "iso:country":"US",
    "sg:address":"402 E Springfield Rd",
    "sg:city":"Arcola",
    "sg:classifiers":[
        {
            "category":"Food & Beverages",
            "subcategory":"Groceries & Convenience Stores",
            "type":"Retail Goods"
        }
    ],
    "sg:phone":"+1   ",
    "sg:postcode":"61910",
    "sg:province":"IL",
    "wof:name":"El Charro Inc",
    "wof:placetype":"venue"
},
  "geometry": {"coordinates":[-88.303899,39.680773],"type":"Point"}
}