{
  "type": "Feature",
  "properties": {
    "iso:country":"US",
    "sg:address":"1904 Park Ave",
    "sg:city":"Alton",
    "sg:classifiers":[
        {
            "category":"Building & Trades",
            "subcategory":"Construction",
            "type":"Services"
        }
    ],
    "sg:phone":"+1 618 462 0641",
    "sg:postcode":"62002",
    "sg:province":"IL",
    "sg:tags":[
        "house",
        "contractor"
    ],
    "wof:name":"Dave Wannamaker Construction",
    "wof:placetype":"venue"
},
  "geometry": {"coordinates":[-90.141188,38.906595],"type":"Point"}
}