{
  "type": "Feature",
  "properties": {
    "addr:full":"6374 N Lincoln Ave Chicago IL 60659",
    "addr:housenumber":"6374",
    "addr:postcode":"60659",
    "addr:street":"N Lincoln Ave",
    "iso:country":"US",
    "sg:address":"6374 N Lincoln Ave",
    "sg:city":"Chicago",
    "sg:classifiers":[
        {
            "category":"Health Services",
            "subcategory":"Doctor",
            "type":"Services"
        }
    ],
    "sg:phone":"+1 773 267 8820",
    "sg:postcode":"60659",
    "sg:province":"IL",
    "sg:tags":[
        "physician",
        "surgeon"
    ],
    "wof:name":"Dermatology Consultants",
    "wof:placetype":"venue"
},
  "geometry": {"coordinates":[-87.717967,41.997042],"type":"Point"}
}