{
  "type": "Feature",
  "properties": {
    "addr:full":"1400 Black Rd Joliet IL 60435",
    "addr:housenumber":"1400",
    "addr:postcode":"60435",
    "addr:street":"Black Rd",
    "iso:country":"US",
    "sg:address":"1400 Black Rd",
    "sg:city":"Joliet",
    "sg:classifiers":[
        {
            "category":"Insurance",
            "subcategory":"Insurance Agent",
            "type":"Services"
        }
    ],
    "sg:phone":"+1 815 725 3967",
    "sg:postcode":"60435",
    "sg:province":"IL",
    "wof:name":"John Bene' Agency",
    "wof:placetype":"venue"
},
  "geometry": {"coordinates":[-88.117538,41.537327],"type":"Point"}
}