{
  "type": "Feature",
  "properties": {
    "iso:country":"US",
    "sg:address":"2906 W Montrose Ave",
    "sg:city":"Chicago",
    "sg:classifiers":[
        {
            "category":"Retail",
            "subcategory":"Laundry & Dry Cleaning",
            "type":"Services"
        }
    ],
    "sg:phone":"+1 773 588 2244",
    "sg:postcode":"60618",
    "sg:province":"IL",
    "wof:name":"Mmfs",
    "wof:placetype":"venue"
},
  "geometry": {"coordinates":[-87.701302,41.9613],"type":"Point"}
}