{
  "type": "Feature",
  "properties": {
    "addr:full":"573 W Liberty St Wauconda IL 60084",
    "addr:housenumber":"573",
    "addr:postcode":"60084",
    "addr:street":"W Liberty St",
    "iso:country":"US",
    "sg:address":"573 W Liberty St",
    "sg:city":"Wauconda",
    "sg:classifiers":[
        {
            "category":"Health Services",
            "subcategory":"Optometrist",
            "type":"Services"
        }
    ],
    "sg:phone":"+1 847 740 2020",
    "sg:postcode":"60084",
    "sg:province":"IL",
    "wof:name":"Hasto Gregory Od",
    "wof:placetype":"venue"
},
  "geometry": {"coordinates":[-88.154415,42.258088],"type":"Point"}
}