{
  "type": "Feature",
  "properties": {
    "iso:country":"US",
    "sg:address":"618 S 5th Ave",
    "sg:city":"Maywood",
    "sg:classifiers":[
        {
            "category":"Personal",
            "subcategory":"Nail Salon",
            "type":"Services"
        }
    ],
    "sg:phone":"+1 708 410 0074",
    "sg:postcode":"60153",
    "sg:province":"IL",
    "wof:name":"City Nails",
    "wof:placetype":"venue"
},
  "geometry": {"coordinates":[-87.839159,41.882437],"type":"Point"}
}