{
  "type": "Feature",
  "properties": {
    "addr:full":"9201 Golf Rd Des Plaines IL 60016",
    "addr:housenumber":"9201",
    "addr:postcode":"60016",
    "addr:street":"Golf Rd Des",
    "iso:country":"US",
    "sg:address":"9201 Golf Rd",
    "sg:city":"Des Plaines",
    "sg:classifiers":[
        {
            "category":"Restaurant",
            "type":"Food & Drink"
        }
    ],
    "sg:menulink":"http://www.allmenus.com/il/maine/126347-subway/menu/",
    "sg:phone":"+1 847 635 7931",
    "sg:postcode":"60016",
    "sg:province":"IL",
    "sg:tags":[
        "american",
        "sandwich"
    ],
    "wof:name":"Subway",
    "wof:placetype":"venue"
},
  "geometry": {"coordinates":[-87.855059,42.054055],"type":"Point"}
}