{
  "type": "Feature",
  "properties": {
    "iso:country":"US",
    "sg:address":"818 W North Ave",
    "sg:city":"Chicago",
    "sg:classifiers":[
        {
            "category":"Building & Trades",
            "subcategory":"Construction",
            "type":"Services"
        },
        {
            "category":"Wholesale",
            "subcategory":"Home Furnishings",
            "type":"Manufacturing & Wholesale Goods"
        }
    ],
    "sg:phone":"+1 866 641 6344",
    "sg:postcode":"60622",
    "sg:province":"IL",
    "sg:tags":[
        "interior",
        "blind",
        "design",
        "shade"
    ],
    "sg:website":"www.eddiezs.com",
    "wof:name":"Eddie Z's Blinds and Drapery",
    "wof:placetype":"venue"
},
  "geometry": {"coordinates":[-87.64909400000001,41.910949],"type":"Point"}
}