{
  "type": "Feature",
  "properties": {
    "addr:full":"10470 163rd Pl Orland Park IL 60467",
    "addr:housenumber":"10470",
    "addr:postcode":"60467",
    "addr:street":"163Rd Pl",
    "iso:country":"US",
    "sg:address":"10470 163rd Pl",
    "sg:city":"Orland Park",
    "sg:classifiers":[
        {
            "category":"Wholesale",
            "subcategory":"Auto Parts",
            "type":"Manufacturing & Wholesale Goods"
        }
    ],
    "sg:phone":"+1 708 403 0155",
    "sg:postcode":"60467",
    "sg:province":"IL",
    "sg:tags":[
        "body",
        "automobile",
        "shop"
    ],
    "wof:name":"C & Y South Suburban Body Shop",
    "wof:placetype":"venue"
},
  "geometry": {"coordinates":[-87.874044,41.592769],"type":"Point"}
}