{
  "type": "Feature",
  "properties": {
    "iso:country":"US",
    "sg:address":"500 W Monroe Street Suite A",
    "sg:city":"Chicago",
    "sg:classifiers":[
        {
            "category":"Professional",
            "subcategory":"Employment Agencies",
            "type":"Services"
        }
    ],
    "sg:phone":"+1 312 928 0409",
    "sg:postcode":"60661",
    "sg:province":"IL",
    "wof:name":"Staffing Connection",
    "wof:placetype":"venue"
},
  "geometry": {"coordinates":[-87.639655,41.880569],"type":"Point"}
}