{
  "type": "Feature",
  "properties": {
    "iso:country":"US",
    "sg:address":"1562 N Damen Ave",
    "sg:city":"Chicago",
    "sg:classifiers":[
        {
            "category":"Retail",
            "subcategory":"Photofinishing",
            "type":"Services"
        },
        {
            "category":"Professional",
            "subcategory":"Printing & Photocopies",
            "type":"Services"
        }
    ],
    "sg:phone":"+1 773 486 6060",
    "sg:postcode":"60622",
    "sg:province":"IL",
    "sg:tags":[
        "laboratory",
        "laboratories-commercial",
        "finishing-custom",
        "photo"
    ],
    "wof:name":"Triangle Imaging",
    "wof:placetype":"venue"
},
  "geometry": {"coordinates":[-87.67744999999999,41.909674],"type":"Point"}
}