{
  "type": "Feature",
  "properties": {
    "addr:full":"1000 E 95th St Chicago IL 60619",
    "addr:housenumber":"1000",
    "addr:postcode":"60619",
    "addr:street":"E 95Th St",
    "iso:country":"US",
    "sg:address":"1000 E 95th St",
    "sg:city":"Chicago",
    "sg:classifiers":[
        {
            "category":"Retail",
            "subcategory":"Storage",
            "type":"Services"
        }
    ],
    "sg:phone":"+1 773 295 4142",
    "sg:postcode":"60619",
    "sg:province":"IL",
    "sg:tags":[
        "self"
    ],
    "sg:website":"www.smartstopselfstorage.com/",
    "wof:name":"SmartStop Self Storage",
    "wof:placetype":"venue"
},
  "geometry": {"coordinates":[-87.597185,41.723884],"type":"Point"}
}