{
  "type": "Feature",
  "properties": {
    "addr:full":"4042 W Madison St Chicago IL 60624",
    "addr:housenumber":"4042",
    "addr:postcode":"60624",
    "addr:street":"W Madison St",
    "iso:country":"US",
    "sg:address":"4042 W Madison St",
    "sg:city":"Chicago",
    "sg:classifiers":[
        {
            "category":"Shopping",
            "subcategory":"Bicycles & Sporting Goods",
            "type":"Retail Goods"
        }
    ],
    "sg:phone":"+1 773 533 8696",
    "sg:postcode":"60624",
    "sg:province":"IL",
    "wof:name":"Dream Town",
    "wof:placetype":"venue"
},
  "geometry": {"coordinates":[-87.727501,41.880699],"type":"Point"}
}