{
  "type": "Feature",
  "properties": {
    "addr:full":"10 Fiddlestix Ct Bloomington IL 61705",
    "addr:housenumber":"10",
    "addr:postcode":"61705",
    "addr:street":"Fiddlestix Ct",
    "iso:country":"US",
    "sg:address":"10 Fiddlestix Ct",
    "sg:city":"Bloomington",
    "sg:classifiers":[
        {
            "category":"Building & Trades",
            "subcategory":"Electrical",
            "type":"Services"
        }
    ],
    "sg:phone":"+1 309 808 1511",
    "sg:postcode":"61705",
    "sg:province":"IL",
    "sg:tags":[
        "electrician"
    ],
    "wof:name":"Allen Rb Electric",
    "wof:placetype":"venue"
},
  "geometry": {"coordinates":[-89.037796,40.449216],"type":"Point"}
}