{
  "type": "Feature",
  "properties": {
    "iso:country":"US",
    "sg:address":"10706 Grand Ave",
    "sg:city":"Franklin Park",
    "sg:classifiers":[
        {
            "category":"Professional",
            "subcategory":"Business Services",
            "type":"Services"
        }
    ],
    "sg:phone":"+1 847 455 7100",
    "sg:postcode":"60131",
    "sg:province":"IL",
    "sg:tags":[
        "packaging"
    ],
    "wof:name":"Case Packaging",
    "wof:placetype":"venue"
},
  "geometry": {"coordinates":[-87.892405,41.930595],"type":"Point"}
}