{
  "type": "Feature",
  "properties": {
    "iso:country":"US",
    "sg:address":"1122 W Balmoral Ave",
    "sg:city":"Chicago",
    "sg:classifiers":[
        {
            "category":"Retail",
            "subcategory":"Auto Repair",
            "type":"Services"
        }
    ],
    "sg:phone":"+1 773 907 9999",
    "sg:postcode":"60640",
    "sg:province":"IL",
    "sg:tags":[
        "repairing",
        "automobile"
    ],
    "wof:name":"Balmoral Auto Werks",
    "wof:placetype":"venue"
},
  "geometry": {"coordinates":[-87.659099,41.979993],"type":"Point"}
}