{
  "type": "Feature",
  "properties": {
    "addr:full":"912 13th St Viola IL 61486",
    "addr:housenumber":"912",
    "addr:postcode":"61486",
    "addr:street":"13Th St",
    "iso:country":"US",
    "sg:address":"912 13th St",
    "sg:city":"Viola",
    "sg:classifiers":[
        {
            "category":"Food & Beverages",
            "subcategory":"Groceries & Convenience Stores",
            "type":"Retail Goods"
        }
    ],
    "sg:phone":"+1 309 596 2445",
    "sg:postcode":"61486",
    "sg:province":"IL",
    "wof:name":"All Stop",
    "wof:placetype":"venue"
},
  "geometry": {"coordinates":[-90.586546,41.211245],"type":"Point"}
}