{
  "type": "Feature",
  "properties": {
    "iso:country":"US",
    "sg:address":"8317 Prairie Hill Rd",
    "sg:city":"South Beloit",
    "sg:classifiers":[
        {
            "category":"Building & Trades",
            "subcategory":"Landscaping Services",
            "type":"Services"
        }
    ],
    "sg:phone":"+1 815 389 2600",
    "sg:postcode":"61080",
    "sg:province":"WI",
    "sg:tags":[
        "tree"
    ],
    "wof:name":"Bill West Tree Care",
    "wof:placetype":"venue"
},
  "geometry": {"coordinates":[-88.946146,42.471883],"type":"Point"}
}