{
  "type": "Feature",
  "properties": {
    "addr:full":"9812 S Trumbull Ave Evergreen Park IL 60805",
    "addr:housenumber":"9812",
    "addr:postcode":"60805",
    "addr:street":"S Trumbull Ave",
    "iso:country":"US",
    "sg:address":"9812 S Trumbull Ave",
    "sg:city":"Evergreen Park",
    "sg:classifiers":[
        {
            "category":"Arts & Performance",
            "subcategory":"Theater",
            "type":"Entertainment"
        }
    ],
    "sg:phone":"+1 773 436 5176",
    "sg:postcode":"60805",
    "sg:province":"IL",
    "sg:tags":[
        "production"
    ],
    "sg:website":"www.citylightsorchestra.com",
    "wof:name":"BBM Productions",
    "wof:placetype":"venue"
},
  "geometry": {"coordinates":[-87.70780600000001,41.714844],"type":"Point"}
}