{
  "type": "Feature",
  "properties": {
    "addr:full":"525 W Wrightwood Ave Elmhurst IL 60126",
    "addr:housenumber":"525",
    "addr:postcode":"60126",
    "addr:street":"W Wrightwood Ave",
    "iso:country":"US",
    "sg:address":"525 W Wrightwood Ave",
    "sg:city":"Elmhurst",
    "sg:classifiers":[
        {
            "category":"Wholesale",
            "subcategory":"Non-durable Goods",
            "type":"Manufacturing & Wholesale Goods"
        }
    ],
    "sg:phone":"+1 630 834 8080",
    "sg:postcode":"60126",
    "sg:province":"IL",
    "wof:name":"Premium Instrument",
    "wof:placetype":"venue"
},
  "geometry": {"coordinates":[-87.954453,41.924581],"type":"Point"}
}