{
  "type": "Feature",
  "properties": {
    "iso:country":"US",
    "sg:address":"902 Commercial Ave",
    "sg:city":"Cairo",
    "sg:classifiers":[
        {
            "category":"Shopping",
            "subcategory":"Discount & Variety Stores",
            "type":"Retail Goods"
        }
    ],
    "sg:phone":"+1 618 734 9464",
    "sg:postcode":"62914",
    "sg:province":"IL",
    "wof:name":"Dianne's Corner",
    "wof:placetype":"venue"
},
  "geometry": {"coordinates":[-89.167241,37.002102],"type":"Point"}
}