{
  "type": "Feature",
  "properties": {
    "iso:country":"US",
    "sg:address":"25989 E Wildlife Dr",
    "sg:city":"Hopedale",
    "sg:classifiers":[
        {
            "category":"Wholesale",
            "subcategory":"Construction Materials",
            "type":"Manufacturing & Wholesale Goods"
        },
        {
            "category":"Mining & Drilling",
            "type":"Manufacturing & Wholesale Goods"
        }
    ],
    "sg:phone":"+1 309 449 6061",
    "sg:postcode":"61747",
    "sg:province":"IL",
    "sg:tags":[
        "sand",
        "gravel"
    ],
    "wof:name":"R A Cullinan & Son",
    "wof:placetype":"venue"
},
  "geometry": {"coordinates":[-89.440675,40.453427],"type":"Point"}
}