{
  "type": "Feature",
  "properties": {
    "iso:country":"US",
    "sg:address":"810 W Buckingham Pl",
    "sg:city":"Chicago",
    "sg:classifiers":[
        {
            "category":"Home & Garden",
            "subcategory":"Home Furnishings",
            "type":"Retail Goods"
        },
        {
            "category":"Wholesale",
            "subcategory":"Home Furnishings",
            "type":"Manufacturing & Wholesale Goods"
        }
    ],
    "sg:phone":"+1 312 622 3402",
    "sg:postcode":"60657",
    "sg:province":"IL",
    "sg:tags":[
        "draperies",
        "fixture",
        "window",
        "treatment",
        "curtain",
        "drapery"
    ],
    "wof:name":"Art Of Living Inc",
    "wof:placetype":"venue"
},
  "geometry": {"coordinates":[-87.65178,41.942626],"type":"Point"}
}