{
  "type": "Feature",
  "properties": {
    "iso:country":"US",
    "sg:address":"5419 N Clark St",
    "sg:city":"Chicago",
    "sg:classifiers":[
        {
            "category":"Restaurant",
            "type":"Food & Drink"
        }
    ],
    "sg:phone":"+1 773 561 7363",
    "sg:postcode":"60640",
    "sg:province":"IL",
    "sg:tags":[
        "beer",
        "eating",
        "spirit",
        "wine"
    ],
    "wof:name":"Star Gaze Restaurant & Bar",
    "wof:placetype":"venue"
},
  "geometry": {"coordinates":[-87.668404,41.980099],"type":"Point"}
}