{
  "type": "Feature",
  "properties": {
    "addr:full":"2443 Warrenville Rd Lisle IL 60532",
    "addr:housenumber":"2443",
    "addr:postcode":"60532",
    "addr:street":"Warrenville Rd",
    "iso:country":"US",
    "sg:address":"2443 Warrenville Rd",
    "sg:city":"Lisle",
    "sg:classifiers":[
        {
            "category":"Education",
            "subcategory":"Vocational School",
            "type":"Public Place"
        }
    ],
    "sg:phone":"+1 630 245 1505",
    "sg:postcode":"60532",
    "sg:province":"IL",
    "sg:tags":[
        "consulting",
        "management",
        "datum",
        "processing"
    ],
    "wof:name":"R/Access",
    "wof:placetype":"venue"
},
  "geometry": {"coordinates":[-88.10181,41.808155],"type":"Point"}
}