{
  "type": "Feature",
  "properties": {
    "addr:full":"255 N Loucks St Aurora IL 60505",
    "addr:housenumber":"255",
    "addr:postcode":"60505",
    "addr:street":"N Loucks St",
    "iso:country":"US",
    "sg:address":"255 N Loucks St",
    "sg:city":"Aurora",
    "sg:classifiers":[
        {
            "category":"Local Transit",
            "type":"Transportation"
        }
    ],
    "sg:phone":"+1 630 585 5847",
    "sg:postcode":"60505",
    "sg:province":"IL",
    "sg:tags":[
        "airport"
    ],
    "wof:name":"American Taxi Dispatch Inc",
    "wof:placetype":"venue"
},
  "geometry": {"coordinates":[-88.286374,41.759095],"type":"Point"}
}