{
  "type": "Feature",
  "properties": {
    "addr:full":"1240 Larry Power Rd Bourbonnais IL 60914",
    "addr:housenumber":"1240",
    "addr:postcode":"60914",
    "addr:street":"Larry Power Rd",
    "iso:country":"US",
    "sg:address":"1240 Larry Power Rd",
    "sg:city":"Bourbonnais",
    "sg:classifiers":[
        {
            "category":"Wholesale",
            "subcategory":"Machinery & Supplies",
            "type":"Manufacturing & Wholesale Goods"
        }
    ],
    "sg:phone":"+1 815 936 9682",
    "sg:postcode":"60914",
    "sg:province":"IL",
    "sg:tags":[
        "equipment",
        "establishment"
    ],
    "wof:name":"Elgon Midwest Beauty Systems",
    "wof:placetype":"venue"
},
  "geometry": {"coordinates":[-87.855092,41.177308],"type":"Point"}
}