{
  "type": "Feature",
  "properties": {
    "addr:full":"6300 N River Rd Des Plaines IL 60018",
    "addr:housenumber":"6300",
    "addr:postcode":"60018",
    "addr:street":"N River Rd Des",
    "iso:country":"US",
    "sg:address":"6300 N River Rd",
    "sg:city":"Des Plaines",
    "sg:classifiers":[
        {
            "category":"Organizations",
            "subcategory":"Professional Association",
            "type":"Services"
        }
    ],
    "sg:phone":"+1 847 698 9980",
    "sg:postcode":"60018",
    "sg:province":"IL",
    "sg:tags":[
        "research"
    ],
    "wof:name":"Oref",
    "wof:placetype":"venue"
},
  "geometry": {"coordinates":[-87.860973,41.993599],"type":"Point"}
}