{
  "type": "Feature",
  "properties": {
    "iso:country":"US",
    "sg:address":"1530 Artaius Pkwy",
    "sg:city":"Libertyville",
    "sg:classifiers":[
        {
            "category":"Manufacturing",
            "subcategory":"Metals",
            "type":"Manufacturing & Wholesale Goods"
        }
    ],
    "sg:phone":"+1 847 362 8300",
    "sg:postcode":"60048",
    "sg:province":"IL",
    "sg:tags":[
        "expanded"
    ],
    "sg:website":"www.metlx.com",
    "wof:name":"Metalex Corp",
    "wof:placetype":"venue"
},
  "geometry": {"coordinates":[-87.945567,42.257752],"type":"Point"}
}