{
  "type": "Feature",
  "properties": {
    "iso:country":"US",
    "sg:address":"1255 Stanford Dr",
    "sg:city":"Kankakee",
    "sg:classifiers":[
        {
            "category":"Bus Charters",
            "type":"Transportation"
        }
    ],
    "sg:phone":"+1 815 935 8687",
    "sg:postcode":"60901",
    "sg:province":"IL",
    "sg:tags":[
        "rental"
    ],
    "wof:name":"Acme-Bus Tours",
    "wof:placetype":"venue"
},
  "geometry": {"coordinates":[-87.837665,41.137824],"type":"Point"}
}