{
  "type": "Feature",
  "properties": {
    "addr:full":"1548 Butterfield Rd Downers Grove IL 60515",
    "addr:housenumber":"1548",
    "addr:postcode":"60515",
    "addr:street":"Butterfield Rd",
    "iso:country":"US",
    "sg:address":"1548 Butterfield Rd",
    "sg:city":"Downers Grove",
    "sg:classifiers":[
        {
            "category":"Home & Garden",
            "subcategory":"Home Furnishings",
            "type":"Retail Goods"
        }
    ],
    "sg:phone":"+1 630 620 5530",
    "sg:postcode":"60515",
    "sg:province":"IL",
    "sg:tags":[
        "housewares"
    ],
    "sg:website":"www.bedbathandbeyond.com",
    "wof:name":"Bed Bath & Beyond Inc",
    "wof:placetype":"venue"
},
  "geometry": {"coordinates":[-88.022662,41.833943],"type":"Point"}
}