{
  "type": "Feature",
  "properties": {
    "iso:country":"US",
    "sg:address":"2110 Lorraine Ave",
    "sg:city":"Waukegan",
    "sg:classifiers":[
        {
            "category":"Real Estate",
            "subcategory":"Real Estate Operator",
            "type":"Services"
        }
    ],
    "sg:phone":"+1 847 623 0772",
    "sg:postcode":"60087",
    "sg:province":"IL",
    "sg:tags":[
        "apartment"
    ],
    "wof:name":"Foster Major Apts",
    "wof:placetype":"venue"
},
  "geometry": {"coordinates":[-87.852907,42.391939],"type":"Point"}
}