{
  "type": "Feature",
  "properties": {
    "addr:full":"1628 N Newland Ave Chicago IL 60707",
    "addr:housenumber":"1628",
    "addr:postcode":"60707",
    "addr:street":"N Newland Ave",
    "iso:country":"US",
    "sg:address":"1628 N Newland Ave",
    "sg:city":"Chicago",
    "sg:classifiers":[
        {
            "category":"Organizations",
            "subcategory":"Professional Association",
            "type":"Services"
        }
    ],
    "sg:phone":"+1 312 996 5575",
    "sg:postcode":"60707",
    "sg:province":"IL",
    "wof:name":"Maria Krysan",
    "wof:placetype":"venue"
},
  "geometry": {"coordinates":[-87.798479,41.909493],"type":"Point"}
}