{
  "type": "Feature",
  "properties": {
    "iso:country":"US",
    "sg:address":"516 18th Ave",
    "sg:city":"Rockford",
    "sg:classifiers":[
        {
            "category":"Wholesale",
            "subcategory":"Machinery & Supplies",
            "type":"Manufacturing & Wholesale Goods"
        }
    ],
    "sg:phone":"+1 815 961 5000",
    "sg:postcode":"61104",
    "sg:province":"IL",
    "sg:tags":[
        "fastener"
    ],
    "wof:name":"Commercial Solutions Sls Mktg",
    "wof:placetype":"venue"
},
  "geometry": {"coordinates":[-89.089595,42.247836],"type":"Point"}
}