{
  "type": "Feature",
  "properties": {
    "addr:full":"1640 W Hubbard St. Chicago IL 60622",
    "addr:housenumber":"1640",
    "addr:postcode":"60622",
    "addr:street":"W Hubbard",
    "iso:country":"US",
    "sg:address":"1640 W Hubbard St.",
    "sg:city":"Chicago",
    "sg:classifiers":[
        {
            "category":"Shopping",
            "subcategory":"Florist",
            "type":"Retail Goods"
        }
    ],
    "sg:phone":"+1 312 492 9930",
    "sg:postcode":"60622",
    "sg:province":"IL",
    "sg:website":"www.danielsfloral.com/",
    "wof:name":"Daniel's Discriminating Floriculture",
    "wof:placetype":"venue"
},
  "geometry": {"coordinates":[-87.668367,41.890241],"type":"Point"}
}