{
  "type": "Feature",
  "properties": {
    "addr:full":"134 N la Salle St # 1550 Chicago IL 60602",
    "addr:housenumber":"134",
    "addr:postcode":"60602",
    "addr:street":"N La Salle St # 1550",
    "iso:country":"US",
    "sg:address":"134 N la Salle St # 1550",
    "sg:city":"Chicago",
    "sg:classifiers":[
        {
            "category":"Travel",
            "subcategory":"Travel Agent",
            "type":"Entertainment"
        }
    ],
    "sg:phone":"+1 312 994 7601",
    "sg:postcode":"60602",
    "sg:province":"IL",
    "sg:tags":[
        "agency",
        "services-commercial"
    ],
    "wof:name":"Travel 100 Group Incoporated",
    "wof:placetype":"venue"
},
  "geometry": {"coordinates":[-87.632515,41.884084],"type":"Point"}
}