{
  "type": "Feature",
  "properties": {
    "iso:country":"US",
    "sg:address":"10871 Lake Rd",
    "sg:city":"Highland",
    "sg:classifiers":[
        {
            "category":"Professional",
            "subcategory":"Business Services",
            "type":"Services"
        }
    ],
    "sg:phone":"+1 618 644 5877",
    "sg:postcode":"62249",
    "sg:province":"IL",
    "wof:name":"Dave Rutz Auction Svc",
    "wof:placetype":"venue"
},
  "geometry": {"coordinates":[-89.759941,38.728665],"type":"Point"}
}