{
  "type": "Feature",
  "properties": {
    "addr:full":"5800 W Montrose Ave Chicago IL 60634",
    "addr:housenumber":"5800",
    "addr:postcode":"60634",
    "addr:street":"W Montrose Ave",
    "iso:country":"US",
    "sg:address":"5800 W Montrose Ave",
    "sg:city":"Chicago",
    "sg:classifiers":[
        {
            "category":"Bars & Pubs",
            "type":"Food & Drink"
        },
        {
            "category":"Food & Beverages",
            "subcategory":"Liquor & Beverages",
            "type":"Retail Goods"
        }
    ],
    "sg:phone":"+1 773 545 2033",
    "sg:postcode":"60634",
    "sg:province":"IL",
    "sg:tags":[
        "brew",
        "beer",
        "spirit",
        "store",
        "wine"
    ],
    "wof:name":"Menard Liquors",
    "wof:placetype":"venue"
},
  "geometry": {"coordinates":[-87.772301,41.9604],"type":"Point"}
}