{
  "type": "Feature",
  "properties": {
    "iso:country":"US",
    "sg:address":"398 W Baltimore St",
    "sg:city":"Wilmington",
    "sg:classifiers":[
        {
            "category":"Food & Beverages",
            "subcategory":"Bakery",
            "type":"Retail Goods"
        }
    ],
    "sg:phone":"+1 815 476 2483",
    "sg:postcode":"60481",
    "sg:province":"IL",
    "sg:tags":[
        "baker"
    ],
    "wof:name":"Dreamland Gifts & Bakery",
    "wof:placetype":"venue"
},
  "geometry": {"coordinates":[-88.156233,41.305195],"type":"Point"}
}