{
  "type": "Feature",
  "properties": {
    "iso:country":"US",
    "sg:address":"4822 85th St",
    "sg:city":"Kenosha",
    "sg:classifiers":[
        {
            "category":"Building & Trades",
            "subcategory":"Construction",
            "type":"Services"
        }
    ],
    "sg:phone":"+1 262 694 5129",
    "sg:postcode":"53142",
    "sg:province":"IL",
    "sg:tags":[
        "carpentry",
        "contractor"
    ],
    "wof:name":"John Nordstrum Carpt",
    "wof:placetype":"venue"
},
  "geometry": {"coordinates":[-87.864313,42.551847],"type":"Point"}
}