{
  "type": "Feature",
  "properties": {
    "iso:country":"US",
    "sg:address":"1808 Janke Dr Ste F",
    "sg:city":"Northbrook",
    "sg:classifiers":[
        {
            "category":"Building & Trades",
            "subcategory":"Electrical",
            "type":"Services"
        }
    ],
    "sg:phone":"+1 847 272 4602",
    "sg:postcode":"60062",
    "sg:province":"IL",
    "sg:tags":[
        "industrial",
        "electrician",
        "contractors-commercial",
        "electric"
    ],
    "wof:name":"Reidinger Electric Inc",
    "wof:placetype":"venue"
},
  "geometry": {"coordinates":[-87.824692,42.113869],"type":"Point"}
}