{
  "type": "Feature",
  "properties": {
    "addr:full":"608 S Hilltop Blvd Mc Henry IL 60050",
    "addr:housenumber":"608",
    "addr:postcode":"60050",
    "addr:street":"S Hilltop Blvd Mc Henry",
    "iso:country":"US",
    "sg:address":"608 S Hilltop Blvd",
    "sg:city":"Mc Henry",
    "sg:classifiers":[
        {
            "category":"Social Services",
            "subcategory":"Child Care",
            "type":"Services"
        }
    ],
    "sg:phone":"+1 815 344 3309",
    "sg:postcode":"60050",
    "sg:province":"IL",
    "sg:tags":[
        "day"
    ],
    "wof:name":"Sandra Rigsby",
    "wof:placetype":"venue"
},
  "geometry": {"coordinates":[-88.262012,42.319675],"type":"Point"}
}