{
  "type": "Feature",
  "properties": {
    "iso:country":"US",
    "sg:address":"9400 S Cicero Ave Ste 7",
    "sg:city":"Oak Lawn",
    "sg:classifiers":[
        {
            "category":"Banks & Credit Unions",
            "subcategory":"Bank",
            "type":"Services"
        }
    ],
    "sg:phone":"+1 708 636 2112",
    "sg:postcode":"60453",
    "sg:province":"IL",
    "wof:name":"Oak Lawn National Bank",
    "wof:placetype":"venue"
},
  "geometry": {"coordinates":[-87.740799,41.722],"type":"Point"}
}