{
  "type": "Feature",
  "properties": {
    "addr:full":"521 S Main St Gifford IL 61847",
    "addr:housenumber":"521",
    "addr:postcode":"61847",
    "addr:street":"S Main St",
    "iso:country":"US",
    "sg:address":"521 S Main St",
    "sg:city":"Gifford",
    "sg:phone":"+1 217 568 7957",
    "sg:postcode":"61847",
    "sg:province":"IL",
    "sg:tags":[
        "farm",
        "corn",
        "grain",
        "cash"
    ],
    "wof:name":"Gene Severins",
    "wof:placetype":"venue"
},
  "geometry": {"coordinates":[-88.021248,40.298694],"type":"Point"}
}