{
  "type": "Feature",
  "properties": {
    "iso:country":"US",
    "sg:address":"4115 E Lincolnway",
    "sg:city":"Sterling",
    "sg:classifiers":[
        {
            "category":"Deli",
            "type":"Food & Drink"
        }
    ],
    "sg:menulink":"http://www.allmenus.com/il/sterling/127190-blimpie-subs--sandwiches/menu/",
    "sg:phone":"+1 815 564 9373",
    "sg:postcode":"61081",
    "sg:province":"IL",
    "sg:tags":[
        "wrap",
        "american",
        "sandwich"
    ],
    "wof:name":"Blimpie Subs & Sandwiches",
    "wof:placetype":"venue"
},
  "geometry": {"coordinates":[-89.653035,41.812321],"type":"Point"}
}