{
  "type": "Feature",
  "properties": {
    "iso:country":"US",
    "sg:address":"9110 Bruce Rd",
    "sg:city":"Decatur",
    "sg:classifiers":[
        {
            "category":"Home & Garden",
            "subcategory":"Building Materials",
            "type":"Retail Goods"
        },
        {
            "category":"Building & Trades",
            "subcategory":"Construction",
            "type":"Services"
        }
    ],
    "sg:phone":"+1 217 963 2988",
    "sg:postcode":"62526",
    "sg:province":"IL",
    "sg:tags":[
        "concrete-stamped",
        "decorative",
        "foundation",
        "builder",
        "contractor",
        "concrete",
        "patio"
    ],
    "wof:name":"Burnett Dary Concrete Contractor Inc",
    "wof:placetype":"venue"
},
  "geometry": {"coordinates":[-89.103916,39.85986],"type":"Point"}
}