{
  "type": "Feature",
  "properties": {
    "iso:country":"US",
    "sg:address":"3473 S King Dr",
    "sg:city":"Chicago",
    "sg:classifiers":[
        {
            "category":"Organizations",
            "subcategory":"Community Association",
            "type":"Services"
        }
    ],
    "sg:phone":"+1 773 924 7612",
    "sg:postcode":"60653",
    "sg:province":"IL",
    "sg:tags":[
        "youth"
    ],
    "wof:name":"Peace Project",
    "wof:placetype":"venue"
},
  "geometry": {"coordinates":[-87.616912,41.832609],"type":"Point"}
}