{
  "type": "Feature",
  "properties": {
    "addr:full":"1711 N Park Dr East Saint Louis IL 62204",
    "addr:housenumber":"1711",
    "addr:postcode":"62204",
    "addr:street":"N Park Dr East",
    "iso:country":"US",
    "sg:address":"1711 N Park Dr",
    "sg:city":"East Saint Louis",
    "sg:classifiers":[
        {
            "category":"Social Services",
            "subcategory":"Child Care",
            "type":"Services"
        }
    ],
    "sg:phone":"+1 618 875 1343",
    "sg:postcode":"62204",
    "sg:province":"IL",
    "sg:tags":[
        "day"
    ],
    "wof:name":"Vallie A Warrick",
    "wof:placetype":"venue"
},
  "geometry": {"coordinates":[-90.117372,38.633247],"type":"Point"}
}