{
  "type": "Feature",
  "properties": {
    "addr:full":"6122 N Drake Ave Chicago IL 60659",
    "addr:housenumber":"6122",
    "addr:postcode":"60659",
    "addr:street":"N Drake Ave",
    "iso:country":"US",
    "sg:address":"6122 N Drake Ave",
    "sg:city":"Chicago",
    "sg:classifiers":[
        {
            "category":"Wholesale",
            "subcategory":"Sporting Goods",
            "type":"Manufacturing & Wholesale Goods"
        }
    ],
    "sg:phone":"+1 773 478 9033",
    "sg:postcode":"60659",
    "sg:province":"IL",
    "sg:tags":[
        "equipment",
        "rep",
        "mfg",
        "fitness"
    ],
    "wof:name":"Igm Inc",
    "wof:placetype":"venue"
},
  "geometry": {"coordinates":[-87.71780699999999,41.993364],"type":"Point"}
}