{
  "type": "Feature",
  "properties": {
    "addr:full":"5554 N Winthrop Ave Chicago IL 60640",
    "addr:housenumber":"5554",
    "addr:postcode":"60640",
    "addr:street":"N Winthrop Ave",
    "iso:country":"US",
    "sg:address":"5554 N Winthrop Ave",
    "sg:city":"Chicago",
    "sg:classifiers":[
        {
            "category":"Professional",
            "subcategory":"Art Services",
            "type":"Services"
        },
        {
            "category":"Shopping",
            "subcategory":"Crafts & Fabrics",
            "type":"Retail Goods"
        }
    ],
    "sg:phone":"+1 773 334 5333",
    "sg:postcode":"60640",
    "sg:province":"IL",
    "sg:tags":[
        "picture",
        "frame"
    ],
    "wof:name":"Wall To Wall Framing",
    "wof:placetype":"venue"
},
  "geometry": {"coordinates":[-87.65821200000001,41.983386],"type":"Point"}
}