{
  "type": "Feature",
  "properties": {
    "addr:full":"1028 N Honore St Chicago IL 60622",
    "addr:housenumber":"1028",
    "addr:postcode":"60622",
    "addr:street":"N Honore St",
    "iso:country":"US",
    "sg:address":"1028 N Honore St",
    "sg:city":"Chicago",
    "sg:classifiers":[
        {
            "category":"Retail",
            "subcategory":"Repair Shop",
            "type":"Services"
        }
    ],
    "sg:phone":"+1 773 342 1721",
    "sg:postcode":"60622",
    "sg:province":"IL",
    "sg:tags":[
        "vinyl"
    ],
    "wof:name":"Bill Bosco Furniture Se",
    "wof:placetype":"venue"
},
  "geometry": {"coordinates":[-87.673492,41.900113],"type":"Point"}
}