{
  "type": "Feature",
  "properties": {
    "addr:full":"3219 Fiday Rd Joliet IL 60431",
    "addr:housenumber":"3219",
    "addr:postcode":"60431",
    "addr:street":"Fiday Rd",
    "iso:country":"US",
    "sg:address":"3219 Fiday Rd",
    "sg:city":"Joliet",
    "sg:classifiers":[
        {
            "category":"Health Services",
            "subcategory":"Chiropractor",
            "type":"Services"
        }
    ],
    "sg:phone":"+1 815 730 3661",
    "sg:postcode":"60431",
    "sg:province":"IL",
    "sg:tags":[
        "chiropractic"
    ],
    "wof:name":"Perrin Family Chiropractic",
    "wof:placetype":"venue"
},
  "geometry": {"coordinates":[-88.163319,41.558242],"type":"Point"}
}