{
  "type": "Feature",
  "properties": {
    "iso:country":"US",
    "sg:address":"26 Highview Ln",
    "sg:city":"Belleville",
    "sg:classifiers":[
        {
            "category":"Freight",
            "type":"Transportation"
        }
    ],
    "sg:phone":"+1 618 397 9360",
    "sg:postcode":"62223",
    "sg:province":"IL",
    "sg:tags":[
        "terminal",
        "truck",
        "facility"
    ],
    "wof:name":"Looms Transfer Inc",
    "wof:placetype":"venue"
},
  "geometry": {"coordinates":[-90.038618,38.579371],"type":"Point"}
}