{
  "type": "Feature",
  "properties": {
    "iso:country":"US",
    "sg:address":"520 Cooley Ave",
    "sg:city":"Savanna",
    "sg:classifiers":[
        {
            "category":"Sports & Exercise",
            "subcategory":"Bowling",
            "type":"Entertainment"
        }
    ],
    "sg:phone":"+1 815 273 2723",
    "sg:postcode":"61074",
    "sg:province":"IL",
    "sg:tags":[
        "center"
    ],
    "wof:name":"Van Haelst Bowling Svc",
    "wof:placetype":"venue"
},
  "geometry": {"coordinates":[-90.15512,42.096335],"type":"Point"}
}