{
  "type": "Feature",
  "properties": {
    "addr:full":"743 W Irving Park Rd Chicago IL 60613",
    "addr:housenumber":"743",
    "addr:postcode":"60613",
    "addr:street":"W Irving Park Rd",
    "iso:country":"US",
    "sg:address":"743 W Irving Park Rd",
    "sg:city":"Chicago",
    "sg:classifiers":[
        {
            "category":"Deli",
            "type":"Food & Drink"
        },
        {
            "category":"Food & Beverages",
            "subcategory":"Groceries & Convenience Stores",
            "type":"Retail Goods"
        }
    ],
    "sg:phone":"+1 773 248 8580",
    "sg:postcode":"60613",
    "sg:province":"IL",
    "wof:name":"Goodies Deli",
    "wof:placetype":"venue"
},
  "geometry": {"coordinates":[-87.64925700000001,41.954234],"type":"Point"}
}