{
  "type": "Feature",
  "properties": {
    "addr:full":"1523 N Aurora Rd Naperville IL 60563",
    "addr:housenumber":"1523",
    "addr:postcode":"60563",
    "addr:street":"N Aurora Rd",
    "iso:country":"US",
    "sg:address":"1523 N Aurora Rd",
    "sg:city":"Naperville",
    "sg:classifiers":[
        {
            "category":"Coffee & Tea",
            "type":"Food & Drink"
        }
    ],
    "sg:menulink":"http://www.allmenus.com/il/naperville/221130-caribou-coffee/menu/",
    "sg:phone":"+1 630 961 1018",
    "sg:postcode":"60563",
    "sg:province":"IL",
    "sg:tags":[
        "american",
        "diner"
    ],
    "wof:name":"Caribou Coffee",
    "wof:placetype":"venue"
},
  "geometry": {"coordinates":[-88.185501,41.779903],"type":"Point"}
}