{
  "type": "Feature",
  "properties": {
    "addr:full":"1026 N McLean Blvd Elgin IL 60123",
    "addr:housenumber":"1026",
    "addr:postcode":"60123",
    "addr:street":"N Mclean Blvd",
    "iso:country":"US",
    "sg:address":"1026 N McLean Blvd",
    "sg:city":"Elgin",
    "sg:classifiers":[
        {
            "category":"Banks & Credit Unions",
            "subcategory":"Investment Brokerage",
            "type":"Services"
        }
    ],
    "sg:phone":"+1 847 741 2670",
    "sg:postcode":"60123",
    "sg:province":"IL",
    "sg:tags":[
        "stock",
        "bond"
    ],
    "wof:name":"Edward Jones Co",
    "wof:placetype":"venue"
},
  "geometry": {"coordinates":[-88.31451300000001,42.015116],"type":"Point"}
}