{
  "type": "Feature",
  "properties": {
    "addr:full":"1501 E McCord St Centralia IL 62801",
    "addr:housenumber":"1501",
    "addr:postcode":"62801",
    "addr:street":"E Mccord St",
    "iso:country":"US",
    "sg:address":"1501 E McCord St",
    "sg:city":"Centralia",
    "sg:classifiers":[
        {
            "category":"Real Estate",
            "subcategory":"Real Estate Agent",
            "type":"Services"
        }
    ],
    "sg:phone":"+1 618 532 4755",
    "sg:postcode":"62801",
    "sg:province":"IL",
    "wof:name":"Don Geary Realty Inc",
    "wof:placetype":"venue"
},
  "geometry": {"coordinates":[-89.11260299999999,38.52523],"type":"Point"}
}