{
  "type": "Feature",
  "properties": {
    "iso:country":"US",
    "sg:address":"2221 64th St",
    "sg:city":"Woodridge",
    "sg:classifiers":[
        {
            "category":"Restaurant",
            "type":"Food & Drink"
        }
    ],
    "sg:phone":"+1 630 960 2890",
    "sg:postcode":"60517",
    "sg:province":"IL",
    "wof:name":"Canteen Corp",
    "wof:placetype":"venue"
},
  "geometry": {"coordinates":[-88.037762,41.769417],"type":"Point"}
}