{
  "type": "Feature",
  "properties": {
    "iso:country":"US",
    "sg:address":"10615 Aviston Rd",
    "sg:city":"Germantown",
    "sg:classifiers":[
        {
            "category":"Building & Trades",
            "subcategory":"Construction",
            "type":"Services"
        }
    ],
    "sg:phone":"+1 618 228 7635",
    "sg:postcode":"62245",
    "sg:province":"IL",
    "sg:tags":[
        "residential",
        "contractor"
    ],
    "wof:name":"Kreitner Construction Co",
    "wof:placetype":"venue"
},
  "geometry": {"coordinates":[-89.61209700000001,38.577214],"type":"Point"}
}