{
  "type": "Feature",
  "properties": {
    "iso:country":"US",
    "sg:address":"61 N California Ave",
    "sg:city":"Mundelein",
    "sg:classifiers":[
        {
            "category":"Professional",
            "subcategory":"Business Services",
            "type":"Services"
        }
    ],
    "sg:phone":"+1 847 566 3129",
    "sg:postcode":"60060",
    "sg:province":"IL",
    "wof:name":"Moilanen Enterprise",
    "wof:placetype":"venue"
},
  "geometry": {"coordinates":[-88.01381000000001,42.263897],"type":"Point"}
}