{
  "type": "Feature",
  "properties": {
    "addr:full":"10330 S Hamilton Ave Chicago IL 60643",
    "addr:housenumber":"10330",
    "addr:postcode":"60643",
    "addr:street":"S Hamilton Ave",
    "iso:country":"US",
    "sg:address":"10330 S Hamilton Ave",
    "sg:city":"Chicago",
    "sg:classifiers":[
        {
            "category":"Shopping",
            "subcategory":"Gifts & Souvenirs",
            "type":"Retail Goods"
        }
    ],
    "sg:phone":"+1   ",
    "sg:postcode":"60643",
    "sg:province":"IL",
    "wof:name":"Gifts By Design Inc",
    "wof:placetype":"venue"
},
  "geometry": {"coordinates":[-87.67559900000001,41.7052],"type":"Point"}
}