{
  "type": "Feature",
  "properties": {
    "addr:full":"2250 N Lincoln Avenue Chicago IL 60614",
    "addr:housenumber":"2250",
    "addr:postcode":"60614",
    "addr:street":"N Lincoln Avenue",
    "iso:country":"US",
    "sg:address":"2250 N Lincoln Avenue",
    "sg:city":"Chicago",
    "sg:classifiers":[
        {
            "category":"Real Estate",
            "subcategory":"Real Estate Services",
            "type":"Services"
        }
    ],
    "sg:phone":"+1 773 348 5839",
    "sg:postcode":"60614",
    "sg:province":"IL",
    "sg:tags":[
        "management",
        "property"
    ],
    "wof:name":"Sabovic Z H Management",
    "wof:placetype":"venue"
},
  "geometry": {"coordinates":[-87.64505200000001,41.922773],"type":"Point"}
}