{
  "type": "Feature",
  "properties": {
    "iso:country":"US",
    "sg:address":"6120 Pershing Ave",
    "sg:city":"Downers Grove",
    "sg:classifiers":[
        {
            "category":"Building & Trades",
            "subcategory":"Construction",
            "type":"Services"
        }
    ],
    "sg:phone":"+1 800 491 0505",
    "sg:postcode":"60516",
    "sg:province":"IL",
    "sg:tags":[
        "house"
    ],
    "wof:name":"Eklund Services Inc",
    "wof:placetype":"venue"
},
  "geometry": {"coordinates":[-88.034345,41.772947],"type":"Point"}
}