{
  "type": "Feature",
  "properties": {
    "iso:country":"US",
    "sg:address":"19139 Center Ave",
    "sg:city":"Homewood",
    "sg:classifiers":[
        {
            "category":"Government",
            "subcategory":"Fire Station",
            "type":"Public Place"
        },
        {
            "category":"Retail",
            "subcategory":"Laundry & Dry Cleaning",
            "type":"Services"
        },
        {
            "category":"Building & Trades",
            "subcategory":"Cleaning & Sanitation",
            "type":"Services"
        }
    ],
    "sg:phone":"+1 708 816 9100",
    "sg:postcode":"60430",
    "sg:province":"IL",
    "sg:tags":[
        "cleaner",
        "disaster",
        "recovery",
        "damage",
        "rug",
        "water",
        "restoration",
        "relief",
        "carpet"
    ],
    "sg:website":"http://local.puroclean.com/Water-Damage-in-Chicago-IL/783",
    "wof:name":"Puroclean",
    "wof:placetype":"venue"
},
  "geometry": {"coordinates":[-87.64554,41.541333],"type":"Point"}
}