{
  "type": "Feature",
  "properties": {
    "iso:country":"US",
    "sg:address":"8612 Lawndale Ave",
    "sg:city":"Skokie",
    "sg:classifiers":[
        {
            "category":"Building & Trades",
            "subcategory":"Construction",
            "type":"Services"
        }
    ],
    "sg:phone":"+1 773 619 6925",
    "sg:postcode":"60076",
    "sg:province":"IL",
    "sg:tags":[
        "resurfacing",
        "refinishing",
        "floor"
    ],
    "wof:name":"Dino's Flooring",
    "wof:placetype":"venue"
},
  "geometry": {"coordinates":[-87.720691,42.037922],"type":"Point"}
}