{
  "type": "Feature",
  "properties": {
    "iso:country":"US",
    "sg:address":"4207 W Cermak Rd",
    "sg:city":"Chicago",
    "sg:classifiers":[
        {
            "category":"Food & Beverages",
            "subcategory":"Bakery",
            "type":"Retail Goods"
        }
    ],
    "sg:phone":"+1 773 277 8220",
    "sg:postcode":"60623",
    "sg:province":"IL",
    "sg:tags":[
        "sandwich"
    ],
    "wof:name":"Jezzie Pearl's Sandwich & Snack Shop",
    "wof:placetype":"venue"
},
  "geometry": {"coordinates":[-87.729804,41.851269],"type":"Point"}
}