{
  "type": "Feature",
  "properties": {
    "iso:country":"US",
    "sg:address":"4211 Avenue of the Cities",
    "sg:city":"Moline",
    "sg:classifiers":[
        {
            "category":"Personal",
            "subcategory":"Nail Salon",
            "type":"Services"
        }
    ],
    "sg:phone":"+1 309 762 3558",
    "sg:postcode":"61265",
    "sg:province":"IL",
    "wof:name":"California Nails",
    "wof:placetype":"venue"
},
  "geometry": {"coordinates":[-90.476501,41.490101],"type":"Point"}
}