{
  "type": "Feature",
  "properties": {
    "addr:full":"101 Fox Creek Rd Belleville IL 62223",
    "addr:housenumber":"101",
    "addr:postcode":"62223",
    "addr:street":"Fox Creek Rd",
    "iso:country":"US",
    "sg:address":"101 Fox Creek Rd",
    "sg:city":"Belleville",
    "sg:classifiers":[
        {
            "category":"Shopping",
            "type":"Retail Goods"
        }
    ],
    "sg:phone":"+1   ",
    "sg:postcode":"62223",
    "sg:province":"IL",
    "sg:tags":[
        "merchandise"
    ],
    "wof:name":"Ears 2u Hearing Center",
    "wof:placetype":"venue"
},
  "geometry": {"coordinates":[-90.035889,38.562234],"type":"Point"}
}