{
  "type": "Feature",
  "properties": {
    "addr:full":"550 E Business Center Dr Mount Prospect IL 60056",
    "addr:housenumber":"550",
    "addr:postcode":"60056",
    "addr:street":"E Business Center Dr",
    "iso:country":"US",
    "sg:address":"550 E Business Center Dr",
    "sg:city":"Mount Prospect",
    "sg:classifiers":[
        {
            "category":"Social Services",
            "type":"Services"
        }
    ],
    "sg:phone":"+1 847 759 0679",
    "sg:postcode":"60056",
    "sg:province":"IL",
    "wof:name":"Greatr Wheelng Yth Outrch",
    "wof:placetype":"venue"
},
  "geometry": {"coordinates":[-87.925443,42.076585],"type":"Point"}
}