{
  "type": "Feature",
  "properties": {
    "addr:full":"327 N Logan St Mattoon IL 61938",
    "addr:housenumber":"327",
    "addr:postcode":"61938",
    "addr:street":"N Logan St",
    "iso:country":"US",
    "sg:address":"327 N Logan St",
    "sg:city":"Mattoon",
    "sg:classifiers":[
        {
            "category":"Autos & Motor Vehicles",
            "subcategory":"Automobile Sales",
            "type":"Retail Goods"
        }
    ],
    "sg:phone":"+1   ",
    "sg:postcode":"61938",
    "sg:province":"IL",
    "sg:tags":[
        "home",
        "recreational"
    ],
    "wof:name":"Cross County Motors & Rv Ctr",
    "wof:placetype":"venue"
},
  "geometry": {"coordinates":[-88.350296,39.48652],"type":"Point"}
}