{
  "type": "Feature",
  "properties": {
    "iso:country":"US",
    "sg:address":"200 Turner Dr",
    "sg:city":"Rantoul",
    "sg:classifiers":[
        {
            "category":"Professional",
            "subcategory":"Advertising",
            "type":"Services"
        },
        {
            "category":"Shopping",
            "subcategory":"Crafts & Fabrics",
            "type":"Retail Goods"
        },
        {
            "category":"Professional",
            "subcategory":"Printing & Photocopies",
            "type":"Services"
        }
    ],
    "sg:phone":"+1 217 892 2960",
    "sg:postcode":"61866",
    "sg:province":"IL",
    "sg:tags":[
        "shop",
        "sample",
        "product",
        "service-circular",
        "screen",
        "specialty",
        "distributing",
        "advertising-promotional"
    ],
    "sg:website":"http://www.creativevisionsltd.com",
    "wof:name":"Creative Visions, Ltd.",
    "wof:placetype":"venue"
},
  "geometry": {"coordinates":[-88.20771000000001,40.311779],"type":"Point"}
}