{
  "type": "Feature",
  "properties": {
    "addr:full":"1014 N Mason Ave Chicago IL 60651",
    "addr:housenumber":"1014",
    "addr:postcode":"60651",
    "addr:street":"N Mason Ave",
    "iso:country":"US",
    "sg:address":"1014 N Mason Ave",
    "sg:city":"Chicago",
    "sg:classifiers":[
        {
            "category":"Organizations",
            "subcategory":"Religious Organization",
            "type":"Services"
        }
    ],
    "sg:phone":"+1 773 287 3734",
    "sg:postcode":"60651",
    "sg:province":"IL",
    "wof:name":"Greater Works Ministries",
    "wof:placetype":"venue"
},
  "geometry": {"coordinates":[-87.774117,41.898537],"type":"Point"}
}