{
  "type": "Feature",
  "properties": {
    "iso:country":"US",
    "sg:address":"624 Orland Square Dr",
    "sg:city":"Orland Park",
    "sg:classifiers":[
        {
            "category":"Shopping",
            "subcategory":"Clothing, Apparel, & Fashions",
            "type":"Retail Goods"
        }
    ],
    "sg:phone":"+1   ",
    "sg:postcode":"60462",
    "sg:province":"IL",
    "sg:tags":[
        "high",
        "dress",
        "sportswear"
    ],
    "wof:name":"Cache",
    "wof:placetype":"venue"
},
  "geometry": {"coordinates":[-87.851216,41.618444],"type":"Point"}
}