{
  "type": "Feature",
  "properties": {
    "iso:country":"US",
    "sg:address":"2023 Highway 104",
    "sg:city":"Liberty",
    "sg:classifiers":[
        {
            "category":"Farming",
            "subcategory":"Livestock Farm",
            "type":"Manufacturing & Wholesale Goods"
        },
        {
            "category":"Farming",
            "subcategory":"Farm",
            "type":"Manufacturing & Wholesale Goods"
        }
    ],
    "sg:phone":"+1 217 645 3891",
    "sg:postcode":"62347",
    "sg:province":"IL",
    "sg:tags":[
        "ranch"
    ],
    "wof:name":"Ronald Barry",
    "wof:placetype":"venue"
},
  "geometry": {"coordinates":[-91.105148,39.87495],"type":"Point"}
}