{
  "type": "Feature",
  "properties": {
    "addr:full":"17 N Grove Ave Elgin IL 60120",
    "addr:housenumber":"17",
    "addr:postcode":"60120",
    "addr:street":"N Grove Ave",
    "iso:country":"US",
    "sg:address":"17 N Grove Ave",
    "sg:city":"Elgin",
    "sg:classifiers":[
        {
            "category":"Shopping",
            "subcategory":"Florist",
            "type":"Retail Goods"
        }
    ],
    "sg:phone":"+1 847 488 1443",
    "sg:postcode":"60120",
    "sg:province":"IL",
    "wof:name":"Bleu Delph LTD",
    "wof:placetype":"venue"
},
  "geometry": {"coordinates":[-88.284853,42.037885],"type":"Point"}
}