{
  "type": "Feature",
  "properties": {
    "addr:full":"2068 N Milwaukee Ave Chicago IL 60647",
    "addr:housenumber":"2068",
    "addr:postcode":"60647",
    "addr:street":"N Milwaukee Ave",
    "iso:country":"US",
    "sg:address":"2068 N Milwaukee Ave",
    "sg:city":"Chicago",
    "sg:classifiers":[
        {
            "category":"Home & Garden",
            "subcategory":"Furniture",
            "type":"Retail Goods"
        }
    ],
    "sg:phone":"+1 773 227 8566",
    "sg:postcode":"60647",
    "sg:province":"IL",
    "sg:tags":[
        "store"
    ],
    "wof:name":"Velazquez Furniture",
    "wof:placetype":"venue"
},
  "geometry": {"coordinates":[-87.69029999999999,41.9188],"type":"Point"}
}