{
  "type": "Feature",
  "properties": {
    "iso:country":"US",
    "sg:address":"10429 Brookridge Creek Dr",
    "sg:city":"Frankfort",
    "sg:classifiers":[
        {
            "category":"Retail",
            "subcategory":"Portrait Studio",
            "type":"Services"
        }
    ],
    "sg:phone":"+1 815 464 6688",
    "sg:postcode":"60423",
    "sg:province":"IL",
    "sg:tags":[
        "photographer"
    ],
    "wof:name":"Kelly Photography",
    "wof:placetype":"venue"
},
  "geometry": {"coordinates":[-87.870344,41.502984],"type":"Point"}
}