{
  "type": "Feature",
  "properties": {
    "iso:country":"US",
    "sg:address":"600 W Fullerton Pkwy",
    "sg:city":"Chicago",
    "sg:phone":"+1 773 248 8288",
    "sg:postcode":"60614",
    "sg:province":"IL",
    "wof:name":"Lincoln Park Presbyterian Church",
    "wof:placetype":"venue"
},
  "geometry": {"coordinates":[-87.643929,41.925491],"type":"Point"}
}