{
  "type": "Feature",
  "properties": {
    "iso:country":"US",
    "sg:address":"1302 Pines Rd",
    "sg:city":"Oregon",
    "sg:classifiers":[
        {
            "category":"Professional",
            "subcategory":"Business Services",
            "type":"Services"
        }
    ],
    "sg:phone":"+1 815 732 2492",
    "sg:postcode":"61061",
    "sg:province":"IL",
    "sg:tags":[
        "license"
    ],
    "wof:name":"Drivers License Examining Stn",
    "wof:placetype":"venue"
},
  "geometry": {"coordinates":[-89.342655,42.004308],"type":"Point"}
}