{
  "type": "Feature",
  "properties": {
    "addr:full":"6052 W 63rd Street Chicago IL 60638",
    "addr:housenumber":"6052",
    "addr:postcode":"60638",
    "addr:street":"W 63Rd Street",
    "iso:country":"US",
    "sg:address":"6052 W 63rd Street",
    "sg:city":"Chicago",
    "sg:classifiers":[
        {
            "category":"Professional",
            "subcategory":"Lawyer & Legal Services",
            "type":"Services"
        }
    ],
    "sg:phone":"+1 773 788 0800",
    "sg:postcode":"60638",
    "sg:province":"IL",
    "wof:name":"Kowalczyk Thaddeus S",
    "wof:placetype":"venue"
},
  "geometry": {"coordinates":[-87.773358,41.777905],"type":"Point"}
}