{
  "type": "Feature",
  "properties": {
    "iso:country":"US",
    "sg:address":"441 South Blvd",
    "sg:city":"Chicago",
    "sg:classifiers":[
        {
            "category":"Sports & Exercise",
            "subcategory":"Gym",
            "type":"Entertainment"
        }
    ],
    "sg:phone":"+1 866 966 3966",
    "sg:postcode":"60302",
    "sg:province":"IL",
    "sg:tags":[
        "trainer"
    ],
    "sg:website":"www.bulldog-crossfit.com",
    "wof:name":"Bulldog CrossFit",
    "wof:placetype":"venue"
},
  "geometry": {"coordinates":[-87.787003,41.886934],"type":"Point"}
}