{
  "type": "Feature",
  "properties": {
    "iso:country":"US",
    "sg:address":"7733 161st St",
    "sg:city":"Tinley Park",
    "sg:classifiers":[
        {
            "category":"Building & Trades",
            "subcategory":"Construction",
            "type":"Services"
        }
    ],
    "sg:phone":"+1 708 444 8520",
    "sg:postcode":"60477",
    "sg:province":"IL",
    "sg:tags":[
        "siding",
        "contractor"
    ],
    "wof:name":"Elite Siding",
    "wof:placetype":"venue"
},
  "geometry": {"coordinates":[-87.805319,41.598171],"type":"Point"}
}