{
  "type": "Feature",
  "properties": {
    "iso:country":"US",
    "sg:address":"3471 N Elston Ave",
    "sg:city":"Chicago",
    "sg:phone":"+1 773 583 3066",
    "sg:postcode":"60618",
    "sg:province":"IL",
    "wof:name":"Chief O'Neill's Pub",
    "wof:placetype":"venue"
},
  "geometry": {"coordinates":[-87.705299,41.944199],"type":"Point"}
}