{
  "type": "Feature",
  "properties": {
    "iso:country":"US",
    "sg:address":"1222 Gail Dr",
    "sg:city":"Buffalo Grove",
    "sg:classifiers":[
        {
            "category":"Professional",
            "type":"Services"
        }
    ],
    "sg:phone":"+1 847 913 8280",
    "sg:postcode":"60089",
    "sg:province":"IL",
    "wof:name":"Wendy W Perchonok",
    "wof:placetype":"venue"
},
  "geometry": {"coordinates":[-87.972474,42.172616],"type":"Point"}
}