{
  "type": "Feature",
  "properties": {
    "iso:country":"US",
    "sg:address":"2222 Westcourse Dr",
    "sg:city":"Riverwoods",
    "sg:classifiers":[
        {
            "category":"Real Estate",
            "subcategory":"Real Estate Agent",
            "type":"Services"
        }
    ],
    "sg:phone":"+1 847 267 9192",
    "sg:postcode":"60015",
    "sg:province":"IL",
    "wof:name":"Home Plus Inc",
    "wof:placetype":"venue"
},
  "geometry": {"coordinates":[-87.885999,42.184866],"type":"Point"}
}