{
  "type": "Feature",
  "properties": {
    "iso:country":"US",
    "sg:address":"3815 N Mulford Rd",
    "sg:city":"Rockford",
    "sg:classifiers":[
        {
            "category":"Real Estate",
            "subcategory":"Real Estate Agent",
            "type":"Services"
        }
    ],
    "sg:phone":"+1 815 282 2222",
    "sg:postcode":"61114",
    "sg:province":"IL",
    "sg:website":"www.gambinorealtors.com",
    "wof:name":"Gambino Realty",
    "wof:placetype":"venue"
},
  "geometry": {"coordinates":[-88.999489,42.318494],"type":"Point"}
}