{
  "type": "Feature",
  "properties": {
    "iso:country":"US",
    "sg:address":"7017 W North Ave",
    "sg:city":"Oak Park",
    "sg:classifiers":[
        {
            "category":"Shopping",
            "subcategory":"Clothing, Apparel, & Fashions",
            "type":"Retail Goods"
        }
    ],
    "sg:phone":"+1 708 445 7000",
    "sg:postcode":"60302",
    "sg:province":"IL",
    "sg:tags":[
        "children's",
        "clothing"
    ],
    "sg:website":"www.shopgagagirls.com",
    "wof:name":"Ga-Ga Girls Boutique",
    "wof:placetype":"venue"
},
  "geometry": {"coordinates":[-87.80188099999999,41.908434],"type":"Point"}
}