{
  "type": "Feature",
  "properties": {
    "iso:country":"US",
    "sg:address":"1109 Richard Dr",
    "sg:city":"Cahokia",
    "sg:classifiers":[
        {
            "category":"Real Estate",
            "subcategory":"Real Estate Agent",
            "type":"Services"
        }
    ],
    "sg:phone":"+1 618 337 4042",
    "sg:postcode":"62206",
    "sg:province":"IL",
    "sg:tags":[
        "management"
    ],
    "wof:name":"Muhajars Properties",
    "wof:placetype":"venue"
},
  "geometry": {"coordinates":[-90.170208,38.563623],"type":"Point"}
}