{
  "type": "Feature",
  "properties": {
    "iso:country":"US",
    "sg:address":"519 W Madison St",
    "sg:city":"Ottawa",
    "sg:classifiers":[
        {
            "category":"Social Services",
            "type":"Services"
        }
    ],
    "sg:phone":"+1 815 431 0155",
    "sg:postcode":"61350",
    "sg:province":"IL",
    "sg:tags":[
        "organization",
        "welfare"
    ],
    "wof:name":"Community Food Basket",
    "wof:placetype":"venue"
},
  "geometry": {"coordinates":[-88.84762600000001,41.346736],"type":"Point"}
}