{
  "type": "Feature",
  "properties": {
    "iso:country":"US",
    "sg:address":"331 Cherrywood Ct",
    "sg:city":"Vernon Hills",
    "sg:classifiers":[
        {
            "category":"Shopping",
            "subcategory":"Computers & Home Electronics",
            "type":"Retail Goods"
        }
    ],
    "sg:phone":"+1 847 680 2282",
    "sg:postcode":"60061",
    "sg:province":"IL",
    "sg:tags":[
        "equipment",
        "satellite",
        "system"
    ],
    "wof:name":"Dish Network Installations",
    "wof:placetype":"venue"
},
  "geometry": {"coordinates":[-87.972604,42.22922],"type":"Point"}
}