{
  "type": "Feature",
  "properties": {
    "addr:full":"2846 N Lotus Ave Chicago IL 60641",
    "addr:housenumber":"2846",
    "addr:postcode":"60641",
    "addr:street":"N Lotus Ave",
    "iso:country":"US",
    "sg:address":"2846 N Lotus Ave",
    "sg:city":"Chicago",
    "sg:classifiers":[
        {
            "category":"Personal",
            "type":"Services"
        },
        {
            "category":"Building & Trades",
            "subcategory":"Cleaning & Sanitation",
            "type":"Services"
        },
        {
            "category":"Retail",
            "subcategory":"Laundry & Dry Cleaning",
            "type":"Services"
        }
    ],
    "sg:phone":"+1 773 205 7245",
    "sg:postcode":"60641",
    "sg:province":"IL",
    "sg:tags":[
        "cleaner",
        "maids'",
        "butlers'",
        "home",
        "janitorial"
    ],
    "wof:name":"Vera's House Cleaning Service",
    "wof:placetype":"venue"
},
  "geometry": {"coordinates":[-87.762398,41.932899],"type":"Point"}
}