{
  "type": "Feature",
  "properties": {
    "iso:country":"US",
    "sg:address":"2563 State Rte 96",
    "sg:city":"Ursa",
    "sg:phone":"+1 217 985 4818",
    "sg:postcode":"62376",
    "sg:province":"IL",
    "sg:tags":[
        "farm",
        "corn",
        "soybean"
    ],
    "wof:name":"Brad Seald",
    "wof:placetype":"venue"
},
  "geometry": {"coordinates":[-91.365877,40.134148],"type":"Point"}
}