{
  "type": "Feature",
  "properties": {
    "addr:full":"905 Ward St Urbana IL 61802",
    "addr:housenumber":"905",
    "addr:postcode":"61802",
    "addr:street":"Ward St",
    "iso:country":"US",
    "sg:address":"905 Ward St",
    "sg:city":"Urbana",
    "sg:classifiers":[
        {
            "category":"Personal",
            "type":"Services"
        },
        {
            "category":"Retail",
            "subcategory":"Auto Repair",
            "type":"Services"
        }
    ],
    "sg:phone":"+1 217 367 7888",
    "sg:postcode":"61802",
    "sg:province":"IL",
    "sg:tags":[
        "towing"
    ],
    "wof:name":"Feldkamp Tim",
    "wof:placetype":"venue"
},
  "geometry": {"coordinates":[-88.19297,40.120698],"type":"Point"}
}