{
  "type": "Feature",
  "properties": {
    "iso:country":"US",
    "sg:address":"1003 Waterford Cut",
    "sg:city":"Crystal Lake",
    "sg:classifiers":[
        {
            "category":"Wholesale",
            "subcategory":"Non-durable Goods",
            "type":"Manufacturing & Wholesale Goods"
        }
    ],
    "sg:phone":"+1 815 788 9676",
    "sg:postcode":"60014",
    "sg:province":"IL",
    "sg:tags":[
        "herb"
    ],
    "wof:name":"Herbal Solutions",
    "wof:placetype":"venue"
},
  "geometry": {"coordinates":[-88.35731,42.211291],"type":"Point"}
}