{
  "type": "Feature",
  "properties": {
    "addr:full":"1776 Joliet Rd Romeoville IL 60446",
    "addr:housenumber":"1776",
    "addr:postcode":"60446",
    "addr:street":"Joliet Rd",
    "iso:country":"US",
    "sg:address":"1776 Joliet Rd",
    "sg:city":"Romeoville",
    "sg:classifiers":[
        {
            "category":"Professional",
            "type":"Services"
        },
        {
            "category":"Restaurant",
            "type":"Food & Drink"
        },
        {
            "category":"Retail",
            "subcategory":"Event Space",
            "type":"Services"
        }
    ],
    "sg:phone":"+1 815 838 1500",
    "sg:postcode":"60446",
    "sg:province":"IL",
    "sg:tags":[
        "facility",
        "banquet",
        "reception",
        "caterer",
        "hall"
    ],
    "sg:website":"http://www.whitefencefarm.com",
    "wof:name":"White Fence Farm Restaurant",
    "wof:placetype":"venue"
},
  "geometry": {"coordinates":[-88.056144,41.676026],"type":"Point"}
}