{
  "type": "Feature",
  "properties": {
    "iso:country":"US",
    "sg:address":"1122 Broadway",
    "sg:city":"Highland",
    "sg:classifiers":[
        {
            "category":"Government",
            "subcategory":"Fire Station",
            "type":"Public Place"
        }
    ],
    "sg:phone":"+1 618 654 5901",
    "sg:postcode":"62249",
    "sg:province":"IL",
    "sg:tags":[
        "department",
        "township",
        "government-city",
        "village"
    ],
    "sg:website":"http://www.ci.highland.il.us/",
    "wof:name":"Highland Fire Department",
    "wof:placetype":"venue"
},
  "geometry": {"coordinates":[-89.677502,38.739404],"type":"Point"}
}