{
  "type": "Feature",
  "properties": {
    "iso:country":"US",
    "sg:address":"1125 Alexander Ct",
    "sg:city":"Cary",
    "sg:classifiers":[
        {
            "category":"Wholesale",
            "subcategory":"Machinery & Supplies",
            "type":"Manufacturing & Wholesale Goods"
        }
    ],
    "sg:phone":"+1 847 639 6372",
    "sg:postcode":"60013",
    "sg:province":"IL",
    "sg:tags":[
        "navigational",
        "lighting"
    ],
    "wof:name":"Aqua Signal Corporation",
    "wof:placetype":"venue"
},
  "geometry": {"coordinates":[-88.2732,42.220052],"type":"Point"}
}