{
  "type": "Feature",
  "properties": {
    "iso:country":"US",
    "sg:address":"265 S Prospect Ave",
    "sg:city":"Itasca",
    "sg:classifiers":[
        {
            "category":"Home & Garden",
            "subcategory":"Household Appliances",
            "type":"Retail Goods"
        },
        {
            "category":"Wholesale",
            "subcategory":"Electrical",
            "type":"Manufacturing & Wholesale Goods"
        },
        {
            "category":"Professional",
            "subcategory":"Engineering",
            "type":"Services"
        }
    ],
    "sg:phone":"+1 630 250 0337",
    "sg:postcode":"60143",
    "sg:province":"IL",
    "sg:tags":[
        "purifying",
        "system",
        "systems-wholesale",
        "equipment",
        "manufacturer",
        "air conditioning",
        "cleaning"
    ],
    "wof:name":"K Line Logistics USA Inc",
    "wof:placetype":"venue"
},
  "geometry": {"coordinates":[-87.998321,41.967713],"type":"Point"}
}