{
  "type": "Feature",
  "properties": {
    "iso:country":"US",
    "sg:address":"495 S Di Paolo Dr",
    "sg:city":"Coal City",
    "sg:classifiers":[
        {
            "category":"Travel",
            "subcategory":"Travel Agent",
            "type":"Entertainment"
        }
    ],
    "sg:phone":"+1 815 634 4007",
    "sg:postcode":"60416",
    "sg:province":"IL",
    "sg:tags":[
        "agency",
        "bureau"
    ],
    "wof:name":"Travel By Angie",
    "wof:placetype":"venue"
},
  "geometry": {"coordinates":[-88.297986,41.281926],"type":"Point"}
}