{
  "type": "Feature",
  "properties": {
    "iso:country":"US",
    "sg:address":"205 W Dundee Rd",
    "sg:city":"Buffalo Grove",
    "sg:classifiers":[
        {
            "category":"Restaurant",
            "type":"Food & Drink"
        }
    ],
    "sg:menulink":"http://www.allmenus.com/il/wheeling/21126-captn-nemos/menu/",
    "sg:phone":"+1 847 419 7687",
    "sg:postcode":"60089",
    "sg:province":"IL",
    "sg:tags":[
        "american"
    ],
    "wof:name":"Capt'n Nemo's",
    "wof:placetype":"venue"
},
  "geometry": {"coordinates":[-87.962903,42.138886],"type":"Point"}
}