{
  "type": "Feature",
  "properties": {
    "addr:full":"4144 S Archer Ave Chicago IL 60632",
    "addr:housenumber":"4144",
    "addr:postcode":"60632",
    "addr:street":"S Archer Ave",
    "iso:country":"US",
    "sg:address":"4144 S Archer Ave",
    "sg:city":"Chicago",
    "sg:classifiers":[
        {
            "category":"Arena",
            "subcategory":"Sports Club",
            "type":"Entertainment"
        }
    ],
    "sg:phone":"+1 773 843 1627",
    "sg:postcode":"60632",
    "sg:province":"IL",
    "sg:tags":[
        "martial art"
    ],
    "wof:name":"Gomez Taekwondo Center",
    "wof:placetype":"venue"
},
  "geometry": {"coordinates":[-87.697604,41.818173],"type":"Point"}
}