{
  "type": "Feature",
  "properties": {
    "addr:full":"6546 N Milwaukee Avenue Chicago IL 60631",
    "addr:housenumber":"6546",
    "addr:postcode":"60631",
    "addr:street":"N Milwaukee Avenue",
    "iso:country":"US",
    "sg:address":"6546 N Milwaukee Avenue",
    "sg:city":"Chicago",
    "sg:classifiers":[
        {
            "category":"Retail",
            "subcategory":"Auto Repair",
            "type":"Services"
        }
    ],
    "sg:phone":"+1 773 763 1213",
    "sg:postcode":"60631",
    "sg:province":"IL",
    "wof:name":"Auto Worx",
    "wof:placetype":"venue"
},
  "geometry": {"coordinates":[-87.790753,42.00079],"type":"Point"}
}