{
  "type": "Feature",
  "properties": {
    "addr:full":"95 W Madison St Waukegan IL 60085",
    "addr:housenumber":"95",
    "addr:postcode":"60085",
    "addr:street":"W Madison St",
    "iso:country":"US",
    "sg:address":"95 W Madison St",
    "sg:city":"Waukegan",
    "sg:classifiers":[
        {
            "category":"Manufacturing",
            "subcategory":"Apparel",
            "type":"Manufacturing & Wholesale Goods"
        }
    ],
    "sg:phone":"+1 847 623 7240",
    "sg:postcode":"60085",
    "sg:province":"IL",
    "wof:name":"Sail Place Inc",
    "wof:placetype":"venue"
},
  "geometry": {"coordinates":[-87.82933800000001,42.360846],"type":"Point"}
}