{
  "type": "Feature",
  "properties": {
    "addr:full":"6609 W Main St Belleville IL 62223",
    "addr:housenumber":"6609",
    "addr:postcode":"62223",
    "addr:street":"W Main St",
    "iso:country":"US",
    "sg:address":"6609 W Main St",
    "sg:city":"Belleville",
    "sg:classifiers":[
        {
            "category":"Insurance",
            "subcategory":"Title Insurance",
            "type":"Services"
        },
        {
            "category":"Professional",
            "subcategory":"Business Services",
            "type":"Services"
        }
    ],
    "sg:phone":"+1 618 397 9000",
    "sg:postcode":"62223",
    "sg:province":"IL",
    "sg:tags":[
        "appraiser",
        "real estate"
    ],
    "wof:name":"Reliable Research Co Inc",
    "wof:placetype":"venue"
},
  "geometry": {"coordinates":[-90.0431,38.556923],"type":"Point"}
}