{
  "type": "Feature",
  "properties": {
    "iso:country":"US",
    "sg:address":"800 Sherman Ave",
    "sg:city":"Evanston",
    "sg:classifiers":[
        {
            "category":"Professional",
            "subcategory":"Computer Services",
            "type":"Services"
        }
    ],
    "sg:phone":"+1 847 869 6783",
    "sg:postcode":"60202",
    "sg:province":"IL",
    "sg:tags":[
        "programming",
        "custom"
    ],
    "wof:name":"Tvo Multimedia Inc",
    "wof:placetype":"venue"
},
  "geometry": {"coordinates":[-87.682276,42.032435],"type":"Point"}
}