{
  "type": "Feature",
  "properties": {
    "addr:full":"3101 W 26th St Chicago IL 60623",
    "addr:housenumber":"3101",
    "addr:postcode":"60623",
    "addr:street":"W 26Th St",
    "iso:country":"US",
    "sg:address":"3101 W 26th St",
    "sg:city":"Chicago",
    "sg:classifiers":[
        {
            "category":"Ice Cream",
            "type":"Food & Drink"
        }
    ],
    "sg:phone":"+1 773 376 3379",
    "sg:postcode":"60623",
    "sg:province":"IL",
    "sg:tags":[
        "frozen",
        "yogurt"
    ],
    "wof:name":"Roldans'",
    "wof:placetype":"venue"
},
  "geometry": {"coordinates":[-87.703102,41.844398],"type":"Point"}
}