{
  "type": "Feature",
  "properties": {
    "addr:full":"7400 Janes Ave Woodridge IL 60517",
    "addr:housenumber":"7400",
    "addr:postcode":"60517",
    "addr:street":"Janes Ave",
    "iso:country":"US",
    "sg:address":"7400 Janes Ave",
    "sg:city":"Woodridge",
    "sg:classifiers":[
        {
            "category":"Shopping",
            "type":"Retail Goods"
        }
    ],
    "sg:phone":"+1 630 271 9963",
    "sg:postcode":"60517",
    "sg:province":"IL",
    "sg:tags":[
        "african"
    ],
    "wof:name":"Blackstar African Market",
    "wof:placetype":"venue"
},
  "geometry": {"coordinates":[-88.040846,41.751054],"type":"Point"}
}