{
  "type": "Feature",
  "properties": {
    "addr:full":"120 W Laura Dr Addison IL 60101",
    "addr:housenumber":"120",
    "addr:postcode":"60101",
    "addr:street":"W Laura Dr",
    "iso:country":"US",
    "sg:address":"120 W Laura Dr",
    "sg:city":"Addison",
    "sg:classifiers":[
        {
            "category":"Manufacturing",
            "subcategory":"Paper Products",
            "type":"Manufacturing & Wholesale Goods"
        }
    ],
    "sg:phone":"+1 630 543 8227",
    "sg:postcode":"60101",
    "sg:province":"IL",
    "sg:tags":[
        "bookbinder"
    ],
    "sg:website":"http://www.custom-bindery.com",
    "wof:name":"Custom Bindery Services",
    "wof:placetype":"venue"
},
  "geometry": {"coordinates":[-87.99164500000001,41.910112],"type":"Point"}
}