{
  "type": "Feature",
  "properties": {
    "addr:full":"22 S Western Ave Chicago IL 60612",
    "addr:housenumber":"22",
    "addr:postcode":"60612",
    "addr:street":"S Western Ave",
    "iso:country":"US",
    "sg:address":"22 S Western Ave",
    "sg:city":"Chicago",
    "sg:classifiers":[
        {
            "category":"Shopping",
            "subcategory":"Shoes",
            "type":"Retail Goods"
        }
    ],
    "sg:phone":"+1 312 243 3332",
    "sg:postcode":"60612",
    "sg:province":"IL",
    "sg:tags":[
        "store"
    ],
    "wof:name":"Shoomi",
    "wof:placetype":"venue"
},
  "geometry": {"coordinates":[-87.68667000000001,41.88055],"type":"Point"}
}