{
  "type": "Feature",
  "properties": {
    "addr:full":"625 Kandy St Pittsfield IL 62363",
    "addr:housenumber":"625",
    "addr:postcode":"62363",
    "addr:street":"Kandy St",
    "iso:country":"US",
    "sg:address":"625 Kandy St",
    "sg:city":"Pittsfield",
    "sg:classifiers":[
        {
            "category":"Real Estate",
            "subcategory":"Real Estate Agent",
            "type":"Services"
        }
    ],
    "sg:phone":"+1 217 285 6919",
    "sg:postcode":"62363",
    "sg:province":"IL",
    "sg:tags":[
        "appraiser"
    ],
    "wof:name":"Marvin Paxton",
    "wof:placetype":"venue"
},
  "geometry": {"coordinates":[-90.81234000000001,39.599737],"type":"Point"}
}