{
  "type": "Feature",
  "properties": {
    "iso:country":"US",
    "sg:address":"125 N Eastern Ave",
    "sg:city":"Manhattan",
    "sg:classifiers":[
        {
            "category":"Social Services",
            "subcategory":"Child Care",
            "type":"Services"
        }
    ],
    "sg:phone":"+1 815 478 7706",
    "sg:postcode":"60442",
    "sg:province":"IL",
    "sg:tags":[
        "day"
    ],
    "wof:name":"Schoolhouse Machine and Tool",
    "wof:placetype":"venue"
},
  "geometry": {"coordinates":[-87.982159,41.425207],"type":"Point"}
}