{
  "type": "Feature",
  "properties": {
    "addr:full":"151 N. Michigan Ave Chicago IL 60601",
    "addr:housenumber":"151",
    "addr:postcode":"60601",
    "addr:street":"N. Michigan Ave",
    "iso:country":"US",
    "sg:address":"151 N. Michigan Ave",
    "sg:city":"Chicago",
    "sg:classifiers":[
        {
            "category":"Bars & Pubs",
            "type":"Food & Drink"
        }
    ],
    "sg:postcode":"60601",
    "sg:province":"IL",
    "wof:name":"Bar Millennium",
    "wof:placetype":"venue"
},
  "geometry": {"coordinates":[-87.624115,41.885203],"type":"Point"}
}