{
  "type": "Feature",
  "properties": {
    "iso:country":"US",
    "sg:address":"4194 N Elston Ave",
    "sg:city":"Chicago",
    "sg:classifiers":[
        {
            "category":"Wholesale",
            "subcategory":"Meat",
            "type":"Manufacturing & Wholesale Goods"
        }
    ],
    "sg:phone":"+1 773 478 9529",
    "sg:postcode":"60618",
    "sg:province":"IL",
    "sg:tags":[
        "packer"
    ],
    "wof:name":"Victor's Foods",
    "wof:placetype":"venue"
},
  "geometry": {"coordinates":[-87.72436,41.957272],"type":"Point"}
}