{
  "type": "Feature",
  "properties": {
    "iso:country":"US",
    "sg:address":"1837 W Chicago Ave",
    "sg:city":"Chicago",
    "sg:classifiers":[
        {
            "category":"Personal",
            "subcategory":"Nail Salon",
            "type":"Services"
        }
    ],
    "sg:phone":"+1 312 421 1580",
    "sg:postcode":"60622",
    "sg:province":"IL",
    "wof:name":"Stylish Nails",
    "wof:placetype":"venue"
},
  "geometry": {"coordinates":[-87.6735,41.895901],"type":"Point"}
}