{
  "type": "Feature",
  "properties": {
    "addr:full":"14381 W 3000S Rd Buckingham IL 60917",
    "addr:housenumber":"14381",
    "addr:postcode":"60917",
    "addr:street":"W 3000S Rd",
    "iso:country":"US",
    "sg:address":"14381 W 3000S Rd",
    "sg:city":"Buckingham",
    "sg:classifiers":[
        {
            "category":"Retail",
            "subcategory":"Auto Rental",
            "type":"Services"
        }
    ],
    "sg:phone":"+1 815 426 6841",
    "sg:postcode":"60917",
    "sg:province":"IL",
    "sg:tags":[
        "passenger",
        "car"
    ],
    "wof:name":"Mike Hertz",
    "wof:placetype":"venue"
},
  "geometry": {"coordinates":[-88.141159,41.070527],"type":"Point"}
}