{
  "type": "Feature",
  "properties": {
    "iso:country":"US",
    "sg:address":"726 W Jefferson St",
    "sg:city":"Ottawa",
    "sg:classifiers":[
        {
            "category":"Organizations",
            "subcategory":"Religious Organization",
            "type":"Services"
        }
    ],
    "sg:phone":"+1 815 434 0768",
    "sg:postcode":"61350",
    "sg:province":"IL",
    "wof:name":"St Patricks Roman Catholic",
    "wof:placetype":"venue"
},
  "geometry": {"coordinates":[-88.850452,41.347914],"type":"Point"}
}