{
  "type": "Feature",
  "properties": {
    "addr:full":"1255 N Sandburg Ter Chicago IL 60610",
    "addr:housenumber":"1255",
    "addr:postcode":"60610",
    "addr:street":"N Sandburg Ter",
    "iso:country":"US",
    "sg:address":"1255 N Sandburg Ter",
    "sg:city":"Chicago",
    "sg:classifiers":[
        {
            "category":"Professional",
            "type":"Services"
        },
        {
            "category":"Professional",
            "subcategory":"Advertising",
            "type":"Services"
        }
    ],
    "sg:phone":"+1 312 266 1845",
    "sg:postcode":"60610",
    "sg:province":"IL",
    "sg:tags":[
        "product",
        "fair",
        "trade",
        "exposition",
        "advertising-promotional",
        "shows"
    ],
    "wof:name":"Harvard Associates",
    "wof:placetype":"venue"
},
  "geometry": {"coordinates":[-87.63211099999999,41.905631],"type":"Point"}
}