{
  "type": "Feature",
  "properties": {
    "addr:full":"901 Wenzel Rd Peru IL 61354",
    "addr:housenumber":"901",
    "addr:postcode":"61354",
    "addr:street":"Wenzel Rd",
    "iso:country":"US",
    "sg:address":"901 Wenzel Rd",
    "sg:city":"Peru",
    "sg:classifiers":[
        {
            "category":"Insurance",
            "subcategory":"Insurance Agent",
            "type":"Services"
        }
    ],
    "sg:phone":"+1 815 223 0277",
    "sg:postcode":"61354",
    "sg:province":"IL",
    "wof:name":"Duncan Insurance Office",
    "wof:placetype":"venue"
},
  "geometry": {"coordinates":[-89.11854099999999,41.353099],"type":"Point"}
}