{
  "type": "Feature",
  "properties": {
    "iso:country":"US",
    "sg:address":"416 S Milwaukee Ave",
    "sg:city":"Libertyville",
    "sg:phone":"+1 847 247 4433",
    "sg:postcode":"60048",
    "sg:province":"IL",
    "wof:name":"Taco El Reydeoro",
    "wof:placetype":"venue"
},
  "geometry": {"coordinates":[-87.95263799999999,42.279563],"type":"Point"}
}