{
  "type": "Feature",
  "properties": {
    "iso:country":"US",
    "sg:address":"820 Tek Dr",
    "sg:city":"Crystal Lake",
    "sg:classifiers":[
        {
            "category":"Freight",
            "type":"Transportation"
        }
    ],
    "sg:phone":"+1 815 459 3975",
    "sg:postcode":"60014",
    "sg:province":"IL",
    "sg:tags":[
        "mover"
    ],
    "wof:name":"Mc Mahan Movers",
    "wof:placetype":"venue"
},
  "geometry": {"coordinates":[-88.287074,42.215618],"type":"Point"}
}