{
  "type": "Feature",
  "properties": {
    "iso:country":"US",
    "sg:address":"6855 N Crawford Ave",
    "sg:city":"Lincolnwood",
    "sg:classifiers":[
        {
            "category":"Education",
            "subcategory":"School",
            "type":"Public Place"
        }
    ],
    "sg:phone":"+1 847 675 8240",
    "sg:postcode":"60712",
    "sg:province":"IL",
    "wof:name":"Lincoln Hall Middle School",
    "wof:placetype":"venue"
},
  "geometry": {"coordinates":[-87.72863,42.006137],"type":"Point"}
}