{
  "type": "Feature",
  "properties": {
    "iso:country":"US",
    "sg:address":"1970 Larkin Ave",
    "sg:city":"Elgin",
    "sg:classifiers":[
        {
            "category":"Professional",
            "type":"Services"
        },
        {
            "category":"Professional",
            "subcategory":"Lawyer & Legal Services",
            "type":"Services"
        }
    ],
    "sg:phone":"+1 847 699 3399",
    "sg:postcode":"60123",
    "sg:province":"IL",
    "sg:tags":[
        "divorce",
        "assistance",
        "mediation"
    ],
    "sg:website":"http://www.creativeresolution.us",
    "wof:name":"Creative Resolution",
    "wof:placetype":"venue"
},
  "geometry": {"coordinates":[-88.326083,42.032583],"type":"Point"}
}