{
  "type": "Feature",
  "properties": {
    "iso:country":"US",
    "sg:address":"1026 W Devon Ave",
    "sg:city":"Elk Grove Vlg",
    "sg:classifiers":[
        {
            "category":"Building & Trades",
            "subcategory":"Cleaning & Sanitation",
            "type":"Services"
        }
    ],
    "sg:phone":"+1 847 985 0056",
    "sg:postcode":"60007",
    "sg:province":"IL",
    "sg:tags":[
        "janitor"
    ],
    "wof:name":"A & K & Son Svc",
    "wof:placetype":"venue"
},
  "geometry": {"coordinates":[-88.028406,41.992579],"type":"Point"}
}