{
  "type": "Feature",
  "properties": {
    "iso:country":"US",
    "sg:address":"4051 N Humbert Rd",
    "sg:city":"Alton",
    "sg:classifiers":[
        {
            "category":"Organizations",
            "subcategory":"Labor Organization",
            "type":"Services"
        }
    ],
    "sg:phone":"+1 618 462 1627",
    "sg:postcode":"62002",
    "sg:province":"IL",
    "wof:name":"International Electrical Wrkrs",
    "wof:placetype":"venue"
},
  "geometry": {"coordinates":[-90.156264,38.93619],"type":"Point"}
}