{
  "type": "Feature",
  "properties": {
    "iso:country":"US",
    "sg:address":"717 W Maxwell St",
    "sg:city":"Chicago",
    "sg:classifiers":[
        {
            "category":"Professional",
            "type":"Services"
        },
        {
            "category":"Coffee & Tea",
            "type":"Food & Drink"
        },
        {
            "category":"Restaurant",
            "type":"Food & Drink"
        }
    ],
    "sg:phone":"+1 312 997 9969",
    "sg:postcode":"60607",
    "sg:province":"IL",
    "sg:tags":[
        "style",
        "family",
        "espresso",
        "lunch",
        "american",
        "caterer",
        "barbecue",
        "brunch",
        "breakfast"
    ],
    "wof:name":"Wow Cafe & Wingery",
    "wof:placetype":"venue"
},
  "geometry": {"coordinates":[-87.645336,41.864796],"type":"Point"}
}