{
  "type": "Feature",
  "properties": {
    "addr:full":"1325 W Whittaker St Salem IL 62881",
    "addr:housenumber":"1325",
    "addr:postcode":"62881",
    "addr:street":"W Whittaker St",
    "iso:country":"US",
    "sg:address":"1325 W Whittaker St",
    "sg:city":"Salem",
    "sg:classifiers":[
        {
            "category":"Restaurant",
            "type":"Food & Drink"
        }
    ],
    "sg:phone":"+1   ",
    "sg:postcode":"62881",
    "sg:province":"IL",
    "sg:tags":[
        "eating"
    ],
    "wof:name":"Dominos Pizza",
    "wof:placetype":"venue"
},
  "geometry": {"coordinates":[-88.961027,38.623177],"type":"Point"}
}