{
  "type": "Feature",
  "properties": {
    "iso:country":"US",
    "sg:address":"400 Wedgewood Trl",
    "sg:city":"Mc Henry",
    "sg:classifiers":[
        {
            "category":"Shopping",
            "subcategory":"Department Store",
            "type":"Retail Goods"
        }
    ],
    "sg:phone":"+1   ",
    "sg:postcode":"60050",
    "sg:province":"IL",
    "wof:name":"American Heritage Dev Corp",
    "wof:placetype":"venue"
},
  "geometry": {"coordinates":[-88.31423100000001,42.333868],"type":"Point"}
}