{
  "type": "Feature",
  "properties": {
    "addr:full":"710 Bay Hill Ct Deerfield IL 60015",
    "addr:housenumber":"710",
    "addr:postcode":"60015",
    "addr:street":"Bay Hill Ct",
    "iso:country":"US",
    "sg:address":"710 Bay Hill Ct",
    "sg:city":"Deerfield",
    "sg:classifiers":[
        {
            "category":"Professional",
            "subcategory":"Management & Consulting",
            "type":"Services"
        }
    ],
    "sg:phone":"+1 847 945 0101",
    "sg:postcode":"60015",
    "sg:province":"IL",
    "sg:tags":[
        "counselor",
        "public",
        "relations"
    ],
    "wof:name":"Blitz & Associates Inc",
    "wof:placetype":"venue"
},
  "geometry": {"coordinates":[-87.883843,42.166144],"type":"Point"}
}