{
  "type": "Feature",
  "properties": {
    "addr:full":"716 E Boughton Rd Bolingbrook IL 60440",
    "addr:housenumber":"716",
    "addr:postcode":"60440",
    "addr:street":"E Boughton Rd",
    "iso:country":"US",
    "sg:address":"716 E Boughton Rd",
    "sg:city":"Bolingbrook",
    "sg:phone":"+1 630 739 1600",
    "sg:postcode":"60440",
    "sg:province":"IL",
    "sg:website":"http://www.colorificsalon.com",
    "wof:name":"Colorific Hair Salon",
    "wof:placetype":"venue"
},
  "geometry": {"coordinates":[-88.095477,41.706664],"type":"Point"}
}