{
  "type": "Feature",
  "properties": {
    "addr:full":"408 E Side Dr Geneva IL 60134",
    "addr:housenumber":"408",
    "addr:postcode":"60134",
    "addr:street":"E Side Dr",
    "iso:country":"US",
    "sg:address":"408 E Side Dr",
    "sg:city":"Geneva",
    "sg:classifiers":[
        {
            "category":"Wholesale",
            "subcategory":"Construction Materials",
            "type":"Manufacturing & Wholesale Goods"
        }
    ],
    "sg:phone":"+1 630 232 7116",
    "sg:postcode":"60134",
    "sg:province":"IL",
    "sg:tags":[
        "fence"
    ],
    "wof:name":"Dakota Fence & Deck",
    "wof:placetype":"venue"
},
  "geometry": {"coordinates":[-88.290002,41.890221],"type":"Point"}
}