{
  "type": "Feature",
  "properties": {
    "addr:full":"6657 W 111th St Worth IL 60482",
    "addr:housenumber":"6657",
    "addr:postcode":"60482",
    "addr:street":"W 111Th St",
    "iso:country":"US",
    "sg:address":"6657 W 111th St",
    "sg:city":"Worth",
    "sg:classifiers":[
        {
            "category":"Personal",
            "subcategory":"Barber",
            "type":"Services"
        }
    ],
    "sg:phone":"+1 708 361 4240",
    "sg:postcode":"60482",
    "sg:province":"IL",
    "wof:name":"Vip",
    "wof:placetype":"venue"
},
  "geometry": {"coordinates":[-87.785202,41.690201],"type":"Point"}
}