{
  "type": "Feature",
  "properties": {
    "addr:full":"1825 Maple Ave Berwyn IL 60402",
    "addr:housenumber":"1825",
    "addr:postcode":"60402",
    "addr:street":"Maple Ave",
    "iso:country":"US",
    "sg:address":"1825 Maple Ave",
    "sg:city":"Berwyn",
    "sg:classifiers":[
        {
            "category":"Health Services",
            "subcategory":"Health Practitioner",
            "type":"Services"
        }
    ],
    "sg:phone":"+1 708 749 7734",
    "sg:postcode":"60402",
    "sg:province":"IL",
    "wof:name":"Mary Ellen Longdon",
    "wof:placetype":"venue"
},
  "geometry": {"coordinates":[-87.80246200000001,41.855057],"type":"Point"}
}