{
  "type": "Feature",
  "properties": {
    "iso:country":"US",
    "sg:address":"20 S Park Blvd",
    "sg:city":"Glen Ellyn",
    "sg:classifiers":[
        {
            "category":"Professional",
            "subcategory":"Printing & Photocopies",
            "type":"Services"
        }
    ],
    "sg:phone":"+1 630 469 9360",
    "sg:postcode":"60137",
    "sg:province":"IL",
    "sg:tags":[
        "blueprinting"
    ],
    "sg:website":"www.dupage-copy.com",
    "wof:name":"Dupage Copy & Blueprint Svc",
    "wof:placetype":"venue"
},
  "geometry": {"coordinates":[-88.061661,41.859061],"type":"Point"}
}