{
  "type": "Feature",
  "properties": {
    "iso:country":"US",
    "sg:address":"400 W 76th St",
    "sg:city":"Chicago",
    "sg:classifiers":[
        {
            "category":"Real Estate",
            "subcategory":"Real Estate Services",
            "type":"Services"
        }
    ],
    "sg:phone":"+1 773 892 1380",
    "sg:postcode":"60620",
    "sg:province":"IL",
    "sg:tags":[
        "management",
        "property"
    ],
    "wof:name":"Chicago Elite Services",
    "wof:placetype":"venue"
},
  "geometry": {"coordinates":[-87.634399,41.756199],"type":"Point"}
}