{
  "type": "Feature",
  "properties": {
    "addr:full":"1213 Geneva Ave Rockford IL 61108",
    "addr:housenumber":"1213",
    "addr:postcode":"61108",
    "addr:street":"Geneva Ave",
    "iso:country":"US",
    "sg:address":"1213 Geneva Ave",
    "sg:city":"Rockford",
    "sg:classifiers":[
        {
            "category":"Building & Trades",
            "subcategory":"Construction",
            "type":"Services"
        }
    ],
    "sg:phone":"+1 815 397 8065",
    "sg:postcode":"61108",
    "sg:province":"IL",
    "sg:tags":[
        "residential"
    ],
    "wof:name":"E & M Homes Inc",
    "wof:placetype":"venue"
},
  "geometry": {"coordinates":[-89.008337,42.256864],"type":"Point"}
}