{
  "type": "Feature",
  "properties": {
    "addr:full":"8338 S Perry Avenue Chicago IL 60620",
    "addr:housenumber":"8338",
    "addr:postcode":"60620",
    "addr:street":"S Perry Avenue",
    "iso:country":"US",
    "sg:address":"8338 S Perry Avenue",
    "sg:city":"Chicago",
    "sg:classifiers":[
        {
            "category":"Wholesale",
            "subcategory":"Stationery",
            "type":"Manufacturing & Wholesale Goods"
        }
    ],
    "sg:phone":"+1 773 651 6525",
    "sg:postcode":"60620",
    "sg:province":"IL",
    "sg:tags":[
        "card"
    ],
    "wof:name":"Beautfully Black & Reasonable Too",
    "wof:placetype":"venue"
},
  "geometry": {"coordinates":[-87.626914,41.742466],"type":"Point"}
}