{
  "type": "Feature",
  "properties": {
    "iso:country":"US",
    "sg:address":"529 W Mosley St",
    "sg:city":"Freeport",
    "sg:classifiers":[
        {
            "category":"Social Services",
            "subcategory":"Child Care",
            "type":"Services"
        }
    ],
    "sg:phone":"+1 815 232 8819",
    "sg:postcode":"61032",
    "sg:province":"IL",
    "sg:tags":[
        "day"
    ],
    "wof:name":"Kathleen Barber",
    "wof:placetype":"venue"
},
  "geometry": {"coordinates":[-89.625823,42.28923],"type":"Point"}
}