{
  "type": "Feature",
  "properties": {
    "addr:full":"3166 N Lincoln Ave Chicago IL 60657",
    "addr:housenumber":"3166",
    "addr:postcode":"60657",
    "addr:street":"N Lincoln Ave",
    "iso:country":"US",
    "sg:address":"3166 N Lincoln Ave",
    "sg:city":"Chicago",
    "sg:classifiers":[
        {
            "category":"Professional",
            "subcategory":"Computer Services",
            "type":"Services"
        }
    ],
    "sg:phone":"+1 800 522 1435",
    "sg:postcode":"60657",
    "sg:province":"IL",
    "sg:tags":[
        "internet",
        "provider"
    ],
    "wof:name":"Military Community Online",
    "wof:placetype":"venue"
},
  "geometry": {"coordinates":[-87.667259,41.938423],"type":"Point"}
}