{
  "type": "Feature",
  "properties": {
    "addr:full":"4039 N Laporte Ave Chicago IL 60641",
    "addr:housenumber":"4039",
    "addr:postcode":"60641",
    "addr:street":"N Laporte Ave",
    "iso:country":"US",
    "sg:address":"4039 N Laporte Ave",
    "sg:city":"Chicago",
    "sg:classifiers":[
        {
            "category":"Building & Trades",
            "subcategory":"Construction",
            "type":"Services"
        }
    ],
    "sg:phone":"+1 773 545 0262",
    "sg:postcode":"60641",
    "sg:province":"IL",
    "sg:tags":[
        "resurfacing",
        "refinishing",
        "floor"
    ],
    "wof:name":"Expert Flooring",
    "wof:placetype":"venue"
},
  "geometry": {"coordinates":[-87.75099299999999,41.954664],"type":"Point"}
}