{
  "type": "Feature",
  "properties": {
    "iso:country":"US",
    "sg:address":"3750 E 112th Street",
    "sg:city":"Chicago",
    "sg:classifiers":[
        {
            "category":"Education",
            "subcategory":"School",
            "type":"Public Place"
        }
    ],
    "sg:phone":"+1 773 375 5711",
    "sg:postcode":"60617",
    "sg:province":"IL",
    "sg:tags":[
        "high",
        "middle",
        "elementary"
    ],
    "wof:name":"Annunciata School",
    "wof:placetype":"venue"
},
  "geometry": {"coordinates":[-87.532518,41.691851],"type":"Point"}
}