{
  "type": "Feature",
  "properties": {
    "addr:full":"132 W Arthur St Elmhurst IL 60126",
    "addr:housenumber":"132",
    "addr:postcode":"60126",
    "addr:street":"W Arthur St",
    "iso:country":"US",
    "sg:address":"132 W Arthur St",
    "sg:city":"Elmhurst",
    "sg:classifiers":[
        {
            "category":"Education",
            "subcategory":"School",
            "type":"Public Place"
        }
    ],
    "sg:phone":"+1 630 530 3490",
    "sg:postcode":"60126",
    "sg:province":"IL",
    "sg:tags":[
        "elementary"
    ],
    "sg:website":"http://www.icelmhurst.org/icgs",
    "wof:name":"Immaculate Conception Grade School",
    "wof:placetype":"venue"
},
  "geometry": {"coordinates":[-87.94081300000001,41.896061],"type":"Point"}
}