{
  "type": "Feature",
  "properties": {
    "iso:country":"US",
    "sg:address":"125 Twin Oaks Dr",
    "sg:city":"Joliet",
    "sg:classifiers":[
        {
            "category":"Retail",
            "subcategory":"Auto Repair",
            "type":"Services"
        }
    ],
    "sg:phone":"+1 815 730 0653",
    "sg:postcode":"60431",
    "sg:province":"IL",
    "sg:tags":[
        "repairing",
        "automobile"
    ],
    "wof:name":"Siddhi Vinayak Dev Inc",
    "wof:placetype":"venue"
},
  "geometry": {"coordinates":[-88.161462,41.524736],"type":"Point"}
}