{
  "type": "Feature",
  "properties": {
    "iso:country":"US",
    "sg:address":"511 Jennings Dr",
    "sg:city":"Lake In The Hills",
    "sg:classifiers":[
        {
            "category":"Retail",
            "subcategory":"Repair Shop",
            "type":"Services"
        }
    ],
    "sg:phone":"+1 847 658 4812",
    "sg:postcode":"60156",
    "sg:province":"IL",
    "sg:tags":[
        "garage",
        "door",
        "install"
    ],
    "wof:name":"Herbs Door Service",
    "wof:placetype":"venue"
},
  "geometry": {"coordinates":[-88.317289,42.212424],"type":"Point"}
}