{
  "type": "Feature",
  "properties": {
    "addr:full":"300 Water St Cahokia IL 62206",
    "addr:housenumber":"300",
    "addr:postcode":"62206",
    "addr:street":"Water St",
    "iso:country":"US",
    "sg:address":"300 Water St",
    "sg:city":"Cahokia",
    "sg:classifiers":[
        {
            "category":"Autos & Motor Vehicles",
            "subcategory":"Fuel & Gas Station",
            "type":"Retail Goods"
        },
        {
            "category":"Retail",
            "subcategory":"Auto Repair",
            "type":"Services"
        }
    ],
    "sg:phone":"+1 618 332 0661",
    "sg:postcode":"62206",
    "sg:province":"IL",
    "sg:tags":[
        "gasoline",
        "station",
        "wrecker"
    ],
    "wof:name":"Floyd's Towing",
    "wof:placetype":"venue"
},
  "geometry": {"coordinates":[-90.190636,38.567772],"type":"Point"}
}