{
  "type": "Feature",
  "properties": {
    "addr:full":"1503 Hunter School Ave Greenville IL 62246",
    "addr:housenumber":"1503",
    "addr:postcode":"62246",
    "addr:street":"Hunter School Ave",
    "iso:country":"US",
    "sg:address":"1503 Hunter School Ave",
    "sg:city":"Greenville",
    "sg:classifiers":[
        {
            "category":"Food & Beverages",
            "subcategory":"Groceries & Convenience Stores",
            "type":"Retail Goods"
        }
    ],
    "sg:phone":"+1   ",
    "sg:postcode":"62246",
    "sg:province":"IL",
    "wof:name":"DEANS",
    "wof:placetype":"venue"
},
  "geometry": {"coordinates":[-89.34552499999999,38.803568],"type":"Point"}
}