{
  "type": "Feature",
  "properties": {
    "iso:country":"US",
    "sg:address":"660 N Westmoreland Rd",
    "sg:city":"Lake Forest",
    "sg:classifiers":[
        {
            "category":"Health Services",
            "subcategory":"Hospital",
            "type":"Services"
        }
    ],
    "sg:phone":"+1 847 234 6172",
    "sg:postcode":"60045",
    "sg:province":"IL",
    "sg:tags":[
        "occupational"
    ],
    "wof:name":"Occupational Health",
    "wof:placetype":"venue"
},
  "geometry": {"coordinates":[-87.862946,42.252568],"type":"Point"}
}