{
  "type": "Feature",
  "properties": {
    "addr:full":"660 N Westmoreland Rd Lake Forest IL 60045",
    "addr:housenumber":"660",
    "addr:postcode":"60045",
    "addr:street":"N Westmoreland Rd",
    "iso:country":"US",
    "sg:address":"660 N Westmoreland Rd",
    "sg:city":"Lake Forest",
    "sg:classifiers":[
        {
            "category":"Health Services",
            "subcategory":"Hospital",
            "type":"Services"
        }
    ],
    "sg:phone":"+1 847 234 6172",
    "sg:postcode":"60045",
    "sg:province":"IL",
    "sg:tags":[
        "occupational"
    ],
    "wof:name":"Occupational Health",
    "wof:placetype":"venue"
},
  "geometry": {"coordinates":[-87.86294599999999,42.252568],"type":"Point"}
}