{
  "type": "Feature",
  "properties": {
    "iso:country":"US",
    "sg:address":"2215 Morton Dr",
    "sg:city":"East Moline",
    "sg:classifiers":[
        {
            "category":"Government",
            "subcategory":"Office",
            "type":"Public Place"
        }
    ],
    "sg:phone":"+1 309 755 1289",
    "sg:postcode":"61244",
    "sg:province":"IL",
    "wof:name":"Greater Metropolitan Housing",
    "wof:placetype":"venue"
},
  "geometry": {"coordinates":[-90.420547,41.524155],"type":"Point"}
}