{
  "type": "Feature",
  "properties": {
    "iso:country":"US",
    "sg:address":"1315 Wabican Trl",
    "sg:city":"Algonquin",
    "sg:classifiers":[
        {
            "category":"Building & Trades",
            "subcategory":"Cleaning & Sanitation",
            "type":"Services"
        }
    ],
    "sg:phone":"+1 847 428 5109",
    "sg:postcode":"60102",
    "sg:province":"IL",
    "sg:tags":[
        "carpet"
    ],
    "wof:name":"Galaxy North Technology",
    "wof:placetype":"venue"
},
  "geometry": {"coordinates":[-88.287102,42.149799],"type":"Point"}
}