{
  "type": "Feature",
  "properties": {
    "iso:country":"US",
    "sg:address":"680 W Henry St",
    "sg:city":"Kankakee",
    "sg:classifiers":[
        {
            "category":"Personal",
            "subcategory":"Beauty Salon",
            "type":"Services"
        }
    ],
    "sg:phone":"+1 815 937 0902",
    "sg:postcode":"60901",
    "sg:province":"IL",
    "sg:tags":[
        "shop"
    ],
    "wof:name":"Star Nails",
    "wof:placetype":"venue"
},
  "geometry": {"coordinates":[-87.873831,41.13163],"type":"Point"}
}