{
  "type": "Feature",
  "properties": {
    "iso:country":"US",
    "sg:address":"6262 Dornoch Dr",
    "sg:city":"Caledonia",
    "sg:classifiers":[
        {
            "category":"Professional",
            "subcategory":"Business Services",
            "type":"Services"
        }
    ],
    "sg:phone":"+1 815 885 9922",
    "sg:postcode":"61011",
    "sg:province":"IL",
    "wof:name":"Eagle One Enterprises Inc",
    "wof:placetype":"venue"
},
  "geometry": {"coordinates":[-88.949179,42.352934],"type":"Point"}
}