{
  "type": "Feature",
  "properties": {
    "addr:full":"9441 US Hwy 30 Frankfort IL 60423",
    "addr:housenumber":"9441",
    "addr:postcode":"60423",
    "addr:street":"Us Hwy 30",
    "iso:country":"US",
    "sg:address":"9441 US Hwy 30",
    "sg:city":"Frankfort",
    "sg:classifiers":[
        {
            "category":"Retail",
            "subcategory":"Auto Repair",
            "type":"Services"
        }
    ],
    "sg:phone":"+1 815 469 1831",
    "sg:postcode":"60423",
    "sg:province":"IL",
    "sg:tags":[
        "shop",
        "automotive",
        "general"
    ],
    "wof:name":"Automotive Performance",
    "wof:placetype":"venue"
},
  "geometry": {"coordinates":[-87.843706,41.506525],"type":"Point"}
}