{
  "type": "Feature",
  "properties": {
    "iso:country":"US",
    "sg:address":"11950 S Cicero Ave",
    "sg:city":"Alsip",
    "sg:classifiers":[
        {
            "category":"Retail",
            "subcategory":"Car Wash",
            "type":"Services"
        }
    ],
    "sg:phone":"+1 708 388 7787",
    "sg:postcode":"60803",
    "sg:province":"IL",
    "wof:name":"Sunshine Car Wash",
    "wof:placetype":"venue"
},
  "geometry": {"coordinates":[-87.739197,41.6754],"type":"Point"}
}