{
  "type": "Feature",
  "properties": {
    "addr:full":"4021 W Kinzie Street Chicago IL 60624",
    "addr:housenumber":"4021",
    "addr:postcode":"60624",
    "addr:street":"W Kinzie Street",
    "iso:country":"US",
    "sg:address":"4021 W Kinzie Street",
    "sg:city":"Chicago",
    "sg:classifiers":[
        {
            "category":"Deli",
            "type":"Food & Drink"
        },
        {
            "category":"Food & Beverages",
            "subcategory":"Bakery",
            "type":"Retail Goods"
        }
    ],
    "sg:phone":"+1 773 696 3447",
    "sg:postcode":"60624",
    "sg:province":"IL",
    "sg:tags":[
        "sandwich"
    ],
    "sg:website":"www.andysdeli.com",
    "wof:name":"Andy's Deli",
    "wof:placetype":"venue"
},
  "geometry": {"coordinates":[-87.726004,41.8876],"type":"Point"}
}