{
  "type": "Feature",
  "properties": {
    "iso:country":"US",
    "sg:address":"206 W Division St",
    "sg:city":"Fisher",
    "sg:classifiers":[
        {
            "category":"Food & Beverages",
            "subcategory":"Groceries & Convenience Stores",
            "type":"Retail Goods"
        }
    ],
    "sg:phone":"+1   ",
    "sg:postcode":"61843",
    "sg:province":"IL",
    "wof:name":"Caseys General Store",
    "wof:placetype":"venue"
},
  "geometry": {"coordinates":[-88.35346699999999,40.310876],"type":"Point"}
}