{
  "type": "Feature",
  "properties": {
    "iso:country":"US",
    "sg:address":"7050 Mannheim Rd",
    "sg:city":"Des Plaines",
    "sg:classifiers":[
        {
            "category":"Bakery",
            "type":"Food & Drink"
        }
    ],
    "sg:menulink":"http://www.allmenus.com/il/maine/121137-krispy-kreme/menu/",
    "sg:phone":"+1 847 827 8800",
    "sg:postcode":"60018",
    "sg:province":"IL",
    "sg:tags":[
        "american",
        "pastry"
    ],
    "wof:name":"Krispy Kreme",
    "wof:placetype":"venue"
},
  "geometry": {"coordinates":[-87.88486,42.006862],"type":"Point"}
}