{
  "type": "Feature",
  "properties": {
    "iso:country":"US",
    "sg:address":"5204 Fairmount Ave",
    "sg:city":"Downers Grove",
    "sg:classifiers":[
        {
            "category":"Organizations",
            "subcategory":"Professional Association",
            "type":"Services"
        }
    ],
    "sg:phone":"+1 630 655 0112",
    "sg:postcode":"60515",
    "sg:province":"IL",
    "sg:website":"www.asihq.com",
    "wof:name":"Administrative Systems Inc",
    "wof:placetype":"venue"
},
  "geometry": {"coordinates":[-88.002807,41.793689],"type":"Point"}
}