{
  "type": "Feature",
  "properties": {
    "addr:full":"1010 Broadway St Hamilton IL 62341",
    "addr:housenumber":"1010",
    "addr:postcode":"62341",
    "addr:street":"Broadway St",
    "iso:country":"US",
    "sg:address":"1010 Broadway St",
    "sg:city":"Hamilton",
    "sg:classifiers":[
        {
            "category":"Government",
            "subcategory":"Office",
            "type":"Public Place"
        }
    ],
    "sg:phone":"+1 217 847 2936",
    "sg:postcode":"62341",
    "sg:province":"IL",
    "sg:tags":[
        "city"
    ],
    "wof:name":"Hamilton City Clerk",
    "wof:placetype":"venue"
},
  "geometry": {"coordinates":[-91.34529999999999,40.393022],"type":"Point"}
}