{
  "type": "Feature",
  "properties": {
    "addr:full":"6430 E State St Rockford IL 61108",
    "addr:housenumber":"6430",
    "addr:postcode":"61108",
    "addr:street":"E State St",
    "iso:country":"US",
    "sg:address":"6430 E State St",
    "sg:city":"Rockford",
    "sg:classifiers":[
        {
            "category":"Cinema",
            "subcategory":"Movie Rental",
            "type":"Entertainment"
        }
    ],
    "sg:phone":"+1 815 394 1018",
    "sg:postcode":"61108",
    "sg:province":"IL",
    "sg:tags":[
        "video",
        "tape"
    ],
    "wof:name":"Blockbuster",
    "wof:placetype":"venue"
},
  "geometry": {"coordinates":[-88.99091199999999,42.267774],"type":"Point"}
}