{
  "type": "Feature",
  "properties": {
    "iso:country":"US",
    "sg:address":"300 Center Dr",
    "sg:city":"Vernon Hills",
    "sg:classifiers":[
        {
            "category":"Wholesale",
            "subcategory":"Office Equipment",
            "type":"Manufacturing & Wholesale Goods"
        }
    ],
    "sg:phone":"+1 847 247 0022",
    "sg:postcode":"60061",
    "sg:province":"IL",
    "wof:name":"IKON Office Solutions",
    "wof:placetype":"venue"
},
  "geometry": {"coordinates":[-87.95667400000001,42.243877],"type":"Point"}
}