{
  "type": "Feature",
  "properties": {
    "addr:full":"436 E Rollins Rd Round Lake Beach IL 60073",
    "addr:housenumber":"436",
    "addr:postcode":"60073",
    "addr:street":"E Rollins Rd Round Lake Beach",
    "iso:country":"US",
    "sg:address":"436 E Rollins Rd",
    "sg:city":"Round Lake Beach",
    "sg:classifiers":[
        {
            "category":"Shopping",
            "type":"Retail Goods"
        }
    ],
    "sg:phone":"+1 847 740 1290",
    "sg:postcode":"60073",
    "sg:province":"IL",
    "sg:tags":[
        "pet",
        "shop"
    ],
    "wof:name":"PETCO",
    "wof:placetype":"venue"
},
  "geometry": {"coordinates":[-88.068063,42.37907],"type":"Point"}
}