{
  "type": "Feature",
  "properties": {
    "addr:full":"16300 Oak Park Ave Tinley Park IL 60477",
    "addr:housenumber":"16300",
    "addr:postcode":"60477",
    "addr:street":"Oak Park Ave",
    "iso:country":"US",
    "sg:address":"16300 Oak Park Ave",
    "sg:city":"Tinley Park",
    "sg:classifiers":[
        {
            "category":"Shopping",
            "subcategory":"Gifts & Souvenirs",
            "type":"Retail Goods"
        }
    ],
    "sg:phone":"+1   ",
    "sg:postcode":"60477",
    "sg:province":"IL",
    "wof:name":"Timeless Products",
    "wof:placetype":"venue"
},
  "geometry": {"coordinates":[-87.78500099999999,41.594146],"type":"Point"}
}