{
  "type": "Feature",
  "properties": {
    "iso:country":"US",
    "sg:address":"16709 Torrence Ave",
    "sg:city":"Lansing",
    "sg:classifiers":[
        {
            "category":"Shopping",
            "subcategory":"Department Store",
            "type":"Retail Goods"
        }
    ],
    "sg:phone":"+1 708 474 1188",
    "sg:postcode":"60438",
    "sg:province":"IL",
    "sg:website":"www.pier1.com",
    "wof:name":"Pier 1 Imports Inc",
    "wof:placetype":"venue"
},
  "geometry": {"coordinates":[-87.558403,41.5924],"type":"Point"}
}