{
  "type": "Feature",
  "properties": {
    "addr:full":"6414 Breese Rd Aviston IL 62216",
    "addr:postcode":"6414;62216",
    "addr:street":"Breese Rd",
    "iso:country":"US",
    "sg:address":"6414 Breese Rd",
    "sg:city":"Aviston",
    "sg:classifiers":[
        {
            "category":"Building & Trades",
            "subcategory":"Construction",
            "type":"Services"
        }
    ],
    "sg:phone":"+1 618 228 7520",
    "sg:postcode":"62216",
    "sg:province":"IL",
    "sg:tags":[
        "excavating",
        "contractor"
    ],
    "wof:name":"Markus Backhoe",
    "wof:placetype":"venue"
},
  "geometry": {"coordinates":[-89.585576,38.597619],"type":"Point"}
}