{
  "type": "Feature",
  "properties": {
    "addr:full":"2844 W Lunt Ave Chicago IL 60645",
    "addr:housenumber":"2844",
    "addr:postcode":"60645",
    "addr:street":"W Lunt Ave",
    "iso:country":"US",
    "sg:address":"2844 W Lunt Ave",
    "sg:city":"Chicago",
    "sg:classifiers":[
        {
            "category":"Health Services",
            "subcategory":"Doctor",
            "type":"Services"
        }
    ],
    "sg:phone":"+1 773 465 2020",
    "sg:postcode":"60645",
    "sg:province":"IL",
    "sg:tags":[
        "medical"
    ],
    "wof:name":"Mason Jack Dr",
    "wof:placetype":"venue"
},
  "geometry": {"coordinates":[-87.70123599999999,42.008508],"type":"Point"}
}