{
  "type": "Feature",
  "properties": {
    "iso:country":"US",
    "sg:address":"5416 N Clark St",
    "sg:city":"Chicago",
    "sg:classifiers":[
        {
            "category":"Arts & Performance",
            "subcategory":"Art Gallery",
            "type":"Entertainment"
        },
        {
            "category":"Building & Trades",
            "subcategory":"Construction",
            "type":"Services"
        }
    ],
    "sg:phone":"+1 773 961 8544",
    "sg:postcode":"60640",
    "sg:province":"IL",
    "sg:tags":[
        "interior",
        "design"
    ],
    "sg:website":"www.luxehandmadehome.com",
    "wof:name":"Necessary Extravagance",
    "wof:placetype":"venue"
},
  "geometry": {"coordinates":[-87.668368,41.980748],"type":"Point"}
}