{
  "type": "Feature",
  "properties": {
    "iso:country":"US",
    "sg:address":"309 Kearton Dr",
    "sg:city":"Fairview Heights",
    "sg:classifiers":[
        {
            "category":"Building & Trades",
            "subcategory":"Cleaning & Sanitation",
            "type":"Services"
        }
    ],
    "sg:phone":"+1 618 410 0317",
    "sg:postcode":"62208",
    "sg:province":"IL",
    "sg:tags":[
        "maintenance"
    ],
    "wof:name":"Crockett Home Maintenance",
    "wof:placetype":"venue"
},
  "geometry": {"coordinates":[-89.969444,38.598166],"type":"Point"}
}