{
  "type": "Feature",
  "properties": {
    "iso:country":"US",
    "sg:address":"5907 W Cornelia Ave",
    "sg:city":"Chicago",
    "sg:classifiers":[
        {
            "category":"Building & Trades",
            "subcategory":"Construction",
            "type":"Services"
        }
    ],
    "sg:phone":"+1 773 744 0092",
    "sg:postcode":"60634",
    "sg:province":"IL",
    "sg:tags":[
        "contractor"
    ],
    "wof:name":"Trio Granite & Marble Corp.",
    "wof:placetype":"venue"
},
  "geometry": {"coordinates":[-87.77434700000001,41.943706],"type":"Point"}
}