{
  "type": "Feature",
  "properties": {
    "iso:country":"US",
    "sg:address":"474 N Lake Shore Dr Ste 5010",
    "sg:city":"Chicago",
    "sg:classifiers":[
        {
            "category":"Manufacturing",
            "subcategory":"Petroleum Products",
            "type":"Manufacturing & Wholesale Goods"
        },
        {
            "category":"Building & Trades",
            "subcategory":"Construction",
            "type":"Services"
        }
    ],
    "sg:phone":"+1 847 981 4747",
    "sg:postcode":"60611",
    "sg:province":"IL",
    "sg:tags":[
        "finishing",
        "wood",
        "contract"
    ],
    "wof:name":"Professional Library Services Inc",
    "wof:placetype":"venue"
},
  "geometry": {"coordinates":[-87.614189,41.892355],"type":"Point"}
}