{
  "type": "Feature",
  "properties": {
    "iso:country":"US",
    "sg:address":"1801 15th Street Pl",
    "sg:city":"Moline",
    "sg:classifiers":[
        {
            "category":"Health Services",
            "subcategory":"Doctor",
            "type":"Services"
        },
        {
            "category":"Personal",
            "subcategory":"Beauty Salon",
            "type":"Services"
        },
        {
            "category":"Personal",
            "subcategory":"Barber",
            "type":"Services"
        },
        {
            "category":"Personal",
            "subcategory":"Hair Removal",
            "type":"Services"
        }
    ],
    "sg:phone":"+1 309 764 4477",
    "sg:postcode":"61265",
    "sg:province":"IL",
    "sg:tags":[
        "wig",
        "piece",
        "weaving",
        "stylist",
        "replacement"
    ],
    "wof:name":"Hair Restoration Group",
    "wof:placetype":"venue"
},
  "geometry": {"coordinates":[-90.514458,41.494751],"type":"Point"}
}