{
  "type": "Feature",
  "properties": {
    "addr:full":"820 Lake St Maywood IL 60153",
    "addr:housenumber":"820",
    "addr:postcode":"60153",
    "addr:street":"Lake St",
    "iso:country":"US",
    "sg:address":"820 Lake St",
    "sg:city":"Maywood",
    "sg:classifiers":[
        {
            "category":"Autos & Motor Vehicles",
            "subcategory":"Fuel & Gas Station",
            "type":"Retail Goods"
        }
    ],
    "sg:phone":"+1   ",
    "sg:postcode":"60153",
    "sg:province":"IL",
    "sg:tags":[
        "station",
        "gasoline"
    ],
    "wof:name":"Maywood Phillip 66",
    "wof:placetype":"venue"
},
  "geometry": {"coordinates":[-87.8434,41.890483],"type":"Point"}
}