{
  "type": "Feature",
  "properties": {
    "iso:country":"US",
    "sg:address":"7200 N Claremont Ave",
    "sg:city":"Chicago",
    "sg:classifiers":[
        {
            "category":"Food & Beverages",
            "subcategory":"Bakery",
            "type":"Retail Goods"
        }
    ],
    "sg:phone":"+1   ",
    "sg:postcode":"60645",
    "sg:province":"IL",
    "wof:name":"Sideman Assoc",
    "wof:placetype":"venue"
},
  "geometry": {"coordinates":[-87.68889900000001,42.012879],"type":"Point"}
}