{
  "type": "Feature",
  "properties": {
    "iso:country":"US",
    "sg:address":"1050 N Rand Rd",
    "sg:city":"Wauconda",
    "sg:classifiers":[
        {
            "category":"Education",
            "subcategory":"Special Training",
            "type":"Public Place"
        }
    ],
    "sg:phone":"+1 847 526 1299",
    "sg:postcode":"60084",
    "sg:province":"IL",
    "sg:tags":[
        "instruction",
        "driving"
    ],
    "wof:name":"ATS Truck Driving School",
    "wof:placetype":"venue"
},
  "geometry": {"coordinates":[-88.154483,42.275366],"type":"Point"}
}