{
  "type": "Feature",
  "properties": {
    "addr:full":"5737 N Kenmore Ave Apt Main Chicago IL 60660",
    "addr:housenumber":"5737",
    "addr:postcode":"60660",
    "addr:street":"N Kenmore Ave Apt Main",
    "iso:country":"US",
    "sg:address":"5737 N Kenmore Ave Apt Main",
    "sg:city":"Chicago",
    "sg:classifiers":[
        {
            "category":"Real Estate",
            "subcategory":"Real Estate Operator",
            "type":"Services"
        }
    ],
    "sg:phone":"+1 773 561 4888",
    "sg:postcode":"60660",
    "sg:province":"IL",
    "sg:tags":[
        "apartment"
    ],
    "wof:name":"Edgewater Apartments",
    "wof:placetype":"venue"
},
  "geometry": {"coordinates":[-87.656494,41.986136],"type":"Point"}
}