{
  "type": "Feature",
  "properties": {
    "addr:full":"53 N Wolf Rd Wheeling IL 60090",
    "addr:housenumber":"53",
    "addr:postcode":"60090",
    "addr:street":"N Wolf Rd",
    "iso:country":"US",
    "sg:address":"53 N Wolf Rd",
    "sg:city":"Wheeling",
    "sg:classifiers":[
        {
            "category":"Shopping",
            "type":"Retail Goods"
        },
        {
            "category":"Food & Beverages",
            "subcategory":"Groceries & Convenience Stores",
            "type":"Retail Goods"
        }
    ],
    "sg:phone":"+1 847 215 4990",
    "sg:postcode":"60090",
    "sg:province":"IL",
    "sg:tags":[
        "merchandise"
    ],
    "wof:name":"La Casa De Alegria Grocery",
    "wof:placetype":"venue"
},
  "geometry": {"coordinates":[-87.915713,42.140668],"type":"Point"}
}