{
  "type": "Feature",
  "properties": {
    "addr:full":"130 18th St Rock Island IL 61201",
    "addr:housenumber":"130",
    "addr:postcode":"61201",
    "addr:street":"18Th St",
    "iso:country":"US",
    "sg:address":"130 18th St",
    "sg:city":"Rock Island",
    "sg:classifiers":[
        {
            "category":"Shopping",
            "subcategory":"Books",
            "type":"Retail Goods"
        }
    ],
    "sg:phone":"+1 309 788 7517",
    "sg:postcode":"61201",
    "sg:province":"IL",
    "sg:tags":[
        "dealer"
    ],
    "wof:name":"Readmore Book World",
    "wof:placetype":"venue"
},
  "geometry": {"coordinates":[-90.57469500000001,41.51139],"type":"Point"}
}