{
  "type": "Feature",
  "properties": {
    "iso:country":"US",
    "sg:address":"217 2nd St",
    "sg:city":"Lincoln",
    "sg:classifiers":[
        {
            "category":"Building & Trades",
            "subcategory":"Construction",
            "type":"Services"
        }
    ],
    "sg:phone":"+1 217 737 6141",
    "sg:postcode":"62656",
    "sg:province":"IL",
    "sg:tags":[
        "wallcoverings-installation",
        "wallpaper",
        "painting",
        "contractor"
    ],
    "wof:name":"J2 Reglazing And Painting",
    "wof:placetype":"venue"
},
  "geometry": {"coordinates":[-89.370859,40.143975],"type":"Point"}
}