{
  "type": "Feature",
  "properties": {
    "addr:full":"2605 S Clearbrook Dr Arlington Hts IL 60005",
    "addr:housenumber":"2605",
    "addr:postcode":"60005",
    "addr:street":"S Clearbrook Dr",
    "iso:country":"US",
    "sg:address":"2605 S Clearbrook Dr",
    "sg:city":"Arlington Hts",
    "sg:classifiers":[
        {
            "category":"Manufacturing",
            "subcategory":"Paper Products",
            "type":"Manufacturing & Wholesale Goods"
        }
    ],
    "sg:phone":"+1 847 434 0970",
    "sg:postcode":"60005",
    "sg:province":"IL",
    "sg:tags":[
        "box"
    ],
    "wof:name":"H Field & Sons",
    "wof:placetype":"venue"
},
  "geometry": {"coordinates":[-87.973647,42.037697],"type":"Point"}
}