{
  "type": "Feature",
  "properties": {
    "iso:country":"US",
    "sg:address":"10831 Meadowsweet Ln",
    "sg:city":"Roscoe",
    "sg:classifiers":[
        {
            "category":"Wholesale",
            "subcategory":"Non-durable Goods",
            "type":"Manufacturing & Wholesale Goods"
        }
    ],
    "sg:phone":"+1 815 439 5690",
    "sg:postcode":"61073",
    "sg:province":"IL",
    "wof:name":"Classic Scents",
    "wof:placetype":"venue"
},
  "geometry": {"coordinates":[-89.038325,42.416346],"type":"Point"}
}