{
  "type": "Feature",
  "properties": {
    "addr:full":"2233 High Point Dr Lake Villa IL 60046",
    "addr:housenumber":"2233",
    "addr:postcode":"60046",
    "addr:street":"High Point Dr",
    "iso:country":"US",
    "sg:address":"2233 High Point Dr",
    "sg:city":"Lake Villa",
    "sg:classifiers":[
        {
            "category":"Wholesale",
            "subcategory":"Machinery & Supplies",
            "type":"Manufacturing & Wholesale Goods"
        }
    ],
    "sg:phone":"+1 847 245 4122",
    "sg:postcode":"60046",
    "sg:province":"IL",
    "sg:tags":[
        "provide",
        "to",
        "federal"
    ],
    "wof:name":"Gps Products & Services Co",
    "wof:placetype":"venue"
},
  "geometry": {"coordinates":[-88.028953,42.425105],"type":"Point"}
}