{
  "type": "Feature",
  "properties": {
    "addr:full":"6300 W 79th St Burbank IL 60459",
    "addr:housenumber":"6300",
    "addr:postcode":"60459",
    "addr:street":"W 79Th St",
    "iso:country":"US",
    "sg:address":"6300 W 79th St",
    "sg:city":"Burbank",
    "sg:classifiers":[
        {
            "category":"Restaurant",
            "type":"Food & Drink"
        }
    ],
    "sg:phone":"+1 708 599 7333",
    "sg:postcode":"60459",
    "sg:province":"IL",
    "wof:name":"Dugout the",
    "wof:placetype":"venue"
},
  "geometry": {"coordinates":[-87.778397,41.7486],"type":"Point"}
}