{
  "type": "Feature",
  "properties": {
    "addr:full":"6902 S Damen Avenue Chicago IL 60636",
    "addr:housenumber":"6902",
    "addr:postcode":"60636",
    "addr:street":"S Damen Avenue",
    "iso:country":"US",
    "sg:address":"6902 S Damen Avenue",
    "sg:city":"Chicago",
    "sg:classifiers":[
        {
            "category":"Manufacturing",
            "subcategory":"Tools & Machinery",
            "type":"Manufacturing & Wholesale Goods"
        },
        {
            "category":"Home & Garden",
            "subcategory":"Hardware",
            "type":"Retail Goods"
        }
    ],
    "sg:phone":"+1 773 434 6972",
    "sg:postcode":"60636",
    "sg:province":"IL",
    "sg:tags":[
        "machine",
        "store",
        "manufacturer"
    ],
    "wof:name":"Neighborhood Tool Shop",
    "wof:placetype":"venue"
},
  "geometry": {"coordinates":[-87.673655,41.767887],"type":"Point"}
}