{
  "type": "Feature",
  "properties": {
    "iso:country":"US",
    "sg:address":"350 W 194th St",
    "sg:city":"Glenwood",
    "sg:classifiers":[
        {
            "category":"Building & Trades",
            "subcategory":"Construction",
            "type":"Services"
        }
    ],
    "sg:phone":"+1 708 754 6450",
    "sg:postcode":"60425",
    "sg:province":"IL",
    "sg:tags":[
        "paving",
        "contractor"
    ],
    "wof:name":"Lagone Paving & Sealcoating",
    "wof:placetype":"venue"
},
  "geometry": {"coordinates":[-87.625815,41.53732],"type":"Point"}
}