{
  "type": "Feature",
  "properties": {
    "iso:country":"US",
    "sg:address":"6336 Bobby Jones Ln",
    "sg:city":"Woodridge",
    "sg:classifiers":[
        {
            "category":"Professional",
            "subcategory":"Computer Services",
            "type":"Services"
        }
    ],
    "sg:phone":"+1 630 369 8428",
    "sg:postcode":"60517",
    "sg:province":"IL",
    "sg:tags":[
        "datum"
    ],
    "wof:name":"Web Resource Center Co",
    "wof:placetype":"venue"
},
  "geometry": {"coordinates":[-88.078601,41.766695],"type":"Point"}
}