{
  "type": "Feature",
  "properties": {
    "addr:full":"102 Porter St Danville IL 61832",
    "addr:housenumber":"102",
    "addr:postcode":"61832",
    "addr:street":"Porter St",
    "iso:country":"US",
    "sg:address":"102 Porter St",
    "sg:city":"Danville",
    "sg:classifiers":[
        {
            "category":"Retail",
            "subcategory":"Self-service Laundry",
            "type":"Services"
        }
    ],
    "sg:phone":"+1 217 446 8442",
    "sg:postcode":"61832",
    "sg:province":"IL",
    "wof:name":"Custom Care Laundromat",
    "wof:placetype":"venue"
},
  "geometry": {"coordinates":[-87.606545,40.129479],"type":"Point"}
}