{
  "type": "Feature",
  "properties": {
    "iso:country":"US",
    "sg:address":"8130 Lincoln Ave",
    "sg:city":"Skokie",
    "sg:classifiers":[
        {
            "category":"Shopping",
            "subcategory":"Bicycles & Sporting Goods",
            "type":"Retail Goods"
        }
    ],
    "sg:phone":"+1 847 675 5286",
    "sg:postcode":"60077",
    "sg:province":"IL",
    "sg:tags":[
        "equipment",
        "mail",
        "golf",
        "supply"
    ],
    "wof:name":"Emil J Lauter Co Inc",
    "wof:placetype":"venue"
},
  "geometry": {"coordinates":[-87.755077,42.028457],"type":"Point"}
}