{
  "type": "Feature",
  "properties": {
    "iso:country":"US",
    "sg:address":"512 1st Ave",
    "sg:city":"Colona",
    "sg:classifiers":[
        {
            "category":"Shopping",
            "subcategory":"Stationery & Office Supplies",
            "type":"Retail Goods"
        },
        {
            "category":"Professional",
            "subcategory":"Accounting & Tax Preparation",
            "type":"Services"
        }
    ],
    "sg:phone":"+1 309 792 1458",
    "sg:postcode":"61241",
    "sg:province":"IL",
    "sg:tags":[
        "equipment",
        "accountant"
    ],
    "wof:name":"Office Express",
    "wof:placetype":"venue"
},
  "geometry": {"coordinates":[-90.36550099999999,41.483898],"type":"Point"}
}