{
  "type": "Feature",
  "properties": {
    "iso:country":"US",
    "sg:address":"1800 Nations Dr Ste 117",
    "sg:city":"Gurnee",
    "sg:classifiers":[
        {
            "category":"Real Estate",
            "subcategory":"Real Estate Services",
            "type":"Services"
        }
    ],
    "sg:phone":"+1 262 909 4372",
    "sg:postcode":"60031",
    "sg:province":"IL",
    "sg:tags":[
        "management"
    ],
    "wof:name":"Dorchester Home Investments",
    "wof:placetype":"venue"
},
  "geometry": {"coordinates":[-87.94268599999999,42.38413],"type":"Point"}
}