{
  "type": "Feature",
  "properties": {
    "addr:full":"555 Arlington Heights Rd Arlington Heights IL 60005",
    "addr:housenumber":"555",
    "addr:postcode":"60005",
    "addr:street":"Arlington Heights Rd",
    "iso:country":"US",
    "sg:address":"555 Arlington Heights Rd",
    "sg:city":"Arlington Heights",
    "sg:classifiers":[
        {
            "category":"Wholesale",
            "subcategory":"Machinery & Supplies",
            "type":"Manufacturing & Wholesale Goods"
        }
    ],
    "sg:phone":"+1 847 952 6500",
    "sg:postcode":"60005",
    "sg:province":"IL",
    "sg:tags":[
        "machine",
        "sales"
    ],
    "wof:name":"Finn-Power International  Inc",
    "wof:placetype":"venue"
},
  "geometry": {"coordinates":[-87.980468,42.074749],"type":"Point"}
}