{
  "type": "Feature",
  "properties": {
    "iso:country":"US",
    "sg:address":"3190 N Elston Avenue",
    "sg:city":"Chicago",
    "sg:classifiers":[
        {
            "category":"Health Services",
            "subcategory":"Dentist",
            "type":"Services"
        }
    ],
    "sg:phone":"+1 773 267 9777",
    "sg:postcode":"60618",
    "sg:province":"IL",
    "wof:name":"Belmont & California Dental Clinic",
    "wof:placetype":"venue"
},
  "geometry": {"coordinates":[-87.69807,41.939375],"type":"Point"}
}