{
  "type": "Feature",
  "properties": {
    "iso:country":"US",
    "sg:address":"5128 N 2nd St",
    "sg:city":"Loves Park",
    "sg:classifiers":[
        {
            "category":"Manufacturing",
            "subcategory":"Printing",
            "type":"Manufacturing & Wholesale Goods"
        }
    ],
    "sg:phone":"+1 815 639 4934",
    "sg:postcode":"61111",
    "sg:province":"IL",
    "sg:tags":[
        "computer",
        "design",
        "system",
        "typesetting"
    ],
    "wof:name":"Fairchild Graphics",
    "wof:placetype":"venue"
},
  "geometry": {"coordinates":[-89.057861,42.305366],"type":"Point"}
}