{
  "type": "Feature",
  "properties": {
    "iso:country":"US",
    "sg:address":"1411 W 5th St",
    "sg:city":"Coal Valley",
    "sg:classifiers":[
        {
            "category":"Building & Trades",
            "subcategory":"Landscaping Services",
            "type":"Services"
        }
    ],
    "sg:phone":"+1 309 799 3959",
    "sg:postcode":"61240",
    "sg:province":"IL",
    "wof:name":"Kymbyl Komplete Kare Inc",
    "wof:placetype":"venue"
},
  "geometry": {"coordinates":[-90.465664,41.436307],"type":"Point"}
}