{
  "type": "Feature",
  "properties": {
    "iso:country":"US",
    "sg:address":"428 S Stuart Ln",
    "sg:city":"Palatine",
    "sg:classifiers":[
        {
            "category":"Professional",
            "subcategory":"Business Services",
            "type":"Services"
        }
    ],
    "sg:phone":"+1 847 359 7845",
    "sg:postcode":"60067",
    "sg:province":"IL",
    "wof:name":"Prime Time Home Inspections",
    "wof:placetype":"venue"
},
  "geometry": {"coordinates":[-88.057149,42.099556],"type":"Point"}
}