{
  "type": "Feature",
  "properties": {
    "addr:full":"7956 S King Dr Chicago IL 60619",
    "addr:housenumber":"7956",
    "addr:postcode":"60619",
    "addr:street":"S King Dr",
    "iso:country":"US",
    "sg:address":"7956 S King Dr",
    "sg:city":"Chicago",
    "sg:classifiers":[
        {
            "category":"Place Of Worship",
            "subcategory":"Church",
            "type":"Public Place"
        },
        {
            "category":"Place Of Worship",
            "type":"Public Place"
        }
    ],
    "sg:phone":"+1 773 723 3232",
    "sg:postcode":"60619",
    "sg:province":"IL",
    "sg:tags":[
        "lutheran",
        "america",
        "churches-lutheran",
        "churches-lutheran-evangelical"
    ],
    "wof:name":"Ephphatha F V Lutheran",
    "wof:placetype":"venue"
},
  "geometry": {"coordinates":[-87.614896,41.750009],"type":"Point"}
}