{
  "type": "Feature",
  "properties": {
    "addr:full":"5645 W Addison St Chicago IL 60634",
    "addr:housenumber":"5645",
    "addr:postcode":"60634",
    "addr:street":"W Addison St",
    "iso:country":"US",
    "sg:address":"5645 W Addison St",
    "sg:city":"Chicago",
    "sg:classifiers":[
        {
            "category":"Health Services",
            "subcategory":"Doctor",
            "type":"Services"
        }
    ],
    "sg:phone":"+1 773 427 0806",
    "sg:postcode":"60634",
    "sg:province":"IL",
    "sg:tags":[
        "physician",
        "radiology",
        "pediatrics-radiology",
        "surgeons",
        "surgeon"
    ],
    "wof:name":"Midwest Radiology Associates, S.C.",
    "wof:placetype":"venue"
},
  "geometry": {"coordinates":[-87.76781800000001,41.945867],"type":"Point"}
}