{
  "type": "Feature",
  "properties": {
    "addr:full":"1812 Glen Park Dr Champaign IL 61821",
    "addr:housenumber":"1812",
    "addr:postcode":"61821",
    "addr:street":"Glen Park Dr",
    "iso:country":"US",
    "sg:address":"1812 Glen Park Dr",
    "sg:city":"Champaign",
    "sg:classifiers":[
        {
            "category":"Shopping",
            "subcategory":"Stationery & Office Supplies",
            "type":"Retail Goods"
        }
    ],
    "sg:phone":"+1   ",
    "sg:postcode":"61821",
    "sg:province":"IL",
    "wof:name":"Mrs BS School Tools",
    "wof:placetype":"venue"
},
  "geometry": {"coordinates":[-88.27864599999999,40.119637],"type":"Point"}
}