{
  "type": "Feature",
  "properties": {
    "iso:country":"US",
    "sg:address":"4301 W 95th St",
    "sg:city":"Oak Lawn",
    "sg:classifiers":[
        {
            "category":"Health Services",
            "subcategory":"Doctor",
            "type":"Services"
        }
    ],
    "sg:phone":"+1 708 425 4100",
    "sg:postcode":"60453",
    "sg:province":"IL",
    "wof:name":"Defilippo Mary E",
    "wof:placetype":"venue"
},
  "geometry": {"coordinates":[-87.729422,41.720113],"type":"Point"}
}