{
  "type": "Feature",
  "properties": {
    "iso:country":"US",
    "sg:address":"5939 N Saint Louis Ave",
    "sg:city":"Chicago",
    "sg:classifiers":[
        {
            "category":"Professional",
            "subcategory":"Advertising",
            "type":"Services"
        }
    ],
    "sg:phone":"+1 773 463 2200",
    "sg:postcode":"60659",
    "sg:province":"IL",
    "sg:tags":[
        "sample",
        "product",
        "service-circular",
        "specialty",
        "distributing",
        "advertising-promotional"
    ],
    "wof:name":"A To Z You Name It",
    "wof:placetype":"venue"
},
  "geometry": {"coordinates":[-87.71631499999999,41.988746],"type":"Point"}
}