{
  "type": "Feature",
  "properties": {
    "iso:country":"US",
    "sg:address":"8720 W Stuenkel Rd",
    "sg:city":"Frankfort",
    "sg:classifiers":[
        {
            "category":"Organizations",
            "subcategory":"Community Association",
            "type":"Services"
        }
    ],
    "sg:phone":"+1 815 469 8305",
    "sg:postcode":"60423",
    "sg:province":"IL",
    "wof:name":"Delta Kappa Gamma Society",
    "wof:placetype":"venue"
},
  "geometry": {"coordinates":[-87.82525699999999,41.455441],"type":"Point"}
}