{
  "type": "Feature",
  "properties": {
    "addr:full":"164 W 144th St Riverdale IL 60827",
    "addr:housenumber":"164",
    "addr:postcode":"60827",
    "addr:street":"W 144Th St",
    "iso:country":"US",
    "sg:address":"164 W 144th St",
    "sg:city":"Riverdale",
    "sg:classifiers":[
        {
            "category":"Personal",
            "subcategory":"Beauty Salon",
            "type":"Services"
        }
    ],
    "sg:phone":"+1 708 201 1177",
    "sg:postcode":"60827",
    "sg:province":"IL",
    "sg:tags":[
        "nail",
        "salons-equipment",
        "manicuring",
        "supply"
    ],
    "wof:name":"A Touch of Beauty",
    "wof:placetype":"venue"
},
  "geometry": {"coordinates":[-87.62629699999999,41.633499],"type":"Point"}
}