{
  "type": "Feature",
  "properties": {
    "addr:full":"6311 North Ave Oak Park IL 60302",
    "addr:housenumber":"6311",
    "addr:postcode":"60302",
    "addr:street":"North Ave",
    "iso:country":"US",
    "sg:address":"6311 North Ave",
    "sg:city":"Oak Park",
    "sg:classifiers":[
        {
            "category":"Deli",
            "type":"Food & Drink"
        }
    ],
    "sg:phone":"+1 708 386 1306",
    "sg:postcode":"60302",
    "sg:province":"IL",
    "wof:name":"AP Deli",
    "wof:placetype":"venue"
},
  "geometry": {"coordinates":[-87.783548,41.90914],"type":"Point"}
}