{
  "type": "Feature",
  "properties": {
    "addr:full":"5015 N Clark St Chicago IL 60640",
    "addr:housenumber":"5015",
    "addr:postcode":"60640",
    "addr:street":"N Clark St",
    "iso:country":"US",
    "sg:address":"5015 N Clark St",
    "sg:city":"Chicago",
    "sg:classifiers":[
        {
            "category":"Bars & Pubs",
            "subcategory":"Nightclub",
            "type":"Food & Drink"
        }
    ],
    "sg:phone":"+1 773 728 0050",
    "sg:postcode":"60640",
    "sg:province":"IL",
    "sg:tags":[
        "nightlife"
    ],
    "wof:name":"Chgo Eagle",
    "wof:placetype":"venue"
},
  "geometry": {"coordinates":[-87.668198,41.973099],"type":"Point"}
}