{
  "type": "Feature",
  "properties": {
    "addr:full":"237 W 75th Street Chicago IL 60620",
    "addr:housenumber":"237",
    "addr:postcode":"60620",
    "addr:street":"W 75Th Street",
    "iso:country":"US",
    "sg:address":"237 W 75th Street",
    "sg:city":"Chicago",
    "sg:classifiers":[
        {
            "category":"Home & Garden",
            "subcategory":"Furniture",
            "type":"Retail Goods"
        }
    ],
    "sg:phone":"+1 773 488 0581",
    "sg:postcode":"60620",
    "sg:province":"IL",
    "sg:tags":[
        "store"
    ],
    "wof:name":"Royal Ham Management",
    "wof:placetype":"venue"
},
  "geometry": {"coordinates":[-87.630675,41.757931],"type":"Point"}
}