{
  "type": "Feature",
  "properties": {
    "iso:country":"US",
    "sg:address":"2214 Range Rd",
    "sg:city":"Loves Park",
    "sg:classifiers":[
        {
            "category":"Manufacturing",
            "subcategory":"Glass & Minerals",
            "type":"Manufacturing & Wholesale Goods"
        }
    ],
    "sg:phone":"+1 815 654 0323",
    "sg:postcode":"61111",
    "sg:province":"IL",
    "sg:tags":[
        "product",
        "mfg",
        "sink",
        "marble"
    ],
    "wof:name":"E J Quality Marble Co",
    "wof:placetype":"venue"
},
  "geometry": {"coordinates":[-89.01727099999999,42.342565],"type":"Point"}
}