{
  "type": "Feature",
  "properties": {
    "iso:country":"US",
    "sg:address":"125 N Tremont St",
    "sg:city":"Kewanee",
    "sg:classifiers":[
        {
            "category":"Shopping",
            "type":"Retail Goods"
        }
    ],
    "sg:phone":"+1   ",
    "sg:postcode":"61443",
    "sg:province":"IL",
    "sg:tags":[
        "equipment",
        "medical",
        "supply"
    ],
    "wof:name":"Kewanee Home Medical Equipment",
    "wof:placetype":"venue"
},
  "geometry": {"coordinates":[-89.926428,41.244245],"type":"Point"}
}