{
  "type": "Feature",
  "properties": {
    "iso:country":"US",
    "sg:address":"333 N Michigan Ave # 410",
    "sg:city":"Chicago",
    "sg:classifiers":[
        {
            "category":"Communications",
            "type":"Services"
        }
    ],
    "sg:phone":"+1 312 201 1626",
    "sg:postcode":"60601",
    "sg:province":"IL",
    "sg:tags":[
        "translator",
        "interpreter"
    ],
    "wof:name":"German-Merican Bus Translation",
    "wof:placetype":"venue"
},
  "geometry": {"coordinates":[-87.624456,41.887324],"type":"Point"}
}