{
  "type": "Feature",
  "properties": {
    "iso:country":"US",
    "sg:address":"4525 W Madison St",
    "sg:city":"Chicago",
    "sg:classifiers":[
        {
            "category":"Shopping",
            "subcategory":"Tobacco",
            "type":"Retail Goods"
        },
        {
            "category":"Food & Beverages",
            "subcategory":"Groceries & Convenience Stores",
            "type":"Retail Goods"
        }
    ],
    "sg:phone":"+1 773 378 5353",
    "sg:postcode":"60624",
    "sg:province":"IL",
    "sg:tags":[
        "shop"
    ],
    "wof:name":"Dearborn Wholesale Grocers Lp Self-Service Center",
    "wof:placetype":"venue"
},
  "geometry": {"coordinates":[-87.739197,41.880402],"type":"Point"}
}