{
  "type": "Feature",
  "properties": {
    "addr:full":"288 E Geneva Rd Wheaton IL 60187",
    "addr:housenumber":"288",
    "addr:postcode":"60187",
    "addr:street":"E Geneva Rd",
    "iso:country":"US",
    "sg:address":"288 E Geneva Rd",
    "sg:city":"Wheaton",
    "sg:classifiers":[
        {
            "category":"Real Estate",
            "subcategory":"Real Estate Agent",
            "type":"Services"
        }
    ],
    "sg:phone":"+1 630 909 1600",
    "sg:postcode":"60187",
    "sg:province":"IL",
    "wof:name":"RMS Properties Inc",
    "wof:placetype":"venue"
},
  "geometry": {"coordinates":[-88.104,41.888069],"type":"Point"}
}