{
  "type": "Feature",
  "properties": {
    "addr:full":"5 Stuart Dr Kankakee IL 60901",
    "addr:housenumber":"5",
    "addr:postcode":"60901",
    "addr:street":"Stuart Dr",
    "iso:country":"US",
    "sg:address":"5 Stuart Dr",
    "sg:city":"Kankakee",
    "sg:classifiers":[
        {
            "category":"Shopping",
            "type":"Retail Goods"
        }
    ],
    "sg:phone":"+1 815 933 5574",
    "sg:postcode":"60901",
    "sg:province":"IL",
    "sg:tags":[
        "ice"
    ],
    "wof:name":"Home City Ice",
    "wof:placetype":"venue"
},
  "geometry": {"coordinates":[-87.869748,41.078744],"type":"Point"}
}