{
  "type": "Feature",
  "properties": {
    "iso:country":"US",
    "sg:address":"2358 1625 East St",
    "sg:city":"Bradford",
    "sg:classifiers":[
        {
            "category":"Farming",
            "subcategory":"Livestock Farm",
            "type":"Manufacturing & Wholesale Goods"
        },
        {
            "category":"Farming",
            "subcategory":"Farm",
            "type":"Manufacturing & Wholesale Goods"
        }
    ],
    "sg:phone":"+1 309 897 8044",
    "sg:postcode":"61421",
    "sg:province":"IL",
    "sg:tags":[
        "ranch"
    ],
    "wof:name":"Cowser Field & Feedlot",
    "wof:placetype":"venue"
},
  "geometry": {"coordinates":[-89.54405199999999,41.18391],"type":"Point"}
}