{
  "type": "Feature",
  "properties": {
    "iso:country":"US",
    "sg:address":"24586 W Oak St",
    "sg:city":"Round Lake",
    "sg:classifiers":[
        {
            "category":"Building & Trades",
            "subcategory":"Construction",
            "type":"Services"
        }
    ],
    "sg:phone":"+1 847 546 0498",
    "sg:postcode":"60073",
    "sg:province":"IL",
    "sg:tags":[
        "painter"
    ],
    "wof:name":"Krefting Decorating",
    "wof:placetype":"venue"
},
  "geometry": {"coordinates":[-88.112718,42.375664],"type":"Point"}
}