{
  "type": "Feature",
  "properties": {
    "addr:full":"1250 Mackinaw Ave Calumet City IL 60409",
    "addr:housenumber":"1250",
    "addr:postcode":"60409",
    "addr:street":"Mackinaw Ave",
    "iso:country":"US",
    "sg:address":"1250 Mackinaw Ave",
    "sg:city":"Calumet City",
    "sg:classifiers":[
        {
            "category":"Social Services",
            "subcategory":"Child Care",
            "type":"Services"
        }
    ],
    "sg:phone":"+1 708 862 2171",
    "sg:postcode":"60409",
    "sg:province":"IL",
    "wof:name":"Tiptot Toddlers Daycares",
    "wof:placetype":"venue"
},
  "geometry": {"coordinates":[-87.541915,41.597388],"type":"Point"}
}