{
  "type": "Feature",
  "properties": {
    "iso:country":"US",
    "sg:address":"614 Cherbourg Dr",
    "sg:city":"Buffalo Grove",
    "sg:classifiers":[
        {
            "category":"Professional",
            "subcategory":"Management & Consulting",
            "type":"Services"
        }
    ],
    "sg:phone":"+1 847 913 8668",
    "sg:postcode":"60089",
    "sg:province":"IL",
    "sg:tags":[
        "training",
        "program",
        "customized",
        "related"
    ],
    "wof:name":"Nielsen Associates Inc",
    "wof:placetype":"venue"
},
  "geometry": {"coordinates":[-87.96259499999999,42.162552],"type":"Point"}
}