{
  "type": "Feature",
  "properties": {
    "addr:full":"1608 Mohler Ct Naperville IL 60563",
    "addr:housenumber":"1608",
    "addr:postcode":"60563",
    "addr:street":"Mohler Ct",
    "iso:country":"US",
    "sg:address":"1608 Mohler Ct",
    "sg:city":"Naperville",
    "sg:classifiers":[
        {
            "category":"Real Estate",
            "subcategory":"Real Estate Services",
            "type":"Services"
        },
        {
            "category":"Real Estate",
            "subcategory":"Real Estate Agent",
            "type":"Services"
        }
    ],
    "sg:phone":"+1 630 778 8500",
    "sg:postcode":"60563",
    "sg:province":"IL",
    "sg:tags":[
        "buyer",
        "broker"
    ],
    "wof:name":"Pro Reality Group",
    "wof:placetype":"venue"
},
  "geometry": {"coordinates":[-88.158145,41.797193],"type":"Point"}
}