{
  "type": "Feature",
  "properties": {
    "addr:full":"720 E State St Geneva IL 60134",
    "addr:housenumber":"720",
    "addr:postcode":"60134",
    "addr:street":"E State St",
    "iso:country":"US",
    "sg:address":"720 E State St",
    "sg:city":"Geneva",
    "sg:classifiers":[
        {
            "category":"Shopping",
            "subcategory":"Used Merchandise",
            "type":"Retail Goods"
        }
    ],
    "sg:phone":"+1 630 845 9291",
    "sg:postcode":"60134",
    "sg:province":"IL",
    "sg:tags":[
        "antique",
        "coin",
        "supply"
    ],
    "sg:website":"http://www.meanddadstoys.com",
    "wof:name":"Me & Dad's Collectibles",
    "wof:placetype":"venue"
},
  "geometry": {"coordinates":[-88.291667,41.886889],"type":"Point"}
}