{
  "type": "Feature",
  "properties": {
    "iso:country":"US",
    "sg:address":"409 Greenfield St",
    "sg:city":"Oak Park",
    "sg:classifiers":[
        {
            "category":"Organizations",
            "subcategory":"Religious Organization",
            "type":"Services"
        }
    ],
    "sg:phone":"+1 708 386 1576",
    "sg:postcode":"60302",
    "sg:province":"IL",
    "wof:name":"United Lutheran Church",
    "wof:placetype":"venue"
},
  "geometry": {"coordinates":[-87.783608,41.905646],"type":"Point"}
}