{
  "type": "Feature",
  "properties": {
    "addr:full":"1101 S Canal St Chicago IL 60607",
    "addr:housenumber":"1101",
    "addr:postcode":"60607",
    "addr:street":"S Canal St",
    "iso:country":"US",
    "sg:address":"1101 S Canal St",
    "sg:city":"Chicago",
    "sg:classifiers":[
        {
            "category":"Parking",
            "type":"Transportation"
        }
    ],
    "sg:phone":"+1 312 341 1715",
    "sg:postcode":"60607",
    "sg:province":"IL",
    "sg:website":"www.standardparking.com",
    "wof:name":"Standard Parking",
    "wof:placetype":"venue"
},
  "geometry": {"coordinates":[-87.63900700000001,41.868225],"type":"Point"}
}