{
  "type": "Feature",
  "properties": {
    "iso:country":"US",
    "sg:address":"7010 W 111th St",
    "sg:city":"Worth",
    "sg:classifiers":[
        {
            "category":"Sports & Exercise",
            "subcategory":"Gym",
            "type":"Entertainment"
        }
    ],
    "sg:phone":"+1 708 923 1000",
    "sg:postcode":"60482",
    "sg:province":"IL",
    "sg:tags":[
        "fitness",
        "physical",
        "facility"
    ],
    "wof:name":"Curves For Women",
    "wof:placetype":"venue"
},
  "geometry": {"coordinates":[-87.795129,41.690108],"type":"Point"}
}