{
  "type": "Feature",
  "properties": {
    "addr:full":"520 N Michigan Chicago IL 60611",
    "addr:housenumber":"520",
    "addr:postcode":"60611",
    "addr:street":"N",
    "iso:country":"US",
    "sg:address":"520 N Michigan",
    "sg:city":"Chicago",
    "sg:classifiers":[
        {
            "category":"Restaurant",
            "type":"Food & Drink"
        }
    ],
    "sg:postcode":"60611",
    "sg:province":"IL",
    "wof:name":"Coast Burger",
    "wof:placetype":"venue"
},
  "geometry": {"coordinates":[-87.624168,41.89158],"type":"Point"}
}