{
  "type": "Feature",
  "properties": {
    "addr:full":"20108 S Pine Hill Rd Frankfort IL 60423",
    "addr:housenumber":"20108",
    "addr:postcode":"60423",
    "addr:street":"S Pine Hill Rd",
    "iso:country":"US",
    "sg:address":"20108 S Pine Hill Rd",
    "sg:city":"Frankfort",
    "sg:classifiers":[
        {
            "category":"Local Transit",
            "type":"Transportation"
        }
    ],
    "sg:phone":"+1 815 469 1415",
    "sg:postcode":"60423",
    "sg:province":"IL",
    "sg:tags":[
        "passenger"
    ],
    "wof:name":"M and M Limousine Leasing Ltd",
    "wof:placetype":"venue"
},
  "geometry": {"coordinates":[-87.81457,41.524878],"type":"Point"}
}