{
  "type": "Feature",
  "properties": {
    "iso:country":"US",
    "sg:address":"1055 Stevenson Ct",
    "sg:city":"Roselle",
    "sg:classifiers":[
        {
            "category":"Manufacturing",
            "subcategory":"Chemicals & Compounds",
            "type":"Manufacturing & Wholesale Goods"
        }
    ],
    "sg:phone":"+1 630 259 8900",
    "sg:postcode":"60172",
    "sg:province":"IL",
    "sg:tags":[
        "chemicals-wholesale",
        "manufacturer"
    ],
    "wof:name":"Tionicon",
    "wof:placetype":"venue"
},
  "geometry": {"coordinates":[-88.05219700000001,41.985829],"type":"Point"}
}