{
  "type": "Feature",
  "properties": {
    "iso:country":"US",
    "sg:address":"140 N Commercial St",
    "sg:city":"Centralia",
    "sg:classifiers":[
        {
            "category":"Shopping",
            "subcategory":"Florist",
            "type":"Retail Goods"
        }
    ],
    "sg:phone":"+1 618 532 9451",
    "sg:postcode":"62801",
    "sg:province":"IL",
    "wof:name":"Hutchison Florist",
    "wof:placetype":"venue"
},
  "geometry": {"coordinates":[-89.130686,38.547417],"type":"Point"}
}