{
  "type": "Feature",
  "properties": {
    "addr:full":"219 Main St Roselle IL 60172",
    "addr:housenumber":"219",
    "addr:postcode":"60172",
    "addr:street":"Main St",
    "iso:country":"US",
    "sg:address":"219 Main St",
    "sg:city":"Roselle",
    "sg:classifiers":[
        {
            "category":"Sports & Exercise",
            "subcategory":"Gym",
            "type":"Entertainment"
        }
    ],
    "sg:phone":"+1 630 307 0044",
    "sg:postcode":"60172",
    "sg:province":"IL",
    "sg:tags":[
        "trainer"
    ],
    "wof:name":"Anytime Fitness",
    "wof:placetype":"venue"
},
  "geometry": {"coordinates":[-88.07445800000001,41.982683],"type":"Point"}
}