{
  "type": "Feature",
  "properties": {
    "addr:full":"519 W Front St Wheaton IL 60187",
    "addr:housenumber":"519",
    "addr:postcode":"60187",
    "addr:street":"W Front St",
    "iso:country":"US",
    "sg:address":"519 W Front St",
    "sg:city":"Wheaton",
    "sg:classifiers":[
        {
            "category":"Shopping",
            "subcategory":"Gifts & Souvenirs",
            "type":"Retail Goods"
        }
    ],
    "sg:phone":"+1 630 510 9770",
    "sg:postcode":"60187",
    "sg:province":"IL",
    "sg:tags":[
        "printing",
        "commercial"
    ],
    "wof:name":"Thia & Co",
    "wof:placetype":"venue"
},
  "geometry": {"coordinates":[-88.114605,41.86503],"type":"Point"}
}