{
  "type": "Feature",
  "properties": {
    "addr:full":"509 W Upper St Cambridge IL 61238",
    "addr:housenumber":"509",
    "addr:postcode":"61238",
    "addr:street":"W Upper St",
    "iso:country":"US",
    "sg:address":"509 W Upper St",
    "sg:city":"Cambridge",
    "sg:classifiers":[
        {
            "category":"Building & Trades",
            "subcategory":"Construction",
            "type":"Services"
        }
    ],
    "sg:phone":"+1 309 937 5363",
    "sg:postcode":"61238",
    "sg:province":"IL",
    "sg:tags":[
        "house"
    ],
    "wof:name":"G A Wiles Builder",
    "wof:placetype":"venue"
},
  "geometry": {"coordinates":[-90.197306,41.309568],"type":"Point"}
}