{
  "type": "Feature",
  "properties": {
    "iso:country":"US",
    "sg:address":"6316 N Northwest Hwy",
    "sg:city":"Chicago",
    "sg:classifiers":[
        {
            "category":"Building & Trades",
            "subcategory":"Construction",
            "type":"Services"
        }
    ],
    "sg:phone":"+1 773 775 0170",
    "sg:postcode":"60631",
    "sg:province":"IL",
    "sg:tags":[
        "contractor"
    ],
    "wof:name":"Daniels Walter Construction Company",
    "wof:placetype":"venue"
},
  "geometry": {"coordinates":[-87.80596799999999,41.996625],"type":"Point"}
}