{
  "type": "Feature",
  "properties": {
    "iso:country":"US",
    "sg:address":"55 Barney Dr",
    "sg:city":"Joliet",
    "sg:classifiers":[
        {
            "category":"Autos & Motor Vehicles",
            "subcategory":"Automobile Sales",
            "type":"Retail Goods"
        }
    ],
    "sg:phone":"+1 815 744 8478",
    "sg:postcode":"60435",
    "sg:province":"IL",
    "sg:tags":[
        "car",
        "used",
        "dealer"
    ],
    "wof:name":"Darcy's Guaranteed Credit",
    "wof:placetype":"venue"
},
  "geometry": {"coordinates":[-88.143252,41.52295],"type":"Point"}
}