{
  "type": "Feature",
  "properties": {
    "addr:full":"1710 Chatham Cir Deerfield IL 60015",
    "addr:housenumber":"1710",
    "addr:postcode":"60015",
    "addr:street":"Chatham Cir",
    "iso:country":"US",
    "sg:address":"1710 Chatham Cir",
    "sg:city":"Deerfield",
    "sg:classifiers":[
        {
            "category":"Professional",
            "type":"Services"
        }
    ],
    "sg:phone":"+1 847 323 2401",
    "sg:postcode":"60015",
    "sg:province":"IL",
    "wof:name":"Scipertek",
    "wof:placetype":"venue"
},
  "geometry": {"coordinates":[-87.871426,42.171568],"type":"Point"}
}