{
  "type": "Feature",
  "properties": {
    "addr:full":"215 E Noleman St Centralia IL 62801",
    "addr:housenumber":"215",
    "addr:postcode":"62801",
    "addr:street":"E Noleman St",
    "iso:country":"US",
    "sg:address":"215 E Noleman St",
    "sg:city":"Centralia",
    "sg:classifiers":[
        {
            "category":"Shopping",
            "subcategory":"Used Merchandise",
            "type":"Retail Goods"
        }
    ],
    "sg:phone":"+1   ",
    "sg:postcode":"62801",
    "sg:province":"IL",
    "wof:name":"Top Dollar Pawn Inc",
    "wof:placetype":"venue"
},
  "geometry": {"coordinates":[-89.133746,38.52881],"type":"Point"}
}