{
  "type": "Feature",
  "properties": {
    "addr:full":"4821 N Kedzie Ave Chicago IL 60625",
    "addr:housenumber":"4821",
    "addr:postcode":"60625",
    "addr:street":"N Kedzie Ave",
    "iso:country":"US",
    "sg:address":"4821 N Kedzie Ave",
    "sg:city":"Chicago",
    "sg:classifiers":[
        {
            "category":"Coffee & Tea",
            "type":"Food & Drink"
        },
        {
            "category":"Donuts",
            "subcategory":"None",
            "type":"Food & Drink"
        }
    ],
    "sg:phone":"+1 773 463 2691",
    "sg:postcode":"60625",
    "sg:province":"IL",
    "sg:tags":[
        "shop",
        "espresso",
        "restaurant"
    ],
    "sg:website":"www.dunkindonuts.com",
    "wof:name":"Dunkin' Donuts",
    "wof:placetype":"venue"
},
  "geometry": {"coordinates":[-87.708313,41.968964],"type":"Point"}
}