{
  "type": "Feature",
  "properties": {
    "iso:country":"US",
    "sg:address":"1251 Dundee Ave",
    "sg:city":"Elgin",
    "sg:classifiers":[
        {
            "category":"Real Estate",
            "subcategory":"Real Estate Agent",
            "type":"Services"
        }
    ],
    "sg:phone":"+1 847 888 3100",
    "sg:postcode":"60120",
    "sg:province":"IL",
    "sg:tags":[
        "preparation",
        "tax",
        "return"
    ],
    "wof:name":"Karner & Assocs",
    "wof:placetype":"venue"
},
  "geometry": {"coordinates":[-88.26573500000001,42.060993],"type":"Point"}
}