{
  "type": "Feature",
  "properties": {
    "iso:country":"US",
    "sg:address":"1368 Shermer Rd",
    "sg:city":"Northbrook",
    "sg:classifiers":[
        {
            "category":"Banks & Credit Unions",
            "subcategory":"Bank",
            "type":"Services"
        }
    ],
    "sg:phone":"+1 847 509 0352",
    "sg:postcode":"60062",
    "sg:province":"IL",
    "wof:name":"Success National Bank",
    "wof:placetype":"venue"
},
  "geometry": {"coordinates":[-87.82851599999999,42.127766],"type":"Point"}
}