{
  "type": "Feature",
  "properties": {
    "iso:country":"US",
    "sg:address":"801 Dunbar Ct",
    "sg:city":"Schaumburg",
    "sg:classifiers":[
        {
            "category":"Manufacturing",
            "subcategory":"Printing",
            "type":"Manufacturing & Wholesale Goods"
        }
    ],
    "sg:phone":"+1 847 519 9926",
    "sg:postcode":"60194",
    "sg:province":"IL",
    "sg:tags":[
        "commercial"
    ],
    "wof:name":"Willchar Ent",
    "wof:placetype":"venue"
},
  "geometry": {"coordinates":[-88.1271,42.04104],"type":"Point"}
}