{
  "type": "Feature",
  "properties": {
    "addr:full":"444 N Wabash Ave Suite 500 Chicago IL 60611",
    "addr:housenumber":"444",
    "addr:postcode":"60611",
    "addr:street":"N Wabash Ave Suite 500",
    "iso:country":"US",
    "sg:address":"444 N Wabash Ave Suite 500",
    "sg:city":"Chicago",
    "sg:classifiers":[
        {
            "category":"Professional",
            "subcategory":"Computer Services",
            "type":"Services"
        }
    ],
    "sg:phone":"+1 312 595 9209",
    "sg:postcode":"60611",
    "sg:province":"IL",
    "sg:tags":[
        "commercial-real-estate",
        "search-engine"
    ],
    "sg:website":"http://www.commercialiq.com",
    "wof:name":"Commercial IQ",
    "wof:placetype":"venue"
},
  "geometry": {"coordinates":[-87.62675900000001,41.890688],"type":"Point"}
}