{
  "type": "Feature",
  "properties": {
    "addr:full":"1388 Co Rd 300 E Champaign IL 61853",
    "addr:housenumber":"1388",
    "addr:postcode":"61853",
    "addr:street":"Co Rd 300 E",
    "iso:country":"US",
    "sg:address":"1388 Co Rd 300 E",
    "sg:city":"Champaign",
    "sg:phone":"+1 217 687 2812",
    "sg:postcode":"61853",
    "sg:province":"IL",
    "sg:tags":[
        "beef",
        "farm",
        "corn",
        "soybean",
        "cattle",
        "feedlot"
    ],
    "wof:name":"C-Mor Beef Farms",
    "wof:placetype":"venue"
},
  "geometry": {"coordinates":[-88.407723,40.182818],"type":"Point"}
}