{
  "type": "Feature",
  "properties": {
    "iso:country":"US",
    "sg:address":"391 Arbor St",
    "sg:city":"Niota",
    "sg:classifiers":[
        {
            "category":"Bars & Pubs",
            "type":"Food & Drink"
        }
    ],
    "sg:phone":"+1 217 448 4771",
    "sg:postcode":"62358",
    "sg:province":"IL",
    "wof:name":"Wye Knot Tavern",
    "wof:placetype":"venue"
},
  "geometry": {"coordinates":[-91.284616,40.617449],"type":"Point"}
}