{
  "type": "Feature",
  "properties": {
    "iso:country":"US",
    "sg:address":"25649 S Susan Ln",
    "sg:city":"Crete",
    "sg:classifiers":[
        {
            "category":"Building & Trades",
            "subcategory":"Construction",
            "type":"Services"
        }
    ],
    "sg:phone":"+1 708 672 8057",
    "sg:postcode":"60417",
    "sg:province":"IN",
    "sg:tags":[
        "general",
        "contractor"
    ],
    "wof:name":"Giammarco Construction Co",
    "wof:placetype":"venue"
},
  "geometry": {"coordinates":[-87.53572,41.428812],"type":"Point"}
}