{
  "type": "Feature",
  "properties": {
    "iso:country":"US",
    "sg:address":"507 Richardson Ave",
    "sg:city":"Ashton",
    "sg:classifiers":[
        {
            "category":"Manufacturing",
            "subcategory":"Buildings",
            "type":"Manufacturing & Wholesale Goods"
        },
        {
            "category":"Building & Trades",
            "subcategory":"Construction",
            "type":"Services"
        }
    ],
    "sg:phone":"+1 815 994 2101",
    "sg:postcode":"61006",
    "sg:province":"IL",
    "sg:tags":[
        "home",
        "builder",
        "contractor"
    ],
    "wof:name":"Economy Landscape & Const",
    "wof:placetype":"venue"
},
  "geometry": {"coordinates":[-89.226152,41.864214],"type":"Point"}
}