{
  "type": "Feature",
  "properties": {
    "iso:country":"US",
    "sg:address":"501 N Lee St",
    "sg:city":"Bloomington",
    "sg:classifiers":[
        {
            "category":"Real Estate",
            "subcategory":"Real Estate Services",
            "type":"Services"
        },
        {
            "category":"Building & Trades",
            "subcategory":"Cleaning & Sanitation",
            "type":"Services"
        }
    ],
    "sg:phone":"+1 309 829 8760",
    "sg:postcode":"61701",
    "sg:province":"IL",
    "sg:tags":[
        "maintenance",
        "cleaners-interior"
    ],
    "wof:name":"Betinas Cleaning Service",
    "wof:placetype":"venue"
},
  "geometry": {"coordinates":[-88.99756600000001,40.48225],"type":"Point"}
}