{
  "type": "Feature",
  "properties": {
    "iso:country":"US",
    "sg:address":"20676 Wallingford Ln",
    "sg:city":"Barrington",
    "sg:classifiers":[
        {
            "category":"Professional",
            "type":"Services"
        },
        {
            "category":"Professional",
            "subcategory":"Accounting & Tax Preparation",
            "type":"Services"
        }
    ],
    "sg:phone":"+1 847 382 2437",
    "sg:postcode":"60010",
    "sg:province":"IL",
    "sg:tags":[
        "accountant",
        "establishment"
    ],
    "wof:name":"Tassi & Co",
    "wof:placetype":"venue"
},
  "geometry": {"coordinates":[-88.070267,42.157981],"type":"Point"}
}