{
  "type": "Feature",
  "properties": {
    "iso:country":"US",
    "sg:address":"1066 N Marshfield Ave",
    "sg:city":"Chicago",
    "sg:classifiers":[
        {
            "category":"Communications",
            "type":"Services"
        }
    ],
    "sg:phone":"+1 773 661 2338",
    "sg:postcode":"60622",
    "sg:province":"IL",
    "sg:tags":[
        "web",
        "design"
    ],
    "wof:name":"Design Kiwi9",
    "wof:placetype":"venue"
},
  "geometry": {"coordinates":[-87.66889,41.901557],"type":"Point"}
}