{
  "type": "Feature",
  "properties": {
    "addr:full":"142 Army Trail Rd Glendale Heights IL 60139",
    "addr:housenumber":"142",
    "addr:postcode":"60139",
    "addr:street":"Army Trail Rd",
    "iso:country":"US",
    "sg:address":"142 Army Trail Rd",
    "sg:city":"Glendale Heights",
    "sg:classifiers":[
        {
            "category":"Organizations",
            "subcategory":"Community Association",
            "type":"Services"
        }
    ],
    "sg:phone":"+1 630 894 1358",
    "sg:postcode":"60139",
    "sg:province":"IL",
    "wof:name":"Post 2377",
    "wof:placetype":"venue"
},
  "geometry": {"coordinates":[-88.08443699999999,41.937577],"type":"Point"}
}