{
  "type": "Feature",
  "properties": {
    "iso:country":"US",
    "sg:address":"2700 S Lawndale Avenue",
    "sg:city":"Chicago",
    "sg:classifiers":[
        {
            "category":"Professional",
            "subcategory":"Employment Agencies",
            "type":"Services"
        }
    ],
    "sg:phone":"+1 773 542 1436",
    "sg:postcode":"60623",
    "sg:province":"IL",
    "wof:name":"Custom Staffing",
    "wof:placetype":"venue"
},
  "geometry": {"coordinates":[-87.717223,41.842334],"type":"Point"}
}