{
  "type": "Feature",
  "properties": {
    "iso:country":"US",
    "sg:address":"1226 Orchard Rd Apt A",
    "sg:city":"Bloomington",
    "sg:classifiers":[
        {
            "category":"Manufacturing",
            "subcategory":"Buildings",
            "type":"Manufacturing & Wholesale Goods"
        },
        {
            "category":"Real Estate",
            "subcategory":"Developer",
            "type":"Services"
        },
        {
            "category":"Building & Trades",
            "subcategory":"Construction",
            "type":"Services"
        }
    ],
    "sg:phone":"+1 309 662 3374",
    "sg:postcode":"61704",
    "sg:province":"IL",
    "sg:tags":[
        "home",
        "builder",
        "contractor"
    ],
    "wof:name":"Scott Weller Homes Inc",
    "wof:placetype":"venue"
},
  "geometry": {"coordinates":[-88.950541,40.490101],"type":"Point"}
}