{
  "type": "Feature",
  "properties": {
    "iso:country":"US",
    "sg:address":"100 Brook Ct",
    "sg:city":"Bolingbrook",
    "sg:classifiers":[
        {
            "category":"Professional",
            "subcategory":"Advertising",
            "type":"Services"
        },
        {
            "category":"Retail",
            "subcategory":"Auto Repair",
            "type":"Services"
        }
    ],
    "sg:phone":"+1 630 759 7854",
    "sg:postcode":"60440",
    "sg:province":"IL",
    "sg:tags":[
        "coupon",
        "brake"
    ],
    "wof:name":"Bob & Tod's Auto Care",
    "wof:placetype":"venue"
},
  "geometry": {"coordinates":[-88.068489,41.704281],"type":"Point"}
}