{
  "type": "Feature",
  "properties": {
    "iso:country":"US",
    "sg:address":"1323 N Park Dr",
    "sg:city":"Round Lake Beach",
    "sg:classifiers":[
        {
            "category":"Taxi",
            "type":"Transportation"
        }
    ],
    "sg:phone":"+1 847 546 6388",
    "sg:postcode":"60073",
    "sg:province":"IL",
    "sg:tags":[
        "taxicab"
    ],
    "wof:name":"White & Yellow Taxi",
    "wof:placetype":"venue"
},
  "geometry": {"coordinates":[-88.088524,42.373477],"type":"Point"}
}