{
  "type": "Feature",
  "properties": {
    "addr:full":"5235 N Kedzie Ave Chicago IL 60625",
    "addr:housenumber":"5235",
    "addr:postcode":"60625",
    "addr:street":"N Kedzie Ave",
    "iso:country":"US",
    "sg:address":"5235 N Kedzie Ave",
    "sg:city":"Chicago",
    "sg:classifiers":[
        {
            "category":"Banks & Credit Unions",
            "subcategory":"Bank",
            "type":"Services"
        }
    ],
    "sg:phone":"+1 773 588 7700",
    "sg:postcode":"60625",
    "sg:province":"IL",
    "sg:website":"www.fosterbank.com",
    "wof:name":"Foster Bank",
    "wof:placetype":"venue"
},
  "geometry": {"coordinates":[-87.70867200000001,41.976648],"type":"Point"}
}