{
  "type": "Feature",
  "properties": {
    "addr:full":"11230 S Vincennes Ave Chicago IL 60643",
    "addr:housenumber":"11230",
    "addr:postcode":"60643",
    "addr:street":"S Vincennes Ave",
    "iso:country":"US",
    "sg:address":"11230 S Vincennes Ave",
    "sg:city":"Chicago",
    "sg:classifiers":[
        {
            "category":"Social Services",
            "type":"Services"
        }
    ],
    "sg:phone":"+1 773 779 6938",
    "sg:postcode":"60643",
    "sg:province":"IL",
    "wof:name":"Orchard Place of Morgan Park",
    "wof:placetype":"venue"
},
  "geometry": {"coordinates":[-87.66496600000001,41.689789],"type":"Point"}
}