{
  "type": "Feature",
  "properties": {
    "iso:country":"US",
    "sg:address":"1108 W Granville Avenue",
    "sg:city":"Chicago",
    "sg:classifiers":[
        {
            "category":"Health Services",
            "subcategory":"Optometrist",
            "type":"Services"
        },
        {
            "category":"Shopping",
            "subcategory":"Optician",
            "type":"Retail Goods"
        }
    ],
    "sg:phone":"+1 773 274 8222",
    "sg:postcode":"60660",
    "sg:province":"IL",
    "sg:tags":[
        "eyewear"
    ],
    "wof:name":"Granville Vision Center",
    "wof:placetype":"venue"
},
  "geometry": {"coordinates":[-87.658946,41.994616],"type":"Point"}
}