{
  "type": "Feature",
  "properties": {
    "iso:country":"US",
    "sg:address":"6400 N Illinois St",
    "sg:city":"Fairview Heights",
    "sg:classifiers":[
        {
            "category":"Autos & Motor Vehicles",
            "subcategory":"Fuel & Gas Station",
            "type":"Retail Goods"
        }
    ],
    "sg:phone":"+1 618 624 5750",
    "sg:postcode":"62208",
    "sg:province":"IL",
    "wof:name":"Fairview Amoco Food Shop",
    "wof:placetype":"venue"
},
  "geometry": {"coordinates":[-89.984901,38.591702],"type":"Point"}
}