{
  "type": "Feature",
  "properties": {
    "iso:country":"US",
    "sg:address":"3805 Glendenning Rd",
    "sg:city":"Downers Grove",
    "sg:classifiers":[
        {
            "category":"Building & Trades",
            "subcategory":"Construction",
            "type":"Services"
        }
    ],
    "sg:phone":"+1 630 964 4225",
    "sg:postcode":"60515",
    "sg:province":"IL",
    "sg:tags":[
        "home",
        "residential",
        "remodeling",
        "contractor"
    ],
    "wof:name":"Mike Meador Construction",
    "wof:placetype":"venue"
},
  "geometry": {"coordinates":[-88.002385,41.818948],"type":"Point"}
}