{
  "type": "Feature",
  "properties": {
    "iso:country":"US",
    "sg:address":"4530 S Woodlawn Ave",
    "sg:city":"Chicago",
    "sg:classifiers":[
        {
            "category":"Shopping",
            "subcategory":"Computers & Home Electronics",
            "type":"Retail Goods"
        }
    ],
    "sg:phone":"+1 773 536 1980",
    "sg:postcode":"60653",
    "sg:province":"IL",
    "sg:tags":[
        "software"
    ],
    "wof:name":"Advanced Integrated Software",
    "wof:placetype":"venue"
},
  "geometry": {"coordinates":[-87.596954,41.812018],"type":"Point"}
}