{
  "type": "Feature",
  "properties": {
    "iso:country":"US",
    "sg:address":"333 Skokie Blvd",
    "sg:city":"Northbrook",
    "sg:classifiers":[
        {
            "category":"Insurance",
            "subcategory":"Insurance Agent",
            "type":"Services"
        }
    ],
    "sg:phone":"+1 847 498 2860",
    "sg:postcode":"60062",
    "sg:province":"IL",
    "sg:tags":[
        "agency"
    ],
    "wof:name":"Nationwide",
    "wof:placetype":"venue"
},
  "geometry": {"coordinates":[-87.80041300000001,42.150606],"type":"Point"}
}