{
  "type": "Feature",
  "properties": {
    "addr:full":"1433 Main St Lemont IL 60439",
    "addr:housenumber":"1433",
    "addr:postcode":"60439",
    "addr:street":"Main St",
    "iso:country":"US",
    "sg:address":"1433 Main St",
    "sg:city":"Lemont",
    "sg:classifiers":[
        {
            "category":"Organizations",
            "subcategory":"Religious Organization",
            "type":"Services"
        }
    ],
    "sg:phone":"+1 630 759 4578",
    "sg:postcode":"60439",
    "sg:province":"IL",
    "wof:name":"Cornerstone Church",
    "wof:placetype":"venue"
},
  "geometry": {"coordinates":[-87.958382,41.685279],"type":"Point"}
}