{
  "type": "Feature",
  "properties": {
    "addr:full":"8716 Ogden Ave Lyons IL 60534",
    "addr:housenumber":"8716",
    "addr:postcode":"60534",
    "addr:street":"Ogden Ave",
    "iso:country":"US",
    "sg:address":"8716 Ogden Ave",
    "sg:city":"Lyons",
    "sg:classifiers":[
        {
            "category":"Autos & Motor Vehicles",
            "subcategory":"Fuel & Gas Station",
            "type":"Retail Goods"
        }
    ],
    "sg:phone":"+1 708 442 9523",
    "sg:postcode":"60534",
    "sg:province":"IL",
    "sg:website":"http://www.speedway.com",
    "wof:name":"Speedway 4611",
    "wof:placetype":"venue"
},
  "geometry": {"coordinates":[-87.83908099999999,41.816349],"type":"Point"}
}