{
  "type": "Feature",
  "properties": {
    "iso:country":"US",
    "sg:address":"8932 Niles Center Rd",
    "sg:city":"Skokie",
    "sg:classifiers":[
        {
            "category":"Health Services",
            "subcategory":"Medical Lab",
            "type":"Services"
        }
    ],
    "sg:phone":"+1 847 933 0433",
    "sg:postcode":"60076",
    "sg:province":"IL",
    "sg:tags":[
        "laboratory",
        "dental"
    ],
    "wof:name":"Ah Dental Lab Inc",
    "wof:placetype":"venue"
},
  "geometry": {"coordinates":[-87.746011,42.04381],"type":"Point"}
}