{
  "type": "Feature",
  "properties": {
    "addr:full":"350 May Mart Dr Rochelle IL 61068",
    "addr:housenumber":"350",
    "addr:postcode":"61068",
    "addr:street":"May Mart Dr",
    "iso:country":"US",
    "sg:address":"350 May Mart Dr",
    "sg:city":"Rochelle",
    "sg:classifiers":[
        {
            "category":"Organizations",
            "subcategory":"Professional Association",
            "type":"Services"
        }
    ],
    "sg:phone":"+1 815 562 4189",
    "sg:postcode":"61068",
    "sg:province":"IL",
    "sg:tags":[
        "chambers",
        "commerce"
    ],
    "wof:name":"Rochelle Area Chamber-Commerce",
    "wof:placetype":"venue"
},
  "geometry": {"coordinates":[-89.064177,41.933993],"type":"Point"}
}