{
  "type": "Feature",
  "properties": {
    "iso:country":"US",
    "sg:address":"120 Kristin Cir",
    "sg:city":"Schaumburg",
    "sg:classifiers":[
        {
            "category":"Real Estate",
            "subcategory":"Real Estate Operator",
            "type":"Services"
        }
    ],
    "sg:phone":"+1 847 885 8030",
    "sg:postcode":"60195",
    "sg:province":"IL",
    "sg:tags":[
        "apartment",
        "complex"
    ],
    "wof:name":"Archstone Garden Green",
    "wof:placetype":"venue"
},
  "geometry": {"coordinates":[-88.081888,42.059889],"type":"Point"}
}