{
  "type": "Feature",
  "properties": {
    "iso:country":"US",
    "sg:address":"10901 S Peoria St",
    "sg:city":"Chicago",
    "sg:classifiers":[
        {
            "category":"Insurance",
            "subcategory":"Insurance Agent",
            "type":"Services"
        }
    ],
    "sg:phone":"+1 773 928 0465",
    "sg:postcode":"60643",
    "sg:province":"IL",
    "wof:name":"Lovett & Associates",
    "wof:placetype":"venue"
},
  "geometry": {"coordinates":[-87.64487099999999,41.694147],"type":"Point"}
}