{
  "type": "Feature",
  "properties": {
    "iso:country":"US",
    "sg:address":"4019 Dorset Dr",
    "sg:city":"Rockford",
    "sg:classifiers":[
        {
            "category":"Manufacturing",
            "subcategory":"Printing",
            "type":"Manufacturing & Wholesale Goods"
        }
    ],
    "sg:phone":"+1 815 639 9692",
    "sg:postcode":"61114",
    "sg:province":"IL",
    "sg:tags":[
        "printer"
    ],
    "wof:name":"Martin Graphics Inc",
    "wof:placetype":"venue"
},
  "geometry": {"coordinates":[-89.035645,42.300314],"type":"Point"}
}