{
  "type": "Feature",
  "properties": {
    "addr:full":"4512 Oakton St Skokie IL 60076",
    "addr:housenumber":"4512",
    "addr:postcode":"60076",
    "addr:street":"Oakton St",
    "iso:country":"US",
    "sg:address":"4512 Oakton St",
    "sg:city":"Skokie",
    "sg:classifiers":[
        {
            "category":"Bakery",
            "type":"Food & Drink"
        }
    ],
    "sg:phone":"+1 847 675 1355",
    "sg:postcode":"60076",
    "sg:province":"IL",
    "wof:name":"Oakton Bakery",
    "wof:placetype":"venue"
},
  "geometry": {"coordinates":[-87.740742,42.026249],"type":"Point"}
}