{
  "type": "Feature",
  "properties": {
    "iso:country":"US",
    "sg:address":"20 S Chicago Ave",
    "sg:city":"Freeport",
    "sg:classifiers":[
        {
            "category":"Shopping",
            "subcategory":"Discount & Variety Stores",
            "type":"Retail Goods"
        }
    ],
    "sg:phone":"+1 815 232 0212",
    "sg:postcode":"61032",
    "sg:province":"IL",
    "wof:name":"Dollar Depot",
    "wof:placetype":"venue"
},
  "geometry": {"coordinates":[-89.620006,42.298239],"type":"Point"}
}