{
  "type": "Feature",
  "properties": {
    "iso:country":"US",
    "sg:address":"5534 Court Rd",
    "sg:city":"Germantown",
    "sg:phone":"+1 618 248 5378",
    "sg:postcode":"62245",
    "sg:province":"IL",
    "sg:tags":[
        "farm",
        "corn",
        "soybean"
    ],
    "wof:name":"Donald Netemeyer",
    "wof:placetype":"venue"
},
  "geometry": {"coordinates":[-89.60212300000001,38.553924],"type":"Point"}
}