{
  "type": "Feature",
  "properties": {
    "addr:full":"1386 Price Ave Calumet City IL 60409",
    "addr:housenumber":"1386",
    "addr:postcode":"60409",
    "addr:street":"Price Ave",
    "iso:country":"US",
    "sg:address":"1386 Price Ave",
    "sg:city":"Calumet City",
    "sg:classifiers":[
        {
            "category":"Professional",
            "subcategory":"Business Services",
            "type":"Services"
        }
    ],
    "sg:phone":"+1 708 862 3072",
    "sg:postcode":"60409",
    "sg:province":"IL",
    "sg:tags":[
        "flooring",
        "contractor"
    ],
    "wof:name":"Outlaw Claudis",
    "wof:placetype":"venue"
},
  "geometry": {"coordinates":[-87.537127,41.595171],"type":"Point"}
}