{
  "type": "Feature",
  "properties": {
    "addr:full":"715 Sanborn St Alton IL 62002",
    "addr:housenumber":"715",
    "addr:postcode":"62002",
    "addr:street":"Sanborn St",
    "iso:country":"US",
    "sg:address":"715 Sanborn St",
    "sg:city":"Alton",
    "sg:classifiers":[
        {
            "category":"Utilities",
            "subcategory":"Telephone",
            "type":"Services"
        }
    ],
    "sg:phone":"+1 618 463 9753",
    "sg:postcode":"62002",
    "sg:province":"IL",
    "sg:tags":[
        "company"
    ],
    "wof:name":"Children's Telephone",
    "wof:placetype":"venue"
},
  "geometry": {"coordinates":[-90.195683,38.90898],"type":"Point"}
}