{
  "type": "Feature",
  "properties": {
    "iso:country":"US",
    "sg:address":"616 Meyer Ct",
    "sg:city":"Aurora",
    "sg:classifiers":[
        {
            "category":"Building & Trades",
            "subcategory":"Plumbing",
            "type":"Services"
        }
    ],
    "sg:phone":"+1 630 896 6600",
    "sg:postcode":"60506",
    "sg:province":"IL",
    "sg:tags":[
        "plumbing",
        "contractor"
    ],
    "wof:name":"David Deisher Plumbing Inc",
    "wof:placetype":"venue"
},
  "geometry": {"coordinates":[-88.364521,41.750319],"type":"Point"}
}