{
  "type": "Feature",
  "properties": {
    "addr:full":"9445 Oriole Ave Morton Grove IL 60053",
    "addr:housenumber":"9445",
    "addr:postcode":"60053",
    "addr:street":"Oriole Ave",
    "iso:country":"US",
    "sg:address":"9445 Oriole Ave",
    "sg:city":"Morton Grove",
    "sg:classifiers":[
        {
            "category":"Real Estate",
            "subcategory":"Real Estate Agent",
            "type":"Services"
        }
    ],
    "sg:phone":"+1 847 967 0664",
    "sg:postcode":"60053",
    "sg:province":"IL",
    "wof:name":"Century 21 McMullin",
    "wof:placetype":"venue"
},
  "geometry": {"coordinates":[-87.816453,42.054407],"type":"Point"}
}