{
  "type": "Feature",
  "properties": {
    "addr:full":"111 N Center St Buda IL 61314",
    "addr:housenumber":"111",
    "addr:postcode":"61314",
    "addr:street":"N Center St",
    "iso:country":"US",
    "sg:address":"111 N Center St",
    "sg:city":"Buda",
    "sg:classifiers":[
        {
            "category":"Manufacturing",
            "subcategory":"Apparel",
            "type":"Manufacturing & Wholesale Goods"
        }
    ],
    "sg:phone":"+1 309 895 2191",
    "sg:postcode":"61314",
    "sg:province":"IL",
    "sg:tags":[
        "brassiere"
    ],
    "wof:name":"Carmen Products",
    "wof:placetype":"venue"
},
  "geometry": {"coordinates":[-89.68066399999999,41.328126],"type":"Point"}
}