{
  "type": "Feature",
  "properties": {
    "iso:country":"US",
    "sg:address":"7639 N Milwaukee Ave",
    "sg:city":"Niles",
    "sg:classifiers":[
        {
            "category":"Food & Beverages",
            "subcategory":"Liquor & Beverages",
            "type":"Retail Goods"
        }
    ],
    "sg:phone":"+1 847 967 8555",
    "sg:postcode":"60714",
    "sg:province":"IL",
    "sg:tags":[
        "store"
    ],
    "wof:name":"Quality Liquors",
    "wof:placetype":"venue"
},
  "geometry": {"coordinates":[-87.808195,42.019632],"type":"Point"}
}