{
  "type": "Feature",
  "properties": {
    "iso:country":"US",
    "sg:address":"2434 Brunswick Cir",
    "sg:city":"Woodridge",
    "sg:classifiers":[
        {
            "category":"Retail",
            "subcategory":"Repair Shop",
            "type":"Services"
        }
    ],
    "sg:phone":"+1 630 719 1020",
    "sg:postcode":"60517",
    "sg:province":"IL",
    "wof:name":"A D P Plumbing",
    "wof:placetype":"venue"
},
  "geometry": {"coordinates":[-88.04142,41.761252],"type":"Point"}
}