{
  "type": "Feature",
  "properties": {
    "iso:country":"US",
    "sg:address":"2027 Canterbury Pl",
    "sg:city":"Wheaton",
    "sg:classifiers":[
        {
            "category":"Professional",
            "subcategory":"Management & Consulting",
            "type":"Services"
        }
    ],
    "sg:phone":"+1 630 690 7337",
    "sg:postcode":"60187",
    "sg:province":"IL",
    "wof:name":"JM Resources Inc",
    "wof:placetype":"venue"
},
  "geometry": {"coordinates":[-88.117929,41.83107],"type":"Point"}
}