{
  "type": "Feature",
  "properties": {
    "iso:country":"US",
    "sg:address":"11285 Edgemere Ter",
    "sg:city":"Roscoe",
    "sg:classifiers":[
        {
            "category":"Social Services",
            "type":"Services"
        }
    ],
    "sg:phone":"+1 815 623 2087",
    "sg:postcode":"61073",
    "sg:province":"IL",
    "sg:tags":[
        "psychologist"
    ],
    "wof:name":"Robert E Cline",
    "wof:placetype":"venue"
},
  "geometry": {"coordinates":[-89.022683,42.424757],"type":"Point"}
}