{
  "type": "Feature",
  "properties": {
    "iso:country":"US",
    "sg:address":"5609 W Chicago Ave",
    "sg:city":"Chicago",
    "sg:classifiers":[
        {
            "category":"Retail",
            "subcategory":"Laundry & Dry Cleaning",
            "type":"Services"
        }
    ],
    "sg:phone":"+1 773 921 3158",
    "sg:postcode":"60651",
    "sg:province":"IL",
    "wof:name":"Ideel Cleaners",
    "wof:placetype":"venue"
},
  "geometry": {"coordinates":[-87.765778,41.894828],"type":"Point"}
}