{
  "type": "Feature",
  "properties": {
    "addr:full":"2900 4th St Charleston IL 61920",
    "addr:housenumber":"2900",
    "addr:postcode":"61920",
    "addr:street":"4Th St",
    "iso:country":"US",
    "sg:address":"2900 4th St",
    "sg:city":"Charleston",
    "sg:classifiers":[
        {
            "category":"Professional",
            "subcategory":"Business Services",
            "type":"Services"
        }
    ],
    "sg:phone":"+1 217 345 2600",
    "sg:postcode":"61920",
    "sg:province":"IL",
    "wof:name":"Business Account",
    "wof:placetype":"venue"
},
  "geometry": {"coordinates":[-88.17701700000001,39.466783],"type":"Point"}
}