{
  "type": "Feature",
  "properties": {
    "addr:full":"1797 S West Ave Freeport IL 61032",
    "addr:housenumber":"1797",
    "addr:postcode":"61032",
    "addr:street":"S West Ave",
    "iso:country":"US",
    "sg:address":"1797 S West Ave",
    "sg:city":"Freeport",
    "sg:classifiers":[
        {
            "category":"Home & Garden",
            "subcategory":"Building Materials",
            "type":"Retail Goods"
        }
    ],
    "sg:phone":"+1 815 233 7390",
    "sg:postcode":"61032",
    "sg:province":"IL",
    "sg:tags":[
        "equipment",
        "electric",
        "supply"
    ],
    "wof:name":"TMP Svc",
    "wof:placetype":"venue"
},
  "geometry": {"coordinates":[-89.631484,42.276591],"type":"Point"}
}