{
  "type": "Feature",
  "properties": {
    "addr:full":"4023 W North Ave Chicago IL 60639",
    "addr:housenumber":"4023",
    "addr:postcode":"60639",
    "addr:street":"W North Ave",
    "iso:country":"US",
    "sg:address":"4023 W North Ave",
    "sg:city":"Chicago",
    "sg:classifiers":[
        {
            "category":"Shopping",
            "subcategory":"Shoes",
            "type":"Retail Goods"
        }
    ],
    "sg:phone":"+1 773 235 9375",
    "sg:postcode":"60639",
    "sg:province":"IL",
    "sg:tags":[
        "store"
    ],
    "wof:name":"Izen Shoes",
    "wof:placetype":"venue"
},
  "geometry": {"coordinates":[-87.72729699999999,41.909809],"type":"Point"}
}