{
  "type": "Feature",
  "properties": {
    "iso:country":"US",
    "sg:address":"1715 Glenview Rd",
    "sg:city":"Glenview",
    "sg:classifiers":[
        {
            "category":"Health Services",
            "subcategory":"Chiropractor",
            "type":"Services"
        }
    ],
    "sg:phone":"+1 847 724 2273",
    "sg:postcode":"60025",
    "sg:province":"IL",
    "sg:tags":[
        "chiropractic"
    ],
    "wof:name":"Kolaski, Brandon",
    "wof:placetype":"venue"
},
  "geometry": {"coordinates":[-87.799553,42.072781],"type":"Point"}
}