{
  "type": "Feature",
  "properties": {
    "iso:country":"US",
    "sg:address":"136 S County Farm Rd",
    "sg:city":"Wheaton",
    "sg:classifiers":[
        {
            "category":"Government",
            "subcategory":"Office",
            "type":"Public Place"
        }
    ],
    "sg:phone":"+1   ",
    "sg:postcode":"60187",
    "sg:province":"IL",
    "sg:tags":[
        "management",
        "emergency"
    ],
    "wof:name":"Dupage County Off Emrgncy MGT",
    "wof:placetype":"venue"
},
  "geometry": {"coordinates":[-88.142688,41.862225],"type":"Point"}
}