{
  "type": "Feature",
  "properties": {
    "iso:country":"US",
    "sg:address":"14217 Chicago Rd",
    "sg:city":"Dolton",
    "sg:classifiers":[
        {
            "category":"Bars & Pubs",
            "type":"Food & Drink"
        },
        {
            "category":"Restaurant",
            "type":"Food & Drink"
        }
    ],
    "sg:phone":"+1 708 841 9420",
    "sg:postcode":"60419",
    "sg:province":"IL",
    "sg:tags":[
        "brew",
        "grill"
    ],
    "wof:name":"Angel's",
    "wof:placetype":"venue"
},
  "geometry": {"coordinates":[-87.607552,41.636503],"type":"Point"}
}