{
  "type": "Feature",
  "properties": {
    "addr:full":"151 S Alpine Rd Rockford IL 61108",
    "addr:housenumber":"151",
    "addr:postcode":"61108",
    "addr:street":"S Alpine Rd",
    "iso:country":"US",
    "sg:address":"151 S Alpine Rd",
    "sg:city":"Rockford",
    "sg:classifiers":[
        {
            "category":"Food & Beverages",
            "subcategory":"Groceries & Convenience Stores",
            "type":"Retail Goods"
        }
    ],
    "sg:phone":"+1 815 399 9706",
    "sg:postcode":"61108",
    "sg:province":"IL",
    "sg:tags":[
        "grocer"
    ],
    "wof:name":"Site Food Mart",
    "wof:placetype":"venue"
},
  "geometry": {"coordinates":[-89.029099,42.263557],"type":"Point"}
}