{
  "type": "Feature",
  "properties": {
    "iso:country":"US",
    "sg:address":"5837 W Division St",
    "sg:city":"Chicago",
    "sg:classifiers":[
        {
            "category":"Personal",
            "type":"Services"
        }
    ],
    "sg:phone":"+1 773 378 0376",
    "sg:postcode":"60651",
    "sg:province":"IL",
    "sg:tags":[
        "hair",
        "weaving"
    ],
    "wof:name":"African Braids",
    "wof:placetype":"venue"
},
  "geometry": {"coordinates":[-87.772299,41.90197],"type":"Point"}
}