{
  "type": "Feature",
  "properties": {
    "iso:country":"US",
    "sg:address":"115 W Seminole St",
    "sg:city":"Dwight",
    "sg:classifiers":[
        {
            "category":"Banks & Credit Unions",
            "subcategory":"Investment Brokerage",
            "type":"Services"
        },
        {
            "category":"Professional",
            "subcategory":"Accounting & Tax Preparation",
            "type":"Services"
        }
    ],
    "sg:phone":"+1 815 584 1040",
    "sg:postcode":"60420",
    "sg:province":"IL",
    "sg:tags":[
        "advisory",
        "accountant"
    ],
    "wof:name":"Mortensen Financial Services",
    "wof:placetype":"venue"
},
  "geometry": {"coordinates":[-88.42931900000001,41.095062],"type":"Point"}
}