{
  "type": "Feature",
  "properties": {
    "iso:country":"US",
    "sg:address":"1446 S. Michigan Ave. Unit D",
    "sg:city":"Chicago",
    "sg:classifiers":[
        {
            "category":"Building & Trades",
            "subcategory":"Landscaping Services",
            "type":"Services"
        }
    ],
    "sg:phone":"+1 312 545 6550",
    "sg:postcode":"60605",
    "sg:province":"IL",
    "sg:website":"www.rugzoom.com",
    "wof:name":"Rugzoom Synthetic Grass and Landscaping",
    "wof:placetype":"venue"
},
  "geometry": {"coordinates":[-87.624056,41.862683],"type":"Point"}
}