{
  "type": "Feature",
  "properties": {
    "iso:country":"US",
    "sg:address":"6956 W 111th St",
    "sg:city":"Worth",
    "sg:classifiers":[
        {
            "category":"Health Services",
            "subcategory":"Optometrist",
            "type":"Services"
        }
    ],
    "sg:phone":"+1 708 361 1570",
    "sg:postcode":"60482",
    "sg:province":"IL",
    "wof:name":"Dykstra Richard J OD",
    "wof:placetype":"venue"
},
  "geometry": {"coordinates":[-87.793098,41.690201],"type":"Point"}
}