{
  "type": "Feature",
  "properties": {
    "iso:country":"US",
    "sg:address":"2734 Adelaide Ave",
    "sg:city":"Waukegan",
    "sg:classifiers":[
        {
            "category":"Bakery",
            "type":"Food & Drink"
        }
    ],
    "sg:phone":"+1 847 246 1065",
    "sg:postcode":"60087",
    "sg:province":"IL",
    "sg:tags":[
        "cake",
        "pastry",
        "wedding"
    ],
    "wof:name":"Cake 'N Crumbs",
    "wof:placetype":"venue"
},
  "geometry": {"coordinates":[-87.869328,42.401979],"type":"Point"}
}