{
  "type": "Feature",
  "properties": {
    "addr:full":"7500 E Riverside Blvd Loves Park IL 61111",
    "addr:housenumber":"7500",
    "addr:postcode":"61111",
    "addr:street":"E Riverside Blvd",
    "iso:country":"US",
    "sg:address":"7500 E Riverside Blvd",
    "sg:city":"Loves Park",
    "sg:classifiers":[
        {
            "category":"Restaurant",
            "type":"Food & Drink"
        }
    ],
    "sg:menulink":"http://www.allmenus.com/il/rockford/126723-subway/menu/",
    "sg:phone":"+1 815 877 6632",
    "sg:postcode":"61111",
    "sg:province":"IL",
    "sg:tags":[
        "american",
        "sandwich"
    ],
    "wof:name":"Subway",
    "wof:placetype":"venue"
},
  "geometry": {"coordinates":[-88.96897800000001,42.319109],"type":"Point"}
}