{
  "type": "Feature",
  "properties": {
    "addr:full":"1542 40th Ave Moline IL 61265",
    "addr:housenumber":"1542",
    "addr:postcode":"61265",
    "addr:street":"40Th Ave",
    "iso:country":"US",
    "sg:address":"1542 40th Ave",
    "sg:city":"Moline",
    "sg:classifiers":[
        {
            "category":"Building & Trades",
            "subcategory":"Construction",
            "type":"Services"
        }
    ],
    "sg:phone":"+1 309 631 8030",
    "sg:postcode":"61265",
    "sg:province":"IL",
    "sg:tags":[
        "demolition",
        "contractor"
    ],
    "wof:name":"Eowser Construction",
    "wof:placetype":"venue"
},
  "geometry": {"coordinates":[-90.513803,41.469334],"type":"Point"}
}