{
  "type": "Feature",
  "properties": {
    "addr:full":"650 S Ridgeview Ln Peoria IL 61604",
    "addr:housenumber":"650",
    "addr:postcode":"61604",
    "addr:street":"S Ridgeview Ln",
    "iso:country":"US",
    "sg:address":"650 S Ridgeview Ln",
    "sg:city":"Peoria",
    "sg:classifiers":[
        {
            "category":"Building & Trades",
            "subcategory":"Construction",
            "type":"Services"
        }
    ],
    "sg:phone":"+1 309 697 0727",
    "sg:postcode":"61604",
    "sg:province":"IL",
    "sg:tags":[
        "industrial",
        "painting",
        "contractors-commercial",
        "contractor"
    ],
    "wof:name":"Kallister Painting Inc",
    "wof:placetype":"venue"
},
  "geometry": {"coordinates":[-89.66744199999999,40.681751],"type":"Point"}
}