{
  "type": "Feature",
  "properties": {
    "iso:country":"US",
    "sg:address":"13914 S Claire Blvd",
    "sg:city":"Robbins",
    "sg:classifiers":[
        {
            "category":"Insurance",
            "subcategory":"Insurance Agent",
            "type":"Services"
        }
    ],
    "sg:phone":"+1 708 824 1990",
    "sg:postcode":"60472",
    "sg:province":"IL",
    "wof:name":"C & S Insurance Inc",
    "wof:placetype":"venue"
},
  "geometry": {"coordinates":[-87.706749,41.639235],"type":"Point"}
}