{
  "type": "Feature",
  "properties": {
    "iso:country":"US",
    "sg:address":"540 W Colfax St",
    "sg:city":"Palatine",
    "sg:classifiers":[
        {
            "category":"Manufacturing",
            "subcategory":"Toys & Sporting Goods",
            "type":"Manufacturing & Wholesale Goods"
        }
    ],
    "sg:phone":"+1 847 776 7769",
    "sg:postcode":"60067",
    "sg:province":"IL",
    "sg:tags":[
        "mfg"
    ],
    "wof:name":"Holz Schuler Cue",
    "wof:placetype":"venue"
},
  "geometry": {"coordinates":[-88.054962,42.116408],"type":"Point"}
}