{
  "type": "Feature",
  "properties": {
    "addr:full":"4818 W 83rd St Burbank IL 60459",
    "addr:housenumber":"4818",
    "addr:postcode":"60459",
    "addr:street":"W 83Rd St",
    "iso:country":"US",
    "sg:address":"4818 W 83rd St",
    "sg:city":"Burbank",
    "sg:classifiers":[
        {
            "category":"Food & Beverages",
            "subcategory":"Liquor & Beverages",
            "type":"Retail Goods"
        },
        {
            "category":"Food & Beverages",
            "subcategory":"Groceries & Convenience Stores",
            "type":"Retail Goods"
        }
    ],
    "sg:phone":"+1 708 424 6321",
    "sg:postcode":"60459",
    "sg:province":"IL",
    "sg:tags":[
        "grocer",
        "alcoholic"
    ],
    "wof:name":"Burbank Food & Liquor",
    "wof:placetype":"venue"
},
  "geometry": {"coordinates":[-87.74279799999999,41.741798],"type":"Point"}
}