{
  "type": "Feature",
  "properties": {
    "iso:country":"US",
    "sg:address":"18630 81st Ave",
    "sg:city":"Tinley Park",
    "sg:classifiers":[
        {
            "category":"Wholesale",
            "subcategory":"Office Equipment",
            "type":"Manufacturing & Wholesale Goods"
        }
    ],
    "sg:phone":"+1 708 614 1234",
    "sg:postcode":"60487",
    "sg:province":"IL",
    "sg:tags":[
        "furniture"
    ],
    "wof:name":"Martin Whalen Office Solutions",
    "wof:placetype":"venue"
},
  "geometry": {"coordinates":[-87.81580599999999,41.552126],"type":"Point"}
}