{
  "type": "Feature",
  "properties": {
    "iso:country":"US",
    "sg:address":"720 Perry St",
    "sg:city":"Barry",
    "sg:classifiers":[
        {
            "category":"Organizations",
            "subcategory":"Religious Organization",
            "type":"Services"
        }
    ],
    "sg:phone":"+1 217 335 2064",
    "sg:postcode":"62312",
    "sg:province":"IL",
    "sg:tags":[
        "church"
    ],
    "wof:name":"First United Methodist Church",
    "wof:placetype":"venue"
},
  "geometry": {"coordinates":[-91.043845,39.694335],"type":"Point"}
}