{
  "type": "Feature",
  "properties": {
    "iso:country":"US",
    "sg:address":"9 Arlington Heights Rd",
    "sg:city":"Arlington Heights",
    "sg:classifiers":[
        {
            "category":"Retail",
            "subcategory":"Laundry & Dry Cleaning",
            "type":"Services"
        }
    ],
    "sg:phone":"+1 847 437 1412",
    "sg:postcode":"60005",
    "sg:province":"IL",
    "sg:tags":[
        "plant"
    ],
    "wof:name":"Grove Elk Village Cleaners",
    "wof:placetype":"venue"
},
  "geometry": {"coordinates":[-87.980415,42.081111],"type":"Point"}
}