{
  "type": "Feature",
  "properties": {
    "iso:country":"US",
    "sg:address":"27582 Volo Village Rd",
    "sg:city":"Round Lake",
    "sg:classifiers":[
        {
            "category":"Museum",
            "type":"Entertainment"
        }
    ],
    "sg:phone":"+1 815 385 3644",
    "sg:postcode":"60073",
    "sg:province":"IL",
    "sg:tags":[
        "antique",
        "automobile",
        "retail"
    ],
    "wof:name":"Volo Auto Museum",
    "wof:placetype":"venue"
},
  "geometry": {"coordinates":[-88.168379,42.326128],"type":"Point"}
}