{
  "type": "Feature",
  "properties": {
    "iso:country":"US",
    "sg:address":"37 W Broadway St",
    "sg:city":"Witt",
    "sg:classifiers":[
        {
            "category":"Wholesale",
            "subcategory":"Electrical",
            "type":"Manufacturing & Wholesale Goods"
        }
    ],
    "sg:phone":"+1 217 594 2421",
    "sg:postcode":"62094",
    "sg:province":"IL",
    "sg:tags":[
        "electric",
        "motor"
    ],
    "wof:name":"Weitekamp Electric",
    "wof:placetype":"venue"
},
  "geometry": {"coordinates":[-89.352177,39.254148],"type":"Point"}
}