{
  "type": "Feature",
  "properties": {
    "addr:full":"1433 E Walnut St Carbondale IL 62902",
    "addr:housenumber":"1433",
    "addr:postcode":"62902",
    "addr:street":"E Walnut St",
    "iso:country":"US",
    "sg:address":"1433 E Walnut St",
    "sg:city":"Carbondale",
    "sg:classifiers":[
        {
            "category":"Personal",
            "subcategory":"Barber",
            "type":"Services"
        }
    ],
    "sg:phone":"+1 618 529 5440",
    "sg:postcode":"62902",
    "sg:province":"IL",
    "wof:name":"Morales Styles",
    "wof:placetype":"venue"
},
  "geometry": {"coordinates":[-89.18451,37.72676],"type":"Point"}
}