{
  "type": "Feature",
  "properties": {
    "addr:full":"5153 N Broadway Street Chicago IL 60640",
    "addr:housenumber":"5153",
    "addr:postcode":"60640",
    "addr:street":"N Broadway Street",
    "iso:country":"US",
    "sg:address":"5153 N Broadway Street",
    "sg:city":"Chicago",
    "sg:classifiers":[
        {
            "category":"Professional",
            "subcategory":"Lawyer & Legal Services",
            "type":"Services"
        }
    ],
    "sg:phone":"+1 773 907 9600",
    "sg:postcode":"60640",
    "sg:province":"IL",
    "wof:name":"C Dean Matsas & Assoc",
    "wof:placetype":"venue"
},
  "geometry": {"coordinates":[-87.659803,41.975797],"type":"Point"}
}