{
  "type": "Feature",
  "properties": {
    "iso:country":"US",
    "sg:address":"1336 E Joyce Ave",
    "sg:city":"Palatine",
    "sg:classifiers":[
        {
            "category":"Home & Garden",
            "subcategory":"Carpets & Floor Coverings",
            "type":"Retail Goods"
        }
    ],
    "sg:phone":"+1   ",
    "sg:postcode":"60074",
    "sg:province":"IL",
    "wof:name":"A To Z Carpet Service",
    "wof:placetype":"venue"
},
  "geometry": {"coordinates":[-88.011043,42.109114],"type":"Point"}
}