{
  "type": "Feature",
  "properties": {
    "iso:country":"US",
    "sg:address":"4300 Commerce Ct",
    "sg:city":"Lisle",
    "sg:classifiers":[
        {
            "category":"Manufacturing",
            "subcategory":"Printing",
            "type":"Manufacturing & Wholesale Goods"
        }
    ],
    "sg:phone":"+1 630 955 3500",
    "sg:postcode":"60532",
    "sg:province":"IL",
    "sg:tags":[
        "newspaper"
    ],
    "wof:name":"Daily Herald",
    "wof:placetype":"venue"
},
  "geometry": {"coordinates":[-88.107543,41.807092],"type":"Point"}
}