{
  "type": "Feature",
  "properties": {
    "addr:full":"325 Vermont St Quincy IL 62301",
    "addr:housenumber":"325",
    "addr:postcode":"62301",
    "addr:street":"Vermont St",
    "iso:country":"US",
    "sg:address":"325 Vermont St",
    "sg:city":"Quincy",
    "sg:classifiers":[
        {
            "category":"Retail",
            "subcategory":"Auto Rental",
            "type":"Services"
        }
    ],
    "sg:phone":"+1 217 224 7253",
    "sg:postcode":"62301",
    "sg:province":"IL",
    "sg:tags":[
        "equipment",
        "truck"
    ],
    "wof:name":"Ryder",
    "wof:placetype":"venue"
},
  "geometry": {"coordinates":[-91.411382,39.9346],"type":"Point"}
}