{
  "type": "Feature",
  "properties": {
    "addr:full":"100 W Bittersweet Rd Washington IL 61571",
    "addr:housenumber":"100",
    "addr:postcode":"61571",
    "addr:street":"W Bittersweet Rd",
    "iso:country":"US",
    "sg:address":"100 W Bittersweet Rd",
    "sg:city":"Washington",
    "sg:classifiers":[
        {
            "category":"Social Services",
            "type":"Services"
        },
        {
            "category":"Organizations",
            "subcategory":"Membership Organization",
            "type":"Services"
        }
    ],
    "sg:phone":"+1 309 745 5277",
    "sg:postcode":"61571",
    "sg:province":"IL",
    "sg:tags":[
        "military",
        "veteran"
    ],
    "wof:name":"Vietnam Veterans Of Illinois",
    "wof:placetype":"venue"
},
  "geometry": {"coordinates":[-89.488777,40.683319],"type":"Point"}
}