{
  "type": "Feature",
  "properties": {
    "iso:country":"US",
    "sg:address":"11500 Highway 1",
    "sg:city":"Junction",
    "sg:classifiers":[
        {
            "category":"Autos & Motor Vehicles",
            "subcategory":"Fuel & Gas Station",
            "type":"Retail Goods"
        },
        {
            "category":"Restaurant",
            "type":"Food & Drink"
        }
    ],
    "sg:phone":"+1 618 272 8261",
    "sg:postcode":"62954",
    "sg:province":"IL",
    "sg:tags":[
        "stop",
        "truck"
    ],
    "wof:name":"Patton's Truck Stop",
    "wof:placetype":"venue"
},
  "geometry": {"coordinates":[-88.28582,37.732687],"type":"Point"}
}