{
  "type": "Feature",
  "properties": {
    "iso:country":"US",
    "sg:address":"202 S Chestnut St",
    "sg:city":"Arcola",
    "sg:classifiers":[
        {
            "category":"Restaurant",
            "type":"Food & Drink"
        }
    ],
    "sg:phone":"+1 217 268 4900",
    "sg:postcode":"61910",
    "sg:province":"IL",
    "sg:tags":[
        "mexican"
    ],
    "wof:name":"El Taco Tako",
    "wof:placetype":"venue"
},
  "geometry": {"coordinates":[-88.30919299999999,39.683173],"type":"Point"}
}