{
  "type": "Feature",
  "properties": {
    "iso:country":"US",
    "sg:address":"1604 S Banker St",
    "sg:city":"Effingham",
    "sg:classifiers":[
        {
            "category":"Personal",
            "subcategory":"Beauty Salon",
            "type":"Services"
        }
    ],
    "sg:phone":"+1 217 342 4330",
    "sg:postcode":"62401",
    "sg:province":"IL",
    "sg:tags":[
        "shop"
    ],
    "wof:name":"Walk-In Beauty Salons",
    "wof:placetype":"venue"
},
  "geometry": {"coordinates":[-88.54687,39.108143],"type":"Point"}
}