{
  "type": "Feature",
  "properties": {
    "addr:full":"8404 S Roberts Rd Bedford Park IL 60458",
    "addr:housenumber":"8404",
    "addr:postcode":"60458",
    "addr:street":"S Roberts Rd",
    "iso:country":"US",
    "sg:address":"8404 S Roberts Rd",
    "sg:city":"Bedford Park",
    "sg:classifiers":[
        {
            "category":"Manufacturing",
            "subcategory":"Signs",
            "type":"Manufacturing & Wholesale Goods"
        }
    ],
    "sg:phone":"+1 708 430 5502",
    "sg:postcode":"60458",
    "sg:province":"IL",
    "sg:tags":[
        "manufacture"
    ],
    "wof:name":"Slack Signs and Graphics",
    "wof:placetype":"venue"
},
  "geometry": {"coordinates":[-87.81882400000001,41.73811],"type":"Point"}
}