{
  "type": "Feature",
  "properties": {
    "iso:country":"US",
    "sg:address":"3050 Sunset Ln",
    "sg:city":"Franklin Park",
    "sg:classifiers":[
        {
            "category":"Building & Trades",
            "subcategory":"Landscaping Services",
            "type":"Services"
        }
    ],
    "sg:phone":"+1 847 288 9251",
    "sg:postcode":"60131",
    "sg:province":"IL",
    "sg:tags":[
        "landscape",
        "contractor"
    ],
    "wof:name":"Carreno Landscaping Inc",
    "wof:placetype":"venue"
},
  "geometry": {"coordinates":[-87.877649,41.934406],"type":"Point"}
}