{
  "type": "Feature",
  "properties": {
    "addr:full":"1057 W Argyle Street Chicago IL 60640",
    "addr:housenumber":"1057",
    "addr:postcode":"60640",
    "addr:street":"W Argyle Street",
    "iso:country":"US",
    "sg:address":"1057 W Argyle Street",
    "sg:city":"Chicago",
    "sg:classifiers":[
        {
            "category":"Shopping",
            "subcategory":"Jewelry",
            "type":"Retail Goods"
        }
    ],
    "sg:phone":"+1 773 334 9299",
    "sg:postcode":"60640",
    "sg:province":"IL",
    "sg:tags":[
        "watch"
    ],
    "wof:name":"Trung Tin Music & Gift Shop",
    "wof:placetype":"venue"
},
  "geometry": {"coordinates":[-87.65661799999999,41.973178],"type":"Point"}
}