{
  "type": "Feature",
  "properties": {
    "iso:country":"US",
    "sg:address":"1047 N Glenview Ct",
    "sg:city":"Palatine",
    "sg:classifiers":[
        {
            "category":"Professional",
            "subcategory":"Management & Consulting",
            "type":"Services"
        }
    ],
    "sg:phone":"+1 847 358 7441",
    "sg:postcode":"60067",
    "sg:province":"IL",
    "wof:name":"Clark Smaha & Associates Inc",
    "wof:placetype":"venue"
},
  "geometry": {"coordinates":[-88.064631,42.128532],"type":"Point"}
}