{
  "type": "Feature",
  "properties": {
    "addr:full":"1595 Weld Rd Elgin IL 60123",
    "addr:housenumber":"1595",
    "addr:postcode":"60123",
    "addr:street":"Weld Rd",
    "iso:country":"US",
    "sg:address":"1595 Weld Rd",
    "sg:city":"Elgin",
    "sg:classifiers":[
        {
            "category":"Health Services",
            "subcategory":"Chiropractor",
            "type":"Services"
        }
    ],
    "sg:phone":"+1 847 695 0464",
    "sg:postcode":"60123",
    "sg:province":"IL",
    "wof:name":"Sikorsky Chiropractic Clinic",
    "wof:placetype":"venue"
},
  "geometry": {"coordinates":[-88.31999999999999,42.025631],"type":"Point"}
}