{
  "type": "Feature",
  "properties": {
    "addr:full":"360 N Main St Canton IL 61520",
    "addr:housenumber":"360",
    "addr:postcode":"61520",
    "addr:street":"N Main St",
    "iso:country":"US",
    "sg:address":"360 N Main St",
    "sg:city":"Canton",
    "sg:classifiers":[
        {
            "category":"Social Services",
            "type":"Services"
        }
    ],
    "sg:phone":"+1 309 647 9036",
    "sg:postcode":"61520",
    "sg:province":"IL",
    "wof:name":"Older Adult Services",
    "wof:placetype":"venue"
},
  "geometry": {"coordinates":[-90.035175,40.559937],"type":"Point"}
}