{
  "type": "Feature",
  "properties": {
    "iso:country":"US",
    "sg:address":"946 W Newport",
    "sg:city":"Chicago",
    "sg:classifiers":[
        {
            "category":"Restaurant",
            "type":"Food & Drink"
        }
    ],
    "sg:phone":"+1 773 883 6033",
    "sg:postcode":"60657",
    "sg:province":"IL",
    "sg:tags":[
        "mexican"
    ],
    "wof:name":"Marko's Tacos",
    "wof:placetype":"venue"
},
  "geometry": {"coordinates":[-87.65410900000001,41.944491],"type":"Point"}
}