{
  "type": "Feature",
  "properties": {
    "addr:full":"19 Pinewood Ln Belleville IL 62226",
    "addr:housenumber":"19",
    "addr:postcode":"62226",
    "addr:street":"Pinewood Ln",
    "iso:country":"US",
    "sg:address":"19 Pinewood Ln",
    "sg:city":"Belleville",
    "sg:classifiers":[
        {
            "category":"Education",
            "subcategory":"Special Training",
            "type":"Public Place"
        }
    ],
    "sg:phone":"+1 618 257 0929",
    "sg:postcode":"62226",
    "sg:province":"IL",
    "sg:tags":[
        "instruction",
        "music"
    ],
    "wof:name":"Childrens Studio Of Piano",
    "wof:placetype":"venue"
},
  "geometry": {"coordinates":[-89.970732,38.5717],"type":"Point"}
}