{
  "type": "Feature",
  "properties": {
    "iso:country":"US",
    "sg:address":"5309 W 95th St",
    "sg:city":"Oak Lawn",
    "sg:classifiers":[
        {
            "category":"Health Services",
            "subcategory":"Doctor",
            "type":"Services"
        }
    ],
    "sg:phone":"+1 708 424 0853",
    "sg:postcode":"60453",
    "sg:province":"IL",
    "wof:name":"Lipinski Dan Dgn Judge",
    "wof:placetype":"venue"
},
  "geometry": {"coordinates":[-87.753557,41.719659],"type":"Point"}
}