{
  "type": "Feature",
  "properties": {
    "addr:full":"255 S West Ave Elmhurst IL 60126",
    "addr:housenumber":"255",
    "addr:postcode":"60126",
    "addr:street":"S West Ave",
    "iso:country":"US",
    "sg:address":"255 S West Ave",
    "sg:city":"Elmhurst",
    "sg:classifiers":[
        {
            "category":"Real Estate",
            "subcategory":"Real Estate Operator",
            "type":"Services"
        }
    ],
    "sg:phone":"+1 630 279 4020",
    "sg:postcode":"60126",
    "sg:province":"IL",
    "sg:tags":[
        "building",
        "management",
        "apartment",
        "condominium"
    ],
    "wof:name":"Willows Of Elmhurst Condominium",
    "wof:placetype":"venue"
},
  "geometry": {"coordinates":[-87.95934699999999,41.89319],"type":"Point"}
}