{
  "type": "Feature",
  "properties": {
    "iso:country":"US",
    "sg:address":"441 Dundee Ave Ste C",
    "sg:city":"Elgin",
    "sg:classifiers":[
        {
            "category":"Professional",
            "subcategory":"Employment Agencies",
            "type":"Services"
        }
    ],
    "sg:phone":"+1 847 760 4770",
    "sg:postcode":"60120",
    "sg:province":"IL",
    "wof:name":"Labor Nation Llc",
    "wof:placetype":"venue"
},
  "geometry": {"coordinates":[-88.276838,42.045437],"type":"Point"}
}