{
  "type": "Feature",
  "properties": {
    "addr:full":"8145 Gass Ln Collinsville IL 62234",
    "addr:housenumber":"8145",
    "addr:postcode":"62234",
    "addr:street":"Gass Ln",
    "iso:country":"US",
    "sg:address":"8145 Gass Ln",
    "sg:city":"Collinsville",
    "sg:classifiers":[
        {
            "category":"Building & Trades",
            "subcategory":"Construction",
            "type":"Services"
        }
    ],
    "sg:phone":"+1 618 632 7697",
    "sg:postcode":"62234",
    "sg:province":"IL",
    "sg:tags":[
        "house"
    ],
    "wof:name":"Marvin Gass Const Co Inc",
    "wof:placetype":"venue"
},
  "geometry": {"coordinates":[-89.879698,38.653045],"type":"Point"}
}