{
  "type": "Feature",
  "properties": {
    "iso:country":"US",
    "sg:address":"3149 Dundee Rd Ste 280",
    "sg:city":"Northbrook",
    "sg:classifiers":[
        {
            "category":"Professional",
            "type":"Services"
        }
    ],
    "sg:phone":"+1 847 480 1177",
    "sg:postcode":"60062",
    "sg:province":"IL",
    "sg:tags":[
        "transportation"
    ],
    "wof:name":"Bzt Inc",
    "wof:placetype":"venue"
},
  "geometry": {"coordinates":[-87.857147,42.138351],"type":"Point"}
}