{
  "type": "Feature",
  "properties": {
    "iso:country":"US",
    "sg:address":"11514 State Rte 127",
    "sg:city":"Carlyle",
    "sg:classifiers":[
        {
            "category":"Building & Trades",
            "subcategory":"Plumbing",
            "type":"Services"
        }
    ],
    "sg:phone":"+1 618 594 3809",
    "sg:postcode":"62231",
    "sg:province":"IL",
    "sg:tags":[
        "plumbing",
        "heating",
        "contractor"
    ],
    "wof:name":"Carlyle Plumbing & Heating",
    "wof:placetype":"venue"
},
  "geometry": {"coordinates":[-89.372835,38.587792],"type":"Point"}
}