{
  "type": "Feature",
  "properties": {
    "iso:country":"US",
    "sg:address":"38357 N Hamilton Cir",
    "sg:city":"Spring Grove",
    "sg:classifiers":[
        {
            "category":"Professional",
            "type":"Services"
        },
        {
            "category":"Manufacturing",
            "subcategory":"Tools & Machinery",
            "type":"Manufacturing & Wholesale Goods"
        }
    ],
    "sg:phone":"+1 847 395 9142",
    "sg:postcode":"60081",
    "sg:province":"IL",
    "sg:tags":[
        "industrial",
        "establishment",
        "mfg"
    ],
    "wof:name":"Under Pressure",
    "wof:placetype":"venue"
},
  "geometry": {"coordinates":[-88.172089,42.420127],"type":"Point"}
}