{
  "type": "Feature",
  "properties": {
    "iso:country":"US",
    "sg:address":"20796 Ash St",
    "sg:city":"Deerfield",
    "sg:classifiers":[
        {
            "category":"Banks & Credit Unions",
            "subcategory":"Financial Services",
            "type":"Services"
        }
    ],
    "sg:phone":"+1 847 414 5836",
    "sg:postcode":"60015",
    "sg:province":"IL",
    "sg:tags":[
        "investor"
    ],
    "wof:name":"Ddrt Investment Group Inc",
    "wof:placetype":"venue"
},
  "geometry": {"coordinates":[-87.922658,42.166434],"type":"Point"}
}