{
  "type": "Feature",
  "properties": {
    "addr:full":"807 W Fairchild St Danville IL 61832",
    "addr:housenumber":"807",
    "addr:postcode":"61832",
    "addr:street":"W Fairchild St",
    "iso:country":"US",
    "sg:address":"807 W Fairchild St",
    "sg:city":"Danville",
    "sg:classifiers":[
        {
            "category":"Health Services",
            "subcategory":"Doctor",
            "type":"Services"
        }
    ],
    "sg:phone":"+1 217 477 1490",
    "sg:postcode":"61832",
    "sg:province":"IL",
    "sg:tags":[
        "clinic"
    ],
    "sg:website":"www.chardonnaydialysis.com",
    "wof:name":"Chardonnay Dialysis Inc",
    "wof:placetype":"venue"
},
  "geometry": {"coordinates":[-87.641413,40.138325],"type":"Point"}
}