{
  "type": "Feature",
  "properties": {
    "addr:full":"9812 Saint Albans St Hebron IL 60034",
    "addr:housenumber":"9812",
    "addr:postcode":"60034",
    "addr:street":"Saint Albans St",
    "iso:country":"US",
    "sg:address":"9812 Saint Albans St",
    "sg:city":"Hebron",
    "sg:classifiers":[
        {
            "category":"Place Of Worship",
            "subcategory":"Church",
            "type":"Public Place"
        },
        {
            "category":"Place Of Worship",
            "type":"Public Place"
        }
    ],
    "sg:phone":"+1 815 648 2671",
    "sg:postcode":"60034",
    "sg:province":"IL",
    "sg:tags":[
        "lutheran",
        "america",
        "churches-lutheran",
        "churches-lutheran-evangelical"
    ],
    "wof:name":"St Johns Lutheran Church Inc",
    "wof:placetype":"venue"
},
  "geometry": {"coordinates":[-88.430351,42.468182],"type":"Point"}
}