{
  "type": "Feature",
  "properties": {
    "iso:country":"US",
    "sg:address":"758 W Euclid Ave",
    "sg:city":"Palatine",
    "sg:classifiers":[
        {
            "category":"Restaurant",
            "type":"Food & Drink"
        }
    ],
    "sg:phone":"+1 800 813 4652",
    "sg:postcode":"60067",
    "sg:province":"IL",
    "sg:tags":[
        "house",
        "steak",
        "barbecue"
    ],
    "wof:name":"World's Best Barbecue Inc.",
    "wof:placetype":"venue"
},
  "geometry": {"coordinates":[-88.060959,42.08733],"type":"Point"}
}