{
  "type": "Feature",
  "properties": {
    "addr:full":"2427 W. Hubbard St. Chicago IL 60612",
    "addr:housenumber":"2427",
    "addr:postcode":"60612",
    "addr:street":"W. Hubbard",
    "iso:country":"US",
    "sg:address":"2427 W. Hubbard St.",
    "sg:city":"Chicago",
    "sg:classifiers":[
        {
            "category":"Coffee & Tea",
            "type":"Food & Drink"
        }
    ],
    "sg:phone":"+1 312 243 1026",
    "sg:postcode":"60612",
    "sg:province":"IL",
    "wof:name":"Grand Coffee Shop",
    "wof:placetype":"venue"
},
  "geometry": {"coordinates":[-87.68774500000001,41.889291],"type":"Point"}
}