{
  "type": "Feature",
  "properties": {
    "addr:full":"601 S Monroe St Decatur IL 62522",
    "addr:housenumber":"601",
    "addr:postcode":"62522",
    "addr:street":"S Monroe St",
    "iso:country":"US",
    "sg:address":"601 S Monroe St",
    "sg:city":"Decatur",
    "sg:classifiers":[
        {
            "category":"Professional",
            "subcategory":"Management & Consulting",
            "type":"Services"
        }
    ],
    "sg:phone":"+1 217 429 2313",
    "sg:postcode":"62522",
    "sg:province":"IL",
    "sg:tags":[
        "consultant"
    ],
    "wof:name":"Analytech Associates",
    "wof:placetype":"venue"
},
  "geometry": {"coordinates":[-88.963387,39.835049],"type":"Point"}
}