{
  "type": "Feature",
  "properties": {
    "iso:country":"US",
    "sg:address":"2608 21st Ave",
    "sg:city":"Rock Island",
    "sg:classifiers":[
        {
            "category":"Shopping",
            "subcategory":"Used Merchandise",
            "type":"Retail Goods"
        }
    ],
    "sg:phone":"+1   ",
    "sg:postcode":"61201",
    "sg:province":"IL",
    "wof:name":"Book Keeper Paperback Exchange",
    "wof:placetype":"venue"
},
  "geometry": {"coordinates":[-90.562127,41.490678],"type":"Point"}
}