{
  "type": "Feature",
  "properties": {
    "addr:full":"805 Silver St Urbana IL 61801",
    "addr:housenumber":"805",
    "addr:postcode":"61801",
    "addr:street":"Silver St",
    "iso:country":"US",
    "sg:address":"805 Silver St",
    "sg:city":"Urbana",
    "sg:classifiers":[
        {
            "category":"Professional",
            "subcategory":"Business Services",
            "type":"Services"
        }
    ],
    "sg:phone":"+1 217 328 0173",
    "sg:postcode":"61801",
    "sg:province":"IL",
    "sg:tags":[
        "consultant",
        "coach"
    ],
    "sg:website":"http://www.spokenlanguage.com",
    "wof:name":"Spoken Language Services Inc",
    "wof:placetype":"venue"
},
  "geometry": {"coordinates":[-88.19804499999999,40.091469],"type":"Point"}
}