{
  "type": "Feature",
  "properties": {
    "iso:country":"US",
    "sg:address":"1215 Belleforte Ave",
    "sg:city":"Oak Park",
    "sg:classifiers":[
        {
            "category":"Professional",
            "type":"Services"
        }
    ],
    "sg:phone":"+1 708 383 2367",
    "sg:postcode":"60302",
    "sg:province":"IL",
    "wof:name":"Z Harry Piotrowski",
    "wof:placetype":"venue"
},
  "geometry": {"coordinates":[-87.802759,41.908101],"type":"Point"}
}