{
  "type": "Feature",
  "properties": {
    "addr:full":"63 N Williams St Crystal Lake IL 60014",
    "addr:housenumber":"63",
    "addr:postcode":"60014",
    "addr:street":"N Williams St",
    "iso:country":"US",
    "sg:address":"63 N Williams St",
    "sg:city":"Crystal Lake",
    "sg:classifiers":[
        {
            "category":"Shopping",
            "subcategory":"Used Merchandise",
            "type":"Retail Goods"
        }
    ],
    "sg:phone":"+1   ",
    "sg:postcode":"60014",
    "sg:province":"IL",
    "sg:tags":[
        "antique"
    ],
    "wof:name":"Marietta",
    "wof:placetype":"venue"
},
  "geometry": {"coordinates":[-88.317403,42.242751],"type":"Point"}
}