{
  "type": "Feature",
  "properties": {
    "addr:full":"1307 James St Geneva IL 60134",
    "addr:housenumber":"1307",
    "addr:postcode":"60134",
    "addr:street":"James St",
    "iso:country":"US",
    "sg:address":"1307 James St",
    "sg:city":"Geneva",
    "sg:classifiers":[
        {
            "category":"Building & Trades",
            "subcategory":"Construction",
            "type":"Services"
        }
    ],
    "sg:phone":"+1 630 232 4114",
    "sg:postcode":"60134",
    "sg:province":"IL",
    "sg:tags":[
        "designer",
        "dealer",
        "pool",
        "swimming"
    ],
    "wof:name":"Century Pool & Spa",
    "wof:placetype":"venue"
},
  "geometry": {"coordinates":[-88.319171,41.887762],"type":"Point"}
}