{
  "type": "Feature",
  "properties": {
    "addr:full":"1000 N McLean Blvd Elgin IL 60123",
    "addr:housenumber":"1000",
    "addr:postcode":"60123",
    "addr:street":"N Mclean Blvd",
    "iso:country":"US",
    "sg:address":"1000 N McLean Blvd",
    "sg:city":"Elgin",
    "sg:classifiers":[
        {
            "category":"Real Estate",
            "subcategory":"Real Estate Operator",
            "type":"Services"
        }
    ],
    "sg:phone":"+1 847 888 3133",
    "sg:postcode":"60123",
    "sg:province":"IL",
    "sg:tags":[
        "building",
        "osteopathic",
        "nonresidential"
    ],
    "wof:name":"North Mc Lean Professional Ctr",
    "wof:placetype":"venue"
},
  "geometry": {"coordinates":[-88.31440000000001,42.015594],"type":"Point"}
}