{
  "type": "Feature",
  "properties": {
    "iso:country":"US",
    "sg:address":"634 Chicago St",
    "sg:city":"Belvidere",
    "sg:classifiers":[
        {
            "category":"Professional",
            "subcategory":"Management & Consulting",
            "type":"Services"
        }
    ],
    "sg:phone":"+1 815 398 0764",
    "sg:postcode":"61008",
    "sg:province":"IL",
    "wof:name":"Accounts Plus",
    "wof:placetype":"venue"
},
  "geometry": {"coordinates":[-88.84199700000001,42.267375],"type":"Point"}
}