{
  "type": "Feature",
  "properties": {
    "addr:full":"20 N Clark Street Suite 2200 Chicago IL 60602",
    "addr:housenumber":"20",
    "addr:postcode":"60602",
    "addr:street":"N Clark Street Suite 2200",
    "iso:country":"US",
    "sg:address":"20 N Clark Street Suite 2200",
    "sg:city":"Chicago",
    "sg:classifiers":[
        {
            "category":"Professional",
            "subcategory":"Lawyer & Legal Services",
            "type":"Services"
        }
    ],
    "sg:phone":"+1 312 236 8400",
    "sg:postcode":"60602",
    "sg:province":"IL",
    "wof:name":"Flamm & Teibloom Ltd",
    "wof:placetype":"venue"
},
  "geometry": {"coordinates":[-87.62866200000001,41.883213],"type":"Point"}
}