{
  "type": "Feature",
  "properties": {
    "addr:full":"4121 S 24th St Quincy IL 62305",
    "addr:housenumber":"4121",
    "addr:postcode":"62305",
    "addr:street":"S 24Th St",
    "iso:country":"US",
    "sg:address":"4121 S 24th St",
    "sg:city":"Quincy",
    "sg:classifiers":[
        {
            "category":"Social Services",
            "subcategory":"Child Care",
            "type":"Services"
        }
    ],
    "sg:phone":"+1 217 224 1630",
    "sg:postcode":"62305",
    "sg:province":"IL",
    "sg:tags":[
        "day"
    ],
    "wof:name":"Carol Florea",
    "wof:placetype":"venue"
},
  "geometry": {"coordinates":[-91.37796899999999,39.881688],"type":"Point"}
}