{
  "type": "Feature",
  "properties": {
    "iso:country":"US",
    "sg:address":"7230 W Palos Ave",
    "sg:city":"Palos Heights",
    "sg:classifiers":[
        {
            "category":"Restaurant",
            "type":"Food & Drink"
        }
    ],
    "sg:phone":"+1 708 361 5966",
    "sg:postcode":"60463",
    "sg:province":"IL",
    "sg:tags":[
        "cafe"
    ],
    "wof:name":"Cafe Roma",
    "wof:placetype":"venue"
},
  "geometry": {"coordinates":[-87.800677,41.6594],"type":"Point"}
}