{
  "type": "Feature",
  "properties": {
    "addr:full":"622 N Plum St Havana IL 62644",
    "addr:housenumber":"622",
    "addr:postcode":"62644",
    "addr:street":"N Plum St",
    "iso:country":"US",
    "sg:address":"622 N Plum St",
    "sg:city":"Havana",
    "sg:classifiers":[
        {
            "category":"Building & Trades",
            "subcategory":"Plumbing",
            "type":"Services"
        }
    ],
    "sg:phone":"+1 309 543 3158",
    "sg:postcode":"62644",
    "sg:province":"IL",
    "sg:tags":[
        "plumbing",
        "contractor"
    ],
    "wof:name":"Spencer's Plumbing & Pump Svc",
    "wof:placetype":"venue"
},
  "geometry": {"coordinates":[-90.062381,40.306392],"type":"Point"}
}