{
  "type": "Feature",
  "properties": {
    "addr:full":"7002 W Archer Ave Chicago IL 60638",
    "addr:housenumber":"7002",
    "addr:postcode":"60638",
    "addr:street":"W Archer Ave",
    "iso:country":"US",
    "sg:address":"7002 W Archer Ave",
    "sg:city":"Chicago",
    "sg:classifiers":[
        {
            "category":"Real Estate",
            "subcategory":"Real Estate Services",
            "type":"Services"
        },
        {
            "category":"Real Estate",
            "subcategory":"Real Estate Agent",
            "type":"Services"
        }
    ],
    "sg:phone":"+1 773 586 1066",
    "sg:postcode":"60638",
    "sg:province":"IL",
    "sg:tags":[
        "buyer",
        "broker"
    ],
    "wof:name":"Homemart Realty Inc",
    "wof:placetype":"venue"
},
  "geometry": {"coordinates":[-87.796516,41.792067],"type":"Point"}
}