{
  "type": "Feature",
  "properties": {
    "addr:full":"5026 W Lawrence Ave Chicago IL 60630",
    "addr:housenumber":"5026",
    "addr:postcode":"60630",
    "addr:street":"W Lawrence Ave",
    "iso:country":"US",
    "sg:address":"5026 W Lawrence Ave",
    "sg:city":"Chicago",
    "sg:classifiers":[
        {
            "category":"Home & Garden",
            "subcategory":"Household Appliances",
            "type":"Retail Goods"
        },
        {
            "category":"Shopping",
            "subcategory":"Mobile Phones",
            "type":"Retail Goods"
        }
    ],
    "sg:phone":"+1 773 599 8111",
    "sg:postcode":"60630",
    "sg:province":"IL",
    "sg:tags":[
        "repair"
    ],
    "sg:website":"www.ifixcellphone.com",
    "wof:name":"iFix Cell Phone Sales & Repair",
    "wof:placetype":"venue"
},
  "geometry": {"coordinates":[-87.75360999999999,41.968123],"type":"Point"}
}