{
  "type": "Feature",
  "properties": {
    "addr:full":"4039 W 26th Street Chicago IL 60623",
    "addr:housenumber":"4039",
    "addr:postcode":"60623",
    "addr:street":"W 26Th Street",
    "iso:country":"US",
    "sg:address":"4039 W 26th Street",
    "sg:city":"Chicago",
    "sg:classifiers":[
        {
            "category":"Restaurant",
            "type":"Food & Drink"
        }
    ],
    "sg:phone":"+1 773 277 3166",
    "sg:postcode":"60623",
    "sg:province":"IL",
    "sg:tags":[
        "pizza"
    ],
    "wof:name":"Domino's Pizza",
    "wof:placetype":"venue"
},
  "geometry": {"coordinates":[-87.726181,41.844022],"type":"Point"}
}