{
  "type": "Feature",
  "properties": {
    "addr:full":"5607 N Broadway St Chicago IL 60660",
    "addr:housenumber":"5607",
    "addr:postcode":"60660",
    "addr:street":"N Broadway St",
    "iso:country":"US",
    "sg:address":"5607 N Broadway St",
    "sg:city":"Chicago",
    "sg:classifiers":[
        {
            "category":"Personal",
            "subcategory":"Beauty Salon",
            "type":"Services"
        }
    ],
    "sg:phone":"+1 773 784 5997",
    "sg:postcode":"60660",
    "sg:province":"IL",
    "sg:tags":[
        "shop"
    ],
    "wof:name":"Daisy On Broadway",
    "wof:placetype":"venue"
},
  "geometry": {"coordinates":[-87.66000699999999,41.984034],"type":"Point"}
}