{
  "type": "Feature",
  "properties": {
    "addr:full":"1255 W Boughton Rd Bolingbrook IL 60440",
    "addr:housenumber":"1255",
    "addr:postcode":"60440",
    "addr:street":"W Boughton Rd",
    "iso:country":"US",
    "sg:address":"1255 W Boughton Rd",
    "sg:city":"Bolingbrook",
    "sg:classifiers":[
        {
            "category":"Restaurant",
            "type":"Food & Drink"
        }
    ],
    "sg:phone":"+1 630 226 0110",
    "sg:postcode":"60440",
    "sg:province":"IL",
    "sg:tags":[
        "eating"
    ],
    "sg:website":"www.cooldeli.com",
    "wof:name":"Schlotzsky S Deli",
    "wof:placetype":"venue"
},
  "geometry": {"coordinates":[-88.12544200000001,41.702966],"type":"Point"}
}