{
  "type": "Feature",
  "properties": {
    "iso:country":"US",
    "sg:address":"1255 W Boughton Rd",
    "sg:city":"Bolingbrook",
    "sg:classifiers":[
        {
            "category":"Restaurant",
            "type":"Food & Drink"
        }
    ],
    "sg:phone":"+1 630 226 0110",
    "sg:postcode":"60440",
    "sg:province":"IL",
    "sg:tags":[
        "eating"
    ],
    "sg:website":"www.cooldeli.com",
    "wof:name":"Schlotzsky S Deli",
    "wof:placetype":"venue"
},
  "geometry": {"coordinates":[-88.125442,41.702966],"type":"Point"}
}