{
  "type": "Feature",
  "properties": {
    "iso:country":"US",
    "sg:address":"4690 US Hwy 40",
    "sg:city":"Altamont",
    "sg:classifiers":[
        {
            "category":"Retail",
            "subcategory":"Auto Repair",
            "type":"Services"
        }
    ],
    "sg:phone":"+1 618 483 9936",
    "sg:postcode":"62411",
    "sg:province":"IL",
    "sg:tags":[
        "body",
        "automobile",
        "painting"
    ],
    "wof:name":"C-Bert's Body Shop",
    "wof:placetype":"venue"
},
  "geometry": {"coordinates":[-88.71405,39.065407],"type":"Point"}
}