{
  "type": "Feature",
  "properties": {
    "iso:country":"US",
    "sg:address":"1424 Sparta Centre Dr",
    "sg:city":"Sparta",
    "sg:classifiers":[
        {
            "category":"Restaurant",
            "type":"Food & Drink"
        }
    ],
    "sg:menulink":"http://www.allmenus.com/il/sparta/127462-subway/menu/",
    "sg:phone":"+1 618 443 2336",
    "sg:postcode":"62286",
    "sg:province":"IL",
    "sg:tags":[
        "american",
        "sandwich"
    ],
    "wof:name":"Subway",
    "wof:placetype":"venue"
},
  "geometry": {"coordinates":[-89.70463700000001,38.140411],"type":"Point"}
}