{
  "type": "Feature",
  "properties": {
    "iso:country":"US",
    "sg:address":"205 S West St",
    "sg:city":"Dakota",
    "sg:classifiers":[
        {
            "category":"Government",
            "subcategory":"Office",
            "type":"Public Place"
        }
    ],
    "sg:phone":"+1 815 449 2314",
    "sg:postcode":"61018",
    "sg:province":"IL",
    "sg:tags":[
        "village"
    ],
    "wof:name":"Dakota Twp Offices",
    "wof:placetype":"venue"
},
  "geometry": {"coordinates":[-89.526499,42.387411],"type":"Point"}
}