{
  "type": "Feature",
  "properties": {
    "addr:full":"4666 E Faries Pkwy Decatur IL 62526",
    "addr:housenumber":"4666",
    "addr:postcode":"62526",
    "addr:street":"E Faries Pkwy",
    "iso:country":"US",
    "sg:address":"4666 E Faries Pkwy",
    "sg:city":"Decatur",
    "sg:classifiers":[
        {
            "category":"Shopping",
            "subcategory":"Department Store",
            "type":"Retail Goods"
        }
    ],
    "sg:phone":"+1 217 424 5200",
    "sg:postcode":"62526",
    "sg:province":"IL",
    "sg:tags":[
        "oils-vegetable"
    ],
    "sg:website":"http://www.soy7.com",
    "wof:name":"Midwest Processing Company",
    "wof:placetype":"venue"
},
  "geometry": {"coordinates":[-88.88356400000001,39.86357],"type":"Point"}
}