{
  "type": "Feature",
  "properties": {
    "addr:full":"1375 E Schaumburg Rd Schaumburg IL 60194",
    "addr:housenumber":"1375",
    "addr:postcode":"60194",
    "addr:street":"E Schaumburg Rd",
    "iso:country":"US",
    "sg:address":"1375 E Schaumburg Rd",
    "sg:city":"Schaumburg",
    "sg:classifiers":[
        {
            "category":"Insurance",
            "subcategory":"Insurance Agent",
            "type":"Services"
        }
    ],
    "sg:phone":"+1 847 895 9588",
    "sg:postcode":"60194",
    "sg:province":"IL",
    "wof:name":"Schenone Insurance Agency",
    "wof:placetype":"venue"
},
  "geometry": {"coordinates":[-88.047291,42.028557],"type":"Point"}
}