{
  "type": "Feature",
  "properties": {
    "addr:full":"300 W Washington St Ste 500 Chicago IL 60606",
    "addr:housenumber":"300",
    "addr:postcode":"60606",
    "addr:street":"W Washington St Ste 500",
    "iso:country":"US",
    "sg:address":"300 W Washington St Ste 500",
    "sg:city":"Chicago",
    "sg:classifiers":[
        {
            "category":"Home & Garden",
            "subcategory":"Furniture",
            "type":"Retail Goods"
        }
    ],
    "sg:phone":"+1 312 423 5600",
    "sg:postcode":"60606",
    "sg:province":"IL",
    "sg:tags":[
        "store"
    ],
    "wof:name":"Woodard Furniture",
    "wof:placetype":"venue"
},
  "geometry": {"coordinates":[-87.635498,41.883301],"type":"Point"}
}