{
  "type": "Feature",
  "properties": {
    "addr:full":"1801 E 130th St Chicago IL 60633",
    "addr:housenumber":"1801",
    "addr:postcode":"60633",
    "addr:street":"E 130Th St",
    "iso:country":"US",
    "sg:address":"1801 E 130th St",
    "sg:city":"Chicago",
    "sg:classifiers":[
        {
            "category":"Wholesale",
            "subcategory":"Motor Vehicles",
            "type":"Manufacturing & Wholesale Goods"
        },
        {
            "category":"Travel",
            "subcategory":"Travel Agent",
            "type":"Entertainment"
        },
        {
            "category":"Retail",
            "subcategory":"Auto Repair",
            "type":"Services"
        }
    ],
    "sg:phone":"+1 773 646 3507",
    "sg:postcode":"60633",
    "sg:province":"IL",
    "sg:tags":[
        "campers-wholesale",
        "recreational",
        "trailers-repair",
        "truck",
        "trailer",
        "manufacturer"
    ],
    "wof:name":"Calumet Trailer Service Inc",
    "wof:placetype":"venue"
},
  "geometry": {"coordinates":[-87.578682,41.659191],"type":"Point"}
}