{
  "type": "Feature",
  "properties": {
    "addr:full":"6920 S Ashland Ave Chicago IL 60636",
    "addr:housenumber":"6920",
    "addr:postcode":"60636",
    "addr:street":"S Ashland Ave",
    "iso:country":"US",
    "sg:address":"6920 S Ashland Ave",
    "sg:city":"Chicago",
    "sg:classifiers":[
        {
            "category":"Personal",
            "subcategory":"Nail Salon",
            "type":"Services"
        }
    ],
    "sg:phone":"+1 773 434 4588",
    "sg:postcode":"60636",
    "sg:province":"IL",
    "wof:name":"China Nails",
    "wof:placetype":"venue"
},
  "geometry": {"coordinates":[-87.664165,41.768147],"type":"Point"}
}