{
  "type": "Feature",
  "properties": {
    "addr:full":"1772 Bradford Ln Crystal Lake IL 60014",
    "addr:housenumber":"1772",
    "addr:postcode":"60014",
    "addr:street":"Bradford Ln",
    "iso:country":"US",
    "sg:address":"1772 Bradford Ln",
    "sg:city":"Crystal Lake",
    "sg:classifiers":[
        {
            "category":"Wholesale",
            "subcategory":"Groceries",
            "type":"Manufacturing & Wholesale Goods"
        }
    ],
    "sg:phone":"+1 815 477 2470",
    "sg:postcode":"60014",
    "sg:province":"IL",
    "wof:name":"Pappas Clement and Company",
    "wof:placetype":"venue"
},
  "geometry": {"coordinates":[-88.341685,42.191445],"type":"Point"}
}