{
  "type": "Feature",
  "properties": {
    "iso:country":"US",
    "sg:address":"4709 Coxeyville Rd",
    "sg:city":"Columbia",
    "sg:classifiers":[
        {
            "category":"Building & Trades",
            "subcategory":"Construction",
            "type":"Services"
        }
    ],
    "sg:phone":"+1 618 939 3999",
    "sg:postcode":"62236",
    "sg:province":"IL",
    "sg:tags":[
        "excavation",
        "contractor"
    ],
    "wof:name":"Vogt, James H Trckg & Excvtg",
    "wof:placetype":"venue"
},
  "geometry": {"coordinates":[-90.139167,38.386728],"type":"Point"}
}