{
  "type": "Feature",
  "properties": {
    "iso:country":"US",
    "sg:address":"4007 Arthur Ave",
    "sg:city":"Brookfield",
    "sg:classifiers":[
        {
            "category":"Retail",
            "subcategory":"Repair Shop",
            "type":"Services"
        }
    ],
    "sg:phone":"+1 708 485 5610",
    "sg:postcode":"60513",
    "sg:province":"IL",
    "wof:name":"Ryan Communications",
    "wof:placetype":"venue"
},
  "geometry": {"coordinates":[-87.852535,41.817647],"type":"Point"}
}