{
  "type": "Feature",
  "properties": {
    "iso:country":"US",
    "sg:address":"201 US Hwy 45",
    "sg:city":"Vernon Hills",
    "sg:classifiers":[
        {
            "category":"Organizations",
            "subcategory":"Professional Association",
            "type":"Services"
        }
    ],
    "sg:phone":"+1 847 680 3500",
    "sg:postcode":"60061",
    "sg:province":"IL",
    "sg:website":"www.mheda.org",
    "wof:name":"Material Handling Equipment",
    "wof:placetype":"venue"
},
  "geometry": {"coordinates":[-87.968032,42.221266],"type":"Point"}
}