{
  "type": "Feature",
  "properties": {
    "addr:full":"734 Ogden Ave Downers Grove IL 60515",
    "addr:housenumber":"734",
    "addr:postcode":"60515",
    "addr:street":"Ogden Ave",
    "iso:country":"US",
    "sg:address":"734 Ogden Ave",
    "sg:city":"Downers Grove",
    "sg:classifiers":[
        {
            "category":"Shopping",
            "subcategory":"Hobbies, Toys, & Games",
            "type":"Retail Goods"
        }
    ],
    "sg:phone":"+1   ",
    "sg:postcode":"60515",
    "sg:province":"IL",
    "sg:tags":[
        "arts",
        "craft",
        "ornament",
        "lawn"
    ],
    "wof:name":"Carnival Of Crafts",
    "wof:placetype":"venue"
},
  "geometry": {"coordinates":[-88.00473700000001,41.80924],"type":"Point"}
}