{
  "type": "Feature",
  "properties": {
    "iso:country":"US",
    "sg:address":"5939 Lyford Rd",
    "sg:city":"Caledonia",
    "sg:phone":"+1 815 885 3091",
    "sg:postcode":"61011",
    "sg:province":"IL",
    "sg:tags":[
        "hog",
        "farm",
        "corn",
        "cash",
        "dairy",
        "grain",
        "or"
    ],
    "wof:name":"James Lyford Farm",
    "wof:placetype":"venue"
},
  "geometry": {"coordinates":[-88.953856,42.344901],"type":"Point"}
}