{
  "type": "Feature",
  "properties": {
    "iso:country":"US",
    "sg:address":"10210 Lincoln Trl",
    "sg:city":"Fairview Heights",
    "sg:classifiers":[
        {
            "category":"Professional",
            "subcategory":"Accounting & Tax Preparation",
            "type":"Services"
        }
    ],
    "sg:phone":"+1 618 397 0938",
    "sg:postcode":"62208",
    "sg:province":"IL",
    "sg:tags":[
        "return",
        "filing"
    ],
    "wof:name":"Jackson Hewitt Tax Svc",
    "wof:placetype":"venue"
},
  "geometry": {"coordinates":[-90.006889,38.59294],"type":"Point"}
}