{
  "type": "Feature",
  "properties": {
    "addr:full":"18350 Kedzie Ave Homewood IL 60430",
    "addr:housenumber":"18350",
    "addr:postcode":"60430",
    "addr:street":"Kedzie Ave",
    "iso:country":"US",
    "sg:address":"18350 Kedzie Ave",
    "sg:city":"Homewood",
    "sg:classifiers":[
        {
            "category":"Banks & Credit Unions",
            "subcategory":"Bank",
            "type":"Services"
        }
    ],
    "sg:phone":"+1 708 647 7800",
    "sg:postcode":"60430",
    "sg:province":"IL",
    "sg:tags":[
        "broker",
        "mortgage"
    ],
    "wof:name":"Premium Financial Network Inc",
    "wof:placetype":"venue"
},
  "geometry": {"coordinates":[-87.69426,41.557074],"type":"Point"}
}