{
  "type": "Feature",
  "properties": {
    "addr:full":"11 S La Salle St Ste 2401 Chicago IL 60603",
    "addr:housenumber":"11",
    "addr:postcode":"60603",
    "addr:street":"S La Salle St Ste 2401",
    "iso:country":"US",
    "sg:address":"11 S La Salle St Ste 2401",
    "sg:city":"Chicago",
    "sg:classifiers":[
        {
            "category":"Wholesale",
            "subcategory":"Stationery",
            "type":"Manufacturing & Wholesale Goods"
        }
    ],
    "sg:phone":"+1 312 419 9333",
    "sg:postcode":"60603",
    "sg:province":"IL",
    "sg:tags":[
        "card"
    ],
    "wof:name":"Plaza Corp",
    "wof:placetype":"venue"
},
  "geometry": {"coordinates":[-87.63232000000001,41.881667],"type":"Point"}
}