{
  "type": "Feature",
  "properties": {
    "iso:country":"US",
    "sg:address":"6839 N Milwaukee Ave",
    "sg:city":"Niles",
    "sg:classifiers":[
        {
            "category":"Professional",
            "type":"Services"
        },
        {
            "category":"Restaurant",
            "type":"Food & Drink"
        },
        {
            "category":"Retail",
            "subcategory":"Event Space",
            "type":"Services"
        },
        {
            "category":"Conference Center",
            "type":"Public Place"
        }
    ],
    "sg:phone":"+1 847 871 0728",
    "sg:postcode":"60714",
    "sg:province":"IL",
    "sg:tags":[
        "facility",
        "caterer",
        "hall",
        "reception",
        "convention",
        "banquet"
    ],
    "sg:website":"http://www.thewhiteeagle.com",
    "wof:name":"White Eagle Banquets & Restaurant",
    "wof:placetype":"venue"
},
  "geometry": {"coordinates":[-87.795242,42.005428],"type":"Point"}
}