{
  "type": "Feature",
  "properties": {
    "addr:full":"23W525 Saint Charles Rd Carol Stream IL 60188",
    "addr:housenumber":"23w525",
    "addr:postcode":"60188",
    "addr:street":"Saint Charles Rd",
    "iso:country":"US",
    "sg:address":"23W525 Saint Charles Rd",
    "sg:city":"Carol Stream",
    "sg:classifiers":[
        {
            "category":"Health Services",
            "subcategory":"Doctor",
            "type":"Services"
        }
    ],
    "sg:phone":"+1 630 871 0000",
    "sg:postcode":"60188",
    "sg:province":"IL",
    "wof:name":"Nemec Keith Dr",
    "wof:placetype":"venue"
},
  "geometry": {"coordinates":[-88.08521500000001,41.895004],"type":"Point"}
}