{
  "type": "Feature",
  "properties": {
    "addr:full":"400 Skokie Blvd Northbrook IL 60062",
    "addr:housenumber":"400",
    "addr:postcode":"60062",
    "addr:street":"Skokie Blvd",
    "iso:country":"US",
    "sg:address":"400 Skokie Blvd",
    "sg:city":"Northbrook",
    "sg:classifiers":[
        {
            "category":"Professional",
            "subcategory":"Management & Consulting",
            "type":"Services"
        }
    ],
    "sg:phone":"+1 847 504 0990",
    "sg:postcode":"60062",
    "sg:province":"IL",
    "sg:tags":[
        "consultant"
    ],
    "wof:name":"Adroit Consulting",
    "wof:placetype":"venue"
},
  "geometry": {"coordinates":[-87.795126,42.143285],"type":"Point"}
}