{
  "type": "Feature",
  "properties": {
    "iso:country":"US",
    "sg:address":"10 Island View Ln",
    "sg:city":"Kankakee",
    "sg:classifiers":[
        {
            "category":"Shopping",
            "subcategory":"Bicycles & Sporting Goods",
            "type":"Retail Goods"
        }
    ],
    "sg:phone":"+1 815 932 7140",
    "sg:postcode":"60901",
    "sg:province":"IL",
    "sg:tags":[
        "saddlery",
        "harness"
    ],
    "wof:name":"Sunrise Tack Shop",
    "wof:placetype":"venue"
},
  "geometry": {"coordinates":[-87.824877,41.093368],"type":"Point"}
}