{
  "type": "Feature",
  "properties": {
    "addr:full":"4059 N Milwaukee Ave Chicago IL 60641",
    "addr:housenumber":"4059",
    "addr:postcode":"60641",
    "addr:street":"N Milwaukee Ave",
    "iso:country":"US",
    "sg:address":"4059 N Milwaukee Ave",
    "sg:city":"Chicago",
    "sg:classifiers":[
        {
            "category":"Restaurant",
            "type":"Food & Drink"
        }
    ],
    "sg:phone":"+1   ",
    "sg:postcode":"60641",
    "sg:province":"IL",
    "sg:tags":[
        "eating"
    ],
    "wof:name":"Herradero",
    "wof:placetype":"venue"
},
  "geometry": {"coordinates":[-87.749591,41.955091],"type":"Point"}
}