{
  "type": "Feature",
  "properties": {
    "iso:country":"US",
    "sg:address":"7239 S Yale Ave Apt 3",
    "sg:city":"Chicago",
    "sg:classifiers":[
        {
            "category":"Shopping",
            "subcategory":"Crafts & Fabrics",
            "type":"Retail Goods"
        }
    ],
    "sg:phone":"+1 773 723 0710",
    "sg:postcode":"60621",
    "sg:province":"IL",
    "sg:tags":[
        "supplies-wholesale",
        "manufacturer",
        "art",
        "supply"
    ],
    "wof:name":"Rosa L Davis",
    "wof:placetype":"venue"
},
  "geometry": {"coordinates":[-87.630939,41.762875],"type":"Point"}
}