{
  "type": "Feature",
  "properties": {
    "addr:full":"7900 Nagle Ave Morton Grove IL 60053",
    "addr:housenumber":"7900",
    "addr:postcode":"60053",
    "addr:street":"Nagle Ave",
    "iso:country":"US",
    "sg:address":"7900 Nagle Ave",
    "sg:city":"Morton Grove",
    "sg:classifiers":[
        {
            "category":"Health Services",
            "subcategory":"Clinic",
            "type":"Services"
        }
    ],
    "sg:phone":"+1 847 965 9269",
    "sg:postcode":"60053",
    "sg:province":"IL",
    "sg:tags":[
        "home",
        "care"
    ],
    "wof:name":"Addus Healthcare Inc",
    "wof:placetype":"venue"
},
  "geometry": {"coordinates":[-87.78743299999999,42.02466],"type":"Point"}
}