{
  "type": "Feature",
  "properties": {
    "iso:country":"US",
    "sg:address":"8535 Mansfield Ave",
    "sg:city":"Morton Grove",
    "sg:classifiers":[
        {
            "category":"Professional",
            "subcategory":"Art Services",
            "type":"Services"
        }
    ],
    "sg:phone":"+1 847 965 6871",
    "sg:postcode":"60053",
    "sg:province":"IL",
    "sg:tags":[
        "commercial",
        "design"
    ],
    "wof:name":"Blue Stem Studio",
    "wof:placetype":"venue"
},
  "geometry": {"coordinates":[-87.772743,42.037069],"type":"Point"}
}