{
  "type": "Feature",
  "properties": {
    "addr:full":"339 Margaret St Ste 2 Pekin IL 61554",
    "addr:housenumber":"339",
    "addr:postcode":"61554",
    "addr:street":"Margaret St Ste 2",
    "iso:country":"US",
    "sg:address":"339 Margaret St Ste 2",
    "sg:city":"Pekin",
    "sg:phone":"+1 309 346 4247",
    "sg:postcode":"61554",
    "sg:province":"IL",
    "wof:name":"Central Hair Salon Inc",
    "wof:placetype":"venue"
},
  "geometry": {"coordinates":[-89.647791,40.570499],"type":"Point"}
}