{
  "type": "Feature",
  "properties": {
    "iso:country":"US",
    "sg:address":"3125 N Cicero Ave",
    "sg:city":"Chicago",
    "sg:classifiers":[
        {
            "category":"Autos & Motor Vehicles",
            "subcategory":"Automobile Sales",
            "type":"Retail Goods"
        }
    ],
    "sg:phone":"+1 773 286 8888",
    "sg:postcode":"60641",
    "sg:province":"IL",
    "sg:tags":[
        "car"
    ],
    "sg:website":"www.automaxchicago.com",
    "wof:name":"Automax",
    "wof:placetype":"venue"
},
  "geometry": {"coordinates":[-87.746802,41.937768],"type":"Point"}
}