{
  "type": "Feature",
  "properties": {
    "iso:country":"US",
    "sg:address":"1818 E Northwest Hwy",
    "sg:city":"Arlington Hts",
    "sg:classifiers":[
        {
            "category":"Wholesale",
            "subcategory":"Home Furnishings",
            "type":"Manufacturing & Wholesale Goods"
        },
        {
            "category":"Wholesale",
            "subcategory":"Durable Goods & Equipment",
            "type":"Manufacturing & Wholesale Goods"
        }
    ],
    "sg:phone":"+1 847 577 0560",
    "sg:postcode":"60004",
    "sg:province":"IL",
    "sg:tags":[
        "hardware",
        "representative",
        "manufacturer"
    ],
    "wof:name":"Conlon-Meyer & Associates",
    "wof:placetype":"venue"
},
  "geometry": {"coordinates":[-87.960302,42.074098],"type":"Point"}
}