{
  "type": "Feature",
  "properties": {
    "addr:full":"1138 N California Ave Chicago IL 60622",
    "addr:housenumber":"1138",
    "addr:postcode":"60622",
    "addr:street":"N California Ave",
    "iso:country":"US",
    "sg:address":"1138 N California Ave",
    "sg:city":"Chicago",
    "sg:classifiers":[
        {
            "category":"Arts & Performance",
            "subcategory":"Art Gallery",
            "type":"Entertainment"
        }
    ],
    "sg:phone":"+1 773 733 1966",
    "sg:postcode":"60622",
    "sg:province":"IL",
    "sg:website":"www.christopherfurman.com/",
    "wof:name":"CF Devices",
    "wof:placetype":"venue"
},
  "geometry": {"coordinates":[-87.697238,41.902246],"type":"Point"}
}