{
  "type": "Feature",
  "properties": {
    "addr:full":"1300 Butterfield Rd Downers Grove IL 60515",
    "addr:housenumber":"1300",
    "addr:postcode":"60515",
    "addr:street":"Butterfield Rd",
    "iso:country":"US",
    "sg:address":"1300 Butterfield Rd",
    "sg:city":"Downers Grove",
    "sg:classifiers":[
        {
            "category":"Shopping",
            "subcategory":"Clothing, Apparel, & Fashions",
            "type":"Retail Goods"
        }
    ],
    "sg:phone":"+1 630 495 8558",
    "sg:postcode":"60515",
    "sg:province":"IL",
    "wof:name":"Catherines Plus Sizes",
    "wof:placetype":"venue"
},
  "geometry": {"coordinates":[-88.018963,41.834416],"type":"Point"}
}