{
  "type": "Feature",
  "properties": {
    "addr:full":"711 W Gordon Ter Chicago IL 60613",
    "addr:housenumber":"711",
    "addr:postcode":"60613",
    "addr:street":"W Gordon Ter",
    "iso:country":"US",
    "sg:address":"711 W Gordon Ter",
    "sg:city":"Chicago",
    "sg:classifiers":[
        {
            "category":"Wholesale",
            "subcategory":"Motor Vehicles",
            "type":"Manufacturing & Wholesale Goods"
        }
    ],
    "sg:phone":"+1 773 965 0123",
    "sg:postcode":"60613",
    "sg:province":"IL",
    "sg:tags":[
        "scooter"
    ],
    "wof:name":"Kickbike America",
    "wof:placetype":"venue"
},
  "geometry": {"coordinates":[-87.64821999999999,41.957851],"type":"Point"}
}