{
  "type": "Feature",
  "properties": {
    "iso:country":"US",
    "sg:address":"2939 W 63rd St",
    "sg:city":"Chicago",
    "sg:classifiers":[
        {
            "category":"Food & Beverages",
            "subcategory":"Groceries & Convenience Stores",
            "type":"Retail Goods"
        }
    ],
    "sg:phone":"+1 773 737 0549",
    "sg:postcode":"60629",
    "sg:province":"IL",
    "wof:name":"Los DOS Rios",
    "wof:placetype":"venue"
},
  "geometry": {"coordinates":[-87.697304,41.7789],"type":"Point"}
}