{
  "type": "Feature",
  "properties": {
    "iso:country":"US",
    "sg:address":"461 N Mulford Rd",
    "sg:city":"Rockford",
    "sg:classifiers":[
        {
            "category":"Insurance",
            "subcategory":"Insurance Agent",
            "type":"Services"
        }
    ],
    "sg:phone":"+1 815 229 3553",
    "sg:postcode":"61107",
    "sg:province":"IL",
    "wof:name":"Assurance Unlimited Service",
    "wof:placetype":"venue"
},
  "geometry": {"coordinates":[-88.99938,42.272213],"type":"Point"}
}