{
  "type": "Feature",
  "properties": {
    "addr:full":"1405 W Jeffery St Kankakee IL 60914",
    "addr:housenumber":"1405",
    "addr:postcode":"60914",
    "addr:street":"W Jeffery St",
    "iso:country":"US",
    "sg:address":"1405 W Jeffery St",
    "sg:city":"Kankakee",
    "sg:classifiers":[
        {
            "category":"Utilities",
            "subcategory":"Mobile Phone",
            "type":"Services"
        }
    ],
    "sg:phone":"+1 815 320 0118",
    "sg:postcode":"60914",
    "sg:province":"IL",
    "sg:tags":[
        "equipment",
        "paging",
        "signaling",
        "system"
    ],
    "wof:name":"Heartland Communications",
    "wof:placetype":"venue"
},
  "geometry": {"coordinates":[-87.891693,41.106083],"type":"Point"}
}