{
  "type": "Feature",
  "properties": {
    "iso:country":"US",
    "sg:address":"710 E 2nd St",
    "sg:city":"Gilman",
    "sg:classifiers":[
        {
            "category":"Building & Trades",
            "subcategory":"Construction",
            "type":"Services"
        }
    ],
    "sg:phone":"+1 815 265 4881",
    "sg:postcode":"60938",
    "sg:province":"IL",
    "sg:tags":[
        "general",
        "contractor"
    ],
    "wof:name":"General Material Corp",
    "wof:placetype":"venue"
},
  "geometry": {"coordinates":[-87.978167,40.768651],"type":"Point"}
}