{
  "type": "Feature",
  "properties": {
    "addr:full":"1643 N Claremont Ave Chicago IL 60647",
    "addr:housenumber":"1643",
    "addr:postcode":"60647",
    "addr:street":"N Claremont Ave",
    "iso:country":"US",
    "sg:address":"1643 N Claremont Ave",
    "sg:city":"Chicago",
    "sg:classifiers":[
        {
            "category":"Wholesale",
            "subcategory":"Medical Equipment & Supplies",
            "type":"Manufacturing & Wholesale Goods"
        }
    ],
    "sg:phone":"+1 773 384 6010",
    "sg:postcode":"60647",
    "sg:province":"IL",
    "sg:tags":[
        "massage"
    ],
    "wof:name":"Aqua-Float Inc",
    "wof:placetype":"venue"
},
  "geometry": {"coordinates":[-87.685965,41.911675],"type":"Point"}
}