{
  "type": "Feature",
  "properties": {
    "addr:full":"854 S Arthur Ave Arlington Hts IL 60005",
    "addr:housenumber":"854",
    "addr:postcode":"60005",
    "addr:street":"S Arthur Ave",
    "iso:country":"US",
    "sg:address":"854 S Arthur Ave",
    "sg:city":"Arlington Hts",
    "sg:classifiers":[
        {
            "category":"Retail",
            "subcategory":"Repair Shop",
            "type":"Services"
        }
    ],
    "sg:phone":"+1 847 255 7130",
    "sg:postcode":"60005",
    "sg:province":"IL",
    "sg:tags":[
        "cleaners",
        "parts",
        "vacuum"
    ],
    "wof:name":"Electrolux",
    "wof:placetype":"venue"
},
  "geometry": {"coordinates":[-87.966145,42.073276],"type":"Point"}
}