{
  "type": "Feature",
  "properties": {
    "iso:country":"US",
    "sg:address":"3446 West Foster Ave",
    "sg:city":"Chicago",
    "sg:classifiers":[
        {
            "category":"Restaurant",
            "type":"Food & Drink"
        }
    ],
    "sg:phone":"+1 773 539 9004",
    "sg:postcode":"60625",
    "sg:province":"IL",
    "sg:tags":[
        "greek",
        "mediterranean"
    ],
    "wof:name":"Carthage Cafe",
    "wof:placetype":"venue"
},
  "geometry": {"coordinates":[-87.715103,41.9758],"type":"Point"}
}