{
  "type": "Feature",
  "properties": {
    "iso:country":"US",
    "sg:address":"9601 S Torrence Ave",
    "sg:city":"Chicago",
    "sg:classifiers":[
        {
            "category":"Autos & Motor Vehicles",
            "subcategory":"Automobile Sales",
            "type":"Retail Goods"
        },
        {
            "category":"Autos & Motor Vehicles",
            "subcategory":"Auto Supplies",
            "type":"Retail Goods"
        }
    ],
    "sg:phone":"+1 773 978 2160",
    "sg:postcode":"60617",
    "sg:province":"IL",
    "sg:tags":[
        "salvage",
        "rebuilt",
        "part",
        "supplies-used"
    ],
    "wof:name":"Torrence Auto Wreckers & Used Parts",
    "wof:placetype":"venue"
},
  "geometry": {"coordinates":[-87.559822,41.72084],"type":"Point"}
}