{
  "type": "Feature",
  "properties": {
    "addr:full":"5805 W Gardner Rd Verona IL 60479",
    "addr:housenumber":"5805",
    "addr:postcode":"60479",
    "addr:street":"W Gardner Rd",
    "iso:country":"US",
    "sg:address":"5805 W Gardner Rd",
    "sg:city":"Verona",
    "sg:classifiers":[
        {
            "category":"Freight",
            "type":"Transportation"
        }
    ],
    "sg:phone":"+1 815 287 2177",
    "sg:postcode":"60479",
    "sg:province":"IL",
    "sg:tags":[
        "local",
        "storage",
        "trucking"
    ],
    "wof:name":"Jbc Carriers Inc",
    "wof:placetype":"venue"
},
  "geometry": {"coordinates":[-88.528887,41.181096],"type":"Point"}
}