{
  "type": "Feature",
  "properties": {
    "addr:full":"4300 S Morgan Street Chicago IL 60609",
    "addr:housenumber":"4300",
    "addr:postcode":"60609",
    "addr:street":"S Morgan Street",
    "iso:country":"US",
    "sg:address":"4300 S Morgan Street",
    "sg:city":"Chicago",
    "sg:classifiers":[
        {
            "category":"Food & Beverages",
            "subcategory":"Candy",
            "type":"Retail Goods"
        }
    ],
    "sg:phone":"+1 773 927 4000",
    "sg:postcode":"60609",
    "sg:province":"IL",
    "sg:tags":[
        "store"
    ],
    "wof:name":"Guernsey Bell",
    "wof:placetype":"venue"
},
  "geometry": {"coordinates":[-87.65061900000001,41.815978],"type":"Point"}
}