{
  "type": "Feature",
  "properties": {
    "iso:country":"US",
    "sg:address":"267 Maple St",
    "sg:city":"Springfield",
    "sg:classifiers":[
        {
            "category":"Organizations",
            "subcategory":"Community Association",
            "type":"Services"
        }
    ],
    "sg:phone":"+1 217 529 4901",
    "sg:postcode":"61238",
    "sg:province":"IL",
    "sg:tags":[
        "club"
    ],
    "wof:name":"Prop Club",
    "wof:placetype":"venue"
},
  "geometry": {"coordinates":[-90.190302,41.29845],"type":"Point"}
}