{
  "type": "Feature",
  "properties": {
    "iso:country":"US",
    "sg:address":"1054 Ridgefield Cir",
    "sg:city":"Carol Stream",
    "sg:classifiers":[
        {
            "category":"Insurance",
            "subcategory":"Insurance Agent",
            "type":"Services"
        }
    ],
    "sg:phone":"+1 630 213 2544",
    "sg:postcode":"60188",
    "sg:province":"IL",
    "wof:name":"Insurance Benefits",
    "wof:placetype":"venue"
},
  "geometry": {"coordinates":[-88.158396,41.9398],"type":"Point"}
}