{
  "type": "Feature",
  "properties": {
    "addr:full":"301 S 7th St Quincy IL 62301",
    "addr:housenumber":"301",
    "addr:postcode":"62301",
    "addr:street":"S 7Th St",
    "iso:country":"US",
    "sg:address":"301 S 7th St",
    "sg:city":"Quincy",
    "sg:classifiers":[
        {
            "category":"Wholesale",
            "subcategory":"Electrical",
            "type":"Manufacturing & Wholesale Goods"
        }
    ],
    "sg:phone":"+1 217 222 0545",
    "sg:postcode":"62301",
    "sg:province":"IL",
    "sg:tags":[
        "supply"
    ],
    "wof:name":"Gem City Electric Co",
    "wof:placetype":"venue"
},
  "geometry": {"coordinates":[-91.40468799999999,39.929334],"type":"Point"}
}