{
  "type": "Feature",
  "properties": {
    "iso:country":"US",
    "sg:address":"1410 W Polk St",
    "sg:city":"Chicago",
    "sg:classifiers":[
        {
            "category":"Education",
            "subcategory":"School",
            "type":"Public Place"
        }
    ],
    "sg:phone":"+1 708 215 1608",
    "sg:postcode":"60607",
    "sg:province":"IL",
    "sg:tags":[
        "k-",
        "private"
    ],
    "wof:name":"Romance Language Academy",
    "wof:placetype":"venue"
},
  "geometry": {"coordinates":[-87.66234900000001,41.871697],"type":"Point"}
}