{
  "type": "Feature",
  "properties": {
    "addr:full":"5909 Town Hall Rd Belleville IL 62223",
    "addr:housenumber":"5909",
    "addr:postcode":"62223",
    "addr:street":"Town Hall Rd",
    "iso:country":"US",
    "sg:address":"5909 Town Hall Rd",
    "sg:city":"Belleville",
    "sg:classifiers":[
        {
            "category":"Home & Garden",
            "subcategory":"Building Materials",
            "type":"Retail Goods"
        }
    ],
    "sg:phone":"+1 618 277 7010",
    "sg:postcode":"62223",
    "sg:province":"IL",
    "sg:tags":[
        "roofing"
    ],
    "wof:name":"Dealers Service & Supply",
    "wof:placetype":"venue"
},
  "geometry": {"coordinates":[-90.036435,38.522076],"type":"Point"}
}