{
  "type": "Feature",
  "properties": {
    "iso:country":"US",
    "sg:address":"1418 E Hintz Rd",
    "sg:city":"Arlington Heights",
    "sg:classifiers":[
        {
            "category":"Food & Beverages",
            "subcategory":"Groceries & Convenience Stores",
            "type":"Retail Goods"
        }
    ],
    "sg:phone":"+1   ",
    "sg:postcode":"60004",
    "sg:province":"IL",
    "wof:name":"White Hen Pantry",
    "wof:placetype":"venue"
},
  "geometry": {"coordinates":[-87.966233,42.124546],"type":"Point"}
}