{
  "type": "Feature",
  "properties": {
    "iso:country":"US",
    "sg:address":"1401 W Oak St",
    "sg:city":"Fairbury",
    "sg:classifiers":[
        {
            "category":"Utilities",
            "subcategory":"Water",
            "type":"Services"
        },
        {
            "category":"Building & Trades",
            "subcategory":"Plumbing",
            "type":"Services"
        },
        {
            "category":"Home & Garden",
            "subcategory":"Hardware",
            "type":"Retail Goods"
        }
    ],
    "sg:phone":"+1 815 692 3113",
    "sg:postcode":"61739",
    "sg:province":"IL",
    "sg:tags":[
        "filtration",
        "softening",
        "supply",
        "work",
        "purification",
        "equipment",
        "conditioning"
    ],
    "sg:website":"http://www.hicksgas.com",
    "wof:name":"Hicksgas",
    "wof:placetype":"venue"
},
  "geometry": {"coordinates":[-88.53411800000001,40.744022],"type":"Point"}
}