{
  "type": "Feature",
  "properties": {
    "addr:full":"4995 W Pershing Rd Cicero IL 60804",
    "addr:housenumber":"4995",
    "addr:postcode":"60804",
    "addr:street":"W Pershing Rd",
    "iso:country":"US",
    "sg:address":"4995 W Pershing Rd",
    "sg:city":"Cicero",
    "sg:classifiers":[
        {
            "category":"Autos & Motor Vehicles",
            "subcategory":"Fuel & Gas Station",
            "type":"Retail Goods"
        }
    ],
    "sg:phone":"+1 708 222 8404",
    "sg:postcode":"60804",
    "sg:province":"IL",
    "sg:tags":[
        "terminal",
        "truck"
    ],
    "wof:name":"Chicago Motor Express Inc",
    "wof:placetype":"venue"
},
  "geometry": {"coordinates":[-87.758747,41.821705],"type":"Point"}
}