{
  "type": "Feature",
  "properties": {
    "iso:country":"US",
    "sg:address":"165 W Pershing Rd",
    "sg:city":"Decatur",
    "sg:classifiers":[
        {
            "category":"Autos & Motor Vehicles",
            "subcategory":"Automobile Sales",
            "type":"Retail Goods"
        },
        {
            "category":"Retail",
            "subcategory":"Auto Repair",
            "type":"Services"
        }
    ],
    "sg:phone":"+1 866 390 0187",
    "sg:postcode":"62526",
    "sg:province":"IL",
    "sg:tags":[
        "used",
        "leasing",
        "car",
        "truck",
        "new"
    ],
    "sg:website":"http://www.milesnissan.com/",
    "wof:name":"Miles Nissan",
    "wof:placetype":"venue"
},
  "geometry": {"coordinates":[-88.982727,39.876135],"type":"Point"}
}