{
  "type": "Feature",
  "properties": {
    "iso:country":"US",
    "sg:address":"212 S Marion St",
    "sg:city":"Oak Park",
    "sg:classifiers":[
        {
            "category":"Manufacturing",
            "subcategory":"Tools & Machinery",
            "type":"Manufacturing & Wholesale Goods"
        }
    ],
    "sg:phone":"+1 708 848 3388",
    "sg:postcode":"60302",
    "sg:province":"IL",
    "sg:tags":[
        "equipment",
        "peripheral",
        "computer",
        "mfg"
    ],
    "wof:name":"Harry B Voigt Graphic Designer",
    "wof:placetype":"venue"
},
  "geometry": {"coordinates":[-87.802432,41.885541],"type":"Point"}
}