{
  "type": "Feature",
  "properties": {
    "iso:country":"US",
    "sg:address":"30 E Olive St",
    "sg:city":"Canton",
    "sg:classifiers":[
        {
            "category":"Personal",
            "subcategory":"Beauty Salon",
            "type":"Services"
        }
    ],
    "sg:phone":"+1 309 647 6563",
    "sg:postcode":"61520",
    "sg:province":"IL",
    "wof:name":"Guys & Dolls Styling Salon",
    "wof:placetype":"venue"
},
  "geometry": {"coordinates":[-90.03383,40.562131],"type":"Point"}
}