{
  "type": "Feature",
  "properties": {
    "iso:country":"US",
    "sg:address":"2107 E A St",
    "sg:city":"Belleville",
    "sg:classifiers":[
        {
            "category":"Organizations",
            "subcategory":"Community Association",
            "type":"Services"
        }
    ],
    "sg:phone":"+1 618 277 6214",
    "sg:postcode":"62221",
    "sg:province":"IL",
    "sg:tags":[
        "youth"
    ],
    "wof:name":"Interntnal Order Jobs Dughters",
    "wof:placetype":"venue"
},
  "geometry": {"coordinates":[-89.955108,38.526424],"type":"Point"}
}