{
  "type": "Feature",
  "properties": {
    "iso:country":"US",
    "sg:address":"2322 7th Ave",
    "sg:city":"Rockford",
    "sg:classifiers":[
        {
            "category":"Manufacturing",
            "subcategory":"Tools & Machinery",
            "type":"Manufacturing & Wholesale Goods"
        },
        {
            "category":"Manufacturing",
            "subcategory":"Motor Vehicles & Parts",
            "type":"Manufacturing & Wholesale Goods"
        }
    ],
    "sg:phone":"+1 815 229 5300",
    "sg:postcode":"61104",
    "sg:province":"IL",
    "sg:tags":[
        "manufacture",
        "engine",
        "industrial",
        "relay",
        "governor",
        "control"
    ],
    "sg:website":"www.precisiongovernors.com",
    "wof:name":"Precision Governors Inc",
    "wof:placetype":"venue"
},
  "geometry": {"coordinates":[-89.058012,42.259466],"type":"Point"}
}