{
  "type": "Feature",
  "properties": {
    "iso:country":"US",
    "sg:address":"1663 McDowell Ave",
    "sg:city":"Aurora",
    "sg:classifiers":[
        {
            "category":"Social Services",
            "subcategory":"Child Care",
            "type":"Services"
        }
    ],
    "sg:phone":"+1 630 585 6374",
    "sg:postcode":"60504",
    "sg:province":"IL",
    "wof:name":"Dawn Seno",
    "wof:placetype":"venue"
},
  "geometry": {"coordinates":[-88.265028,41.725822],"type":"Point"}
}