{
  "type": "Feature",
  "properties": {
    "addr:full":"151 Harrison St Bourbonnais IL 60914",
    "addr:housenumber":"151",
    "addr:postcode":"60914",
    "addr:street":"Harrison St",
    "iso:country":"US",
    "sg:address":"151 Harrison St",
    "sg:city":"Bourbonnais",
    "sg:classifiers":[
        {
            "category":"Personal",
            "type":"Services"
        }
    ],
    "sg:phone":"+1 815 933 3434",
    "sg:postcode":"60914",
    "sg:province":"IL",
    "wof:name":"Brownbodies Tanning",
    "wof:placetype":"venue"
},
  "geometry": {"coordinates":[-87.878238,41.153781],"type":"Point"}
}