{
  "type": "Feature",
  "properties": {
    "addr:full":"1360 N Sandburg Ter Chicago IL 60610",
    "addr:housenumber":"1360",
    "addr:postcode":"60610",
    "addr:street":"N Sandburg Ter",
    "iso:country":"US",
    "sg:address":"1360 N Sandburg Ter",
    "sg:city":"Chicago",
    "sg:classifiers":[
        {
            "category":"Health Services",
            "subcategory":"Doctor",
            "type":"Services"
        },
        {
            "category":"Health Services",
            "subcategory":"Hospital",
            "type":"Services"
        }
    ],
    "sg:phone":"+1 360 400 6012",
    "sg:postcode":"60610",
    "sg:province":"IL",
    "sg:tags":[
        "nursing",
        "consultant",
        "medical",
        "practice",
        "home"
    ],
    "wof:name":"Jana Health Care Marketing",
    "wof:placetype":"venue"
},
  "geometry": {"coordinates":[-87.63215,41.906968],"type":"Point"}
}