{
  "type": "Feature",
  "properties": {
    "addr:full":"540 W North Ave Elmhurst IL 60126",
    "addr:housenumber":"540",
    "addr:postcode":"60126",
    "addr:street":"W North Ave",
    "iso:country":"US",
    "sg:address":"540 W North Ave",
    "sg:city":"Elmhurst",
    "sg:classifiers":[
        {
            "category":"Shopping",
            "type":"Retail Goods"
        }
    ],
    "sg:phone":"+1 630 834 2776",
    "sg:postcode":"60126",
    "sg:province":"IL",
    "sg:tags":[
        "telephone",
        "cellular"
    ],
    "sg:website":"www.a1communications.com",
    "wof:name":"Celluar Conection",
    "wof:placetype":"venue"
},
  "geometry": {"coordinates":[-87.961415,41.905726],"type":"Point"}
}