{
  "type": "Feature",
  "properties": {
    "iso:country":"US",
    "sg:address":"6731 Meadow Crest Dr",
    "sg:city":"Downers Grove",
    "sg:classifiers":[
        {
            "category":"Professional",
            "subcategory":"Management & Consulting",
            "type":"Services"
        }
    ],
    "sg:phone":"+1 630 769 0500",
    "sg:postcode":"60516",
    "sg:province":"IL",
    "sg:tags":[
        "business"
    ],
    "wof:name":"Progressive Solutions",
    "wof:placetype":"venue"
},
  "geometry": {"coordinates":[-88.00171,41.764884],"type":"Point"}
}