{
  "type": "Feature",
  "properties": {
    "iso:country":"US",
    "sg:address":"2010 W State St",
    "sg:city":"Rockford",
    "sg:classifiers":[
        {
            "category":"Real Estate",
            "subcategory":"Real Estate Agent",
            "type":"Services"
        }
    ],
    "sg:phone":"+1 815 964 5301",
    "sg:postcode":"61102",
    "sg:province":"IL",
    "wof:name":"A & T Real Estate Investing",
    "wof:placetype":"venue"
},
  "geometry": {"coordinates":[-89.119348,42.276247],"type":"Point"}
}