{
  "type": "Feature",
  "properties": {
    "addr:full":"9304 Keystone Rd Richmond IL 60071",
    "addr:housenumber":"9304",
    "addr:postcode":"60071",
    "addr:street":"Keystone Rd",
    "iso:country":"US",
    "sg:address":"9304 Keystone Rd",
    "sg:city":"Richmond",
    "sg:phone":"+1 815 678 4188",
    "sg:postcode":"60071",
    "sg:province":"IL",
    "sg:tags":[
        "beef",
        "farm",
        "corn",
        "soybean",
        "cattle",
        "feedlot"
    ],
    "wof:name":"Olsen Delmer",
    "wof:placetype":"venue"
},
  "geometry": {"coordinates":[-88.335115,42.465485],"type":"Point"}
}