{
  "type": "Feature",
  "properties": {
    "iso:country":"US",
    "sg:address":"920 Fairway Park Dr",
    "sg:city":"Madison",
    "sg:classifiers":[
        {
            "category":"Wholesale",
            "subcategory":"Farm Supplies",
            "type":"Manufacturing & Wholesale Goods"
        },
        {
            "category":"Wholesale",
            "subcategory":"Medical Equipment & Supplies",
            "type":"Manufacturing & Wholesale Goods"
        },
        {
            "category":"Farming",
            "subcategory":"Poultry Farm",
            "type":"Manufacturing & Wholesale Goods"
        },
        {
            "category":"Shopping",
            "subcategory":"Pets & Pet Supplies",
            "type":"Retail Goods"
        }
    ],
    "sg:phone":"+1 618 274 6007",
    "sg:postcode":"62060",
    "sg:province":"IL",
    "sg:tags":[
        "feed",
        "feed-wholesale",
        "livestock",
        "supplement",
        "concentrate",
        "manufacturer"
    ],
    "wof:name":"Feed Products South Inc",
    "wof:placetype":"venue"
},
  "geometry": {"coordinates":[-90.153933,38.658403],"type":"Point"}
}