{
  "type": "Feature",
  "properties": {
    "iso:country":"US",
    "sg:address":"550 N Commons Dr Suite 100",
    "sg:city":"Aurora",
    "sg:classifiers":[
        {
            "category":"Manufacturing",
            "subcategory":"Chemicals & Compounds",
            "type":"Manufacturing & Wholesale Goods"
        },
        {
            "category":"Professional",
            "subcategory":"Business Services",
            "type":"Services"
        },
        {
            "category":"Building & Trades",
            "subcategory":"Pest Control",
            "type":"Services"
        }
    ],
    "sg:phone":"+1 630 870 1940",
    "sg:postcode":"60504",
    "sg:province":"IL",
    "sg:tags":[
        "industrial",
        "supply",
        "services-commercial",
        "termite",
        "bee",
        "equipment",
        "repellent",
        "mothproofing",
        "barriers",
        "removal",
        "inspection",
        "bird"
    ],
    "wof:name":"Terminix",
    "wof:placetype":"venue"
},
  "geometry": {"coordinates":[-88.220161,41.766151],"type":"Point"}
}