{
  "type": "Feature",
  "properties": {
    "addr:full":"17525 Depot St Union IL 60180",
    "addr:housenumber":"17525",
    "addr:postcode":"60180",
    "addr:street":"Depot St",
    "iso:country":"US",
    "sg:address":"17525 Depot St",
    "sg:city":"Union",
    "sg:classifiers":[
        {
            "category":"Manufacturing",
            "subcategory":"Tools & Machinery",
            "type":"Manufacturing & Wholesale Goods"
        }
    ],
    "sg:phone":"+1 815 923 8604",
    "sg:postcode":"60180",
    "sg:province":"IL",
    "sg:tags":[
        "die",
        "maker"
    ],
    "wof:name":"Wilcox Tool & Engineering",
    "wof:placetype":"venue"
},
  "geometry": {"coordinates":[-88.53925700000001,42.233394],"type":"Point"}
}