{
  "type": "Feature",
  "properties": {
    "addr:full":"1745 E 71st St Chicago IL 60649",
    "addr:housenumber":"1745",
    "addr:postcode":"60649",
    "addr:street":"E 71St St",
    "iso:country":"US",
    "sg:address":"1745 E 71st St",
    "sg:city":"Chicago",
    "sg:classifiers":[
        {
            "category":"Organizations",
            "subcategory":"Membership Organization",
            "type":"Services"
        }
    ],
    "sg:phone":"+1 773 667 1226",
    "sg:postcode":"60649",
    "sg:province":"IL",
    "wof:name":"Gods Clothes Closet",
    "wof:placetype":"venue"
},
  "geometry": {"coordinates":[-87.58233,41.766023],"type":"Point"}
}