{
  "type": "Feature",
  "properties": {
    "addr:full":"6197 Leo Dr Belleville IL 62223",
    "addr:housenumber":"6197",
    "addr:postcode":"62223",
    "addr:street":"Leo Dr",
    "iso:country":"US",
    "sg:address":"6197 Leo Dr",
    "sg:city":"Belleville",
    "sg:classifiers":[
        {
            "category":"Shopping",
            "type":"Retail Goods"
        }
    ],
    "sg:phone":"+1 618 398 3474",
    "sg:postcode":"62223",
    "sg:province":"IL",
    "sg:tags":[
        "pet",
        "shop"
    ],
    "wof:name":"Aqua Interiors",
    "wof:placetype":"venue"
},
  "geometry": {"coordinates":[-90.039103,38.537448],"type":"Point"}
}