{
  "type": "Feature",
  "properties": {
    "iso:country":"US",
    "sg:address":"2777 N Milwaukee Ave",
    "sg:city":"Chicago",
    "sg:classifiers":[
        {
            "category":"Shopping",
            "subcategory":"Shoes",
            "type":"Retail Goods"
        }
    ],
    "sg:phone":"+1   ",
    "sg:postcode":"60647",
    "sg:province":"IL",
    "sg:tags":[
        "shoe",
        "store"
    ],
    "wof:name":"Young Shoes Inc",
    "wof:placetype":"venue"
},
  "geometry": {"coordinates":[-87.711213,41.931436],"type":"Point"}
}