{
  "type": "Feature",
  "properties": {
    "iso:country":"US",
    "sg:address":"13800 134th Ave W",
    "sg:city":"Taylor Ridge",
    "sg:classifiers":[
        {
            "category":"Government",
            "subcategory":"Fire Station",
            "type":"Public Place"
        }
    ],
    "sg:phone":"+1 309 795 1111",
    "sg:postcode":"61284",
    "sg:province":"IL",
    "sg:tags":[
        "department"
    ],
    "wof:name":"Edgington Fire Protection Dist",
    "wof:placetype":"venue"
},
  "geometry": {"coordinates":[-90.744712,41.386843],"type":"Point"}
}