{
  "type": "Feature",
  "properties": {
    "addr:full":"6610 Albany Rd Erie IL 61250",
    "addr:housenumber":"6610",
    "addr:postcode":"61250",
    "addr:street":"Albany Rd",
    "iso:country":"US",
    "sg:address":"6610 Albany Rd",
    "sg:city":"Erie",
    "sg:classifiers":[
        {
            "category":"Retail",
            "subcategory":"Repair Shop",
            "type":"Services"
        }
    ],
    "sg:phone":"+1 309 659 7917",
    "sg:postcode":"61250",
    "sg:province":"IL",
    "wof:name":"Wheeler Repair Inc",
    "wof:placetype":"venue"
},
  "geometry": {"coordinates":[-90.089617,41.679955],"type":"Point"}
}