{
  "type": "Feature",
  "properties": {
    "iso:country":"US",
    "sg:address":"721 Beacon St",
    "sg:city":"Loves Park",
    "sg:classifiers":[
        {
            "category":"Manufacturing",
            "subcategory":"Metals",
            "type":"Manufacturing & Wholesale Goods"
        }
    ],
    "sg:phone":"+1 815 877 7436",
    "sg:postcode":"61111",
    "sg:province":"IL",
    "sg:tags":[
        "treating",
        "heat",
        "commercial"
    ],
    "wof:name":"Eklund Metal Treating Inc",
    "wof:placetype":"venue"
},
  "geometry": {"coordinates":[-89.053734,42.302808],"type":"Point"}
}