{
  "type": "Feature",
  "properties": {
    "addr:full":"409 Beaver Ct Oswego IL 60543",
    "addr:housenumber":"409",
    "addr:postcode":"60543",
    "addr:street":"Beaver Ct",
    "iso:country":"US",
    "sg:address":"409 Beaver Ct",
    "sg:city":"Oswego",
    "sg:classifiers":[
        {
            "category":"Social Services",
            "subcategory":"Job Training",
            "type":"Services"
        }
    ],
    "sg:phone":"+1 630 554 0298",
    "sg:postcode":"60543",
    "sg:province":"IL",
    "sg:tags":[
        "technician",
        "assistant",
        "school",
        "dental",
        "medical"
    ],
    "wof:name":"L A Enterprises Us Inc",
    "wof:placetype":"venue"
},
  "geometry": {"coordinates":[-88.364288,41.693989],"type":"Point"}
}