{
  "type": "Feature",
  "properties": {
    "iso:country":"US",
    "sg:address":"227 Columbia Ave",
    "sg:city":"Park Ridge",
    "sg:classifiers":[
        {
            "category":"Building & Trades",
            "subcategory":"Electrical",
            "type":"Services"
        }
    ],
    "sg:phone":"+1 847 823 3003",
    "sg:postcode":"60068",
    "sg:province":"IL",
    "sg:tags":[
        "electrician"
    ],
    "wof:name":"Source Technologies",
    "wof:placetype":"venue"
},
  "geometry": {"coordinates":[-87.825203,42.002899],"type":"Point"}
}