{
  "type": "Feature",
  "properties": {
    "iso:country":"US",
    "sg:address":"223 W Main St",
    "sg:city":"Galesburg",
    "sg:classifiers":[
        {
            "category":"Restaurant",
            "type":"Food & Drink"
        }
    ],
    "sg:menulink":"http://www.allmenus.com/il/galesburg-city/226260-caseys-general-store/menu/",
    "sg:phone":"+1 309 344 7224",
    "sg:postcode":"61401",
    "sg:province":"IL",
    "sg:tags":[
        "american",
        "pizza"
    ],
    "wof:name":"Casey's General Store",
    "wof:placetype":"venue"
},
  "geometry": {"coordinates":[-90.37458700000001,40.9475],"type":"Point"}
}