{
  "type": "Feature",
  "properties": {
    "iso:country":"US",
    "sg:address":"10915 Franklin Ave",
    "sg:city":"Franklin Park",
    "sg:classifiers":[
        {
            "category":"Wholesale",
            "subcategory":"Non-durable Goods",
            "type":"Manufacturing & Wholesale Goods"
        }
    ],
    "sg:phone":"+1 847 455 0320",
    "sg:postcode":"60131",
    "sg:province":"IL",
    "wof:name":"Display Factory",
    "wof:placetype":"venue"
},
  "geometry": {"coordinates":[-87.902235,41.944096],"type":"Point"}
}