{
  "type": "Feature",
  "properties": {
    "addr:full":"1625 E Norris Dr Ottawa IL 61350",
    "addr:housenumber":"1625",
    "addr:postcode":"61350",
    "addr:street":"E Norris Dr",
    "iso:country":"US",
    "sg:address":"1625 E Norris Dr",
    "sg:city":"Ottawa",
    "sg:classifiers":[
        {
            "category":"Restaurant",
            "type":"Food & Drink"
        }
    ],
    "sg:phone":"+1   ",
    "sg:postcode":"61350",
    "sg:province":"IL",
    "sg:tags":[
        "eating"
    ],
    "wof:name":"Two Rivers Grill Rest & Lounge",
    "wof:placetype":"venue"
},
  "geometry": {"coordinates":[-88.814249,41.351074],"type":"Point"}
}