{
  "type": "Feature",
  "properties": {
    "iso:country":"US",
    "sg:address":"8820 Skokie Blvd",
    "sg:city":"Skokie",
    "sg:classifiers":[
        {
            "category":"Banks & Credit Unions",
            "subcategory":"Bank",
            "type":"Services"
        }
    ],
    "sg:phone":"+1 847 983 0200",
    "sg:postcode":"60077",
    "sg:province":"IL",
    "sg:tags":[
        "trade",
        "barter",
        "exchange"
    ],
    "wof:name":"Trimark Trade Advisors",
    "wof:placetype":"venue"
},
  "geometry": {"coordinates":[-87.74706999999999,42.041351],"type":"Point"}
}