{
  "type": "Feature",
  "properties": {
    "iso:country":"US",
    "sg:address":"625 3rd Ave",
    "sg:city":"Rock Island",
    "sg:classifiers":[
        {
            "category":"Freight",
            "type":"Transportation"
        }
    ],
    "sg:phone":"+1 309 794 0723",
    "sg:postcode":"61201",
    "sg:province":"IL",
    "sg:tags":[
        "distance",
        "long",
        "trucking"
    ],
    "wof:name":"Dohrn Transfer Company",
    "wof:placetype":"venue"
},
  "geometry": {"coordinates":[-90.589595,41.506891],"type":"Point"}
}