{
  "type": "Feature",
  "properties": {
    "iso:country":"US",
    "sg:address":"252 Coe Rd",
    "sg:city":"Clarendon Hills",
    "sg:classifiers":[
        {
            "category":"Health Services",
            "subcategory":"Doctor",
            "type":"Services"
        }
    ],
    "sg:phone":"+1 630 655 6332",
    "sg:postcode":"60514",
    "sg:province":"IL",
    "wof:name":"Kurt A Wagner DDS",
    "wof:placetype":"venue"
},
  "geometry": {"coordinates":[-87.948725,41.806827],"type":"Point"}
}