{
  "type": "Feature",
  "properties": {
    "addr:full":"12855 S Cicero Ave Alsip IL 60803",
    "addr:housenumber":"12855",
    "addr:postcode":"60803",
    "addr:street":"S Cicero Ave",
    "iso:country":"US",
    "sg:address":"12855 S Cicero Ave",
    "sg:city":"Alsip",
    "sg:classifiers":[
        {
            "category":"Insurance",
            "subcategory":"Insurance Agent",
            "type":"Services"
        }
    ],
    "sg:phone":"+1 708 272 4500",
    "sg:postcode":"60803",
    "sg:province":"IL",
    "sg:website":"www.emerald-services.com",
    "wof:name":"Emerald Insurance Svc",
    "wof:placetype":"venue"
},
  "geometry": {"coordinates":[-87.738342,41.656773],"type":"Point"}
}