{
  "type": "Feature",
  "properties": {
    "iso:country":"US",
    "sg:address":"3435 W Scioto Mills Rd",
    "sg:city":"Freeport",
    "sg:classifiers":[
        {
            "category":"Farming",
            "subcategory":"Farm",
            "type":"Manufacturing & Wholesale Goods"
        }
    ],
    "sg:phone":"+1 815 563 4898",
    "sg:postcode":"61032",
    "sg:province":"IL",
    "sg:tags":[
        "crop",
        "general"
    ],
    "wof:name":"Wendell Devries",
    "wof:placetype":"venue"
},
  "geometry": {"coordinates":[-89.68038,42.358739],"type":"Point"}
}