{
  "type": "Feature",
  "properties": {
    "iso:country":"US",
    "sg:address":"105 E Main St",
    "sg:city":"Morrison",
    "sg:classifiers":[
        {
            "category":"Professional",
            "subcategory":"Lawyer & Legal Services",
            "type":"Services"
        }
    ],
    "sg:phone":"+1 815 772 2164",
    "sg:postcode":"61270",
    "sg:province":"IL",
    "wof:name":"Russell J Holesinger Atty",
    "wof:placetype":"venue"
},
  "geometry": {"coordinates":[-89.9667,41.809179],"type":"Point"}
}