{
  "type": "Feature",
  "properties": {
    "addr:full":"4290 Old Hwy 51 N Cobden IL 62920",
    "addr:housenumber":"4290",
    "addr:postcode":"62920",
    "addr:street":"Old Hwy 51 N",
    "iso:country":"US",
    "sg:address":"4290 Old Hwy 51 N",
    "sg:city":"Cobden",
    "sg:classifiers":[
        {
            "category":"Organizations",
            "subcategory":"Religious Organization",
            "type":"Services"
        }
    ],
    "sg:phone":"+1 618 893 4916",
    "sg:postcode":"62920",
    "sg:province":"IL",
    "sg:tags":[
        "church"
    ],
    "wof:name":"Immanuel Baptist Church",
    "wof:placetype":"venue"
},
  "geometry": {"coordinates":[-89.258241,37.516188],"type":"Point"}
}