{
  "type": "Feature",
  "properties": {
    "addr:full":"7784 S Cicero Ave Burbank IL 60459",
    "addr:housenumber":"7784",
    "addr:postcode":"60459",
    "addr:street":"S Cicero Ave",
    "iso:country":"US",
    "sg:address":"7784 S Cicero Ave",
    "sg:city":"Burbank",
    "sg:classifiers":[
        {
            "category":"Cinema",
            "subcategory":"Movie Rental",
            "type":"Entertainment"
        }
    ],
    "sg:phone":"+1 708 423 7529",
    "sg:postcode":"60459",
    "sg:province":"IL",
    "sg:tags":[
        "game",
        "video"
    ],
    "wof:name":"Play N Trade",
    "wof:placetype":"venue"
},
  "geometry": {"coordinates":[-87.741704,41.751302],"type":"Point"}
}