{
  "type": "Feature",
  "properties": {
    "addr:full":"11 N 21st St Belleville IL 62226",
    "addr:housenumber":"11",
    "addr:postcode":"62226",
    "addr:street":"N 21St St",
    "iso:country":"US",
    "sg:address":"11 N 21st St",
    "sg:city":"Belleville",
    "sg:classifiers":[
        {
            "category":"Personal",
            "subcategory":"Beauty Salon",
            "type":"Services"
        }
    ],
    "sg:phone":"+1 618 234 8900",
    "sg:postcode":"62226",
    "sg:province":"IL",
    "sg:tags":[
        "shop"
    ],
    "wof:name":"Anthony's Hair Designs",
    "wof:placetype":"venue"
},
  "geometry": {"coordinates":[-90.007079,38.520858],"type":"Point"}
}