{
  "type": "Feature",
  "properties": {
    "addr:full":"9691 N County Highway 2 Ipava IL 61441",
    "addr:housenumber":"9691",
    "addr:postcode":"61441",
    "addr:street":"N County Highway 2 Ipava",
    "iso:country":"US",
    "sg:address":"9691 N County Highway 2",
    "sg:city":"Ipava",
    "sg:classifiers":[
        {
            "category":"Farming",
            "subcategory":"Livestock Farm",
            "type":"Manufacturing & Wholesale Goods"
        },
        {
            "category":"Farming",
            "subcategory":"Farm",
            "type":"Manufacturing & Wholesale Goods"
        }
    ],
    "sg:phone":"+1 309 753 8415",
    "sg:postcode":"61441",
    "sg:province":"IL",
    "sg:tags":[
        "feeding"
    ],
    "wof:name":"Harold Palm",
    "wof:placetype":"venue"
},
  "geometry": {"coordinates":[-90.31566599999999,40.318885],"type":"Point"}
}