{
  "type": "Feature",
  "properties": {
    "iso:country":"US",
    "sg:address":"127 Main St",
    "sg:city":"Carthage",
    "sg:classifiers":[
        {
            "category":"Banks & Credit Unions",
            "subcategory":"Investment Brokerage",
            "type":"Services"
        }
    ],
    "sg:phone":"+1 217 357 9311",
    "sg:postcode":"62321",
    "sg:province":"IL",
    "sg:tags":[
        "security",
        "management",
        "consulting"
    ],
    "wof:name":"Taask Financial Advisors",
    "wof:placetype":"venue"
},
  "geometry": {"coordinates":[-91.143074,40.413824],"type":"Point"}
}