{
  "type": "Feature",
  "properties": {
    "iso:country":"US",
    "sg:address":"3515 Court St",
    "sg:city":"Pekin",
    "sg:classifiers":[
        {
            "category":"Mining & Drilling",
            "type":"Manufacturing & Wholesale Goods"
        },
        {
            "category":"Building & Trades",
            "subcategory":"Equipment Rental",
            "type":"Services"
        }
    ],
    "sg:phone":"+1 309 347 6651",
    "sg:postcode":"61554",
    "sg:province":"IL",
    "sg:tags":[
        "gravel",
        "sand",
        "handling",
        "supply"
    ],
    "sg:website":"http://www.cefcu.com",
    "wof:name":"Cefcu",
    "wof:placetype":"venue"
},
  "geometry": {"coordinates":[-89.597981,40.543205],"type":"Point"}
}