{
  "type": "Feature",
  "properties": {
    "iso:country":"US",
    "sg:address":"722 Biermann Ave",
    "sg:city":"Villa Park",
    "sg:classifiers":[
        {
            "category":"Wholesale",
            "subcategory":"Medical Equipment & Supplies",
            "type":"Manufacturing & Wholesale Goods"
        }
    ],
    "sg:phone":"+1 630 279 1677",
    "sg:postcode":"60181",
    "sg:province":"IL",
    "wof:name":"Technologies In Star Mode",
    "wof:placetype":"venue"
},
  "geometry": {"coordinates":[-87.992159,41.904325],"type":"Point"}
}