{
  "type": "Feature",
  "properties": {
    "iso:country":"US",
    "sg:address":"409 S Cicero Avenue",
    "sg:city":"Chicago",
    "sg:classifiers":[
        {
            "category":"Home & Garden",
            "subcategory":"Furniture",
            "type":"Retail Goods"
        }
    ],
    "sg:phone":"+1 773 261 6025",
    "sg:postcode":"60644",
    "sg:province":"IL",
    "sg:tags":[
        "store"
    ],
    "wof:name":"T C Furniture & Appliances",
    "wof:placetype":"venue"
},
  "geometry": {"coordinates":[-87.74475200000001,41.874787],"type":"Point"}
}