{
  "type": "Feature",
  "properties": {
    "addr:full":"1325 Santa Anita Dr Bartlett IL 60133",
    "addr:housenumber":"1325",
    "addr:postcode":"60133",
    "addr:street":"Santa Anita Dr",
    "iso:country":"US",
    "sg:address":"1325 Santa Anita Dr",
    "sg:city":"Bartlett",
    "sg:classifiers":[
        {
            "category":"Retail",
            "subcategory":"Repair Shop",
            "type":"Services"
        }
    ],
    "sg:phone":"+1 630 372 7788",
    "sg:postcode":"60133",
    "sg:province":"IL",
    "wof:name":"Schaumburg Lock & Key",
    "wof:placetype":"venue"
},
  "geometry": {"coordinates":[-88.135323,41.97143],"type":"Point"}
}