{
  "type": "Feature",
  "properties": {
    "addr:full":"910 Touhy Ave Elk Grove Village IL 60007",
    "addr:housenumber":"910",
    "addr:postcode":"60007",
    "addr:street":"Touhy Ave",
    "iso:country":"US",
    "sg:address":"910 Touhy Ave",
    "sg:city":"Elk Grove Village",
    "sg:classifiers":[
        {
            "category":"Building & Trades",
            "subcategory":"Construction",
            "type":"Services"
        }
    ],
    "sg:phone":"+1 847 290 0100",
    "sg:postcode":"60007",
    "sg:province":"IL",
    "sg:tags":[
        "contractor"
    ],
    "wof:name":"Security Board",
    "wof:placetype":"venue"
},
  "geometry": {"coordinates":[-87.971287,42.007676],"type":"Point"}
}