{
  "type": "Feature",
  "properties": {
    "addr:full":"700 Prairie Ave Glen Ellyn IL 60137",
    "addr:housenumber":"700",
    "addr:postcode":"60137",
    "addr:street":"Prairie Ave",
    "iso:country":"US",
    "sg:address":"700 Prairie Ave",
    "sg:city":"Glen Ellyn",
    "sg:classifiers":[
        {
            "category":"Building & Trades",
            "subcategory":"Plumbing",
            "type":"Services"
        }
    ],
    "sg:phone":"+1 630 858 5484",
    "sg:postcode":"60137",
    "sg:province":"IL",
    "sg:tags":[
        "plumbing",
        "contractor"
    ],
    "wof:name":"Indoor Plumbing Inc",
    "wof:placetype":"venue"
},
  "geometry": {"coordinates":[-88.07110299999999,41.886888],"type":"Point"}
}