{
  "type": "Feature",
  "properties": {
    "addr:full":"703 Peoria St Washington IL 61536",
    "addr:housenumber":"703",
    "addr:postcode":"61536",
    "addr:street":"Peoria St",
    "iso:country":"US",
    "sg:address":"703 Peoria St",
    "sg:city":"Washington",
    "sg:classifiers":[
        {
            "category":"Retail",
            "subcategory":"Portrait Studio",
            "type":"Services"
        }
    ],
    "sg:phone":"+1 309 444 7010",
    "sg:postcode":"61536",
    "sg:province":"IL",
    "sg:tags":[
        "photographer"
    ],
    "wof:name":"Photography By Lee",
    "wof:placetype":"venue"
},
  "geometry": {"coordinates":[-89.79569600000001,40.694141],"type":"Point"}
}