{
  "type": "Feature",
  "properties": {
    "addr:full":"1970 W Army Trail Rd Bartlett IL 60133",
    "addr:housenumber":"1970",
    "addr:postcode":"60133",
    "addr:street":"W Army Trail Rd",
    "iso:country":"US",
    "sg:address":"1970 W Army Trail Rd",
    "sg:city":"Bartlett",
    "sg:classifiers":[
        {
            "category":"Professional",
            "type":"Services"
        }
    ],
    "sg:phone":"+1 630 540 0699",
    "sg:postcode":"60133",
    "sg:province":"IL",
    "wof:name":"T A C B Inc",
    "wof:placetype":"venue"
},
  "geometry": {"coordinates":[-88.15209299999999,41.940657],"type":"Point"}
}