{
  "type": "Feature",
  "properties": {
    "addr:full":"6737 West Forest Preserve Dr Chicago IL 60634",
    "addr:housenumber":"6737",
    "addr:postcode":"60634",
    "addr:street":"West Forest Preserve Dr",
    "iso:country":"US",
    "sg:address":"6737 West Forest Preserve Dr",
    "sg:city":"Chicago",
    "sg:classifiers":[
        {
            "category":"Education",
            "subcategory":"School",
            "type":"Public Place"
        },
        {
            "category":"Community Center",
            "type":"Public Place"
        }
    ],
    "sg:phone":"+1 773 286 6226",
    "sg:postcode":"60634",
    "sg:province":"IL",
    "sg:tags":[
        "high",
        "middle",
        "medical",
        "elementary"
    ],
    "sg:website":"www.newhorizoncenter.org",
    "wof:name":"New Horizon Center",
    "wof:placetype":"venue"
},
  "geometry": {"coordinates":[-87.79577,41.959306],"type":"Point"}
}