{
  "type": "Feature",
  "properties": {
    "iso:country":"US",
    "sg:address":"2220 Chadwick Way",
    "sg:city":"Mundelein",
    "sg:classifiers":[
        {
            "category":"Professional",
            "subcategory":"Management & Consulting",
            "type":"Services"
        }
    ],
    "sg:phone":"+1 847 949 9225",
    "sg:postcode":"60060",
    "sg:province":"IL",
    "sg:tags":[
        "marketing"
    ],
    "wof:name":"Dgm Creative Inc",
    "wof:placetype":"venue"
},
  "geometry": {"coordinates":[-88.03273299999999,42.287872],"type":"Point"}
}