{
  "type": "Feature",
  "properties": {
    "iso:country":"US",
    "sg:address":"25324 W Il Route 173",
    "sg:city":"Antioch",
    "sg:classifiers":[
        {
            "category":"Travel",
            "subcategory":"Hotels & Motels",
            "type":"Entertainment"
        }
    ],
    "sg:phone":"+1 847 395 1527",
    "sg:postcode":"60002",
    "sg:province":"IL",
    "wof:name":"Antioch Motel",
    "wof:placetype":"venue"
},
  "geometry": {"coordinates":[-88.1343,42.479401],"type":"Point"}
}