{
  "type": "Feature",
  "properties": {
    "addr:full":"1916 S State Street Chicago IL 60616",
    "addr:housenumber":"1916",
    "addr:postcode":"60616",
    "addr:street":"S State Street",
    "iso:country":"US",
    "sg:address":"1916 S State Street",
    "sg:city":"Chicago",
    "sg:classifiers":[
        {
            "category":"Restaurant",
            "type":"Food & Drink"
        }
    ],
    "sg:phone":"+1 312 808 1914",
    "sg:postcode":"60616",
    "sg:province":"IL",
    "wof:name":"Subway Sandwich",
    "wof:placetype":"venue"
},
  "geometry": {"coordinates":[-87.627329,41.856509],"type":"Point"}
}