{
  "type": "Feature",
  "properties": {
    "addr:full":"1032 Maple Ave Lisle IL 60532",
    "addr:housenumber":"1032",
    "addr:postcode":"60532",
    "addr:street":"Maple Ave",
    "iso:country":"US",
    "sg:address":"1032 Maple Ave",
    "sg:city":"Lisle",
    "sg:classifiers":[
        {
            "category":"Restaurant",
            "type":"Food & Drink"
        }
    ],
    "sg:phone":"+1 630 769 1311",
    "sg:postcode":"60532",
    "sg:province":"IL",
    "wof:name":"Bountiful Market & Cafe",
    "wof:placetype":"venue"
},
  "geometry": {"coordinates":[-88.071901,41.786606],"type":"Point"}
}