{
  "type": "Feature",
  "properties": {
    "iso:country":"US",
    "sg:address":"5840 N Spaulding Ave",
    "sg:city":"Chicago",
    "sg:classifiers":[
        {
            "category":"Retail",
            "subcategory":"Laundry & Dry Cleaning",
            "type":"Services"
        },
        {
            "category":"Building & Trades",
            "subcategory":"Cleaning & Sanitation",
            "type":"Services"
        }
    ],
    "sg:phone":"+1 773 539 3541",
    "sg:postcode":"60659",
    "sg:province":"IL",
    "sg:tags":[
        "cleaner",
        "house"
    ],
    "wof:name":"Team Clean Up Co",
    "wof:placetype":"venue"
},
  "geometry": {"coordinates":[-87.711446,41.987403],"type":"Point"}
}