{
  "type": "Feature",
  "properties": {
    "iso:country":"US",
    "sg:address":"2121 Dewey Avenue Unit B",
    "sg:city":"Evanston",
    "sg:classifiers":[
        {
            "category":"Professional",
            "subcategory":"Advertising",
            "type":"Services"
        }
    ],
    "sg:postcode":"60201",
    "sg:province":"IL",
    "sg:tags":[
        "advertising",
        "marketing",
        "customer-acquisition"
    ],
    "sg:website":"http://www.flypapermediaholdings.com",
    "wof:name":"Flypaper Media Holdings",
    "wof:placetype":"venue"
},
  "geometry": {"coordinates":[-87.69565299999999,42.056257],"type":"Point"}
}