{
  "type": "Feature",
  "properties": {
    "iso:country":"US",
    "sg:address":"4500 N Ravenswood Ave",
    "sg:city":"Chicago",
    "sg:classifiers":[
        {
            "category":"Professional",
            "subcategory":"Printing & Photocopies",
            "type":"Services"
        },
        {
            "category":"Shopping",
            "subcategory":"Computers & Home Electronics",
            "type":"Retail Goods"
        }
    ],
    "sg:phone":"+1 773 878 6800",
    "sg:postcode":"60640",
    "sg:province":"IL",
    "sg:tags":[
        "plate",
        "name",
        "trophies",
        "medal",
        "plaque"
    ],
    "sg:website":"http://www.gabelandschubert.com",
    "wof:name":"Gabel & Schubert Bronze",
    "wof:placetype":"venue"
},
  "geometry": {"coordinates":[-87.67456799999999,41.963322],"type":"Point"}
}