{
  "type": "Feature",
  "properties": {
    "iso:country":"US",
    "sg:address":"350 N 15th St",
    "sg:city":"Rochelle",
    "sg:classifiers":[
        {
            "category":"Manufacturing",
            "subcategory":"Food",
            "type":"Manufacturing & Wholesale Goods"
        }
    ],
    "sg:phone":"+1 815 562 1243",
    "sg:postcode":"61068",
    "sg:province":"IL",
    "sg:tags":[
        "product",
        "manufacturer"
    ],
    "wof:name":"Del Monte Foods",
    "wof:placetype":"venue"
},
  "geometry": {"coordinates":[-89.07850000000001,41.922111],"type":"Point"}
}