{
  "type": "Feature",
  "properties": {
    "addr:full":"1713 88th Ave W Rock Island IL 61201",
    "addr:housenumber":"1713",
    "addr:postcode":"61201",
    "addr:street":"88Th Ave W",
    "iso:country":"US",
    "sg:address":"1713 88th Ave W",
    "sg:city":"Rock Island",
    "sg:classifiers":[
        {
            "category":"Real Estate",
            "subcategory":"Real Estate Operator",
            "type":"Services"
        }
    ],
    "sg:phone":"+1 309 787 2408",
    "sg:postcode":"61201",
    "sg:province":"IL",
    "sg:tags":[
        "property",
        "lessor"
    ],
    "wof:name":"George Kieffer",
    "wof:placetype":"venue"
},
  "geometry": {"coordinates":[-90.591549,41.432046],"type":"Point"}
}