{
  "type": "Feature",
  "properties": {
    "iso:country":"US",
    "sg:address":"24380 N Sunset Ave",
    "sg:city":"Cary",
    "sg:classifiers":[
        {
            "category":"Professional",
            "subcategory":"Engineering",
            "type":"Services"
        },
        {
            "category":"Wholesale",
            "subcategory":"Chemicals & Plastics",
            "type":"Manufacturing & Wholesale Goods"
        }
    ],
    "sg:phone":"+1 847 516 6427",
    "sg:postcode":"60013",
    "sg:province":"IL",
    "sg:tags":[
        "engineer"
    ],
    "wof:name":"J Sinclair & Associates Inc",
    "wof:placetype":"venue"
},
  "geometry": {"coordinates":[-88.19270299999999,42.218541],"type":"Point"}
}