{
  "type": "Feature",
  "properties": {
    "iso:country":"US",
    "sg:address":"6014 W Diversey Ave",
    "sg:city":"Chicago",
    "sg:classifiers":[
        {
            "category":"Building & Trades",
            "subcategory":"Construction",
            "type":"Services"
        }
    ],
    "sg:phone":"+1 773 237 7730",
    "sg:postcode":"60639",
    "sg:province":"IL",
    "sg:tags":[
        "contractor"
    ],
    "sg:website":"www.blueskyroofinginc.com",
    "wof:name":"Blue Sky Roofing, Inc.",
    "wof:placetype":"venue"
},
  "geometry": {"coordinates":[-87.776545,41.931051],"type":"Point"}
}