{
  "type": "Feature",
  "properties": {
    "addr:full":"1340 Dekalb Ave Sycamore IL 60178",
    "addr:housenumber":"1340",
    "addr:postcode":"60178",
    "addr:street":"Dekalb Ave",
    "iso:country":"US",
    "sg:address":"1340 Dekalb Ave",
    "sg:city":"Sycamore",
    "sg:classifiers":[
        {
            "category":"Wholesale",
            "subcategory":"Medical Equipment & Supplies",
            "type":"Manufacturing & Wholesale Goods"
        },
        {
            "category":"Shopping",
            "subcategory":"Beauty & Cosmetics",
            "type":"Retail Goods"
        },
        {
            "category":"Food & Beverages",
            "subcategory":"Specialty",
            "type":"Retail Goods"
        },
        {
            "category":"Shopping",
            "subcategory":"Computers & Home Electronics",
            "type":"Retail Goods"
        },
        {
            "category":"Shopping",
            "subcategory":"Optical Goods",
            "type":"Retail Goods"
        },
        {
            "category":"Personal",
            "subcategory":"Skin Care",
            "type":"Services"
        },
        {
            "category":"Manufacturing",
            "subcategory":"Chemicals & Compounds",
            "type":"Manufacturing & Wholesale Goods"
        },
        {
            "category":"Retail",
            "subcategory":"Photofinishing",
            "type":"Services"
        },
        {
            "category":"Shopping",
            "subcategory":"Pharmacy",
            "type":"Retail Goods"
        },
        {
            "category":"Health Services",
            "subcategory":"Optometrist",
            "type":"Services"
        },
        {
            "category":"Food & Beverages",
            "subcategory":"Groceries & Convenience Stores",
            "type":"Retail Goods"
        }
    ],
    "sg:phone":"+1 815 895 4609",
    "sg:postcode":"60178",
    "sg:province":"IL",
    "sg:tags":[
        "pharmaceutical",
        "product",
        "photo",
        "wheelchair",
        "vitamin",
        "perfume",
        "lens",
        "supplement",
        "contact",
        "wellness",
        "finishing",
        "consumer"
    ],
    "sg:website":"http://www.walgreens.com/default.jsp?ec=iyp_yellowpages_trademark",
    "wof:name":"Walgreens Pharmacies",
    "wof:placetype":"venue"
},
  "geometry": {"coordinates":[-88.708493,41.980451],"type":"Point"}
}