{
  "type": "Feature",
  "properties": {
    "iso:country":"US",
    "sg:address":"116 W Main St",
    "sg:city":"Atkinson",
    "sg:classifiers":[
        {
            "category":"Professional",
            "subcategory":"Business Services",
            "type":"Services"
        }
    ],
    "sg:phone":"+1 309 936 7688",
    "sg:postcode":"61235",
    "sg:province":"IL",
    "wof:name":"Quad City Skydiving Ctr Inc",
    "wof:placetype":"venue"
},
  "geometry": {"coordinates":[-90.01685000000001,41.421409],"type":"Point"}
}