{
  "type": "Feature",
  "properties": {
    "addr:full":"6220 N Olcott Avenue Chicago IL 60631",
    "addr:housenumber":"6220",
    "addr:postcode":"60631",
    "addr:street":"N Olcott Avenue",
    "iso:country":"US",
    "sg:address":"6220 N Olcott Avenue",
    "sg:city":"Chicago",
    "sg:classifiers":[
        {
            "category":"Education",
            "subcategory":"School",
            "type":"Public Place"
        }
    ],
    "sg:phone":"+1 773 534 1209",
    "sg:postcode":"60631",
    "sg:province":"IL",
    "sg:tags":[
        "high",
        "middle",
        "elementary"
    ],
    "wof:name":"Schools Public",
    "wof:placetype":"venue"
},
  "geometry": {"coordinates":[-87.813418,41.994512],"type":"Point"}
}