{
  "type": "Feature",
  "properties": {
    "iso:country":"US",
    "sg:address":"403 S Mulford Rd",
    "sg:city":"Rockford",
    "sg:classifiers":[
        {
            "category":"Freight",
            "type":"Transportation"
        }
    ],
    "sg:phone":"+1 815 633 3333",
    "sg:postcode":"61108",
    "sg:province":"IL",
    "sg:tags":[
        "warehouse"
    ],
    "wof:name":"Littlfeld Ralph Whl Siding Inc",
    "wof:placetype":"venue"
},
  "geometry": {"coordinates":[-88.999745,42.263625],"type":"Point"}
}