{
  "type": "Feature",
  "properties": {
    "iso:country":"US",
    "sg:address":"1480 W Webster Ave",
    "sg:city":"Chicago",
    "sg:classifiers":[
        {
            "category":"Bars & Pubs",
            "subcategory":"Wine Bar",
            "type":"Food & Drink"
        }
    ],
    "sg:phone":"+1 773 868 0608",
    "sg:postcode":"60614",
    "sg:province":"IL",
    "sg:website":"www.websterwinebar.com/",
    "wof:name":"Webster's Wine Bar",
    "wof:placetype":"venue"
},
  "geometry": {"coordinates":[-87.66570299999999,41.9216],"type":"Point"}
}