{
  "type": "Feature",
  "properties": {
    "iso:country":"US",
    "sg:address":"941 Superior St",
    "sg:city":"Bradley",
    "sg:classifiers":[
        {
            "category":"Retail",
            "subcategory":"Repair Shop",
            "type":"Services"
        }
    ],
    "sg:phone":"+1 815 935 2060",
    "sg:postcode":"60915",
    "sg:province":"IL",
    "sg:tags":[
        "upholsterer"
    ],
    "wof:name":"Upholstery By Coy",
    "wof:placetype":"venue"
},
  "geometry": {"coordinates":[-87.874954,41.139658],"type":"Point"}
}