{
  "type": "Feature",
  "properties": {
    "addr:full":"225 N Michigan Ave # 2304 Chicago IL 60601",
    "addr:housenumber":"225",
    "addr:postcode":"60601",
    "addr:street":"N Michigan Ave # 2304",
    "iso:country":"US",
    "sg:address":"225 N Michigan Ave # 2304",
    "sg:city":"Chicago",
    "sg:classifiers":[
        {
            "category":"Airline",
            "type":"Transportation"
        }
    ],
    "sg:phone":"+1 312 819 2350",
    "sg:postcode":"60601",
    "sg:province":"IL",
    "wof:name":"Aeroflot Russian Airlines",
    "wof:placetype":"venue"
},
  "geometry": {"coordinates":[-87.624439,41.886003],"type":"Point"}
}