{
  "type": "Feature",
  "properties": {
    "iso:country":"US",
    "sg:address":"1524 N Milwaukee Ave",
    "sg:city":"Chicago",
    "sg:classifiers":[
        {
            "category":"Shopping",
            "subcategory":"Gifts & Souvenirs",
            "type":"Retail Goods"
        }
    ],
    "sg:phone":"+1 773 486 5894",
    "sg:postcode":"60622",
    "sg:province":"IL",
    "sg:tags":[
        "flower"
    ],
    "wof:name":"Botanica Brisas de Michoacan",
    "wof:placetype":"venue"
},
  "geometry": {"coordinates":[-87.67591400000001,41.909388],"type":"Point"}
}