{
  "type": "Feature",
  "properties": {
    "iso:country":"US",
    "sg:address":"600 Union St",
    "sg:city":"Crescent City",
    "sg:classifiers":[
        {
            "category":"Organizations",
            "subcategory":"Religious Organization",
            "type":"Services"
        }
    ],
    "sg:phone":"+1 815 683 2176",
    "sg:postcode":"60928",
    "sg:province":"IL",
    "sg:tags":[
        "church"
    ],
    "wof:name":"Cresent City United Methodist",
    "wof:placetype":"venue"
},
  "geometry": {"coordinates":[-87.85542599999999,40.769095],"type":"Point"}
}