{
  "type": "Feature",
  "properties": {
    "addr:full":"998 Victoria St Antioch IL 60002",
    "addr:housenumber":"998",
    "addr:postcode":"60002",
    "addr:street":"Victoria St",
    "iso:country":"US",
    "sg:address":"998 Victoria St",
    "sg:city":"Antioch",
    "sg:classifiers":[
        {
            "category":"Shopping",
            "subcategory":"Hobbies, Toys, & Games",
            "type":"Retail Goods"
        }
    ],
    "sg:phone":"+1 847 395 2594",
    "sg:postcode":"60002",
    "sg:province":"IL",
    "sg:tags":[
        "mfg"
    ],
    "wof:name":"L&H Deco Art Inc",
    "wof:placetype":"venue"
},
  "geometry": {"coordinates":[-88.09685,42.473821],"type":"Point"}
}