{
  "type": "Feature",
  "properties": {
    "addr:full":"305 W Saint Charles Rd Villa Park IL 60181",
    "addr:housenumber":"305",
    "addr:postcode":"60181",
    "addr:street":"W Saint Charles Rd",
    "iso:country":"US",
    "sg:address":"305 W Saint Charles Rd",
    "sg:city":"Villa Park",
    "sg:classifiers":[
        {
            "category":"Banks & Credit Unions",
            "subcategory":"Financial Services",
            "type":"Services"
        }
    ],
    "sg:phone":"+1 630 530 5000",
    "sg:postcode":"60181",
    "sg:province":"IL",
    "sg:tags":[
        "company",
        "holding"
    ],
    "wof:name":"Amerimark Financial Corp",
    "wof:placetype":"venue"
},
  "geometry": {"coordinates":[-87.986294,41.889684],"type":"Point"}
}