{
  "type": "Feature",
  "properties": {
    "iso:country":"US",
    "sg:address":"6157 N Broadway St",
    "sg:city":"Chicago",
    "sg:classifiers":[
        {
            "category":"Communications",
            "type":"Services"
        }
    ],
    "sg:phone":"+1 773 262 1305",
    "sg:postcode":"60660",
    "sg:province":"IL",
    "sg:tags":[
        "equipment",
        "satellite",
        "system"
    ],
    "wof:name":"Starcast Network",
    "wof:placetype":"venue"
},
  "geometry": {"coordinates":[-87.660386,41.993884],"type":"Point"}
}