{
  "type": "Feature",
  "properties": {
    "iso:country":"US",
    "sg:address":"229 Main St",
    "sg:city":"Savanna",
    "sg:classifiers":[
        {
            "category":"Banks & Credit Unions",
            "subcategory":"Bank",
            "type":"Services"
        }
    ],
    "sg:phone":"+1 815 273 2228",
    "sg:postcode":"61074",
    "sg:province":"IL",
    "sg:tags":[
        "saving",
        "commercial"
    ],
    "sg:website":"http://www.thenb.com",
    "wof:name":"Branch 1",
    "wof:placetype":"venue"
},
  "geometry": {"coordinates":[-90.15597,42.092616],"type":"Point"}
}