{
  "type": "Feature",
  "properties": {
    "iso:country":"US",
    "sg:address":"2420 Young St",
    "sg:city":"Nauvoo",
    "sg:classifiers":[
        {
            "category":"Professional",
            "subcategory":"Accounting & Tax Preparation",
            "type":"Services"
        }
    ],
    "sg:phone":"+1 217 453 2788",
    "sg:postcode":"62354",
    "sg:province":"IL",
    "sg:tags":[
        "accountant"
    ],
    "wof:name":"Martin Accounting & Tax Svc",
    "wof:placetype":"venue"
},
  "geometry": {"coordinates":[-91.36547899999999,40.551703],"type":"Point"}
}