{
  "type": "Feature",
  "properties": {
    "iso:country":"US",
    "sg:address":"120 Cunat Blvd",
    "sg:city":"Richmond",
    "sg:classifiers":[
        {
            "category":"Arts & Performance",
            "subcategory":"Dance",
            "type":"Entertainment"
        }
    ],
    "sg:phone":"+1 815 347 0555",
    "sg:postcode":"60071",
    "sg:province":"IL",
    "sg:tags":[
        "instruction",
        "dancing"
    ],
    "wof:name":"Full Spin Productions Nfp",
    "wof:placetype":"venue"
},
  "geometry": {"coordinates":[-88.296019,42.449442],"type":"Point"}
}