{
  "type": "Feature",
  "properties": {
    "iso:country":"US",
    "sg:address":"1111 W Addison St",
    "sg:city":"Chicago",
    "sg:classifiers":[
        {
            "category":"Fast Food",
            "type":"Food & Drink"
        },
        {
            "category":"Restaurant",
            "type":"Food & Drink"
        }
    ],
    "sg:phone":"+1 773 281 4937",
    "sg:postcode":"60613",
    "sg:province":"IL",
    "sg:tags":[
        "mexican"
    ],
    "sg:website":"www.tacobell.com",
    "wof:name":"Taco Bell",
    "wof:placetype":"venue"
},
  "geometry": {"coordinates":[-87.657799,41.947102],"type":"Point"}
}