{
  "type": "Feature",
  "properties": {
    "iso:country":"US",
    "sg:address":"2001 W 47th St",
    "sg:city":"Chicago",
    "sg:classifiers":[
        {
            "category":"Banks & Credit Unions",
            "subcategory":"Financial Services",
            "type":"Services"
        }
    ],
    "sg:phone":"+1 773 247 5261",
    "sg:postcode":"60609",
    "sg:province":"IL",
    "sg:tags":[
        "cashing",
        "check"
    ],
    "wof:name":"PLS Check Cashers",
    "wof:placetype":"venue"
},
  "geometry": {"coordinates":[-87.67481600000001,41.808529],"type":"Point"}
}