{
  "type": "Feature",
  "properties": {
    "addr:full":"7020 W North Ave Chicago IL 60707",
    "addr:housenumber":"7020",
    "addr:postcode":"60707",
    "addr:street":"W North Ave",
    "iso:country":"US",
    "sg:address":"7020 W North Ave",
    "sg:city":"Chicago",
    "sg:classifiers":[
        {
            "category":"Health Services",
            "subcategory":"Dentist",
            "type":"Services"
        }
    ],
    "sg:phone":"+1 708 386 6517",
    "sg:postcode":"60707",
    "sg:province":"IL",
    "sg:tags":[
        "dentists-cosmetic",
        "dentistry"
    ],
    "sg:website":"www.youroakparkdentist.com",
    "wof:name":"Jeffrey R Blankshain DDS",
    "wof:placetype":"venue"
},
  "geometry": {"coordinates":[-87.800927,41.909034],"type":"Point"}
}