{
  "type": "Feature",
  "properties": {
    "addr:full":"479 Ela Rd Lake Zurich IL 60047",
    "addr:housenumber":"479",
    "addr:postcode":"60047",
    "addr:street":"Ela Rd",
    "iso:country":"US",
    "sg:address":"479 Ela Rd",
    "sg:city":"Lake Zurich",
    "sg:classifiers":[
        {
            "category":"Shopping",
            "subcategory":"Gifts & Souvenirs",
            "type":"Retail Goods"
        }
    ],
    "sg:phone":"+1   ",
    "sg:postcode":"60047",
    "sg:province":"IL",
    "wof:name":"Pat Schweda",
    "wof:placetype":"venue"
},
  "geometry": {"coordinates":[-88.101721,42.185456],"type":"Point"}
}