{
  "type": "Feature",
  "properties": {
    "addr:full":"413 W Walnut St Chillicothe IL 61523",
    "addr:housenumber":"413",
    "addr:postcode":"61523",
    "addr:street":"W Walnut St",
    "iso:country":"US",
    "sg:address":"413 W Walnut St",
    "sg:city":"Chillicothe",
    "sg:classifiers":[
        {
            "category":"Autos & Motor Vehicles",
            "subcategory":"Automobile Sales",
            "type":"Retail Goods"
        }
    ],
    "sg:phone":"+1 309 274 3976",
    "sg:postcode":"61523",
    "sg:province":"IL",
    "sg:tags":[
        "car",
        "dealer"
    ],
    "wof:name":"Childers Auto Sales",
    "wof:placetype":"venue"
},
  "geometry": {"coordinates":[-89.489754,40.917187],"type":"Point"}
}