{
  "type": "Feature",
  "properties": {
    "addr:full":"1725 Ridge Ave Rockford IL 61103",
    "addr:housenumber":"1725",
    "addr:postcode":"61103",
    "addr:street":"Ridge Ave",
    "iso:country":"US",
    "sg:address":"1725 Ridge Ave",
    "sg:city":"Rockford",
    "sg:classifiers":[
        {
            "category":"Manufacturing",
            "subcategory":"Motor Vehicles & Parts",
            "type":"Manufacturing & Wholesale Goods"
        }
    ],
    "sg:phone":"+1 815 963 1315",
    "sg:postcode":"61103",
    "sg:province":"IL",
    "sg:tags":[
        "mfg"
    ],
    "wof:name":"T & B Leather",
    "wof:placetype":"venue"
},
  "geometry": {"coordinates":[-89.090908,42.291202],"type":"Point"}
}