{
  "type": "Feature",
  "properties": {
    "iso:country":"US",
    "sg:address":"384 E Montrose Ave",
    "sg:city":"Wood Dale",
    "sg:classifiers":[
        {
            "category":"Building & Trades",
            "subcategory":"Cleaning & Sanitation",
            "type":"Services"
        }
    ],
    "sg:phone":"+1 773 742 2943",
    "sg:postcode":"60191",
    "sg:province":"IL",
    "sg:tags":[
        "maintenance"
    ],
    "wof:name":"C & L Building Maintenance",
    "wof:placetype":"venue"
},
  "geometry": {"coordinates":[-87.965224,41.956903],"type":"Point"}
}