{
  "type": "Feature",
  "properties": {
    "iso:country":"US",
    "sg:address":"133 Millis Ln",
    "sg:city":"Schaumburg",
    "sg:classifiers":[
        {
            "category":"Building & Trades",
            "subcategory":"Construction",
            "type":"Services"
        }
    ],
    "sg:phone":"+1 847 301 8110",
    "sg:postcode":"60193",
    "sg:province":"IL",
    "sg:tags":[
        "hanging",
        "contractor"
    ],
    "wof:name":"A Rodriguez Decorating",
    "wof:placetype":"venue"
},
  "geometry": {"coordinates":[-88.13574300000001,42.022947],"type":"Point"}
}