{
  "type": "Feature",
  "properties": {
    "addr:full":"4065 N Milwaukee Ave Chicago IL 60641",
    "addr:housenumber":"4065",
    "addr:postcode":"60641",
    "addr:street":"N Milwaukee Ave",
    "iso:country":"US",
    "sg:address":"4065 N Milwaukee Ave",
    "sg:city":"Chicago",
    "sg:classifiers":[
        {
            "category":"Manufacturing",
            "subcategory":"Apparel",
            "type":"Manufacturing & Wholesale Goods"
        }
    ],
    "sg:phone":"+1 773 905 5081",
    "sg:postcode":"60641",
    "sg:province":"IL",
    "sg:tags":[
        "wig",
        "hair",
        "piece",
        "costume",
        "mfg"
    ],
    "sg:website":"http://www.fantasycostumes.com",
    "wof:name":"Custom & Hard To Find Wigs Ltd",
    "wof:placetype":"venue"
},
  "geometry": {"coordinates":[-87.749289,41.954638],"type":"Point"}
}