{
  "type": "Feature",
  "properties": {
    "addr:full":"5856 N Mobile Ave Chicago IL 60646",
    "addr:housenumber":"5856",
    "addr:postcode":"60646",
    "addr:street":"N Mobile Ave",
    "iso:country":"US",
    "sg:address":"5856 N Mobile Ave",
    "sg:city":"Chicago",
    "sg:classifiers":[
        {
            "category":"Building & Trades",
            "subcategory":"Construction",
            "type":"Services"
        }
    ],
    "sg:phone":"+1 773 775 4256",
    "sg:postcode":"60646",
    "sg:province":"IL",
    "sg:tags":[
        "residential",
        "nonresidential"
    ],
    "wof:name":"Veller Construction",
    "wof:placetype":"venue"
},
  "geometry": {"coordinates":[-87.785298,41.987333],"type":"Point"}
}