{
  "type": "Feature",
  "properties": {
    "addr:full":"308 W Erie St Chicago IL 60654",
    "addr:housenumber":"308",
    "addr:postcode":"60654",
    "addr:street":"W Erie St",
    "iso:country":"US",
    "sg:address":"308 W Erie St",
    "sg:city":"Chicago",
    "sg:classifiers":[
        {
            "category":"Real Estate",
            "subcategory":"Real Estate Services",
            "type":"Services"
        },
        {
            "category":"Banks & Credit Unions",
            "subcategory":"Financial Services",
            "type":"Services"
        }
    ],
    "sg:phone":"+1 312 944 7340",
    "sg:postcode":"60654",
    "sg:province":"IL",
    "sg:tags":[
        "financing",
        "processing",
        "loan"
    ],
    "sg:website":"http://www.theboldtcompany.com",
    "wof:name":"Boldt Consulting Services",
    "wof:placetype":"venue"
},
  "geometry": {"coordinates":[-87.635974,41.893949],"type":"Point"}
}