{
  "type": "Feature",
  "properties": {
    "addr:full":"1803 S Galena Ave Dixon IL 61021",
    "addr:housenumber":"1803",
    "addr:postcode":"61021",
    "addr:street":"S Galena Ave",
    "iso:country":"US",
    "sg:address":"1803 S Galena Ave",
    "sg:city":"Dixon",
    "sg:classifiers":[
        {
            "category":"Restaurant",
            "type":"Food & Drink"
        }
    ],
    "sg:menulink":"http://www.allmenus.com/il/south-dixon/126350-subway/menu/",
    "sg:phone":"+1 815 288 7826",
    "sg:postcode":"61021",
    "sg:province":"IL",
    "sg:tags":[
        "american",
        "sandwich"
    ],
    "wof:name":"Subway",
    "wof:placetype":"venue"
},
  "geometry": {"coordinates":[-89.47439,41.823281],"type":"Point"}
}