{
  "type": "Feature",
  "properties": {
    "addr:full":"226 E 43rd Street Chicago IL 60653",
    "addr:housenumber":"226",
    "addr:postcode":"60653",
    "addr:street":"E 43Rd Street",
    "iso:country":"US",
    "sg:address":"226 E 43rd Street",
    "sg:city":"Chicago",
    "sg:classifiers":[
        {
            "category":"Social Services",
            "subcategory":"Child Care",
            "type":"Services"
        }
    ],
    "sg:phone":"+1 773 624 0061",
    "sg:postcode":"60653",
    "sg:province":"IL",
    "sg:tags":[
        "day"
    ],
    "wof:name":"Centers For New Horizons",
    "wof:placetype":"venue"
},
  "geometry": {"coordinates":[-87.62033099999999,41.81646],"type":"Point"}
}