{
  "type": "Feature",
  "properties": {
    "iso:country":"US",
    "sg:address":"605 E Roosevelt Rd",
    "sg:city":"Wheaton",
    "sg:classifiers":[
        {
            "category":"Social Services",
            "type":"Services"
        }
    ],
    "sg:phone":"+1 630 221 8041",
    "sg:postcode":"60187",
    "sg:province":"IL",
    "wof:name":"Family Shelter Service",
    "wof:placetype":"venue"
},
  "geometry": {"coordinates":[-88.097168,41.858981],"type":"Point"}
}