{
  "type": "Feature",
  "properties": {
    "iso:country":"US",
    "sg:address":"2450 Black Ln",
    "sg:city":"Caseyville",
    "sg:classifiers":[
        {
            "category":"Wholesale",
            "subcategory":"Auto Parts",
            "type":"Manufacturing & Wholesale Goods"
        }
    ],
    "sg:phone":"+1 618 345 6832",
    "sg:postcode":"62232",
    "sg:province":"IL",
    "sg:tags":[
        "automobile",
        "supply"
    ],
    "wof:name":"LKQ Metro-East Salvage Inc",
    "wof:placetype":"venue"
},
  "geometry": {"coordinates":[-90.046858,38.640928],"type":"Point"}
}