{
  "type": "Feature",
  "properties": {
    "iso:country":"US",
    "sg:address":"555 S Schuyler Ave",
    "sg:city":"Kankakee",
    "sg:classifiers":[
        {
            "category":"Social Services",
            "type":"Services"
        }
    ],
    "sg:phone":"+1 815 932 1695",
    "sg:postcode":"60901",
    "sg:province":"IL",
    "sg:tags":[
        "organization",
        "welfare"
    ],
    "wof:name":"Central Baptist Family Svc",
    "wof:placetype":"venue"
},
  "geometry": {"coordinates":[-87.865093,41.114629],"type":"Point"}
}