{
  "type": "Feature",
  "properties": {
    "iso:country":"US",
    "sg:address":"2902 W State Rte 17",
    "sg:city":"Kankakee",
    "sg:classifiers":[
        {
            "category":"Building & Trades",
            "subcategory":"Construction",
            "type":"Services"
        }
    ],
    "sg:phone":"+1 815 939 0107",
    "sg:postcode":"60901",
    "sg:province":"IL",
    "sg:tags":[
        "concrete",
        "contractor"
    ],
    "wof:name":"Thorne Concrete LLC",
    "wof:placetype":"venue"
},
  "geometry": {"coordinates":[-87.91095300000001,41.118442],"type":"Point"}
}