{
  "type": "Feature",
  "properties": {
    "addr:full":"316 S Joliet St Joliet IL 60436",
    "addr:housenumber":"316",
    "addr:postcode":"60436",
    "addr:street":"S Joliet St",
    "iso:country":"US",
    "sg:address":"316 S Joliet St",
    "sg:city":"Joliet",
    "sg:classifiers":[
        {
            "category":"Personal",
            "subcategory":"Beauty Salon",
            "type":"Services"
        }
    ],
    "sg:phone":"+1 815 723 5224",
    "sg:postcode":"60436",
    "sg:province":"IL",
    "wof:name":"Magic Comb Beauty Salon",
    "wof:placetype":"venue"
},
  "geometry": {"coordinates":[-88.084187,41.518761],"type":"Point"}
}