{
  "type": "Feature",
  "properties": {
    "iso:country":"US",
    "sg:address":"1415 N Dunton Ave",
    "sg:city":"Arlington Heights",
    "sg:classifiers":[
        {
            "category":"Banks & Credit Unions",
            "subcategory":"Bank",
            "type":"Services"
        }
    ],
    "sg:phone":"+1 847 253 9366",
    "sg:postcode":"60004",
    "sg:province":"IL",
    "sg:tags":[
        "broker",
        "mortgage"
    ],
    "wof:name":"Dunton Mortgage Corporation",
    "wof:placetype":"venue"
},
  "geometry": {"coordinates":[-87.982796,42.100718],"type":"Point"}
}