{
  "type": "Feature",
  "properties": {
    "addr:full":"139 Jason Ct Aurora IL 60502",
    "addr:housenumber":"139",
    "addr:postcode":"60502",
    "addr:street":"Jason Ct",
    "iso:country":"US",
    "sg:address":"139 Jason Ct",
    "sg:city":"Aurora",
    "sg:classifiers":[
        {
            "category":"Professional",
            "subcategory":"Advertising",
            "type":"Services"
        }
    ],
    "sg:phone":"+1 630 236 0599",
    "sg:postcode":"60502",
    "sg:province":"IL",
    "sg:tags":[
        "agency"
    ],
    "wof:name":"JG Design",
    "wof:placetype":"venue"
},
  "geometry": {"coordinates":[-88.257544,41.755378],"type":"Point"}
}