{
  "type": "Feature",
  "properties": {
    "addr:full":"3411 N. Paulina St. Chicago IL 60657",
    "addr:housenumber":"3411",
    "addr:postcode":"60657",
    "addr:street":"N. Paulina St.",
    "iso:country":"US",
    "sg:address":"3411 N. Paulina St.",
    "sg:city":"Chicago",
    "sg:classifiers":[
        {
            "category":"Local Transit",
            "type":"Transportation"
        }
    ],
    "sg:postcode":"60657",
    "sg:province":"IL",
    "sg:tags":[
        "public"
    ],
    "sg:website":"www.yourcta.com",
    "wof:name":"Paulina Brown Line CTA",
    "wof:placetype":"venue"
},
  "geometry": {"coordinates":[-87.670998,41.9436],"type":"Point"}
}