{
  "type": "Feature",
  "properties": {
    "iso:country":"US",
    "sg:address":"15800 State St",
    "sg:city":"South Holland",
    "sg:classifiers":[
        {
            "category":"Education",
            "subcategory":"University",
            "type":"Public Place"
        }
    ],
    "sg:phone":"+1 219 931 0096",
    "sg:postcode":"60473",
    "sg:province":"IL",
    "sg:tags":[
        "college"
    ],
    "wof:name":"South Suburban College",
    "wof:placetype":"venue"
},
  "geometry": {"coordinates":[-87.617293,41.607607],"type":"Point"}
}