{
  "type": "Feature",
  "properties": {
    "addr:full":"205 E Rand Rd Mount Prospect IL 60056",
    "addr:housenumber":"205",
    "addr:postcode":"60056",
    "addr:street":"E Rand Rd",
    "iso:country":"US",
    "sg:address":"205 E Rand Rd",
    "sg:city":"Mount Prospect",
    "sg:classifiers":[
        {
            "category":"Restaurant",
            "type":"Food & Drink"
        }
    ],
    "sg:menulink":"http://www.allmenus.com/il/wheeling/181049-wendys/menu/",
    "sg:phone":"+1 847 255 3250",
    "sg:postcode":"60056",
    "sg:province":"IL",
    "sg:tags":[
        "burger",
        "american",
        "soup"
    ],
    "wof:name":"Wendy's",
    "wof:placetype":"venue"
},
  "geometry": {"coordinates":[-87.93335,42.07878],"type":"Point"}
}