{
  "type": "Feature",
  "properties": {
    "iso:country":"US",
    "sg:address":"346 N Neil St",
    "sg:city":"Champaign",
    "sg:classifiers":[
        {
            "category":"Professional",
            "subcategory":"Accounting & Tax Preparation",
            "type":"Services"
        }
    ],
    "sg:phone":"+1 217 398 8698",
    "sg:postcode":"61820",
    "sg:province":"IL",
    "wof:name":"Managment Accounting Services",
    "wof:placetype":"venue"
},
  "geometry": {"coordinates":[-88.243482,40.118781],"type":"Point"}
}