{
  "type": "Feature",
  "properties": {
    "iso:country":"US",
    "sg:address":"7281 East Ave",
    "sg:city":"Bartlett",
    "sg:classifiers":[
        {
            "category":"Professional",
            "subcategory":"Computer Services",
            "type":"Services"
        }
    ],
    "sg:phone":"+1 630 830 0752",
    "sg:postcode":"60133",
    "sg:province":"IL",
    "sg:tags":[
        "related"
    ],
    "wof:name":"Jolie Enterprises Inc",
    "wof:placetype":"venue"
},
  "geometry": {"coordinates":[-88.154397,42.005616],"type":"Point"}
}