{
  "type": "Feature",
  "properties": {
    "addr:full":"720 Olive Street 30th Floor St. Louis MO 63101",
    "addr:housenumber":"720;30th",
    "addr:postcode":"63101",
    "addr:street":"Olive Street;Floor",
    "iso:country":"US",
    "sg:address":"720 Olive Street 30th Floor",
    "sg:city":"St. Louis",
    "sg:classifiers":[
        {
            "category":"Restaurant",
            "type":"Food & Drink"
        }
    ],
    "sg:phone":"+1 314 421 2745",
    "sg:postcode":"63101",
    "sg:province":"MO",
    "sg:tags":[
        "new",
        "american"
    ],
    "sg:website":"www.pattylongcatering.com",
    "wof:name":"Point Of View",
    "wof:placetype":"venue"
},
  "geometry": {"coordinates":[-90.19215699999999,38.628492],"type":"Point"}
}