{
  "type": "Feature",
  "properties": {
    "addr:full":"4956 W George St Chicago IL 60641",
    "addr:housenumber":"4956",
    "addr:postcode":"60641",
    "addr:street":"W George St",
    "iso:country":"US",
    "sg:address":"4956 W George St",
    "sg:city":"Chicago",
    "sg:classifiers":[
        {
            "category":"Place Of Worship",
            "subcategory":"Church",
            "type":"Public Place"
        },
        {
            "category":"Place Of Worship",
            "type":"Public Place"
        }
    ],
    "sg:phone":"+1 773 545 6207",
    "sg:postcode":"60641",
    "sg:province":"IL",
    "sg:tags":[
        "churches-baptist-general",
        "churches-baptist"
    ],
    "wof:name":"Maplewood Bible Baptist Church",
    "wof:placetype":"venue"
},
  "geometry": {"coordinates":[-87.750529,41.933297],"type":"Point"}
}