{
  "type": "Feature",
  "properties": {
    "iso:country":"US",
    "sg:address":"1941 Grove Ave",
    "sg:city":"Berwyn",
    "sg:classifiers":[
        {
            "category":"Real Estate",
            "subcategory":"Real Estate Operator",
            "type":"Services"
        }
    ],
    "sg:phone":"+1 708 788 9864",
    "sg:postcode":"60402",
    "sg:province":"IL",
    "sg:tags":[
        "building",
        "apartment"
    ],
    "wof:name":"Grove Avenue Apartments",
    "wof:placetype":"venue"
},
  "geometry": {"coordinates":[-87.794562,41.852928],"type":"Point"}
}