{
  "type": "Feature",
  "properties": {
    "addr:full":"723 N Charles St Belleville IL 62220",
    "addr:housenumber":"723",
    "addr:postcode":"62220",
    "addr:street":"N Charles St",
    "iso:country":"US",
    "sg:address":"723 N Charles St",
    "sg:city":"Belleville",
    "sg:classifiers":[
        {
            "category":"Shopping",
            "subcategory":"Jewelry",
            "type":"Retail Goods"
        }
    ],
    "sg:phone":"+1   ",
    "sg:postcode":"62220",
    "sg:province":"IL",
    "wof:name":"Beadazzled Creations",
    "wof:placetype":"venue"
},
  "geometry": {"coordinates":[-89.977737,38.5212],"type":"Point"}
}