{
  "type": "Feature",
  "properties": {
    "iso:country":"US",
    "sg:address":"1365 Wiley Rd",
    "sg:city":"Schaumburg",
    "sg:classifiers":[
        {
            "category":"Utilities",
            "subcategory":"Telephone",
            "type":"Services"
        }
    ],
    "sg:phone":"+1 847 805 0217",
    "sg:postcode":"60173",
    "sg:province":"IL",
    "sg:tags":[
        "distance",
        "companies-long"
    ],
    "wof:name":"Vinakom Communications",
    "wof:placetype":"venue"
},
  "geometry": {"coordinates":[-88.045603,42.058855],"type":"Point"}
}