{
  "type": "Feature",
  "properties": {
    "addr:full":"2524 Grove St Blue Island IL 60406",
    "addr:housenumber":"2524",
    "addr:postcode":"60406",
    "addr:street":"Grove St",
    "iso:country":"US",
    "sg:address":"2524 Grove St",
    "sg:city":"Blue Island",
    "sg:classifiers":[
        {
            "category":"Communications",
            "subcategory":"Film & Video Production",
            "type":"Services"
        }
    ],
    "sg:phone":"+1 708 389 6140",
    "sg:postcode":"60406",
    "sg:province":"IL",
    "sg:tags":[
        "taping"
    ],
    "wof:name":"Editing Techniques",
    "wof:placetype":"venue"
},
  "geometry": {"coordinates":[-87.68270699999999,41.654535],"type":"Point"}
}