{
  "type": "Feature",
  "properties": {
    "addr:full":"652 W Randolph St Chicago IL 60661",
    "addr:housenumber":"652",
    "addr:postcode":"60661",
    "addr:street":"W Randolph St",
    "iso:country":"US",
    "sg:address":"652 W Randolph St",
    "sg:city":"Chicago",
    "sg:classifiers":[
        {
            "category":"Real Estate",
            "subcategory":"Architect",
            "type":"Services"
        }
    ],
    "sg:phone":"+1 312 258 0301",
    "sg:postcode":"60661",
    "sg:province":"IL",
    "wof:name":"Studio Gc",
    "wof:placetype":"venue"
},
  "geometry": {"coordinates":[-87.644443,41.884682],"type":"Point"}
}