{
  "type": "Feature",
  "properties": {
    "iso:country":"US",
    "sg:address":"2001 W Willow Knolls Dr",
    "sg:city":"Peoria",
    "sg:classifiers":[
        {
            "category":"Insurance",
            "subcategory":"Insurance Agent",
            "type":"Services"
        },
        {
            "category":"Insurance",
            "subcategory":"Hazard Insurance",
            "type":"Services"
        },
        {
            "category":"Insurance",
            "subcategory":"Title Insurance",
            "type":"Services"
        },
        {
            "category":"Insurance",
            "subcategory":"Life Insurance",
            "type":"Services"
        }
    ],
    "sg:phone":"+1 309 691 0104",
    "sg:postcode":"61614",
    "sg:province":"IL",
    "sg:tags":[
        "business",
        "auto",
        "commercial",
        "homeowner",
        "motorcycle",
        "renter"
    ],
    "wof:name":"Allstate Insurance Company - Chuck Hubert",
    "wof:placetype":"venue"
},
  "geometry": {"coordinates":[-89.623099,40.776205],"type":"Point"}
}