{
  "type": "Feature",
  "properties": {
    "iso:country":"US",
    "sg:address":"406 E 3rd St",
    "sg:city":"Brookport",
    "sg:classifiers":[
        {
            "category":"Building & Trades",
            "subcategory":"Construction",
            "type":"Services"
        }
    ],
    "sg:phone":"+1 618 564 2423",
    "sg:postcode":"62910",
    "sg:province":"IL",
    "sg:tags":[
        "general",
        "contractor"
    ],
    "wof:name":"R M Construction",
    "wof:placetype":"venue"
},
  "geometry": {"coordinates":[-88.623121,37.123404],"type":"Point"}
}