{
  "type": "Feature",
  "properties": {
    "iso:country":"US",
    "sg:address":"3098 Lone Oak Rd",
    "sg:city":"Ava",
    "sg:classifiers":[
        {
            "category":"Wholesale",
            "subcategory":"Construction Materials",
            "type":"Manufacturing & Wholesale Goods"
        }
    ],
    "sg:phone":"+1 618 426 3065",
    "sg:postcode":"62907",
    "sg:province":"IL",
    "sg:tags":[
        "timberland",
        "company",
        "timber"
    ],
    "wof:name":"Loneoak Timber",
    "wof:placetype":"venue"
},
  "geometry": {"coordinates":[-89.455361,37.843291],"type":"Point"}
}