{
  "type": "Feature",
  "properties": {
    "iso:country":"US",
    "sg:address":"1212 E University Ave # A",
    "sg:city":"Urbana",
    "sg:classifiers":[
        {
            "category":"Building & Trades",
            "subcategory":"Electrical",
            "type":"Services"
        }
    ],
    "sg:phone":"+1 217 367 0252",
    "sg:postcode":"61802",
    "sg:province":"IL",
    "sg:tags":[
        "electrician"
    ],
    "wof:name":"Davis Electric Inc",
    "wof:placetype":"venue"
},
  "geometry": {"coordinates":[-88.193398,40.115799],"type":"Point"}
}