{
  "type": "Feature",
  "properties": {
    "iso:country":"US",
    "sg:address":"350 Mc Ginnis St",
    "sg:city":"Alton",
    "sg:classifiers":[
        {
            "category":"Building & Trades",
            "subcategory":"Construction",
            "type":"Services"
        }
    ],
    "sg:phone":"+1 618 462 6947",
    "sg:postcode":"62002",
    "sg:province":"IL",
    "sg:tags":[
        "house",
        "carpentry",
        "contractor"
    ],
    "wof:name":"S & H Construction",
    "wof:placetype":"venue"
},
  "geometry": {"coordinates":[-90.180793,38.90737],"type":"Point"}
}