{
  "type": "Feature",
  "properties": {
    "iso:country":"US",
    "sg:address":"312 2nd St W",
    "sg:city":"Lyndon",
    "sg:classifiers":[
        {
            "category":"Organizations",
            "subcategory":"Religious Organization",
            "type":"Services"
        }
    ],
    "sg:phone":"+1 815 778 3751",
    "sg:postcode":"61261",
    "sg:province":"IL",
    "sg:tags":[
        "church"
    ],
    "wof:name":"United Methodist Church",
    "wof:placetype":"venue"
},
  "geometry": {"coordinates":[-89.92501300000001,41.71415],"type":"Point"}
}