{
  "type": "Feature",
  "properties": {
    "iso:country":"US",
    "sg:address":"104 S Morrison Ave",
    "sg:city":"Collinsville",
    "sg:classifiers":[
        {
            "category":"Professional",
            "subcategory":"Business Services",
            "type":"Services"
        }
    ],
    "sg:phone":"+1 618 345 4100",
    "sg:postcode":"62234",
    "sg:province":"IL",
    "sg:tags":[
        "interior",
        "consultant",
        "design",
        "decorator"
    ],
    "wof:name":"Sheila's Interior Motives",
    "wof:placetype":"venue"
},
  "geometry": {"coordinates":[-89.984482,38.669953],"type":"Point"}
}