{
  "type": "Feature",
  "properties": {
    "iso:country":"US",
    "sg:address":"1909 Larkin Ave",
    "sg:city":"Elgin",
    "sg:classifiers":[
        {
            "category":"Autos & Motor Vehicles",
            "subcategory":"Motorcycle Sales",
            "type":"Retail Goods"
        }
    ],
    "sg:phone":"+1   ",
    "sg:postcode":"60123",
    "sg:province":"IL",
    "sg:tags":[
        "all",
        "parts",
        "terrain",
        "accessory"
    ],
    "wof:name":"P A Aero Ltd",
    "wof:placetype":"venue"
},
  "geometry": {"coordinates":[-88.32631600000001,42.032459],"type":"Point"}
}