{
  "type": "Feature",
  "properties": {
    "addr:full":"5576 N Elston Ave Chicago IL 60630",
    "addr:housenumber":"5576",
    "addr:postcode":"60630",
    "addr:street":"N Elston Ave",
    "iso:country":"US",
    "sg:address":"5576 N Elston Ave",
    "sg:city":"Chicago",
    "sg:classifiers":[
        {
            "category":"Professional",
            "subcategory":"Lawyer & Legal Services",
            "type":"Services"
        }
    ],
    "sg:phone":"+1 773 775 5257",
    "sg:postcode":"60630",
    "sg:province":"IL",
    "wof:name":"Shelesny Stephen G Atty",
    "wof:placetype":"venue"
},
  "geometry": {"coordinates":[-87.764099,41.982899],"type":"Point"}
}