{
  "type": "Feature",
  "properties": {
    "addr:full":"5140 N California Avenue Chicago IL 60625",
    "addr:housenumber":"5140",
    "addr:postcode":"60625",
    "addr:street":"N California Avenue",
    "iso:country":"US",
    "sg:address":"5140 N California Avenue",
    "sg:city":"Chicago",
    "sg:classifiers":[
        {
            "category":"Health Services",
            "subcategory":"Doctor",
            "type":"Services"
        }
    ],
    "sg:phone":"+1 773 878 7555",
    "sg:postcode":"60625",
    "sg:province":"IL",
    "wof:name":"Associated Urologists Sc",
    "wof:placetype":"venue"
},
  "geometry": {"coordinates":[-87.698905,41.975156],"type":"Point"}
}