{
  "type": "Feature",
  "properties": {
    "addr:full":"536 Atrium Dr Vernon Hills IL 60061",
    "addr:housenumber":"536",
    "addr:postcode":"60061",
    "addr:street":"Atrium Dr",
    "iso:country":"US",
    "sg:address":"536 Atrium Dr",
    "sg:city":"Vernon Hills",
    "sg:classifiers":[
        {
            "category":"Insurance",
            "subcategory":"Life Insurance",
            "type":"Services"
        }
    ],
    "sg:phone":"+1 847 327 3000",
    "sg:postcode":"60061",
    "sg:province":"IL",
    "wof:name":"Allstate",
    "wof:placetype":"venue"
},
  "geometry": {"coordinates":[-87.965424,42.237438],"type":"Point"}
}