{
  "type": "Feature",
  "properties": {
    "iso:country":"US",
    "sg:address":"356 N Co Rd 425 E",
    "sg:city":"Arthur",
    "sg:classifiers":[
        {
            "category":"Freight",
            "type":"Transportation"
        }
    ],
    "sg:phone":"+1 217 543 3386",
    "sg:postcode":"61911",
    "sg:province":"IL",
    "sg:tags":[
        "grain",
        "elevator"
    ],
    "wof:name":"Chesterville Elevator",
    "wof:placetype":"venue"
},
  "geometry": {"coordinates":[-88.390383,39.702923],"type":"Point"}
}