{
  "type": "Feature",
  "properties": {
    "iso:country":"US",
    "sg:address":"10101 S Roberts Rd",
    "sg:city":"Palos Hills",
    "sg:classifiers":[
        {
            "category":"Professional",
            "subcategory":"Employment Agencies",
            "type":"Services"
        }
    ],
    "sg:phone":"+1 708 233 1541",
    "sg:postcode":"60465",
    "sg:province":"IL",
    "wof:name":"Dental Connection Employment Services",
    "wof:placetype":"venue"
},
  "geometry": {"coordinates":[-87.817398,41.7076],"type":"Point"}
}