{
  "type": "Feature",
  "properties": {
    "addr:full":"462 Westmere Rd Des Plaines IL 60016",
    "addr:housenumber":"462",
    "addr:postcode":"60016",
    "addr:street":"Westmere Rd Des",
    "iso:country":"US",
    "sg:address":"462 Westmere Rd",
    "sg:city":"Des Plaines",
    "sg:classifiers":[
        {
            "category":"Wholesale",
            "subcategory":"Hardware",
            "type":"Manufacturing & Wholesale Goods"
        }
    ],
    "sg:phone":"+1 847 699 0818",
    "sg:postcode":"60016",
    "sg:province":"IL",
    "wof:name":"Prime Heating Co",
    "wof:placetype":"venue"
},
  "geometry": {"coordinates":[-87.934467,42.043551],"type":"Point"}
}