{
  "type": "Feature",
  "properties": {
    "iso:country":"US",
    "sg:address":"133 Indiana St",
    "sg:city":"Park Forest",
    "sg:classifiers":[
        {
            "category":"Building & Trades",
            "subcategory":"Construction",
            "type":"Services"
        }
    ],
    "sg:phone":"+1 708 748 8182",
    "sg:postcode":"60466",
    "sg:province":"IL",
    "sg:tags":[
        "hanging",
        "contractor"
    ],
    "wof:name":"Blacksmith Painting Services",
    "wof:placetype":"venue"
},
  "geometry": {"coordinates":[-87.69402599999999,41.501589],"type":"Point"}
}