{
  "type": "Feature",
  "properties": {
    "iso:country":"US",
    "sg:address":"1215 13th St",
    "sg:city":"Viola",
    "sg:classifiers":[
        {
            "category":"Personal",
            "subcategory":"Beauty Salon",
            "type":"Services"
        }
    ],
    "sg:phone":"+1 309 596 2188",
    "sg:postcode":"61486",
    "sg:province":"IL",
    "wof:name":"Mane Designs",
    "wof:placetype":"venue"
},
  "geometry": {"coordinates":[-90.586783,41.208563],"type":"Point"}
}