{
  "type": "Feature",
  "properties": {
    "addr:full":"7430 S Harlem Ave Bridgeview IL 60455",
    "addr:housenumber":"7430",
    "addr:postcode":"60455",
    "addr:street":"S Harlem Ave",
    "iso:country":"US",
    "sg:address":"7430 S Harlem Ave",
    "sg:city":"Bridgeview",
    "sg:classifiers":[
        {
            "category":"Food & Beverages",
            "subcategory":"Groceries & Convenience Stores",
            "type":"Retail Goods"
        }
    ],
    "sg:phone":"+1 708 458 1810",
    "sg:postcode":"60455",
    "sg:province":"IL",
    "sg:tags":[
        "grocer"
    ],
    "wof:name":"Bangkok Oriental Grocery",
    "wof:placetype":"venue"
},
  "geometry": {"coordinates":[-87.800201,41.756699],"type":"Point"}
}