{
  "type": "Feature",
  "properties": {
    "iso:country":"US",
    "sg:address":"420 Sheridan Rd",
    "sg:city":"Highwood",
    "sg:classifiers":[
        {
            "category":"Personal",
            "subcategory":"Beauty Salon",
            "type":"Services"
        },
        {
            "category":"Personal",
            "subcategory":"Skin Care",
            "type":"Services"
        },
        {
            "category":"Personal",
            "subcategory":"Nail Salon",
            "type":"Services"
        }
    ],
    "sg:phone":"+1 847 433 5314",
    "sg:postcode":"60040",
    "sg:province":"IL",
    "wof:name":"Mia's Facial & Waxing",
    "wof:placetype":"venue"
},
  "geometry": {"coordinates":[-87.809978,42.204207],"type":"Point"}
}