{
  "type": "Feature",
  "properties": {
    "addr:full":"1709 S Neil St Champaign IL 61820",
    "addr:housenumber":"1709",
    "addr:postcode":"61820",
    "addr:street":"S Neil St",
    "iso:country":"US",
    "sg:address":"1709 S Neil St",
    "sg:city":"Champaign",
    "sg:classifiers":[
        {
            "category":"Restaurant",
            "type":"Food & Drink"
        }
    ],
    "sg:phone":"+1 217 352 5001",
    "sg:postcode":"61820",
    "sg:province":"IL",
    "wof:name":"Steak and Shake Illinois Division",
    "wof:placetype":"venue"
},
  "geometry": {"coordinates":[-88.245003,40.095299],"type":"Point"}
}