{
  "type": "Feature",
  "properties": {
    "iso:country":"US",
    "sg:address":"223 S Locust St",
    "sg:city":"Champaign",
    "sg:classifiers":[
        {
            "category":"Professional",
            "subcategory":"Advertising",
            "type":"Services"
        },
        {
            "category":"Professional",
            "subcategory":"Printing & Photocopies",
            "type":"Services"
        },
        {
            "category":"Organizations",
            "subcategory":"Community Association",
            "type":"Services"
        }
    ],
    "sg:phone":"+1 217 351 7958",
    "sg:postcode":"61820",
    "sg:province":"IL",
    "sg:tags":[
        "engraving",
        "badge",
        "specialty",
        "trophies",
        "medal",
        "plaque"
    ],
    "sg:website":"http://www.trophytime.com",
    "wof:name":"Trophy Time Inc",
    "wof:placetype":"venue"
},
  "geometry": {"coordinates":[-88.238963,40.115322],"type":"Point"}
}