{
  "type": "Feature",
  "properties": {
    "addr:full":"408 S Oak Park Ave Oak Park IL 60302",
    "addr:housenumber":"408",
    "addr:postcode":"60302",
    "addr:street":"S Oak Park Ave",
    "iso:country":"US",
    "sg:address":"408 S Oak Park Ave",
    "sg:city":"Oak Park",
    "sg:classifiers":[
        {
            "category":"Personal",
            "subcategory":"Barber",
            "type":"Services"
        }
    ],
    "sg:phone":"+1 708 848 1570",
    "sg:postcode":"60302",
    "sg:province":"IL",
    "wof:name":"Emil's Barber Shop Hair Styling Salon",
    "wof:placetype":"venue"
},
  "geometry": {"coordinates":[-87.794197,41.881401],"type":"Point"}
}