{
  "type": "Feature",
  "properties": {
    "iso:country":"US",
    "sg:address":"12195 N Pine Cir",
    "sg:city":"Genoa",
    "sg:classifiers":[
        {
            "category":"Building & Trades",
            "subcategory":"Electrical",
            "type":"Services"
        }
    ],
    "sg:phone":"+1 815 784 3444",
    "sg:postcode":"60135",
    "sg:province":"IL",
    "sg:tags":[
        "electrical",
        "contractor"
    ],
    "wof:name":"Moore Electric",
    "wof:placetype":"venue"
},
  "geometry": {"coordinates":[-88.701404,42.119449],"type":"Point"}
}