{
  "type": "Feature",
  "properties": {
    "addr:full":"20168 N Rand Rd Palatine IL 60074",
    "addr:housenumber":"20168",
    "addr:postcode":"60074",
    "addr:street":"N Rand Rd",
    "iso:country":"US",
    "sg:address":"20168 N Rand Rd",
    "sg:city":"Palatine",
    "sg:classifiers":[
        {
            "category":"Retail",
            "subcategory":"Auto Repair",
            "type":"Services"
        }
    ],
    "sg:phone":"+1 847 359 2600",
    "sg:postcode":"60074",
    "sg:province":"IL",
    "sg:tags":[
        "body",
        "automobile",
        "painting"
    ],
    "wof:name":"Deer Park Collision Inc",
    "wof:placetype":"venue"
},
  "geometry": {"coordinates":[-88.04302300000001,42.156954],"type":"Point"}
}