{
  "type": "Feature",
  "properties": {
    "iso:country":"US",
    "sg:address":"6141 N Pulaski Rd",
    "sg:city":"Chicago",
    "sg:classifiers":[
        {
            "category":"Health Services",
            "subcategory":"Nursing And Care Facility",
            "type":"Services"
        }
    ],
    "sg:phone":"+1 773 478 2000",
    "sg:postcode":"60646",
    "sg:province":"IL",
    "sg:tags":[
        "skilled"
    ],
    "wof:name":"Peterson Park Health Care Ctr",
    "wof:placetype":"venue"
},
  "geometry": {"coordinates":[-87.728804,41.992968],"type":"Point"}
}