{
  "type": "Feature",
  "properties": {
    "addr:full":"900 N Washington Ave Kankakee IL 60901",
    "addr:housenumber":"900",
    "addr:postcode":"60901",
    "addr:street":"N Washington Ave",
    "iso:country":"US",
    "sg:address":"900 N Washington Ave",
    "sg:city":"Kankakee",
    "sg:classifiers":[
        {
            "category":"Retail",
            "subcategory":"Repair Shop",
            "type":"Services"
        }
    ],
    "sg:phone":"+1 815 932 3621",
    "sg:postcode":"60901",
    "sg:province":"IL",
    "sg:tags":[
        "welding"
    ],
    "wof:name":"Mastach Parks",
    "wof:placetype":"venue"
},
  "geometry": {"coordinates":[-87.865696,41.129963],"type":"Point"}
}