{
  "type": "Feature",
  "properties": {
    "iso:country":"US",
    "sg:address":"18159 Dixie Hwy",
    "sg:city":"Homewood",
    "sg:classifiers":[
        {
            "category":"Professional",
            "subcategory":"Lawyer & Legal Services",
            "type":"Services"
        }
    ],
    "sg:phone":"+1 708 798 7141",
    "sg:postcode":"60430",
    "sg:province":"IL",
    "wof:name":"Lantry & Lantry",
    "wof:placetype":"venue"
},
  "geometry": {"coordinates":[-87.665327,41.560138],"type":"Point"}
}