{
  "type": "Feature",
  "properties": {
    "addr:full":"306 E University Ave Champaign IL 61820",
    "addr:housenumber":"306",
    "addr:postcode":"61820",
    "addr:street":"E University Ave",
    "iso:country":"US",
    "sg:address":"306 E University Ave",
    "sg:city":"Champaign",
    "sg:classifiers":[
        {
            "category":"Building & Trades",
            "subcategory":"Equipment Rental",
            "type":"Services"
        }
    ],
    "sg:phone":"+1 217 351 7040",
    "sg:postcode":"61820",
    "sg:province":"IL",
    "wof:name":"U-Haul",
    "wof:placetype":"venue"
},
  "geometry": {"coordinates":[-88.23366,40.116425],"type":"Point"}
}