{
  "type": "Feature",
  "properties": {
    "iso:country":"US",
    "sg:address":"200 Lageschulte St",
    "sg:city":"Barrington",
    "sg:classifiers":[
        {
            "category":"Building & Trades",
            "subcategory":"Construction",
            "type":"Services"
        }
    ],
    "sg:phone":"+1 847 382 2001",
    "sg:postcode":"60010",
    "sg:province":"IL",
    "sg:tags":[
        "carpentry",
        "contractor"
    ],
    "wof:name":"Arbuthnot Construction Co",
    "wof:placetype":"venue"
},
  "geometry": {"coordinates":[-88.14309799999999,42.152416],"type":"Point"}
}