{
  "type": "Feature",
  "properties": {
    "iso:country":"US",
    "sg:address":"711 N Gilbert St",
    "sg:city":"Danville",
    "sg:classifiers":[
        {
            "category":"Insurance",
            "subcategory":"Insurance Agent",
            "type":"Services"
        },
        {
            "category":"Insurance",
            "subcategory":"Hazard Insurance",
            "type":"Services"
        },
        {
            "category":"Insurance",
            "subcategory":"Title Insurance",
            "type":"Services"
        }
    ],
    "sg:phone":"+1 217 442 8120",
    "sg:postcode":"61832",
    "sg:province":"IL",
    "sg:tags":[
        "auto",
        "homeowner"
    ],
    "sg:website":"http://apps.amfam.com/agentlocator/JSTIP1?sourceid=yp3",
    "wof:name":"American Family Insurance- Jeffrey Stipp",
    "wof:placetype":"venue"
},
  "geometry": {"coordinates":[-87.635559,40.136011],"type":"Point"}
}