{
  "type": "Feature",
  "properties": {
    "iso:country":"US",
    "sg:address":"1403 Joe Abbott Way",
    "sg:city":"Marion",
    "sg:classifiers":[
        {
            "category":"Shopping",
            "subcategory":"Department Store",
            "type":"Retail Goods"
        },
        {
            "category":"Shopping",
            "subcategory":"Discount & Variety Stores",
            "type":"Retail Goods"
        }
    ],
    "sg:phone":"+1 618 993 5246",
    "sg:postcode":"62959",
    "sg:province":"IL",
    "sg:website":"http://www.goldline-usa.com",
    "wof:name":"Goldline (U.S.A.) Inc.",
    "wof:placetype":"venue"
},
  "geometry": {"coordinates":[-88.946808,37.742583],"type":"Point"}
}