{
  "type": "Feature",
  "properties": {
    "iso:country":"US",
    "sg:address":"424 S 8th St",
    "sg:city":"Quincy",
    "sg:classifiers":[
        {
            "category":"Personal",
            "subcategory":"Beauty Salon",
            "type":"Services"
        }
    ],
    "sg:phone":"+1 217 223 1500",
    "sg:postcode":"62301",
    "sg:province":"IL",
    "sg:tags":[
        "shop"
    ],
    "wof:name":"Kristophers",
    "wof:placetype":"venue"
},
  "geometry": {"coordinates":[-91.403378,39.927639],"type":"Point"}
}