{
  "type": "Feature",
  "properties": {
    "addr:full":"1140 Hull Ct Aurora IL 60504",
    "addr:housenumber":"1140",
    "addr:postcode":"60504",
    "addr:street":"Hull Ct",
    "iso:country":"US",
    "sg:address":"1140 Hull Ct",
    "sg:city":"Aurora",
    "sg:classifiers":[
        {
            "category":"Professional",
            "subcategory":"Accounting & Tax Preparation",
            "type":"Services"
        }
    ],
    "sg:phone":"+1 630 978 8665",
    "sg:postcode":"60504",
    "sg:province":"IL",
    "sg:tags":[
        "accountant"
    ],
    "wof:name":"Null & Assoc",
    "wof:placetype":"venue"
},
  "geometry": {"coordinates":[-88.261388,41.735743],"type":"Point"}
}