{
  "type": "Feature",
  "properties": {
    "addr:full":"632 W Algonquin Rd Des Plaines IL 60016",
    "addr:housenumber":"632",
    "addr:postcode":"60016",
    "addr:street":"W Algonquin Rd Des",
    "iso:country":"US",
    "sg:address":"632 W Algonquin Rd",
    "sg:city":"Des Plaines",
    "sg:classifiers":[
        {
            "category":"Shopping",
            "subcategory":"Clothing, Apparel, & Fashions",
            "type":"Retail Goods"
        }
    ],
    "sg:phone":"+1 847 640 7774",
    "sg:postcode":"60016",
    "sg:province":"IL",
    "sg:tags":[
        "navy",
        "army"
    ],
    "sg:website":"www.yoursupply.com",
    "wof:name":"Army Navy Supply Depot",
    "wof:placetype":"venue"
},
  "geometry": {"coordinates":[-87.936453,42.030191],"type":"Point"}
}