{
  "type": "Feature",
  "properties": {
    "iso:country":"US",
    "sg:address":"3178 Doolittle Dr",
    "sg:city":"Northbrook",
    "sg:classifiers":[
        {
            "category":"Wholesale",
            "subcategory":"Furniture",
            "type":"Manufacturing & Wholesale Goods"
        }
    ],
    "sg:phone":"+1 847 564 9454",
    "sg:postcode":"60062",
    "sg:province":"IL",
    "sg:tags":[
        "hardwood"
    ],
    "wof:name":"Lpk International Inc",
    "wof:placetype":"venue"
},
  "geometry": {"coordinates":[-87.858617,42.144725],"type":"Point"}
}