{
  "type": "Feature",
  "properties": {
    "iso:country":"US",
    "sg:address":"1869 E 1950th Ave",
    "sg:city":"Beecher City",
    "sg:classifiers":[
        {
            "category":"Building & Trades",
            "subcategory":"Construction",
            "type":"Services"
        }
    ],
    "sg:phone":"+1 618 487 5070",
    "sg:postcode":"62414",
    "sg:province":"IL",
    "sg:tags":[
        "house"
    ],
    "wof:name":"Brandt Construction",
    "wof:placetype":"venue"
},
  "geometry": {"coordinates":[-88.776494,39.194182],"type":"Point"}
}