{
  "type": "Feature",
  "properties": {
    "addr:full":"300 N Jefferson St Salem IL 62881",
    "addr:housenumber":"300",
    "addr:postcode":"62881",
    "addr:street":"N Jefferson St",
    "iso:country":"US",
    "sg:address":"300 N Jefferson St",
    "sg:city":"Salem",
    "sg:classifiers":[
        {
            "category":"Social Services",
            "subcategory":"Child Care",
            "type":"Services"
        }
    ],
    "sg:phone":"+1 618 548 2273",
    "sg:postcode":"62881",
    "sg:province":"IL",
    "sg:tags":[
        "day"
    ],
    "wof:name":"Apple Tree Child Dev Ctr",
    "wof:placetype":"venue"
},
  "geometry": {"coordinates":[-88.943679,38.629323],"type":"Point"}
}