{
  "type": "Feature",
  "properties": {
    "iso:country":"US",
    "sg:address":"1550 Central Ave",
    "sg:city":"Roselle",
    "sg:classifiers":[
        {
            "category":"Manufacturing",
            "subcategory":"Electronics",
            "type":"Manufacturing & Wholesale Goods"
        }
    ],
    "sg:phone":"+1 630 924 7080",
    "sg:postcode":"60172",
    "sg:province":"IL",
    "sg:tags":[
        "printers-equipment",
        "supply"
    ],
    "wof:name":"Madden Communications",
    "wof:placetype":"venue"
},
  "geometry": {"coordinates":[-88.11763000000001,41.982444],"type":"Point"}
}