{
  "type": "Feature",
  "properties": {
    "iso:country":"US",
    "sg:address":"624 Hillview Rd",
    "sg:city":"Winchester",
    "sg:phone":"+1 217 742 9381",
    "sg:postcode":"62694",
    "sg:province":"IL",
    "sg:tags":[
        "farm",
        "corn",
        "soybean"
    ],
    "wof:name":"Larry Hoots",
    "wof:placetype":"venue"
},
  "geometry": {"coordinates":[-90.528503,39.611565],"type":"Point"}
}