{
  "type": "Feature",
  "properties": {
    "addr:full":"1800 Sutton Ln Schaumburg IL 60194",
    "addr:housenumber":"1800",
    "addr:postcode":"60194",
    "addr:street":"Sutton Ln",
    "iso:country":"US",
    "sg:address":"1800 Sutton Ln",
    "sg:city":"Schaumburg",
    "sg:classifiers":[
        {
            "category":"Autos & Motor Vehicles",
            "subcategory":"Auto Supplies",
            "type":"Retail Goods"
        }
    ],
    "sg:phone":"+1 847 310 1096",
    "sg:postcode":"60194",
    "sg:province":"IL",
    "sg:tags":[
        "glass",
        "window",
        "coating",
        "tinting"
    ],
    "wof:name":"Stachula, Gary R",
    "wof:placetype":"venue"
},
  "geometry": {"coordinates":[-88.123993,42.030949],"type":"Point"}
}