{
  "type": "Feature",
  "properties": {
    "addr:full":"2795 S Belt W Belleville IL 62226",
    "addr:housenumber":"2795",
    "addr:postcode":"62226",
    "addr:street":"S Belt W",
    "iso:country":"US",
    "sg:address":"2795 S Belt W",
    "sg:city":"Belleville",
    "sg:classifiers":[
        {
            "category":"Home & Garden",
            "subcategory":"Household Appliances",
            "type":"Retail Goods"
        }
    ],
    "sg:phone":"+1   ",
    "sg:postcode":"62226",
    "sg:province":"IL",
    "sg:tags":[
        "repair",
        "store"
    ],
    "wof:name":"Direct Maytag",
    "wof:placetype":"venue"
},
  "geometry": {"coordinates":[-90.022166,38.525872],"type":"Point"}
}