{
  "type": "Feature",
  "properties": {
    "addr:full":"540 W North Ave Lombard IL 60148",
    "addr:housenumber":"540",
    "addr:postcode":"60148",
    "addr:street":"W North Ave",
    "iso:country":"US",
    "sg:address":"540 W North Ave",
    "sg:city":"Lombard",
    "sg:classifiers":[
        {
            "category":"Restaurant",
            "type":"Food & Drink"
        }
    ],
    "sg:menulink":"http://www.allmenus.com/il/addison/212446-mcdonalds/menu/",
    "sg:postcode":"60148",
    "sg:province":"IL",
    "sg:tags":[
        "burger",
        "american"
    ],
    "wof:name":"McDonald's",
    "wof:placetype":"venue"
},
  "geometry": {"coordinates":[-88.031083,41.904449],"type":"Point"}
}