{
  "type": "Feature",
  "properties": {
    "iso:country":"US",
    "sg:address":"76 Carlyle Plaza Dr",
    "sg:city":"Belleville",
    "sg:classifiers":[
        {
            "category":"Shopping",
            "subcategory":"Gifts & Souvenirs",
            "type":"Retail Goods"
        }
    ],
    "sg:phone":"+1 618 277 2325",
    "sg:postcode":"62221",
    "sg:province":"IL",
    "sg:tags":[
        "shop"
    ],
    "wof:name":"Jan's Hallmark",
    "wof:placetype":"venue"
},
  "geometry": {"coordinates":[-89.955269,38.514453],"type":"Point"}
}