{
  "type": "Feature",
  "properties": {
    "iso:country":"US",
    "sg:address":"2208 Beachside Rd",
    "sg:city":"Mc Henry",
    "sg:classifiers":[
        {
            "category":"Shopping",
            "subcategory":"Hobbies, Toys, & Games",
            "type":"Retail Goods"
        }
    ],
    "sg:phone":"+1   ",
    "sg:postcode":"60050",
    "sg:province":"IL",
    "wof:name":"Kitty & ME Country Crafts",
    "wof:placetype":"venue"
},
  "geometry": {"coordinates":[-88.30159999999999,42.35713],"type":"Point"}
}