{
  "type": "Feature",
  "properties": {
    "iso:country":"US",
    "sg:address":"324 Bonnie Brae Ave",
    "sg:city":"Grayslake",
    "sg:classifiers":[
        {
            "category":"Wholesale",
            "subcategory":"Hardware",
            "type":"Manufacturing & Wholesale Goods"
        }
    ],
    "sg:phone":"+1 847 752 8335",
    "sg:postcode":"60030",
    "sg:province":"IL",
    "sg:tags":[
        "hardware-wholesale",
        "manufacturer"
    ],
    "wof:name":"Bradley K Hansen",
    "wof:placetype":"venue"
},
  "geometry": {"coordinates":[-88.03885200000001,42.354688],"type":"Point"}
}