{
  "type": "Feature",
  "properties": {
    "addr:full":"3150 W Montrose Ave Chicago IL 60618",
    "addr:housenumber":"3150",
    "addr:postcode":"60618",
    "addr:street":"W Montrose Ave",
    "iso:country":"US",
    "sg:address":"3150 W Montrose Ave",
    "sg:city":"Chicago",
    "sg:classifiers":[
        {
            "category":"Bakery",
            "type":"Food & Drink"
        }
    ],
    "sg:phone":"+1 773 463 6356",
    "sg:postcode":"60618",
    "sg:province":"IL",
    "wof:name":"Sweetheart Bake Shop",
    "wof:placetype":"venue"
},
  "geometry": {"coordinates":[-87.734495,41.960905],"type":"Point"}
}