{
  "type": "Feature",
  "properties": {
    "addr:full":"2338 Charles St Rockford IL 61104",
    "addr:housenumber":"2338",
    "addr:postcode":"61104",
    "addr:street":"Charles St",
    "iso:country":"US",
    "sg:address":"2338 Charles St",
    "sg:city":"Rockford",
    "sg:classifiers":[
        {
            "category":"Restaurant",
            "type":"Food & Drink"
        }
    ],
    "sg:phone":"+1 815 398 9900",
    "sg:postcode":"61104",
    "sg:province":"IL",
    "sg:tags":[
        "pizza"
    ],
    "wof:name":"Opsahl's Pizza II",
    "wof:placetype":"venue"
},
  "geometry": {"coordinates":[-89.05770699999999,42.260392],"type":"Point"}
}