{
  "type": "Feature",
  "properties": {
    "iso:country":"US",
    "sg:address":"6907 Charlotte Ave",
    "sg:city":"Crystal Lake",
    "sg:classifiers":[
        {
            "category":"Farming",
            "subcategory":"Farm",
            "type":"Manufacturing & Wholesale Goods"
        }
    ],
    "sg:phone":"+1 815 459 1344",
    "sg:postcode":"60014",
    "sg:province":"IL",
    "sg:tags":[
        "crop",
        "general"
    ],
    "wof:name":"Duane Hawthorne",
    "wof:placetype":"venue"
},
  "geometry": {"coordinates":[-88.373526,42.229797],"type":"Point"}
}