{
  "type": "Feature",
  "properties": {
    "iso:country":"US",
    "sg:address":"11318 Genoa Rd",
    "sg:city":"Genoa",
    "sg:phone":"+1 815 784 3066",
    "sg:postcode":"60135",
    "sg:province":"IL",
    "sg:tags":[
        "farm",
        "corn",
        "soybean"
    ],
    "wof:name":"Volkening Farms",
    "wof:placetype":"venue"
},
  "geometry": {"coordinates":[-88.6956,42.164968],"type":"Point"}
}