{
  "type": "Feature",
  "properties": {
    "iso:country":"US",
    "sg:address":"224 N Alpine Rd",
    "sg:city":"Rockford",
    "sg:classifiers":[
        {
            "category":"Autos & Motor Vehicles",
            "subcategory":"Automobile Sales",
            "type":"Retail Goods"
        }
    ],
    "sg:phone":"+1 815 229 0510",
    "sg:postcode":"61107",
    "sg:province":"IL",
    "sg:tags":[
        "car",
        "dealer"
    ],
    "sg:website":"www.rockriverford.net",
    "wof:name":"Rock River Ford & Hyundai",
    "wof:placetype":"venue"
},
  "geometry": {"coordinates":[-89.028992,42.264099],"type":"Point"}
}