{
  "type": "Feature",
  "properties": {
    "addr:full":"1080 Ashbury Ct Geneva IL 60134",
    "addr:housenumber":"1080",
    "addr:postcode":"60134",
    "addr:street":"Ashbury Ct",
    "iso:country":"US",
    "sg:address":"1080 Ashbury Ct",
    "sg:city":"Geneva",
    "sg:classifiers":[
        {
            "category":"Professional",
            "subcategory":"Management & Consulting",
            "type":"Services"
        }
    ],
    "sg:phone":"+1 630 845 8416",
    "sg:postcode":"60134",
    "sg:province":"IL",
    "sg:tags":[
        "business"
    ],
    "wof:name":"People Centrics",
    "wof:placetype":"venue"
},
  "geometry": {"coordinates":[-88.324208,41.876336],"type":"Point"}
}