{
  "type": "Feature",
  "properties": {
    "addr:full":"613 W Jefferson St Ottawa IL 61350",
    "addr:housenumber":"613",
    "addr:postcode":"61350",
    "addr:street":"W Jefferson St",
    "iso:country":"US",
    "sg:address":"613 W Jefferson St",
    "sg:city":"Ottawa",
    "sg:classifiers":[
        {
            "category":"Building & Trades",
            "subcategory":"Construction",
            "type":"Services"
        }
    ],
    "sg:phone":"+1 815 434 0220",
    "sg:postcode":"61350",
    "sg:province":"IL",
    "sg:tags":[
        "home",
        "general",
        "commercial",
        "family",
        "contractor"
    ],
    "wof:name":"Koch Bros General Contractors",
    "wof:placetype":"venue"
},
  "geometry": {"coordinates":[-88.84892499999999,41.347773],"type":"Point"}
}