{
  "type": "Feature",
  "properties": {
    "iso:country":"US",
    "sg:address":"811 Fairfax St",
    "sg:city":"Carlyle",
    "sg:classifiers":[
        {
            "category":"Health Services",
            "subcategory":"Doctor",
            "type":"Services"
        },
        {
            "category":"Health Services",
            "subcategory":"Clinic",
            "type":"Services"
        },
        {
            "category":"Community Center",
            "type":"Public Place"
        }
    ],
    "sg:phone":"+1 618 594 3025",
    "sg:postcode":"62231",
    "sg:province":"IL",
    "sg:tags":[
        "physician",
        "family",
        "medical",
        "practice",
        "surgeons",
        "medicine"
    ],
    "wof:name":"St Mary's Good Samaritan Fa",
    "wof:placetype":"venue"
},
  "geometry": {"coordinates":[-89.367829,38.61119],"type":"Point"}
}