{
  "type": "Feature",
  "properties": {
    "iso:country":"US",
    "sg:address":"223 W Illinois St",
    "sg:city":"Wheaton",
    "sg:classifiers":[
        {
            "category":"Health Services",
            "subcategory":"Doctor",
            "type":"Services"
        }
    ],
    "sg:phone":"+1 630 668 4500",
    "sg:postcode":"60187",
    "sg:province":"IL",
    "sg:tags":[
        "surgeon",
        "oral"
    ],
    "wof:name":"Beck Dennis Jas DDS",
    "wof:placetype":"venue"
},
  "geometry": {"coordinates":[-88.10929899999999,41.862],"type":"Point"}
}