{
  "type": "Feature",
  "properties": {
    "iso:country":"US",
    "sg:address":"4506 Avenue of the Cities",
    "sg:city":"Moline",
    "sg:classifiers":[
        {
            "category":"Restaurant",
            "type":"Food & Drink"
        }
    ],
    "sg:phone":"+1 309 743 0091",
    "sg:postcode":"61265",
    "sg:province":"IL",
    "sg:tags":[
        "mongolian",
        "chinese"
    ],
    "sg:website":"www.hihowok.com",
    "wof:name":"Hi Ho Mongolian Grill",
    "wof:placetype":"venue"
},
  "geometry": {"coordinates":[-90.473139,41.489681],"type":"Point"}
}