{
  "type": "Feature",
  "properties": {
    "addr:full":"2309 Oak Ln Rolling Meadows IL 60008",
    "addr:housenumber":"2309",
    "addr:postcode":"60008",
    "addr:street":"Oak Ln",
    "iso:country":"US",
    "sg:address":"2309 Oak Ln",
    "sg:city":"Rolling Meadows",
    "sg:classifiers":[
        {
            "category":"Retail",
            "subcategory":"Repair Shop",
            "type":"Services"
        }
    ],
    "sg:phone":"+1 847 253 7797",
    "sg:postcode":"60008",
    "sg:province":"IL",
    "wof:name":"Frame Expressions",
    "wof:placetype":"venue"
},
  "geometry": {"coordinates":[-88.012176,42.063992],"type":"Point"}
}