{
  "type": "Feature",
  "properties": {
    "iso:country":"US",
    "sg:address":"11749 Southwest Hwy",
    "sg:city":"Palos Heights",
    "sg:classifiers":[
        {
            "category":"Health Services",
            "subcategory":"Optometrist",
            "type":"Services"
        },
        {
            "category":"Shopping",
            "subcategory":"Optician",
            "type":"Retail Goods"
        }
    ],
    "sg:phone":"+1 708 361 5236",
    "sg:postcode":"60463",
    "sg:province":"IL",
    "sg:tags":[
        "eyewear"
    ],
    "wof:name":"Palos Vision Center",
    "wof:placetype":"venue"
},
  "geometry": {"coordinates":[-87.8134,41.677502],"type":"Point"}
}