{
  "type": "Feature",
  "properties": {
    "iso:country":"US",
    "sg:address":"4730 138th St",
    "sg:city":"Crestwood",
    "sg:classifiers":[
        {
            "category":"Building & Trades",
            "subcategory":"Construction",
            "type":"Services"
        }
    ],
    "sg:phone":"+1 708 371 6540",
    "sg:postcode":"60445",
    "sg:province":"IL",
    "sg:tags":[
        "contractor"
    ],
    "wof:name":"Ipema Concrete Construction Inc",
    "wof:placetype":"venue"
},
  "geometry": {"coordinates":[-87.737801,41.6422],"type":"Point"}
}