{
  "type": "Feature",
  "properties": {
    "iso:country":"US",
    "sg:address":"709 S Chippewa Ave",
    "sg:city":"Freeport",
    "sg:classifiers":[
        {
            "category":"Government",
            "subcategory":"Office",
            "type":"Public Place"
        }
    ],
    "sg:phone":"+1 815 232 1319",
    "sg:postcode":"61032",
    "sg:province":"IL",
    "sg:tags":[
        "village"
    ],
    "wof:name":"Freeport Mosquito Abatement",
    "wof:placetype":"venue"
},
  "geometry": {"coordinates":[-89.604115,42.293444],"type":"Point"}
}