{
  "type": "Feature",
  "properties": {
    "addr:full":"709 S Chippewa Ave Freeport IL 61032",
    "addr:housenumber":"709",
    "addr:postcode":"61032",
    "addr:street":"S Chippewa Ave",
    "iso:country":"US",
    "sg:address":"709 S Chippewa Ave",
    "sg:city":"Freeport",
    "sg:classifiers":[
        {
            "category":"Government",
            "subcategory":"Office",
            "type":"Public Place"
        }
    ],
    "sg:phone":"+1 815 232 1319",
    "sg:postcode":"61032",
    "sg:province":"IL",
    "sg:tags":[
        "village"
    ],
    "wof:name":"Freeport Mosquito Abatement",
    "wof:placetype":"venue"
},
  "geometry": {"coordinates":[-89.60411499999999,42.293444],"type":"Point"}
}