{
  "type": "Feature",
  "properties": {
    "iso:country":"US",
    "sg:address":"322 W State St",
    "sg:city":"Geneva",
    "sg:classifiers":[
        {
            "category":"Insurance",
            "subcategory":"Hazard Insurance",
            "type":"Services"
        },
        {
            "category":"Insurance",
            "subcategory":"Life Insurance",
            "type":"Services"
        },
        {
            "category":"Banks & Credit Unions",
            "subcategory":"Financial Services",
            "type":"Services"
        }
    ],
    "sg:phone":"+1 630 262 6122",
    "sg:postcode":"60134",
    "sg:province":"IL",
    "sg:tags":[
        "annuity",
        "retirement",
        "commercial",
        "plan",
        "business"
    ],
    "wof:name":"James E Schwarzbach Insurance",
    "wof:placetype":"venue"
},
  "geometry": {"coordinates":[-88.308198,41.887963],"type":"Point"}
}