{
  "type": "Feature",
  "properties": {
    "addr:full":"566 W Lake St Chicago IL 60661",
    "addr:housenumber":"566",
    "addr:postcode":"60661",
    "addr:street":"W Lake St",
    "iso:country":"US",
    "sg:address":"566 W Lake St",
    "sg:city":"Chicago",
    "sg:classifiers":[
        {
            "category":"Professional",
            "type":"Services"
        }
    ],
    "sg:phone":"+1 312 928 0667",
    "sg:postcode":"60661",
    "sg:province":"IL",
    "sg:tags":[
        "scientist"
    ],
    "wof:name":"Arias Technology Corp",
    "wof:placetype":"venue"
},
  "geometry": {"coordinates":[-87.641313,41.885698],"type":"Point"}
}