{
  "type": "Feature",
  "properties": {
    "addr:full":"215 Blackberry Dr Bolingbrook IL 60440",
    "addr:housenumber":"215",
    "addr:postcode":"60440",
    "addr:street":"Blackberry Dr",
    "iso:country":"US",
    "sg:address":"215 Blackberry Dr",
    "sg:city":"Bolingbrook",
    "sg:classifiers":[
        {
            "category":"Building & Trades",
            "subcategory":"Landscaping Services",
            "type":"Services"
        }
    ],
    "sg:phone":"+1 630 378 4977",
    "sg:postcode":"60440",
    "sg:province":"IL",
    "sg:tags":[
        "tree"
    ],
    "wof:name":"Tree Masters Inc",
    "wof:placetype":"venue"
},
  "geometry": {"coordinates":[-88.100274,41.693601],"type":"Point"}
}