{
  "type": "Feature",
  "properties": {
    "addr:full":"7020 W Cullom Ave Norridge IL 60706",
    "addr:housenumber":"7020",
    "addr:postcode":"60706",
    "addr:street":"W Cullom Ave",
    "iso:country":"US",
    "sg:address":"7020 W Cullom Ave",
    "sg:city":"Norridge",
    "sg:classifiers":[
        {
            "category":"Food & Beverages",
            "subcategory":"Groceries & Convenience Stores",
            "type":"Retail Goods"
        }
    ],
    "sg:phone":"+1 708 457 8340",
    "sg:postcode":"60706",
    "sg:province":"IL",
    "wof:name":"Rich Food Store",
    "wof:placetype":"venue"
},
  "geometry": {"coordinates":[-87.80295,41.957814],"type":"Point"}
}