{
  "type": "Feature",
  "properties": {
    "iso:country":"US",
    "sg:address":"1403 E Broadway",
    "sg:city":"Alton",
    "sg:classifiers":[
        {
            "category":"Professional",
            "subcategory":"Lawyer & Legal Services",
            "type":"Services"
        }
    ],
    "sg:phone":"+1 618 462 9284",
    "sg:postcode":"62002",
    "sg:province":"IL",
    "sg:tags":[
        "attorney",
        "practice"
    ],
    "wof:name":"William E Miller Iii Law Ofc",
    "wof:placetype":"venue"
},
  "geometry": {"coordinates":[-90.165288,38.887761],"type":"Point"}
}