{
  "type": "Feature",
  "properties": {
    "iso:country":"US",
    "sg:address":"9910 S Prospect Ave",
    "sg:city":"Chicago",
    "sg:classifiers":[
        {
            "category":"Retail",
            "subcategory":"Auto Repair",
            "type":"Services"
        }
    ],
    "sg:phone":"+1 773 779 7492",
    "sg:postcode":"60643",
    "sg:province":"IL",
    "sg:tags":[
        "automotive"
    ],
    "wof:name":"Triangulos International",
    "wof:placetype":"venue"
},
  "geometry": {"coordinates":[-87.663176,41.713238],"type":"Point"}
}