{
  "type": "Feature",
  "properties": {
    "iso:country":"US",
    "sg:address":"1548 S Randall Rd",
    "sg:city":"Geneva",
    "sg:classifiers":[
        {
            "category":"Shopping",
            "subcategory":"Gifts & Souvenirs",
            "type":"Retail Goods"
        }
    ],
    "sg:phone":"+1 630 262 8793",
    "sg:postcode":"60134",
    "sg:province":"IL",
    "sg:tags":[
        "party",
        "supply"
    ],
    "sg:website":"www.factorycard.com",
    "wof:name":"Factory Card and Party Outlet",
    "wof:placetype":"venue"
},
  "geometry": {"coordinates":[-88.340369,41.870709],"type":"Point"}
}