{
  "type": "Feature",
  "properties": {
    "iso:country":"US",
    "sg:address":"205 N Michigan Ave # 4310",
    "sg:city":"Chicago",
    "sg:classifiers":[
        {
            "category":"Autos & Motor Vehicles",
            "subcategory":"Auto Supplies",
            "type":"Retail Goods"
        }
    ],
    "sg:phone":"+1 312 565 3001",
    "sg:postcode":"60601",
    "sg:province":"IL",
    "sg:tags":[
        "muffler",
        "system",
        "exhaust"
    ],
    "sg:website":"http://www.midas.com",
    "wof:name":"Midas Muffler",
    "wof:placetype":"venue"
},
  "geometry": {"coordinates":[-87.62442299999999,41.885795],"type":"Point"}
}