{
  "type": "Feature",
  "properties": {
    "addr:full":"466 N 5th St Breese IL 62230",
    "addr:housenumber":"466",
    "addr:postcode":"62230",
    "addr:street":"N 5Th St",
    "iso:country":"US",
    "sg:address":"466 N 5th St",
    "sg:city":"Breese",
    "sg:classifiers":[
        {
            "category":"Shopping",
            "subcategory":"Discount & Variety Stores",
            "type":"Retail Goods"
        }
    ],
    "sg:phone":"+1   ",
    "sg:postcode":"62230",
    "sg:province":"IL",
    "sg:tags":[
        "household",
        "general",
        "merchandise",
        "furniture"
    ],
    "wof:name":"Jans Uniforms",
    "wof:placetype":"venue"
},
  "geometry": {"coordinates":[-89.529591,38.611647],"type":"Point"}
}