{
  "type": "Feature",
  "properties": {
    "iso:country":"US",
    "sg:address":"101 S Bench St",
    "sg:city":"Galena",
    "sg:classifiers":[
        {
            "category":"Government",
            "subcategory":"Fire Station",
            "type":"Public Place"
        }
    ],
    "sg:phone":"+1 815 777 0025",
    "sg:postcode":"61036",
    "sg:province":"IL",
    "sg:tags":[
        "department"
    ],
    "wof:name":"Galena Fire Dept",
    "wof:placetype":"venue"
},
  "geometry": {"coordinates":[-90.428893,42.416796],"type":"Point"}
}