{
  "type": "Feature",
  "properties": {
    "addr:full":"5345 W Devon Ave Chicago IL 60646",
    "addr:housenumber":"5345",
    "addr:postcode":"60646",
    "addr:street":"W Devon Ave",
    "iso:country":"US",
    "sg:address":"5345 W Devon Ave",
    "sg:city":"Chicago",
    "sg:classifiers":[
        {
            "category":"Restaurant",
            "type":"Food & Drink"
        }
    ],
    "sg:menulink":"http://www.allmenus.com/il/chicago/224173-villa-rosa/menu/",
    "sg:phone":"+1 773 774 7107",
    "sg:postcode":"60646",
    "sg:province":"IL",
    "sg:tags":[
        "american",
        "diner"
    ],
    "wof:name":"Villa Rosa",
    "wof:placetype":"venue"
},
  "geometry": {"coordinates":[-87.762508,41.997256],"type":"Point"}
}