{
  "type": "Feature",
  "properties": {
    "iso:country":"US",
    "sg:address":"9920 Lincoln Rd",
    "sg:city":"Morrison",
    "sg:classifiers":[
        {
            "category":"Manufacturing",
            "subcategory":"Food",
            "type":"Manufacturing & Wholesale Goods"
        },
        {
            "category":"Farming",
            "subcategory":"Farm",
            "type":"Manufacturing & Wholesale Goods"
        }
    ],
    "sg:phone":"+1 815 772 4736",
    "sg:postcode":"61270",
    "sg:province":"IL",
    "sg:tags":[
        "corn",
        "product"
    ],
    "wof:name":"Edward Abbott",
    "wof:placetype":"venue"
},
  "geometry": {"coordinates":[-90.05829900000001,41.84563],"type":"Point"}
}