{
  "type": "Feature",
  "properties": {
    "iso:country":"US",
    "sg:address":"1511 Chestnut St",
    "sg:city":"Ottawa",
    "sg:classifiers":[
        {
            "category":"Recreation",
            "type":"Entertainment"
        }
    ],
    "sg:phone":"+1 815 433 9463",
    "sg:postcode":"61350",
    "sg:province":"IL",
    "sg:tags":[
        "skating",
        "rink"
    ],
    "wof:name":"Paramount Skating Arena Inc",
    "wof:placetype":"venue"
},
  "geometry": {"coordinates":[-88.848906,41.356139],"type":"Point"}
}