{
  "type": "Feature",
  "properties": {
    "iso:country":"US",
    "sg:address":"430 E Broadway St",
    "sg:city":"Bradley",
    "sg:classifiers":[
        {
            "category":"Shopping",
            "subcategory":"Used Merchandise",
            "type":"Retail Goods"
        }
    ],
    "sg:phone":"+1 815 936 1930",
    "sg:postcode":"60915",
    "sg:province":"IL",
    "sg:tags":[
        "antique"
    ],
    "wof:name":"Antiquery",
    "wof:placetype":"venue"
},
  "geometry": {"coordinates":[-87.85687799999999,41.144406],"type":"Point"}
}