{
  "type": "Feature",
  "properties": {
    "iso:country":"US",
    "sg:address":"17712 Oak Park Ave",
    "sg:city":"Tinley Park",
    "sg:classifiers":[
        {
            "category":"Insurance",
            "subcategory":"Insurance Agent",
            "type":"Services"
        }
    ],
    "sg:phone":"+1 708 532 2201",
    "sg:postcode":"60477",
    "sg:province":"IL",
    "wof:name":"Richard Robilotta Insur Agcy",
    "wof:placetype":"venue"
},
  "geometry": {"coordinates":[-87.78419100000001,41.568262],"type":"Point"}
}