{
  "type": "Feature",
  "properties": {
    "iso:country":"US",
    "sg:address":"10665 Granada Ct",
    "sg:city":"Palos Hills",
    "sg:classifiers":[
        {
            "category":"Communications",
            "subcategory":"Film & Video Production",
            "type":"Services"
        }
    ],
    "sg:phone":"+1 708 598 8280",
    "sg:postcode":"60465",
    "sg:province":"IL",
    "sg:tags":[
        "motion"
    ],
    "wof:name":"All Pro Video Productions",
    "wof:placetype":"venue"
},
  "geometry": {"coordinates":[-87.832647,41.696625],"type":"Point"}
}