{
  "type": "Feature",
  "properties": {
    "addr:full":"9415 Enterprise Dr Mokena IL 60448",
    "addr:housenumber":"9415",
    "addr:postcode":"60448",
    "addr:street":"Enterprise Dr",
    "iso:country":"US",
    "sg:address":"9415 Enterprise Dr",
    "sg:city":"Mokena",
    "sg:classifiers":[
        {
            "category":"Retail",
            "subcategory":"Auto Repair",
            "type":"Services"
        }
    ],
    "sg:phone":"+1 708 478 6500",
    "sg:postcode":"60448",
    "sg:province":"IL",
    "sg:tags":[
        "scooters-repairing",
        "motorcycle",
        "motor"
    ],
    "wof:name":"Sterling Custom Cycle",
    "wof:placetype":"venue"
},
  "geometry": {"coordinates":[-87.84570100000001,41.540305],"type":"Point"}
}