{
  "type": "Feature",
  "properties": {
    "iso:country":"US",
    "sg:address":"1412 W 18th St",
    "sg:city":"Chicago",
    "sg:classifiers":[
        {
            "category":"Personal",
            "subcategory":"Beauty Salon",
            "type":"Services"
        }
    ],
    "sg:phone":"+1 312 226 8436",
    "sg:postcode":"60608",
    "sg:province":"IL",
    "sg:tags":[
        "hair"
    ],
    "wof:name":"Pancho's Barber Shop",
    "wof:placetype":"venue"
},
  "geometry": {"coordinates":[-87.661697,41.858002],"type":"Point"}
}