{
  "type": "Feature",
  "properties": {
    "addr:full":"7101 W Archer Ave Chicago IL 60638",
    "addr:housenumber":"7101",
    "addr:postcode":"60638",
    "addr:street":"W Archer Ave",
    "iso:country":"US",
    "sg:address":"7101 W Archer Ave",
    "sg:city":"Chicago",
    "sg:classifiers":[
        {
            "category":"Health Services",
            "subcategory":"Doctor",
            "type":"Services"
        }
    ],
    "sg:phone":"+1 773 586 6555",
    "sg:postcode":"60638",
    "sg:province":"IL",
    "wof:name":"Randin Francisco J MD",
    "wof:placetype":"venue"
},
  "geometry": {"coordinates":[-87.799103,41.791901],"type":"Point"}
}