{
  "type": "Feature",
  "properties": {
    "addr:full":"200 W Main St Greenville IL 62246",
    "addr:housenumber":"200",
    "addr:postcode":"62246",
    "addr:street":"W Main St",
    "iso:country":"US",
    "sg:address":"200 W Main St",
    "sg:city":"Greenville",
    "sg:classifiers":[
        {
            "category":"Banks & Credit Unions",
            "subcategory":"Bank",
            "type":"Services"
        }
    ],
    "sg:phone":"+1 618 664 1111",
    "sg:postcode":"62246",
    "sg:province":"IL",
    "wof:name":"First Bank",
    "wof:placetype":"venue"
},
  "geometry": {"coordinates":[-89.41346299999999,38.892042],"type":"Point"}
}