{
  "type": "Feature",
  "properties": {
    "iso:country":"US",
    "sg:address":"16216 Old State Rd",
    "sg:city":"Carlyle",
    "sg:classifiers":[
        {
            "category":"Retail",
            "subcategory":"Repair Shop",
            "type":"Services"
        }
    ],
    "sg:phone":"+1 618 594 8572",
    "sg:postcode":"62231",
    "sg:province":"IL",
    "sg:tags":[
        "welding"
    ],
    "wof:name":"Duane Luebbers Welding",
    "wof:placetype":"venue"
},
  "geometry": {"coordinates":[-89.406353,38.616552],"type":"Point"}
}