{
  "type": "Feature",
  "properties": {
    "iso:country":"US",
    "sg:address":"314 S Johnson Ave",
    "sg:city":"Mount Vernon",
    "sg:classifiers":[
        {
            "category":"Retail",
            "subcategory":"Auto Repair",
            "type":"Services"
        }
    ],
    "sg:phone":"+1 618 242 2509",
    "sg:postcode":"62864",
    "sg:province":"IL",
    "sg:tags":[
        "body",
        "automotive",
        "shop"
    ],
    "wof:name":"Wilsons Body Shop",
    "wof:placetype":"venue"
},
  "geometry": {"coordinates":[-88.90141,38.315781],"type":"Point"}
}