{
  "type": "Feature",
  "properties": {
    "addr:full":"23949 Gridley Rd Virginia IL 62691",
    "addr:postcode":"23949;62691",
    "addr:street":"Gridley Rd",
    "iso:country":"US",
    "sg:address":"23949 Gridley Rd",
    "sg:city":"Virginia",
    "sg:classifiers":[
        {
            "category":"Professional",
            "subcategory":"Computer Services",
            "type":"Services"
        }
    ],
    "sg:phone":"+1 217 452 7346",
    "sg:postcode":"62691",
    "sg:province":"IL",
    "sg:tags":[
        "internet"
    ],
    "wof:name":"G L Winkelman Internet",
    "wof:placetype":"venue"
},
  "geometry": {"coordinates":[-90.129583,39.952928],"type":"Point"}
}