{
  "type": "Feature",
  "properties": {
    "iso:country":"US",
    "sg:address":"2755 Eastwood Ave",
    "sg:city":"Evanston",
    "sg:classifiers":[
        {
            "category":"Banks & Credit Unions",
            "subcategory":"Investment Brokerage",
            "type":"Services"
        }
    ],
    "sg:phone":"+1 847 328 0200",
    "sg:postcode":"60201",
    "sg:province":"IL",
    "sg:tags":[
        "consultant",
        "planning",
        "financial"
    ],
    "wof:name":"Capital Programs Corp",
    "wof:placetype":"venue"
},
  "geometry": {"coordinates":[-87.695492,42.0685],"type":"Point"}
}