{
  "type": "Feature",
  "properties": {
    "iso:country":"US",
    "sg:address":"1513 Greenleaf St",
    "sg:city":"Evanston",
    "sg:classifiers":[
        {
            "category":"Professional",
            "subcategory":"Business Services",
            "type":"Services"
        }
    ],
    "sg:phone":"+1 847 864 6552",
    "sg:postcode":"60202",
    "sg:province":"IL",
    "sg:tags":[
        "repair"
    ],
    "wof:name":"J M Oshanna Interiors",
    "wof:placetype":"venue"
},
  "geometry": {"coordinates":[-87.694428,42.037656],"type":"Point"}
}