{
  "type": "Feature",
  "properties": {
    "iso:country":"US",
    "sg:address":"2930 Meridian Rd",
    "sg:city":"Peru",
    "sg:classifiers":[
        {
            "category":"Organizations",
            "subcategory":"Religious Organization",
            "type":"Services"
        }
    ],
    "sg:phone":"+1 815 663 1478",
    "sg:postcode":"61354",
    "sg:province":"IL",
    "sg:tags":[
        "church"
    ],
    "wof:name":"Eagle Rock Christian Center",
    "wof:placetype":"venue"
},
  "geometry": {"coordinates":[-89.164344,41.355444],"type":"Point"}
}