{
  "type": "Feature",
  "properties": {
    "addr:full":"1099 Anchor Rd Dixon IL 61021",
    "addr:housenumber":"1099",
    "addr:postcode":"61021",
    "addr:street":"Anchor Rd",
    "iso:country":"US",
    "sg:address":"1099 Anchor Rd",
    "sg:city":"Dixon",
    "sg:classifiers":[
        {
            "category":"Food & Beverages",
            "subcategory":"Specialty",
            "type":"Retail Goods"
        }
    ],
    "sg:phone":"+1 815 288 7432",
    "sg:postcode":"61021",
    "sg:province":"IL",
    "sg:tags":[
        "health",
        "diet"
    ],
    "wof:name":"Power Store",
    "wof:placetype":"venue"
},
  "geometry": {"coordinates":[-89.460838,41.834825],"type":"Point"}
}