{
  "type": "Feature",
  "properties": {
    "addr:full":"26478 N East Lake Shore Dr Wauconda IL 60084",
    "addr:housenumber":"26478",
    "addr:postcode":"60084",
    "addr:street":"N East Lake Shore Dr",
    "iso:country":"US",
    "sg:address":"26478 N East Lake Shore Dr",
    "sg:city":"Wauconda",
    "sg:classifiers":[
        {
            "category":"Retail",
            "subcategory":"Repair Shop",
            "type":"Services"
        }
    ],
    "sg:phone":"+1 847 526 2323",
    "sg:postcode":"60084",
    "sg:province":"IL",
    "sg:tags":[
        "home",
        "appliance",
        "refrigerator"
    ],
    "wof:name":"S & S Home Appliance",
    "wof:placetype":"venue"
},
  "geometry": {"coordinates":[-88.129744,42.245232],"type":"Point"}
}