{
  "type": "Feature",
  "properties": {
    "iso:country":"US",
    "sg:address":"10 W. Chicago Ave.",
    "sg:city":"Oak Park",
    "sg:classifiers":[
        {
            "category":"Fast Food",
            "type":"Food & Drink"
        },
        {
            "category":"Restaurant",
            "type":"Food & Drink"
        }
    ],
    "sg:phone":"+1 708 660 9845",
    "sg:postcode":"60302",
    "sg:province":"IL",
    "sg:tags":[
        "chicken",
        "caribbean",
        "wing"
    ],
    "wof:name":"Jamaican Grill",
    "wof:placetype":"venue"
},
  "geometry": {"coordinates":[-87.77573099999999,41.894609],"type":"Point"}
}