{
  "type": "Feature",
  "properties": {
    "iso:country":"US",
    "sg:address":"1161 W Cullerton Street",
    "sg:city":"Chicago",
    "sg:classifiers":[
        {
            "category":"Shopping",
            "subcategory":"Music",
            "type":"Retail Goods"
        }
    ],
    "sg:phone":"+1 312 421 6819",
    "sg:postcode":"60608",
    "sg:province":"IL",
    "sg:tags":[
        "dvd's"
    ],
    "wof:name":"International Records",
    "wof:placetype":"venue"
},
  "geometry": {"coordinates":[-87.654758,41.855217],"type":"Point"}
}