{
  "type": "Feature",
  "properties": {
    "iso:country":"US",
    "sg:address":"251 S State St",
    "sg:city":"Hampshire",
    "sg:classifiers":[
        {
            "category":"Banks & Credit Unions",
            "subcategory":"Bank",
            "type":"Services"
        }
    ],
    "sg:phone":"+1 847 683 5430",
    "sg:postcode":"60140",
    "sg:province":"IL",
    "sg:website":"www.53.com",
    "wof:name":"Fifth Third Bank",
    "wof:placetype":"venue"
},
  "geometry": {"coordinates":[-88.53119700000001,42.0942],"type":"Point"}
}