{
  "type": "Feature",
  "properties": {
    "iso:country":"US",
    "sg:address":"5901 Sherman Ave",
    "sg:city":"Downers Grove",
    "sg:classifiers":[
        {
            "category":"Building & Trades",
            "subcategory":"Construction",
            "type":"Services"
        }
    ],
    "sg:phone":"+1 630 725 1016",
    "sg:postcode":"60516",
    "sg:province":"IL",
    "sg:tags":[
        "concrete",
        "contractor"
    ],
    "wof:name":"Quick Raising",
    "wof:placetype":"venue"
},
  "geometry": {"coordinates":[-88.029566,41.776266],"type":"Point"}
}