{
  "type": "Feature",
  "properties": {
    "iso:country":"US",
    "sg:address":"4842 F S Rd",
    "sg:city":"Shipman",
    "sg:classifiers":[
        {
            "category":"Farming",
            "subcategory":"Farm",
            "type":"Manufacturing & Wholesale Goods"
        }
    ],
    "sg:phone":"+1 618 836 7522",
    "sg:postcode":"62685",
    "sg:province":"IL",
    "sg:tags":[
        "crop",
        "general"
    ],
    "wof:name":"Loy Farms",
    "wof:placetype":"venue"
},
  "geometry": {"coordinates":[-90.057624,39.169399],"type":"Point"}
}