{
  "type": "Feature",
  "properties": {
    "addr:full":"12139 S Princeton Ave Chicago IL 60628",
    "addr:housenumber":"12139",
    "addr:postcode":"60628",
    "addr:street":"S Princeton Ave",
    "iso:country":"US",
    "sg:address":"12139 S Princeton Ave",
    "sg:city":"Chicago",
    "sg:classifiers":[
        {
            "category":"Building & Trades",
            "subcategory":"Pest Control",
            "type":"Services"
        }
    ],
    "sg:phone":"+1 773 264 3456",
    "sg:postcode":"60628",
    "sg:province":"IL",
    "wof:name":"Pamela Williams",
    "wof:placetype":"venue"
},
  "geometry": {"coordinates":[-87.62969699999999,41.672935],"type":"Point"}
}