{
  "type": "Feature",
  "properties": {
    "iso:country":"US",
    "sg:address":"1950 N US Hwy 45",
    "sg:city":"Libertyville",
    "sg:classifiers":[
        {
            "category":"Sports & Exercise",
            "subcategory":"Gym",
            "type":"Entertainment"
        }
    ],
    "sg:phone":"+1 847 367 1504",
    "sg:postcode":"60048",
    "sg:province":"IL",
    "sg:tags":[
        "facility",
        "club",
        "gymnasium",
        "health",
        "fitness",
        "studio",
        "physical"
    ],
    "wof:name":"Libertyville Fitness Center",
    "wof:placetype":"venue"
},
  "geometry": {"coordinates":[-88.00431500000001,42.297859],"type":"Point"}
}