{
  "type": "Feature",
  "properties": {
    "addr:full":"1630 5th St Lincoln IL 62656",
    "addr:housenumber":"1630",
    "addr:postcode":"62656",
    "addr:street":"5Th St",
    "iso:country":"US",
    "sg:address":"1630 5th St",
    "sg:city":"Lincoln",
    "sg:classifiers":[
        {
            "category":"Government",
            "subcategory":"Office",
            "type":"Public Place"
        }
    ],
    "sg:phone":"+1 217 735 4331",
    "sg:postcode":"62656",
    "sg:province":"IL",
    "sg:tags":[
        "federal",
        "planning",
        "dev"
    ],
    "wof:name":"USDA Rural Development",
    "wof:placetype":"venue"
},
  "geometry": {"coordinates":[-89.386841,40.146929],"type":"Point"}
}