{
  "type": "Feature",
  "properties": {
    "addr:full":"7235 N Western Ave Chicago IL 60645",
    "addr:housenumber":"7235",
    "addr:postcode":"60645",
    "addr:street":"N Western Ave",
    "iso:country":"US",
    "sg:address":"7235 N Western Ave",
    "sg:city":"Chicago",
    "sg:classifiers":[
        {
            "category":"Wholesale",
            "subcategory":"Office Equipment",
            "type":"Manufacturing & Wholesale Goods"
        }
    ],
    "sg:phone":"+1 773 262 4457",
    "sg:postcode":"60645",
    "sg:province":"IL",
    "sg:tags":[
        "machine",
        "accounting",
        "bookkeeping",
        "supply"
    ],
    "wof:name":"Accounting For Small Business",
    "wof:placetype":"venue"
},
  "geometry": {"coordinates":[-87.690247,42.01278],"type":"Point"}
}