{
  "type": "Feature",
  "properties": {
    "addr:full":"7725 159th Pl Tinley Park IL 60477",
    "addr:housenumber":"7725",
    "addr:postcode":"60477",
    "addr:street":"159Th Pl",
    "iso:country":"US",
    "sg:address":"7725 159th Pl",
    "sg:city":"Tinley Park",
    "sg:classifiers":[
        {
            "category":"Utilities",
            "subcategory":"Mobile Phone",
            "type":"Services"
        }
    ],
    "sg:phone":"+1 708 802 6400",
    "sg:postcode":"60477",
    "sg:province":"IL",
    "sg:tags":[
        "communication",
        "radiotelephone"
    ],
    "wof:name":"Activation Point Inc",
    "wof:placetype":"venue"
},
  "geometry": {"coordinates":[-87.80548899999999,41.600771],"type":"Point"}
}