{
  "type": "Feature",
  "properties": {
    "iso:country":"US",
    "sg:address":"10735 S Cicero Ave Ste 208",
    "sg:city":"Oak Lawn",
    "sg:classifiers":[
        {
            "category":"Health Services",
            "subcategory":"Clinic",
            "type":"Services"
        }
    ],
    "sg:phone":"+1 708 424 0001",
    "sg:postcode":"60453",
    "sg:province":"IL",
    "sg:tags":[
        "counseling",
        "mental"
    ],
    "sg:website":"www.CPStherapy.com",
    "wof:name":"Center For Psychological Services Ltd",
    "wof:placetype":"venue"
},
  "geometry": {"coordinates":[-87.739823,41.696959],"type":"Point"}
}