{
  "type": "Feature",
  "properties": {
    "addr:full":"163 Pinedale Dr Belleville IL 62226",
    "addr:housenumber":"163",
    "addr:postcode":"62226",
    "addr:street":"Pinedale Dr",
    "iso:country":"US",
    "sg:address":"163 Pinedale Dr",
    "sg:city":"Belleville",
    "sg:classifiers":[
        {
            "category":"Local Transit",
            "type":"Transportation"
        },
        {
            "category":"Professional",
            "subcategory":"Employment Agencies",
            "type":"Services"
        }
    ],
    "sg:phone":"+1 618 632 5300",
    "sg:postcode":"62226",
    "sg:province":"IL",
    "sg:tags":[
        "chauffeur",
        "passenger"
    ],
    "wof:name":"Washington Limousine Inc",
    "wof:placetype":"venue"
},
  "geometry": {"coordinates":[-89.990785,38.541986],"type":"Point"}
}