{
  "type": "Feature",
  "properties": {
    "iso:country":"US",
    "sg:address":"1851 Allen Dr",
    "sg:city":"Geneva",
    "sg:classifiers":[
        {
            "category":"Building & Trades",
            "subcategory":"Plumbing",
            "type":"Services"
        }
    ],
    "sg:phone":"+1 630 262 8312",
    "sg:postcode":"60134",
    "sg:province":"IL",
    "sg:tags":[
        "plumbing",
        "contractor"
    ],
    "wof:name":"Sullivan Plumbing",
    "wof:placetype":"venue"
},
  "geometry": {"coordinates":[-88.320763,41.86864],"type":"Point"}
}