{
  "type": "Feature",
  "properties": {
    "iso:country":"US",
    "sg:address":"6703 N Northwest Hwy",
    "sg:city":"Chicago",
    "sg:classifiers":[
        {
            "category":"Shopping",
            "subcategory":"Pharmacy",
            "type":"Retail Goods"
        }
    ],
    "sg:phone":"+1 773 774 6090",
    "sg:postcode":"60631",
    "sg:province":"IL",
    "sg:tags":[
        "drugstore"
    ],
    "wof:name":"Pll Llc",
    "wof:placetype":"venue"
},
  "geometry": {"coordinates":[-87.816093,42.002911],"type":"Point"}
}