{
  "type": "Feature",
  "properties": {
    "iso:country":"US",
    "sg:address":"1009 Totem Trl",
    "sg:city":"Mchenry",
    "sg:classifiers":[
        {
            "category":"Health Services",
            "subcategory":"Dentist",
            "type":"Services"
        }
    ],
    "sg:phone":"+1 815 385 1223",
    "sg:postcode":"60051",
    "sg:province":"IL",
    "sg:tags":[
        "equipment-repairing",
        "equipment",
        "dental",
        "refinishing",
        "supply"
    ],
    "sg:website":"http://www.gidental.com",
    "wof:name":"G & I Dental Precision Hand Piece Repair",
    "wof:placetype":"venue"
},
  "geometry": {"coordinates":[-88.25099299999999,42.315111],"type":"Point"}
}