{
  "type": "Feature",
  "properties": {
    "iso:country":"US",
    "sg:address":"3350 N Delaney Rd",
    "sg:city":"Waukegan",
    "sg:classifiers":[
        {
            "category":"Social Services",
            "subcategory":"Child Care",
            "type":"Services"
        }
    ],
    "sg:phone":"+1 847 625 1156",
    "sg:postcode":"60087",
    "sg:province":"IL",
    "wof:name":"Tomorrow's Future Preschool",
    "wof:placetype":"venue"
},
  "geometry": {"coordinates":[-87.904137,42.409493],"type":"Point"}
}