{
  "type": "Feature",
  "properties": {
    "iso:country":"US",
    "sg:address":"29515 136th Ave N",
    "sg:city":"Hillsdale",
    "sg:classifiers":[
        {
            "category":"Manufacturing",
            "subcategory":"Lumber",
            "type":"Manufacturing & Wholesale Goods"
        }
    ],
    "sg:phone":"+1 309 658 2267",
    "sg:postcode":"61257",
    "sg:province":"IL",
    "sg:tags":[
        "mill"
    ],
    "wof:name":"Steven A Battern",
    "wof:placetype":"venue"
},
  "geometry": {"coordinates":[-90.223326,41.657096],"type":"Point"}
}