{
  "type": "Feature",
  "properties": {
    "iso:country":"US",
    "sg:address":"888 W Eldorado St",
    "sg:city":"Decatur",
    "sg:classifiers":[
        {
            "category":"Home & Garden",
            "subcategory":"Household Appliances",
            "type":"Retail Goods"
        },
        {
            "category":"Utilities",
            "subcategory":"Water",
            "type":"Services"
        }
    ],
    "sg:phone":"+1 217 423 1464",
    "sg:postcode":"62522",
    "sg:province":"IL",
    "sg:tags":[
        "bulk",
        "major",
        "companies-bottled",
        "appliances-small"
    ],
    "wof:name":"Polar Products",
    "wof:placetype":"venue"
},
  "geometry": {"coordinates":[-88.967859,39.845587],"type":"Point"}
}