{
  "type": "Feature",
  "properties": {
    "iso:country":"US",
    "sg:address":"315 Greenfield Rd",
    "sg:city":"Joliet",
    "sg:classifiers":[
        {
            "category":"Restaurant",
            "type":"Food & Drink"
        }
    ],
    "sg:phone":"+1   ",
    "sg:postcode":"60404",
    "sg:province":"IL",
    "sg:tags":[
        "eating"
    ],
    "wof:name":"Mama Judy S Home Cookin Inc",
    "wof:placetype":"venue"
},
  "geometry": {"coordinates":[-90.170369,38.667781],"type":"Point"}
}