{
  "type": "Feature",
  "properties": {
    "iso:country":"US",
    "sg:address":"285 Industrial Dr",
    "sg:city":"Wauconda",
    "sg:classifiers":[
        {
            "category":"Wholesale",
            "subcategory":"Machinery & Supplies",
            "type":"Manufacturing & Wholesale Goods"
        }
    ],
    "sg:phone":"+1 847 487 9111",
    "sg:postcode":"60084",
    "sg:province":"IL",
    "sg:tags":[
        "bearing"
    ],
    "wof:name":"Fyh Bearing Units USA Inc",
    "wof:placetype":"venue"
},
  "geometry": {"coordinates":[-88.146809,42.281128],"type":"Point"}
}