{
  "type": "Feature",
  "properties": {
    "addr:full":"128 W Main St Carlinville IL 62626",
    "addr:housenumber":"128",
    "addr:postcode":"62626",
    "addr:street":"W Main St",
    "iso:country":"US",
    "sg:address":"128 W Main St",
    "sg:city":"Carlinville",
    "sg:classifiers":[
        {
            "category":"Insurance",
            "subcategory":"Hazard Insurance",
            "type":"Services"
        }
    ],
    "sg:phone":"+1 217 854 0045",
    "sg:postcode":"62626",
    "sg:province":"IL",
    "sg:tags":[
        "commercial",
        "business"
    ],
    "wof:name":"American Family Insurance",
    "wof:placetype":"venue"
},
  "geometry": {"coordinates":[-89.88090099999999,39.279756],"type":"Point"}
}