{
  "type": "Feature",
  "properties": {
    "addr:full":"810 W Main St West Dundee IL 60118",
    "addr:housenumber":"810",
    "addr:postcode":"60118",
    "addr:street":"W Main St",
    "iso:country":"US",
    "sg:address":"810 W Main St",
    "sg:city":"West Dundee",
    "sg:classifiers":[
        {
            "category":"Retail",
            "subcategory":"Portrait Studio",
            "type":"Services"
        },
        {
            "category":"Shopping",
            "subcategory":"Pharmacy",
            "type":"Retail Goods"
        }
    ],
    "sg:phone":"+1 847 426 1773",
    "sg:postcode":"60118",
    "sg:province":"IL",
    "sg:tags":[
        "photography",
        "drugstore",
        "store"
    ],
    "sg:website":"www.walgreens.com",
    "wof:name":"Walgreen Drug Stores",
    "wof:placetype":"venue"
},
  "geometry": {"coordinates":[-88.287003,42.098301],"type":"Point"}
}