{
  "type": "Feature",
  "properties": {
    "addr:full":"620 Central Ave Highland Park IL 60035",
    "addr:housenumber":"620",
    "addr:postcode":"60035",
    "addr:street":"Central Ave",
    "iso:country":"US",
    "sg:address":"620 Central Ave",
    "sg:city":"Highland Park",
    "sg:classifiers":[
        {
            "category":"Bakery",
            "type":"Food & Drink"
        }
    ],
    "sg:menulink":"http://www.allmenus.com/il/moraine/115472-the-original-pancake-house/menu/",
    "sg:phone":"+1 847 432 0660",
    "sg:postcode":"60035",
    "sg:province":"IL",
    "sg:tags":[
        "american",
        "pastry",
        "diner"
    ],
    "wof:name":"The Original Pancake House",
    "wof:placetype":"venue"
},
  "geometry": {"coordinates":[-87.800668,42.185085],"type":"Point"}
}