{
  "type": "Feature",
  "properties": {
    "iso:country":"US",
    "sg:address":"427 W Clinton St",
    "sg:city":"Rushville",
    "sg:classifiers":[
        {
            "category":"Home & Garden",
            "subcategory":"Building Materials",
            "type":"Retail Goods"
        }
    ],
    "sg:phone":"+1 217 322 3133",
    "sg:postcode":"62681",
    "sg:province":"IL",
    "sg:tags":[
        "glass",
        "window",
        "plate"
    ],
    "wof:name":"Glass Specialty Co",
    "wof:placetype":"venue"
},
  "geometry": {"coordinates":[-90.567482,40.117738],"type":"Point"}
}