{
  "type": "Feature",
  "properties": {
    "iso:country":"US",
    "sg:address":"1609 Chicago Ave",
    "sg:city":"Evanston",
    "sg:classifiers":[
        {
            "category":"Professional",
            "subcategory":"Employment Agencies",
            "type":"Services"
        }
    ],
    "sg:phone":"+1 847 570 7804",
    "sg:postcode":"60201",
    "sg:province":"IL",
    "sg:tags":[
        "help",
        "supply"
    ],
    "wof:name":"Irmco Equipment Supply",
    "wof:placetype":"venue"
},
  "geometry": {"coordinates":[-87.678887,42.047593],"type":"Point"}
}