{
  "type": "Feature",
  "properties": {
    "addr:full":"7501 W 103rd St Palos Hills IL 60465",
    "addr:housenumber":"7501",
    "addr:postcode":"60465",
    "addr:street":"W 103Rd St",
    "iso:country":"US",
    "sg:address":"7501 W 103rd St",
    "sg:city":"Palos Hills",
    "sg:classifiers":[
        {
            "category":"Building & Trades",
            "subcategory":"Construction",
            "type":"Services"
        }
    ],
    "sg:phone":"+1 708 237 0600",
    "sg:postcode":"60465",
    "sg:province":"IL",
    "sg:tags":[
        "home",
        "builder"
    ],
    "wof:name":"Concord Homes",
    "wof:placetype":"venue"
},
  "geometry": {"coordinates":[-87.80665999999999,41.704236],"type":"Point"}
}