{
  "type": "Feature",
  "properties": {
    "iso:country":"US",
    "sg:address":"2223 N Sawyer Avenue",
    "sg:city":"Chicago",
    "sg:classifiers":[
        {
            "category":"Animal Shelter",
            "type":"Public Place"
        },
        {
            "category":"Shopping",
            "subcategory":"Pets & Pet Supplies",
            "type":"Retail Goods"
        }
    ],
    "sg:phone":"+1 773 486 9548",
    "sg:postcode":"60647",
    "sg:province":"IL",
    "sg:tags":[
        "store"
    ],
    "wof:name":"Shelter Alternatives Network",
    "wof:placetype":"venue"
},
  "geometry": {"coordinates":[-87.70902,41.921449],"type":"Point"}
}