{
  "type": "Feature",
  "properties": {
    "iso:country":"US",
    "sg:address":"8404 Gross Point Rd",
    "sg:city":"Skokie",
    "sg:classifiers":[
        {
            "category":"Retail",
            "subcategory":"Laundry & Dry Cleaning",
            "type":"Services"
        }
    ],
    "sg:phone":"+1   ",
    "sg:postcode":"60077",
    "sg:province":"IL",
    "wof:name":"Gross Point Tailor Shop",
    "wof:placetype":"venue"
},
  "geometry": {"coordinates":[-87.76194,42.033637],"type":"Point"}
}