{
  "type": "Feature",
  "properties": {
    "addr:full":"105 W Rockland Rd Libertyville IL 60048",
    "addr:housenumber":"105",
    "addr:postcode":"60048",
    "addr:street":"W Rockland Rd",
    "iso:country":"US",
    "sg:address":"105 W Rockland Rd",
    "sg:city":"Libertyville",
    "sg:classifiers":[
        {
            "category":"Shopping",
            "subcategory":"Books",
            "type":"Retail Goods"
        }
    ],
    "sg:phone":"+1 847 680 0727",
    "sg:postcode":"60048",
    "sg:province":"IL",
    "sg:tags":[
        "comic"
    ],
    "wof:name":"Dreamland Comics II",
    "wof:placetype":"venue"
},
  "geometry": {"coordinates":[-87.952421,42.277973],"type":"Point"}
}