{
  "type": "Feature",
  "properties": {
    "iso:country":"US",
    "sg:address":"2701 S Pulaski Rd",
    "sg:city":"Chicago",
    "sg:classifiers":[
        {
            "category":"Personal",
            "subcategory":"Beauty Salon",
            "type":"Services"
        },
        {
            "category":"Personal",
            "subcategory":"Barber",
            "type":"Services"
        }
    ],
    "sg:phone":"+1 773 277 0490",
    "sg:postcode":"60623",
    "sg:province":"IL",
    "wof:name":"Victor Barber Shop & Beauty",
    "wof:placetype":"venue"
},
  "geometry": {"coordinates":[-87.724503,41.842411],"type":"Point"}
}