{
  "type": "Feature",
  "properties": {
    "iso:country":"US",
    "sg:address":"4270 W 82nd Pl",
    "sg:city":"Chicago",
    "sg:classifiers":[
        {
            "category":"Building & Trades",
            "subcategory":"Construction",
            "type":"Services"
        }
    ],
    "sg:phone":"+1 773 284 0268",
    "sg:postcode":"60652",
    "sg:province":"IL",
    "sg:tags":[
        "concrete",
        "contractor"
    ],
    "wof:name":"Concrete Frazier",
    "wof:placetype":"venue"
},
  "geometry": {"coordinates":[-87.72893500000001,41.742865],"type":"Point"}
}