{
  "type": "Feature",
  "properties": {
    "iso:country":"US",
    "sg:address":"803 N Oak Park Ave",
    "sg:city":"Oak Park",
    "sg:classifiers":[
        {
            "category":"Health Services",
            "subcategory":"Clinic",
            "type":"Services"
        }
    ],
    "sg:phone":"+1 708 445 9046",
    "sg:postcode":"60302",
    "sg:province":"IL",
    "sg:tags":[
        "counseling",
        "mental"
    ],
    "wof:name":"Mejta Cheryl L Psycholgst",
    "wof:placetype":"venue"
},
  "geometry": {"coordinates":[-87.7948,41.899899],"type":"Point"}
}