{
  "type": "Feature",
  "properties": {
    "iso:country":"US",
    "sg:address":"4720 Wallbank Ave",
    "sg:city":"Downers Grove",
    "sg:classifiers":[
        {
            "category":"Professional",
            "subcategory":"Art Services",
            "type":"Services"
        }
    ],
    "sg:phone":"+1 630 969 2199",
    "sg:postcode":"60515",
    "sg:province":"IL",
    "sg:tags":[
        "graphic",
        "printing",
        "specialty"
    ],
    "wof:name":"Go Graphic Inc",
    "wof:placetype":"venue"
},
  "geometry": {"coordinates":[-88.022903,41.800141],"type":"Point"}
}