{
  "type": "Feature",
  "properties": {
    "addr:full":"4951 W Sunnyside Ave Chicago IL 60630",
    "addr:housenumber":"4951",
    "addr:postcode":"60630",
    "addr:street":"W Sunnyside Ave",
    "iso:country":"US",
    "sg:address":"4951 W Sunnyside Ave",
    "sg:city":"Chicago",
    "sg:classifiers":[
        {
            "category":"Building & Trades",
            "subcategory":"Construction",
            "type":"Services"
        }
    ],
    "sg:phone":"+1 773 777 0752",
    "sg:postcode":"60630",
    "sg:province":"IL",
    "sg:tags":[
        "mason",
        "masonry",
        "industrial",
        "contractors-commercial",
        "contractor"
    ],
    "wof:name":"Ziggy's Elite Contracting, Inc.",
    "wof:placetype":"venue"
},
  "geometry": {"coordinates":[-87.751609,41.962487],"type":"Point"}
}