{
  "type": "Feature",
  "properties": {
    "iso:country":"US",
    "sg:address":"216 W Railroad St",
    "sg:city":"Lena",
    "sg:classifiers":[
        {
            "category":"Autos & Motor Vehicles",
            "subcategory":"Auto Supplies",
            "type":"Retail Goods"
        },
        {
            "category":"Manufacturing",
            "subcategory":"Motor Vehicles & Parts",
            "type":"Manufacturing & Wholesale Goods"
        },
        {
            "category":"Retail",
            "subcategory":"Auto Repair",
            "type":"Services"
        }
    ],
    "sg:phone":"+1 815 369 9747",
    "sg:postcode":"61048",
    "sg:province":"IL",
    "sg:tags":[
        "body",
        "shop",
        "buses-distributors",
        "automobile",
        "removal",
        "buses-parts",
        "equipment",
        "parts",
        "accessories-wholesale",
        "dent",
        "painting",
        "repairing",
        "manufacturer"
    ],
    "wof:name":"Checkered Flag Auto Body",
    "wof:placetype":"venue"
},
  "geometry": {"coordinates":[-89.824432,42.37923],"type":"Point"}
}