{
  "type": "Feature",
  "properties": {
    "iso:country":"US",
    "sg:address":"9425 S 68th Ct",
    "sg:city":"Oak Lawn",
    "sg:classifiers":[
        {
            "category":"Education",
            "subcategory":"Special Training",
            "type":"Public Place"
        }
    ],
    "sg:phone":"+1 708 430 1991",
    "sg:postcode":"60453",
    "sg:province":"IL",
    "wof:name":"Quranic Literacy Institute",
    "wof:placetype":"venue"
},
  "geometry": {"coordinates":[-87.790707,41.719615],"type":"Point"}
}