{
  "type": "Feature",
  "properties": {
    "iso:country":"US",
    "sg:address":"7639 174th St",
    "sg:city":"Tinley Park",
    "sg:classifiers":[
        {
            "category":"Professional",
            "subcategory":"Accounting & Tax Preparation",
            "type":"Services"
        }
    ],
    "sg:phone":"+1 708 429 0569",
    "sg:postcode":"60477",
    "sg:province":"IL",
    "wof:name":"Tinsman Accounting",
    "wof:placetype":"venue"
},
  "geometry": {"coordinates":[-87.803223,41.573515],"type":"Point"}
}