{
  "type": "Feature",
  "properties": {
    "addr:full":"651 N Milwaukee Avenue Chicago IL 60622",
    "addr:housenumber":"651",
    "addr:postcode":"60622",
    "addr:street":"N Milwaukee Avenue",
    "iso:country":"US",
    "sg:address":"651 N Milwaukee Avenue",
    "sg:city":"Chicago",
    "sg:classifiers":[
        {
            "category":"Retail",
            "subcategory":"Laundry & Dry Cleaning",
            "type":"Services"
        }
    ],
    "sg:phone":"+1 312 633 9960",
    "sg:postcode":"60622",
    "sg:province":"IL",
    "wof:name":"Viva Cleaning & Shirt Laundry",
    "wof:placetype":"venue"
},
  "geometry": {"coordinates":[-87.65104599999999,41.893425],"type":"Point"}
}