{
  "type": "Feature",
  "properties": {
    "iso:country":"US",
    "sg:address":"3047 N Lincoln Ave",
    "sg:city":"Chicago",
    "sg:classifiers":[
        {
            "category":"Real Estate",
            "subcategory":"Developer",
            "type":"Services"
        }
    ],
    "sg:phone":"+1 773 883 1762",
    "sg:postcode":"60657",
    "sg:province":"IL",
    "sg:tags":[
        "development"
    ],
    "wof:name":"Tandem Realty Corp",
    "wof:placetype":"venue"
},
  "geometry": {"coordinates":[-87.66513,41.937111],"type":"Point"}
}