{
  "type": "Feature",
  "properties": {
    "iso:country":"US",
    "sg:address":"6435 S Maryland Ave",
    "sg:city":"Chicago",
    "sg:classifiers":[
        {
            "category":"Sports & Exercise",
            "subcategory":"Sports Center",
            "type":"Entertainment"
        }
    ],
    "sg:phone":"+1 773 684 6518",
    "sg:postcode":"60637",
    "sg:province":"IL",
    "wof:name":"64 Pl Dead Block Club",
    "wof:placetype":"venue"
},
  "geometry": {"coordinates":[-87.604646,41.777941],"type":"Point"}
}