{
  "type": "Feature",
  "properties": {
    "iso:country":"US",
    "sg:address":"325 S Schmale Rd",
    "sg:city":"Carol Stream",
    "sg:classifiers":[
        {
            "category":"Restaurant",
            "type":"Food & Drink"
        }
    ],
    "sg:phone":"+1 630 462 0660",
    "sg:postcode":"60188",
    "sg:province":"IL",
    "sg:tags":[
        "pizza"
    ],
    "wof:name":"Amigos Pizza & Taco",
    "wof:placetype":"venue"
},
  "geometry": {"coordinates":[-88.101997,41.895802],"type":"Point"}
}