{
  "type": "Feature",
  "properties": {
    "addr:full":"10001 S Pulaski Road Chicago IL 60655",
    "addr:housenumber":"10001",
    "addr:postcode":"60655",
    "addr:street":"S Pulaski Road",
    "iso:country":"US",
    "sg:address":"10001 S Pulaski Road",
    "sg:city":"Chicago",
    "sg:classifiers":[
        {
            "category":"Education",
            "subcategory":"School",
            "type":"Public Place"
        }
    ],
    "sg:phone":"+1 773 429 4300",
    "sg:postcode":"60655",
    "sg:province":"IL",
    "wof:name":"Brother Rice High School",
    "wof:placetype":"venue"
},
  "geometry": {"coordinates":[-87.72081,41.710906],"type":"Point"}
}