{
  "type": "Feature",
  "properties": {
    "addr:full":"30 N Michigan Ave Lbby Chicago IL 60602",
    "addr:housenumber":"30",
    "addr:postcode":"60602",
    "addr:street":"N Michigan Ave",
    "iso:country":"US",
    "sg:address":"30 N Michigan Ave Lbby",
    "sg:city":"Chicago",
    "sg:classifiers":[
        {
            "category":"Health Services",
            "subcategory":"Doctor",
            "type":"Services"
        }
    ],
    "sg:phone":"+1 312 920 0426",
    "sg:postcode":"60602",
    "sg:province":"IL",
    "wof:name":"Kreiner Karen MD",
    "wof:placetype":"venue"
},
  "geometry": {"coordinates":[-87.62449599999999,41.882401],"type":"Point"}
}