{
  "type": "Feature",
  "properties": {
    "iso:country":"US",
    "sg:address":"113 Claret Knoll Ave",
    "sg:city":"Oglesby",
    "sg:classifiers":[
        {
            "category":"Professional",
            "subcategory":"Business Services",
            "type":"Services"
        }
    ],
    "sg:phone":"+1 815 663 3007",
    "sg:postcode":"61348",
    "sg:province":"IL",
    "wof:name":"House Dressing",
    "wof:placetype":"venue"
},
  "geometry": {"coordinates":[-89.103245,41.2947],"type":"Point"}
}