{
  "type": "Feature",
  "properties": {
    "iso:country":"US",
    "sg:address":"122 E Broadway",
    "sg:city":"Alton",
    "sg:classifiers":[
        {
            "category":"Restaurant",
            "type":"Food & Drink"
        }
    ],
    "sg:menulink":"http://www.allmenus.com/il/alton/102650-gentelins-on-broadway/menu/",
    "sg:phone":"+1 618 465 6080",
    "sg:postcode":"62002",
    "sg:province":"IL",
    "sg:tags":[
        "seafood",
        "american"
    ],
    "wof:name":"Gentelin's On Broadway",
    "wof:placetype":"venue"
},
  "geometry": {"coordinates":[-90.184071,38.890078],"type":"Point"}
}