{
  "type": "Feature",
  "properties": {
    "addr:full":"1335 W Harrison Street Chicago IL 60607",
    "addr:housenumber":"1335",
    "addr:postcode":"60607",
    "addr:street":"W Harrison Street",
    "iso:country":"US",
    "sg:address":"1335 W Harrison Street",
    "sg:city":"Chicago",
    "sg:classifiers":[
        {
            "category":"Place Of Worship",
            "subcategory":"Church",
            "type":"Public Place"
        }
    ],
    "sg:phone":"+1 312 243 7400",
    "sg:postcode":"60607",
    "sg:province":"IL",
    "wof:name":"Notre Dame De Chicago Church",
    "wof:placetype":"venue"
},
  "geometry": {"coordinates":[-87.66065399999999,41.874284],"type":"Point"}
}