{
  "type": "Feature",
  "properties": {
    "addr:full":"401 S Cicero Ave Chicago IL 60644",
    "addr:housenumber":"401",
    "addr:postcode":"60644",
    "addr:street":"S Cicero Ave",
    "iso:country":"US",
    "sg:address":"401 S Cicero Ave",
    "sg:city":"Chicago",
    "sg:classifiers":[
        {
            "category":"Food & Beverages",
            "subcategory":"Specialty",
            "type":"Retail Goods"
        },
        {
            "category":"Food & Beverages",
            "subcategory":"Supermarket",
            "type":"Retail Goods"
        },
        {
            "category":"Food & Beverages",
            "subcategory":"Groceries & Convenience Stores",
            "type":"Retail Goods"
        }
    ],
    "sg:phone":"+1 773 287 4725",
    "sg:postcode":"60644",
    "sg:province":"IL",
    "sg:tags":[
        "super",
        "grocers-specialty"
    ],
    "wof:name":"Tofi Food Market",
    "wof:placetype":"venue"
},
  "geometry": {"coordinates":[-87.745071,41.875011],"type":"Point"}
}