{
  "type": "Feature",
  "properties": {
    "addr:full":"105 Lanaghan Dr Fairview Heights IL 62208",
    "addr:housenumber":"105",
    "addr:postcode":"62208",
    "addr:street":"Lanaghan Dr",
    "iso:country":"US",
    "sg:address":"105 Lanaghan Dr",
    "sg:city":"Fairview Heights",
    "sg:classifiers":[
        {
            "category":"Building & Trades",
            "subcategory":"Construction",
            "type":"Services"
        }
    ],
    "sg:phone":"+1 618 394 9720",
    "sg:postcode":"62208",
    "sg:province":"IL",
    "sg:tags":[
        "carpentry",
        "contractor"
    ],
    "wof:name":"Markus Cabinet",
    "wof:placetype":"venue"
},
  "geometry": {"coordinates":[-89.987348,38.592642],"type":"Point"}
}