{
  "type": "Feature",
  "properties": {
    "addr:full":"700 Ruby St Joliet IL 60435",
    "addr:housenumber":"700",
    "addr:postcode":"60435",
    "addr:street":"Ruby St",
    "iso:country":"US",
    "sg:address":"700 Ruby St",
    "sg:city":"Joliet",
    "sg:classifiers":[
        {
            "category":"Restaurant",
            "type":"Food & Drink"
        }
    ],
    "sg:phone":"+1   ",
    "sg:postcode":"60435",
    "sg:province":"IL",
    "sg:tags":[
        "shop",
        "eating",
        "gift"
    ],
    "wof:name":"Corner Cafe",
    "wof:placetype":"venue"
},
  "geometry": {"coordinates":[-88.100145,41.53778],"type":"Point"}
}