{
  "type": "Feature",
  "properties": {
    "iso:country":"US",
    "sg:address":"4415 Dunbar Pl",
    "sg:city":"Rockford",
    "sg:classifiers":[
        {
            "category":"Building & Trades",
            "subcategory":"Construction",
            "type":"Services"
        }
    ],
    "sg:phone":"+1 815 633 5030",
    "sg:postcode":"61114",
    "sg:province":"IL",
    "sg:tags":[
        "painter"
    ],
    "wof:name":"Elizabeth's Painting Svc",
    "wof:placetype":"venue"
},
  "geometry": {"coordinates":[-89.03049799999999,42.301313],"type":"Point"}
}