{
  "type": "Feature",
  "properties": {
    "iso:country":"US",
    "sg:address":"1415 Ellinwood Ave",
    "sg:city":"Des Plaines",
    "sg:classifiers":[
        {
            "category":"Recreation",
            "type":"Entertainment"
        }
    ],
    "sg:phone":"+1 847 827 4343",
    "sg:postcode":"60016",
    "sg:province":"IL",
    "sg:tags":[
        "martial",
        "arts",
        "instruction"
    ],
    "wof:name":"Chicago Mudo Center",
    "wof:placetype":"venue"
},
  "geometry": {"coordinates":[-87.888486,42.041257],"type":"Point"}
}