{
  "type": "Feature",
  "properties": {
    "iso:country":"US",
    "sg:address":"3941 Pintail Dr",
    "sg:city":"Springfield",
    "sg:classifiers":[
        {
            "category":"Autos & Motor Vehicles",
            "subcategory":"Auto Supplies",
            "type":"Retail Goods"
        }
    ],
    "sg:phone":"+1 217 546 0008",
    "sg:postcode":"62711",
    "sg:province":"IL",
    "sg:tags":[
        "automobile",
        "accessory"
    ],
    "wof:name":"Pups 14",
    "wof:placetype":"venue"
},
  "geometry": {"coordinates":[-89.712864,39.742986],"type":"Point"}
}