{
  "type": "Feature",
  "properties": {
    "iso:country":"US",
    "sg:address":"2311 W North Ave",
    "sg:city":"Chicago",
    "sg:classifiers":[
        {
            "category":"Restaurant",
            "type":"Food & Drink"
        }
    ],
    "sg:menulink":"http://www.allmenus.com/il/chicago/272857-the-handlebar/menu/",
    "sg:phone":"+1 773 384 9546",
    "sg:postcode":"60647",
    "sg:province":"IL",
    "sg:tags":[
        "american",
        "vegetarian"
    ],
    "wof:name":"The Handlebar",
    "wof:placetype":"venue"
},
  "geometry": {"coordinates":[-87.68526300000001,41.910202],"type":"Point"}
}