{
  "type": "Feature",
  "properties": {
    "addr:full":"3925 W Eddy St Chicago IL 60618",
    "addr:housenumber":"3925",
    "addr:postcode":"60618",
    "addr:street":"W Eddy St",
    "iso:country":"US",
    "sg:address":"3925 W Eddy St",
    "sg:city":"Chicago",
    "sg:classifiers":[
        {
            "category":"Professional",
            "subcategory":"Computer Services",
            "type":"Services"
        }
    ],
    "sg:phone":"+1 773 209 1255",
    "sg:postcode":"60618",
    "sg:province":"IL",
    "sg:tags":[
        "repair"
    ],
    "wof:name":"TekFix Computers",
    "wof:placetype":"venue"
},
  "geometry": {"coordinates":[-87.72595699999999,41.945226],"type":"Point"}
}