{
  "type": "Feature",
  "properties": {
    "iso:country":"US",
    "sg:address":"9132 31st St",
    "sg:city":"Brookfield",
    "sg:classifiers":[
        {
            "category":"Restaurant",
            "type":"Food & Drink"
        }
    ],
    "sg:phone":"+1 708 387 7955",
    "sg:postcode":"60513",
    "sg:province":"IL",
    "sg:tags":[
        "breakfast",
        "style",
        "brunch",
        "family"
    ],
    "wof:name":"Nick's Breakfast House",
    "wof:placetype":"venue"
},
  "geometry": {"coordinates":[-87.85071600000001,41.835025],"type":"Point"}
}