{
  "type": "Feature",
  "properties": {
    "addr:full":"6050 Lake Bluff Dr Tinley Park IL 60477",
    "addr:housenumber":"6050",
    "addr:postcode":"60477",
    "addr:street":"Lake Bluff Dr",
    "iso:country":"US",
    "sg:address":"6050 Lake Bluff Dr",
    "sg:city":"Tinley Park",
    "sg:classifiers":[
        {
            "category":"Social Services",
            "subcategory":"Job Training",
            "type":"Services"
        }
    ],
    "sg:phone":"+1 708 444 0035",
    "sg:postcode":"60477",
    "sg:province":"IL",
    "sg:tags":[
        "community"
    ],
    "wof:name":"Drc",
    "wof:placetype":"venue"
},
  "geometry": {"coordinates":[-87.76315,41.585288],"type":"Point"}
}