{
  "type": "Feature",
  "properties": {
    "iso:country":"US",
    "sg:address":"2222 Commonwealth Ave",
    "sg:city":"North Chicago",
    "sg:classifiers":[
        {
            "category":"Manufacturing",
            "subcategory":"Metals",
            "type":"Manufacturing & Wholesale Goods"
        }
    ],
    "sg:phone":"+1 847 473 3600",
    "sg:postcode":"60064",
    "sg:province":"IL",
    "sg:tags":[
        "repair",
        "metalwork",
        "sheet",
        "mfg",
        "stampings",
        "welding"
    ],
    "wof:name":"Adler-Norco Inc",
    "wof:placetype":"venue"
},
  "geometry": {"coordinates":[-87.84669,42.316893],"type":"Point"}
}