{
  "type": "Feature",
  "properties": {
    "iso:country":"US",
    "sg:address":"1412 W Fayette Ave",
    "sg:city":"Effingham",
    "sg:classifiers":[
        {
            "category":"Travel",
            "subcategory":"Hotels & Motels",
            "type":"Entertainment"
        }
    ],
    "sg:phone":"+1 217 342 3921",
    "sg:postcode":"62401",
    "sg:province":"IL",
    "wof:name":"Days Inn",
    "wof:placetype":"venue"
},
  "geometry": {"coordinates":[-88.56161400000001,39.120512],"type":"Point"}
}