{
  "type": "Feature",
  "properties": {
    "iso:country":"US",
    "sg:address":"1020 Williams St",
    "sg:city":"Barry",
    "sg:phone":"+1 217 335 2719",
    "sg:postcode":"62312",
    "sg:province":"IL",
    "sg:tags":[
        "farm"
    ],
    "wof:name":"E & R Farms",
    "wof:placetype":"venue"
},
  "geometry": {"coordinates":[-91.03721,39.695324],"type":"Point"}
}