{
  "type": "Feature",
  "properties": {
    "iso:country":"US",
    "sg:address":"809 Indiana Ave",
    "sg:city":"Collinsville",
    "sg:classifiers":[
        {
            "category":"Social Services",
            "subcategory":"Child Care",
            "type":"Services"
        }
    ],
    "sg:phone":"+1 618 344 5690",
    "sg:postcode":"62234",
    "sg:province":"IL",
    "wof:name":"Bonnie Durham",
    "wof:placetype":"venue"
},
  "geometry": {"coordinates":[-89.970832,38.68581],"type":"Point"}
}