{
  "type": "Feature",
  "properties": {
    "addr:full":"483 S Blackjack Rd Galena IL 61036",
    "addr:housenumber":"483",
    "addr:postcode":"61036",
    "addr:street":"S Blackjack Rd",
    "iso:country":"US",
    "sg:address":"483 S Blackjack Rd",
    "sg:city":"Galena",
    "sg:classifiers":[
        {
            "category":"Building & Trades",
            "subcategory":"Plumbing",
            "type":"Services"
        }
    ],
    "sg:phone":"+1 815 777 6202",
    "sg:postcode":"61036",
    "sg:province":"IL",
    "sg:tags":[
        "air",
        "heating",
        "contractor",
        "system",
        "conditioning"
    ],
    "wof:name":"Moore & Son Heating and AC",
    "wof:placetype":"venue"
},
  "geometry": {"coordinates":[-90.4027,42.364515],"type":"Point"}
}