{
  "type": "Feature",
  "properties": {
    "iso:country":"US",
    "sg:address":"310 7th St",
    "sg:city":"Rockford",
    "sg:classifiers":[
        {
            "category":"Organizations",
            "subcategory":"Non-profit Organization",
            "type":"Services"
        },
        {
            "category":"Social Services",
            "type":"Services"
        }
    ],
    "sg:phone":"+1 815 962 6754",
    "sg:postcode":"61104",
    "sg:province":"IL",
    "sg:tags":[
        "welfare"
    ],
    "wof:name":"Love Inc of Greater Rockford",
    "wof:placetype":"venue"
},
  "geometry": {"coordinates":[-89.080725,42.263823],"type":"Point"}
}