{
  "type": "Feature",
  "properties": {
    "addr:full":"7501 Lemont Rd Woodridge IL 60517",
    "addr:housenumber":"7501",
    "addr:postcode":"60517",
    "addr:street":"Lemont Rd",
    "iso:country":"US",
    "sg:address":"7501 Lemont Rd",
    "sg:city":"Woodridge",
    "sg:classifiers":[
        {
            "category":"Banks & Credit Unions",
            "subcategory":"Bank",
            "type":"Services"
        }
    ],
    "sg:phone":"+1 630 985 1000",
    "sg:postcode":"60517",
    "sg:province":"IL",
    "wof:name":"Bank One",
    "wof:placetype":"venue"
},
  "geometry": {"coordinates":[-88.012653,41.749693],"type":"Point"}
}