{
  "type": "Feature",
  "properties": {
    "addr:full":"175 E Hawthorn Pkwy Vernon Hills IL 60061",
    "addr:housenumber":"175",
    "addr:postcode":"60061",
    "addr:street":"E Hawthorn Pkwy",
    "iso:country":"US",
    "sg:address":"175 E Hawthorn Pkwy",
    "sg:city":"Vernon Hills",
    "sg:classifiers":[
        {
            "category":"Professional",
            "subcategory":"Accounting & Tax Preparation",
            "type":"Services"
        }
    ],
    "sg:phone":"+1 847 680 3804",
    "sg:postcode":"60061",
    "sg:province":"IL",
    "sg:tags":[
        "accountant"
    ],
    "wof:name":"Geib & Co",
    "wof:placetype":"venue"
},
  "geometry": {"coordinates":[-87.961423,42.241629],"type":"Point"}
}