{
  "type": "Feature",
  "properties": {
    "addr:full":"3601 S. Halsted St Chicago IL 60616",
    "addr:housenumber":"3601",
    "addr:postcode":"60616",
    "addr:street":"S. Halsted St",
    "iso:country":"US",
    "sg:address":"3601 S. Halsted St",
    "sg:city":"Chicago",
    "sg:classifiers":[
        {
            "category":"Professional",
            "type":"Services"
        }
    ],
    "sg:phone":"+1 773 523 0315",
    "sg:postcode":"60616",
    "sg:province":"IL",
    "sg:website":"www.wokmaker.com",
    "wof:name":"C&R Restaurant Equipment Supply",
    "wof:placetype":"venue"
},
  "geometry": {"coordinates":[-87.645696,41.828637],"type":"Point"}
}