{
  "type": "Feature",
  "properties": {
    "iso:country":"US",
    "sg:address":"1309 Mill St",
    "sg:city":"Rock Island",
    "sg:classifiers":[
        {
            "category":"Government",
            "subcategory":"Office",
            "type":"Public Place"
        }
    ],
    "sg:phone":"+1 309 788 4380",
    "sg:postcode":"61201",
    "sg:province":"IL",
    "sg:tags":[
        "village"
    ],
    "wof:name":"Rock Island Bridge Maintenance",
    "wof:placetype":"venue"
},
  "geometry": {"coordinates":[-90.59737199999999,41.494283],"type":"Point"}
}