{
  "type": "Feature",
  "properties": {
    "addr:full":"1643 E 87th Street Chicago IL 60617",
    "addr:housenumber":"1643",
    "addr:postcode":"60617",
    "addr:street":"E 87Th Street",
    "iso:country":"US",
    "sg:address":"1643 E 87th Street",
    "sg:city":"Chicago",
    "sg:classifiers":[
        {
            "category":"Shopping",
            "subcategory":"Crafts & Fabrics",
            "type":"Retail Goods"
        }
    ],
    "sg:phone":"+1 773 768 3003",
    "sg:postcode":"60617",
    "sg:province":"IL",
    "sg:tags":[
        "store"
    ],
    "wof:name":"Kayra Imports",
    "wof:placetype":"venue"
},
  "geometry": {"coordinates":[-87.583623,41.73706],"type":"Point"}
}