{
  "type": "Feature",
  "properties": {
    "iso:country":"US",
    "sg:address":"508 W 46th Pl",
    "sg:city":"Chicago",
    "sg:classifiers":[
        {
            "category":"Building & Trades",
            "subcategory":"Landscaping Services",
            "type":"Services"
        }
    ],
    "sg:phone":"+1 773 548 0900",
    "sg:postcode":"60609",
    "sg:province":"IL",
    "sg:tags":[
        "landscape",
        "contractor"
    ],
    "wof:name":"Perfect Lawns Co, Inc",
    "wof:placetype":"venue"
},
  "geometry": {"coordinates":[-87.638452,41.809907],"type":"Point"}
}