{
  "type": "Feature",
  "properties": {
    "addr:full":"500 W Indiana Ave Beecher IL 60401",
    "addr:housenumber":"500",
    "addr:postcode":"60401",
    "addr:street":"W Indiana Ave",
    "iso:country":"US",
    "sg:address":"500 W Indiana Ave",
    "sg:city":"Beecher",
    "sg:classifiers":[
        {
            "category":"Personal",
            "subcategory":"Tanning Parlor",
            "type":"Services"
        }
    ],
    "sg:phone":"+1 708 946 9822",
    "sg:postcode":"60401",
    "sg:province":"IL",
    "sg:tags":[
        "salon"
    ],
    "wof:name":"Offshore Tan Inc",
    "wof:placetype":"venue"
},
  "geometry": {"coordinates":[-87.621353,41.340728],"type":"Point"}
}