{
  "type": "Feature",
  "properties": {
    "addr:full":"1501 Madison St Evanston IL 60202",
    "addr:housenumber":"1501",
    "addr:postcode":"60202",
    "addr:street":"Madison St",
    "iso:country":"US",
    "sg:address":"1501 Madison St",
    "sg:city":"Evanston",
    "sg:classifiers":[
        {
            "category":"Manufacturing",
            "subcategory":"Printing",
            "type":"Manufacturing & Wholesale Goods"
        }
    ],
    "sg:phone":"+1 847 363 1830",
    "sg:postcode":"60202",
    "sg:province":"IL",
    "sg:tags":[
        "publishing"
    ],
    "wof:name":"Agate Publishing Inc",
    "wof:placetype":"venue"
},
  "geometry": {"coordinates":[-87.693787,42.031772],"type":"Point"}
}