{
  "type": "Feature",
  "properties": {
    "iso:country":"US",
    "sg:address":"5708 Ring Ct",
    "sg:city":"Hanover Park",
    "sg:classifiers":[
        {
            "category":"Local Transit",
            "type":"Transportation"
        }
    ],
    "sg:phone":"+1 630 830 9794",
    "sg:postcode":"60133",
    "sg:province":"IL",
    "sg:tags":[
        "limousine"
    ],
    "wof:name":"A Class Limousine",
    "wof:placetype":"venue"
},
  "geometry": {"coordinates":[-88.14438800000001,41.974357],"type":"Point"}
}