{
  "type": "Feature",
  "properties": {
    "addr:full":"3839 E State St Rockford IL 61108",
    "addr:housenumber":"3839",
    "addr:postcode":"61108",
    "addr:street":"E State St",
    "iso:country":"US",
    "sg:address":"3839 E State St",
    "sg:city":"Rockford",
    "sg:classifiers":[
        {
            "category":"Professional",
            "type":"Services"
        }
    ],
    "sg:phone":"+1 815 227 9341",
    "sg:postcode":"61108",
    "sg:province":"IL",
    "sg:tags":[
        "establishment"
    ],
    "wof:name":"Rabine Paving",
    "wof:placetype":"venue"
},
  "geometry": {"coordinates":[-89.029764,42.264159],"type":"Point"}
}