{
  "type": "Feature",
  "properties": {
    "addr:full":"1935 Stanley St Northbrook IL 60062",
    "addr:housenumber":"1935",
    "addr:postcode":"60062",
    "addr:street":"Stanley St",
    "iso:country":"US",
    "sg:address":"1935 Stanley St",
    "sg:city":"Northbrook",
    "sg:classifiers":[
        {
            "category":"Manufacturing",
            "subcategory":"Tools & Machinery",
            "type":"Manufacturing & Wholesale Goods"
        }
    ],
    "sg:phone":"+1 847 272 6202",
    "sg:postcode":"60062",
    "sg:province":"IL",
    "sg:tags":[
        "mfg",
        "industrial",
        "general"
    ],
    "wof:name":"Robko Co",
    "wof:placetype":"venue"
},
  "geometry": {"coordinates":[-87.827314,42.118922],"type":"Point"}
}