{
  "type": "Feature",
  "properties": {
    "iso:country":"US",
    "sg:address":"410 S Clark St",
    "sg:city":"Chicago",
    "sg:classifiers":[
        {
            "category":"Restaurant",
            "type":"Food & Drink"
        }
    ],
    "sg:phone":"+1 312 235 9000",
    "sg:postcode":"60605",
    "sg:province":"IL",
    "sg:tags":[
        "greek",
        "mediterranean"
    ],
    "wof:name":"Haifa Cafe",
    "wof:placetype":"venue"
},
  "geometry": {"coordinates":[-87.630882,41.876671],"type":"Point"}
}