{
  "type": "Feature",
  "properties": {
    "addr:full":"341 Frey Ln Fairview Heights IL 62208",
    "addr:housenumber":"341",
    "addr:postcode":"62208",
    "addr:street":"Frey Ln",
    "iso:country":"US",
    "sg:address":"341 Frey Ln",
    "sg:city":"Fairview Heights",
    "sg:classifiers":[
        {
            "category":"Professional",
            "subcategory":"Computer Services",
            "type":"Services"
        }
    ],
    "sg:phone":"+1 618 624 0105",
    "sg:postcode":"62208",
    "sg:province":"IL",
    "sg:tags":[
        "repair"
    ],
    "sg:website":"www.tillmancomputerservices.com",
    "wof:name":"Tillman Computer Svc LLC",
    "wof:placetype":"venue"
},
  "geometry": {"coordinates":[-89.97905900000001,38.587601],"type":"Point"}
}