{
  "type": "Feature",
  "properties": {
    "iso:country":"US",
    "sg:address":"926 Main St Ofc",
    "sg:city":"Peoria",
    "sg:classifiers":[
        {
            "category":"Real Estate",
            "subcategory":"Real Estate Operator",
            "type":"Services"
        }
    ],
    "sg:phone":"+1 309 673 0202",
    "sg:postcode":"61602",
    "sg:province":"IL",
    "sg:tags":[
        "apartment"
    ],
    "wof:name":"Glen Oak Towers",
    "wof:placetype":"venue"
},
  "geometry": {"coordinates":[-89.596109,40.69798],"type":"Point"}
}