{
  "type": "Feature",
  "properties": {
    "iso:country":"US",
    "sg:address":"500 W Lake St",
    "sg:city":"Addison",
    "sg:classifiers":[
        {
            "category":"Restaurant",
            "type":"Food & Drink"
        }
    ],
    "sg:menulink":"http://www.allmenus.com/il/addison/198993-kfc---kentucky-fried-chicken/menu/",
    "sg:phone":"+1 630 543 2151",
    "sg:postcode":"60101",
    "sg:province":"IL",
    "sg:tags":[
        "american",
        "chicken"
    ],
    "wof:name":"KFC - Kentucky Fried Chicken",
    "wof:placetype":"venue"
},
  "geometry": {"coordinates":[-88.001591,41.937736],"type":"Point"}
}