{
  "type": "Feature",
  "properties": {
    "iso:country":"US",
    "sg:address":"6255 N Milwaukee Ave",
    "sg:city":"Chicago",
    "sg:classifiers":[
        {
            "category":"Real Estate",
            "subcategory":"Real Estate Services",
            "type":"Services"
        }
    ],
    "sg:phone":"+1 773 774 8300",
    "sg:postcode":"60646",
    "sg:province":"IL",
    "wof:name":"Keto Fred M Realtor",
    "wof:placetype":"venue"
},
  "geometry": {"coordinates":[-87.785698,41.9949],"type":"Point"}
}