{
  "type": "Feature",
  "properties": {
    "iso:country":"US",
    "sg:address":"6001 88th Ave",
    "sg:city":"Kenosha",
    "sg:classifiers":[
        {
            "category":"Organizations",
            "subcategory":"Religious Organization",
            "type":"Services"
        }
    ],
    "sg:phone":"+1 262 654 0575",
    "sg:postcode":"53142",
    "sg:province":"IL",
    "sg:tags":[
        "church"
    ],
    "sg:website":"www.aaicw.com",
    "wof:name":"Amer Albanian Islamic Center",
    "wof:placetype":"venue"
},
  "geometry": {"coordinates":[-87.914624,42.579162],"type":"Point"}
}