{
  "type": "Feature",
  "properties": {
    "iso:country":"US",
    "sg:address":"1500 N Oakland Ave",
    "sg:city":"Carbondale",
    "sg:classifiers":[
        {
            "category":"Professional",
            "subcategory":"Business Services",
            "type":"Services"
        },
        {
            "category":"Organizations",
            "subcategory":"Professional Association",
            "type":"Services"
        }
    ],
    "sg:phone":"+1 618 529 7600",
    "sg:postcode":"62901",
    "sg:province":"IL",
    "sg:tags":[
        "referral",
        "contractor"
    ],
    "wof:name":"Egyptian Contrators Associatio",
    "wof:placetype":"venue"
},
  "geometry": {"coordinates":[-89.227535,37.74361],"type":"Point"}
}