{
  "type": "Feature",
  "properties": {
    "addr:full":"6917 W Higgins Avenue Chicago IL 60656",
    "addr:housenumber":"6917",
    "addr:postcode":"60656",
    "addr:street":"W Higgins Avenue",
    "iso:country":"US",
    "sg:address":"6917 W Higgins Avenue",
    "sg:city":"Chicago",
    "sg:classifiers":[
        {
            "category":"Health Services",
            "subcategory":"Dentist",
            "type":"Services"
        }
    ],
    "sg:phone":"+1 773 774 2114",
    "sg:postcode":"60656",
    "sg:province":"IL",
    "wof:name":"Higgins Dental Group",
    "wof:placetype":"venue"
},
  "geometry": {"coordinates":[-87.80029,41.979503],"type":"Point"}
}