{
  "type": "Feature",
  "properties": {
    "addr:full":"3325 N Knox Avenue Chicago IL 60641",
    "addr:housenumber":"3325",
    "addr:postcode":"60641",
    "addr:street":"N Knox Avenue",
    "iso:country":"US",
    "sg:address":"3325 N Knox Avenue",
    "sg:city":"Chicago",
    "sg:classifiers":[
        {
            "category":"Retail",
            "subcategory":"Auto Repair",
            "type":"Services"
        }
    ],
    "sg:phone":"+1 773 286 7686",
    "sg:postcode":"60641",
    "sg:province":"IL",
    "wof:name":"S & T Automotive",
    "wof:placetype":"venue"
},
  "geometry": {"coordinates":[-87.742774,41.940617],"type":"Point"}
}