{
  "type": "Feature",
  "properties": {
    "iso:country":"US",
    "sg:address":"419 N Mulford Rd",
    "sg:city":"Rockford",
    "sg:classifiers":[
        {
            "category":"Professional",
            "type":"Services"
        }
    ],
    "sg:phone":"+1 815 397 2041",
    "sg:postcode":"61107",
    "sg:province":"IL",
    "sg:tags":[
        "establishment"
    ],
    "wof:name":"Source",
    "wof:placetype":"venue"
},
  "geometry": {"coordinates":[-88.99951799999999,42.27157],"type":"Point"}
}