{
  "type": "Feature",
  "properties": {
    "iso:country":"US",
    "sg:address":"712 W Slippery Rock Dr",
    "sg:city":"Palatine",
    "sg:classifiers":[
        {
            "category":"Professional",
            "subcategory":"Computer Services",
            "type":"Services"
        },
        {
            "category":"Wholesale",
            "subcategory":"Computers",
            "type":"Manufacturing & Wholesale Goods"
        }
    ],
    "sg:phone":"+1 847 925 1870",
    "sg:postcode":"60067",
    "sg:province":"IL",
    "sg:tags":[
        "equipment",
        "cd-rom",
        "software"
    ],
    "sg:website":"http://www.smartbytesolutions.com",
    "wof:name":"Smartbyte Solutions Inc",
    "wof:placetype":"venue"
},
  "geometry": {"coordinates":[-88.06012200000001,42.085293],"type":"Point"}
}