{
  "type": "Feature",
  "properties": {
    "addr:full":"4014 W Addison St Chicago IL 60641",
    "addr:housenumber":"4014",
    "addr:postcode":"60641",
    "addr:street":"W Addison St",
    "iso:country":"US",
    "sg:address":"4014 W Addison St",
    "sg:city":"Chicago",
    "sg:classifiers":[
        {
            "category":"Professional",
            "subcategory":"Business Services",
            "type":"Services"
        }
    ],
    "sg:phone":"+1 773 283 1847",
    "sg:postcode":"60641",
    "sg:province":"IL",
    "wof:name":"Emmanuel Kritikos",
    "wof:placetype":"venue"
},
  "geometry": {"coordinates":[-87.727611,41.946446],"type":"Point"}
}