{
  "type": "Feature",
  "properties": {
    "addr:full":"5900 Bond Ave East St Louis IL 62207",
    "addr:housenumber":"5900",
    "addr:postcode":"62207",
    "addr:street":"Bond Ave",
    "iso:country":"US",
    "sg:address":"5900 Bond Ave",
    "sg:city":"East St Louis",
    "sg:classifiers":[
        {
            "category":"Banks & Credit Unions",
            "subcategory":"Bank",
            "type":"Services"
        }
    ],
    "sg:phone":"+1 618 337 3924",
    "sg:postcode":"62207",
    "sg:province":"IL",
    "wof:name":"West Point Bank & Trust Co",
    "wof:placetype":"venue"
},
  "geometry": {"coordinates":[-90.104269,38.568372],"type":"Point"}
}