{
  "type": "Feature",
  "properties": {
    "addr:full":"1410 N Market St Sparta IL 62286",
    "addr:housenumber":"1410",
    "addr:postcode":"62286",
    "addr:street":"N Market St",
    "iso:country":"US",
    "sg:address":"1410 N Market St",
    "sg:city":"Sparta",
    "sg:classifiers":[
        {
            "category":"Personal",
            "subcategory":"Beauty Salon",
            "type":"Services"
        }
    ],
    "sg:phone":"+1 618 443 3357",
    "sg:postcode":"62286",
    "sg:province":"IL",
    "sg:tags":[
        "hair",
        "stylist"
    ],
    "wof:name":"Smarts Style",
    "wof:placetype":"venue"
},
  "geometry": {"coordinates":[-89.703506,38.138748],"type":"Point"}
}