{
  "type": "Feature",
  "properties": {
    "addr:full":"1370 Warrington Ave Danville IL 61832",
    "addr:housenumber":"1370",
    "addr:postcode":"61832",
    "addr:street":"Warrington Ave",
    "iso:country":"US",
    "sg:address":"1370 Warrington Ave",
    "sg:city":"Danville",
    "sg:classifiers":[
        {
            "category":"Utilities",
            "subcategory":"Mobile Phone",
            "type":"Services"
        }
    ],
    "sg:phone":"+1 217 446 0567",
    "sg:postcode":"61832",
    "sg:province":"IL",
    "sg:tags":[
        "telephone",
        "cellular"
    ],
    "wof:name":"Abbey Cellular",
    "wof:placetype":"venue"
},
  "geometry": {"coordinates":[-87.67364000000001,40.126405],"type":"Point"}
}