{
  "type": "Feature",
  "properties": {
    "addr:full":"250 W Nebraska St Elburn IL 60119",
    "addr:housenumber":"250",
    "addr:postcode":"60119",
    "addr:street":"W Nebraska St",
    "iso:country":"US",
    "sg:address":"250 W Nebraska St",
    "sg:city":"Elburn",
    "sg:classifiers":[
        {
            "category":"Building & Trades",
            "subcategory":"Plumbing",
            "type":"Services"
        },
        {
            "category":"Building & Trades",
            "subcategory":"Construction",
            "type":"Services"
        },
        {
            "category":"Utilities",
            "type":"Services"
        }
    ],
    "sg:phone":"+1 630 365 6266",
    "sg:postcode":"60119",
    "sg:province":"IL",
    "sg:tags":[
        "plumber",
        "geothermal",
        "specialty",
        "cooling",
        "heating",
        "contractor"
    ],
    "sg:website":"http://www.jrherra.com",
    "wof:name":"J & R Herra Inc",
    "wof:placetype":"venue"
},
  "geometry": {"coordinates":[-88.474267,41.890491],"type":"Point"}
}