{
  "type": "Feature",
  "properties": {
    "iso:country":"US",
    "sg:address":"10137-B S Harlem Ave",
    "sg:city":"Chicago Ridge",
    "sg:classifiers":[
        {
            "category":"Wholesale",
            "subcategory":"Computers",
            "type":"Manufacturing & Wholesale Goods"
        },
        {
            "category":"Professional",
            "subcategory":"Computer Services",
            "type":"Services"
        }
    ],
    "sg:phone":"+1 708 424 3000",
    "sg:postcode":"60415",
    "sg:province":"IL",
    "sg:tags":[
        "repair"
    ],
    "sg:website":"www.computercloseouts.net",
    "wof:name":"Computer Closeouts",
    "wof:placetype":"venue"
},
  "geometry": {"coordinates":[-87.798085,41.707179],"type":"Point"}
}