{
  "type": "Feature",
  "properties": {
    "iso:country":"US",
    "sg:address":"227 Sycamore Rd",
    "sg:city":"Genoa",
    "sg:classifiers":[
        {
            "category":"Restaurant",
            "type":"Food & Drink"
        }
    ],
    "sg:phone":"+1 815 784 3425",
    "sg:postcode":"60135",
    "sg:province":"IL",
    "wof:name":"Robert's Drive In",
    "wof:placetype":"venue"
},
  "geometry": {"coordinates":[-88.684021,42.093888],"type":"Point"}
}