{
  "type": "Feature",
  "properties": {
    "iso:country":"US",
    "sg:address":"506 S Jefferson St",
    "sg:city":"Flanagan",
    "sg:classifiers":[
        {
            "category":"Transit Center",
            "subcategory":"Freight",
            "type":"Transportation"
        },
        {
            "category":"Freight",
            "type":"Transportation"
        }
    ],
    "sg:phone":"+1 815 993 8161",
    "sg:postcode":"61740",
    "sg:province":"IL",
    "sg:tags":[
        "local",
        "trucking-motor",
        "trucking"
    ],
    "wof:name":"Larry Couch Trucking",
    "wof:placetype":"venue"
},
  "geometry": {"coordinates":[-88.86257000000001,40.872396],"type":"Point"}
}