{
  "type": "Feature",
  "properties": {
    "addr:full":"7772 N 1935th Ave Geneseo IL 61254",
    "addr:housenumber":"7772",
    "addr:postcode":"61254",
    "addr:street":"N 1935Th Ave",
    "iso:country":"US",
    "sg:address":"7772 N 1935th Ave",
    "sg:city":"Geneseo",
    "sg:classifiers":[
        {
            "category":"Farming",
            "subcategory":"Livestock Farm",
            "type":"Manufacturing & Wholesale Goods"
        }
    ],
    "sg:phone":"+1 309 949 2526",
    "sg:postcode":"61254",
    "sg:province":"IL",
    "sg:tags":[
        "feedlot",
        "hog",
        "or",
        "beef",
        "cattle"
    ],
    "wof:name":"Edward Viager Farm",
    "wof:placetype":"venue"
},
  "geometry": {"coordinates":[-90.28225999999999,41.433291],"type":"Point"}
}