{
  "type": "Feature",
  "properties": {
    "addr:full":"1845 W Tower Rd Kankakee IL 60901",
    "addr:housenumber":"1845",
    "addr:postcode":"60901",
    "addr:street":"W Tower Rd",
    "iso:country":"US",
    "sg:address":"1845 W Tower Rd",
    "sg:city":"Kankakee",
    "sg:phone":"+1 815 933 7246",
    "sg:postcode":"60901",
    "sg:province":"IL",
    "sg:tags":[
        "farm",
        "corn",
        "soybean"
    ],
    "wof:name":"Andy Wulff",
    "wof:placetype":"venue"
},
  "geometry": {"coordinates":[-87.910275,41.140205],"type":"Point"}
}