{
  "type": "Feature",
  "properties": {
    "addr:full":"5034 N Melvina Ave Chicago IL 60630",
    "addr:housenumber":"5034",
    "addr:postcode":"60630",
    "addr:street":"N Melvina Ave",
    "iso:country":"US",
    "sg:address":"5034 N Melvina Ave",
    "sg:city":"Chicago",
    "sg:classifiers":[
        {
            "category":"Insurance",
            "subcategory":"Hazard Insurance",
            "type":"Services"
        }
    ],
    "sg:phone":"+1 773 202 1894",
    "sg:postcode":"60630",
    "sg:province":"IL",
    "sg:tags":[
        "commercial",
        "business"
    ],
    "wof:name":"Allstate",
    "wof:placetype":"venue"
},
  "geometry": {"coordinates":[-87.783089,41.972483],"type":"Point"}
}