{
  "type": "Feature",
  "properties": {
    "addr:full":"209 S Morrison Ave Collinsville IL 62234",
    "addr:housenumber":"209",
    "addr:postcode":"62234",
    "addr:street":"S Morrison Ave",
    "iso:country":"US",
    "sg:address":"209 S Morrison Ave",
    "sg:city":"Collinsville",
    "sg:classifiers":[
        {
            "category":"Professional",
            "subcategory":"Lawyer & Legal Services",
            "type":"Services"
        }
    ],
    "sg:phone":"+1 618 346 8181",
    "sg:postcode":"62234",
    "sg:province":"IL",
    "sg:tags":[
        "attorney"
    ],
    "wof:name":"Steve Grimm Law Office",
    "wof:placetype":"venue"
},
  "geometry": {"coordinates":[-89.984021,38.668782],"type":"Point"}
}