{
  "type": "Feature",
  "properties": {
    "iso:country":"US",
    "sg:address":"210 N Crestlane Dr",
    "sg:city":"Kankakee",
    "sg:classifiers":[
        {
            "category":"Building & Trades",
            "subcategory":"Construction",
            "type":"Services"
        }
    ],
    "sg:phone":"+1 815 932 7086",
    "sg:postcode":"60901",
    "sg:province":"IL",
    "sg:tags":[
        "concrete",
        "contractor"
    ],
    "wof:name":"A & M Concrete",
    "wof:placetype":"venue"
},
  "geometry": {"coordinates":[-87.835157,41.119511],"type":"Point"}
}