{
  "type": "Feature",
  "properties": {
    "iso:country":"US",
    "sg:address":"14335 Jamestown Rd",
    "sg:city":"Breese",
    "sg:classifiers":[
        {
            "category":"Real Estate",
            "subcategory":"Real Estate Operator",
            "type":"Services"
        }
    ],
    "sg:phone":"+1 618 526 0100",
    "sg:postcode":"62230",
    "sg:province":"IL",
    "sg:tags":[
        "apartment"
    ],
    "sg:website":"www.thevillasatstjames.com",
    "wof:name":"Villas At Saint James",
    "wof:placetype":"venue"
},
  "geometry": {"coordinates":[-89.525894,38.630747],"type":"Point"}
}