{
  "type": "Feature",
  "properties": {
    "iso:country":"US",
    "sg:address":"5125 Highway 34 N",
    "sg:city":"Raleigh",
    "sg:classifiers":[
        {
            "category":"Airline",
            "type":"Transportation"
        }
    ],
    "sg:phone":"+1 800 433 7300",
    "sg:postcode":"62977",
    "sg:province":"IL",
    "sg:website":"http://www.aa.com",
    "wof:name":"American Airlines",
    "wof:placetype":"venue"
},
  "geometry": {"coordinates":[-88.539832,37.805011],"type":"Point"}
}