{
  "type": "Feature",
  "properties": {
    "addr:full":"2618 11th St Rock Island IL 61201",
    "addr:housenumber":"2618",
    "addr:postcode":"61201",
    "addr:street":"11Th St",
    "iso:country":"US",
    "sg:address":"2618 11th St",
    "sg:city":"Rock Island",
    "sg:classifiers":[
        {
            "category":"Building & Trades",
            "subcategory":"Equipment Rental",
            "type":"Services"
        }
    ],
    "sg:phone":"+1 309 786 9707",
    "sg:postcode":"61201",
    "sg:province":"IL",
    "wof:name":"Rent-A-Center",
    "wof:placetype":"venue"
},
  "geometry": {"coordinates":[-90.583011,41.485177],"type":"Point"}
}