{
  "type": "Feature",
  "properties": {
    "iso:country":"US",
    "sg:address":"720 W Army Trail Rd",
    "sg:city":"Carol Stream",
    "sg:classifiers":[
        {
            "category":"Insurance",
            "subcategory":"Insurance Agent",
            "type":"Services"
        }
    ],
    "sg:phone":"+1 630 372 0650",
    "sg:postcode":"60188",
    "sg:province":"IL",
    "wof:name":"Allstate Insurance",
    "wof:placetype":"venue"
},
  "geometry": {"coordinates":[-88.145119,41.940269],"type":"Point"}
}