{
  "type": "Feature",
  "properties": {
    "iso:country":"US",
    "sg:address":"1546 Mule Rd",
    "sg:city":"Columbia",
    "sg:classifiers":[
        {
            "category":"Professional",
            "subcategory":"Management & Consulting",
            "type":"Services"
        }
    ],
    "sg:phone":"+1 618 281 6006",
    "sg:postcode":"62236",
    "sg:province":"IL",
    "wof:name":"TS Enterprises",
    "wof:placetype":"venue"
},
  "geometry": {"coordinates":[-90.170662,38.484981],"type":"Point"}
}