{
  "type": "Feature",
  "properties": {
    "iso:country":"US",
    "sg:address":"125 S Milwaukee Ave",
    "sg:city":"Libertyville",
    "sg:classifiers":[
        {
            "category":"Retail",
            "subcategory":"Auto Repair",
            "type":"Services"
        }
    ],
    "sg:phone":"+1   ",
    "sg:postcode":"60048",
    "sg:province":"IL",
    "sg:tags":[
        "station",
        "gasoline",
        "general"
    ],
    "wof:name":"Jerrys Service",
    "wof:placetype":"venue"
},
  "geometry": {"coordinates":[-87.953304,42.282694],"type":"Point"}
}