{
  "type": "Feature",
  "properties": {
    "addr:full":"299 N Fairview Ave Decatur IL 62522",
    "addr:housenumber":"299",
    "addr:postcode":"62522",
    "addr:street":"N Fairview Ave",
    "iso:country":"US",
    "sg:address":"299 N Fairview Ave",
    "sg:city":"Decatur",
    "sg:classifiers":[
        {
            "category":"Education",
            "subcategory":"College",
            "type":"Public Place"
        },
        {
            "category":"Organizations",
            "subcategory":"Membership Organization",
            "type":"Services"
        }
    ],
    "sg:phone":"+1 217 424 3916",
    "sg:postcode":"62522",
    "sg:province":"IL",
    "sg:tags":[
        "sorority",
        "housing",
        "student",
        "fraternity"
    ],
    "sg:website":"http://www.alphachiomega.net",
    "wof:name":"Alpha Chi Omega",
    "wof:placetype":"venue"
},
  "geometry": {"coordinates":[-88.97747,39.843597],"type":"Point"}
}