{
  "type": "Feature",
  "properties": {
    "iso:country":"US",
    "sg:address":"26533 Stephanie Ct",
    "sg:city":"Monee",
    "sg:classifiers":[
        {
            "category":"Organizations",
            "subcategory":"Religious Organization",
            "type":"Services"
        }
    ],
    "sg:phone":"+1 708 534 2625",
    "sg:postcode":"60449",
    "sg:province":"IL",
    "wof:name":"Charles Mickens Rev",
    "wof:placetype":"venue"
},
  "geometry": {"coordinates":[-87.735658,41.407605],"type":"Point"}
}