{
  "type": "Feature",
  "properties": {
    "iso:country":"US",
    "sg:address":"750 N Dearborn St",
    "sg:city":"Chicago",
    "sg:classifiers":[
        {
            "category":"Insurance",
            "subcategory":"Hazard Insurance",
            "type":"Services"
        }
    ],
    "sg:phone":"+1 312 336 0063",
    "sg:postcode":"60654",
    "sg:province":"IL",
    "sg:tags":[
        "commercial",
        "business"
    ],
    "wof:name":"United American Insurance Company",
    "wof:placetype":"venue"
},
  "geometry": {"coordinates":[-87.629745,41.895997],"type":"Point"}
}