{
  "type": "Feature",
  "properties": {
    "addr:full":"901 W Madison St Chicago IL 60607",
    "addr:housenumber":"901",
    "addr:postcode":"60607",
    "addr:street":"W Madison St",
    "iso:country":"US",
    "sg:address":"901 W Madison St",
    "sg:city":"Chicago",
    "sg:classifiers":[
        {
            "category":"Professional",
            "type":"Services"
        },
        {
            "category":"Restaurant",
            "type":"Food & Drink"
        }
    ],
    "sg:phone":"+1 312 666 8788",
    "sg:postcode":"60607",
    "sg:province":"IL",
    "sg:tags":[
        "mexican",
        "caterer"
    ],
    "wof:name":"El Famous Burrito",
    "wof:placetype":"venue"
},
  "geometry": {"coordinates":[-87.650291,41.881416],"type":"Point"}
}