{
  "type": "Feature",
  "properties": {
    "addr:full":"1311 S Schoolhouse Rd New Lenox IL 60451",
    "addr:housenumber":"1311",
    "addr:postcode":"60451",
    "addr:street":"S Schoolhouse Rd",
    "iso:country":"US",
    "sg:address":"1311 S Schoolhouse Rd",
    "sg:city":"New Lenox",
    "sg:classifiers":[
        {
            "category":"Manufacturing",
            "subcategory":"Tools & Machinery",
            "type":"Manufacturing & Wholesale Goods"
        }
    ],
    "sg:phone":"+1 815 463 9607",
    "sg:postcode":"60451",
    "sg:province":"IL",
    "sg:tags":[
        "machine",
        "shop"
    ],
    "wof:name":"EDW Enterprise",
    "wof:placetype":"venue"
},
  "geometry": {"coordinates":[-87.92621200000001,41.484877],"type":"Point"}
}