{
  "type": "Feature",
  "properties": {
    "iso:country":"US",
    "sg:address":"306 3rd Ave N",
    "sg:city":"White Hall",
    "sg:classifiers":[
        {
            "category":"Autos & Motor Vehicles",
            "subcategory":"Automobile Sales",
            "type":"Retail Goods"
        },
        {
            "category":"Retail",
            "subcategory":"Auto Repair",
            "type":"Services"
        }
    ],
    "sg:phone":"+1 217 374 2788",
    "sg:postcode":"62092",
    "sg:province":"IL",
    "sg:tags":[
        "body",
        "car",
        "used",
        "dealer"
    ],
    "wof:name":"Country Classics",
    "wof:placetype":"venue"
},
  "geometry": {"coordinates":[-90.399175,39.447013],"type":"Point"}
}