{
  "type": "Feature",
  "properties": {
    "iso:country":"US",
    "sg:address":"1830 N Hudson Ave Unit D",
    "sg:city":"Chicago",
    "sg:classifiers":[
        {
            "category":"Home & Garden",
            "subcategory":"Building Materials",
            "type":"Retail Goods"
        }
    ],
    "sg:phone":"+1 312 642 3889",
    "sg:postcode":"60614",
    "sg:province":"IL",
    "sg:tags":[
        "bathroom",
        "cabinet",
        "fixtures",
        "accessory"
    ],
    "sg:website":"http://www.rjmsales.com",
    "wof:name":"R J M Sales Inc",
    "wof:placetype":"venue"
},
  "geometry": {"coordinates":[-87.639917,41.91532],"type":"Point"}
}