{
  "type": "Feature",
  "properties": {
    "iso:country":"US",
    "sg:address":"290 Warren Rd",
    "sg:city":"Carbondale",
    "sg:classifiers":[
        {
            "category":"Restaurant",
            "type":"Food & Drink"
        }
    ],
    "sg:phone":"+1   ",
    "sg:postcode":"62901",
    "sg:province":"IL",
    "sg:tags":[
        "personal",
        "eating"
    ],
    "wof:name":"Pasta House Company",
    "wof:placetype":"venue"
},
  "geometry": {"coordinates":[-89.195021,37.705864],"type":"Point"}
}