{
  "type": "Feature",
  "properties": {
    "iso:country":"US",
    "sg:address":"7330 W Madison St",
    "sg:city":"Forest Park",
    "sg:classifiers":[
        {
            "category":"Restaurant",
            "type":"Food & Drink"
        }
    ],
    "sg:phone":"+1 708 488 0480",
    "sg:postcode":"60130",
    "sg:province":"IL",
    "sg:tags":[
        "sushi",
        "bar"
    ],
    "sg:website":"buahana.com",
    "wof:name":"Bua Hana",
    "wof:placetype":"venue"
},
  "geometry": {"coordinates":[-87.808656,41.879548],"type":"Point"}
}