{
  "type": "Feature",
  "properties": {
    "iso:country":"US",
    "sg:address":"431 Ridge Ct",
    "sg:city":"Lake In The Hills",
    "sg:classifiers":[
        {
            "category":"Shopping",
            "subcategory":"Hobbies, Toys, & Games",
            "type":"Retail Goods"
        }
    ],
    "sg:phone":"+1   ",
    "sg:postcode":"60156",
    "sg:province":"IL",
    "wof:name":"Aircraft Miniatures",
    "wof:placetype":"venue"
},
  "geometry": {"coordinates":[-88.361312,42.1821],"type":"Point"}
}