{
  "type": "Feature",
  "properties": {
    "iso:country":"US",
    "sg:address":"303 Springfield Ave",
    "sg:city":"Joliet",
    "sg:classifiers":[
        {
            "category":"Organizations",
            "subcategory":"Professional Association",
            "type":"Services"
        }
    ],
    "sg:phone":"+1 815 744 4520",
    "sg:postcode":"60435",
    "sg:province":"IL",
    "sg:tags":[
        "trade"
    ],
    "sg:website":"www.wgaronline.com",
    "wof:name":"Three Rivers Assn Of Realtors",
    "wof:placetype":"venue"
},
  "geometry": {"coordinates":[-88.137739,41.527078],"type":"Point"}
}