{
  "type": "Feature",
  "properties": {
    "iso:country":"US",
    "sg:address":"977 N. Oaklawn Avenue Suite 106",
    "sg:city":"Elmhurst",
    "sg:classifiers":[
        {
            "category":"Professional",
            "subcategory":"Computer Services",
            "type":"Services"
        }
    ],
    "sg:postcode":"60126",
    "sg:province":"IL",
    "sg:tags":[
        "browser",
        "data",
        "analysis",
        "database"
    ],
    "sg:website":"http://www.kirix.com/",
    "wof:name":"Kirix Corporation",
    "wof:placetype":"venue"
},
  "geometry": {"coordinates":[-87.956265,41.92858],"type":"Point"}
}