{
  "type": "Feature",
  "properties": {
    "iso:country":"US",
    "sg:address":"7830 W 71st St",
    "sg:city":"Bridgeview",
    "sg:classifiers":[
        {
            "category":"Freight",
            "type":"Transportation"
        }
    ],
    "sg:phone":"+1 708 594 3116",
    "sg:postcode":"60455",
    "sg:province":"IL",
    "sg:tags":[
        "operator",
        "gene",
        "local",
        "trucking"
    ],
    "sg:website":"www.carrytransit.com",
    "wof:name":"Carry Transit",
    "wof:placetype":"venue"
},
  "geometry": {"coordinates":[-87.810921,41.76254],"type":"Point"}
}