{
  "type": "Feature",
  "properties": {
    "addr:full":"411 S Larkin Ave Joliet IL 60436",
    "addr:housenumber":"411",
    "addr:postcode":"60436",
    "addr:street":"S Larkin Ave",
    "iso:country":"US",
    "sg:address":"411 S Larkin Ave",
    "sg:city":"Joliet",
    "sg:classifiers":[
        {
            "category":"Travel",
            "subcategory":"Hotels & Motels",
            "type":"Entertainment"
        },
        {
            "category":"Retail",
            "subcategory":"Event Space",
            "type":"Services"
        },
        {
            "category":"Travel",
            "subcategory":"Resort",
            "type":"Entertainment"
        }
    ],
    "sg:phone":"+1 800 345 8082",
    "sg:postcode":"60436",
    "sg:province":"IL",
    "sg:tags":[
        "facility",
        "banquet",
        "reception",
        "lodging",
        "corporate",
        "hall"
    ],
    "sg:website":"http://ad.doubleclick.net/clk;223371278;47096201;d?http://www.holidayinn.com/redirect?path=hd&brandCode=hi&hotelCode=jotso&_PMID=99601036&cm_mmc=mdpr-_-yellowpages-_-hi-_-jotso",
    "wof:name":"Holiday Inn Joliet - Conference Center",
    "wof:placetype":"venue"
},
  "geometry": {"coordinates":[-88.124413,41.514389],"type":"Point"}
}