{
  "type": "Feature",
  "properties": {
    "addr:full":"3 E Roosevelt Road Chicago IL 60605",
    "addr:housenumber":"3",
    "addr:postcode":"60605",
    "addr:street":"E Roosevelt Road",
    "iso:country":"US",
    "sg:address":"3 E Roosevelt Road",
    "sg:city":"Chicago",
    "sg:classifiers":[
        {
            "category":"Retail",
            "subcategory":"Laundry & Dry Cleaning",
            "type":"Services"
        },
        {
            "category":"Building & Trades",
            "subcategory":"Cleaning & Sanitation",
            "type":"Services"
        }
    ],
    "sg:phone":"+1 312 566 9414",
    "sg:postcode":"60605",
    "sg:province":"IL",
    "sg:tags":[
        "cleaner",
        "house"
    ],
    "wof:name":"Grand Park Cleaner",
    "wof:placetype":"venue"
},
  "geometry": {"coordinates":[-87.62699600000001,41.867442],"type":"Point"}
}