{
  "type": "Feature",
  "properties": {
    "iso:country":"US",
    "sg:address":"1900 Oxford Way",
    "sg:city":"Joliet",
    "sg:classifiers":[
        {
            "category":"Education",
            "subcategory":"School",
            "type":"Public Place"
        }
    ],
    "sg:phone":"+1 815 577 2021",
    "sg:postcode":"60431",
    "sg:province":"IL",
    "sg:tags":[
        "elementary"
    ],
    "wof:name":"Thomas Jefferson Elementary School",
    "wof:placetype":"venue"
},
  "geometry": {"coordinates":[-88.285202,41.554371],"type":"Point"}
}