{
  "type": "Feature",
  "properties": {
    "iso:country":"US",
    "sg:address":"166 N 1st St",
    "sg:city":"Breese",
    "sg:classifiers":[
        {
            "category":"Personal",
            "subcategory":"Beauty Salon",
            "type":"Services"
        }
    ],
    "sg:phone":"+1 618 526 7743",
    "sg:postcode":"62230",
    "sg:province":"IL",
    "sg:tags":[
        "shop"
    ],
    "wof:name":"Style Hut",
    "wof:placetype":"venue"
},
  "geometry": {"coordinates":[-89.533574,38.607772],"type":"Point"}
}