{
  "type": "Feature",
  "properties": {
    "addr:full":"5518 Oak St Highland IL 62249",
    "addr:housenumber":"5518",
    "addr:postcode":"62249",
    "addr:street":"Oak St",
    "iso:country":"US",
    "sg:address":"5518 Oak St",
    "sg:city":"Highland",
    "sg:classifiers":[
        {
            "category":"Building & Trades",
            "subcategory":"Landscaping Services",
            "type":"Services"
        }
    ],
    "sg:phone":"+1 618 675 3463",
    "sg:postcode":"62249",
    "sg:province":"IL",
    "sg:tags":[
        "landscape",
        "contractor"
    ],
    "wof:name":"Miener's Nursery & Tree Plntng",
    "wof:placetype":"venue"
},
  "geometry": {"coordinates":[-89.668654,38.857406],"type":"Point"}
}