{
  "type": "Feature",
  "properties": {
    "iso:country":"US",
    "sg:address":"115 N Neil St",
    "sg:city":"Champaign",
    "sg:classifiers":[
        {
            "category":"Professional",
            "subcategory":"Lawyer & Legal Services",
            "type":"Services"
        }
    ],
    "sg:phone":"+1 217 356 2577",
    "sg:postcode":"61820",
    "sg:province":"IL",
    "wof:name":"Hatch Lawrence R Atty",
    "wof:placetype":"venue"
},
  "geometry": {"coordinates":[-88.243301,40.116402],"type":"Point"}
}