{
  "type": "Feature",
  "properties": {
    "iso:country":"US",
    "sg:address":"3722 W. Chicago Ave",
    "sg:city":"Chicago",
    "sg:classifiers":[
        {
            "category":"Arts & Performance",
            "subcategory":"Art Gallery",
            "type":"Entertainment"
        }
    ],
    "sg:phone":"+1 773 269 8351",
    "sg:postcode":"60651",
    "sg:province":"IL",
    "sg:website":"graf-hick.com",
    "wof:name":"T.h.ink",
    "wof:placetype":"venue"
},
  "geometry": {"coordinates":[-87.719725,41.895716],"type":"Point"}
}