{
  "type": "Feature",
  "properties": {
    "iso:country":"US",
    "sg:address":"Fullerton and Kedzie",
    "sg:city":"Chicago",
    "sg:classifiers":[
        {
            "category":"Personal",
            "type":"Services"
        }
    ],
    "sg:phone":"+1 630 697 5078",
    "sg:postcode":"60647",
    "sg:province":"IL",
    "sg:tags":[
        "planning",
        "wedding"
    ],
    "sg:website":"www.fivegrainevents.com",
    "wof:name":"Five Grain Events",
    "wof:placetype":"venue"
},
  "geometry": {"coordinates":[-87.70755800000001,41.924707],"type":"Point"}
}