{
  "type": "Feature",
  "properties": {
    "addr:full":"1200 W Wilson St Batavia IL 60510",
    "addr:housenumber":"1200",
    "addr:postcode":"60510",
    "addr:street":"W Wilson St",
    "iso:country":"US",
    "sg:address":"1200 W Wilson St",
    "sg:city":"Batavia",
    "sg:classifiers":[
        {
            "category":"Education",
            "subcategory":"School",
            "type":"Public Place"
        }
    ],
    "sg:phone":"+1 630 879 4601",
    "sg:postcode":"60510",
    "sg:province":"IL",
    "wof:name":"Board Of Education Dist 101",
    "wof:placetype":"venue"
},
  "geometry": {"coordinates":[-88.32573600000001,41.849758],"type":"Point"}
}