{
  "type": "Feature",
  "properties": {
    "addr:full":"861 N Central Ave Wood Dale IL 60191",
    "addr:housenumber":"861",
    "addr:postcode":"60191",
    "addr:street":"N Central Ave",
    "iso:country":"US",
    "sg:address":"861 N Central Ave",
    "sg:city":"Wood Dale",
    "sg:classifiers":[
        {
            "category":"Building & Trades",
            "subcategory":"Equipment Rental",
            "type":"Services"
        }
    ],
    "sg:phone":"+1 630 766 7848",
    "sg:postcode":"60191",
    "sg:province":"IL",
    "wof:name":"Litronicx Ltd",
    "wof:placetype":"venue"
},
  "geometry": {"coordinates":[-87.971914,41.978227],"type":"Point"}
}