{
  "type": "Feature",
  "properties": {
    "iso:country":"US",
    "sg:address":"5129 Oak Center Dr",
    "sg:city":"Oak Lawn",
    "sg:classifiers":[
        {
            "category":"Building & Trades",
            "subcategory":"Construction",
            "type":"Services"
        }
    ],
    "sg:phone":"+1 708 636 2165",
    "sg:postcode":"60453",
    "sg:province":"IL",
    "sg:tags":[
        "house"
    ],
    "wof:name":"K & P Craftsmen Inc",
    "wof:placetype":"venue"
},
  "geometry": {"coordinates":[-87.748681,41.711581],"type":"Point"}
}