{
  "type": "Feature",
  "properties": {
    "iso:country":"US",
    "sg:address":"5735 S Lutz Rd",
    "sg:city":"Gardner",
    "sg:classifiers":[
        {
            "category":"Freight",
            "type":"Transportation"
        }
    ],
    "sg:phone":"+1 815 237 8263",
    "sg:postcode":"60424",
    "sg:province":"IL",
    "sg:tags":[
        "general"
    ],
    "wof:name":"Creekside Storage Inc",
    "wof:placetype":"venue"
},
  "geometry": {"coordinates":[-88.311521,41.203942],"type":"Point"}
}