{
  "type": "Feature",
  "properties": {
    "iso:country":"US",
    "sg:address":"2415 Gardner Rd",
    "sg:city":"Broadview",
    "sg:classifiers":[
        {
            "category":"Professional",
            "type":"Services"
        }
    ],
    "sg:phone":"+1 708 345 4850",
    "sg:postcode":"60155",
    "sg:province":"IL",
    "sg:tags":[
        "establishment"
    ],
    "wof:name":"Dowic LTD",
    "wof:placetype":"venue"
},
  "geometry": {"coordinates":[-87.867018,41.849466],"type":"Point"}
}