{
  "type": "Feature",
  "properties": {
    "iso:country":"US",
    "sg:address":"3137 N Lewis Ave",
    "sg:city":"Waukegan",
    "sg:classifiers":[
        {
            "category":"Personal",
            "subcategory":"Tanning Parlor",
            "type":"Services"
        }
    ],
    "sg:phone":"+1 847 336 5544",
    "sg:postcode":"60087",
    "sg:province":"IL",
    "sg:tags":[
        "salon"
    ],
    "wof:name":"Lighthouse Tanning LTD",
    "wof:placetype":"venue"
},
  "geometry": {"coordinates":[-87.854943,42.407847],"type":"Point"}
}