{
  "type": "Feature",
  "properties": {
    "addr:full":"455 Stevens St Geneva IL 60134",
    "addr:housenumber":"455",
    "addr:postcode":"60134",
    "addr:street":"Stevens St",
    "iso:country":"US",
    "sg:address":"455 Stevens St",
    "sg:city":"Geneva",
    "sg:classifiers":[
        {
            "category":"Manufacturing",
            "subcategory":"Motor Vehicles & Parts",
            "type":"Manufacturing & Wholesale Goods"
        }
    ],
    "sg:phone":"+1 630 232 0275",
    "sg:postcode":"60134",
    "sg:province":"IL",
    "sg:tags":[
        "equipment",
        "truck"
    ],
    "sg:website":"www.snmfg.com",
    "wof:name":"S & N Mfg",
    "wof:placetype":"venue"
},
  "geometry": {"coordinates":[-88.309048,41.892394],"type":"Point"}
}