{
  "type": "Feature",
  "properties": {
    "addr:full":"3905 W Ernestine Dr Marion IL 62959",
    "addr:housenumber":"3905",
    "addr:postcode":"62959",
    "addr:street":"W Ernestine Dr",
    "iso:country":"US",
    "sg:address":"3905 W Ernestine Dr",
    "sg:city":"Marion",
    "sg:classifiers":[
        {
            "category":"Shopping",
            "subcategory":"Stationery & Office Supplies",
            "type":"Retail Goods"
        }
    ],
    "sg:phone":"+1 618 997 7756",
    "sg:postcode":"62959",
    "sg:province":"IL",
    "sg:tags":[
        "equipment"
    ],
    "wof:name":"Cds Office Technologies",
    "wof:placetype":"venue"
},
  "geometry": {"coordinates":[-88.995003,37.748699],"type":"Point"}
}