{
  "type": "Feature",
  "properties": {
    "addr:full":"7130 N Western Ave Chicago IL 60645",
    "addr:housenumber":"7130",
    "addr:postcode":"60645",
    "addr:street":"N Western Ave",
    "iso:country":"US",
    "sg:address":"7130 N Western Ave",
    "sg:city":"Chicago",
    "sg:classifiers":[
        {
            "category":"Retail",
            "subcategory":"Car Wash",
            "type":"Services"
        }
    ],
    "sg:phone":"+1 773 465 1462",
    "sg:postcode":"60645",
    "sg:province":"IL",
    "sg:tags":[
        "polishing",
        "washing"
    ],
    "wof:name":"Fast Carwash",
    "wof:placetype":"venue"
},
  "geometry": {"coordinates":[-87.690318,42.01209],"type":"Point"}
}