{
  "type": "Feature",
  "properties": {
    "iso:country":"US",
    "sg:address":"5626 N 2nd St",
    "sg:city":"Loves Park",
    "sg:classifiers":[
        {
            "category":"Sports & Exercise",
            "subcategory":"Bowling",
            "type":"Entertainment"
        }
    ],
    "sg:phone":"+1 815 633 8824",
    "sg:postcode":"61111",
    "sg:province":"IL",
    "sg:tags":[
        "center"
    ],
    "wof:name":"B & B Park Bowl",
    "wof:placetype":"venue"
},
  "geometry": {"coordinates":[-89.05795500000001,42.31246],"type":"Point"}
}