{
  "type": "Feature",
  "properties": {
    "addr:full":"1422 E Hintz Rd Arlington Hts IL 60004",
    "addr:housenumber":"1422",
    "addr:postcode":"60004",
    "addr:street":"E Hintz Rd",
    "iso:country":"US",
    "sg:address":"1422 E Hintz Rd",
    "sg:city":"Arlington Hts",
    "sg:classifiers":[
        {
            "category":"Food & Beverages",
            "subcategory":"Liquor & Beverages",
            "type":"Retail Goods"
        }
    ],
    "sg:phone":"+1 847 506 9926",
    "sg:postcode":"60004",
    "sg:province":"IL",
    "sg:tags":[
        "alcoholic"
    ],
    "wof:name":"Brook Run Liquors Inc",
    "wof:placetype":"venue"
},
  "geometry": {"coordinates":[-87.96624300000001,42.124547],"type":"Point"}
}