{
  "type": "Feature",
  "properties": {
    "iso:country":"US",
    "sg:address":"135 W Broadway",
    "sg:city":"Astoria",
    "sg:classifiers":[
        {
            "category":"Health Services",
            "subcategory":"Clinic",
            "type":"Services"
        }
    ],
    "sg:phone":"+1 309 329 2926",
    "sg:postcode":"61501",
    "sg:province":"IL",
    "sg:tags":[
        "medical"
    ],
    "wof:name":"Community Medical Clinic",
    "wof:placetype":"venue"
},
  "geometry": {"coordinates":[-90.35894399999999,40.226958],"type":"Point"}
}