{
  "type": "Feature",
  "properties": {
    "iso:country":"US",
    "sg:address":"43 E Jefferson Ave",
    "sg:city":"Naperville",
    "sg:classifiers":[
        {
            "category":"Health Services",
            "subcategory":"Doctor",
            "type":"Services"
        },
        {
            "category":"Social Services",
            "type":"Services"
        }
    ],
    "sg:phone":"+1 630 369 8885",
    "sg:postcode":"60540",
    "sg:province":"IL",
    "sg:tags":[
        "family",
        "psychologist",
        "individual",
        "marriage",
        "child",
        "counselor"
    ],
    "sg:website":"http://www.kenedytherapy.com",
    "wof:name":"Barbara Kenedy & Associates",
    "wof:placetype":"venue"
},
  "geometry": {"coordinates":[-88.14633499999999,41.772887],"type":"Point"}
}