{
  "type": "Feature",
  "properties": {
    "addr:full":"10204 Franklin Ave Franklin Park IL 60131",
    "addr:housenumber":"10204",
    "addr:postcode":"60131",
    "addr:street":"Franklin Ave",
    "iso:country":"US",
    "sg:address":"10204 Franklin Ave",
    "sg:city":"Franklin Park",
    "sg:classifiers":[
        {
            "category":"Shopping",
            "type":"Retail Goods"
        }
    ],
    "sg:phone":"+1 847 233 0310",
    "sg:postcode":"60131",
    "sg:province":"IL",
    "sg:tags":[
        "awning",
        "canopy"
    ],
    "wof:name":"Awnings Over Chicago Land Inc",
    "wof:placetype":"venue"
},
  "geometry": {"coordinates":[-87.88129499999999,41.94],"type":"Point"}
}