{
  "type": "Feature",
  "properties": {
    "iso:country":"US",
    "sg:address":"600 Industrial Dr",
    "sg:city":"Cary",
    "sg:classifiers":[
        {
            "category":"Health Services",
            "subcategory":"Clinic",
            "type":"Services"
        }
    ],
    "sg:phone":"+1 847 462 0303",
    "sg:postcode":"60013",
    "sg:province":"IL",
    "sg:tags":[
        "home",
        "care"
    ],
    "wof:name":"Home Instead Inc",
    "wof:placetype":"venue"
},
  "geometry": {"coordinates":[-88.252665,42.213288],"type":"Point"}
}