{
  "type": "Feature",
  "properties": {
    "addr:full":"5808 W Fulton St Chicago IL 60644",
    "addr:housenumber":"5808",
    "addr:postcode":"60644",
    "addr:street":"W Fulton St",
    "iso:country":"US",
    "sg:address":"5808 W Fulton St",
    "sg:city":"Chicago",
    "sg:classifiers":[
        {
            "category":"Social Services",
            "subcategory":"Adult Care",
            "type":"Services"
        }
    ],
    "sg:phone":"+1 773 257 3007",
    "sg:postcode":"60644",
    "sg:province":"IL",
    "sg:tags":[
        "home",
        "child",
        "center",
        "day"
    ],
    "wof:name":"Lydia Home Association Inc",
    "wof:placetype":"venue"
},
  "geometry": {"coordinates":[-87.770837,41.885708],"type":"Point"}
}