{
  "type": "Feature",
  "properties": {
    "iso:country":"US",
    "sg:address":"2520 S State St",
    "sg:city":"Chicago",
    "sg:classifiers":[
        {
            "category":"Travel",
            "subcategory":"Travel Agent",
            "type":"Entertainment"
        }
    ],
    "sg:phone":"+1 312 326 6639",
    "sg:postcode":"60616",
    "sg:province":"IL",
    "sg:tags":[
        "agency"
    ],
    "wof:name":"Doma Travel",
    "wof:placetype":"venue"
},
  "geometry": {"coordinates":[-87.626952,41.846578],"type":"Point"}
}