{
  "type": "Feature",
  "properties": {
    "addr:full":"5029 American Rd Rockford IL 61109",
    "addr:housenumber":"5029",
    "addr:postcode":"61109",
    "addr:street":"American Rd",
    "iso:country":"US",
    "sg:address":"5029 American Rd",
    "sg:city":"Rockford",
    "sg:classifiers":[
        {
            "category":"Wholesale",
            "subcategory":"Wine & Distilled Alcoholic Beverages",
            "type":"Manufacturing & Wholesale Goods"
        }
    ],
    "sg:phone":"+1 815 874 7770",
    "sg:postcode":"61109",
    "sg:province":"IL",
    "wof:name":"River City Distributing",
    "wof:placetype":"venue"
},
  "geometry": {"coordinates":[-89.012878,42.22744],"type":"Point"}
}