{
  "type": "Feature",
  "properties": {
    "addr:full":"6430 S Pulaski Rd Chicago IL 60629",
    "addr:housenumber":"6430",
    "addr:postcode":"60629",
    "addr:street":"S Pulaski Rd",
    "iso:country":"US",
    "sg:address":"6430 S Pulaski Rd",
    "sg:city":"Chicago",
    "sg:classifiers":[
        {
            "category":"Restaurant",
            "type":"Food & Drink"
        }
    ],
    "sg:menulink":"http://www.allmenus.com/il/chicago/223920-shark-seafood/menu/",
    "sg:phone":"+1 773 884 2100",
    "sg:postcode":"60629",
    "sg:province":"IL",
    "sg:tags":[
        "seafood",
        "american"
    ],
    "wof:name":"Shark Seafood",
    "wof:placetype":"venue"
},
  "geometry": {"coordinates":[-87.72260799999999,41.775816],"type":"Point"}
}