{
  "type": "Feature",
  "properties": {
    "iso:country":"US",
    "sg:address":"3948 W Lawrence Ave",
    "sg:city":"Chicago",
    "sg:classifiers":[
        {
            "category":"Bars & Pubs",
            "subcategory":"Nightclub",
            "type":"Food & Drink"
        }
    ],
    "sg:phone":"+1 773 267 0474",
    "sg:postcode":"60686",
    "sg:province":"IL",
    "sg:tags":[
        "nightlife"
    ],
    "wof:name":"240 Lounge & Cafe",
    "wof:placetype":"venue"
},
  "geometry": {"coordinates":[-87.72745399999999,41.96814],"type":"Point"}
}