{
  "type": "Feature",
  "properties": {
    "addr:full":"930 N Meacham Rd Schaumburg IL 60173",
    "addr:housenumber":"930",
    "addr:postcode":"60173",
    "addr:street":"N Meacham Rd",
    "iso:country":"US",
    "sg:address":"930 N Meacham Rd",
    "sg:city":"Schaumburg",
    "sg:phone":"+1 847 413 8337",
    "sg:postcode":"60173",
    "sg:province":"IL",
    "wof:name":"Ted's Montana Grill",
    "wof:placetype":"venue"
},
  "geometry": {"coordinates":[-88.045227,42.045809],"type":"Point"}
}