{
  "type": "Feature",
  "properties": {
    "iso:country":"US",
    "sg:address":"828 Locust St",
    "sg:city":"Galesburg",
    "sg:classifiers":[
        {
            "category":"Government",
            "subcategory":"Fire Station",
            "type":"Public Place"
        },
        {
            "category":"Retail",
            "subcategory":"Laundry & Dry Cleaning",
            "type":"Services"
        },
        {
            "category":"Building & Trades",
            "subcategory":"Cleaning & Sanitation",
            "type":"Services"
        }
    ],
    "sg:phone":"+1 309 343 8159",
    "sg:postcode":"61401",
    "sg:province":"IL",
    "sg:tags":[
        "cleaner",
        "disaster",
        "recovery",
        "rug",
        "relief",
        "janitorial",
        "carpet"
    ],
    "wof:name":"Quality Carpet Care",
    "wof:placetype":"venue"
},
  "geometry": {"coordinates":[-90.350396,40.937198],"type":"Point"}
}