{
  "type": "Feature",
  "properties": {
    "iso:country":"US",
    "sg:address":"9995 Tabler Rd",
    "sg:city":"Morris",
    "sg:classifiers":[
        {
            "category":"Professional",
            "subcategory":"Business Services",
            "type":"Services"
        }
    ],
    "sg:phone":"+1 815 467 6893",
    "sg:postcode":"60450",
    "sg:province":"IL",
    "wof:name":"Arnold Racing Enterprises Inc",
    "wof:placetype":"venue"
},
  "geometry": {"coordinates":[-88.329049,41.428317],"type":"Point"}
}