{
  "type": "Feature",
  "properties": {
    "addr:full":"397 Lake St Antioch IL 60002",
    "addr:housenumber":"397",
    "addr:postcode":"60002",
    "addr:street":"Lake St",
    "iso:country":"US",
    "sg:address":"397 Lake St",
    "sg:city":"Antioch",
    "sg:classifiers":[
        {
            "category":"Professional",
            "subcategory":"Lawyer & Legal Services",
            "type":"Services"
        }
    ],
    "sg:phone":"+1 847 395 1640",
    "sg:postcode":"60002",
    "sg:province":"IL",
    "wof:name":"Heyl Erica Atty",
    "wof:placetype":"venue"
},
  "geometry": {"coordinates":[-88.098,42.4771],"type":"Point"}
}