{
  "type": "Feature",
  "properties": {
    "addr:full":"222 S Riverside Plz # 900 Chicago IL 60606",
    "addr:housenumber":"222",
    "addr:postcode":"60606",
    "addr:street":"S Riverside Plz # 900",
    "iso:country":"US",
    "sg:address":"222 S Riverside Plz # 900",
    "sg:city":"Chicago",
    "sg:classifiers":[
        {
            "category":"Banks & Credit Unions",
            "subcategory":"Investment Brokerage",
            "type":"Services"
        }
    ],
    "sg:phone":"+1 312 373 5478",
    "sg:postcode":"60606",
    "sg:province":"IL",
    "sg:tags":[
        "broker",
        "commodity"
    ],
    "wof:name":"Rjo Futures",
    "wof:placetype":"venue"
},
  "geometry": {"coordinates":[-87.638509,41.879037],"type":"Point"}
}