{
  "type": "Feature",
  "properties": {
    "addr:full":"302 E Roselawn St Danville IL 61832",
    "addr:housenumber":"302",
    "addr:postcode":"61832",
    "addr:street":"E Roselawn St",
    "iso:country":"US",
    "sg:address":"302 E Roselawn St",
    "sg:city":"Danville",
    "sg:classifiers":[
        {
            "category":"Sports & Exercise",
            "subcategory":"Gym",
            "type":"Entertainment"
        }
    ],
    "sg:phone":"+1 217 442 7277",
    "sg:postcode":"61832",
    "sg:province":"IL",
    "sg:tags":[
        "school",
        "fitness",
        "physical",
        "facility"
    ],
    "wof:name":"Roselawn Center",
    "wof:placetype":"venue"
},
  "geometry": {"coordinates":[-87.62468800000001,40.151773],"type":"Point"}
}