{
  "type": "Feature",
  "properties": {
    "iso:country":"US",
    "sg:address":"4439 Blackhawk Ln",
    "sg:city":"Lisle",
    "sg:classifiers":[
        {
            "category":"Real Estate",
            "subcategory":"Real Estate Operator",
            "type":"Services"
        }
    ],
    "sg:phone":"+1 630 357 1240",
    "sg:postcode":"60532",
    "sg:province":"IL",
    "sg:tags":[
        "building",
        "apartment"
    ],
    "wof:name":"Lisle Place Apartments",
    "wof:placetype":"venue"
},
  "geometry": {"coordinates":[-88.099402,41.80414],"type":"Point"}
}