{
  "type": "Feature",
  "properties": {
    "iso:country":"US",
    "sg:address":"1725 Galloway Cir",
    "sg:city":"Barrington",
    "sg:classifiers":[
        {
            "category":"Real Estate",
            "subcategory":"Real Estate Agent",
            "type":"Services"
        }
    ],
    "sg:phone":"+1 847 358 3910",
    "sg:postcode":"60010",
    "sg:province":"IL",
    "wof:name":"Payel Corporation",
    "wof:placetype":"venue"
},
  "geometry": {"coordinates":[-88.108602,42.124441],"type":"Point"}
}