{
  "type": "Feature",
  "properties": {
    "iso:country":"US",
    "sg:address":"715 N Milwaukee Ave",
    "sg:city":"Libertyville",
    "sg:classifiers":[
        {
            "category":"Professional",
            "subcategory":"Advertising",
            "type":"Services"
        },
        {
            "category":"Home & Garden",
            "subcategory":"Building Materials",
            "type":"Retail Goods"
        },
        {
            "category":"Manufacturing",
            "subcategory":"Building Materials",
            "type":"Manufacturing & Wholesale Goods"
        }
    ],
    "sg:phone":"+1 847 367 4744",
    "sg:postcode":"60048",
    "sg:province":"IL",
    "sg:tags":[
        "door",
        "coupon",
        "accessory",
        "garage",
        "opener",
        "doors",
        "frames"
    ],
    "sg:website":"http://www.acjenterprises.com",
    "wof:name":"Aero Garage Door",
    "wof:placetype":"venue"
},
  "geometry": {"coordinates":[-87.94581599999999,42.248146],"type":"Point"}
}