{
  "type": "Feature",
  "properties": {
    "addr:full":"613 N 24th St East Saint Louis IL 62205",
    "addr:housenumber":"613",
    "addr:postcode":"62205",
    "addr:street":"N 24Th St",
    "iso:country":"US",
    "sg:address":"613 N 24th St",
    "sg:city":"East Saint Louis",
    "sg:classifiers":[
        {
            "category":"Shopping",
            "subcategory":"Jewelry",
            "type":"Retail Goods"
        }
    ],
    "sg:phone":"+1 618 274 4000",
    "sg:postcode":"62205",
    "sg:province":"IL",
    "wof:name":"Jireh",
    "wof:placetype":"venue"
},
  "geometry": {"coordinates":[-90.128608,38.616953],"type":"Point"}
}