{
  "type": "Feature",
  "properties": {
    "iso:country":"US",
    "sg:address":"4028 Blackhawk Rd",
    "sg:city":"Rock Island",
    "sg:classifiers":[
        {
            "category":"Health Services",
            "subcategory":"Doctor",
            "type":"Services"
        }
    ],
    "sg:phone":"+1 309 788 6689",
    "sg:postcode":"61201",
    "sg:province":"IL",
    "sg:tags":[
        "dentist"
    ],
    "wof:name":"21st Century Dental",
    "wof:placetype":"venue"
},
  "geometry": {"coordinates":[-90.542655,41.468216],"type":"Point"}
}