{
  "type": "Feature",
  "properties": {
    "iso:country":"US",
    "sg:address":"5973 N Broadway Rd",
    "sg:city":"Apple River",
    "sg:classifiers":[
        {
            "category":"Personal",
            "type":"Services"
        }
    ],
    "sg:phone":"+1 815 594 9021",
    "sg:postcode":"61001",
    "sg:province":"IL",
    "sg:tags":[
        "carpentry",
        "contractor"
    ],
    "wof:name":"Gary & Diana Mundt",
    "wof:placetype":"venue"
},
  "geometry": {"coordinates":[-90.092708,42.449182],"type":"Point"}
}