{
  "type": "Feature",
  "properties": {
    "iso:country":"US",
    "sg:address":"5242 Grand Ave",
    "sg:city":"Downers Grove",
    "sg:classifiers":[
        {
            "category":"Health Services",
            "subcategory":"Health Practitioner",
            "type":"Services"
        }
    ],
    "sg:phone":"+1 630 852 1799",
    "sg:postcode":"60515",
    "sg:province":"IL",
    "wof:name":"Sommers Solution The",
    "wof:placetype":"venue"
},
  "geometry": {"coordinates":[-87.99692899999999,41.787969],"type":"Point"}
}