{
  "type": "Feature",
  "properties": {
    "iso:country":"US",
    "sg:address":"3360 Ugland Dr",
    "sg:city":"Joliet",
    "sg:classifiers":[
        {
            "category":"Shopping",
            "subcategory":"Gifts & Souvenirs",
            "type":"Retail Goods"
        }
    ],
    "sg:phone":"+1 815 485 5974",
    "sg:postcode":"60432",
    "sg:province":"IL",
    "sg:tags":[
        "shop"
    ],
    "wof:name":"Trinity Services Inc",
    "wof:placetype":"venue"
},
  "geometry": {"coordinates":[-88.001277,41.527619],"type":"Point"}
}