{
  "type": "Feature",
  "properties": {
    "addr:full":"11930 Western Ave Blue Island IL 60406",
    "addr:housenumber":"11930",
    "addr:postcode":"60406",
    "addr:street":"Western Ave",
    "iso:country":"US",
    "sg:address":"11930 Western Ave",
    "sg:city":"Blue Island",
    "sg:classifiers":[
        {
            "category":"Professional",
            "subcategory":"Management & Consulting",
            "type":"Services"
        }
    ],
    "sg:phone":"+1 708 385 4378",
    "sg:postcode":"60406",
    "sg:province":"IL",
    "wof:name":"Thresholds",
    "wof:placetype":"venue"
},
  "geometry": {"coordinates":[-87.680761,41.676696],"type":"Point"}
}