{
  "type": "Feature",
  "properties": {
    "addr:full":"2909 W Fargo Ave Chicago IL 60645",
    "addr:housenumber":"2909",
    "addr:postcode":"60645",
    "addr:street":"W Fargo Ave",
    "iso:country":"US",
    "sg:address":"2909 W Fargo Ave",
    "sg:city":"Chicago",
    "sg:classifiers":[
        {
            "category":"Health Services",
            "subcategory":"Health Practitioner",
            "type":"Services"
        }
    ],
    "sg:phone":"+1 773 262 5757",
    "sg:postcode":"60645",
    "sg:province":"IL",
    "sg:tags":[
        "psychologist"
    ],
    "wof:name":"Center For Panic & Phobia",
    "wof:placetype":"venue"
},
  "geometry": {"coordinates":[-87.704213,42.016432],"type":"Point"}
}