{
  "type": "Feature",
  "properties": {
    "addr:full":"2109 Industrial Park Rd Rock Falls IL 61071",
    "addr:housenumber":"2109",
    "addr:postcode":"61071",
    "addr:street":"Industrial Park Rd",
    "iso:country":"US",
    "sg:address":"2109 Industrial Park Rd",
    "sg:city":"Rock Falls",
    "sg:classifiers":[
        {
            "category":"Autos & Motor Vehicles",
            "subcategory":"Recreational Vehicle Sales",
            "type":"Retail Goods"
        }
    ],
    "sg:phone":"+1 815 625 4343",
    "sg:postcode":"61071",
    "sg:province":"IL",
    "sg:tags":[
        "home"
    ],
    "wof:name":"Hank Bright Rv Ctr",
    "wof:placetype":"venue"
},
  "geometry": {"coordinates":[-89.675061,41.761531],"type":"Point"}
}