{
  "type": "Feature",
  "properties": {
    "addr:full":"1008 North Blvd. Oak Park IL 60301",
    "addr:housenumber":"1008",
    "addr:postcode":"60301",
    "addr:street":"North Blvd.",
    "iso:country":"US",
    "sg:address":"1008 North Blvd.",
    "sg:city":"Oak Park",
    "sg:classifiers":[
        {
            "category":"Health Services",
            "subcategory":"Health Practitioner",
            "type":"Services"
        }
    ],
    "sg:phone":"+1 708 829 6173",
    "sg:postcode":"60301",
    "sg:province":"IL",
    "sg:tags":[
        "home",
        "care"
    ],
    "wof:name":"Massage by Jean & David",
    "wof:placetype":"venue"
},
  "geometry": {"coordinates":[-87.801117,41.887254],"type":"Point"}
}