{
  "type": "Feature",
  "properties": {
    "addr:full":"404 E Lakeshore Dr Tower Lakes IL 60010",
    "addr:housenumber":"404",
    "addr:postcode":"60010",
    "addr:street":"E Lakeshore Dr",
    "iso:country":"US",
    "sg:address":"404 E Lakeshore Dr",
    "sg:city":"Tower Lakes",
    "sg:classifiers":[
        {
            "category":"Health Services",
            "subcategory":"Clinic",
            "type":"Services"
        }
    ],
    "sg:phone":"+1 847 487 1668",
    "sg:postcode":"60010",
    "sg:province":"IL",
    "sg:tags":[
        "organization",
        "medical",
        "surgical"
    ],
    "wof:name":"Barrington Ventures",
    "wof:placetype":"venue"
},
  "geometry": {"coordinates":[-88.153285,42.231795],"type":"Point"}
}