{
  "type": "Feature",
  "properties": {
    "iso:country":"US",
    "sg:address":"748 23rd St",
    "sg:city":"Moline",
    "sg:classifiers":[
        {
            "category":"Building & Trades",
            "subcategory":"Cleaning & Sanitation",
            "type":"Services"
        }
    ],
    "sg:phone":"+1 309 755 5410",
    "sg:postcode":"61265",
    "sg:province":"IL",
    "sg:tags":[
        "maintenance"
    ],
    "wof:name":"Townsell Janitorial Service",
    "wof:placetype":"venue"
},
  "geometry": {"coordinates":[-90.504258,41.507344],"type":"Point"}
}