{
  "type": "Feature",
  "properties": {
    "iso:country":"US",
    "sg:address":"6985 N Arrow Wood Rd",
    "sg:city":"Dundas",
    "sg:classifiers":[
        {
            "category":"Farming",
            "subcategory":"Poultry Farm",
            "type":"Manufacturing & Wholesale Goods"
        }
    ],
    "sg:phone":"+1 618 754 3325",
    "sg:postcode":"62425",
    "sg:province":"IL",
    "sg:tags":[
        "egg"
    ],
    "wof:name":"Zuber Turkey Farm",
    "wof:placetype":"venue"
},
  "geometry": {"coordinates":[-88.016423,38.82697],"type":"Point"}
}