{
  "type": "Feature",
  "properties": {
    "iso:country":"US",
    "sg:address":"224 Saint Louis St",
    "sg:city":"Edwardsville",
    "sg:classifiers":[
        {
            "category":"Government",
            "subcategory":"Police Station",
            "type":"Public Place"
        },
        {
            "category":"Professional",
            "subcategory":"Lawyer & Legal Services",
            "type":"Services"
        }
    ],
    "sg:phone":"+1 618 656 2321",
    "sg:postcode":"62025",
    "sg:province":"IL",
    "sg:tags":[
        "attorney",
        "law",
        "duo",
        "traffic",
        "criminal",
        "dwi"
    ],
    "sg:website":"http://www.lbtdlaw.com",
    "wof:name":"Lucco Brown Threlkeld & Dawson Attorneys at Law",
    "wof:placetype":"venue"
},
  "geometry": {"coordinates":[-89.958204,38.811681],"type":"Point"}
}