{
  "type": "Feature",
  "properties": {
    "addr:full":"201 E Wabash St Norris City IL 62869",
    "addr:housenumber":"201",
    "addr:postcode":"62869",
    "addr:street":"E Wabash St",
    "iso:country":"US",
    "sg:address":"201 E Wabash St",
    "sg:city":"Norris City",
    "sg:classifiers":[
        {
            "category":"Restaurant",
            "type":"Food & Drink"
        }
    ],
    "sg:phone":"+1   ",
    "sg:postcode":"62869",
    "sg:province":"IL",
    "sg:tags":[
        "eating"
    ],
    "wof:name":"Cardinal Restaurant The",
    "wof:placetype":"venue"
},
  "geometry": {"coordinates":[-88.327659,37.981351],"type":"Point"}
}