{
  "type": "Feature",
  "properties": {
    "iso:country":"US",
    "sg:address":"302 S Mclean Blvd Ste G",
    "sg:city":"Elgin",
    "sg:classifiers":[
        {
            "category":"Bars & Pubs",
            "type":"Food & Drink"
        }
    ],
    "sg:phone":"+1 847 695 2011",
    "sg:postcode":"60123",
    "sg:province":"IL",
    "wof:name":"Mudd Eddie's Pub",
    "wof:placetype":"venue"
},
  "geometry": {"coordinates":[-88.311916,42.027122],"type":"Point"}
}