{
  "type": "Feature",
  "properties": {
    "iso:country":"US",
    "sg:address":"2501 Wesley Ave",
    "sg:city":"Berwyn",
    "sg:classifiers":[
        {
            "category":"Professional",
            "subcategory":"Advertising",
            "type":"Services"
        }
    ],
    "sg:phone":"+1 708 788 9024",
    "sg:postcode":"60402",
    "sg:province":"IL",
    "sg:tags":[
        "mail",
        "direct"
    ],
    "wof:name":"Gigis Dairy Service Inc",
    "wof:placetype":"venue"
},
  "geometry": {"coordinates":[-87.790696,41.843751],"type":"Point"}
}