{
  "type": "Feature",
  "properties": {
    "iso:country":"US",
    "sg:address":"1323 Elgin Ln",
    "sg:city":"Schaumburg",
    "sg:classifiers":[
        {
            "category":"Building & Trades",
            "subcategory":"Plumbing",
            "type":"Services"
        }
    ],
    "sg:phone":"+1 847 519 0211",
    "sg:postcode":"60194",
    "sg:province":"IL",
    "sg:tags":[
        "contractor"
    ],
    "wof:name":"MB Heating Co",
    "wof:placetype":"venue"
},
  "geometry": {"coordinates":[-88.114873,42.028525],"type":"Point"}
}