{
  "type": "Feature",
  "properties": {
    "addr:full":"4179 W Irving Park Rd Chicago IL 60641",
    "addr:housenumber":"4179",
    "addr:postcode":"60641",
    "addr:street":"W Irving Park Rd",
    "iso:country":"US",
    "sg:address":"4179 W Irving Park Rd",
    "sg:city":"Chicago",
    "sg:classifiers":[
        {
            "category":"Professional",
            "subcategory":"Detective & Security Services",
            "type":"Services"
        }
    ],
    "sg:phone":"+1 773 272 4929",
    "sg:postcode":"60641",
    "sg:province":"IL",
    "sg:tags":[
        "locksmiths-commercial",
        "detect",
        "monitoring",
        "lock",
        "system",
        "industrial",
        "safety"
    ],
    "wof:name":"Emergency 24",
    "wof:placetype":"venue"
},
  "geometry": {"coordinates":[-87.732364,41.953602],"type":"Point"}
}