{
  "type": "Feature",
  "properties": {
    "addr:full":"1528 S Wabash Ave Chicago IL 60605",
    "addr:housenumber":"1528",
    "addr:postcode":"60605",
    "addr:street":"S Wabash Ave",
    "iso:country":"US",
    "sg:address":"1528 S Wabash Ave",
    "sg:city":"Chicago",
    "sg:classifiers":[
        {
            "category":"Building & Trades",
            "subcategory":"Construction",
            "type":"Services"
        }
    ],
    "sg:phone":"+1 312 957 1938",
    "sg:postcode":"60605",
    "sg:province":"IL",
    "sg:tags":[
        "system",
        "contractor",
        "air conditioning"
    ],
    "wof:name":"Ninth Service Corp.",
    "wof:placetype":"venue"
},
  "geometry": {"coordinates":[-87.625651,41.861229],"type":"Point"}
}