{
  "type": "Feature",
  "properties": {
    "iso:country":"US",
    "sg:address":"7 Blanchard Cir",
    "sg:city":"Wheaton",
    "sg:classifiers":[
        {
            "category":"Health Services",
            "subcategory":"Doctor",
            "type":"Services"
        }
    ],
    "sg:phone":"+1 630 681 0108",
    "sg:postcode":"60187",
    "sg:province":"IL",
    "wof:name":"Howard Alstrom DDS PC",
    "wof:placetype":"venue"
},
  "geometry": {"coordinates":[-88.102156,41.834908],"type":"Point"}
}