{
  "type": "Feature",
  "properties": {
    "iso:country":"US",
    "sg:address":"6539 Lanterne Dr",
    "sg:city":"Loves Park",
    "sg:classifiers":[
        {
            "category":"Building & Trades",
            "subcategory":"Construction",
            "type":"Services"
        }
    ],
    "sg:phone":"+1 815 885 4244",
    "sg:postcode":"61111",
    "sg:province":"IL",
    "sg:tags":[
        "hanging",
        "contractor"
    ],
    "wof:name":"Lous Painting",
    "wof:placetype":"venue"
},
  "geometry": {"coordinates":[-88.988281,42.333924],"type":"Point"}
}