{
  "type": "Feature",
  "properties": {
    "addr:full":"21535 Wolf Rd Frankfort IL 60448",
    "addr:housenumber":"21535",
    "addr:postcode":"60448",
    "addr:street":"Wolf Rd",
    "iso:country":"US",
    "sg:address":"21535 Wolf Rd",
    "sg:city":"Frankfort",
    "sg:classifiers":[
        {
            "category":"Professional",
            "subcategory":"Art Services",
            "type":"Services"
        }
    ],
    "sg:phone":"+1 815 469 2806",
    "sg:postcode":"60448",
    "sg:province":"IL",
    "sg:tags":[
        "commercial",
        "design"
    ],
    "wof:name":"Calligrphy With An Angels Tuch",
    "wof:placetype":"venue"
},
  "geometry": {"coordinates":[-87.888077,41.49571],"type":"Point"}
}