{
  "type": "Feature",
  "properties": {
    "addr:full":"1139 Inlet Rd Amboy IL 61310",
    "addr:housenumber":"1139",
    "addr:postcode":"61310",
    "addr:street":"Inlet Rd",
    "iso:country":"US",
    "sg:address":"1139 Inlet Rd",
    "sg:city":"Amboy",
    "sg:classifiers":[
        {
            "category":"Building & Trades",
            "subcategory":"Construction",
            "type":"Services"
        }
    ],
    "sg:phone":"+1 815 857 4225",
    "sg:postcode":"61310",
    "sg:province":"IL",
    "sg:tags":[
        "hanging",
        "contractor"
    ],
    "wof:name":"Hudson Painting",
    "wof:placetype":"venue"
},
  "geometry": {"coordinates":[-89.282853,41.749382],"type":"Point"}
}