{
  "type": "Feature",
  "properties": {
    "iso:country":"US",
    "sg:address":"3125 Ramsgate Rd",
    "sg:city":"Rockford",
    "sg:classifiers":[
        {
            "category":"Real Estate",
            "subcategory":"Real Estate Operator",
            "type":"Services"
        }
    ],
    "sg:phone":"+1 815 877 2115",
    "sg:postcode":"61114",
    "sg:province":"IL",
    "sg:tags":[
        "apartment"
    ],
    "wof:name":"Terra Creek",
    "wof:placetype":"venue"
},
  "geometry": {"coordinates":[-89.033974,42.301311],"type":"Point"}
}