{
  "type": "Feature",
  "properties": {
    "iso:country":"US",
    "sg:address":"350 N Orleans St Ste 13-110",
    "sg:city":"Chicago",
    "sg:classifiers":[
        {
            "category":"Shopping",
            "subcategory":"Jewelry",
            "type":"Retail Goods"
        }
    ],
    "sg:phone":"+1 312 527 4493",
    "sg:postcode":"60654",
    "sg:province":"IL",
    "sg:tags":[
        "watch"
    ],
    "wof:name":"Fossil Inc",
    "wof:placetype":"venue"
},
  "geometry": {"coordinates":[-87.636893,41.888078],"type":"Point"}
}