{
  "type": "Feature",
  "properties": {
    "addr:full":"5681 W Touhy Ave Niles IL 60714",
    "addr:housenumber":"5681",
    "addr:postcode":"60714",
    "addr:street":"W Touhy Ave",
    "iso:country":"US",
    "sg:address":"5681 W Touhy Ave",
    "sg:city":"Niles",
    "sg:classifiers":[
        {
            "category":"Restaurant",
            "type":"Food & Drink"
        }
    ],
    "sg:menulink":"http://www.allmenus.com/il/niles/104641-noodles--company/menu/",
    "sg:phone":"+1 847 647 2544",
    "sg:postcode":"60714",
    "sg:province":"IL",
    "sg:tags":[
        "noodle",
        "bar",
        "salad",
        "chinese",
        "japanese",
        "soup",
        "american",
        "asian",
        "thai",
        "italian"
    ],
    "wof:name":"Noodles & Company",
    "wof:placetype":"venue"
},
  "geometry": {"coordinates":[-87.769655,42.011887],"type":"Point"}
}