{
  "type": "Feature",
  "properties": {
    "iso:country":"US",
    "sg:address":"4567 Opal Dr",
    "sg:city":"Schaumburg",
    "sg:classifiers":[
        {
            "category":"Professional",
            "subcategory":"Business Services",
            "type":"Services"
        }
    ],
    "sg:phone":"+1 847 202 3904",
    "sg:postcode":"60192",
    "sg:province":"IL",
    "sg:tags":[
        "home",
        "commercial",
        "design"
    ],
    "wof:name":"Kby Design",
    "wof:placetype":"venue"
},
  "geometry": {"coordinates":[-88.112439,42.107012],"type":"Point"}
}