{
  "type": "Feature",
  "properties": {
    "iso:country":"US",
    "sg:address":"6440 Grand Ave # 201",
    "sg:city":"Gurnee",
    "sg:classifiers":[
        {
            "category":"Health Services",
            "subcategory":"Doctor",
            "type":"Services"
        }
    ],
    "sg:phone":"+1 847 855 8881",
    "sg:postcode":"60031",
    "sg:province":"IL",
    "sg:tags":[
        "gynecology",
        "physician",
        "surgeon",
        "surgeons",
        "obstetrics"
    ],
    "sg:website":"http://www.obgynedocs.com",
    "wof:name":"Ob Gyn Assoc-Libertyville",
    "wof:placetype":"venue"
},
  "geometry": {"coordinates":[-87.96162200000001,42.385011],"type":"Point"}
}