{
  "type": "Feature",
  "properties": {
    "iso:country":"US",
    "sg:address":"7022 S South Shore Dr",
    "sg:city":"Chicago",
    "sg:classifiers":[
        {
            "category":"Manufacturing",
            "subcategory":"Apparel",
            "type":"Manufacturing & Wholesale Goods"
        }
    ],
    "sg:phone":"+1 773 363 5899",
    "sg:postcode":"60649",
    "sg:province":"IL",
    "sg:tags":[
        "mfg"
    ],
    "wof:name":"Liquidrock Chicago",
    "wof:placetype":"venue"
},
  "geometry": {"coordinates":[-87.566576,41.767416],"type":"Point"}
}