{
  "type": "Feature",
  "properties": {
    "iso:country":"US",
    "sg:address":"306 S Front St",
    "sg:city":"Cobden",
    "sg:classifiers":[
        {
            "category":"Retail",
            "subcategory":"Auto Repair",
            "type":"Services"
        }
    ],
    "sg:phone":"+1 618 893 2941",
    "sg:postcode":"62920",
    "sg:province":"IL",
    "sg:tags":[
        "body",
        "automobile",
        "painting"
    ],
    "wof:name":"Cobden Auto Svc",
    "wof:placetype":"venue"
},
  "geometry": {"coordinates":[-89.254149,37.527138],"type":"Point"}
}