{
  "type": "Feature",
  "properties": {
    "iso:country":"US",
    "sg:address":"21411 W Schweizer Rd",
    "sg:city":"Elwood",
    "sg:classifiers":[
        {
            "category":"Wholesale",
            "subcategory":"Petroleum",
            "type":"Manufacturing & Wholesale Goods"
        }
    ],
    "sg:phone":"+1 815 723 5457",
    "sg:postcode":"60421",
    "sg:province":"IL",
    "sg:tags":[
        "pipe",
        "line",
        "company"
    ],
    "wof:name":"ANR Pipeline Co",
    "wof:placetype":"venue"
},
  "geometry": {"coordinates":[-88.132608,41.464779],"type":"Point"}
}