{
  "type": "Feature",
  "properties": {
    "iso:country":"US",
    "sg:address":"1706 S Baileyville Rd",
    "sg:city":"Freeport",
    "sg:classifiers":[
        {
            "category":"Building & Trades",
            "subcategory":"Landscaping Services",
            "type":"Services"
        },
        {
            "category":"Farming",
            "subcategory":"Nursery",
            "type":"Manufacturing & Wholesale Goods"
        },
        {
            "category":"Shopping",
            "subcategory":"Florist",
            "type":"Retail Goods"
        }
    ],
    "sg:phone":"+1 815 235 2606",
    "sg:postcode":"61032",
    "sg:province":"IL",
    "sg:tags":[
        "lawn",
        "designer",
        "nurseries-plants",
        "consultant",
        "tree",
        "maintenance",
        "landscape"
    ],
    "wof:name":"De Meester Flower Shop & Greenhouse, Inc",
    "wof:placetype":"venue"
},
  "geometry": {"coordinates":[-89.601761,42.279592],"type":"Point"}
}