{
  "type": "Feature",
  "properties": {
    "addr:full":"5702 W 55th Street Chicago IL 60638",
    "addr:housenumber":"5702",
    "addr:postcode":"60638",
    "addr:street":"W 55Th Street",
    "iso:country":"US",
    "sg:address":"5702 W 55th Street",
    "sg:city":"Chicago",
    "sg:classifiers":[
        {
            "category":"Bakery",
            "type":"Food & Drink"
        }
    ],
    "sg:phone":"+1 773 585 9259",
    "sg:postcode":"60638",
    "sg:province":"IL",
    "wof:name":"Continental Baking Company",
    "wof:placetype":"venue"
},
  "geometry": {"coordinates":[-87.764511,41.792776],"type":"Point"}
}