{
  "type": "Feature",
  "properties": {
    "iso:country":"US",
    "sg:address":"4017 N Lincoln Avenue",
    "sg:city":"Chicago",
    "sg:classifiers":[
        {
            "category":"Shopping",
            "subcategory":"Mobile Phones",
            "type":"Retail Goods"
        }
    ],
    "sg:phone":"+1 773 472 1111",
    "sg:postcode":"60618",
    "sg:province":"IL",
    "sg:website":"www.sprint.com",
    "wof:name":"Sprint / MSM Connect",
    "wof:placetype":"venue"
},
  "geometry": {"coordinates":[-87.679249,41.954841],"type":"Point"}
}