{
  "type": "Feature",
  "properties": {
    "addr:full":"2001 S 13th Ave Maywood IL 60153",
    "addr:housenumber":"2001",
    "addr:postcode":"60153",
    "addr:street":"S 13Th Ave",
    "iso:country":"US",
    "sg:address":"2001 S 13th Ave",
    "sg:city":"Maywood",
    "sg:classifiers":[
        {
            "category":"Professional",
            "subcategory":"Management & Consulting",
            "type":"Services"
        }
    ],
    "sg:phone":"+1   ",
    "sg:postcode":"60153",
    "sg:province":"IL",
    "sg:tags":[
        "retail",
        "direct",
        "sales"
    ],
    "wof:name":"Shaklee Independent Distr",
    "wof:placetype":"venue"
},
  "geometry": {"coordinates":[-87.848198,41.866001],"type":"Point"}
}