{
  "type": "Feature",
  "properties": {
    "iso:country":"US",
    "sg:address":"121 Hardin Ave",
    "sg:city":"Jacksonville",
    "sg:classifiers":[
        {
            "category":"Social Services",
            "type":"Services"
        }
    ],
    "sg:phone":"+1 217 245 2521",
    "sg:postcode":"62650",
    "sg:province":"IL",
    "sg:tags":[
        "counseling"
    ],
    "wof:name":"Catholic Charities",
    "wof:placetype":"venue"
},
  "geometry": {"coordinates":[-90.22107699999999,39.733843],"type":"Point"}
}