{
  "type": "Feature",
  "properties": {
    "addr:full":"3415 N Clark S Chicago IL 60657",
    "addr:housenumber":"3415",
    "addr:postcode":"60657",
    "addr:street":"N Clark S",
    "iso:country":"US",
    "sg:address":"3415 N Clark S",
    "sg:city":"Chicago",
    "sg:classifiers":[
        {
            "category":"Fast Food",
            "type":"Food & Drink"
        },
        {
            "category":"Restaurant",
            "type":"Food & Drink"
        }
    ],
    "sg:phone":"+1 773 975 6677",
    "sg:postcode":"60657",
    "sg:province":"IL",
    "sg:tags":[
        "burger",
        "pizza"
    ],
    "sg:website":"www.parkavechicago.com",
    "wof:name":"Park Ave",
    "wof:placetype":"venue"
},
  "geometry": {"coordinates":[-87.65362,41.943943],"type":"Point"}
}