{
  "type": "Feature",
  "properties": {
    "addr:full":"Addison St And Wolcott Ave Chicago IL 60613",
    "addr:postcode":"60613",
    "addr:street":"Addison St;Wolcott Ave",
    "iso:country":"US",
    "sg:address":"Addison St And Wolcott Ave",
    "sg:city":"Chicago",
    "sg:classifiers":[
        {
            "category":"Education",
            "subcategory":"Music School",
            "type":"Public Place"
        }
    ],
    "sg:phone":"+1 248 910 8819",
    "sg:postcode":"60613",
    "sg:province":"IL",
    "sg:tags":[
        "instrument",
        "teacher",
        "musical"
    ],
    "sg:website":"web.me.com/emilyhyl",
    "wof:name":"Emily Lau Piano Studio",
    "wof:placetype":"venue"
},
  "geometry": {"coordinates":[-87.67612,41.946895],"type":"Point"}
}