{
  "type": "Feature",
  "properties": {
    "iso:country":"US",
    "sg:address":"8359 Sayre Ave",
    "sg:city":"Bedford Park",
    "sg:classifiers":[
        {
            "category":"Freight",
            "type":"Transportation"
        }
    ],
    "sg:phone":"+1 708 233 0622",
    "sg:postcode":"60459",
    "sg:province":"IL",
    "sg:tags":[
        "a",
        "as",
        "broker",
        "operates"
    ],
    "wof:name":"Jennstar Inc",
    "wof:placetype":"venue"
},
  "geometry": {"coordinates":[-87.794403,41.739167],"type":"Point"}
}