{
  "type": "Feature",
  "properties": {
    "iso:country":"US",
    "sg:address":"887 E Wilmette Rd",
    "sg:city":"Palatine",
    "sg:classifiers":[
        {
            "category":"Professional",
            "subcategory":"Employment Agencies",
            "type":"Services"
        }
    ],
    "sg:phone":"+1 847 963 0300",
    "sg:postcode":"60074",
    "sg:province":"IL",
    "sg:tags":[
        "training",
        "recruiting",
        "insurance",
        "agent"
    ],
    "wof:name":"Miramar Group",
    "wof:placetype":"venue"
},
  "geometry": {"coordinates":[-88.02401399999999,42.104658],"type":"Point"}
}