{
  "type": "Feature",
  "properties": {
    "iso:country":"US",
    "sg:address":"3 Stuart Dr",
    "sg:city":"Kankakee",
    "sg:classifiers":[
        {
            "category":"Wholesale",
            "subcategory":"Farm Supplies",
            "type":"Manufacturing & Wholesale Goods"
        },
        {
            "category":"Wholesale",
            "subcategory":"Machinery & Supplies",
            "type":"Manufacturing & Wholesale Goods"
        },
        {
            "category":"Recreation",
            "subcategory":"Picnic Area",
            "type":"Entertainment"
        }
    ],
    "sg:phone":"+1 815 933 4439",
    "sg:postcode":"60901",
    "sg:province":"IL",
    "sg:tags":[
        "baling",
        "repair",
        "equipment-parts",
        "equipment"
    ],
    "sg:website":"http://www.shoupparts.com",
    "wof:name":"Shoup Manufacturing Co., Inc.",
    "wof:placetype":"venue"
},
  "geometry": {"coordinates":[-87.869193,41.080973],"type":"Point"}
}