{
  "type": "Feature",
  "properties": {
    "iso:country":"US",
    "sg:address":"1305 E Grand Ave",
    "sg:city":"Carbondale",
    "sg:classifiers":[
        {
            "category":"Organizations",
            "subcategory":"Religious Organization",
            "type":"Services"
        }
    ],
    "sg:phone":"+1 618 351 6572",
    "sg:postcode":"62901",
    "sg:province":"IL",
    "sg:tags":[
        "church"
    ],
    "wof:name":"Western Heights Christian",
    "wof:placetype":"venue"
},
  "geometry": {"coordinates":[-89.192852,37.717532],"type":"Point"}
}