{
  "type": "Feature",
  "properties": {
    "iso:country":"US",
    "sg:address":"2156 Deep Water Ln",
    "sg:city":"Naperville",
    "sg:classifiers":[
        {
            "category":"Health Services",
            "subcategory":"Health Practitioner",
            "type":"Services"
        }
    ],
    "sg:phone":"+1 630 904 5641",
    "sg:postcode":"60564",
    "sg:province":"IL",
    "sg:tags":[
        "therapist",
        "physical"
    ],
    "sg:website":"http://www.actiontherapyservices.com",
    "wof:name":"Action Therapy Services",
    "wof:placetype":"venue"
},
  "geometry": {"coordinates":[-88.203852,41.725425],"type":"Point"}
}