{
  "type": "Feature",
  "properties": {
    "addr:full":"225 N Wabash Ave Chicago IL 60601",
    "addr:housenumber":"225",
    "addr:postcode":"60601",
    "addr:street":"N Wabash Ave",
    "iso:country":"US",
    "sg:address":"225 N Wabash Ave",
    "sg:city":"Chicago",
    "sg:classifiers":[
        {
            "category":"Travel",
            "subcategory":"Hotels & Motels",
            "type":"Entertainment"
        }
    ],
    "sg:phone":"+1 312 960 8500",
    "sg:postcode":"60601",
    "sg:province":"IL",
    "sg:website":"www.monaco-chicago.com",
    "wof:name":"Hotel Monaco",
    "wof:placetype":"venue"
},
  "geometry": {"coordinates":[-87.62640399999999,41.8862],"type":"Point"}
}