{
  "type": "Feature",
  "properties": {
    "iso:country":"US",
    "sg:address":"901 8th St",
    "sg:city":"La Salle",
    "sg:classifiers":[
        {
            "category":"Personal",
            "subcategory":"Beauty Salon",
            "type":"Services"
        }
    ],
    "sg:phone":"+1 815 223 6063",
    "sg:postcode":"61301",
    "sg:province":"IL",
    "sg:tags":[
        "shop"
    ],
    "wof:name":"L A Designs",
    "wof:placetype":"venue"
},
  "geometry": {"coordinates":[-89.092503,41.336152],"type":"Point"}
}