{
  "type": "Feature",
  "properties": {
    "iso:country":"US",
    "sg:address":"502 E Broadway",
    "sg:city":"Centralia",
    "sg:classifiers":[
        {
            "category":"Shopping",
            "subcategory":"Used Merchandise",
            "type":"Retail Goods"
        }
    ],
    "sg:phone":"+1 618 545 5555",
    "sg:postcode":"62801",
    "sg:province":"IL",
    "sg:tags":[
        "antique"
    ],
    "wof:name":"Alley Way Antiques",
    "wof:placetype":"venue"
},
  "geometry": {"coordinates":[-89.129879,38.5269],"type":"Point"}
}