{
  "type": "Feature",
  "properties": {
    "iso:country":"US",
    "sg:address":"4315 Prescott Ave",
    "sg:city":"Lyons",
    "sg:classifiers":[
        {
            "category":"Building & Trades",
            "subcategory":"Plumbing",
            "type":"Services"
        }
    ],
    "sg:phone":"+1 708 485 1270",
    "sg:postcode":"60534",
    "sg:province":"IL",
    "sg:tags":[
        "contractor"
    ],
    "wof:name":"Modern Heat-N-Air",
    "wof:placetype":"venue"
},
  "geometry": {"coordinates":[-87.81931400000001,41.813159],"type":"Point"}
}