{
  "type": "Feature",
  "properties": {
    "iso:country":"US",
    "sg:address":"11240 S Avenue N G",
    "sg:city":"Chicago",
    "sg:classifiers":[
        {
            "category":"Education",
            "subcategory":"University",
            "type":"Public Place"
        }
    ],
    "sg:phone":"+1 312 695 0255",
    "sg:postcode":"60617",
    "sg:province":"IL",
    "sg:tags":[
        "college"
    ],
    "sg:website":"http://www.digital-kids.net",
    "wof:name":"Northwestern University Myocardial Research Lab",
    "wof:placetype":"venue"
},
  "geometry": {"coordinates":[-87.529449,41.692005],"type":"Point"}
}