{
  "type": "Feature",
  "properties": {
    "addr:full":"722 la Salle St Ottawa IL 61350",
    "addr:housenumber":"722",
    "addr:postcode":"61350",
    "addr:street":"La Salle St",
    "iso:country":"US",
    "sg:address":"722 la Salle St",
    "sg:city":"Ottawa",
    "sg:classifiers":[
        {
            "category":"Shopping",
            "subcategory":"Pets & Pet Supplies",
            "type":"Retail Goods"
        },
        {
            "category":"Shopping",
            "subcategory":"Party Supplies",
            "type":"Retail Goods"
        },
        {
            "category":"Professional",
            "subcategory":"Art Services",
            "type":"Services"
        }
    ],
    "sg:phone":"+1 815 434 4114",
    "sg:postcode":"61350",
    "sg:province":"IL",
    "sg:tags":[
        "photographers-portrait",
        "specialty",
        "wedding"
    ],
    "sg:website":"http://www.annettebarrphotography.com",
    "wof:name":"Annette Barr Photography Studio",
    "wof:placetype":"venue"
},
  "geometry": {"coordinates":[-88.84266100000001,41.347078],"type":"Point"}
}