{
  "type": "Feature",
  "properties": {
    "iso:country":"US",
    "sg:address":"205 E South Mahomet Rd",
    "sg:city":"Mahomet",
    "sg:classifiers":[
        {
            "category":"Professional",
            "subcategory":"Lawyer & Legal Services",
            "type":"Services"
        }
    ],
    "sg:phone":"+1 217 586 6384",
    "sg:postcode":"61853",
    "sg:province":"IL",
    "wof:name":"William H Cawley",
    "wof:placetype":"venue"
},
  "geometry": {"coordinates":[-88.405924,40.178503],"type":"Point"}
}