{
  "type": "Feature",
  "properties": {
    "iso:country":"US",
    "sg:address":"541 N Fairbanks Ct",
    "sg:city":"Chicago",
    "sg:classifiers":[
        {
            "category":"Banks & Credit Unions",
            "subcategory":"Investment Brokerage",
            "type":"Services"
        }
    ],
    "sg:phone":"+1 312 595 1200",
    "sg:postcode":"60611",
    "sg:province":"IL",
    "sg:tags":[
        "investing"
    ],
    "wof:name":"Agristar Global Networks Ltd",
    "wof:placetype":"venue"
},
  "geometry": {"coordinates":[-87.61990400000001,41.8918],"type":"Point"}
}