{
  "type": "Feature",
  "properties": {
    "addr:full":"3525 W Peterson Ave Chicago IL 60659",
    "addr:housenumber":"3525",
    "addr:postcode":"60659",
    "addr:street":"W Peterson Ave",
    "iso:country":"US",
    "sg:address":"3525 W Peterson Ave",
    "sg:city":"Chicago",
    "sg:classifiers":[
        {
            "category":"Insurance",
            "subcategory":"Insurance Agent",
            "type":"Services"
        },
        {
            "category":"Insurance",
            "subcategory":"Hazard Insurance",
            "type":"Services"
        },
        {
            "category":"Insurance",
            "subcategory":"Title Insurance",
            "type":"Services"
        }
    ],
    "sg:phone":"+1 773 539 5488",
    "sg:postcode":"60659",
    "sg:province":"IL",
    "sg:tags":[
        "auto",
        "homeowner"
    ],
    "sg:website":"http://apps.amfam.com/agentlocator/KJOHNSO9?sourceid=yp3",
    "wof:name":"American Family Insurance- Kristi Johnson",
    "wof:placetype":"venue"
},
  "geometry": {"coordinates":[-87.717448,41.990299],"type":"Point"}
}