{
  "type": "Feature",
  "properties": {
    "iso:country":"US",
    "sg:address":"108 E Wesley St",
    "sg:city":"Wheaton",
    "sg:classifiers":[
        {
            "category":"Organizations",
            "subcategory":"Professional Association",
            "type":"Services"
        }
    ],
    "sg:phone":"+1 630 668 6464",
    "sg:postcode":"60187",
    "sg:province":"IL",
    "sg:tags":[
        "business"
    ],
    "wof:name":"Wheaton Chamber of Commerce",
    "wof:placetype":"venue"
},
  "geometry": {"coordinates":[-88.105258,41.866075],"type":"Point"}
}