{
  "type": "Feature",
  "properties": {
    "iso:country":"US",
    "sg:address":"1708 SE 3rd St",
    "sg:city":"Aledo",
    "sg:classifiers":[
        {
            "category":"Sports & Exercise",
            "subcategory":"Bowling",
            "type":"Entertainment"
        }
    ],
    "sg:phone":"+1 309 582 5197",
    "sg:postcode":"61231",
    "sg:province":"IL",
    "sg:tags":[
        "center"
    ],
    "wof:name":"Millennium Lanes",
    "wof:placetype":"venue"
},
  "geometry": {"coordinates":[-90.730573,41.199473],"type":"Point"}
}