{
  "type": "Feature",
  "properties": {
    "iso:country":"US",
    "sg:address":"710 E Higgins Rd",
    "sg:city":"Schaumburg",
    "sg:phone":"+1 847 519 1008",
    "sg:postcode":"60173",
    "sg:province":"IL",
    "wof:name":"Art & Beauty Salon",
    "wof:placetype":"venue"
},
  "geometry": {"coordinates":[-88.062023,42.041287],"type":"Point"}
}