{
  "type": "Feature",
  "properties": {
    "addr:full":"114 S Jackson St Waukegan IL 60085",
    "addr:housenumber":"114",
    "addr:postcode":"60085",
    "addr:street":"S Jackson St",
    "iso:country":"US",
    "sg:address":"114 S Jackson St",
    "sg:city":"Waukegan",
    "sg:classifiers":[
        {
            "category":"Building & Trades",
            "subcategory":"Plumbing",
            "type":"Services"
        }
    ],
    "sg:phone":"+1 847 662 2847",
    "sg:postcode":"60085",
    "sg:province":"IL",
    "sg:tags":[
        "plumbing",
        "contractor"
    ],
    "wof:name":"Drinka Plumbing",
    "wof:placetype":"venue"
},
  "geometry": {"coordinates":[-87.84484,42.358234],"type":"Point"}
}