{
  "type": "Feature",
  "properties": {
    "addr:full":"8247 County Line Rd Collinsville IL 62234",
    "addr:housenumber":"8247",
    "addr:postcode":"62234",
    "addr:street":"County Line Rd",
    "iso:country":"US",
    "sg:address":"8247 County Line Rd",
    "sg:city":"Collinsville",
    "sg:classifiers":[
        {
            "category":"Organizations",
            "subcategory":"Religious Organization",
            "type":"Services"
        }
    ],
    "sg:phone":"+1 618 632 4477",
    "sg:postcode":"62234",
    "sg:province":"IL",
    "wof:name":"Troy Assembly Of God",
    "wof:placetype":"venue"
},
  "geometry": {"coordinates":[-89.87821599999999,38.65381],"type":"Point"}
}