{
  "type": "Feature",
  "properties": {
    "iso:country":"US",
    "sg:address":"400 Broadway",
    "sg:city":"Highland",
    "sg:classifiers":[
        {
            "category":"Wholesale",
            "subcategory":"Electrical",
            "type":"Manufacturing & Wholesale Goods"
        }
    ],
    "sg:phone":"+1 618 654 2371",
    "sg:postcode":"62249",
    "sg:province":"IL",
    "sg:tags":[
        "electric",
        "motor"
    ],
    "sg:website":"www.jakelinc.com",
    "wof:name":"Jakel Inc",
    "wof:placetype":"venue"
},
  "geometry": {"coordinates":[-89.68534099999999,38.739331],"type":"Point"}
}