{
  "type": "Feature",
  "properties": {
    "iso:country":"US",
    "sg:address":"2900 N Lake Shore Dr",
    "sg:city":"Chicago",
    "sg:phone":"+1 773 665 3317",
    "sg:postcode":"60657",
    "sg:province":"IL",
    "wof:name":"St Joseph Hosp Skilled Nursing",
    "wof:placetype":"venue"
},
  "geometry": {"coordinates":[-87.636723,41.934843],"type":"Point"}
}