{
  "type": "Feature",
  "properties": {
    "iso:country":"US",
    "sg:address":"200 W Marquette St",
    "sg:city":"Ottawa",
    "sg:classifiers":[
        {
            "category":"Retail",
            "subcategory":"Auto Repair",
            "type":"Services"
        }
    ],
    "sg:phone":"+1 815 433 0811",
    "sg:postcode":"61350",
    "sg:province":"IL",
    "sg:tags":[
        "repairing",
        "automobile",
        "general"
    ],
    "wof:name":"Skip's Auto Repair",
    "wof:placetype":"venue"
},
  "geometry": {"coordinates":[-88.844404,41.354184],"type":"Point"}
}