{
  "type": "Feature",
  "properties": {
    "iso:country":"US",
    "sg:address":"3450 Montgomery Rd",
    "sg:city":"Aurora",
    "sg:classifiers":[
        {
            "category":"Retail",
            "subcategory":"Veterinary Services",
            "type":"Services"
        }
    ],
    "sg:phone":"+1 630 820 2733",
    "sg:postcode":"60504",
    "sg:province":"IL",
    "sg:tags":[
        "veterinarian"
    ],
    "sg:website":"http://auroracatclinic.org/",
    "wof:name":"Aurora Cat Clinic",
    "wof:placetype":"venue"
},
  "geometry": {"coordinates":[-88.23150099999999,41.732271],"type":"Point"}
}