{
  "type": "Feature",
  "properties": {
    "iso:country":"US",
    "sg:address":"558 W Diversey Pkwy",
    "sg:city":"Chicago",
    "sg:classifiers":[
        {
            "category":"Banks & Credit Unions",
            "subcategory":"Investment Brokerage",
            "type":"Services"
        },
        {
            "category":"Banks & Credit Unions",
            "subcategory":"Bank",
            "type":"Services"
        }
    ],
    "sg:phone":"+1 773 880 2150",
    "sg:postcode":"60614",
    "sg:province":"IL",
    "sg:tags":[
        "commercial",
        "trust",
        "saving"
    ],
    "sg:website":"www.harrisbank.com",
    "wof:name":"Harris Bank",
    "wof:placetype":"venue"
},
  "geometry": {"coordinates":[-87.64340199999999,41.932899],"type":"Point"}
}