{
  "type": "Feature",
  "properties": {
    "addr:full":"9029 S Commercial Avenue Chicago IL 60617",
    "addr:housenumber":"9029",
    "addr:postcode":"60617",
    "addr:street":"S Commercial Avenue",
    "iso:country":"US",
    "sg:address":"9029 S Commercial Avenue",
    "sg:city":"Chicago",
    "sg:classifiers":[
        {
            "category":"Restaurant",
            "type":"Food & Drink"
        }
    ],
    "sg:phone":"+1 773 978 4981",
    "sg:postcode":"60617",
    "sg:province":"IL",
    "sg:tags":[
        "mexican"
    ],
    "wof:name":"El Guero Supermercado",
    "wof:placetype":"venue"
},
  "geometry": {"coordinates":[-87.550822,41.730991],"type":"Point"}
}