{
  "type": "Feature",
  "properties": {
    "addr:full":"310 N State St Lockport IL 60441",
    "addr:housenumber":"310",
    "addr:postcode":"60441",
    "addr:street":"N State St",
    "iso:country":"US",
    "sg:address":"310 N State St",
    "sg:city":"Lockport",
    "sg:classifiers":[
        {
            "category":"Travel",
            "subcategory":"Travel Agent",
            "type":"Entertainment"
        }
    ],
    "sg:phone":"+1 815 836 9970",
    "sg:postcode":"60441",
    "sg:province":"IL",
    "sg:tags":[
        "agency",
        "bureau"
    ],
    "wof:name":"Singles Travel Intl",
    "wof:placetype":"venue"
},
  "geometry": {"coordinates":[-88.05180799999999,41.601481],"type":"Point"}
}