{
  "type": "Feature",
  "properties": {
    "iso:country":"US",
    "sg:address":"320 N 9th St",
    "sg:city":"Breese",
    "sg:classifiers":[
        {
            "category":"Building & Trades",
            "subcategory":"Construction",
            "type":"Services"
        }
    ],
    "sg:phone":"+1 618 526 0014",
    "sg:postcode":"62230",
    "sg:province":"IL",
    "sg:tags":[
        "contractor"
    ],
    "wof:name":"Affordable Seamless Guttering",
    "wof:placetype":"venue"
},
  "geometry": {"coordinates":[-89.531401,38.615335],"type":"Point"}
}