{
  "type": "Feature",
  "properties": {
    "iso:country":"US",
    "sg:address":"3808 Hull St",
    "sg:city":"Skokie",
    "sg:classifiers":[
        {
            "category":"Professional",
            "subcategory":"Art Services",
            "type":"Services"
        }
    ],
    "sg:phone":"+1 847 677 5550",
    "sg:postcode":"60076",
    "sg:province":"IL",
    "sg:tags":[
        "photography",
        "commercial"
    ],
    "wof:name":"Luongo Photo",
    "wof:placetype":"venue"
},
  "geometry": {"coordinates":[-87.72418399999999,42.023636],"type":"Point"}
}