{
  "type": "Feature",
  "properties": {
    "iso:country":"US",
    "sg:address":"3036 W Sherwin Ave",
    "sg:city":"Chicago",
    "sg:classifiers":[
        {
            "category":"Professional",
            "subcategory":"Accounting & Tax Preparation",
            "type":"Services"
        }
    ],
    "sg:phone":"+1 773 617 6691",
    "sg:postcode":"60645",
    "sg:province":"IL",
    "wof:name":"Abraham H Bajtner Limited",
    "wof:placetype":"venue"
},
  "geometry": {"coordinates":[-87.705994,42.01473],"type":"Point"}
}