{
  "type": "Feature",
  "properties": {
    "addr:full":"838 W Sunnyside Ave Chicago IL 60640",
    "addr:housenumber":"838",
    "addr:postcode":"60640",
    "addr:street":"W Sunnyside Ave",
    "iso:country":"US",
    "sg:address":"838 W Sunnyside Ave",
    "sg:city":"Chicago",
    "sg:classifiers":[
        {
            "category":"Real Estate",
            "subcategory":"Real Estate Operator",
            "type":"Services"
        }
    ],
    "sg:phone":"+1 773 784 0459",
    "sg:postcode":"60640",
    "sg:province":"IL",
    "sg:tags":[
        "building",
        "apartment"
    ],
    "wof:name":"Sunnyside Apartments",
    "wof:placetype":"venue"
},
  "geometry": {"coordinates":[-87.652305,41.963563],"type":"Point"}
}