{
  "type": "Feature",
  "properties": {
    "addr:full":"3524 W 159th St Markham IL 60428",
    "addr:housenumber":"3524",
    "addr:postcode":"60428",
    "addr:street":"W 159Th St",
    "iso:country":"US",
    "sg:address":"3524 W 159th St",
    "sg:city":"Markham",
    "sg:classifiers":[
        {
            "category":"Travel",
            "subcategory":"Hotels & Motels",
            "type":"Entertainment"
        }
    ],
    "sg:phone":"+1 708 331 5866",
    "sg:postcode":"60428",
    "sg:province":"IL",
    "wof:name":"Hi Way Motel",
    "wof:placetype":"venue"
},
  "geometry": {"coordinates":[-87.70288499999999,41.60075],"type":"Point"}
}