{
  "type": "Feature",
  "properties": {
    "iso:country":"US",
    "sg:address":"1129 Timbertrails Rd",
    "sg:city":"Downers Grove",
    "sg:classifiers":[
        {
            "category":"Real Estate",
            "subcategory":"Real Estate Agent",
            "type":"Services"
        }
    ],
    "sg:phone":"+1 630 910 1830",
    "sg:postcode":"60516",
    "sg:province":"IL",
    "wof:name":"Miskus Estate Services",
    "wof:placetype":"venue"
},
  "geometry": {"coordinates":[-88.014582,41.722569],"type":"Point"}
}