{
  "type": "Feature",
  "properties": {
    "iso:country":"US",
    "sg:address":"1500 N Lewis Ave",
    "sg:city":"Waukegan",
    "sg:classifiers":[
        {
            "category":"Restaurant",
            "type":"Food & Drink"
        }
    ],
    "sg:phone":"+1   ",
    "sg:postcode":"60085",
    "sg:province":"IL",
    "sg:tags":[
        "pizza"
    ],
    "wof:name":"Jesters Bar",
    "wof:placetype":"venue"
},
  "geometry": {"coordinates":[-87.855546,42.378985],"type":"Point"}
}