{
  "type": "Feature",
  "properties": {
    "iso:country":"US",
    "sg:address":"3406 N Seminary Ave",
    "sg:city":"Chicago",
    "sg:classifiers":[
        {
            "category":"Cinema",
            "subcategory":"Movie Theater",
            "type":"Entertainment"
        }
    ],
    "sg:phone":"+1 773 871 3481",
    "sg:postcode":"60657",
    "sg:province":"IL",
    "sg:tags":[
        "theatrical",
        "consultant"
    ],
    "wof:name":"Chemically Imbalanced Production",
    "wof:placetype":"venue"
},
  "geometry": {"coordinates":[-87.65655099999999,41.943617],"type":"Point"}
}