{
  "type": "Feature",
  "properties": {
    "addr:full":"222 Merchandise Mart Plz Ste 204 Chicago IL 60654",
    "addr:housenumber":"222",
    "addr:postcode":"60654",
    "addr:street":"Merchandise Mart Plz Ste 204",
    "iso:country":"US",
    "sg:address":"222 Merchandise Mart Plz Ste 204",
    "sg:city":"Chicago",
    "sg:classifiers":[
        {
            "category":"Shopping",
            "subcategory":"Books",
            "type":"Retail Goods"
        }
    ],
    "sg:phone":"+1 312 329 1881",
    "sg:postcode":"60654",
    "sg:province":"IL",
    "sg:tags":[
        "bookstore",
        "store"
    ],
    "sg:website":"http://www.bdalton.com",
    "wof:name":"B Dalton Bookseller",
    "wof:placetype":"venue"
},
  "geometry": {"coordinates":[-87.635392,41.887901],"type":"Point"}
}