{
  "type": "Feature",
  "properties": {
    "addr:full":"3112 Whisperwoods Ct Northbrook IL 60062",
    "addr:housenumber":"3112",
    "addr:postcode":"60062",
    "addr:street":"Whisperwoods Ct",
    "iso:country":"US",
    "sg:address":"3112 Whisperwoods Ct",
    "sg:city":"Northbrook",
    "sg:classifiers":[
        {
            "category":"Professional",
            "subcategory":"Business Services",
            "type":"Services"
        }
    ],
    "sg:phone":"+1 847 400 5141",
    "sg:postcode":"60062",
    "sg:province":"IL",
    "wof:name":"Lifchitz MD Sc Alan J",
    "wof:placetype":"venue"
},
  "geometry": {"coordinates":[-87.857288,42.113727],"type":"Point"}
}