{
  "type": "Feature",
  "properties": {
    "iso:country":"US",
    "sg:address":"3729 Grand Blvd",
    "sg:city":"Brookfield",
    "sg:classifiers":[
        {
            "category":"Travel",
            "subcategory":"Travel Agent",
            "type":"Entertainment"
        }
    ],
    "sg:phone":"+1 708 485 1333",
    "sg:postcode":"60513",
    "sg:province":"IL",
    "sg:tags":[
        "agency"
    ],
    "wof:name":"Weber Travel Agency Inc",
    "wof:placetype":"venue"
},
  "geometry": {"coordinates":[-87.844601,41.822798],"type":"Point"}
}