{
  "type": "Feature",
  "properties": {
    "iso:country":"US",
    "sg:address":"2201 Wedgewood Dr",
    "sg:city":"Alton",
    "sg:classifiers":[
        {
            "category":"Building & Trades",
            "subcategory":"Construction",
            "type":"Services"
        }
    ],
    "sg:phone":"+1 618 462 1785",
    "sg:postcode":"62002",
    "sg:province":"IL",
    "sg:tags":[
        "general",
        "remodeling",
        "contractor"
    ],
    "wof:name":"Harold Seymour & Sons",
    "wof:placetype":"venue"
},
  "geometry": {"coordinates":[-90.15481800000001,38.938365],"type":"Point"}
}