{
  "type": "Feature",
  "properties": {
    "addr:full":"12760 S Palos Ave Palos Heights IL 60463",
    "addr:housenumber":"12760",
    "addr:postcode":"60463",
    "addr:street":"S Palos Ave",
    "iso:country":"US",
    "sg:address":"12760 S Palos Ave",
    "sg:city":"Palos Heights",
    "sg:classifiers":[
        {
            "category":"Professional",
            "subcategory":"Business Services",
            "type":"Services"
        }
    ],
    "sg:phone":"+1 708 361 6900",
    "sg:postcode":"60463",
    "sg:province":"IL",
    "sg:tags":[
        "packaging"
    ],
    "wof:name":"Ability Packaging Corp",
    "wof:placetype":"venue"
},
  "geometry": {"coordinates":[-87.797878,41.660229],"type":"Point"}
}