{
  "type": "Feature",
  "properties": {
    "iso:country":"US",
    "sg:address":"4971 Cal Sag Rd",
    "sg:city":"Crestwood",
    "sg:classifiers":[
        {
            "category":"Shopping",
            "subcategory":"Department Store",
            "type":"Retail Goods"
        }
    ],
    "sg:phone":"+1 708 389 5783",
    "sg:postcode":"60445",
    "sg:province":"IL",
    "sg:website":"www.tjmaxx.com",
    "wof:name":"T J Maxx",
    "wof:placetype":"venue"
},
  "geometry": {"coordinates":[-87.742599,41.655602],"type":"Point"}
}