{
  "type": "Feature",
  "properties": {
    "addr:full":"818 Main St Highland IL 62249",
    "addr:housenumber":"818",
    "addr:postcode":"62249",
    "addr:street":"Main St",
    "iso:country":"US",
    "sg:address":"818 Main St",
    "sg:city":"Highland",
    "sg:classifiers":[
        {
            "category":"Shopping",
            "type":"Retail Goods"
        }
    ],
    "sg:phone":"+1 618 654 6767",
    "sg:postcode":"62249",
    "sg:province":"IL",
    "sg:tags":[
        "hearing",
        "equipment",
        "supply",
        "impaired"
    ],
    "wof:name":"Hearing Care Ctr Of Highland",
    "wof:placetype":"venue"
},
  "geometry": {"coordinates":[-89.681378,38.740364],"type":"Point"}
}