{
  "type": "Feature",
  "properties": {
    "iso:country":"US",
    "sg:address":"19250 Everett Ln",
    "sg:city":"Mokena",
    "sg:classifiers":[
        {
            "category":"Professional",
            "subcategory":"Accounting & Tax Preparation",
            "type":"Services"
        }
    ],
    "sg:phone":"+1 708 478 4650",
    "sg:postcode":"60448",
    "sg:province":"IL",
    "sg:tags":[
        "accountant"
    ],
    "wof:name":"Hearne & Assoc PC",
    "wof:placetype":"venue"
},
  "geometry": {"coordinates":[-87.856475,41.539239],"type":"Point"}
}