{
  "type": "Feature",
  "properties": {
    "iso:country":"US",
    "sg:address":"9818 S Michigan Avenue",
    "sg:city":"Chicago",
    "sg:classifiers":[
        {
            "category":"Restaurant",
            "type":"Food & Drink"
        },
        {
            "category":"Food & Beverages",
            "subcategory":"Groceries & Convenience Stores",
            "type":"Retail Goods"
        }
    ],
    "sg:phone":"+1 773 264 4764",
    "sg:postcode":"60628",
    "sg:province":"IL",
    "wof:name":"Mama Jones Burgers",
    "wof:placetype":"venue"
},
  "geometry": {"coordinates":[-87.620581,41.715722],"type":"Point"}
}