{
  "type": "Feature",
  "properties": {
    "iso:country":"US",
    "sg:address":"3767 N Racine Avenue",
    "sg:city":"Chicago",
    "sg:classifiers":[
        {
            "category":"Real Estate",
            "subcategory":"Real Estate Operator",
            "type":"Services"
        }
    ],
    "sg:phone":"+1 773 929 1620",
    "sg:postcode":"60613",
    "sg:province":"IL",
    "sg:tags":[
        "apartment"
    ],
    "wof:name":"H A Langer & Associates",
    "wof:placetype":"venue"
},
  "geometry": {"coordinates":[-87.659402,41.951337],"type":"Point"}
}