{
  "type": "Feature",
  "properties": {
    "iso:country":"US",
    "sg:address":"2250 W North Ave",
    "sg:city":"Chicago",
    "sg:classifiers":[
        {
            "category":"Professional",
            "subcategory":"Business Services",
            "type":"Services"
        }
    ],
    "sg:phone":"+1 773 862 1880",
    "sg:postcode":"60647",
    "sg:province":"IL",
    "sg:tags":[
        "recording",
        "rehearsal",
        "studio"
    ],
    "sg:website":"www.gravitystudios.com",
    "wof:name":"Gravity Studios",
    "wof:placetype":"venue"
},
  "geometry": {"coordinates":[-87.684327,41.91055],"type":"Point"}
}