{
  "type": "Feature",
  "properties": {
    "iso:country":"US",
    "sg:address":"6180 Sky Ranch Rd",
    "sg:city":"Manito",
    "sg:classifiers":[
        {
            "category":"Retail",
            "subcategory":"Repair Shop",
            "type":"Services"
        }
    ],
    "sg:phone":"+1 309 545 3117",
    "sg:postcode":"61546",
    "sg:province":"IL",
    "sg:tags":[
        "upholsterer"
    ],
    "wof:name":"Springlake Upholstery",
    "wof:placetype":"venue"
},
  "geometry": {"coordinates":[-89.80907999999999,40.507643],"type":"Point"}
}