{
  "type": "Feature",
  "properties": {
    "iso:country":"US",
    "sg:address":"345 Sullivan Rd",
    "sg:city":"Aurora",
    "sg:classifiers":[
        {
            "category":"Health Services",
            "subcategory":"Doctor",
            "type":"Services"
        }
    ],
    "sg:phone":"+1 630 892 3993",
    "sg:postcode":"60506",
    "sg:province":"IL",
    "wof:name":"Aurora Dental Specialists",
    "wof:placetype":"venue"
},
  "geometry": {"coordinates":[-88.32347,41.788733],"type":"Point"}
}