{
  "type": "Feature",
  "properties": {
    "iso:country":"US",
    "sg:address":"1307 W Washington St # 115",
    "sg:city":"Oregon",
    "sg:classifiers":[
        {
            "category":"Health Services",
            "subcategory":"Chiropractor",
            "type":"Services"
        }
    ],
    "sg:phone":"+1 815 732 2826",
    "sg:postcode":"61061",
    "sg:province":"IL",
    "sg:tags":[
        "chiropractic"
    ],
    "wof:name":"Rock Valley Chiropractic Assoc",
    "wof:placetype":"venue"
},
  "geometry": {"coordinates":[-89.342145,42.017943],"type":"Point"}
}