{
  "type": "Feature",
  "properties": {
    "iso:country":"US",
    "sg:address":"2700 S 21st Ave",
    "sg:city":"Broadview",
    "sg:classifiers":[
        {
            "category":"Manufacturing",
            "subcategory":"Metals",
            "type":"Manufacturing & Wholesale Goods"
        }
    ],
    "sg:phone":"+1 708 865 2000",
    "sg:postcode":"60155",
    "sg:province":"IL",
    "sg:tags":[
        "finishing",
        "coloring",
        "coating",
        "powder"
    ],
    "wof:name":"Alton Industries Inc",
    "wof:placetype":"venue"
},
  "geometry": {"coordinates":[-87.85774499999999,41.855962],"type":"Point"}
}