{
  "type": "Feature",
  "properties": {
    "iso:country":"US",
    "sg:address":"3900 W 95th St Ste 3",
    "sg:city":"Evergreen Park",
    "sg:classifiers":[
        {
            "category":"Banks & Credit Unions",
            "subcategory":"Financial Services",
            "type":"Services"
        }
    ],
    "sg:phone":"+1 708 424 7933",
    "sg:postcode":"60805",
    "sg:province":"IL",
    "sg:tags":[
        "broker",
        "mortgage"
    ],
    "wof:name":"Professional Financial Mortgage",
    "wof:placetype":"venue"
},
  "geometry": {"coordinates":[-87.718903,41.720501],"type":"Point"}
}