{
  "type": "Feature",
  "properties": {
    "addr:full":"9050 S Roberts Rd Oak Lawn IL 60457",
    "addr:housenumber":"9050",
    "addr:postcode":"60457",
    "addr:street":"S Roberts Rd",
    "iso:country":"US",
    "sg:address":"9050 S Roberts Rd",
    "sg:city":"Oak Lawn",
    "sg:classifiers":[
        {
            "category":"Freight",
            "type":"Transportation"
        }
    ],
    "sg:phone":"+1 708 598 5958",
    "sg:postcode":"60457",
    "sg:province":"IL",
    "sg:tags":[
        "operator",
        "trucking"
    ],
    "wof:name":"Javd Transportation Inc",
    "wof:placetype":"venue"
},
  "geometry": {"coordinates":[-87.818246,41.725851],"type":"Point"}
}