{
  "type": "Feature",
  "properties": {
    "addr:full":"1621 Thornton Rd Lansing IL 60438",
    "addr:housenumber":"1621",
    "addr:postcode":"60438",
    "addr:street":"Thornton Rd",
    "iso:country":"US",
    "sg:address":"1621 Thornton Rd",
    "sg:city":"Lansing",
    "sg:classifiers":[
        {
            "category":"Wholesale",
            "subcategory":"Auto Parts",
            "type":"Manufacturing & Wholesale Goods"
        }
    ],
    "sg:phone":"+1 708 895 2505",
    "sg:postcode":"60438",
    "sg:province":"IL",
    "sg:tags":[
        "machine",
        "automotive",
        "shop"
    ],
    "wof:name":"Toth Automotive",
    "wof:placetype":"venue"
},
  "geometry": {"coordinates":[-87.574371,41.569535],"type":"Point"}
}