{
  "type": "Feature",
  "properties": {
    "addr:full":"20314 Hickory Hills Rd Sterling IL 61081",
    "addr:housenumber":"20314",
    "addr:postcode":"61081",
    "addr:street":"Hickory Hills Rd",
    "iso:country":"US",
    "sg:address":"20314 Hickory Hills Rd",
    "sg:city":"Sterling",
    "sg:classifiers":[
        {
            "category":"Place Of Worship",
            "subcategory":"Church",
            "type":"Public Place"
        },
        {
            "category":"Place Of Worship",
            "type":"Public Place"
        }
    ],
    "sg:phone":"+1 815 625 5407",
    "sg:postcode":"61081",
    "sg:province":"IL",
    "sg:tags":[
        "lutheran",
        "america",
        "churches-lutheran",
        "churches-lutheran-evangelical"
    ],
    "wof:name":"First Ev. Lutheran Church Of Jordan",
    "wof:placetype":"venue"
},
  "geometry": {"coordinates":[-89.72613800000001,41.883266],"type":"Point"}
}