{
  "type": "Feature",
  "properties": {
    "iso:country":"US",
    "sg:address":"618 Library Pl",
    "sg:city":"Evanston",
    "sg:classifiers":[
        {
            "category":"Health Services",
            "subcategory":"Doctor",
            "type":"Services"
        },
        {
            "category":"Social Services",
            "type":"Services"
        }
    ],
    "sg:phone":"+1 866 849 6669",
    "sg:postcode":"60201",
    "sg:province":"IL",
    "sg:tags":[
        "family",
        "psychologist",
        "individual",
        "marriage",
        "child",
        "counselor"
    ],
    "sg:website":"http://www.family-institute.org",
    "wof:name":"The Family Institute At Northwestern University",
    "wof:placetype":"venue"
},
  "geometry": {"coordinates":[-87.67701,42.054955],"type":"Point"}
}