{
  "type": "Feature",
  "properties": {
    "iso:country":"US",
    "sg:address":"15941 Wood St",
    "sg:city":"Harvey",
    "sg:classifiers":[
        {
            "category":"Travel",
            "subcategory":"Hotels & Motels",
            "type":"Entertainment"
        }
    ],
    "sg:phone":"+1 708 596 3399",
    "sg:postcode":"60426",
    "sg:province":"IL",
    "wof:name":"Beacon Motel",
    "wof:placetype":"venue"
},
  "geometry": {"coordinates":[-87.6605,41.5994],"type":"Point"}
}