{
  "type": "Feature",
  "properties": {
    "iso:country":"US",
    "sg:address":"2645 Lorado Ln",
    "sg:city":"Rockford",
    "sg:classifiers":[
        {
            "category":"Retail",
            "subcategory":"Repair Shop",
            "type":"Services"
        }
    ],
    "sg:phone":"+1 815 636 8241",
    "sg:postcode":"61101",
    "sg:province":"IL",
    "sg:tags":[
        "high",
        "fidelity",
        "stereophonic"
    ],
    "wof:name":"T M Speaker Repair & Rebuild",
    "wof:placetype":"venue"
},
  "geometry": {"coordinates":[-89.100391,42.31262],"type":"Point"}
}