{
  "type": "Feature",
  "properties": {
    "iso:country":"US",
    "sg:address":"8521 S Commercial Ave",
    "sg:city":"Chicago",
    "sg:classifiers":[
        {
            "category":"Place Of Worship",
            "subcategory":"Church",
            "type":"Public Place"
        },
        {
            "category":"Place Of Worship",
            "type":"Public Place"
        }
    ],
    "sg:phone":"+1 773 978 5822",
    "sg:postcode":"60617",
    "sg:province":"IL",
    "sg:tags":[
        "christ",
        "churches-community"
    ],
    "wof:name":"Cornerstone Church Of Chicago",
    "wof:placetype":"venue"
},
  "geometry": {"coordinates":[-87.551491,41.740649],"type":"Point"}
}