{
  "type": "Feature",
  "properties": {
    "iso:country":"US",
    "sg:address":"7325 Hamlin Ave",
    "sg:city":"Skokie",
    "sg:classifiers":[
        {
            "category":"Retail",
            "subcategory":"Auto Repair",
            "type":"Services"
        }
    ],
    "sg:phone":"+1 847 677 5877",
    "sg:postcode":"60076",
    "sg:province":"IL",
    "sg:tags":[
        "general"
    ],
    "wof:name":"Village Auto Repair",
    "wof:placetype":"venue"
},
  "geometry": {"coordinates":[-87.723591,42.01403],"type":"Point"}
}