{
  "type": "Feature",
  "properties": {
    "addr:full":"7440 Archer Ave Summit Argo IL 60501",
    "addr:housenumber":"7440",
    "addr:postcode":"60501",
    "addr:street":"Archer Ave",
    "iso:country":"US",
    "sg:address":"7440 Archer Ave",
    "sg:city":"Summit Argo",
    "sg:classifiers":[
        {
            "category":"Building & Trades",
            "subcategory":"Plumbing",
            "type":"Services"
        }
    ],
    "sg:phone":"+1 708 563 9283",
    "sg:postcode":"60501",
    "sg:province":"IL",
    "sg:tags":[
        "air",
        "heating",
        "conditioning",
        "contractor"
    ],
    "wof:name":"Renaissance Service Inc",
    "wof:placetype":"venue"
},
  "geometry": {"coordinates":[-87.808533,41.791747],"type":"Point"}
}