{
  "type": "Feature",
  "properties": {
    "iso:country":"US",
    "sg:address":"322 Olympian Blvd",
    "sg:city":"Beloit",
    "sg:classifiers":[
        {
            "category":"Organizations",
            "subcategory":"Religious Organization",
            "type":"Services"
        }
    ],
    "sg:phone":"+1 608 362 7547",
    "sg:postcode":"53511",
    "sg:province":"IL",
    "wof:name":"Cornerstone Church Of God",
    "wof:placetype":"venue"
},
  "geometry": {"coordinates":[-89.04307900000001,42.515991],"type":"Point"}
}