{
  "type": "Feature",
  "properties": {
    "iso:country":"US",
    "sg:address":"754 Cypress Ln",
    "sg:city":"Carol Stream",
    "sg:classifiers":[
        {
            "category":"Shopping",
            "type":"Retail Goods"
        }
    ],
    "sg:phone":"+1 630 876 8870",
    "sg:postcode":"60188",
    "sg:province":"IL",
    "sg:tags":[
        "equipment",
        "telephone",
        "supply"
    ],
    "wof:name":"Call One Inc",
    "wof:placetype":"venue"
},
  "geometry": {"coordinates":[-88.16533800000001,41.921703],"type":"Point"}
}