{
  "type": "Feature",
  "properties": {
    "addr:full":"1019 W Foster Avenue Chicago IL 60640",
    "addr:housenumber":"1019",
    "addr:postcode":"60640",
    "addr:street":"W Foster Avenue",
    "iso:country":"US",
    "sg:address":"1019 W Foster Avenue",
    "sg:city":"Chicago",
    "sg:classifiers":[
        {
            "category":"Building & Trades",
            "subcategory":"Cleaning & Sanitation",
            "type":"Services"
        }
    ],
    "sg:phone":"+1 773 728 0366",
    "sg:postcode":"60640",
    "sg:province":"IL",
    "sg:tags":[
        "carpet"
    ],
    "sg:website":"www.servicemaster.com",
    "wof:name":"Service Master",
    "wof:placetype":"venue"
},
  "geometry": {"coordinates":[-87.65569499999999,41.976324],"type":"Point"}
}