{
  "type": "Feature",
  "properties": {
    "iso:country":"US",
    "sg:address":"3807 N Western Avenue",
    "sg:city":"Chicago",
    "sg:classifiers":[
        {
            "category":"Retail",
            "subcategory":"Veterinary Services",
            "type":"Services"
        }
    ],
    "sg:phone":"+1 773 478 7070",
    "sg:postcode":"60618",
    "sg:province":"IL",
    "sg:tags":[
        "veterinarian"
    ],
    "wof:name":"Lincolnwood Animal Hospital",
    "wof:placetype":"venue"
},
  "geometry": {"coordinates":[-87.688508,41.951128],"type":"Point"}
}