{
  "type": "Feature",
  "properties": {
    "addr:full":"190 Half Moon Bay Ct Romeoville IL 60446",
    "addr:housenumber":"190",
    "addr:postcode":"60446",
    "addr:street":"Half Moon Bay Ct",
    "iso:country":"US",
    "sg:address":"190 Half Moon Bay Ct",
    "sg:city":"Romeoville",
    "sg:classifiers":[
        {
            "category":"Health Services",
            "subcategory":"Clinic",
            "type":"Services"
        },
        {
            "category":"Insurance",
            "subcategory":"Hazard Insurance",
            "type":"Services"
        },
        {
            "category":"Insurance",
            "subcategory":"Health Insurance",
            "type":"Services"
        }
    ],
    "sg:phone":"+1 815 886 4454",
    "sg:postcode":"60446",
    "sg:province":"IL",
    "sg:tags":[
        "medical",
        "maintenance"
    ],
    "sg:website":"http://www.chcla.com",
    "wof:name":"Coventry Health Care, Inc.",
    "wof:placetype":"venue"
},
  "geometry": {"coordinates":[-88.112717,41.632641],"type":"Point"}
}