{
  "type": "Feature",
  "properties": {
    "addr:full":"807 Garfield St Oak Park IL 60304",
    "addr:housenumber":"807",
    "addr:postcode":"60304",
    "addr:street":"Garfield St",
    "iso:country":"US",
    "sg:address":"807 Garfield St",
    "sg:city":"Oak Park",
    "sg:classifiers":[
        {
            "category":"Real Estate",
            "subcategory":"Real Estate Agent",
            "type":"Services"
        }
    ],
    "sg:phone":"+1 708 848 0830",
    "sg:postcode":"60304",
    "sg:province":"IL",
    "wof:name":"Covenant Realty Management LLC",
    "wof:placetype":"venue"
},
  "geometry": {"coordinates":[-87.79415899999999,41.871955],"type":"Point"}
}