{
  "type": "Feature",
  "properties": {
    "addr:full":"1824 W Cortland St Chicago IL 60622",
    "addr:housenumber":"1824",
    "addr:postcode":"60622",
    "addr:street":"W Cortland St",
    "iso:country":"US",
    "sg:address":"1824 W Cortland St",
    "sg:city":"Chicago",
    "sg:classifiers":[
        {
            "category":"Restaurant",
            "type":"Food & Drink"
        },
        {
            "category":"Community Center",
            "subcategory":"Social",
            "type":"Public Place"
        }
    ],
    "sg:phone":"+1 773 278 0093",
    "sg:postcode":"60622",
    "sg:province":"IL",
    "sg:tags":[
        "club",
        "flavor",
        "local"
    ],
    "sg:website":"www.legion.org",
    "wof:name":"American Legion - Franklin Delano Roosevelt Post No 923",
    "wof:placetype":"venue"
},
  "geometry": {"coordinates":[-87.67375800000001,41.916267],"type":"Point"}
}