{
  "type": "Feature",
  "properties": {
    "iso:country":"US",
    "sg:address":"624 N York St",
    "sg:city":"Elmhurst",
    "sg:classifiers":[
        {
            "category":"Travel",
            "subcategory":"Hotels & Motels",
            "type":"Entertainment"
        },
        {
            "category":"Retail",
            "subcategory":"Event Space",
            "type":"Services"
        },
        {
            "category":"Travel",
            "subcategory":"Resort",
            "type":"Entertainment"
        }
    ],
    "sg:phone":"+1 800 345 8082",
    "sg:postcode":"60126",
    "sg:province":"IL",
    "sg:tags":[
        "hall",
        "lodging",
        "banquet",
        "reception",
        "facility"
    ],
    "sg:website":"http://ad.doubleclick.net/clk;223371278;47096201;d?http://www.holidayinn.com/redirect?path=hd&brandCode=hi&hotelCode=chieh&_PMID=99601036&cm_mmc=mdpr-_-yellowpages-_-hi-_-chieh",
    "wof:name":"Holiday Inn Chicago-Elmhurst",
    "wof:placetype":"venue"
},
  "geometry": {"coordinates":[-87.93971500000001,41.917364],"type":"Point"}
}