{
  "type": "Feature",
  "properties": {
    "iso:country":"US",
    "sg:address":"664 Wesley Dr",
    "sg:city":"Wood River",
    "sg:classifiers":[
        {
            "category":"Restaurant",
            "type":"Food & Drink"
        }
    ],
    "sg:menulink":"http://www.allmenus.com/il/wood-river/127585-subway/menu/",
    "sg:phone":"+1 618 259 7970",
    "sg:postcode":"62095",
    "sg:province":"IL",
    "sg:tags":[
        "american",
        "sandwich"
    ],
    "wof:name":"Subway",
    "wof:placetype":"venue"
},
  "geometry": {"coordinates":[-90.067277,38.870824],"type":"Point"}
}