{
  "type": "Feature",
  "properties": {
    "iso:country":"US",
    "sg:address":"1325 Remington Rd",
    "sg:city":"Schaumburg",
    "sg:classifiers":[
        {
            "category":"Professional",
            "subcategory":"Computer Services",
            "type":"Services"
        }
    ],
    "sg:phone":"+1 847 717 7647",
    "sg:postcode":"60173",
    "sg:province":"IL",
    "sg:tags":[
        "linux",
        "monitoring"
    ],
    "sg:website":"http://www.supportpro.com",
    "wof:name":"SupportPRO",
    "wof:placetype":"venue"
},
  "geometry": {"coordinates":[-88.051541,42.053227],"type":"Point"}
}