{
  "type": "Feature",
  "properties": {
    "iso:country":"US",
    "sg:address":"2246 Kenilworth Ave",
    "sg:city":"Berwyn",
    "sg:classifiers":[
        {
            "category":"Personal",
            "subcategory":"Beauty Salon",
            "type":"Services"
        }
    ],
    "sg:phone":"+1 708 795 9144",
    "sg:postcode":"60402",
    "sg:province":"IL",
    "wof:name":"Split Rock",
    "wof:placetype":"venue"
},
  "geometry": {"coordinates":[-87.795751,41.849683],"type":"Point"}
}