{
  "type": "Feature",
  "properties": {
    "addr:full":"77 W Washington Street Suite 1500 Chicago IL 60602",
    "addr:housenumber":"77",
    "addr:postcode":"60602",
    "addr:street":"W Washington Street Suite 1500",
    "iso:country":"US",
    "sg:address":"77 W Washington Street Suite 1500",
    "sg:city":"Chicago",
    "sg:classifiers":[
        {
            "category":"Professional",
            "subcategory":"Lawyer & Legal Services",
            "type":"Services"
        }
    ],
    "sg:phone":"+1 312 236 8628",
    "sg:postcode":"60602",
    "sg:province":"IL",
    "sg:tags":[
        "personal",
        "injury"
    ],
    "wof:name":"Jacobson & Sorkin Ltd",
    "wof:placetype":"venue"
},
  "geometry": {"coordinates":[-87.630084,41.883183],"type":"Point"}
}