{
  "type": "Feature",
  "properties": {
    "addr:full":"683 Co Rd 450 N Norris City IL 62869",
    "addr:housenumber":"683;450 n",
    "addr:postcode":"62869",
    "addr:street":"Co Rd",
    "iso:country":"US",
    "sg:address":"683 Co Rd 450 N",
    "sg:city":"Norris City",
    "sg:classifiers":[
        {
            "category":"Government",
            "subcategory":"Office",
            "type":"Public Place"
        }
    ],
    "sg:phone":"+1   ",
    "sg:postcode":"62869",
    "sg:province":"IL",
    "sg:tags":[
        "govt",
        "executive"
    ],
    "wof:name":"Heralds Prairie Township of",
    "wof:placetype":"venue"
},
  "geometry": {"coordinates":[-88.246471,37.944698],"type":"Point"}
}