{
  "type": "Feature",
  "properties": {
    "addr:full":"903 W 35th St Chicago IL 60609",
    "addr:housenumber":"903",
    "addr:postcode":"60609",
    "addr:street":"W 35Th St",
    "iso:country":"US",
    "sg:address":"903 W 35th St",
    "sg:city":"Chicago",
    "sg:classifiers":[
        {
            "category":"Government",
            "subcategory":"Post Office",
            "type":"Public Place"
        }
    ],
    "sg:phone":"+1 773 843 0108",
    "sg:postcode":"60609",
    "sg:province":"IL",
    "sg:tags":[
        "receiving",
        "mailbox-rental"
    ],
    "wof:name":"Mail Max",
    "wof:placetype":"venue"
},
  "geometry": {"coordinates":[-87.647874,41.830728],"type":"Point"}
}