{
  "type": "Feature",
  "properties": {
    "iso:country":"US",
    "sg:address":"3 Grandbrook Blvd",
    "sg:city":"Collinsville",
    "sg:classifiers":[
        {
            "category":"Real Estate",
            "subcategory":"Real Estate Operator",
            "type":"Services"
        }
    ],
    "sg:phone":"+1 618 344 9187",
    "sg:postcode":"62234",
    "sg:province":"IL",
    "sg:tags":[
        "building",
        "apartment"
    ],
    "wof:name":"Kocot Apts",
    "wof:placetype":"venue"
},
  "geometry": {"coordinates":[-89.99108099999999,38.686758],"type":"Point"}
}