{
  "type": "Feature",
  "properties": {
    "iso:country":"US",
    "sg:address":"3703 N Main St",
    "sg:city":"Rockford",
    "sg:classifiers":[
        {
            "category":"Home & Garden",
            "subcategory":"Furniture",
            "type":"Retail Goods"
        }
    ],
    "sg:phone":"+1   ",
    "sg:postcode":"61103",
    "sg:province":"IL",
    "sg:tags":[
        "gallery",
        "store"
    ],
    "wof:name":"Pennsylvania House",
    "wof:placetype":"venue"
},
  "geometry": {"coordinates":[-89.077195,42.31761],"type":"Point"}
}