{
  "type": "Feature",
  "properties": {
    "addr:full":"3103 S Kedzie Ave Chicago IL 60623",
    "addr:housenumber":"3103",
    "addr:postcode":"60623",
    "addr:street":"S Kedzie Ave",
    "iso:country":"US",
    "sg:address":"3103 S Kedzie Ave",
    "sg:city":"Chicago",
    "sg:classifiers":[
        {
            "category":"Personal",
            "type":"Services"
        }
    ],
    "sg:phone":"+1 773 737 1803",
    "sg:postcode":"60623",
    "sg:province":"IL",
    "sg:tags":[
        "towing"
    ],
    "wof:name":"Jamie Towing",
    "wof:placetype":"venue"
},
  "geometry": {"coordinates":[-87.704903,41.836399],"type":"Point"}
}