{
  "type": "Feature",
  "properties": {
    "iso:country":"US",
    "sg:address":"307 N Willis St",
    "sg:city":"Heyworth",
    "sg:classifiers":[
        {
            "category":"Professional",
            "subcategory":"Testing Lab",
            "type":"Services"
        }
    ],
    "sg:phone":"+1 309 473 2867",
    "sg:postcode":"61745",
    "sg:province":"IL",
    "sg:tags":[
        "correction",
        "radon"
    ],
    "wof:name":"Area Radon Svc",
    "wof:placetype":"venue"
},
  "geometry": {"coordinates":[-88.976311,40.317726],"type":"Point"}
}