{
  "type": "Feature",
  "properties": {
    "addr:full":"46 Magnolia Dr Belleville IL 62221",
    "addr:housenumber":"46",
    "addr:postcode":"62221",
    "addr:street":"Magnolia Dr",
    "iso:country":"US",
    "sg:address":"46 Magnolia Dr",
    "sg:city":"Belleville",
    "sg:classifiers":[
        {
            "category":"Professional",
            "subcategory":"Management & Consulting",
            "type":"Services"
        },
        {
            "category":"Education",
            "subcategory":"Special Training",
            "type":"Public Place"
        }
    ],
    "sg:phone":"+1 618 234 0850",
    "sg:postcode":"62221",
    "sg:province":"IL",
    "wof:name":"Quantum III Consultants Inc",
    "wof:placetype":"venue"
},
  "geometry": {"coordinates":[-89.939831,38.525622],"type":"Point"}
}