{
  "type": "Feature",
  "properties": {
    "iso:country":"US",
    "sg:address":"6316 N Kedvale Ave",
    "sg:city":"Chicago",
    "sg:classifiers":[
        {
            "category":"Building & Trades",
            "subcategory":"Electrical",
            "type":"Services"
        }
    ],
    "sg:phone":"+1 773 777 1869",
    "sg:postcode":"60646",
    "sg:province":"IL",
    "sg:tags":[
        "electrical",
        "contractor"
    ],
    "wof:name":"S&D Electric Construction",
    "wof:placetype":"venue"
},
  "geometry": {"coordinates":[-87.73262699999999,41.996499],"type":"Point"}
}