{
  "type": "Feature",
  "properties": {
    "iso:country":"US",
    "sg:address":"1862 Fox Run Dr",
    "sg:city":"Elk Grove Village",
    "sg:classifiers":[
        {
            "category":"Manufacturing",
            "subcategory":"Printing",
            "type":"Manufacturing & Wholesale Goods"
        }
    ],
    "sg:phone":"+1 847 891 7714",
    "sg:postcode":"60007",
    "sg:province":"IL",
    "sg:tags":[
        "book"
    ],
    "wof:name":"Aqua Art Publishing",
    "wof:placetype":"venue"
},
  "geometry": {"coordinates":[-88.059677,42.018573],"type":"Point"}
}