{
  "type": "Feature",
  "properties": {
    "iso:country":"US",
    "sg:address":"43 E Chicago Avenue",
    "sg:city":"Chicago",
    "sg:classifiers":[
        {
            "category":"Restaurant",
            "type":"Food & Drink"
        }
    ],
    "sg:phone":"+1 312 915 0355",
    "sg:postcode":"60611",
    "sg:province":"IL",
    "wof:name":"Mrj Family Sub",
    "wof:placetype":"venue"
},
  "geometry": {"coordinates":[-87.626206,41.896802],"type":"Point"}
}