{
  "type": "Feature",
  "properties": {
    "iso:country":"US",
    "sg:address":"8707 Skokie Blvd",
    "sg:city":"Skokie",
    "sg:classifiers":[
        {
            "category":"Health Services",
            "subcategory":"Clinic",
            "type":"Services"
        }
    ],
    "sg:phone":"+1 847 677 0364",
    "sg:postcode":"60077",
    "sg:province":"IL",
    "sg:tags":[
        "home",
        "employment",
        "temp",
        "care"
    ],
    "wof:name":"Kelly Services",
    "wof:placetype":"venue"
},
  "geometry": {"coordinates":[-87.747041,42.039621],"type":"Point"}
}