{
  "type": "Feature",
  "properties": {
    "iso:country":"US",
    "sg:address":"5768 W 2000N Rd",
    "sg:city":"Bonfield",
    "sg:classifiers":[
        {
            "category":"Real Estate",
            "subcategory":"Architect",
            "type":"Services"
        }
    ],
    "sg:phone":"+1 815 592 1687",
    "sg:postcode":"60913",
    "sg:province":"IL",
    "sg:tags":[
        "home",
        "planning",
        "design"
    ],
    "wof:name":"Nids Custom Designs",
    "wof:placetype":"venue"
},
  "geometry": {"coordinates":[-87.984226,41.147201],"type":"Point"}
}