{
  "type": "Feature",
  "properties": {
    "iso:country":"US",
    "sg:address":"1802 Washington St",
    "sg:city":"Waukegan",
    "sg:phone":"+1 847 662 1388",
    "sg:postcode":"60085",
    "sg:province":"IL",
    "wof:name":"Hong Kong Chinese Restaurant",
    "wof:placetype":"venue"
},
  "geometry": {"coordinates":[-87.854652,42.35971],"type":"Point"}
}