{
  "type": "Feature",
  "properties": {
    "iso:country":"US",
    "sg:address":"200 Rockland Rd",
    "sg:city":"Lake Bluff",
    "sg:classifiers":[
        {
            "category":"Professional",
            "subcategory":"Management & Consulting",
            "type":"Services"
        }
    ],
    "sg:phone":"+1 847 295 7788",
    "sg:postcode":"60044",
    "sg:province":"IL",
    "sg:tags":[
        "utility"
    ],
    "wof:name":"Central Lake Joint Water Agenc",
    "wof:placetype":"venue"
},
  "geometry": {"coordinates":[-87.852913,42.279731],"type":"Point"}
}