{
  "type": "Feature",
  "properties": {
    "iso:country":"US",
    "sg:address":"291 Margate Ter",
    "sg:city":"Antioch",
    "sg:classifiers":[
        {
            "category":"Professional",
            "subcategory":"Business Services",
            "type":"Services"
        }
    ],
    "sg:phone":"+1 847 838 3600",
    "sg:postcode":"60002",
    "sg:province":"IL",
    "sg:tags":[
        "packaging"
    ],
    "wof:name":"Industrial Packaging Concepts",
    "wof:placetype":"venue"
},
  "geometry": {"coordinates":[-88.09299799999999,42.466569],"type":"Point"}
}