{
  "type": "Feature",
  "properties": {
    "addr:full":"221 S Locust St Champaign IL 61820",
    "addr:housenumber":"221",
    "addr:postcode":"61820",
    "addr:street":"S Locust St",
    "iso:country":"US",
    "sg:address":"221 S Locust St",
    "sg:city":"Champaign",
    "sg:classifiers":[
        {
            "category":"Wholesale",
            "subcategory":"Drugs",
            "type":"Manufacturing & Wholesale Goods"
        }
    ],
    "sg:phone":"+1 217 352 3427",
    "sg:postcode":"61820",
    "sg:province":"IL",
    "sg:tags":[
        "perfume"
    ],
    "wof:name":"D's Appliance Pick Up",
    "wof:placetype":"venue"
},
  "geometry": {"coordinates":[-88.2394,40.114538],"type":"Point"}
}