{
  "type": "Feature",
  "properties": {
    "iso:country":"US",
    "sg:address":"4500 Beau Monde Dr",
    "sg:city":"Lisle",
    "sg:classifiers":[
        {
            "category":"Restaurant",
            "type":"Food & Drink"
        }
    ],
    "sg:phone":"+1 630 968 5399",
    "sg:postcode":"60532",
    "sg:province":"IL",
    "sg:tags":[
        "style",
        "family"
    ],
    "wof:name":"C/O R M Dell",
    "wof:placetype":"venue"
},
  "geometry": {"coordinates":[-88.098152,41.80394],"type":"Point"}
}