{
  "type": "Feature",
  "properties": {
    "iso:country":"US",
    "sg:address":"511 School St",
    "sg:city":"Henry",
    "sg:classifiers":[
        {
            "category":"Government",
            "subcategory":"Office",
            "type":"Public Place"
        }
    ],
    "sg:phone":"+1 309 364 2376",
    "sg:postcode":"61537",
    "sg:province":"IL",
    "sg:tags":[
        "county",
        "resource"
    ],
    "wof:name":"County Of Marshall Human Svc",
    "wof:placetype":"venue"
},
  "geometry": {"coordinates":[-89.355177,41.112474],"type":"Point"}
}