{
  "type": "Feature",
  "properties": {
    "addr:full":"1933 E Court St Kankakee IL 60901",
    "addr:housenumber":"1933",
    "addr:postcode":"60901",
    "addr:street":"E Court St",
    "iso:country":"US",
    "sg:address":"1933 E Court St",
    "sg:city":"Kankakee",
    "sg:classifiers":[
        {
            "category":"Shopping",
            "subcategory":"Discount & Variety Stores",
            "type":"Retail Goods"
        }
    ],
    "sg:phone":"+1   ",
    "sg:postcode":"60901",
    "sg:province":"IL",
    "wof:name":"Dollar General 2487",
    "wof:placetype":"venue"
},
  "geometry": {"coordinates":[-87.83883400000001,41.119025],"type":"Point"}
}