{
  "type": "Feature",
  "properties": {
    "iso:country":"US",
    "sg:address":"447 W 31st St",
    "sg:city":"Chicago",
    "sg:classifiers":[
        {
            "category":"Organizations",
            "subcategory":"Labor Organization",
            "type":"Services"
        }
    ],
    "sg:phone":"+1 312 326 1430",
    "sg:postcode":"60616",
    "sg:province":"IL",
    "wof:name":"Iuoe",
    "wof:placetype":"venue"
},
  "geometry": {"coordinates":[-87.637794,41.838161],"type":"Point"}
}