{
  "type": "Feature",
  "properties": {
    "iso:country":"US",
    "sg:address":"10723 N Il Route 2",
    "sg:city":"Rockford",
    "sg:classifiers":[
        {
            "category":"Travel",
            "subcategory":"Hotels & Motels",
            "type":"Entertainment"
        }
    ],
    "sg:phone":"+1 815 234 5544",
    "sg:postcode":"61102",
    "sg:province":"IL",
    "wof:name":"Blackhawk Trails Lodge Inc",
    "wof:placetype":"venue"
},
  "geometry": {"coordinates":[-89.21793099999999,42.169317],"type":"Point"}
}