{
  "type": "Feature",
  "properties": {
    "iso:country":"US",
    "sg:address":"5415 W Devon Ave",
    "sg:city":"Chicago",
    "sg:classifiers":[
        {
            "category":"Professional",
            "subcategory":"Accounting & Tax Preparation",
            "type":"Services"
        }
    ],
    "sg:phone":"+1 773 775 4700",
    "sg:postcode":"60646",
    "sg:province":"IL",
    "sg:tags":[
        "accountant"
    ],
    "wof:name":"Albert B Daoud & Assoc",
    "wof:placetype":"venue"
},
  "geometry": {"coordinates":[-87.765029,41.997258],"type":"Point"}
}