{
  "type": "Feature",
  "properties": {
    "addr:full":"1272 W Northwest Hwy Palatine IL 60067",
    "addr:housenumber":"1272",
    "addr:postcode":"60067",
    "addr:street":"W Northwest Hwy",
    "iso:country":"US",
    "sg:address":"1272 W Northwest Hwy",
    "sg:city":"Palatine",
    "sg:classifiers":[
        {
            "category":"Professional",
            "subcategory":"Employment Agencies",
            "type":"Services"
        }
    ],
    "sg:phone":"+1 847 776 0800",
    "sg:postcode":"60067",
    "sg:province":"IL",
    "sg:tags":[
        "home",
        "health"
    ],
    "wof:name":"Healthcare Plus Corporation",
    "wof:placetype":"venue"
},
  "geometry": {"coordinates":[-88.074158,42.124986],"type":"Point"}
}