{
  "type": "Feature",
  "properties": {
    "addr:full":"900 N Westmoreland Rd Lake Forest IL 60045",
    "addr:housenumber":"900",
    "addr:postcode":"60045",
    "addr:street":"N Westmoreland Rd",
    "iso:country":"US",
    "sg:address":"900 N Westmoreland Rd",
    "sg:city":"Lake Forest",
    "sg:classifiers":[
        {
            "category":"Health Services",
            "subcategory":"Doctor",
            "type":"Services"
        }
    ],
    "sg:phone":"+1 847 234 3860",
    "sg:postcode":"60045",
    "sg:province":"IL",
    "sg:tags":[
        "physician",
        "surgeon"
    ],
    "wof:name":"Lake Forest Ob/Gyn",
    "wof:placetype":"venue"
},
  "geometry": {"coordinates":[-87.863012,42.256756],"type":"Point"}
}