{
  "type": "Feature",
  "properties": {
    "iso:country":"US",
    "sg:address":"1507 East 53rd St Ste 834",
    "sg:city":"Chicago",
    "sg:classifiers":[
        {
            "category":"Building & Trades",
            "subcategory":"Construction",
            "type":"Services"
        }
    ],
    "sg:phone":"+1 312 243 3335",
    "sg:postcode":"60615",
    "sg:province":"IL",
    "sg:tags":[
        "contractor"
    ],
    "sg:website":"www.nayerconstruction.com",
    "wof:name":"Nayer Construction",
    "wof:placetype":"venue"
},
  "geometry": {"coordinates":[-87.588791,41.79946],"type":"Point"}
}