{
  "type": "Feature",
  "properties": {
    "addr:full":"1514 Glenside Dr Bolingbrook IL 60490",
    "addr:housenumber":"1514",
    "addr:postcode":"60490",
    "addr:street":"Glenside Dr",
    "iso:country":"US",
    "sg:address":"1514 Glenside Dr",
    "sg:city":"Bolingbrook",
    "sg:classifiers":[
        {
            "category":"Real Estate",
            "subcategory":"Real Estate Services",
            "type":"Services"
        },
        {
            "category":"Real Estate",
            "subcategory":"Real Estate Agent",
            "type":"Services"
        }
    ],
    "sg:phone":"+1 630 788 7340",
    "sg:postcode":"60490",
    "sg:province":"IL",
    "sg:tags":[
        "buyer",
        "broker"
    ],
    "wof:name":"Citizens Realty Profession",
    "wof:placetype":"venue"
},
  "geometry": {"coordinates":[-88.13905800000001,41.674283],"type":"Point"}
}