{
  "type": "Feature",
  "properties": {
    "iso:country":"US",
    "sg:address":"4710 Main St",
    "sg:city":"Downers Grove",
    "sg:classifiers":[
        {
            "category":"Professional",
            "subcategory":"Engineering",
            "type":"Services"
        }
    ],
    "sg:phone":"+1 630 493 1841",
    "sg:postcode":"60515",
    "sg:province":"IL",
    "sg:tags":[
        "engineer"
    ],
    "sg:website":"www.abhengineers.com",
    "wof:name":"Alvord Burdick & Howson",
    "wof:placetype":"venue"
},
  "geometry": {"coordinates":[-88.01082,41.800268],"type":"Point"}
}