{
  "type": "Feature",
  "properties": {
    "iso:country":"US",
    "sg:address":"2057 W 51st Street",
    "sg:city":"Chicago",
    "sg:classifiers":[
        {
            "category":"Food & Beverages",
            "subcategory":"Groceries & Convenience Stores",
            "type":"Retail Goods"
        }
    ],
    "sg:phone":"+1 773 434 2624",
    "sg:postcode":"60609",
    "sg:province":"IL",
    "wof:name":"Cidras Food",
    "wof:placetype":"venue"
},
  "geometry": {"coordinates":[-87.676688,41.800986],"type":"Point"}
}