{
  "type": "Feature",
  "properties": {
    "addr:full":"306 S Prospect Ave Park Ridge IL 60068",
    "addr:housenumber":"306",
    "addr:postcode":"60068",
    "addr:street":"S Prospect Ave",
    "iso:country":"US",
    "sg:address":"306 S Prospect Ave",
    "sg:city":"Park Ridge",
    "sg:classifiers":[
        {
            "category":"Organizations",
            "subcategory":"Religious Organization",
            "type":"Services"
        }
    ],
    "sg:phone":"+1 847 823 4126",
    "sg:postcode":"60068",
    "sg:province":"IL",
    "wof:name":"St Marys Episcopal Church",
    "wof:placetype":"venue"
},
  "geometry": {"coordinates":[-87.83283400000001,42.00577],"type":"Point"}
}