{
  "type": "Feature",
  "properties": {
    "iso:country":"US",
    "sg:address":"3350 N Bell School Rd",
    "sg:city":"Rockford",
    "sg:classifiers":[
        {
            "category":"Education",
            "subcategory":"Junior College",
            "type":"Public Place"
        }
    ],
    "sg:phone":"+1 815 921 3933",
    "sg:postcode":"61107",
    "sg:province":"IL",
    "wof:name":"Rvc Cnter For Lrng In Rtrement",
    "wof:placetype":"venue"
},
  "geometry": {"coordinates":[-88.970216,42.310042],"type":"Point"}
}