{
  "type": "Feature",
  "properties": {
    "addr:full":"10331 S Kedzie Avenue Chicago IL 60655",
    "addr:housenumber":"10331",
    "addr:postcode":"60655",
    "addr:street":"S Kedzie Avenue",
    "iso:country":"US",
    "sg:address":"10331 S Kedzie Avenue",
    "sg:city":"Chicago",
    "sg:classifiers":[
        {
            "category":"Restaurant",
            "type":"Food & Drink"
        }
    ],
    "sg:phone":"+1 773 779 2200",
    "sg:postcode":"60655",
    "sg:province":"IL",
    "wof:name":"Popeyes Chicken & Biscuits",
    "wof:placetype":"venue"
},
  "geometry": {"coordinates":[-87.70111799999999,41.705798],"type":"Point"}
}