{
  "type": "Feature",
  "properties": {
    "iso:country":"US",
    "sg:address":"443 E Saint Charles Rd",
    "sg:city":"Villa Park",
    "sg:classifiers":[
        {
            "category":"Autos & Motor Vehicles",
            "subcategory":"Automobile Sales",
            "type":"Retail Goods"
        }
    ],
    "sg:phone":"+1   ",
    "sg:postcode":"60181",
    "sg:province":"IL",
    "sg:tags":[
        "repair",
        "pickup",
        "used",
        "au",
        "new"
    ],
    "wof:name":"Oakfield Ford Inc",
    "wof:placetype":"venue"
},
  "geometry": {"coordinates":[-87.991332,41.88979],"type":"Point"}
}