{
  "type": "Feature",
  "properties": {
    "addr:full":"4935 W 63rd St Chicago IL 60638",
    "addr:housenumber":"4935",
    "addr:postcode":"60638",
    "addr:street":"W 63Rd St",
    "iso:country":"US",
    "sg:address":"4935 W 63rd St",
    "sg:city":"Chicago",
    "sg:classifiers":[
        {
            "category":"Retail",
            "subcategory":"Auto Rental",
            "type":"Services"
        }
    ],
    "sg:phone":"+1 773 767 2222",
    "sg:postcode":"60638",
    "sg:province":"IL",
    "sg:tags":[
        "car"
    ],
    "wof:name":"Priceless Car Rental",
    "wof:placetype":"venue"
},
  "geometry": {"coordinates":[-87.74630000000001,41.778099],"type":"Point"}
}