{
  "type": "Feature",
  "properties": {
    "iso:country":"US",
    "sg:address":"19975 S la Grange Rd",
    "sg:city":"Frankfort",
    "sg:classifiers":[
        {
            "category":"Shopping",
            "subcategory":"Optical Goods",
            "type":"Retail Goods"
        },
        {
            "category":"Shopping",
            "subcategory":"Optician",
            "type":"Retail Goods"
        },
        {
            "category":"Health Services",
            "subcategory":"Optometrist",
            "type":"Services"
        },
        {
            "category":"Personal",
            "subcategory":"Shoe Repair & Shine",
            "type":"Services"
        }
    ],
    "sg:phone":"+1 815 464 5009",
    "sg:postcode":"60423",
    "sg:province":"IL",
    "sg:tags":[
        "eyeglass",
        "sunglass"
    ],
    "sg:website":"http://",
    "wof:name":"Sears Optical",
    "wof:placetype":"venue"
},
  "geometry": {"coordinates":[-87.850058,41.526568],"type":"Point"}
}