{
  "type": "Feature",
  "properties": {
    "iso:country":"US",
    "sg:address":"438 US Hwy 20",
    "sg:city":"Cherry Valley",
    "sg:classifiers":[
        {
            "category":"Restaurant",
            "type":"Food & Drink"
        }
    ],
    "sg:phone":"+1 815 332 9920",
    "sg:postcode":"61016",
    "sg:province":"IL",
    "wof:name":"Take 20",
    "wof:placetype":"venue"
},
  "geometry": {"coordinates":[-88.92242899999999,42.239526],"type":"Point"}
}