{
  "type": "Feature",
  "properties": {
    "iso:country":"US",
    "sg:address":"52 Countryside Plz",
    "sg:city":"Countryside",
    "sg:classifiers":[
        {
            "category":"Bakery",
            "type":"Food & Drink"
        }
    ],
    "sg:phone":"+1 708 354 6110",
    "sg:postcode":"60525",
    "sg:province":"IL",
    "wof:name":"Wonder Hostess Bakery Outlet",
    "wof:placetype":"venue"
},
  "geometry": {"coordinates":[-87.868301,41.779202],"type":"Point"}
}