{
  "type": "Feature",
  "properties": {
    "iso:country":"US",
    "sg:address":"2320 Wyoming Dr",
    "sg:city":"Rockford",
    "sg:classifiers":[
        {
            "category":"Building & Trades",
            "subcategory":"Construction",
            "type":"Services"
        }
    ],
    "sg:phone":"+1 815 399 1404",
    "sg:postcode":"61108",
    "sg:province":"IL",
    "sg:tags":[
        "hanging",
        "contractor"
    ],
    "wof:name":"Plantz Painting Rick",
    "wof:placetype":"venue"
},
  "geometry": {"coordinates":[-89.034369,42.240714],"type":"Point"}
}