{
  "type": "Feature",
  "properties": {
    "addr:full":"1135 W Bryn Mawr Ave Chicago IL 60660",
    "addr:housenumber":"1135",
    "addr:postcode":"60660",
    "addr:street":"W Bryn Mawr Ave",
    "iso:country":"US",
    "sg:address":"1135 W Bryn Mawr Ave",
    "sg:city":"Chicago",
    "sg:classifiers":[
        {
            "category":"Personal",
            "subcategory":"Beauty Salon",
            "type":"Services"
        }
    ],
    "sg:phone":"+1 773 728 4166",
    "sg:postcode":"60660",
    "sg:province":"IL",
    "wof:name":"Diosa S Beauty Salon",
    "wof:placetype":"venue"
},
  "geometry": {"coordinates":[-87.659109,41.983565],"type":"Point"}
}