{
  "type": "Feature",
  "properties": {
    "addr:full":"7139 W Higgins Avenue Chicago IL 60656",
    "addr:housenumber":"7139",
    "addr:postcode":"60656",
    "addr:street":"W Higgins Avenue",
    "iso:country":"US",
    "sg:address":"7139 W Higgins Avenue",
    "sg:city":"Chicago",
    "sg:classifiers":[
        {
            "category":"Shopping",
            "subcategory":"Hobbies, Toys, & Games",
            "type":"Retail Goods"
        }
    ],
    "sg:phone":"+1 773 775 2100",
    "sg:postcode":"60656",
    "sg:province":"IL",
    "sg:tags":[
        "shop",
        "hobby"
    ],
    "wof:name":"Stamp King",
    "wof:placetype":"venue"
},
  "geometry": {"coordinates":[-87.806298,41.980805],"type":"Point"}
}