{
  "type": "Feature",
  "properties": {
    "iso:country":"US",
    "sg:address":"931 Brook Forest Ave",
    "sg:city":"Shorewood",
    "sg:classifiers":[
        {
            "category":"Banks & Credit Unions",
            "subcategory":"Bank",
            "type":"Services"
        }
    ],
    "sg:phone":"+1 815 609 7785",
    "sg:postcode":"60404",
    "sg:province":"IL",
    "sg:tags":[
        "saving",
        "commercial"
    ],
    "wof:name":"First Financial Bank",
    "wof:placetype":"venue"
},
  "geometry": {"coordinates":[-88.199252,41.536868],"type":"Point"}
}