{
  "type": "Feature",
  "properties": {
    "iso:country":"US",
    "sg:address":"803 S State St",
    "sg:city":"Lockport",
    "sg:classifiers":[
        {
            "category":"Landmark",
            "subcategory":"Historic",
            "type":"Public Place"
        },
        {
            "category":"Landmark",
            "subcategory":"Tourist Information",
            "type":"Public Place"
        },
        {
            "category":"Museum",
            "type":"Entertainment"
        }
    ],
    "sg:phone":"+1 815 838 5080",
    "sg:postcode":"60441",
    "sg:province":"IL",
    "sg:tags":[
        "attraction",
        "historical"
    ],
    "wof:name":"Will County Historical Society",
    "wof:placetype":"venue"
},
  "geometry": {"coordinates":[-88.057129,41.590092],"type":"Point"}
}