{
  "type": "Feature",
  "properties": {
    "addr:city":"Lockport",
    "addr:full":"803 S State St Lockport, Il 60441-3433",
    "addr:house_number":"803",
    "addr:housenumber":"803",
    "addr:phone":"+1 815-838-5080",
    "addr:postcode":"60441-3433",
    "addr:road":"S State St",
    "addr:state":"IL",
    "addr:street":"S State St",
    "iso:country":"US",
    "sg:address":"803 S State St",
    "sg:city":"Lockport",
    "sg:classifiers":[
        {
            "category":"Landmark",
            "subcategory":"Historic",
            "type":"Public Place"
        },
        {
            "category":"Landmark",
            "subcategory":"Tourist Information",
            "type":"Public Place"
        },
        {
            "category":"Museum",
            "type":"Entertainment"
        }
    ],
    "sg:phone":"+1 815 838 5080",
    "sg:postcode":"60441",
    "sg:province":"IL",
    "sg:tags":[
        "attraction",
        "historical"
    ],
    "wof:airports":[
        102529087,
        102534369
    ],
    "wof:name":"Will County Historical Society",
    "wof:placetype":"venue"
},
  "geometry": {"coordinates":[-88.05716,41.59019],"type":"Point"}
}