{
  "type": "Feature",
  "properties": {
    "addr:full":"3710 N Clark St Chicago IL 60613",
    "addr:housenumber":"3710",
    "addr:postcode":"60613",
    "addr:street":"N Clark St",
    "iso:country":"US",
    "sg:address":"3710 N Clark St",
    "sg:city":"Chicago",
    "sg:classifiers":[
        {
            "category":"Bars & Pubs",
            "subcategory":"Sports Bar",
            "type":"Food & Drink"
        },
        {
            "category":"Restaurant",
            "type":"Food & Drink"
        }
    ],
    "sg:phone":"+1 773 525 9200",
    "sg:postcode":"60613",
    "sg:province":"IL",
    "sg:tags":[
        "traditional",
        "american"
    ],
    "wof:name":"Yakzies Bar Grill",
    "wof:placetype":"venue"
},
  "geometry": {"coordinates":[-87.65799699999999,41.949299],"type":"Point"}
}