{
  "type": "Feature",
  "properties": {
    "iso:country":"US",
    "sg:address":"6700 Lakeside Dr",
    "sg:city":"Plano",
    "sg:classifiers":[
        {
            "category":"Autos & Motor Vehicles",
            "subcategory":"Fuel & Gas Station",
            "type":"Retail Goods"
        }
    ],
    "sg:phone":"+1   ",
    "sg:postcode":"60516",
    "sg:province":"IL",
    "sg:tags":[
        "station",
        "gasoline"
    ],
    "wof:name":"Murphy USA",
    "wof:placetype":"venue"
},
  "geometry": {"coordinates":[-88.004189,41.736789],"type":"Point"}
}