{
  "type": "Feature",
  "properties": {
    "iso:country":"US",
    "sg:address":"2640 W Touhy Ave",
    "sg:city":"Chicago",
    "sg:classifiers":[
        {
            "category":"Banks & Credit Unions",
            "subcategory":"Bank",
            "type":"Services"
        }
    ],
    "sg:phone":"+1 773 262 0400",
    "sg:postcode":"60645",
    "sg:province":"IL",
    "sg:tags":[
        "loan",
        "broker"
    ],
    "wof:name":"Nexus Financial Ltd",
    "wof:placetype":"venue"
},
  "geometry": {"coordinates":[-87.69651399999999,42.012219],"type":"Point"}
}