{
  "type": "Feature",
  "properties": {
    "addr:full":"2551 N Clark St Chicago IL 60614",
    "addr:housenumber":"2551",
    "addr:postcode":"60614",
    "addr:street":"N Clark St",
    "iso:country":"US",
    "sg:address":"2551 N Clark St",
    "sg:city":"Chicago",
    "sg:classifiers":[
        {
            "category":"Health Services",
            "subcategory":"Dentist",
            "type":"Services"
        }
    ],
    "sg:phone":"+1 773 541 8208",
    "sg:postcode":"60614",
    "sg:province":"IL",
    "sg:website":"http://www.thedentalpractice.com",
    "wof:name":"Flak Matthew",
    "wof:placetype":"venue"
},
  "geometry": {"coordinates":[-87.642788,41.929516],"type":"Point"}
}