{
  "type": "Feature",
  "properties": {
    "addr:full":"4545 W Augusta Blvd Chicago IL 60651",
    "addr:housenumber":"4545",
    "addr:postcode":"60651",
    "addr:street":"W Augusta Blvd",
    "iso:country":"US",
    "sg:address":"4545 W Augusta Blvd",
    "sg:city":"Chicago",
    "sg:classifiers":[
        {
            "category":"Home & Garden",
            "subcategory":"Furniture",
            "type":"Retail Goods"
        }
    ],
    "sg:phone":"+1 773 524 2440",
    "sg:postcode":"60651",
    "sg:province":"IL",
    "sg:tags":[
        "benches-seating"
    ],
    "sg:website":"http://www.freedmanseating.com",
    "wof:name":"Freedman Seating",
    "wof:placetype":"venue"
},
  "geometry": {"coordinates":[-87.739994,41.898797],"type":"Point"}
}