{
  "type": "Feature",
  "properties": {
    "iso:country":"US",
    "sg:address":"17926 Arkansas Ct",
    "sg:city":"Orland Park",
    "sg:classifiers":[
        {
            "category":"Home & Garden",
            "subcategory":"Building Materials",
            "type":"Retail Goods"
        }
    ],
    "sg:phone":"+1   ",
    "sg:postcode":"60467",
    "sg:province":"IL",
    "wof:name":"J M K Stained Glass",
    "wof:placetype":"venue"
},
  "geometry": {"coordinates":[-87.884122,41.563574],"type":"Point"}
}