{
  "type": "Feature",
  "properties": {
    "iso:country":"US",
    "sg:address":"1316 2nd Ave",
    "sg:city":"Danville",
    "sg:classifiers":[
        {
            "category":"Personal",
            "subcategory":"Beauty Salon",
            "type":"Services"
        }
    ],
    "sg:phone":"+1 217 443 0059",
    "sg:postcode":"61832",
    "sg:province":"IL",
    "wof:name":"Baker's Beauty Barn",
    "wof:placetype":"venue"
},
  "geometry": {"coordinates":[-87.631996,40.102549],"type":"Point"}
}