{
  "type": "Feature",
  "properties": {
    "iso:country":"US",
    "sg:address":"943 Darla Ct",
    "sg:city":"Waukegan",
    "sg:classifiers":[
        {
            "category":"Professional",
            "subcategory":"Business Services",
            "type":"Services"
        }
    ],
    "sg:phone":"+1 847 244 7608",
    "sg:postcode":"60085",
    "sg:province":"IL",
    "wof:name":"Expert Archive Inc",
    "wof:placetype":"venue"
},
  "geometry": {"coordinates":[-87.913147,42.342928],"type":"Point"}
}