{
  "type": "Feature",
  "properties": {
    "iso:country":"US",
    "sg:address":"1725 E State St",
    "sg:city":"Rockford",
    "sg:classifiers":[
        {
            "category":"Health Services",
            "subcategory":"Hospital",
            "type":"Services"
        }
    ],
    "sg:phone":"+1 815 397 9331",
    "sg:postcode":"61104",
    "sg:province":"IL",
    "sg:tags":[
        "clinic",
        "general",
        "specialty",
        "outpatient"
    ],
    "wof:name":"Janet Wattles Center",
    "wof:placetype":"venue"
},
  "geometry": {"coordinates":[-89.067477,42.26689],"type":"Point"}
}