{
  "type": "Feature",
  "properties": {
    "addr:full":"107 W McHenry St Urbana IL 61801",
    "addr:housenumber":"107",
    "addr:postcode":"61801",
    "addr:street":"W Mchenry St",
    "iso:country":"US",
    "sg:address":"107 W McHenry St",
    "sg:city":"Urbana",
    "sg:classifiers":[
        {
            "category":"Farming",
            "subcategory":"Aquatic Farm",
            "type":"Manufacturing & Wholesale Goods"
        }
    ],
    "sg:phone":"+1 217 328 6671",
    "sg:postcode":"61801",
    "sg:province":"IL",
    "wof:name":"Dale O Tutje Rev",
    "wof:placetype":"venue"
},
  "geometry": {"coordinates":[-88.20733799999999,40.086943],"type":"Point"}
}