{
  "type": "Feature",
  "properties": {
    "addr:full":"4 W Francis Ave Mundelein IL 60060",
    "addr:housenumber":"4",
    "addr:postcode":"60060",
    "addr:street":"W Francis Ave",
    "iso:country":"US",
    "sg:address":"4 W Francis Ave",
    "sg:city":"Mundelein",
    "sg:classifiers":[
        {
            "category":"Retail",
            "subcategory":"Auto Repair",
            "type":"Services"
        }
    ],
    "sg:phone":"+1 847 566 4040",
    "sg:postcode":"60060",
    "sg:province":"IL",
    "sg:tags":[
        "automotive"
    ],
    "wof:name":"Sound of Music",
    "wof:placetype":"venue"
},
  "geometry": {"coordinates":[-88.00345799999999,42.242324],"type":"Point"}
}