{
  "type": "Feature",
  "properties": {
    "addr:full":"7 Rhodes St Big Rock IL 60511",
    "addr:housenumber":"7",
    "addr:postcode":"60511",
    "addr:street":"Rhodes St",
    "iso:country":"US",
    "sg:address":"7 Rhodes St",
    "sg:city":"Big Rock",
    "sg:classifiers":[
        {
            "category":"Real Estate",
            "subcategory":"Real Estate Agent",
            "type":"Services"
        }
    ],
    "sg:phone":"+1 630 556 9969",
    "sg:postcode":"60511",
    "sg:province":"IL",
    "wof:name":"Rooster AG Realty",
    "wof:placetype":"venue"
},
  "geometry": {"coordinates":[-88.547133,41.759075],"type":"Point"}
}