{
  "type": "Feature",
  "properties": {
    "addr:full":"718 N Park Ave Herrin IL 62948",
    "addr:housenumber":"718",
    "addr:postcode":"62948",
    "addr:street":"N Park Ave",
    "iso:country":"US",
    "sg:address":"718 N Park Ave",
    "sg:city":"Herrin",
    "sg:classifiers":[
        {
            "category":"Autos & Motor Vehicles",
            "subcategory":"Auto Supplies",
            "type":"Retail Goods"
        }
    ],
    "sg:phone":"+1 618 988 8473",
    "sg:postcode":"62948",
    "sg:province":"IL",
    "sg:tags":[
        "tire"
    ],
    "wof:name":"A 1 Auto & Tire",
    "wof:placetype":"venue"
},
  "geometry": {"coordinates":[-89.027496,37.809898],"type":"Point"}
}