{
  "type": "Feature",
  "properties": {
    "addr:full":"288 Orland Square Dr Orland Park IL 60462",
    "addr:housenumber":"288",
    "addr:postcode":"60462",
    "addr:street":"Orland Square Dr",
    "iso:country":"US",
    "sg:address":"288 Orland Square Dr",
    "sg:city":"Orland Park",
    "sg:classifiers":[
        {
            "category":"Personal",
            "subcategory":"Beauty Salon",
            "type":"Services"
        }
    ],
    "sg:phone":"+1 708 403 3594",
    "sg:postcode":"60462",
    "sg:province":"IL",
    "sg:tags":[
        "treatment",
        "skin"
    ],
    "wof:name":"H2O Plus Inc",
    "wof:placetype":"venue"
},
  "geometry": {"coordinates":[-87.845979,41.622558],"type":"Point"}
}