{
  "type": "Feature",
  "properties": {
    "iso:country":"US",
    "sg:address":"14 Westhaven Ct",
    "sg:city":"Taylorville",
    "sg:classifiers":[
        {
            "category":"Professional",
            "subcategory":"Lawyer & Legal Services",
            "type":"Services"
        }
    ],
    "sg:phone":"+1 217 824 4110",
    "sg:postcode":"62568",
    "sg:province":"IL",
    "sg:tags":[
        "attorney",
        "practice"
    ],
    "wof:name":"Daniel W Austin Atty",
    "wof:placetype":"venue"
},
  "geometry": {"coordinates":[-89.237324,39.534522],"type":"Point"}
}