{
  "type": "Feature",
  "properties": {
    "addr:full":"155 N Michigan Ave Ste 500 Chicago IL 60601",
    "addr:housenumber":"155",
    "addr:postcode":"60601",
    "addr:street":"N Michigan Ave Ste 500",
    "iso:country":"US",
    "sg:address":"155 N Michigan Ave Ste 500",
    "sg:city":"Chicago",
    "sg:classifiers":[
        {
            "category":"Real Estate",
            "subcategory":"Real Estate Operator",
            "type":"Services"
        }
    ],
    "sg:phone":"+1 312 729 5060",
    "sg:postcode":"60601",
    "sg:province":"IL",
    "sg:tags":[
        "apartment"
    ],
    "wof:name":"Millennium Park Plaza",
    "wof:placetype":"venue"
},
  "geometry": {"coordinates":[-87.624346,41.884848],"type":"Point"}
}