{
  "type": "Feature",
  "properties": {
    "addr:full":"4920 S Halsted St Chicago IL 60609",
    "addr:housenumber":"4920",
    "addr:postcode":"60609",
    "addr:street":"S Halsted St",
    "iso:country":"US",
    "sg:address":"4920 S Halsted St",
    "sg:city":"Chicago",
    "sg:classifiers":[
        {
            "category":"Retail",
            "subcategory":"Car Wash",
            "type":"Services"
        }
    ],
    "sg:phone":"+1 773 548 4721",
    "sg:postcode":"60609",
    "sg:province":"IL",
    "wof:name":"Liberty Car Wash",
    "wof:placetype":"venue"
},
  "geometry": {"coordinates":[-87.6455,41.804798],"type":"Point"}
}