{
  "type": "Feature",
  "properties": {
    "iso:country":"US",
    "sg:address":"172 Easy St",
    "sg:city":"Carol Stream",
    "sg:classifiers":[
        {
            "category":"Manufacturing",
            "subcategory":"Paper Products",
            "type":"Manufacturing & Wholesale Goods"
        }
    ],
    "sg:phone":"+1 630 784 8500",
    "sg:postcode":"60188",
    "sg:province":"IL",
    "wof:name":"Navis Industries  Inc",
    "wof:placetype":"venue"
},
  "geometry": {"coordinates":[-88.116785,41.896418],"type":"Point"}
}