{
  "type": "Feature",
  "properties": {
    "addr:full":"21544 S 116th Ave New Lenox IL 60451",
    "addr:housenumber":"21544",
    "addr:postcode":"60451",
    "addr:street":"S 116Th Ave",
    "iso:country":"US",
    "sg:address":"21544 S 116th Ave",
    "sg:city":"New Lenox",
    "sg:classifiers":[
        {
            "category":"Retail",
            "subcategory":"Animal Services",
            "type":"Services"
        }
    ],
    "sg:phone":"+1 815 469 4456",
    "sg:postcode":"60451",
    "sg:province":"IL",
    "wof:name":"Grasslands Golden Retreiver",
    "wof:placetype":"venue"
},
  "geometry": {"coordinates":[-87.898017,41.498308],"type":"Point"}
}