{
  "type": "Feature",
  "properties": {
    "iso:country":"US",
    "sg:address":"5037 N Il 130",
    "sg:city":"Olney",
    "sg:classifiers":[
        {
            "category":"Professional",
            "subcategory":"Engineering",
            "type":"Services"
        },
        {
            "category":"Building & Trades",
            "subcategory":"Construction",
            "type":"Services"
        }
    ],
    "sg:phone":"+1 618 395 3788",
    "sg:postcode":"62450",
    "sg:province":"IL",
    "sg:tags":[
        "system",
        "contractor",
        "equipment",
        "refrigeration",
        "air conditioning",
        "engineer"
    ],
    "wof:name":"Stevens Refrigeration & Ac",
    "wof:placetype":"venue"
},
  "geometry": {"coordinates":[-88.094574,38.754691],"type":"Point"}
}