{
  "type": "Feature",
  "properties": {
    "iso:country":"US",
    "sg:address":"1109 Hartman Ln",
    "sg:city":"Belleville",
    "sg:classifiers":[
        {
            "category":"Banks & Credit Unions",
            "subcategory":"Bank",
            "type":"Services"
        }
    ],
    "sg:phone":"+1 618 239 0212",
    "sg:postcode":"62221",
    "sg:province":"IL",
    "wof:name":"Catholic & Comm Credit Union",
    "wof:placetype":"venue"
},
  "geometry": {"coordinates":[-89.947607,38.573397],"type":"Point"}
}