{
  "type": "Feature",
  "properties": {
    "iso:country":"US",
    "sg:address":"2225 W Jefferson St Ste A",
    "sg:city":"Joliet",
    "sg:classifiers":[
        {
            "category":"Communications",
            "subcategory":"News Services",
            "type":"Services"
        },
        {
            "category":"Professional",
            "subcategory":"Printing & Photocopies",
            "type":"Services"
        },
        {
            "category":"Manufacturing",
            "subcategory":"Printing",
            "type":"Manufacturing & Wholesale Goods"
        }
    ],
    "sg:phone":"+1 815 741 8810",
    "sg:postcode":"60435",
    "sg:province":"IL",
    "sg:tags":[
        "fax",
        "form",
        "services-commercial",
        "duplicating",
        "printers-business",
        "imaging",
        "copying",
        "digital"
    ],
    "sg:website":"http://www.sirspeedy.com",
    "wof:name":"Sir Speedy",
    "wof:placetype":"venue"
},
  "geometry": {"coordinates":[-88.088989,41.524996],"type":"Point"}
}