{
  "type": "Feature",
  "properties": {
    "iso:country":"US",
    "sg:address":"160 N Western Ave",
    "sg:city":"Carpentersville",
    "sg:classifiers":[
        {
            "category":"Education",
            "subcategory":"Music School",
            "type":"Public Place"
        }
    ],
    "sg:phone":"+1 847 551 1009",
    "sg:postcode":"60110",
    "sg:province":"IL",
    "sg:tags":[
        "instrument",
        "teacher",
        "musical"
    ],
    "wof:name":"Eagle Instruments",
    "wof:placetype":"venue"
},
  "geometry": {"coordinates":[-88.296232,42.112029],"type":"Point"}
}