{
  "type": "Feature",
  "properties": {
    "iso:country":"US",
    "sg:address":"398 Army Trail Rd Ste 114",
    "sg:city":"Bloomingdale",
    "sg:classifiers":[
        {
            "category":"Education",
            "subcategory":"Special Training",
            "type":"Public Place"
        }
    ],
    "sg:phone":"+1 630 307 7475",
    "sg:postcode":"60108",
    "sg:province":"IL",
    "sg:tags":[
        "tutoring"
    ],
    "wof:name":"Enopi Bloomingdale Learning Center",
    "wof:placetype":"venue"
},
  "geometry": {"coordinates":[-88.11499000000001,41.939255],"type":"Point"}
}