{
  "type": "Feature",
  "properties": {
    "addr:full":"7515 Madison St Forest Park IL 60130",
    "addr:housenumber":"7515",
    "addr:postcode":"60130",
    "addr:street":"Madison St",
    "iso:country":"US",
    "sg:address":"7515 Madison St",
    "sg:city":"Forest Park",
    "sg:classifiers":[
        {
            "category":"Freight",
            "type":"Transportation"
        }
    ],
    "sg:phone":"+1 708 383 3000",
    "sg:postcode":"60130",
    "sg:province":"IL",
    "wof:name":"Pisces Shipping Inc",
    "wof:placetype":"venue"
},
  "geometry": {"coordinates":[-87.812592,41.879569],"type":"Point"}
}