{
  "type": "Feature",
  "properties": {
    "addr:full":"6119 Matznick Rd Prophetstown IL 61277",
    "addr:housenumber":"6119",
    "addr:postcode":"61277",
    "addr:street":"Matznick Rd",
    "iso:country":"US",
    "sg:address":"6119 Matznick Rd",
    "sg:city":"Prophetstown",
    "sg:phone":"+1 815 438 3481",
    "sg:postcode":"61277",
    "sg:province":"IL",
    "sg:tags":[
        "farm",
        "corn",
        "soybean"
    ],
    "wof:name":"Stanley Loudenburg Farm",
    "wof:placetype":"venue"
},
  "geometry": {"coordinates":[-89.825462,41.678489],"type":"Point"}
}