{
  "type": "Feature",
  "properties": {
    "iso:country":"US",
    "sg:address":"3702 Kearns Dr",
    "sg:city":"Champaign",
    "sg:classifiers":[
        {
            "category":"Transit Center",
            "subcategory":"Freight",
            "type":"Transportation"
        },
        {
            "category":"Freight",
            "type":"Transportation"
        }
    ],
    "sg:phone":"+1 217 356 6800",
    "sg:postcode":"61822",
    "sg:province":"IL",
    "sg:tags":[
        "local",
        "trucking-motor",
        "trucking"
    ],
    "wof:name":"Tom Franey Trucking Inc",
    "wof:placetype":"venue"
},
  "geometry": {"coordinates":[-88.30988600000001,40.11039],"type":"Point"}
}