{
  "type": "Feature",
  "properties": {
    "addr:full":"1274 Camp Jackson Rd Cahokia IL 62206",
    "addr:housenumber":"1274",
    "addr:postcode":"62206",
    "addr:street":"Camp Jackson Rd",
    "iso:country":"US",
    "sg:address":"1274 Camp Jackson Rd",
    "sg:city":"Cahokia",
    "sg:classifiers":[
        {
            "category":"Shopping",
            "subcategory":"Computers & Home Electronics",
            "type":"Retail Goods"
        }
    ],
    "sg:phone":"+1 618 337 3737",
    "sg:postcode":"62206",
    "sg:province":"IL",
    "sg:tags":[
        "equipment",
        "electronic",
        "supply"
    ],
    "wof:name":"Radio Shack",
    "wof:placetype":"venue"
},
  "geometry": {"coordinates":[-90.174263,38.560942],"type":"Point"}
}