{
  "type": "Feature",
  "properties": {
    "iso:country":"US",
    "sg:address":"1321 N Raynor Ave",
    "sg:city":"Joliet",
    "sg:classifiers":[
        {
            "category":"Real Estate",
            "subcategory":"Real Estate Services",
            "type":"Services"
        },
        {
            "category":"Real Estate",
            "subcategory":"Real Estate Agent",
            "type":"Services"
        }
    ],
    "sg:phone":"+1 815 727 2044",
    "sg:postcode":"60435",
    "sg:province":"IL",
    "sg:tags":[
        "buyer",
        "broker"
    ],
    "wof:name":"Lakewood Falls Realty Corp",
    "wof:placetype":"venue"
},
  "geometry": {"coordinates":[-88.10160999999999,41.54721],"type":"Point"}
}