{
  "type": "Feature",
  "properties": {
    "iso:country":"US",
    "sg:address":"16901 Van Dam Rd",
    "sg:city":"South Holland",
    "sg:classifiers":[
        {
            "category":"Building & Trades",
            "subcategory":"Construction",
            "type":"Services"
        }
    ],
    "sg:phone":"+1 708 339 7633",
    "sg:postcode":"60473",
    "sg:province":"IL",
    "sg:tags":[
        "contractor"
    ],
    "wof:name":"Dynamic Wrecking & Excavation Inc",
    "wof:placetype":"venue"
},
  "geometry": {"coordinates":[-87.580822,41.589264],"type":"Point"}
}