{
  "type": "Feature",
  "properties": {
    "iso:country":"US",
    "sg:address":"955 Estes Ave",
    "sg:city":"Elk Grove Village",
    "sg:classifiers":[
        {
            "category":"Wholesale",
            "subcategory":"Machinery & Supplies",
            "type":"Manufacturing & Wholesale Goods"
        }
    ],
    "sg:phone":"+1 847 437 3333",
    "sg:postcode":"60007",
    "sg:province":"IL",
    "sg:tags":[
        "equipment",
        "construction"
    ],
    "wof:name":"Hyundai Cnstr Eqp USA Inc",
    "wof:placetype":"venue"
},
  "geometry": {"coordinates":[-87.97109,42.005663],"type":"Point"}
}