{
  "type": "Feature",
  "properties": {
    "addr:full":"318 E Washington St Belleville IL 62220",
    "addr:housenumber":"318",
    "addr:postcode":"62220",
    "addr:street":"E Washington St",
    "iso:country":"US",
    "sg:address":"318 E Washington St",
    "sg:city":"Belleville",
    "sg:classifiers":[
        {
            "category":"Restaurant",
            "type":"Food & Drink"
        }
    ],
    "sg:phone":"+1 618 239 9529",
    "sg:postcode":"62220",
    "sg:province":"IL",
    "wof:name":"Washington Street Grille",
    "wof:placetype":"venue"
},
  "geometry": {"coordinates":[-89.979221,38.512566],"type":"Point"}
}