{
  "type": "Feature",
  "properties": {
    "iso:country":"US",
    "sg:address":"12201 S Loomis St",
    "sg:city":"Chicago",
    "sg:classifiers":[
        {
            "category":"Local Transit",
            "type":"Transportation"
        }
    ],
    "sg:phone":"+1 773 374 7460",
    "sg:postcode":"60643",
    "sg:province":"IL",
    "sg:tags":[
        "limousine"
    ],
    "wof:name":"DElegant Limousine",
    "wof:placetype":"venue"
},
  "geometry": {"coordinates":[-87.656294,41.670774],"type":"Point"}
}