{
  "type": "Feature",
  "properties": {
    "addr:full":"118 N. Clark St., Suite 112 Chicago IL 60602",
    "addr:housenumber":"118",
    "addr:postcode":"60602",
    "addr:street":"N. Clark St. Suite 112",
    "iso:country":"US",
    "sg:address":"118 N. Clark St., Suite 112",
    "sg:city":"Chicago",
    "sg:classifiers":[
        {
            "category":"Government",
            "subcategory":"City Hall",
            "type":"Public Place"
        }
    ],
    "sg:phone":"+1 312 443 5100",
    "sg:postcode":"60602",
    "sg:province":"IL",
    "sg:website":"www.cookcountytreasurer.com",
    "wof:name":"Cook County Treasurer's Office",
    "wof:placetype":"venue"
},
  "geometry": {"coordinates":[-87.631654,41.88384],"type":"Point"}
}