{
  "type": "Feature",
  "properties": {
    "iso:country":"US",
    "sg:address":"218 S Central Ave",
    "sg:city":"Casey",
    "sg:classifiers":[
        {
            "category":"Sports & Exercise",
            "subcategory":"Gym",
            "type":"Entertainment"
        }
    ],
    "sg:phone":"+1 217 932 5249",
    "sg:postcode":"62420",
    "sg:province":"IL",
    "sg:tags":[
        "club",
        "studio",
        "health",
        "gymnasium"
    ],
    "wof:name":"The Fitness Club",
    "wof:placetype":"venue"
},
  "geometry": {"coordinates":[-87.992752,39.29745],"type":"Point"}
}