{
  "type": "Feature",
  "properties": {
    "iso:country":"US",
    "sg:address":"555 West Polk Street Suite LL1",
    "sg:city":"Chicago",
    "sg:classifiers":[
        {
            "category":"Professional",
            "subcategory":"Computer Services",
            "type":"Services"
        }
    ],
    "sg:phone":"+1 312 431 9200 ext. 301",
    "sg:postcode":"60661",
    "sg:province":"IL",
    "sg:tags":[
        "floorplan-real-estate-property-management-survey-construction-rehab-as-built"
    ],
    "sg:website":"http://www.iplanmaker.com",
    "wof:name":"iPlanmaker",
    "wof:placetype":"venue"
},
  "geometry": {"coordinates":[-87.64197799999999,41.871918],"type":"Point"}
}