{
  "type": "Feature",
  "properties": {
    "iso:country":"US",
    "sg:address":"12336 US Hwy 150",
    "sg:city":"Oakwood",
    "sg:classifiers":[
        {
            "category":"Retail",
            "subcategory":"Auto Repair",
            "type":"Services"
        }
    ],
    "sg:phone":"+1 217 443 8473",
    "sg:postcode":"61858",
    "sg:province":"IL",
    "sg:tags":[
        "tire",
        "supply"
    ],
    "wof:name":"Tommy House Tire Company",
    "wof:placetype":"venue"
},
  "geometry": {"coordinates":[-87.704339,40.126047],"type":"Point"}
}