{
  "type": "Feature",
  "properties": {
    "iso:country":"US",
    "sg:address":"2215 S Union Ave",
    "sg:city":"Chicago",
    "sg:classifiers":[
        {
            "category":"Coffee & Tea",
            "type":"Food & Drink"
        }
    ],
    "sg:phone":"+1 312 850 0295",
    "sg:postcode":"60616",
    "sg:province":"IL",
    "wof:name":"Stivers Coffee Inc",
    "wof:placetype":"venue"
},
  "geometry": {"coordinates":[-87.644203,41.850498],"type":"Point"}
}