{
  "type": "Feature",
  "properties": {
    "iso:country":"US",
    "sg:address":"3048 N Wilton Ave",
    "sg:city":"Chicago",
    "sg:classifiers":[
        {
            "category":"Organizations",
            "subcategory":"Community Association",
            "type":"Services"
        }
    ],
    "sg:phone":"+1 773 296 7400",
    "sg:postcode":"60657",
    "sg:province":"IL",
    "wof:name":"Mr & Mrs Masonic Med",
    "wof:placetype":"venue"
},
  "geometry": {"coordinates":[-87.65291000000001,41.938009],"type":"Point"}
}