{
  "type": "Feature",
  "properties": {
    "iso:country":"US",
    "sg:address":"2301 Lunt Ave",
    "sg:city":"Elk Grove Village",
    "sg:classifiers":[
        {
            "category":"Wholesale",
            "subcategory":"Stationery",
            "type":"Manufacturing & Wholesale Goods"
        }
    ],
    "sg:phone":"+1 847 952 9000",
    "sg:postcode":"60007",
    "sg:province":"IL",
    "sg:tags":[
        "product",
        "paper",
        "disposable",
        "plastic"
    ],
    "wof:name":"A W Mendenhall Co Inc",
    "wof:placetype":"venue"
},
  "geometry": {"coordinates":[-87.944058,42.002229],"type":"Point"}
}