{
  "type": "Feature",
  "properties": {
    "iso:country":"US",
    "sg:address":"418 W Touhy Ave",
    "sg:city":"Park Ridge",
    "sg:classifiers":[
        {
            "category":"Organizations",
            "subcategory":"Religious Organization",
            "type":"Services"
        }
    ],
    "sg:phone":"+1 847 825 3144",
    "sg:postcode":"60068",
    "sg:province":"IL",
    "sg:website":"www.parkridgeumc.org",
    "wof:name":"First United Methodist Church",
    "wof:placetype":"venue"
},
  "geometry": {"coordinates":[-87.827701,42.011354],"type":"Point"}
}