{
  "type": "Feature",
  "properties": {
    "iso:country":"US",
    "sg:address":"1616 Barclay Blvd",
    "sg:city":"Buffalo Grove",
    "sg:classifiers":[
        {
            "category":"Building & Trades",
            "subcategory":"Construction",
            "type":"Services"
        }
    ],
    "sg:phone":"+1 847 229 0056",
    "sg:postcode":"60089",
    "sg:province":"IL",
    "sg:tags":[
        "general",
        "contractor"
    ],
    "wof:name":"Elite Construction Co",
    "wof:placetype":"venue"
},
  "geometry": {"coordinates":[-87.93565700000001,42.179604],"type":"Point"}
}