{
  "type": "Feature",
  "properties": {
    "iso:country":"US",
    "sg:address":"520 N Kingsbury",
    "sg:city":"Chicago",
    "sg:classifiers":[
        {
            "category":"Shopping",
            "subcategory":"Clothing, Apparel, & Fashions",
            "type":"Retail Goods"
        }
    ],
    "sg:phone":"+1 773 276 3888",
    "sg:postcode":"60654",
    "sg:province":"IL",
    "sg:tags":[
        "clothing",
        "women's"
    ],
    "sg:website":"www.shopverucasalt.com",
    "wof:name":"Veruca Salt",
    "wof:placetype":"venue"
},
  "geometry": {"coordinates":[-87.639751,41.891358],"type":"Point"}
}