{
  "type": "Feature",
  "properties": {
    "addr:full":"3752 S Ashland Ave Chicago IL 60609",
    "addr:housenumber":"3752",
    "addr:postcode":"60609",
    "addr:street":"S Ashland Ave",
    "iso:country":"US",
    "sg:address":"3752 S Ashland Ave",
    "sg:city":"Chicago",
    "sg:classifiers":[
        {
            "category":"Food & Beverages",
            "subcategory":"Groceries & Convenience Stores",
            "type":"Retail Goods"
        },
        {
            "category":"Food & Beverages",
            "subcategory":"Meat & Fish",
            "type":"Retail Goods"
        }
    ],
    "sg:phone":"+1 773 523 8891",
    "sg:postcode":"60609",
    "sg:province":"IL",
    "sg:tags":[
        "market"
    ],
    "wof:name":"Francisco Vivo Inc",
    "wof:placetype":"venue"
},
  "geometry": {"coordinates":[-87.665594,41.825617],"type":"Point"}
}