{
  "type": "Feature",
  "properties": {
    "addr:full":"1650 W F St Belleville IL 62226",
    "addr:housenumber":"1650",
    "addr:postcode":"62226",
    "addr:street":"W F St",
    "iso:country":"US",
    "sg:address":"1650 W F St",
    "sg:city":"Belleville",
    "sg:classifiers":[
        {
            "category":"Shopping",
            "subcategory":"Florist",
            "type":"Retail Goods"
        }
    ],
    "sg:phone":"+1 618 746 2467",
    "sg:postcode":"62226",
    "sg:province":"IL",
    "wof:name":"Scott Flower Shop",
    "wof:placetype":"venue"
},
  "geometry": {"coordinates":[-90.000913,38.521312],"type":"Point"}
}