{
  "type": "Feature",
  "properties": {
    "addr:full":"9318 N Old Towerline Rd Edwards IL 61528",
    "addr:housenumber":"9318",
    "addr:postcode":"61528",
    "addr:street":"N Old Towerline Rd",
    "iso:country":"US",
    "sg:address":"9318 N Old Towerline Rd",
    "sg:city":"Edwards",
    "sg:classifiers":[
        {
            "category":"Farming",
            "subcategory":"Farm",
            "type":"Manufacturing & Wholesale Goods"
        }
    ],
    "sg:phone":"+1 309 692 0146",
    "sg:postcode":"61528",
    "sg:province":"IL",
    "sg:tags":[
        "crop",
        "general"
    ],
    "wof:name":"Burns Farms",
    "wof:placetype":"venue"
},
  "geometry": {"coordinates":[-89.73694500000001,40.790656],"type":"Point"}
}