{
  "type": "Feature",
  "properties": {
    "addr:full":"700 N Milwaukee Ave Vernon Hills IL 60061",
    "addr:housenumber":"700",
    "addr:postcode":"60061",
    "addr:street":"N Milwaukee Ave",
    "iso:country":"US",
    "sg:address":"700 N Milwaukee Ave",
    "sg:city":"Vernon Hills",
    "sg:classifiers":[
        {
            "category":"Bakery",
            "type":"Food & Drink"
        },
        {
            "category":"Coffee & Tea",
            "type":"Food & Drink"
        },
        {
            "category":"Bagels",
            "type":"Food & Drink"
        },
        {
            "category":"Donuts",
            "type":"Food & Drink"
        }
    ],
    "sg:menulink":"http://www.allmenus.com/il/vernon/135308-dunkin-donuts/menu/",
    "sg:phone":"+1 847 362 4224",
    "sg:postcode":"60061",
    "sg:province":"IL",
    "sg:tags":[
        "american",
        "pastry"
    ],
    "wof:name":"Dunkin' Donuts",
    "wof:placetype":"venue"
},
  "geometry": {"coordinates":[-87.944333,42.23801],"type":"Point"}
}