{
  "type": "Feature",
  "properties": {
    "iso:country":"US",
    "sg:address":"1065 Chase Ave",
    "sg:city":"Elk Grove Vlg",
    "sg:classifiers":[
        {
            "category":"Wholesale",
            "subcategory":"Hardware",
            "type":"Manufacturing & Wholesale Goods"
        }
    ],
    "sg:phone":"+1 847 427 0500",
    "sg:postcode":"60007",
    "sg:province":"IL",
    "sg:tags":[
        "screw",
        "fastener"
    ],
    "sg:website":"www.activescrew.com",
    "wof:name":"Active Screw & Fastener",
    "wof:placetype":"venue"
},
  "geometry": {"coordinates":[-87.97168000000001,42.009953],"type":"Point"}
}