{
  "type": "Feature",
  "properties": {
    "addr:full":"1187 N Farnsworth Ave Aurora IL 60505",
    "addr:housenumber":"1187",
    "addr:postcode":"60505",
    "addr:street":"N Farnsworth Ave",
    "iso:country":"US",
    "sg:address":"1187 N Farnsworth Ave",
    "sg:city":"Aurora",
    "sg:classifiers":[
        {
            "category":"Education",
            "subcategory":"Special Training",
            "type":"Public Place"
        }
    ],
    "sg:phone":"+1 630 585 0184",
    "sg:postcode":"60505",
    "sg:province":"IL",
    "sg:tags":[
        "educational"
    ],
    "wof:name":"Ombudsman Educational Svc",
    "wof:placetype":"venue"
},
  "geometry": {"coordinates":[-88.281723,41.77952],"type":"Point"}
}