{
  "type": "Feature",
  "properties": {
    "iso:country":"US",
    "sg:address":"1315 Alexandra Blvd",
    "sg:city":"Crystal Lake",
    "sg:classifiers":[
        {
            "category":"Building & Trades",
            "subcategory":"Construction",
            "type":"Services"
        }
    ],
    "sg:phone":"+1 815 788 9805",
    "sg:postcode":"60014",
    "sg:province":"IL",
    "sg:tags":[
        "concrete",
        "contractor"
    ],
    "wof:name":"AMS Concrete",
    "wof:placetype":"venue"
},
  "geometry": {"coordinates":[-88.368678,42.200209],"type":"Point"}
}