{
  "type": "Feature",
  "properties": {
    "addr:full":"2611 Patricia Ln Mc Henry IL 60050",
    "addr:housenumber":"2611",
    "addr:postcode":"60050",
    "addr:street":"Patricia Ln Mc Henry",
    "iso:country":"US",
    "sg:address":"2611 Patricia Ln",
    "sg:city":"Mc Henry",
    "sg:classifiers":[
        {
            "category":"Social Services",
            "subcategory":"Child Care",
            "type":"Services"
        }
    ],
    "sg:phone":"+1 815 363 8058",
    "sg:postcode":"60050",
    "sg:province":"IL",
    "sg:tags":[
        "day"
    ],
    "wof:name":"Bonnie Lynk",
    "wof:placetype":"venue"
},
  "geometry": {"coordinates":[-88.256032,42.365207],"type":"Point"}
}