{
  "type": "Feature",
  "properties": {
    "addr:full":"651 N Raddant Rd Batavia IL 60510",
    "addr:housenumber":"651",
    "addr:postcode":"60510",
    "addr:street":"N Raddant Rd",
    "iso:country":"US",
    "sg:address":"651 N Raddant Rd",
    "sg:city":"Batavia",
    "sg:classifiers":[
        {
            "category":"Manufacturing",
            "subcategory":"Paper Products",
            "type":"Manufacturing & Wholesale Goods"
        }
    ],
    "sg:phone":"+1 630 761 3335",
    "sg:postcode":"60510",
    "sg:province":"IL",
    "sg:tags":[
        "packaging",
        "bag",
        "mfg"
    ],
    "sg:website":"www.flex-pak.biz",
    "wof:name":"Flex-Pak Packaging Products",
    "wof:placetype":"venue"
},
  "geometry": {"coordinates":[-88.29297,41.85934],"type":"Point"}
}