{
  "type": "Feature",
  "properties": {
    "addr:full":"14507 Flat Branch Rd Carlyle IL 62231",
    "addr:housenumber":"14507",
    "addr:postcode":"62231",
    "addr:street":"Flat Branch Rd",
    "iso:country":"US",
    "sg:address":"14507 Flat Branch Rd",
    "sg:city":"Carlyle",
    "sg:classifiers":[
        {
            "category":"Farming",
            "subcategory":"Farm",
            "type":"Manufacturing & Wholesale Goods"
        }
    ],
    "sg:phone":"+1 618 594 8900",
    "sg:postcode":"62231",
    "sg:province":"IL",
    "sg:tags":[
        "crop",
        "general"
    ],
    "wof:name":"Erwin Schaeli",
    "wof:placetype":"venue"
},
  "geometry": {"coordinates":[-89.400811,38.632059],"type":"Point"}
}