{
  "type": "Feature",
  "properties": {
    "addr:full":"145 Wayne Rd Rochelle IL 61068",
    "addr:housenumber":"145",
    "addr:postcode":"61068",
    "addr:street":"Wayne Rd",
    "iso:country":"US",
    "sg:address":"145 Wayne Rd",
    "sg:city":"Rochelle",
    "sg:classifiers":[
        {
            "category":"Building & Trades",
            "subcategory":"Construction",
            "type":"Services"
        }
    ],
    "sg:phone":"+1 815 562 3796",
    "sg:postcode":"61068",
    "sg:province":"IL",
    "sg:tags":[
        "house"
    ],
    "wof:name":"El J Construction",
    "wof:placetype":"venue"
},
  "geometry": {"coordinates":[-89.071994,41.949758],"type":"Point"}
}