{
  "type": "Feature",
  "properties": {
    "addr:full":"1409 N Euclid Ave Princeton IL 61356",
    "addr:housenumber":"1409",
    "addr:postcode":"61356",
    "addr:street":"N Euclid Ave",
    "iso:country":"US",
    "sg:address":"1409 N Euclid Ave",
    "sg:city":"Princeton",
    "sg:classifiers":[
        {
            "category":"Wholesale",
            "subcategory":"Motor Vehicles",
            "type":"Manufacturing & Wholesale Goods"
        }
    ],
    "sg:phone":"+1 815 872 1630",
    "sg:postcode":"61356",
    "sg:province":"IL",
    "sg:tags":[
        "car",
        "used"
    ],
    "wof:name":"K & E Auto Sales",
    "wof:placetype":"venue"
},
  "geometry": {"coordinates":[-89.460418,41.39253],"type":"Point"}
}