{
  "type": "Feature",
  "properties": {
    "addr:full":"2130 W Chicago Ave Chicago IL 60622",
    "addr:housenumber":"2130",
    "addr:postcode":"60622",
    "addr:street":"W Chicago Ave",
    "iso:country":"US",
    "sg:address":"2130 W Chicago Ave",
    "sg:city":"Chicago",
    "sg:classifiers":[
        {
            "category":"Travel",
            "subcategory":"Travel Agent",
            "type":"Entertainment"
        }
    ],
    "sg:phone":"+1 773 235 9322",
    "sg:postcode":"60622",
    "sg:province":"IL",
    "sg:tags":[
        "agency"
    ],
    "wof:name":"Ata American Travel Agency",
    "wof:placetype":"venue"
},
  "geometry": {"coordinates":[-87.680255,41.895878],"type":"Point"}
}