{
  "type": "Feature",
  "properties": {
    "iso:country":"US",
    "sg:address":"5600 W 35th St",
    "sg:city":"Cicero",
    "sg:classifiers":[
        {
            "category":"Restaurant",
            "type":"Food & Drink"
        }
    ],
    "sg:phone":"+1 708 652 5866",
    "sg:postcode":"60804",
    "sg:province":"IL",
    "wof:name":"Cozzi Corner",
    "wof:placetype":"venue"
},
  "geometry": {"coordinates":[-87.763603,41.829102],"type":"Point"}
}