{
  "type": "Feature",
  "properties": {
    "addr:full":"8200 Melvina Ave Bedford Park IL 60459",
    "addr:postcode":"8200;60459",
    "addr:street":"Melvina Ave",
    "iso:country":"US",
    "sg:address":"8200 Melvina Ave",
    "sg:city":"Bedford Park",
    "sg:classifiers":[
        {
            "category":"Professional",
            "subcategory":"Computer Services",
            "type":"Services"
        }
    ],
    "sg:phone":"+1 708 599 8238",
    "sg:postcode":"60459",
    "sg:province":"IL",
    "sg:tags":[
        "prepackaged",
        "software"
    ],
    "wof:name":"Framework Software Inc",
    "wof:placetype":"venue"
},
  "geometry": {"coordinates":[-87.77513500000001,41.742152],"type":"Point"}
}