{
  "type": "Feature",
  "properties": {
    "addr:full":"501 4th St Cornell IL 61319",
    "addr:housenumber":"501",
    "addr:postcode":"61319",
    "addr:street":"4Th St",
    "iso:country":"US",
    "sg:address":"501 4th St",
    "sg:city":"Cornell",
    "sg:classifiers":[
        {
            "category":"Organizations",
            "subcategory":"Religious Organization",
            "type":"Services"
        }
    ],
    "sg:phone":"+1 815 358 2347",
    "sg:postcode":"61319",
    "sg:province":"IL",
    "sg:tags":[
        "church"
    ],
    "wof:name":"United Methodist Church",
    "wof:placetype":"venue"
},
  "geometry": {"coordinates":[-88.73145,40.99413],"type":"Point"}
}