{
  "type": "Feature",
  "properties": {
    "iso:country":"US",
    "sg:address":"656 W Randolph St",
    "sg:city":"Chicago",
    "sg:classifiers":[
        {
            "category":"Professional",
            "subcategory":"Lawyer & Legal Services",
            "type":"Services"
        }
    ],
    "sg:phone":"+1 312 902 9970",
    "sg:postcode":"60661",
    "sg:province":"IL",
    "wof:name":"Richard C Balough",
    "wof:placetype":"venue"
},
  "geometry": {"coordinates":[-87.644623,41.8845],"type":"Point"}
}