{
  "type": "Feature",
  "properties": {
    "iso:country":"US",
    "sg:address":"920 Maple Ave",
    "sg:city":"Evanston",
    "sg:classifiers":[
        {
            "category":"Manufacturing",
            "subcategory":"Tools & Machinery",
            "type":"Manufacturing & Wholesale Goods"
        }
    ],
    "sg:phone":"+1 847 491 3686",
    "sg:postcode":"60202",
    "sg:province":"IL",
    "sg:tags":[
        "optical",
        "mfg"
    ],
    "wof:name":"Yotem",
    "wof:placetype":"venue"
},
  "geometry": {"coordinates":[-87.685273,42.035449],"type":"Point"}
}