{
  "type": "Feature",
  "properties": {
    "iso:country":"US",
    "sg:address":"1506 W 127th St Ste 1",
    "sg:city":"Calumet Park",
    "sg:classifiers":[
        {
            "category":"Personal",
            "subcategory":"Barber",
            "type":"Services"
        }
    ],
    "sg:phone":"+1 708 293 1632",
    "sg:postcode":"60827",
    "sg:province":"IL",
    "wof:name":"B & B Barber Shop",
    "wof:placetype":"venue"
},
  "geometry": {"coordinates":[-87.658514,41.663115],"type":"Point"}
}