{
  "type": "Feature",
  "properties": {
    "addr:full":"426 N Wanda Ln Palatine IL 60067",
    "addr:housenumber":"426",
    "addr:postcode":"60067",
    "addr:street":"N Wanda Ln",
    "iso:country":"US",
    "sg:address":"426 N Wanda Ln",
    "sg:city":"Palatine",
    "sg:classifiers":[
        {
            "category":"Building & Trades",
            "subcategory":"Construction",
            "type":"Services"
        }
    ],
    "sg:phone":"+1 847 705 7373",
    "sg:postcode":"60067",
    "sg:province":"IL",
    "sg:tags":[
        "painting",
        "contractor"
    ],
    "wof:name":"Ultimate Painting Inc",
    "wof:placetype":"venue"
},
  "geometry": {"coordinates":[-88.05574900000001,42.118305],"type":"Point"}
}