{
  "type": "Feature",
  "properties": {
    "iso:country":"US",
    "sg:address":"12120 Western Ave",
    "sg:city":"Blue Island",
    "sg:classifiers":[
        {
            "category":"Wholesale",
            "subcategory":"Painting Supplies",
            "type":"Manufacturing & Wholesale Goods"
        }
    ],
    "sg:phone":"+1 708 371 2240",
    "sg:postcode":"60406",
    "sg:province":"IL",
    "sg:tags":[
        "paint",
        "wallpaper",
        "brush"
    ],
    "wof:name":"Calumet Paint & Wallpaper Inc",
    "wof:placetype":"venue"
},
  "geometry": {"coordinates":[-87.680643,41.673234],"type":"Point"}
}