{
  "type": "Feature",
  "properties": {
    "iso:country":"US",
    "sg:address":"2690 E 2350th St",
    "sg:city":"Vermont",
    "sg:classifiers":[
        {
            "category":"Professional",
            "subcategory":"Employment Agencies",
            "type":"Services"
        }
    ],
    "sg:phone":"+1 309 784 2156",
    "sg:postcode":"61484",
    "sg:province":"IL",
    "sg:tags":[
        "consultant",
        "search",
        "executive"
    ],
    "wof:name":"Physician Source Inc",
    "wof:placetype":"venue"
},
  "geometry": {"coordinates":[-90.459098,40.319308],"type":"Point"}
}