{
  "type": "Feature",
  "properties": {
    "addr:full":"6630 Stonewall Ave Downers Grove IL 60516",
    "addr:housenumber":"6630",
    "addr:postcode":"60516",
    "addr:street":"Stonewall Ave",
    "iso:country":"US",
    "sg:address":"6630 Stonewall Ave",
    "sg:city":"Downers Grove",
    "sg:classifiers":[
        {
            "category":"Health Services",
            "subcategory":"Hospital",
            "type":"Services"
        }
    ],
    "sg:phone":"+1 708 915 6307",
    "sg:postcode":"60516",
    "sg:province":"IL",
    "sg:tags":[
        "general"
    ],
    "wof:name":"Ingalls Memorial Hospital",
    "wof:placetype":"venue"
},
  "geometry": {"coordinates":[-88.02826,41.766482],"type":"Point"}
}