{
  "type": "Feature",
  "properties": {
    "addr:full":"12540 S Holiday Dr Alsip IL 60803",
    "addr:housenumber":"12540",
    "addr:postcode":"60803",
    "addr:street":"S Holiday Dr",
    "iso:country":"US",
    "sg:address":"12540 S Holiday Dr",
    "sg:city":"Alsip",
    "sg:classifiers":[
        {
            "category":"Wholesale",
            "subcategory":"Machinery & Supplies",
            "type":"Manufacturing & Wholesale Goods"
        }
    ],
    "sg:phone":"+1 708 388 3300",
    "sg:postcode":"60803",
    "sg:province":"IL",
    "sg:tags":[
        "equipment",
        "pneumatic",
        "component",
        "hydraulic"
    ],
    "wof:name":"American Fluid Power Co Inc",
    "wof:placetype":"venue"
},
  "geometry": {"coordinates":[-87.74619,41.663831],"type":"Point"}
}