{
  "type": "Feature",
  "properties": {
    "iso:country":"US",
    "sg:address":"300 W Main St",
    "sg:city":"Belleville",
    "sg:classifiers":[
        {
            "category":"Insurance",
            "subcategory":"Insurance Agent",
            "type":"Services"
        }
    ],
    "sg:phone":"+1 618 233 0644",
    "sg:postcode":"62220",
    "sg:province":"IL",
    "wof:name":"W A Schickedanz Agency Inc",
    "wof:placetype":"venue"
},
  "geometry": {"coordinates":[-89.989928,38.513625],"type":"Point"}
}