{
  "type": "Feature",
  "properties": {
    "addr:full":"2903 N Broadway Chicago IL 60657",
    "addr:housenumber":"2903",
    "addr:postcode":"60657",
    "addr:street":"N Broadway",
    "iso:country":"US",
    "sg:address":"2903 N Broadway",
    "sg:city":"Chicago",
    "sg:classifiers":[
        {
            "category":"Personal",
            "subcategory":"Beauty Salon",
            "type":"Services"
        }
    ],
    "sg:phone":"+1 773 472 0883",
    "sg:postcode":"60657",
    "sg:province":"IL",
    "sg:tags":[
        "hair"
    ],
    "wof:name":"L'Etoile Salon & Spa",
    "wof:placetype":"venue"
},
  "geometry": {"coordinates":[-87.644215,41.935096],"type":"Point"}
}