{
  "type": "Feature",
  "properties": {
    "addr:full":"10452 Randall Rd Capron IL 61012",
    "addr:housenumber":"10452",
    "addr:postcode":"61012",
    "addr:street":"Randall Rd",
    "iso:country":"US",
    "sg:address":"10452 Randall Rd",
    "sg:city":"Capron",
    "sg:classifiers":[
        {
            "category":"Farming",
            "subcategory":"Farm",
            "type":"Manufacturing & Wholesale Goods"
        }
    ],
    "sg:phone":"+1 815 737 8736",
    "sg:postcode":"61012",
    "sg:province":"IL",
    "sg:tags":[
        "crop",
        "general"
    ],
    "wof:name":"Anderson Joyne",
    "wof:placetype":"venue"
},
  "geometry": {"coordinates":[-88.74288799999999,42.458483],"type":"Point"}
}