{
  "type": "Feature",
  "properties": {
    "addr:full":"228 W Main St Collinsville IL 62234",
    "addr:housenumber":"228",
    "addr:postcode":"62234",
    "addr:street":"W Main St",
    "iso:country":"US",
    "sg:address":"228 W Main St",
    "sg:city":"Collinsville",
    "sg:classifiers":[
        {
            "category":"Shopping",
            "subcategory":"Pharmacy",
            "type":"Retail Goods"
        }
    ],
    "sg:phone":"+1   ",
    "sg:postcode":"62234",
    "sg:province":"IL",
    "sg:tags":[
        "drug",
        "store"
    ],
    "wof:name":"Family Pharmacy Collinsville",
    "wof:placetype":"venue"
},
  "geometry": {"coordinates":[-89.988371,38.669256],"type":"Point"}
}