{
  "type": "Feature",
  "properties": {
    "addr:full":"375 W Briarcliff Rd Bolingbrook IL 60440",
    "addr:housenumber":"375",
    "addr:postcode":"60440",
    "addr:street":"W Briarcliff Rd",
    "iso:country":"US",
    "sg:address":"375 W Briarcliff Rd",
    "sg:city":"Bolingbrook",
    "sg:classifiers":[
        {
            "category":"Organizations",
            "subcategory":"Professional Association",
            "type":"Services"
        }
    ],
    "sg:phone":"+1 630 226 8420",
    "sg:postcode":"60440",
    "sg:province":"IL",
    "sg:tags":[
        "chambers",
        "commerce"
    ],
    "wof:name":"Bolingbrook Chamber-Commerce",
    "wof:placetype":"venue"
},
  "geometry": {"coordinates":[-88.081045,41.698115],"type":"Point"}
}