{
  "type": "Feature",
  "properties": {
    "addr:full":"36 W Randolph St Chicago IL 60601",
    "addr:housenumber":"36",
    "addr:postcode":"60601",
    "addr:street":"W Randolph St",
    "iso:country":"US",
    "sg:address":"36 W Randolph St",
    "sg:city":"Chicago",
    "sg:classifiers":[
        {
            "category":"Insurance",
            "subcategory":"Insurance Agent",
            "type":"Services"
        },
        {
            "category":"Insurance",
            "subcategory":"Hazard Insurance",
            "type":"Services"
        }
    ],
    "sg:phone":"+1 312 553 9999",
    "sg:postcode":"60601",
    "sg:province":"IL",
    "sg:tags":[
        "insured",
        "property",
        "adjuster",
        "replacement"
    ],
    "wof:name":"Eps Settlement Chicgo",
    "wof:placetype":"venue"
},
  "geometry": {"coordinates":[-87.629057,41.884477],"type":"Point"}
}