{
  "type": "Feature",
  "properties": {
    "iso:country":"US",
    "sg:address":"1808 Beach St",
    "sg:city":"Broadview",
    "sg:classifiers":[
        {
            "category":"Retail",
            "subcategory":"Repair Shop",
            "type":"Services"
        },
        {
            "category":"Building & Trades",
            "subcategory":"Construction",
            "type":"Services"
        }
    ],
    "sg:phone":"+1 708 345 2800",
    "sg:postcode":"60155",
    "sg:province":"IL",
    "sg:tags":[
        "equipment",
        "electrical",
        "contractor"
    ],
    "sg:website":"www.consolidatedrepair.com",
    "wof:name":"Consolidated Repair Services",
    "wof:placetype":"venue"
},
  "geometry": {"coordinates":[-87.86575999999999,41.870642],"type":"Point"}
}