{
  "type": "Feature",
  "properties": {
    "iso:country":"US",
    "sg:address":"5510 N Menard Avenue",
    "sg:city":"Chicago",
    "sg:classifiers":[
        {
            "category":"Health Services",
            "subcategory":"Health Practitioner",
            "type":"Services"
        }
    ],
    "sg:phone":"+1 773 792 1288",
    "sg:postcode":"60630",
    "sg:province":"IL",
    "sg:tags":[
        "naturopathic/holistic"
    ],
    "wof:name":"Thomas Michael J Naprpth",
    "wof:placetype":"venue"
},
  "geometry": {"coordinates":[-87.77296800000001,41.981374],"type":"Point"}
}