{
  "type": "Feature",
  "properties": {
    "addr:full":"400 W Lake St Barrington IL 60010",
    "addr:housenumber":"400",
    "addr:postcode":"60010",
    "addr:street":"W Lake St",
    "iso:country":"US",
    "sg:address":"400 W Lake St",
    "sg:city":"Barrington",
    "sg:classifiers":[
        {
            "category":"Building & Trades",
            "subcategory":"Construction",
            "type":"Services"
        }
    ],
    "sg:phone":"+1 847 381 6945",
    "sg:postcode":"60010",
    "sg:province":"IL",
    "sg:tags":[
        "paving",
        "contractor"
    ],
    "wof:name":"Special Service Maintenance",
    "wof:placetype":"venue"
},
  "geometry": {"coordinates":[-88.142169,42.152489],"type":"Point"}
}