{
  "type": "Feature",
  "properties": {
    "addr:full":"1832 W 95th St Chicago IL 60643",
    "addr:housenumber":"1832",
    "addr:postcode":"60643",
    "addr:street":"W 95Th St",
    "iso:country":"US",
    "sg:address":"1832 W 95th St",
    "sg:city":"Chicago",
    "sg:classifiers":[
        {
            "category":"Shopping",
            "type":"Retail Goods"
        }
    ],
    "sg:phone":"+1   ",
    "sg:postcode":"60643",
    "sg:province":"IL",
    "sg:tags":[
        "equipment",
        "durable",
        "medical"
    ],
    "wof:name":"S & S Durable Med Eqp & Sup",
    "wof:placetype":"venue"
},
  "geometry": {"coordinates":[-87.668881,41.721197],"type":"Point"}
}