{
  "type": "Feature",
  "properties": {
    "addr:full":"4523 W Belmont Ave Chicago IL 60641",
    "addr:housenumber":"4523",
    "addr:postcode":"60641",
    "addr:street":"W Belmont Ave",
    "iso:country":"US",
    "sg:address":"4523 W Belmont Ave",
    "sg:city":"Chicago",
    "sg:classifiers":[
        {
            "category":"Retail",
            "subcategory":"Auto Repair",
            "type":"Services"
        }
    ],
    "sg:phone":"+1 773 685 4460",
    "sg:postcode":"60641",
    "sg:province":"IL",
    "wof:name":"Autoworks Quality Repair Inc",
    "wof:placetype":"venue"
},
  "geometry": {"coordinates":[-87.740577,41.938795],"type":"Point"}
}