{
  "type": "Feature",
  "properties": {
    "iso:country":"US",
    "sg:address":"1345 N Main St",
    "sg:city":"Canton",
    "sg:classifiers":[
        {
            "category":"Manufacturing",
            "subcategory":"Tools & Machinery",
            "type":"Manufacturing & Wholesale Goods"
        }
    ],
    "sg:phone":"+1 309 647 2331",
    "sg:postcode":"61520",
    "sg:province":"IL",
    "sg:tags":[
        "electric",
        "mfg"
    ],
    "wof:name":"Main Sno Shack",
    "wof:placetype":"venue"
},
  "geometry": {"coordinates":[-90.036057,40.575178],"type":"Point"}
}