{
  "type": "Feature",
  "properties": {
    "iso:country":"US",
    "sg:address":"385 N Wells St",
    "sg:city":"Nauvoo",
    "sg:classifiers":[
        {
            "category":"Organizations",
            "subcategory":"Religious Organization",
            "type":"Services"
        }
    ],
    "sg:phone":"+1 217 453 2300",
    "sg:postcode":"62354",
    "sg:province":"IL",
    "sg:tags":[
        "church"
    ],
    "wof:name":"Reorg Ch Of Jesus Christ Lds",
    "wof:placetype":"venue"
},
  "geometry": {"coordinates":[-91.384919,40.553372],"type":"Point"}
}