{
  "type": "Feature",
  "properties": {
    "addr:full":"5665 N Lincoln Ave Chicago IL 60686",
    "addr:housenumber":"5665",
    "addr:postcode":"60686",
    "addr:street":"N Lincoln Ave",
    "iso:country":"US",
    "sg:address":"5665 N Lincoln Ave",
    "sg:city":"Chicago",
    "sg:classifiers":[
        {
            "category":"Restaurant",
            "type":"Food & Drink"
        }
    ],
    "sg:phone":"+1 773 561 2277",
    "sg:postcode":"60686",
    "sg:province":"IL",
    "sg:tags":[
        "korean",
        "sushi",
        "bar",
        "japanese"
    ],
    "sg:website":"www.tampopochicago.com",
    "wof:name":"Tampopo \u00a0Japanese Restaurant",
    "wof:placetype":"venue"
},
  "geometry": {"coordinates":[-87.69734800000001,41.984448],"type":"Point"}
}