{
  "type": "Feature",
  "properties": {
    "iso:country":"US",
    "sg:address":"69 E Elm St",
    "sg:city":"Canton",
    "sg:classifiers":[
        {
            "category":"Manufacturing",
            "subcategory":"Tobacco Products",
            "type":"Manufacturing & Wholesale Goods"
        }
    ],
    "sg:phone":"+1 309 647 7569",
    "sg:postcode":"61520",
    "sg:province":"IL",
    "sg:tags":[
        "cigarette",
        "cigar"
    ],
    "wof:name":"Smokers Paradise",
    "wof:placetype":"venue"
},
  "geometry": {"coordinates":[-90.034137,40.555843],"type":"Point"}
}