{
  "type": "Feature",
  "properties": {
    "iso:country":"US",
    "sg:address":"2500 N Milwaukee Ave",
    "sg:city":"Chicago",
    "sg:classifiers":[
        {
            "category":"Manufacturing",
            "subcategory":"Leather Goods",
            "type":"Manufacturing & Wholesale Goods"
        },
        {
            "category":"Shopping",
            "subcategory":"Luggage & Leather Goods",
            "type":"Retail Goods"
        }
    ],
    "sg:phone":"+1 773 292 6202",
    "sg:postcode":"60647",
    "sg:province":"IL",
    "wof:name":"Hannans Leather & Stuff",
    "wof:placetype":"venue"
},
  "geometry": {"coordinates":[-87.702945,41.926338],"type":"Point"}
}