{
  "type": "Feature",
  "properties": {
    "iso:country":"US",
    "sg:address":"3001 N Duncan Rd",
    "sg:city":"Champaign",
    "sg:classifiers":[
        {
            "category":"Shopping",
            "type":"Retail Goods"
        }
    ],
    "sg:phone":"+1 217 359 4400",
    "sg:postcode":"61822",
    "sg:province":"IL",
    "sg:tags":[
        "equipment",
        "telephone",
        "supply"
    ],
    "wof:name":"Alliance Communications",
    "wof:placetype":"venue"
},
  "geometry": {"coordinates":[-88.295973,40.148649],"type":"Point"}
}