{
  "type": "Feature",
  "properties": {
    "iso:country":"US",
    "sg:address":"160 Ridgewood Rd",
    "sg:city":"Riverside",
    "sg:classifiers":[
        {
            "category":"Building & Trades",
            "subcategory":"Construction",
            "type":"Services"
        }
    ],
    "sg:phone":"+1 708 442 5709",
    "sg:postcode":"60546",
    "sg:province":"IL",
    "sg:tags":[
        "contractor"
    ],
    "wof:name":"James McHugh Construction",
    "wof:placetype":"venue"
},
  "geometry": {"coordinates":[-87.828569,41.82818],"type":"Point"}
}