{
  "type": "Feature",
  "properties": {
    "iso:country":"US",
    "sg:address":"625 Rudat Ct",
    "sg:city":"Crystal Lake",
    "sg:classifiers":[
        {
            "category":"Social Services",
            "subcategory":"Child Care",
            "type":"Services"
        }
    ],
    "sg:phone":"+1 815 459 2266",
    "sg:postcode":"60014",
    "sg:province":"IL",
    "sg:tags":[
        "kindergarten",
        "academic",
        "school",
        "day"
    ],
    "wof:name":"Thunderbird City Nursery Schl",
    "wof:placetype":"venue"
},
  "geometry": {"coordinates":[-88.33579400000001,42.225738],"type":"Point"}
}