{
  "type": "Feature",
  "properties": {
    "iso:country":"US",
    "sg:address":"437 8th St",
    "sg:city":"Lincoln",
    "sg:classifiers":[
        {
            "category":"Wholesale",
            "subcategory":"Vending Machines",
            "type":"Manufacturing & Wholesale Goods"
        }
    ],
    "sg:phone":"+1 217 735 1230",
    "sg:postcode":"62656",
    "sg:province":"IL",
    "sg:tags":[
        "screw",
        "product"
    ],
    "sg:website":"http://www.lawscrew.com",
    "wof:name":"Lawrence Screw Products Inc",
    "wof:placetype":"venue"
},
  "geometry": {"coordinates":[-89.373238,40.150363],"type":"Point"}
}