{
  "type": "Feature",
  "properties": {
    "addr:full":"703 Moffett Rd Lake Bluff IL 60044",
    "addr:housenumber":"703",
    "addr:postcode":"60044",
    "addr:street":"Moffett Rd",
    "iso:country":"US",
    "sg:address":"703 Moffett Rd",
    "sg:city":"Lake Bluff",
    "sg:classifiers":[
        {
            "category":"Wholesale",
            "subcategory":"Stationery",
            "type":"Manufacturing & Wholesale Goods"
        }
    ],
    "sg:phone":"+1 847 234 1701",
    "sg:postcode":"60044",
    "sg:province":"IL",
    "sg:tags":[
        "paper",
        "metal",
        "center"
    ],
    "wof:name":"John H Kuhlmann & Associates",
    "wof:placetype":"venue"
},
  "geometry": {"coordinates":[-87.836218,42.282147],"type":"Point"}
}