{
  "type": "Feature",
  "properties": {
    "iso:country":"US",
    "sg:address":"601 E Hurlbut Ave",
    "sg:city":"Belvidere",
    "sg:classifiers":[
        {
            "category":"Social Services",
            "subcategory":"Child Care",
            "type":"Services"
        }
    ],
    "sg:phone":"+1 815 547 4897",
    "sg:postcode":"61008",
    "sg:province":"IL",
    "sg:tags":[
        "day"
    ],
    "wof:name":"Pearson Kitchens & Bath",
    "wof:placetype":"venue"
},
  "geometry": {"coordinates":[-88.841077,42.263484],"type":"Point"}
}