{
  "type": "Feature",
  "properties": {
    "iso:country":"US",
    "sg:address":"17953 Bypass Rd",
    "sg:city":"Charleston",
    "sg:classifiers":[
        {
            "category":"Shopping",
            "subcategory":"Stationery & Office Supplies",
            "type":"Retail Goods"
        }
    ],
    "sg:phone":"+1 217 345 4007",
    "sg:postcode":"61920",
    "sg:province":"IL",
    "sg:tags":[
        "map"
    ],
    "wof:name":"Phelps Map Svc",
    "wof:placetype":"venue"
},
  "geometry": {"coordinates":[-88.146301,39.455331],"type":"Point"}
}