{
  "type": "Feature",
  "properties": {
    "iso:country":"US",
    "sg:address":"401 S Clay St",
    "sg:city":"Mount Carroll",
    "sg:classifiers":[
        {
            "category":"Ice Cream",
            "type":"Food & Drink"
        }
    ],
    "sg:menulink":"http://www.allmenus.com/il/mount-carroll/161927-dairy-queen/menu/",
    "sg:phone":"+1 815 244 4305",
    "sg:postcode":"61053",
    "sg:province":"IL",
    "sg:tags":[
        "burger",
        "american"
    ],
    "wof:name":"Dairy Queen",
    "wof:placetype":"venue"
},
  "geometry": {"coordinates":[-89.977617,42.094745],"type":"Point"}
}