{
  "type": "Feature",
  "properties": {
    "iso:country":"US",
    "sg:address":"1020 S Hunt Club Dr",
    "sg:city":"Mount Prospect",
    "sg:classifiers":[
        {
            "category":"Social Services",
            "subcategory":"Child Care",
            "type":"Services"
        }
    ],
    "sg:phone":"+1 847 956 6222",
    "sg:postcode":"60056",
    "sg:province":"IL",
    "sg:tags":[
        "day"
    ],
    "wof:name":"Minee-Subee City",
    "wof:placetype":"venue"
},
  "geometry": {"coordinates":[-87.944885,42.045126],"type":"Point"}
}