{
  "type": "Feature",
  "properties": {
    "iso:country":"US",
    "sg:address":"346 Taft Ave",
    "sg:city":"Glen Ellyn",
    "sg:classifiers":[
        {
            "category":"Banks & Credit Unions",
            "subcategory":"Bank",
            "type":"Services"
        }
    ],
    "sg:phone":"+1 630 858 0730",
    "sg:postcode":"60137",
    "sg:province":"IL",
    "wof:name":"Comunity Bank Wheaton Glen Ellyn",
    "wof:placetype":"venue"
},
  "geometry": {"coordinates":[-88.074203,41.858398],"type":"Point"}
}