{
  "type": "Feature",
  "properties": {
    "addr:full":"1206 Gertrude Ave Champaign IL 61821",
    "addr:housenumber":"1206",
    "addr:postcode":"61821",
    "addr:street":"Gertrude Ave",
    "iso:country":"US",
    "sg:address":"1206 Gertrude Ave",
    "sg:city":"Champaign",
    "sg:classifiers":[
        {
            "category":"Building & Trades",
            "subcategory":"Construction",
            "type":"Services"
        }
    ],
    "sg:phone":"+1 217 355 1329",
    "sg:postcode":"61821",
    "sg:province":"IL",
    "sg:tags":[
        "contractor"
    ],
    "wof:name":"Delmedico Construction Inc",
    "wof:placetype":"venue"
},
  "geometry": {"coordinates":[-88.265322,40.133688],"type":"Point"}
}