{
  "type": "Feature",
  "properties": {
    "iso:country":"US",
    "sg:address":"2800 Outer Dr",
    "sg:city":"Marion",
    "sg:classifiers":[
        {
            "category":"Home & Garden",
            "subcategory":"Carpets & Floor Coverings",
            "type":"Retail Goods"
        },
        {
            "category":"Building & Trades",
            "subcategory":"Construction",
            "type":"Services"
        },
        {
            "category":"Home & Garden",
            "subcategory":"Furniture",
            "type":"Retail Goods"
        }
    ],
    "sg:phone":"+1 618 993 2202",
    "sg:postcode":"62959",
    "sg:province":"IL",
    "sg:tags":[
        "interior",
        "design",
        "carpeting",
        "store"
    ],
    "sg:website":"www.distinctiveinteriors.com",
    "wof:name":"Distinctive Interiors Inc",
    "wof:placetype":"venue"
},
  "geometry": {"coordinates":[-88.974532,37.746469],"type":"Point"}
}