{
  "type": "Feature",
  "properties": {
    "addr:full":"4770 Main St Lisle IL 60532",
    "addr:housenumber":"4770",
    "addr:postcode":"60532",
    "addr:street":"Main St",
    "iso:country":"US",
    "sg:address":"4770 Main St",
    "sg:city":"Lisle",
    "sg:classifiers":[
        {
            "category":"Utilities",
            "subcategory":"Cable",
            "type":"Services"
        }
    ],
    "sg:phone":"+1 630 963 1372",
    "sg:postcode":"60532",
    "sg:province":"IL",
    "sg:tags":[
        "television"
    ],
    "wof:name":"AT&T",
    "wof:placetype":"venue"
},
  "geometry": {"coordinates":[-88.074648,41.799048],"type":"Point"}
}