{
  "type": "Feature",
  "properties": {
    "iso:country":"US",
    "sg:address":"510 Island Ave",
    "sg:city":"Rockford",
    "sg:classifiers":[
        {
            "category":"Organizations",
            "subcategory":"Religious Organization",
            "type":"Services"
        }
    ],
    "sg:phone":"+1 815 962 5282",
    "sg:postcode":"61102",
    "sg:province":"IL",
    "sg:tags":[
        "church"
    ],
    "wof:name":"Southside Church Of God",
    "wof:placetype":"venue"
},
  "geometry": {"coordinates":[-89.105193,42.254869],"type":"Point"}
}