{
  "type": "Feature",
  "properties": {
    "addr:full":"1 Grant St Crystal Lake IL 60014",
    "addr:housenumber":"1",
    "addr:postcode":"60014",
    "addr:street":"Grant St",
    "iso:country":"US",
    "sg:address":"1 Grant St",
    "sg:city":"Crystal Lake",
    "sg:classifiers":[
        {
            "category":"Freight",
            "type":"Transportation"
        }
    ],
    "sg:phone":"+1 815 455 4505",
    "sg:postcode":"60014",
    "sg:province":"IL",
    "sg:tags":[
        "mover"
    ],
    "wof:name":"New Movers",
    "wof:placetype":"venue"
},
  "geometry": {"coordinates":[-88.319177,42.242976],"type":"Point"}
}