{
  "type": "Feature",
  "properties": {
    "addr:full":"7300 Lawndale Ave Skokie IL 60076",
    "addr:housenumber":"7300",
    "addr:postcode":"60076",
    "addr:street":"Lawndale Ave",
    "iso:country":"US",
    "sg:address":"7300 Lawndale Ave",
    "sg:city":"Skokie",
    "sg:classifiers":[
        {
            "category":"Building & Trades",
            "subcategory":"Landscaping Services",
            "type":"Services"
        }
    ],
    "sg:phone":"+1 847 982 2077",
    "sg:postcode":"60076",
    "sg:province":"IL",
    "wof:name":"Aviv Gardening Inc",
    "wof:placetype":"venue"
},
  "geometry": {"coordinates":[-87.72122,42.015416],"type":"Point"}
}