{
  "type": "Feature",
  "properties": {
    "addr:full":"2434 Wolf Rd Westchester IL 60154",
    "addr:housenumber":"2434",
    "addr:postcode":"60154",
    "addr:street":"Wolf Rd",
    "iso:country":"US",
    "sg:address":"2434 Wolf Rd",
    "sg:city":"Westchester",
    "sg:classifiers":[
        {
            "category":"Health Services",
            "subcategory":"Doctor",
            "type":"Services"
        }
    ],
    "sg:phone":"+1 708 562 5541",
    "sg:postcode":"60154",
    "sg:province":"IL",
    "sg:tags":[
        "medical"
    ],
    "wof:name":"Donald Higgins Do",
    "wof:placetype":"venue"
},
  "geometry": {"coordinates":[-87.901157,41.842368],"type":"Point"}
}