{
  "type": "Feature",
  "properties": {
    "addr:full":"4001 N Nashville Ave Chicago IL 60634",
    "addr:housenumber":"4001",
    "addr:postcode":"60634",
    "addr:street":"N Nashville Ave",
    "iso:country":"US",
    "sg:address":"4001 N Nashville Ave",
    "sg:city":"Chicago",
    "sg:classifiers":[
        {
            "category":"Manufacturing",
            "subcategory":"Motor Vehicles & Parts",
            "type":"Manufacturing & Wholesale Goods"
        },
        {
            "category":"Wholesale",
            "subcategory":"Auto Parts",
            "type":"Manufacturing & Wholesale Goods"
        },
        {
            "category":"Retail",
            "subcategory":"Auto Repair",
            "type":"Services"
        }
    ],
    "sg:phone":"+1 773 725 8930",
    "sg:postcode":"60634",
    "sg:province":"IL",
    "sg:tags":[
        "body",
        "shop",
        "supply",
        "automobile",
        "supply-wholesale",
        "equipment",
        "service-equipment",
        "repairing",
        "manufacturer"
    ],
    "wof:name":"Derpol",
    "wof:placetype":"venue"
},
  "geometry": {"coordinates":[-87.791878,41.952808],"type":"Point"}
}