{
  "type": "Feature",
  "properties": {
    "addr:full":"219 Robert Parker Coffin Rd Long Grove IL 60047",
    "addr:housenumber":"219",
    "addr:postcode":"60047",
    "addr:street":"Robert Parker Coffin Rd",
    "iso:country":"US",
    "sg:address":"219 Robert Parker Coffin Rd",
    "sg:city":"Long Grove",
    "sg:classifiers":[
        {
            "category":"Shopping",
            "subcategory":"Gifts & Souvenirs",
            "type":"Retail Goods"
        }
    ],
    "sg:phone":"+1 847 634 6552",
    "sg:postcode":"60047",
    "sg:province":"IL",
    "sg:tags":[
        "announcement",
        "invitation"
    ],
    "wof:name":"Nickelby's",
    "wof:placetype":"venue"
},
  "geometry": {"coordinates":[-87.998532,42.178139],"type":"Point"}
}