{
  "type": "Feature",
  "properties": {
    "iso:country":"US",
    "sg:address":"2411 E Oakton St",
    "sg:city":"Arlington Hts",
    "sg:classifiers":[
        {
            "category":"Building & Trades",
            "subcategory":"Construction",
            "type":"Services"
        }
    ],
    "sg:phone":"+1 847 437 7900",
    "sg:postcode":"60005",
    "sg:province":"IL",
    "sg:tags":[
        "roofing",
        "contractor"
    ],
    "wof:name":"Bill Weyrich Metal & Roofing",
    "wof:placetype":"venue"
},
  "geometry": {"coordinates":[-87.94923,42.022501],"type":"Point"}
}