{
  "type": "Feature",
  "properties": {
    "iso:country":"US",
    "sg:address":"1315 Paramount Pkwy",
    "sg:city":"Batavia",
    "sg:classifiers":[
        {
            "category":"Manufacturing",
            "subcategory":"Tools & Machinery",
            "type":"Manufacturing & Wholesale Goods"
        }
    ],
    "sg:phone":"+1 630 879 1200",
    "sg:postcode":"60510",
    "sg:province":"IL",
    "sg:tags":[
        "design",
        "consul",
        "mfg",
        "electronic",
        "instrument"
    ],
    "wof:name":"Mar-TEC Research Inc",
    "wof:placetype":"venue"
},
  "geometry": {"coordinates":[-88.271798,41.865003],"type":"Point"}
}