{
  "type": "Feature",
  "properties": {
    "iso:country":"US",
    "sg:address":"25692 E 825 N Rd",
    "sg:city":"Forrest",
    "sg:classifiers":[
        {
            "category":"Wholesale",
            "subcategory":"Farm Supplies",
            "type":"Manufacturing & Wholesale Goods"
        }
    ],
    "sg:phone":"+1 815 657 8129",
    "sg:postcode":"61741",
    "sg:province":"IL",
    "sg:tags":[
        "buyer",
        "livestock"
    ],
    "wof:name":"Ibp Inc",
    "wof:placetype":"venue"
},
  "geometry": {"coordinates":[-88.436246,40.748695],"type":"Point"}
}