{
  "type": "Feature",
  "properties": {
    "iso:country":"US",
    "sg:address":"500 Industrial Rd",
    "sg:city":"Crystal Lake",
    "sg:classifiers":[
        {
            "category":"Manufacturing",
            "subcategory":"Tools & Machinery",
            "type":"Manufacturing & Wholesale Goods"
        }
    ],
    "sg:phone":"+1 815 459 2210",
    "sg:postcode":"60012",
    "sg:province":"IL",
    "sg:tags":[
        "farm",
        "equipment"
    ],
    "sg:website":"www.mathewsco.com",
    "wof:name":"Mathews Co",
    "wof:placetype":"venue"
},
  "geometry": {"coordinates":[-88.30735799999999,42.251711],"type":"Point"}
}