{
  "type": "Feature",
  "properties": {
    "iso:country":"US",
    "sg:address":"24531 W Ford Rd",
    "sg:city":"Channahon",
    "sg:classifiers":[
        {
            "category":"Travel",
            "subcategory":"Hotels & Motels",
            "type":"Entertainment"
        }
    ],
    "sg:phone":"+1 815 467 2171",
    "sg:postcode":"60410",
    "sg:province":"IL",
    "sg:website":"www.lakeshokakana.com",
    "wof:name":"Lake Shokakana Family Resort",
    "wof:placetype":"venue"
},
  "geometry": {"coordinates":[-88.23339799999999,41.435699],"type":"Point"}
}