{
  "type": "Feature",
  "properties": {
    "addr:full":"6701 Ogden Ave Berwyn IL 60402",
    "addr:housenumber":"6701",
    "addr:postcode":"60402",
    "addr:street":"Ogden Ave",
    "iso:country":"US",
    "sg:address":"6701 Ogden Ave",
    "sg:city":"Berwyn",
    "sg:classifiers":[
        {
            "category":"Retail",
            "subcategory":"Auto Repair",
            "type":"Services"
        }
    ],
    "sg:phone":"+1 708 788 1539",
    "sg:postcode":"60402",
    "sg:province":"IL",
    "sg:tags":[
        "general"
    ],
    "wof:name":"Motra Milex Car Care Ctr",
    "wof:placetype":"venue"
},
  "geometry": {"coordinates":[-87.79140700000001,41.827667],"type":"Point"}
}