{
  "type": "Feature",
  "properties": {
    "addr:full":"6051 W 115th St Alsip IL 60803",
    "addr:housenumber":"6051",
    "addr:postcode":"60803",
    "addr:street":"W 115Th St",
    "iso:country":"US",
    "sg:address":"6051 W 115th St",
    "sg:city":"Alsip",
    "sg:classifiers":[
        {
            "category":"Freight",
            "type":"Transportation"
        }
    ],
    "sg:phone":"+1 708 239 7000",
    "sg:postcode":"60803",
    "sg:province":"IL",
    "sg:tags":[
        "management",
        "arrangement"
    ],
    "wof:name":"National Consolidation Service",
    "wof:placetype":"venue"
},
  "geometry": {"coordinates":[-87.772087,41.683139],"type":"Point"}
}