{
  "type": "Feature",
  "properties": {
    "addr:full":"2085 Prairie Rd Ashton IL 61006",
    "addr:housenumber":"2085",
    "addr:postcode":"61006",
    "addr:street":"Prairie Rd",
    "iso:country":"US",
    "sg:address":"2085 Prairie Rd",
    "sg:city":"Ashton",
    "sg:classifiers":[
        {
            "category":"Mining & Drilling",
            "type":"Manufacturing & Wholesale Goods"
        }
    ],
    "sg:phone":"+1 815 453 2240",
    "sg:postcode":"61006",
    "sg:province":"IL",
    "sg:tags":[
        "quarry"
    ],
    "wof:name":"Macklin Inc",
    "wof:placetype":"venue"
},
  "geometry": {"coordinates":[-89.260679,41.882599],"type":"Point"}
}