{
  "type": "Feature",
  "properties": {
    "iso:country":"US",
    "sg:address":"600 Roosevelt Rd",
    "sg:city":"Glen Ellyn",
    "sg:classifiers":[
        {
            "category":"Banks & Credit Unions",
            "subcategory":"Bank",
            "type":"Services"
        }
    ],
    "sg:phone":"+1 630 469 6520",
    "sg:postcode":"60137",
    "sg:province":"IL",
    "sg:website":"www.lasallebank.com",
    "wof:name":"Lasalle Bank",
    "wof:placetype":"venue"
},
  "geometry": {"coordinates":[-88.061401,41.859299],"type":"Point"}
}