{
  "type": "Feature",
  "properties": {
    "addr:full":"3255 E Burville Rd Crete IL 60417",
    "addr:housenumber":"3255",
    "addr:postcode":"60417",
    "addr:street":"E Burville Rd",
    "iso:country":"US",
    "sg:address":"3255 E Burville Rd",
    "sg:city":"Crete",
    "sg:classifiers":[
        {
            "category":"Professional",
            "subcategory":"Management & Consulting",
            "type":"Services"
        }
    ],
    "sg:phone":"+1 708 672 6665",
    "sg:postcode":"60417",
    "sg:province":"IL",
    "sg:tags":[
        "business"
    ],
    "wof:name":"Kbl Consulting Inc",
    "wof:placetype":"venue"
},
  "geometry": {"coordinates":[-87.53537,41.440948],"type":"Point"}
}