{
  "type": "Feature",
  "properties": {
    "iso:country":"US",
    "sg:address":"14 Prosper Ct",
    "sg:city":"Lake In The Hls",
    "sg:classifiers":[
        {
            "category":"Wholesale",
            "subcategory":"Electrical",
            "type":"Manufacturing & Wholesale Goods"
        }
    ],
    "sg:phone":"+1 847 658 7525",
    "sg:postcode":"60156",
    "sg:province":"IL",
    "sg:tags":[
        "control"
    ],
    "wof:name":"Automated Systems",
    "wof:placetype":"venue"
},
  "geometry": {"coordinates":[-88.30415499999999,42.190106],"type":"Point"}
}