{
  "type": "Feature",
  "properties": {
    "iso:country":"US",
    "sg:address":"520 W Howard St",
    "sg:city":"Pontiac",
    "sg:classifiers":[
        {
            "category":"Place Of Worship",
            "subcategory":"Church",
            "type":"Public Place"
        },
        {
            "category":"Place Of Worship",
            "type":"Public Place"
        }
    ],
    "sg:phone":"+1 815 842 1366",
    "sg:postcode":"61764",
    "sg:province":"IL",
    "sg:tags":[
        "jesus",
        "churches-church",
        "christ",
        "saint",
        "latter-day"
    ],
    "sg:website":"http://www.lds.org",
    "wof:name":"Mormon's Church",
    "wof:placetype":"venue"
},
  "geometry": {"coordinates":[-88.633476,40.881139],"type":"Point"}
}