{
  "type": "Feature",
  "properties": {
    "iso:country":"US",
    "sg:address":"5514 W Fullerton Avenue",
    "sg:city":"Chicago",
    "sg:classifiers":[
        {
            "category":"Banks & Credit Unions",
            "subcategory":"Financial Services",
            "type":"Services"
        }
    ],
    "sg:phone":"+1 773 237 1800",
    "sg:postcode":"60639",
    "sg:province":"IL",
    "sg:tags":[
        "broker",
        "mortgage"
    ],
    "wof:name":"Mla Mortgage",
    "wof:placetype":"venue"
},
  "geometry": {"coordinates":[-87.763927,41.924047],"type":"Point"}
}