{
  "type": "Feature",
  "properties": {
    "iso:country":"US",
    "sg:address":"13 S 2nd St",
    "sg:city":"Geneva",
    "sg:classifiers":[
        {
            "category":"Personal",
            "type":"Services"
        }
    ],
    "sg:phone":"+1 630 262 5399",
    "sg:postcode":"60134",
    "sg:province":"IL",
    "wof:name":"Internatl Society Hair Restor",
    "wof:placetype":"venue"
},
  "geometry": {"coordinates":[-88.306639,41.886793],"type":"Point"}
}