{
  "type": "Feature",
  "properties": {
    "iso:country":"US",
    "sg:address":"170 Chicago St",
    "sg:city":"Cary",
    "sg:classifiers":[
        {
            "category":"Manufacturing",
            "subcategory":"Petroleum Products",
            "type":"Manufacturing & Wholesale Goods"
        }
    ],
    "sg:phone":"+1 847 462 8000",
    "sg:postcode":"60013",
    "sg:province":"IL",
    "sg:tags":[
        "contract"
    ],
    "wof:name":"Skyler Manufacturing Corp",
    "wof:placetype":"venue"
},
  "geometry": {"coordinates":[-88.232316,42.202148],"type":"Point"}
}