{
  "type": "Feature",
  "properties": {
    "addr:full":"2017 State Rte 23 Grand Ridge IL 61325",
    "addr:housenumber":"2017",
    "addr:postcode":"61325",
    "addr:street":"State Rte 23 Grand Ridge",
    "iso:country":"US",
    "sg:address":"2017 State Rte 23",
    "sg:city":"Grand Ridge",
    "sg:classifiers":[
        {
            "category":"Wholesale",
            "subcategory":"Farm Supplies",
            "type":"Manufacturing & Wholesale Goods"
        }
    ],
    "sg:phone":"+1 815 249 6216",
    "sg:postcode":"61325",
    "sg:province":"IL",
    "sg:tags":[
        "bulb",
        "seed"
    ],
    "wof:name":"Mycogen Seeds",
    "wof:placetype":"venue"
},
  "geometry": {"coordinates":[-88.83617099999999,41.222706],"type":"Point"}
}