{
  "type": "Feature",
  "properties": {
    "iso:country":"US",
    "sg:address":"75 Market St",
    "sg:city":"Elgin",
    "sg:classifiers":[
        {
            "category":"Insurance",
            "subcategory":"Life Insurance",
            "type":"Services"
        }
    ],
    "sg:phone":"+1 847 741 6252",
    "sg:postcode":"60123",
    "sg:province":"IL",
    "sg:tags":[
        "carrier"
    ],
    "wof:name":"MetLife",
    "wof:placetype":"venue"
},
  "geometry": {"coordinates":[-88.32021899999999,42.035504],"type":"Point"}
}