{
  "type": "Feature",
  "properties": {
    "iso:country":"US",
    "sg:address":"426 E Devon Ave",
    "sg:city":"Elk Grove Vlg",
    "sg:classifiers":[
        {
            "category":"Retail",
            "subcategory":"Repair Shop",
            "type":"Services"
        },
        {
            "category":"Shopping",
            "subcategory":"Computers & Home Electronics",
            "type":"Retail Goods"
        }
    ],
    "sg:phone":"+1 847 437 1212",
    "sg:postcode":"60007",
    "sg:province":"IL",
    "sg:tags":[
        "rental",
        "radio",
        "television",
        "video",
        "tape"
    ],
    "wof:name":"Elk Grove TV & Video",
    "wof:placetype":"venue"
},
  "geometry": {"coordinates":[-87.988112,41.992785],"type":"Point"}
}