{
  "type": "Feature",
  "properties": {
    "iso:country":"US",
    "sg:address":"1210 S Waukegan Rd",
    "sg:city":"Waukegan",
    "sg:classifiers":[
        {
            "category":"Wholesale",
            "subcategory":"Medical Equipment & Supplies",
            "type":"Manufacturing & Wholesale Goods"
        }
    ],
    "sg:phone":"+1 847 578 4200",
    "sg:postcode":"60085",
    "sg:province":"IL",
    "sg:tags":[
        "laboratory"
    ],
    "sg:website":"http://www.vwrsp.com",
    "wof:name":"Vwr Scientific Products",
    "wof:placetype":"venue"
},
  "geometry": {"coordinates":[-87.89497900000001,42.337075],"type":"Point"}
}