{
  "type": "Feature",
  "properties": {
    "iso:country":"US",
    "sg:address":"418 W Blackhawk Dr",
    "sg:city":"Byron",
    "sg:classifiers":[
        {
            "category":"Insurance",
            "subcategory":"Hazard Insurance",
            "type":"Services"
        },
        {
            "category":"Insurance",
            "subcategory":"Insurance Agent",
            "type":"Services"
        },
        {
            "category":"Insurance",
            "subcategory":"Life Insurance",
            "type":"Services"
        },
        {
            "category":"Insurance",
            "subcategory":"Title Insurance",
            "type":"Services"
        }
    ],
    "sg:phone":"+1 815 234 2735",
    "sg:postcode":"61010",
    "sg:province":"IL",
    "sg:tags":[
        "auto",
        "commercial",
        "business",
        "homeowner"
    ],
    "sg:website":"http://www.countryfinancial.com/chris.criddle",
    "wof:name":"COUNTRY Financial Christopher Criddle",
    "wof:placetype":"venue"
},
  "geometry": {"coordinates":[-89.313168,42.095456],"type":"Point"}
}