{
  "type": "Feature",
  "properties": {
    "addr:full":"404 Jackson St Henry IL 61537",
    "addr:housenumber":"404",
    "addr:postcode":"61537",
    "addr:street":"Jackson St",
    "iso:country":"US",
    "sg:address":"404 Jackson St",
    "sg:city":"Henry",
    "sg:classifiers":[
        {
            "category":"Autos & Motor Vehicles",
            "subcategory":"Automobile Sales",
            "type":"Retail Goods"
        }
    ],
    "sg:phone":"+1   ",
    "sg:postcode":"61537",
    "sg:province":"IL",
    "sg:tags":[
        "used"
    ],
    "wof:name":"Foley Motors",
    "wof:placetype":"venue"
},
  "geometry": {"coordinates":[-89.369776,41.111391],"type":"Point"}
}