{
  "type": "Feature",
  "properties": {
    "addr:full":"3140 Harvey Ave Berwyn IL 60402",
    "addr:housenumber":"3140",
    "addr:postcode":"60402",
    "addr:street":"Harvey Ave",
    "iso:country":"US",
    "sg:address":"3140 Harvey Ave",
    "sg:city":"Berwyn",
    "sg:classifiers":[
        {
            "category":"Shopping",
            "subcategory":"Computers & Home Electronics",
            "type":"Retail Goods"
        }
    ],
    "sg:phone":"+1 708 788 6516",
    "sg:postcode":"60402",
    "sg:province":"IL",
    "sg:tags":[
        "equipment",
        "satellite",
        "system"
    ],
    "wof:name":"Dish Communications",
    "wof:placetype":"venue"
},
  "geometry": {"coordinates":[-87.77950300000001,41.834702],"type":"Point"}
}