{
  "type": "Feature",
  "properties": {
    "addr:full":"2601 Quentin Rd Schaumburg IL 60173",
    "addr:housenumber":"2601",
    "addr:postcode":"60173",
    "addr:street":"Quentin Rd",
    "iso:country":"US",
    "sg:address":"2601 Quentin Rd",
    "sg:city":"Schaumburg",
    "sg:classifiers":[
        {
            "category":"Social Services",
            "subcategory":"Child Care",
            "type":"Services"
        },
        {
            "category":"Education",
            "subcategory":"Preschool",
            "type":"Public Place"
        }
    ],
    "sg:phone":"+1 847 397 0799",
    "sg:postcode":"60173",
    "sg:province":"IL",
    "sg:tags":[
        "kindergarten",
        "nursery",
        "day"
    ],
    "sg:website":"http://www.kindercare.com/our-centers/center-details/301541/?cid=YP_KC301541",
    "wof:name":"North Schaumburg KinderCare",
    "wof:placetype":"venue"
},
  "geometry": {"coordinates":[-88.062988,42.075241],"type":"Point"}
}