{
  "type": "Feature",
  "properties": {
    "iso:country":"US",
    "sg:address":"1231 Rockland Rd",
    "sg:city":"Lake Bluff",
    "sg:classifiers":[
        {
            "category":"Autos & Motor Vehicles",
            "subcategory":"Automobile Sales",
            "type":"Retail Goods"
        }
    ],
    "sg:phone":"+1 847 918 1576",
    "sg:postcode":"60044",
    "sg:province":"IL",
    "sg:tags":[
        "car",
        "used",
        "dealer"
    ],
    "wof:name":"Memory Lane Motors Inc",
    "wof:placetype":"venue"
},
  "geometry": {"coordinates":[-87.887734,42.280067],"type":"Point"}
}