{
  "type": "Feature",
  "properties": {
    "addr:full":"6909 N Ridge Blvd Chicago IL 60645",
    "addr:housenumber":"6909",
    "addr:postcode":"60645",
    "addr:street":"N Ridge Blvd",
    "iso:country":"US",
    "sg:address":"6909 N Ridge Blvd",
    "sg:city":"Chicago",
    "sg:classifiers":[
        {
            "category":"Taxi",
            "type":"Transportation"
        }
    ],
    "sg:phone":"+1 773 764 9936",
    "sg:postcode":"60645",
    "sg:province":"IL",
    "sg:tags":[
        "taxicab"
    ],
    "wof:name":"Chicago Breeze Cab Co",
    "wof:placetype":"venue"
},
  "geometry": {"coordinates":[-87.68119299999999,42.007591],"type":"Point"}
}