{
  "type": "Feature",
  "properties": {
    "iso:country":"US",
    "sg:address":"1406 Walnut St",
    "sg:city":"Lawrenceville",
    "sg:classifiers":[
        {
            "category":"Social Services",
            "subcategory":"Child Care",
            "type":"Services"
        }
    ],
    "sg:phone":"+1 618 943 5421",
    "sg:postcode":"62439",
    "sg:province":"IL",
    "sg:tags":[
        "day"
    ],
    "wof:name":"First Chrstn Chch Day Care Ctr",
    "wof:placetype":"venue"
},
  "geometry": {"coordinates":[-87.685457,38.730219],"type":"Point"}
}