{
  "type": "Feature",
  "properties": {
    "iso:country":"US",
    "sg:address":"24661 Passavant Ave",
    "sg:city":"Round Lake",
    "sg:classifiers":[
        {
            "category":"Building & Trades",
            "subcategory":"Landscaping Services",
            "type":"Services"
        }
    ],
    "sg:phone":"+1 847 740 8072",
    "sg:postcode":"60073",
    "sg:province":"IL",
    "sg:tags":[
        "landscape"
    ],
    "wof:name":"Ambriz Landscaping",
    "wof:placetype":"venue"
},
  "geometry": {"coordinates":[-88.114277,42.37214],"type":"Point"}
}