{
  "type": "Feature",
  "properties": {
    "iso:country":"US",
    "sg:address":"4556 W Grand Ave",
    "sg:city":"Chicago",
    "sg:classifiers":[
        {
            "category":"Manufacturing",
            "subcategory":"Tools & Machinery",
            "type":"Manufacturing & Wholesale Goods"
        },
        {
            "category":"Wholesale",
            "subcategory":"Machinery & Supplies",
            "type":"Manufacturing & Wholesale Goods"
        },
        {
            "category":"Home & Garden",
            "subcategory":"Home Furnishings",
            "type":"Retail Goods"
        }
    ],
    "sg:phone":"+1 773 252 0400",
    "sg:postcode":"60639",
    "sg:province":"IL",
    "sg:tags":[
        "handling",
        "shelving",
        "equipment-wholesale",
        "material",
        "equipment",
        "industrial",
        "manufacturer"
    ],
    "wof:name":"Reb Storage Systems Intl",
    "wof:placetype":"venue"
},
  "geometry": {"coordinates":[-87.740427,41.911716],"type":"Point"}
}