{
  "type": "Feature",
  "properties": {
    "iso:country":"US",
    "sg:address":"1314 Main St",
    "sg:city":"Batavia",
    "sg:classifiers":[
        {
            "category":"Organizations",
            "subcategory":"Religious Organization",
            "type":"Services"
        }
    ],
    "sg:phone":"+1 630 879 3721",
    "sg:postcode":"60510",
    "sg:province":"IL",
    "sg:tags":[
        "place",
        "worship",
        "church"
    ],
    "sg:website":"http://www.thecovenant.net",
    "wof:name":"Batavia Covenant Church",
    "wof:placetype":"venue"
},
  "geometry": {"coordinates":[-88.330555,41.846831],"type":"Point"}
}