{
  "type": "Feature",
  "properties": {
    "addr:full":"70 S Madison St Carthage IL 62321",
    "addr:housenumber":"70",
    "addr:postcode":"62321",
    "addr:street":"S Madison St",
    "iso:country":"US",
    "sg:address":"70 S Madison St",
    "sg:city":"Carthage",
    "sg:classifiers":[
        {
            "category":"Shopping",
            "subcategory":"Pharmacy",
            "type":"Retail Goods"
        }
    ],
    "sg:phone":"+1 217 357 2623",
    "sg:postcode":"62321",
    "sg:province":"IL",
    "wof:name":"Mc Hugh Drug Store",
    "wof:placetype":"venue"
},
  "geometry": {"coordinates":[-91.136374,40.412746],"type":"Point"}
}