{
  "type": "Feature",
  "properties": {
    "iso:country":"US",
    "sg:address":"845 Danforth St",
    "sg:city":"Alton",
    "sg:classifiers":[
        {
            "category":"Place Of Worship",
            "subcategory":"Monastery",
            "type":"Public Place"
        },
        {
            "category":"Organizations",
            "subcategory":"Religious Organization",
            "type":"Services"
        }
    ],
    "sg:phone":"+1 618 465 0791",
    "sg:postcode":"62002",
    "sg:province":"IL",
    "sg:tags":[
        "convent"
    ],
    "wof:name":"Ursline Infirmary",
    "wof:placetype":"venue"
},
  "geometry": {"coordinates":[-90.196223,38.907431],"type":"Point"}
}