{
  "type": "Feature",
  "properties": {
    "addr:full":"1190 N McLean Blvd Elgin IL 60123",
    "addr:housenumber":"1190",
    "addr:postcode":"60123",
    "addr:street":"N Mclean Blvd",
    "iso:country":"US",
    "sg:address":"1190 N McLean Blvd",
    "sg:city":"Elgin",
    "sg:classifiers":[
        {
            "category":"Autos & Motor Vehicles",
            "subcategory":"Fuel & Gas Station",
            "type":"Retail Goods"
        }
    ],
    "sg:phone":"+1 847 488 9404",
    "sg:postcode":"60123",
    "sg:province":"IL",
    "wof:name":"T B Petroleum",
    "wof:placetype":"venue"
},
  "geometry": {"coordinates":[-88.315399,42.0625],"type":"Point"}
}