{
  "type": "Feature",
  "properties": {
    "addr:full":"2289 S Mount Prospect Rd Des Plaines IL 60018",
    "addr:housenumber":"2289",
    "addr:postcode":"60018",
    "addr:street":"S Mount Prospect Rd Des",
    "iso:country":"US",
    "sg:address":"2289 S Mount Prospect Rd",
    "sg:city":"Des Plaines",
    "sg:classifiers":[
        {
            "category":"Shopping",
            "subcategory":"Pharmacy",
            "type":"Retail Goods"
        }
    ],
    "sg:phone":"+1 847 635 9189",
    "sg:postcode":"60018",
    "sg:province":"IL",
    "wof:name":"Care Tech",
    "wof:placetype":"venue"
},
  "geometry": {"coordinates":[-87.920675,42.01568],"type":"Point"}
}