{
  "type": "Feature",
  "properties": {
    "iso:country":"US",
    "sg:address":"108 E 11th St",
    "sg:city":"Rock Falls",
    "sg:classifiers":[
        {
            "category":"Manufacturing",
            "subcategory":"Glass & Minerals",
            "type":"Manufacturing & Wholesale Goods"
        }
    ],
    "sg:phone":"+1 815 625 2233",
    "sg:postcode":"61071",
    "sg:province":"IL",
    "sg:tags":[
        "prod",
        "made"
    ],
    "wof:name":"Kurtz Enterprises",
    "wof:placetype":"venue"
},
  "geometry": {"coordinates":[-89.689269,41.770876],"type":"Point"}
}