{
  "type": "Feature",
  "properties": {
    "iso:country":"US",
    "sg:address":"300 N Kennedy Dr",
    "sg:city":"Bradley",
    "sg:classifiers":[
        {
            "category":"Insurance",
            "subcategory":"Insurance Agent",
            "type":"Services"
        }
    ],
    "sg:phone":"+1 815 935 2182",
    "sg:postcode":"60915",
    "sg:province":"IL",
    "wof:name":"Primerica",
    "wof:placetype":"venue"
},
  "geometry": {"coordinates":[-87.875434,41.148006],"type":"Point"}
}