{
  "type": "Feature",
  "properties": {
    "addr:full":"18845 Hwy 113 Custer Park IL 60481",
    "addr:housenumber":"18845",
    "addr:postcode":"60481",
    "addr:street":"Hwy 113;Park",
    "iso:country":"US",
    "sg:address":"18845 Hwy 113",
    "sg:city":"Custer Park",
    "sg:classifiers":[
        {
            "category":"Building & Trades",
            "subcategory":"Construction",
            "type":"Services"
        }
    ],
    "sg:phone":"+1 815 458 2939",
    "sg:postcode":"60481",
    "sg:province":"IL",
    "sg:tags":[
        "insulation",
        "heat",
        "contractor"
    ],
    "wof:name":"Innovative Insulation Inc",
    "wof:placetype":"venue"
},
  "geometry": {"coordinates":[-88.03639200000001,41.212471],"type":"Point"}
}