{
  "type": "Feature",
  "properties": {
    "addr:full":"1026 W Montrose Ave Chicago IL 60613",
    "addr:housenumber":"1026",
    "addr:postcode":"60613",
    "addr:street":"W Montrose Ave",
    "iso:country":"US",
    "sg:address":"1026 W Montrose Ave",
    "sg:city":"Chicago",
    "sg:classifiers":[
        {
            "category":"Fast Food",
            "type":"Food & Drink"
        },
        {
            "category":"Restaurant",
            "type":"Food & Drink"
        }
    ],
    "sg:phone":"+1 773 880 0355",
    "sg:postcode":"60613",
    "sg:province":"IL",
    "sg:tags":[
        "mexican",
        "take"
    ],
    "wof:name":"Mr. Salsa",
    "wof:placetype":"venue"
},
  "geometry": {"coordinates":[-87.655868,41.961757],"type":"Point"}
}