{
  "type": "Feature",
  "properties": {
    "addr:full":"3510 Hobson Rd Woodridge IL 60517",
    "addr:housenumber":"3510",
    "addr:postcode":"60517",
    "addr:street":"Hobson Rd",
    "iso:country":"US",
    "sg:address":"3510 Hobson Rd",
    "sg:city":"Woodridge",
    "sg:classifiers":[
        {
            "category":"Health Services",
            "subcategory":"Doctor",
            "type":"Services"
        }
    ],
    "sg:phone":"+1 630 969 3663",
    "sg:postcode":"60517",
    "sg:province":"IL",
    "sg:tags":[
        "medical"
    ],
    "wof:name":"Elias M Haddad",
    "wof:placetype":"venue"
},
  "geometry": {"coordinates":[-88.06771999999999,41.760263],"type":"Point"}
}