{
  "type": "Feature",
  "properties": {
    "iso:country":"US",
    "sg:address":"3301 Kirchoff Rd",
    "sg:city":"Rolling Meadows",
    "sg:classifiers":[
        {
            "category":"Restaurant",
            "type":"Food & Drink"
        }
    ],
    "sg:phone":"+1 847 253 3401",
    "sg:postcode":"60008",
    "sg:province":"IL",
    "wof:name":"Fratellos II",
    "wof:placetype":"venue"
},
  "geometry": {"coordinates":[-88.025199,42.080082],"type":"Point"}
}