{
  "type": "Feature",
  "properties": {
    "iso:country":"US",
    "sg:address":"1401 E Main St",
    "sg:city":"Streator",
    "sg:classifiers":[
        {
            "category":"Restaurant",
            "type":"Food & Drink"
        }
    ],
    "sg:menulink":"http://www.allmenus.com/il/bruce/226444-caseys-general-store/menu/",
    "sg:phone":"+1 815 673 5946",
    "sg:postcode":"61364",
    "sg:province":"IL",
    "sg:tags":[
        "american",
        "pizza"
    ],
    "wof:name":"Casey's General Store",
    "wof:placetype":"venue"
},
  "geometry": {"coordinates":[-88.817984,41.121016],"type":"Point"}
}