{
  "type": "Feature",
  "properties": {
    "iso:country":"US",
    "sg:address":"1001 E Main St # 3",
    "sg:city":"Carbondale",
    "sg:classifiers":[
        {
            "category":"Health Services",
            "subcategory":"Dentist",
            "type":"Services"
        }
    ],
    "sg:phone":"+1 618 457 2522",
    "sg:postcode":"62901",
    "sg:province":"IL",
    "wof:name":"Simpson James E DMD",
    "wof:placetype":"venue"
},
  "geometry": {"coordinates":[-89.20168,37.728484],"type":"Point"}
}