{
  "type": "Feature",
  "properties": {
    "iso:country":"US",
    "sg:address":"1026 Moen Ave",
    "sg:city":"Rockdale",
    "sg:classifiers":[
        {
            "category":"Building & Trades",
            "subcategory":"Construction",
            "type":"Services"
        }
    ],
    "sg:phone":"+1 815 729 1560",
    "sg:postcode":"60436",
    "sg:province":"IL",
    "sg:tags":[
        "general",
        "contractor"
    ],
    "wof:name":"Modern Builders Industrial",
    "wof:placetype":"venue"
},
  "geometry": {"coordinates":[-88.123914,41.50481],"type":"Point"}
}