{
  "type": "Feature",
  "properties": {
    "addr:full":"200 N 36th St Quincy IL 62301",
    "addr:housenumber":"200",
    "addr:postcode":"62301",
    "addr:street":"N 36Th St",
    "iso:country":"US",
    "sg:address":"200 N 36th St",
    "sg:city":"Quincy",
    "sg:classifiers":[
        {
            "category":"Restaurant",
            "type":"Food & Drink"
        }
    ],
    "sg:menulink":"http://www.allmenus.com/il/quincy/109355-village-inn/menu/",
    "sg:phone":"+1 217 228 1817",
    "sg:postcode":"62301",
    "sg:province":"IL",
    "sg:tags":[
        "new",
        "american"
    ],
    "wof:name":"Village Inn",
    "wof:placetype":"venue"
},
  "geometry": {"coordinates":[-91.358133,39.932801],"type":"Point"}
}