{
  "type": "Feature",
  "properties": {
    "addr:full":"815 W Country Dr Bartlett IL 60103",
    "addr:housenumber":"815",
    "addr:postcode":"60103",
    "addr:street":"W Country Dr",
    "iso:country":"US",
    "sg:address":"815 W Country Dr",
    "sg:city":"Bartlett",
    "sg:classifiers":[
        {
            "category":"Transit Center",
            "subcategory":"Freight",
            "type":"Transportation"
        },
        {
            "category":"Freight",
            "type":"Transportation"
        }
    ],
    "sg:phone":"+1 630 372 1268",
    "sg:postcode":"60103",
    "sg:province":"IL",
    "sg:tags":[
        "forwarding",
        "trucking-motor",
        "trucking"
    ],
    "wof:name":"Transport Resource Logistics",
    "wof:placetype":"venue"
},
  "geometry": {"coordinates":[-88.181726,41.978866],"type":"Point"}
}