{
  "type": "Feature",
  "properties": {
    "iso:country":"US",
    "sg:address":"928 37th Ave",
    "sg:city":"Rock Island",
    "sg:classifiers":[
        {
            "category":"Personal",
            "subcategory":"Beauty Salon",
            "type":"Services"
        }
    ],
    "sg:phone":"+1 309 786 5591",
    "sg:postcode":"61201",
    "sg:province":"IL",
    "sg:tags":[
        "shop"
    ],
    "wof:name":"Hair Art & Design",
    "wof:placetype":"venue"
},
  "geometry": {"coordinates":[-90.589557,41.474277],"type":"Point"}
}