{
  "type": "Feature",
  "properties": {
    "iso:country":"US",
    "sg:address":"1307 N Lewis Ave",
    "sg:city":"Waukegan",
    "sg:classifiers":[
        {
            "category":"Shopping",
            "subcategory":"Beauty & Cosmetics",
            "type":"Retail Goods"
        }
    ],
    "sg:phone":"+1   ",
    "sg:postcode":"60085",
    "sg:province":"IL",
    "sg:tags":[
        "merchandise"
    ],
    "wof:name":"Joy Beauty Supply",
    "wof:placetype":"venue"
},
  "geometry": {"coordinates":[-87.855368,42.381875],"type":"Point"}
}