{
  "type": "Feature",
  "properties": {
    "addr:full":"9956 S Michigan Avenue Chicago IL 60628",
    "addr:housenumber":"9956",
    "addr:postcode":"60628",
    "addr:street":"S Michigan Avenue",
    "iso:country":"US",
    "sg:address":"9956 S Michigan Avenue",
    "sg:city":"Chicago",
    "sg:classifiers":[
        {
            "category":"Retail",
            "subcategory":"Auto Repair",
            "type":"Services"
        }
    ],
    "sg:phone":"+1 773 785 9771",
    "sg:postcode":"60628",
    "sg:province":"IL",
    "wof:name":"A-1 Radiator Service",
    "wof:placetype":"venue"
},
  "geometry": {"coordinates":[-87.62027399999999,41.712786],"type":"Point"}
}