{
  "type": "Feature",
  "properties": {
    "addr:full":"320 S Wells St Chicago IL 60606",
    "addr:housenumber":"320",
    "addr:postcode":"60606",
    "addr:street":"S Wells St",
    "iso:country":"US",
    "sg:address":"320 S Wells St",
    "sg:city":"Chicago",
    "sg:classifiers":[
        {
            "category":"Building & Trades",
            "subcategory":"Construction",
            "type":"Services"
        }
    ],
    "sg:phone":"+1 312 836 1706",
    "sg:postcode":"60606",
    "sg:province":"IL",
    "sg:tags":[
        "painting",
        "contractor"
    ],
    "wof:name":"Triangle Decorating Co.",
    "wof:placetype":"venue"
},
  "geometry": {"coordinates":[-87.633728,41.877319],"type":"Point"}
}