{
  "type": "Feature",
  "properties": {
    "iso:country":"US",
    "sg:address":"1224 North Ave",
    "sg:city":"Waukegan",
    "sg:phone":"+1 866 984 4921",
    "sg:postcode":"60085",
    "sg:province":"IL",
    "sg:website":"http://www.koscoflags.com",
    "wof:name":"Kosco Flags & Flagpoles LLC",
    "wof:placetype":"venue"
},
  "geometry": {"coordinates":[-87.835876,42.376766],"type":"Point"}
}