{
  "type": "Feature",
  "properties": {
    "addr:full":"11015 US Hwy 12 Richmond IL 60071",
    "addr:housenumber":"11015",
    "addr:postcode":"60071",
    "addr:street":"Us Hwy 12",
    "iso:country":"US",
    "sg:address":"11015 US Hwy 12",
    "sg:city":"Richmond",
    "sg:classifiers":[
        {
            "category":"Restaurant",
            "type":"Food & Drink"
        }
    ],
    "sg:phone":"+1   ",
    "sg:postcode":"60071",
    "sg:province":"IL",
    "sg:tags":[
        "eating"
    ],
    "wof:name":"Richmond Dog & Suds",
    "wof:placetype":"venue"
},
  "geometry": {"coordinates":[-88.306166,42.485645],"type":"Point"}
}