{
  "type": "Feature",
  "properties": {
    "addr:full":"615 W Liberty St Wauconda IL 60084",
    "addr:housenumber":"615",
    "addr:postcode":"60084",
    "addr:street":"W Liberty St",
    "iso:country":"US",
    "sg:address":"615 W Liberty St",
    "sg:city":"Wauconda",
    "sg:classifiers":[
        {
            "category":"Autos & Motor Vehicles",
            "subcategory":"Auto Supplies",
            "type":"Retail Goods"
        }
    ],
    "sg:phone":"+1 847 705 9100",
    "sg:postcode":"60084",
    "sg:province":"IL",
    "sg:tags":[
        "automobile",
        "stereo",
        "radio"
    ],
    "wof:name":"Excel Audio Inc",
    "wof:placetype":"venue"
},
  "geometry": {"coordinates":[-88.154415,42.258089],"type":"Point"}
}