{
  "type": "Feature",
  "properties": {
    "addr:full":"1707 Pearl Ct Crystal Lake IL 60014",
    "addr:housenumber":"1707",
    "addr:postcode":"60014",
    "addr:street":"Pearl Ct",
    "iso:country":"US",
    "sg:address":"1707 Pearl Ct",
    "sg:city":"Crystal Lake",
    "sg:classifiers":[
        {
            "category":"Building & Trades",
            "subcategory":"Construction",
            "type":"Services"
        }
    ],
    "sg:phone":"+1 815 444 0484",
    "sg:postcode":"60014",
    "sg:province":"IL",
    "sg:tags":[
        "house"
    ],
    "wof:name":"Homestead Home Improvement Co",
    "wof:placetype":"venue"
},
  "geometry": {"coordinates":[-88.343568,42.194329],"type":"Point"}
}