{
  "type": "Feature",
  "properties": {
    "iso:country":"US",
    "sg:address":"1449 N Quentin Rd",
    "sg:city":"Palatine",
    "sg:classifiers":[
        {
            "category":"Health Services",
            "subcategory":"Health Practitioner",
            "type":"Services"
        }
    ],
    "sg:phone":"+1 847 358 5840",
    "sg:postcode":"60067",
    "sg:province":"IL",
    "sg:tags":[
        "hypnotherapy",
        "hypnotist"
    ],
    "wof:name":"Holistic Approach to Life",
    "wof:placetype":"venue"
},
  "geometry": {"coordinates":[-88.062241,42.083801],"type":"Point"}
}