{
  "type": "Feature",
  "properties": {
    "iso:country":"US",
    "sg:address":"528 Spring Rd",
    "sg:city":"Elmhurst",
    "sg:classifiers":[
        {
            "category":"Retail",
            "subcategory":"Veterinary Services",
            "type":"Services"
        }
    ],
    "sg:phone":"+1 630 833 7387",
    "sg:postcode":"60126",
    "sg:province":"IL",
    "sg:tags":[
        "veterinarian"
    ],
    "wof:name":"De Vries Animal Hospital",
    "wof:placetype":"venue"
},
  "geometry": {"coordinates":[-87.949655,41.885147],"type":"Point"}
}