{
  "type": "Feature",
  "properties": {
    "iso:country":"US",
    "sg:address":"5422 N River Rd",
    "sg:city":"Chicago",
    "sg:classifiers":[
        {
            "category":"Retail",
            "subcategory":"Auto Rental",
            "type":"Services"
        }
    ],
    "sg:phone":"+1 312 612 1941",
    "sg:postcode":"60656",
    "sg:province":"IL",
    "sg:tags":[
        "limousine"
    ],
    "wof:name":"Citi Limousine Inc",
    "wof:placetype":"venue"
},
  "geometry": {"coordinates":[-87.83704,41.959345],"type":"Point"}
}