{
  "type": "Feature",
  "properties": {
    "iso:country":"US",
    "sg:address":"770 Wingate Rd",
    "sg:city":"Glen Ellyn",
    "sg:classifiers":[
        {
            "category":"Home & Garden",
            "subcategory":"Hardware",
            "type":"Retail Goods"
        }
    ],
    "sg:phone":"+1 630 790 2273",
    "sg:postcode":"60137",
    "sg:province":"IL",
    "wof:name":"Aubuchon & Assoc",
    "wof:placetype":"venue"
},
  "geometry": {"coordinates":[-88.054672,41.867585],"type":"Point"}
}