{
  "type": "Feature",
  "properties": {
    "iso:country":"US",
    "sg:address":"4114 Southwest Hwy",
    "sg:city":"Hometown",
    "sg:classifiers":[
        {
            "category":"Health Services",
            "subcategory":"Health Practitioner",
            "type":"Services"
        }
    ],
    "sg:phone":"+1 708 424 4047",
    "sg:postcode":"60456",
    "sg:province":"IL",
    "sg:tags":[
        "therapy",
        "physical"
    ],
    "wof:name":"Athletex Physical Therapy",
    "wof:placetype":"venue"
},
  "geometry": {"coordinates":[-87.725098,41.7328],"type":"Point"}
}