{
  "type": "Feature",
  "properties": {
    "iso:country":"US",
    "sg:address":"272 Danada Sq W",
    "sg:city":"Wheaton",
    "sg:classifiers":[
        {
            "category":"Retail",
            "subcategory":"Laundry & Dry Cleaning",
            "type":"Services"
        }
    ],
    "sg:phone":"+1 630 682 0707",
    "sg:postcode":"60187",
    "sg:province":"IL",
    "sg:tags":[
        "drycleaning",
        "plant"
    ],
    "wof:name":"Danada Cleaners",
    "wof:placetype":"venue"
},
  "geometry": {"coordinates":[-88.110031,41.829834],"type":"Point"}
}