{
  "type": "Feature",
  "properties": {
    "iso:country":"US",
    "sg:address":"2590 W Schaumburg Rd",
    "sg:city":"Schaumburg",
    "sg:classifiers":[
        {
            "category":"Restaurant",
            "type":"Food & Drink"
        }
    ],
    "sg:phone":"+1   ",
    "sg:postcode":"60194",
    "sg:province":"IL",
    "sg:tags":[
        "eating"
    ],
    "wof:name":"Starbucks",
    "wof:placetype":"venue"
},
  "geometry": {"coordinates":[-88.153391,42.029303],"type":"Point"}
}