{
  "type": "Feature",
  "properties": {
    "iso:country":"US",
    "sg:address":"705 W Main St",
    "sg:city":"Carbondale",
    "sg:classifiers":[
        {
            "category":"Insurance",
            "subcategory":"Insurance Agent",
            "type":"Services"
        },
        {
            "category":"Insurance",
            "subcategory":"Hazard Insurance",
            "type":"Services"
        },
        {
            "category":"Insurance",
            "subcategory":"Title Insurance",
            "type":"Services"
        },
        {
            "category":"Insurance",
            "subcategory":"Life Insurance",
            "type":"Services"
        }
    ],
    "sg:phone":"+1 618 457 6625",
    "sg:postcode":"62901",
    "sg:province":"IL",
    "sg:tags":[
        "business",
        "auto",
        "commercial",
        "homeowner",
        "motorcycle",
        "renter"
    ],
    "wof:name":"Allstate Insurance Company - James Renshaw",
    "wof:placetype":"venue"
},
  "geometry": {"coordinates":[-89.224694,37.726586],"type":"Point"}
}