{
  "type": "Feature",
  "properties": {
    "addr:full":"5929 N Merrimac Ave Chicago IL 60646",
    "addr:housenumber":"5929",
    "addr:postcode":"60646",
    "addr:street":"N Merrimac Ave",
    "iso:country":"US",
    "sg:address":"5929 N Merrimac Ave",
    "sg:city":"Chicago",
    "sg:classifiers":[
        {
            "category":"Building & Trades",
            "subcategory":"Construction",
            "type":"Services"
        }
    ],
    "sg:phone":"+1 773 774 7544",
    "sg:postcode":"60646",
    "sg:province":"IL",
    "sg:tags":[
        "painting",
        "contractor"
    ],
    "wof:name":"Gus Arapitoglou",
    "wof:placetype":"venue"
},
  "geometry": {"coordinates":[-87.783979,41.988932],"type":"Point"}
}