{
  "type": "Feature",
  "properties": {
    "addr:full":"566 Ryan Way Crystal Lake IL 60012",
    "addr:housenumber":"566",
    "addr:postcode":"60012",
    "addr:street":"Ryan Way",
    "iso:country":"US",
    "sg:address":"566 Ryan Way",
    "sg:city":"Crystal Lake",
    "sg:classifiers":[
        {
            "category":"Professional",
            "subcategory":"Business Services",
            "type":"Services"
        }
    ],
    "sg:phone":"+1 815 459 6455",
    "sg:postcode":"60012",
    "sg:province":"IL",
    "wof:name":"North Shore Interiors Inc",
    "wof:placetype":"venue"
},
  "geometry": {"coordinates":[-88.33041,42.257254],"type":"Point"}
}