{
  "type": "Feature",
  "properties": {
    "iso:country":"US",
    "sg:address":"190 S La Salle St",
    "sg:city":"Chicago",
    "sg:classifiers":[
        {
            "category":"Professional",
            "subcategory":"Lawyer & Legal Services",
            "type":"Services"
        }
    ],
    "sg:phone":"+1 312 357 0370",
    "sg:postcode":"60603",
    "sg:province":"IL",
    "sg:website":"www.cmht.com",
    "wof:name":"Cohen Milstein Hausfeld & Toll",
    "wof:placetype":"venue"
},
  "geometry": {"coordinates":[-87.632457,41.879575],"type":"Point"}
}