{
  "type": "Feature",
  "properties": {
    "iso:country":"US",
    "sg:address":"1869 N Milwaukee Ave",
    "sg:city":"Chicago",
    "sg:classifiers":[
        {
            "category":"Building & Trades",
            "subcategory":"Construction",
            "type":"Services"
        }
    ],
    "sg:phone":"+1 773 342 4314",
    "sg:postcode":"60647",
    "sg:province":"IL",
    "sg:tags":[
        "system",
        "specialty",
        "heating",
        "contractor",
        "air conditioning"
    ],
    "wof:name":"Aa Mechanical Heating & Air Co",
    "wof:placetype":"venue"
},
  "geometry": {"coordinates":[-87.68538599999999,41.91551],"type":"Point"}
}