{
  "type": "Feature",
  "properties": {
    "iso:country":"US",
    "sg:address":"6000 N 2nd St",
    "sg:city":"Loves Park",
    "sg:classifiers":[
        {
            "category":"Restaurant",
            "type":"Food & Drink"
        }
    ],
    "sg:menulink":"http://www.allmenus.com/il/rockford/212448-mcdonalds/menu/",
    "sg:postcode":"61111",
    "sg:province":"IL",
    "sg:tags":[
        "burger",
        "american"
    ],
    "wof:name":"McDonald's",
    "wof:placetype":"venue"
},
  "geometry": {"coordinates":[-89.05795999999999,42.317206],"type":"Point"}
}