{
  "type": "Feature",
  "properties": {
    "addr:full":"5225 Old Orchard Rd Skokie IL 60077",
    "addr:housenumber":"5225",
    "addr:postcode":"60077",
    "addr:street":"Old Orchard Rd",
    "iso:country":"US",
    "sg:address":"5225 Old Orchard Rd",
    "sg:city":"Skokie",
    "sg:classifiers":[
        {
            "category":"Manufacturing",
            "subcategory":"Tools & Machinery",
            "type":"Manufacturing & Wholesale Goods"
        }
    ],
    "sg:phone":"+1 847 965 4455",
    "sg:postcode":"60077",
    "sg:province":"IL",
    "sg:tags":[
        "mfg",
        "ophthalmic"
    ],
    "wof:name":"Scott Dean B Certif Ocularist",
    "wof:placetype":"venue"
},
  "geometry": {"coordinates":[-87.756151,42.062442],"type":"Point"}
}