{
  "type": "Feature",
  "properties": {
    "addr:full":"2101 S Carpenter St Chicago IL 60608",
    "addr:housenumber":"2101",
    "addr:postcode":"60608",
    "addr:street":"S Carpenter St",
    "iso:country":"US",
    "sg:address":"2101 S Carpenter St",
    "sg:city":"Chicago",
    "sg:classifiers":[
        {
            "category":"Professional",
            "subcategory":"Business Services",
            "type":"Services"
        }
    ],
    "sg:phone":"+1 312 421 7000",
    "sg:postcode":"60608",
    "sg:province":"IL",
    "sg:tags":[
        "consultant",
        "coach"
    ],
    "wof:name":"Chicago MidWest Vending Systems Inc",
    "wof:placetype":"venue"
},
  "geometry": {"coordinates":[-87.65306099999999,41.853851],"type":"Point"}
}