{
  "type": "Feature",
  "properties": {
    "iso:country":"US",
    "sg:address":"303 S Main St",
    "sg:city":"Wheaton",
    "sg:classifiers":[
        {
            "category":"Restaurant",
            "type":"Food & Drink"
        }
    ],
    "sg:phone":"+1 630 681 0777",
    "sg:postcode":"60187",
    "sg:province":"IL",
    "sg:tags":[
        "pizza"
    ],
    "sg:website":"www.nancyspizza.com/",
    "wof:name":"Nancy's Pizzeria",
    "wof:placetype":"venue"
},
  "geometry": {"coordinates":[-88.106499,41.8629],"type":"Point"}
}