{
  "type": "Feature",
  "properties": {
    "addr:full":"907 North Path Wheaton IL 60187",
    "addr:housenumber":"907",
    "addr:postcode":"60187",
    "addr:street":"North Path",
    "iso:country":"US",
    "sg:address":"907 North Path",
    "sg:city":"Wheaton",
    "sg:classifiers":[
        {
            "category":"Banks & Credit Unions",
            "subcategory":"Financial Services",
            "type":"Services"
        }
    ],
    "sg:phone":"+1 312 628 6800",
    "sg:postcode":"60187",
    "sg:province":"IL",
    "sg:tags":[
        "broker",
        "mortgage"
    ],
    "wof:name":"Crane Mortgage Inc",
    "wof:placetype":"venue"
},
  "geometry": {"coordinates":[-88.09286899999999,41.872427],"type":"Point"}
}