{
  "type": "Feature",
  "properties": {
    "iso:country":"US",
    "sg:address":"2843 W 63rd St",
    "sg:city":"Chicago",
    "sg:classifiers":[
        {
            "category":"Restaurant",
            "type":"Food & Drink"
        }
    ],
    "sg:phone":"+1 773 436 2100",
    "sg:postcode":"60629",
    "sg:province":"IL",
    "sg:tags":[
        "pizza",
        "italian"
    ],
    "wof:name":"Papa T's Pizza and Ribs",
    "wof:placetype":"venue"
},
  "geometry": {"coordinates":[-87.695297,41.7789],"type":"Point"}
}