{
  "type": "Feature",
  "properties": {
    "addr:full":"100 Broadview Village Sq Broadview IL 60155",
    "addr:housenumber":"100",
    "addr:postcode":"60155",
    "addr:street":"Broadview Village Sq",
    "iso:country":"US",
    "sg:address":"100 Broadview Village Sq",
    "sg:city":"Broadview",
    "sg:classifiers":[
        {
            "category":"Insurance",
            "subcategory":"Health Insurance",
            "type":"Services"
        }
    ],
    "sg:phone":"+1 708 343 5053",
    "sg:postcode":"60155",
    "sg:province":"IL",
    "sg:tags":[
        "market"
    ],
    "sg:website":"www.gnc.com",
    "wof:name":"General Nutrition Center",
    "wof:placetype":"venue"
},
  "geometry": {"coordinates":[-87.8526,41.852901],"type":"Point"}
}