{
  "type": "Feature",
  "properties": {
    "iso:country":"US",
    "sg:address":"119 W Railroad St",
    "sg:city":"Earlville",
    "sg:classifiers":[
        {
            "category":"Restaurant",
            "type":"Food & Drink"
        }
    ],
    "sg:phone":"+1 815 246 6051",
    "sg:postcode":"60518",
    "sg:province":"IL",
    "wof:name":"Earlville Restaurant",
    "wof:placetype":"venue"
},
  "geometry": {"coordinates":[-88.92195599999999,41.590262],"type":"Point"}
}