{
  "type": "Feature",
  "properties": {
    "iso:country":"US",
    "sg:address":"14243 108th Ave",
    "sg:city":"Orland Park",
    "sg:classifiers":[
        {
            "category":"Building & Trades",
            "subcategory":"Construction",
            "type":"Services"
        }
    ],
    "sg:phone":"+1 708 403 3577",
    "sg:postcode":"60467",
    "sg:province":"IL",
    "sg:tags":[
        "new",
        "remodeling",
        "home"
    ],
    "wof:name":"Henry J Coyle and Company Inc",
    "wof:placetype":"venue"
},
  "geometry": {"coordinates":[-87.88275400000001,41.632743],"type":"Point"}
}