{
  "type": "Feature",
  "properties": {
    "addr:full":"479 N Harlem Ave Oak Park IL 60301",
    "addr:housenumber":"479",
    "addr:postcode":"60301",
    "addr:street":"N Harlem Ave",
    "iso:country":"US",
    "sg:address":"479 N Harlem Ave",
    "sg:city":"Oak Park",
    "sg:classifiers":[
        {
            "category":"Personal",
            "type":"Services"
        },
        {
            "category":"Education",
            "subcategory":"Vocational School",
            "type":"Public Place"
        }
    ],
    "sg:phone":"+1 708 689 9028",
    "sg:postcode":"60301",
    "sg:province":"IL",
    "sg:tags":[
        "chef",
        "cooking"
    ],
    "wof:name":"Tommaso's Private Cooking Class & Personal Chef",
    "wof:placetype":"venue"
},
  "geometry": {"coordinates":[-87.805009,41.888345],"type":"Point"}
}