{
  "type": "Feature",
  "properties": {
    "iso:country":"US",
    "sg:address":"819 E 142nd St",
    "sg:city":"Dolton",
    "sg:classifiers":[
        {
            "category":"Restaurant",
            "type":"Food & Drink"
        }
    ],
    "sg:phone":"+1 708 201 9320",
    "sg:postcode":"60419",
    "sg:province":"IL",
    "sg:tags":[
        "american"
    ],
    "wof:name":"Samichez",
    "wof:placetype":"venue"
},
  "geometry": {"coordinates":[-87.59739,41.63715],"type":"Point"}
}