{
  "type": "Feature",
  "properties": {
    "addr:full":"112 W Main St Salem IL 62881",
    "addr:housenumber":"112",
    "addr:postcode":"62881",
    "addr:street":"W Main St",
    "iso:country":"US",
    "sg:address":"112 W Main St",
    "sg:city":"Salem",
    "sg:classifiers":[
        {
            "category":"Professional",
            "subcategory":"Accounting & Tax Preparation",
            "type":"Services"
        }
    ],
    "sg:phone":"+1 618 548 6854",
    "sg:postcode":"62881",
    "sg:province":"IL",
    "wof:name":"Shetley Investments Inc",
    "wof:placetype":"venue"
},
  "geometry": {"coordinates":[-88.945763,38.627153],"type":"Point"}
}