{
  "type": "Feature",
  "properties": {
    "iso:country":"US",
    "sg:address":"217 W Clay St",
    "sg:city":"Collinsville",
    "sg:classifiers":[
        {
            "category":"Health Services",
            "subcategory":"Doctor",
            "type":"Services"
        }
    ],
    "sg:phone":"+1 618 344 6480",
    "sg:postcode":"62234",
    "sg:province":"IL",
    "sg:tags":[
        "surgeon",
        "oral"
    ],
    "wof:name":"McAtee John F DDS",
    "wof:placetype":"venue"
},
  "geometry": {"coordinates":[-89.9888,38.6702],"type":"Point"}
}