{
  "type": "Feature",
  "properties": {
    "addr:full":"130 Gates St Elburn IL 60119",
    "addr:housenumber":"130",
    "addr:postcode":"60119",
    "addr:street":"Gates St",
    "iso:country":"US",
    "sg:address":"130 Gates St",
    "sg:city":"Elburn",
    "sg:classifiers":[
        {
            "category":"Retail",
            "subcategory":"Driving School",
            "type":"Services"
        }
    ],
    "sg:phone":"+1 630 365 5050",
    "sg:postcode":"60119",
    "sg:province":"IL",
    "sg:tags":[
        "proficiency",
        "test",
        "instruction"
    ],
    "sg:website":"http://www.foxvalleydriving.com",
    "wof:name":"Fox Valley Driving LLC",
    "wof:placetype":"venue"
},
  "geometry": {"coordinates":[-88.47362800000001,41.892569],"type":"Point"}
}