{
  "type": "Feature",
  "properties": {
    "iso:country":"US",
    "sg:address":"980 S Bartlett Rd",
    "sg:city":"Bartlett",
    "sg:classifiers":[
        {
            "category":"Food & Beverages",
            "subcategory":"Liquor & Beverages",
            "type":"Retail Goods"
        },
        {
            "category":"Food & Beverages",
            "subcategory":"Groceries & Convenience Stores",
            "type":"Retail Goods"
        }
    ],
    "sg:phone":"+1 630 830 0022",
    "sg:postcode":"60103",
    "sg:province":"IL",
    "sg:tags":[
        "beer",
        "spirit",
        "wine"
    ],
    "wof:name":"Mr Quik-Ezz",
    "wof:placetype":"venue"
},
  "geometry": {"coordinates":[-88.183998,41.968201],"type":"Point"}
}