{
  "type": "Feature",
  "properties": {
    "iso:country":"US",
    "sg:address":"203 Goethe Ave",
    "sg:city":"Collinsville",
    "sg:classifiers":[
        {
            "category":"Banks & Credit Unions",
            "subcategory":"Financial Services",
            "type":"Services"
        }
    ],
    "sg:phone":"+1 618 343 2900",
    "sg:postcode":"62234",
    "sg:province":"IL",
    "sg:tags":[
        "broker",
        "mortgage"
    ],
    "wof:name":"First Co Mortgage",
    "wof:placetype":"venue"
},
  "geometry": {"coordinates":[-89.990601,38.6698],"type":"Point"}
}