{
  "type": "Feature",
  "properties": {
    "addr:full":"12705 N Winslow Rd Durand IL 61024",
    "addr:housenumber":"12705",
    "addr:postcode":"61024",
    "addr:street":"N Winslow Rd",
    "iso:country":"US",
    "sg:address":"12705 N Winslow Rd",
    "sg:city":"Durand",
    "sg:classifiers":[
        {
            "category":"Building & Trades",
            "subcategory":"Plumbing",
            "type":"Services"
        }
    ],
    "sg:phone":"+1 815 629 2375",
    "sg:postcode":"61024",
    "sg:province":"IL",
    "sg:tags":[
        "contractor"
    ],
    "wof:name":"Atlas Plumbing and Heating",
    "wof:placetype":"venue"
},
  "geometry": {"coordinates":[-89.243028,42.437575],"type":"Point"}
}