{
  "type": "Feature",
  "properties": {
    "iso:country":"US",
    "sg:address":"202 Orchard St",
    "sg:city":"Wayne City",
    "sg:classifiers":[
        {
            "category":"Professional",
            "subcategory":"Business Services",
            "type":"Services"
        }
    ],
    "sg:phone":"+1 618 895 3131",
    "sg:postcode":"62895",
    "sg:province":"IL",
    "wof:name":"Illinois Official Grn Inspctn",
    "wof:placetype":"venue"
},
  "geometry": {"coordinates":[-88.589294,38.345533],"type":"Point"}
}