{
  "type": "Feature",
  "properties": {
    "iso:country":"US",
    "sg:address":"407 S Dearborn St",
    "sg:city":"Chicago",
    "sg:classifiers":[
        {
            "category":"Retail",
            "subcategory":"Laundry & Dry Cleaning",
            "type":"Services"
        }
    ],
    "sg:phone":"+1 312 427 5300",
    "sg:postcode":"60605",
    "sg:province":"IL",
    "wof:name":"Order US Cleaning Service",
    "wof:placetype":"venue"
},
  "geometry": {"coordinates":[-87.62930299999999,41.876801],"type":"Point"}
}