{
  "type": "Feature",
  "properties": {
    "addr:full":"3634 W Chicago Ave Chicago IL 60651",
    "addr:housenumber":"3634",
    "addr:postcode":"60651",
    "addr:street":"W Chicago Ave",
    "iso:country":"US",
    "sg:address":"3634 W Chicago Ave",
    "sg:city":"Chicago",
    "sg:classifiers":[
        {
            "category":"Food & Beverages",
            "subcategory":"Groceries & Convenience Stores",
            "type":"Retail Goods"
        }
    ],
    "sg:phone":"+1 773 486 4470",
    "sg:postcode":"60651",
    "sg:province":"IL",
    "wof:name":"Penny Pantry",
    "wof:placetype":"venue"
},
  "geometry": {"coordinates":[-87.717613,41.895616],"type":"Point"}
}