{
  "type": "Feature",
  "properties": {
    "addr:full":"4185 Eastwood Pl Waukegan IL 60085",
    "addr:housenumber":"4185",
    "addr:postcode":"60085",
    "addr:street":"Eastwood Pl",
    "iso:country":"US",
    "sg:address":"4185 Eastwood Pl",
    "sg:city":"Waukegan",
    "sg:classifiers":[
        {
            "category":"Shopping",
            "type":"Retail Goods"
        }
    ],
    "sg:phone":"+1   ",
    "sg:postcode":"60085",
    "sg:province":"IL",
    "sg:tags":[
        "merchandise"
    ],
    "wof:name":"Christmas Tree Express",
    "wof:placetype":"venue"
},
  "geometry": {"coordinates":[-87.905805,42.348077],"type":"Point"}
}