{
  "type": "Feature",
  "properties": {
    "iso:country":"US",
    "sg:address":"210 Oak Grove Ave",
    "sg:city":"South Beloit",
    "sg:classifiers":[
        {
            "category":"Sports & Exercise",
            "subcategory":"Bowling",
            "type":"Entertainment"
        }
    ],
    "sg:phone":"+1   ",
    "sg:postcode":"61080",
    "sg:province":"WI",
    "sg:tags":[
        "lounge",
        "alley"
    ],
    "wof:name":"Chippers Pub",
    "wof:placetype":"venue"
},
  "geometry": {"coordinates":[-89.044516,42.488233],"type":"Point"}
}