{
  "type": "Feature",
  "properties": {
    "addr:full":"25130 Ellrie Ter Lake Zurich IL 60047",
    "addr:postcode":"25130;60047",
    "addr:street":"Ellrie Ter",
    "iso:country":"US",
    "sg:address":"25130 Ellrie Ter",
    "sg:city":"Lake Zurich",
    "sg:classifiers":[
        {
            "category":"Home & Garden",
            "subcategory":"Furniture",
            "type":"Retail Goods"
        }
    ],
    "sg:phone":"+1 847 540 6527",
    "sg:postcode":"60047",
    "sg:province":"IL",
    "sg:tags":[
        "cabinet"
    ],
    "wof:name":"Finer Woodworking Inc",
    "wof:placetype":"venue"
},
  "geometry": {"coordinates":[-88.103002,42.228015],"type":"Point"}
}