{
  "type": "Feature",
  "properties": {
    "iso:country":"US",
    "sg:address":"316 Wood Rd",
    "sg:city":"Rockford",
    "sg:classifiers":[
        {
            "category":"Social Services",
            "type":"Services"
        }
    ],
    "sg:phone":"+1 815 399 7203",
    "sg:postcode":"61107",
    "sg:province":"IL",
    "sg:tags":[
        "organization",
        "religious"
    ],
    "wof:name":"Rockford Youth For Christ",
    "wof:placetype":"venue"
},
  "geometry": {"coordinates":[-89.033974,42.271173],"type":"Point"}
}