{
  "type": "Feature",
  "properties": {
    "addr:full":"244 Tower Ln Elk Grove Village IL 60007",
    "addr:housenumber":"244",
    "addr:postcode":"60007",
    "addr:street":"Tower Ln",
    "iso:country":"US",
    "sg:address":"244 Tower Ln",
    "sg:city":"Elk Grove Village",
    "sg:classifiers":[
        {
            "category":"Home & Garden",
            "subcategory":"Carpets & Floor Coverings",
            "type":"Retail Goods"
        }
    ],
    "sg:phone":"+1   ",
    "sg:postcode":"60007",
    "sg:province":"IL",
    "wof:name":"G&K Floor Covering Specialist",
    "wof:placetype":"venue"
},
  "geometry": {"coordinates":[-87.990983,42.013716],"type":"Point"}
}