{
  "type": "Feature",
  "properties": {
    "iso:country":"US",
    "sg:address":"3420 W North Ave",
    "sg:city":"Chicago",
    "sg:classifiers":[
        {
            "category":"Food & Beverages",
            "subcategory":"Ethnic Foods",
            "type":"Retail Goods"
        }
    ],
    "sg:phone":"+1 773 489 1000",
    "sg:postcode":"60647",
    "sg:province":"IL",
    "wof:name":"Baba's Kitchen Fish and Chicken",
    "wof:placetype":"venue"
},
  "geometry": {"coordinates":[-87.712564,41.91037],"type":"Point"}
}