{
  "type": "Feature",
  "properties": {
    "addr:full":"200 N 8th St East Saint Louis IL 62201",
    "addr:housenumber":"200",
    "addr:postcode":"62201",
    "addr:street":"N 8Th St",
    "iso:country":"US",
    "sg:address":"200 N 8th St",
    "sg:city":"East Saint Louis",
    "sg:classifiers":[
        {
            "category":"Restaurant",
            "type":"Food & Drink"
        }
    ],
    "sg:phone":"+1 618 274 0300",
    "sg:postcode":"62201",
    "sg:province":"IL",
    "sg:tags":[
        "barbeque"
    ],
    "wof:name":"Sandy's Barbeque & More",
    "wof:placetype":"venue"
},
  "geometry": {"coordinates":[-90.1558,38.623501],"type":"Point"}
}