{
  "type": "Feature",
  "properties": {
    "iso:country":"US",
    "sg:address":"2045 Milwaukee Ave",
    "sg:city":"Deerfield",
    "sg:classifiers":[
        {
            "category":"Shopping",
            "subcategory":"Party Supplies",
            "type":"Retail Goods"
        },
        {
            "category":"Shopping",
            "subcategory":"Gifts & Souvenirs",
            "type":"Retail Goods"
        },
        {
            "category":"Personal",
            "type":"Services"
        }
    ],
    "sg:phone":"+1 847 537 2868",
    "sg:postcode":"60015",
    "sg:province":"IL",
    "sg:tags":[
        "delivery",
        "basket",
        "balloon",
        "balloons-retail",
        "decorator"
    ],
    "sg:website":"http://www.ediblearrangements.com",
    "wof:name":"Edible Arrangements",
    "wof:placetype":"venue"
},
  "geometry": {"coordinates":[-87.922957,42.171673],"type":"Point"}
}