{
  "type": "Feature",
  "properties": {
    "addr:full":"3033 Thayer St Evanston IL 60201",
    "addr:housenumber":"3033",
    "addr:postcode":"60201",
    "addr:street":"Thayer St",
    "iso:country":"US",
    "sg:address":"3033 Thayer St",
    "sg:city":"Evanston",
    "sg:classifiers":[
        {
            "category":"Communications",
            "type":"Services"
        }
    ],
    "sg:phone":"+1 847 864 4608",
    "sg:postcode":"60201",
    "sg:province":"IL",
    "wof:name":"Beatty Lindstrom Comms",
    "wof:placetype":"venue"
},
  "geometry": {"coordinates":[-87.719797,42.067512],"type":"Point"}
}