{
  "type": "Feature",
  "properties": {
    "addr:full":"6958 Meadow Song Trl Rockford IL 61109",
    "addr:housenumber":"6958",
    "addr:postcode":"61109",
    "addr:street":"Meadow Song Trl",
    "iso:country":"US",
    "sg:address":"6958 Meadow Song Trl",
    "sg:city":"Rockford",
    "sg:classifiers":[
        {
            "category":"Professional",
            "subcategory":"Business Services",
            "type":"Services"
        }
    ],
    "sg:phone":"+1 815 398 3558",
    "sg:postcode":"61109",
    "sg:province":"IL",
    "wof:name":"Nicks Underwater Salv & Video",
    "wof:placetype":"venue"
},
  "geometry": {"coordinates":[-89.066907,42.181371],"type":"Point"}
}