{
  "type": "Feature",
  "properties": {
    "addr:full":"131 North St Armington IL 61721",
    "addr:housenumber":"131",
    "addr:postcode":"61721",
    "addr:street":"North St",
    "iso:country":"US",
    "sg:address":"131 North St",
    "sg:city":"Armington",
    "sg:classifiers":[
        {
            "category":"Building & Trades",
            "subcategory":"Construction",
            "type":"Services"
        }
    ],
    "sg:phone":"+1 309 275 5319",
    "sg:postcode":"61721",
    "sg:province":"IL",
    "sg:tags":[
        "handyman"
    ],
    "wof:name":"Biehl's Repair",
    "wof:placetype":"venue"
},
  "geometry": {"coordinates":[-89.31922400000001,40.340931],"type":"Point"}
}