{
  "type": "Feature",
  "properties": {
    "addr:full":"4238 N. Broadway St Chicago IL 60613",
    "addr:housenumber":"4238",
    "addr:postcode":"60613",
    "addr:street":"N. Broadway St",
    "iso:country":"US",
    "sg:address":"4238 N. Broadway St",
    "sg:city":"Chicago",
    "sg:classifiers":[
        {
            "category":"Wholesale",
            "subcategory":"Stationery",
            "type":"Manufacturing & Wholesale Goods"
        }
    ],
    "sg:phone":"+1 773 549 7776",
    "sg:postcode":"60613",
    "sg:province":"IL",
    "sg:tags":[
        "card"
    ],
    "sg:website":"www.lightspeedchi.com",
    "wof:name":"Light Speed: Chicago",
    "wof:placetype":"venue"
},
  "geometry": {"coordinates":[-87.653847,41.959301],"type":"Point"}
}