{
  "type": "Feature",
  "properties": {
    "addr:full":"460 N Main St Glen Ellyn IL 60137",
    "addr:housenumber":"460",
    "addr:postcode":"60137",
    "addr:street":"N Main St",
    "iso:country":"US",
    "sg:address":"460 N Main St",
    "sg:city":"Glen Ellyn",
    "sg:classifiers":[
        {
            "category":"Shopping",
            "subcategory":"Discount & Variety Stores",
            "type":"Retail Goods"
        }
    ],
    "sg:phone":"+1 630 942 0458",
    "sg:postcode":"60137",
    "sg:province":"IL",
    "sg:tags":[
        "merchandise",
        "general"
    ],
    "wof:name":"Aspen Products Inc",
    "wof:placetype":"venue"
},
  "geometry": {"coordinates":[-88.066785,41.876251],"type":"Point"}
}