{
  "type": "Feature",
  "properties": {
    "iso:country":"US",
    "sg:address":"4810 Prince St",
    "sg:city":"Downers Grove",
    "sg:classifiers":[
        {
            "category":"Professional",
            "subcategory":"Business Services",
            "type":"Services"
        }
    ],
    "sg:phone":"+1 630 971 3142",
    "sg:postcode":"60515",
    "sg:province":"IL",
    "wof:name":"Beckwith James Intr Designers",
    "wof:placetype":"venue"
},
  "geometry": {"coordinates":[-88.01326,41.798625],"type":"Point"}
}