{
  "type": "Feature",
  "properties": {
    "addr:full":"1007 Geneva St Shorewood IL 60404",
    "addr:housenumber":"1007",
    "addr:postcode":"60404",
    "addr:street":"Geneva St",
    "iso:country":"US",
    "sg:address":"1007 Geneva St",
    "sg:city":"Shorewood",
    "sg:classifiers":[
        {
            "category":"Wholesale",
            "subcategory":"Groceries",
            "type":"Manufacturing & Wholesale Goods"
        }
    ],
    "sg:phone":"+1 815 729 4567",
    "sg:postcode":"60404",
    "sg:province":"IL",
    "sg:tags":[
        "food",
        "product"
    ],
    "wof:name":"Chicago Boxed Beef Distr",
    "wof:placetype":"venue"
},
  "geometry": {"coordinates":[-88.211917,41.515477],"type":"Point"}
}