{
  "type": "Feature",
  "properties": {
    "addr:full":"25 E Washington St Ste 1601 Chicago IL 60602",
    "addr:housenumber":"25",
    "addr:postcode":"60602",
    "addr:street":"E Washington St Ste 1601",
    "iso:country":"US",
    "sg:address":"25 E Washington St Ste 1601",
    "sg:city":"Chicago",
    "sg:classifiers":[
        {
            "category":"Health Services",
            "subcategory":"Doctor",
            "type":"Services"
        }
    ],
    "sg:phone":"+1 312 895 4431",
    "sg:postcode":"60602",
    "sg:province":"IL",
    "wof:name":"Gilmer William MD",
    "wof:placetype":"venue"
},
  "geometry": {"coordinates":[-87.62693,41.883083],"type":"Point"}
}