{
  "type": "Feature",
  "properties": {
    "addr:full":"9957 Roberts Rd Palos Hl Oak Lawn IL 60453",
    "addr:housenumber":"9957",
    "addr:postcode":"60453",
    "addr:street":"Roberts Rd",
    "iso:country":"US",
    "sg:address":"9957 Roberts Rd Palos Hl",
    "sg:city":"Oak Lawn",
    "sg:classifiers":[
        {
            "category":"Health Services",
            "subcategory":"Dentist",
            "type":"Services"
        }
    ],
    "sg:phone":"+1 708 599 8400",
    "sg:postcode":"60453",
    "sg:province":"IL",
    "wof:name":"7 To 7 Dental",
    "wof:placetype":"venue"
},
  "geometry": {"coordinates":[-87.817521,41.709779],"type":"Point"}
}