{
  "type": "Feature",
  "properties": {
    "iso:country":"US",
    "sg:address":"509 S Maryland Rd",
    "sg:city":"Polo",
    "sg:classifiers":[
        {
            "category":"Shopping",
            "type":"Retail Goods"
        }
    ],
    "sg:phone":"+1 815 946 2780",
    "sg:postcode":"61064",
    "sg:province":"IL",
    "sg:tags":[
        "merchandise"
    ],
    "wof:name":"The Upholstery Shoppe",
    "wof:placetype":"venue"
},
  "geometry": {"coordinates":[-89.548858,42.009588],"type":"Point"}
}