{
  "type": "Feature",
  "properties": {
    "iso:country":"US",
    "sg:address":"2221 Grand Ave",
    "sg:city":"Waukegan",
    "sg:classifiers":[
        {
            "category":"Insurance",
            "subcategory":"Insurance Agent",
            "type":"Services"
        }
    ],
    "sg:phone":"+1 847 672 6120",
    "sg:postcode":"60085",
    "sg:province":"IL",
    "wof:name":"Prudential Insurance Co",
    "wof:placetype":"venue"
},
  "geometry": {"coordinates":[-87.86206300000001,42.370241],"type":"Point"}
}