{
  "type": "Feature",
  "properties": {
    "iso:country":"US",
    "sg:address":"205 5th Ave",
    "sg:city":"Sherrard",
    "sg:classifiers":[
        {
            "category":"Education",
            "subcategory":"Library",
            "type":"Public Place"
        }
    ],
    "sg:phone":"+1 309 593 2178",
    "sg:postcode":"61281",
    "sg:province":"IL",
    "sg:website":"www.sherrardlibrary.org",
    "wof:name":"Sherrard Community Library",
    "wof:placetype":"venue"
},
  "geometry": {"coordinates":[-90.507263,41.320895],"type":"Point"}
}