{
  "type": "Feature",
  "properties": {
    "iso:country":"US",
    "sg:address":"2652 W Devon Avenue",
    "sg:city":"Chicago",
    "sg:classifiers":[
        {
            "category":"Shopping",
            "subcategory":"Jewelry",
            "type":"Retail Goods"
        }
    ],
    "sg:phone":"+1 773 465 5755",
    "sg:postcode":"60659",
    "sg:province":"IL",
    "wof:name":"Raj Jewels of London",
    "wof:placetype":"venue"
},
  "geometry": {"coordinates":[-87.69697600000001,41.997615],"type":"Point"}
}