{
  "type": "Feature",
  "properties": {
    "iso:country":"US",
    "sg:address":"687 Clark St",
    "sg:city":"Galesburg",
    "sg:classifiers":[
        {
            "category":"Shopping",
            "subcategory":"Bicycles & Sporting Goods",
            "type":"Retail Goods"
        },
        {
            "category":"Parking",
            "subcategory":"Bicycle",
            "type":"Transportation"
        }
    ],
    "sg:phone":"+1 309 343 4772",
    "sg:postcode":"61401",
    "sg:province":"IL",
    "sg:tags":[
        "shop",
        "rack",
        "security",
        "system",
        "bicycles-repair"
    ],
    "wof:name":"Dave's Cycling & Fitness Ctr",
    "wof:placetype":"venue"
},
  "geometry": {"coordinates":[-90.37764900000001,40.955742],"type":"Point"}
}