{
  "type": "Feature",
  "properties": {
    "addr:full":"3427 Ridge Rd Lansing IL 60438",
    "addr:housenumber":"3427",
    "addr:postcode":"60438",
    "addr:street":"Ridge Rd",
    "iso:country":"US",
    "sg:address":"3427 Ridge Rd",
    "sg:city":"Lansing",
    "sg:classifiers":[
        {
            "category":"Shopping",
            "subcategory":"Computers & Home Electronics",
            "type":"Retail Goods"
        },
        {
            "category":"Professional",
            "subcategory":"Computer Services",
            "type":"Services"
        }
    ],
    "sg:phone":"+1 708 585 2200",
    "sg:postcode":"60438",
    "sg:province":"IL",
    "sg:tags":[
        "repair"
    ],
    "sg:website":"www.connectedcomputer.com",
    "wof:name":"Connected Computer Services, Inc",
    "wof:placetype":"venue"
},
  "geometry": {"coordinates":[-87.533162,41.564245],"type":"Point"}
}