{
  "type": "Feature",
  "properties": {
    "iso:country":"US",
    "sg:address":"1901 Ottawa Ave",
    "sg:city":"Ottawa",
    "sg:classifiers":[
        {
            "category":"Restaurant",
            "type":"Food & Drink"
        }
    ],
    "sg:phone":"+1 815 431 9528",
    "sg:postcode":"61350",
    "sg:province":"IL",
    "sg:tags":[
        "eating"
    ],
    "wof:name":"Aric's Pub & Pizza",
    "wof:placetype":"venue"
},
  "geometry": {"coordinates":[-88.876516,41.334458],"type":"Point"}
}