{
  "type": "Feature",
  "properties": {
    "addr:full":"3101 W Irving Park Road Chicago IL 60618",
    "addr:housenumber":"3101",
    "addr:postcode":"60618",
    "addr:street":"W Irving Park Road",
    "iso:country":"US",
    "sg:address":"3101 W Irving Park Road",
    "sg:city":"Chicago",
    "sg:classifiers":[
        {
            "category":"Donuts",
            "subcategory":"None",
            "type":"Food & Drink"
        }
    ],
    "sg:phone":"+1 773 583 4048",
    "sg:postcode":"60618",
    "sg:province":"IL",
    "sg:website":"www.dunkindonuts.com",
    "wof:name":"Dunkin' Donuts",
    "wof:placetype":"venue"
},
  "geometry": {"coordinates":[-87.70419699999999,41.944759],"type":"Point"}
}