{
  "type": "Feature",
  "properties": {
    "iso:country":"US",
    "sg:address":"722 W Exchange St",
    "sg:city":"Crete",
    "sg:classifiers":[
        {
            "category":"Building & Trades",
            "subcategory":"Landscaping Services",
            "type":"Services"
        }
    ],
    "sg:phone":"+1 708 672 6802",
    "sg:postcode":"60417",
    "sg:province":"IL",
    "sg:tags":[
        "lawn",
        "maintenance",
        "grounds"
    ],
    "wof:name":"Slusser's Green Thumb Inc",
    "wof:placetype":"venue"
},
  "geometry": {"coordinates":[-87.641453,41.443781],"type":"Point"}
}