{
  "type": "Feature",
  "properties": {
    "iso:country":"US",
    "sg:address":"1435 30th St",
    "sg:city":"Rock Island",
    "sg:classifiers":[
        {
            "category":"Home & Garden",
            "subcategory":"Hardware",
            "type":"Retail Goods"
        }
    ],
    "sg:phone":"+1   ",
    "sg:postcode":"61201",
    "sg:province":"IL",
    "wof:name":"Handy True Value Store",
    "wof:placetype":"venue"
},
  "geometry": {"coordinates":[-90.55710999999999,41.497211],"type":"Point"}
}