{
  "type": "Feature",
  "properties": {
    "iso:country":"US",
    "sg:address":"11136 S Michigan Ave",
    "sg:city":"Chicago",
    "sg:classifiers":[
        {
            "category":"Food & Beverages",
            "subcategory":"Groceries & Convenience Stores",
            "type":"Retail Goods"
        }
    ],
    "sg:phone":"+1 773 660 9106",
    "sg:postcode":"60628",
    "sg:province":"IL",
    "wof:name":"Dollar King Food Inc",
    "wof:placetype":"venue"
},
  "geometry": {"coordinates":[-87.621101,41.691502],"type":"Point"}
}