{
  "type": "Feature",
  "properties": {
    "addr:full":"20958 S Canterbury St Joliet IL 60404",
    "addr:housenumber":"20958",
    "addr:postcode":"60404",
    "addr:street":"S Canterbury St",
    "iso:country":"US",
    "sg:address":"20958 S Canterbury St",
    "sg:city":"Joliet",
    "sg:classifiers":[
        {
            "category":"Building & Trades",
            "subcategory":"Construction",
            "type":"Services"
        }
    ],
    "sg:phone":"+1 815 725 7143",
    "sg:postcode":"60404",
    "sg:province":"IL",
    "sg:tags":[
        "home",
        "builder"
    ],
    "wof:name":"Homes By Milan",
    "wof:placetype":"venue"
},
  "geometry": {"coordinates":[-90.04298900000001,38.900147],"type":"Point"}
}