{
  "type": "Feature",
  "properties": {
    "iso:country":"US",
    "sg:address":"213 Burlington Ave",
    "sg:city":"Clarendon Hills",
    "sg:classifiers":[
        {
            "category":"Personal",
            "subcategory":"Beauty Salon",
            "type":"Services"
        }
    ],
    "sg:phone":"+1 630 920 8090",
    "sg:postcode":"60514",
    "sg:province":"IL",
    "sg:tags":[
        "shop"
    ],
    "wof:name":"Indifference",
    "wof:placetype":"venue"
},
  "geometry": {"coordinates":[-87.955735,41.797227],"type":"Point"}
}