{
  "type": "Feature",
  "properties": {
    "iso:country":"US",
    "sg:address":"900 W Sycamore St",
    "sg:city":"Carbondale",
    "sg:classifiers":[
        {
            "category":"Government",
            "subcategory":"Office",
            "type":"Public Place"
        }
    ],
    "sg:phone":"+1 618 549 5711",
    "sg:postcode":"62901",
    "sg:province":"IL",
    "sg:tags":[
        "federal",
        "security"
    ],
    "wof:name":"US Army National Guard Armory",
    "wof:placetype":"venue"
},
  "geometry": {"coordinates":[-89.22824799999999,37.730502],"type":"Point"}
}