{
  "type": "Feature",
  "properties": {
    "addr:full":"3044 W Fullerton Chicago IL 60647",
    "addr:housenumber":"3044",
    "addr:postcode":"60647",
    "addr:street":"W Fullerton",
    "iso:country":"US",
    "sg:address":"3044 W Fullerton",
    "sg:city":"Chicago",
    "sg:classifiers":[
        {
            "category":"Personal",
            "subcategory":"Beauty Salon",
            "type":"Services"
        }
    ],
    "sg:phone":"+1 773 277 7740",
    "sg:postcode":"60647",
    "sg:province":"IL",
    "sg:tags":[
        "hair"
    ],
    "wof:name":"Damaris Unisex",
    "wof:placetype":"venue"
},
  "geometry": {"coordinates":[-87.704149,41.924791],"type":"Point"}
}