{
  "type": "Feature",
  "properties": {
    "addr:full":"25338 Wren Rd Tower Lakes IL 60010",
    "addr:housenumber":"25338",
    "addr:postcode":"60010",
    "addr:street":"Wren Rd",
    "iso:country":"US",
    "sg:address":"25338 Wren Rd",
    "sg:city":"Tower Lakes",
    "sg:classifiers":[
        {
            "category":"Professional",
            "subcategory":"Computer Services",
            "type":"Services"
        }
    ],
    "sg:phone":"+1 847 487 9154",
    "sg:postcode":"60010",
    "sg:province":"IL",
    "sg:tags":[
        "consultant",
        "designer"
    ],
    "wof:name":"Albert Consulting Inc",
    "wof:placetype":"venue"
},
  "geometry": {"coordinates":[-88.163793,42.231754],"type":"Point"}
}