{
  "type": "Feature",
  "properties": {
    "iso:country":"US",
    "sg:address":"7155 S Lawndale Ave",
    "sg:city":"Chicago",
    "sg:classifiers":[
        {
            "category":"Manufacturing",
            "subcategory":"Musical Instruments",
            "type":"Manufacturing & Wholesale Goods"
        }
    ],
    "sg:phone":"+1 773 582 3437",
    "sg:postcode":"60629",
    "sg:province":"IL",
    "sg:tags":[
        "instruments-wholesale",
        "manufacturer"
    ],
    "wof:name":"Amplification Light Products",
    "wof:placetype":"venue"
},
  "geometry": {"coordinates":[-87.715006,41.763197],"type":"Point"}
}