{
  "type": "Feature",
  "properties": {
    "iso:country":"US",
    "sg:address":"711 W Grand Ave Commercial Space",
    "sg:city":"Chicago",
    "sg:classifiers":[
        {
            "category":"Sports & Exercise",
            "subcategory":"Gym",
            "type":"Entertainment"
        }
    ],
    "sg:phone":"+1 312 666 5107",
    "sg:postcode":"60654",
    "sg:province":"IL",
    "sg:website":"www.emeraldsmokemma.com",
    "wof:name":"Emerald Smoke MMA and Fitness",
    "wof:placetype":"venue"
},
  "geometry": {"coordinates":[-87.64663899999999,41.890986],"type":"Point"}
}