{
  "type": "Feature",
  "properties": {
    "iso:country":"US",
    "sg:address":"5761 W 118th St",
    "sg:city":"Alsip",
    "sg:classifiers":[
        {
            "category":"Wholesale",
            "subcategory":"Metals & Minerals",
            "type":"Manufacturing & Wholesale Goods"
        }
    ],
    "sg:phone":"+1 708 389 3380",
    "sg:postcode":"60803",
    "sg:province":"IL",
    "sg:tags":[
        "blast",
        "furnace",
        "center",
        "works"
    ],
    "wof:name":"New Process Steel LP",
    "wof:placetype":"venue"
},
  "geometry": {"coordinates":[-87.763099,41.677661],"type":"Point"}
}