{
  "type": "Feature",
  "properties": {
    "iso:country":"US",
    "sg:address":"155 W Central Rd",
    "sg:city":"Schaumburg",
    "sg:classifiers":[
        {
            "category":"Communications",
            "type":"Services"
        }
    ],
    "sg:phone":"+1 847 963 0941",
    "sg:postcode":"60195",
    "sg:province":"IL",
    "sg:website":"http://www.verascape.com",
    "wof:name":"Verascape, Inc.",
    "wof:placetype":"venue"
},
  "geometry": {"coordinates":[-88.08195499999999,42.06702],"type":"Point"}
}