{
  "type": "Feature",
  "properties": {
    "addr:full":"5828 S Archer Ave Chicago IL 60638",
    "addr:housenumber":"5828",
    "addr:postcode":"60638",
    "addr:street":"S Archer Ave",
    "iso:country":"US",
    "sg:address":"5828 S Archer Ave",
    "sg:city":"Chicago",
    "sg:classifiers":[
        {
            "category":"Professional",
            "subcategory":"Lawyer & Legal Services",
            "type":"Services"
        }
    ],
    "sg:phone":"+1 773 582 2300",
    "sg:postcode":"60638",
    "sg:province":"IL",
    "wof:name":"Hermanek Hubert E Jr & Assoc",
    "wof:placetype":"venue"
},
  "geometry": {"coordinates":[-87.760002,41.796101],"type":"Point"}
}