{
  "type": "Feature",
  "properties": {
    "addr:full":"307 N Michigan Ave Ste 308 Chicago IL 60601",
    "addr:housenumber":"307",
    "addr:postcode":"60601",
    "addr:street":"N Michigan Ave Ste 308",
    "iso:country":"US",
    "sg:address":"307 N Michigan Ave Ste 308",
    "sg:city":"Chicago",
    "sg:classifiers":[
        {
            "category":"Shopping",
            "subcategory":"Jewelry",
            "type":"Retail Goods"
        },
        {
            "category":"Shopping",
            "subcategory":"Antiques",
            "type":"Retail Goods"
        }
    ],
    "sg:phone":"+1 312 814 8510",
    "sg:postcode":"60601",
    "sg:province":"IL",
    "sg:website":"www.mirappraisal.com",
    "wof:name":"MIR Appraisal Services, Inc.",
    "wof:placetype":"venue"
},
  "geometry": {"coordinates":[-87.62441099999999,41.887105],"type":"Point"}
}