{
  "type": "Feature",
  "properties": {
    "addr:full":"2 S 5th Ave Maywood IL 60153",
    "addr:housenumber":"2",
    "addr:postcode":"60153",
    "addr:street":"S 5Th Ave",
    "iso:country":"US",
    "sg:address":"2 S 5th Ave",
    "sg:city":"Maywood",
    "sg:classifiers":[
        {
            "category":"Bars & Pubs",
            "type":"Food & Drink"
        }
    ],
    "sg:phone":"+1 708 450 1194",
    "sg:postcode":"60153",
    "sg:province":"IL",
    "sg:tags":[
        "drinking",
        "restaurant"
    ],
    "wof:name":"Maywood Express",
    "wof:placetype":"venue"
},
  "geometry": {"coordinates":[-87.839302,41.888199],"type":"Point"}
}