{
  "type": "Feature",
  "properties": {
    "iso:country":"US",
    "sg:address":"400 19th St",
    "sg:city":"Moline",
    "sg:classifiers":[
        {
            "category":"Insurance",
            "subcategory":"Health Insurance",
            "type":"Services"
        }
    ],
    "sg:phone":"+1 309 765 3177",
    "sg:postcode":"61265",
    "sg:province":"IL",
    "sg:tags":[
        "organization",
        "maintenance"
    ],
    "wof:name":"John Deere",
    "wof:placetype":"venue"
},
  "geometry": {"coordinates":[-90.511619,41.509062],"type":"Point"}
}