{
  "type": "Feature",
  "properties": {
    "addr:full":"14142 Cicero Ave Crestwood IL 60445",
    "addr:housenumber":"14142",
    "addr:postcode":"60445",
    "addr:street":"Cicero Ave",
    "iso:country":"US",
    "sg:address":"14142 Cicero Ave",
    "sg:city":"Crestwood",
    "sg:classifiers":[
        {
            "category":"Professional",
            "subcategory":"Employment Agencies",
            "type":"Services"
        }
    ],
    "sg:phone":"+1 708 385 6600",
    "sg:postcode":"60445",
    "sg:province":"IL",
    "wof:name":"Surestaff Inc",
    "wof:placetype":"venue"
},
  "geometry": {"coordinates":[-87.737893,41.63543],"type":"Point"}
}