{
  "type": "Feature",
  "properties": {
    "iso:country":"US",
    "sg:address":"290 N 2nd St",
    "sg:city":"Hamilton",
    "sg:classifiers":[
        {
            "category":"Government",
            "subcategory":"Office",
            "type":"Public Place"
        }
    ],
    "sg:phone":"+1 217 847 2946",
    "sg:postcode":"62341",
    "sg:province":"IL",
    "sg:tags":[
        "village"
    ],
    "wof:name":"Hamilton Sewage Treatment Plnt",
    "wof:placetype":"venue"
},
  "geometry": {"coordinates":[-91.353655,40.395558],"type":"Point"}
}