{
  "type": "Feature",
  "properties": {
    "addr:full":"7479 Walton St Rockford IL 61108",
    "addr:housenumber":"7479",
    "addr:postcode":"61108",
    "addr:street":"Walton St",
    "iso:country":"US",
    "sg:address":"7479 Walton St",
    "sg:city":"Rockford",
    "sg:classifiers":[
        {
            "category":"Wholesale",
            "subcategory":"Office Equipment",
            "type":"Manufacturing & Wholesale Goods"
        }
    ],
    "sg:phone":"+1 815 397 8145",
    "sg:postcode":"61108",
    "sg:province":"IL",
    "sg:tags":[
        "machine",
        "duplicating",
        "copying"
    ],
    "wof:name":"Ikon Office Solutions Inc",
    "wof:placetype":"venue"
},
  "geometry": {"coordinates":[-88.972753,42.268792],"type":"Point"}
}