{
  "type": "Feature",
  "properties": {
    "iso:country":"US",
    "sg:address":"510 E Ivy Ln",
    "sg:city":"Arlington Heights",
    "sg:classifiers":[
        {
            "category":"Health Services",
            "subcategory":"Health Practitioner",
            "type":"Services"
        }
    ],
    "sg:phone":"+1 847 253 9470",
    "sg:postcode":"60004",
    "sg:province":"IL",
    "wof:name":"Speech Connections PC",
    "wof:placetype":"venue"
},
  "geometry": {"coordinates":[-87.97878799999999,42.116373],"type":"Point"}
}