{
  "type": "Feature",
  "properties": {
    "iso:country":"US",
    "sg:address":"1645 Kimber Rd",
    "sg:city":"Dongola",
    "sg:classifiers":[
        {
            "category":"Farming",
            "subcategory":"Farm",
            "type":"Manufacturing & Wholesale Goods"
        }
    ],
    "sg:phone":"+1 618 827 3609",
    "sg:postcode":"62926",
    "sg:province":"IL",
    "wof:name":"Robert Kimber",
    "wof:placetype":"venue"
},
  "geometry": {"coordinates":[-89.208595,37.364447],"type":"Point"}
}