{
  "type": "Feature",
  "properties": {
    "addr:full":"3906 W 84th St Chicago IL 60652",
    "addr:housenumber":"3906",
    "addr:postcode":"60652",
    "addr:street":"W 84Th St",
    "iso:country":"US",
    "sg:address":"3906 W 84th St",
    "sg:city":"Chicago",
    "sg:classifiers":[
        {
            "category":"Banks & Credit Unions",
            "subcategory":"Financial Services",
            "type":"Services"
        }
    ],
    "sg:phone":"+1 773 767 6533",
    "sg:postcode":"60652",
    "sg:province":"IL",
    "sg:tags":[
        "trust",
        "management"
    ],
    "wof:name":"Sintic J John",
    "wof:placetype":"venue"
},
  "geometry": {"coordinates":[-87.720901,41.740435],"type":"Point"}
}