{
  "type": "Feature",
  "properties": {
    "iso:country":"US",
    "sg:address":"652 Deerfield Rd",
    "sg:city":"Deerfield",
    "sg:classifiers":[
        {
            "category":"Restaurant",
            "type":"Food & Drink"
        }
    ],
    "sg:phone":"+1 847 945 3380",
    "sg:postcode":"60015",
    "sg:province":"IL",
    "wof:name":"Golden Star",
    "wof:placetype":"venue"
},
  "geometry": {"coordinates":[-87.845162,42.167375],"type":"Point"}
}