{
  "type": "Feature",
  "properties": {
    "addr:full":"4124 N Oriole Ave Norridge IL 60706",
    "addr:housenumber":"4124",
    "addr:postcode":"60706",
    "addr:street":"N Oriole Ave",
    "iso:country":"US",
    "sg:address":"4124 N Oriole Ave",
    "sg:city":"Norridge",
    "sg:classifiers":[
        {
            "category":"Home & Garden",
            "subcategory":"Household Appliances",
            "type":"Retail Goods"
        },
        {
            "category":"Building & Trades",
            "subcategory":"Cleaning & Sanitation",
            "type":"Services"
        },
        {
            "category":"Building & Trades",
            "subcategory":"Construction",
            "type":"Services"
        }
    ],
    "sg:phone":"+1 708 456 4220",
    "sg:postcode":"60706",
    "sg:province":"IL",
    "sg:tags":[
        "site-clean-up",
        "floor",
        "waxing",
        "contractor",
        "window",
        "cleaning-industrial",
        "vacuum",
        "polishing",
        "janitorial"
    ],
    "sg:website":"https://smclean.custhelp.com/cgi-bin/smclean.cfg/php/enduser/doc_serve.php?2=BSYellowPages09",
    "wof:name":"ServiceMaster Clean",
    "wof:placetype":"venue"
},
  "geometry": {"coordinates":[-87.817032,41.954789],"type":"Point"}
}