{
  "type": "Feature",
  "properties": {
    "iso:country":"US",
    "sg:address":"1175 Alexander Ct",
    "sg:city":"Cary",
    "sg:classifiers":[
        {
            "category":"Professional",
            "subcategory":"Employment Agencies",
            "type":"Services"
        }
    ],
    "sg:phone":"+1 847 462 8128",
    "sg:postcode":"60013",
    "sg:province":"IL",
    "sg:tags":[
        "help",
        "contractor"
    ],
    "wof:name":"Tandem Staffing For Industry",
    "wof:placetype":"venue"
},
  "geometry": {"coordinates":[-88.273122,42.21935],"type":"Point"}
}