{
  "type": "Feature",
  "properties": {
    "iso:country":"US",
    "sg:address":"1011 Stratford Cir",
    "sg:city":"Streamwood",
    "sg:classifiers":[
        {
            "category":"Wholesale",
            "subcategory":"Books, Periodicals, & Newspapers",
            "type":"Manufacturing & Wholesale Goods"
        }
    ],
    "sg:phone":"+1 630 213 9083",
    "sg:postcode":"60107",
    "sg:province":"IL",
    "sg:tags":[
        "publisher",
        "book"
    ],
    "wof:name":"St James Press Inc",
    "wof:placetype":"venue"
},
  "geometry": {"coordinates":[-88.17187,42.01221],"type":"Point"}
}