{
  "type": "Feature",
  "properties": {
    "iso:country":"US",
    "sg:address":"5751 W 97th St",
    "sg:city":"Oak Lawn",
    "sg:classifiers":[
        {
            "category":"Freight",
            "type":"Transportation"
        }
    ],
    "sg:phone":"+1 708 499 5272",
    "sg:postcode":"60453",
    "sg:province":"IL",
    "sg:tags":[
        "operator",
        "local",
        "trucking"
    ],
    "wof:name":"G & J Cartage",
    "wof:placetype":"venue"
},
  "geometry": {"coordinates":[-87.764978,41.716002],"type":"Point"}
}