{
  "type": "Feature",
  "properties": {
    "addr:full":"111 E Davis St Bowen IL 62316",
    "addr:housenumber":"111",
    "addr:postcode":"62316",
    "addr:street":"E Davis St",
    "iso:country":"US",
    "sg:address":"111 E Davis St",
    "sg:city":"Bowen",
    "sg:classifiers":[
        {
            "category":"Freight",
            "type":"Transportation"
        }
    ],
    "sg:phone":"+1 217 842 5461",
    "sg:postcode":"62316",
    "sg:province":"IL",
    "sg:tags":[
        "operator",
        "local",
        "trucking"
    ],
    "wof:name":"Brian Gaines Trucking Inc",
    "wof:placetype":"venue"
},
  "geometry": {"coordinates":[-91.06447300000001,40.230198],"type":"Point"}
}