{
  "type": "Feature",
  "properties": {
    "iso:country":"US",
    "sg:address":"7 Rheam Dr",
    "sg:city":"Homewood",
    "sg:classifiers":[
        {
            "category":"Building & Trades",
            "subcategory":"Construction",
            "type":"Services"
        }
    ],
    "sg:phone":"+1 708 957 2535",
    "sg:postcode":"60430",
    "sg:province":"IL",
    "sg:tags":[
        "house",
        "industrial",
        "co"
    ],
    "wof:name":"Peacock Building Restoration",
    "wof:placetype":"venue"
},
  "geometry": {"coordinates":[-87.651053,41.539],"type":"Point"}
}