{
  "type": "Feature",
  "properties": {
    "iso:country":"US",
    "sg:address":"905 S Russell St",
    "sg:city":"Champaign",
    "sg:phone":"+1 217 356 3635",
    "sg:postcode":"61821",
    "sg:province":"IL",
    "sg:website":"http://www.stpetersucc.com",
    "wof:name":"St Peter's Church Of Christ",
    "wof:placetype":"venue"
},
  "geometry": {"coordinates":[-88.267173,40.107251],"type":"Point"}
}