{
  "type": "Feature",
  "properties": {
    "iso:country":"US",
    "sg:address":"7231 W Palos Ave",
    "sg:city":"Palos Heights",
    "sg:classifiers":[
        {
            "category":"Restaurant",
            "type":"Food & Drink"
        }
    ],
    "sg:phone":"+1   ",
    "sg:postcode":"60463",
    "sg:province":"IL",
    "sg:tags":[
        "eating"
    ],
    "wof:name":"Wagners Seafood West",
    "wof:placetype":"venue"
},
  "geometry": {"coordinates":[-87.800686,41.65955],"type":"Point"}
}