{
  "type": "Feature",
  "properties": {
    "iso:country":"US",
    "sg:address":"128 N Saint Paul St",
    "sg:city":"Spring Valley",
    "sg:classifiers":[
        {
            "category":"Shopping",
            "subcategory":"Books",
            "type":"Retail Goods"
        }
    ],
    "sg:phone":"+1   ",
    "sg:postcode":"61326",
    "sg:province":"IL",
    "wof:name":"Doodle Bug Scrap Book Store",
    "wof:placetype":"venue"
},
  "geometry": {"coordinates":[-89.25152799999999,41.2646],"type":"Point"}
}