{
  "type": "Feature",
  "properties": {
    "iso:country":"US",
    "sg:address":"611 Busse Rd",
    "sg:city":"Bensenville",
    "sg:classifiers":[
        {
            "category":"Organizations",
            "subcategory":"Professional Association",
            "type":"Services"
        }
    ],
    "sg:phone":"+1 630 350 3000",
    "sg:postcode":"60152",
    "sg:province":"IL",
    "sg:tags":[
        "membership",
        "restoration"
    ],
    "wof:name":"Disaster Kleenup International",
    "wof:placetype":"venue"
},
  "geometry": {"coordinates":[-88.608282,42.342199],"type":"Point"}
}