{
  "type": "Feature",
  "properties": {
    "iso:country":"US",
    "sg:address":"2400 Belvidere Rd",
    "sg:city":"Waukegan",
    "sg:classifiers":[
        {
            "category":"Government",
            "subcategory":"Office",
            "type":"Public Place"
        }
    ],
    "sg:phone":"+1 847 360 6500",
    "sg:postcode":"60085",
    "sg:province":"IL",
    "sg:tags":[
        "county",
        "administrative",
        "program",
        "health"
    ],
    "wof:name":"Lake County Health Department",
    "wof:placetype":"venue"
},
  "geometry": {"coordinates":[-87.857457,42.350774],"type":"Point"}
}