{
  "type": "Feature",
  "properties": {
    "addr:full":"1150 W Carl Sandburg Dr Ste C11 Galesburg IL 61401",
    "addr:housenumber":"1150",
    "addr:postcode":"61401",
    "addr:street":"W Carl Sandburg Dr Ste C11",
    "iso:country":"US",
    "sg:address":"1150 W Carl Sandburg Dr Ste C11",
    "sg:city":"Galesburg",
    "sg:classifiers":[
        {
            "category":"Shopping",
            "subcategory":"Clothing, Apparel, & Fashions",
            "type":"Retail Goods"
        },
        {
            "category":"Shopping",
            "subcategory":"Shoes",
            "type":"Retail Goods"
        }
    ],
    "sg:phone":"+1 309 344 3869",
    "sg:postcode":"61401",
    "sg:province":"IL",
    "sg:tags":[
        "sportswear",
        "store"
    ],
    "sg:website":"http://www.footlocker.com",
    "wof:name":"Foot Locker",
    "wof:placetype":"venue"
},
  "geometry": {"coordinates":[-90.390789,40.974299],"type":"Point"}
}