{
  "type": "Feature",
  "properties": {
    "iso:country":"US",
    "sg:address":"179 E Jackson St",
    "sg:city":"Virden",
    "sg:classifiers":[
        {
            "category":"Social Services",
            "subcategory":"Child Care",
            "type":"Services"
        }
    ],
    "sg:phone":"+1 217 965 4548",
    "sg:postcode":"62690",
    "sg:province":"IL",
    "sg:tags":[
        "day"
    ],
    "wof:name":"Care O Sel Day Care Annex Inc",
    "wof:placetype":"venue"
},
  "geometry": {"coordinates":[-89.76657,39.501615],"type":"Point"}
}