{
  "type": "Feature",
  "properties": {
    "iso:country":"US",
    "sg:address":"6261 Balboa St",
    "sg:city":"Rockford",
    "sg:classifiers":[
        {
            "category":"Manufacturing",
            "subcategory":"Glass & Minerals",
            "type":"Manufacturing & Wholesale Goods"
        }
    ],
    "sg:phone":"+1 815 874 5206",
    "sg:postcode":"61109",
    "sg:province":"IL",
    "sg:tags":[
        "glass-wholesale",
        "shape",
        "circle",
        "special",
        "manufacturer"
    ],
    "wof:name":"Original Glass Creations",
    "wof:placetype":"venue"
},
  "geometry": {"coordinates":[-89.06784500000001,42.190046],"type":"Point"}
}