{
  "type": "Feature",
  "properties": {
    "addr:full":"412 W Everett St Dixon IL 61021",
    "addr:housenumber":"412",
    "addr:postcode":"61021",
    "addr:street":"W Everett St",
    "iso:country":"US",
    "sg:address":"412 W Everett St",
    "sg:city":"Dixon",
    "sg:classifiers":[
        {
            "category":"Government",
            "subcategory":"Office",
            "type":"Public Place"
        }
    ],
    "sg:phone":"+1   ",
    "sg:postcode":"61021",
    "sg:province":"IL",
    "sg:tags":[
        "national",
        "security"
    ],
    "wof:name":"National Guard Recruiter",
    "wof:placetype":"venue"
},
  "geometry": {"coordinates":[-89.488911,41.847808],"type":"Point"}
}