{
  "type": "Feature",
  "properties": {
    "iso:country":"US",
    "sg:address":"10425 Laramie Ave",
    "sg:city":"Oak Lawn",
    "sg:classifiers":[
        {
            "category":"Building & Trades",
            "subcategory":"Construction",
            "type":"Services"
        }
    ],
    "sg:phone":"+1 708 422 6209",
    "sg:postcode":"60453",
    "sg:province":"IL",
    "sg:tags":[
        "contractor"
    ],
    "wof:name":"James Snooks Tile Installation",
    "wof:placetype":"venue"
},
  "geometry": {"coordinates":[-87.74983400000001,41.702189],"type":"Point"}
}