{
  "type": "Feature",
  "properties": {
    "addr:full":"1150 N 5th St Springfield IL 62702",
    "addr:housenumber":"1150",
    "addr:postcode":"62702",
    "addr:street":"N 5Th St",
    "iso:country":"US",
    "sg:address":"1150 N 5th St",
    "sg:city":"Springfield",
    "sg:classifiers":[
        {
            "category":"Professional",
            "subcategory":"Accounting & Tax Preparation",
            "type":"Services"
        },
        {
            "category":"Banks & Credit Unions",
            "subcategory":"Financial Services",
            "type":"Services"
        }
    ],
    "sg:phone":"+1 217 544 1361",
    "sg:postcode":"62702",
    "sg:province":"IL",
    "sg:tags":[
        "return",
        "preparation-business",
        "taxes-consultants",
        "loan",
        "reporting",
        "representative",
        "alternative",
        "bookkeeping"
    ],
    "sg:website":"http://www.hrblock.com",
    "wof:name":"H&R Block",
    "wof:placetype":"venue"
},
  "geometry": {"coordinates":[-89.649216,39.815168],"type":"Point"}
}