{
  "type": "Feature",
  "properties": {
    "addr:full":"4300 Vernon Ave Brookfield IL 60513",
    "addr:housenumber":"4300",
    "addr:postcode":"60513",
    "addr:street":"Vernon Ave",
    "iso:country":"US",
    "sg:address":"4300 Vernon Ave",
    "sg:city":"Brookfield",
    "sg:classifiers":[
        {
            "category":"Wholesale",
            "subcategory":"Metals & Minerals",
            "type":"Manufacturing & Wholesale Goods"
        }
    ],
    "sg:phone":"+1 708 485 0628",
    "sg:postcode":"60513",
    "sg:province":"IL",
    "sg:tags":[
        "center"
    ],
    "wof:name":"Jpg Inc",
    "wof:placetype":"venue"
},
  "geometry": {"coordinates":[-87.845011,41.811167],"type":"Point"}
}