{
  "type": "Feature",
  "properties": {
    "iso:country":"US",
    "sg:address":"1310 Kingsland Dr",
    "sg:city":"Batavia",
    "sg:classifiers":[
        {
            "category":"Manufacturing",
            "subcategory":"Building Materials",
            "type":"Manufacturing & Wholesale Goods"
        }
    ],
    "sg:phone":"+1 630 879 2696",
    "sg:postcode":"60510",
    "sg:province":"IL",
    "sg:tags":[
        "product",
        "aluminum"
    ],
    "wof:name":"Cast Aluminum Solutions",
    "wof:placetype":"venue"
},
  "geometry": {"coordinates":[-88.28685900000001,41.866009],"type":"Point"}
}