{
  "type": "Feature",
  "properties": {
    "addr:full":"215 W 1st St Dixon IL 61021",
    "addr:housenumber":"215",
    "addr:postcode":"61021",
    "addr:street":"W 1St St",
    "iso:country":"US",
    "sg:address":"215 W 1st St",
    "sg:city":"Dixon",
    "sg:classifiers":[
        {
            "category":"Bars & Pubs",
            "type":"Food & Drink"
        }
    ],
    "sg:phone":"+1 815 285 2211",
    "sg:postcode":"61021",
    "sg:province":"IL",
    "sg:tags":[
        "club",
        "night"
    ],
    "wof:name":"Night Spot",
    "wof:placetype":"venue"
},
  "geometry": {"coordinates":[-89.48412999999999,41.843302],"type":"Point"}
}