{
  "type": "Feature",
  "properties": {
    "addr:full":"1706 Garden Hills Dr Champaign IL 61821",
    "addr:housenumber":"1706",
    "addr:postcode":"61821",
    "addr:street":"Garden Hills Dr",
    "iso:country":"US",
    "sg:address":"1706 Garden Hills Dr",
    "sg:city":"Champaign",
    "sg:classifiers":[
        {
            "category":"Retail",
            "subcategory":"Repair Shop",
            "type":"Services"
        }
    ],
    "sg:phone":"+1 217 356 9319",
    "sg:postcode":"61821",
    "sg:province":"IL",
    "sg:tags":[
        "equipment",
        "audio"
    ],
    "wof:name":"Spalding Audio",
    "wof:placetype":"venue"
},
  "geometry": {"coordinates":[-88.272796,40.133733],"type":"Point"}
}