{
  "type": "Feature",
  "properties": {
    "iso:country":"US",
    "sg:address":"142 S Gary Ave Ste 101",
    "sg:city":"Bloomingdale",
    "sg:classifiers":[
        {
            "category":"Shopping Center",
            "type":"Public Place"
        }
    ],
    "sg:phone":"+1 630 351 4885",
    "sg:postcode":"60108",
    "sg:province":"IL",
    "wof:name":"Newmark Merrill Companies",
    "wof:placetype":"venue"
},
  "geometry": {"coordinates":[-88.120724,41.952242],"type":"Point"}
}