{
  "type": "Feature",
  "properties": {
    "iso:country":"US",
    "sg:address":"827 Turnberry Ln",
    "sg:city":"Northbrook",
    "sg:classifiers":[
        {
            "category":"Banks & Credit Unions",
            "subcategory":"Investment Brokerage",
            "type":"Services"
        },
        {
            "category":"Real Estate",
            "subcategory":"Developer",
            "type":"Services"
        }
    ],
    "sg:phone":"+1 847 656 8781",
    "sg:postcode":"60062",
    "sg:province":"IL",
    "sg:tags":[
        "investing"
    ],
    "wof:name":"Nerex.Com",
    "wof:placetype":"venue"
},
  "geometry": {"coordinates":[-87.800574,42.115242],"type":"Point"}
}