{
  "type": "Feature",
  "properties": {
    "iso:country":"US",
    "sg:address":"1872 N Damen Ave",
    "sg:city":"Chicago",
    "sg:classifiers":[
        {
            "category":"Shopping",
            "subcategory":"Clothing, Apparel, & Fashions",
            "type":"Retail Goods"
        }
    ],
    "sg:phone":"+1 773 252 1888",
    "sg:postcode":"60647",
    "sg:province":"IL",
    "sg:tags":[
        "accessory",
        "clothing",
        "women's"
    ],
    "sg:website":"www.michelletan.com",
    "wof:name":"Michelle Tan",
    "wof:placetype":"venue"
},
  "geometry": {"coordinates":[-87.677589,41.915791],"type":"Point"}
}