{
  "type": "Feature",
  "properties": {
    "addr:full":"717 Fairlane Dr Joliet IL 60435",
    "addr:housenumber":"717",
    "addr:postcode":"60435",
    "addr:street":"Fairlane Dr",
    "iso:country":"US",
    "sg:address":"717 Fairlane Dr",
    "sg:city":"Joliet",
    "sg:classifiers":[
        {
            "category":"Building & Trades",
            "subcategory":"Plumbing",
            "type":"Services"
        }
    ],
    "sg:phone":"+1 815 741 0307",
    "sg:postcode":"60435",
    "sg:province":"IL",
    "sg:tags":[
        "heating",
        "specialty"
    ],
    "wof:name":"Lemke Refrigeration Co",
    "wof:placetype":"venue"
},
  "geometry": {"coordinates":[-88.150429,41.536032],"type":"Point"}
}