{
  "type": "Feature",
  "properties": {
    "addr:full":"1781 Lunt Ave Des Plaines IL 60018",
    "addr:housenumber":"1781",
    "addr:postcode":"60018",
    "addr:street":"Lunt Ave",
    "iso:country":"US",
    "sg:address":"1781 Lunt Ave",
    "sg:city":"Des Plaines",
    "sg:classifiers":[
        {
            "category":"Professional",
            "subcategory":"Engineering",
            "type":"Services"
        }
    ],
    "sg:phone":"+1 847 824 2100",
    "sg:postcode":"60018",
    "sg:province":"IL",
    "wof:name":"North American Research",
    "wof:placetype":"venue"
},
  "geometry": {"coordinates":[-87.883505,42.005911],"type":"Point"}
}