{
  "type": "Feature",
  "properties": {
    "iso:country":"US",
    "sg:address":"1645 State Rte 104",
    "sg:city":"Quincy",
    "sg:classifiers":[
        {
            "category":"Retail",
            "subcategory":"Auto Rental",
            "type":"Services"
        }
    ],
    "sg:phone":"+1 217 885 3994",
    "sg:postcode":"62305",
    "sg:province":"IL",
    "sg:tags":[
        "passenger",
        "car"
    ],
    "wof:name":"Kurts Rent-A-Car",
    "wof:placetype":"venue"
},
  "geometry": {"coordinates":[-91.200433,39.933399],"type":"Point"}
}