{
  "type": "Feature",
  "properties": {
    "iso:country":"US",
    "sg:address":"1015 W Webster Ave",
    "sg:city":"Chicago",
    "sg:classifiers":[
        {
            "category":"Insurance",
            "subcategory":"Hazard Insurance",
            "type":"Services"
        }
    ],
    "sg:phone":"+1 773 975 6550",
    "sg:postcode":"60614",
    "sg:province":"IL",
    "wof:name":"Linda Kuczka",
    "wof:placetype":"venue"
},
  "geometry": {"coordinates":[-87.654177,41.921471],"type":"Point"}
}