{
  "type": "Feature",
  "properties": {
    "iso:country":"US",
    "sg:address":"315 N Westridge Dr",
    "sg:city":"Carbondale",
    "sg:classifiers":[
        {
            "category":"Shopping",
            "subcategory":"Gifts & Souvenirs",
            "type":"Retail Goods"
        }
    ],
    "sg:phone":"+1   ",
    "sg:postcode":"62901",
    "sg:province":"IL",
    "wof:name":"Annani Gift Baskets",
    "wof:placetype":"venue"
},
  "geometry": {"coordinates":[-89.25514200000001,37.732329],"type":"Point"}
}