{
  "type": "Feature",
  "properties": {
    "iso:country":"US",
    "sg:address":"812 N Lake St",
    "sg:city":"Mundelein",
    "sg:classifiers":[
        {
            "category":"Retail",
            "subcategory":"Auto Repair",
            "type":"Services"
        }
    ],
    "sg:phone":"+1 847 949 6085",
    "sg:postcode":"60060",
    "sg:province":"IL",
    "sg:tags":[
        "general"
    ],
    "wof:name":"Preventix Custom Auto Service",
    "wof:placetype":"venue"
},
  "geometry": {"coordinates":[-88.004123,42.275985],"type":"Point"}
}