{
  "type": "Feature",
  "properties": {
    "addr:full":"4153 N Kostner Ave Chicago IL 60641",
    "addr:housenumber":"4153",
    "addr:postcode":"60641",
    "addr:street":"N Kostner Ave",
    "iso:country":"US",
    "sg:address":"4153 N Kostner Ave",
    "sg:city":"Chicago",
    "sg:classifiers":[
        {
            "category":"Autos & Motor Vehicles",
            "subcategory":"Auto Supplies",
            "type":"Retail Goods"
        },
        {
            "category":"Wholesale",
            "subcategory":"Auto Parts",
            "type":"Manufacturing & Wholesale Goods"
        },
        {
            "category":"Building & Trades",
            "subcategory":"Electrical",
            "type":"Services"
        }
    ],
    "sg:phone":"+1 773 282 8686",
    "sg:postcode":"60641",
    "sg:province":"IL",
    "sg:tags":[
        "bearing",
        "power",
        "transmission",
        "bearings-wholesale",
        "equipment"
    ],
    "sg:website":"http://www.bearingsales.com",
    "wof:name":"Bearing Sales Corporation",
    "wof:placetype":"venue"
},
  "geometry": {"coordinates":[-87.738186,41.956232],"type":"Point"}
}