{
  "type": "Feature",
  "properties": {
    "addr:full":"940 Dillon Dr Wood Dale IL 60191",
    "addr:housenumber":"940",
    "addr:postcode":"60191",
    "addr:street":"Dillon Dr",
    "iso:country":"US",
    "sg:address":"940 Dillon Dr",
    "sg:city":"Wood Dale",
    "sg:classifiers":[
        {
            "category":"Manufacturing",
            "subcategory":"Metals",
            "type":"Manufacturing & Wholesale Goods"
        }
    ],
    "sg:phone":"+1 630 766 5600",
    "sg:postcode":"60191",
    "sg:province":"IL",
    "sg:tags":[
        "sheet",
        "mfg",
        "die",
        "tool",
        "specialty",
        "special"
    ],
    "wof:name":"Icon Metalcraft Inc",
    "wof:placetype":"venue"
},
  "geometry": {"coordinates":[-87.967022,41.978953],"type":"Point"}
}