{
  "type": "Feature",
  "properties": {
    "addr:full":"1007 W Jefferson Ave Effingham IL 62401",
    "addr:housenumber":"1007",
    "addr:postcode":"62401",
    "addr:street":"W Jefferson Ave",
    "iso:country":"US",
    "sg:address":"1007 W Jefferson Ave",
    "sg:city":"Effingham",
    "sg:classifiers":[
        {
            "category":"Banks & Credit Unions",
            "subcategory":"Investment Brokerage",
            "type":"Services"
        }
    ],
    "sg:phone":"+1 217 347 0757",
    "sg:postcode":"62401",
    "sg:province":"IL",
    "sg:tags":[
        "consultant",
        "planning",
        "financial"
    ],
    "wof:name":"American Express Financial Adv",
    "wof:placetype":"venue"
},
  "geometry": {"coordinates":[-88.555066,39.122081],"type":"Point"}
}