{
  "type": "Feature",
  "properties": {
    "addr:full":"322 E Champaign Ave Rantoul IL 61866",
    "addr:housenumber":"322",
    "addr:postcode":"61866",
    "addr:street":"E Champaign Ave",
    "iso:country":"US",
    "sg:address":"322 E Champaign Ave",
    "sg:city":"Rantoul",
    "sg:classifiers":[
        {
            "category":"Food & Beverages",
            "subcategory":"Groceries & Convenience Stores",
            "type":"Retail Goods"
        }
    ],
    "sg:phone":"+1   ",
    "sg:postcode":"61866",
    "sg:province":"IL",
    "wof:name":"Supermarket El Rey",
    "wof:placetype":"venue"
},
  "geometry": {"coordinates":[-88.155395,40.308123],"type":"Point"}
}