{
  "type": "Feature",
  "properties": {
    "addr:full":"5965 N Clark Chicago IL 60660",
    "addr:housenumber":"5965",
    "addr:postcode":"60660",
    "addr:street":"N Clark",
    "iso:country":"US",
    "sg:address":"5965 N Clark",
    "sg:city":"Chicago",
    "sg:classifiers":[
        {
            "category":"Arts & Performance",
            "subcategory":"Arts Center",
            "type":"Entertainment"
        },
        {
            "category":"Arts & Performance",
            "subcategory":"Dance",
            "type":"Entertainment"
        }
    ],
    "sg:phone":"+1 773 960 4909",
    "sg:postcode":"60660",
    "sg:province":"IL",
    "sg:tags":[
        "school",
        "performing"
    ],
    "sg:website":"www.inasidechicagodance.org",
    "wof:name":"Inaside Chicago Dance",
    "wof:placetype":"venue"
},
  "geometry": {"coordinates":[-87.669791,41.990482],"type":"Point"}
}