{
  "type": "Feature",
  "properties": {
    "addr:full":"4193 Grove Ave Gurnee IL 60031",
    "addr:housenumber":"4193",
    "addr:postcode":"60031",
    "addr:street":"Grove Ave",
    "iso:country":"US",
    "sg:address":"4193 Grove Ave",
    "sg:city":"Gurnee",
    "sg:classifiers":[
        {
            "category":"Insurance",
            "subcategory":"Hazard Insurance",
            "type":"Services"
        }
    ],
    "sg:phone":"+1 847 360 9300",
    "sg:postcode":"60031",
    "sg:province":"IL",
    "sg:tags":[
        "commercial",
        "business"
    ],
    "sg:website":"http://www.nmfn.com",
    "wof:name":"Northwestern Mutual Life Insur",
    "wof:placetype":"venue"
},
  "geometry": {"coordinates":[-87.906673,42.378941],"type":"Point"}
}