{
  "type": "Feature",
  "properties": {
    "addr:full":"212 E Ohio St Ste 300 Chicago IL 60611",
    "addr:housenumber":"212",
    "addr:postcode":"60611",
    "addr:street":"E Ohio St Ste 300",
    "iso:country":"US",
    "sg:address":"212 E Ohio St Ste 300",
    "sg:city":"Chicago",
    "sg:classifiers":[
        {
            "category":"Communications",
            "subcategory":"Film & Video Production",
            "type":"Services"
        },
        {
            "category":"Communications",
            "subcategory":"Television Station",
            "type":"Services"
        }
    ],
    "sg:phone":"+1 312 654 1100",
    "sg:postcode":"60611",
    "sg:province":"IL",
    "sg:tags":[
        "picture",
        "producer",
        "companies-film",
        "tv",
        "motion",
        "program",
        "radio",
        "distributor"
    ],
    "sg:website":"http://www.ccptv.com",
    "wof:name":"Central City Productions",
    "wof:placetype":"venue"
},
  "geometry": {"coordinates":[-87.62240300000001,41.892574],"type":"Point"}
}