{
  "type": "Feature",
  "properties": {
    "addr:full":"150 North Michigan Avenue 20th Floor Chicago IL 60601",
    "addr:housenumber":"150;20th",
    "addr:postcode":"60601",
    "addr:street":"North Michigan Avenue",
    "iso:country":"US",
    "sg:address":"150 North Michigan Avenue 20th Floor",
    "sg:city":"Chicago",
    "sg:classifiers":[
        {
            "category":"Professional",
            "type":"Services"
        }
    ],
    "sg:phone":"+1 312 236 1606",
    "sg:postcode":"60601",
    "sg:province":"IL",
    "sg:website":"www.translations.com",
    "wof:name":"Translations.com",
    "wof:placetype":"venue"
},
  "geometry": {"coordinates":[-87.624978,41.885031],"type":"Point"}
}