{
  "type": "Feature",
  "properties": {
    "addr:full":"7700 Olde Salem Rd Bartlett IL 60133",
    "addr:housenumber":"7700",
    "addr:postcode":"60133",
    "addr:street":"Olde Salem Rd",
    "iso:country":"US",
    "sg:address":"7700 Olde Salem Rd",
    "sg:city":"Bartlett",
    "sg:classifiers":[
        {
            "category":"Real Estate",
            "subcategory":"Real Estate Operator",
            "type":"Services"
        }
    ],
    "sg:phone":"+1 847 985 9700",
    "sg:postcode":"60133",
    "sg:province":"IL",
    "sg:tags":[
        "building",
        "apartment"
    ],
    "wof:name":"Century 21",
    "wof:placetype":"venue"
},
  "geometry": {"coordinates":[-88.129392,42.008729],"type":"Point"}
}