{
  "type": "Feature",
  "properties": {
    "addr:full":"1047 Ferdinand Ave Forest Park IL 60130",
    "addr:housenumber":"1047",
    "addr:postcode":"60130",
    "addr:street":"Ferdinand Ave",
    "iso:country":"US",
    "sg:address":"1047 Ferdinand Ave",
    "sg:city":"Forest Park",
    "sg:classifiers":[
        {
            "category":"Professional",
            "type":"Services"
        }
    ],
    "sg:phone":"+1 708 771 2282",
    "sg:postcode":"60130",
    "sg:province":"IL",
    "wof:name":"Solarnet Internet Services",
    "wof:placetype":"venue"
},
  "geometry": {"coordinates":[-87.81287399999999,41.86754],"type":"Point"}
}