{
  "type": "Feature",
  "properties": {
    "iso:country":"US",
    "sg:address":"2350 Sauget Industrial Pkwy",
    "sg:city":"East St Louis",
    "sg:classifiers":[
        {
            "category":"Autos & Motor Vehicles",
            "subcategory":"Automobile Sales",
            "type":"Retail Goods"
        }
    ],
    "sg:phone":"+1 618 337 5917",
    "sg:postcode":"62206",
    "sg:province":"IL",
    "sg:tags":[
        "truck"
    ],
    "wof:name":"Mack Trucks Inc",
    "wof:placetype":"venue"
},
  "geometry": {"coordinates":[-90.132459,38.571091],"type":"Point"}
}