{
  "type": "Feature",
  "properties": {
    "addr:full":"5700 N Main St Rockford IL 61103",
    "addr:housenumber":"5700",
    "addr:postcode":"61103",
    "addr:street":"N Main St",
    "iso:country":"US",
    "sg:address":"5700 N Main St",
    "sg:city":"Rockford",
    "sg:classifiers":[
        {
            "category":"Travel",
            "subcategory":"Campground",
            "type":"Entertainment"
        }
    ],
    "sg:phone":"+1 815 654 0758",
    "sg:postcode":"61103",
    "sg:province":"IL",
    "sg:tags":[
        "camp"
    ],
    "wof:name":"Camp Winnebago YMCA",
    "wof:placetype":"venue"
},
  "geometry": {"coordinates":[-89.078266,42.339299],"type":"Point"}
}