{
  "type": "Feature",
  "properties": {
    "addr:full":"1940 W Irving Park Rd # 201 Chicago IL 60613",
    "addr:housenumber":"1940",
    "addr:postcode":"60613",
    "addr:street":"W Irving Park Rd # 201",
    "iso:country":"US",
    "sg:address":"1940 W Irving Park Rd # 201",
    "sg:city":"Chicago",
    "sg:classifiers":[
        {
            "category":"Professional",
            "subcategory":"Management & Consulting",
            "type":"Services"
        }
    ],
    "sg:phone":"+1 773 975 1345",
    "sg:postcode":"60613",
    "sg:province":"IL",
    "sg:tags":[
        "counselor",
        "relation",
        "public"
    ],
    "sg:website":"http://www.amdurspitz.com",
    "wof:name":"Amdur Spitz And Associates Inc",
    "wof:placetype":"venue"
},
  "geometry": {"coordinates":[-87.67731499999999,41.954177],"type":"Point"}
}