{
  "type": "Feature",
  "properties": {
    "iso:country":"US",
    "sg:address":"903 Francis Dr",
    "sg:city":"Champaign",
    "sg:classifiers":[
        {
            "category":"Building & Trades",
            "subcategory":"Construction",
            "type":"Services"
        },
        {
            "category":"Building & Trades",
            "subcategory":"Electrical",
            "type":"Services"
        }
    ],
    "sg:phone":"+1 217 356 6999",
    "sg:postcode":"61821",
    "sg:province":"IL",
    "sg:tags":[
        "electrician",
        "contractor"
    ],
    "wof:name":"Remco Electrical Corp",
    "wof:placetype":"venue"
},
  "geometry": {"coordinates":[-88.258499,40.130699],"type":"Point"}
}