{
  "type": "Feature",
  "properties": {
    "addr:full":"1320 Tower Rd Schaumburg IL 60173",
    "addr:housenumber":"1320",
    "addr:postcode":"60173",
    "addr:street":"Tower Rd",
    "iso:country":"US",
    "sg:address":"1320 Tower Rd",
    "sg:city":"Schaumburg",
    "sg:phone":"+1 847 344 4475",
    "sg:postcode":"60173",
    "sg:province":"IL",
    "sg:website":"http://www.cgood.info",
    "wof:name":"The Children's Good",
    "wof:placetype":"venue"
},
  "geometry": {"coordinates":[-88.050831,42.056478],"type":"Point"}
}