{
  "type": "Feature",
  "properties": {
    "iso:country":"US",
    "sg:address":"2930 N Broadway St",
    "sg:city":"Chicago",
    "sg:classifiers":[
        {
            "category":"Restaurant",
            "type":"Food & Drink"
        }
    ],
    "sg:phone":"+1 773 883 1616",
    "sg:postcode":"60657",
    "sg:province":"IL",
    "sg:tags":[
        "pizza"
    ],
    "sg:website":"www.nancyspizza.com",
    "wof:name":"Nancy's Pizza",
    "wof:placetype":"venue"
},
  "geometry": {"coordinates":[-87.644096,41.935902],"type":"Point"}
}