{
  "type": "Feature",
  "properties": {
    "iso:country":"US",
    "sg:address":"405 E 75th St",
    "sg:city":"Chicago",
    "sg:classifiers":[
        {
            "category":"Restaurant",
            "type":"Food & Drink"
        }
    ],
    "sg:phone":"+1 773 874 4965",
    "sg:postcode":"60619",
    "sg:province":"IL",
    "wof:name":"Black Woc the",
    "wof:placetype":"venue"
},
  "geometry": {"coordinates":[-87.6147,41.7584],"type":"Point"}
}