{
  "type": "Feature",
  "properties": {
    "iso:country":"US",
    "sg:address":"6754 Indian Creek Rd",
    "sg:city":"Long Grove",
    "sg:classifiers":[
        {
            "category":"Building & Trades",
            "subcategory":"Landscaping Services",
            "type":"Services"
        }
    ],
    "sg:phone":"+1 847 949 6667",
    "sg:postcode":"60047",
    "sg:province":"IL",
    "sg:tags":[
        "landscape",
        "contractor"
    ],
    "sg:website":"www.pouls.com",
    "wof:name":"Poul's Landscaping & Nursery",
    "wof:placetype":"venue"
},
  "geometry": {"coordinates":[-88.009276,42.233447],"type":"Point"}
}