{
  "type": "Feature",
  "properties": {
    "iso:country":"US",
    "sg:address":"726 Hickory St",
    "sg:city":"Lemont",
    "sg:classifiers":[
        {
            "category":"Building & Trades",
            "subcategory":"Landscaping Services",
            "type":"Services"
        }
    ],
    "sg:phone":"+1 630 257 9028",
    "sg:postcode":"60439",
    "sg:province":"IL",
    "wof:name":"Affordable Landscaping & Lawn",
    "wof:placetype":"venue"
},
  "geometry": {"coordinates":[-87.997162,41.667287],"type":"Point"}
}