{
  "type": "Feature",
  "properties": {
    "iso:country":"US",
    "sg:address":"17560 Chicago Ave",
    "sg:city":"Lansing",
    "sg:classifiers":[
        {
            "category":"Freight",
            "type":"Transportation"
        }
    ],
    "sg:phone":"+1 708 474 9472",
    "sg:postcode":"60438",
    "sg:province":"IL",
    "sg:tags":[
        "special"
    ],
    "wof:name":"Lansing Storage",
    "wof:placetype":"venue"
},
  "geometry": {"coordinates":[-87.544319,41.575866],"type":"Point"}
}