{
  "type": "Feature",
  "properties": {
    "addr:full":"3300 Commercial Ave Northbrook IL 60062",
    "addr:housenumber":"3300",
    "addr:postcode":"60062",
    "addr:street":"Commercial Ave",
    "iso:country":"US",
    "sg:address":"3300 Commercial Ave",
    "sg:city":"Northbrook",
    "sg:classifiers":[
        {
            "category":"Building & Trades",
            "subcategory":"Equipment Rental",
            "type":"Services"
        },
        {
            "category":"Shopping",
            "subcategory":"Computers & Home Electronics",
            "type":"Retail Goods"
        }
    ],
    "sg:phone":"+1 847 205 5557",
    "sg:postcode":"60062",
    "sg:province":"IL",
    "sg:tags":[
        "support",
        "audio",
        "staging",
        "event"
    ],
    "wof:name":"Edge Audio",
    "wof:placetype":"venue"
},
  "geometry": {"coordinates":[-87.861431,42.14657],"type":"Point"}
}