{
  "type": "Feature",
  "properties": {
    "iso:country":"US",
    "sg:address":"28753 E 3000th St",
    "sg:city":"Tampico",
    "sg:phone":"+1 815 438 7615",
    "sg:postcode":"61283",
    "sg:province":"IL",
    "sg:tags":[
        "farm",
        "corn",
        "soybean"
    ],
    "wof:name":"Russell Meridian",
    "wof:placetype":"venue"
},
  "geometry": {"coordinates":[-89.85931100000001,41.520126],"type":"Point"}
}