{
  "type": "Feature",
  "properties": {
    "iso:country":"US",
    "sg:address":"129 N Oak Park Ave",
    "sg:city":"Oak Park",
    "sg:classifiers":[
        {
            "category":"Shopping",
            "subcategory":"Gifts & Souvenirs",
            "type":"Retail Goods"
        }
    ],
    "sg:phone":"+1 708 524 4644",
    "sg:postcode":"60301",
    "sg:province":"IL",
    "sg:tags":[
        "shop"
    ],
    "wof:name":"Camille Et Famille",
    "wof:placetype":"venue"
},
  "geometry": {"coordinates":[-87.79459,41.888526],"type":"Point"}
}