{
  "type": "Feature",
  "properties": {
    "addr:full":"7600 College Dr Palos Heights IL 60463",
    "addr:housenumber":"7600",
    "addr:postcode":"60463",
    "addr:street":"College Dr",
    "iso:country":"US",
    "sg:address":"7600 College Dr",
    "sg:city":"Palos Heights",
    "sg:classifiers":[
        {
            "category":"Health Services",
            "subcategory":"Dentist",
            "type":"Services"
        }
    ],
    "sg:phone":"+1 708 361 1770",
    "sg:postcode":"60463",
    "sg:province":"IL",
    "wof:name":"James E McCormick, DMD, MS",
    "wof:placetype":"venue"
},
  "geometry": {"coordinates":[-87.80726199999999,41.675556],"type":"Point"}
}