{
  "type": "Feature",
  "properties": {
    "addr:full":"714 Lunt Ave Schaumburg IL 60193",
    "addr:housenumber":"714",
    "addr:postcode":"60193",
    "addr:street":"Lunt Ave",
    "iso:country":"US",
    "sg:address":"714 Lunt Ave",
    "sg:city":"Schaumburg",
    "sg:classifiers":[
        {
            "category":"Retail",
            "subcategory":"Auto Repair",
            "type":"Services"
        }
    ],
    "sg:phone":"+1 847 923 0727",
    "sg:postcode":"60193",
    "sg:province":"IL",
    "sg:tags":[
        "body",
        "automobile",
        "painting"
    ],
    "wof:name":"D & D Autobody",
    "wof:placetype":"venue"
},
  "geometry": {"coordinates":[-88.095939,42.001717],"type":"Point"}
}