{
  "type": "Feature",
  "properties": {
    "iso:country":"US",
    "sg:address":"799 Roosevelt Rd Ste 3-106",
    "sg:city":"Glen Ellyn",
    "sg:classifiers":[
        {
            "category":"Professional",
            "subcategory":"Employment Agencies",
            "type":"Services"
        }
    ],
    "sg:phone":"+1 630 545 3333",
    "sg:postcode":"60137",
    "sg:province":"IL",
    "sg:website":"www.venatoradvantage.com",
    "wof:name":"Venator Advantage Llc",
    "wof:placetype":"venue"
},
  "geometry": {"coordinates":[-88.052851,41.859308],"type":"Point"}
}