{
  "type": "Feature",
  "properties": {
    "iso:country":"US",
    "sg:address":"1000 McKee St",
    "sg:city":"Batavia",
    "sg:classifiers":[
        {
            "category":"Manufacturing",
            "subcategory":"Tools & Machinery",
            "type":"Manufacturing & Wholesale Goods"
        }
    ],
    "sg:phone":"+1 630 879 6000",
    "sg:postcode":"60510",
    "sg:province":"IL",
    "sg:tags":[
        "control",
        "industrial"
    ],
    "wof:name":"Siemens-Furnas Controls",
    "wof:placetype":"venue"
},
  "geometry": {"coordinates":[-88.325778,41.852143],"type":"Point"}
}