{
  "type": "Feature",
  "properties": {
    "addr:full":"634 Pratt Ave N Schaumburg IL 60193",
    "addr:housenumber":"634",
    "addr:postcode":"60193",
    "addr:street":"Pratt Ave N",
    "iso:country":"US",
    "sg:address":"634 Pratt Ave N",
    "sg:city":"Schaumburg",
    "sg:classifiers":[
        {
            "category":"Retail",
            "subcategory":"Repair Shop",
            "type":"Services"
        }
    ],
    "sg:phone":"+1 847 301 9712",
    "sg:postcode":"60193",
    "sg:province":"IL",
    "sg:website":"www.mac-tech.com",
    "wof:name":"Braketown USA Inc",
    "wof:placetype":"venue"
},
  "geometry": {"coordinates":[-88.083815,41.997847],"type":"Point"}
}