{
  "type": "Feature",
  "properties": {
    "iso:country":"US",
    "sg:address":"14323 S Halsted St",
    "sg:city":"Riverdale",
    "sg:classifiers":[
        {
            "category":"Social Services",
            "type":"Services"
        }
    ],
    "sg:phone":"+1 708 201 0951",
    "sg:postcode":"60827",
    "sg:province":"IL",
    "wof:name":"Thornton Township Senior Youth",
    "wof:placetype":"venue"
},
  "geometry": {"coordinates":[-87.641397,41.633869],"type":"Point"}
}