{
  "type": "Feature",
  "properties": {
    "addr:full":"2801 N Lincoln Ave Urbana IL 61802",
    "addr:housenumber":"2801",
    "addr:postcode":"61802",
    "addr:street":"N Lincoln Ave",
    "iso:country":"US",
    "sg:address":"2801 N Lincoln Ave",
    "sg:city":"Urbana",
    "sg:classifiers":[
        {
            "category":"Wholesale",
            "subcategory":"Machinery & Supplies",
            "type":"Manufacturing & Wholesale Goods"
        }
    ],
    "sg:phone":"+1 217 367 9521",
    "sg:postcode":"61802",
    "sg:province":"IL",
    "sg:tags":[
        "fire",
        "equipment"
    ],
    "wof:name":"Illini Fire Equipment Company",
    "wof:placetype":"venue"
},
  "geometry": {"coordinates":[-88.21993999999999,40.141807],"type":"Point"}
}