{
  "type": "Feature",
  "properties": {
    "iso:country":"US",
    "sg:address":"804 E Jackson St",
    "sg:city":"Macomb",
    "sg:classifiers":[
        {
            "category":"Insurance",
            "subcategory":"Insurance Agent",
            "type":"Services"
        }
    ],
    "sg:phone":"+1 309 833 2267",
    "sg:postcode":"61455",
    "sg:province":"IL",
    "wof:name":"Prudential",
    "wof:placetype":"venue"
},
  "geometry": {"coordinates":[-90.662075,40.458727],"type":"Point"}
}