{
  "type": "Feature",
  "properties": {
    "addr:full":"462 N McLean Blvd Elgin IL 60123",
    "addr:housenumber":"462",
    "addr:postcode":"60123",
    "addr:street":"N Mclean Blvd",
    "iso:country":"US",
    "sg:address":"462 N McLean Blvd",
    "sg:city":"Elgin",
    "sg:classifiers":[
        {
            "category":"Real Estate",
            "subcategory":"Architect",
            "type":"Services"
        }
    ],
    "sg:phone":"+1 847 742 4063",
    "sg:postcode":"60123",
    "sg:province":"IL",
    "sg:tags":[
        "architectural"
    ],
    "wof:name":"Dahlquist & Lutzow Architects",
    "wof:placetype":"venue"
},
  "geometry": {"coordinates":[-88.312878,42.02172],"type":"Point"}
}