{
  "type": "Feature",
  "properties": {
    "addr:full":"984 S Bartlett Rd Bartlett IL 60103",
    "addr:housenumber":"984",
    "addr:postcode":"60103",
    "addr:street":"S Bartlett Rd",
    "iso:country":"US",
    "sg:address":"984 S Bartlett Rd",
    "sg:city":"Bartlett",
    "sg:classifiers":[
        {
            "category":"Banks & Credit Unions",
            "subcategory":"Bank",
            "type":"Services"
        }
    ],
    "sg:phone":"+1 630 289 9850",
    "sg:postcode":"60103",
    "sg:province":"IL",
    "wof:name":"State Farm Insurance Companies",
    "wof:placetype":"venue"
},
  "geometry": {"coordinates":[-88.183998,41.968201],"type":"Point"}
}