{
  "type": "Feature",
  "properties": {
    "iso:country":"US",
    "sg:address":"24656 S Willow Brook Trl",
    "sg:city":"Crete",
    "sg:classifiers":[
        {
            "category":"Real Estate",
            "subcategory":"Real Estate Services",
            "type":"Services"
        },
        {
            "category":"Real Estate",
            "subcategory":"Surveying",
            "type":"Services"
        }
    ],
    "sg:phone":"+1 708 757 3884",
    "sg:postcode":"60417",
    "sg:province":"IL",
    "sg:tags":[
        "industrial",
        "appraisers-commercial",
        "appraiser"
    ],
    "wof:name":"Laird Appraisals Tr Laird Dba",
    "wof:placetype":"venue"
},
  "geometry": {"coordinates":[-87.54441199999999,41.443553],"type":"Point"}
}