{
  "type": "Feature",
  "properties": {
    "addr:full":"1040 E Grissom Dr Palatine IL 60074",
    "addr:housenumber":"1040",
    "addr:postcode":"60074",
    "addr:street":"E Grissom Dr",
    "iso:country":"US",
    "sg:address":"1040 E Grissom Dr",
    "sg:city":"Palatine",
    "sg:classifiers":[
        {
            "category":"Shopping",
            "subcategory":"Department Store",
            "type":"Retail Goods"
        }
    ],
    "sg:phone":"+1 847 358 1341",
    "sg:postcode":"60074",
    "sg:province":"IL",
    "wof:name":"Classique Inc",
    "wof:placetype":"venue"
},
  "geometry": {"coordinates":[-88.01605499999999,42.126419],"type":"Point"}
}