{
  "type": "Feature",
  "properties": {
    "iso:country":"US",
    "sg:address":"304 E Washington St",
    "sg:city":"Freeport",
    "sg:classifiers":[
        {
            "category":"Building & Trades",
            "subcategory":"Construction",
            "type":"Services"
        }
    ],
    "sg:phone":"+1 815 235 3475",
    "sg:postcode":"61032",
    "sg:province":"IL",
    "sg:tags":[
        "roofing",
        "contractor"
    ],
    "wof:name":"Elite Construction",
    "wof:placetype":"venue"
},
  "geometry": {"coordinates":[-89.613043,42.297316],"type":"Point"}
}