{
  "type": "Feature",
  "properties": {
    "addr:full":"9640 S Western Ave Evergreen Park IL 60805",
    "addr:housenumber":"9640",
    "addr:postcode":"60805",
    "addr:street":"S Western Ave",
    "iso:country":"US",
    "sg:address":"9640 S Western Ave",
    "sg:city":"Evergreen Park",
    "sg:classifiers":[
        {
            "category":"Retail",
            "subcategory":"Auto Rental",
            "type":"Services"
        }
    ],
    "sg:phone":"+1 708 499 7602",
    "sg:postcode":"60805",
    "sg:province":"IL",
    "sg:tags":[
        "car"
    ],
    "wof:name":"Enterprise Rent-A-Car",
    "wof:placetype":"venue"
},
  "geometry": {"coordinates":[-87.682239,41.718385],"type":"Point"}
}