{
  "type": "Feature",
  "properties": {
    "addr:full":"800 E Devon Ave Elk Grove Village IL 60007",
    "addr:housenumber":"800",
    "addr:postcode":"60007",
    "addr:street":"E Devon Ave",
    "iso:country":"US",
    "sg:address":"800 E Devon Ave",
    "sg:city":"Elk Grove Village",
    "sg:classifiers":[
        {
            "category":"Wholesale",
            "subcategory":"Electrical",
            "type":"Manufacturing & Wholesale Goods"
        }
    ],
    "sg:phone":"+1 847 593 3400",
    "sg:postcode":"60007",
    "sg:province":"IL",
    "sg:tags":[
        "light",
        "bulb"
    ],
    "wof:name":"Osram Sylvania Inc",
    "wof:placetype":"venue"
},
  "geometry": {"coordinates":[-87.97525899999999,41.993009],"type":"Point"}
}