{
  "type": "Feature",
  "properties": {
    "iso:country":"US",
    "sg:address":"2808 Thole-Plocher Rd",
    "sg:city":"Highland",
    "sg:classifiers":[
        {
            "category":"Building & Trades",
            "subcategory":"Construction",
            "type":"Services"
        }
    ],
    "sg:phone":"+1 618 654 9408",
    "sg:postcode":"62249",
    "sg:province":"IL",
    "sg:tags":[
        "repairing",
        "contracting",
        "contractor",
        "concrete",
        "carpentry",
        "general",
        "remodeling",
        "structural"
    ],
    "wof:name":"Plocher Construction Company",
    "wof:placetype":"venue"
},
  "geometry": {"coordinates":[-89.611566,38.762219],"type":"Point"}
}