{
  "type": "Feature",
  "properties": {
    "iso:country":"US",
    "sg:address":"12 S 5th St Ste 1",
    "sg:city":"Geneva",
    "sg:classifiers":[
        {
            "category":"Professional",
            "subcategory":"Management & Consulting",
            "type":"Services"
        },
        {
            "category":"Professional",
            "subcategory":"Advertising",
            "type":"Services"
        }
    ],
    "sg:phone":"+1 630 208 9700",
    "sg:postcode":"60134",
    "sg:province":"IL",
    "sg:tags":[
        "marketing",
        "program",
        "consultant"
    ],
    "sg:website":"http://www.rranda.com",
    "wof:name":"Robert Russell And Associates",
    "wof:placetype":"venue"
},
  "geometry": {"coordinates":[-88.310648,41.88819],"type":"Point"}
}