{
  "type": "Feature",
  "properties": {
    "addr:full":"18 S 5th St Geneva IL 60134",
    "addr:housenumber":"18",
    "addr:postcode":"60134",
    "addr:street":"S 5Th St",
    "iso:country":"US",
    "sg:address":"18 S 5th St",
    "sg:city":"Geneva",
    "sg:classifiers":[
        {
            "category":"Social Services",
            "type":"Services"
        }
    ],
    "sg:phone":"+1 630 208 6263",
    "sg:postcode":"60134",
    "sg:province":"IL",
    "wof:name":"Lisa Gomien Lcsw",
    "wof:placetype":"venue"
},
  "geometry": {"coordinates":[-88.31090399999999,41.887411],"type":"Point"}
}