{
  "type": "Feature",
  "properties": {
    "iso:country":"US",
    "sg:address":"200 E Randolph Dr",
    "sg:city":"Chicago",
    "sg:classifiers":[
        {
            "category":"Retail",
            "subcategory":"Laundry & Dry Cleaning",
            "type":"Services"
        },
        {
            "category":"Personal",
            "subcategory":"Shoe Repair & Shine",
            "type":"Services"
        }
    ],
    "sg:phone":"+1 312 861 0055",
    "sg:postcode":"60601",
    "sg:province":"IL",
    "wof:name":"Kim's Valet Service",
    "wof:placetype":"venue"
},
  "geometry": {"coordinates":[-87.62199,41.884742],"type":"Point"}
}