{
  "type": "Feature",
  "properties": {
    "addr:full":"1 Times Square Mall Mount Vernon IL 62864",
    "addr:housenumber":"1",
    "addr:postcode":"62864",
    "addr:street":"Times Square Mall",
    "iso:country":"US",
    "sg:address":"1 Times Square Mall",
    "sg:city":"Mount Vernon",
    "sg:classifiers":[
        {
            "category":"Restaurant",
            "type":"Food & Drink"
        }
    ],
    "sg:menulink":"http://www.allmenus.com/il/shiloh/198945-kfc---kentucky-fried-chicken/menu/",
    "sg:phone":"+1 618 244 3106",
    "sg:postcode":"62864",
    "sg:province":"IL",
    "sg:tags":[
        "american",
        "chicken"
    ],
    "wof:name":"KFC - Kentucky Fried Chicken",
    "wof:placetype":"venue"
},
  "geometry": {"coordinates":[-88.942165,38.313162],"type":"Point"}
}