{
  "type": "Feature",
  "properties": {
    "iso:country":"US",
    "sg:address":"7411 Lake Riv",
    "sg:city":"Forest Park",
    "sg:classifiers":[
        {
            "category":"Health Services",
            "subcategory":"Doctor",
            "type":"Services"
        }
    ],
    "sg:phone":"+1 708 488 1122",
    "sg:postcode":"60130",
    "sg:province":"IL",
    "sg:tags":[
        "cardiologist"
    ],
    "wof:name":"Millman William L MD",
    "wof:placetype":"venue"
},
  "geometry": {"coordinates":[-87.810001,41.888425],"type":"Point"}
}