{
  "type": "Feature",
  "properties": {
    "iso:country":"US",
    "sg:address":"815 E Chatham St",
    "sg:city":"Metamora",
    "sg:classifiers":[
        {
            "category":"Education",
            "subcategory":"School",
            "type":"Public Place"
        }
    ],
    "sg:phone":"+1 309 367 2361",
    "sg:postcode":"61548",
    "sg:province":"IL",
    "sg:tags":[
        "elementary"
    ],
    "wof:name":"Metamora Community Consolidated-Grade School",
    "wof:placetype":"venue"
},
  "geometry": {"coordinates":[-89.35427900000001,40.792599],"type":"Point"}
}