{
  "type": "Feature",
  "properties": {
    "iso:country":"US",
    "sg:address":"30 W University Dr",
    "sg:city":"Arlington Hts",
    "sg:classifiers":[
        {
            "category":"Organizations",
            "subcategory":"Non-profit Organization",
            "type":"Services"
        }
    ],
    "sg:phone":"+1 847 394 0150",
    "sg:postcode":"60004",
    "sg:province":"IL",
    "sg:website":"www.amca.org",
    "wof:name":"Air Movement & Control Assn",
    "wof:placetype":"venue"
},
  "geometry": {"coordinates":[-87.986081,42.132772],"type":"Point"}
}