{
  "type": "Feature",
  "properties": {
    "addr:full":"340 E Randolph St Chicago IL 60601",
    "addr:housenumber":"340",
    "addr:postcode":"60601",
    "addr:street":"E Randolph St",
    "iso:country":"US",
    "sg:address":"340 E Randolph St",
    "sg:city":"Chicago",
    "sg:classifiers":[
        {
            "category":"Retail",
            "subcategory":"Laundry & Dry Cleaning",
            "type":"Services"
        }
    ],
    "sg:phone":"+1 312 552 0050",
    "sg:postcode":"60601",
    "sg:province":"IL",
    "wof:name":"340 On the Park Cleaners",
    "wof:placetype":"venue"
},
  "geometry": {"coordinates":[-87.618875,41.884677],"type":"Point"}
}