{
  "type": "Feature",
  "properties": {
    "addr:full":"1772 S Randall Rd Geneva IL 60134",
    "addr:housenumber":"1772",
    "addr:postcode":"60134",
    "addr:street":"S Randall Rd",
    "iso:country":"US",
    "sg:address":"1772 S Randall Rd",
    "sg:city":"Geneva",
    "sg:classifiers":[
        {
            "category":"Restaurant",
            "type":"Food & Drink"
        }
    ],
    "sg:menulink":"http://www.allmenus.com/il/geneva/86916-nancy-pizza/menu/",
    "sg:phone":"+1 630 262 0670",
    "sg:postcode":"60134",
    "sg:province":"IL",
    "sg:tags":[
        "american",
        "pizza"
    ],
    "wof:name":"Nancy Pizza",
    "wof:placetype":"venue"
},
  "geometry": {"coordinates":[-88.340497,41.869735],"type":"Point"}
}