{
  "type": "Feature",
  "properties": {
    "iso:country":"US",
    "sg:address":"316-130 W Army Trail Rd",
    "sg:city":"Bloomingdale",
    "sg:classifiers":[
        {
            "category":"Shopping",
            "subcategory":"Clothing, Apparel, & Fashions",
            "type":"Retail Goods"
        }
    ],
    "sg:phone":"+1 630 295 8575",
    "sg:postcode":"60117",
    "sg:province":"IL",
    "sg:tags":[
        "children's",
        "clothing"
    ],
    "sg:website":"www.carters.com",
    "wof:name":"Carter's Outlet Store",
    "wof:placetype":"venue"
},
  "geometry": {"coordinates":[-88.10293900000001,41.938967],"type":"Point"}
}