{
  "type": "Feature",
  "properties": {
    "iso:country":"US",
    "sg:address":"900 Lincoln Ave",
    "sg:city":"Charleston",
    "sg:classifiers":[
        {
            "category":"Autos & Motor Vehicles",
            "subcategory":"Fuel & Gas Station",
            "type":"Retail Goods"
        }
    ],
    "sg:phone":"+1   ",
    "sg:postcode":"61920",
    "sg:province":"IL",
    "sg:tags":[
        "grocery",
        "station",
        "gasoline"
    ],
    "wof:name":"Gasland",
    "wof:placetype":"venue"
},
  "geometry": {"coordinates":[-88.172406,39.484378],"type":"Point"}
}