{
  "type": "Feature",
  "properties": {
    "iso:country":"US",
    "sg:address":"724 Sussex Ter",
    "sg:city":"Crete",
    "sg:classifiers":[
        {
            "category":"Shopping",
            "subcategory":"Computers & Home Electronics",
            "type":"Retail Goods"
        }
    ],
    "sg:phone":"+1 708 672 4915",
    "sg:postcode":"60417",
    "sg:province":"IN",
    "sg:tags":[
        "software"
    ],
    "wof:name":"Jtl Systems Inc",
    "wof:placetype":"venue"
},
  "geometry": {"coordinates":[-87.59574000000001,41.460159],"type":"Point"}
}