{
  "type": "Feature",
  "properties": {
    "addr:full":"2831 N Lowell Ave Chicago IL 60641",
    "addr:housenumber":"2831",
    "addr:postcode":"60641",
    "addr:street":"N Lowell Ave",
    "iso:country":"US",
    "sg:address":"2831 N Lowell Ave",
    "sg:city":"Chicago",
    "sg:classifiers":[
        {
            "category":"Retail",
            "subcategory":"Laundry & Dry Cleaning",
            "type":"Services"
        }
    ],
    "sg:phone":"+1 773 282 3768",
    "sg:postcode":"60641",
    "sg:province":"IL",
    "sg:tags":[
        "garment",
        "agent"
    ],
    "wof:name":"Elizabeth A McIntyre",
    "wof:placetype":"venue"
},
  "geometry": {"coordinates":[-87.735551,41.933409],"type":"Point"}
}