{
  "type": "Feature",
  "properties": {
    "addr:full":"31612 S Rathje Rd Peotone IL 60468",
    "addr:housenumber":"31612",
    "addr:postcode":"60468",
    "addr:street":"S Rathje Rd",
    "iso:country":"US",
    "sg:address":"31612 S Rathje Rd",
    "sg:city":"Peotone",
    "sg:classifiers":[
        {
            "category":"Retail",
            "subcategory":"Auto Repair",
            "type":"Services"
        }
    ],
    "sg:phone":"+1 708 258 6818",
    "sg:postcode":"60468",
    "sg:province":"IL",
    "sg:tags":[
        "general"
    ],
    "wof:name":"Garys Garage",
    "wof:placetype":"venue"
},
  "geometry": {"coordinates":[-87.80441399999999,41.315831],"type":"Point"}
}