{
  "type": "Feature",
  "properties": {
    "iso:country":"US",
    "sg:address":"104 Maple St",
    "sg:city":"Ferris",
    "sg:classifiers":[
        {
            "category":"Home & Garden",
            "subcategory":"Garden Supply",
            "type":"Retail Goods"
        }
    ],
    "sg:phone":"+1 217 746 2431",
    "sg:postcode":"62336",
    "sg:province":"IL",
    "sg:tags":[
        "engine"
    ],
    "wof:name":"Burnside Garage",
    "wof:placetype":"venue"
},
  "geometry": {"coordinates":[-91.16874300000001,40.465317],"type":"Point"}
}