{
  "type": "Feature",
  "properties": {
    "iso:country":"US",
    "sg:address":"1800 W Lake St",
    "sg:city":"Melrose Park",
    "sg:classifiers":[
        {
            "category":"Health Services",
            "subcategory":"Dentist",
            "type":"Services"
        }
    ],
    "sg:phone":"+1 708 345 5505",
    "sg:postcode":"60160",
    "sg:province":"IL",
    "wof:name":"Looby Terrence P DDS",
    "wof:placetype":"venue"
},
  "geometry": {"coordinates":[-87.85534699999999,41.893026],"type":"Point"}
}