{
  "type": "Feature",
  "properties": {
    "iso:country":"US",
    "sg:address":"319 Wilson Ave",
    "sg:city":"West Chicago",
    "sg:classifiers":[
        {
            "category":"Retail",
            "subcategory":"Auto Repair",
            "type":"Services"
        }
    ],
    "sg:phone":"+1 630 293 7750",
    "sg:postcode":"60185",
    "sg:province":"IL",
    "sg:tags":[
        "body",
        "shop"
    ],
    "wof:name":"Deluxe Auto Werks",
    "wof:placetype":"venue"
},
  "geometry": {"coordinates":[-88.200996,41.879501],"type":"Point"}
}