{
  "type": "Feature",
  "properties": {
    "addr:full":"1119 S 7th St Quincy IL 62301",
    "addr:housenumber":"1119",
    "addr:postcode":"62301",
    "addr:street":"S 7Th St",
    "iso:country":"US",
    "sg:address":"1119 S 7th St",
    "sg:city":"Quincy",
    "sg:classifiers":[
        {
            "category":"Organizations",
            "subcategory":"Religious Organization",
            "type":"Services"
        }
    ],
    "sg:phone":"+1 217 222 2759",
    "sg:postcode":"62301",
    "sg:province":"IL",
    "wof:name":"St Marys Rectory",
    "wof:placetype":"venue"
},
  "geometry": {"coordinates":[-91.404568,39.918292],"type":"Point"}
}