{
  "type": "Feature",
  "properties": {
    "iso:country":"US",
    "sg:address":"801 N Central Ave",
    "sg:city":"Wood Dale",
    "sg:classifiers":[
        {
            "category":"Retail",
            "subcategory":"Auto Repair",
            "type":"Services"
        }
    ],
    "sg:phone":"+1 630 350 7776",
    "sg:postcode":"60191",
    "sg:province":"IL",
    "sg:tags":[
        "transmission"
    ],
    "wof:name":"Finish Line Transmission Inc",
    "wof:placetype":"venue"
},
  "geometry": {"coordinates":[-87.972884,41.979653],"type":"Point"}
}