{
  "type": "Feature",
  "properties": {
    "iso:country":"US",
    "sg:address":"4726 W Race Ave",
    "sg:city":"Chicago",
    "sg:classifiers":[
        {
            "category":"Social Services",
            "type":"Services"
        }
    ],
    "sg:phone":"+1 773 887 4418",
    "sg:postcode":"60644",
    "sg:province":"IL",
    "sg:tags":[
        "human"
    ],
    "wof:name":"Young Creative Minds",
    "wof:placetype":"venue"
},
  "geometry": {"coordinates":[-87.74382799999999,41.890477],"type":"Point"}
}