{
  "type": "Feature",
  "properties": {
    "addr:full":"2560 E 1251st Rd Ottawa IL 61350",
    "addr:housenumber":"2560",
    "addr:postcode":"61350",
    "addr:street":"E 1251St Rd",
    "iso:country":"US",
    "sg:address":"2560 E 1251st Rd",
    "sg:city":"Ottawa",
    "sg:classifiers":[
        {
            "category":"Recreation",
            "type":"Entertainment"
        }
    ],
    "sg:phone":"+1 815 434 0518",
    "sg:postcode":"61350",
    "sg:province":"IL",
    "sg:tags":[
        "parks"
    ],
    "wof:name":"Catlin Park",
    "wof:placetype":"venue"
},
  "geometry": {"coordinates":[-88.91368300000001,41.316272],"type":"Point"}
}