{
  "type": "Feature",
  "properties": {
    "iso:country":"US",
    "sg:address":"695 Church Rd",
    "sg:city":"Elgin",
    "sg:classifiers":[
        {
            "category":"Building & Trades",
            "subcategory":"Construction",
            "type":"Services"
        }
    ],
    "sg:phone":"+1 847 214 9500",
    "sg:postcode":"60123",
    "sg:province":"IL",
    "sg:tags":[
        "pavement",
        "marking",
        "contractor"
    ],
    "wof:name":"A C Pavement Striping Co",
    "wof:placetype":"venue"
},
  "geometry": {"coordinates":[-88.294758,42.073285],"type":"Point"}
}