{
  "type": "Feature",
  "properties": {
    "iso:country":"US",
    "sg:address":"339 E Chicago Ave",
    "sg:city":"Chicago",
    "sg:classifiers":[
        {
            "category":"Education",
            "subcategory":"University",
            "type":"Public Place"
        }
    ],
    "sg:phone":"+1 312 503 6950",
    "sg:postcode":"60611",
    "sg:province":"IL",
    "sg:tags":[
        "college"
    ],
    "wof:name":"Northwestern School of Continuing Studies",
    "wof:placetype":"venue"
},
  "geometry": {"coordinates":[-87.619102,41.8969],"type":"Point"}
}