{
  "type": "Feature",
  "properties": {
    "addr:full":"1115 W Berwyn Ave Chicago IL 60640",
    "addr:housenumber":"1115",
    "addr:postcode":"60640",
    "addr:street":"W Berwyn Ave",
    "iso:country":"US",
    "sg:address":"1115 W Berwyn Ave",
    "sg:city":"Chicago",
    "sg:classifiers":[
        {
            "category":"Arts & Performance",
            "subcategory":"Arts Center",
            "type":"Entertainment"
        }
    ],
    "sg:phone":"+1 312 458 0722",
    "sg:postcode":"60640",
    "sg:province":"IL",
    "sg:tags":[
        "performing"
    ],
    "sg:website":"www.steeptheatre.com",
    "wof:name":"Steep Theatre Company",
    "wof:placetype":"venue"
},
  "geometry": {"coordinates":[-87.658558,41.97812],"type":"Point"}
}