{
  "type": "Feature",
  "properties": {
    "addr:full":"5799 N Lincoln Avenue Chicago IL 60659",
    "addr:housenumber":"5799",
    "addr:postcode":"60659",
    "addr:street":"N Lincoln Avenue",
    "iso:country":"US",
    "sg:address":"5799 N Lincoln Avenue",
    "sg:city":"Chicago",
    "sg:classifiers":[
        {
            "category":"Personal",
            "type":"Services"
        }
    ],
    "sg:phone":"+1 773 728 6098",
    "sg:postcode":"60659",
    "sg:province":"IL",
    "sg:tags":[
        "sewing",
        "alteration"
    ],
    "sg:website":"www.phenom247.com",
    "wof:name":"England Custom Tailor",
    "wof:placetype":"venue"
},
  "geometry": {"coordinates":[-87.701184,41.987094],"type":"Point"}
}