{
  "type": "Feature",
  "properties": {
    "iso:country":"US",
    "sg:address":"305 W Jackson St",
    "sg:city":"Carbondale",
    "sg:classifiers":[
        {
            "category":"Health Services",
            "subcategory":"Hospital",
            "type":"Services"
        },
        {
            "category":"Health Services",
            "subcategory":"Health Practitioner",
            "type":"Services"
        }
    ],
    "sg:phone":"+1 618 549 0721",
    "sg:postcode":"62901",
    "sg:province":"IL",
    "sg:tags":[
        "therapy",
        "physical"
    ],
    "wof:name":"Fiets Gregory L MD",
    "wof:placetype":"venue"
},
  "geometry": {"coordinates":[-89.218768,37.727938],"type":"Point"}
}