{
  "type": "Feature",
  "properties": {
    "iso:country":"US",
    "sg:address":"4616 W Chicago Ave",
    "sg:city":"Chicago",
    "sg:classifiers":[
        {
            "category":"Autos & Motor Vehicles",
            "subcategory":"Auto Supplies",
            "type":"Retail Goods"
        }
    ],
    "sg:phone":"+1 773 921 8558",
    "sg:postcode":"60651",
    "sg:province":"IL",
    "sg:tags":[
        "grill",
        "guard",
        "bumper",
        "automobile"
    ],
    "wof:name":"General Bumpers",
    "wof:placetype":"venue"
},
  "geometry": {"coordinates":[-87.741372,41.895169],"type":"Point"}
}