{
  "type": "Feature",
  "properties": {
    "iso:country":"US",
    "sg:address":"49 S Waukegan Rd",
    "sg:city":"Deerfield",
    "sg:phone":"+1 847 559 1999",
    "sg:postcode":"60015",
    "sg:province":"IL",
    "sg:website":"http://www.borders.com",
    "wof:name":"Borders",
    "wof:placetype":"venue"
},
  "geometry": {"coordinates":[-87.8351,42.152236],"type":"Point"}
}