{
  "type": "Feature",
  "properties": {
    "addr:full":"2632 W 51st St Chicago IL 60632",
    "addr:housenumber":"2632",
    "addr:postcode":"60632",
    "addr:street":"W 51St St",
    "iso:country":"US",
    "sg:address":"2632 W 51st St",
    "sg:city":"Chicago",
    "sg:classifiers":[
        {
            "category":"Food & Beverages",
            "subcategory":"Groceries & Convenience Stores",
            "type":"Retail Goods"
        }
    ],
    "sg:phone":"+1 773 776 4828",
    "sg:postcode":"60632",
    "sg:province":"IL",
    "wof:name":"La Altena",
    "wof:placetype":"venue"
},
  "geometry": {"coordinates":[-87.69056999999999,41.801315],"type":"Point"}
}