{
  "type": "Feature",
  "properties": {
    "iso:country":"US",
    "sg:address":"732 S Horace Ave",
    "sg:city":"Rockford",
    "sg:classifiers":[
        {
            "category":"Freight",
            "type":"Transportation"
        }
    ],
    "sg:phone":"+1 815 489 9399",
    "sg:postcode":"61102",
    "sg:province":"IL",
    "sg:tags":[
        "commercial",
        "storage"
    ],
    "wof:name":"Security Shop & Storage",
    "wof:placetype":"venue"
},
  "geometry": {"coordinates":[-89.129393,42.26976],"type":"Point"}
}