{
  "type": "Feature",
  "properties": {
    "iso:country":"US",
    "sg:address":"2010 Sheffield Ln",
    "sg:city":"Geneva",
    "sg:classifiers":[
        {
            "category":"Food & Beverages",
            "subcategory":"Groceries & Convenience Stores",
            "type":"Retail Goods"
        }
    ],
    "sg:phone":"+1   ",
    "sg:postcode":"60134",
    "sg:province":"IL",
    "wof:name":"B&V Asian Market Inc",
    "wof:placetype":"venue"
},
  "geometry": {"coordinates":[-88.332466,41.89133],"type":"Point"}
}