{
  "type": "Feature",
  "properties": {
    "iso:country":"US",
    "sg:address":"2401 E Co Rd 650",
    "sg:city":"Carthage",
    "sg:phone":"+1 217 743 5582",
    "sg:postcode":"62321",
    "sg:province":"IL",
    "sg:tags":[
        "farm",
        "grain",
        "cash"
    ],
    "wof:name":"Ray Stuehrenberg",
    "wof:placetype":"venue"
},
  "geometry": {"coordinates":[-91.045282,40.289774],"type":"Point"}
}