{
  "type": "Feature",
  "properties": {
    "iso:country":"US",
    "sg:address":"216 W Lawrence Ave",
    "sg:city":"Springfield",
    "sg:classifiers":[
        {
            "category":"Personal",
            "subcategory":"Massage",
            "type":"Services"
        },
        {
            "category":"Health Services",
            "subcategory":"Clinic",
            "type":"Services"
        },
        {
            "category":"Health Services",
            "subcategory":"Health Practitioner",
            "type":"Services"
        }
    ],
    "sg:phone":"+1 217 415 7970",
    "sg:postcode":"62704",
    "sg:province":"IL",
    "sg:tags":[
        "therapist",
        "therapy",
        "physical"
    ],
    "wof:name":"Bordignon Rita Harmony Center Massage Therapy",
    "wof:placetype":"venue"
},
  "geometry": {"coordinates":[-89.656219,39.793973],"type":"Point"}
}