{
  "type": "Feature",
  "properties": {
    "iso:country":"US",
    "sg:address":"1110 Chestnut St",
    "sg:city":"Waukegan",
    "sg:classifiers":[
        {
            "category":"Education",
            "subcategory":"School",
            "type":"Public Place"
        }
    ],
    "sg:phone":"+1 847 360 5468",
    "sg:postcode":"60085",
    "sg:province":"IL",
    "sg:tags":[
        "elementary"
    ],
    "sg:website":"http://www.wps.lake.k12.il.us",
    "wof:name":"Glen Flora Elementary School",
    "wof:placetype":"venue"
},
  "geometry": {"coordinates":[-87.84072,42.375351],"type":"Point"}
}