{
  "type": "Feature",
  "properties": {
    "addr:full":"3615 W Freund Ave Mc Henry IL 60050",
    "addr:housenumber":"3615",
    "addr:postcode":"60050",
    "addr:street":"W Freund Ave Mc Henry",
    "iso:country":"US",
    "sg:address":"3615 W Freund Ave",
    "sg:city":"Mc Henry",
    "sg:classifiers":[
        {
            "category":"Professional",
            "subcategory":"Computer Services",
            "type":"Services"
        }
    ],
    "sg:phone":"+1 815 385 6530",
    "sg:postcode":"60050",
    "sg:province":"IL",
    "sg:tags":[
        "datum",
        "business"
    ],
    "wof:name":"Gough Impressions",
    "wof:placetype":"venue"
},
  "geometry": {"coordinates":[-88.26964,42.347274],"type":"Point"}
}