{
  "type": "Feature",
  "properties": {
    "addr:full":"2240 W Ogden Avenue Chicago IL 60612",
    "addr:housenumber":"2240",
    "addr:postcode":"60612",
    "addr:street":"W Ogden Avenue",
    "iso:country":"US",
    "sg:address":"2240 W Ogden Avenue",
    "sg:city":"Chicago",
    "sg:classifiers":[
        {
            "category":"Education",
            "subcategory":"University",
            "type":"Public Place"
        }
    ],
    "sg:phone":"+1 312 421 6290",
    "sg:postcode":"60612",
    "sg:province":"IL",
    "sg:tags":[
        "college"
    ],
    "sg:website":"www.uchicago.edu",
    "wof:name":"University of Chicago",
    "wof:placetype":"venue"
},
  "geometry": {"coordinates":[-87.68208300000001,41.868169],"type":"Point"}
}