{
  "type": "Feature",
  "properties": {
    "iso:country":"US",
    "sg:address":"4011 N Ravenswood Ave",
    "sg:city":"Chicago",
    "sg:classifiers":[
        {
            "category":"Retail",
            "subcategory":"Event Space",
            "type":"Services"
        }
    ],
    "sg:phone":"+1 773 388 2170",
    "sg:postcode":"60613",
    "sg:province":"IL",
    "sg:tags":[
        "venue"
    ],
    "sg:website":"www.ravenswoodeventcenter.com",
    "wof:name":"Ravenswood Event Center",
    "wof:placetype":"venue"
},
  "geometry": {"coordinates":[-87.673754,41.954475],"type":"Point"}
}