{
  "type": "Feature",
  "properties": {
    "addr:full":"201 S Althea St Elmwood IL 61529",
    "addr:housenumber":"201",
    "addr:postcode":"61529",
    "addr:street":"S Althea St",
    "iso:country":"US",
    "sg:address":"201 S Althea St",
    "sg:city":"Elmwood",
    "sg:classifiers":[
        {
            "category":"Recreation",
            "type":"Entertainment"
        }
    ],
    "sg:phone":"+1 309 742 8510",
    "sg:postcode":"61529",
    "sg:province":"IL",
    "sg:tags":[
        "center"
    ],
    "wof:name":"Elmwood Community Ctr",
    "wof:placetype":"venue"
},
  "geometry": {"coordinates":[-89.968997,40.776415],"type":"Point"}
}