{
  "type": "Feature",
  "properties": {
    "iso:country":"US",
    "sg:address":"6715 Ogden Ave",
    "sg:city":"Berwyn",
    "sg:classifiers":[
        {
            "category":"Shopping",
            "subcategory":"Tobacco",
            "type":"Retail Goods"
        }
    ],
    "sg:phone":"+1 708 484 1043",
    "sg:postcode":"60402",
    "sg:province":"IL",
    "sg:tags":[
        "venue",
        "product",
        "music"
    ],
    "sg:website":"www.cigarsandstripes.com/index.html",
    "wof:name":"Cigars & Stripes",
    "wof:placetype":"venue"
},
  "geometry": {"coordinates":[-87.790802,41.827599],"type":"Point"}
}