{
  "type": "Feature",
  "properties": {
    "addr:full":"9998 St Clair Ave. Fairview Heights IL 62208",
    "addr:housenumber":"9998",
    "addr:postcode":"62208",
    "addr:street":"St Clair Ave.",
    "iso:country":"US",
    "sg:address":"9998 St Clair Ave.",
    "sg:city":"Fairview Heights",
    "sg:classifiers":[
        {
            "category":"Autos & Motor Vehicles",
            "subcategory":"Auto Supplies",
            "type":"Retail Goods"
        }
    ],
    "sg:phone":"+1 618 744 9771",
    "sg:postcode":"62208",
    "sg:province":"IL",
    "sg:tags":[
        "glass"
    ],
    "sg:website":"www.safelite.com",
    "wof:name":"Safelite AutoGlass",
    "wof:placetype":"venue"
},
  "geometry": {"coordinates":[-90.016397,38.593706],"type":"Point"}
}