{
  "type": "Feature",
  "properties": {
    "iso:country":"US",
    "sg:address":"876 Geneva Dr",
    "sg:city":"Geneva",
    "sg:classifiers":[
        {
            "category":"Professional",
            "subcategory":"Business Services",
            "type":"Services"
        }
    ],
    "sg:phone":"+1 630 208 7136",
    "sg:postcode":"60134",
    "sg:province":"IL",
    "wof:name":"Piper Sales Group Inc",
    "wof:placetype":"venue"
},
  "geometry": {"coordinates":[-88.287694,41.894236],"type":"Point"}
}