{
  "type": "Feature",
  "properties": {
    "addr:full":"3720 N Broadway St Chicago IL 60613",
    "addr:housenumber":"3720",
    "addr:postcode":"60613",
    "addr:street":"N Broadway St",
    "iso:country":"US",
    "sg:address":"3720 N Broadway St",
    "sg:city":"Chicago",
    "sg:classifiers":[
        {
            "category":"Farming",
            "subcategory":"Fish & Marine Products",
            "type":"Manufacturing & Wholesale Goods"
        },
        {
            "category":"Retail",
            "subcategory":"Repair Shop",
            "type":"Services"
        },
        {
            "category":"Professional",
            "subcategory":"Art Services",
            "type":"Services"
        },
        {
            "category":"Manufacturing",
            "subcategory":"Wood Products",
            "type":"Manufacturing & Wholesale Goods"
        }
    ],
    "sg:phone":"+1 773 935 3278",
    "sg:postcode":"60613",
    "sg:province":"IL",
    "sg:tags":[
        "picture",
        "frames-wholesale",
        "frame",
        "restoration",
        "framing",
        "manufacturer"
    ],
    "sg:website":"http://www.fastframe.com",
    "wof:name":"Fastframe",
    "wof:placetype":"venue"
},
  "geometry": {"coordinates":[-87.64858700000001,41.949549],"type":"Point"}
}