{
  "type": "Feature",
  "properties": {
    "iso:country":"US",
    "sg:address":"334 Washington St",
    "sg:city":"Prophetstown",
    "sg:classifiers":[
        {
            "category":"Shopping",
            "subcategory":"Hobbies, Toys, & Games",
            "type":"Retail Goods"
        },
        {
            "category":"Shopping",
            "subcategory":"Gifts & Souvenirs",
            "type":"Retail Goods"
        }
    ],
    "sg:phone":"+1 815 537 5589",
    "sg:postcode":"61277",
    "sg:province":"IL",
    "sg:tags":[
        "equipment",
        "ceramic",
        "supply"
    ],
    "wof:name":"Ceramics Center",
    "wof:placetype":"venue"
},
  "geometry": {"coordinates":[-89.93638900000001,41.670289],"type":"Point"}
}