{
  "type": "Feature",
  "properties": {
    "iso:country":"US",
    "sg:address":"421 Blackhawk Dr",
    "sg:city":"Batavia",
    "sg:classifiers":[
        {
            "category":"Wholesale",
            "subcategory":"Durable Goods & Equipment",
            "type":"Manufacturing & Wholesale Goods"
        }
    ],
    "sg:phone":"+1 630 879 0938",
    "sg:postcode":"60510",
    "sg:province":"IL",
    "wof:name":"Chem Plus Inc",
    "wof:placetype":"venue"
},
  "geometry": {"coordinates":[-88.327967,41.857148],"type":"Point"}
}