{
  "type": "Feature",
  "properties": {
    "iso:country":"US",
    "sg:address":"10455 S Ewing Ave",
    "sg:city":"Chicago",
    "sg:classifiers":[
        {
            "category":"Social Services",
            "type":"Services"
        }
    ],
    "sg:phone":"+1 773 978 8725",
    "sg:postcode":"60617",
    "sg:province":"IL",
    "sg:tags":[
        "human"
    ],
    "wof:name":"La Flor Social Services, Inc.",
    "wof:placetype":"venue"
},
  "geometry": {"coordinates":[-87.535263,41.705431],"type":"Point"}
}