{
  "type": "Feature",
  "properties": {
    "iso:country":"US",
    "sg:address":"300 E Pleasant St",
    "sg:city":"Bunker Hill",
    "sg:classifiers":[
        {
            "category":"Government",
            "subcategory":"Office",
            "type":"Public Place"
        }
    ],
    "sg:phone":"+1   ",
    "sg:postcode":"62014",
    "sg:province":"IL",
    "sg:tags":[
        "executive"
    ],
    "wof:name":"Bunker Hill Township",
    "wof:placetype":"venue"
},
  "geometry": {"coordinates":[-89.950598,39.048486],"type":"Point"}
}