{
  "type": "Feature",
  "properties": {
    "addr:full":"6210 S Archer Rd Summit Argo IL 60501",
    "addr:housenumber":"6210",
    "addr:postcode":"60501",
    "addr:street":"S Archer Rd",
    "iso:country":"US",
    "sg:address":"6210 S Archer Rd",
    "sg:city":"Summit Argo",
    "sg:classifiers":[
        {
            "category":"Autos & Motor Vehicles",
            "subcategory":"Automobile Sales",
            "type":"Retail Goods"
        }
    ],
    "sg:phone":"+1 708 458 7668",
    "sg:postcode":"60501",
    "sg:province":"IL",
    "sg:tags":[
        "car"
    ],
    "wof:name":"Hathaway Geo H Coffee Co",
    "wof:placetype":"venue"
},
  "geometry": {"coordinates":[-87.81349899999999,41.7784],"type":"Point"}
}