{
  "type": "Feature",
  "properties": {
    "iso:country":"US",
    "sg:address":"3357 N Harlem Ave",
    "sg:city":"Chicago",
    "sg:classifiers":[
        {
            "category":"Airline",
            "type":"Transportation"
        }
    ],
    "sg:phone":"+1 773 777 7733",
    "sg:postcode":"60634",
    "sg:province":"IL",
    "sg:tags":[
        "shuttle",
        "airport"
    ],
    "wof:name":"Rek 5",
    "wof:placetype":"venue"
},
  "geometry": {"coordinates":[-87.8069,41.9412],"type":"Point"}
}