{
  "type": "Feature",
  "properties": {
    "addr:full":"211 19th St Rock Island IL 61201",
    "addr:housenumber":"211",
    "addr:postcode":"61201",
    "addr:street":"19Th St",
    "iso:country":"US",
    "sg:address":"211 19th St",
    "sg:city":"Rock Island",
    "sg:classifiers":[
        {
            "category":"Government",
            "subcategory":"Court House",
            "type":"Public Place"
        }
    ],
    "sg:phone":"+1 309 793 5798",
    "sg:postcode":"61201",
    "sg:province":"IL",
    "sg:tags":[
        "federal",
        "counsel"
    ],
    "wof:name":"US Attorney",
    "wof:placetype":"venue"
},
  "geometry": {"coordinates":[-90.573155,41.510043],"type":"Point"}
}