{
  "type": "Feature",
  "properties": {
    "iso:country":"US",
    "sg:address":"210 W Church St",
    "sg:city":"Champaign",
    "sg:classifiers":[
        {
            "category":"Social Services",
            "subcategory":"Child Care",
            "type":"Services"
        },
        {
            "category":"Education",
            "subcategory":"Preschool",
            "type":"Public Place"
        },
        {
            "category":"Education",
            "subcategory":"School",
            "type":"Public Place"
        }
    ],
    "sg:phone":"+1 217 356 1247",
    "sg:postcode":"61820",
    "sg:province":"IL",
    "sg:tags":[
        "elementary",
        "day"
    ],
    "wof:name":"First United Methodist Child Care Center",
    "wof:placetype":"venue"
},
  "geometry": {"coordinates":[-88.2453,40.118301],"type":"Point"}
}