{
  "type": "Feature",
  "properties": {
    "iso:country":"US",
    "sg:address":"2505 N Willow Rd",
    "sg:city":"Urbana",
    "sg:classifiers":[
        {
            "category":"Building & Trades",
            "subcategory":"Equipment Rental",
            "type":"Services"
        }
    ],
    "sg:phone":"+1 217 344 3850",
    "sg:postcode":"61802",
    "sg:province":"IL",
    "sg:tags":[
        "yard",
        "leasing",
        "store"
    ],
    "wof:name":"Jesse L Clark Rentals",
    "wof:placetype":"venue"
},
  "geometry": {"coordinates":[-88.200791,40.138371],"type":"Point"}
}