{
  "type": "Feature",
  "properties": {
    "addr:full":"25104 Blackthorne Rd Manhattan IL 60442",
    "addr:housenumber":"25104",
    "addr:postcode":"60442",
    "addr:street":"Blackthorne Rd",
    "iso:country":"US",
    "sg:address":"25104 Blackthorne Rd",
    "sg:city":"Manhattan",
    "sg:classifiers":[
        {
            "category":"Professional",
            "subcategory":"Computer Services",
            "type":"Services"
        }
    ],
    "sg:phone":"+1 815 478 3250",
    "sg:postcode":"60442",
    "sg:province":"IL",
    "sg:tags":[
        "related"
    ],
    "wof:name":"J R B Consulting",
    "wof:placetype":"venue"
},
  "geometry": {"coordinates":[-87.990453,41.432351],"type":"Point"}
}