{
  "type": "Feature",
  "properties": {
    "iso:country":"US",
    "sg:address":"21 N 3rd St",
    "sg:city":"Geneva",
    "sg:classifiers":[
        {
            "category":"Insurance",
            "subcategory":"Insurance Agent",
            "type":"Services"
        }
    ],
    "sg:phone":"+1 630 262 3859",
    "sg:postcode":"60134",
    "sg:province":"IL",
    "wof:name":"Franklin Life",
    "wof:placetype":"venue"
},
  "geometry": {"coordinates":[-88.307723,41.888779],"type":"Point"}
}