{
  "type": "Feature",
  "properties": {
    "iso:country":"US",
    "sg:address":"4761 Bluestem Rd",
    "sg:city":"Roscoe",
    "sg:classifiers":[
        {
            "category":"Freight",
            "type":"Transportation"
        }
    ],
    "sg:phone":"+1 815 623 7770",
    "sg:postcode":"61073",
    "sg:province":"IL",
    "sg:tags":[
        "commercial",
        "storage"
    ],
    "wof:name":"Roscoe Mini Storage",
    "wof:placetype":"venue"
},
  "geometry": {"coordinates":[-89.025014,42.434343],"type":"Point"}
}