{
  "type": "Feature",
  "properties": {
    "addr:full":"7735 Joliet Dr S Tinley Park IL 60477",
    "addr:housenumber":"7735",
    "addr:postcode":"60477",
    "addr:street":"Joliet Dr S;Park",
    "iso:country":"US",
    "sg:address":"7735 Joliet Dr S",
    "sg:city":"Tinley Park",
    "sg:classifiers":[
        {
            "category":"Real Estate",
            "subcategory":"Real Estate Agent",
            "type":"Services"
        }
    ],
    "sg:phone":"+1 708 444 4024",
    "sg:postcode":"60477",
    "sg:province":"IL",
    "wof:name":"Janed Corporation",
    "wof:placetype":"venue"
},
  "geometry": {"coordinates":[-87.806551,41.570401],"type":"Point"}
}