{
  "type": "Feature",
  "properties": {
    "iso:country":"US",
    "sg:address":"7734 S Cottage Grove Ave",
    "sg:city":"Chicago",
    "sg:classifiers":[
        {
            "category":"Home & Garden",
            "subcategory":"Furniture",
            "type":"Retail Goods"
        }
    ],
    "sg:phone":"+1 773 994 4900",
    "sg:postcode":"60619",
    "sg:province":"IL",
    "sg:tags":[
        "store"
    ],
    "wof:name":"Mose's New & Used Furniture",
    "wof:placetype":"venue"
},
  "geometry": {"coordinates":[-87.6054,41.7537],"type":"Point"}
}