{
  "type": "Feature",
  "properties": {
    "iso:country":"US",
    "sg:address":"3340 Oak Park Ave",
    "sg:city":"Berwyn",
    "sg:classifiers":[
        {
            "category":"Health Services",
            "subcategory":"Doctor",
            "type":"Services"
        }
    ],
    "sg:phone":"+1 708 783 0300",
    "sg:postcode":"60402",
    "sg:province":"IL",
    "sg:tags":[
        "physician",
        "oncology",
        "surgeons",
        "surgeon",
        "gynecologic"
    ],
    "wof:name":"Mac Neal Cancer Center",
    "wof:placetype":"venue"
},
  "geometry": {"coordinates":[-87.792754,41.831301],"type":"Point"}
}