{
  "type": "Feature",
  "properties": {
    "addr:full":"1110 S Water St Havana IL 62644",
    "addr:housenumber":"1110",
    "addr:postcode":"62644",
    "addr:street":"S Water St",
    "iso:country":"US",
    "sg:address":"1110 S Water St",
    "sg:city":"Havana",
    "sg:classifiers":[
        {
            "category":"Restaurant",
            "type":"Food & Drink"
        }
    ],
    "sg:phone":"+1 309 543 3598",
    "sg:postcode":"62644",
    "sg:province":"IL",
    "wof:name":"Kracker's Korner",
    "wof:placetype":"venue"
},
  "geometry": {"coordinates":[-90.06925099999999,40.28794],"type":"Point"}
}