{
  "type": "Feature",
  "properties": {
    "iso:country":"US",
    "sg:address":"208 State St",
    "sg:city":"Alton",
    "sg:classifiers":[
        {
            "category":"Restaurant",
            "type":"Food & Drink"
        }
    ],
    "sg:phone":"+1 618 465 4605",
    "sg:postcode":"62002",
    "sg:province":"IL",
    "sg:tags":[
        "seafood",
        "american"
    ],
    "wof:name":"Seafood Escape",
    "wof:placetype":"venue"
},
  "geometry": {"coordinates":[-90.188534,38.890775],"type":"Point"}
}