{
  "type": "Feature",
  "properties": {
    "iso:country":"US",
    "sg:address":"9 W Golf Rd",
    "sg:city":"Schaumburg",
    "sg:classifiers":[
        {
            "category":"Personal",
            "subcategory":"Beauty Salon",
            "type":"Services"
        }
    ],
    "sg:phone":"+1 847 519 7743",
    "sg:postcode":"60195",
    "sg:province":"IL",
    "sg:tags":[
        "hair"
    ],
    "wof:name":"Creative Hairdressers",
    "wof:placetype":"venue"
},
  "geometry": {"coordinates":[-88.083005,42.049369],"type":"Point"}
}