{
  "type": "Feature",
  "properties": {
    "iso:country":"US",
    "sg:address":"6463 N Northwest Hwy",
    "sg:city":"Chicago",
    "sg:classifiers":[
        {
            "category":"Real Estate",
            "subcategory":"Real Estate Operator",
            "type":"Services"
        }
    ],
    "sg:phone":"+1 773 467 0807",
    "sg:postcode":"60631",
    "sg:province":"IL",
    "sg:tags":[
        "apartment"
    ],
    "wof:name":"V Nm Llc Designated Series F",
    "wof:placetype":"venue"
},
  "geometry": {"coordinates":[-87.808455,41.998187],"type":"Point"}
}