{
  "type": "Feature",
  "properties": {
    "iso:country":"US",
    "sg:address":"1081 W Broadway",
    "sg:city":"Centralia",
    "sg:classifiers":[
        {
            "category":"Building & Trades",
            "subcategory":"Equipment Rental",
            "type":"Services"
        }
    ],
    "sg:phone":"+1 618 532 3066",
    "sg:postcode":"62801",
    "sg:province":"IL",
    "sg:tags":[
        "leasing",
        "furniture"
    ],
    "wof:name":"Rent-A-Center",
    "wof:placetype":"venue"
},
  "geometry": {"coordinates":[-89.14883500000001,38.529525],"type":"Point"}
}