{
  "type": "Feature",
  "properties": {
    "addr:full":"115 New Castle Ct Rolling Meadows IL 60008",
    "addr:housenumber":"115",
    "addr:postcode":"60008",
    "addr:street":"New Castle Ct",
    "iso:country":"US",
    "sg:address":"115 New Castle Ct",
    "sg:city":"Rolling Meadows",
    "sg:classifiers":[
        {
            "category":"Professional",
            "subcategory":"Business Services",
            "type":"Services"
        }
    ],
    "sg:phone":"+1 716 626 7212",
    "sg:postcode":"60008",
    "sg:province":"IL",
    "wof:name":"Medical Connection",
    "wof:placetype":"venue"
},
  "geometry": {"coordinates":[-88.048811,42.082895],"type":"Point"}
}