{
  "type": "Feature",
  "properties": {
    "iso:country":"US",
    "sg:address":"2301 29th St",
    "sg:city":"Moline",
    "sg:classifiers":[
        {
            "category":"Shopping",
            "subcategory":"Jewelry",
            "type":"Retail Goods"
        }
    ],
    "sg:phone":"+1 309 797 6145",
    "sg:postcode":"61265",
    "sg:province":"IL",
    "wof:name":"Diamonds On The Avenue",
    "wof:placetype":"venue"
},
  "geometry": {"coordinates":[-90.4966,41.48925],"type":"Point"}
}