{
  "type": "Feature",
  "properties": {
    "iso:country":"US",
    "sg:address":"12355 E County Road 210N",
    "sg:city":"Lerna",
    "sg:classifiers":[
        {
            "category":"Manufacturing",
            "subcategory":"Food",
            "type":"Manufacturing & Wholesale Goods"
        },
        {
            "category":"Farming",
            "subcategory":"Farm",
            "type":"Manufacturing & Wholesale Goods"
        }
    ],
    "sg:phone":"+1 217 345 2980",
    "sg:postcode":"62440",
    "sg:province":"IL",
    "sg:tags":[
        "corn",
        "product"
    ],
    "sg:website":"http://www.atwells.com",
    "wof:name":"Atwell Farms",
    "wof:placetype":"venue"
},
  "geometry": {"coordinates":[-88.24425599999999,39.405021],"type":"Point"}
}