{
  "type": "Feature",
  "properties": {
    "addr:full":"340 Burlington Ave Downers Grove IL 60515",
    "addr:housenumber":"340",
    "addr:postcode":"60515",
    "addr:street":"Burlington Ave",
    "iso:country":"US",
    "sg:address":"340 Burlington Ave",
    "sg:city":"Downers Grove",
    "sg:classifiers":[
        {
            "category":"Real Estate",
            "subcategory":"Real Estate Agent",
            "type":"Services"
        }
    ],
    "sg:phone":"+1 630 960 1881",
    "sg:postcode":"60515",
    "sg:province":"IL",
    "wof:name":"First Signature Homes",
    "wof:placetype":"venue"
},
  "geometry": {"coordinates":[-87.994536,41.79584],"type":"Point"}
}