{
  "type": "Feature",
  "properties": {
    "iso:country":"US",
    "sg:address":"200 N Central Ave",
    "sg:city":"Roxana",
    "sg:classifiers":[
        {
            "category":"Education",
            "subcategory":"Library",
            "type":"Public Place"
        }
    ],
    "sg:phone":"+1   ",
    "sg:postcode":"62084",
    "sg:province":"IL",
    "sg:tags":[
        "executive"
    ],
    "sg:website":"www.roxanalibrary.org",
    "wof:name":"Roxana Public Library",
    "wof:placetype":"venue"
},
  "geometry": {"coordinates":[-90.079005,38.850964],"type":"Point"}
}