{
  "type": "Feature",
  "properties": {
    "iso:country":"US",
    "sg:address":"920 Roosevelt Rd",
    "sg:city":"Glen Ellyn",
    "sg:classifiers":[
        {
            "category":"Shopping",
            "subcategory":"Tobacco",
            "type":"Retail Goods"
        }
    ],
    "sg:phone":"+1 630 942 9297",
    "sg:postcode":"60137",
    "sg:province":"IL",
    "sg:tags":[
        "shop"
    ],
    "wof:name":"Tobacco Outlet",
    "wof:placetype":"venue"
},
  "geometry": {"coordinates":[-88.045799,41.859402],"type":"Point"}
}