{
  "type": "Feature",
  "properties": {
    "iso:country":"US",
    "sg:address":"1231 S Walnut Ave",
    "sg:city":"Freeport",
    "sg:classifiers":[
        {
            "category":"Social Services",
            "type":"Services"
        }
    ],
    "sg:phone":"+1 815 235 9563",
    "sg:postcode":"61032",
    "sg:province":"IL",
    "wof:name":"Catholic Charities",
    "wof:placetype":"venue"
},
  "geometry": {"coordinates":[-89.621177,42.288126],"type":"Point"}
}