{
  "type": "Feature",
  "properties": {
    "iso:country":"US",
    "sg:address":"7051 S Oglesby Ave",
    "sg:city":"Chicago",
    "sg:classifiers":[
        {
            "category":"Real Estate",
            "subcategory":"Real Estate Agent",
            "type":"Services"
        }
    ],
    "sg:phone":"+1 773 955 9366",
    "sg:postcode":"60649",
    "sg:province":"IL",
    "wof:name":"Godwin & Godwin Inc",
    "wof:placetype":"venue"
},
  "geometry": {"coordinates":[-87.568092,41.766982],"type":"Point"}
}