{
  "type": "Feature",
  "properties": {
    "iso:country":"US",
    "sg:address":"922 W Roosevelt Road",
    "sg:city":"Chicago",
    "sg:classifiers":[
        {
            "category":"Restaurant",
            "type":"Food & Drink"
        }
    ],
    "sg:phone":"+1 630 231 9393",
    "sg:postcode":"60608",
    "sg:province":"IL",
    "sg:tags":[
        "pizza",
        "italian"
    ],
    "wof:name":"Pal Joey's Restaurant & Lounge",
    "wof:placetype":"venue"
},
  "geometry": {"coordinates":[-87.649478,41.867162],"type":"Point"}
}