{
  "type": "Feature",
  "properties": {
    "iso:country":"US",
    "sg:address":"13408 Michael Rd",
    "sg:city":"Highland",
    "sg:classifiers":[
        {
            "category":"Freight",
            "type":"Transportation"
        },
        {
            "category":"Bus Charters",
            "type":"Transportation"
        }
    ],
    "sg:phone":"+1 618 654 3368",
    "sg:postcode":"62249",
    "sg:province":"IL",
    "sg:tags":[
        "buses-charter",
        "rental",
        "trucking"
    ],
    "wof:name":"Zobrist Bus Lines, Inc",
    "wof:placetype":"venue"
},
  "geometry": {"coordinates":[-89.643431,38.742706],"type":"Point"}
}