{
  "type": "Feature",
  "properties": {
    "iso:country":"US",
    "sg:address":"225 W Main St",
    "sg:city":"Staunton",
    "sg:classifiers":[
        {
            "category":"Insurance",
            "subcategory":"Hazard Insurance",
            "type":"Services"
        },
        {
            "category":"Banks & Credit Unions",
            "subcategory":"Investment Brokerage",
            "type":"Services"
        },
        {
            "category":"Insurance",
            "subcategory":"Life Insurance",
            "type":"Services"
        },
        {
            "category":"Banks & Credit Unions",
            "subcategory":"Financial Services",
            "type":"Services"
        }
    ],
    "sg:phone":"+1 618 635 8249",
    "sg:postcode":"62088",
    "sg:province":"IL",
    "sg:website":"http://stlouis.citysearch.com/profile/external/35358388/staunton_il/country_financial.html?publisher=yellowpages&reference_id=1&placement=ypwebsitemip",
    "wof:name":"COUNTRY FINANCIAL",
    "wof:placetype":"venue"
},
  "geometry": {"coordinates":[-89.78794000000001,39.012103],"type":"Point"}
}