{
  "type": "Feature",
  "properties": {
    "addr:full":"2451 S Ashland Ave Chicago IL 60608",
    "addr:housenumber":"2451",
    "addr:postcode":"60608",
    "addr:street":"S Ashland Ave",
    "iso:country":"US",
    "sg:address":"2451 S Ashland Ave",
    "sg:city":"Chicago",
    "sg:classifiers":[
        {
            "category":"Government",
            "subcategory":"Office",
            "type":"Public Place"
        }
    ],
    "sg:phone":"+1 312 746 4400",
    "sg:postcode":"60608",
    "sg:province":"IL",
    "sg:website":"http://www.ci.chi.il.us",
    "wof:name":"Streets And Sanitation, Dept",
    "wof:placetype":"venue"
},
  "geometry": {"coordinates":[-87.66595599999999,41.848576],"type":"Point"}
}