{
  "type": "Feature",
  "properties": {
    "iso:country":"US",
    "sg:address":"3310 E 5000N Rd",
    "sg:city":"Bourbonnais",
    "sg:phone":"+1 815 932 9687",
    "sg:postcode":"60914",
    "sg:province":"IL",
    "sg:tags":[
        "farm",
        "corn",
        "soybean"
    ],
    "wof:name":"Jay Raymond",
    "wof:placetype":"venue"
},
  "geometry": {"coordinates":[-87.804564,41.192018],"type":"Point"}
}