{
  "type": "Feature",
  "properties": {
    "addr:full":"575 Newcastle Dr Lake Forest IL 60045",
    "addr:housenumber":"575",
    "addr:postcode":"60045",
    "addr:street":"Newcastle Dr",
    "iso:country":"US",
    "sg:address":"575 Newcastle Dr",
    "sg:city":"Lake Forest",
    "sg:classifiers":[
        {
            "category":"Building & Trades",
            "subcategory":"Construction",
            "type":"Services"
        }
    ],
    "sg:phone":"+1 847 295 3770",
    "sg:postcode":"60045",
    "sg:province":"IL",
    "sg:tags":[
        "home",
        "general",
        "contractor"
    ],
    "wof:name":"Howard Elies Builders Inc",
    "wof:placetype":"venue"
},
  "geometry": {"coordinates":[-87.86886699999999,42.229546],"type":"Point"}
}