{
  "type": "Feature",
  "properties": {
    "iso:country":"US",
    "sg:address":"15412 Park Ave",
    "sg:city":"Harvey",
    "sg:classifiers":[
        {
            "category":"Retail",
            "subcategory":"Auto Repair",
            "type":"Services"
        }
    ],
    "sg:phone":"+1 708 331 4855",
    "sg:postcode":"60426",
    "sg:province":"IL",
    "sg:tags":[
        "body",
        "shop"
    ],
    "wof:name":"Parkway Auto Rebuilders",
    "wof:placetype":"venue"
},
  "geometry": {"coordinates":[-87.643997,41.6087],"type":"Point"}
}