{
  "type": "Feature",
  "properties": {
    "iso:country":"US",
    "sg:address":"4750 Main St",
    "sg:city":"Lisle",
    "sg:classifiers":[
        {
            "category":"Food & Beverages",
            "subcategory":"Bakery",
            "type":"Retail Goods"
        }
    ],
    "sg:phone":"+1   ",
    "sg:postcode":"60532",
    "sg:province":"IL",
    "wof:name":"Lindstroms Bakery",
    "wof:placetype":"venue"
},
  "geometry": {"coordinates":[-88.074625,41.798627],"type":"Point"}
}