{
  "type": "Feature",
  "properties": {
    "addr:full":"24059 S Municipal Dr Channahon IL 60410",
    "addr:housenumber":"24059",
    "addr:postcode":"60410",
    "addr:street":"S Municipal Dr",
    "iso:country":"US",
    "sg:address":"24059 S Municipal Dr",
    "sg:city":"Channahon",
    "sg:classifiers":[
        {
            "category":"Autos & Motor Vehicles",
            "subcategory":"Auto Supplies",
            "type":"Retail Goods"
        }
    ],
    "sg:phone":"+1 815 467 1275",
    "sg:postcode":"60410",
    "sg:province":"IL",
    "sg:tags":[
        "tire"
    ],
    "wof:name":"Lucenta Tire",
    "wof:placetype":"venue"
},
  "geometry": {"coordinates":[-88.204803,41.446499],"type":"Point"}
}