{
  "type": "Feature",
  "properties": {
    "iso:country":"US",
    "sg:address":"912 S Plum Grove Rd",
    "sg:city":"Palatine",
    "sg:classifiers":[
        {
            "category":"Building & Trades",
            "subcategory":"Construction",
            "type":"Services"
        }
    ],
    "sg:phone":"+1 847 705 1926",
    "sg:postcode":"60067",
    "sg:province":"IL",
    "sg:tags":[
        "house"
    ],
    "wof:name":"Beneficial Construction Inc",
    "wof:placetype":"venue"
},
  "geometry": {"coordinates":[-88.04387800000001,42.093776],"type":"Point"}
}