{
  "type": "Feature",
  "properties": {
    "iso:country":"US",
    "sg:address":"2264 Cottonwood Dr",
    "sg:city":"Elgin",
    "sg:classifiers":[
        {
            "category":"Communications",
            "subcategory":"Film & Video Production",
            "type":"Services"
        }
    ],
    "sg:phone":"+1 847 429 9242",
    "sg:postcode":"60123",
    "sg:province":"IL",
    "sg:tags":[
        "duplication",
        "tape"
    ],
    "wof:name":"Jiffy Video Tape Svc",
    "wof:placetype":"venue"
},
  "geometry": {"coordinates":[-88.329168,41.996937],"type":"Point"}
}