{
  "type": "Feature",
  "properties": {
    "addr:full":"128 Newberry Ave Libertyville IL 60048",
    "addr:housenumber":"128",
    "addr:postcode":"60048",
    "addr:street":"Newberry Ave",
    "iso:country":"US",
    "sg:address":"128 Newberry Ave",
    "sg:city":"Libertyville",
    "sg:classifiers":[
        {
            "category":"Health Services",
            "subcategory":"Health Practitioner",
            "type":"Services"
        }
    ],
    "sg:phone":"+1 847 680 0272",
    "sg:postcode":"60048",
    "sg:province":"IL",
    "sg:tags":[
        "psychologist"
    ],
    "wof:name":"Mark Solomon",
    "wof:placetype":"venue"
},
  "geometry": {"coordinates":[-87.95206899999999,42.289982],"type":"Point"}
}