{
  "type": "Feature",
  "properties": {
    "addr:full":"9436 47th St Brookfield IL 60513",
    "addr:housenumber":"9436",
    "addr:postcode":"60513",
    "addr:street":"47Th St",
    "iso:country":"US",
    "sg:address":"9436 47th St",
    "sg:city":"Brookfield",
    "sg:classifiers":[
        {
            "category":"Building & Trades",
            "subcategory":"Plumbing",
            "type":"Services"
        }
    ],
    "sg:phone":"+1 708 485 7827",
    "sg:postcode":"60513",
    "sg:province":"IL",
    "sg:tags":[
        "conditioning",
        "air",
        "system",
        "contractor"
    ],
    "wof:name":"Advanced Heating & Air Co",
    "wof:placetype":"venue"
},
  "geometry": {"coordinates":[-87.85692,41.8054],"type":"Point"}
}