{
  "type": "Feature",
  "properties": {
    "iso:country":"US",
    "sg:address":"3258 S Princeton Ave",
    "sg:city":"Chicago",
    "sg:classifiers":[
        {
            "category":"Bars & Pubs",
            "type":"Food & Drink"
        }
    ],
    "sg:phone":"+1 312 842 0769",
    "sg:postcode":"60616",
    "sg:province":"IL",
    "sg:website":"corkandkerrychicago.com",
    "wof:name":"Cork and Kerry at the Park",
    "wof:placetype":"venue"
},
  "geometry": {"coordinates":[-87.634354,41.83468],"type":"Point"}
}