{
  "type": "Feature",
  "properties": {
    "addr:full":"16 S Prospect Ave Clarendon Hills IL 60514",
    "addr:housenumber":"16",
    "addr:postcode":"60514",
    "addr:street":"S Prospect Ave",
    "iso:country":"US",
    "sg:address":"16 S Prospect Ave",
    "sg:city":"Clarendon Hills",
    "sg:classifiers":[
        {
            "category":"Shopping",
            "subcategory":"Books",
            "type":"Retail Goods"
        }
    ],
    "sg:phone":"+1 630 323 4673",
    "sg:postcode":"60514",
    "sg:province":"IL",
    "sg:tags":[
        "religious",
        "dealer",
        "store"
    ],
    "wof:name":"Amazing Grace Book Store",
    "wof:placetype":"venue"
},
  "geometry": {"coordinates":[-87.954622,41.796729],"type":"Point"}
}