{
  "type": "Feature",
  "properties": {
    "iso:country":"US",
    "sg:address":"E 65th At Lake Michiga",
    "sg:city":"Chicago",
    "sg:classifiers":[
        {
            "category":"Health Services",
            "subcategory":"Hospital",
            "type":"Services"
        }
    ],
    "sg:phone":"+1 773 363 6701",
    "sg:postcode":"60607",
    "sg:province":"IL",
    "sg:website":"www.larabida.org",
    "wof:name":"La Rabida Children's Hospital",
    "wof:placetype":"venue"
},
  "geometry": {"coordinates":[-87.656932,41.873792],"type":"Point"}
}