{
  "type": "Feature",
  "properties": {
    "iso:country":"US",
    "sg:address":"514 Range Rd",
    "sg:city":"Sandoval",
    "sg:classifiers":[
        {
            "category":"Building & Trades",
            "subcategory":"Construction",
            "type":"Services"
        }
    ],
    "sg:phone":"+1 618 247 3301",
    "sg:postcode":"62882",
    "sg:province":"IL",
    "sg:tags":[
        "excavating",
        "contractor"
    ],
    "wof:name":"Wayne Carter Excavating",
    "wof:placetype":"venue"
},
  "geometry": {"coordinates":[-89.121568,38.634425],"type":"Point"}
}