{
  "type": "Feature",
  "properties": {
    "addr:full":"4638 N Cumberland Ave Norridge IL 60656",
    "addr:housenumber":"4638",
    "addr:postcode":"60656",
    "addr:street":"N Cumberland Ave",
    "iso:country":"US",
    "sg:address":"4638 N Cumberland Ave",
    "sg:city":"Norridge",
    "sg:classifiers":[
        {
            "category":"Personal",
            "subcategory":"Beauty Salon",
            "type":"Services"
        }
    ],
    "sg:phone":"+1 773 625 6023",
    "sg:postcode":"60656",
    "sg:province":"IL",
    "sg:tags":[
        "nail",
        "shop"
    ],
    "wof:name":"Number One Nails",
    "wof:placetype":"venue"
},
  "geometry": {"coordinates":[-87.836502,41.963699],"type":"Point"}
}