{
  "type": "Feature",
  "properties": {
    "iso:country":"US",
    "sg:address":"1 S River Ln",
    "sg:city":"Geneva",
    "sg:classifiers":[
        {
            "category":"Personal",
            "subcategory":"Beauty Salon",
            "type":"Services"
        }
    ],
    "sg:phone":"+1 630 845 4090",
    "sg:postcode":"60134",
    "sg:province":"IL",
    "wof:name":"Melissa Salon",
    "wof:placetype":"venue"
},
  "geometry": {"coordinates":[-88.303719,41.88739],"type":"Point"}
}