{
  "type": "Feature",
  "properties": {
    "iso:country":"US",
    "sg:address":"473 Mockingbird",
    "sg:city":"Lindenhurst",
    "sg:classifiers":[
        {
            "category":"Wholesale",
            "subcategory":"Office Equipment",
            "type":"Manufacturing & Wholesale Goods"
        }
    ],
    "sg:phone":"+1 847 245 8777",
    "sg:postcode":"60046",
    "sg:province":"IL",
    "sg:tags":[
        "machine",
        "duplicating",
        "copying"
    ],
    "wof:name":"Crown Copier Svc",
    "wof:placetype":"venue"
},
  "geometry": {"coordinates":[-88.017925,42.406163],"type":"Point"}
}