{
  "type": "Feature",
  "properties": {
    "addr:full":"108 N 2nd St Greenville IL 62246",
    "addr:housenumber":"108",
    "addr:postcode":"62246",
    "addr:street":"N 2Nd St",
    "iso:country":"US",
    "sg:address":"108 N 2nd St",
    "sg:city":"Greenville",
    "sg:classifiers":[
        {
            "category":"Restaurant",
            "type":"Food & Drink"
        }
    ],
    "sg:menulink":"http://www.allmenus.com/il/central/126536-subway/menu/",
    "sg:phone":"+1 618 664 3161",
    "sg:postcode":"62246",
    "sg:province":"IL",
    "sg:tags":[
        "american",
        "sandwich"
    ],
    "wof:name":"Subway",
    "wof:placetype":"venue"
},
  "geometry": {"coordinates":[-89.41253,38.892101],"type":"Point"}
}