{
  "type": "Feature",
  "properties": {
    "addr:full":"10580 Wellen Rd Aviston IL 62245",
    "addr:postcode":"10580;62245",
    "addr:street":"Wellen Rd",
    "iso:country":"US",
    "sg:address":"10580 Wellen Rd",
    "sg:city":"Aviston",
    "sg:classifiers":[
        {
            "category":"Manufacturing",
            "subcategory":"Food",
            "type":"Manufacturing & Wholesale Goods"
        }
    ],
    "sg:phone":"+1 618 228 9111",
    "sg:postcode":"62245",
    "sg:province":"IL",
    "sg:tags":[
        "winery"
    ],
    "wof:name":"Hidden Lake Winery",
    "wof:placetype":"venue"
},
  "geometry": {"coordinates":[-89.63069,38.578794],"type":"Point"}
}