{
  "type": "Feature",
  "properties": {
    "addr:full":"530 Main St Marseilles IL 61341",
    "addr:housenumber":"530",
    "addr:postcode":"61341",
    "addr:street":"Main St",
    "iso:country":"US",
    "sg:address":"530 Main St",
    "sg:city":"Marseilles",
    "sg:classifiers":[
        {
            "category":"Food & Beverages",
            "subcategory":"Liquor & Beverages",
            "type":"Retail Goods"
        }
    ],
    "sg:phone":"+1   ",
    "sg:postcode":"61341",
    "sg:province":"IL",
    "sg:tags":[
        "alcoholic"
    ],
    "wof:name":"Spirits",
    "wof:placetype":"venue"
},
  "geometry": {"coordinates":[-88.708269,41.330136],"type":"Point"}
}