{
  "type": "Feature",
  "properties": {
    "iso:country":"US",
    "sg:address":"6103 Brittney Ln",
    "sg:city":"Tinley Park",
    "sg:classifiers":[
        {
            "category":"Real Estate",
            "subcategory":"Real Estate Agent",
            "type":"Services"
        }
    ],
    "sg:phone":"+1 708 614 0290",
    "sg:postcode":"60477",
    "sg:province":"IL",
    "wof:name":"Valuation Group",
    "wof:placetype":"venue"
},
  "geometry": {"coordinates":[-87.76772099999999,41.586442],"type":"Point"}
}