{
  "type": "Feature",
  "properties": {
    "addr:full":"515 N la Grange Rd Frankfort IL 60423",
    "addr:housenumber":"515",
    "addr:postcode":"60423",
    "addr:street":"N La Grange Rd",
    "iso:country":"US",
    "sg:address":"515 N la Grange Rd",
    "sg:city":"Frankfort",
    "sg:classifiers":[
        {
            "category":"Shopping",
            "type":"Retail Goods"
        }
    ],
    "sg:phone":"+1 815 464 0300",
    "sg:postcode":"60423",
    "sg:province":"IL",
    "sg:tags":[
        "telephone",
        "cellular"
    ],
    "wof:name":"Cellular Connection",
    "wof:placetype":"venue"
},
  "geometry": {"coordinates":[-87.90701799999999,41.575561],"type":"Point"}
}