{
  "type": "Feature",
  "properties": {
    "addr:full":"730 Bainbridge St Barry IL 62312",
    "addr:housenumber":"730",
    "addr:postcode":"62312",
    "addr:street":"Bainbridge St",
    "iso:country":"US",
    "sg:address":"730 Bainbridge St",
    "sg:city":"Barry",
    "sg:classifiers":[
        {
            "category":"Personal",
            "subcategory":"Beauty Salon",
            "type":"Services"
        }
    ],
    "sg:phone":"+1 217 335 3317",
    "sg:postcode":"62312",
    "sg:province":"IL",
    "wof:name":"Camilla's",
    "wof:placetype":"venue"
},
  "geometry": {"coordinates":[-91.040406,39.694216],"type":"Point"}
}