{
  "type": "Feature",
  "properties": {
    "iso:country":"US",
    "sg:address":"6221 N Milwaukee Ave",
    "sg:city":"Chicago",
    "sg:classifiers":[
        {
            "category":"Travel",
            "subcategory":"Travel Agent",
            "type":"Entertainment"
        }
    ],
    "sg:phone":"+1 773 792 3300",
    "sg:postcode":"60646",
    "sg:province":"IL",
    "sg:tags":[
        "operator",
        "tour",
        "agency"
    ],
    "wof:name":"Mirage Travel",
    "wof:placetype":"venue"
},
  "geometry": {"coordinates":[-87.784949,41.99429],"type":"Point"}
}