{
  "type": "Feature",
  "properties": {
    "iso:country":"US",
    "sg:address":"605 W 31st St",
    "sg:city":"Chicago",
    "sg:classifiers":[
        {
            "category":"Restaurant",
            "type":"Food & Drink"
        }
    ],
    "sg:phone":"+1 312 949 1314",
    "sg:postcode":"60616",
    "sg:province":"IL",
    "sg:tags":[
        "seafood",
        "chinese"
    ],
    "sg:website":"www.han202.com/",
    "wof:name":"Han 202",
    "wof:placetype":"venue"
},
  "geometry": {"coordinates":[-87.641704,41.83788],"type":"Point"}
}