{
  "type": "Feature",
  "properties": {
    "addr:full":"521 E Jefferson St Freeport IL 61032",
    "addr:housenumber":"521",
    "addr:postcode":"61032",
    "addr:street":"E Jefferson St",
    "iso:country":"US",
    "sg:address":"521 E Jefferson St",
    "sg:city":"Freeport",
    "sg:classifiers":[
        {
            "category":"Restaurant",
            "type":"Food & Drink"
        }
    ],
    "sg:phone":"+1   ",
    "sg:postcode":"61032",
    "sg:province":"IL",
    "sg:tags":[
        "eating"
    ],
    "wof:name":"Filling Station",
    "wof:placetype":"venue"
},
  "geometry": {"coordinates":[-89.60704800000001,42.285489],"type":"Point"}
}