{
  "type": "Feature",
  "properties": {
    "addr:full":"11800 Factory Shops Blvd Huntley IL 60142",
    "addr:housenumber":"11800",
    "addr:postcode":"60142",
    "addr:street":"Factory Shops Blvd",
    "iso:country":"US",
    "sg:address":"11800 Factory Shops Blvd",
    "sg:city":"Huntley",
    "sg:classifiers":[
        {
            "category":"Shopping",
            "subcategory":"Gifts & Souvenirs",
            "type":"Retail Goods"
        }
    ],
    "sg:phone":"+1 847 515 1818",
    "sg:postcode":"60142",
    "sg:province":"IL",
    "sg:tags":[
        "shop"
    ],
    "wof:name":"Temptations",
    "wof:placetype":"venue"
},
  "geometry": {"coordinates":[-88.426552,42.122822],"type":"Point"}
}