{
  "type": "Feature",
  "properties": {
    "addr:full":"1405 N Quentin Rd Palatine IL 60067",
    "addr:housenumber":"1405",
    "addr:postcode":"60067",
    "addr:street":"N Quentin Rd",
    "iso:country":"US",
    "sg:address":"1405 N Quentin Rd",
    "sg:city":"Palatine",
    "sg:classifiers":[
        {
            "category":"Organizations",
            "subcategory":"Religious Organization",
            "type":"Services"
        }
    ],
    "sg:phone":"+1 847 934 6131",
    "sg:postcode":"60067",
    "sg:province":"IL",
    "wof:name":"Second Baptist Church Palatine",
    "wof:placetype":"venue"
},
  "geometry": {"coordinates":[-88.06293599999999,42.135792],"type":"Point"}
}