{
  "type": "Feature",
  "properties": {
    "iso:country":"US",
    "sg:address":"11440 Main St",
    "sg:city":"Roscoe",
    "sg:classifiers":[
        {
            "category":"Banks & Credit Unions",
            "subcategory":"Bank",
            "type":"Services"
        }
    ],
    "sg:phone":"+1 815 623 2161",
    "sg:postcode":"61073",
    "sg:province":"IL",
    "sg:website":"www.bankone.com",
    "wof:name":"Bank One",
    "wof:placetype":"venue"
},
  "geometry": {"coordinates":[-89.01267799999999,42.42662],"type":"Point"}
}