{
  "type": "Feature",
  "properties": {
    "addr:full":"6445 S Cicero Ave Chicago IL 60638",
    "addr:housenumber":"6445",
    "addr:postcode":"60638",
    "addr:street":"S Cicero Ave",
    "iso:country":"US",
    "sg:address":"6445 S Cicero Ave",
    "sg:city":"Chicago",
    "sg:classifiers":[
        {
            "category":"Restaurant",
            "type":"Food & Drink"
        }
    ],
    "sg:menulink":"http://www.allmenus.com/il/chicago/221489-taqueria-california/menu/",
    "sg:phone":"+1 773 585 8785",
    "sg:postcode":"60638",
    "sg:province":"IL",
    "sg:tags":[
        "mexican"
    ],
    "wof:name":"Taqueria California",
    "wof:placetype":"venue"
},
  "geometry": {"coordinates":[-87.74208,41.775678],"type":"Point"}
}