{
  "type": "Feature",
  "properties": {
    "iso:country":"US",
    "sg:address":"2846 Hitchcock Ave",
    "sg:city":"Downers Grove",
    "sg:classifiers":[
        {
            "category":"Professional",
            "subcategory":"Business Services",
            "type":"Services"
        }
    ],
    "sg:phone":"+1 630 663 1223",
    "sg:postcode":"60515",
    "sg:province":"IL",
    "sg:tags":[
        "relocation",
        "term",
        "short",
        "corporate",
        "housing"
    ],
    "wof:name":"Marriott",
    "wof:placetype":"venue"
},
  "geometry": {"coordinates":[-88.052229,41.793689],"type":"Point"}
}