{
  "type": "Feature",
  "properties": {
    "addr:full":"850 W Eastwood Ave Chicago IL 60640",
    "addr:housenumber":"850",
    "addr:postcode":"60640",
    "addr:street":"W Eastwood Ave",
    "iso:country":"US",
    "sg:address":"850 W Eastwood Ave",
    "sg:city":"Chicago",
    "sg:classifiers":[
        {
            "category":"Social Services",
            "type":"Services"
        }
    ],
    "sg:phone":"+1 312 271 9403",
    "sg:postcode":"60640",
    "sg:province":"IL",
    "sg:tags":[
        "child",
        "day",
        "care"
    ],
    "wof:name":"Christpher Hse Estwood Lcation",
    "wof:placetype":"venue"
},
  "geometry": {"coordinates":[-87.651782,41.966491],"type":"Point"}
}