{
  "type": "Feature",
  "properties": {
    "iso:country":"US",
    "sg:address":"440 Bonnie Ln",
    "sg:city":"Elk Grove Village",
    "sg:classifiers":[
        {
            "category":"Manufacturing",
            "subcategory":"Tools & Machinery",
            "type":"Manufacturing & Wholesale Goods"
        }
    ],
    "sg:phone":"+1 847 956 1940",
    "sg:postcode":"60007",
    "sg:province":"IL",
    "sg:tags":[
        "mfg"
    ],
    "wof:name":"Integrated Measurement Systems",
    "wof:placetype":"venue"
},
  "geometry": {"coordinates":[-87.971174,42.018133],"type":"Point"}
}