{
  "type": "Feature",
  "properties": {
    "iso:country":"US",
    "sg:address":"1254 2550th St",
    "sg:city":"Emden",
    "sg:phone":"+1 217 648 2636",
    "sg:postcode":"62656",
    "sg:province":"IL",
    "sg:tags":[
        "farm",
        "corn",
        "soybean"
    ],
    "wof:name":"Ann Born Farm",
    "wof:placetype":"venue"
},
  "geometry": {"coordinates":[-89.366103,40.287403],"type":"Point"}
}