{
  "type": "Feature",
  "properties": {
    "iso:country":"US",
    "sg:address":"4325 Avenue of the Cities",
    "sg:city":"Moline",
    "sg:classifiers":[
        {
            "category":"Education",
            "subcategory":"Music School",
            "type":"Public Place"
        }
    ],
    "sg:phone":"+1 309 762 9147",
    "sg:postcode":"61265",
    "sg:province":"IL",
    "sg:tags":[
        "instrument",
        "teacher",
        "musical"
    ],
    "wof:name":"Music Mart",
    "wof:placetype":"venue"
},
  "geometry": {"coordinates":[-90.47429700000001,41.490002],"type":"Point"}
}