{
  "type": "Feature",
  "properties": {
    "iso:country":"US",
    "sg:address":"8711 Ogden Ave",
    "sg:city":"Lyons",
    "sg:classifiers":[
        {
            "category":"Retail",
            "subcategory":"Funeral Services",
            "type":"Services"
        }
    ],
    "sg:phone":"+1 708 221 9667",
    "sg:postcode":"60534",
    "sg:province":"IL",
    "sg:tags":[
        "casket",
        "supply"
    ],
    "sg:website":"http://chicago.citysearch.com/profile/external/610199060/lyons_il/impressive_casket_inc.html?publisher=yellowpages&reference_id=15&placement=ypwebsitemip",
    "wof:name":"Impressive Casket Inc",
    "wof:placetype":"venue"
},
  "geometry": {"coordinates":[-87.83862000000001,41.816328],"type":"Point"}
}