{
  "type": "Feature",
  "properties": {
    "iso:country":"US",
    "sg:address":"1170 Riverview Rd",
    "sg:city":"Amboy",
    "sg:phone":"+1 815 857 2523",
    "sg:postcode":"61310",
    "sg:province":"IL",
    "sg:tags":[
        "farm",
        "grain",
        "cash"
    ],
    "wof:name":"William Lyons",
    "wof:placetype":"venue"
},
  "geometry": {"coordinates":[-89.40363600000001,41.696887],"type":"Point"}
}