{
  "type": "Feature",
  "properties": {
    "addr:full":"220 N 4th St Breese IL 62230",
    "addr:housenumber":"220",
    "addr:postcode":"62230",
    "addr:street":"N 4Th St",
    "iso:country":"US",
    "sg:address":"220 N 4th St",
    "sg:city":"Breese",
    "sg:classifiers":[
        {
            "category":"Shopping",
            "type":"Retail Goods"
        }
    ],
    "sg:phone":"+1 618 526 7792",
    "sg:postcode":"62230",
    "sg:province":"IL",
    "sg:tags":[
        "monument"
    ],
    "wof:name":"Lager Monument Works",
    "wof:placetype":"venue"
},
  "geometry": {"coordinates":[-89.532797,38.610818],"type":"Point"}
}