{
  "type": "Feature",
  "properties": {
    "iso:country":"US",
    "sg:address":"401 W Madison St",
    "sg:city":"Yorkville",
    "sg:classifiers":[
        {
            "category":"Retail",
            "subcategory":"Laundry & Dry Cleaning",
            "type":"Services"
        },
        {
            "category":"Building & Trades",
            "subcategory":"Cleaning & Sanitation",
            "type":"Services"
        }
    ],
    "sg:phone":"+1 630 385 2141",
    "sg:postcode":"60560",
    "sg:province":"IL",
    "sg:tags":[
        "cleaner",
        "house"
    ],
    "wof:name":"Double D Cleaning",
    "wof:placetype":"venue"
},
  "geometry": {"coordinates":[-88.45040899999999,41.640888],"type":"Point"}
}