{
  "type": "Feature",
  "properties": {
    "addr:full":"819 Main St Evanston IL 60202",
    "addr:housenumber":"819",
    "addr:postcode":"60202",
    "addr:street":"Main St",
    "iso:country":"US",
    "sg:address":"819 Main St",
    "sg:city":"Evanston",
    "sg:classifiers":[
        {
            "category":"Insurance",
            "subcategory":"Insurance Agent",
            "type":"Services"
        }
    ],
    "sg:phone":"+1 847 356 1900",
    "sg:postcode":"60202",
    "sg:province":"IL",
    "sg:website":"www.earll.com",
    "wof:name":"Earll Lyman & Haigh",
    "wof:placetype":"venue"
},
  "geometry": {"coordinates":[-87.683504,42.034064],"type":"Point"}
}