{
  "type": "Feature",
  "properties": {
    "iso:country":"US",
    "sg:address":"901 N Dunlap Ave",
    "sg:city":"Savoy",
    "sg:classifiers":[
        {
            "category":"Recreation",
            "subcategory":"Amusement Park",
            "type":"Entertainment"
        },
        {
            "category":"Sports & Exercise",
            "subcategory":"Golf",
            "type":"Entertainment"
        }
    ],
    "sg:phone":"+1 217 378 4653",
    "sg:postcode":"61874",
    "sg:province":"IL",
    "sg:tags":[
        "mini"
    ],
    "wof:name":"Old Orchard Links Inc",
    "wof:placetype":"venue"
},
  "geometry": {"coordinates":[-88.250298,40.061798],"type":"Point"}
}