{
  "type": "Feature",
  "properties": {
    "addr:full":"918 16th Ave East Moline IL 61244",
    "addr:housenumber":"918",
    "addr:postcode":"61244",
    "addr:street":"16Th Ave East",
    "iso:country":"US",
    "sg:address":"918 16th Ave",
    "sg:city":"East Moline",
    "sg:classifiers":[
        {
            "category":"Health Services",
            "subcategory":"Chiropractor",
            "type":"Services"
        }
    ],
    "sg:phone":"+1 309 752 0750",
    "sg:postcode":"61244",
    "sg:province":"IL",
    "wof:name":"Freebern Chiropratic",
    "wof:placetype":"venue"
},
  "geometry": {"coordinates":[-90.439697,41.515202],"type":"Point"}
}