{
  "type": "Feature",
  "properties": {
    "iso:country":"US",
    "sg:address":"George Tomecki, M.D. 8905 Burlington Ave.",
    "sg:city":"Brookfield",
    "sg:classifiers":[
        {
            "category":"Health Services",
            "subcategory":"Doctor",
            "type":"Services"
        }
    ],
    "sg:phone":"+1 708 387 7000",
    "sg:postcode":"60513",
    "sg:province":"IL",
    "sg:tags":[
        "practice",
        "family"
    ],
    "sg:website":"www.thefamilydoctors.org/",
    "wof:name":"The Family Doctors",
    "wof:placetype":"venue"
},
  "geometry": {"coordinates":[-87.844281,41.82166],"type":"Point"}
}