{
  "type": "Feature",
  "properties": {
    "iso:country":"US",
    "sg:address":"200 Poplar St",
    "sg:city":"Sumner",
    "sg:classifiers":[
        {
            "category":"Health Services",
            "subcategory":"Hospital",
            "type":"Services"
        }
    ],
    "sg:phone":"+1 618 936 2703",
    "sg:postcode":"62466",
    "sg:province":"IL",
    "sg:tags":[
        "mental"
    ],
    "wof:name":"Pine Lawn Health Care Ctr",
    "wof:placetype":"venue"
},
  "geometry": {"coordinates":[-87.860903,38.723531],"type":"Point"}
}