{
  "type": "Feature",
  "properties": {
    "addr:full":"530 W Reynolds St Springfield IL 62702",
    "addr:housenumber":"530",
    "addr:postcode":"62702",
    "addr:street":"W Reynolds St",
    "iso:country":"US",
    "sg:address":"530 W Reynolds St",
    "sg:city":"Springfield",
    "sg:classifiers":[
        {
            "category":"Education",
            "subcategory":"School",
            "type":"Public Place"
        }
    ],
    "sg:phone":"+1 217 525 3040",
    "sg:postcode":"62702",
    "sg:province":"IL",
    "sg:website":"http://www.springfield.k12.il.us",
    "wof:name":"Springfield Pblc Schl D186 Bsn",
    "wof:placetype":"venue"
},
  "geometry": {"coordinates":[-89.662127,39.806442],"type":"Point"}
}