{
  "type": "Feature",
  "properties": {
    "iso:country":"US",
    "sg:address":"518 Windsor Rd",
    "sg:city":"Loves Park",
    "sg:classifiers":[
        {
            "category":"Retail",
            "subcategory":"Car Wash",
            "type":"Services"
        }
    ],
    "sg:phone":"+1 815 877 9274",
    "sg:postcode":"61111",
    "sg:province":"IL",
    "sg:tags":[
        "polishing",
        "washing"
    ],
    "wof:name":"Windsor Wash",
    "wof:placetype":"venue"
},
  "geometry": {"coordinates":[-89.057053,42.325002],"type":"Point"}
}