{
  "type": "Feature",
  "properties": {
    "iso:country":"US",
    "sg:address":"425 Main St",
    "sg:city":"Carthage",
    "sg:classifiers":[
        {
            "category":"Home & Garden",
            "subcategory":"Furniture",
            "type":"Retail Goods"
        }
    ],
    "sg:phone":"+1 217 357 2212",
    "sg:postcode":"62321",
    "sg:province":"IL",
    "sg:tags":[
        "floor",
        "covering"
    ],
    "wof:name":"Twaddle Furniture Company",
    "wof:placetype":"venue"
},
  "geometry": {"coordinates":[-91.137701,40.413762],"type":"Point"}
}