{
  "type": "Feature",
  "properties": {
    "addr:full":"425 Main St Carthage IL 62321",
    "addr:housenumber":"425",
    "addr:postcode":"62321",
    "addr:street":"Main St",
    "iso:country":"US",
    "sg:address":"425 Main St",
    "sg:city":"Carthage",
    "sg:classifiers":[
        {
            "category":"Home & Garden",
            "subcategory":"Furniture",
            "type":"Retail Goods"
        }
    ],
    "sg:phone":"+1 217 357 2212",
    "sg:postcode":"62321",
    "sg:province":"IL",
    "sg:tags":[
        "floor",
        "covering"
    ],
    "wof:name":"Twaddle Furniture Company",
    "wof:placetype":"venue"
},
  "geometry": {"coordinates":[-91.13770100000001,40.413762],"type":"Point"}
}