{
  "type": "Feature",
  "properties": {
    "addr:full":"6307 S Archer Rd Summit Argo IL 60501",
    "addr:housenumber":"6307",
    "addr:postcode":"60501",
    "addr:street":"S Archer Rd",
    "iso:country":"US",
    "sg:address":"6307 S Archer Rd",
    "sg:city":"Summit Argo",
    "sg:classifiers":[
        {
            "category":"Bars & Pubs",
            "type":"Food & Drink"
        }
    ],
    "sg:phone":"+1 708 496 1202",
    "sg:postcode":"60501",
    "sg:province":"IL",
    "sg:tags":[
        "club",
        "drinking",
        "night"
    ],
    "wof:name":"Before & After Lounge Inc",
    "wof:placetype":"venue"
},
  "geometry": {"coordinates":[-87.814335,41.77636],"type":"Point"}
}