{
  "type": "Feature",
  "properties": {
    "addr:full":"2500 Lincoln Hwy Olympia Fields IL 60461",
    "addr:housenumber":"2500",
    "addr:postcode":"60461",
    "addr:street":"Lincoln Hwy",
    "iso:country":"US",
    "sg:address":"2500 Lincoln Hwy",
    "sg:city":"Olympia Fields",
    "sg:classifiers":[
        {
            "category":"Food & Beverages",
            "subcategory":"Groceries & Convenience Stores",
            "type":"Retail Goods"
        }
    ],
    "sg:phone":"+1   ",
    "sg:postcode":"60461",
    "sg:province":"IL",
    "wof:name":"Jewel-Osco 3090",
    "wof:placetype":"venue"
},
  "geometry": {"coordinates":[-87.67798999999999,41.506103],"type":"Point"}
}