{
  "type": "Feature",
  "properties": {
    "iso:country":"US",
    "sg:address":"110 S Larkin Ave",
    "sg:city":"Joliet",
    "sg:classifiers":[
        {
            "category":"Restaurant",
            "type":"Food & Drink"
        }
    ],
    "sg:menulink":"http://www.allmenus.com/il/joliet/181026-wendys/menu/",
    "sg:phone":"+1 815 730 9708",
    "sg:postcode":"60436",
    "sg:province":"IL",
    "sg:tags":[
        "burger",
        "american",
        "soup"
    ],
    "wof:name":"Wendy's",
    "wof:placetype":"venue"
},
  "geometry": {"coordinates":[-88.12400100000001,41.520184],"type":"Point"}
}