{
  "type": "Feature",
  "properties": {
    "iso:country":"US",
    "sg:address":"426 Wyoming Ave",
    "sg:city":"Paw Paw",
    "sg:classifiers":[
        {
            "category":"Building & Trades",
            "subcategory":"Construction",
            "type":"Services"
        }
    ],
    "sg:phone":"+1 815 627 8091",
    "sg:postcode":"61353",
    "sg:province":"IL",
    "sg:tags":[
        "house"
    ],
    "wof:name":"Hawbaker Construction",
    "wof:placetype":"venue"
},
  "geometry": {"coordinates":[-88.985864,41.691356],"type":"Point"}
}