{
  "type": "Feature",
  "properties": {
    "iso:country":"US",
    "sg:address":"32 Pentwater Dr",
    "sg:city":"South Barrington",
    "sg:classifiers":[
        {
            "category":"Building & Trades",
            "subcategory":"Construction",
            "type":"Services"
        }
    ],
    "sg:phone":"+1 847 428 5212",
    "sg:postcode":"60010",
    "sg:province":"IL",
    "sg:tags":[
        "contractor"
    ],
    "wof:name":"Loico Construction",
    "wof:placetype":"venue"
},
  "geometry": {"coordinates":[-88.17150100000001,42.077099],"type":"Point"}
}