{
  "type": "Feature",
  "properties": {
    "iso:country":"US",
    "sg:address":"9343 Oak Park Ave",
    "sg:city":"Morton Grove",
    "sg:classifiers":[
        {
            "category":"Professional",
            "subcategory":"Business Services",
            "type":"Services"
        }
    ],
    "sg:phone":"+1 312 263 6442",
    "sg:postcode":"60053",
    "sg:province":"IL",
    "wof:name":"Embossed Sign Service",
    "wof:placetype":"venue"
},
  "geometry": {"coordinates":[-87.79538599999999,42.052733],"type":"Point"}
}