{
  "type": "Feature",
  "properties": {
    "addr:full":"3 Black Oak Dr Highland IL 62249",
    "addr:housenumber":"3",
    "addr:postcode":"62249",
    "addr:street":"Black Oak Dr",
    "iso:country":"US",
    "sg:address":"3 Black Oak Dr",
    "sg:city":"Highland",
    "sg:classifiers":[
        {
            "category":"Manufacturing",
            "subcategory":"Lumber",
            "type":"Manufacturing & Wholesale Goods"
        }
    ],
    "sg:phone":"+1 618 654 2713",
    "sg:postcode":"62249",
    "sg:province":"IL",
    "sg:tags":[
        "tree",
        "grow"
    ],
    "wof:name":"Earthmark International",
    "wof:placetype":"venue"
},
  "geometry": {"coordinates":[-89.668162,38.728615],"type":"Point"}
}