{
  "type": "Feature",
  "properties": {
    "iso:country":"US",
    "sg:address":"3307 Broadway St",
    "sg:city":"Mount Vernon",
    "sg:classifiers":[
        {
            "category":"Health Services",
            "subcategory":"Doctor",
            "type":"Services"
        }
    ],
    "sg:phone":"+1 618 244 2560",
    "sg:postcode":"62864",
    "sg:province":"IL",
    "sg:tags":[
        "medical"
    ],
    "wof:name":"Agarwalk Naresh K",
    "wof:placetype":"venue"
},
  "geometry": {"coordinates":[-88.932045,38.314395],"type":"Point"}
}