{
  "type": "Feature",
  "properties": {
    "iso:country":"US",
    "sg:address":"809 S 5th St",
    "sg:city":"Champaign",
    "sg:classifiers":[
        {
            "category":"Place Of Worship",
            "subcategory":"Church",
            "type":"Public Place"
        }
    ],
    "sg:phone":"+1 217 344 0297",
    "sg:postcode":"61820",
    "sg:province":"IL",
    "sg:website":"www.mckinley-church.org",
    "wof:name":"McKinley Presbyterian Church & Foundation",
    "wof:placetype":"venue"
},
  "geometry": {"coordinates":[-88.23205400000001,40.108988],"type":"Point"}
}