{
  "type": "Feature",
  "properties": {
    "addr:full":"782 Western Ave New Lenox IL 60451",
    "addr:housenumber":"782",
    "addr:postcode":"60451",
    "addr:street":"Western Ave",
    "iso:country":"US",
    "sg:address":"782 Western Ave",
    "sg:city":"New Lenox",
    "sg:classifiers":[
        {
            "category":"Building & Trades",
            "subcategory":"Construction",
            "type":"Services"
        }
    ],
    "sg:phone":"+1 815 485 0852",
    "sg:postcode":"60451",
    "sg:province":"IL",
    "sg:tags":[
        "water",
        "well",
        "drilling"
    ],
    "wof:name":"Windy City Drilling Inc",
    "wof:placetype":"venue"
},
  "geometry": {"coordinates":[-87.97503500000001,41.503035],"type":"Point"}
}