{
  "type": "Feature",
  "properties": {
    "addr:full":"229 W Norris Dr Ottawa IL 61350",
    "addr:housenumber":"229",
    "addr:postcode":"61350",
    "addr:street":"W Norris Dr",
    "iso:country":"US",
    "sg:address":"229 W Norris Dr",
    "sg:city":"Ottawa",
    "sg:classifiers":[
        {
            "category":"Personal",
            "subcategory":"Beauty Salon",
            "type":"Services"
        }
    ],
    "sg:phone":"+1 815 433 4243",
    "sg:postcode":"61350",
    "sg:province":"IL",
    "wof:name":"Hair Studio",
    "wof:placetype":"venue"
},
  "geometry": {"coordinates":[-88.843092,41.356065],"type":"Point"}
}