{
  "type": "Feature",
  "properties": {
    "iso:country":"US",
    "sg:address":"13045 N State Highway 130",
    "sg:city":"Newton",
    "sg:classifiers":[
        {
            "category":"Farming",
            "subcategory":"Livestock Farm",
            "type":"Manufacturing & Wholesale Goods"
        },
        {
            "category":"Farming",
            "subcategory":"Farm",
            "type":"Manufacturing & Wholesale Goods"
        }
    ],
    "sg:phone":"+1 618 783 2177",
    "sg:postcode":"62448",
    "sg:province":"IL",
    "wof:name":"Michel Farms",
    "wof:placetype":"venue"
},
  "geometry": {"coordinates":[-88.136825,38.960743],"type":"Point"}
}