{
  "type": "Feature",
  "properties": {
    "addr:full":"20 N Wacker Dr Ste 656 Chicago IL 60606",
    "addr:housenumber":"20",
    "addr:postcode":"60606",
    "addr:street":"N Wacker Dr Ste 656",
    "iso:country":"US",
    "sg:address":"20 N Wacker Dr Ste 656",
    "sg:city":"Chicago",
    "sg:classifiers":[
        {
            "category":"Utilities",
            "subcategory":"Telephone",
            "type":"Services"
        }
    ],
    "sg:phone":"+1 312 630 9013",
    "sg:postcode":"60606",
    "sg:province":"IL",
    "sg:tags":[
        "distance",
        "companies-long"
    ],
    "wof:name":"Qwest",
    "wof:placetype":"venue"
},
  "geometry": {"coordinates":[-87.637032,41.882221],"type":"Point"}
}