{
  "type": "Feature",
  "properties": {
    "iso:country":"US",
    "sg:address":"102 River Oaks Center Dr",
    "sg:city":"Calumet City",
    "sg:classifiers":[
        {
            "category":"Shopping",
            "subcategory":"Hobbies, Toys, & Games",
            "type":"Retail Goods"
        }
    ],
    "sg:phone":"+1   ",
    "sg:postcode":"60409",
    "sg:province":"IL",
    "sg:tags":[
        "item"
    ],
    "wof:name":"Kb Toys",
    "wof:placetype":"venue"
},
  "geometry": {"coordinates":[-87.531963,41.596811],"type":"Point"}
}