{
  "type": "Feature",
  "properties": {
    "iso:country":"US",
    "sg:address":"79 W Monroe Street",
    "sg:city":"Chicago",
    "sg:classifiers":[
        {
            "category":"Real Estate",
            "subcategory":"Architect",
            "type":"Services"
        }
    ],
    "sg:phone":"+1 312 782 9562",
    "sg:postcode":"60603",
    "sg:province":"IL",
    "wof:name":"Michael R Eiben Aia",
    "wof:placetype":"venue"
},
  "geometry": {"coordinates":[-87.63007399999999,41.88068],"type":"Point"}
}