{
  "type": "Feature",
  "properties": {
    "addr:full":"19901 Houbolt Rd Joliet IL 60431",
    "addr:housenumber":"19901",
    "addr:postcode":"60431",
    "addr:street":"Houbolt Rd",
    "iso:country":"US",
    "sg:address":"19901 Houbolt Rd",
    "sg:city":"Joliet",
    "sg:classifiers":[
        {
            "category":"Organizations",
            "subcategory":"Religious Organization",
            "type":"Services"
        }
    ],
    "sg:phone":"+1 815 741 4488",
    "sg:postcode":"60431",
    "sg:province":"IL",
    "sg:website":"www.messiahlutheranjoliet.com",
    "wof:name":"Messiah Lutheran Church",
    "wof:placetype":"venue"
},
  "geometry": {"coordinates":[-88.16911500000001,41.505887],"type":"Point"}
}