{
  "type": "Feature",
  "properties": {
    "iso:country":"US",
    "sg:address":"8242 McCormick Blvd",
    "sg:city":"Skokie",
    "sg:classifiers":[
        {
            "category":"Autos & Motor Vehicles",
            "subcategory":"Auto Supplies",
            "type":"Retail Goods"
        }
    ],
    "sg:phone":"+1   ",
    "sg:postcode":"60076",
    "sg:province":"IL",
    "wof:name":"Drivers Image",
    "wof:placetype":"venue"
},
  "geometry": {"coordinates":[-87.711063,42.03107],"type":"Point"}
}