{
  "type": "Feature",
  "properties": {
    "addr:full":"4851 N Hamilton Ave Chicago IL 60625",
    "addr:housenumber":"4851",
    "addr:postcode":"60625",
    "addr:street":"N Hamilton Ave",
    "iso:country":"US",
    "sg:address":"4851 N Hamilton Ave",
    "sg:city":"Chicago",
    "sg:classifiers":[
        {
            "category":"Sports & Exercise",
            "subcategory":"Gym",
            "type":"Entertainment"
        }
    ],
    "sg:phone":"+1 773 561 1788",
    "sg:postcode":"60625",
    "sg:province":"IL",
    "sg:tags":[
        "yoga"
    ],
    "wof:name":"Eight Limbs Inc",
    "wof:placetype":"venue"
},
  "geometry": {"coordinates":[-87.683098,41.970299],"type":"Point"}
}