{
  "type": "Feature",
  "properties": {
    "iso:country":"US",
    "sg:address":"214 E Main St",
    "sg:city":"Golconda",
    "sg:classifiers":[
        {
            "category":"Home & Garden",
            "subcategory":"Hardware",
            "type":"Retail Goods"
        }
    ],
    "sg:phone":"+1 618 683 2551",
    "sg:postcode":"62924",
    "sg:province":"IL",
    "wof:name":"Watson True Value Hardware",
    "wof:placetype":"venue"
},
  "geometry": {"coordinates":[-89.22566399999999,37.815957],"type":"Point"}
}