{
  "type": "Feature",
  "properties": {
    "addr:full":"15310 Central Ave Oak Forest IL 60452",
    "addr:postcode":"15310;60452",
    "addr:street":"Central Ave",
    "iso:country":"US",
    "sg:address":"15310 Central Ave",
    "sg:city":"Oak Forest",
    "sg:classifiers":[
        {
            "category":"Building & Trades",
            "subcategory":"Construction",
            "type":"Services"
        }
    ],
    "sg:phone":"+1 708 687 2243",
    "sg:postcode":"60452",
    "sg:province":"IL",
    "sg:tags":[
        "carpentry",
        "contractor"
    ],
    "wof:name":"O Gorman Timberworks",
    "wof:placetype":"venue"
},
  "geometry": {"coordinates":[-87.756432,41.613453],"type":"Point"}
}