{
  "type": "Feature",
  "properties": {
    "iso:country":"US",
    "sg:address":"4121 Old Collinsville Rd",
    "sg:city":"Swansea",
    "sg:classifiers":[
        {
            "category":"Health Services",
            "subcategory":"Dentist",
            "type":"Services"
        }
    ],
    "sg:phone":"+1 618 222 1991",
    "sg:postcode":"62226",
    "sg:province":"IL",
    "wof:name":"PR On Demand",
    "wof:placetype":"venue"
},
  "geometry": {"coordinates":[-89.966217,38.557917],"type":"Point"}
}