{
  "type": "Feature",
  "properties": {
    "iso:country":"US",
    "sg:address":"228 E Main St",
    "sg:city":"Barrington",
    "sg:classifiers":[
        {
            "category":"Professional",
            "subcategory":"Business Services",
            "type":"Services"
        }
    ],
    "sg:phone":"+1 847 382 9130",
    "sg:postcode":"60010",
    "sg:province":"IL",
    "wof:name":"Reata Group Inc",
    "wof:placetype":"venue"
},
  "geometry": {"coordinates":[-88.133318,42.154277],"type":"Point"}
}