{
  "type": "Feature",
  "properties": {
    "addr:full":"10 S Dearborn St Chicago IL 60670",
    "addr:housenumber":"10",
    "addr:postcode":"60670",
    "addr:street":"S Dearborn St",
    "iso:country":"US",
    "sg:address":"10 S Dearborn St",
    "sg:city":"Chicago",
    "sg:classifiers":[
        {
            "category":"Banks & Credit Unions",
            "subcategory":"Bank",
            "type":"Services"
        }
    ],
    "sg:phone":"+1 312 336 0891",
    "sg:postcode":"60670",
    "sg:province":"IL",
    "wof:name":"Chase",
    "wof:placetype":"venue"
},
  "geometry": {"coordinates":[-87.628182,41.848388],"type":"Point"}
}