{
  "type": "Feature",
  "properties": {
    "iso:country":"US",
    "sg:address":"6346 W Irving Park Road",
    "sg:city":"Chicago",
    "sg:classifiers":[
        {
            "category":"Restaurant",
            "type":"Food & Drink"
        }
    ],
    "sg:phone":"+1 773 725 2659",
    "sg:postcode":"60634",
    "sg:province":"IL",
    "wof:name":"Harlem Cafe",
    "wof:placetype":"venue"
},
  "geometry": {"coordinates":[-87.785128,41.952936],"type":"Point"}
}