{
  "type": "Feature",
  "properties": {
    "iso:country":"US",
    "sg:address":"512 1st Ave",
    "sg:city":"Colona",
    "sg:classifiers":[
        {
            "category":"Recreation",
            "type":"Entertainment"
        }
    ],
    "sg:phone":"+1 309 796 4531",
    "sg:postcode":"61241",
    "sg:province":"IL",
    "sg:tags":[
        "martial art",
        "instruction"
    ],
    "wof:name":"Jai Johnson Karate Center",
    "wof:placetype":"venue"
},
  "geometry": {"coordinates":[-90.364051,41.483772],"type":"Point"}
}