{
  "type": "Feature",
  "properties": {
    "iso:country":"US",
    "sg:address":"1218 Swanwick St",
    "sg:city":"Chester",
    "sg:classifiers":[
        {
            "category":"Restaurant",
            "type":"Food & Drink"
        }
    ],
    "sg:menulink":"http://www.allmenus.com/il/chester/127802-subway/menu/",
    "sg:phone":"+1 618 826 3191",
    "sg:postcode":"62233",
    "sg:province":"IL",
    "sg:tags":[
        "american",
        "sandwich"
    ],
    "wof:name":"Subway",
    "wof:placetype":"venue"
},
  "geometry": {"coordinates":[-89.822275,37.913898],"type":"Point"}
}