{
  "type": "Feature",
  "properties": {
    "iso:country":"US",
    "sg:address":"22 W Crystal Lake Ave",
    "sg:city":"Crystal Lake",
    "sg:classifiers":[
        {
            "category":"Health Services",
            "subcategory":"Doctor",
            "type":"Services"
        }
    ],
    "sg:phone":"+1 815 459 9900",
    "sg:postcode":"60014",
    "sg:province":"IL",
    "sg:tags":[
        "dentist"
    ],
    "wof:name":"Chris K Burseth DDS",
    "wof:placetype":"venue"
},
  "geometry": {"coordinates":[-88.321405,42.241206],"type":"Point"}
}