{
  "type": "Feature",
  "properties": {
    "addr:full":"27 Crystal Lake Plz Crystal Lake IL 60014",
    "addr:housenumber":"27",
    "addr:postcode":"60014",
    "addr:street":"Crystal;Plz",
    "iso:country":"US",
    "sg:address":"27 Crystal Lake Plz",
    "sg:city":"Crystal Lake",
    "sg:classifiers":[
        {
            "category":"Wholesale",
            "subcategory":"Machinery & Supplies",
            "type":"Manufacturing & Wholesale Goods"
        }
    ],
    "sg:phone":"+1 815 356 0016",
    "sg:postcode":"60014",
    "sg:province":"IL",
    "sg:tags":[
        "equipment",
        "establishment"
    ],
    "wof:name":"Aerial Company Inc",
    "wof:placetype":"venue"
},
  "geometry": {"coordinates":[-88.32320199999999,42.227473],"type":"Point"}
}