{
  "type": "Feature",
  "properties": {
    "addr:full":"2113 Belvidere Rd Waukegan IL 60085",
    "addr:housenumber":"2113",
    "addr:postcode":"60085",
    "addr:street":"Belvidere Rd",
    "iso:country":"US",
    "sg:address":"2113 Belvidere Rd",
    "sg:city":"Waukegan",
    "sg:classifiers":[
        {
            "category":"Shopping",
            "subcategory":"Clothing, Apparel, & Fashions",
            "type":"Retail Goods"
        }
    ],
    "sg:phone":"+1   ",
    "sg:postcode":"60085",
    "sg:province":"IL",
    "wof:name":"DC Sports Inc",
    "wof:placetype":"venue"
},
  "geometry": {"coordinates":[-87.862183,42.350283],"type":"Point"}
}