{
  "type": "Feature",
  "properties": {
    "addr:full":"1330 NE Adams St Peoria IL 61603",
    "addr:housenumber":"1330",
    "addr:postcode":"61603",
    "addr:street":"Ne Adams St",
    "iso:country":"US",
    "sg:address":"1330 NE Adams St",
    "sg:city":"Peoria",
    "sg:classifiers":[
        {
            "category":"Retail",
            "subcategory":"Auto Repair",
            "type":"Services"
        }
    ],
    "sg:phone":"+1 309 674 0113",
    "sg:postcode":"61603",
    "sg:province":"IL",
    "sg:tags":[
        "body",
        "repairing",
        "customizing",
        "painting",
        "automobile"
    ],
    "sg:website":"http://www.jimbautobody.com",
    "wof:name":"Jims' Autobody & Refinishing Inc",
    "wof:placetype":"venue"
},
  "geometry": {"coordinates":[-89.574949,40.701088],"type":"Point"}
}