{
  "type": "Feature",
  "properties": {
    "addr:full":"225 Indiana St Elmhurst IL 60126",
    "addr:housenumber":"225",
    "addr:postcode":"60126",
    "addr:street":"Indiana St",
    "iso:country":"US",
    "sg:address":"225 Indiana St",
    "sg:city":"Elmhurst",
    "sg:classifiers":[
        {
            "category":"Shopping",
            "subcategory":"Catalog Store",
            "type":"Retail Goods"
        }
    ],
    "sg:phone":"+1   ",
    "sg:postcode":"60126",
    "sg:province":"IL",
    "sg:tags":[
        "mail",
        "house"
    ],
    "wof:name":"Rampant Lion Celtic Traders",
    "wof:placetype":"venue"
},
  "geometry": {"coordinates":[-87.93531,41.902833],"type":"Point"}
}