{
  "type": "Feature",
  "properties": {
    "iso:country":"US",
    "sg:address":"154 S Western Ave",
    "sg:city":"Carpentersville",
    "sg:classifiers":[
        {
            "category":"Shopping",
            "subcategory":"Jewelry",
            "type":"Retail Goods"
        }
    ],
    "sg:phone":"+1 847 428 9333",
    "sg:postcode":"60110",
    "sg:province":"IL",
    "sg:website":"www.helzberg.com",
    "wof:name":"Helzberg Diamonds 611",
    "wof:placetype":"venue"
},
  "geometry": {"coordinates":[-88.28980300000001,42.103298],"type":"Point"}
}