{
  "type": "Feature",
  "properties": {
    "addr:full":"5805 State Rte 161 Belleville IL 62223",
    "addr:housenumber":"5805",
    "addr:postcode":"62223",
    "addr:street":"State Rte 161",
    "iso:country":"US",
    "sg:address":"5805 State Rte 161",
    "sg:city":"Belleville",
    "sg:classifiers":[
        {
            "category":"Wholesale",
            "subcategory":"Machinery & Supplies",
            "type":"Manufacturing & Wholesale Goods"
        }
    ],
    "sg:phone":"+1 618 398 4100",
    "sg:postcode":"62223",
    "sg:province":"IL",
    "sg:tags":[
        "equipment",
        "construction"
    ],
    "wof:name":"Advanced Eqp Trck & Trlrs",
    "wof:placetype":"venue"
},
  "geometry": {"coordinates":[-90.021236,38.558539],"type":"Point"}
}