{
  "type": "Feature",
  "properties": {
    "addr:full":"924 Stratford Rd Deerfield IL 60015",
    "addr:housenumber":"924",
    "addr:postcode":"60015",
    "addr:street":"Stratford Rd",
    "iso:country":"US",
    "sg:address":"924 Stratford Rd",
    "sg:city":"Deerfield",
    "sg:classifiers":[
        {
            "category":"Shopping",
            "subcategory":"Computers & Home Electronics",
            "type":"Retail Goods"
        }
    ],
    "sg:phone":"+1 847 948 0309",
    "sg:postcode":"60015",
    "sg:province":"IL",
    "sg:tags":[
        "software"
    ],
    "sg:website":"www.internetforassociations.com",
    "wof:name":"Internet 4 Assn",
    "wof:placetype":"venue"
},
  "geometry": {"coordinates":[-87.85852199999999,42.170548],"type":"Point"}
}