{
  "type": "Feature",
  "properties": {
    "addr:full":"8117 S Pulaski Rd Chicago IL 60652",
    "addr:housenumber":"8117",
    "addr:postcode":"60652",
    "addr:street":"S Pulaski Rd",
    "iso:country":"US",
    "sg:address":"8117 S Pulaski Rd",
    "sg:city":"Chicago",
    "sg:classifiers":[
        {
            "category":"Shopping",
            "type":"Retail Goods"
        }
    ],
    "sg:phone":"+1 773 585 2007",
    "sg:postcode":"60652",
    "sg:province":"IL",
    "sg:tags":[
        "cosmetic",
        "perfume"
    ],
    "wof:name":"Avon Products",
    "wof:placetype":"venue"
},
  "geometry": {"coordinates":[-87.721711,41.745651],"type":"Point"}
}