{
  "type": "Feature",
  "properties": {
    "iso:country":"US",
    "sg:address":"27W010 Saint Charles Rd",
    "sg:city":"Wheaton",
    "sg:classifiers":[
        {
            "category":"Building & Trades",
            "subcategory":"Construction",
            "type":"Services"
        }
    ],
    "sg:phone":"+1 630 293 0505",
    "sg:postcode":"60187",
    "sg:province":"IL",
    "sg:tags":[
        "contractor"
    ],
    "wof:name":"Digioia Brothers Construction Company Inc",
    "wof:placetype":"venue"
},
  "geometry": {"coordinates":[-88.1129,41.855],"type":"Point"}
}