{
  "type": "Feature",
  "properties": {
    "iso:country":"US",
    "sg:address":"721 Sheldon Ave",
    "sg:city":"Aurora",
    "sg:classifiers":[
        {
            "category":"Freight",
            "type":"Transportation"
        }
    ],
    "sg:phone":"+1 630 768 6463",
    "sg:postcode":"60506",
    "sg:province":"IL",
    "sg:tags":[
        "operator",
        "trucking"
    ],
    "wof:name":"Steve Rick Trucking",
    "wof:placetype":"venue"
},
  "geometry": {"coordinates":[-88.340427,41.771892],"type":"Point"}
}