{
  "type": "Feature",
  "properties": {
    "iso:country":"US",
    "sg:address":"1605 Bunn St",
    "sg:city":"Bloomington",
    "sg:phone":"+1 309 827 3122",
    "sg:postcode":"61701",
    "sg:province":"IL",
    "wof:name":"Canine Design",
    "wof:placetype":"venue"
},
  "geometry": {"coordinates":[-88.98166500000001,40.463442],"type":"Point"}
}