{
  "type": "Feature",
  "properties": {
    "addr:full":"2420 Hiller Ridge Johnsburg IL 60050",
    "addr:postcode":"2420;60050",
    "addr:street":"Hiller Ridge",
    "iso:country":"US",
    "sg:address":"2420 Hiller Ridge",
    "sg:city":"Johnsburg",
    "sg:classifiers":[
        {
            "category":"Home & Garden",
            "subcategory":"Building Materials",
            "type":"Retail Goods"
        }
    ],
    "sg:phone":"+1 815 344 9910",
    "sg:postcode":"60050",
    "sg:province":"IL",
    "sg:tags":[
        "door"
    ],
    "wof:name":"Architectural Garage Door Dsgn",
    "wof:placetype":"venue"
},
  "geometry": {"coordinates":[-88.244377,42.40646],"type":"Point"}
}