{
  "type": "Feature",
  "properties": {
    "addr:full":"3415 Quincy Mall Quincy IL 62301",
    "addr:housenumber":"3415",
    "addr:postcode":"62301",
    "addr:street":"Quincy Mall",
    "iso:country":"US",
    "sg:address":"3415 Quincy Mall",
    "sg:city":"Quincy",
    "sg:classifiers":[
        {
            "category":"Personal",
            "subcategory":"Beauty Salon",
            "type":"Services"
        }
    ],
    "sg:phone":"+1 217 223 5029",
    "sg:postcode":"62301",
    "sg:province":"IL",
    "sg:tags":[
        "nail",
        "shop"
    ],
    "wof:name":"Magic Nails",
    "wof:placetype":"venue"
},
  "geometry": {"coordinates":[-91.361851,39.935781],"type":"Point"}
}