{
  "type": "Feature",
  "properties": {
    "iso:country":"US",
    "sg:address":"29038 Grennan Rd",
    "sg:city":"Rock Falls",
    "sg:classifiers":[
        {
            "category":"Arts & Performance",
            "subcategory":"Theater",
            "type":"Entertainment"
        }
    ],
    "sg:phone":"+1 815 535 0824",
    "sg:postcode":"61071",
    "sg:province":"IL",
    "sg:tags":[
        "group"
    ],
    "wof:name":"Music By Night",
    "wof:placetype":"venue"
},
  "geometry": {"coordinates":[-89.670557,41.718364],"type":"Point"}
}