{
  "type": "Feature",
  "properties": {
    "addr:full":"10500 S Western Ave Chicago IL 60643",
    "addr:housenumber":"10500",
    "addr:postcode":"60643",
    "addr:street":"S Western Ave",
    "iso:country":"US",
    "sg:address":"10500 S Western Ave",
    "sg:city":"Chicago",
    "sg:classifiers":[
        {
            "category":"Restaurant",
            "type":"Food & Drink"
        }
    ],
    "sg:phone":"+1 773 238 3982",
    "sg:postcode":"60643",
    "sg:province":"IL",
    "sg:tags":[
        "mexican"
    ],
    "wof:name":"Taqueria Valparaiso",
    "wof:placetype":"venue"
},
  "geometry": {"coordinates":[-87.681906,41.702615],"type":"Point"}
}