{
  "type": "Feature",
  "properties": {
    "addr:full":"2850 W 95th St Evergreen Park IL 60805",
    "addr:housenumber":"2850",
    "addr:postcode":"60805",
    "addr:street":"W 95Th St",
    "iso:country":"US",
    "sg:address":"2850 W 95th St",
    "sg:city":"Evergreen Park",
    "sg:classifiers":[
        {
            "category":"Professional",
            "subcategory":"Business Services",
            "type":"Services"
        }
    ],
    "sg:phone":"+1 708 425 2328",
    "sg:postcode":"60805",
    "sg:province":"IL",
    "sg:tags":[
        "broker"
    ],
    "wof:name":"Excell Business Service Inc",
    "wof:placetype":"venue"
},
  "geometry": {"coordinates":[-87.69409400000001,41.720893],"type":"Point"}
}