{
  "type": "Feature",
  "properties": {
    "iso:country":"US",
    "sg:address":"2850 W 95th St",
    "sg:city":"Evergreen Park",
    "sg:classifiers":[
        {
            "category":"Professional",
            "subcategory":"Business Services",
            "type":"Services"
        }
    ],
    "sg:phone":"+1 708 425 2328",
    "sg:postcode":"60805",
    "sg:province":"IL",
    "sg:tags":[
        "broker"
    ],
    "wof:name":"Excell Business Service Inc",
    "wof:placetype":"venue"
},
  "geometry": {"coordinates":[-87.694094,41.720893],"type":"Point"}
}