{
  "type": "Feature",
  "properties": {
    "addr:full":"1201 N 79th St East St Louis IL 62203",
    "addr:housenumber":"1201",
    "addr:postcode":"62203",
    "addr:street":"N 79Th St",
    "iso:country":"US",
    "sg:address":"1201 N 79th St",
    "sg:city":"East St Louis",
    "sg:classifiers":[
        {
            "category":"Health Services",
            "subcategory":"Medical Lab",
            "type":"Services"
        }
    ],
    "sg:phone":"+1 618 397 1462",
    "sg:postcode":"62203",
    "sg:province":"IL",
    "sg:tags":[
        "laboratory",
        "dental"
    ],
    "wof:name":"Fairchild Dental Laboratory",
    "wof:placetype":"venue"
},
  "geometry": {"coordinates":[-90.06459,38.607929],"type":"Point"}
}