{
  "type": "Feature",
  "properties": {
    "addr:full":"2821 Richmond St Joliet IL 60435",
    "addr:housenumber":"2821",
    "addr:postcode":"60435",
    "addr:street":"Richmond St",
    "iso:country":"US",
    "sg:address":"2821 Richmond St",
    "sg:city":"Joliet",
    "sg:classifiers":[
        {
            "category":"Professional",
            "subcategory":"Advertising",
            "type":"Services"
        }
    ],
    "sg:phone":"+1 815 729 0862",
    "sg:postcode":"60435",
    "sg:province":"IL",
    "sg:tags":[
        "counselor"
    ],
    "wof:name":"Hollywood",
    "wof:placetype":"venue"
},
  "geometry": {"coordinates":[-88.152289,41.52443],"type":"Point"}
}