{
  "type": "Feature",
  "properties": {
    "iso:country":"US",
    "sg:address":"1887 Waxwing Ln",
    "sg:city":"Libertyville",
    "sg:classifiers":[
        {
            "category":"Shopping",
            "subcategory":"Computers & Home Electronics",
            "type":"Retail Goods"
        }
    ],
    "sg:phone":"+1   ",
    "sg:postcode":"60048",
    "sg:province":"IL",
    "sg:tags":[
        "component"
    ],
    "wof:name":"Voodoo Memory",
    "wof:placetype":"venue"
},
  "geometry": {"coordinates":[-87.913011,42.325699],"type":"Point"}
}