{
  "type": "Feature",
  "properties": {
    "iso:country":"US",
    "sg:address":"21W151 Hill Ave",
    "sg:city":"Glen Ellyn",
    "sg:classifiers":[
        {
            "category":"Retail",
            "subcategory":"Auto Repair",
            "type":"Services"
        }
    ],
    "sg:phone":"+1 630 858 1355",
    "sg:postcode":"60137",
    "sg:province":"IL",
    "sg:tags":[
        "body",
        "shop"
    ],
    "wof:name":"Al Heidorn Complete Auto Body Repair",
    "wof:placetype":"venue"
},
  "geometry": {"coordinates":[-88.03510300000001,41.883598],"type":"Point"}
}