{
  "type": "Feature",
  "properties": {
    "iso:country":"US",
    "sg:address":"149 Page St",
    "sg:city":"Aviston",
    "sg:classifiers":[
        {
            "category":"Government",
            "subcategory":"Office",
            "type":"Public Place"
        }
    ],
    "sg:phone":"+1 618 228 7262",
    "sg:postcode":"62216",
    "sg:province":"IL",
    "sg:tags":[
        "village"
    ],
    "wof:name":"Aviston Village Hall",
    "wof:placetype":"venue"
},
  "geometry": {"coordinates":[-89.605576,38.609619],"type":"Point"}
}