{
  "type": "Feature",
  "properties": {
    "addr:full":"25 Main St Roselle IL 60172",
    "addr:housenumber":"25",
    "addr:postcode":"60172",
    "addr:street":"Main St",
    "iso:country":"US",
    "sg:address":"25 Main St",
    "sg:city":"Roselle",
    "sg:classifiers":[
        {
            "category":"Coffee & Tea",
            "type":"Food & Drink"
        }
    ],
    "sg:phone":"+1 630 351 6058",
    "sg:postcode":"60172",
    "sg:province":"IL",
    "sg:website":"www.starbucks.com",
    "wof:name":"Starbucks Coffee",
    "wof:placetype":"venue"
},
  "geometry": {"coordinates":[-88.074725,41.982882],"type":"Point"}
}