{
  "type": "Feature",
  "properties": {
    "iso:country":"US",
    "sg:address":"745 S Ashland Ave",
    "sg:city":"La Grange",
    "sg:classifiers":[
        {
            "category":"Food & Beverages",
            "subcategory":"Groceries & Convenience Stores",
            "type":"Retail Goods"
        }
    ],
    "sg:phone":"+1 708 354 1144",
    "sg:postcode":"60525",
    "sg:province":"IL",
    "wof:name":"Consumer Vinegar & Spice",
    "wof:placetype":"venue"
},
  "geometry": {"coordinates":[-87.871526,41.800555],"type":"Point"}
}