{
  "type": "Feature",
  "properties": {
    "iso:country":"US",
    "sg:address":"2030 High St",
    "sg:city":"Blue Island",
    "sg:classifiers":[
        {
            "category":"Real Estate",
            "subcategory":"Real Estate Agent",
            "type":"Services"
        }
    ],
    "sg:phone":"+1 708 385 6556",
    "sg:postcode":"60406",
    "sg:province":"IL",
    "sg:tags":[
        "manager",
        "property"
    ],
    "wof:name":"Rita John D & Rose",
    "wof:placetype":"venue"
},
  "geometry": {"coordinates":[-87.672877,41.658304],"type":"Point"}
}