{
  "type": "Feature",
  "properties": {
    "addr:full":"100 W Roosevelt Rd Ste B8-203 Wheaton IL 60187",
    "addr:housenumber":"100",
    "addr:postcode":"60187",
    "addr:street":"W Roosevelt Rd Ste B8-203",
    "iso:country":"US",
    "sg:address":"100 W Roosevelt Rd Ste B8-203",
    "sg:city":"Wheaton",
    "sg:classifiers":[
        {
            "category":"Building & Trades",
            "subcategory":"Cleaning & Sanitation",
            "type":"Services"
        },
        {
            "category":"Health Services",
            "subcategory":"Health Practitioner",
            "type":"Services"
        }
    ],
    "sg:phone":"+1 630 689 4050",
    "sg:postcode":"60187",
    "sg:province":"IL",
    "sg:tags":[
        "home",
        "care"
    ],
    "sg:website":"www.seniorhelpers.com/wheaton",
    "wof:name":"Senior Helpers",
    "wof:placetype":"venue"
},
  "geometry": {"coordinates":[-88.105952,41.858771],"type":"Point"}
}