{
  "type": "Feature",
  "properties": {
    "addr:full":"2030 Wagner Rd Batavia IL 60510",
    "addr:housenumber":"2030",
    "addr:postcode":"60510",
    "addr:street":"Wagner Rd",
    "iso:country":"US",
    "sg:address":"2030 Wagner Rd",
    "sg:city":"Batavia",
    "sg:classifiers":[
        {
            "category":"Shopping",
            "subcategory":"Computers & Home Electronics",
            "type":"Retail Goods"
        }
    ],
    "sg:phone":"+1 630 879 2160",
    "sg:postcode":"60510",
    "sg:province":"IL",
    "sg:tags":[
        "software"
    ],
    "wof:name":"Mitem Corp",
    "wof:placetype":"venue"
},
  "geometry": {"coordinates":[-88.282258,41.826114],"type":"Point"}
}