{
  "type": "Feature",
  "properties": {
    "iso:country":"US",
    "sg:address":"7020 W 79th St",
    "sg:city":"Bridgeview",
    "sg:classifiers":[
        {
            "category":"Health Services",
            "subcategory":"Doctor",
            "type":"Services"
        }
    ],
    "sg:phone":"+1 708 598 8919",
    "sg:postcode":"60455",
    "sg:province":"IL",
    "wof:name":"B Allarin Leszek MD",
    "wof:placetype":"venue"
},
  "geometry": {"coordinates":[-87.796063,41.748387],"type":"Point"}
}