{
  "type": "Feature",
  "properties": {
    "iso:country":"US",
    "sg:address":"4052 W Grand Ave",
    "sg:city":"Chicago",
    "sg:classifiers":[
        {
            "category":"Home & Garden",
            "subcategory":"Hardware",
            "type":"Retail Goods"
        }
    ],
    "sg:phone":"+1   ",
    "sg:postcode":"60651",
    "sg:province":"IL",
    "wof:name":"Home Owners Bargin Outlet",
    "wof:placetype":"venue"
},
  "geometry": {"coordinates":[-87.727795,41.906773],"type":"Point"}
}