{
  "type": "Feature",
  "properties": {
    "iso:country":"US",
    "sg:address":"5923 N Hermitage Ave",
    "sg:city":"Chicago",
    "sg:classifiers":[
        {
            "category":"Professional",
            "subcategory":"Management & Consulting",
            "type":"Services"
        }
    ],
    "sg:phone":"+1 773 271 7324",
    "sg:postcode":"60660",
    "sg:province":"IL",
    "sg:tags":[
        "book",
        "business"
    ],
    "wof:name":"Hort Concepts",
    "wof:placetype":"venue"
},
  "geometry": {"coordinates":[-87.673096,41.990251],"type":"Point"}
}