{
  "type": "Feature",
  "properties": {
    "iso:country":"US",
    "sg:address":"2120 Roberts Dr",
    "sg:city":"Broadview",
    "sg:classifiers":[
        {
            "category":"Wholesale",
            "subcategory":"Hardware",
            "type":"Manufacturing & Wholesale Goods"
        }
    ],
    "sg:phone":"+1 708 344 0810",
    "sg:postcode":"60155",
    "sg:province":"IL",
    "sg:tags":[
        "refrigeration",
        "con"
    ],
    "wof:name":"Gustave A Larson Company",
    "wof:placetype":"venue"
},
  "geometry": {"coordinates":[-87.857927,41.854069],"type":"Point"}
}