{
  "type": "Feature",
  "properties": {
    "addr:full":"730 S 5th Ave Canton IL 61520",
    "addr:housenumber":"730",
    "addr:postcode":"61520",
    "addr:street":"S 5Th Ave",
    "iso:country":"US",
    "sg:address":"730 S 5th Ave",
    "sg:city":"Canton",
    "sg:classifiers":[
        {
            "category":"Building & Trades",
            "subcategory":"Equipment Rental",
            "type":"Services"
        }
    ],
    "sg:phone":"+1 309 647 2900",
    "sg:postcode":"61520",
    "sg:province":"IL",
    "sg:tags":[
        "yard"
    ],
    "wof:name":"Rent-A-Center",
    "wof:placetype":"venue"
},
  "geometry": {"coordinates":[-90.027604,40.546921],"type":"Point"}
}