{
  "type": "Feature",
  "properties": {
    "iso:country":"US",
    "sg:address":"909 Oakton St",
    "sg:city":"Elk Grove Vlg",
    "sg:classifiers":[
        {
            "category":"Wholesale",
            "subcategory":"Machinery & Supplies",
            "type":"Manufacturing & Wholesale Goods"
        },
        {
            "category":"Wholesale",
            "subcategory":"Electrical",
            "type":"Manufacturing & Wholesale Goods"
        }
    ],
    "sg:phone":"+1 847 952 3730",
    "sg:postcode":"60007",
    "sg:province":"IL",
    "sg:tags":[
        "industrial",
        "clothing",
        "devices",
        "automation",
        "equipment",
        "safety",
        "electronic"
    ],
    "sg:website":"www.bircheramerica.com",
    "wof:name":"Bircher America Inc",
    "wof:placetype":"venue"
},
  "geometry": {"coordinates":[-87.972119,42.022162],"type":"Point"}
}