{
  "type": "Feature",
  "properties": {
    "addr:full":"7368 Countryshire Ln Rockford IL 61107",
    "addr:housenumber":"7368",
    "addr:postcode":"61107",
    "addr:street":"Countryshire Ln",
    "iso:country":"US",
    "sg:address":"7368 Countryshire Ln",
    "sg:city":"Rockford",
    "sg:classifiers":[
        {
            "category":"Banks & Credit Unions",
            "subcategory":"Investment Brokerage",
            "type":"Services"
        }
    ],
    "sg:phone":"+1 815 979 6932",
    "sg:postcode":"61107",
    "sg:province":"IL",
    "sg:tags":[
        "advisory",
        "financial"
    ],
    "wof:name":"Financial Educators",
    "wof:placetype":"venue"
},
  "geometry": {"coordinates":[-88.972166,42.293996],"type":"Point"}
}