{
  "type": "Feature",
  "properties": {
    "addr:full":"226 W Elm St Alton IL 62002",
    "addr:housenumber":"226",
    "addr:postcode":"62002",
    "addr:street":"W Elm St",
    "iso:country":"US",
    "sg:address":"226 W Elm St",
    "sg:city":"Alton",
    "sg:classifiers":[
        {
            "category":"Shopping",
            "subcategory":"Books",
            "type":"Retail Goods"
        },
        {
            "category":"Shopping",
            "type":"Retail Goods"
        }
    ],
    "sg:phone":"+1 618 466 2703",
    "sg:postcode":"62002",
    "sg:province":"IL",
    "sg:tags":[
        "bible",
        "religious",
        "store"
    ],
    "wof:name":"Bibles & More",
    "wof:placetype":"venue"
},
  "geometry": {"coordinates":[-90.189784,38.92089],"type":"Point"}
}