{
  "type": "Feature",
  "properties": {
    "addr:full":"440 N Mcclurg Ct Apt 1215 Chicago IL 60611",
    "addr:housenumber":"440;1215",
    "addr:postcode":"60611",
    "addr:street":"N Mcclurg Ct Apt",
    "iso:country":"US",
    "sg:address":"440 N Mcclurg Ct Apt 1215",
    "sg:city":"Chicago",
    "sg:classifiers":[
        {
            "category":"Professional",
            "subcategory":"Art Services",
            "type":"Services"
        }
    ],
    "sg:phone":"+1 312 799 7599",
    "sg:postcode":"60611",
    "sg:province":"IL",
    "sg:tags":[
        "designer",
        "display",
        "producer"
    ],
    "wof:name":"Kelly Coyle Interior Design",
    "wof:placetype":"venue"
},
  "geometry": {"coordinates":[-87.617683,41.890148],"type":"Point"}
}