{
  "type": "Feature",
  "properties": {
    "iso:country":"US",
    "sg:address":"3001 N Austin Avenue",
    "sg:city":"Chicago",
    "sg:classifiers":[
        {
            "category":"Home & Garden",
            "subcategory":"Garden Supply",
            "type":"Retail Goods"
        }
    ],
    "sg:phone":"+1 773 237 9400",
    "sg:postcode":"60634",
    "sg:province":"IL",
    "sg:website":"www.century-tile.com",
    "wof:name":"Century Tile",
    "wof:placetype":"venue"
},
  "geometry": {"coordinates":[-87.776149,41.934854],"type":"Point"}
}