{
  "type": "Feature",
  "properties": {
    "iso:country":"US",
    "sg:address":"2722 Harlem Ave",
    "sg:city":"Riverside",
    "sg:classifiers":[
        {
            "category":"Personal",
            "subcategory":"Beauty Salon",
            "type":"Services"
        },
        {
            "category":"Personal",
            "subcategory":"Barber",
            "type":"Services"
        }
    ],
    "sg:phone":"+1 708 447 3341",
    "sg:postcode":"60546",
    "sg:province":"IL",
    "sg:tags":[
        "hair",
        "stylist"
    ],
    "wof:name":"Europeana Salon",
    "wof:placetype":"venue"
},
  "geometry": {"coordinates":[-87.803348,41.841668],"type":"Point"}
}