{
  "type": "Feature",
  "properties": {
    "addr:full":"7595 Pulver Dr Rockford IL 61103",
    "addr:housenumber":"7595",
    "addr:postcode":"61103",
    "addr:street":"Pulver Dr",
    "iso:country":"US",
    "sg:address":"7595 Pulver Dr",
    "sg:city":"Rockford",
    "sg:classifiers":[
        {
            "category":"Personal",
            "type":"Services"
        }
    ],
    "sg:phone":"+1 815 654 8550",
    "sg:postcode":"61103",
    "sg:province":"IL",
    "wof:name":"Herbalife International",
    "wof:placetype":"venue"
},
  "geometry": {"coordinates":[-89.05908700000001,42.370719],"type":"Point"}
}