{
  "type": "Feature",
  "properties": {
    "addr:full":"406 Liberty St Morris IL 60450",
    "addr:housenumber":"406",
    "addr:postcode":"60450",
    "addr:street":"Liberty St",
    "iso:country":"US",
    "sg:address":"406 Liberty St",
    "sg:city":"Morris",
    "sg:classifiers":[
        {
            "category":"Education",
            "subcategory":"Dance Studio",
            "type":"Public Place"
        }
    ],
    "sg:phone":"+1 815 942 5686",
    "sg:postcode":"60450",
    "sg:province":"IL",
    "sg:tags":[
        "instruction",
        "dancing"
    ],
    "wof:name":"Carolyn's Toe N' Tap",
    "wof:placetype":"venue"
},
  "geometry": {"coordinates":[-88.423947,41.359595],"type":"Point"}
}