{
  "type": "Feature",
  "properties": {
    "addr:full":"2480 Westchester Ct Aurora IL 60506",
    "addr:housenumber":"2480",
    "addr:postcode":"60506",
    "addr:street":"Westchester Ct",
    "iso:country":"US",
    "sg:address":"2480 Westchester Ct",
    "sg:city":"Aurora",
    "sg:classifiers":[
        {
            "category":"Professional",
            "subcategory":"Lawyer & Legal Services",
            "type":"Services"
        }
    ],
    "sg:phone":"+1 630 264 6100",
    "sg:postcode":"60506",
    "sg:province":"IL",
    "wof:name":"Steven R Robertson",
    "wof:placetype":"venue"
},
  "geometry": {"coordinates":[-88.378024,41.766573],"type":"Point"}
}