{
  "type": "Feature",
  "properties": {
    "addr:full":"381 N York St Elmhurst IL 60126",
    "addr:housenumber":"381",
    "addr:postcode":"60126",
    "addr:street":"N York St",
    "iso:country":"US",
    "sg:address":"381 N York St",
    "sg:city":"Elmhurst",
    "sg:classifiers":[
        {
            "category":"Retail",
            "subcategory":"Laundry & Dry Cleaning",
            "type":"Services"
        }
    ],
    "sg:phone":"+1 630 530 2323",
    "sg:postcode":"60126",
    "sg:province":"IL",
    "sg:tags":[
        "cleaners",
        "rug",
        "carpet"
    ],
    "wof:name":"Coit Drapery & Carpet Cleaners",
    "wof:placetype":"venue"
},
  "geometry": {"coordinates":[-87.939751,41.908816],"type":"Point"}
}