{
  "type": "Feature",
  "properties": {
    "addr:full":"2001 N Alpine Rd Rockford IL 61107",
    "addr:housenumber":"2001",
    "addr:postcode":"61107",
    "addr:street":"N Alpine Rd",
    "iso:country":"US",
    "sg:address":"2001 N Alpine Rd",
    "sg:city":"Rockford",
    "sg:classifiers":[
        {
            "category":"Social Services",
            "type":"Services"
        }
    ],
    "sg:phone":"+1 815 399 5909",
    "sg:postcode":"61107",
    "sg:province":"IL",
    "sg:tags":[
        "counselor",
        "marriage",
        "family"
    ],
    "wof:name":"Another Chance",
    "wof:placetype":"venue"
},
  "geometry": {"coordinates":[-89.02910300000001,42.287867],"type":"Point"}
}