{
  "type": "Feature",
  "properties": {
    "iso:country":"US",
    "sg:address":"5466 E State St",
    "sg:city":"Rockford",
    "sg:classifiers":[
        {
            "category":"Shopping",
            "subcategory":"Optical Goods",
            "type":"Retail Goods"
        }
    ],
    "sg:phone":"+1 815 398 8703",
    "sg:postcode":"61108",
    "sg:province":"IL",
    "sg:tags":[
        "optician"
    ],
    "wof:name":"Eyeglass World",
    "wof:placetype":"venue"
},
  "geometry": {"coordinates":[-89.009471,42.265425],"type":"Point"}
}