{
  "type": "Feature",
  "properties": {
    "iso:country":"US",
    "sg:address":"102 N 1st St",
    "sg:city":"San Jose",
    "sg:classifiers":[
        {
            "category":"Restaurant",
            "type":"Food & Drink"
        }
    ],
    "sg:phone":"+1   ",
    "sg:postcode":"62682",
    "sg:province":"IL",
    "sg:tags":[
        "eating"
    ],
    "wof:name":"Pegs Corner",
    "wof:placetype":"venue"
},
  "geometry": {"coordinates":[-89.602604,40.306038],"type":"Point"}
}