{
  "type": "Feature",
  "properties": {
    "addr:full":"115 N Kennedy Dr Bradley IL 60915",
    "addr:housenumber":"115",
    "addr:postcode":"60915",
    "addr:street":"N Kennedy Dr",
    "iso:country":"US",
    "sg:address":"115 N Kennedy Dr",
    "sg:city":"Bradley",
    "sg:classifiers":[
        {
            "category":"Health Services",
            "subcategory":"Chiropractor",
            "type":"Services"
        }
    ],
    "sg:phone":"+1 815 933 5688",
    "sg:postcode":"60915",
    "sg:province":"IL",
    "wof:name":"David Van Dehey DC",
    "wof:placetype":"venue"
},
  "geometry": {"coordinates":[-87.87603900000001,41.144755],"type":"Point"}
}