{
  "type": "Feature",
  "properties": {
    "iso:country":"US",
    "sg:address":"739 E Roosevelt Rd",
    "sg:city":"Glen Ellyn",
    "sg:classifiers":[
        {
            "category":"Professional",
            "subcategory":"Art Services",
            "type":"Services"
        }
    ],
    "sg:phone":"+1 630 790 0011",
    "sg:postcode":"60137",
    "sg:province":"IL",
    "sg:tags":[
        "graphic",
        "designer"
    ],
    "wof:name":"Belniak Media Works",
    "wof:placetype":"venue"
},
  "geometry": {"coordinates":[-88.055448,41.859324],"type":"Point"}
}