{
  "type": "Feature",
  "properties": {
    "addr:full":"4255 Eldamain Rd Plano IL 60545",
    "addr:housenumber":"4255",
    "addr:postcode":"60545",
    "addr:street":"Eldamain Rd",
    "iso:country":"US",
    "sg:address":"4255 Eldamain Rd",
    "sg:city":"Plano",
    "sg:classifiers":[
        {
            "category":"Retail",
            "subcategory":"Veterinary Services",
            "type":"Services"
        }
    ],
    "sg:phone":"+1 630 552 7804",
    "sg:postcode":"60545",
    "sg:province":"IL",
    "sg:tags":[
        "veterinarian"
    ],
    "sg:website":"http://www.crittercarevet.net",
    "wof:name":"Critter Care",
    "wof:placetype":"venue"
},
  "geometry": {"coordinates":[-88.487846,41.654889],"type":"Point"}
}