{
  "type": "Feature",
  "properties": {
    "addr:full":"650 Albion Ave Schaumburg IL 60193",
    "addr:housenumber":"650",
    "addr:postcode":"60193",
    "addr:street":"Albion Ave",
    "iso:country":"US",
    "sg:address":"650 Albion Ave",
    "sg:city":"Schaumburg",
    "sg:classifiers":[
        {
            "category":"Professional",
            "type":"Services"
        }
    ],
    "sg:phone":"+1 847 891 1656",
    "sg:postcode":"60193",
    "sg:province":"IL",
    "sg:tags":[
        "establishment"
    ],
    "wof:name":"Fox River Sytems",
    "wof:placetype":"venue"
},
  "geometry": {"coordinates":[-88.097605,41.994706],"type":"Point"}
}