{
  "type": "Feature",
  "properties": {
    "addr:full":"1110 3rd St Fulton IL 61252",
    "addr:housenumber":"1110",
    "addr:postcode":"61252",
    "addr:street":"3Rd St",
    "iso:country":"US",
    "sg:address":"1110 3rd St",
    "sg:city":"Fulton",
    "sg:classifiers":[
        {
            "category":"Education",
            "subcategory":"School",
            "type":"Public Place"
        }
    ],
    "sg:phone":"+1 815 589 2711",
    "sg:postcode":"61252",
    "sg:province":"IL",
    "sg:tags":[
        "district"
    ],
    "sg:website":"http://riverbendschools.org/",
    "wof:name":"River Bend Community Unit School District 2",
    "wof:placetype":"venue"
},
  "geometry": {"coordinates":[-90.16668,41.866199],"type":"Point"}
}