{
  "type": "Feature",
  "properties": {
    "addr:full":"107 E Bluff St Winnebago IL 61088",
    "addr:housenumber":"107",
    "addr:postcode":"61088",
    "addr:street":"E Bluff St",
    "iso:country":"US",
    "sg:address":"107 E Bluff St",
    "sg:city":"Winnebago",
    "sg:classifiers":[
        {
            "category":"Building & Trades",
            "subcategory":"Construction",
            "type":"Services"
        }
    ],
    "sg:phone":"+1 815 335 2892",
    "sg:postcode":"61088",
    "sg:province":"IL",
    "sg:tags":[
        "repair",
        "handyman",
        "maintenance",
        "home"
    ],
    "wof:name":"Samuelson Construction",
    "wof:placetype":"venue"
},
  "geometry": {"coordinates":[-89.24131199999999,42.267343],"type":"Point"}
}