{
  "type": "Feature",
  "properties": {
    "iso:country":"US",
    "sg:address":"316 N Alpine Rd",
    "sg:city":"Rockford",
    "sg:classifiers":[
        {
            "category":"Home & Garden",
            "subcategory":"Furniture",
            "type":"Retail Goods"
        }
    ],
    "sg:phone":"+1 815 398 0300",
    "sg:postcode":"61107",
    "sg:province":"IL",
    "wof:name":"Classic Oak Designs",
    "wof:placetype":"venue"
},
  "geometry": {"coordinates":[-89.029159,42.268336],"type":"Point"}
}