{
  "type": "Feature",
  "properties": {
    "iso:country":"US",
    "sg:address":"401 Broadway St",
    "sg:city":"Lincoln",
    "sg:classifiers":[
        {
            "category":"Wholesale",
            "subcategory":"Hardware",
            "type":"Manufacturing & Wholesale Goods"
        }
    ],
    "sg:phone":"+1 217 732 1932",
    "sg:postcode":"62656",
    "sg:province":"IL",
    "sg:tags":[
        "fastener"
    ],
    "wof:name":"Fastenal Co",
    "wof:placetype":"venue"
},
  "geometry": {"coordinates":[-89.365207,40.148579],"type":"Point"}
}