{
  "type": "Feature",
  "properties": {
    "addr:full":"1308 N 7th St Riverton IL 62561",
    "addr:housenumber":"1308",
    "addr:postcode":"62561",
    "addr:street":"N 7Th St",
    "iso:country":"US",
    "sg:address":"1308 N 7th St",
    "sg:city":"Riverton",
    "sg:classifiers":[
        {
            "category":"Social Services",
            "subcategory":"Child Care",
            "type":"Services"
        }
    ],
    "sg:phone":"+1 217 629 8030",
    "sg:postcode":"62561",
    "sg:province":"IL",
    "sg:tags":[
        "nursery",
        "day"
    ],
    "wof:name":"Teddy Bear Christian Daycare And Preschool, Inc",
    "wof:placetype":"venue"
},
  "geometry": {"coordinates":[-89.539688,39.861931],"type":"Point"}
}