{
  "type": "Feature",
  "properties": {
    "iso:country":"US",
    "sg:address":"1349 N Lyle Ave",
    "sg:city":"Elgin",
    "sg:classifiers":[
        {
            "category":"Professional",
            "subcategory":"Management & Consulting",
            "type":"Services"
        }
    ],
    "sg:phone":"+1 847 468 8938",
    "sg:postcode":"60123",
    "sg:province":"IL",
    "sg:tags":[
        "consultant"
    ],
    "wof:name":"Robinson Legal Services LLC",
    "wof:placetype":"venue"
},
  "geometry": {"coordinates":[-88.324601,42.066221],"type":"Point"}
}