{
  "type": "Feature",
  "properties": {
    "iso:country":"US",
    "sg:address":"111 W Maple Street",
    "sg:city":"Chicago",
    "sg:classifiers":[
        {
            "category":"Retail",
            "subcategory":"Laundry & Dry Cleaning",
            "type":"Services"
        }
    ],
    "sg:phone":"+1 312 642 7747",
    "sg:postcode":"60610",
    "sg:province":"IL",
    "wof:name":"Paramount Cleaners",
    "wof:placetype":"venue"
},
  "geometry": {"coordinates":[-87.63172,41.901831],"type":"Point"}
}