{
  "type": "Feature",
  "properties": {
    "addr:full":"2000 Fox Ln Elgin IL 60123",
    "addr:housenumber":"2000",
    "addr:postcode":"60123",
    "addr:street":"Fox Ln",
    "iso:country":"US",
    "sg:address":"2000 Fox Ln",
    "sg:city":"Elgin",
    "sg:classifiers":[
        {
            "category":"Shopping",
            "subcategory":"Stationery & Office Supplies",
            "type":"Retail Goods"
        },
        {
            "category":"Home & Garden",
            "subcategory":"Furniture",
            "type":"Retail Goods"
        }
    ],
    "sg:phone":"+1 847 622 9711",
    "sg:postcode":"60123",
    "sg:province":"IL",
    "sg:tags":[
        "equipment",
        "store"
    ],
    "wof:name":"Rieke Office Interiors",
    "wof:placetype":"venue"
},
  "geometry": {"coordinates":[-88.32409,42.074776],"type":"Point"}
}