{
  "type": "Feature",
  "properties": {
    "iso:country":"US",
    "sg:address":"21517 Eich Dr",
    "sg:city":"Joliet",
    "sg:classifiers":[
        {
            "category":"Building & Trades",
            "subcategory":"Construction",
            "type":"Services"
        }
    ],
    "sg:phone":"+1 815 744 6841",
    "sg:postcode":"60403",
    "sg:province":"IL",
    "sg:tags":[
        "general",
        "contractor"
    ],
    "wof:name":"T B Contracting & Consulting",
    "wof:placetype":"venue"
},
  "geometry": {"coordinates":[-90.011398,38.892272],"type":"Point"}
}