{
  "type": "Feature",
  "properties": {
    "iso:country":"US",
    "sg:address":"1516 Kirkwood Dr",
    "sg:city":"Geneva",
    "sg:classifiers":[
        {
            "category":"Coffee & Tea",
            "type":"Food & Drink"
        },
        {
            "category":"Restaurant",
            "type":"Food & Drink"
        }
    ],
    "sg:phone":"+1 630 208 1104",
    "sg:postcode":"60134",
    "sg:province":"IL",
    "sg:tags":[
        "espresso"
    ],
    "wof:name":"Andrew S Cafe Ltd",
    "wof:placetype":"venue"
},
  "geometry": {"coordinates":[-88.279234,41.891048],"type":"Point"}
}