{
  "type": "Feature",
  "properties": {
    "addr:full":"201 E Main St Clayton IL 62324",
    "addr:housenumber":"201",
    "addr:postcode":"62324",
    "addr:street":"E Main St",
    "iso:country":"US",
    "sg:address":"201 E Main St",
    "sg:city":"Clayton",
    "sg:classifiers":[
        {
            "category":"Organizations",
            "subcategory":"Religious Organization",
            "type":"Services"
        }
    ],
    "sg:phone":"+1 217 894 7105",
    "sg:postcode":"62324",
    "sg:province":"IL",
    "sg:tags":[
        "church"
    ],
    "wof:name":"Clayton Christian Church",
    "wof:placetype":"venue"
},
  "geometry": {"coordinates":[-90.957217,40.031158],"type":"Point"}
}