{
  "type": "Feature",
  "properties": {
    "iso:country":"US",
    "sg:address":"100 S York St",
    "sg:city":"Elmhurst",
    "sg:classifiers":[
        {
            "category":"Banks & Credit Unions",
            "subcategory":"Investment Brokerage",
            "type":"Services"
        }
    ],
    "sg:phone":"+1 630 941 9179",
    "sg:postcode":"60126",
    "sg:province":"IL",
    "sg:tags":[
        "consultant",
        "planning",
        "financial"
    ],
    "wof:name":"Financial Independents Inc",
    "wof:placetype":"venue"
},
  "geometry": {"coordinates":[-87.940001,41.898554],"type":"Point"}
}