{
  "type": "Feature",
  "properties": {
    "iso:country":"US",
    "sg:address":"104 N Broadway",
    "sg:city":"Goreville",
    "sg:classifiers":[
        {
            "category":"Professional",
            "subcategory":"Lawyer & Legal Services",
            "type":"Services"
        }
    ],
    "sg:phone":"+1 618 995 1814",
    "sg:postcode":"62939",
    "sg:province":"IL",
    "sg:tags":[
        "attorney",
        "planning",
        "estate"
    ],
    "wof:name":"Perry, Amy L Attorney At Law",
    "wof:placetype":"venue"
},
  "geometry": {"coordinates":[-88.97223,37.555661],"type":"Point"}
}