{
  "type": "Feature",
  "properties": {
    "addr:full":"1000 3rd St Galena IL 61036",
    "addr:housenumber":"1000",
    "addr:postcode":"61036",
    "addr:street":"3Rd St",
    "iso:country":"US",
    "sg:address":"1000 3rd St",
    "sg:city":"Galena",
    "sg:classifiers":[
        {
            "category":"Travel",
            "subcategory":"Hotels & Motels",
            "type":"Entertainment"
        }
    ],
    "sg:phone":"+1 815 777 3062",
    "sg:postcode":"61036",
    "sg:province":"IL",
    "sg:tags":[
        "country",
        "bed",
        "accommodation",
        "inn",
        "breakfast",
        "operation"
    ],
    "wof:name":"Snoop Sister's Inn",
    "wof:placetype":"venue"
},
  "geometry": {"coordinates":[-90.42756,42.410136],"type":"Point"}
}