{
  "type": "Feature",
  "properties": {
    "addr:full":"972 Main St Crete IL 60417",
    "addr:housenumber":"972",
    "addr:postcode":"60417",
    "addr:street":"Main St",
    "iso:country":"US",
    "sg:address":"972 Main St",
    "sg:city":"Crete",
    "sg:classifiers":[
        {
            "category":"Retail",
            "subcategory":"Auto Repair",
            "type":"Services"
        }
    ],
    "sg:phone":"+1 708 672 1111",
    "sg:postcode":"60417",
    "sg:province":"IL",
    "sg:tags":[
        "repairing",
        "automobile",
        "radiator"
    ],
    "wof:name":"Sibley Radiator & Air Cond Svc",
    "wof:placetype":"venue"
},
  "geometry": {"coordinates":[-87.633551,41.457804],"type":"Point"}
}