{
  "type": "Feature",
  "properties": {
    "iso:country":"US",
    "sg:address":"13701 Kenton Ave",
    "sg:city":"Crestwood",
    "sg:classifiers":[
        {
            "category":"Retail",
            "subcategory":"Repair Shop",
            "type":"Services"
        }
    ],
    "sg:phone":"+1 800 427 4330",
    "sg:postcode":"60445",
    "sg:province":"IL",
    "sg:tags":[
        "equipment",
        "scale",
        "commercial"
    ],
    "sg:website":"http://www.censcale.com",
    "wof:name":"Central Scale & Supply Co Inc",
    "wof:placetype":"venue"
},
  "geometry": {"coordinates":[-87.73304,41.64365],"type":"Point"}
}