{
  "type": "Feature",
  "properties": {
    "iso:country":"US",
    "sg:address":"114 E Sibley Blvd",
    "sg:city":"Dolton",
    "sg:classifiers":[
        {
            "category":"Personal",
            "subcategory":"Barber",
            "type":"Services"
        }
    ],
    "sg:phone":"+1 708 201 0331",
    "sg:postcode":"60419",
    "sg:province":"IL",
    "wof:name":"Stephon Barber's & Beauty Salon",
    "wof:placetype":"venue"
},
  "geometry": {"coordinates":[-87.61920600000001,41.62286],"type":"Point"}
}