{
  "type": "Feature",
  "properties": {
    "iso:country":"US",
    "sg:address":"809 Kimberly Ln",
    "sg:city":"Ottawa",
    "sg:classifiers":[
        {
            "category":"Place Of Worship",
            "type":"Public Place"
        }
    ],
    "sg:phone":"+1 815 431 0135",
    "sg:postcode":"61350",
    "sg:province":"IL",
    "sg:tags":[
        "church"
    ],
    "wof:name":"Rock Regional Church",
    "wof:placetype":"venue"
},
  "geometry": {"coordinates":[-88.846812,41.318556],"type":"Point"}
}