{
  "type": "Feature",
  "properties": {
    "iso:country":"US",
    "sg:address":"5116 Marion Ave",
    "sg:city":"Rockford",
    "sg:classifiers":[
        {
            "category":"Wholesale",
            "subcategory":"Sporting Goods",
            "type":"Manufacturing & Wholesale Goods"
        }
    ],
    "sg:phone":"+1 815 394 4800",
    "sg:postcode":"61108",
    "sg:province":"IL",
    "sg:tags":[
        "equipment",
        "golf",
        "supply"
    ],
    "wof:name":"Discount Golf Wholesalers",
    "wof:placetype":"venue"
},
  "geometry": {"coordinates":[-89.013176,42.249523],"type":"Point"}
}