{
  "type": "Feature",
  "properties": {
    "addr:full":"601 W 8th St Gibson City IL 60936",
    "addr:housenumber":"601",
    "addr:postcode":"60936",
    "addr:street":"W 8Th St",
    "iso:country":"US",
    "sg:address":"601 W 8th St",
    "sg:city":"Gibson City",
    "sg:classifiers":[
        {
            "category":"Retail",
            "subcategory":"Auto Repair",
            "type":"Services"
        }
    ],
    "sg:phone":"+1 217 784 5778",
    "sg:postcode":"60936",
    "sg:province":"IL",
    "sg:tags":[
        "body",
        "automobile",
        "painting"
    ],
    "wof:name":"Styck's Body Shop Inc",
    "wof:placetype":"venue"
},
  "geometry": {"coordinates":[-88.383088,40.465013],"type":"Point"}
}