{
  "type": "Feature",
  "properties": {
    "iso:country":"US",
    "sg:address":"1505 12th St",
    "sg:city":"Lawrenceville",
    "sg:classifiers":[
        {
            "category":"Building & Trades",
            "subcategory":"Construction",
            "type":"Services"
        }
    ],
    "sg:phone":"+1 618 943 5963",
    "sg:postcode":"62439",
    "sg:province":"IL",
    "sg:tags":[
        "system",
        "contractor",
        "air conditioning"
    ],
    "wof:name":"Bud's Heating Air Conditioning & Sheet Metal",
    "wof:placetype":"venue"
},
  "geometry": {"coordinates":[-87.683857,38.722443],"type":"Point"}
}