{
  "type": "Feature",
  "properties": {
    "iso:country":"US",
    "sg:address":"7706 W 66th Pl",
    "sg:city":"Summit Argo",
    "sg:classifiers":[
        {
            "category":"Building & Trades",
            "subcategory":"Plumbing",
            "type":"Services"
        }
    ],
    "sg:phone":"+1 708 458 9911",
    "sg:postcode":"60501",
    "sg:province":"IL",
    "sg:tags":[
        "conditioning",
        "air",
        "system",
        "contractor"
    ],
    "wof:name":"Accurate Heating Cooling",
    "wof:placetype":"venue"
},
  "geometry": {"coordinates":[-87.81513200000001,41.771128],"type":"Point"}
}