{
  "type": "Feature",
  "properties": {
    "iso:country":"US",
    "sg:address":"1420 Miner St",
    "sg:city":"Des Plaines",
    "sg:classifiers":[
        {
            "category":"Government",
            "subcategory":"Office",
            "type":"Public Place"
        }
    ],
    "sg:phone":"+1 847 391 5310",
    "sg:postcode":"60016",
    "sg:province":"IL",
    "sg:tags":[
        "city"
    ],
    "wof:name":"Des Plaines City Clerk",
    "wof:placetype":"venue"
},
  "geometry": {"coordinates":[-87.888077,42.04194],"type":"Point"}
}