{
  "type": "Feature",
  "properties": {
    "iso:country":"US",
    "sg:address":"2704 17th St",
    "sg:city":"Marion",
    "sg:classifiers":[
        {
            "category":"Deli",
            "type":"Food & Drink"
        }
    ],
    "sg:menulink":"http://www.allmenus.com/il/west-marion/93005-mcalisters-deli/menu/",
    "sg:phone":"+1 618 997 1300",
    "sg:postcode":"62959",
    "sg:province":"IL",
    "sg:tags":[
        "wrap",
        "american",
        "sandwich"
    ],
    "wof:name":"Mcalister's Deli",
    "wof:placetype":"venue"
},
  "geometry": {"coordinates":[-88.96549400000001,37.742532],"type":"Point"}
}