{
  "type": "Feature",
  "properties": {
    "iso:country":"US",
    "sg:address":"5237 N Kedzie Avenue",
    "sg:city":"Chicago",
    "sg:classifiers":[
        {
            "category":"Shopping",
            "subcategory":"Jewelry",
            "type":"Retail Goods"
        }
    ],
    "sg:phone":"+1 773 583 4024",
    "sg:postcode":"60625",
    "sg:province":"IL",
    "wof:name":"Mbc Fine Jewlry Distributor",
    "wof:placetype":"venue"
},
  "geometry": {"coordinates":[-87.708831,41.9763],"type":"Point"}
}