{
  "type": "Feature",
  "properties": {
    "iso:country":"US",
    "sg:address":"6072 Brynwood Dr",
    "sg:city":"Rockford",
    "sg:classifiers":[
        {
            "category":"Professional",
            "subcategory":"Lawyer & Legal Services",
            "type":"Services"
        }
    ],
    "sg:phone":"+1 815 282 8228",
    "sg:postcode":"61114",
    "sg:province":"IL",
    "sg:tags":[
        "attorney"
    ],
    "wof:name":"Abate & Smith Counselors",
    "wof:placetype":"venue"
},
  "geometry": {"coordinates":[-88.998205,42.300033],"type":"Point"}
}