{
  "type": "Feature",
  "properties": {
    "addr:full":"1080 Cochran St Aurora IL 60506",
    "addr:housenumber":"1080",
    "addr:postcode":"60506",
    "addr:street":"Cochran St",
    "iso:country":"US",
    "sg:address":"1080 Cochran St",
    "sg:city":"Aurora",
    "sg:classifiers":[
        {
            "category":"Insurance",
            "subcategory":"Hazard Insurance",
            "type":"Services"
        }
    ],
    "sg:phone":"+1 630 892 8670",
    "sg:postcode":"60506",
    "sg:province":"IL",
    "sg:tags":[
        "carrier"
    ],
    "wof:name":"Firemans Fund",
    "wof:placetype":"venue"
},
  "geometry": {"coordinates":[-88.362903,41.77893],"type":"Point"}
}