{
  "type": "Feature",
  "properties": {
    "iso:country":"US",
    "sg:address":"1040 Portsmouth Cir",
    "sg:city":"Gurnee",
    "sg:classifiers":[
        {
            "category":"Utilities",
            "subcategory":"Electric",
            "type":"Services"
        },
        {
            "category":"Manufacturing",
            "subcategory":"Electronics",
            "type":"Manufacturing & Wholesale Goods"
        },
        {
            "category":"Building & Trades",
            "subcategory":"Electrical",
            "type":"Services"
        }
    ],
    "sg:phone":"+1 847 856 1553",
    "sg:postcode":"60031",
    "sg:province":"IL",
    "sg:tags":[
        "industrial",
        "electrician",
        "contractors-commercial",
        "equipment-testing"
    ],
    "sg:website":"http://www.lldelectric.com",
    "wof:name":"L. L. D. Electric Co.",
    "wof:placetype":"venue"
},
  "geometry": {"coordinates":[-87.96826299999999,42.37537],"type":"Point"}
}