{
  "type": "Feature",
  "properties": {
    "iso:country":"US",
    "sg:address":"1932 Industrial Dr",
    "sg:city":"Libertyville",
    "sg:phone":"+1 847 367 6650",
    "sg:postcode":"60048",
    "sg:province":"IL",
    "sg:tags":[
        "scale"
    ],
    "sg:website":"www.systemsassoc.com",
    "wof:name":"Systems Associates Inc",
    "wof:placetype":"venue"
},
  "geometry": {"coordinates":[-88.010154,42.310872],"type":"Point"}
}