{
  "type": "Feature",
  "properties": {
    "iso:country":"US",
    "sg:address":"2775 N Co Rd 2500",
    "sg:city":"La Harpe",
    "sg:classifiers":[
        {
            "category":"Retail",
            "subcategory":"Auto Repair",
            "type":"Services"
        }
    ],
    "sg:phone":"+1 217 659 3748",
    "sg:postcode":"61450",
    "sg:province":"IL",
    "sg:tags":[
        "automobile",
        "electric",
        "automotive"
    ],
    "wof:name":"Cliff's Repair",
    "wof:placetype":"venue"
},
  "geometry": {"coordinates":[-91.022195,40.593166],"type":"Point"}
}