{
  "type": "Feature",
  "properties": {
    "addr:full":"7537 S Roberts Rd Bridgeview IL 60455",
    "addr:housenumber":"7537",
    "addr:postcode":"60455",
    "addr:street":"S Roberts Rd",
    "iso:country":"US",
    "sg:address":"7537 S Roberts Rd",
    "sg:city":"Bridgeview",
    "sg:classifiers":[
        {
            "category":"Taxi",
            "type":"Transportation"
        }
    ],
    "sg:phone":"+1 708 458 7777",
    "sg:postcode":"60455",
    "sg:province":"IL",
    "sg:tags":[
        "taxicab"
    ],
    "wof:name":"Cheap Taxi",
    "wof:placetype":"venue"
},
  "geometry": {"coordinates":[-87.819292,41.753605],"type":"Point"}
}