{
  "type": "Feature",
  "properties": {
    "addr:full":"540 W American St Freeport IL 61032",
    "addr:housenumber":"540",
    "addr:postcode":"61032",
    "addr:street":"W American St",
    "iso:country":"US",
    "sg:address":"540 W American St",
    "sg:city":"Freeport",
    "sg:classifiers":[
        {
            "category":"Travel",
            "subcategory":"Travel Agent",
            "type":"Entertainment"
        }
    ],
    "sg:phone":"+1 815 232 6022",
    "sg:postcode":"61032",
    "sg:province":"IL",
    "sg:tags":[
        "agency",
        "bureau"
    ],
    "wof:name":"Collectables & More",
    "wof:placetype":"venue"
},
  "geometry": {"coordinates":[-89.625579,42.290108],"type":"Point"}
}