{
  "type": "Feature",
  "properties": {
    "iso:country":"US",
    "sg:address":"2508 North Clark",
    "sg:city":"Chicago",
    "sg:classifiers":[
        {
            "category":"Real Estate",
            "subcategory":"Real Estate Operator",
            "type":"Services"
        }
    ],
    "sg:phone":"+1 773 281 3331",
    "sg:postcode":"60614",
    "sg:province":"IL",
    "sg:tags":[
        "apartment"
    ],
    "sg:website":"www.beldenvintageproperties.com/",
    "wof:name":"Belden Properties",
    "wof:placetype":"venue"
},
  "geometry": {"coordinates":[-87.64196800000001,41.928029],"type":"Point"}
}