{
  "type": "Feature",
  "properties": {
    "iso:country":"US",
    "sg:address":"226 Maple Dr",
    "sg:city":"Bethalto",
    "sg:classifiers":[
        {
            "category":"Organizations",
            "subcategory":"Religious Organization",
            "type":"Services"
        }
    ],
    "sg:phone":"+1 618 377 8804",
    "sg:postcode":"62010",
    "sg:province":"IL",
    "sg:tags":[
        "god",
        "churches-church"
    ],
    "sg:website":"http://www.mcogonline.com",
    "wof:name":"First Church of God Meadowbrook",
    "wof:placetype":"venue"
},
  "geometry": {"coordinates":[-90.009197,38.897117],"type":"Point"}
}