{
  "type": "Feature",
  "properties": {
    "addr:full":"131 W Wing St Arlington Heights IL 60005",
    "addr:housenumber":"131",
    "addr:postcode":"60005",
    "addr:street":"W Wing St",
    "iso:country":"US",
    "sg:address":"131 W Wing St",
    "sg:city":"Arlington Heights",
    "sg:classifiers":[
        {
            "category":"Banks & Credit Unions",
            "subcategory":"Bank",
            "type":"Services"
        }
    ],
    "sg:phone":"+1 847 398 2230",
    "sg:postcode":"60005",
    "sg:province":"IL",
    "sg:tags":[
        "federal",
        "savings",
        "institution"
    ],
    "wof:name":"Washington Mutual Bank",
    "wof:placetype":"venue"
},
  "geometry": {"coordinates":[-87.984409,42.083685],"type":"Point"}
}