{
  "type": "Feature",
  "properties": {
    "addr:full":"902 Grand Ave Waukegan IL 60085",
    "addr:housenumber":"902",
    "addr:postcode":"60085",
    "addr:street":"Grand Ave",
    "iso:country":"US",
    "sg:address":"902 Grand Ave",
    "sg:city":"Waukegan",
    "sg:classifiers":[
        {
            "category":"Autos & Motor Vehicles",
            "subcategory":"Fuel & Gas Station",
            "type":"Retail Goods"
        }
    ],
    "sg:phone":"+1 847 662 8585",
    "sg:postcode":"60085",
    "sg:province":"IL",
    "sg:tags":[
        "oil"
    ],
    "wof:name":"Grand Amoco Inc",
    "wof:placetype":"venue"
},
  "geometry": {"coordinates":[-87.84576199999999,42.368719],"type":"Point"}
}