{
  "type": "Feature",
  "properties": {
    "addr:full":"26709 W Wilmot Rd Antioch IL 60002",
    "addr:housenumber":"26709",
    "addr:postcode":"60002",
    "addr:street":"W Wilmot Rd",
    "iso:country":"US",
    "sg:address":"26709 W Wilmot Rd",
    "sg:city":"Antioch",
    "sg:classifiers":[
        {
            "category":"Wholesale",
            "subcategory":"Stationery",
            "type":"Manufacturing & Wholesale Goods"
        },
        {
            "category":"Professional",
            "subcategory":"Art Services",
            "type":"Services"
        }
    ],
    "sg:phone":"+1 847 395 5769",
    "sg:postcode":"60002",
    "sg:province":"IL",
    "sg:tags":[
        "commercial",
        "design",
        "business",
        "form",
        "system"
    ],
    "wof:name":"Graphics Unlimited Inc",
    "wof:placetype":"venue"
},
  "geometry": {"coordinates":[-88.15582499999999,42.491908],"type":"Point"}
}