{
  "type": "Feature",
  "properties": {
    "iso:country":"US",
    "sg:address":"926 Wilma Ln",
    "sg:city":"Elk Grove Village",
    "sg:classifiers":[
        {
            "category":"Communications",
            "subcategory":"Film & Video Production",
            "type":"Services"
        }
    ],
    "sg:phone":"+1 847 895 8681",
    "sg:postcode":"60007",
    "sg:province":"IL",
    "sg:tags":[
        "motion"
    ],
    "wof:name":"All Occasion Productions Inc",
    "wof:placetype":"venue"
},
  "geometry": {"coordinates":[-88.032135,42.000646],"type":"Point"}
}