{
  "type": "Feature",
  "properties": {
    "iso:country":"US",
    "sg:address":"900 Arlington Heights Rd",
    "sg:city":"Arlington Heights",
    "sg:classifiers":[
        {
            "category":"Wholesale",
            "subcategory":"Stationery",
            "type":"Manufacturing & Wholesale Goods"
        }
    ],
    "sg:phone":"+1 847 870 0075",
    "sg:postcode":"60005",
    "sg:province":"IL",
    "sg:tags":[
        "paper"
    ],
    "wof:name":"International Paper",
    "wof:placetype":"venue"
},
  "geometry": {"coordinates":[-87.979981,42.066514],"type":"Point"}
}