{
  "type": "Feature",
  "properties": {
    "iso:country":"US",
    "sg:address":"10610 S Plahm Ct",
    "sg:city":"Worth",
    "sg:classifiers":[
        {
            "category":"Professional",
            "subcategory":"Business Services",
            "type":"Services"
        }
    ],
    "sg:phone":"+1 708 425 4765",
    "sg:postcode":"60482",
    "sg:province":"IL",
    "wof:name":"Saf Enterprises Inc",
    "wof:placetype":"venue"
},
  "geometry": {"coordinates":[-87.790344,41.697742],"type":"Point"}
}