{
  "type": "Feature",
  "properties": {
    "iso:country":"US",
    "sg:address":"2829 W 167th St",
    "sg:city":"Markham",
    "sg:classifiers":[
        {
            "category":"Building & Trades",
            "subcategory":"Landscaping Services",
            "type":"Services"
        }
    ],
    "sg:phone":"+1 708 333 3802",
    "sg:postcode":"60428",
    "sg:province":"IL",
    "sg:tags":[
        "consultant",
        "lawn",
        "designer",
        "landscape",
        "maintenance"
    ],
    "wof:name":"Earth Friendly Lawn Care",
    "wof:placetype":"venue"
},
  "geometry": {"coordinates":[-87.685974,41.5863],"type":"Point"}
}