{
  "type": "Feature",
  "properties": {
    "addr:full":"620 E New York St Aurora IL 60505",
    "addr:housenumber":"620",
    "addr:postcode":"60505",
    "addr:street":"E New York St",
    "iso:country":"US",
    "sg:address":"620 E New York St",
    "sg:city":"Aurora",
    "sg:classifiers":[
        {
            "category":"Shopping",
            "subcategory":"Department Store",
            "type":"Retail Goods"
        },
        {
            "category":"Shopping",
            "subcategory":"Clothing, Apparel, & Fashions",
            "type":"Retail Goods"
        }
    ],
    "sg:phone":"+1 630 851 4137",
    "sg:postcode":"60505",
    "sg:province":"IL",
    "wof:name":"Celia's Fashions",
    "wof:placetype":"venue"
},
  "geometry": {"coordinates":[-88.30145,41.754261],"type":"Point"}
}