{
  "type": "Feature",
  "properties": {
    "addr:full":"13810 Trask Bridge Rd Durand IL 61024",
    "addr:housenumber":"13810",
    "addr:postcode":"61024",
    "addr:street":"Trask Bridge Rd",
    "iso:country":"US",
    "sg:address":"13810 Trask Bridge Rd",
    "sg:city":"Durand",
    "sg:phone":"+1 815 239 2247",
    "sg:postcode":"61024",
    "sg:province":"IL",
    "sg:tags":[
        "farm",
        "grain",
        "cash"
    ],
    "wof:name":"Charles Thomas Derwent",
    "wof:placetype":"venue"
},
  "geometry": {"coordinates":[-89.306585,42.379358],"type":"Point"}
}