{
  "type": "Feature",
  "properties": {
    "addr:full":"2346 S Cicero Ave Cicero IL 60804",
    "addr:housenumber":"2346",
    "addr:postcode":"60804",
    "addr:street":"S Cicero Ave",
    "iso:country":"US",
    "sg:address":"2346 S Cicero Ave",
    "sg:city":"Cicero",
    "sg:classifiers":[
        {
            "category":"Food & Beverages",
            "subcategory":"Groceries & Convenience Stores",
            "type":"Retail Goods"
        }
    ],
    "sg:phone":"+1 708 780 8808",
    "sg:postcode":"60804",
    "sg:province":"IL",
    "wof:name":"Mundo Hispano",
    "wof:placetype":"venue"
},
  "geometry": {"coordinates":[-87.74430099999999,41.848598],"type":"Point"}
}