{
  "type": "Feature",
  "properties": {
    "iso:country":"US",
    "sg:address":"455 Jarvis Ave",
    "sg:city":"Des Plaines",
    "sg:classifiers":[
        {
            "category":"Wholesale",
            "subcategory":"Construction Materials",
            "type":"Manufacturing & Wholesale Goods"
        }
    ],
    "sg:phone":"+1 847 699 2040",
    "sg:postcode":"60018",
    "sg:province":"IL",
    "wof:name":"Northwest Millwork Co",
    "wof:placetype":"venue"
},
  "geometry": {"coordinates":[-87.90893,42.012375],"type":"Point"}
}