{
  "type": "Feature",
  "properties": {
    "addr:full":"5151 W Madison St Chicago IL 60644",
    "addr:housenumber":"5151",
    "addr:postcode":"60644",
    "addr:street":"W Madison St",
    "iso:country":"US",
    "sg:address":"5151 W Madison St",
    "sg:city":"Chicago",
    "sg:classifiers":[
        {
            "category":"Place Of Worship",
            "subcategory":"Church",
            "type":"Public Place"
        },
        {
            "category":"Place Of Worship",
            "type":"Public Place"
        }
    ],
    "sg:phone":"+1 773 626 3800",
    "sg:postcode":"60644",
    "sg:province":"IL",
    "sg:tags":[
        "churches-interdenominational",
        "denomination",
        "churches-various",
        "churches-non-denominational"
    ],
    "sg:website":"http://www.tdcc.org",
    "wof:name":"Truth & Deliverance Christian Center",
    "wof:placetype":"venue"
},
  "geometry": {"coordinates":[-87.754099,41.880393],"type":"Point"}
}