{
  "type": "Feature",
  "properties": {
    "addr:full":"2009 W 75th St Woodridge IL 60517",
    "addr:housenumber":"2009",
    "addr:postcode":"60517",
    "addr:street":"W 75Th St",
    "iso:country":"US",
    "sg:address":"2009 W 75th St",
    "sg:city":"Woodridge",
    "sg:classifiers":[
        {
            "category":"Retail",
            "subcategory":"Veterinary Services",
            "type":"Services"
        }
    ],
    "sg:phone":"+1 630 985 3101",
    "sg:postcode":"60517",
    "sg:province":"IL",
    "wof:name":"Macchia Dennis J",
    "wof:placetype":"venue"
},
  "geometry": {"coordinates":[-88.03121899999999,41.750666],"type":"Point"}
}