{
  "type": "Feature",
  "properties": {
    "iso:country":"US",
    "sg:address":"214 S Main St",
    "sg:city":"Anna",
    "sg:classifiers":[
        {
            "category":"Restaurant",
            "type":"Food & Drink"
        }
    ],
    "sg:phone":"+1 618 833 7552",
    "sg:postcode":"62906",
    "sg:province":"IL",
    "sg:tags":[
        "asian",
        "chinese",
        "pan"
    ],
    "wof:name":"King Wok",
    "wof:placetype":"venue"
},
  "geometry": {"coordinates":[-89.245946,37.461587],"type":"Point"}
}