{
  "type": "Feature",
  "properties": {
    "addr:full":"2180 Glenwood Dyer Rd Lynwood IL 60411",
    "addr:housenumber":"2180",
    "addr:postcode":"60411",
    "addr:street":"Glenwood Dyer Rd",
    "iso:country":"US",
    "sg:address":"2180 Glenwood Dyer Rd",
    "sg:city":"Lynwood",
    "sg:classifiers":[
        {
            "category":"Restaurant",
            "type":"Food & Drink"
        }
    ],
    "sg:phone":"+1 708 474 1000",
    "sg:postcode":"60411",
    "sg:province":"IL",
    "sg:website":"http://angieswarsawinn.com",
    "wof:name":"Warsaw Inn",
    "wof:placetype":"venue"
},
  "geometry": {"coordinates":[-87.563057,41.525485],"type":"Point"}
}