{
  "type": "Feature",
  "properties": {
    "addr:full":"809 W Rand Rd Arlington Hts IL 60004",
    "addr:housenumber":"809",
    "addr:postcode":"60004",
    "addr:street":"W Rand Rd",
    "iso:country":"US",
    "sg:address":"809 W Rand Rd",
    "sg:city":"Arlington Hts",
    "sg:classifiers":[
        {
            "category":"Health Services",
            "subcategory":"Doctor",
            "type":"Services"
        }
    ],
    "sg:phone":"+1 847 394 5750",
    "sg:postcode":"60004",
    "sg:province":"IL",
    "sg:tags":[
        "dentist"
    ],
    "wof:name":"Gilbert X Mendez LTD",
    "wof:placetype":"venue"
},
  "geometry": {"coordinates":[-87.99189699999999,42.120128],"type":"Point"}
}