{
  "type": "Feature",
  "properties": {
    "iso:country":"US",
    "sg:address":"6247 S Pulaski Road",
    "sg:city":"Chicago",
    "sg:classifiers":[
        {
            "category":"Real Estate",
            "subcategory":"Real Estate Services",
            "type":"Services"
        },
        {
            "category":"Professional",
            "subcategory":"Lawyer & Legal Services",
            "type":"Services"
        }
    ],
    "sg:phone":"+1 773 284 5822",
    "sg:postcode":"60629",
    "sg:province":"IL",
    "sg:tags":[
        "management",
        "property"
    ],
    "wof:name":"Steadman Realty",
    "wof:placetype":"venue"
},
  "geometry": {"coordinates":[-87.72256299999999,41.779789],"type":"Point"}
}