{
  "type": "Feature",
  "properties": {
    "addr:full":"301 W A St Belleville IL 62220",
    "addr:housenumber":"301",
    "addr:postcode":"62220",
    "addr:street":"W A St",
    "iso:country":"US",
    "sg:address":"301 W A St",
    "sg:city":"Belleville",
    "sg:classifiers":[
        {
            "category":"Professional",
            "type":"Services"
        }
    ],
    "sg:phone":"+1 618 222 8955",
    "sg:postcode":"62220",
    "sg:province":"IL",
    "sg:tags":[
        "establishment"
    ],
    "wof:name":"Oliver C Joseph Inc",
    "wof:placetype":"venue"
},
  "geometry": {"coordinates":[-89.989901,38.514528],"type":"Point"}
}