{
  "type": "Feature",
  "properties": {
    "iso:country":"US",
    "sg:address":"211 E Illinois St",
    "sg:city":"Wheaton",
    "sg:classifiers":[
        {
            "category":"Personal",
            "subcategory":"Massage",
            "type":"Services"
        }
    ],
    "sg:phone":"+1 630 933 0737",
    "sg:postcode":"60187",
    "sg:province":"IL",
    "wof:name":"Clinical Care Concepts Ltd",
    "wof:placetype":"venue"
},
  "geometry": {"coordinates":[-88.101997,41.864399],"type":"Point"}
}