{
  "type": "Feature",
  "properties": {
    "addr:full":"4249 E State St Rockford IL 61108",
    "addr:housenumber":"4249",
    "addr:postcode":"61108",
    "addr:street":"E State St",
    "iso:country":"US",
    "sg:address":"4249 E State St",
    "sg:city":"Rockford",
    "sg:classifiers":[
        {
            "category":"Organizations",
            "subcategory":"Religious Organization",
            "type":"Services"
        }
    ],
    "sg:phone":"+1 815 397 9644",
    "sg:postcode":"61108",
    "sg:province":"IL",
    "sg:tags":[
        "church"
    ],
    "wof:name":"Lutheran Brotherhood",
    "wof:placetype":"venue"
},
  "geometry": {"coordinates":[-89.035375,42.265297],"type":"Point"}
}