{
  "type": "Feature",
  "properties": {
    "addr:full":"566 W Lake St Chicago IL 60661",
    "addr:housenumber":"566",
    "addr:postcode":"60661",
    "addr:street":"W Lake St",
    "iso:country":"US",
    "sg:address":"566 W Lake St",
    "sg:city":"Chicago",
    "sg:classifiers":[
        {
            "category":"Insurance",
            "subcategory":"Insurance Agent",
            "type":"Services"
        }
    ],
    "sg:phone":"+1 877 503 4001",
    "sg:postcode":"60661",
    "sg:province":"IL",
    "sg:tags":[
        "consultant",
        "analyst"
    ],
    "sg:website":"http://www.highroads.com",
    "wof:name":"Hr Advisory Service",
    "wof:placetype":"venue"
},
  "geometry": {"coordinates":[-87.641767,41.885693],"type":"Point"}
}