{
  "type": "Feature",
  "properties": {
    "iso:country":"US",
    "sg:address":"10540 S Western Avenue Suite 103",
    "sg:city":"Chicago",
    "sg:classifiers":[
        {
            "category":"Professional",
            "subcategory":"Lawyer & Legal Services",
            "type":"Services"
        }
    ],
    "sg:phone":"+1 773 238 5195",
    "sg:postcode":"60643",
    "sg:province":"IL",
    "wof:name":"Plesha Gregory G",
    "wof:placetype":"venue"
},
  "geometry": {"coordinates":[-87.681381,41.701966],"type":"Point"}
}