{
  "type": "Feature",
  "properties": {
    "addr:full":"366 Bluff City Blvd Elgin IL 60120",
    "addr:housenumber":"366",
    "addr:postcode":"60120",
    "addr:street":"Bluff City Blvd",
    "iso:country":"US",
    "sg:address":"366 Bluff City Blvd",
    "sg:city":"Elgin",
    "sg:classifiers":[
        {
            "category":"Building & Trades",
            "subcategory":"Construction",
            "type":"Services"
        }
    ],
    "sg:phone":"+1 847 741 7292",
    "sg:postcode":"60120",
    "sg:province":"IL",
    "sg:tags":[
        "roofing",
        "contractor"
    ],
    "wof:name":"Elgin Roofing Co",
    "wof:placetype":"venue"
},
  "geometry": {"coordinates":[-88.271362,42.01917],"type":"Point"}
}