{
  "type": "Feature",
  "properties": {
    "addr:full":"4422 E New York St Aurora IL 60504",
    "addr:housenumber":"4422",
    "addr:postcode":"60504",
    "addr:street":"E New York St",
    "iso:country":"US",
    "sg:address":"4422 E New York St",
    "sg:city":"Aurora",
    "sg:classifiers":[
        {
            "category":"Banks & Credit Unions",
            "subcategory":"Financial Services",
            "type":"Services"
        }
    ],
    "sg:phone":"+1 630 236 1200",
    "sg:postcode":"60504",
    "sg:province":"IL",
    "sg:tags":[
        "financing",
        "cashing",
        "money",
        "loan",
        "check",
        "payday",
        "order"
    ],
    "sg:website":"http://ad.doubleclick.net/clk;225053199;48888911;w?http://www.checkngo.com?source=yellowpages&cat=TLs&AfsCampaignId=642",
    "wof:name":"Check 'n Go",
    "wof:placetype":"venue"
},
  "geometry": {"coordinates":[-88.20660599999999,41.762402],"type":"Point"}
}