{
  "type": "Feature",
  "properties": {
    "addr:full":"8 N Dunton Ave Arlington Heights IL 60005",
    "addr:housenumber":"8",
    "addr:postcode":"60005",
    "addr:street":"N Dunton Ave",
    "iso:country":"US",
    "sg:address":"8 N Dunton Ave",
    "sg:city":"Arlington Heights",
    "sg:classifiers":[
        {
            "category":"Health Services",
            "subcategory":"Podiatrist",
            "type":"Services"
        }
    ],
    "sg:phone":"+1 847 255 5004",
    "sg:postcode":"60005",
    "sg:province":"IL",
    "wof:name":"Pastore Robin DPM",
    "wof:placetype":"venue"
},
  "geometry": {"coordinates":[-87.982991,42.083176],"type":"Point"}
}