{
  "type": "Feature",
  "properties": {
    "iso:country":"US",
    "sg:address":"1906 E Maya Ln",
    "sg:city":"Mount Prospect",
    "sg:classifiers":[
        {
            "category":"Professional",
            "subcategory":"Art Services",
            "type":"Services"
        }
    ],
    "sg:phone":"+1 847 296 4884",
    "sg:postcode":"60056",
    "sg:province":"IL",
    "sg:tags":[
        "commercial",
        "graphic",
        "design"
    ],
    "wof:name":"Hirt & Associates Inc",
    "wof:placetype":"venue"
},
  "geometry": {"coordinates":[-87.896681,42.098094],"type":"Point"}
}