{
  "type": "Feature",
  "properties": {
    "iso:country":"US",
    "sg:address":"4 N Vermilion St",
    "sg:city":"Danville",
    "sg:classifiers":[
        {
            "category":"Real Estate",
            "subcategory":"Real Estate Agent",
            "type":"Services"
        }
    ],
    "sg:phone":"+1 217 446 0110",
    "sg:postcode":"61832",
    "sg:province":"IL",
    "wof:name":"Norm Paxton Real Estate",
    "wof:placetype":"venue"
},
  "geometry": {"coordinates":[-87.62995,40.12634],"type":"Point"}
}