{
  "type": "Feature",
  "properties": {
    "iso:country":"US",
    "sg:address":"217 W Prairie Ln",
    "sg:city":"Round Lake",
    "sg:classifiers":[
        {
            "category":"Education",
            "subcategory":"Special Training",
            "type":"Public Place"
        }
    ],
    "sg:phone":"+1 847 740 5395",
    "sg:postcode":"60073",
    "sg:province":"IL",
    "wof:name":"Accordion Lab",
    "wof:placetype":"venue"
},
  "geometry": {"coordinates":[-88.089597,42.345219],"type":"Point"}
}