{
  "type": "Feature",
  "properties": {
    "iso:country":"US",
    "sg:address":"125 1st Ave",
    "sg:city":"Silvis",
    "sg:classifiers":[
        {
            "category":"Shopping",
            "subcategory":"Computers & Home Electronics",
            "type":"Retail Goods"
        }
    ],
    "sg:phone":"+1 309 755 9600",
    "sg:postcode":"61282",
    "sg:province":"IL",
    "sg:tags":[
        "equipment",
        "satellite",
        "system"
    ],
    "wof:name":"Midwest Satcom Svc",
    "wof:placetype":"venue"
},
  "geometry": {"coordinates":[-90.424348,41.514835],"type":"Point"}
}