{
  "type": "Feature",
  "properties": {
    "iso:country":"US",
    "sg:address":"1410 N Main St",
    "sg:city":"Rockford",
    "sg:classifiers":[
        {
            "category":"Shopping",
            "subcategory":"Gifts & Souvenirs",
            "type":"Retail Goods"
        }
    ],
    "sg:phone":"+1 815 966 1240",
    "sg:postcode":"61103",
    "sg:province":"IL",
    "sg:tags":[
        "shop"
    ],
    "wof:name":"Cleo's Aroma-Pothecary",
    "wof:placetype":"venue"
},
  "geometry": {"coordinates":[-89.080865,42.287255],"type":"Point"}
}