{
  "type": "Feature",
  "properties": {
    "addr:full":"244 E 35th St Chicago IL 60616",
    "addr:housenumber":"244",
    "addr:postcode":"60616",
    "addr:street":"E 35Th St",
    "iso:country":"US",
    "sg:address":"244 E 35th St",
    "sg:city":"Chicago",
    "sg:classifiers":[
        {
            "category":"Shopping",
            "subcategory":"Mobile Phones",
            "type":"Retail Goods"
        }
    ],
    "sg:phone":"+1 773 891 5102",
    "sg:postcode":"60616",
    "sg:province":"IL",
    "wof:name":"One Two Three Wireless",
    "wof:placetype":"venue"
},
  "geometry": {"coordinates":[-87.620009,41.831216],"type":"Point"}
}