{
  "type": "Feature",
  "properties": {
    "iso:country":"US",
    "sg:address":"7755 W Briar Ct",
    "sg:city":"Frankfort",
    "sg:classifiers":[
        {
            "category":"Shopping",
            "type":"Retail Goods"
        }
    ],
    "sg:phone":"+1   ",
    "sg:postcode":"60423",
    "sg:province":"IL",
    "sg:tags":[
        "merchandise"
    ],
    "wof:name":"Stamp N Stuff",
    "wof:placetype":"venue"
},
  "geometry": {"coordinates":[-87.804429,41.522843],"type":"Point"}
}