{
  "type": "Feature",
  "properties": {
    "addr:full":"305 Moen Ave Joliet IL 60436",
    "addr:housenumber":"305",
    "addr:postcode":"60436",
    "addr:street":"Moen Ave",
    "iso:country":"US",
    "sg:address":"305 Moen Ave",
    "sg:city":"Joliet",
    "sg:classifiers":[
        {
            "category":"Personal",
            "subcategory":"Beauty Salon",
            "type":"Services"
        },
        {
            "category":"Personal",
            "subcategory":"Barber",
            "type":"Services"
        }
    ],
    "sg:phone":"+1 815 741 8435",
    "sg:postcode":"60436",
    "sg:province":"IL",
    "sg:tags":[
        "shop"
    ],
    "wof:name":"Trendsetters",
    "wof:placetype":"venue"
},
  "geometry": {"coordinates":[-88.112071,41.505298],"type":"Point"}
}