{
  "type": "Feature",
  "properties": {
    "addr:full":"5933 W 35th St Cicero IL 60804",
    "addr:housenumber":"5933",
    "addr:postcode":"60804",
    "addr:street":"W 35Th St",
    "iso:country":"US",
    "sg:address":"5933 W 35th St",
    "sg:city":"Cicero",
    "sg:classifiers":[
        {
            "category":"Real Estate",
            "subcategory":"Real Estate Agent",
            "type":"Services"
        }
    ],
    "sg:phone":"+1 708 652 0386",
    "sg:postcode":"60804",
    "sg:province":"IL",
    "wof:name":"Cicero Housing Authority",
    "wof:placetype":"venue"
},
  "geometry": {"coordinates":[-87.77239,41.828876],"type":"Point"}
}