{
  "type": "Feature",
  "properties": {
    "iso:country":"US",
    "sg:address":"2403 W Springfield Ave",
    "sg:city":"Champaign",
    "sg:classifiers":[
        {
            "category":"Health Services",
            "subcategory":"Health Practitioner",
            "type":"Services"
        }
    ],
    "sg:phone":"+1 217 355 5679",
    "sg:postcode":"61821",
    "sg:province":"IL",
    "sg:tags":[
        "acupuncture"
    ],
    "wof:name":"Harmony Healthcare",
    "wof:placetype":"venue"
},
  "geometry": {"coordinates":[-88.28671199999999,40.112649],"type":"Point"}
}