{
  "type": "Feature",
  "properties": {
    "iso:country":"US",
    "sg:address":"1213 Blackhawk Dr",
    "sg:city":"Park Forest",
    "sg:classifiers":[
        {
            "category":"Social Services",
            "type":"Services"
        }
    ],
    "sg:phone":"+1 708 534 3869",
    "sg:postcode":"60466",
    "sg:province":"IL",
    "sg:tags":[
        "counseling",
        "clinical"
    ],
    "wof:name":"Neurotechtonics Inc Nfp",
    "wof:placetype":"venue"
},
  "geometry": {"coordinates":[-87.680307,41.429114],"type":"Point"}
}