{
  "type": "Feature",
  "properties": {
    "addr:full":"105 Plaza Ct Edwardsville IL 62025",
    "addr:housenumber":"105",
    "addr:postcode":"62025",
    "addr:street":"Plaza Ct",
    "iso:country":"US",
    "sg:address":"105 Plaza Ct",
    "sg:city":"Edwardsville",
    "sg:classifiers":[
        {
            "category":"Banks & Credit Unions",
            "subcategory":"Investment Brokerage",
            "type":"Services"
        },
        {
            "category":"Insurance",
            "subcategory":"Hazard Insurance",
            "type":"Services"
        }
    ],
    "sg:phone":"+1 618 656 0120",
    "sg:postcode":"62025",
    "sg:province":"IL",
    "sg:tags":[
        "commercial",
        "agent",
        "business",
        "resume"
    ],
    "sg:website":"http://www.siua.com",
    "wof:name":"Southern Illinois Underwriters",
    "wof:placetype":"venue"
},
  "geometry": {"coordinates":[-89.95505199999999,38.811499],"type":"Point"}
}