{
  "type": "Feature",
  "properties": {
    "addr:full":"701 N Bowman Ave Danville IL 61832",
    "addr:housenumber":"701",
    "addr:postcode":"61832",
    "addr:street":"N Bowman Ave",
    "iso:country":"US",
    "sg:address":"701 N Bowman Ave",
    "sg:city":"Danville",
    "sg:classifiers":[
        {
            "category":"Wholesale",
            "subcategory":"Hardware",
            "type":"Manufacturing & Wholesale Goods"
        }
    ],
    "sg:phone":"+1 217 443 1555",
    "sg:postcode":"61832",
    "sg:province":"IL",
    "sg:tags":[
        "fastener"
    ],
    "wof:name":"Fastenal Co",
    "wof:placetype":"venue"
},
  "geometry": {"coordinates":[-87.61177000000001,40.13612],"type":"Point"}
}