{
  "type": "Feature",
  "properties": {
    "iso:country":"US",
    "sg:address":"4146 W Chicago Avenue",
    "sg:city":"Chicago",
    "sg:classifiers":[
        {
            "category":"Organizations",
            "subcategory":"Religious Organization",
            "type":"Services"
        }
    ],
    "sg:phone":"+1 773 395 6822",
    "sg:postcode":"60651",
    "sg:province":"IL",
    "wof:name":"Tlc Ministries International",
    "wof:placetype":"venue"
},
  "geometry": {"coordinates":[-87.730261,41.89531],"type":"Point"}
}