{
  "type": "Feature",
  "properties": {
    "iso:country":"US",
    "sg:address":"507 W Pine St",
    "sg:city":"Le Roy",
    "sg:classifiers":[
        {
            "category":"Autos & Motor Vehicles",
            "subcategory":"Fuel & Gas Station",
            "type":"Retail Goods"
        }
    ],
    "sg:phone":"+1 309 962 4206",
    "sg:postcode":"61752",
    "sg:province":"IL",
    "sg:tags":[
        "oil"
    ],
    "wof:name":"River City Oil",
    "wof:placetype":"venue"
},
  "geometry": {"coordinates":[-88.76757,40.346211],"type":"Point"}
}