{
  "type": "Feature",
  "properties": {
    "addr:full":"1275 Robin Dr Carol Stream IL 60188",
    "addr:housenumber":"1275",
    "addr:postcode":"60188",
    "addr:street":"Robin Dr",
    "iso:country":"US",
    "sg:address":"1275 Robin Dr",
    "sg:city":"Carol Stream",
    "sg:classifiers":[
        {
            "category":"Restaurant",
            "type":"Food & Drink"
        }
    ],
    "sg:phone":"+1   ",
    "sg:postcode":"60188",
    "sg:province":"IL",
    "sg:tags":[
        "eating"
    ],
    "wof:name":"Barlinos Grille Inc",
    "wof:placetype":"venue"
},
  "geometry": {"coordinates":[-88.16795399999999,41.930233],"type":"Point"}
}