{
  "type": "Feature",
  "properties": {
    "iso:country":"US",
    "sg:address":"404 Park Ln",
    "sg:city":"Wood Dale",
    "sg:classifiers":[
        {
            "category":"Building & Trades",
            "subcategory":"Construction",
            "type":"Services"
        }
    ],
    "sg:phone":"+1 630 766 2179",
    "sg:postcode":"60191",
    "sg:province":"IL",
    "sg:tags":[
        "dry wall",
        "contractor"
    ],
    "wof:name":"Drywall Doctor & Co",
    "wof:placetype":"venue"
},
  "geometry": {"coordinates":[-87.99773500000001,41.961984],"type":"Point"}
}