{
  "type": "Feature",
  "properties": {
    "addr:full":"1401 Redeker Rd Des Plaines IL 60016",
    "addr:housenumber":"1401",
    "addr:postcode":"60016",
    "addr:street":"Redeker Rd Des",
    "iso:country":"US",
    "sg:address":"1401 Redeker Rd",
    "sg:city":"Des Plaines",
    "sg:classifiers":[
        {
            "category":"Manufacturing",
            "subcategory":"Rubber & Plastics",
            "type":"Manufacturing & Wholesale Goods"
        }
    ],
    "sg:phone":"+1 847 827 6100",
    "sg:postcode":"60016",
    "sg:province":"IL",
    "sg:tags":[
        "product",
        "power",
        "mfg"
    ],
    "wof:name":"Stock Gears Inc",
    "wof:placetype":"venue"
},
  "geometry": {"coordinates":[-87.88876999999999,42.053145],"type":"Point"}
}