{
  "type": "Feature",
  "properties": {
    "iso:country":"US",
    "sg:address":"20633 Promethian Way",
    "sg:city":"Olympia Fields",
    "sg:classifiers":[
        {
            "category":"Real Estate",
            "subcategory":"Real Estate Operator",
            "type":"Services"
        }
    ],
    "sg:phone":"+1 708 335 1145",
    "sg:postcode":"60461",
    "sg:province":"IL",
    "sg:tags":[
        "property",
        "management"
    ],
    "wof:name":"Success Realty and MGT Svcs",
    "wof:placetype":"venue"
},
  "geometry": {"coordinates":[-87.68473899999999,41.513898],"type":"Point"}
}