{
  "type": "Feature",
  "properties": {
    "addr:full":"337 N Central Ave Chicago IL 60644",
    "addr:housenumber":"337",
    "addr:postcode":"60644",
    "addr:street":"N Central Ave",
    "iso:country":"US",
    "sg:address":"337 N Central Ave",
    "sg:city":"Chicago",
    "sg:classifiers":[
        {
            "category":"Wholesale",
            "subcategory":"Machinery & Supplies",
            "type":"Manufacturing & Wholesale Goods"
        }
    ],
    "sg:phone":"+1 773 378 2010",
    "sg:postcode":"60644",
    "sg:province":"IL",
    "sg:tags":[
        "equipment",
        "establishment"
    ],
    "wof:name":"Es Discount Beauty Supply",
    "wof:placetype":"venue"
},
  "geometry": {"coordinates":[-87.76499099999999,41.88595],"type":"Point"}
}