{
  "type": "Feature",
  "properties": {
    "addr:full":"109 N 1st St Cary IL 60013",
    "addr:housenumber":"109",
    "addr:postcode":"60013",
    "addr:street":"N 1St St",
    "iso:country":"US",
    "sg:address":"109 N 1st St",
    "sg:city":"Cary",
    "sg:classifiers":[
        {
            "category":"Retail",
            "subcategory":"Laundry & Dry Cleaning",
            "type":"Services"
        }
    ],
    "sg:phone":"+1 847 639 9545",
    "sg:postcode":"60013",
    "sg:province":"IL",
    "sg:tags":[
        "cleaners"
    ],
    "wof:name":"Family Pride Cleaners",
    "wof:placetype":"venue"
},
  "geometry": {"coordinates":[-88.23818,42.210574],"type":"Point"}
}