{
  "type": "Feature",
  "properties": {
    "iso:country":"US",
    "sg:address":"712 E Juniper Dr",
    "sg:city":"Palatine",
    "sg:classifiers":[
        {
            "category":"Building & Trades",
            "subcategory":"Electrical",
            "type":"Services"
        }
    ],
    "sg:phone":"+1 847 359 9789",
    "sg:postcode":"60074",
    "sg:province":"IL",
    "sg:tags":[
        "electric",
        "contractor"
    ],
    "wof:name":"Dailey Electric Inc",
    "wof:placetype":"venue"
},
  "geometry": {"coordinates":[-88.026214,42.130202],"type":"Point"}
}