{
  "type": "Feature",
  "properties": {
    "addr:full":"767 Cemetery Rd Freeburg IL 62243",
    "addr:housenumber":"767",
    "addr:postcode":"62243",
    "addr:street":"Cemetery Rd",
    "iso:country":"US",
    "sg:address":"767 Cemetery Rd",
    "sg:city":"Freeburg",
    "sg:phone":"+1 618 539 3387",
    "sg:postcode":"62243",
    "sg:province":"IL",
    "sg:tags":[
        "farm",
        "wheat"
    ],
    "wof:name":"Larry Rhutasel",
    "wof:placetype":"venue"
},
  "geometry": {"coordinates":[-89.900952,38.423968],"type":"Point"}
}