{
  "type": "Feature",
  "properties": {
    "iso:country":"US",
    "sg:address":"7 Canty Ln",
    "sg:city":"Fairview Heights",
    "sg:classifiers":[
        {
            "category":"Retail",
            "subcategory":"Repair Shop",
            "type":"Services"
        }
    ],
    "sg:phone":"+1 618 398 1200",
    "sg:postcode":"62208",
    "sg:province":"IL",
    "sg:tags":[
        "repairing",
        "lamp"
    ],
    "wof:name":"Mcateers",
    "wof:placetype":"venue"
},
  "geometry": {"coordinates":[-89.992234,38.590214],"type":"Point"}
}