{
  "type": "Feature",
  "properties": {
    "addr:full":"2001 Larkin Ave Elgin IL 60123",
    "addr:housenumber":"2001",
    "addr:postcode":"60123",
    "addr:street":"Larkin Ave",
    "iso:country":"US",
    "sg:address":"2001 Larkin Ave",
    "sg:city":"Elgin",
    "sg:classifiers":[
        {
            "category":"Banks & Credit Unions",
            "subcategory":"Bank",
            "type":"Services"
        }
    ],
    "sg:phone":"+1 847 429 0133",
    "sg:postcode":"60123",
    "sg:province":"IL",
    "wof:name":"State Financial Bank",
    "wof:placetype":"venue"
},
  "geometry": {"coordinates":[-88.32892699999999,42.032316],"type":"Point"}
}