{
  "type": "Feature",
  "properties": {
    "iso:country":"US",
    "sg:address":"509 N West St",
    "sg:city":"Le Roy",
    "sg:classifiers":[
        {
            "category":"Wholesale",
            "subcategory":"Farm Supplies",
            "type":"Manufacturing & Wholesale Goods"
        }
    ],
    "sg:phone":"+1 309 962 8446",
    "sg:postcode":"61752",
    "sg:province":"IL",
    "sg:tags":[
        "feed"
    ],
    "wof:name":"Tucker's Feed & Supply",
    "wof:placetype":"venue"
},
  "geometry": {"coordinates":[-88.764077,40.351542],"type":"Point"}
}