{
  "type": "Feature",
  "properties": {
    "iso:country":"US",
    "sg:address":"219 S Main St",
    "sg:city":"Cherry",
    "sg:classifiers":[
        {
            "category":"Insurance",
            "subcategory":"Hazard Insurance",
            "type":"Services"
        }
    ],
    "sg:phone":"+1 815 894 3310",
    "sg:postcode":"61317",
    "sg:province":"IL",
    "sg:tags":[
        "commercial",
        "business"
    ],
    "wof:name":"Blue Cross",
    "wof:placetype":"venue"
},
  "geometry": {"coordinates":[-89.212987,41.425435],"type":"Point"}
}