{
  "type": "Feature",
  "properties": {
    "iso:country":"US",
    "sg:address":"328 S Austin Blvd",
    "sg:city":"Oak Park",
    "sg:classifiers":[
        {
            "category":"Shopping",
            "subcategory":"Computers & Home Electronics",
            "type":"Retail Goods"
        }
    ],
    "sg:phone":"+1   ",
    "sg:postcode":"60304",
    "sg:province":"IL",
    "sg:tags":[
        "retailer"
    ],
    "wof:name":"Paragon Technology",
    "wof:placetype":"venue"
},
  "geometry": {"coordinates":[-87.774558,41.875186],"type":"Point"}
}