{
  "type": "Feature",
  "properties": {
    "iso:country":"US",
    "sg:address":"2824 Brighton Ln",
    "sg:city":"Bloomington",
    "sg:classifiers":[
        {
            "category":"Shopping",
            "subcategory":"Clothing, Apparel, & Fashions",
            "type":"Retail Goods"
        },
        {
            "category":"Manufacturing",
            "subcategory":"Apparel",
            "type":"Manufacturing & Wholesale Goods"
        }
    ],
    "sg:phone":"+1 309 662 5035",
    "sg:postcode":"61704",
    "sg:province":"IL",
    "sg:tags":[
        "apparel-wholesale",
        "manufacturer",
        "clothing",
        "boys'",
        "women's"
    ],
    "wof:name":"Thompson Products",
    "wof:placetype":"venue"
},
  "geometry": {"coordinates":[-88.93065199999999,40.490002],"type":"Point"}
}