{
  "type": "Feature",
  "properties": {
    "addr:full":"6127 S University Avenue Chicago IL 60637",
    "addr:housenumber":"6127",
    "addr:postcode":"60637",
    "addr:street":"S University Avenue",
    "iso:country":"US",
    "sg:address":"6127 S University Avenue",
    "sg:city":"Chicago",
    "sg:classifiers":[
        {
            "category":"Social Services",
            "subcategory":"Child Care",
            "type":"Services"
        }
    ],
    "sg:phone":"+1 773 753 0600",
    "sg:postcode":"60637",
    "sg:province":"IL",
    "sg:tags":[
        "day"
    ],
    "wof:name":"Lutheran Child and Family Services of Illinois",
    "wof:placetype":"venue"
},
  "geometry": {"coordinates":[-87.59762600000001,41.783319],"type":"Point"}
}