{
  "type": "Feature",
  "properties": {
    "iso:country":"US",
    "sg:address":"401 Alton St",
    "sg:city":"Alton",
    "sg:classifiers":[
        {
            "category":"Manufacturing",
            "subcategory":"Paper Products",
            "type":"Manufacturing & Wholesale Goods"
        }
    ],
    "sg:phone":"+1 618 463 6000",
    "sg:postcode":"62002",
    "sg:province":"IL",
    "sg:tags":[
        "box"
    ],
    "sg:website":"www.smurfit-stonecontainerboard.com",
    "wof:name":"Smurfit-Stone Container Corp",
    "wof:placetype":"venue"
},
  "geometry": {"coordinates":[-90.181806,38.89234],"type":"Point"}
}