{
  "type": "Feature",
  "properties": {
    "addr:full":"210 N 3rd St Coulterville IL 62237",
    "addr:housenumber":"210",
    "addr:postcode":"62237",
    "addr:street":"N 3Rd St",
    "iso:country":"US",
    "sg:address":"210 N 3rd St",
    "sg:city":"Coulterville",
    "sg:classifiers":[
        {
            "category":"Building & Trades",
            "subcategory":"Construction",
            "type":"Services"
        }
    ],
    "sg:phone":"+1 618 758 2573",
    "sg:postcode":"62237",
    "sg:province":"IL",
    "sg:tags":[
        "marking",
        "maintenance",
        "parking"
    ],
    "wof:name":"Jake Malott",
    "wof:placetype":"venue"
},
  "geometry": {"coordinates":[-89.602706,38.187605],"type":"Point"}
}