{
  "type": "Feature",
  "properties": {
    "iso:country":"US",
    "sg:address":"713 N Michigan Avenue",
    "sg:city":"Chicago",
    "sg:classifiers":[
        {
            "category":"Shopping",
            "subcategory":"Department Store",
            "type":"Retail Goods"
        },
        {
            "category":"Shopping",
            "subcategory":"Clothing, Apparel, & Fashions",
            "type":"Retail Goods"
        }
    ],
    "sg:phone":"+1 312 915 0060",
    "sg:postcode":"60611",
    "sg:province":"IL",
    "sg:tags":[
        "apparel",
        "clothing",
        "boys'",
        "glove",
        "women's"
    ],
    "sg:website":"http://BrooksBrothers.com",
    "wof:name":"Brooks Brothers",
    "wof:placetype":"venue"
},
  "geometry": {"coordinates":[-87.62430999999999,41.895195],"type":"Point"}
}