{
  "type": "Feature",
  "properties": {
    "addr:full":"415 Jane Ave Lemont IL 60439",
    "addr:housenumber":"415",
    "addr:postcode":"60439",
    "addr:street":"Jane Ave",
    "iso:country":"US",
    "sg:address":"415 Jane Ave",
    "sg:city":"Lemont",
    "sg:classifiers":[
        {
            "category":"Manufacturing",
            "subcategory":"Glass & Minerals",
            "type":"Manufacturing & Wholesale Goods"
        }
    ],
    "sg:phone":"+1 630 243 1537",
    "sg:postcode":"60439",
    "sg:province":"IL",
    "sg:tags":[
        "structural"
    ],
    "wof:name":"ARK Builders Inc",
    "wof:placetype":"venue"
},
  "geometry": {"coordinates":[-87.973071,41.65657],"type":"Point"}
}