{
  "type": "Feature",
  "properties": {
    "addr:full":"6400 W Fullerton Ave Chicago IL 60707",
    "addr:housenumber":"6400",
    "addr:postcode":"60707",
    "addr:street":"W Fullerton Ave",
    "iso:country":"US",
    "sg:address":"6400 W Fullerton Ave",
    "sg:city":"Chicago",
    "sg:classifiers":[
        {
            "category":"Fast Food",
            "type":"Food & Drink"
        }
    ],
    "sg:phone":"+1 773 237 6559",
    "sg:postcode":"60707",
    "sg:province":"IL",
    "wof:name":"Burger King",
    "wof:placetype":"venue"
},
  "geometry": {"coordinates":[-87.785872,41.924017],"type":"Point"}
}