{
  "type": "Feature",
  "properties": {
    "addr:full":"400 N Kennedy Dr Bradley IL 60915",
    "addr:housenumber":"400",
    "addr:postcode":"60915",
    "addr:street":"N Kennedy Dr",
    "iso:country":"US",
    "sg:address":"400 N Kennedy Dr",
    "sg:city":"Bradley",
    "sg:classifiers":[
        {
            "category":"Health Services",
            "subcategory":"Doctor",
            "type":"Services"
        }
    ],
    "sg:phone":"+1 815 932 3132",
    "sg:postcode":"60915",
    "sg:province":"IL",
    "sg:tags":[
        "physician",
        "surgeon"
    ],
    "wof:name":"Carolyn Rivera-Garcia MD",
    "wof:placetype":"venue"
},
  "geometry": {"coordinates":[-87.875491,41.147065],"type":"Point"}
}