{
  "type": "Feature",
  "properties": {
    "iso:country":"US",
    "sg:address":"1455 McKinley Ave",
    "sg:city":"Belvidere",
    "sg:classifiers":[
        {
            "category":"Education",
            "subcategory":"Special Training",
            "type":"Public Place"
        }
    ],
    "sg:phone":"+1 815 547 5585",
    "sg:postcode":"61008",
    "sg:province":"IL",
    "wof:name":"Drivers Edge Driving School",
    "wof:placetype":"venue"
},
  "geometry": {"coordinates":[-88.84142799999999,42.274598],"type":"Point"}
}