{
  "type": "Feature",
  "properties": {
    "addr:full":"4153 166th St Oak Forest IL 60452",
    "addr:housenumber":"4153",
    "addr:postcode":"60452",
    "addr:street":"166Th St",
    "iso:country":"US",
    "sg:address":"4153 166th St",
    "sg:city":"Oak Forest",
    "sg:classifiers":[
        {
            "category":"Health Services",
            "subcategory":"Clinic",
            "type":"Services"
        }
    ],
    "sg:phone":"+1 708 596 7701",
    "sg:postcode":"60452",
    "sg:province":"IL",
    "wof:name":"Tiara Medical Systems Inc",
    "wof:placetype":"venue"
},
  "geometry": {"coordinates":[-87.716887,41.587743],"type":"Point"}
}