{
  "type": "Feature",
  "properties": {
    "iso:country":"US",
    "sg:address":"303 Elles Ave",
    "sg:city":"Carterville",
    "sg:classifiers":[
        {
            "category":"Building & Trades",
            "subcategory":"Plumbing",
            "type":"Services"
        }
    ],
    "sg:phone":"+1 618 985 6259",
    "sg:postcode":"62918",
    "sg:province":"IL",
    "sg:tags":[
        "plumbing",
        "contractor"
    ],
    "wof:name":"Reed's Plumbing",
    "wof:placetype":"venue"
},
  "geometry": {"coordinates":[-89.078928,37.754697],"type":"Point"}
}