{
  "type": "Feature",
  "properties": {
    "iso:country":"US",
    "sg:address":"2751 E 1350th Ave",
    "sg:city":"Oblong",
    "sg:classifiers":[
        {
            "category":"Manufacturing",
            "subcategory":"Buildings",
            "type":"Manufacturing & Wholesale Goods"
        },
        {
            "category":"Home & Garden",
            "subcategory":"Building Materials",
            "type":"Retail Goods"
        },
        {
            "category":"Building & Trades",
            "subcategory":"Construction",
            "type":"Services"
        }
    ],
    "sg:phone":"+1 618 592 4625",
    "sg:postcode":"62449",
    "sg:province":"IL",
    "sg:tags":[
        "roofing",
        "industrial",
        "excavation",
        "builder",
        "contractor",
        "concrete",
        "contractors-commercial",
        "staining"
    ],
    "wof:name":"E H Mehler Construction",
    "wof:placetype":"venue"
},
  "geometry": {"coordinates":[-87.898319,39.049297],"type":"Point"}
}