{
  "type": "Feature",
  "properties": {
    "addr:full":"760 W. Jackson Boulevard Chicago IL 60657",
    "addr:housenumber":"760",
    "addr:postcode":"60657",
    "addr:street":"W. Jackson Boulevard",
    "iso:country":"US",
    "sg:address":"760 W. Jackson Boulevard",
    "sg:city":"Chicago",
    "sg:classifiers":[
        {
            "category":"Restaurant",
            "type":"Food & Drink"
        }
    ],
    "sg:phone":"+1 312 906 9885",
    "sg:postcode":"60657",
    "sg:province":"IL",
    "sg:tags":[
        "middle",
        "eastern"
    ],
    "wof:name":"Kabab Luxor",
    "wof:placetype":"venue"
},
  "geometry": {"coordinates":[-87.646698,41.878101],"type":"Point"}
}