{
  "type": "Feature",
  "properties": {
    "addr:full":"2013 W Division St Chicago IL 60622",
    "addr:housenumber":"2013",
    "addr:postcode":"60622",
    "addr:street":"W Division St",
    "iso:country":"US",
    "sg:address":"2013 W Division St",
    "sg:city":"Chicago",
    "sg:classifiers":[
        {
            "category":"Restaurant",
            "type":"Food & Drink"
        }
    ],
    "sg:phone":"+1 773 235 7310",
    "sg:postcode":"60622",
    "sg:province":"IL",
    "sg:tags":[
        "mexican",
        "french"
    ],
    "sg:website":"www.saborsaveur.com/",
    "wof:name":"Sabor Saveur",
    "wof:placetype":"venue"
},
  "geometry": {"coordinates":[-87.677843,41.902893],"type":"Point"}
}