{
  "type": "Feature",
  "properties": {
    "iso:country":"US",
    "sg:address":"3511 37th St",
    "sg:city":"Rock Island",
    "sg:classifiers":[
        {
            "category":"Professional",
            "subcategory":"Accounting & Tax Preparation",
            "type":"Services"
        }
    ],
    "sg:phone":"+1 309 786 4108",
    "sg:postcode":"61201",
    "sg:province":"IL",
    "wof:name":"Wm D Osmundson",
    "wof:placetype":"venue"
},
  "geometry": {"coordinates":[-90.548964,41.474687],"type":"Point"}
}