{
  "type": "Feature",
  "properties": {
    "addr:full":"202 4th St Hillsdale IL 61257",
    "addr:housenumber":"202",
    "addr:postcode":"61257",
    "addr:street":"4Th St",
    "iso:country":"US",
    "sg:address":"202 4th St",
    "sg:city":"Hillsdale",
    "sg:classifiers":[
        {
            "category":"Food & Beverages",
            "subcategory":"Groceries & Convenience Stores",
            "type":"Retail Goods"
        }
    ],
    "sg:phone":"+1 309 658 2232",
    "sg:postcode":"61257",
    "sg:province":"IL",
    "wof:name":"Hill & Dell Oil Co",
    "wof:placetype":"venue"
},
  "geometry": {"coordinates":[-90.17633600000001,41.612588],"type":"Point"}
}