{
  "type": "Feature",
  "properties": {
    "iso:country":"US",
    "sg:address":"730 Hastings Dr",
    "sg:city":"Buffalo Grove",
    "sg:classifiers":[
        {
            "category":"Wholesale",
            "subcategory":"Durable Goods & Equipment",
            "type":"Manufacturing & Wholesale Goods"
        }
    ],
    "sg:phone":"+1 847 459 7590",
    "sg:postcode":"60089",
    "sg:province":"IL",
    "sg:tags":[
        "professional"
    ],
    "wof:name":"Detari",
    "wof:placetype":"venue"
},
  "geometry": {"coordinates":[-87.940337,42.160065],"type":"Point"}
}