{
  "type": "Feature",
  "properties": {
    "addr:full":"10240 Samuel Rd Carterville IL 62918",
    "addr:housenumber":"10240",
    "addr:postcode":"62918",
    "addr:street":"Samuel Rd",
    "iso:country":"US",
    "sg:address":"10240 Samuel Rd",
    "sg:city":"Carterville",
    "sg:classifiers":[
        {
            "category":"Sports & Exercise",
            "subcategory":"Bowling",
            "type":"Entertainment"
        }
    ],
    "sg:phone":"+1   ",
    "sg:postcode":"62918",
    "sg:province":"IL",
    "sg:tags":[
        "outdoor",
        "bar",
        "volleyball",
        "lounge",
        "sand",
        "alley",
        "co"
    ],
    "wof:name":"Coo Coos",
    "wof:placetype":"venue"
},
  "geometry": {"coordinates":[-89.044822,37.75427],"type":"Point"}
}