{
  "type": "Feature",
  "properties": {
    "iso:country":"US",
    "sg:address":"626 E Lincolnway",
    "sg:city":"Morrison",
    "sg:classifiers":[
        {
            "category":"Health Services",
            "subcategory":"Chiropractor",
            "type":"Services"
        }
    ],
    "sg:phone":"+1 815 772 7114",
    "sg:postcode":"61270",
    "sg:province":"IL",
    "wof:name":"Complete Wellness Medical Ctr",
    "wof:placetype":"venue"
},
  "geometry": {"coordinates":[-89.95653,41.807384],"type":"Point"}
}