{
  "type": "Feature",
  "properties": {
    "iso:country":"US",
    "sg:address":"7425 W Ute Ln",
    "sg:city":"Palos Heights",
    "sg:classifiers":[
        {
            "category":"Travel",
            "subcategory":"Travel Agent",
            "type":"Entertainment"
        }
    ],
    "sg:phone":"+1 312 318 6606",
    "sg:postcode":"60463",
    "sg:province":"IL",
    "sg:tags":[
        "agency"
    ],
    "wof:name":"Sherry A Meyer",
    "wof:placetype":"venue"
},
  "geometry": {"coordinates":[-87.802062,41.65389],"type":"Point"}
}