{
  "type": "Feature",
  "properties": {
    "addr:full":"325 N 25th Rd Peru IL 61354",
    "addr:housenumber":"325",
    "addr:postcode":"61354",
    "addr:street":"N 25Th Rd",
    "iso:country":"US",
    "sg:address":"325 N 25th Rd",
    "sg:city":"Peru",
    "sg:classifiers":[
        {
            "category":"Retail",
            "subcategory":"Auto Repair",
            "type":"Services"
        }
    ],
    "sg:phone":"+1   ",
    "sg:postcode":"61354",
    "sg:province":"IL",
    "sg:tags":[
        "body",
        "shop",
        "used",
        "car",
        "truck",
        "automotive"
    ],
    "wof:name":"Supans Wheels",
    "wof:placetype":"venue"
},
  "geometry": {"coordinates":[-89.104541,41.295145],"type":"Point"}
}