{
  "type": "Feature",
  "properties": {
    "iso:country":"US",
    "sg:address":"4901 W Warwick Ave",
    "sg:city":"Chicago",
    "sg:classifiers":[
        {
            "category":"Professional",
            "type":"Services"
        }
    ],
    "sg:phone":"+1 773 794 0504",
    "sg:postcode":"60641",
    "sg:province":"IL",
    "wof:name":"Matcha & More",
    "wof:placetype":"venue"
},
  "geometry": {"coordinates":[-87.75210199999999,41.9488],"type":"Point"}
}