{
  "type": "Feature",
  "properties": {
    "iso:country":"US",
    "sg:address":"440 Southgate St",
    "sg:city":"Lincoln",
    "sg:classifiers":[
        {
            "category":"Building & Trades",
            "subcategory":"Construction",
            "type":"Services"
        }
    ],
    "sg:phone":"+1 217 732 3434",
    "sg:postcode":"62656",
    "sg:province":"IL",
    "sg:tags":[
        "road",
        "contractor"
    ],
    "wof:name":"Ed Koehler & Son Construction",
    "wof:placetype":"venue"
},
  "geometry": {"coordinates":[-89.341837,40.162461],"type":"Point"}
}