{
  "type": "Feature",
  "properties": {
    "addr:full":"3314 N Hamlin # 1 Chicago IL 60618",
    "addr:housenumber":"3314",
    "addr:postcode":"60618",
    "addr:street":"N Hamlin # 1",
    "iso:country":"US",
    "sg:address":"3314 N Hamlin # 1",
    "sg:city":"Chicago",
    "sg:classifiers":[
        {
            "category":"Shopping",
            "subcategory":"Jewelry",
            "type":"Retail Goods"
        }
    ],
    "sg:phone":"+1 630 502 9222",
    "sg:postcode":"60618",
    "sg:province":"IL",
    "sg:website":"www.nicolejamesjewelry.com",
    "wof:name":"Nicole James Jewelry",
    "wof:placetype":"venue"
},
  "geometry": {"coordinates":[-87.722615,41.941361],"type":"Point"}
}