{
  "type": "Feature",
  "properties": {
    "addr:full":"203 N Wabash Ave Chicago IL 60601",
    "addr:housenumber":"203",
    "addr:postcode":"60601",
    "addr:street":"N Wabash Ave",
    "iso:country":"US",
    "sg:address":"203 N Wabash Ave",
    "sg:city":"Chicago",
    "sg:classifiers":[
        {
            "category":"Professional",
            "subcategory":"Computer Services",
            "type":"Services"
        }
    ],
    "sg:phone":"+1 312 977 9800",
    "sg:postcode":"60601",
    "sg:province":"IL",
    "sg:tags":[
        "repair",
        "designer",
        "network",
        "technical",
        "consultant",
        "assistance",
        "system",
        "design",
        "equipment-service",
        "support"
    ],
    "sg:website":"http://www.inventtechnology.com",
    "wof:name":"Tech Support",
    "wof:placetype":"venue"
},
  "geometry": {"coordinates":[-87.626266,41.885784],"type":"Point"}
}