{
  "type": "Feature",
  "properties": {
    "addr:full":"1810 Walters Ave Northbrook IL 60062",
    "addr:housenumber":"1810",
    "addr:postcode":"60062",
    "addr:street":"Walters Ave",
    "iso:country":"US",
    "sg:address":"1810 Walters Ave",
    "sg:city":"Northbrook",
    "sg:classifiers":[
        {
            "category":"Park",
            "type":"Public Place"
        }
    ],
    "sg:phone":"+1 847 562 5782",
    "sg:postcode":"60062",
    "sg:province":"IL",
    "sg:website":"http://www.nbparks.org",
    "wof:name":"Northbrook Park District - Village Green Center",
    "wof:placetype":"venue"
},
  "geometry": {"coordinates":[-87.82541999999999,42.127325],"type":"Point"}
}