{
  "type": "Feature",
  "properties": {
    "addr:full":"1085 Johnson Dr Buffalo Grove IL 60089",
    "addr:housenumber":"1085",
    "addr:postcode":"60089",
    "addr:street":"Johnson Dr",
    "iso:country":"US",
    "sg:address":"1085 Johnson Dr",
    "sg:city":"Buffalo Grove",
    "sg:classifiers":[
        {
            "category":"Manufacturing",
            "subcategory":"Tools & Machinery",
            "type":"Manufacturing & Wholesale Goods"
        }
    ],
    "sg:phone":"+1 847 279 0627",
    "sg:postcode":"60089",
    "sg:province":"IL",
    "sg:tags":[
        "equipment",
        "lighting",
        "commercial",
        "fixture",
        "mfg"
    ],
    "wof:name":"Security Lighting Systems",
    "wof:placetype":"venue"
},
  "geometry": {"coordinates":[-87.92896500000001,42.154067],"type":"Point"}
}