{
  "type": "Feature",
  "properties": {
    "iso:country":"US",
    "sg:address":"855 Cog Cir",
    "sg:city":"Crystal Lake",
    "sg:classifiers":[
        {
            "category":"Bars & Pubs",
            "type":"Food & Drink"
        }
    ],
    "sg:menulink":"http://www.allmenus.com/il/algonquin/185542-barnellis-pasta-bowl/menu/",
    "sg:phone":"+1 815 788 0800",
    "sg:postcode":"60014",
    "sg:province":"IL",
    "sg:tags":[
        "italian"
    ],
    "wof:name":"Barnelli's Pasta Bowl",
    "wof:placetype":"venue"
},
  "geometry": {"coordinates":[-88.29023100000001,42.226842],"type":"Point"}
}