{
  "type": "Feature",
  "properties": {
    "iso:country":"US",
    "sg:address":"401 E Ontario St",
    "sg:city":"Chicago",
    "sg:classifiers":[
        {
            "category":"Shopping",
            "subcategory":"Pets & Pet Supplies",
            "type":"Retail Goods"
        },
        {
            "category":"Retail",
            "subcategory":"Pet Boarding",
            "type":"Services"
        }
    ],
    "sg:phone":"+1 312 787 7792",
    "sg:postcode":"60611",
    "sg:province":"IL",
    "sg:tags":[
        "boarding/pet",
        "store",
        "groomers",
        "sitting"
    ],
    "wof:name":"Streeterville Pet Spa & Boutique",
    "wof:placetype":"venue"
},
  "geometry": {"coordinates":[-87.61694,41.893397],"type":"Point"}
}