{
  "type": "Feature",
  "properties": {
    "iso:country":"US",
    "sg:address":"409 Front St",
    "sg:city":"Mc Henry",
    "sg:classifiers":[
        {
            "category":"Shopping",
            "subcategory":"Clothing, Apparel, & Fashions",
            "type":"Retail Goods"
        }
    ],
    "sg:phone":"+1   ",
    "sg:postcode":"60050",
    "sg:province":"IL",
    "sg:tags":[
        "retailer"
    ],
    "wof:name":"Motherhood Memories Inc",
    "wof:placetype":"venue"
},
  "geometry": {"coordinates":[-88.27451600000001,42.332625],"type":"Point"}
}