{
  "type": "Feature",
  "properties": {
    "addr:full":"474 E Il Route 173 Antioch IL 60002",
    "addr:housenumber":"474",
    "addr:postcode":"60002",
    "addr:street":"E Il Route 173",
    "iso:country":"US",
    "sg:address":"474 E Il Route 173",
    "sg:city":"Antioch",
    "sg:classifiers":[
        {
            "category":"Autos & Motor Vehicles",
            "subcategory":"Auto Supplies",
            "type":"Retail Goods"
        },
        {
            "category":"Retail",
            "subcategory":"Auto Repair",
            "type":"Services"
        }
    ],
    "sg:phone":"+1 847 395 2345",
    "sg:postcode":"60002",
    "sg:province":"IL",
    "sg:tags":[
        "tire"
    ],
    "sg:website":"www.fasttire.us",
    "wof:name":"Fast Tire",
    "wof:placetype":"venue"
},
  "geometry": {"coordinates":[-88.055787,42.466407],"type":"Point"}
}