{
  "type": "Feature",
  "properties": {
    "iso:country":"US",
    "sg:address":"4418 Windswept Way",
    "sg:city":"Loves Park",
    "sg:classifiers":[
        {
            "category":"Restaurant",
            "type":"Food & Drink"
        }
    ],
    "sg:phone":"+1 815 637 2097",
    "sg:postcode":"61111",
    "sg:province":"IL",
    "sg:tags":[
        "parlor",
        "ice",
        "cream"
    ],
    "wof:name":"WCB Ice Cream",
    "wof:placetype":"venue"
},
  "geometry": {"coordinates":[-88.99391300000001,42.324677],"type":"Point"}
}