{
  "type": "Feature",
  "properties": {
    "iso:country":"US",
    "sg:address":"212 Richard Ave",
    "sg:city":"Dupo",
    "sg:classifiers":[
        {
            "category":"Home & Garden",
            "subcategory":"Building Materials",
            "type":"Retail Goods"
        }
    ],
    "sg:phone":"+1 618 286 5050",
    "sg:postcode":"62239",
    "sg:province":"IL",
    "sg:tags":[
        "glass",
        "window",
        "plate"
    ],
    "wof:name":"All Glass",
    "wof:placetype":"venue"
},
  "geometry": {"coordinates":[-90.199449,38.533739],"type":"Point"}
}