{
  "type": "Feature",
  "properties": {
    "addr:full":"5313 N Sheridan Road Chicago IL 60640",
    "addr:housenumber":"5313",
    "addr:postcode":"60640",
    "addr:street":"N Sheridan Road",
    "iso:country":"US",
    "sg:address":"5313 N Sheridan Road",
    "sg:city":"Chicago",
    "sg:classifiers":[
        {
            "category":"Retail",
            "subcategory":"Auto Rental",
            "type":"Services"
        }
    ],
    "sg:phone":"+1 773 271 4500",
    "sg:postcode":"60640",
    "sg:province":"IL",
    "sg:tags":[
        "car"
    ],
    "sg:website":"www.enterprise.com",
    "wof:name":"Enterprise Rent-A-Car",
    "wof:placetype":"venue"
},
  "geometry": {"coordinates":[-87.655199,41.978676],"type":"Point"}
}