{
  "type": "Feature",
  "properties": {
    "addr:full":"2204 State St Chester IL 62233",
    "addr:housenumber":"2204",
    "addr:postcode":"62233",
    "addr:street":"State St",
    "iso:country":"US",
    "sg:address":"2204 State St",
    "sg:city":"Chester",
    "sg:classifiers":[
        {
            "category":"Shopping",
            "subcategory":"Used Merchandise",
            "type":"Retail Goods"
        }
    ],
    "sg:phone":"+1 618 826 5124",
    "sg:postcode":"62233",
    "sg:province":"IL",
    "sg:tags":[
        "furniture"
    ],
    "wof:name":"Buy & Save",
    "wof:placetype":"venue"
},
  "geometry": {"coordinates":[-89.80524,37.926841],"type":"Point"}
}