{
  "type": "Feature",
  "properties": {
    "iso:country":"US",
    "sg:address":"5513 E Lake Dr",
    "sg:city":"Lisle",
    "sg:classifiers":[
        {
            "category":"Wholesale",
            "subcategory":"Groceries",
            "type":"Manufacturing & Wholesale Goods"
        }
    ],
    "sg:phone":"+1 630 969 2354",
    "sg:postcode":"60532",
    "sg:province":"IL",
    "sg:tags":[
        "general"
    ],
    "wof:name":"Creative Foods Products Inc",
    "wof:placetype":"venue"
},
  "geometry": {"coordinates":[-88.081149,41.785613],"type":"Point"}
}