{
  "type": "Feature",
  "properties": {
    "addr:full":"409 N Wolcott Ave Chicago IL 60622",
    "addr:housenumber":"409",
    "addr:postcode":"60622",
    "addr:street":"N Wolcott Ave",
    "iso:country":"US",
    "sg:address":"409 N Wolcott Ave",
    "sg:city":"Chicago",
    "sg:classifiers":[
        {
            "category":"Communications",
            "subcategory":"Film & Video Production",
            "type":"Services"
        }
    ],
    "sg:phone":"+1 312 666 4283",
    "sg:postcode":"60622",
    "sg:province":"IL",
    "sg:tags":[
        "record",
        "tapes-wholesale",
        "cd's",
        "manufacturer"
    ],
    "sg:website":"http://www.thickrecords.com",
    "wof:name":"Thick Records, Inc",
    "wof:placetype":"venue"
},
  "geometry": {"coordinates":[-87.67440000000001,41.889004],"type":"Point"}
}