{
  "type": "Feature",
  "properties": {
    "iso:country":"US",
    "sg:address":"13190 Da Vinci St",
    "sg:city":"Lemont",
    "sg:classifiers":[
        {
            "category":"Real Estate",
            "subcategory":"Real Estate Services",
            "type":"Services"
        },
        {
            "category":"Real Estate",
            "subcategory":"Real Estate Agent",
            "type":"Services"
        }
    ],
    "sg:phone":"+1 630 257 5243",
    "sg:postcode":"60439",
    "sg:province":"IL",
    "sg:tags":[
        "buyer",
        "broker"
    ],
    "wof:name":"Vms Realty Partners",
    "wof:placetype":"venue"
},
  "geometry": {"coordinates":[-87.98214400000001,41.648102],"type":"Point"}
}