{
  "type": "Feature",
  "properties": {
    "iso:country":"US",
    "sg:address":"6323 Cermak Rd",
    "sg:city":"Berwyn",
    "sg:classifiers":[
        {
            "category":"Food & Beverages",
            "subcategory":"Groceries & Convenience Stores",
            "type":"Retail Goods"
        }
    ],
    "sg:phone":"+1 708 749 5090",
    "sg:postcode":"60402",
    "sg:province":"IL",
    "wof:name":"Valle's Produce Corp Two",
    "wof:placetype":"venue"
},
  "geometry": {"coordinates":[-87.78216500000001,41.850535],"type":"Point"}
}