{
  "type": "Feature",
  "properties": {
    "addr:full":"7235 W 103rd St Palos Hills IL 60465",
    "addr:housenumber":"7235",
    "addr:postcode":"60465",
    "addr:street":"W 103Rd St",
    "iso:country":"US",
    "sg:address":"7235 W 103rd St",
    "sg:city":"Palos Hills",
    "sg:classifiers":[
        {
            "category":"Professional",
            "subcategory":"Lawyer & Legal Services",
            "type":"Services"
        }
    ],
    "sg:phone":"+1 708 430 9800",
    "sg:postcode":"60465",
    "sg:province":"IL",
    "wof:name":"Stepanek James I Atty",
    "wof:placetype":"venue"
},
  "geometry": {"coordinates":[-87.79949999999999,41.704201],"type":"Point"}
}