{
  "type": "Feature",
  "properties": {
    "iso:country":"US",
    "sg:address":"305 E Main St",
    "sg:city":"East Dundee",
    "sg:classifiers":[
        {
            "category":"Autos & Motor Vehicles",
            "subcategory":"Fuel & Gas Station",
            "type":"Retail Goods"
        }
    ],
    "sg:phone":"+1 847 426 3013",
    "sg:postcode":"60118",
    "sg:province":"IL",
    "sg:website":"www.marathon.com",
    "wof:name":"Dundee Marathon",
    "wof:placetype":"venue"
},
  "geometry": {"coordinates":[-88.274002,42.098598],"type":"Point"}
}