{
  "type": "Feature",
  "properties": {
    "iso:country":"US",
    "sg:address":"17627 Virginia Rd",
    "sg:city":"Virginia",
    "sg:phone":"+1 217 452 7513",
    "sg:postcode":"62691",
    "sg:province":"IL",
    "sg:tags":[
        "farm",
        "soybean"
    ],
    "wof:name":"Sayre Merle",
    "wof:placetype":"venue"
},
  "geometry": {"coordinates":[-90.30868700000001,39.923786],"type":"Point"}
}