{
  "type": "Feature",
  "properties": {
    "iso:country":"US",
    "sg:address":"1272 Winston Plz",
    "sg:city":"Melrose Park",
    "sg:classifiers":[
        {
            "category":"Personal",
            "subcategory":"Hair Removal",
            "type":"Services"
        }
    ],
    "sg:phone":"+1 708 615 7546",
    "sg:postcode":"60160",
    "sg:province":"IL",
    "sg:website":"www.skinperfecta.com",
    "wof:name":"La Piel Perfecta",
    "wof:placetype":"venue"
},
  "geometry": {"coordinates":[-87.84989899999999,41.902901],"type":"Point"}
}