{
  "type": "Feature",
  "properties": {
    "addr:full":"5526 S La Grange Rd Countryside IL 60525",
    "addr:housenumber":"5526",
    "addr:postcode":"60525",
    "addr:street":"S La Grange Rd",
    "iso:country":"US",
    "sg:address":"5526 S La Grange Rd",
    "sg:city":"Countryside",
    "sg:classifiers":[
        {
            "category":"Shopping",
            "subcategory":"Florist",
            "type":"Retail Goods"
        }
    ],
    "sg:phone":"+1 708 352 5050",
    "sg:postcode":"60525",
    "sg:province":"IL",
    "sg:website":"phillipsflowers.com",
    "wof:name":"Phillip's Flowers & Gifts",
    "wof:placetype":"venue"
},
  "geometry": {"coordinates":[-87.868797,41.789902],"type":"Point"}
}