{
  "type": "Feature",
  "properties": {
    "addr:full":"226 W Jackson Blvd Chicago IL 60606",
    "addr:housenumber":"226",
    "addr:postcode":"60606",
    "addr:street":"W Jackson Blvd",
    "iso:country":"US",
    "sg:address":"226 W Jackson Blvd",
    "sg:city":"Chicago",
    "sg:classifiers":[
        {
            "category":"Social Services",
            "type":"Services"
        },
        {
            "category":"Shopping",
            "type":"Retail Goods"
        },
        {
            "category":"Organizations",
            "subcategory":"Non-profit Organization",
            "type":"Services"
        }
    ],
    "sg:phone":"+1 312 920 9605",
    "sg:postcode":"60606",
    "sg:province":"IL",
    "sg:tags":[
        "supply",
        "fund",
        "games",
        "raising",
        "merchandise"
    ],
    "wof:name":"For The Love Of Chocolate Foundation",
    "wof:placetype":"venue"
},
  "geometry": {"coordinates":[-87.634152,41.878117],"type":"Point"}
}