{
  "type": "Feature",
  "properties": {
    "iso:country":"US",
    "sg:address":"520 S Dearborn Ave",
    "sg:city":"Kankakee",
    "sg:classifiers":[
        {
            "category":"Organizations",
            "subcategory":"Non-profit Organization",
            "type":"Services"
        }
    ],
    "sg:phone":"+1 815 933 7374",
    "sg:postcode":"60901",
    "sg:province":"IL",
    "sg:tags":[
        "social"
    ],
    "wof:name":"Dearborn Court",
    "wof:placetype":"venue"
},
  "geometry": {"coordinates":[-87.863606,41.11403],"type":"Point"}
}