{
  "type": "Feature",
  "properties": {
    "iso:country":"US",
    "sg:address":"3634 W North Ave",
    "sg:city":"Chicago",
    "sg:classifiers":[
        {
            "category":"Autos & Motor Vehicles",
            "subcategory":"Auto Supplies",
            "type":"Retail Goods"
        }
    ],
    "sg:phone":"+1   ",
    "sg:postcode":"60647",
    "sg:province":"IL",
    "wof:name":"Economy New & Used Auto Parts",
    "wof:placetype":"venue"
},
  "geometry": {"coordinates":[-87.717765,41.910047],"type":"Point"}
}