{
  "type": "Feature",
  "properties": {
    "iso:country":"US",
    "sg:address":"928 N Taylor Ave",
    "sg:city":"Oak Park",
    "sg:classifiers":[
        {
            "category":"Professional",
            "subcategory":"Business Services",
            "type":"Services"
        }
    ],
    "sg:phone":"+1 708 660 1240",
    "sg:postcode":"60302",
    "sg:province":"IL",
    "wof:name":"Haven Designs Ltd",
    "wof:placetype":"venue"
},
  "geometry": {"coordinates":[-87.77777399999999,41.903335],"type":"Point"}
}