{
  "type": "Feature",
  "properties": {
    "iso:country":"US",
    "sg:address":"9 Longwood Ct",
    "sg:city":"Joliet",
    "sg:classifiers":[
        {
            "category":"Professional",
            "type":"Services"
        }
    ],
    "sg:phone":"+1 815 727 0326",
    "sg:postcode":"60432",
    "sg:province":"IL",
    "wof:name":"United Services",
    "wof:placetype":"venue"
},
  "geometry": {"coordinates":[-88.028344,41.533968],"type":"Point"}
}