{
  "type": "Feature",
  "properties": {
    "iso:country":"US",
    "sg:address":"605 New Fairfield Rd",
    "sg:city":"Mount Vernon",
    "sg:classifiers":[
        {
            "category":"Professional",
            "subcategory":"Business Services",
            "type":"Services"
        }
    ],
    "sg:phone":"+1 618 242 9975",
    "sg:postcode":"62864",
    "sg:province":"IL",
    "wof:name":"SBC",
    "wof:placetype":"venue"
},
  "geometry": {"coordinates":[-88.884733,38.317038],"type":"Point"}
}