{
  "type": "Feature",
  "properties": {
    "iso:country":"US",
    "sg:address":"1048 Douglas St",
    "sg:city":"Madison",
    "sg:classifiers":[
        {
            "category":"Place Of Worship",
            "subcategory":"Church",
            "type":"Public Place"
        },
        {
            "category":"Place Of Worship",
            "type":"Public Place"
        },
        {
            "category":"Organizations",
            "subcategory":"Religious Organization",
            "type":"Services"
        }
    ],
    "sg:phone":"+1 618 877 3072",
    "sg:postcode":"62060",
    "sg:province":"IL",
    "sg:tags":[
        "god",
        "denomination",
        "churches-church",
        "churches-pentecostal",
        "churches-non-denominational",
        "churches-interdenominational",
        "churches-various"
    ],
    "sg:website":"www.churchofgod.cc",
    "wof:name":"North End Church of God",
    "wof:placetype":"venue"
},
  "geometry": {"coordinates":[-90.166298,38.682499],"type":"Point"}
}