{
  "type": "Feature",
  "properties": {
    "addr:full":"4417 N Central Avenue Chicago IL 60630",
    "addr:housenumber":"4417",
    "addr:postcode":"60630",
    "addr:street":"N Central Avenue",
    "iso:country":"US",
    "sg:address":"4417 N Central Avenue",
    "sg:city":"Chicago",
    "sg:classifiers":[
        {
            "category":"Health Services",
            "subcategory":"Dentist",
            "type":"Services"
        }
    ],
    "sg:phone":"+1 773 282 4020",
    "sg:postcode":"60630",
    "sg:province":"IL",
    "wof:name":"Rogalska Wanda DDS",
    "wof:placetype":"venue"
},
  "geometry": {"coordinates":[-87.76731700000001,41.960729],"type":"Point"}
}