{
  "type": "Feature",
  "properties": {
    "addr:full":"936 W Diversey Pkwy Chicago IL 60614",
    "addr:housenumber":"936",
    "addr:postcode":"60614",
    "addr:street":"W Diversey Pkwy",
    "iso:country":"US",
    "sg:address":"936 W Diversey Pkwy",
    "sg:city":"Chicago",
    "sg:classifiers":[
        {
            "category":"Personal",
            "subcategory":"Beauty Salon",
            "type":"Services"
        }
    ],
    "sg:phone":"+1 773 248 0077",
    "sg:postcode":"60614",
    "sg:province":"IL",
    "sg:tags":[
        "hair"
    ],
    "sg:website":"www.gorancoban.com",
    "wof:name":"Goran Coban Salon",
    "wof:placetype":"venue"
},
  "geometry": {"coordinates":[-87.65294900000001,41.932845],"type":"Point"}
}