{
  "type": "Feature",
  "properties": {
    "addr:full":"27242 W Eames St Channahon IL 60410",
    "addr:housenumber":"27242",
    "addr:postcode":"60410",
    "addr:street":"W Eames St",
    "iso:country":"US",
    "sg:address":"27242 W Eames St",
    "sg:city":"Channahon",
    "sg:classifiers":[
        {
            "category":"Banks & Credit Unions",
            "subcategory":"Bank",
            "type":"Services"
        }
    ],
    "sg:phone":"+1 815 467 9705",
    "sg:postcode":"60410",
    "sg:province":"IL",
    "wof:name":"Chase",
    "wof:placetype":"venue"
},
  "geometry": {"coordinates":[-88.230051,41.428495],"type":"Point"}
}