{
  "type": "Feature",
  "properties": {
    "iso:country":"US",
    "sg:address":"1421 Lowe Dr",
    "sg:city":"Algonquin",
    "sg:classifiers":[
        {
            "category":"Professional",
            "subcategory":"Advertising",
            "type":"Services"
        },
        {
            "category":"Professional",
            "subcategory":"Art Services",
            "type":"Services"
        },
        {
            "category":"Communications",
            "subcategory":"Film & Video Production",
            "type":"Services"
        }
    ],
    "sg:phone":"+1 847 854 1111",
    "sg:postcode":"60102",
    "sg:province":"IL",
    "sg:tags":[
        "audio-visual",
        "agency",
        "specialty",
        "creative"
    ],
    "sg:website":"http://www.spectralarts.com",
    "wof:name":"Creative Core Inc",
    "wof:placetype":"venue"
},
  "geometry": {"coordinates":[-88.27605699999999,42.174082],"type":"Point"}
}