{
  "type": "Feature",
  "properties": {
    "iso:country":"US",
    "sg:address":"630 Newport Ave",
    "sg:city":"Westmont",
    "sg:classifiers":[
        {
            "category":"Wholesale",
            "subcategory":"Vending Machines",
            "type":"Manufacturing & Wholesale Goods"
        }
    ],
    "sg:phone":"+1 630 789 1578",
    "sg:postcode":"60559",
    "sg:province":"IL",
    "sg:tags":[
        "merchandise"
    ],
    "wof:name":"Cbs Vending",
    "wof:placetype":"venue"
},
  "geometry": {"coordinates":[-87.953504,41.811286],"type":"Point"}
}