{
  "type": "Feature",
  "properties": {
    "addr:full":"1835 W Central Rd Arlington Heights IL 60005",
    "addr:housenumber":"1835",
    "addr:postcode":"60005",
    "addr:street":"W Central Rd",
    "iso:country":"US",
    "sg:address":"1835 W Central Rd",
    "sg:city":"Arlington Heights",
    "sg:classifiers":[
        {
            "category":"Social Services",
            "subcategory":"Job Training",
            "type":"Services"
        }
    ],
    "sg:phone":"+1 847 870 7711",
    "sg:postcode":"60005",
    "sg:province":"IL",
    "wof:name":"Clearbrook",
    "wof:placetype":"venue"
},
  "geometry": {"coordinates":[-88.00236099999999,42.066544],"type":"Point"}
}