{
  "type": "Feature",
  "properties": {
    "iso:country":"US",
    "sg:address":"967 Brook Forest Ave",
    "sg:city":"Joliet",
    "sg:classifiers":[
        {
            "category":"Restaurant",
            "type":"Food & Drink"
        }
    ],
    "sg:phone":"+1 815 436 8822",
    "sg:postcode":"60431",
    "sg:province":"IL",
    "sg:tags":[
        "eating"
    ],
    "wof:name":"Quiznos Subs",
    "wof:placetype":"venue"
},
  "geometry": {"coordinates":[-88.199411,41.539114],"type":"Point"}
}