{
  "type": "Feature",
  "properties": {
    "iso:country":"US",
    "sg:address":"610 Broadway St",
    "sg:city":"Lincoln",
    "sg:classifiers":[
        {
            "category":"Shopping",
            "subcategory":"Books",
            "type":"Retail Goods"
        }
    ],
    "sg:phone":"+1 217 732 7504",
    "sg:postcode":"62656",
    "sg:province":"IL",
    "sg:tags":[
        "dealer"
    ],
    "wof:name":"Lighthouse Book Store",
    "wof:placetype":"venue"
},
  "geometry": {"coordinates":[-89.362423,40.146756],"type":"Point"}
}