{
  "type": "Feature",
  "properties": {
    "iso:country":"US",
    "sg:address":"12346 S Keeler Ave",
    "sg:city":"Alsip",
    "sg:classifiers":[
        {
            "category":"Wholesale",
            "subcategory":"Hardware",
            "type":"Manufacturing & Wholesale Goods"
        }
    ],
    "sg:phone":"+1 708 597 5555",
    "sg:postcode":"60803",
    "sg:province":"IL",
    "sg:tags":[
        "water",
        "representative",
        "treatment"
    ],
    "wof:name":"Mullarkey Associates Inc",
    "wof:placetype":"venue"
},
  "geometry": {"coordinates":[-87.725115,41.667339],"type":"Point"}
}