{
  "type": "Feature",
  "properties": {
    "iso:country":"US",
    "sg:address":"3257 N Nottingham Avenue",
    "sg:city":"Chicago",
    "sg:classifiers":[
        {
            "category":"Building & Trades",
            "subcategory":"Cleaning & Sanitation",
            "type":"Services"
        }
    ],
    "sg:phone":"+1 773 667 7687",
    "sg:postcode":"60634",
    "sg:province":"IL",
    "sg:tags":[
        "carpet"
    ],
    "wof:name":"Jonny On the Spot",
    "wof:placetype":"venue"
},
  "geometry": {"coordinates":[-87.804354,41.939609],"type":"Point"}
}