{
  "type": "Feature",
  "properties": {
    "iso:country":"US",
    "sg:address":"439 Des Plaines Ave",
    "sg:city":"Forest Park",
    "sg:classifiers":[
        {
            "category":"Wholesale",
            "subcategory":"Groceries",
            "type":"Manufacturing & Wholesale Goods"
        }
    ],
    "sg:phone":"+1 708 488 0800",
    "sg:postcode":"60130",
    "sg:province":"IL",
    "sg:tags":[
        "bakery",
        "retail",
        "mfg"
    ],
    "sg:website":"www.silverlanddesserts.com",
    "wof:name":"Silverland Desserts",
    "wof:placetype":"venue"
},
  "geometry": {"coordinates":[-87.81390399999999,41.878101],"type":"Point"}
}