{
  "type": "Feature",
  "properties": {
    "iso:country":"US",
    "sg:address":"601 Greenwood Rd",
    "sg:city":"Glenview",
    "sg:classifiers":[
        {
            "category":"Autos & Motor Vehicles",
            "subcategory":"Fuel & Gas Station",
            "type":"Retail Goods"
        }
    ],
    "sg:phone":"+1 847 729 4050",
    "sg:postcode":"60025",
    "sg:province":"IL",
    "wof:name":"Demetry's 6 J's",
    "wof:placetype":"venue"
},
  "geometry": {"coordinates":[-87.83998099999999,42.065781],"type":"Point"}
}