{
  "type": "Feature",
  "properties": {
    "iso:country":"US",
    "sg:address":"820 Roslyn Ter",
    "sg:city":"Evanston",
    "sg:classifiers":[
        {
            "category":"Professional",
            "subcategory":"Engineering",
            "type":"Services"
        }
    ],
    "sg:phone":"+1 847 733 7410",
    "sg:postcode":"60201",
    "sg:province":"IL",
    "wof:name":"Biztek Consulting Inc",
    "wof:placetype":"venue"
},
  "geometry": {"coordinates":[-87.682338,42.07106],"type":"Point"}
}