{
  "type": "Feature",
  "properties": {
    "addr:full":"1115 Knollwood Rd Deerfield IL 60015",
    "addr:housenumber":"1115",
    "addr:postcode":"60015",
    "addr:street":"Knollwood Rd",
    "iso:country":"US",
    "sg:address":"1115 Knollwood Rd",
    "sg:city":"Deerfield",
    "sg:classifiers":[
        {
            "category":"Professional",
            "subcategory":"Management & Consulting",
            "type":"Services"
        }
    ],
    "sg:phone":"+1 847 405 9250",
    "sg:postcode":"60015",
    "sg:province":"IL",
    "sg:tags":[
        "business"
    ],
    "wof:name":"A Hire Authority",
    "wof:placetype":"venue"
},
  "geometry": {"coordinates":[-87.84064100000001,42.175481],"type":"Point"}
}