{
  "type": "Feature",
  "properties": {
    "addr:full":"6655 S California Avenue Chicago IL 60629",
    "addr:housenumber":"6655",
    "addr:postcode":"60629",
    "addr:street":"S California Avenue",
    "iso:country":"US",
    "sg:address":"6655 S California Avenue",
    "sg:city":"Chicago",
    "sg:classifiers":[
        {
            "category":"Shopping",
            "subcategory":"Mobile Phones",
            "type":"Retail Goods"
        }
    ],
    "sg:phone":"+1 773 434 1618",
    "sg:postcode":"60629",
    "sg:province":"IL",
    "wof:name":"K & M Market",
    "wof:placetype":"venue"
},
  "geometry": {"coordinates":[-87.693023,41.772015],"type":"Point"}
}