{
  "type": "Feature",
  "properties": {
    "addr:full":"1529 E Reynolds Dr Palatine IL 60074",
    "addr:housenumber":"1529",
    "addr:postcode":"60074",
    "addr:street":"E Reynolds Dr",
    "iso:country":"US",
    "sg:address":"1529 E Reynolds Dr",
    "sg:city":"Palatine",
    "sg:classifiers":[
        {
            "category":"Professional",
            "subcategory":"Art Services",
            "type":"Services"
        }
    ],
    "sg:phone":"+1 847 202 1478",
    "sg:postcode":"60074",
    "sg:province":"IL",
    "sg:tags":[
        "commercial",
        "design"
    ],
    "wof:name":"Coop Designz",
    "wof:placetype":"venue"
},
  "geometry": {"coordinates":[-88.005881,42.116917],"type":"Point"}
}