{
  "type": "Feature",
  "properties": {
    "iso:country":"US",
    "sg:address":"311 W Superior St Ste 309",
    "sg:city":"Chicago",
    "sg:classifiers":[
        {
            "category":"Professional",
            "type":"Services"
        }
    ],
    "sg:phone":"+1 312 943 6900",
    "sg:postcode":"60654",
    "sg:province":"IL",
    "sg:tags":[
        "planning",
        "event"
    ],
    "sg:website":"wagstaffworldwide.com",
    "wof:name":"Wagstaff Worldwide",
    "wof:placetype":"venue"
},
  "geometry": {"coordinates":[-87.636573,41.895315],"type":"Point"}
}