{
  "type": "Feature",
  "properties": {
    "addr:full":"7855 S Western Avenue Chicago IL 60620",
    "addr:housenumber":"7855",
    "addr:postcode":"60620",
    "addr:street":"S Western Avenue",
    "iso:country":"US",
    "sg:address":"7855 S Western Avenue",
    "sg:city":"Chicago",
    "sg:classifiers":[
        {
            "category":"Shopping",
            "subcategory":"Pharmacy",
            "type":"Retail Goods"
        }
    ],
    "sg:phone":"+1 773 436 6000",
    "sg:postcode":"60620",
    "sg:province":"IL",
    "sg:tags":[
        "drugstore"
    ],
    "sg:website":"www.cvs.com",
    "wof:name":"Cvs Pharmacy",
    "wof:placetype":"venue"
},
  "geometry": {"coordinates":[-87.682605,41.750229],"type":"Point"}
}