{
  "type": "Feature",
  "properties": {
    "iso:country":"US",
    "sg:address":"1625 Plum Ct",
    "sg:city":"Downers Grove",
    "sg:classifiers":[
        {
            "category":"Insurance",
            "subcategory":"Insurance Agent",
            "type":"Services"
        }
    ],
    "sg:phone":"+1 630 963 7178",
    "sg:postcode":"60515",
    "sg:province":"IL",
    "wof:name":"CNA Insurance",
    "wof:placetype":"venue"
},
  "geometry": {"coordinates":[-88.024967,41.817257],"type":"Point"}
}