{
  "type": "Feature",
  "properties": {
    "addr:full":"970 Elizabeth St Elgin IL 60120",
    "addr:housenumber":"970",
    "addr:postcode":"60120",
    "addr:street":"Elizabeth St",
    "iso:country":"US",
    "sg:address":"970 Elizabeth St",
    "sg:city":"Elgin",
    "sg:classifiers":[
        {
            "category":"Manufacturing",
            "subcategory":"Tools & Machinery",
            "type":"Manufacturing & Wholesale Goods"
        }
    ],
    "sg:phone":"+1 847 741 2514",
    "sg:postcode":"60120",
    "sg:province":"IL",
    "sg:tags":[
        "transmission",
        "equipment",
        "power",
        "mfg"
    ],
    "wof:name":"Eastview Manufacturing Inc",
    "wof:placetype":"venue"
},
  "geometry": {"coordinates":[-88.270071,42.015922],"type":"Point"}
}