{
  "type": "Feature",
  "properties": {
    "addr:full":"420 Medical Center Dr Bolingbrook IL 60440",
    "addr:housenumber":"420",
    "addr:postcode":"60440",
    "addr:street":"Medical Center Dr",
    "iso:country":"US",
    "sg:address":"420 Medical Center Dr",
    "sg:city":"Bolingbrook",
    "sg:classifiers":[
        {
            "category":"Health Services",
            "subcategory":"Doctor",
            "type":"Services"
        }
    ],
    "sg:phone":"+1 630 759 0788",
    "sg:postcode":"60440",
    "sg:province":"IL",
    "sg:tags":[
        "medical",
        "management"
    ],
    "wof:name":"Javeed Akhter",
    "wof:placetype":"venue"
},
  "geometry": {"coordinates":[-88.08348599999999,41.681021],"type":"Point"}
}