{
  "type": "Feature",
  "properties": {
    "iso:country":"US",
    "sg:address":"3485 N State Rte 47",
    "sg:city":"Morris",
    "sg:classifiers":[
        {
            "category":"Autos & Motor Vehicles",
            "subcategory":"Fuel & Gas Station",
            "type":"Retail Goods"
        }
    ],
    "sg:phone":"+1   ",
    "sg:postcode":"60450",
    "sg:province":"IL",
    "sg:tags":[
        "convenience",
        "station",
        "gasoline",
        "store"
    ],
    "wof:name":"D JS Amoco Food Mart",
    "wof:placetype":"venue"
},
  "geometry": {"coordinates":[-88.421246,41.335353],"type":"Point"}
}