{
  "type": "Feature",
  "properties": {
    "iso:country":"US",
    "sg:address":"1601 9th Ave",
    "sg:city":"Fulton",
    "sg:classifiers":[
        {
            "category":"Bars & Pubs",
            "type":"Food & Drink"
        }
    ],
    "sg:phone":"+1 815 589 4376",
    "sg:postcode":"61252",
    "sg:province":"IL",
    "wof:name":"Stadium Sports Bar & Grill",
    "wof:placetype":"venue"
},
  "geometry": {"coordinates":[-90.14759,41.868081],"type":"Point"}
}