{
  "type": "Feature",
  "properties": {
    "addr:full":"5523 W Montrose Ave Chicago IL 60641",
    "addr:housenumber":"5523",
    "addr:postcode":"60641",
    "addr:street":"W Montrose Ave",
    "iso:country":"US",
    "sg:address":"5523 W Montrose Ave",
    "sg:city":"Chicago",
    "sg:classifiers":[
        {
            "category":"Food & Beverages",
            "subcategory":"Groceries & Convenience Stores",
            "type":"Retail Goods"
        }
    ],
    "sg:phone":"+1   ",
    "sg:postcode":"60641",
    "sg:province":"IL",
    "wof:name":"Jasmine Foods Inc",
    "wof:placetype":"venue"
},
  "geometry": {"coordinates":[-87.766231,41.960422],"type":"Point"}
}