{
  "type": "Feature",
  "properties": {
    "iso:country":"US",
    "sg:address":"80 McHenry Rd",
    "sg:city":"Buffalo Grove",
    "sg:classifiers":[
        {
            "category":"Restaurant",
            "type":"Food & Drink"
        }
    ],
    "sg:phone":"+1   ",
    "sg:postcode":"60089",
    "sg:province":"IL",
    "sg:tags":[
        "eating"
    ],
    "wof:name":"Burger King",
    "wof:placetype":"venue"
},
  "geometry": {"coordinates":[-87.959503,42.154397],"type":"Point"}
}