{
  "type": "Feature",
  "properties": {
    "addr:full":"1617 N Main St Normal IL 61761",
    "addr:housenumber":"1617",
    "addr:postcode":"61761",
    "addr:street":"N Main St",
    "iso:country":"US",
    "sg:address":"1617 N Main St",
    "sg:city":"Normal",
    "sg:classifiers":[
        {
            "category":"Restaurant",
            "type":"Food & Drink"
        }
    ],
    "sg:menulink":"http://www.allmenus.com/il/normal/167183-burger-king/menu/",
    "sg:phone":"+1 309 451 8844",
    "sg:postcode":"61761",
    "sg:province":"IL",
    "sg:tags":[
        "burger",
        "american"
    ],
    "wof:name":"Burger King",
    "wof:placetype":"venue"
},
  "geometry": {"coordinates":[-88.995583,40.529743],"type":"Point"}
}