{
  "type": "Feature",
  "properties": {
    "iso:country":"US",
    "sg:address":"2 Mills Cart Rd",
    "sg:city":"Salem",
    "sg:classifiers":[
        {
            "category":"Retail",
            "subcategory":"Auto Repair",
            "type":"Services"
        }
    ],
    "sg:phone":"+1 618 548 3309",
    "sg:postcode":"62881",
    "sg:province":"IL",
    "sg:tags":[
        "body",
        "automobile",
        "painting"
    ],
    "wof:name":"Landers Towing & Collision Ctr",
    "wof:placetype":"venue"
},
  "geometry": {"coordinates":[-88.963256,38.627046],"type":"Point"}
}