{
  "type": "Feature",
  "properties": {
    "iso:country":"US",
    "sg:address":"1307 Shermer Rd",
    "sg:city":"Northbrook",
    "sg:classifiers":[
        {
            "category":"Building & Trades",
            "subcategory":"Electrical",
            "type":"Services"
        }
    ],
    "sg:phone":"+1 847 272 0700",
    "sg:postcode":"60062",
    "sg:province":"IL",
    "sg:tags":[
        "work",
        "electrical",
        "contractor"
    ],
    "wof:name":"Lower Electric LLC",
    "wof:placetype":"venue"
},
  "geometry": {"coordinates":[-87.82516800000001,42.130078],"type":"Point"}
}