{
  "type": "Feature",
  "properties": {
    "addr:full":"1231 Woodland Ave Batavia IL 60510",
    "addr:housenumber":"1231",
    "addr:postcode":"60510",
    "addr:street":"Woodland Ave",
    "iso:country":"US",
    "sg:address":"1231 Woodland Ave",
    "sg:city":"Batavia",
    "sg:classifiers":[
        {
            "category":"Professional",
            "subcategory":"Accounting & Tax Preparation",
            "type":"Services"
        }
    ],
    "sg:phone":"+1 630 879 5603",
    "sg:postcode":"60510",
    "sg:province":"IL",
    "wof:name":"Wayne H Jorgensen CPA",
    "wof:placetype":"venue"
},
  "geometry": {"coordinates":[-88.31553700000001,41.833415],"type":"Point"}
}