{
  "type": "Feature",
  "properties": {
    "addr:full":"25659 S Dixie Hwy Crete IL 60417",
    "addr:housenumber":"25659",
    "addr:postcode":"60417",
    "addr:street":"S Dixie Hwy",
    "iso:country":"US",
    "sg:address":"25659 S Dixie Hwy",
    "sg:city":"Crete",
    "sg:classifiers":[
        {
            "category":"Building & Trades",
            "subcategory":"Construction",
            "type":"Services"
        }
    ],
    "sg:phone":"+1 708 672 8869",
    "sg:postcode":"60417",
    "sg:province":"IL",
    "sg:tags":[
        "concrete",
        "contractor"
    ],
    "wof:name":"Natale Construction Inc",
    "wof:placetype":"venue"
},
  "geometry": {"coordinates":[-87.629803,41.418545],"type":"Point"}
}