{
  "type": "Feature",
  "properties": {
    "iso:country":"US",
    "sg:address":"225 N 1st St",
    "sg:city":"Cary",
    "sg:classifiers":[
        {
            "category":"Manufacturing",
            "subcategory":"Electronics",
            "type":"Manufacturing & Wholesale Goods"
        }
    ],
    "sg:phone":"+1 847 639 2102",
    "sg:postcode":"60013",
    "sg:province":"IL",
    "sg:tags":[
        "printed",
        "circuit",
        "boards"
    ],
    "sg:website":"www.bartlettmfg.com",
    "wof:name":"Bartlett Manufacturing Co",
    "wof:placetype":"venue"
},
  "geometry": {"coordinates":[-88.23817200000001,42.211594],"type":"Point"}
}