{
  "type": "Feature",
  "properties": {
    "iso:country":"US",
    "sg:address":"518 Walnut St",
    "sg:city":"Joliet",
    "sg:classifiers":[
        {
            "category":"Personal",
            "subcategory":"Barber",
            "type":"Services"
        }
    ],
    "sg:phone":"+1 815 723 1593",
    "sg:postcode":"60432",
    "sg:province":"IL",
    "wof:name":"Duke's House Of Styles",
    "wof:placetype":"venue"
},
  "geometry": {"coordinates":[-88.052988,41.535441],"type":"Point"}
}