{
  "type": "Feature",
  "properties": {
    "iso:country":"US",
    "sg:address":"199 Maple",
    "sg:city":"Hampshire",
    "sg:classifiers":[
        {
            "category":"Food & Beverages",
            "subcategory":"Meat & Fish",
            "type":"Retail Goods"
        },
        {
            "category":"Food & Beverages",
            "subcategory":"Groceries & Convenience Stores",
            "type":"Retail Goods"
        }
    ],
    "sg:phone":"+1 847 683 2531",
    "sg:postcode":"60140",
    "sg:province":"IL",
    "sg:tags":[
        "shop"
    ],
    "wof:name":"Blocks Country Market",
    "wof:placetype":"venue"
},
  "geometry": {"coordinates":[-88.529375,42.097807],"type":"Point"}
}