{
  "type": "Feature",
  "properties": {
    "iso:country":"US",
    "sg:address":"200 W Lincoln Ave",
    "sg:city":"Caseyville",
    "sg:classifiers":[
        {
            "category":"Wholesale",
            "subcategory":"Medical Equipment & Supplies",
            "type":"Manufacturing & Wholesale Goods"
        },
        {
            "category":"Health Services",
            "subcategory":"Hospital",
            "type":"Services"
        },
        {
            "category":"Health Services",
            "subcategory":"Health Practitioner",
            "type":"Services"
        },
        {
            "category":"Shopping",
            "subcategory":"Pharmacy",
            "type":"Retail Goods"
        }
    ],
    "sg:phone":"+1 618 345 0188",
    "sg:postcode":"62232",
    "sg:province":"IL",
    "sg:tags":[
        "home",
        "drugstore"
    ],
    "wof:name":"Caseyville Pharmacy",
    "wof:placetype":"venue"
},
  "geometry": {"coordinates":[-90.03070099999999,38.6343],"type":"Point"}
}