{
  "type": "Feature",
  "properties": {
    "iso:country":"US",
    "sg:address":"1631 8th Ave",
    "sg:city":"Rockford",
    "sg:classifiers":[
        {
            "category":"Retail",
            "subcategory":"Repair Shop",
            "type":"Services"
        }
    ],
    "sg:phone":"+1 815 395 1634",
    "sg:postcode":"61104",
    "sg:province":"IL",
    "sg:tags":[
        "microwave",
        "oven"
    ],
    "wof:name":"Ray's Service & Appliances",
    "wof:placetype":"venue"
},
  "geometry": {"coordinates":[-89.069177,42.258219],"type":"Point"}
}