{
  "type": "Feature",
  "properties": {
    "addr:full":"1000 S Hamilton St Lockport IL 60441",
    "addr:housenumber":"1000",
    "addr:postcode":"60441",
    "addr:street":"S Hamilton St",
    "iso:country":"US",
    "sg:address":"1000 S Hamilton St",
    "sg:city":"Lockport",
    "sg:classifiers":[
        {
            "category":"Building & Trades",
            "subcategory":"Construction",
            "type":"Services"
        }
    ],
    "sg:phone":"+1 815 424 0161",
    "sg:postcode":"60441",
    "sg:province":"IL",
    "sg:tags":[
        "general",
        "contractor"
    ],
    "wof:name":"Great Southwest Construction",
    "wof:placetype":"venue"
},
  "geometry": {"coordinates":[-88.05703699999999,41.586928],"type":"Point"}
}