{
  "type": "Feature",
  "properties": {
    "addr:full":"95 Monee Rd Park Forest IL 60466",
    "addr:housenumber":"95",
    "addr:postcode":"60466",
    "addr:street":"Monee Rd Park",
    "iso:country":"US",
    "sg:address":"95 Monee Rd",
    "sg:city":"Park Forest",
    "sg:classifiers":[
        {
            "category":"Social Services",
            "subcategory":"Child Care",
            "type":"Services"
        }
    ],
    "sg:phone":"+1 708 747 5969",
    "sg:postcode":"60466",
    "sg:province":"IL",
    "sg:tags":[
        "day"
    ],
    "wof:name":"Alderson Arnita",
    "wof:placetype":"venue"
},
  "geometry": {"coordinates":[-87.678504,41.470736],"type":"Point"}
}