{
  "type": "Feature",
  "properties": {
    "iso:country":"US",
    "sg:address":"1424 N Sheridan Rd",
    "sg:city":"Waukegan",
    "sg:classifiers":[
        {
            "category":"Professional",
            "subcategory":"Research",
            "type":"Services"
        }
    ],
    "sg:phone":"+1 847 623 0940",
    "sg:postcode":"60085",
    "sg:province":"IL",
    "sg:tags":[
        "nonphysical",
        "commercial"
    ],
    "wof:name":"Strategic Business Research",
    "wof:placetype":"venue"
},
  "geometry": {"coordinates":[-87.831467,42.380158],"type":"Point"}
}