{
  "type": "Feature",
  "properties": {
    "addr:full":"1820 Elm St Park Ridge IL 60068",
    "addr:housenumber":"1820",
    "addr:postcode":"60068",
    "addr:street":"Elm St",
    "iso:country":"US",
    "sg:address":"1820 Elm St",
    "sg:city":"Park Ridge",
    "sg:classifiers":[
        {
            "category":"Professional",
            "type":"Services"
        }
    ],
    "sg:phone":"+1 847 867 6749",
    "sg:postcode":"60068",
    "sg:province":"IL",
    "wof:name":"Dynamic Instructional Inc",
    "wof:placetype":"venue"
},
  "geometry": {"coordinates":[-87.850174,42.01434],"type":"Point"}
}