{
  "type": "Feature",
  "properties": {
    "iso:country":"US",
    "sg:address":"4259 S Berkeley Avenue",
    "sg:city":"Chicago",
    "sg:classifiers":[
        {
            "category":"Community Center",
            "type":"Public Place"
        }
    ],
    "sg:phone":"+1 773 268 7600",
    "sg:postcode":"60653",
    "sg:province":"IL",
    "sg:tags":[
        "medical"
    ],
    "sg:website":"www.nearnorthhealth.org/sites/kh...",
    "wof:name":"Komed-Holman Health Center",
    "wof:placetype":"venue"
},
  "geometry": {"coordinates":[-87.600482,41.817358],"type":"Point"}
}