{
  "type": "Feature",
  "properties": {
    "addr:full":"2352 172nd St Lansing IL 60438",
    "addr:housenumber":"2352",
    "addr:postcode":"60438",
    "addr:street":"172Nd St",
    "iso:country":"US",
    "sg:address":"2352 172nd St",
    "sg:city":"Lansing",
    "sg:classifiers":[
        {
            "category":"Restaurant",
            "type":"Food & Drink"
        }
    ],
    "sg:phone":"+1 708 474 1378",
    "sg:postcode":"60438",
    "sg:province":"IL",
    "sg:tags":[
        "southern"
    ],
    "sg:website":"www.dixiekitchenlansing.com/lans...",
    "wof:name":"Dixie Kitchen & Bait Shop",
    "wof:placetype":"venue"
},
  "geometry": {"coordinates":[-87.56059999999999,41.582802],"type":"Point"}
}