{
  "type": "Feature",
  "properties": {
    "iso:country":"US",
    "sg:address":"2610 Doncaster Dr",
    "sg:city":"Aurora",
    "sg:classifiers":[
        {
            "category":"Insurance",
            "subcategory":"Insurance Agent",
            "type":"Services"
        }
    ],
    "sg:phone":"+1 630 978 1817",
    "sg:postcode":"60504",
    "sg:province":"IL",
    "wof:name":"Insurance Resource Consultants",
    "wof:placetype":"venue"
},
  "geometry": {"coordinates":[-88.25262,41.753711],"type":"Point"}
}