{
  "type": "Feature",
  "properties": {
    "addr:full":"415 E 87th St Chicago IL 60619",
    "addr:housenumber":"415",
    "addr:postcode":"60619",
    "addr:street":"E 87Th St",
    "iso:country":"US",
    "sg:address":"415 E 87th St",
    "sg:city":"Chicago",
    "sg:classifiers":[
        {
            "category":"Insurance",
            "subcategory":"Insurance Agent",
            "type":"Services"
        },
        {
            "category":"Insurance",
            "subcategory":"Hazard Insurance",
            "type":"Services"
        },
        {
            "category":"Insurance",
            "subcategory":"Title Insurance",
            "type":"Services"
        },
        {
            "category":"Insurance",
            "subcategory":"Life Insurance",
            "type":"Services"
        }
    ],
    "sg:phone":"+1 773 723 0400",
    "sg:postcode":"60619",
    "sg:province":"IL",
    "sg:tags":[
        "business",
        "auto",
        "commercial",
        "homeowner",
        "motorcycle",
        "renter"
    ],
    "wof:name":"Allstate Insurance Company - Henry Benjamin",
    "wof:placetype":"venue"
},
  "geometry": {"coordinates":[-87.613893,41.73653],"type":"Point"}
}