{
  "type": "Feature",
  "properties": {
    "iso:country":"US",
    "sg:address":"9222 S Kedzie Ave",
    "sg:city":"Evergreen Park",
    "sg:classifiers":[
        {
            "category":"Social Services",
            "subcategory":"Child Care",
            "type":"Services"
        },
        {
            "category":"Education",
            "subcategory":"Preschool",
            "type":"Public Place"
        },
        {
            "category":"Education",
            "subcategory":"School",
            "type":"Public Place"
        }
    ],
    "sg:phone":"+1 708 636 3640",
    "sg:postcode":"60805",
    "sg:province":"IL",
    "sg:tags":[
        "elementary",
        "day"
    ],
    "wof:name":"Little Shepherd Pre-Schl",
    "wof:placetype":"venue"
},
  "geometry": {"coordinates":[-87.702003,41.7258],"type":"Point"}
}