{
  "type": "Feature",
  "properties": {
    "addr:full":"7115 Virginia Rd Crystal Lake IL 60014",
    "addr:housenumber":"7115",
    "addr:postcode":"60014",
    "addr:street":"Virginia Rd",
    "iso:country":"US",
    "sg:address":"7115 Virginia Rd",
    "sg:city":"Crystal Lake",
    "sg:classifiers":[
        {
            "category":"Professional",
            "subcategory":"Secretarial Services",
            "type":"Services"
        }
    ],
    "sg:phone":"+1 815 477 2230",
    "sg:postcode":"60014",
    "sg:province":"IL",
    "sg:tags":[
        "convention",
        "reporting",
        "court",
        "reporter"
    ],
    "wof:name":"Q & A Reporting",
    "wof:placetype":"venue"
},
  "geometry": {"coordinates":[-88.32697899999999,42.226296],"type":"Point"}
}