{
  "type": "Feature",
  "properties": {
    "addr:full":"3001 Research Rd Champaign IL 61822",
    "addr:housenumber":"3001",
    "addr:postcode":"61822",
    "addr:street":"Research Rd",
    "iso:country":"US",
    "sg:address":"3001 Research Rd",
    "sg:city":"Champaign",
    "sg:classifiers":[
        {
            "category":"Building & Trades",
            "subcategory":"Construction",
            "type":"Services"
        }
    ],
    "sg:phone":"+1 217 356 1448",
    "sg:postcode":"61822",
    "sg:province":"IL",
    "sg:tags":[
        "contractor"
    ],
    "wof:name":"Dodds Co the",
    "wof:placetype":"venue"
},
  "geometry": {"coordinates":[-88.275002,40.1506],"type":"Point"}
}