{
  "type": "Feature",
  "properties": {
    "iso:country":"US",
    "sg:address":"1408 Short Eleventh St",
    "sg:city":"Lincoln",
    "sg:classifiers":[
        {
            "category":"Recreation",
            "type":"Entertainment"
        }
    ],
    "sg:phone":"+1 217 735 9621",
    "sg:postcode":"62656",
    "sg:province":"IL",
    "sg:tags":[
        "carnival"
    ],
    "wof:name":"Logan County Fair Public Phone",
    "wof:placetype":"venue"
},
  "geometry": {"coordinates":[-89.382936,40.152429],"type":"Point"}
}