{
  "type": "Feature",
  "properties": {
    "iso:country":"US",
    "sg:address":"1503 Ogden Ave",
    "sg:city":"Downers Grove",
    "sg:classifiers":[
        {
            "category":"Professional",
            "subcategory":"Accounting & Tax Preparation",
            "type":"Services"
        }
    ],
    "sg:phone":"+1 630 968 1550",
    "sg:postcode":"60515",
    "sg:province":"IL",
    "sg:tags":[
        "accountant",
        "public",
        "certified"
    ],
    "wof:name":"Domino & Associates",
    "wof:placetype":"venue"
},
  "geometry": {"coordinates":[-88.023138,41.808124],"type":"Point"}
}