{
  "type": "Feature",
  "properties": {
    "iso:country":"US",
    "sg:address":"101 W University Ave",
    "sg:city":"Champaign",
    "sg:classifiers":[
        {
            "category":"Health Services",
            "subcategory":"Doctor",
            "type":"Services"
        }
    ],
    "sg:phone":"+1 217 366 8775",
    "sg:postcode":"61820",
    "sg:province":"IL",
    "wof:name":"England Albert C III MD",
    "wof:placetype":"venue"
},
  "geometry": {"coordinates":[-88.24351,40.116193],"type":"Point"}
}