{
  "type": "Feature",
  "properties": {
    "iso:country":"US",
    "sg:address":"534 Orland Square Dr",
    "sg:city":"Orland Park",
    "sg:classifiers":[
        {
            "category":"Food & Beverages",
            "subcategory":"Bakery",
            "type":"Retail Goods"
        }
    ],
    "sg:phone":"+1   ",
    "sg:postcode":"60462",
    "sg:province":"IL",
    "wof:name":"St Louis Bread Company 642",
    "wof:placetype":"venue"
},
  "geometry": {"coordinates":[-87.852369,41.620219],"type":"Point"}
}