{
  "type": "Feature",
  "properties": {
    "iso:country":"US",
    "sg:address":"7434 W 90th St",
    "sg:city":"Bridgeview",
    "sg:classifiers":[
        {
            "category":"Retail",
            "subcategory":"Auto Repair",
            "type":"Services"
        }
    ],
    "sg:phone":"+1 708 599 5884",
    "sg:postcode":"60455",
    "sg:province":"IL",
    "wof:name":"Rc Autoworks",
    "wof:placetype":"venue"
},
  "geometry": {"coordinates":[-87.804063,41.72798],"type":"Point"}
}