{
  "type": "Feature",
  "properties": {
    "addr:full":"300 S 2nd St San Jose IL 62682",
    "addr:housenumber":"300",
    "addr:postcode":"62682",
    "addr:street":"S 2Nd St",
    "iso:country":"US",
    "sg:address":"300 S 2nd St",
    "sg:city":"San Jose",
    "sg:classifiers":[
        {
            "category":"Banks & Credit Unions",
            "subcategory":"Bank",
            "type":"Services"
        }
    ],
    "sg:phone":"+1 309 247 3216",
    "sg:postcode":"62682",
    "sg:province":"IL",
    "wof:name":"San Jose Tri-County Bank",
    "wof:placetype":"venue"
},
  "geometry": {"coordinates":[-89.60392299999999,40.303554],"type":"Point"}
}