{
  "type": "Feature",
  "properties": {
    "iso:country":"US",
    "sg:address":"11007 S Troy St",
    "sg:city":"Chicago",
    "sg:classifiers":[
        {
            "category":"Shopping",
            "subcategory":"Party Supplies",
            "type":"Retail Goods"
        },
        {
            "category":"Building & Trades",
            "subcategory":"Construction",
            "type":"Services"
        }
    ],
    "sg:phone":"+1 773 779 6060",
    "sg:postcode":"60655",
    "sg:province":"IL",
    "sg:tags":[
        "decorating",
        "painter",
        "convention"
    ],
    "wof:name":"Kelsen Decorating",
    "wof:placetype":"venue"
},
  "geometry": {"coordinates":[-87.69940200000001,41.693199],"type":"Point"}
}