{
  "type": "Feature",
  "properties": {
    "iso:country":"US",
    "sg:address":"426 Ann St",
    "sg:city":"West Chicago",
    "sg:classifiers":[
        {
            "category":"Building & Trades",
            "subcategory":"Construction",
            "type":"Services"
        }
    ],
    "sg:phone":"+1 630 267 8380",
    "sg:postcode":"60185",
    "sg:province":"IL",
    "sg:tags":[
        "paving",
        "contractor"
    ],
    "wof:name":"Fernandos Brick Paving Specs",
    "wof:placetype":"venue"
},
  "geometry": {"coordinates":[-88.211515,41.878113],"type":"Point"}
}