{
  "type": "Feature",
  "properties": {
    "iso:country":"US",
    "sg:address":"3358 N Ashland Ave",
    "sg:city":"Chicago",
    "sg:classifiers":[
        {
            "category":"Restaurant",
            "type":"Food & Drink"
        },
        {
            "category":"Bars & Pubs",
            "subcategory":"Nightclub",
            "type":"Food & Drink"
        }
    ],
    "sg:phone":"+1 773 248 5475",
    "sg:postcode":"60622",
    "sg:province":"IL",
    "sg:tags":[
        "mexican",
        "nightlife"
    ],
    "wof:name":"La Taberna Tapatia",
    "wof:placetype":"venue"
},
  "geometry": {"coordinates":[-87.669123,41.943225],"type":"Point"}
}