{
  "type": "Feature",
  "properties": {
    "iso:country":"US",
    "sg:address":"301 Quincy St",
    "sg:city":"Golden",
    "sg:phone":"+1 217 696 2516",
    "sg:postcode":"62339",
    "sg:province":"IL",
    "wof:name":"Osborne Food Center",
    "wof:placetype":"venue"
},
  "geometry": {"coordinates":[-91.016068,40.10931],"type":"Point"}
}