{
  "type": "Feature",
  "properties": {
    "iso:country":"US",
    "sg:address":"1005 W Roosevelt Rd",
    "sg:city":"Wheaton",
    "sg:classifiers":[
        {
            "category":"Social Services",
            "subcategory":"Child Care",
            "type":"Services"
        }
    ],
    "sg:phone":"+1 630 462 3561",
    "sg:postcode":"60187",
    "sg:province":"IL",
    "sg:tags":[
        "center"
    ],
    "wof:name":"Ruthie Clark",
    "wof:placetype":"venue"
},
  "geometry": {"coordinates":[-88.122432,41.858606],"type":"Point"}
}