{
  "type": "Feature",
  "properties": {
    "iso:country":"US",
    "sg:address":"4039 W Madison Street",
    "sg:city":"Chicago",
    "sg:classifiers":[
        {
            "category":"Shopping",
            "subcategory":"Clothing, Apparel, & Fashions",
            "type":"Retail Goods"
        }
    ],
    "sg:phone":"+1 773 265 6378",
    "sg:postcode":"60624",
    "sg:province":"IL",
    "sg:tags":[
        "accessory",
        "clothing",
        "women's"
    ],
    "wof:name":"Fashion Trend 616",
    "wof:placetype":"venue"
},
  "geometry": {"coordinates":[-87.727012,41.880527],"type":"Point"}
}