{
  "type": "Feature",
  "properties": {
    "addr:full":"4635 N Lincoln Ave Chicago IL 60625",
    "addr:housenumber":"4635",
    "addr:postcode":"60625",
    "addr:street":"N Lincoln Ave",
    "iso:country":"US",
    "sg:address":"4635 N Lincoln Ave",
    "sg:city":"Chicago",
    "sg:classifiers":[
        {
            "category":"Shopping",
            "subcategory":"Clothing, Apparel, & Fashions",
            "type":"Retail Goods"
        }
    ],
    "sg:phone":"+1 773 728 0088",
    "sg:postcode":"60625",
    "sg:province":"IL",
    "sg:tags":[
        "accessory",
        "clothing",
        "women's"
    ],
    "sg:website":"www.thedressingroomchicago.com",
    "wof:name":"The Dressing Room",
    "wof:placetype":"venue"
},
  "geometry": {"coordinates":[-87.68687,41.966],"type":"Point"}
}