{
  "type": "Feature",
  "properties": {
    "addr:full":"239 Jana Rd Macomb IL 61455",
    "addr:housenumber":"239",
    "addr:postcode":"61455",
    "addr:street":"Jana Rd",
    "iso:country":"US",
    "sg:address":"239 Jana Rd",
    "sg:city":"Macomb",
    "sg:classifiers":[
        {
            "category":"Professional",
            "subcategory":"Business Services",
            "type":"Services"
        }
    ],
    "sg:phone":"+1 309 837 2854",
    "sg:postcode":"61455",
    "sg:province":"IL",
    "wof:name":"Harzman Enterprises",
    "wof:placetype":"venue"
},
  "geometry": {"coordinates":[-90.691418,40.473329],"type":"Point"}
}