{
  "type": "Feature",
  "properties": {
    "addr:full":"5640 S Harlem Ave Summit Argo IL 60501",
    "addr:housenumber":"5640",
    "addr:postcode":"60501",
    "addr:street":"S Harlem Ave",
    "iso:country":"US",
    "sg:address":"5640 S Harlem Ave",
    "sg:city":"Summit Argo",
    "sg:classifiers":[
        {
            "category":"Bakery",
            "type":"Food & Drink"
        }
    ],
    "sg:menulink":"http://www.allmenus.com/il/lyons/121879-krispy-kreme/menu/",
    "sg:phone":"+1 708 728 0500",
    "sg:postcode":"60501",
    "sg:province":"IL",
    "sg:tags":[
        "american",
        "pastry"
    ],
    "wof:name":"Krispy Kreme",
    "wof:placetype":"venue"
},
  "geometry": {"coordinates":[-87.80170200000001,41.7889],"type":"Point"}
}