{
  "type": "Feature",
  "properties": {
    "iso:country":"US",
    "sg:address":"5320 W Grand Ave",
    "sg:city":"Chicago",
    "sg:classifiers":[
        {
            "category":"Home & Garden",
            "subcategory":"Building Materials",
            "type":"Retail Goods"
        }
    ],
    "sg:phone":"+1 773 417 3785",
    "sg:postcode":"60639",
    "sg:province":"IL",
    "sg:tags":[
        "granite"
    ],
    "wof:name":"Pro Granite & Marble",
    "wof:placetype":"venue"
},
  "geometry": {"coordinates":[-87.75931799999999,41.917573],"type":"Point"}
}