{
  "type": "Feature",
  "properties": {
    "addr:full":"5416 Winding Creek Dr W Mc Henry IL 60050",
    "addr:housenumber":"5416",
    "addr:postcode":"60050",
    "addr:street":"Winding Creek Dr W Mc Henry",
    "iso:country":"US",
    "sg:address":"5416 Winding Creek Dr W",
    "sg:city":"Mc Henry",
    "sg:classifiers":[
        {
            "category":"Shopping",
            "subcategory":"Bicycles & Sporting Goods",
            "type":"Retail Goods"
        }
    ],
    "sg:phone":"+1   ",
    "sg:postcode":"60050",
    "sg:province":"IL",
    "wof:name":"All American Sports",
    "wof:placetype":"venue"
},
  "geometry": {"coordinates":[-88.30418,42.326026],"type":"Point"}
}