{
  "type": "Feature",
  "properties": {
    "addr:full":"18 W Stephenson St Freeport IL 61032",
    "addr:housenumber":"18",
    "addr:postcode":"61032",
    "addr:street":"W Stephenson St",
    "iso:country":"US",
    "sg:address":"18 W Stephenson St",
    "sg:city":"Freeport",
    "sg:classifiers":[
        {
            "category":"Shopping",
            "subcategory":"Clothing, Apparel, & Fashions",
            "type":"Retail Goods"
        }
    ],
    "sg:phone":"+1   ",
    "sg:postcode":"61032",
    "sg:province":"IL",
    "wof:name":"Heavenly Yours Dancewear",
    "wof:placetype":"venue"
},
  "geometry": {"coordinates":[-89.620204,42.298406],"type":"Point"}
}