{
  "type": "Feature",
  "properties": {
    "iso:country":"US",
    "sg:address":"Chgo Ohare Internatl",
    "sg:city":"Chicago",
    "sg:classifiers":[
        {
            "category":"Airline",
            "type":"Transportation"
        }
    ],
    "sg:phone":"+1 773 686 6014",
    "sg:postcode":"60607",
    "sg:province":"IL",
    "sg:tags":[
        "shuttle",
        "airport"
    ],
    "wof:name":"Aer Lingus Irish Airlines Cargo",
    "wof:placetype":"venue"
},
  "geometry": {"coordinates":[-87.657501,41.873199],"type":"Point"}
}