{
  "type": "Feature",
  "properties": {
    "iso:country":"US",
    "sg:address":"449 N Pinecrest Rd",
    "sg:city":"Bolingbrook",
    "sg:classifiers":[
        {
            "category":"Retail",
            "subcategory":"Repair Shop",
            "type":"Services"
        }
    ],
    "sg:phone":"+1 630 739 2050",
    "sg:postcode":"60440",
    "sg:province":"IL",
    "sg:tags":[
        "equipment",
        "video"
    ],
    "wof:name":"VCR Specialist",
    "wof:placetype":"venue"
},
  "geometry": {"coordinates":[-88.052829,41.712562],"type":"Point"}
}