{
  "type": "Feature",
  "properties": {
    "addr:full":"40110 N Delany Rd Wadsworth IL 60083",
    "addr:housenumber":"40110",
    "addr:postcode":"60083",
    "addr:street":"N Delany Rd",
    "iso:country":"US",
    "sg:address":"40110 N Delany Rd",
    "sg:city":"Wadsworth",
    "sg:classifiers":[
        {
            "category":"Real Estate",
            "subcategory":"Real Estate Agent",
            "type":"Services"
        }
    ],
    "sg:phone":"+1 847 244 7919",
    "sg:postcode":"60083",
    "sg:province":"IL",
    "wof:name":"Century 21",
    "wof:placetype":"venue"
},
  "geometry": {"coordinates":[-87.903823,42.447256],"type":"Point"}
}