{
  "type": "Feature",
  "properties": {
    "iso:country":"US",
    "sg:address":"1471 Ellinwood Ave",
    "sg:city":"Des Plaines",
    "sg:classifiers":[
        {
            "category":"Personal",
            "subcategory":"Beauty Salon",
            "type":"Services"
        }
    ],
    "sg:phone":"+1 847 824 8564",
    "sg:postcode":"60016",
    "sg:province":"IL",
    "sg:tags":[
        "shop"
    ],
    "wof:name":"Great Clips",
    "wof:placetype":"venue"
},
  "geometry": {"coordinates":[-87.88645099999999,42.040274],"type":"Point"}
}