{
  "type": "Feature",
  "properties": {
    "addr:full":"2031 N Damen Ave Chicago IL 60647",
    "addr:housenumber":"2031",
    "addr:postcode":"60647",
    "addr:street":"N Damen Ave",
    "iso:country":"US",
    "sg:address":"2031 N Damen Ave",
    "sg:city":"Chicago",
    "sg:phone":"+1 773 227 7341",
    "sg:postcode":"60647",
    "sg:province":"IL",
    "wof:name":"Red Dog House",
    "wof:placetype":"venue"
},
  "geometry": {"coordinates":[-87.677654,41.918625],"type":"Point"}
}