{
  "type": "Feature",
  "properties": {
    "iso:country":"US",
    "sg:address":"3501 N Southport, #225",
    "sg:city":"Chicago",
    "sg:classifiers":[
        {
            "category":"Shopping",
            "subcategory":"Pets & Pet Supplies",
            "type":"Retail Goods"
        }
    ],
    "sg:phone":"+1 773 818 5570",
    "sg:postcode":"60657",
    "sg:province":"IL",
    "sg:tags":[
        "training"
    ],
    "sg:website":"www.chicagopaws.com/",
    "wof:name":"Chicago Paws",
    "wof:placetype":"venue"
},
  "geometry": {"coordinates":[-87.663579,41.945397],"type":"Point"}
}