{
  "type": "Feature",
  "properties": {
    "addr:full":"4520 11th St Rock Island IL 61201",
    "addr:housenumber":"4520",
    "addr:postcode":"61201",
    "addr:street":"11Th St",
    "iso:country":"US",
    "sg:address":"4520 11th St",
    "sg:city":"Rock Island",
    "sg:classifiers":[
        {
            "category":"Food & Beverages",
            "subcategory":"Groceries & Convenience Stores",
            "type":"Retail Goods"
        }
    ],
    "sg:phone":"+1 309 794 0252",
    "sg:postcode":"61201",
    "sg:province":"IL",
    "sg:tags":[
        "filling",
        "station"
    ],
    "wof:name":"Mother Hubbard's Cupboard",
    "wof:placetype":"venue"
},
  "geometry": {"coordinates":[-90.584098,41.46614],"type":"Point"}
}