{
  "type": "Feature",
  "properties": {
    "addr:full":"6910 N Illinois St Fairview Heights IL 62208",
    "addr:housenumber":"6910",
    "addr:postcode":"62208",
    "addr:street":"N Illinois St",
    "iso:country":"US",
    "sg:address":"6910 N Illinois St",
    "sg:city":"Fairview Heights",
    "sg:classifiers":[
        {
            "category":"Restaurant",
            "type":"Food & Drink"
        }
    ],
    "sg:phone":"+1 618 624 8443",
    "sg:postcode":"62208",
    "sg:province":"IL",
    "wof:name":"Tgi Friday's",
    "wof:placetype":"venue"
},
  "geometry": {"coordinates":[-89.985001,38.620201],"type":"Point"}
}