{
  "type": "Feature",
  "properties": {
    "iso:country":"US",
    "sg:address":"564 N Greenfield Dr",
    "sg:city":"Freeport",
    "sg:classifiers":[
        {
            "category":"Professional",
            "subcategory":"Business Services",
            "type":"Services"
        }
    ],
    "sg:phone":"+1 815 232 2769",
    "sg:postcode":"61032",
    "sg:province":"IL",
    "wof:name":"1st Class Home Inspections",
    "wof:placetype":"venue"
},
  "geometry": {"coordinates":[-89.66074399999999,42.303279],"type":"Point"}
}