{
  "type": "Feature",
  "properties": {
    "addr:full":"5452 S Kedzie Avenue Chicago IL 60632",
    "addr:housenumber":"5452",
    "addr:postcode":"60632",
    "addr:street":"S Kedzie Avenue",
    "iso:country":"US",
    "sg:address":"5452 S Kedzie Avenue",
    "sg:city":"Chicago",
    "sg:classifiers":[
        {
            "category":"Health Services",
            "subcategory":"Dentist",
            "type":"Services"
        }
    ],
    "sg:phone":"+1 773 925 8606",
    "sg:postcode":"60632",
    "sg:province":"IL",
    "wof:name":"Greenburg Julius N DDS",
    "wof:placetype":"venue"
},
  "geometry": {"coordinates":[-87.703661,41.793718],"type":"Point"}
}