{
  "type": "Feature",
  "properties": {
    "iso:country":"US",
    "sg:address":"4712 W Chicago Avenue",
    "sg:city":"Chicago",
    "sg:classifiers":[
        {
            "category":"Retail",
            "subcategory":"Car Wash",
            "type":"Services"
        }
    ],
    "sg:phone":"+1 773 287 3500",
    "sg:postcode":"60651",
    "sg:province":"IL",
    "wof:name":"Top of the Line",
    "wof:placetype":"venue"
},
  "geometry": {"coordinates":[-87.74454799999999,41.89506],"type":"Point"}
}