{
  "type": "Feature",
  "properties": {
    "iso:country":"US",
    "sg:address":"179 E 3rd St",
    "sg:city":"Dallas City",
    "sg:classifiers":[
        {
            "category":"Personal",
            "subcategory":"Beauty Salon",
            "type":"Services"
        }
    ],
    "sg:phone":"+1 217 852 3512",
    "sg:postcode":"62330",
    "sg:province":"IL",
    "wof:name":"Sandi's Beauty Salon",
    "wof:placetype":"venue"
},
  "geometry": {"coordinates":[-91.167494,40.636402],"type":"Point"}
}