{
  "type": "Feature",
  "properties": {
    "addr:full":"3814 Kiner Rd Prophetstown IL 61277",
    "addr:housenumber":"3814",
    "addr:postcode":"61277",
    "addr:street":"Kiner Rd",
    "iso:country":"US",
    "sg:address":"3814 Kiner Rd",
    "sg:city":"Prophetstown",
    "sg:classifiers":[
        {
            "category":"Farming",
            "subcategory":"Livestock Farm",
            "type":"Manufacturing & Wholesale Goods"
        }
    ],
    "sg:phone":"+1 815 537 2805",
    "sg:postcode":"61277",
    "sg:province":"IL",
    "sg:tags":[
        "feedlot",
        "hog",
        "or",
        "soybean"
    ],
    "wof:name":"Lrv Farms",
    "wof:placetype":"venue"
},
  "geometry": {"coordinates":[-89.946702,41.660327],"type":"Point"}
}