{
  "type": "Feature",
  "properties": {
    "iso:country":"US",
    "sg:address":"14425 W Jody Ln",
    "sg:city":"Wadsworth",
    "sg:classifiers":[
        {
            "category":"Wholesale",
            "subcategory":"Scrap",
            "type":"Manufacturing & Wholesale Goods"
        }
    ],
    "sg:phone":"+1 847 662 1905",
    "sg:postcode":"60083",
    "sg:province":"IL",
    "sg:tags":[
        "recycling",
        "center"
    ],
    "wof:name":"Amer Recycling System Inc",
    "wof:placetype":"venue"
},
  "geometry": {"coordinates":[-87.909927,42.435064],"type":"Point"}
}