{
  "type": "Feature",
  "properties": {
    "iso:country":"US",
    "sg:address":"4601 Harlem Ave",
    "sg:city":"Berwyn",
    "sg:classifiers":[
        {
            "category":"Food & Beverages",
            "subcategory":"Specialty",
            "type":"Retail Goods"
        },
        {
            "category":"Food & Beverages",
            "subcategory":"Groceries & Convenience Stores",
            "type":"Retail Goods"
        }
    ],
    "sg:phone":"+1 708 484 1259",
    "sg:postcode":"60402",
    "sg:province":"IL",
    "sg:tags":[
        "grocers-specialty"
    ],
    "wof:name":"Zee Food Mart",
    "wof:placetype":"venue"
},
  "geometry": {"coordinates":[-87.801806,41.808527],"type":"Point"}
}