{
  "type": "Feature",
  "properties": {
    "addr:full":"5311 W 123rd Pl Alsip IL 60803",
    "addr:housenumber":"5311",
    "addr:postcode":"60803",
    "addr:street":"W 123Rd Pl",
    "iso:country":"US",
    "sg:address":"5311 W 123rd Pl",
    "sg:city":"Alsip",
    "sg:classifiers":[
        {
            "category":"Shopping",
            "subcategory":"Discount & Variety Stores",
            "type":"Retail Goods"
        }
    ],
    "sg:phone":"+1   ",
    "sg:postcode":"60803",
    "sg:province":"IL",
    "sg:tags":[
        "merchandise",
        "general"
    ],
    "wof:name":"L & M Distribution",
    "wof:placetype":"venue"
},
  "geometry": {"coordinates":[-87.74987900000001,41.668027],"type":"Point"}
}