{
  "type": "Feature",
  "properties": {
    "iso:country":"US",
    "sg:address":"16N158 Tyrrell Rd",
    "sg:city":"Elgin",
    "sg:classifiers":[
        {
            "category":"Building & Trades",
            "subcategory":"Construction",
            "type":"Services"
        }
    ],
    "sg:phone":"+1 847 836 1027",
    "sg:postcode":"60123",
    "sg:province":"IL",
    "sg:tags":[
        "contractor"
    ],
    "wof:name":"Riemer J S Excavating Contractors Inc",
    "wof:placetype":"venue"
},
  "geometry": {"coordinates":[-88.343498,42.068802],"type":"Point"}
}