{
  "type": "Feature",
  "properties": {
    "addr:full":"718 Center St Waukegan IL 60085",
    "addr:housenumber":"718",
    "addr:postcode":"60085",
    "addr:street":"Center St",
    "iso:country":"US",
    "sg:address":"718 Center St",
    "sg:city":"Waukegan",
    "sg:classifiers":[
        {
            "category":"Building & Trades",
            "subcategory":"Landscaping Services",
            "type":"Services"
        }
    ],
    "sg:phone":"+1 847 623 6970",
    "sg:postcode":"60085",
    "sg:province":"IL",
    "sg:tags":[
        "lawn",
        "maintenance",
        "grounds"
    ],
    "wof:name":"Coronas Landscaping",
    "wof:placetype":"venue"
},
  "geometry": {"coordinates":[-87.840954,42.370792],"type":"Point"}
}