{
  "type": "Feature",
  "properties": {
    "addr:full":"938 Maine St Quincy IL 62301",
    "addr:housenumber":"938",
    "addr:postcode":"62301",
    "addr:street":"Maine St",
    "iso:country":"US",
    "sg:address":"938 Maine St",
    "sg:city":"Quincy",
    "sg:classifiers":[
        {
            "category":"Building & Trades",
            "subcategory":"Plumbing",
            "type":"Services"
        }
    ],
    "sg:phone":"+1 217 224 5151",
    "sg:postcode":"62301",
    "sg:province":"IL",
    "sg:tags":[
        "conditioning",
        "air",
        "system",
        "contractor"
    ],
    "wof:name":"Comfort & Safety Svc",
    "wof:placetype":"venue"
},
  "geometry": {"coordinates":[-91.401161,39.931797],"type":"Point"}
}