{
  "type": "Feature",
  "properties": {
    "addr:full":"682 N Van Buren Ave Freeport IL 61032",
    "addr:housenumber":"682",
    "addr:postcode":"61032",
    "addr:street":"N Van Buren Ave",
    "iso:country":"US",
    "sg:address":"682 N Van Buren Ave",
    "sg:city":"Freeport",
    "sg:classifiers":[
        {
            "category":"Retail",
            "subcategory":"Animal Services",
            "type":"Services"
        }
    ],
    "sg:phone":"+1 815 235 8999",
    "sg:postcode":"61032",
    "sg:province":"IL",
    "sg:tags":[
        "merchandise"
    ],
    "wof:name":"Timber Hill Kennel",
    "wof:placetype":"venue"
},
  "geometry": {"coordinates":[-89.62543599999999,42.303682],"type":"Point"}
}