{
  "type": "Feature",
  "properties": {
    "iso:country":"US",
    "sg:address":"3110 Green Mount Xing Dr",
    "sg:city":"O Fallon",
    "sg:classifiers":[
        {
            "category":"Personal",
            "subcategory":"Massage",
            "type":"Services"
        }
    ],
    "sg:phone":"+1 618 628 6921",
    "sg:postcode":"62269",
    "sg:province":"IL",
    "wof:name":"Beauty Brands Salon",
    "wof:placetype":"venue"
},
  "geometry": {"coordinates":[-89.928299,38.573002],"type":"Point"}
}