{
  "type": "Feature",
  "properties": {
    "addr:full":"7550 E Rice Rd Gardner IL 60424",
    "addr:housenumber":"7550",
    "addr:postcode":"60424",
    "addr:street":"E Rice Rd",
    "iso:country":"US",
    "sg:address":"7550 E Rice Rd",
    "sg:city":"Gardner",
    "sg:classifiers":[
        {
            "category":"Home & Garden",
            "subcategory":"Carpets & Floor Coverings",
            "type":"Retail Goods"
        }
    ],
    "sg:phone":"+1 815 237 8678",
    "sg:postcode":"60424",
    "sg:province":"IL",
    "sg:tags":[
        "flooring",
        "contractor"
    ],
    "sg:website":"http://www.imperialrestoration.com",
    "wof:name":"Imperial Restoration, Inc.",
    "wof:placetype":"venue"
},
  "geometry": {"coordinates":[-88.270622,41.17208],"type":"Point"}
}