{
  "type": "Feature",
  "properties": {
    "iso:country":"US",
    "sg:address":"100 W 87th Street",
    "sg:city":"Chicago",
    "sg:classifiers":[
        {
            "category":"Restaurant",
            "type":"Food & Drink"
        }
    ],
    "sg:phone":"+1 773 873 8282",
    "sg:postcode":"60620",
    "sg:province":"IL",
    "sg:tags":[
        "chinese"
    ],
    "wof:name":"Grand Chinese Kitchen",
    "wof:placetype":"venue"
},
  "geometry": {"coordinates":[-87.627229,41.73633],"type":"Point"}
}