{
  "type": "Feature",
  "properties": {
    "addr:full":"122 E Washington Ave Effingham IL 62401",
    "addr:housenumber":"122",
    "addr:postcode":"62401",
    "addr:street":"E Washington Ave",
    "iso:country":"US",
    "sg:address":"122 E Washington Ave",
    "sg:city":"Effingham",
    "sg:classifiers":[
        {
            "category":"Professional",
            "subcategory":"Lawyer & Legal Services",
            "type":"Services"
        }
    ],
    "sg:phone":"+1 217 342 3925",
    "sg:postcode":"62401",
    "sg:province":"IL",
    "sg:tags":[
        "attorney",
        "trust",
        "estate",
        "business",
        "corporation",
        "wills",
        "partnership",
        "planning",
        "law"
    ],
    "sg:website":"http://www.taylorlaw.net",
    "wof:name":"Burkey Bruce A",
    "wof:placetype":"venue"
},
  "geometry": {"coordinates":[-88.54107399999999,39.122209],"type":"Point"}
}