{
  "type": "Feature",
  "properties": {
    "iso:country":"US",
    "sg:address":"2827 W State St",
    "sg:city":"Rockford",
    "sg:classifiers":[
        {
            "category":"Organizations",
            "subcategory":"Religious Organization",
            "type":"Services"
        }
    ],
    "sg:phone":"+1 815 962 7565",
    "sg:postcode":"61102",
    "sg:province":"IL",
    "sg:tags":[
        "church"
    ],
    "wof:name":"Deliverance Church OF Rockford",
    "wof:placetype":"venue"
},
  "geometry": {"coordinates":[-89.13051,42.276964],"type":"Point"}
}