{
  "type": "Feature",
  "properties": {
    "addr:full":"545 California Ave Aurora IL 60506",
    "addr:housenumber":"545",
    "addr:postcode":"60506",
    "addr:street":"California Ave",
    "iso:country":"US",
    "sg:address":"545 California Ave",
    "sg:city":"Aurora",
    "sg:classifiers":[
        {
            "category":"Shopping",
            "subcategory":"Hobbies, Toys, & Games",
            "type":"Retail Goods"
        }
    ],
    "sg:phone":"+1   ",
    "sg:postcode":"60506",
    "sg:province":"IL",
    "wof:name":"Snowball Mountain Soap Co",
    "wof:placetype":"venue"
},
  "geometry": {"coordinates":[-88.32684399999999,41.775408],"type":"Point"}
}