{
  "type": "Feature",
  "properties": {
    "iso:country":"US",
    "sg:address":"697 Glendale Dr",
    "sg:city":"Prospect Heights",
    "sg:classifiers":[
        {
            "category":"Building & Trades",
            "subcategory":"Construction",
            "type":"Services"
        }
    ],
    "sg:phone":"+1 847 255 4615",
    "sg:postcode":"60070",
    "sg:province":"IL",
    "sg:tags":[
        "concrete",
        "contractor"
    ],
    "wof:name":"K&K Concrete",
    "wof:placetype":"venue"
},
  "geometry": {"coordinates":[-87.929347,42.10841],"type":"Point"}
}