{
  "type": "Feature",
  "properties": {
    "addr:full":"2014 N Harlem Ave Elmwood Park IL 60707",
    "addr:housenumber":"2014",
    "addr:postcode":"60707",
    "addr:street":"N Harlem Ave",
    "iso:country":"US",
    "sg:address":"2014 N Harlem Ave",
    "sg:city":"Elmwood Park",
    "sg:classifiers":[
        {
            "category":"Shopping",
            "subcategory":"Beauty & Cosmetics",
            "type":"Retail Goods"
        }
    ],
    "sg:phone":"+1 708 452 0910",
    "sg:postcode":"60707",
    "sg:province":"IL",
    "sg:tags":[
        "supply"
    ],
    "wof:name":"Virgo Beauty Products Inc",
    "wof:placetype":"venue"
},
  "geometry": {"coordinates":[-87.805801,41.916801],"type":"Point"}
}