{
  "type": "Feature",
  "properties": {
    "iso:country":"US",
    "sg:address":"316 Lincolnshire Blvd",
    "sg:city":"Belleville",
    "sg:classifiers":[
        {
            "category":"Wholesale",
            "subcategory":"Non-durable Goods",
            "type":"Manufacturing & Wholesale Goods"
        }
    ],
    "sg:phone":"+1 618 277 7979",
    "sg:postcode":"62221",
    "sg:province":"IL",
    "sg:tags":[
        "advertising"
    ],
    "wof:name":"For The Wealth Of Your Bus",
    "wof:placetype":"venue"
},
  "geometry": {"coordinates":[-89.942329,38.516839],"type":"Point"}
}