{
  "type": "Feature",
  "properties": {
    "iso:country":"US",
    "sg:address":"206 E High St",
    "sg:city":"Monticello",
    "sg:classifiers":[
        {
            "category":"Social Services",
            "type":"Services"
        }
    ],
    "sg:phone":"+1 217 762 9507",
    "sg:postcode":"61856",
    "sg:province":"IL",
    "wof:name":"Kristen Gortner Counseling SE",
    "wof:placetype":"venue"
},
  "geometry": {"coordinates":[-88.5704,40.028461],"type":"Point"}
}