{
  "type": "Feature",
  "properties": {
    "addr:full":"2022 Philo Rd Urbana IL 61802",
    "addr:housenumber":"2022",
    "addr:postcode":"61802",
    "addr:street":"Philo Rd",
    "iso:country":"US",
    "sg:address":"2022 Philo Rd",
    "sg:city":"Urbana",
    "sg:classifiers":[
        {
            "category":"Shopping",
            "subcategory":"Tobacco",
            "type":"Retail Goods"
        }
    ],
    "sg:phone":"+1 217 337 5770",
    "sg:postcode":"61802",
    "sg:province":"IL",
    "sg:tags":[
        "shop"
    ],
    "wof:name":"Discount Smoke Shop",
    "wof:placetype":"venue"
},
  "geometry": {"coordinates":[-88.190646,40.092951],"type":"Point"}
}