{
  "type": "Feature",
  "properties": {
    "iso:country":"US",
    "sg:address":"3310 State St",
    "sg:city":"East Saint Louis",
    "sg:classifiers":[
        {
            "category":"Education",
            "subcategory":"School",
            "type":"Public Place"
        }
    ],
    "sg:phone":"+1 618 646 3750",
    "sg:postcode":"62205",
    "sg:province":"IL",
    "sg:tags":[
        "high",
        "middle",
        "elementary"
    ],
    "wof:name":"Schools Public",
    "wof:placetype":"venue"
},
  "geometry": {"coordinates":[-90.11873,38.611451],"type":"Point"}
}