{
  "type": "Feature",
  "properties": {
    "iso:country":"US",
    "sg:address":"504 Dd Rd",
    "sg:city":"Columbia",
    "sg:classifiers":[
        {
            "category":"Professional",
            "subcategory":"Engineering",
            "type":"Services"
        }
    ],
    "sg:phone":"+1 618 281 9100",
    "sg:postcode":"62236",
    "sg:province":"IL",
    "sg:tags":[
        "consulting",
        "engineer"
    ],
    "wof:name":"Maverick Technologies",
    "wof:placetype":"venue"
},
  "geometry": {"coordinates":[-90.23412999999999,38.464237],"type":"Point"}
}