{
  "type": "Feature",
  "properties": {
    "addr:full":"19027 S Jodi Rd Ste F Mokena IL 60448",
    "addr:housenumber":"19027",
    "addr:postcode":"60448",
    "addr:street":"S Jodi Rd Ste F",
    "iso:country":"US",
    "sg:address":"19027 S Jodi Rd Ste F",
    "sg:city":"Mokena",
    "sg:classifiers":[
        {
            "category":"Professional",
            "subcategory":"Engineering",
            "type":"Services"
        },
        {
            "category":"Manufacturing",
            "subcategory":"Electronics",
            "type":"Manufacturing & Wholesale Goods"
        }
    ],
    "sg:phone":"+1 708 479 4309",
    "sg:postcode":"60448",
    "sg:province":"IL",
    "sg:tags":[
        "control",
        "system",
        "automation",
        "electronic",
        "controls-manufacturers",
        "engineer"
    ],
    "wof:name":"Sundown",
    "wof:placetype":"venue"
},
  "geometry": {"coordinates":[-87.841921,41.545132],"type":"Point"}
}