{
  "type": "Feature",
  "properties": {
    "addr:full":"1207 Plainfield Rd Joliet IL 60435",
    "addr:housenumber":"1207",
    "addr:postcode":"60435",
    "addr:street":"Plainfield Rd",
    "iso:country":"US",
    "sg:address":"1207 Plainfield Rd",
    "sg:city":"Joliet",
    "sg:classifiers":[
        {
            "category":"Restaurant",
            "type":"Food & Drink"
        }
    ],
    "sg:phone":"+1 815 726 7741",
    "sg:postcode":"60435",
    "sg:province":"IL",
    "wof:name":"Ace Drive-In",
    "wof:placetype":"venue"
},
  "geometry": {"coordinates":[-88.112979,41.546149],"type":"Point"}
}