{
  "type": "Feature",
  "properties": {
    "addr:full":"20 S County St Waukegan IL 60085",
    "addr:housenumber":"20",
    "addr:postcode":"60085",
    "addr:street":"S County St",
    "iso:country":"US",
    "sg:address":"20 S County St",
    "sg:city":"Waukegan",
    "sg:classifiers":[
        {
            "category":"Government",
            "subcategory":"Office",
            "type":"Public Place"
        }
    ],
    "sg:phone":"+1 847 360 5717",
    "sg:postcode":"60085",
    "sg:province":"IL",
    "wof:name":"Lake County Pretrial",
    "wof:placetype":"venue"
},
  "geometry": {"coordinates":[-87.832722,42.358294],"type":"Point"}
}