{
  "type": "Feature",
  "properties": {
    "iso:country":"US",
    "sg:address":"505 E 67th Street",
    "sg:city":"Chicago",
    "sg:classifiers":[
        {
            "category":"Autos & Motor Vehicles",
            "subcategory":"Fuel & Gas Station",
            "type":"Retail Goods"
        }
    ],
    "sg:phone":"+1 773 947 0870",
    "sg:postcode":"60637",
    "sg:province":"IL",
    "wof:name":"Saja Distribution Company",
    "wof:placetype":"venue"
},
  "geometry": {"coordinates":[-87.612765,41.772975],"type":"Point"}
}