{
  "type": "Feature",
  "properties": {
    "addr:full":"364 W Grand Ave Elmhurst IL 60126",
    "addr:housenumber":"364",
    "addr:postcode":"60126",
    "addr:street":"W Grand Ave",
    "iso:country":"US",
    "sg:address":"364 W Grand Ave",
    "sg:city":"Elmhurst",
    "sg:classifiers":[
        {
            "category":"Autos & Motor Vehicles",
            "subcategory":"Automobile Sales",
            "type":"Retail Goods"
        }
    ],
    "sg:phone":"+1   ",
    "sg:postcode":"60126",
    "sg:province":"IL",
    "sg:tags":[
        "new",
        "used"
    ],
    "wof:name":"Howard Hyundai",
    "wof:placetype":"venue"
},
  "geometry": {"coordinates":[-87.951976,41.930781],"type":"Point"}
}