{
  "type": "Feature",
  "properties": {
    "iso:country":"US",
    "sg:address":"448 W North Ave",
    "sg:city":"Lombard",
    "sg:classifiers":[
        {
            "category":"Retail",
            "subcategory":"Auto Rental",
            "type":"Services"
        }
    ],
    "sg:phone":"+1 630 834 9292",
    "sg:postcode":"60148",
    "sg:province":"IL",
    "sg:tags":[
        "car"
    ],
    "wof:name":"Dunn-Rite Car & Truck Rental",
    "wof:placetype":"venue"
},
  "geometry": {"coordinates":[-88.042603,41.904999],"type":"Point"}
}