{
  "type": "Feature",
  "properties": {
    "addr:full":"15423 Capron Rd Capron IL 61012",
    "addr:housenumber":"15423",
    "addr:postcode":"61012",
    "addr:street":"Capron Rd",
    "iso:country":"US",
    "sg:address":"15423 Capron Rd",
    "sg:city":"Capron",
    "sg:classifiers":[
        {
            "category":"Shopping",
            "subcategory":"Party Supplies",
            "type":"Retail Goods"
        }
    ],
    "sg:phone":"+1 815 569 2789",
    "sg:postcode":"61012",
    "sg:province":"IL",
    "sg:tags":[
        "decorating",
        "convention"
    ],
    "wof:name":"Melinda Reynolds",
    "wof:placetype":"venue"
},
  "geometry": {"coordinates":[-88.744812,42.377199],"type":"Point"}
}