{
  "type": "Feature",
  "properties": {
    "iso:country":"US",
    "sg:address":"126 N Campbell Ave",
    "sg:city":"Glenwood",
    "sg:classifiers":[
        {
            "category":"Real Estate",
            "subcategory":"Real Estate Agent",
            "type":"Services"
        }
    ],
    "sg:phone":"+1 708 758 5055",
    "sg:postcode":"60425",
    "sg:province":"IL",
    "wof:name":"Real Estate Appraisals",
    "wof:placetype":"venue"
},
  "geometry": {"coordinates":[-87.612476,41.549247],"type":"Point"}
}