{
  "type": "Feature",
  "properties": {
    "addr:full":"4935 Oakton St Skokie IL 60077",
    "addr:housenumber":"4935",
    "addr:postcode":"60077",
    "addr:street":"Oakton St",
    "iso:country":"US",
    "sg:address":"4935 Oakton St",
    "sg:city":"Skokie",
    "sg:classifiers":[
        {
            "category":"Home & Garden",
            "subcategory":"Furniture",
            "type":"Retail Goods"
        }
    ],
    "sg:phone":"+1 847 677 0990",
    "sg:postcode":"60077",
    "sg:province":"IL",
    "wof:name":"Casa Elegante Of Chicago Inc",
    "wof:placetype":"venue"
},
  "geometry": {"coordinates":[-87.750399,42.0262],"type":"Point"}
}