{
  "type": "Feature",
  "properties": {
    "addr:full":"3301 W 59th St Chicago IL 60629",
    "addr:housenumber":"3301",
    "addr:postcode":"60629",
    "addr:street":"W 59Th St",
    "iso:country":"US",
    "sg:address":"3301 W 59th St",
    "sg:city":"Chicago",
    "sg:classifiers":[
        {
            "category":"Retail",
            "subcategory":"Auto Repair",
            "type":"Services"
        }
    ],
    "sg:phone":"+1 773 476 0737",
    "sg:postcode":"60629",
    "sg:province":"IL",
    "wof:name":"Walter's Auto Repair",
    "wof:placetype":"venue"
},
  "geometry": {"coordinates":[-87.70590199999999,41.785999],"type":"Point"}
}