{
  "type": "Feature",
  "properties": {
    "addr:full":"809 E 2nd St Dixon IL 61021",
    "addr:housenumber":"809",
    "addr:postcode":"61021",
    "addr:street":"E 2Nd St",
    "iso:country":"US",
    "sg:address":"809 E 2nd St",
    "sg:city":"Dixon",
    "sg:classifiers":[
        {
            "category":"Professional",
            "subcategory":"Engineering",
            "type":"Services"
        },
        {
            "category":"Real Estate",
            "subcategory":"Surveying",
            "type":"Services"
        }
    ],
    "sg:phone":"+1 815 725 4525",
    "sg:postcode":"61021",
    "sg:province":"IL",
    "sg:tags":[
        "surveyor",
        "consulting",
        "land",
        "structural",
        "engineer"
    ],
    "sg:website":"http://www.willetthofmann.com",
    "wof:name":"Willett Hofmann & Associates Inc.",
    "wof:placetype":"venue"
},
  "geometry": {"coordinates":[-89.47238299999999,41.844663],"type":"Point"}
}