{
  "type": "Feature",
  "properties": {
    "iso:country":"US",
    "sg:address":"1886 W Ashbury Ln 1R",
    "sg:city":"Inverness",
    "sg:classifiers":[
        {
            "category":"Real Estate",
            "subcategory":"Real Estate Services",
            "type":"Services"
        },
        {
            "category":"Real Estate",
            "subcategory":"Surveying",
            "type":"Services"
        },
        {
            "category":"Real Estate",
            "subcategory":"Real Estate Agent",
            "type":"Services"
        }
    ],
    "sg:phone":"+1 847 359 5400",
    "sg:postcode":"60067",
    "sg:province":"IL",
    "sg:tags":[
        "industrial",
        "appraisers-commercial",
        "broker",
        "buyer",
        "appraiser"
    ],
    "sg:website":"http://www.corporaterealestateadvisors.com",
    "wof:name":"Corporate Real Estate Advisor",
    "wof:placetype":"venue"
},
  "geometry": {"coordinates":[-88.086226,42.084067],"type":"Point"}
}