{
  "type": "Feature",
  "properties": {
    "iso:country":"US",
    "sg:address":"14300 S Normal Ave",
    "sg:city":"Riverdale",
    "sg:classifiers":[
        {
            "category":"Professional",
            "subcategory":"Management & Consulting",
            "type":"Services"
        }
    ],
    "sg:phone":"+1 708 333 8133",
    "sg:postcode":"60827",
    "sg:province":"IL",
    "sg:tags":[
        "business"
    ],
    "wof:name":"Benson Environmental Safe",
    "wof:placetype":"venue"
},
  "geometry": {"coordinates":[-87.634182,41.633974],"type":"Point"}
}