{
  "type": "Feature",
  "properties": {
    "addr:full":"139 Roberts Rd New Lenox IL 60451",
    "addr:housenumber":"139",
    "addr:postcode":"60451",
    "addr:street":"Roberts Rd",
    "iso:country":"US",
    "sg:address":"139 Roberts Rd",
    "sg:city":"New Lenox",
    "sg:classifiers":[
        {
            "category":"Building & Trades",
            "subcategory":"Landscaping Services",
            "type":"Services"
        }
    ],
    "sg:phone":"+1 815 462 0846",
    "sg:postcode":"60451",
    "sg:province":"IL",
    "sg:tags":[
        "designer",
        "landscape"
    ],
    "wof:name":"T J Wilson Landscape Archtctrl",
    "wof:placetype":"venue"
},
  "geometry": {"coordinates":[-87.95425299999999,41.51009],"type":"Point"}
}