{
  "type": "Feature",
  "properties": {
    "iso:country":"US",
    "sg:address":"71 W 156th St Ste 102",
    "sg:city":"Harvey",
    "sg:classifiers":[
        {
            "category":"Health Services",
            "subcategory":"Doctor",
            "type":"Services"
        }
    ],
    "sg:phone":"+1 708 596 8710",
    "sg:postcode":"60426",
    "sg:province":"IL",
    "sg:website":"www.illinoisretina.com",
    "wof:name":"Cohen Jack A MD",
    "wof:placetype":"venue"
},
  "geometry": {"coordinates":[-87.660471,41.606415],"type":"Point"}
}