{
  "type": "Feature",
  "properties": {
    "iso:country":"US",
    "sg:address":"8658 S Cottage Grove Ave. Space #2 Bldg. E",
    "sg:city":"Chicago",
    "sg:classifiers":[
        {
            "category":"Shopping",
            "subcategory":"Clothing, Apparel, & Fashions",
            "type":"Retail Goods"
        }
    ],
    "sg:phone":"+1 773 994 1256",
    "sg:postcode":"60619",
    "sg:province":"IL",
    "sg:tags":[
        "accessory",
        "clothing",
        "women's"
    ],
    "sg:website":"http://www.ashleystewart.com",
    "wof:name":"Ashley Stewart",
    "wof:placetype":"venue"
},
  "geometry": {"coordinates":[-87.60491399999999,41.737403],"type":"Point"}
}