{
  "type": "Feature",
  "properties": {
    "iso:country":"US",
    "sg:address":"2787 N Milwaukee Avenue",
    "sg:city":"Chicago",
    "sg:classifiers":[
        {
            "category":"Restaurant",
            "type":"Food & Drink"
        }
    ],
    "sg:phone":"+1 773 227 2651",
    "sg:postcode":"60647",
    "sg:province":"IL",
    "wof:name":"Costa Alegre",
    "wof:placetype":"venue"
},
  "geometry": {"coordinates":[-87.712209,41.931835],"type":"Point"}
}