{
  "type": "Feature",
  "properties": {
    "iso:country":"US",
    "sg:address":"2432 20th St",
    "sg:city":"Rockford",
    "sg:classifiers":[
        {
            "category":"Manufacturing",
            "subcategory":"Printing",
            "type":"Manufacturing & Wholesale Goods"
        }
    ],
    "sg:phone":"+1 815 398 2432",
    "sg:postcode":"61104",
    "sg:province":"IL",
    "sg:tags":[
        "printer"
    ],
    "wof:name":"Regal Printing Co",
    "wof:placetype":"venue"
},
  "geometry": {"coordinates":[-89.057565,42.240932],"type":"Point"}
}