{
  "type": "Feature",
  "properties": {
    "addr:full":"8150 W Erin Dr Palos Hills IL 60465",
    "addr:housenumber":"8150",
    "addr:postcode":"60465",
    "addr:street":"W Erin Dr Palos",
    "iso:country":"US",
    "sg:address":"8150 W Erin Dr",
    "sg:city":"Palos Hills",
    "sg:classifiers":[
        {
            "category":"Real Estate",
            "subcategory":"Architect",
            "type":"Services"
        }
    ],
    "sg:phone":"+1 708 233 1000",
    "sg:postcode":"60465",
    "sg:province":"IL",
    "sg:tags":[
        "architectural"
    ],
    "wof:name":"Residential Design & Development Inc",
    "wof:placetype":"venue"
},
  "geometry": {"coordinates":[-87.821899,41.707901],"type":"Point"}
}