{
  "type": "Feature",
  "properties": {
    "iso:country":"US",
    "sg:address":"204 S Main St",
    "sg:city":"Columbia",
    "sg:classifiers":[
        {
            "category":"Shopping",
            "subcategory":"Computers & Home Electronics",
            "type":"Retail Goods"
        }
    ],
    "sg:phone":"+1 618 281 4164",
    "sg:postcode":"62236",
    "sg:province":"IL",
    "sg:tags":[
        "residential",
        "commercial",
        "high",
        "electron",
        "stereophonic",
        "low",
        "fidelity",
        "voltage"
    ],
    "sg:website":"www.audiovideoconcept.com",
    "wof:name":"Audio Video Concepts Inc",
    "wof:placetype":"venue"
},
  "geometry": {"coordinates":[-90.197849,38.442143],"type":"Point"}
}