{
  "type": "Feature",
  "properties": {
    "addr:full":"13055 S Ashland Ave Riverdale IL 60827",
    "addr:housenumber":"13055",
    "addr:postcode":"60827",
    "addr:street":"S Ashland Ave",
    "iso:country":"US",
    "sg:address":"13055 S Ashland Ave",
    "sg:city":"Riverdale",
    "sg:classifiers":[
        {
            "category":"Restaurant",
            "type":"Food & Drink"
        }
    ],
    "sg:menulink":"http://www.allmenus.com/il/calumet/127726-subway/menu/",
    "sg:phone":"+1 708 371 9455",
    "sg:postcode":"60827",
    "sg:province":"IL",
    "sg:tags":[
        "american",
        "sandwich"
    ],
    "wof:name":"Subway",
    "wof:placetype":"venue"
},
  "geometry": {"coordinates":[-87.660636,41.657039],"type":"Point"}
}