{
  "type": "Feature",
  "properties": {
    "addr:full":"25521 W State Rte 173 Antioch IL 60002",
    "addr:housenumber":"25521",
    "addr:postcode":"60002",
    "addr:street":"W State Rte 173",
    "iso:country":"US",
    "sg:address":"25521 W State Rte 173",
    "sg:city":"Antioch",
    "sg:classifiers":[
        {
            "category":"Retail",
            "subcategory":"Auto Repair",
            "type":"Services"
        }
    ],
    "sg:phone":"+1 847 395 6662",
    "sg:postcode":"60002",
    "sg:province":"IL",
    "sg:tags":[
        "repairing",
        "automobile",
        "general"
    ],
    "wof:name":"Antioch Auto Center",
    "wof:placetype":"venue"
},
  "geometry": {"coordinates":[-88.131593,42.478299],"type":"Point"}
}