{
  "type": "Feature",
  "properties": {
    "addr:full":"418 W Blackhawk Dr Byron IL 61010",
    "addr:housenumber":"418",
    "addr:postcode":"61010",
    "addr:street":"W Blackhawk Dr",
    "iso:country":"US",
    "sg:address":"418 W Blackhawk Dr",
    "sg:city":"Byron",
    "sg:classifiers":[
        {
            "category":"Building & Trades",
            "subcategory":"Construction",
            "type":"Services"
        }
    ],
    "sg:phone":"+1 815 234 8739",
    "sg:postcode":"61010",
    "sg:province":"IL",
    "sg:tags":[
        "house"
    ],
    "wof:name":"Classics Colonials Cstm Homes",
    "wof:placetype":"venue"
},
  "geometry": {"coordinates":[-89.260391,42.125228],"type":"Point"}
}