{
  "type": "Feature",
  "properties": {
    "iso:country":"US",
    "sg:address":"5 Timber Ct",
    "sg:city":"Bolingbrook",
    "sg:classifiers":[
        {
            "category":"Professional",
            "subcategory":"Advertising",
            "type":"Services"
        }
    ],
    "sg:phone":"+1 630 771 1220",
    "sg:postcode":"60440",
    "sg:province":"IL",
    "sg:tags":[
        "distributing",
        "sample"
    ],
    "wof:name":"Kenco",
    "wof:placetype":"venue"
},
  "geometry": {"coordinates":[-88.078874,41.6858],"type":"Point"}
}