{
  "type": "Feature",
  "properties": {
    "addr:full":"1901 Church St Evanston IL 60201",
    "addr:housenumber":"1901",
    "addr:postcode":"60201",
    "addr:street":"Church St",
    "iso:country":"US",
    "sg:address":"1901 Church St",
    "sg:city":"Evanston",
    "sg:classifiers":[
        {
            "category":"Shopping",
            "type":"Retail Goods"
        },
        {
            "category":"Food & Beverages",
            "subcategory":"Groceries & Convenience Stores",
            "type":"Retail Goods"
        }
    ],
    "sg:phone":"+1 847 328 4212",
    "sg:postcode":"60201",
    "sg:province":"IL",
    "sg:tags":[
        "merchandise"
    ],
    "wof:name":"Mani's Mini-Mart",
    "wof:placetype":"venue"
},
  "geometry": {"coordinates":[-87.69898999999999,42.048382],"type":"Point"}
}