{
  "type": "Feature",
  "properties": {
    "iso:country":"US",
    "sg:address":"207 S Bowman Ave",
    "sg:city":"Danville",
    "sg:classifiers":[
        {
            "category":"Autos & Motor Vehicles",
            "subcategory":"Automobile Sales",
            "type":"Retail Goods"
        }
    ],
    "sg:phone":"+1 217 431 8282",
    "sg:postcode":"61832",
    "sg:province":"IL",
    "sg:tags":[
        "car",
        "used",
        "dealer"
    ],
    "wof:name":"Race Way Auto Sales",
    "wof:placetype":"venue"
},
  "geometry": {"coordinates":[-87.61157900000001,40.122762],"type":"Point"}
}