{
  "type": "Feature",
  "properties": {
    "addr:full":"305 W Main St Marion IL 62959",
    "addr:housenumber":"305",
    "addr:postcode":"62959",
    "addr:street":"W Main St",
    "iso:country":"US",
    "sg:address":"305 W Main St",
    "sg:city":"Marion",
    "sg:classifiers":[
        {
            "category":"Place Of Worship",
            "type":"Public Place"
        },
        {
            "category":"Organizations",
            "subcategory":"Religious Organization",
            "type":"Services"
        }
    ],
    "sg:phone":"+1 618 998 9939",
    "sg:postcode":"62959",
    "sg:province":"IL",
    "sg:tags":[
        "church"
    ],
    "sg:website":"http://www.highpointchurch.us",
    "wof:name":"High Point Church",
    "wof:placetype":"venue"
},
  "geometry": {"coordinates":[-88.929125,37.730814],"type":"Point"}
}