{
  "type": "Feature",
  "properties": {
    "addr:full":"4001 W Jackson Blvd Chicago IL 60624",
    "addr:housenumber":"4001",
    "addr:postcode":"60624",
    "addr:street":"W Jackson Blvd",
    "iso:country":"US",
    "sg:address":"4001 W Jackson Blvd",
    "sg:city":"Chicago",
    "sg:classifiers":[
        {
            "category":"Retail",
            "subcategory":"Auto Repair",
            "type":"Services"
        }
    ],
    "sg:phone":"+1 773 722 3531",
    "sg:postcode":"60624",
    "sg:province":"IL",
    "sg:tags":[
        "body",
        "shop"
    ],
    "wof:name":"Davis Custom Top & Trim",
    "wof:placetype":"venue"
},
  "geometry": {"coordinates":[-87.725601,41.8769],"type":"Point"}
}