{
  "type": "Feature",
  "properties": {
    "addr:full":"833 W 115th St Chicago IL 60643",
    "addr:housenumber":"833",
    "addr:postcode":"60643",
    "addr:street":"W 115Th St",
    "iso:country":"US",
    "sg:address":"833 W 115th St",
    "sg:city":"Chicago",
    "sg:classifiers":[
        {
            "category":"Government",
            "subcategory":"Office",
            "type":"Public Place"
        }
    ],
    "sg:phone":"+1   ",
    "sg:postcode":"60643",
    "sg:province":"IL",
    "sg:tags":[
        "building",
        "program",
        "housing",
        "apartment",
        "operator"
    ],
    "wof:name":"Chicago Housing Authority",
    "wof:placetype":"venue"
},
  "geometry": {"coordinates":[-87.645245,41.685041],"type":"Point"}
}