{
  "type": "Feature",
  "properties": {
    "addr:full":"811 Garfield St Oak Park IL 60304",
    "addr:housenumber":"811",
    "addr:postcode":"60304",
    "addr:street":"Garfield St",
    "iso:country":"US",
    "sg:address":"811 Garfield St",
    "sg:city":"Oak Park",
    "sg:classifiers":[
        {
            "category":"Retail",
            "subcategory":"Auto Repair",
            "type":"Services"
        }
    ],
    "sg:phone":"+1 708 386 8040",
    "sg:postcode":"60304",
    "sg:province":"IL",
    "sg:tags":[
        "body",
        "shop"
    ],
    "wof:name":"Perfection Autobody",
    "wof:placetype":"venue"
},
  "geometry": {"coordinates":[-87.794403,41.871899],"type":"Point"}
}