{
  "type": "Feature",
  "properties": {
    "addr:full":"8824 Turkey Hollow Rd Milan IL 61264",
    "addr:housenumber":"8824",
    "addr:postcode":"61264",
    "addr:street":"Turkey Hollow Rd",
    "iso:country":"US",
    "sg:address":"8824 Turkey Hollow Rd",
    "sg:city":"Milan",
    "sg:classifiers":[
        {
            "category":"Retail",
            "subcategory":"Repair Shop",
            "type":"Services"
        }
    ],
    "sg:phone":"+1 309 788 7298",
    "sg:postcode":"61264",
    "sg:province":"IL",
    "sg:tags":[
        "electrical"
    ],
    "wof:name":"Strandlund Appliance Serv",
    "wof:placetype":"venue"
},
  "geometry": {"coordinates":[-90.652816,41.430647],"type":"Point"}
}