{
  "type": "Feature",
  "properties": {
    "iso:country":"US",
    "sg:address":"15000 Knox Ave",
    "sg:city":"Midlothian",
    "sg:classifiers":[
        {
            "category":"Professional",
            "type":"Services"
        }
    ],
    "sg:phone":"+1 708 687 4183",
    "sg:postcode":"60445",
    "sg:province":"IL",
    "wof:name":"Restoration Service By Steve",
    "wof:placetype":"venue"
},
  "geometry": {"coordinates":[-87.733249,41.619333],"type":"Point"}
}