{
  "type": "Feature",
  "properties": {
    "addr:full":"11900 S Marshfield Ave Calumet Park IL 60827",
    "addr:housenumber":"11900",
    "addr:postcode":"60827",
    "addr:street":"S Marshfield Ave",
    "iso:country":"US",
    "sg:address":"11900 S Marshfield Ave",
    "sg:city":"Calumet Park",
    "sg:classifiers":[
        {
            "category":"Retail",
            "subcategory":"Car Wash",
            "type":"Services"
        }
    ],
    "sg:phone":"+1 708 824 0002",
    "sg:postcode":"60827",
    "sg:province":"IL",
    "sg:tags":[
        "polishing",
        "washing"
    ],
    "wof:name":"Grandstand Auto Bath",
    "wof:placetype":"venue"
},
  "geometry": {"coordinates":[-87.662385,41.676581],"type":"Point"}
}