{
  "type": "Feature",
  "properties": {
    "addr:full":"345 W Dundee Rd Buffalo Grove IL 60089",
    "addr:housenumber":"345",
    "addr:postcode":"60089",
    "addr:street":"W Dundee Rd",
    "iso:country":"US",
    "sg:address":"345 W Dundee Rd",
    "sg:city":"Buffalo Grove",
    "sg:classifiers":[
        {
            "category":"Banks & Credit Unions",
            "subcategory":"Bank",
            "type":"Services"
        }
    ],
    "sg:phone":"+1 847 465 4820",
    "sg:postcode":"60089",
    "sg:province":"IL",
    "wof:name":"Fifth Third Bank",
    "wof:placetype":"venue"
},
  "geometry": {"coordinates":[-87.96603899999999,42.138963],"type":"Point"}
}