{
  "type": "Feature",
  "properties": {
    "iso:country":"US",
    "sg:address":"555 E Townline Rd",
    "sg:city":"Vernon Hills",
    "sg:classifiers":[
        {
            "category":"Shopping",
            "type":"Retail Goods"
        }
    ],
    "sg:phone":"+1 847 816 3821",
    "sg:postcode":"60061",
    "sg:province":"IL",
    "sg:tags":[
        "pet",
        "shop"
    ],
    "wof:name":"PETCO",
    "wof:placetype":"venue"
},
  "geometry": {"coordinates":[-87.94830399999999,42.240381],"type":"Point"}
}