{
  "type": "Feature",
  "properties": {
    "addr:full":"921 W Wise Rd Schaumburg IL 60193",
    "addr:housenumber":"921",
    "addr:postcode":"60193",
    "addr:street":"W Wise Rd",
    "iso:country":"US",
    "sg:address":"921 W Wise Rd",
    "sg:city":"Schaumburg",
    "sg:classifiers":[
        {
            "category":"Communications",
            "subcategory":"Film & Video Production",
            "type":"Services"
        }
    ],
    "sg:phone":"+1 847 524 0211",
    "sg:postcode":"60193",
    "sg:province":"IL",
    "sg:tags":[
        "motion"
    ],
    "wof:name":"World Video Center",
    "wof:placetype":"venue"
},
  "geometry": {"coordinates":[-88.10499799999999,42.004323],"type":"Point"}
}