{
  "type": "Feature",
  "properties": {
    "iso:country":"US",
    "sg:address":"1600 SE 3rd St",
    "sg:city":"Aledo",
    "sg:classifiers":[
        {
            "category":"Restaurant",
            "type":"Food & Drink"
        }
    ],
    "sg:phone":"+1   ",
    "sg:postcode":"61231",
    "sg:province":"IL",
    "sg:tags":[
        "eating"
    ],
    "wof:name":"Hardees",
    "wof:placetype":"venue"
},
  "geometry": {"coordinates":[-90.731667,41.19949],"type":"Point"}
}