{
  "type": "Feature",
  "properties": {
    "iso:country":"US",
    "sg:address":"1468 Lee St",
    "sg:city":"Des Plaines",
    "sg:classifiers":[
        {
            "category":"Shopping",
            "subcategory":"Hobbies, Toys, & Games",
            "type":"Retail Goods"
        }
    ],
    "sg:phone":"+1 847 297 2118",
    "sg:postcode":"60018",
    "sg:province":"IL",
    "sg:tags":[
        "model",
        "supply"
    ],
    "sg:website":"www.desplaineshobbies.com",
    "wof:name":"Des Plaines Hobbies",
    "wof:placetype":"venue"
},
  "geometry": {"coordinates":[-87.894489,42.027024],"type":"Point"}
}