{
  "type": "Feature",
  "properties": {
    "addr:full":"305 W Jackson St Carbondale IL 62901",
    "addr:housenumber":"305",
    "addr:postcode":"62901",
    "addr:street":"W Jackson St",
    "iso:country":"US",
    "sg:address":"305 W Jackson St",
    "sg:city":"Carbondale",
    "sg:classifiers":[
        {
            "category":"Health Services",
            "subcategory":"Hospital",
            "type":"Services"
        }
    ],
    "sg:phone":"+1 618 549 0721",
    "sg:postcode":"62901",
    "sg:province":"IL",
    "wof:name":"Memorial Hospital Of Carbondal",
    "wof:placetype":"venue"
},
  "geometry": {"coordinates":[-89.218737,37.727991],"type":"Point"}
}