{
  "type": "Feature",
  "properties": {
    "iso:country":"US",
    "sg:address":"2618 W Peterson Ave",
    "sg:city":"Chicago",
    "sg:classifiers":[
        {
            "category":"Health Services",
            "subcategory":"Dentist",
            "type":"Services"
        }
    ],
    "sg:phone":"+1 773 274 8800",
    "sg:postcode":"60659",
    "sg:province":"IL",
    "sg:website":"www.dentaltouchchicago.com",
    "wof:name":"Dental Touch",
    "wof:placetype":"venue"
},
  "geometry": {"coordinates":[-87.695367,41.990726],"type":"Point"}
}