{
  "type": "Feature",
  "properties": {
    "addr:full":"617 Collins St Joliet IL 60432",
    "addr:housenumber":"617",
    "addr:postcode":"60432",
    "addr:street":"Collins St",
    "iso:country":"US",
    "sg:address":"617 Collins St",
    "sg:city":"Joliet",
    "sg:classifiers":[
        {
            "category":"Education",
            "subcategory":"Special Training",
            "type":"Public Place"
        }
    ],
    "sg:phone":"+1 815 722 1078",
    "sg:postcode":"60432",
    "sg:province":"IL",
    "sg:tags":[
        "school",
        "instruction",
        "art"
    ],
    "wof:name":"Artes Bellas",
    "wof:placetype":"venue"
},
  "geometry": {"coordinates":[-88.072782,41.536023],"type":"Point"}
}