{
  "type": "Feature",
  "properties": {
    "iso:country":"US",
    "sg:address":"1633 Old State Rd",
    "sg:city":"Esmond",
    "sg:classifiers":[
        {
            "category":"Farming",
            "subcategory":"Farm",
            "type":"Manufacturing & Wholesale Goods"
        }
    ],
    "sg:phone":"+1 815 393 4305",
    "sg:postcode":"60129",
    "sg:province":"IL",
    "sg:tags":[
        "crop",
        "general"
    ],
    "wof:name":"Edwin Barnes",
    "wof:placetype":"venue"
},
  "geometry": {"coordinates":[-88.91541,42.043219],"type":"Point"}
}