{
  "type": "Feature",
  "properties": {
    "iso:country":"US",
    "sg:address":"41 Meadowview Center",
    "sg:city":"Kankakee",
    "sg:classifiers":[
        {
            "category":"Home & Garden",
            "subcategory":"Building Materials",
            "type":"Retail Goods"
        }
    ],
    "sg:phone":"+1   ",
    "sg:postcode":"60901",
    "sg:province":"IL",
    "sg:tags":[
        "used",
        "merchandise"
    ],
    "wof:name":"Seconds To Go",
    "wof:placetype":"venue"
},
  "geometry": {"coordinates":[-87.874686,41.134801],"type":"Point"}
}