{
  "type": "Feature",
  "properties": {
    "iso:country":"US",
    "sg:address":"1572 N Milwaukee Ave",
    "sg:city":"Chicago",
    "sg:classifiers":[
        {
            "category":"Recreation",
            "subcategory":"Dance Hall",
            "type":"Entertainment"
        }
    ],
    "sg:phone":"+1 773 489 3160",
    "sg:postcode":"60622",
    "sg:province":"IL",
    "sg:tags":[
        "club"
    ],
    "sg:website":"www.doubledoor.com",
    "wof:name":"Double Door Nightclub",
    "wof:placetype":"venue"
},
  "geometry": {"coordinates":[-87.677137,41.909889],"type":"Point"}
}