{
  "type": "Feature",
  "properties": {
    "addr:full":"5 E Northwest Hwy Palatine IL 60067",
    "addr:housenumber":"5",
    "addr:postcode":"60067",
    "addr:street":"E Northwest Hwy",
    "iso:country":"US",
    "sg:address":"5 E Northwest Hwy",
    "sg:city":"Palatine",
    "sg:classifiers":[
        {
            "category":"Retail",
            "subcategory":"Laundry & Dry Cleaning",
            "type":"Services"
        }
    ],
    "sg:phone":"+1 847 991 8818",
    "sg:postcode":"60067",
    "sg:province":"IL",
    "sg:tags":[
        "cleaners"
    ],
    "wof:name":"Johns Cleaners",
    "wof:placetype":"venue"
},
  "geometry": {"coordinates":[-88.04311800000001,42.12093],"type":"Point"}
}