{
  "type": "Feature",
  "properties": {
    "iso:country":"US",
    "sg:address":"980 S Rte 59 MD G16581",
    "sg:city":"Bartlett",
    "sg:classifiers":[
        {
            "category":"Banks & Credit Unions",
            "subcategory":"Financial Services",
            "type":"Services"
        }
    ],
    "sg:phone":"+1 630 213 4653",
    "sg:postcode":"60103",
    "sg:province":"IL",
    "sg:tags":[
        "broker",
        "mortgage"
    ],
    "wof:name":"Fifth Third",
    "wof:placetype":"venue"
},
  "geometry": {"coordinates":[-88.206727,41.968144],"type":"Point"}
}