{
  "type": "Feature",
  "properties": {
    "addr:full":"185 Paramount Dr Wood Dale IL 60191",
    "addr:housenumber":"185",
    "addr:postcode":"60191",
    "addr:street":"Paramount Dr",
    "iso:country":"US",
    "sg:address":"185 Paramount Dr",
    "sg:city":"Wood Dale",
    "sg:classifiers":[
        {
            "category":"Building & Trades",
            "subcategory":"Cleaning & Sanitation",
            "type":"Services"
        }
    ],
    "sg:phone":"+1 630 595 9130",
    "sg:postcode":"60191",
    "sg:province":"IL",
    "sg:tags":[
        "maintenance"
    ],
    "wof:name":"Mar & Mar Cleaning Service",
    "wof:placetype":"venue"
},
  "geometry": {"coordinates":[-87.992571,41.958918],"type":"Point"}
}