{
  "type": "Feature",
  "properties": {
    "addr:full":"5359 N Kedzie Ave Chicago IL 60625",
    "addr:housenumber":"5359",
    "addr:postcode":"60625",
    "addr:street":"N Kedzie Ave",
    "iso:country":"US",
    "sg:address":"5359 N Kedzie Ave",
    "sg:city":"Chicago",
    "sg:classifiers":[
        {
            "category":"Building & Trades",
            "subcategory":"Construction",
            "type":"Services"
        }
    ],
    "sg:phone":"+1 773 588 1249",
    "sg:postcode":"60625",
    "sg:province":"IL",
    "sg:tags":[
        "excavation",
        "contractor"
    ],
    "sg:website":"http://www.floodcompany.com",
    "wof:name":"Flood Company",
    "wof:placetype":"venue"
},
  "geometry": {"coordinates":[-87.708735,41.978662],"type":"Point"}
}