{
  "type": "Feature",
  "properties": {
    "iso:country":"US",
    "sg:address":"9211 W Brush Rd",
    "sg:city":"German Valley",
    "sg:classifiers":[
        {
            "category":"Shopping",
            "subcategory":"Florist",
            "type":"Retail Goods"
        }
    ],
    "sg:phone":"+1   ",
    "sg:postcode":"61039",
    "sg:province":"IL",
    "wof:name":"Brush Creek Floral",
    "wof:placetype":"venue"
},
  "geometry": {"coordinates":[-89.503631,42.186272],"type":"Point"}
}