{
  "type": "Feature",
  "properties": {
    "iso:country":"US",
    "sg:address":"810 McMullin Dr",
    "sg:city":"Kankakee",
    "sg:classifiers":[
        {
            "category":"Freight",
            "type":"Transportation"
        }
    ],
    "sg:phone":"+1 815 932 4727",
    "sg:postcode":"60901",
    "sg:province":"IL",
    "sg:tags":[
        "mover"
    ],
    "sg:website":"www.stsunited.com",
    "wof:name":"Summers Transportation Svc",
    "wof:placetype":"venue"
},
  "geometry": {"coordinates":[-87.868732,41.110648],"type":"Point"}
}