{
  "type": "Feature",
  "properties": {
    "iso:country":"US",
    "sg:address":"24920 S Sage St",
    "sg:city":"Channahon",
    "sg:classifiers":[
        {
            "category":"Education",
            "subcategory":"School",
            "type":"Public Place"
        }
    ],
    "sg:phone":"+1 815 467 4312",
    "sg:postcode":"60410",
    "sg:province":"IL",
    "sg:tags":[
        "high",
        "middle",
        "elementary"
    ],
    "wof:name":"Channahon Schools Dist 17",
    "wof:placetype":"venue"
},
  "geometry": {"coordinates":[-88.227203,41.430199],"type":"Point"}
}