{
  "type": "Feature",
  "properties": {
    "addr:full":"608 E Oak St Fairbury IL 61739",
    "addr:housenumber":"608",
    "addr:postcode":"61739",
    "addr:street":"E Oak St",
    "iso:country":"US",
    "sg:address":"608 E Oak St",
    "sg:city":"Fairbury",
    "sg:classifiers":[
        {
            "category":"Insurance",
            "subcategory":"Hazard Insurance",
            "type":"Services"
        }
    ],
    "sg:phone":"+1 815 692 2011",
    "sg:postcode":"61739",
    "sg:province":"IL",
    "sg:tags":[
        "commercial",
        "business"
    ],
    "wof:name":"Bess E Willard Ins",
    "wof:placetype":"venue"
},
  "geometry": {"coordinates":[-88.505224,40.743859],"type":"Point"}
}