{
  "type": "Feature",
  "properties": {
    "addr:full":"15612 Centennial Ct Orland Park IL 60462",
    "addr:housenumber":"15612",
    "addr:postcode":"60462",
    "addr:street":"Centennial Ct",
    "iso:country":"US",
    "sg:address":"15612 Centennial Ct",
    "sg:city":"Orland Park",
    "sg:classifiers":[
        {
            "category":"Insurance",
            "subcategory":"Life Insurance",
            "type":"Services"
        }
    ],
    "sg:phone":"+1 708 873 0287",
    "sg:postcode":"60462",
    "sg:province":"IL",
    "sg:tags":[
        "carrier"
    ],
    "wof:name":"New York Life",
    "wof:placetype":"venue"
},
  "geometry": {"coordinates":[-87.861732,41.605116],"type":"Point"}
}