{
  "type": "Feature",
  "properties": {
    "addr:full":"2027 W Division Chicago IL 60622",
    "addr:housenumber":"2027",
    "addr:postcode":"60622",
    "addr:street":"W Division",
    "iso:country":"US",
    "sg:address":"2027 W Division",
    "sg:city":"Chicago",
    "sg:classifiers":[
        {
            "category":"Personal",
            "type":"Services"
        }
    ],
    "sg:phone":"+1 773 227 1122",
    "sg:postcode":"60622",
    "sg:province":"IL",
    "sg:tags":[
        "party",
        "planning",
        "event"
    ],
    "sg:website":"www.eventstudiochicago.com/",
    "wof:name":"Event Studio",
    "wof:placetype":"venue"
},
  "geometry": {"coordinates":[-87.678359,41.903142],"type":"Point"}
}