{
  "type": "Feature",
  "properties": {
    "iso:country":"US",
    "sg:address":"6419 Columbine Blvd",
    "sg:city":"Rockford",
    "sg:classifiers":[
        {
            "category":"Building & Trades",
            "subcategory":"Construction",
            "type":"Services"
        }
    ],
    "sg:phone":"+1 815 244 2577",
    "sg:postcode":"61108",
    "sg:province":"IL",
    "sg:tags":[
        "house"
    ],
    "wof:name":"St Joseph Builders Inc",
    "wof:placetype":"venue"
},
  "geometry": {"coordinates":[-88.993177,42.240023],"type":"Point"}
}