{
  "type": "Feature",
  "properties": {
    "addr:full":"775 Touhy Ave Elk Grove Vlg IL 60007",
    "addr:housenumber":"775",
    "addr:postcode":"60007",
    "addr:street":"Touhy Ave",
    "iso:country":"US",
    "sg:address":"775 Touhy Ave",
    "sg:city":"Elk Grove Vlg",
    "sg:classifiers":[
        {
            "category":"Manufacturing",
            "subcategory":"Electronics",
            "type":"Manufacturing & Wholesale Goods"
        }
    ],
    "sg:phone":"+1 847 437 3120",
    "sg:postcode":"60007",
    "sg:province":"IL",
    "sg:tags":[
        "assembly",
        "boards",
        "mfg",
        "electrical",
        "printed",
        "circuit",
        "etched"
    ],
    "wof:name":"Assembly International Inc",
    "wof:placetype":"venue"
},
  "geometry": {"coordinates":[-87.977045,42.006273],"type":"Point"}
}