{
  "type": "Feature",
  "properties": {
    "iso:country":"US",
    "sg:address":"575 N Randall Rd",
    "sg:city":"Aurora",
    "sg:classifiers":[
        {
            "category":"Building & Trades",
            "subcategory":"Electrical",
            "type":"Services"
        }
    ],
    "sg:phone":"+1 630 859 8029",
    "sg:postcode":"60506",
    "sg:province":"IL",
    "sg:tags":[
        "electrical",
        "contractor"
    ],
    "wof:name":"Little Electric LLC",
    "wof:placetype":"venue"
},
  "geometry": {"coordinates":[-88.349656,41.767823],"type":"Point"}
}