{
  "type": "Feature",
  "properties": {
    "addr:full":"854 Brompton Ct Carol Stream IL 60188",
    "addr:housenumber":"854",
    "addr:postcode":"60188",
    "addr:street":"Brompton Ct",
    "iso:country":"US",
    "sg:address":"854 Brompton Ct",
    "sg:city":"Carol Stream",
    "sg:classifiers":[
        {
            "category":"Manufacturing",
            "subcategory":"Tools & Machinery",
            "type":"Manufacturing & Wholesale Goods"
        }
    ],
    "sg:phone":"+1 630 653 4794",
    "sg:postcode":"60188",
    "sg:province":"IL",
    "sg:tags":[
        "recording",
        "medium",
        "mfg"
    ],
    "wof:name":"Image Control",
    "wof:placetype":"venue"
},
  "geometry": {"coordinates":[-88.091863,41.899282],"type":"Point"}
}