{
  "type": "Feature",
  "properties": {
    "addr:full":"11503 Three Mile Rd Thomson IL 61285",
    "addr:housenumber":"11503",
    "addr:postcode":"61285",
    "addr:street":"Three Mile Rd",
    "iso:country":"US",
    "sg:address":"11503 Three Mile Rd",
    "sg:city":"Thomson",
    "sg:classifiers":[
        {
            "category":"Travel",
            "subcategory":"Hotels & Motels",
            "type":"Entertainment"
        }
    ],
    "sg:phone":"+1 815 259 8484",
    "sg:postcode":"61285",
    "sg:province":"IL",
    "wof:name":"Motel At Lynnwood Lynks",
    "wof:placetype":"venue"
},
  "geometry": {"coordinates":[-90.090417,42.003061],"type":"Point"}
}