{
  "type": "Feature",
  "properties": {
    "iso:country":"US",
    "sg:address":"110 E Washington St",
    "sg:city":"Marengo",
    "sg:classifiers":[
        {
            "category":"Health Services",
            "subcategory":"Doctor",
            "type":"Services"
        }
    ],
    "sg:phone":"+1 815 568 1202",
    "sg:postcode":"60152",
    "sg:province":"IL",
    "wof:name":"Gary R Dettman",
    "wof:placetype":"venue"
},
  "geometry": {"coordinates":[-88.608383,42.24932],"type":"Point"}
}