{
  "type": "Feature",
  "properties": {
    "iso:country":"US",
    "sg:address":"1405 S 5th Ave",
    "sg:city":"Maywood",
    "sg:classifiers":[
        {
            "category":"Restaurant",
            "type":"Food & Drink"
        }
    ],
    "sg:phone":"+1   ",
    "sg:postcode":"60153",
    "sg:province":"IL",
    "sg:tags":[
        "eating"
    ],
    "wof:name":"T & Jjs Supreme Steaks",
    "wof:placetype":"venue"
},
  "geometry": {"coordinates":[-87.838612,41.874442],"type":"Point"}
}