{
  "type": "Feature",
  "properties": {
    "iso:country":"US",
    "sg:address":"205 Chaparral Cir",
    "sg:city":"Elgin",
    "sg:classifiers":[
        {
            "category":"Real Estate",
            "subcategory":"Real Estate Agent",
            "type":"Services"
        }
    ],
    "sg:phone":"+1 847 695 2836",
    "sg:postcode":"60120",
    "sg:province":"IL",
    "sg:tags":[
        "property",
        "rental"
    ],
    "wof:name":"Joseph Koziol",
    "wof:placetype":"venue"
},
  "geometry": {"coordinates":[-88.238701,42.033841],"type":"Point"}
}