{
  "type": "Feature",
  "properties": {
    "iso:country":"US",
    "sg:address":"905 Lily Cache Ln",
    "sg:city":"Bolingbrook",
    "sg:classifiers":[
        {
            "category":"Education",
            "subcategory":"School",
            "type":"Public Place"
        }
    ],
    "sg:phone":"+1 630 759 7200",
    "sg:postcode":"60440",
    "sg:province":"IL",
    "wof:name":"Jane Addams Middle School",
    "wof:placetype":"venue"
},
  "geometry": {"coordinates":[-88.10252,41.69015],"type":"Point"}
}