{
  "type": "Feature",
  "properties": {
    "iso:country":"US",
    "sg:address":"1751 Lake Cook Rd",
    "sg:city":"Deerfield",
    "sg:classifiers":[
        {
            "category":"Real Estate",
            "subcategory":"Real Estate Agent",
            "type":"Services"
        }
    ],
    "sg:phone":"+1 847 945 8282",
    "sg:postcode":"60015",
    "sg:province":"IL",
    "sg:tags":[
        "management"
    ],
    "wof:name":"C B Richard Ellis",
    "wof:placetype":"venue"
},
  "geometry": {"coordinates":[-87.87079799999999,42.153015],"type":"Point"}
}