{
  "type": "Feature",
  "properties": {
    "addr:full":"4012 N Milwaukee Avenue Chicago IL 60641",
    "addr:housenumber":"4012",
    "addr:postcode":"60641",
    "addr:street":"N Milwaukee Avenue",
    "iso:country":"US",
    "sg:address":"4012 N Milwaukee Avenue",
    "sg:city":"Chicago",
    "sg:classifiers":[
        {
            "category":"Shopping",
            "subcategory":"Optical Goods",
            "type":"Retail Goods"
        },
        {
            "category":"Health Services",
            "subcategory":"Optometrist",
            "type":"Services"
        },
        {
            "category":"Shopping",
            "subcategory":"Optician",
            "type":"Retail Goods"
        }
    ],
    "sg:phone":"+1 773 545 2660",
    "sg:postcode":"60641",
    "sg:province":"IL",
    "sg:tags":[
        "eyeglass",
        "contact",
        "lens"
    ],
    "sg:website":"http://chicago.citysearch.com/profile/external/3687076/chicago_il/pearle_vision.html?publisher=yellowpages&reference_id=1&placement=ypwebsitemip",
    "wof:name":"Pearle Vision",
    "wof:placetype":"venue"
},
  "geometry": {"coordinates":[-87.747365,41.953561],"type":"Point"}
}