{
  "type": "Feature",
  "properties": {
    "addr:full":"1842 Centre Point Cir Ste 105 Naperville IL 60563",
    "addr:housenumber":"1842",
    "addr:postcode":"60563",
    "addr:street":"Centre Point Cir Ste 105",
    "iso:country":"US",
    "sg:address":"1842 Centre Point Cir Ste 105",
    "sg:city":"Naperville",
    "sg:classifiers":[
        {
            "category":"Manufacturing",
            "subcategory":"Tools & Machinery",
            "type":"Manufacturing & Wholesale Goods"
        },
        {
            "category":"Freight",
            "type":"Transportation"
        },
        {
            "category":"Building & Trades",
            "subcategory":"Construction",
            "type":"Services"
        }
    ],
    "sg:phone":"+1 630 505 0505",
    "sg:postcode":"60563",
    "sg:province":"IL",
    "sg:tags":[
        "conveying",
        "conveyor",
        "equipment-wholesale",
        "system",
        "equipment",
        "monorail",
        "manufacturer"
    ],
    "wof:name":"Fastechnology",
    "wof:placetype":"venue"
},
  "geometry": {"coordinates":[-88.132133,41.804642],"type":"Point"}
}