{
  "type": "Feature",
  "properties": {
    "iso:country":"US",
    "sg:address":"945 Tonne Rd",
    "sg:city":"Elk Grove Vlg",
    "sg:classifiers":[
        {
            "category":"Food & Beverages",
            "subcategory":"Bakery",
            "type":"Retail Goods"
        }
    ],
    "sg:phone":"+1 847 981 1600",
    "sg:postcode":"60007",
    "sg:province":"IL",
    "sg:tags":[
        "baker"
    ],
    "wof:name":"Chicago Gourmet Wholesale Bake",
    "wof:placetype":"venue"
},
  "geometry": {"coordinates":[-87.979115,42.006288],"type":"Point"}
}