{
  "type": "Feature",
  "properties": {
    "iso:country":"US",
    "sg:address":"123 May St",
    "sg:city":"Elmhurst",
    "sg:classifiers":[
        {
            "category":"Manufacturing",
            "subcategory":"Tools & Machinery",
            "type":"Manufacturing & Wholesale Goods"
        }
    ],
    "sg:phone":"+1 630 530 8088",
    "sg:postcode":"60126",
    "sg:province":"IL",
    "sg:tags":[
        "computer",
        "electronic"
    ],
    "wof:name":"S Peters Melvin",
    "wof:placetype":"venue"
},
  "geometry": {"coordinates":[-87.939381,41.886677],"type":"Point"}
}