{
  "type": "Feature",
  "properties": {
    "iso:country":"US",
    "sg:address":"1745 Dekalb Ave",
    "sg:city":"Sycamore",
    "sg:classifiers":[
        {
            "category":"Restaurant",
            "type":"Food & Drink"
        }
    ],
    "sg:menulink":"http://www.allmenus.com/il/dekalb/20261-big-boyz/menu/",
    "sg:phone":"+1 815 739 0605",
    "sg:postcode":"60178",
    "sg:province":"IL",
    "sg:tags":[
        "american"
    ],
    "wof:name":"Big Boyz",
    "wof:placetype":"venue"
},
  "geometry": {"coordinates":[-88.717889,41.972331],"type":"Point"}
}