{
  "type": "Feature",
  "properties": {
    "addr:full":"303 S Prairie St Bethalto IL 62010",
    "addr:housenumber":"303",
    "addr:postcode":"62010",
    "addr:street":"S Prairie St",
    "iso:country":"US",
    "sg:address":"303 S Prairie St",
    "sg:city":"Bethalto",
    "sg:classifiers":[
        {
            "category":"Building & Trades",
            "subcategory":"Plumbing",
            "type":"Services"
        }
    ],
    "sg:phone":"+1 618 978 0685",
    "sg:postcode":"62010",
    "sg:province":"IL",
    "sg:tags":[
        "contractor"
    ],
    "wof:name":"L & P Housecleaning",
    "wof:placetype":"venue"
},
  "geometry": {"coordinates":[-90.04051,38.90663],"type":"Point"}
}