{
  "type": "Feature",
  "properties": {
    "iso:country":"US",
    "sg:address":"12620 S Holiday Dr",
    "sg:city":"Alsip",
    "sg:classifiers":[
        {
            "category":"Professional",
            "subcategory":"Computer Services",
            "type":"Services"
        }
    ],
    "sg:phone":"+1 708 385 8649",
    "sg:postcode":"60803",
    "sg:province":"IL",
    "sg:tags":[
        "consultant",
        "designer"
    ],
    "wof:name":"Atg",
    "wof:placetype":"venue"
},
  "geometry": {"coordinates":[-87.746133,41.662397],"type":"Point"}
}