{
  "type": "Feature",
  "properties": {
    "addr:full":"311 S Kinzie Ave Bradley IL 60915",
    "addr:housenumber":"311",
    "addr:postcode":"60915",
    "addr:street":"S Kinzie Ave",
    "iso:country":"US",
    "sg:address":"311 S Kinzie Ave",
    "sg:city":"Bradley",
    "sg:classifiers":[
        {
            "category":"Autos & Motor Vehicles",
            "subcategory":"Fuel & Gas Station",
            "type":"Retail Goods"
        }
    ],
    "sg:phone":"+1 815 939 2247",
    "sg:postcode":"60915",
    "sg:province":"IL",
    "sg:tags":[
        "oil"
    ],
    "wof:name":"Harper Oil Co",
    "wof:placetype":"venue"
},
  "geometry": {"coordinates":[-87.850981,41.139037],"type":"Point"}
}