{
  "type": "Feature",
  "properties": {
    "iso:country":"US",
    "sg:address":"2905 Meadow Dr",
    "sg:city":"Rolling Meadows",
    "sg:classifiers":[
        {
            "category":"Education",
            "subcategory":"School",
            "type":"Public Place"
        }
    ],
    "sg:phone":"+1 847 963 5200",
    "sg:postcode":"60008",
    "sg:province":"IL",
    "sg:tags":[
        "elementary"
    ],
    "wof:name":"Kimball Hill Elementary School",
    "wof:placetype":"venue"
},
  "geometry": {"coordinates":[-88.0159,42.079558],"type":"Point"}
}