{
  "type": "Feature",
  "properties": {
    "iso:country":"US",
    "sg:address":"4109 Colleen Dr",
    "sg:city":"Champaign",
    "sg:classifiers":[
        {
            "category":"Place Of Worship",
            "subcategory":"Church",
            "type":"Public Place"
        },
        {
            "category":"Place Of Worship",
            "type":"Public Place"
        }
    ],
    "sg:phone":"+1 217 337 4952",
    "sg:postcode":"61822",
    "sg:province":"IL",
    "sg:tags":[
        "churches-baptist-general",
        "churches-baptist"
    ],
    "wof:name":"Birchwood Baptist Church",
    "wof:placetype":"venue"
},
  "geometry": {"coordinates":[-88.31316,40.108786],"type":"Point"}
}