{
  "type": "Feature",
  "properties": {
    "addr:full":"7890 Kingsbury Dr Hanover Park IL 60133",
    "addr:housenumber":"7890",
    "addr:postcode":"60133",
    "addr:street":"Kingsbury Dr Hanover Park",
    "iso:country":"US",
    "sg:address":"7890 Kingsbury Dr",
    "sg:city":"Hanover Park",
    "sg:classifiers":[
        {
            "category":"Building & Trades",
            "subcategory":"Construction",
            "type":"Services"
        }
    ],
    "sg:phone":"+1 630 830 0528",
    "sg:postcode":"60133",
    "sg:province":"IL",
    "sg:tags":[
        "painter"
    ],
    "wof:name":"D & S Decorating",
    "wof:placetype":"venue"
},
  "geometry": {"coordinates":[-88.14141499999999,42.011803],"type":"Point"}
}