{
  "type": "Feature",
  "properties": {
    "iso:country":"US",
    "sg:address":"55 S Barrington Rd",
    "sg:city":"South Barrington",
    "sg:classifiers":[
        {
            "category":"Utilities",
            "subcategory":"Electric",
            "type":"Services"
        }
    ],
    "sg:phone":"+1 847 765 1125",
    "sg:postcode":"60010",
    "sg:province":"IL",
    "sg:tags":[
        "company"
    ],
    "wof:name":"Gas Recovery Svc Of Ill",
    "wof:placetype":"venue"
},
  "geometry": {"coordinates":[-88.143718,42.070081],"type":"Point"}
}