{
  "type": "Feature",
  "properties": {
    "iso:country":"US",
    "sg:address":"70 E Old Mill Trl",
    "sg:city":"Antioch",
    "sg:classifiers":[
        {
            "category":"Utilities",
            "subcategory":"Mobile Phone",
            "type":"Services"
        }
    ],
    "sg:phone":"+1 847 838 4662",
    "sg:postcode":"60002",
    "sg:province":"IL",
    "sg:tags":[
        "communication",
        "radiotelephone"
    ],
    "wof:name":"Antioch Wireless Broadband",
    "wof:placetype":"venue"
},
  "geometry": {"coordinates":[-88.071253,42.481271],"type":"Point"}
}