{
  "type": "Feature",
  "properties": {
    "addr:full":"750 E Benton St Morris IL 60450",
    "addr:housenumber":"750",
    "addr:postcode":"60450",
    "addr:street":"E Benton",
    "iso:country":"US",
    "sg:address":"750 E Benton St",
    "sg:city":"Morris",
    "sg:classifiers":[
        {
            "category":"Shopping",
            "subcategory":"Computers & Home Electronics",
            "type":"Retail Goods"
        }
    ],
    "sg:phone":"+1   ",
    "sg:postcode":"60450",
    "sg:province":"IL",
    "wof:name":"Et Communications Inc",
    "wof:placetype":"venue"
},
  "geometry": {"coordinates":[-88.41542200000001,41.363104],"type":"Point"}
}