{
  "type": "Feature",
  "properties": {
    "iso:country":"US",
    "sg:address":"2395 Kildeer St",
    "sg:city":"Woodridge",
    "sg:classifiers":[
        {
            "category":"Building & Trades",
            "subcategory":"Construction",
            "type":"Services"
        }
    ],
    "sg:phone":"+1 630 322 9771",
    "sg:postcode":"60517",
    "sg:province":"IL",
    "sg:tags":[
        "hanging",
        "contractor"
    ],
    "wof:name":"Quantum Painting Inc",
    "wof:placetype":"venue"
},
  "geometry": {"coordinates":[-88.04016300000001,41.762415],"type":"Point"}
}