{
  "type": "Feature",
  "properties": {
    "iso:country":"US",
    "sg:address":"2025 175th St",
    "sg:city":"Lansing",
    "sg:classifiers":[
        {
            "category":"Shopping",
            "subcategory":"Clothing, Apparel, & Fashions",
            "type":"Retail Goods"
        }
    ],
    "sg:phone":"+1 708 474 5191",
    "sg:postcode":"60438",
    "sg:province":"IL",
    "sg:tags":[
        "accessory",
        "clothing",
        "women's"
    ],
    "wof:name":"Americall Corporation",
    "wof:placetype":"venue"
},
  "geometry": {"coordinates":[-87.568122,41.576864],"type":"Point"}
}