{
  "type": "Feature",
  "properties": {
    "addr:full":"128 James St Geneva IL 60134",
    "addr:housenumber":"128",
    "addr:postcode":"60134",
    "addr:street":"James St",
    "iso:country":"US",
    "sg:address":"128 James St",
    "sg:city":"Geneva",
    "sg:classifiers":[
        {
            "category":"Professional",
            "subcategory":"Management & Consulting",
            "type":"Services"
        }
    ],
    "sg:phone":"+1 630 262 9194",
    "sg:postcode":"60134",
    "sg:province":"IL",
    "sg:tags":[
        "consultant",
        "hospital"
    ],
    "wof:name":"Owens & Assoc",
    "wof:placetype":"venue"
},
  "geometry": {"coordinates":[-88.30645699999999,41.886552],"type":"Point"}
}