{
  "type": "Feature",
  "properties": {
    "iso:country":"US",
    "sg:address":"128 James St",
    "sg:city":"Geneva",
    "sg:classifiers":[
        {
            "category":"Professional",
            "subcategory":"Management & Consulting",
            "type":"Services"
        }
    ],
    "sg:phone":"+1 630 262 9194",
    "sg:postcode":"60134",
    "sg:province":"IL",
    "sg:tags":[
        "consultant",
        "hospital"
    ],
    "wof:name":"Owens & Assoc",
    "wof:placetype":"venue"
},
  "geometry": {"coordinates":[-88.306457,41.886552],"type":"Point"}
}