{
  "type": "Feature",
  "properties": {
    "iso:country":"US",
    "sg:address":"5513 Burwood Rd",
    "sg:city":"Oakwood Hills",
    "sg:classifiers":[
        {
            "category":"Bars & Pubs",
            "type":"Food & Drink"
        }
    ],
    "sg:phone":"+1 847 516 3644",
    "sg:postcode":"60013",
    "sg:province":"IL",
    "wof:name":"Cary Indoor Golf & Billiards",
    "wof:placetype":"venue"
},
  "geometry": {"coordinates":[-88.249344,42.250498],"type":"Point"}
}