{
  "type": "Feature",
  "properties": {
    "iso:country":"US",
    "sg:address":"21238 Shawneetown Rd",
    "sg:city":"Thompsonville",
    "sg:classifiers":[
        {
            "category":"Organizations",
            "subcategory":"Religious Organization",
            "type":"Services"
        }
    ],
    "sg:phone":"+1 618 627 2228",
    "sg:postcode":"62890",
    "sg:province":"IL",
    "wof:name":"Thompsnvlle Frst Baptst Church",
    "wof:placetype":"venue"
},
  "geometry": {"coordinates":[-88.764057,37.917925],"type":"Point"}
}