{
  "type": "Feature",
  "properties": {
    "iso:country":"US",
    "sg:address":"2713 Flossmoor Rd",
    "sg:city":"Flossmoor",
    "sg:classifiers":[
        {
            "category":"Insurance",
            "subcategory":"Insurance Agent",
            "type":"Services"
        }
    ],
    "sg:phone":"+1 708 799 8020",
    "sg:postcode":"60422",
    "sg:province":"IL",
    "wof:name":"State Farm Insurance",
    "wof:placetype":"venue"
},
  "geometry": {"coordinates":[-87.68320799999999,41.54266],"type":"Point"}
}