{
  "type": "Feature",
  "properties": {
    "addr:full":"11132 W 179th St Orland Park IL 60467",
    "addr:housenumber":"11132",
    "addr:postcode":"60467",
    "addr:street":"W 179Th St",
    "iso:country":"US",
    "sg:address":"11132 W 179th St",
    "sg:city":"Orland Park",
    "sg:classifiers":[
        {
            "category":"Insurance",
            "subcategory":"Insurance Agent",
            "type":"Services"
        }
    ],
    "sg:phone":"+1 708 478 3332",
    "sg:postcode":"60467",
    "sg:province":"IL",
    "sg:tags":[
        "company"
    ],
    "wof:name":"State Farm Insurance",
    "wof:placetype":"venue"
},
  "geometry": {"coordinates":[-87.889996,41.564371],"type":"Point"}
}