{
  "type": "Feature",
  "properties": {
    "addr:full":"2585 S Apple River Rd Elizabeth IL 61028",
    "addr:housenumber":"2585",
    "addr:postcode":"61028",
    "addr:street":"S Apple River Rd",
    "iso:country":"US",
    "sg:address":"2585 S Apple River Rd",
    "sg:city":"Elizabeth",
    "sg:classifiers":[
        {
            "category":"Real Estate",
            "subcategory":"Real Estate Operator",
            "type":"Services"
        }
    ],
    "sg:phone":"+1 815 858 3763",
    "sg:postcode":"61028",
    "sg:province":"IL",
    "sg:tags":[
        "property",
        "lessor"
    ],
    "wof:name":"Lee Beyer",
    "wof:placetype":"venue"
},
  "geometry": {"coordinates":[-90.209011,42.332588],"type":"Point"}
}