{
  "type": "Feature",
  "properties": {
    "iso:country":"US",
    "sg:address":"502 12th St",
    "sg:city":"Fulton",
    "sg:classifiers":[
        {
            "category":"Social Services",
            "subcategory":"Child Care",
            "type":"Services"
        }
    ],
    "sg:phone":"+1 815 589 4940",
    "sg:postcode":"61252",
    "sg:province":"IL",
    "wof:name":"River City Daycare",
    "wof:placetype":"venue"
},
  "geometry": {"coordinates":[-90.154639,41.870704],"type":"Point"}
}