{
  "type": "Feature",
  "properties": {
    "addr:full":"1596 Burning Bush Ln Schaumburg IL 60192",
    "addr:housenumber":"1596",
    "addr:postcode":"60192",
    "addr:street":"Burning Bush Ln",
    "iso:country":"US",
    "sg:address":"1596 Burning Bush Ln",
    "sg:city":"Schaumburg",
    "sg:classifiers":[
        {
            "category":"Professional",
            "subcategory":"Accounting & Tax Preparation",
            "type":"Services"
        }
    ],
    "sg:phone":"+1 847 934 0294",
    "sg:postcode":"60192",
    "sg:province":"IL",
    "wof:name":"Joseph A Rivkin CPA",
    "wof:placetype":"venue"
},
  "geometry": {"coordinates":[-88.118782,42.098618],"type":"Point"}
}