{
  "type": "Feature",
  "properties": {
    "iso:country":"US",
    "sg:address":"2100 McDonough St",
    "sg:city":"Joliet",
    "sg:classifiers":[
        {
            "category":"Wholesale",
            "subcategory":"Auto Parts",
            "type":"Manufacturing & Wholesale Goods"
        }
    ],
    "sg:phone":"+1 815 744 9271",
    "sg:postcode":"60436",
    "sg:province":"IL",
    "wof:name":"Keystone Automotive",
    "wof:placetype":"venue"
},
  "geometry": {"coordinates":[-88.132593,41.515096],"type":"Point"}
}