{
  "type": "Feature",
  "properties": {
    "iso:country":"US",
    "sg:address":"3110 N Sheridan Rd",
    "sg:city":"Chicago",
    "sg:classifiers":[
        {
            "category":"Professional",
            "subcategory":"Computer Services",
            "type":"Services"
        }
    ],
    "sg:phone":"+1 773 248 1031",
    "sg:postcode":"60657",
    "sg:province":"IL",
    "sg:tags":[
        "related"
    ],
    "wof:name":"Inventech Technology",
    "wof:placetype":"venue"
},
  "geometry": {"coordinates":[-87.639566,41.938417],"type":"Point"}
}