{
  "type": "Feature",
  "properties": {
    "iso:country":"US",
    "sg:address":"2728 N Main St",
    "sg:city":"Decatur",
    "sg:classifiers":[
        {
            "category":"Home & Garden",
            "subcategory":"Household Appliances",
            "type":"Retail Goods"
        },
        {
            "category":"Utilities",
            "subcategory":"Electric",
            "type":"Services"
        },
        {
            "category":"Retail",
            "subcategory":"Repair Shop",
            "type":"Services"
        }
    ],
    "sg:phone":"+1 217 428 6523",
    "sg:postcode":"62526",
    "sg:province":"IL",
    "sg:tags":[
        "small",
        "major",
        "equipment-repair",
        "appliances-small",
        "refinishing"
    ],
    "sg:website":"http://www.tomdeb.com",
    "wof:name":"Bob's Appliance Service",
    "wof:placetype":"venue"
},
  "geometry": {"coordinates":[-88.95646000000001,39.872137],"type":"Point"}
}