{
  "type": "Feature",
  "properties": {
    "iso:country":"US",
    "sg:address":"717 Estes Ave",
    "sg:city":"Schaumburg",
    "sg:classifiers":[
        {
            "category":"Shopping",
            "type":"Retail Goods"
        }
    ],
    "sg:phone":"+1   ",
    "sg:postcode":"60193",
    "sg:province":"IL",
    "sg:tags":[
        "packaging",
        "material"
    ],
    "wof:name":"Cliffside Packaging",
    "wof:placetype":"venue"
},
  "geometry": {"coordinates":[-88.095989,42.002837],"type":"Point"}
}