{
  "type": "Feature",
  "properties": {
    "iso:country":"US",
    "sg:address":"402 Chalmers St",
    "sg:city":"Geneva",
    "sg:classifiers":[
        {
            "category":"Wholesale",
            "subcategory":"Jewelry",
            "type":"Manufacturing & Wholesale Goods"
        }
    ],
    "sg:phone":"+1 630 262 8526",
    "sg:postcode":"60134",
    "sg:province":"IL",
    "sg:tags":[
        "jeweler"
    ],
    "wof:name":"Midwest Amber",
    "wof:placetype":"venue"
},
  "geometry": {"coordinates":[-88.29537000000001,41.882732],"type":"Point"}
}