{
  "type": "Feature",
  "properties": {
    "iso:country":"US",
    "sg:address":"5431 W Chicago Ave",
    "sg:city":"Chicago",
    "sg:classifiers":[
        {
            "category":"Food & Beverages",
            "subcategory":"Groceries & Convenience Stores",
            "type":"Retail Goods"
        }
    ],
    "sg:phone":"+1 773 261 0000",
    "sg:postcode":"60651",
    "sg:province":"IL",
    "wof:name":"Austin Food Mart",
    "wof:placetype":"venue"
},
  "geometry": {"coordinates":[-87.76177,41.89477],"type":"Point"}
}