{
  "type": "Feature",
  "properties": {
    "iso:country":"US",
    "sg:address":"4855 N Elston Ave",
    "sg:city":"Chicago",
    "sg:classifiers":[
        {
            "category":"Education",
            "subcategory":"College",
            "type":"Public Place"
        },
        {
            "category":"Organizations",
            "subcategory":"Membership Organization",
            "type":"Services"
        }
    ],
    "sg:phone":"+1 773 685 1464",
    "sg:postcode":"60630",
    "sg:province":"IL",
    "sg:tags":[
        "fraternal",
        "sorority",
        "housing",
        "student",
        "fraternity"
    ],
    "wof:name":"Sokol Community Hall",
    "wof:placetype":"venue"
},
  "geometry": {"coordinates":[-87.741709,41.969044],"type":"Point"}
}