{
  "type": "Feature",
  "properties": {
    "iso:country":"US",
    "sg:address":"230 W Johnson St",
    "sg:city":"Palatine",
    "sg:classifiers":[
        {
            "category":"Professional",
            "subcategory":"Management & Consulting",
            "type":"Services"
        }
    ],
    "sg:phone":"+1 847 358 0762",
    "sg:postcode":"60067",
    "sg:province":"IL",
    "sg:tags":[
        "fuel"
    ],
    "wof:name":"ABBE Management Co",
    "wof:placetype":"venue"
},
  "geometry": {"coordinates":[-88.050191,42.109602],"type":"Point"}
}