{
  "type": "Feature",
  "properties": {
    "addr:full":"1644 Cambridge Dr Elgin IL 60123",
    "addr:housenumber":"1644",
    "addr:postcode":"60123",
    "addr:street":"Cambridge Dr",
    "iso:country":"US",
    "sg:address":"1644 Cambridge Dr",
    "sg:city":"Elgin",
    "sg:classifiers":[
        {
            "category":"Wholesale",
            "subcategory":"Electrical",
            "type":"Manufacturing & Wholesale Goods"
        }
    ],
    "sg:phone":"+1 847 488 9200",
    "sg:postcode":"60123",
    "sg:province":"IL",
    "sg:tags":[
        "equipment",
        "industrial",
        "electronic",
        "electric",
        "supply"
    ],
    "sg:website":"www.allcontrol.com",
    "wof:name":"All Controll Enterprises",
    "wof:placetype":"venue"
},
  "geometry": {"coordinates":[-88.320359,42.062945],"type":"Point"}
}