{
  "type": "Feature",
  "properties": {
    "addr:full":"347 W Church St Ste B Sandwich IL 60548",
    "addr:housenumber":"347",
    "addr:postcode":"60548",
    "addr:street":"W Church St Ste B",
    "iso:country":"US",
    "sg:address":"347 W Church St Ste B",
    "sg:city":"Sandwich",
    "sg:classifiers":[
        {
            "category":"Insurance",
            "subcategory":"Hazard Insurance",
            "type":"Services"
        },
        {
            "category":"Insurance",
            "subcategory":"Insurance Agent",
            "type":"Services"
        },
        {
            "category":"Insurance",
            "subcategory":"Life Insurance",
            "type":"Services"
        },
        {
            "category":"Insurance",
            "subcategory":"Title Insurance",
            "type":"Services"
        }
    ],
    "sg:phone":"+1 815 786 6584",
    "sg:postcode":"60548",
    "sg:province":"IL",
    "sg:tags":[
        "auto",
        "commercial",
        "business",
        "homeowner"
    ],
    "sg:website":"http://www.countryfinancial.com/kathleen.martin",
    "wof:name":"COUNTRY Financial Kathleen Martin",
    "wof:placetype":"venue"
},
  "geometry": {"coordinates":[-88.626582,41.644087],"type":"Point"}
}