{
  "type": "Feature",
  "properties": {
    "iso:country":"US",
    "sg:address":"7818 Newbold Rd",
    "sg:city":"Cary",
    "sg:classifiers":[
        {
            "category":"Building & Trades",
            "subcategory":"Construction",
            "type":"Services"
        }
    ],
    "sg:phone":"+1 847 639 5972",
    "sg:postcode":"60013",
    "sg:province":"IL",
    "sg:tags":[
        "steel",
        "fabrication",
        "welding"
    ],
    "wof:name":"Loeffel Steel Products",
    "wof:placetype":"venue"
},
  "geometry": {"coordinates":[-88.209014,42.214966],"type":"Point"}
}