{
  "type": "Feature",
  "properties": {
    "iso:country":"US",
    "sg:address":"2505 Thoroughbred Trl",
    "sg:city":"Woodstock",
    "sg:classifiers":[
        {
            "category":"Building & Trades",
            "subcategory":"Landscaping Services",
            "type":"Services"
        }
    ],
    "sg:phone":"+1 815 337 7129",
    "sg:postcode":"60098",
    "sg:province":"IL",
    "sg:tags":[
        "lawn"
    ],
    "wof:name":"Spethman Landscaping",
    "wof:placetype":"venue"
},
  "geometry": {"coordinates":[-88.40246999999999,42.362672],"type":"Point"}
}