{
  "type": "Feature",
  "properties": {
    "addr:full":"8828 S Cicero Ave Oak Lawn IL 60453",
    "addr:housenumber":"8828",
    "addr:postcode":"60453",
    "addr:street":"S Cicero Ave",
    "iso:country":"US",
    "sg:address":"8828 S Cicero Ave",
    "sg:city":"Oak Lawn",
    "sg:classifiers":[
        {
            "category":"Shopping",
            "subcategory":"Mobile Phones",
            "type":"Retail Goods"
        }
    ],
    "sg:phone":"+1 708 229 0051",
    "sg:postcode":"60453",
    "sg:province":"IL",
    "wof:name":"Cleartalk Communications",
    "wof:placetype":"venue"
},
  "geometry": {"coordinates":[-87.741472,41.732175],"type":"Point"}
}