{
  "type": "Feature",
  "properties": {
    "iso:country":"US",
    "sg:address":"3310 N Milwaukee Ave",
    "sg:city":"Chicago",
    "sg:classifiers":[
        {
            "category":"Professional",
            "subcategory":"Management & Consulting",
            "type":"Services"
        }
    ],
    "sg:phone":"+1 773 777 7470",
    "sg:postcode":"60641",
    "sg:province":"IL",
    "wof:name":"Marins Construction",
    "wof:placetype":"venue"
},
  "geometry": {"coordinates":[-87.728009,41.941538],"type":"Point"}
}