{
  "type": "Feature",
  "properties": {
    "addr:full":"1705 Estes Ave Elk Grove Vlg IL 60007",
    "addr:housenumber":"1705",
    "addr:postcode":"60007",
    "addr:street":"Estes Ave",
    "iso:country":"US",
    "sg:address":"1705 Estes Ave",
    "sg:city":"Elk Grove Vlg",
    "sg:classifiers":[
        {
            "category":"Professional",
            "subcategory":"Business Services",
            "type":"Services"
        },
        {
            "category":"Manufacturing",
            "subcategory":"Paper Products",
            "type":"Manufacturing & Wholesale Goods"
        }
    ],
    "sg:phone":"+1 847 290 1014",
    "sg:postcode":"60007",
    "sg:province":"IL",
    "sg:tags":[
        "lamination",
        "mfg"
    ],
    "wof:name":"East Of Midnight Laminations",
    "wof:placetype":"venue"
},
  "geometry": {"coordinates":[-87.949527,42.006092],"type":"Point"}
}