{
  "type": "Feature",
  "properties": {
    "addr:full":"350 McHenry Rd Buffalo Grove IL 60089",
    "addr:housenumber":"350",
    "addr:postcode":"60089",
    "addr:street":"Mchenry Rd",
    "iso:country":"US",
    "sg:address":"350 McHenry Rd",
    "sg:city":"Buffalo Grove",
    "sg:classifiers":[
        {
            "category":"Arts & Performance",
            "subcategory":"Theater",
            "type":"Entertainment"
        },
        {
            "category":"Recreation",
            "type":"Entertainment"
        }
    ],
    "sg:phone":"+1 847 520 5800",
    "sg:postcode":"60089",
    "sg:province":"IL",
    "sg:tags":[
        "group",
        "center"
    ],
    "wof:name":"Eskape Entertainment Center",
    "wof:placetype":"venue"
},
  "geometry": {"coordinates":[-87.960987,42.160506],"type":"Point"}
}