{
  "type": "Feature",
  "properties": {
    "addr:full":"300 N James St Tremont IL 61568",
    "addr:housenumber":"300",
    "addr:postcode":"61568",
    "addr:street":"N James St",
    "iso:country":"US",
    "sg:address":"300 N James St",
    "sg:city":"Tremont",
    "sg:classifiers":[
        {
            "category":"Building & Trades",
            "subcategory":"Construction",
            "type":"Services"
        },
        {
            "category":"Manufacturing",
            "subcategory":"Building Materials",
            "type":"Manufacturing & Wholesale Goods"
        }
    ],
    "sg:phone":"+1 309 925 5602",
    "sg:postcode":"61568",
    "sg:province":"IL",
    "sg:tags":[
        "roofing",
        "industrial",
        "supply",
        "contractor",
        "equipment",
        "siding",
        "contractors-commercial"
    ],
    "wof:name":"Koch Konstruction",
    "wof:placetype":"venue"
},
  "geometry": {"coordinates":[-89.48983800000001,40.529549],"type":"Point"}
}