{
  "type": "Feature",
  "properties": {
    "addr:full":"2531 Ashland Ave Evanston IL 60201",
    "addr:housenumber":"2531",
    "addr:postcode":"60201",
    "addr:street":"Ashland Ave",
    "iso:country":"US",
    "sg:address":"2531 Ashland Ave",
    "sg:city":"Evanston",
    "sg:classifiers":[
        {
            "category":"Shopping",
            "subcategory":"Books",
            "type":"Retail Goods"
        }
    ],
    "sg:phone":"+1   ",
    "sg:postcode":"60201",
    "sg:province":"IL",
    "wof:name":"Jeff Hirsch Books",
    "wof:placetype":"venue"
},
  "geometry": {"coordinates":[-87.693817,42.063032],"type":"Point"}
}