{
  "type": "Feature",
  "properties": {
    "iso:country":"US",
    "sg:address":"1842 E 79th St",
    "sg:city":"Chicago",
    "sg:classifiers":[
        {
            "category":"Utilities",
            "subcategory":"Telephone",
            "type":"Services"
        }
    ],
    "sg:phone":"+1 773 374 3700",
    "sg:postcode":"60649",
    "sg:province":"IL",
    "sg:tags":[
        "security",
        "system",
        "install"
    ],
    "wof:name":"Foscetts Communications Alarm",
    "wof:placetype":"venue"
},
  "geometry": {"coordinates":[-87.578671,41.751646],"type":"Point"}
}