{
  "type": "Feature",
  "properties": {
    "addr:full":"26605 W Wilmot Rd Antioch IL 60002",
    "addr:housenumber":"26605",
    "addr:postcode":"60002",
    "addr:street":"W Wilmot Rd",
    "iso:country":"US",
    "sg:address":"26605 W Wilmot Rd",
    "sg:city":"Antioch",
    "sg:classifiers":[
        {
            "category":"Organizations",
            "subcategory":"Religious Organization",
            "type":"Services"
        }
    ],
    "sg:phone":"+1 847 395 7801",
    "sg:postcode":"60002",
    "sg:province":"IL",
    "wof:name":"Lakeview Mssnary Baptst Church",
    "wof:placetype":"venue"
},
  "geometry": {"coordinates":[-88.154619,42.491915],"type":"Point"}
}