{
  "type": "Feature",
  "properties": {
    "addr:full":"350 N La Salle Drive Chicago IL 60654",
    "addr:housenumber":"350",
    "addr:postcode":"60654",
    "addr:street":"N La Salle Drive",
    "iso:country":"US",
    "sg:address":"350 N La Salle Drive",
    "sg:city":"Chicago",
    "sg:classifiers":[
        {
            "category":"Professional",
            "subcategory":"Lawyer & Legal Services",
            "type":"Services"
        }
    ],
    "sg:phone":"+1 312 329 0830",
    "sg:postcode":"60654",
    "sg:province":"IL",
    "sg:website":"www.wgclarklaw.com",
    "wof:name":"Clark William G Jr & Associates Ltd",
    "wof:placetype":"venue"
},
  "geometry": {"coordinates":[-87.633089,41.88856],"type":"Point"}
}