{
  "type": "Feature",
  "properties": {
    "addr:full":"1801 S Indiana Ave Chicago IL 60616",
    "addr:housenumber":"1801",
    "addr:postcode":"60616",
    "addr:street":"S Indiana Ave",
    "iso:country":"US",
    "sg:address":"1801 S Indiana Ave",
    "sg:city":"Chicago",
    "sg:classifiers":[
        {
            "category":"Arts & Performance",
            "subcategory":"Art Gallery",
            "type":"Entertainment"
        },
        {
            "category":"Museum",
            "type":"Entertainment"
        }
    ],
    "sg:phone":"+1 312 326 0270",
    "sg:postcode":"60616",
    "sg:province":"IL",
    "sg:website":"www.nvvam.org/",
    "wof:name":"National Vietnam Veterans Art Museum",
    "wof:placetype":"venue"
},
  "geometry": {"coordinates":[-87.622101,41.857498],"type":"Point"}
}