{
  "type": "Feature",
  "properties": {
    "addr:full":"1100 N Illinois St Swansea IL 62226",
    "addr:housenumber":"1100",
    "addr:postcode":"62226",
    "addr:street":"N Illinois St",
    "iso:country":"US",
    "sg:address":"1100 N Illinois St",
    "sg:city":"Swansea",
    "sg:classifiers":[
        {
            "category":"Manufacturing",
            "subcategory":"Metals",
            "type":"Manufacturing & Wholesale Goods"
        }
    ],
    "sg:phone":"+1 618 233 0182",
    "sg:postcode":"62226",
    "sg:province":"IL",
    "sg:tags":[
        "casting"
    ],
    "sg:website":"www.century-brass.com",
    "wof:name":"Century Brass Works Inc",
    "wof:placetype":"venue"
},
  "geometry": {"coordinates":[-89.98419199999999,38.524795],"type":"Point"}
}