{
  "type": "Feature",
  "properties": {
    "addr:full":"2205 N Lewis Ave Waukegan IL 60087",
    "addr:housenumber":"2205",
    "addr:postcode":"60087",
    "addr:street":"N Lewis Ave",
    "iso:country":"US",
    "sg:address":"2205 N Lewis Ave",
    "sg:city":"Waukegan",
    "sg:classifiers":[
        {
            "category":"Shopping",
            "subcategory":"Department Store",
            "type":"Retail Goods"
        }
    ],
    "sg:phone":"+1 847 263 4408",
    "sg:postcode":"60087",
    "sg:province":"IL",
    "sg:tags":[
        "shop"
    ],
    "wof:name":"Dollar General",
    "wof:placetype":"venue"
},
  "geometry": {"coordinates":[-87.855158,42.393773],"type":"Point"}
}