{
  "type": "Feature",
  "properties": {
    "iso:country":"US",
    "sg:address":"804 State St",
    "sg:city":"Quincy",
    "sg:classifiers":[
        {
            "category":"Professional",
            "subcategory":"Advertising",
            "type":"Services"
        }
    ],
    "sg:phone":"+1 217 222 8499",
    "sg:postcode":"62301",
    "sg:province":"IL",
    "sg:tags":[
        "counselor"
    ],
    "wof:name":"Amateur Sports Promotion",
    "wof:placetype":"venue"
},
  "geometry": {"coordinates":[-91.40325,39.926486],"type":"Point"}
}