{
  "type": "Feature",
  "properties": {
    "iso:country":"US",
    "sg:address":"120 W Ferguson Ave",
    "sg:city":"Wood River",
    "sg:classifiers":[
        {
            "category":"Home & Garden",
            "subcategory":"Building Materials",
            "type":"Retail Goods"
        },
        {
            "category":"Building & Trades",
            "subcategory":"Construction",
            "type":"Services"
        }
    ],
    "sg:phone":"+1 618 254 5786",
    "sg:postcode":"62095",
    "sg:province":"IL",
    "sg:tags":[
        "glass",
        "window",
        "contractor",
        "installing",
        "plate"
    ],
    "wof:name":"Slayden Glass Inc",
    "wof:placetype":"venue"
},
  "geometry": {"coordinates":[-90.10053,38.860827],"type":"Point"}
}