{
  "type": "Feature",
  "properties": {
    "iso:country":"US",
    "sg:address":"3400 W 79th St",
    "sg:city":"Chicago",
    "sg:classifiers":[
        {
            "category":"Home & Garden",
            "subcategory":"Building Materials",
            "type":"Retail Goods"
        }
    ],
    "sg:phone":"+1 773 776 6933",
    "sg:postcode":"60652",
    "sg:province":"IL",
    "sg:tags":[
        "supply"
    ],
    "wof:name":"One Stop Parts & Service",
    "wof:placetype":"venue"
},
  "geometry": {"coordinates":[-87.70730399999999,41.749799],"type":"Point"}
}