{
  "type": "Feature",
  "properties": {
    "iso:country":"US",
    "sg:address":"529 Illinois Rd",
    "sg:city":"Wilmette",
    "sg:classifiers":[
        {
            "category":"Building & Trades",
            "subcategory":"Construction",
            "type":"Services"
        }
    ],
    "sg:phone":"+1 224 522 2006",
    "sg:postcode":"60091",
    "sg:province":"IL",
    "sg:tags":[
        "painting",
        "contractor"
    ],
    "wof:name":"Sierra Remodeling,Inc.",
    "wof:placetype":"venue"
},
  "geometry": {"coordinates":[-87.730762,42.07424],"type":"Point"}
}