{
  "type": "Feature",
  "properties": {
    "addr:full":"803 N Elm St Centralia IL 62801",
    "addr:housenumber":"803",
    "addr:postcode":"62801",
    "addr:street":"N Elm St",
    "iso:country":"US",
    "sg:address":"803 N Elm St",
    "sg:city":"Centralia",
    "sg:classifiers":[
        {
            "category":"Shopping",
            "subcategory":"Discount & Variety Stores",
            "type":"Retail Goods"
        },
        {
            "category":"Shopping",
            "subcategory":"Department Store",
            "type":"Retail Goods"
        }
    ],
    "sg:phone":"+1 618 532 6584",
    "sg:postcode":"62801",
    "sg:province":"IL",
    "sg:tags":[
        "shop"
    ],
    "wof:name":"Family Dollar Stores",
    "wof:placetype":"venue"
},
  "geometry": {"coordinates":[-89.12965199999999,38.535451],"type":"Point"}
}