{
  "type": "Feature",
  "properties": {
    "addr:full":"207 N 2nd St Peotone IL 60468",
    "addr:housenumber":"207",
    "addr:postcode":"60468",
    "addr:street":"N 2Nd St",
    "iso:country":"US",
    "sg:address":"207 N 2nd St",
    "sg:city":"Peotone",
    "sg:classifiers":[
        {
            "category":"Insurance",
            "subcategory":"Insurance Agent",
            "type":"Services"
        }
    ],
    "sg:phone":"+1 708 258 6775",
    "sg:postcode":"60468",
    "sg:province":"IL",
    "wof:name":"Lyle Carstens Insurance",
    "wof:placetype":"venue"
},
  "geometry": {"coordinates":[-87.790769,41.335423],"type":"Point"}
}