{
  "type": "Feature",
  "properties": {
    "addr:full":"476 Diens Dr Wheeling IL 60090",
    "addr:housenumber":"476",
    "addr:postcode":"60090",
    "addr:street":"Diens Dr",
    "iso:country":"US",
    "sg:address":"476 Diens Dr",
    "sg:city":"Wheeling",
    "sg:classifiers":[
        {
            "category":"Shopping",
            "subcategory":"Stationery & Office Supplies",
            "type":"Retail Goods"
        }
    ],
    "sg:phone":"+1 847 850 5263",
    "sg:postcode":"60090",
    "sg:province":"IL",
    "sg:tags":[
        "packing",
        "room",
        "shipping",
        "materials-shipping"
    ],
    "wof:name":"Monnex",
    "wof:placetype":"venue"
},
  "geometry": {"coordinates":[-87.93038199999999,42.14898],"type":"Point"}
}