{
  "type": "Feature",
  "properties": {
    "iso:country":"US",
    "sg:address":"20 Sunnydale Ave",
    "sg:city":"Jacksonville",
    "sg:classifiers":[
        {
            "category":"Farming",
            "subcategory":"Livestock Farm",
            "type":"Manufacturing & Wholesale Goods"
        },
        {
            "category":"Farming",
            "subcategory":"Farm",
            "type":"Manufacturing & Wholesale Goods"
        }
    ],
    "sg:phone":"+1 217 245 6489",
    "sg:postcode":"62650",
    "sg:province":"IL",
    "sg:tags":[
        "ranch"
    ],
    "wof:name":"Blanch Henderson",
    "wof:placetype":"venue"
},
  "geometry": {"coordinates":[-90.265764,39.725033],"type":"Point"}
}