{
  "type": "Feature",
  "properties": {
    "iso:country":"US",
    "sg:address":"417 15th St",
    "sg:city":"Moline",
    "sg:classifiers":[
        {
            "category":"Restaurant",
            "type":"Food & Drink"
        }
    ],
    "sg:menulink":"http://www.allmenus.com/il/moline/282734-bier-stube/menu/",
    "sg:phone":"+1 309 797 3049",
    "sg:postcode":"61265",
    "sg:province":"IL",
    "sg:tags":[
        "german",
        "american",
        "pub"
    ],
    "wof:name":"Bier Stube",
    "wof:placetype":"venue"
},
  "geometry": {"coordinates":[-90.51678099999999,41.506962],"type":"Point"}
}