{
  "type": "Feature",
  "properties": {
    "iso:country":"US",
    "sg:address":"1084 Industrial Dr",
    "sg:city":"Bensenville",
    "sg:classifiers":[
        {
            "category":"Health Services",
            "subcategory":"Nursing And Care Facility",
            "type":"Services"
        }
    ],
    "sg:phone":"+1 630 238 6580",
    "sg:postcode":"60106",
    "sg:province":"IL",
    "sg:tags":[
        "wound"
    ],
    "wof:name":"Clinical Wound Solutions",
    "wof:placetype":"venue"
},
  "geometry": {"coordinates":[-87.955746,41.976408],"type":"Point"}
}