{
  "type": "Feature",
  "properties": {
    "addr:full":"900 W Glenn Trl Elk Grove Village IL 60007",
    "addr:housenumber":"900",
    "addr:postcode":"60007",
    "addr:street":"W Glenn Trl",
    "iso:country":"US",
    "sg:address":"900 W Glenn Trl",
    "sg:city":"Elk Grove Village",
    "sg:classifiers":[
        {
            "category":"Education",
            "subcategory":"School",
            "type":"Public Place"
        }
    ],
    "sg:phone":"+1 847 301 2130",
    "sg:postcode":"60007",
    "sg:province":"IL",
    "sg:tags":[
        "elementary"
    ],
    "wof:name":"Adolph Link Elementary School",
    "wof:placetype":"venue"
},
  "geometry": {"coordinates":[-88.03865999999999,42.005891],"type":"Point"}
}