{
  "type": "Feature",
  "properties": {
    "addr:full":"2828 N Lincoln Ave Chicago IL 60657",
    "addr:housenumber":"2828",
    "addr:postcode":"60657",
    "addr:street":"N Lincoln Ave",
    "iso:country":"US",
    "sg:address":"2828 N Lincoln Ave",
    "sg:city":"Chicago",
    "sg:classifiers":[
        {
            "category":"Bars & Pubs",
            "type":"Food & Drink"
        }
    ],
    "sg:phone":"+1   ",
    "sg:postcode":"60657",
    "sg:province":"IL",
    "sg:tags":[
        "drinking"
    ],
    "wof:name":"Home Tavern",
    "wof:placetype":"venue"
},
  "geometry": {"coordinates":[-87.65871,41.932556],"type":"Point"}
}