{
  "type": "Feature",
  "properties": {
    "addr:full":"20 W Kinzie St Chicago IL 60654",
    "addr:housenumber":"20",
    "addr:postcode":"60654",
    "addr:street":"W Kinzie St",
    "iso:country":"US",
    "sg:address":"20 W Kinzie St",
    "sg:city":"Chicago",
    "sg:classifiers":[
        {
            "category":"Travel",
            "subcategory":"Hotels & Motels",
            "type":"Entertainment"
        }
    ],
    "sg:phone":"+1 312 395 9000",
    "sg:postcode":"60654",
    "sg:province":"IL",
    "sg:website":"www.amalfihotelchicago.com",
    "wof:name":"Amalfi Hotel Chicago",
    "wof:placetype":"venue"
},
  "geometry": {"coordinates":[-87.628912,41.889474],"type":"Point"}
}