{
  "type": "Feature",
  "properties": {
    "iso:country":"US",
    "sg:address":"535 N Lake St",
    "sg:city":"Mundelein",
    "sg:classifiers":[
        {
            "category":"Social Services",
            "type":"Services"
        }
    ],
    "sg:phone":"+1 847 949 1000",
    "sg:postcode":"60060",
    "sg:province":"IL",
    "sg:tags":[
        "profit",
        "agency"
    ],
    "wof:name":"American Red Cross Mid America",
    "wof:placetype":"venue"
},
  "geometry": {"coordinates":[-88.003953,42.272011],"type":"Point"}
}