{
  "type": "Feature",
  "properties": {
    "iso:country":"US",
    "sg:address":"78 Quail Run",
    "sg:city":"Collinsville",
    "sg:classifiers":[
        {
            "category":"Travel",
            "subcategory":"Travel Agent",
            "type":"Entertainment"
        }
    ],
    "sg:phone":"+1 618 346 9089",
    "sg:postcode":"62234",
    "sg:province":"IL",
    "sg:tags":[
        "agency",
        "bureau"
    ],
    "wof:name":"Lan-Se-Air Travel Inc",
    "wof:placetype":"venue"
},
  "geometry": {"coordinates":[-90.005161,38.691795],"type":"Point"}
}