{
  "type": "Feature",
  "properties": {
    "iso:country":"US",
    "sg:address":"129 Phelps Ave",
    "sg:city":"Rockford",
    "sg:classifiers":[
        {
            "category":"Wholesale",
            "subcategory":"Machinery & Supplies",
            "type":"Manufacturing & Wholesale Goods"
        }
    ],
    "sg:phone":"+1 815 229 8860",
    "sg:postcode":"61108",
    "sg:province":"IL",
    "sg:tags":[
        "bearing"
    ],
    "wof:name":"AST Bearings",
    "wof:placetype":"venue"
},
  "geometry": {"coordinates":[-89.004654,42.26272],"type":"Point"}
}