{
  "type": "Feature",
  "properties": {
    "iso:country":"US",
    "sg:address":"643 N Independence Blvd",
    "sg:city":"Romeoville",
    "sg:classifiers":[
        {
            "category":"Restaurant",
            "type":"Food & Drink"
        }
    ],
    "sg:phone":"+1 815 886 4242",
    "sg:postcode":"60446",
    "sg:province":"IL",
    "wof:name":"Danny Boy's",
    "wof:placetype":"venue"
},
  "geometry": {"coordinates":[-88.080456,41.6404],"type":"Point"}
}