{
  "type": "Feature",
  "properties": {
    "addr:full":"1061 W Argyle St Chicago IL 60640",
    "addr:housenumber":"1061",
    "addr:postcode":"60640",
    "addr:street":"W Argyle St",
    "iso:country":"US",
    "sg:address":"1061 W Argyle St",
    "sg:city":"Chicago",
    "sg:classifiers":[
        {
            "category":"Food & Beverages",
            "subcategory":"Bakery",
            "type":"Retail Goods"
        }
    ],
    "sg:phone":"+1 773 334 3735",
    "sg:postcode":"60640",
    "sg:province":"IL",
    "sg:tags":[
        "baker"
    ],
    "wof:name":"Double Happiness",
    "wof:placetype":"venue"
},
  "geometry": {"coordinates":[-87.65709699999999,41.973202],"type":"Point"}
}