{
  "type": "Feature",
  "properties": {
    "addr:full":"5100 W 122nd St Alsip IL 60803",
    "addr:housenumber":"5100",
    "addr:postcode":"60803",
    "addr:street":"W 122Nd St",
    "iso:country":"US",
    "sg:address":"5100 W 122nd St",
    "sg:city":"Alsip",
    "sg:classifiers":[
        {
            "category":"Professional",
            "subcategory":"Business Services",
            "type":"Services"
        }
    ],
    "sg:phone":"+1 708 427 2601",
    "sg:postcode":"60803",
    "sg:province":"IL",
    "wof:name":"Carl Reda Communication Inc",
    "wof:placetype":"venue"
},
  "geometry": {"coordinates":[-87.746664,41.670801],"type":"Point"}
}