{
  "type": "Feature",
  "properties": {
    "iso:country":"US",
    "sg:address":"107 E Center St",
    "sg:city":"Brighton",
    "sg:classifiers":[
        {
            "category":"Professional",
            "subcategory":"Engineering",
            "type":"Services"
        },
        {
            "category":"Home & Garden",
            "subcategory":"Building Materials",
            "type":"Retail Goods"
        },
        {
            "category":"Building & Trades",
            "subcategory":"Construction",
            "type":"Services"
        }
    ],
    "sg:phone":"+1 618 372 8375",
    "sg:postcode":"62012",
    "sg:province":"IL",
    "sg:tags":[
        "system",
        "specialty",
        "heating",
        "equipment",
        "contractor",
        "air conditioning"
    ],
    "sg:website":"http://find.trane.com/tcs-dealer-402467?utm_source=YP&utm_medium=banner&utm_campaign=TL",
    "wof:name":"Den-Son Inc",
    "wof:placetype":"venue"
},
  "geometry": {"coordinates":[-90.140524,39.039382],"type":"Point"}
}