{
  "type": "Feature",
  "properties": {
    "addr:full":"499 N Main St Glen Ellyn IL 60137",
    "addr:housenumber":"499",
    "addr:postcode":"60137",
    "addr:street":"N Main St",
    "iso:country":"US",
    "sg:address":"499 N Main St",
    "sg:city":"Glen Ellyn",
    "sg:classifiers":[
        {
            "category":"Restaurant",
            "type":"Food & Drink"
        }
    ],
    "sg:phone":"+1 630 469 0000",
    "sg:postcode":"60137",
    "sg:province":"IL",
    "sg:tags":[
        "new",
        "american",
        "brunch",
        "breakfast"
    ],
    "sg:website":"www.honeycafe.net",
    "wof:name":"Honey Caf?",
    "wof:placetype":"venue"
},
  "geometry": {"coordinates":[-88.066754,41.877561],"type":"Point"}
}