{
  "type": "Feature",
  "properties": {
    "iso:country":"US",
    "sg:address":"222 S Riverside Plz # 800",
    "sg:city":"Chicago",
    "sg:classifiers":[
        {
            "category":"Insurance",
            "subcategory":"Hazard Insurance",
            "type":"Services"
        },
        {
            "category":"Insurance",
            "subcategory":"Life Insurance",
            "type":"Services"
        },
        {
            "category":"Insurance",
            "subcategory":"Health Insurance",
            "type":"Services"
        }
    ],
    "sg:phone":"+1 312 454 9632",
    "sg:postcode":"60606",
    "sg:province":"IL",
    "sg:tags":[
        "dental"
    ],
    "wof:name":"Sun Life Assurance Company Of Canada (Us)",
    "wof:placetype":"venue"
},
  "geometry": {"coordinates":[-87.638509,41.879037],"type":"Point"}
}