{
  "type": "Feature",
  "properties": {
    "iso:country":"US",
    "sg:address":"539 N State St",
    "sg:city":"Chicago",
    "sg:classifiers":[
        {
            "category":"Restaurant",
            "type":"Food & Drink"
        }
    ],
    "sg:menulink":"http://www.allmenus.com/il/chicago/23184-weber-grill/menu/",
    "sg:phone":"+1 312 467 9696",
    "sg:postcode":"60610",
    "sg:province":"IL",
    "sg:tags":[
        "american"
    ],
    "wof:name":"Weber Grill",
    "wof:placetype":"venue"
},
  "geometry": {"coordinates":[-87.628091,41.891853],"type":"Point"}
}