{
  "type": "Feature",
  "properties": {
    "iso:country":"US",
    "sg:address":"225 James St",
    "sg:city":"Bethalto",
    "sg:classifiers":[
        {
            "category":"Banks & Credit Unions",
            "subcategory":"Bank",
            "type":"Services"
        }
    ],
    "sg:phone":"+1 618 377 3948",
    "sg:postcode":"62010",
    "sg:province":"IL",
    "sg:tags":[
        "state"
    ],
    "wof:name":"Bea Credit Union",
    "wof:placetype":"venue"
},
  "geometry": {"coordinates":[-90.03972,38.913271],"type":"Point"}
}