{
  "type": "Feature",
  "properties": {
    "iso:country":"US",
    "sg:address":"1770 Potter Rd",
    "sg:city":"Park Ridge",
    "sg:classifiers":[
        {
            "category":"Freight",
            "type":"Transportation"
        }
    ],
    "sg:phone":"+1 847 823 2655",
    "sg:postcode":"60068",
    "sg:province":"IL",
    "sg:tags":[
        "arrangement"
    ],
    "wof:name":"Chaika Inc",
    "wof:placetype":"venue"
},
  "geometry": {"coordinates":[-87.86001899999999,42.038233],"type":"Point"}
}