{
  "type": "Feature",
  "properties": {
    "addr:full":"701 S Pulaski Rd Chicago IL 60624",
    "addr:housenumber":"701",
    "addr:postcode":"60624",
    "addr:street":"S Pulaski Rd",
    "iso:country":"US",
    "sg:address":"701 S Pulaski Rd",
    "sg:city":"Chicago",
    "sg:classifiers":[
        {
            "category":"Health Services",
            "subcategory":"Doctor",
            "type":"Services"
        }
    ],
    "sg:phone":"+1 773 638 6655",
    "sg:postcode":"60624",
    "sg:province":"IL",
    "wof:name":"Duwell Medical Cntr",
    "wof:placetype":"venue"
},
  "geometry": {"coordinates":[-87.725098,41.872101],"type":"Point"}
}