{
  "type": "Feature",
  "properties": {
    "iso:country":"US",
    "sg:address":"44 E Downer Pl",
    "sg:city":"Aurora",
    "sg:classifiers":[
        {
            "category":"Recreation",
            "type":"Entertainment"
        }
    ],
    "sg:phone":"+1 630 844 3648",
    "sg:postcode":"60505",
    "sg:province":"IL",
    "sg:tags":[
        "historical"
    ],
    "wof:name":"Aurora Historic Districts",
    "wof:placetype":"venue"
},
  "geometry": {"coordinates":[-88.31559900000001,41.756947],"type":"Point"}
}