{
  "type": "Feature",
  "properties": {
    "iso:country":"US",
    "sg:address":"500 Moran St",
    "sg:city":"Joliet",
    "sg:classifiers":[
        {
            "category":"Education",
            "subcategory":"School",
            "type":"Public Place"
        }
    ],
    "sg:phone":"+1 815 723 0169",
    "sg:postcode":"60435",
    "sg:province":"IL",
    "wof:name":"M J Cunningham School",
    "wof:placetype":"venue"
},
  "geometry": {"coordinates":[-88.095398,41.541537],"type":"Point"}
}