{
  "type": "Feature",
  "properties": {
    "iso:country":"US",
    "sg:address":"444 N Main Plz",
    "sg:city":"Chatham",
    "sg:classifiers":[
        {
            "category":"Insurance",
            "subcategory":"Hazard Insurance",
            "type":"Services"
        },
        {
            "category":"Banks & Credit Unions",
            "subcategory":"Financial Services",
            "type":"Services"
        }
    ],
    "sg:phone":"+1 217 483 9460",
    "sg:postcode":"62629",
    "sg:province":"IL",
    "sg:tags":[
        "commercial",
        "business"
    ],
    "wof:name":"Sullivan Financial Services",
    "wof:placetype":"venue"
},
  "geometry": {"coordinates":[-89.704462,39.670025],"type":"Point"}
}