{
  "type": "Feature",
  "properties": {
    "addr:full":"865 Schluetter Germaine Rd Belleville IL 62220",
    "addr:housenumber":"865",
    "addr:postcode":"62220",
    "addr:street":"Schluetter Germaine Rd",
    "iso:country":"US",
    "sg:address":"865 Schluetter Germaine Rd",
    "sg:city":"Belleville",
    "sg:classifiers":[
        {
            "category":"Building & Trades",
            "subcategory":"Construction",
            "type":"Services"
        }
    ],
    "sg:phone":"+1 618 233 6970",
    "sg:postcode":"62220",
    "sg:province":"IL",
    "sg:tags":[
        "contracting",
        "masonry"
    ],
    "wof:name":"Gass Masonry Inc",
    "wof:placetype":"venue"
},
  "geometry": {"coordinates":[-89.955399,38.46349],"type":"Point"}
}