{
  "type": "Feature",
  "properties": {
    "addr:full":"714 Greenbay Ave Calumet City IL 60409",
    "addr:housenumber":"714",
    "addr:postcode":"60409",
    "addr:street":"Greenbay Ave",
    "iso:country":"US",
    "sg:address":"714 Greenbay Ave",
    "sg:city":"Calumet City",
    "sg:classifiers":[
        {
            "category":"Recreation",
            "type":"Entertainment"
        }
    ],
    "sg:phone":"+1 708 868 6159",
    "sg:postcode":"60409",
    "sg:province":"IL",
    "sg:tags":[
        "club",
        "membership"
    ],
    "wof:name":"Willy Roy Soccer",
    "wof:placetype":"venue"
},
  "geometry": {"coordinates":[-87.540598,41.614716],"type":"Point"}
}