{
  "type": "Feature",
  "properties": {
    "addr:full":"225 W New York St Aurora IL 60506",
    "addr:housenumber":"225",
    "addr:postcode":"60506",
    "addr:street":"W New York St",
    "iso:country":"US",
    "sg:address":"225 W New York St",
    "sg:city":"Aurora",
    "sg:classifiers":[
        {
            "category":"Retail",
            "subcategory":"Auto Repair",
            "type":"Services"
        }
    ],
    "sg:phone":"+1 630 892 6441",
    "sg:postcode":"60506",
    "sg:province":"IL",
    "sg:tags":[
        "body",
        "automobile",
        "painting",
        "repairing"
    ],
    "wof:name":"Pino Auto Body Shop",
    "wof:placetype":"venue"
},
  "geometry": {"coordinates":[-88.31810299999999,41.760915],"type":"Point"}
}