{
  "type": "Feature",
  "properties": {
    "addr:full":"275 Old Orchard Shopping Ctr Skokie IL 60077",
    "addr:housenumber":"275",
    "addr:postcode":"60077",
    "addr:street":"Old Orchard Shopping Ctr",
    "iso:country":"US",
    "sg:address":"275 Old Orchard Shopping Ctr",
    "sg:city":"Skokie",
    "sg:classifiers":[
        {
            "category":"Restaurant",
            "type":"Food & Drink"
        }
    ],
    "sg:menulink":"http://www.allmenus.com/il/niles/212601-mcdonalds/menu/",
    "sg:postcode":"60077",
    "sg:province":"IL",
    "sg:tags":[
        "burger",
        "american"
    ],
    "wof:name":"McDonald's",
    "wof:placetype":"venue"
},
  "geometry": {"coordinates":[-87.748859,42.056955],"type":"Point"}
}