{
  "type": "Feature",
  "properties": {
    "addr:full":"11800 Cardinal Ln Caledonia IL 61011",
    "addr:housenumber":"11800",
    "addr:postcode":"61011",
    "addr:street":"Cardinal Ln",
    "iso:country":"US",
    "sg:address":"11800 Cardinal Ln",
    "sg:city":"Caledonia",
    "sg:classifiers":[
        {
            "category":"Health Services",
            "subcategory":"Clinic",
            "type":"Services"
        }
    ],
    "sg:phone":"+1 815 885 4329",
    "sg:postcode":"61011",
    "sg:province":"IL",
    "wof:name":"Rockford Med Rehabilitation",
    "wof:placetype":"venue"
},
  "geometry": {"coordinates":[-88.931904,42.323941],"type":"Point"}
}