{
  "type": "Feature",
  "properties": {
    "iso:country":"US",
    "sg:address":"1197 N Henderson St",
    "sg:city":"Galesburg",
    "sg:classifiers":[
        {
            "category":"Banks & Credit Unions",
            "subcategory":"Investment Brokerage",
            "type":"Services"
        },
        {
            "category":"Banks & Credit Unions",
            "subcategory":"Bank",
            "type":"Services"
        },
        {
            "category":"Banks & Credit Unions",
            "subcategory":"Financial Services",
            "type":"Services"
        }
    ],
    "sg:phone":"+1 888 648 5816",
    "sg:postcode":"61401",
    "sg:province":"IL",
    "sg:tags":[
        "advisory",
        "mutual",
        "retirement",
        "annuity",
        "broker",
        "fund",
        "planning",
        "plan",
        "consultant",
        "security",
        "bond",
        "insurance",
        "stock"
    ],
    "sg:website":"http://edwardjones.com",
    "wof:name":"Edward Jones - DANIEL B BUTLER",
    "wof:placetype":"venue"
},
  "geometry": {"coordinates":[-90.38318700000001,40.962258],"type":"Point"}
}