{
  "type": "Feature",
  "properties": {
    "addr:full":"1908 N Kostner Ave Fl 1 Chicago IL 60639",
    "addr:housenumber":"1908;1",
    "addr:postcode":"60639",
    "addr:street":"N Kostner Ave Fl",
    "iso:country":"US",
    "sg:address":"1908 N Kostner Ave Fl 1",
    "sg:city":"Chicago",
    "sg:classifiers":[
        {
            "category":"Wholesale",
            "subcategory":"Office Equipment",
            "type":"Manufacturing & Wholesale Goods"
        }
    ],
    "sg:phone":"+1 773 772 6960",
    "sg:postcode":"60639",
    "sg:province":"IL",
    "sg:tags":[
        "equipment-installation",
        "furniture"
    ],
    "wof:name":"Metro Facility Services",
    "wof:placetype":"venue"
},
  "geometry": {"coordinates":[-87.736255,41.915368],"type":"Point"}
}