{
  "type": "Feature",
  "properties": {
    "iso:country":"US",
    "sg:address":"470 W Lincoln Hwy",
    "sg:city":"Chicago Heights",
    "sg:classifiers":[
        {
            "category":"Restaurant",
            "type":"Food & Drink"
        }
    ],
    "sg:menulink":"http://www.allmenus.com/il/bloom/105808-pepes-mexican-restaurant/menu/",
    "sg:phone":"+1 708 748 2400",
    "sg:postcode":"60411",
    "sg:province":"IL",
    "sg:tags":[
        "mexican"
    ],
    "wof:name":"Pepe's Mexican Restaurant",
    "wof:placetype":"venue"
},
  "geometry": {"coordinates":[-87.663898,41.506006],"type":"Point"}
}