{
  "type": "Feature",
  "properties": {
    "iso:country":"US",
    "sg:address":"2866 N Milwaukee Ave",
    "sg:city":"Chicago",
    "sg:classifiers":[
        {
            "category":"Home & Garden",
            "subcategory":"Home Furnishings",
            "type":"Retail Goods"
        },
        {
            "category":"Manufacturing",
            "subcategory":"Soap",
            "type":"Manufacturing & Wholesale Goods"
        }
    ],
    "sg:phone":"+1 773 276 7777",
    "sg:postcode":"60618",
    "sg:province":"IL",
    "sg:tags":[
        "housewares",
        "housewares-wholesale",
        "manufacturer"
    ],
    "wof:name":"Chicago Houseware Int'l",
    "wof:placetype":"venue"
},
  "geometry": {"coordinates":[-87.71433500000001,41.933308],"type":"Point"}
}