{
  "type": "Feature",
  "properties": {
    "iso:country":"US",
    "sg:address":"430 Pennsylvania Ave",
    "sg:city":"Glen Ellyn",
    "sg:classifiers":[
        {
            "category":"Health Services",
            "subcategory":"Doctor",
            "type":"Services"
        }
    ],
    "sg:phone":"+1 630 469 7700",
    "sg:postcode":"60137",
    "sg:province":"IL",
    "wof:name":"Huang Annie MD",
    "wof:placetype":"venue"
},
  "geometry": {"coordinates":[-88.071189,41.876954],"type":"Point"}
}