{
  "type": "Feature",
  "properties": {
    "iso:country":"US",
    "sg:address":"6730 N 900th Rd",
    "sg:city":"Colchester",
    "sg:phone":"+1 309 776 4689",
    "sg:postcode":"62326",
    "sg:province":"IL",
    "sg:tags":[
        "farm",
        "grain",
        "cash"
    ],
    "wof:name":"Chas Butterfield",
    "wof:placetype":"venue"
},
  "geometry": {"coordinates":[-90.77865199999999,40.412529],"type":"Point"}
}