{
  "type": "Feature",
  "properties": {
    "addr:full":"406 W 5th Ave Naperville IL 60563",
    "addr:housenumber":"406",
    "addr:postcode":"60563",
    "addr:street":"W 5Th Ave",
    "iso:country":"US",
    "sg:address":"406 W 5th Ave",
    "sg:city":"Naperville",
    "sg:classifiers":[
        {
            "category":"Restaurant",
            "type":"Food & Drink"
        }
    ],
    "sg:menulink":"http://www.allmenus.com/il/naperville/68918-rosatis-pizza/menu/",
    "sg:phone":"+1 630 305 3500",
    "sg:postcode":"60563",
    "sg:province":"IL",
    "sg:tags":[
        "american",
        "pizza"
    ],
    "wof:name":"Rosati's Pizza",
    "wof:placetype":"venue"
},
  "geometry": {"coordinates":[-88.154404,41.780998],"type":"Point"}
}