{
  "type": "Feature",
  "properties": {
    "addr:full":"23939 Lancaster Ct Deer Park IL 60010",
    "addr:housenumber":"23939",
    "addr:postcode":"60010",
    "addr:street":"Lancaster Ct",
    "iso:country":"US",
    "sg:address":"23939 Lancaster Ct",
    "sg:city":"Deer Park",
    "sg:classifiers":[
        {
            "category":"Building & Trades",
            "subcategory":"Landscaping Services",
            "type":"Services"
        }
    ],
    "sg:phone":"+1 847 719 1009",
    "sg:postcode":"60010",
    "sg:province":"IL",
    "sg:tags":[
        "landscape",
        "contractor"
    ],
    "wof:name":"Chicagoland Greenskeeper Inc",
    "wof:placetype":"venue"
},
  "geometry": {"coordinates":[-88.09891399999999,42.181622],"type":"Point"}
}