{
  "type": "Feature",
  "properties": {
    "iso:country":"US",
    "sg:address":"2601 W Main St",
    "sg:city":"Carbondale",
    "sg:classifiers":[
        {
            "category":"Health Services",
            "subcategory":"Doctor",
            "type":"Services"
        }
    ],
    "sg:phone":"+1 618 549 5361",
    "sg:postcode":"62901",
    "sg:province":"IL",
    "wof:name":"Pfalzgraf Frederick J MD",
    "wof:placetype":"venue"
},
  "geometry": {"coordinates":[-89.251404,37.7355],"type":"Point"}
}