{
  "type": "Feature",
  "properties": {
    "iso:country":"US",
    "sg:address":"714 E White St",
    "sg:city":"Clinton",
    "sg:classifiers":[
        {
            "category":"Place Of Worship",
            "type":"Public Place"
        }
    ],
    "sg:phone":"+1 217 935 3809",
    "sg:postcode":"61727",
    "sg:province":"IL",
    "sg:tags":[
        "church"
    ],
    "wof:name":"Little Galilee Christian Assembly",
    "wof:placetype":"venue"
},
  "geometry": {"coordinates":[-88.968425,40.148861],"type":"Point"}
}