{
  "type": "Feature",
  "properties": {
    "addr:full":"Willard Airport Savoy IL 61874",
    "addr:postcode":"61874",
    "iso:country":"US",
    "sg:address":"Willard Airport",
    "sg:city":"Savoy",
    "sg:classifiers":[
        {
            "category":"Retail",
            "subcategory":"Auto Rental",
            "type":"Services"
        }
    ],
    "sg:phone":"+1 217 359 5259",
    "sg:postcode":"61874",
    "sg:province":"IL",
    "sg:tags":[
        "car"
    ],
    "wof:name":"National Car Rental",
    "wof:placetype":"venue"
},
  "geometry": {"coordinates":[-88.24659699999999,40.066299],"type":"Point"}
}