{
  "type": "Feature",
  "properties": {
    "iso:country":"US",
    "sg:address":"204 N Locust St",
    "sg:city":"Arcola",
    "sg:classifiers":[
        {
            "category":"Local Transit",
            "type":"Transportation"
        }
    ],
    "sg:phone":"+1 217 268 4848",
    "sg:postcode":"61910",
    "sg:province":"IL",
    "sg:tags":[
        "ambulance"
    ],
    "wof:name":"Schrader Ambulance Svc",
    "wof:placetype":"venue"
},
  "geometry": {"coordinates":[-88.306186,39.686806],"type":"Point"}
}