{
  "type": "Feature",
  "properties": {
    "iso:country":"US",
    "sg:address":"1871 Hicks Rd",
    "sg:city":"Rolling Meadows",
    "sg:classifiers":[
        {
            "category":"Utilities",
            "subcategory":"Telephone",
            "type":"Services"
        }
    ],
    "sg:phone":"+1 847 885 3333",
    "sg:postcode":"60008",
    "sg:province":"IL",
    "sg:tags":[
        "communications",
        "contact",
        "system",
        "center"
    ],
    "sg:website":"www.csccsc.com",
    "wof:name":"Communication Solutions Corp",
    "wof:placetype":"venue"
},
  "geometry": {"coordinates":[-88.034114,42.089657],"type":"Point"}
}