{
  "type": "Feature",
  "properties": {
    "addr:full":"447 Circle Dr Kewanee IL 61443",
    "addr:housenumber":"447",
    "addr:postcode":"61443",
    "addr:street":"Circle Dr",
    "iso:country":"US",
    "sg:address":"447 Circle Dr",
    "sg:city":"Kewanee",
    "sg:classifiers":[
        {
            "category":"Building & Trades",
            "subcategory":"Construction",
            "type":"Services"
        }
    ],
    "sg:phone":"+1 309 853 5304",
    "sg:postcode":"61443",
    "sg:province":"IL",
    "sg:tags":[
        "masonry",
        "contractor"
    ],
    "wof:name":"Southside Masonry Constr Inc",
    "wof:placetype":"venue"
},
  "geometry": {"coordinates":[-89.937837,41.224345],"type":"Point"}
}