{
  "type": "Feature",
  "properties": {
    "iso:country":"US",
    "sg:address":"2201 Myrtle St",
    "sg:city":"Rock Falls",
    "sg:classifiers":[
        {
            "category":"Farming",
            "subcategory":"Farm",
            "type":"Manufacturing & Wholesale Goods"
        }
    ],
    "sg:phone":"+1 815 625 0661",
    "sg:postcode":"61071",
    "sg:province":"IL",
    "wof:name":"Blackburn Brothers Farm",
    "wof:placetype":"venue"
},
  "geometry": {"coordinates":[-89.657046,41.774611],"type":"Point"}
}