{
  "type": "Feature",
  "properties": {
    "iso:country":"US",
    "sg:address":"302 N Dunton Ave",
    "sg:city":"Arlington Hts",
    "sg:classifiers":[
        {
            "category":"Organizations",
            "subcategory":"Non-profit Organization",
            "type":"Services"
        }
    ],
    "sg:phone":"+1 847 342 0846",
    "sg:postcode":"60004",
    "sg:province":"IL",
    "sg:tags":[
        "human"
    ],
    "wof:name":"Faith Community Homes",
    "wof:placetype":"venue"
},
  "geometry": {"coordinates":[-87.982961,42.086458],"type":"Point"}
}