{
  "type": "Feature",
  "properties": {
    "iso:country":"US",
    "sg:address":"1255 N Pulaski Rd",
    "sg:city":"Chicago",
    "sg:classifiers":[
        {
            "category":"Restaurant",
            "type":"Food & Drink"
        }
    ],
    "sg:phone":"+1 773 486 8977",
    "sg:postcode":"60651",
    "sg:province":"IL",
    "sg:tags":[
        "american",
        "latin"
    ],
    "wof:name":"El Sitio",
    "wof:placetype":"venue"
},
  "geometry": {"coordinates":[-87.72580499999999,41.904177],"type":"Point"}
}