{
  "type": "Feature",
  "properties": {
    "iso:country":"US",
    "sg:address":"1413 Leonard Pl",
    "sg:city":"Evanston",
    "sg:classifiers":[
        {
            "category":"Shopping",
            "subcategory":"Used Merchandise",
            "type":"Retail Goods"
        }
    ],
    "sg:phone":"+1   ",
    "sg:postcode":"60201",
    "sg:province":"IL",
    "wof:name":"Ways of Wisdom",
    "wof:placetype":"venue"
},
  "geometry": {"coordinates":[-87.691377,42.057258],"type":"Point"}
}