{
  "type": "Feature",
  "properties": {
    "addr:full":"13982 N 1500th Ave Geneseo IL 61254",
    "addr:housenumber":"13982",
    "addr:postcode":"61254",
    "addr:street":"N 1500Th Ave",
    "iso:country":"US",
    "sg:address":"13982 N 1500th Ave",
    "sg:city":"Geneseo",
    "sg:classifiers":[
        {
            "category":"Government",
            "subcategory":"Office",
            "type":"Public Place"
        }
    ],
    "sg:phone":"+1 309 944 6355",
    "sg:postcode":"61254",
    "sg:province":"IL",
    "sg:tags":[
        "city"
    ],
    "wof:name":"Munson Center Town Hall",
    "wof:placetype":"venue"
},
  "geometry": {"coordinates":[-90.165813,41.368422],"type":"Point"}
}