{
  "type": "Feature",
  "properties": {
    "addr:full":"70 Barney Dr Joliet IL 60435",
    "addr:housenumber":"70",
    "addr:postcode":"60435",
    "addr:street":"Barney Dr",
    "iso:country":"US",
    "sg:address":"70 Barney Dr",
    "sg:city":"Joliet",
    "sg:classifiers":[
        {
            "category":"Restaurant",
            "type":"Food & Drink"
        }
    ],
    "sg:phone":"+1 815 741 2502",
    "sg:postcode":"60435",
    "sg:province":"IL",
    "sg:tags":[
        "eating"
    ],
    "wof:name":"Pizzas By Marchelloni",
    "wof:placetype":"venue"
},
  "geometry": {"coordinates":[-88.143095,41.522674],"type":"Point"}
}