{
  "type": "Feature",
  "properties": {
    "iso:country":"US",
    "sg:address":"1507 E 142nd St",
    "sg:city":"Dolton",
    "sg:classifiers":[
        {
            "category":"Wholesale",
            "subcategory":"Home Furnishings",
            "type":"Manufacturing & Wholesale Goods"
        },
        {
            "category":"Retail",
            "subcategory":"Repair Shop",
            "type":"Services"
        },
        {
            "category":"Home & Garden",
            "subcategory":"Carpets & Floor Coverings",
            "type":"Retail Goods"
        }
    ],
    "sg:phone":"+1 773 994 3743",
    "sg:postcode":"60419",
    "sg:province":"IL",
    "sg:tags":[
        "blind",
        "reupholstery",
        "shade",
        "carpeting",
        "furniture"
    ],
    "wof:name":"House of Decor",
    "wof:placetype":"venue"
},
  "geometry": {"coordinates":[-87.58110000000001,41.637402],"type":"Point"}
}