{
  "type": "Feature",
  "properties": {
    "iso:country":"US",
    "sg:address":"629 Forest Ave",
    "sg:city":"River Forest",
    "sg:classifiers":[
        {
            "category":"Professional",
            "subcategory":"Research",
            "type":"Services"
        }
    ],
    "sg:phone":"+1 708 771 8727",
    "sg:postcode":"60305",
    "sg:province":"IL",
    "sg:tags":[
        "development",
        "marketing",
        "product"
    ],
    "wof:name":"Cadventures",
    "wof:placetype":"venue"
},
  "geometry": {"coordinates":[-87.821663,41.889475],"type":"Point"}
}