{
  "type": "Feature",
  "properties": {
    "addr:full":"235 S Marion St Oak Park IL 60302",
    "addr:housenumber":"235",
    "addr:postcode":"60302",
    "addr:street":"S Marion St",
    "iso:country":"US",
    "sg:address":"235 S Marion St",
    "sg:city":"Oak Park",
    "sg:classifiers":[
        {
            "category":"Organizations",
            "subcategory":"Non-profit Organization",
            "type":"Services"
        }
    ],
    "sg:phone":"+1 630 942 2016",
    "sg:postcode":"60302",
    "sg:province":"IL",
    "wof:name":"Endowment For Future Gnrtns",
    "wof:placetype":"venue"
},
  "geometry": {"coordinates":[-87.802504,41.88545],"type":"Point"}
}