{
  "type": "Feature",
  "properties": {
    "iso:country":"US",
    "sg:address":"2 Memorial Dr",
    "sg:city":"Alton",
    "sg:classifiers":[
        {
            "category":"Health Services",
            "subcategory":"Doctor",
            "type":"Services"
        }
    ],
    "sg:phone":"+1 618 462 9743",
    "sg:postcode":"62002",
    "sg:province":"IL",
    "sg:tags":[
        "physician",
        "surgeon"
    ],
    "wof:name":"Riverbend Physicians & Surgeon",
    "wof:placetype":"venue"
},
  "geometry": {"coordinates":[-90.16034999999999,38.900428],"type":"Point"}
}