{
  "type": "Feature",
  "properties": {
    "iso:country":"US",
    "sg:address":"42273 N Woodbine Ave",
    "sg:city":"Antioch",
    "sg:classifiers":[
        {
            "category":"Restaurant",
            "type":"Food & Drink"
        }
    ],
    "sg:phone":"+1 847 395 4704",
    "sg:postcode":"60002",
    "sg:province":"IL",
    "sg:tags":[
        "traditional",
        "american"
    ],
    "sg:website":"www.thirstyturtlebbq.com",
    "wof:name":"Thirsty Turtle Beach Bar and Grill",
    "wof:placetype":"venue"
},
  "geometry": {"coordinates":[-88.147598,42.479099],"type":"Point"}
}