{
  "type": "Feature",
  "properties": {
    "addr:full":"1718 Sherman Ave Evanston IL 60201",
    "addr:housenumber":"1718",
    "addr:postcode":"60201",
    "addr:street":"Sherman Ave",
    "iso:country":"US",
    "sg:address":"1718 Sherman Ave",
    "sg:city":"Evanston",
    "sg:classifiers":[
        {
            "category":"Professional",
            "type":"Services"
        }
    ],
    "sg:phone":"+1 847 869 4792",
    "sg:postcode":"60201",
    "sg:province":"IL",
    "wof:name":"National Geographic",
    "wof:placetype":"venue"
},
  "geometry": {"coordinates":[-87.68190300000001,42.048738],"type":"Point"}
}