{
  "type": "Feature",
  "properties": {
    "addr:full":"285 N Schuyler Ave Kankakee IL 60901",
    "addr:housenumber":"285",
    "addr:postcode":"60901",
    "addr:street":"N Schuyler Ave",
    "iso:country":"US",
    "sg:address":"285 N Schuyler Ave",
    "sg:city":"Kankakee",
    "sg:classifiers":[
        {
            "category":"Government",
            "subcategory":"Office",
            "type":"Public Place"
        }
    ],
    "sg:phone":"+1 815 939 4544",
    "sg:postcode":"60901",
    "sg:province":"IL",
    "sg:tags":[
        "state",
        "resource"
    ],
    "wof:name":"Public Aid Dept",
    "wof:placetype":"venue"
},
  "geometry": {"coordinates":[-87.863693,41.121841],"type":"Point"}
}