{
  "type": "Feature",
  "properties": {
    "iso:country":"US",
    "sg:address":"7400 S Saint Lawrence Ave",
    "sg:city":"Chicago",
    "sg:classifiers":[
        {
            "category":"Place Of Worship",
            "subcategory":"Church",
            "type":"Public Place"
        },
        {
            "category":"Place Of Worship",
            "type":"Public Place"
        },
        {
            "category":"Organizations",
            "subcategory":"Religious Organization",
            "type":"Services"
        }
    ],
    "sg:phone":"+1 773 994 3732",
    "sg:postcode":"60619",
    "sg:province":"IL",
    "sg:tags":[
        "god",
        "churches-pentecostal-independent",
        "churches-church",
        "churches-pentecostal"
    ],
    "wof:name":"St Alwrence Church Of God In Christ",
    "wof:placetype":"venue"
},
  "geometry": {"coordinates":[-87.610291,41.760201],"type":"Point"}
}