{
  "type": "Feature",
  "properties": {
    "iso:country":"US",
    "sg:address":"7101 W Higgins Ave",
    "sg:city":"Chicago",
    "sg:classifiers":[
        {
            "category":"Health Services",
            "subcategory":"Doctor",
            "type":"Services"
        }
    ],
    "sg:phone":"+1 773 792 9111",
    "sg:postcode":"60656",
    "sg:province":"IL",
    "wof:name":"Vyas Uday MD",
    "wof:placetype":"venue"
},
  "geometry": {"coordinates":[-87.804802,41.980499],"type":"Point"}
}