{
  "type": "Feature",
  "properties": {
    "addr:full":"319 E Franklin Ave Wheaton IL 60187",
    "addr:housenumber":"319",
    "addr:postcode":"60187",
    "addr:street":"E Franklin Ave",
    "iso:country":"US",
    "sg:address":"319 E Franklin Ave",
    "sg:city":"Wheaton",
    "sg:classifiers":[
        {
            "category":"Recreation",
            "type":"Entertainment"
        }
    ],
    "sg:phone":"+1 630 653 2222",
    "sg:postcode":"60187",
    "sg:province":"IL",
    "sg:tags":[
        "martial",
        "arts",
        "instruction"
    ],
    "wof:name":"Aikido Club Of Glen Ellyn",
    "wof:placetype":"venue"
},
  "geometry": {"coordinates":[-88.101502,41.869454],"type":"Point"}
}