{
  "type": "Feature",
  "properties": {
    "iso:country":"US",
    "sg:address":"1002 W Fayette Ave",
    "sg:city":"Effingham",
    "sg:classifiers":[
        {
            "category":"Bagels",
            "type":"Food & Drink"
        }
    ],
    "sg:menulink":"http://www.allmenus.com/il/douglas/235795-the-great-american-bagel/menu/",
    "sg:phone":"+1 217 347 2399",
    "sg:postcode":"62401",
    "sg:province":"IL",
    "sg:tags":[
        "wrap",
        "american",
        "sandwich"
    ],
    "wof:name":"The Great American Bagel",
    "wof:placetype":"venue"
},
  "geometry": {"coordinates":[-88.554097,39.120304],"type":"Point"}
}