{
  "type": "Feature",
  "properties": {
    "iso:country":"US",
    "sg:address":"1055 W Catalpa Avenue",
    "sg:city":"Chicago",
    "sg:classifiers":[
        {
            "category":"Real Estate",
            "subcategory":"Real Estate Services",
            "type":"Services"
        }
    ],
    "sg:phone":"+1 773 561 7070",
    "sg:postcode":"60640",
    "sg:province":"IL",
    "sg:tags":[
        "management",
        "property"
    ],
    "wof:name":"Hunter Properties",
    "wof:placetype":"venue"
},
  "geometry": {"coordinates":[-87.65664,41.981775],"type":"Point"}
}