{
  "type": "Feature",
  "properties": {
    "iso:country":"US",
    "sg:address":"436 Joseph Dr",
    "sg:city":"Maryville",
    "sg:classifiers":[
        {
            "category":"Wholesale",
            "subcategory":"Books, Periodicals, & Newspapers",
            "type":"Manufacturing & Wholesale Goods"
        }
    ],
    "sg:phone":"+1 618 791 8490",
    "sg:postcode":"62062",
    "sg:province":"IL",
    "sg:tags":[
        "publisher",
        "book"
    ],
    "wof:name":"Eclipse Publisher",
    "wof:placetype":"venue"
},
  "geometry": {"coordinates":[-89.96299,38.734749],"type":"Point"}
}