{
  "type": "Feature",
  "properties": {
    "iso:country":"US",
    "sg:address":"1011 Clark St",
    "sg:city":"Marseilles",
    "sg:classifiers":[
        {
            "category":"Banks & Credit Unions",
            "subcategory":"Investment Brokerage",
            "type":"Services"
        }
    ],
    "sg:phone":"+1 815 795 4976",
    "sg:postcode":"61341",
    "sg:province":"IL",
    "sg:tags":[
        "commodity",
        "contract"
    ],
    "wof:name":"International Traders",
    "wof:placetype":"venue"
},
  "geometry": {"coordinates":[-88.727035,41.335409],"type":"Point"}
}