{
  "type": "Feature",
  "properties": {
    "iso:country":"US",
    "sg:address":"4525 S Oakenwald Ave",
    "sg:city":"Chicago",
    "sg:classifiers":[
        {
            "category":"Wholesale",
            "subcategory":"Chemicals & Plastics",
            "type":"Manufacturing & Wholesale Goods"
        }
    ],
    "sg:phone":"+1 773 624 0120",
    "sg:postcode":"60653",
    "sg:province":"IL",
    "wof:name":"L M Industries Inc",
    "wof:placetype":"venue"
},
  "geometry": {"coordinates":[-87.594544,41.813431],"type":"Point"}
}