{
  "type": "Feature",
  "properties": {
    "addr:full":"119 S Green Bay Rd Waukegan IL 60085",
    "addr:housenumber":"119",
    "addr:postcode":"60085",
    "addr:street":"S Green Bay Rd",
    "iso:country":"US",
    "sg:address":"119 S Green Bay Rd",
    "sg:city":"Waukegan",
    "sg:classifiers":[
        {
            "category":"Retail",
            "subcategory":"Auto Repair",
            "type":"Services"
        }
    ],
    "sg:phone":"+1 847 336 2324",
    "sg:postcode":"60085",
    "sg:province":"IL",
    "sg:tags":[
        "repairing",
        "automobile"
    ],
    "wof:name":"Car-X Muffler & Brake",
    "wof:placetype":"venue"
},
  "geometry": {"coordinates":[-87.87353899999999,42.356882],"type":"Point"}
}