{
  "type": "Feature",
  "properties": {
    "addr:full":"6200 S Ashland Ave Chicago IL 60636",
    "addr:housenumber":"6200",
    "addr:postcode":"60636",
    "addr:street":"S Ashland Ave",
    "iso:country":"US",
    "sg:address":"6200 S Ashland Ave",
    "sg:city":"Chicago",
    "sg:classifiers":[
        {
            "category":"Personal",
            "type":"Services"
        }
    ],
    "sg:phone":"+1 773 778 8444",
    "sg:postcode":"60636",
    "sg:province":"IL",
    "sg:tags":[
        "towing"
    ],
    "wof:name":"Pleason Lou Motor",
    "wof:placetype":"venue"
},
  "geometry": {"coordinates":[-87.664299,41.780899],"type":"Point"}
}