{
  "type": "Feature",
  "properties": {
    "addr:full":"848 Main St Antioch IL 60002",
    "addr:housenumber":"848",
    "addr:postcode":"60002",
    "addr:street":"Main St",
    "iso:country":"US",
    "sg:address":"848 Main St",
    "sg:city":"Antioch",
    "sg:classifiers":[
        {
            "category":"Social Services",
            "subcategory":"Child Care",
            "type":"Services"
        }
    ],
    "sg:phone":"+1 847 395 6494",
    "sg:postcode":"60002",
    "sg:province":"IL",
    "sg:tags":[
        "kindergarten",
        "academic",
        "school"
    ],
    "wof:name":"Peppermint Stick Pre-Schools",
    "wof:placetype":"venue"
},
  "geometry": {"coordinates":[-88.096434,42.479595],"type":"Point"}
}