{
  "type": "Feature",
  "properties": {
    "addr:full":"809 N Western Ave Chicago IL 60622",
    "addr:housenumber":"809",
    "addr:postcode":"60622",
    "addr:street":"N Western Ave",
    "iso:country":"US",
    "sg:address":"809 N Western Ave",
    "sg:city":"Chicago",
    "sg:classifiers":[
        {
            "category":"Health Services",
            "subcategory":"Doctor",
            "type":"Services"
        }
    ],
    "sg:phone":"+1 773 276 8600",
    "sg:postcode":"60622",
    "sg:province":"IL",
    "wof:name":"Melnik Youri MD",
    "wof:placetype":"venue"
},
  "geometry": {"coordinates":[-87.68699599999999,41.896],"type":"Point"}
}