{
  "type": "Feature",
  "properties": {
    "addr:full":"4646 N Marine Drive Chicago IL 60640",
    "addr:housenumber":"4646",
    "addr:postcode":"60640",
    "addr:street":"N Marine Drive",
    "iso:country":"US",
    "sg:address":"4646 N Marine Drive",
    "sg:city":"Chicago",
    "sg:classifiers":[
        {
            "category":"Health Services",
            "subcategory":"Doctor",
            "type":"Services"
        }
    ],
    "sg:phone":"+1 773 728 7373",
    "sg:postcode":"60640",
    "sg:province":"IL",
    "wof:name":"Marine Drive Medical Group",
    "wof:placetype":"venue"
},
  "geometry": {"coordinates":[-87.64899,41.966929],"type":"Point"}
}