{
  "type": "Feature",
  "properties": {
    "addr:full":"1006 Collins Ave Lawrenceville IL 62439",
    "addr:housenumber":"1006",
    "addr:postcode":"62439",
    "addr:street":"Collins Ave",
    "iso:country":"US",
    "sg:address":"1006 Collins Ave",
    "sg:city":"Lawrenceville",
    "sg:classifiers":[
        {
            "category":"Organizations",
            "subcategory":"Religious Organization",
            "type":"Services"
        }
    ],
    "sg:phone":"+1 618 943 5255",
    "sg:postcode":"62439",
    "sg:province":"IL",
    "sg:tags":[
        "church"
    ],
    "wof:name":"Saint Lawrence Catholic Church",
    "wof:placetype":"venue"
},
  "geometry": {"coordinates":[-87.682067,38.722386],"type":"Point"}
}