{
  "type": "Feature",
  "properties": {
    "iso:country":"US",
    "sg:address":"31632 N Ellis Dr",
    "sg:city":"Volo",
    "sg:classifiers":[
        {
            "category":"Manufacturing",
            "subcategory":"Building Materials",
            "type":"Manufacturing & Wholesale Goods"
        }
    ],
    "sg:phone":"+1 847 593 5530",
    "sg:postcode":"60073",
    "sg:province":"IL",
    "sg:website":"www.continentalwoodworking.com",
    "wof:name":"Continental Woodworking Inc",
    "wof:placetype":"venue"
},
  "geometry": {"coordinates":[-88.163253,42.324102],"type":"Point"}
}