{
  "type": "Feature",
  "properties": {
    "iso:country":"US",
    "sg:address":"1600 Dundee Ave",
    "sg:city":"Elgin",
    "sg:classifiers":[
        {
            "category":"Professional",
            "subcategory":"Management & Consulting",
            "type":"Services"
        }
    ],
    "sg:phone":"+1 847 608 0984",
    "sg:postcode":"60120",
    "sg:province":"IL",
    "sg:tags":[
        "construction"
    ],
    "wof:name":"Shales Mc Nutt Construction",
    "wof:placetype":"venue"
},
  "geometry": {"coordinates":[-88.26407,42.065492],"type":"Point"}
}