{
  "type": "Feature",
  "properties": {
    "addr:full":"315 31st Ave Rock Island IL 61201",
    "addr:housenumber":"315",
    "addr:postcode":"61201",
    "addr:street":"31St Ave",
    "iso:country":"US",
    "sg:address":"315 31st Ave",
    "sg:city":"Rock Island",
    "sg:classifiers":[
        {
            "category":"Wholesale",
            "subcategory":"Auto Parts",
            "type":"Manufacturing & Wholesale Goods"
        }
    ],
    "sg:phone":"+1 309 788 7686",
    "sg:postcode":"61201",
    "sg:province":"IL",
    "sg:tags":[
        "automobile",
        "rebuilt"
    ],
    "wof:name":"E & J Used Auto & Truck Parts",
    "wof:placetype":"venue"
},
  "geometry": {"coordinates":[-90.595178,41.479677],"type":"Point"}
}