{
  "type": "Feature",
  "properties": {
    "iso:country":"US",
    "sg:address":"7626 Madison St",
    "sg:city":"Forest Park",
    "sg:classifiers":[
        {
            "category":"Retail",
            "subcategory":"Pet Boarding",
            "type":"Services"
        }
    ],
    "sg:phone":"+1 708 366 3900",
    "sg:postcode":"60130",
    "sg:province":"IL",
    "sg:tags":[
        "boarding/pet",
        "sitting"
    ],
    "wof:name":"My Best Friend Groom & Board",
    "wof:placetype":"venue"
},
  "geometry": {"coordinates":[-87.815201,41.879501],"type":"Point"}
}