{
  "type": "Feature",
  "properties": {
    "addr:full":"34833 N Gogol Ave Ingleside IL 60041",
    "addr:housenumber":"34833",
    "addr:postcode":"60041",
    "addr:street":"N Gogol Ave",
    "iso:country":"US",
    "sg:address":"34833 N Gogol Ave",
    "sg:city":"Ingleside",
    "sg:classifiers":[
        {
            "category":"Personal",
            "type":"Services"
        }
    ],
    "sg:phone":"+1 847 223 6101",
    "sg:postcode":"60041",
    "sg:province":"IL",
    "sg:tags":[
        "therapist",
        "massage"
    ],
    "wof:name":"Le Spa Boutique",
    "wof:placetype":"venue"
},
  "geometry": {"coordinates":[-88.18462700000001,42.370365],"type":"Point"}
}