{
  "type": "Feature",
  "properties": {
    "iso:country":"US",
    "sg:address":"101 N 3rd St",
    "sg:city":"Fisher",
    "sg:classifiers":[
        {
            "category":"Personal",
            "subcategory":"Beauty Salon",
            "type":"Services"
        }
    ],
    "sg:phone":"+1 217 897 1364",
    "sg:postcode":"61843",
    "sg:province":"IL",
    "sg:tags":[
        "shop"
    ],
    "wof:name":"Seims Styling Hutch",
    "wof:placetype":"venue"
},
  "geometry": {"coordinates":[-88.349691,40.318413],"type":"Point"}
}