{
  "type": "Feature",
  "properties": {
    "iso:country":"US",
    "sg:address":"4019 N Narragansett Ave",
    "sg:city":"Chicago",
    "sg:classifiers":[
        {
            "category":"Recreation",
            "subcategory":"Boat Charter",
            "type":"Entertainment"
        }
    ],
    "sg:phone":"+1 773 777 1489",
    "sg:postcode":"60634",
    "sg:province":"IL",
    "sg:tags":[
        "boating"
    ],
    "sg:website":"www.chicagolandcanoebase.com",
    "wof:name":"Chicagoland Canoe Base Inc",
    "wof:placetype":"venue"
},
  "geometry": {"coordinates":[-87.786475,41.953399],"type":"Point"}
}