{
  "type": "Feature",
  "properties": {
    "addr:full":"1341 W 107th St Chicago IL 60643",
    "addr:housenumber":"1341",
    "addr:postcode":"60643",
    "addr:street":"W 107Th St",
    "iso:country":"US",
    "sg:address":"1341 W 107th St",
    "sg:city":"Chicago",
    "sg:classifiers":[
        {
            "category":"Food & Beverages",
            "subcategory":"Bakery",
            "type":"Retail Goods"
        }
    ],
    "sg:phone":"+1 773 233 1257",
    "sg:postcode":"60643",
    "sg:province":"IL",
    "sg:tags":[
        "baker"
    ],
    "wof:name":"Brian The Baker",
    "wof:placetype":"venue"
},
  "geometry": {"coordinates":[-87.655506,41.699569],"type":"Point"}
}