{
  "type": "Feature",
  "properties": {
    "iso:country":"US",
    "sg:address":"11242 S Harlem Ave",
    "sg:city":"Worth",
    "sg:classifiers":[
        {
            "category":"Retail",
            "subcategory":"Pet Boarding",
            "type":"Services"
        }
    ],
    "sg:phone":"+1 708 361 2338",
    "sg:postcode":"60482",
    "sg:province":"IL",
    "sg:tags":[
        "boarding/pet",
        "sitting"
    ],
    "wof:name":"Furry Friends",
    "wof:placetype":"venue"
},
  "geometry": {"coordinates":[-87.79740099999999,41.6866],"type":"Point"}
}