{
  "type": "Feature",
  "properties": {
    "iso:country":"US",
    "sg:address":"5624 N 2nd St",
    "sg:city":"Loves Park",
    "sg:classifiers":[
        {
            "category":"Bars & Pubs",
            "type":"Food & Drink"
        }
    ],
    "sg:phone":"+1   ",
    "sg:postcode":"61111",
    "sg:province":"IL",
    "sg:tags":[
        "drinking",
        "eating"
    ],
    "wof:name":"Town Hall Taverns",
    "wof:placetype":"venue"
},
  "geometry": {"coordinates":[-89.057957,42.31251],"type":"Point"}
}