{
  "type": "Feature",
  "properties": {
    "iso:country":"US",
    "sg:address":"520 N Michigan Ave Suite 222",
    "sg:city":"Chicago",
    "sg:classifiers":[
        {
            "category":"Shopping",
            "subcategory":"Stationery & Office Supplies",
            "type":"Retail Goods"
        },
        {
            "category":"Shopping",
            "subcategory":"Gifts & Souvenirs",
            "type":"Retail Goods"
        },
        {
            "category":"Wholesale",
            "subcategory":"Stationery",
            "type":"Manufacturing & Wholesale Goods"
        }
    ],
    "sg:phone":"+1 312 329 0154",
    "sg:postcode":"60611",
    "sg:province":"IL",
    "sg:tags":[
        "announcement",
        "envelope",
        "greeting",
        "card",
        "invitation",
        "store"
    ],
    "sg:website":"www.papyrusonline.com",
    "wof:name":"Papyrus",
    "wof:placetype":"venue"
},
  "geometry": {"coordinates":[-87.624664,41.89156],"type":"Point"}
}