{
  "type": "Feature",
  "properties": {
    "iso:country":"US",
    "sg:address":"206 Alpine Dr",
    "sg:city":"Lake Zurich",
    "sg:classifiers":[
        {
            "category":"Professional",
            "subcategory":"Computer Services",
            "type":"Services"
        }
    ],
    "sg:phone":"+1 847 726 0133",
    "sg:postcode":"60047",
    "sg:province":"IL",
    "sg:tags":[
        "related"
    ],
    "wof:name":"Corporate Resource Group",
    "wof:placetype":"venue"
},
  "geometry": {"coordinates":[-88.09296999999999,42.20904],"type":"Point"}
}