{
  "type": "Feature",
  "properties": {
    "iso:country":"US",
    "sg:address":"245 W Roosevelt Rd #84",
    "sg:city":"West Chicago",
    "sg:classifiers":[
        {
            "category":"Building & Trades",
            "subcategory":"Cleaning & Sanitation",
            "type":"Services"
        }
    ],
    "sg:phone":"+1 630 293 1015",
    "sg:postcode":"60185",
    "sg:province":"IL",
    "sg:tags":[
        "home"
    ],
    "sg:website":"www.thecleaningauthority.com",
    "wof:name":"The Cleaning Authority",
    "wof:placetype":"venue"
},
  "geometry": {"coordinates":[-88.20762499999999,41.866348],"type":"Point"}
}