{
  "type": "Feature",
  "properties": {
    "iso:country":"US",
    "sg:address":"980 W Army Trail Rd",
    "sg:city":"Carol Stream",
    "sg:classifiers":[
        {
            "category":"Autos & Motor Vehicles",
            "subcategory":"Auto Supplies",
            "type":"Retail Goods"
        }
    ],
    "sg:phone":"+1 630 246 2677",
    "sg:postcode":"60188",
    "sg:province":"IL",
    "sg:tags":[
        "tire"
    ],
    "wof:name":"Army Trail Tire & Service Center",
    "wof:placetype":"venue"
},
  "geometry": {"coordinates":[-88.158401,41.941299],"type":"Point"}
}