{
  "type": "Feature",
  "properties": {
    "iso:country":"US",
    "sg:address":"6901 N Ridge Blvd",
    "sg:city":"Chicago",
    "sg:classifiers":[
        {
            "category":"Building & Trades",
            "subcategory":"Cleaning & Sanitation",
            "type":"Services"
        },
        {
            "category":"Home & Garden",
            "subcategory":"Building Materials",
            "type":"Retail Goods"
        },
        {
            "category":"Building & Trades",
            "subcategory":"Construction",
            "type":"Services"
        }
    ],
    "sg:phone":"+1 312 730 4408",
    "sg:postcode":"60645",
    "sg:province":"IL",
    "sg:tags":[
        "waterproofing",
        "contractor",
        "concrete",
        "restoration",
        "staining",
        "sealing"
    ],
    "wof:name":"R B D Foundation Repair",
    "wof:placetype":"venue"
},
  "geometry": {"coordinates":[-87.680733,42.00642],"type":"Point"}
}