{
  "type": "Feature",
  "properties": {
    "iso:country":"US",
    "sg:address":"836 1850th St",
    "sg:city":"Lincoln",
    "sg:phone":"+1 217 732 6351",
    "sg:postcode":"62656",
    "sg:province":"IL",
    "sg:tags":[
        "farm",
        "corn",
        "soybean"
    ],
    "wof:name":"Orville Baker",
    "wof:placetype":"venue"
},
  "geometry": {"coordinates":[-89.43704700000001,40.186915],"type":"Point"}
}