{
  "type": "Feature",
  "properties": {
    "addr:full":"2930 4th St Peru IL 61354",
    "addr:housenumber":"2930",
    "addr:postcode":"61354",
    "addr:street":"4Th St",
    "iso:country":"US",
    "sg:address":"2930 4th St",
    "sg:city":"Peru",
    "sg:classifiers":[
        {
            "category":"Health Services",
            "subcategory":"Chiropractor",
            "type":"Services"
        }
    ],
    "sg:phone":"+1 815 224 8090",
    "sg:postcode":"61354",
    "sg:province":"IL",
    "wof:name":"Mertes Family Chiropractic",
    "wof:placetype":"venue"
},
  "geometry": {"coordinates":[-89.145741,41.327567],"type":"Point"}
}