{
  "type": "Feature",
  "properties": {
    "iso:country":"US",
    "sg:address":"406 W 3rd St",
    "sg:city":"Lostant",
    "sg:classifiers":[
        {
            "category":"Retail",
            "subcategory":"Funeral Services",
            "type":"Services"
        }
    ],
    "sg:phone":"+1 815 368 3312",
    "sg:postcode":"61334",
    "sg:province":"IL",
    "sg:tags":[
        "director"
    ],
    "wof:name":"Mueller Funeral Homes Inc",
    "wof:placetype":"venue"
},
  "geometry": {"coordinates":[-89.06431499999999,41.141507],"type":"Point"}
}