{
  "type": "Feature",
  "properties": {
    "iso:country":"US",
    "sg:address":"115 N Noble Ave",
    "sg:city":"Noble",
    "sg:classifiers":[
        {
            "category":"Restaurant",
            "type":"Food & Drink"
        }
    ],
    "sg:phone":"+1 618 723 2533",
    "sg:postcode":"62868",
    "sg:province":"IL",
    "wof:name":"Season Good Pizza",
    "wof:placetype":"venue"
},
  "geometry": {"coordinates":[-88.223755,38.698018],"type":"Point"}
}