{
  "type": "Feature",
  "properties": {
    "iso:country":"US",
    "sg:address":"18 S Lake St",
    "sg:city":"Grayslake",
    "sg:classifiers":[
        {
            "category":"Personal",
            "subcategory":"Massage",
            "type":"Services"
        }
    ],
    "sg:phone":"+1 847 223 8568",
    "sg:postcode":"60030",
    "sg:province":"IL",
    "sg:tags":[
        "therapist"
    ],
    "wof:name":"Shiatsu Spirit Mnd Bdywrk",
    "wof:placetype":"venue"
},
  "geometry": {"coordinates":[-88.043719,42.343838],"type":"Point"}
}