{
  "type": "Feature",
  "properties": {
    "addr:full":"1148 N Honore Street Chicago IL 60622",
    "addr:housenumber":"1148",
    "addr:postcode":"60622",
    "addr:street":"N Honore Street",
    "iso:country":"US",
    "sg:address":"1148 N Honore Street",
    "sg:city":"Chicago",
    "sg:classifiers":[
        {
            "category":"Education",
            "subcategory":"School",
            "type":"Public Place"
        }
    ],
    "sg:phone":"+1 773 534 4276",
    "sg:postcode":"60622",
    "sg:province":"IL",
    "sg:tags":[
        "high",
        "middle",
        "elementary"
    ],
    "wof:name":"Schools Public",
    "wof:placetype":"venue"
},
  "geometry": {"coordinates":[-87.67341999999999,41.902641],"type":"Point"}
}