{
  "type": "Feature",
  "properties": {
    "iso:country":"US",
    "sg:address":"920 S Seminary Ave",
    "sg:city":"Park Ridge",
    "sg:classifiers":[
        {
            "category":"Professional",
            "subcategory":"Art Services",
            "type":"Services"
        }
    ],
    "sg:phone":"+1 847 292 9101",
    "sg:postcode":"60068",
    "sg:province":"IL",
    "sg:tags":[
        "commercial",
        "design"
    ],
    "wof:name":"Dempsey Design",
    "wof:placetype":"venue"
},
  "geometry": {"coordinates":[-87.848174,41.998307],"type":"Point"}
}