{
  "type": "Feature",
  "properties": {
    "addr:full":"2520 E 72nd Pl Chicago IL 60649",
    "addr:housenumber":"2520",
    "addr:postcode":"60649",
    "addr:street":"E 72Nd Pl",
    "iso:country":"US",
    "sg:address":"2520 E 72nd Pl",
    "sg:city":"Chicago",
    "sg:classifiers":[
        {
            "category":"Real Estate",
            "subcategory":"Developer",
            "type":"Services"
        }
    ],
    "sg:phone":"+1 773 706 0263",
    "sg:postcode":"60649",
    "sg:province":"IL",
    "sg:tags":[
        "investing"
    ],
    "wof:name":"Angels Roof",
    "wof:placetype":"venue"
},
  "geometry": {"coordinates":[-87.56353799999999,41.763353],"type":"Point"}
}