{
  "type": "Feature",
  "properties": {
    "iso:country":"US",
    "sg:address":"16703 Spring View Dr",
    "sg:city":"Lockport",
    "sg:classifiers":[
        {
            "category":"Building & Trades",
            "subcategory":"Construction",
            "type":"Services"
        }
    ],
    "sg:phone":"+1 815 834 2292",
    "sg:postcode":"60441",
    "sg:province":"IL",
    "sg:tags":[
        "carpentry",
        "contractor"
    ],
    "wof:name":"Wille Construction",
    "wof:placetype":"venue"
},
  "geometry": {"coordinates":[-88.024069,41.58441],"type":"Point"}
}