{
  "type": "Feature",
  "properties": {
    "addr:full":"437 S Main St Clifton IL 60927",
    "addr:housenumber":"437",
    "addr:postcode":"60927",
    "addr:street":"S Main St",
    "iso:country":"US",
    "sg:address":"437 S Main St",
    "sg:city":"Clifton",
    "sg:classifiers":[
        {
            "category":"Insurance",
            "subcategory":"Insurance Agent",
            "type":"Services"
        },
        {
            "category":"Insurance",
            "subcategory":"Hazard Insurance",
            "type":"Services"
        },
        {
            "category":"Insurance",
            "subcategory":"Title Insurance",
            "type":"Services"
        },
        {
            "category":"Insurance",
            "subcategory":"Life Insurance",
            "type":"Services"
        }
    ],
    "sg:phone":"+1 815 694 2331",
    "sg:postcode":"60927",
    "sg:province":"IL",
    "sg:tags":[
        "auto",
        "commercial",
        "business",
        "homeowner"
    ],
    "sg:website":"http://www.countryfinancial.com/zach.gray",
    "wof:name":"COUNTRY Financial Zachary Gray",
    "wof:placetype":"venue"
},
  "geometry": {"coordinates":[-87.934853,40.933397],"type":"Point"}
}