{
  "type": "Feature",
  "properties": {
    "iso:country":"US",
    "sg:address":"449 E Bowyer St",
    "sg:city":"Bement",
    "sg:classifiers":[
        {
            "category":"Organizations",
            "subcategory":"Community Association",
            "type":"Services"
        }
    ],
    "sg:phone":"+1 217 678 7121",
    "sg:postcode":"61813",
    "sg:province":"IL",
    "sg:tags":[
        "military"
    ],
    "wof:name":"American Legion",
    "wof:placetype":"venue"
},
  "geometry": {"coordinates":[-88.568066,39.924567],"type":"Point"}
}