{
  "type": "Feature",
  "properties": {
    "iso:country":"US",
    "sg:address":"222 Lake St",
    "sg:city":"Oak Park",
    "sg:classifiers":[
        {
            "category":"Communications",
            "subcategory":"Film & Video Production",
            "type":"Services"
        }
    ],
    "sg:phone":"+1 708 358 0920",
    "sg:postcode":"60302",
    "sg:province":"IL",
    "sg:tags":[
        "co"
    ],
    "wof:name":"Pixel-Flick Entertainment",
    "wof:placetype":"venue"
},
  "geometry": {"coordinates":[-87.78041,41.888259],"type":"Point"}
}