{
  "type": "Feature",
  "properties": {
    "iso:country":"US",
    "sg:address":"4715 Old Oaks Dr",
    "sg:city":"Lisle",
    "sg:classifiers":[
        {
            "category":"Building & Trades",
            "subcategory":"Construction",
            "type":"Services"
        }
    ],
    "sg:phone":"+1 630 301 1956",
    "sg:postcode":"60532",
    "sg:province":"IL",
    "sg:tags":[
        "tile",
        "dealer"
    ],
    "wof:name":"Custom Cut Tile Works",
    "wof:placetype":"venue"
},
  "geometry": {"coordinates":[-88.107433,41.797999],"type":"Point"}
}