{
  "type": "Feature",
  "properties": {
    "iso:country":"US",
    "sg:address":"620 W Belmont Ave",
    "sg:city":"Chicago",
    "sg:classifiers":[
        {
            "category":"Professional",
            "type":"Services"
        }
    ],
    "sg:phone":"+1 773 549 7858",
    "sg:postcode":"60657",
    "sg:province":"IL",
    "wof:name":"Patrick Roullier",
    "wof:placetype":"venue"
},
  "geometry": {"coordinates":[-87.644603,41.940117],"type":"Point"}
}