{
  "type": "Feature",
  "properties": {
    "iso:country":"US",
    "sg:address":"1013 N Cicero Ave",
    "sg:city":"Chicago",
    "sg:classifiers":[
        {
            "category":"Place Of Worship",
            "subcategory":"Church",
            "type":"Public Place"
        },
        {
            "category":"Place Of Worship",
            "type":"Public Place"
        }
    ],
    "sg:phone":"+1 773 287 3736",
    "sg:postcode":"60651",
    "sg:province":"IL",
    "sg:tags":[
        "churches-pentecostal-independent",
        "denomination",
        "churches-pentecostal",
        "churches-interdenominational",
        "churches-various"
    ],
    "wof:name":"Pentecostal Assemblies The Truth That Sets You Free Inc",
    "wof:placetype":"venue"
},
  "geometry": {"coordinates":[-87.74588199999999,41.898911],"type":"Point"}
}