{
  "type": "Feature",
  "properties": {
    "addr:full":"15 Fairlane Dr Joliet IL 60435",
    "addr:housenumber":"15",
    "addr:postcode":"60435",
    "addr:street":"Fairlane Dr",
    "iso:country":"US",
    "sg:address":"15 Fairlane Dr",
    "sg:city":"Joliet",
    "sg:classifiers":[
        {
            "category":"Home & Garden",
            "subcategory":"Home Furnishings",
            "type":"Retail Goods"
        }
    ],
    "sg:phone":"+1   ",
    "sg:postcode":"60435",
    "sg:province":"IL",
    "wof:name":"Window Designs",
    "wof:placetype":"venue"
},
  "geometry": {"coordinates":[-88.149939,41.523564],"type":"Point"}
}