{
  "type": "Feature",
  "properties": {
    "iso:country":"US",
    "sg:address":"7215 W 73rd St",
    "sg:city":"Bridgeview",
    "sg:classifiers":[
        {
            "category":"Personal",
            "type":"Services"
        }
    ],
    "sg:phone":"+1 708 563 1515",
    "sg:postcode":"60455",
    "sg:province":"IL",
    "sg:tags":[
        "wedding",
        "chapel"
    ],
    "wof:name":"Garden Wedding Chapel",
    "wof:placetype":"venue"
},
  "geometry": {"coordinates":[-87.802305,41.758906],"type":"Point"}
}