{
  "type": "Feature",
  "properties": {
    "addr:full":"5959 Forest Trail Dr Rockford IL 61109",
    "addr:housenumber":"5959",
    "addr:postcode":"61109",
    "addr:street":"Forest Trail Dr",
    "iso:country":"US",
    "sg:address":"5959 Forest Trail Dr",
    "sg:city":"Rockford",
    "sg:classifiers":[
        {
            "category":"Manufacturing",
            "subcategory":"Tools & Machinery",
            "type":"Manufacturing & Wholesale Goods"
        }
    ],
    "sg:phone":"+1 815 873 8866",
    "sg:postcode":"61109",
    "sg:province":"IL",
    "sg:tags":[
        "machine",
        "repair"
    ],
    "wof:name":"Precision Machine Tool Co",
    "wof:placetype":"venue"
},
  "geometry": {"coordinates":[-89.000461,42.207693],"type":"Point"}
}