{
  "type": "Feature",
  "properties": {
    "iso:country":"US",
    "sg:address":"932 Lee St",
    "sg:city":"Des Plaines",
    "sg:classifiers":[
        {
            "category":"Organizations",
            "subcategory":"Political Organization",
            "type":"Services"
        }
    ],
    "sg:phone":"+1 847 297 6533",
    "sg:postcode":"60016",
    "sg:province":"IL",
    "wof:name":"Citizens For Rosemary Mul",
    "wof:placetype":"venue"
},
  "geometry": {"coordinates":[-87.891693,42.036829],"type":"Point"}
}