{
  "type": "Feature",
  "properties": {
    "iso:country":"US",
    "sg:address":"1331 N Fullerton Ave",
    "sg:city":"Chicago",
    "sg:classifiers":[
        {
            "category":"Shopping",
            "subcategory":"Mobile Phones",
            "type":"Retail Goods"
        }
    ],
    "sg:postcode":"60614",
    "sg:province":"IL",
    "sg:website":"www.towerwirelessltd.com/",
    "wof:name":"Tower Wireless",
    "wof:placetype":"venue"
},
  "geometry": {"coordinates":[-87.661501,41.924887],"type":"Point"}
}