{
  "type": "Feature",
  "properties": {
    "addr:full":"4415 Harrison Ave Rockford IL 61108",
    "addr:housenumber":"4415",
    "addr:postcode":"61108",
    "addr:street":"Harrison Ave",
    "iso:country":"US",
    "sg:address":"4415 Harrison Ave",
    "sg:city":"Rockford",
    "sg:classifiers":[
        {
            "category":"Personal",
            "subcategory":"Beauty Salon",
            "type":"Services"
        }
    ],
    "sg:phone":"+1 815 399 9685",
    "sg:postcode":"61108",
    "sg:province":"IL",
    "sg:website":"www.haircuttery.com",
    "wof:name":"Hair Cuttery",
    "wof:placetype":"venue"
},
  "geometry": {"coordinates":[-89.03046000000001,42.23819],"type":"Point"}
}