{
  "type": "Feature",
  "properties": {
    "addr:full":"27 Durrell Dr Kankakee IL 60901",
    "addr:housenumber":"27",
    "addr:postcode":"60901",
    "addr:street":"Durrell Dr",
    "iso:country":"US",
    "sg:address":"27 Durrell Dr",
    "sg:city":"Kankakee",
    "sg:classifiers":[
        {
            "category":"Building & Trades",
            "subcategory":"Construction",
            "type":"Services"
        }
    ],
    "sg:phone":"+1 815 933 4806",
    "sg:postcode":"60901",
    "sg:province":"IL",
    "sg:tags":[
        "house"
    ],
    "wof:name":"St Peter Construction",
    "wof:placetype":"venue"
},
  "geometry": {"coordinates":[-87.815646,41.08217],"type":"Point"}
}