{
  "type": "Feature",
  "properties": {
    "addr:full":"1600 N Main St Dupo IL 62239",
    "addr:housenumber":"1600",
    "addr:postcode":"62239",
    "addr:street":"N Main St",
    "iso:country":"US",
    "sg:address":"1600 N Main St",
    "sg:city":"Dupo",
    "sg:classifiers":[
        {
            "category":"Bars & Pubs",
            "type":"Food & Drink"
        }
    ],
    "sg:phone":"+1 618 286 5353",
    "sg:postcode":"62239",
    "sg:province":"IL",
    "wof:name":"Side Trax Tavern",
    "wof:placetype":"venue"
},
  "geometry": {"coordinates":[-90.201823,38.537849],"type":"Point"}
}