{
  "type": "Feature",
  "properties": {
    "addr:full":"1401 Waukegan Rd Glenview IL 60025",
    "addr:housenumber":"1401",
    "addr:postcode":"60025",
    "addr:street":"Waukegan Rd",
    "iso:country":"US",
    "sg:address":"1401 Waukegan Rd",
    "sg:city":"Glenview",
    "sg:classifiers":[
        {
            "category":"Restaurant",
            "type":"Food & Drink"
        }
    ],
    "sg:menulink":"http://www.allmenus.com/il/northfield/152673-boston-market/menu/",
    "sg:phone":"+1 847 724 8000",
    "sg:postcode":"60025",
    "sg:province":"IL",
    "sg:tags":[
        "barbecue",
        "american",
        "soup"
    ],
    "wof:name":"Boston Market",
    "wof:placetype":"venue"
},
  "geometry": {"coordinates":[-87.798346,42.0802],"type":"Point"}
}