{
  "type": "Feature",
  "properties": {
    "addr:full":"4100 N Marine Dr Chicago IL 60613",
    "addr:housenumber":"4100",
    "addr:postcode":"60613",
    "addr:street":"N Marine Dr",
    "iso:country":"US",
    "sg:address":"4100 N Marine Dr",
    "sg:city":"Chicago",
    "sg:classifiers":[
        {
            "category":"Arts & Performance",
            "subcategory":"Art Gallery",
            "type":"Entertainment"
        },
        {
            "category":"Shopping",
            "subcategory":"Crafts & Fabrics",
            "type":"Retail Goods"
        }
    ],
    "sg:phone":"+1 773 857 0173",
    "sg:postcode":"60613",
    "sg:province":"IL",
    "sg:tags":[
        "consultant",
        "galleries",
        "instruction"
    ],
    "wof:name":"Illinois, Institute of Art",
    "wof:placetype":"venue"
},
  "geometry": {"coordinates":[-87.6455,41.955662],"type":"Point"}
}