{
  "type": "Feature",
  "properties": {
    "addr:full":"6101 S Kenneth Ave Chicago IL 60629",
    "addr:housenumber":"6101",
    "addr:postcode":"60629",
    "addr:street":"S Kenneth Ave",
    "iso:country":"US",
    "sg:address":"6101 S Kenneth Ave",
    "sg:city":"Chicago",
    "sg:classifiers":[
        {
            "category":"Commercial Area",
            "type":"Public Place"
        },
        {
            "category":"Manufacturing",
            "subcategory":"Glass & Minerals",
            "type":"Manufacturing & Wholesale Goods"
        }
    ],
    "sg:phone":"+1 708 862 6670",
    "sg:postcode":"60629",
    "sg:province":"IL",
    "sg:tags":[
        "plate",
        "glass-auto",
        "shape",
        "glass-wholesale",
        "window",
        "store",
        "front",
        "circle",
        "special",
        "manufacturer"
    ],
    "wof:name":"Georges Northwest Glass Inc",
    "wof:placetype":"venue"
},
  "geometry": {"coordinates":[-87.73384900000001,41.782181],"type":"Point"}
}