{
  "type": "Feature",
  "properties": {
    "iso:country":"US",
    "sg:address":"552 Crescent Blvd",
    "sg:city":"Glen Ellyn",
    "sg:classifiers":[
        {
            "category":"Restaurant",
            "type":"Food & Drink"
        }
    ],
    "sg:phone":"+1   ",
    "sg:postcode":"60137",
    "sg:province":"IL",
    "sg:tags":[
        "eating"
    ],
    "wof:name":"Mama Sues Inc",
    "wof:placetype":"venue"
},
  "geometry": {"coordinates":[-88.066711,41.876414],"type":"Point"}
}