{
  "type": "Feature",
  "properties": {
    "iso:country":"US",
    "sg:address":"724 Chester St",
    "sg:city":"Chester",
    "sg:classifiers":[
        {
            "category":"Banks & Credit Unions",
            "subcategory":"Bank",
            "type":"Services"
        }
    ],
    "sg:phone":"+1 618 826 1555",
    "sg:postcode":"62233",
    "sg:province":"IL",
    "sg:tags":[
        "depository",
        "banking",
        "loan"
    ],
    "wof:name":"Cash Store The",
    "wof:placetype":"venue"
},
  "geometry": {"coordinates":[-89.817824,37.898277],"type":"Point"}
}