{
  "type": "Feature",
  "properties": {
    "addr:full":"915 Abbotsford Ln Frankfort IL 60423",
    "addr:housenumber":"915",
    "addr:postcode":"60423",
    "addr:street":"Abbotsford Ln",
    "iso:country":"US",
    "sg:address":"915 Abbotsford Ln",
    "sg:city":"Frankfort",
    "sg:classifiers":[
        {
            "category":"Professional",
            "subcategory":"Business Services",
            "type":"Services"
        }
    ],
    "sg:phone":"+1 815 469 6107",
    "sg:postcode":"60423",
    "sg:province":"IL",
    "wof:name":"Micrecord Sales and Service",
    "wof:placetype":"venue"
},
  "geometry": {"coordinates":[-87.805785,41.489099],"type":"Point"}
}