{
  "type": "Feature",
  "properties": {
    "iso:country":"US",
    "sg:address":"309 James Ln",
    "sg:city":"Henry",
    "sg:classifiers":[
        {
            "category":"Freight",
            "type":"Transportation"
        }
    ],
    "sg:phone":"+1 309 364 2973",
    "sg:postcode":"61537",
    "sg:province":"IL",
    "sg:tags":[
        "commercial",
        "storage"
    ],
    "wof:name":"Dawson Mini Storage",
    "wof:placetype":"venue"
},
  "geometry": {"coordinates":[-89.35415399999999,41.116696],"type":"Point"}
}