{
  "type": "Feature",
  "properties": {
    "addr:full":"705 W Blackhawk Dr Byron IL 61010",
    "addr:housenumber":"705",
    "addr:postcode":"61010",
    "addr:street":"W Blackhawk Dr",
    "iso:country":"US",
    "sg:address":"705 W Blackhawk Dr",
    "sg:city":"Byron",
    "sg:classifiers":[
        {
            "category":"Travel",
            "subcategory":"Bed & Breakfast",
            "type":"Entertainment"
        }
    ],
    "sg:phone":"+1 815 234 8281",
    "sg:postcode":"61010",
    "sg:province":"IL",
    "sg:tags":[
        "inn"
    ],
    "wof:name":"Sam's Drive Inn",
    "wof:placetype":"venue"
},
  "geometry": {"coordinates":[-89.313698,42.095032],"type":"Point"}
}