{
  "type": "Feature",
  "properties": {
    "iso:country":"US",
    "sg:address":"1250 Crispin Dr",
    "sg:city":"Elgin",
    "sg:classifiers":[
        {
            "category":"Wholesale",
            "subcategory":"Construction Materials",
            "type":"Manufacturing & Wholesale Goods"
        },
        {
            "category":"Manufacturing",
            "subcategory":"Electronics",
            "type":"Manufacturing & Wholesale Goods"
        }
    ],
    "sg:phone":"+1 847 742 3566",
    "sg:postcode":"60123",
    "sg:province":"IL",
    "sg:tags":[
        "control",
        "system",
        "controls",
        "regulators-wholesale",
        "solenoid",
        "manufacturer"
    ],
    "sg:website":"http://www.occorp.com",
    "wof:name":"Olympic Controls",
    "wof:placetype":"venue"
},
  "geometry": {"coordinates":[-88.308542,42.00909],"type":"Point"}
}