{
  "type": "Feature",
  "properties": {
    "iso:country":"US",
    "sg:address":"500 W Madison St",
    "sg:city":"Chicago",
    "sg:classifiers":[
        {
            "category":"Restaurant",
            "type":"Food & Drink"
        }
    ],
    "sg:postcode":"60606",
    "sg:province":"IL",
    "wof:name":"Simply Greens",
    "wof:placetype":"venue"
},
  "geometry": {"coordinates":[-87.640175,41.881898],"type":"Point"}
}