{
  "type": "Feature",
  "properties": {
    "iso:country":"US",
    "sg:address":"10127 W Roosevelt Rd B1",
    "sg:city":"Westchester",
    "sg:classifiers":[
        {
            "category":"Building & Trades",
            "subcategory":"Electrical",
            "type":"Services"
        }
    ],
    "sg:phone":"+1 708 450 1156",
    "sg:postcode":"60154",
    "sg:province":"IL",
    "sg:tags":[
        "electrician"
    ],
    "wof:name":"J M Electric Services, Inc.",
    "wof:placetype":"venue"
},
  "geometry": {"coordinates":[-87.87573399999999,41.863443],"type":"Point"}
}