{
  "type": "Feature",
  "properties": {
    "addr:full":"4820 Carol Ct Rockford IL 61108",
    "addr:housenumber":"4820",
    "addr:postcode":"61108",
    "addr:street":"Carol Ct",
    "iso:country":"US",
    "sg:address":"4820 Carol Ct",
    "sg:city":"Rockford",
    "sg:classifiers":[
        {
            "category":"Education",
            "subcategory":"School",
            "type":"Public Place"
        }
    ],
    "sg:phone":"+1 815 229 2176",
    "sg:postcode":"61108",
    "sg:province":"IL",
    "sg:tags":[
        "elementary"
    ],
    "wof:name":"Gregory Elementary School",
    "wof:placetype":"venue"
},
  "geometry": {"coordinates":[-89.016141,42.258486],"type":"Point"}
}