{
  "type": "Feature",
  "properties": {
    "iso:country":"US",
    "sg:address":"55 McHenry Rd",
    "sg:city":"Buffalo Grove",
    "sg:classifiers":[
        {
            "category":"Restaurant",
            "type":"Food & Drink"
        }
    ],
    "sg:phone":"+1   ",
    "sg:postcode":"60089",
    "sg:province":"IL",
    "sg:tags":[
        "eating"
    ],
    "wof:name":"Starbucks",
    "wof:placetype":"venue"
},
  "geometry": {"coordinates":[-87.959267,42.154571],"type":"Point"}
}