{
  "type": "Feature",
  "properties": {
    "addr:full":"2000 N Clybourn Ave Ste D Chicago IL 60614",
    "addr:housenumber":"2000",
    "addr:postcode":"60614",
    "addr:street":"N Clybourn Ave Ste D",
    "iso:country":"US",
    "sg:address":"2000 N Clybourn Ave Ste D",
    "sg:city":"Chicago",
    "sg:classifiers":[
        {
            "category":"Wholesale",
            "subcategory":"Home Furnishings",
            "type":"Manufacturing & Wholesale Goods"
        }
    ],
    "sg:phone":"+1 312 795 0801",
    "sg:postcode":"60614",
    "sg:province":"IL",
    "sg:tags":[
        "blind",
        "shade"
    ],
    "sg:website":"www.3day.com",
    "wof:name":"3 Day Blinds",
    "wof:placetype":"venue"
},
  "geometry": {"coordinates":[-87.65969800000001,41.917751],"type":"Point"}
}