{
  "type": "Feature",
  "properties": {
    "addr:full":"5541 W 79th St Burbank IL 60459",
    "addr:housenumber":"5541",
    "addr:postcode":"60459",
    "addr:street":"W 79Th St",
    "iso:country":"US",
    "sg:address":"5541 W 79th St",
    "sg:city":"Burbank",
    "sg:classifiers":[
        {
            "category":"Food & Beverages",
            "subcategory":"Groceries & Convenience Stores",
            "type":"Retail Goods"
        }
    ],
    "sg:phone":"+1 708 422 7511",
    "sg:postcode":"60459",
    "sg:province":"IL",
    "wof:name":"Lucky Korner Inc",
    "wof:placetype":"venue"
},
  "geometry": {"coordinates":[-87.76010100000001,41.748699],"type":"Point"}
}