{
  "type": "Feature",
  "properties": {
    "addr:full":"3530 W Peterson Avenue Chicago IL 60659",
    "addr:housenumber":"3530",
    "addr:postcode":"60659",
    "addr:street":"W Peterson Avenue",
    "iso:country":"US",
    "sg:address":"3530 W Peterson Avenue",
    "sg:city":"Chicago",
    "sg:classifiers":[
        {
            "category":"Professional",
            "subcategory":"Accounting & Tax Preparation",
            "type":"Services"
        }
    ],
    "sg:phone":"+1 773 539 1236",
    "sg:postcode":"60659",
    "sg:province":"IL",
    "sg:tags":[
        "accountant"
    ],
    "wof:name":"Lee Mutual Accounting",
    "wof:placetype":"venue"
},
  "geometry": {"coordinates":[-87.71758199999999,41.990171],"type":"Point"}
}