{
  "type": "Feature",
  "properties": {
    "iso:country":"US",
    "sg:address":"226 17th St",
    "sg:city":"Rock Island",
    "sg:classifiers":[
        {
            "category":"Restaurant",
            "type":"Food & Drink"
        }
    ],
    "sg:menulink":"http://www.allmenus.com/il/rock-island/91499-bennigans-grill--tavern/menu/",
    "sg:phone":"+1 309 786 8686",
    "sg:postcode":"61201",
    "sg:province":"IL",
    "sg:tags":[
        "sandwich",
        "salad",
        "burger",
        "pub",
        "soup",
        "american",
        "wrap"
    ],
    "wof:name":"Bennigan's Grill & Tavern",
    "wof:placetype":"venue"
},
  "geometry": {"coordinates":[-90.575997,41.510697],"type":"Point"}
}