{
  "type": "Feature",
  "properties": {
    "addr:full":"653 Collins St Joliet IL 60432",
    "addr:housenumber":"653",
    "addr:postcode":"60432",
    "addr:street":"Collins St",
    "iso:country":"US",
    "sg:address":"653 Collins St",
    "sg:city":"Joliet",
    "sg:classifiers":[
        {
            "category":"Personal",
            "subcategory":"Beauty Salon",
            "type":"Services"
        }
    ],
    "sg:phone":"+1 815 722 4480",
    "sg:postcode":"60432",
    "sg:province":"IL",
    "wof:name":"Diana Hair Studio",
    "wof:placetype":"venue"
},
  "geometry": {"coordinates":[-88.07281,41.537205],"type":"Point"}
}