{
  "type": "Feature",
  "properties": {
    "iso:country":"US",
    "sg:address":"440 Locust St",
    "sg:city":"Quincy",
    "sg:phone":"+1 217 223 0900",
    "sg:postcode":"62301",
    "sg:province":"IL",
    "sg:tags":[
        "equipment",
        "commercial",
        "repair"
    ],
    "wof:name":"Hobart Sales & Service",
    "wof:placetype":"venue"
},
  "geometry": {"coordinates":[-91.40871,39.950432],"type":"Point"}
}