{
  "type": "Feature",
  "properties": {
    "iso:country":"US",
    "sg:address":"110 S 1st Ave",
    "sg:city":"Coal City",
    "sg:classifiers":[
        {
            "category":"Taxi",
            "type":"Transportation"
        }
    ],
    "sg:phone":"+1 815 634 3623",
    "sg:postcode":"60416",
    "sg:province":"IL",
    "wof:name":"Positive Connections",
    "wof:placetype":"venue"
},
  "geometry": {"coordinates":[-88.275893,41.287054],"type":"Point"}
}