{
  "type": "Feature",
  "properties": {
    "addr:full":"5441 127th St Crestwood IL 60445",
    "addr:housenumber":"5441",
    "addr:postcode":"60445",
    "addr:street":"127Th St",
    "iso:country":"US",
    "sg:address":"5441 127th St",
    "sg:city":"Crestwood",
    "sg:classifiers":[
        {
            "category":"Recreation",
            "subcategory":"Amusement Park",
            "type":"Entertainment"
        },
        {
            "category":"Shopping",
            "subcategory":"Hobbies, Toys, & Games",
            "type":"Retail Goods"
        }
    ],
    "sg:phone":"+1 708 385 6271",
    "sg:postcode":"60445",
    "sg:province":"IL",
    "sg:tags":[
        "shop",
        "hobby"
    ],
    "wof:name":"Charity Bingo",
    "wof:placetype":"venue"
},
  "geometry": {"coordinates":[-87.75509599999999,41.661301],"type":"Point"}
}