{
  "type": "Feature",
  "properties": {
    "iso:country":"US",
    "sg:address":"1210 Abbott St",
    "sg:city":"Carlyle",
    "sg:classifiers":[
        {
            "category":"Retail",
            "subcategory":"Car Wash",
            "type":"Services"
        }
    ],
    "sg:phone":"+1 618 594 2513",
    "sg:postcode":"62231",
    "sg:province":"IL",
    "sg:tags":[
        "automobile",
        "detail",
        "clean"
    ],
    "wof:name":"Carlyle Super Wash",
    "wof:placetype":"venue"
},
  "geometry": {"coordinates":[-89.374113,38.616967],"type":"Point"}
}