{
  "type": "Feature",
  "properties": {
    "iso:country":"US",
    "sg:address":"824 E Sibley Blvd",
    "sg:city":"Dolton",
    "sg:classifiers":[
        {
            "category":"Travel",
            "subcategory":"Travel Agent",
            "type":"Entertainment"
        }
    ],
    "sg:phone":"+1 708 201 6333",
    "sg:postcode":"60419",
    "sg:province":"IL",
    "sg:website":"www.comforttravel.org",
    "wof:name":"Comfort Travel",
    "wof:placetype":"venue"
},
  "geometry": {"coordinates":[-87.59657300000001,41.622818],"type":"Point"}
}