{
  "type": "Feature",
  "properties": {
    "iso:country":"US",
    "sg:address":"524 E Exchange St",
    "sg:city":"Geneseo",
    "sg:classifiers":[
        {
            "category":"Wholesale",
            "subcategory":"Machinery & Supplies",
            "type":"Manufacturing & Wholesale Goods"
        }
    ],
    "sg:phone":"+1 309 944 6153",
    "sg:postcode":"61254",
    "sg:province":"IL",
    "sg:tags":[
        "equipment",
        "industrial"
    ],
    "wof:name":"All Quip Inc",
    "wof:placetype":"venue"
},
  "geometry": {"coordinates":[-90.148595,41.453212],"type":"Point"}
}