{
  "type": "Feature",
  "properties": {
    "iso:country":"US",
    "sg:address":"780 Villa St",
    "sg:city":"Elgin",
    "sg:classifiers":[
        {
            "category":"Restaurant",
            "type":"Food & Drink"
        }
    ],
    "sg:phone":"+1   ",
    "sg:postcode":"60120",
    "sg:province":"IL",
    "sg:tags":[
        "eating"
    ],
    "wof:name":"Great American Family Diner",
    "wof:placetype":"venue"
},
  "geometry": {"coordinates":[-88.263206,42.029129],"type":"Point"}
}