{
  "type": "Feature",
  "properties": {
    "addr:full":"200 S 3rd St Effingham IL 62401",
    "addr:housenumber":"200",
    "addr:postcode":"62401",
    "addr:street":"S 3Rd St",
    "iso:country":"US",
    "sg:address":"200 S 3rd St",
    "sg:city":"Effingham",
    "sg:classifiers":[
        {
            "category":"Organizations",
            "subcategory":"Membership Organization",
            "type":"Services"
        }
    ],
    "sg:phone":"+1 217 342 4418",
    "sg:postcode":"62401",
    "sg:province":"IL",
    "sg:tags":[
        "automobile"
    ],
    "wof:name":"AAA Chicago Motor Club",
    "wof:placetype":"venue"
},
  "geometry": {"coordinates":[-88.54080999999999,39.120411],"type":"Point"}
}