{
  "type": "Feature",
  "properties": {
    "addr:full":"6810 S Ashland Avenue Chicago IL 60636",
    "addr:housenumber":"6810",
    "addr:postcode":"60636",
    "addr:street":"S Ashland Avenue",
    "iso:country":"US",
    "sg:address":"6810 S Ashland Avenue",
    "sg:city":"Chicago",
    "sg:classifiers":[
        {
            "category":"Place Of Worship",
            "subcategory":"Church",
            "type":"Public Place"
        },
        {
            "category":"Place Of Worship",
            "type":"Public Place"
        },
        {
            "category":"Organizations",
            "subcategory":"Religious Organization",
            "type":"Services"
        }
    ],
    "sg:phone":"+1 773 436 7940",
    "sg:postcode":"60636",
    "sg:province":"IL",
    "sg:tags":[
        "churches-interdenominational",
        "churches-non-denominational",
        "churches-various",
        "denomination"
    ],
    "wof:name":"Liberation Christian Center",
    "wof:placetype":"venue"
},
  "geometry": {"coordinates":[-87.664011,41.77005],"type":"Point"}
}