{
  "type": "Feature",
  "properties": {
    "addr:full":"406 N East St Princeton IL 61356",
    "addr:housenumber":"406",
    "addr:postcode":"61356",
    "addr:street":"N East St",
    "iso:country":"US",
    "sg:address":"406 N East St",
    "sg:city":"Princeton",
    "sg:classifiers":[
        {
            "category":"Retail",
            "subcategory":"Animal Services",
            "type":"Services"
        }
    ],
    "sg:phone":"+1 815 925 2423",
    "sg:postcode":"61356",
    "sg:province":"IL",
    "sg:tags":[
        "shelter",
        "rescue"
    ],
    "wof:name":"Friends of Strays Inc",
    "wof:placetype":"venue"
},
  "geometry": {"coordinates":[-89.39357099999999,41.436856],"type":"Point"}
}