{
  "type": "Feature",
  "properties": {
    "addr:full":"630 N Hamlin Ave Park Ridge IL 60068",
    "addr:housenumber":"630",
    "addr:postcode":"60068",
    "addr:street":"N Hamlin Ave",
    "iso:country":"US",
    "sg:address":"630 N Hamlin Ave",
    "sg:city":"Park Ridge",
    "sg:classifiers":[
        {
            "category":"Professional",
            "subcategory":"Management & Consulting",
            "type":"Services"
        }
    ],
    "sg:phone":"+1 847 818 0386",
    "sg:postcode":"60068",
    "sg:province":"IL",
    "sg:tags":[
        "consultant",
        "business"
    ],
    "wof:name":"Business Funding Solutions Inc",
    "wof:placetype":"venue"
},
  "geometry": {"coordinates":[-87.850478,42.02023],"type":"Point"}
}