{
  "type": "Feature",
  "properties": {
    "addr:full":"124 Wagner Dr Cary IL 60013",
    "addr:housenumber":"124",
    "addr:postcode":"60013",
    "addr:street":"Wagner Dr",
    "iso:country":"US",
    "sg:address":"124 Wagner Dr",
    "sg:city":"Cary",
    "sg:classifiers":[
        {
            "category":"Building & Trades",
            "subcategory":"Construction",
            "type":"Services"
        }
    ],
    "sg:phone":"+1 847 639 3758",
    "sg:postcode":"60013",
    "sg:province":"IL",
    "sg:tags":[
        "house"
    ],
    "wof:name":"Mr Home Improvements",
    "wof:placetype":"venue"
},
  "geometry": {"coordinates":[-88.24169500000001,42.212692],"type":"Point"}
}