{
  "type": "Feature",
  "properties": {
    "addr:full":"1441 Branding Ln Downers Grove IL 60515",
    "addr:housenumber":"1441",
    "addr:postcode":"60515",
    "addr:street":"Branding Ln",
    "iso:country":"US",
    "sg:address":"1441 Branding Ln",
    "sg:city":"Downers Grove",
    "sg:classifiers":[
        {
            "category":"Health Services",
            "subcategory":"Clinic",
            "type":"Services"
        }
    ],
    "sg:phone":"+1 630 963 1699",
    "sg:postcode":"60515",
    "sg:province":"IL",
    "sg:tags":[
        "home",
        "care"
    ],
    "wof:name":"Healthsource Infusion Therapy",
    "wof:placetype":"venue"
},
  "geometry": {"coordinates":[-88.022927,41.831487],"type":"Point"}
}