{
  "type": "Feature",
  "properties": {
    "iso:country":"US",
    "sg:address":"1020 31st St",
    "sg:city":"Downers Grove",
    "sg:classifiers":[
        {
            "category":"Professional",
            "type":"Services"
        }
    ],
    "sg:phone":"+1 630 852 6868",
    "sg:postcode":"60515",
    "sg:province":"IL",
    "sg:tags":[
        "establishment"
    ],
    "wof:name":"Cb Richard Ellis Inc",
    "wof:placetype":"venue"
},
  "geometry": {"coordinates":[-88.01118099999999,41.831084],"type":"Point"}
}