{
  "type": "Feature",
  "properties": {
    "addr:full":"2659 W Division St Chicago IL 60622",
    "addr:housenumber":"2659",
    "addr:postcode":"60622",
    "addr:street":"W Division St",
    "iso:country":"US",
    "sg:address":"2659 W Division St",
    "sg:city":"Chicago",
    "sg:classifiers":[
        {
            "category":"Home & Garden",
            "subcategory":"Hardware",
            "type":"Retail Goods"
        }
    ],
    "sg:phone":"+1 773 276 3691",
    "sg:postcode":"60622",
    "sg:province":"IL",
    "sg:tags":[
        "store"
    ],
    "wof:name":"Joe's Hardware",
    "wof:placetype":"venue"
},
  "geometry": {"coordinates":[-87.694199,41.902802],"type":"Point"}
}