{
  "type": "Feature",
  "properties": {
    "iso:country":"US",
    "sg:address":"4543 E 800 North Rd",
    "sg:city":"Fairmount",
    "sg:classifiers":[
        {
            "category":"Wholesale",
            "subcategory":"Farm Supplies",
            "type":"Manufacturing & Wholesale Goods"
        }
    ],
    "sg:phone":"+1 217 288 9466",
    "sg:postcode":"61841",
    "sg:province":"IL",
    "wof:name":"Mohr Family Farms Inc",
    "wof:placetype":"venue"
},
  "geometry": {"coordinates":[-87.858806,39.982436],"type":"Point"}
}