{
  "type": "Feature",
  "properties": {
    "addr:full":"9 S Van Buren St Batavia IL 60510",
    "addr:housenumber":"9",
    "addr:postcode":"60510",
    "addr:street":"S Van Buren St",
    "iso:country":"US",
    "sg:address":"9 S Van Buren St",
    "sg:city":"Batavia",
    "sg:classifiers":[
        {
            "category":"Professional",
            "subcategory":"Detective & Security Services",
            "type":"Services"
        }
    ],
    "sg:phone":"+1 630 761 0620",
    "sg:postcode":"60510",
    "sg:province":"IL",
    "sg:tags":[
        "car"
    ],
    "wof:name":"Delorto Mazzola & Associates",
    "wof:placetype":"venue"
},
  "geometry": {"coordinates":[-88.303172,41.848881],"type":"Point"}
}