{
  "type": "Feature",
  "properties": {
    "iso:country":"US",
    "sg:address":"12 Oneill St",
    "sg:city":"Joliet",
    "sg:classifiers":[
        {
            "category":"Building & Trades",
            "subcategory":"Construction",
            "type":"Services"
        }
    ],
    "sg:phone":"+1 815 723 5018",
    "sg:postcode":"60436",
    "sg:province":"IL",
    "sg:tags":[
        "wallcoverings-installation",
        "wallpaper",
        "painting",
        "contractor"
    ],
    "wof:name":"Davison Painting Inc",
    "wof:placetype":"venue"
},
  "geometry": {"coordinates":[-88.110291,41.522879],"type":"Point"}
}