{
  "type": "Feature",
  "properties": {
    "addr:full":"29601 Yonk Rd Prophetstown IL 61277",
    "addr:postcode":"29601;61277",
    "addr:street":"Yonk Rd",
    "iso:country":"US",
    "sg:address":"29601 Yonk Rd",
    "sg:city":"Prophetstown",
    "sg:classifiers":[
        {
            "category":"Shopping",
            "subcategory":"Crafts & Fabrics",
            "type":"Retail Goods"
        }
    ],
    "sg:phone":"+1   ",
    "sg:postcode":"61277",
    "sg:province":"IL",
    "sg:tags":[
        "housewares",
        "sewing",
        "supply"
    ],
    "wof:name":"Fabric Loft",
    "wof:placetype":"venue"
},
  "geometry": {"coordinates":[-89.86982500000001,41.574455],"type":"Point"}
}