{
  "type": "Feature",
  "properties": {
    "addr:full":"4201 W Division St Chicago IL 60651",
    "addr:housenumber":"4201",
    "addr:postcode":"60651",
    "addr:street":"W Division St",
    "iso:country":"US",
    "sg:address":"4201 W Division St",
    "sg:city":"Chicago",
    "sg:classifiers":[
        {
            "category":"Building & Trades",
            "subcategory":"Locksmith",
            "type":"Services"
        }
    ],
    "sg:phone":"+1 773 724 6120",
    "sg:postcode":"60651",
    "sg:province":"IL",
    "sg:tags":[
        "key"
    ],
    "wof:name":"24 Hour Locks and Locksmith",
    "wof:placetype":"venue"
},
  "geometry": {"coordinates":[-87.731189,41.902473],"type":"Point"}
}