{
  "type": "Feature",
  "properties": {
    "addr:full":"3107 Theodore St Joliet IL 60435",
    "addr:housenumber":"3107",
    "addr:postcode":"60435",
    "addr:street":"Theodore St",
    "iso:country":"US",
    "sg:address":"3107 Theodore St",
    "sg:city":"Joliet",
    "sg:classifiers":[
        {
            "category":"Professional",
            "subcategory":"Computer Services",
            "type":"Services"
        }
    ],
    "sg:phone":"+1 815 744 7132",
    "sg:postcode":"60435",
    "sg:province":"IL",
    "wof:name":"Computers Done Right Inc",
    "wof:placetype":"venue"
},
  "geometry": {"coordinates":[-88.161023,41.55106],"type":"Point"}
}