{
  "type": "Feature",
  "properties": {
    "addr:full":"935 Curtiss St Downers Grove IL 60515",
    "addr:housenumber":"935",
    "addr:postcode":"60515",
    "addr:street":"Curtiss St",
    "iso:country":"US",
    "sg:address":"935 Curtiss St",
    "sg:city":"Downers Grove",
    "sg:classifiers":[
        {
            "category":"Food & Beverages",
            "subcategory":"Meat & Fish",
            "type":"Retail Goods"
        }
    ],
    "sg:phone":"+1 630 434 4201",
    "sg:postcode":"60515",
    "sg:province":"IL",
    "sg:tags":[
        "seafood"
    ],
    "wof:name":"Exquisitely Smoked Salmon",
    "wof:placetype":"venue"
},
  "geometry": {"coordinates":[-88.009946,41.793704],"type":"Point"}
}