{
  "type": "Feature",
  "properties": {
    "addr:full":"14735 Pulaski Rd Midlothian IL 60445",
    "addr:housenumber":"14735",
    "addr:postcode":"60445",
    "addr:street":"Pulaski Rd",
    "iso:country":"US",
    "sg:address":"14735 Pulaski Rd",
    "sg:city":"Midlothian",
    "sg:classifiers":[
        {
            "category":"Health Services",
            "subcategory":"Doctor",
            "type":"Services"
        }
    ],
    "sg:phone":"+1 708 371 0077",
    "sg:postcode":"60445",
    "sg:province":"IL",
    "wof:name":"Family Doctors",
    "wof:placetype":"venue"
},
  "geometry": {"coordinates":[-87.71790300000001,41.621101],"type":"Point"}
}