{
  "type": "Feature",
  "properties": {
    "iso:country":"US",
    "sg:address":"444 Commerce St",
    "sg:city":"Aurora",
    "sg:classifiers":[
        {
            "category":"Personal",
            "type":"Services"
        }
    ],
    "sg:phone":"+1 630 692 5000",
    "sg:postcode":"60504",
    "sg:province":"IL",
    "sg:tags":[
        "paying",
        "bill"
    ],
    "sg:website":"www.checkfreecorp.com",
    "wof:name":"Check Free Corp",
    "wof:placetype":"venue"
},
  "geometry": {"coordinates":[-88.229952,41.764104],"type":"Point"}
}