{
  "type": "Feature",
  "properties": {
    "iso:country":"US",
    "sg:address":"8409 S Vernon Ave",
    "sg:city":"Chicago",
    "sg:classifiers":[
        {
            "category":"Retail",
            "subcategory":"Auto Rental",
            "type":"Services"
        }
    ],
    "sg:phone":"+1 773 320 8632",
    "sg:postcode":"60619",
    "sg:province":"IL",
    "sg:tags":[
        "limousine"
    ],
    "wof:name":"Avinew Limo Svc",
    "wof:placetype":"venue"
},
  "geometry": {"coordinates":[-87.613055,41.741857],"type":"Point"}
}