{
  "type": "Feature",
  "properties": {
    "addr:full":"6621 W Higgins Ave Apt 1 Chicago IL 60656",
    "addr:housenumber":"6621;1",
    "addr:postcode":"60656",
    "addr:street":"W Higgins Ave Apt",
    "iso:country":"US",
    "sg:address":"6621 W Higgins Ave Apt 1",
    "sg:city":"Chicago",
    "sg:classifiers":[
        {
            "category":"Restaurant",
            "type":"Food & Drink"
        }
    ],
    "sg:phone":"+1 773 545 5589",
    "sg:postcode":"60656",
    "sg:province":"IL",
    "sg:tags":[
        "chicken"
    ],
    "wof:name":"Elston Chicken Poultry",
    "wof:placetype":"venue"
},
  "geometry": {"coordinates":[-87.79346700000001,41.978103],"type":"Point"}
}