{
  "type": "Feature",
  "properties": {
    "addr:full":"1209 Dunstan Rd Geneva IL 60134",
    "addr:housenumber":"1209",
    "addr:postcode":"60134",
    "addr:street":"Dunstan Rd",
    "iso:country":"US",
    "sg:address":"1209 Dunstan Rd",
    "sg:city":"Geneva",
    "sg:classifiers":[
        {
            "category":"Insurance",
            "subcategory":"Insurance Agent",
            "type":"Services"
        }
    ],
    "sg:phone":"+1 630 232 1552",
    "sg:postcode":"60134",
    "sg:province":"IL",
    "wof:name":"Elms Inc",
    "wof:placetype":"venue"
},
  "geometry": {"coordinates":[-88.318924,41.873931],"type":"Point"}
}