{
  "type": "Feature",
  "properties": {
    "iso:country":"US",
    "sg:address":"781 Joyce Rd",
    "sg:city":"Joliet",
    "sg:classifiers":[
        {
            "category":"Wholesale",
            "subcategory":"Stationery",
            "type":"Manufacturing & Wholesale Goods"
        },
        {
            "category":"Shopping",
            "subcategory":"Stationery & Office Supplies",
            "type":"Retail Goods"
        }
    ],
    "sg:phone":"+1 815 744 1422",
    "sg:postcode":"60436",
    "sg:province":"IL",
    "sg:tags":[
        "equipment"
    ],
    "wof:name":"Josco Office Plus 294",
    "wof:placetype":"venue"
},
  "geometry": {"coordinates":[-88.140364,41.512845],"type":"Point"}
}