{
  "type": "Feature",
  "properties": {
    "addr:full":"4804 N Central Ave Chicago IL 60630",
    "addr:housenumber":"4804",
    "addr:postcode":"60630",
    "addr:street":"N Central Ave",
    "iso:country":"US",
    "sg:address":"4804 N Central Ave",
    "sg:city":"Chicago",
    "sg:classifiers":[
        {
            "category":"Shopping",
            "subcategory":"Florist",
            "type":"Retail Goods"
        }
    ],
    "sg:phone":"+1 773 725 9200",
    "sg:postcode":"60630",
    "sg:province":"IL",
    "sg:website":"www.grecosflowers.com",
    "wof:name":"Grecos Flowers & Gifts Ltd",
    "wof:placetype":"venue"
},
  "geometry": {"coordinates":[-87.76751,41.967956],"type":"Point"}
}