{
  "type": "Feature",
  "properties": {
    "iso:country":"US",
    "sg:address":"610 Mount Zion Rd",
    "sg:city":"Vienna",
    "sg:classifiers":[
        {
            "category":"Manufacturing",
            "subcategory":"Food",
            "type":"Manufacturing & Wholesale Goods"
        }
    ],
    "sg:phone":"+1 618 658 9317",
    "sg:postcode":"62995",
    "sg:province":"IL",
    "sg:tags":[
        "product"
    ],
    "wof:name":"Robert Harris",
    "wof:placetype":"venue"
},
  "geometry": {"coordinates":[-88.961828,37.435399],"type":"Point"}
}