{
  "type": "Feature",
  "properties": {
    "addr:full":"18019 Dixie Hwy Homewood IL 60430",
    "addr:housenumber":"18019",
    "addr:postcode":"60430",
    "addr:street":"Dixie Hwy",
    "iso:country":"US",
    "sg:address":"18019 Dixie Hwy",
    "sg:city":"Homewood",
    "sg:classifiers":[
        {
            "category":"Professional",
            "subcategory":"Business Services",
            "type":"Services"
        }
    ],
    "sg:phone":"+1 708 799 0930",
    "sg:postcode":"60430",
    "sg:province":"IL",
    "wof:name":"Telecom Answering Service",
    "wof:placetype":"venue"
},
  "geometry": {"coordinates":[-87.665335,41.56165],"type":"Point"}
}