{
  "type": "Feature",
  "properties": {
    "iso:country":"US",
    "sg:address":"1125 46th Ave",
    "sg:city":"Rock Island",
    "sg:classifiers":[
        {
            "category":"Retail",
            "subcategory":"Repair Shop",
            "type":"Services"
        }
    ],
    "sg:phone":"+1   ",
    "sg:postcode":"61201",
    "sg:province":"IL",
    "sg:tags":[
        "appliance",
        "household",
        "electrical"
    ],
    "wof:name":"Pfister & Sons Appliances",
    "wof:placetype":"venue"
},
  "geometry": {"coordinates":[-90.58295099999999,41.466002],"type":"Point"}
}