{
  "type": "Feature",
  "properties": {
    "addr:full":"3211 W 103rd St Chicago IL 60655",
    "addr:housenumber":"3211",
    "addr:postcode":"60655",
    "addr:street":"W 103Rd St",
    "iso:country":"US",
    "sg:address":"3211 W 103rd St",
    "sg:city":"Chicago",
    "sg:classifiers":[
        {
            "category":"Banks & Credit Unions",
            "subcategory":"Bank",
            "type":"Services"
        }
    ],
    "sg:phone":"+1 773 233 4220",
    "sg:postcode":"60655",
    "sg:province":"IL",
    "sg:tags":[
        "currency",
        "exchange"
    ],
    "wof:name":"103rd-Kedzie Currency Exchange",
    "wof:placetype":"venue"
},
  "geometry": {"coordinates":[-87.701517,41.706109],"type":"Point"}
}