{
  "type": "Feature",
  "properties": {
    "addr:full":"2120 183rd Pl Lansing IL 60438",
    "addr:housenumber":"2120",
    "addr:postcode":"60438",
    "addr:street":"183Rd Pl",
    "iso:country":"US",
    "sg:address":"2120 183rd Pl",
    "sg:city":"Lansing",
    "sg:classifiers":[
        {
            "category":"Freight",
            "type":"Transportation"
        }
    ],
    "sg:phone":"+1 708 895 8605",
    "sg:postcode":"60438",
    "sg:province":"IL",
    "sg:tags":[
        "operator",
        "local",
        "trucking"
    ],
    "wof:name":"Rietveld Trucking Inc",
    "wof:placetype":"venue"
},
  "geometry": {"coordinates":[-87.56447799999999,41.56184],"type":"Point"}
}