{
  "type": "Feature",
  "properties": {
    "addr:full":"2249 Highland Park Dr Joliet IL 60432",
    "addr:housenumber":"2249",
    "addr:postcode":"60432",
    "addr:street":"Highland Park Dr",
    "iso:country":"US",
    "sg:address":"2249 Highland Park Dr",
    "sg:city":"Joliet",
    "sg:classifiers":[
        {
            "category":"Shopping",
            "subcategory":"Computers & Home Electronics",
            "type":"Retail Goods"
        }
    ],
    "sg:phone":"+1 815 553 0300",
    "sg:postcode":"60432",
    "sg:province":"IL",
    "sg:tags":[
        "software"
    ],
    "wof:name":"Primetime Computer Svc",
    "wof:placetype":"venue"
},
  "geometry": {"coordinates":[-88.03198,41.53544],"type":"Point"}
}