{
  "type": "Feature",
  "properties": {
    "addr:full":"360 W Maple St Roseville IL 61473",
    "addr:housenumber":"360",
    "addr:postcode":"61473",
    "addr:street":"W Maple St",
    "iso:country":"US",
    "sg:address":"360 W Maple St",
    "sg:city":"Roseville",
    "sg:classifiers":[
        {
            "category":"Education",
            "subcategory":"Special Training",
            "type":"Public Place"
        }
    ],
    "sg:phone":"+1 309 426 2731",
    "sg:postcode":"61473",
    "sg:province":"IL",
    "sg:tags":[
        "school",
        "instruction",
        "art"
    ],
    "wof:name":"Karla's Brush & Palette",
    "wof:placetype":"venue"
},
  "geometry": {"coordinates":[-90.66834799999999,40.734268],"type":"Point"}
}