{
  "type": "Feature",
  "properties": {
    "addr:full":"1310 N Keller Dr Ste 1 Effingham IL 62401",
    "addr:housenumber":"1310",
    "addr:postcode":"62401",
    "addr:street":"N Keller Dr Ste 1",
    "iso:country":"US",
    "sg:address":"1310 N Keller Dr Ste 1",
    "sg:city":"Effingham",
    "sg:classifiers":[
        {
            "category":"Autos & Motor Vehicles",
            "subcategory":"Automobile Sales",
            "type":"Retail Goods"
        }
    ],
    "sg:phone":"+1 217 342 1000",
    "sg:postcode":"62401",
    "sg:province":"IL",
    "sg:tags":[
        "dealers-used",
        "car",
        "used",
        "cars-wholesale",
        "new"
    ],
    "wof:name":"Diamond Car Rental & Sales",
    "wof:placetype":"venue"
},
  "geometry": {"coordinates":[-88.560543,39.130714],"type":"Point"}
}