{
  "type": "Feature",
  "properties": {
    "addr:full":"4421 Vernon Ave Brookfield IL 60513",
    "addr:housenumber":"4421",
    "addr:postcode":"60513",
    "addr:street":"Vernon Ave",
    "iso:country":"US",
    "sg:address":"4421 Vernon Ave",
    "sg:city":"Brookfield",
    "sg:classifiers":[
        {
            "category":"Building & Trades",
            "subcategory":"Construction",
            "type":"Services"
        }
    ],
    "sg:phone":"+1 708 387 2131",
    "sg:postcode":"60513",
    "sg:province":"IL",
    "sg:tags":[
        "house"
    ],
    "wof:name":"Lac Construction",
    "wof:placetype":"venue"
},
  "geometry": {"coordinates":[-87.844881,41.809567],"type":"Point"}
}