{
  "type": "Feature",
  "properties": {
    "iso:country":"US",
    "sg:address":"1904 W George St",
    "sg:city":"Chicago",
    "sg:classifiers":[
        {
            "category":"Shopping",
            "subcategory":"Clothing, Apparel, & Fashions",
            "type":"Retail Goods"
        }
    ],
    "sg:phone":"+1   ",
    "sg:postcode":"60657",
    "sg:province":"IL",
    "sg:tags":[
        "novelty",
        "t",
        "patch"
    ],
    "wof:name":"Dioses Ocultos",
    "wof:placetype":"venue"
},
  "geometry": {"coordinates":[-87.677497,41.934191],"type":"Point"}
}