{
  "type": "Feature",
  "properties": {
    "addr:full":"5 Cour Michele Palos Hills IL 60465",
    "addr:housenumber":"5",
    "addr:postcode":"60465",
    "addr:street":"Cour Michele Palos",
    "iso:country":"US",
    "sg:address":"5 Cour Michele",
    "sg:city":"Palos Hills",
    "sg:classifiers":[
        {
            "category":"Building & Trades",
            "subcategory":"Electrical",
            "type":"Services"
        }
    ],
    "sg:phone":"+1 708 974 0111",
    "sg:postcode":"60465",
    "sg:province":"IL",
    "sg:tags":[
        "electric",
        "contractor"
    ],
    "wof:name":"Advanced Electrical Control",
    "wof:placetype":"venue"
},
  "geometry": {"coordinates":[-87.82925400000001,41.687327],"type":"Point"}
}