{
  "type": "Feature",
  "properties": {
    "iso:country":"US",
    "sg:address":"7667 W 95th St",
    "sg:city":"Hickory Hills",
    "sg:classifiers":[
        {
            "category":"Professional",
            "subcategory":"Secretarial Services",
            "type":"Services"
        }
    ],
    "sg:phone":"+1 708 599 8886",
    "sg:postcode":"60457",
    "sg:province":"IL",
    "sg:tags":[
        "resume"
    ],
    "wof:name":"A Better Resume Svc",
    "wof:placetype":"venue"
},
  "geometry": {"coordinates":[-87.81013299999999,41.718632],"type":"Point"}
}