{
  "type": "Feature",
  "properties": {
    "iso:country":"US",
    "sg:address":"2638 Clarence Ave",
    "sg:city":"Berwyn",
    "sg:classifiers":[
        {
            "category":"Home & Garden",
            "subcategory":"Furniture",
            "type":"Retail Goods"
        }
    ],
    "sg:phone":"+1   ",
    "sg:postcode":"60402",
    "sg:province":"IL",
    "wof:name":"This End Up Furniture",
    "wof:placetype":"venue"
},
  "geometry": {"coordinates":[-87.789492,41.841743],"type":"Point"}
}