{
  "type": "Feature",
  "properties": {
    "iso:country":"US",
    "sg:address":"28 N Clark St",
    "sg:city":"Chicago",
    "sg:classifiers":[
        {
            "category":"Education",
            "subcategory":"Special Training",
            "type":"Public Place"
        },
        {
            "category":"Education",
            "subcategory":"University",
            "type":"Public Place"
        }
    ],
    "sg:phone":"+1 312 332 0707",
    "sg:postcode":"60602",
    "sg:province":"IL",
    "sg:tags":[
        "college",
        "school",
        "art"
    ],
    "sg:website":"www.flashpointacademy.com",
    "wof:name":"Flashpoint ?- The Academy of Media Arts and Sciences",
    "wof:placetype":"venue"
},
  "geometry": {"coordinates":[-87.63124500000001,41.882806],"type":"Point"}
}