{
  "type": "Feature",
  "properties": {
    "iso:country":"US",
    "sg:address":"4015 W Carroll Ave",
    "sg:city":"Chicago",
    "sg:classifiers":[
        {
            "category":"Shopping",
            "subcategory":"Clothing, Apparel, & Fashions",
            "type":"Retail Goods"
        }
    ],
    "sg:phone":"+1 773 265 6630",
    "sg:postcode":"60624",
    "sg:province":"IL",
    "sg:tags":[
        "clothing",
        "women's"
    ],
    "wof:name":"S I Industries",
    "wof:placetype":"venue"
},
  "geometry": {"coordinates":[-87.72599,41.8867],"type":"Point"}
}