{
  "type": "Feature",
  "properties": {
    "iso:country":"US",
    "sg:address":"430 Bonnie Ln",
    "sg:city":"Elk Grove Village",
    "sg:classifiers":[
        {
            "category":"Manufacturing",
            "subcategory":"Electronics",
            "type":"Manufacturing & Wholesale Goods"
        }
    ],
    "sg:phone":"+1 847 640 0007",
    "sg:postcode":"60007",
    "sg:province":"IL",
    "sg:tags":[
        "engineering"
    ],
    "wof:name":"Intratek Inc",
    "wof:placetype":"venue"
},
  "geometry": {"coordinates":[-87.971173,42.017972],"type":"Point"}
}