{
  "type": "Feature",
  "properties": {
    "iso:country":"US",
    "sg:address":"3316 Quincy Mall",
    "sg:city":"Quincy",
    "sg:classifiers":[
        {
            "category":"Shopping",
            "subcategory":"Gifts & Souvenirs",
            "type":"Retail Goods"
        }
    ],
    "sg:phone":"+1   ",
    "sg:postcode":"62301",
    "sg:province":"IL",
    "wof:name":"Spencer Gifts LLC",
    "wof:placetype":"venue"
},
  "geometry": {"coordinates":[-91.36112300000001,39.935698],"type":"Point"}
}