{
  "type": "Feature",
  "properties": {
    "addr:full":"9107 Grand Ave Franklin Park IL 60131",
    "addr:housenumber":"9107",
    "addr:postcode":"60131",
    "addr:street":"Grand Ave",
    "iso:country":"US",
    "sg:address":"9107 Grand Ave",
    "sg:city":"Franklin Park",
    "sg:classifiers":[
        {
            "category":"Insurance",
            "subcategory":"Insurance Agent",
            "type":"Services"
        }
    ],
    "sg:phone":"+1 847 455 7222",
    "sg:postcode":"60131",
    "sg:province":"IL",
    "wof:name":"Richard E Lange Inc",
    "wof:placetype":"venue"
},
  "geometry": {"coordinates":[-87.853728,41.929118],"type":"Point"}
}