{
  "type": "Feature",
  "properties": {
    "addr:full":"2824 W Armitage Chicago IL 60647",
    "addr:housenumber":"2824",
    "addr:postcode":"60647",
    "addr:street":"W Armitage",
    "iso:country":"US",
    "sg:address":"2824 W Armitage",
    "sg:city":"Chicago",
    "sg:classifiers":[
        {
            "category":"Professional",
            "type":"Services"
        },
        {
            "category":"Restaurant",
            "type":"Food & Drink"
        },
        {
            "category":"Fast Food",
            "type":"Food & Drink"
        }
    ],
    "sg:phone":"+1 773 687 8148",
    "sg:postcode":"60647",
    "sg:province":"IL",
    "sg:tags":[
        "house",
        "lunch",
        "take",
        "caterer",
        "barbecue",
        "brunch",
        "steak",
        "breakfast",
        "barbeque"
    ],
    "sg:website":"www.brandbbqmarket.com/",
    "wof:name":"Brand BBQ Market",
    "wof:placetype":"venue"
},
  "geometry": {"coordinates":[-87.69824300000001,41.917789],"type":"Point"}
}