{
  "type": "Feature",
  "properties": {
    "iso:country":"US",
    "sg:address":"910 Woodlands Pkwy",
    "sg:city":"Vernon Hills",
    "sg:classifiers":[
        {
            "category":"Professional",
            "subcategory":"Lawyer & Legal Services",
            "type":"Services"
        }
    ],
    "sg:phone":"+1 847 793 0306",
    "sg:postcode":"60061",
    "sg:province":"IL",
    "wof:name":"Scott A Sandroff",
    "wof:placetype":"venue"
},
  "geometry": {"coordinates":[-87.93837,42.208754],"type":"Point"}
}