{
  "type": "Feature",
  "properties": {
    "addr:full":"1601 W North Ave Chicago IL 60622",
    "addr:housenumber":"1601",
    "addr:postcode":"60622",
    "addr:street":"W North Ave",
    "iso:country":"US",
    "sg:address":"1601 W North Ave",
    "sg:city":"Chicago",
    "sg:classifiers":[
        {
            "category":"Restaurant",
            "type":"Food & Drink"
        }
    ],
    "sg:phone":"+1 773 395 1818",
    "sg:postcode":"60622",
    "sg:province":"IL",
    "sg:tags":[
        "traditional",
        "american",
        "brunch",
        "breakfast"
    ],
    "sg:website":"www.hollywood-grill.com",
    "wof:name":"Hollywood Grill",
    "wof:placetype":"venue"
},
  "geometry": {"coordinates":[-87.66768399999999,41.910595],"type":"Point"}
}