{
  "type": "Feature",
  "properties": {
    "addr:full":"100 S Fairbank St Addison IL 60101",
    "addr:housenumber":"100",
    "addr:postcode":"60101",
    "addr:street":"S Fairbank St",
    "iso:country":"US",
    "sg:address":"100 S Fairbank St",
    "sg:city":"Addison",
    "sg:classifiers":[
        {
            "category":"Real Estate",
            "subcategory":"Real Estate Services",
            "type":"Services"
        },
        {
            "category":"Real Estate",
            "subcategory":"Real Estate Agent",
            "type":"Services"
        }
    ],
    "sg:phone":"+1 630 458 9115",
    "sg:postcode":"60101",
    "sg:province":"IL",
    "sg:tags":[
        "buyer",
        "management",
        "broker"
    ],
    "wof:name":"Rothbart Realty",
    "wof:placetype":"venue"
},
  "geometry": {"coordinates":[-88.018089,41.925541],"type":"Point"}
}