{
  "type": "Feature",
  "properties": {
    "iso:country":"US",
    "sg:address":"1601 Wentworth Ave",
    "sg:city":"Calumet City",
    "sg:classifiers":[
        {
            "category":"Education",
            "subcategory":"School",
            "type":"Public Place"
        }
    ],
    "sg:phone":"+1 708 585 2300",
    "sg:postcode":"60409",
    "sg:province":"IL",
    "wof:name":"Thornton Fractional Dist 215 Administration Center",
    "wof:placetype":"venue"
},
  "geometry": {"coordinates":[-87.5299,41.586498],"type":"Point"}
}