{
  "type": "Feature",
  "properties": {
    "iso:country":"US",
    "sg:address":"15413 Orchid Ct",
    "sg:city":"Orland Park",
    "sg:classifiers":[
        {
            "category":"Professional",
            "subcategory":"Lawyer & Legal Services",
            "type":"Services"
        }
    ],
    "sg:phone":"+1 708 771 6701",
    "sg:postcode":"60462",
    "sg:province":"IL",
    "wof:name":"Mary L Norwell",
    "wof:placetype":"venue"
},
  "geometry": {"coordinates":[-87.809664,41.610971],"type":"Point"}
}