{
  "type": "Feature",
  "properties": {
    "iso:country":"US",
    "sg:address":"403 Hollyridge Ct",
    "sg:city":"Saint Joseph",
    "sg:classifiers":[
        {
            "category":"Retail",
            "subcategory":"Repair Shop",
            "type":"Services"
        }
    ],
    "sg:phone":"+1 217 469 7900",
    "sg:postcode":"61873",
    "sg:province":"IL",
    "sg:tags":[
        "bakery",
        "product"
    ],
    "wof:name":"C & S Sales",
    "wof:placetype":"venue"
},
  "geometry": {"coordinates":[-88.048805,40.118072],"type":"Point"}
}