{
  "type": "Feature",
  "properties": {
    "iso:country":"US",
    "sg:address":"2850 Golf Rd",
    "sg:city":"Rolling Meadows",
    "sg:classifiers":[
        {
            "category":"Banks & Credit Unions",
            "subcategory":"Bank",
            "type":"Services"
        }
    ],
    "sg:phone":"+1 847 952 1110",
    "sg:postcode":"60008",
    "sg:province":"IL",
    "sg:tags":[
        "state",
        "commercial"
    ],
    "wof:name":"Bank of America",
    "wof:placetype":"venue"
},
  "geometry": {"coordinates":[-88.015163,42.051198],"type":"Point"}
}