{
  "type": "Feature",
  "properties": {
    "iso:country":"US",
    "sg:address":"3000 Warrenville Rd",
    "sg:city":"Lisle",
    "sg:classifiers":[
        {
            "category":"Travel",
            "subcategory":"Hotels & Motels",
            "type":"Entertainment"
        }
    ],
    "sg:postcode":"60532",
    "sg:province":"IL",
    "sg:tags":[
        "operation",
        "eating",
        "drinking"
    ],
    "sg:website":"http://www.thayerinteractive.com/clickthru/clickthrough.rry/102263",
    "wof:name":"Wyndham Lisle",
    "wof:placetype":"venue"
},
  "geometry": {"coordinates":[-88.111076,41.808781],"type":"Point"}
}