{
  "type": "Feature",
  "properties": {
    "addr:full":"8305 Willow West Dr Willow Springs IL 60480",
    "addr:housenumber":"8305",
    "addr:postcode":"60480",
    "addr:street":"Willow West Dr",
    "iso:country":"US",
    "sg:address":"8305 Willow West Dr",
    "sg:city":"Willow Springs",
    "sg:classifiers":[
        {
            "category":"Professional",
            "subcategory":"Advertising",
            "type":"Services"
        }
    ],
    "sg:phone":"+1 708 354 8960",
    "sg:postcode":"60480",
    "sg:province":"IL",
    "sg:tags":[
        "medium",
        "broker"
    ],
    "wof:name":"C M Print Group Inc",
    "wof:placetype":"venue"
},
  "geometry": {"coordinates":[-87.889877,41.738536],"type":"Point"}
}