{
  "type": "Feature",
  "properties": {
    "iso:country":"US",
    "sg:address":"2017 W Cedar Hills Dr",
    "sg:city":"Dunlap",
    "sg:classifiers":[
        {
            "category":"Home & Garden",
            "subcategory":"Carpets & Floor Coverings",
            "type":"Retail Goods"
        }
    ],
    "sg:phone":"+1 309 243 7766",
    "sg:postcode":"61525",
    "sg:province":"IL",
    "sg:tags":[
        "dealer",
        "rug"
    ],
    "wof:name":"Country Carpets",
    "wof:placetype":"venue"
},
  "geometry": {"coordinates":[-89.63038,40.842617],"type":"Point"}
}