{
  "type": "Feature",
  "properties": {
    "addr:full":"15561 N 1700th St Teutopolis IL 62467",
    "addr:housenumber":"15561",
    "addr:postcode":"62467",
    "addr:street":"N 1700Th St",
    "iso:country":"US",
    "sg:address":"15561 N 1700th St",
    "sg:city":"Teutopolis",
    "sg:classifiers":[
        {
            "category":"Professional",
            "subcategory":"Business Services",
            "type":"Services"
        }
    ],
    "sg:phone":"+1 217 857 6644",
    "sg:postcode":"62467",
    "sg:province":"IL",
    "wof:name":"Illinois Education Assoc",
    "wof:placetype":"venue"
},
  "geometry": {"coordinates":[-88.486108,39.142474],"type":"Point"}
}