{
  "type": "Feature",
  "properties": {
    "iso:country":"US",
    "sg:address":"807 N State St",
    "sg:city":"Champaign",
    "sg:classifiers":[
        {
            "category":"Retail",
            "subcategory":"Auto Repair",
            "type":"Services"
        }
    ],
    "sg:phone":"+1 217 351 7503",
    "sg:postcode":"61820",
    "sg:province":"IL",
    "wof:name":"Cochran's State St Auto Imports Parts & Service",
    "wof:placetype":"venue"
},
  "geometry": {"coordinates":[-88.24690200000001,40.123199],"type":"Point"}
}