{
  "type": "Feature",
  "properties": {
    "iso:country":"US",
    "sg:address":"8119 Justin Ct",
    "sg:city":"Tinley Park",
    "sg:classifiers":[
        {
            "category":"Arts & Performance",
            "subcategory":"Theater",
            "type":"Entertainment"
        }
    ],
    "sg:phone":"+1 708 429 9873",
    "sg:postcode":"60477",
    "sg:province":"IL",
    "sg:tags":[
        "a",
        "as",
        "jockey",
        "disc",
        "operates"
    ],
    "wof:name":"Dynamic Sounds",
    "wof:placetype":"venue"
},
  "geometry": {"coordinates":[-87.817778,41.596638],"type":"Point"}
}