{
  "type": "Feature",
  "properties": {
    "iso:country":"US",
    "sg:address":"6075 E State St",
    "sg:city":"Rockford",
    "sg:classifiers":[
        {
            "category":"Shopping",
            "subcategory":"Computers & Home Electronics",
            "type":"Retail Goods"
        }
    ],
    "sg:phone":"+1 815 397 6475",
    "sg:postcode":"61108",
    "sg:province":"IL",
    "sg:tags":[
        "game",
        "video"
    ],
    "wof:name":"Game Stop Corp",
    "wof:placetype":"venue"
},
  "geometry": {"coordinates":[-88.996925,42.266913],"type":"Point"}
}