{
  "type": "Feature",
  "properties": {
    "addr:full":"319 N Western Avenue Chicago IL 60612",
    "addr:housenumber":"319",
    "addr:postcode":"60612",
    "addr:street":"N Western Avenue",
    "iso:country":"US",
    "sg:address":"319 N Western Avenue",
    "sg:city":"Chicago",
    "sg:classifiers":[
        {
            "category":"Retail",
            "subcategory":"Portrait Studio",
            "type":"Services"
        },
        {
            "category":"Professional",
            "subcategory":"Art Services",
            "type":"Services"
        }
    ],
    "sg:phone":"+1 312 733 8901",
    "sg:postcode":"60612",
    "sg:province":"IL",
    "sg:tags":[
        "photographer",
        "photography",
        "store"
    ],
    "sg:website":"www.rubinic.com",
    "wof:name":"Rubinic Photography",
    "wof:placetype":"venue"
},
  "geometry": {"coordinates":[-87.686694,41.887046],"type":"Point"}
}