{
  "type": "Feature",
  "properties": {
    "addr:full":"1300 Locke Dr Bradley IL 60914",
    "addr:housenumber":"1300",
    "addr:postcode":"60914",
    "addr:street":"Locke Dr",
    "iso:country":"US",
    "sg:address":"1300 Locke Dr",
    "sg:city":"Bradley",
    "sg:classifiers":[
        {
            "category":"Food & Beverages",
            "subcategory":"Groceries & Convenience Stores",
            "type":"Retail Goods"
        }
    ],
    "sg:phone":"+1 815 000 1111",
    "sg:postcode":"60914",
    "sg:province":"IL",
    "sg:tags":[
        "grocer"
    ],
    "wof:name":"Aldi",
    "wof:placetype":"venue"
},
  "geometry": {"coordinates":[-87.84898200000001,41.162684],"type":"Point"}
}