{
  "type": "Feature",
  "properties": {
    "iso:country":"US",
    "sg:address":"1443 Webster Ln",
    "sg:city":"Des Plaines",
    "sg:classifiers":[
        {
            "category":"Wholesale",
            "subcategory":"Toys & Hobbies",
            "type":"Manufacturing & Wholesale Goods"
        }
    ],
    "sg:phone":"+1 847 759 9555",
    "sg:postcode":"60018",
    "sg:province":"IL",
    "sg:tags":[
        "game",
        "supply"
    ],
    "wof:name":"Coda International Tel Fax",
    "wof:placetype":"venue"
},
  "geometry": {"coordinates":[-87.900452,42.026967],"type":"Point"}
}