{
  "type": "Feature",
  "properties": {
    "addr:full":"635 Cooper Ct Schaumburg IL 60173",
    "addr:housenumber":"635",
    "addr:postcode":"60173",
    "addr:street":"Cooper Ct",
    "iso:country":"US",
    "sg:address":"635 Cooper Ct",
    "sg:city":"Schaumburg",
    "sg:classifiers":[
        {
            "category":"Retail",
            "subcategory":"Repair Shop",
            "type":"Services"
        }
    ],
    "sg:phone":"+1 847 882 0060",
    "sg:postcode":"60173",
    "sg:province":"IL",
    "sg:tags":[
        "upholsterer"
    ],
    "wof:name":"Ackerman S Refinishing & Uphl",
    "wof:placetype":"venue"
},
  "geometry": {"coordinates":[-88.06461,42.054409],"type":"Point"}
}