{
  "type": "Feature",
  "properties": {
    "iso:country":"US",
    "sg:address":"203 W Roosevelt Rd",
    "sg:city":"Wheaton",
    "sg:classifiers":[
        {
            "category":"Personal",
            "type":"Services"
        },
        {
            "category":"Recreation",
            "type":"Entertainment"
        }
    ],
    "sg:phone":"+1 630 690 3001",
    "sg:postcode":"60187",
    "sg:province":"IL",
    "sg:tags":[
        "party",
        "planning",
        "entertainers-family",
        "event",
        "business"
    ],
    "wof:name":"Chicago Fun Events",
    "wof:placetype":"venue"
},
  "geometry": {"coordinates":[-88.10812900000001,41.85873],"type":"Point"}
}