{
  "type": "Feature",
  "properties": {
    "addr:full":"7979 Forest Hills Rd Loves Park IL 61111",
    "addr:housenumber":"7979",
    "addr:postcode":"61111",
    "addr:street":"Forest Hills Rd",
    "iso:country":"US",
    "sg:address":"7979 Forest Hills Rd",
    "sg:city":"Loves Park",
    "sg:classifiers":[
        {
            "category":"Manufacturing",
            "subcategory":"Metals",
            "type":"Manufacturing & Wholesale Goods"
        }
    ],
    "sg:phone":"+1 815 654 8498",
    "sg:postcode":"61111",
    "sg:province":"IL",
    "sg:tags":[
        "blast",
        "mfg",
        "tool",
        "accessory",
        "machine",
        "works",
        "furnace"
    ],
    "wof:name":"Raetech Manufacturing",
    "wof:placetype":"venue"
},
  "geometry": {"coordinates":[-89.018524,42.33779],"type":"Point"}
}