{
  "type": "Feature",
  "properties": {
    "iso:country":"US",
    "sg:address":"10437 S Western Ave",
    "sg:city":"Chicago",
    "sg:classifiers":[
        {
            "category":"Restaurant",
            "type":"Food & Drink"
        }
    ],
    "sg:phone":"+1   ",
    "sg:postcode":"60643",
    "sg:province":"IL",
    "sg:tags":[
        "eating"
    ],
    "wof:name":"KFC",
    "wof:placetype":"venue"
},
  "geometry": {"coordinates":[-87.68144700000001,41.703403],"type":"Point"}
}