{
  "type": "Feature",
  "properties": {
    "iso:country":"US",
    "sg:address":"141 W Main St",
    "sg:city":"Williamsville",
    "sg:classifiers":[
        {
            "category":"Government",
            "subcategory":"Office",
            "type":"Public Place"
        }
    ],
    "sg:phone":"+1   ",
    "sg:postcode":"62693",
    "sg:province":"IL",
    "sg:tags":[
        "township"
    ],
    "wof:name":"Township of Williams",
    "wof:placetype":"venue"
},
  "geometry": {"coordinates":[-89.549083,39.95427],"type":"Point"}
}