{
  "type": "Feature",
  "properties": {
    "iso:country":"US",
    "sg:address":"102 W 2nd St",
    "sg:city":"Rock Falls",
    "sg:classifiers":[
        {
            "category":"Shopping",
            "subcategory":"Clothing, Apparel, & Fashions",
            "type":"Retail Goods"
        }
    ],
    "sg:phone":"+1 815 625 8804",
    "sg:postcode":"61071",
    "sg:province":"IL",
    "wof:name":"Innovations",
    "wof:placetype":"venue"
},
  "geometry": {"coordinates":[-89.691756,41.782207],"type":"Point"}
}