{
  "type": "Feature",
  "properties": {
    "addr:full":"1145 W Diversey Pkwy Chicago IL 60614",
    "addr:housenumber":"1145",
    "addr:postcode":"60614",
    "addr:street":"W Diversey Pkwy",
    "iso:country":"US",
    "sg:address":"1145 W Diversey Pkwy",
    "sg:city":"Chicago",
    "sg:classifiers":[
        {
            "category":"Health Services",
            "subcategory":"Doctor",
            "type":"Services"
        }
    ],
    "sg:phone":"+1 773 880 1460",
    "sg:postcode":"60614",
    "sg:province":"IL",
    "wof:name":"Ncchc",
    "wof:placetype":"venue"
},
  "geometry": {"coordinates":[-87.657462,41.932472],"type":"Point"}
}