{
  "type": "Feature",
  "properties": {
    "iso:country":"US",
    "sg:address":"1621 Carboy Rd",
    "sg:city":"Arlington Hts",
    "sg:classifiers":[
        {
            "category":"Wholesale",
            "subcategory":"Electrical",
            "type":"Manufacturing & Wholesale Goods"
        }
    ],
    "sg:phone":"+1 847 364 1100",
    "sg:postcode":"60005",
    "sg:province":"IL",
    "sg:tags":[
        "sound",
        "equipment",
        "system"
    ],
    "sg:website":"www.dbsound.com",
    "wof:name":"D B Sound LP",
    "wof:placetype":"venue"
},
  "geometry": {"coordinates":[-87.945252,42.02709],"type":"Point"}
}