{
  "type": "Feature",
  "properties": {
    "addr:full":"2410 Des Plaines River Rd Des Plaines IL 60018",
    "addr:housenumber":"2410",
    "addr:postcode":"60018",
    "addr:street":"Des Plaines River Rd Des",
    "iso:country":"US",
    "sg:address":"2410 Des Plaines River Rd",
    "sg:city":"Des Plaines",
    "sg:classifiers":[
        {
            "category":"Professional",
            "subcategory":"Advertising",
            "type":"Services"
        }
    ],
    "sg:phone":"+1 847 827 7700",
    "sg:postcode":"60018",
    "sg:province":"IL",
    "sg:tags":[
        "mail",
        "direct"
    ],
    "wof:name":"Higgins Mailing Service",
    "wof:placetype":"venue"
},
  "geometry": {"coordinates":[-87.869378,42.009698],"type":"Point"}
}