{
  "type": "Feature",
  "properties": {
    "addr:full":"9020 Parkside Ave Oak Lawn IL 60453",
    "addr:housenumber":"9020",
    "addr:postcode":"60453",
    "addr:street":"Parkside Ave",
    "iso:country":"US",
    "sg:address":"9020 Parkside Ave",
    "sg:city":"Oak Lawn",
    "sg:classifiers":[
        {
            "category":"Building & Trades",
            "subcategory":"Cleaning & Sanitation",
            "type":"Services"
        }
    ],
    "sg:phone":"+1 708 422 0064",
    "sg:postcode":"60453",
    "sg:province":"IL",
    "sg:tags":[
        "maintenance"
    ],
    "wof:name":"Orland Window Cleaning",
    "wof:placetype":"venue"
},
  "geometry": {"coordinates":[-87.761861,41.727372],"type":"Point"}
}