{
  "type": "Feature",
  "properties": {
    "iso:country":"US",
    "sg:address":"750 W Rte 173",
    "sg:city":"Antioch",
    "sg:classifiers":[
        {
            "category":"Recreation",
            "subcategory":"Dance Hall",
            "type":"Entertainment"
        }
    ],
    "sg:postcode":"60002",
    "sg:province":"IL",
    "sg:tags":[
        "club"
    ],
    "sg:website":"www.myspace.com/onyxnightclub",
    "wof:name":"Onyx Night Club",
    "wof:placetype":"venue"
},
  "geometry": {"coordinates":[-88.111814,42.478106],"type":"Point"}
}