{
  "type": "Feature",
  "properties": {
    "addr:full":"State 773 1229 W Belmont Chicago IL 60657",
    "addr:housenumber":"1229",
    "addr:postcode":"60657",
    "addr:street":"W Belmont",
    "iso:country":"US",
    "sg:address":"State 773 1229 W Belmont",
    "sg:city":"Chicago",
    "sg:classifiers":[
        {
            "category":"Arts & Performance",
            "subcategory":"Arts Center",
            "type":"Entertainment"
        }
    ],
    "sg:phone":"+1 773 888 1228",
    "sg:postcode":"60657",
    "sg:province":"IL",
    "sg:tags":[
        "performing"
    ],
    "sg:website":"www.fightjamchicago.com/home",
    "wof:name":"Fight Jam",
    "wof:placetype":"venue"
},
  "geometry": {"coordinates":[-87.660247,41.939747],"type":"Point"}
}