{
  "type": "Feature",
  "properties": {
    "iso:country":"US",
    "sg:address":"660 W Randolph St",
    "sg:city":"Chicago",
    "sg:classifiers":[
        {
            "category":"Professional",
            "subcategory":"Advertising",
            "type":"Services"
        }
    ],
    "sg:phone":"+1 312 474 1100",
    "sg:postcode":"60661",
    "sg:province":"IL",
    "sg:tags":[
        "designer",
        "sheet",
        "producer",
        "work",
        "metal",
        "display"
    ],
    "sg:website":"www.decorcable.com",
    "wof:name":"Decorcable Innovations",
    "wof:placetype":"venue"
},
  "geometry": {"coordinates":[-87.64461799999999,41.884424],"type":"Point"}
}