{
  "type": "Feature",
  "properties": {
    "iso:country":"US",
    "sg:address":"1209 Shappert Dr",
    "sg:city":"Machesney Park",
    "sg:classifiers":[
        {
            "category":"Retail",
            "subcategory":"Repair Shop",
            "type":"Services"
        }
    ],
    "sg:phone":"+1 815 877 5623",
    "sg:postcode":"61115",
    "sg:province":"IL",
    "sg:tags":[
        "job"
    ],
    "wof:name":"H & M Machining Inc",
    "wof:placetype":"venue"
},
  "geometry": {"coordinates":[-89.02968199999999,42.373882],"type":"Point"}
}