{
  "type": "Feature",
  "properties": {
    "addr:full":"1431 W Glenlake Ave Chicago IL 60660",
    "addr:housenumber":"1431",
    "addr:postcode":"60660",
    "addr:street":"W Glenlake Ave",
    "iso:country":"US",
    "sg:address":"1431 W Glenlake Ave",
    "sg:city":"Chicago",
    "sg:classifiers":[
        {
            "category":"Arts & Performance",
            "subcategory":"Theater",
            "type":"Entertainment"
        }
    ],
    "sg:phone":"+1 773 743 2121",
    "sg:postcode":"60660",
    "sg:province":"IL",
    "sg:tags":[
        "group"
    ],
    "wof:name":"Cathy Ford Ltd",
    "wof:placetype":"venue"
},
  "geometry": {"coordinates":[-87.666979,41.992568],"type":"Point"}
}