{
  "type": "Feature",
  "properties": {
    "iso:country":"US",
    "sg:address":"1281 Longford Cir",
    "sg:city":"Elgin",
    "sg:classifiers":[
        {
            "category":"Building & Trades",
            "subcategory":"Cleaning & Sanitation",
            "type":"Services"
        }
    ],
    "sg:phone":"+1 847 697 2241",
    "sg:postcode":"60120",
    "sg:province":"IL",
    "sg:tags":[
        "maintenance"
    ],
    "wof:name":"Lance L Oines",
    "wof:placetype":"venue"
},
  "geometry": {"coordinates":[-88.243421,42.036506],"type":"Point"}
}