{
  "type": "Feature",
  "properties": {
    "iso:country":"US",
    "sg:address":"6537 N Washtenaw Ave",
    "sg:city":"Chicago",
    "sg:classifiers":[
        {
            "category":"Building & Trades",
            "subcategory":"Construction",
            "type":"Services"
        }
    ],
    "sg:phone":"+1 773 764 7590",
    "sg:postcode":"60645",
    "sg:province":"IL",
    "sg:tags":[
        "hanging",
        "contractor"
    ],
    "wof:name":"Galou Painting & Decorating",
    "wof:placetype":"venue"
},
  "geometry": {"coordinates":[-87.697208,42.000574],"type":"Point"}
}