{
  "type": "Feature",
  "properties": {
    "iso:country":"US",
    "sg:address":"5456 N Damen",
    "sg:city":"Chicago",
    "sg:classifiers":[
        {
            "category":"Retail",
            "subcategory":"Animal Services",
            "type":"Services"
        }
    ],
    "sg:phone":"+1 773 271 5577",
    "sg:postcode":"60640",
    "sg:province":"IL",
    "sg:tags":[
        "pet"
    ],
    "sg:website":"adogslifechicago.intuitwebsites....",
    "wof:name":"A Dog's Life on Damen",
    "wof:placetype":"venue"
},
  "geometry": {"coordinates":[-87.679704,41.981232],"type":"Point"}
}