{
  "type": "Feature",
  "properties": {
    "addr:full":"171 N Wabash Ave Chicago IL 60601",
    "addr:housenumber":"171",
    "addr:postcode":"60601",
    "addr:street":"N Wabash Ave",
    "iso:country":"US",
    "sg:address":"171 N Wabash Ave",
    "sg:city":"Chicago",
    "sg:phone":"+1 312 242 1035",
    "sg:postcode":"60601",
    "sg:province":"IL",
    "wof:name":"System Parking 296",
    "wof:placetype":"venue"
},
  "geometry": {"coordinates":[-87.626242,41.88506],"type":"Point"}
}