{
  "type": "Feature",
  "properties": {
    "iso:country":"US",
    "sg:address":"4828 W Medill Avenue",
    "sg:city":"Chicago",
    "sg:classifiers":[
        {
            "category":"Building & Trades",
            "subcategory":"Construction",
            "type":"Services"
        }
    ],
    "sg:phone":"+1 773 637 7452",
    "sg:postcode":"60639",
    "sg:province":"IL",
    "sg:tags":[
        "handyman"
    ],
    "wof:name":"Best For Less Handyman",
    "wof:placetype":"venue"
},
  "geometry": {"coordinates":[-87.74723299999999,41.923355],"type":"Point"}
}