{
  "type": "Feature",
  "properties": {
    "iso:country":"US",
    "sg:address":"8904 S Harlem Ave",
    "sg:city":"Bridgeview",
    "sg:classifiers":[
        {
            "category":"Shopping",
            "subcategory":"Stationery & Office Supplies",
            "type":"Retail Goods"
        },
        {
            "category":"Wholesale",
            "subcategory":"Office Equipment",
            "type":"Manufacturing & Wholesale Goods"
        }
    ],
    "sg:phone":"+1 708 237 0707",
    "sg:postcode":"60455",
    "sg:province":"IL",
    "sg:tags":[
        "equipment-installation",
        "furniture"
    ],
    "wof:name":"Systex Inc",
    "wof:placetype":"venue"
},
  "geometry": {"coordinates":[-87.798897,41.729401],"type":"Point"}
}