{
  "type": "Feature",
  "properties": {
    "iso:country":"US",
    "sg:address":"208 W Davie St",
    "sg:city":"Anna",
    "sg:classifiers":[
        {
            "category":"Autos & Motor Vehicles",
            "subcategory":"Auto Supplies",
            "type":"Retail Goods"
        }
    ],
    "sg:phone":"+1 618 833 6272",
    "sg:postcode":"62906",
    "sg:province":"IL",
    "sg:tags":[
        "automobile",
        "parts"
    ],
    "wof:name":"Auto Tire & Parts Co",
    "wof:placetype":"venue"
},
  "geometry": {"coordinates":[-89.250671,37.461483],"type":"Point"}
}