{
  "type": "Feature",
  "properties": {
    "addr:full":"1908 Airport Rd Urbana IL 61802",
    "addr:housenumber":"1908",
    "addr:postcode":"61802",
    "addr:street":"Airport Rd",
    "iso:country":"US",
    "sg:address":"1908 Airport Rd",
    "sg:city":"Urbana",
    "sg:classifiers":[
        {
            "category":"Building & Trades",
            "subcategory":"Construction",
            "type":"Services"
        }
    ],
    "sg:phone":"+1 217 344 1648",
    "sg:postcode":"61802",
    "sg:province":"IL",
    "sg:tags":[
        "drywall",
        "contractor"
    ],
    "wof:name":"Victor Treat & Sons Inc",
    "wof:placetype":"venue"
},
  "geometry": {"coordinates":[-88.183717,40.142125],"type":"Point"}
}