{
  "type": "Feature",
  "properties": {
    "iso:country":"US",
    "sg:address":"1195 Gavin Ct",
    "sg:city":"Lake Forest",
    "sg:classifiers":[
        {
            "category":"Building & Trades",
            "subcategory":"Construction",
            "type":"Services"
        }
    ],
    "sg:phone":"+1 847 615 8780",
    "sg:postcode":"60045",
    "sg:province":"IL",
    "sg:tags":[
        "home",
        "builder"
    ],
    "wof:name":"JOS Development Co-America",
    "wof:placetype":"venue"
},
  "geometry": {"coordinates":[-87.876636,42.230561],"type":"Point"}
}