{
  "type": "Feature",
  "properties": {
    "addr:full":"101 Asbury Ave Evanston IL 60202",
    "addr:housenumber":"101",
    "addr:postcode":"60202",
    "addr:street":"Asbury Ave",
    "iso:country":"US",
    "sg:address":"101 Asbury Ave",
    "sg:city":"Evanston",
    "sg:classifiers":[
        {
            "category":"Banks & Credit Unions",
            "subcategory":"Bank",
            "type":"Services"
        }
    ],
    "sg:phone":"+1 847 864 6223",
    "sg:postcode":"60202",
    "sg:province":"IL",
    "wof:name":"ABNAMROCVS",
    "wof:placetype":"venue"
},
  "geometry": {"coordinates":[-87.690084,42.020169],"type":"Point"}
}