{
  "type": "Feature",
  "properties": {
    "iso:country":"US",
    "sg:address":"5365 W State Rte 17",
    "sg:city":"Kankakee",
    "sg:classifiers":[
        {
            "category":"Manufacturing",
            "subcategory":"Wood Products",
            "type":"Manufacturing & Wholesale Goods"
        }
    ],
    "sg:phone":"+1 815 937 0610",
    "sg:postcode":"60901",
    "sg:province":"IL",
    "sg:tags":[
        "pallet",
        "skid",
        "mfg"
    ],
    "wof:name":"L M Pallets Plus Inc",
    "wof:placetype":"venue"
},
  "geometry": {"coordinates":[-87.972624,41.118316],"type":"Point"}
}