{
  "type": "Feature",
  "properties": {
    "iso:country":"US",
    "sg:address":"16139 E 1485th Ave",
    "sg:city":"Teutopolis",
    "sg:phone":"+1 217 857 6264",
    "sg:postcode":"62467",
    "sg:province":"IL",
    "sg:tags":[
        "farm",
        "corn"
    ],
    "wof:name":"Randy Koester",
    "wof:placetype":"venue"
},
  "geometry": {"coordinates":[-88.50294,39.131699],"type":"Point"}
}