{
  "type": "Feature",
  "properties": {
    "addr:full":"210 35th St Moline IL 61265",
    "addr:housenumber":"210",
    "addr:postcode":"61265",
    "addr:street":"35Th St",
    "iso:country":"US",
    "sg:address":"210 35th St",
    "sg:city":"Moline",
    "sg:classifiers":[
        {
            "category":"Government",
            "subcategory":"Office",
            "type":"Public Place"
        }
    ],
    "sg:phone":"+1 309 797 0741",
    "sg:postcode":"61265",
    "sg:province":"IL",
    "sg:tags":[
        "village"
    ],
    "wof:name":"Moline Animal Control & Shltr",
    "wof:placetype":"venue"
},
  "geometry": {"coordinates":[-90.48793999999999,41.511441],"type":"Point"}
}