{
  "type": "Feature",
  "properties": {
    "iso:country":"US",
    "sg:address":"9205 Lebanon Rd",
    "sg:city":"Belleville",
    "sg:classifiers":[
        {
            "category":"Social Services",
            "subcategory":"Child Care",
            "type":"Services"
        }
    ],
    "sg:phone":"+1 618 397 5075",
    "sg:postcode":"62223",
    "sg:province":"IL",
    "wof:name":"Rosie Granberry",
    "wof:placetype":"venue"
},
  "geometry": {"coordinates":[-90.05238300000001,38.587692],"type":"Point"}
}