{
  "type": "Feature",
  "properties": {
    "iso:country":"US",
    "sg:address":"1538 W 103rd St",
    "sg:city":"Chicago",
    "sg:classifiers":[
        {
            "category":"Building & Trades",
            "subcategory":"Cleaning & Sanitation",
            "type":"Services"
        }
    ],
    "sg:phone":"+1 773 239 7526",
    "sg:postcode":"60643",
    "sg:province":"IL",
    "sg:tags":[
        "maintenance"
    ],
    "wof:name":"Mack Janitor Service",
    "wof:placetype":"venue"
},
  "geometry": {"coordinates":[-87.660409,41.706795],"type":"Point"}
}