{
  "type": "Feature",
  "properties": {
    "iso:country":"US",
    "sg:address":"2457 Crystal Creek Ln",
    "sg:city":"Elgin",
    "sg:classifiers":[
        {
            "category":"Shopping",
            "subcategory":"Bicycles & Sporting Goods",
            "type":"Retail Goods"
        }
    ],
    "sg:phone":"+1   ",
    "sg:postcode":"60124",
    "sg:province":"IL",
    "wof:name":"Rk Sports",
    "wof:placetype":"venue"
},
  "geometry": {"coordinates":[-88.250774,42.062485],"type":"Point"}
}