{
  "type": "Feature",
  "properties": {
    "addr:full":"9524 Franklin Ave Franklin Park IL 60131",
    "addr:housenumber":"9524",
    "addr:postcode":"60131",
    "addr:street":"Franklin Ave",
    "iso:country":"US",
    "sg:address":"9524 Franklin Ave",
    "sg:city":"Franklin Park",
    "sg:classifiers":[
        {
            "category":"Professional",
            "subcategory":"Computer Services",
            "type":"Services"
        }
    ],
    "sg:phone":"+1 847 288 9820",
    "sg:postcode":"60131",
    "sg:province":"IL",
    "sg:tags":[
        "consulting"
    ],
    "wof:name":"Kollar Consulting Services",
    "wof:placetype":"venue"
},
  "geometry": {"coordinates":[-87.86351000000001,41.934759],"type":"Point"}
}