{
  "type": "Feature",
  "properties": {
    "addr:full":"4437 N Harlem Ave Norridge IL 60706",
    "addr:housenumber":"4437",
    "addr:postcode":"60706",
    "addr:street":"N Harlem Ave",
    "iso:country":"US",
    "sg:address":"4437 N Harlem Ave",
    "sg:city":"Norridge",
    "sg:classifiers":[
        {
            "category":"Banks & Credit Unions",
            "subcategory":"Financial Services",
            "type":"Services"
        }
    ],
    "sg:phone":"+1 708 867 6900",
    "sg:postcode":"60706",
    "sg:province":"IL",
    "wof:name":"Chicago Payday Loans",
    "wof:placetype":"venue"
},
  "geometry": {"coordinates":[-87.80673299999999,41.962062],"type":"Point"}
}