{
  "type": "Feature",
  "properties": {
    "addr:full":"41945 Tammi Ter Antioch IL 60002",
    "addr:postcode":"41945;60002",
    "addr:street":"Tammi Ter",
    "iso:country":"US",
    "sg:address":"41945 Tammi Ter",
    "sg:city":"Antioch",
    "sg:classifiers":[
        {
            "category":"Retail",
            "subcategory":"Portrait Studio",
            "type":"Services"
        },
        {
            "category":"Professional",
            "subcategory":"Art Services",
            "type":"Services"
        }
    ],
    "sg:phone":"+1 847 838 2304",
    "sg:postcode":"60002",
    "sg:province":"IL",
    "sg:tags":[
        "photographer",
        "photo"
    ],
    "wof:name":"Cleaver Photography Inc",
    "wof:placetype":"venue"
},
  "geometry": {"coordinates":[-88.021316,42.470922],"type":"Point"}
}