{
  "type": "Feature",
  "properties": {
    "iso:country":"US",
    "sg:address":"4444 Brendenwood Rd",
    "sg:city":"Rockford",
    "sg:classifiers":[
        {
            "category":"Real Estate",
            "subcategory":"Real Estate Operator",
            "type":"Services"
        }
    ],
    "sg:phone":"+1 815 399 9595",
    "sg:postcode":"61107",
    "sg:province":"IL",
    "sg:tags":[
        "property",
        "lessor"
    ],
    "wof:name":"Vera Campion Farm",
    "wof:placetype":"venue"
},
  "geometry": {"coordinates":[-89.02951899999999,42.280722],"type":"Point"}
}