{
  "type": "Feature",
  "properties": {
    "iso:country":"US",
    "sg:address":"201 S Ashland",
    "sg:city":"Chicago",
    "sg:classifiers":[
        {
            "category":"Arts & Performance",
            "subcategory":"Music",
            "type":"Entertainment"
        },
        {
            "category":"Organizations",
            "subcategory":"Religious Organization",
            "type":"Services"
        }
    ],
    "sg:phone":"+1 312 243 4242",
    "sg:postcode":"60607",
    "sg:province":"IL",
    "sg:tags":[
        "venue"
    ],
    "wof:name":"Epiphany",
    "wof:placetype":"venue"
},
  "geometry": {"coordinates":[-87.666212,41.878543],"type":"Point"}
}