{
  "type": "Feature",
  "properties": {
    "iso:country":"US",
    "sg:address":"2001 Noyes St",
    "sg:city":"Evanston",
    "sg:classifiers":[
        {
            "category":"Shopping",
            "subcategory":"Clothing, Apparel, & Fashions",
            "type":"Retail Goods"
        }
    ],
    "sg:phone":"+1   ",
    "sg:postcode":"60201",
    "sg:province":"IL",
    "wof:name":"Intimate Landscapes",
    "wof:placetype":"venue"
},
  "geometry": {"coordinates":[-87.701949,42.058127],"type":"Point"}
}