{
  "type": "Feature",
  "properties": {
    "iso:country":"US",
    "sg:address":"16902 E 700th St",
    "sg:city":"Osco",
    "sg:classifiers":[
        {
            "category":"Retail",
            "subcategory":"Repair Shop",
            "type":"Services"
        }
    ],
    "sg:phone":"+1 309 522 5549",
    "sg:postcode":"61274",
    "sg:province":"IL",
    "sg:tags":[
        "farm",
        "equipment",
        "parts"
    ],
    "wof:name":"Miller Farm Repair",
    "wof:placetype":"venue"
},
  "geometry": {"coordinates":[-90.29888200000001,41.389422],"type":"Point"}
}