{
  "type": "Feature",
  "properties": {
    "iso:country":"US",
    "sg:address":"1551 N Wells",
    "sg:city":"Chicago",
    "sg:classifiers":[
        {
            "category":"Personal",
            "type":"Services"
        }
    ],
    "sg:phone":"+1 312 573 9700",
    "sg:postcode":"60610",
    "sg:province":"IL",
    "sg:tags":[
        "home",
        "local"
    ],
    "sg:website":"www.bizybizy.net",
    "wof:name":"BizyBizy LLC",
    "wof:placetype":"venue"
},
  "geometry": {"coordinates":[-87.63467799999999,41.910674],"type":"Point"}
}