{
  "type": "Feature",
  "properties": {
    "iso:country":"US",
    "sg:address":"15700 Central Ave",
    "sg:city":"Oak Forest",
    "sg:classifiers":[
        {
            "category":"Social Services",
            "subcategory":"Child Care",
            "type":"Services"
        },
        {
            "category":"Education",
            "subcategory":"Preschool",
            "type":"Public Place"
        },
        {
            "category":"Education",
            "subcategory":"School",
            "type":"Public Place"
        }
    ],
    "sg:phone":"+1 708 535 2233",
    "sg:postcode":"60452",
    "sg:province":"IL",
    "sg:tags":[
        "elementary",
        "day"
    ],
    "sg:website":"www.kindercare.com",
    "wof:name":"Kindercare Learning Centers",
    "wof:placetype":"venue"
},
  "geometry": {"coordinates":[-87.756688,41.606067],"type":"Point"}
}