{
  "type": "Feature",
  "properties": {
    "iso:country":"US",
    "sg:address":"320 Railroad Ave",
    "sg:city":"Charleston",
    "sg:classifiers":[
        {
            "category":"Wholesale",
            "subcategory":"Machinery & Supplies",
            "type":"Manufacturing & Wholesale Goods"
        }
    ],
    "sg:phone":"+1 217 345 3777",
    "sg:postcode":"61920",
    "sg:province":"IL",
    "sg:tags":[
        "equipment",
        "welding"
    ],
    "sg:website":"www.ganowelding.com",
    "wof:name":"Gano Welding Supplies",
    "wof:placetype":"venue"
},
  "geometry": {"coordinates":[-88.178979,39.498828],"type":"Point"}
}