{
  "type": "Feature",
  "properties": {
    "iso:country":"US",
    "sg:address":"717 N Wildwood Ave",
    "sg:city":"Kankakee",
    "sg:classifiers":[
        {
            "category":"Organizations",
            "subcategory":"Religious Organization",
            "type":"Services"
        }
    ],
    "sg:phone":"+1 815 932 0538",
    "sg:postcode":"60901",
    "sg:province":"IL",
    "sg:website":"www.secondbaptistchurch.com",
    "wof:name":"Second Baptist Church",
    "wof:placetype":"venue"
},
  "geometry": {"coordinates":[-87.852498,41.128032],"type":"Point"}
}