{
  "type": "Feature",
  "properties": {
    "iso:country":"US",
    "sg:address":"N Waukegan Rd",
    "sg:city":"Niles",
    "sg:classifiers":[
        {
            "category":"Restaurant",
            "type":"Food & Drink"
        }
    ],
    "sg:menulink":"http://www.allmenus.com/il/niles/224600-palace-restaurant/menu/",
    "sg:phone":"+1 847 966 2231",
    "sg:postcode":"60714",
    "sg:province":"IL",
    "sg:tags":[
        "asian",
        "chinese"
    ],
    "wof:name":"Palace Restaurant",
    "wof:placetype":"venue"
},
  "geometry": {"coordinates":[-87.80272100000001,42.023255],"type":"Point"}
}