{
  "type": "Feature",
  "properties": {
    "iso:country":"US",
    "sg:address":"651 S Roselle Rd",
    "sg:city":"Schaumburg",
    "sg:classifiers":[
        {
            "category":"Building & Trades",
            "subcategory":"Plumbing",
            "type":"Services"
        }
    ],
    "sg:phone":"+1 847 352 0528",
    "sg:postcode":"60193",
    "sg:province":"IL",
    "sg:tags":[
        "conditioning",
        "air",
        "system",
        "contractor"
    ],
    "wof:name":"Belimo Air Control",
    "wof:placetype":"venue"
},
  "geometry": {"coordinates":[-88.079923,42.016215],"type":"Point"}
}