{
  "type": "Feature",
  "properties": {
    "iso:country":"US",
    "sg:address":"1280 E Dundee Rd",
    "sg:city":"Palatine",
    "sg:classifiers":[
        {
            "category":"Wholesale",
            "subcategory":"Machinery & Supplies",
            "type":"Manufacturing & Wholesale Goods"
        }
    ],
    "sg:phone":"+1 708 430 1280",
    "sg:postcode":"60074",
    "sg:province":"IL",
    "sg:tags":[
        "equipment",
        "industrial"
    ],
    "wof:name":"Woodcraft Supply Corp",
    "wof:placetype":"venue"
},
  "geometry": {"coordinates":[-88.013554,42.139214],"type":"Point"}
}