{
  "type": "Feature",
  "properties": {
    "iso:country":"US",
    "sg:address":"509 E McAllister St",
    "sg:city":"Lebanon",
    "sg:classifiers":[
        {
            "category":"Retail",
            "subcategory":"Auto Repair",
            "type":"Services"
        }
    ],
    "sg:phone":"+1 618 537 9525",
    "sg:postcode":"62254",
    "sg:province":"IL",
    "sg:tags":[
        "repairing",
        "automobile",
        "general"
    ],
    "wof:name":"Buhl's Auto Repair",
    "wof:placetype":"venue"
},
  "geometry": {"coordinates":[-89.800997,38.595016],"type":"Point"}
}