{
  "type": "Feature",
  "properties": {
    "iso:country":"US",
    "sg:address":"416 Charles Dr",
    "sg:city":"Elk Grove Village",
    "sg:classifiers":[
        {
            "category":"Wholesale",
            "subcategory":"Non-durable Goods",
            "type":"Manufacturing & Wholesale Goods"
        }
    ],
    "sg:phone":"+1 847 472 9077",
    "sg:postcode":"60007",
    "sg:province":"IL",
    "sg:tags":[
        "merchandise",
        "general"
    ],
    "wof:name":"Alexander Great Inc",
    "wof:placetype":"venue"
},
  "geometry": {"coordinates":[-88.00774,42.012983],"type":"Point"}
}