{
  "type": "Feature",
  "properties": {
    "iso:country":"US",
    "sg:address":"6141 W 95th St",
    "sg:city":"Oak Lawn",
    "sg:classifiers":[
        {
            "category":"Banks & Credit Unions",
            "subcategory":"Bank",
            "type":"Services"
        }
    ],
    "sg:phone":"+1 708 424 8002",
    "sg:postcode":"60453",
    "sg:province":"IL",
    "sg:tags":[
        "mortgage",
        "loan",
        "broker",
        "real estate"
    ],
    "sg:website":"www.crownmortgageco.com",
    "wof:name":"Crown Mortgage Company",
    "wof:placetype":"venue"
},
  "geometry": {"coordinates":[-87.77419999999999,41.719501],"type":"Point"}
}