{
  "type": "Feature",
  "properties": {
    "addr:full":"5000 S Central Ave Chicago IL 60638",
    "addr:housenumber":"5000",
    "addr:postcode":"60638",
    "addr:street":"S Central Ave",
    "iso:country":"US",
    "sg:address":"5000 S Central Ave",
    "sg:city":"Chicago",
    "sg:classifiers":[
        {
            "category":"Food & Beverages",
            "subcategory":"Groceries & Convenience Stores",
            "type":"Retail Goods"
        }
    ],
    "sg:phone":"+1 708 563 0100",
    "sg:postcode":"60638",
    "sg:province":"IL",
    "wof:name":"Skip's Wholesale",
    "wof:placetype":"venue"
},
  "geometry": {"coordinates":[-87.763519,41.801201],"type":"Point"}
}