{
  "type": "Feature",
  "properties": {
    "iso:country":"US",
    "sg:address":"325 W Macarthur Dr",
    "sg:city":"Cottage Hills",
    "sg:classifiers":[
        {
            "category":"Wholesale",
            "subcategory":"Groceries",
            "type":"Manufacturing & Wholesale Goods"
        }
    ],
    "sg:phone":"+1 618 259 0879",
    "sg:postcode":"62018",
    "sg:province":"IL",
    "sg:tags":[
        "confectionery"
    ],
    "wof:name":"Fito Lay",
    "wof:placetype":"venue"
},
  "geometry": {"coordinates":[-90.074747,38.903674],"type":"Point"}
}