{
  "type": "Feature",
  "properties": {
    "addr:full":"350 Manor Ct Bolingbrook IL 60440",
    "addr:housenumber":"350",
    "addr:postcode":"60440",
    "addr:street":"Manor Ct",
    "iso:country":"US",
    "sg:address":"350 Manor Ct",
    "sg:city":"Bolingbrook",
    "sg:classifiers":[
        {
            "category":"Home & Garden",
            "subcategory":"Furniture",
            "type":"Retail Goods"
        }
    ],
    "sg:phone":"+1 630 783 1990",
    "sg:postcode":"60440",
    "sg:province":"IL",
    "sg:tags":[
        "equipment",
        "custom",
        "kitchen",
        "cabinet"
    ],
    "wof:name":"Cabinets 4 U Inc",
    "wof:placetype":"venue"
},
  "geometry": {"coordinates":[-88.06339699999999,41.688408],"type":"Point"}
}