{
  "type": "Feature",
  "properties": {
    "addr:full":"10424 S Pulaski Rd Oak Lawn IL 60453",
    "addr:housenumber":"10424",
    "addr:postcode":"60453",
    "addr:street":"S Pulaski Rd",
    "iso:country":"US",
    "sg:address":"10424 S Pulaski Rd",
    "sg:city":"Oak Lawn",
    "sg:classifiers":[
        {
            "category":"Arts & Performance",
            "subcategory":"Theater",
            "type":"Entertainment"
        }
    ],
    "sg:phone":"+1 708 373 1646",
    "sg:postcode":"60453",
    "sg:province":"IL",
    "sg:tags":[
        "management",
        "group"
    ],
    "wof:name":"Acting Services",
    "wof:placetype":"venue"
},
  "geometry": {"coordinates":[-87.72087999999999,41.703591],"type":"Point"}
}