{
  "type": "Feature",
  "properties": {
    "addr:full":"205 W Randolph St Ste 200 Chicago IL 60606",
    "addr:housenumber":"205",
    "addr:postcode":"60606",
    "addr:street":"W Randolph St Ste 200",
    "iso:country":"US",
    "sg:address":"205 W Randolph St Ste 200",
    "sg:city":"Chicago",
    "sg:classifiers":[
        {
            "category":"Education",
            "subcategory":"Vocational School",
            "type":"Public Place"
        }
    ],
    "sg:phone":"+1 312 606 8995",
    "sg:postcode":"60606",
    "sg:province":"IL",
    "sg:tags":[
        "business"
    ],
    "wof:name":"Perfect Access Crn",
    "wof:placetype":"venue"
},
  "geometry": {"coordinates":[-87.63396299999999,41.884449],"type":"Point"}
}