{
  "type": "Feature",
  "properties": {
    "iso:country":"US",
    "sg:address":"19715 Governors Hwy",
    "sg:city":"Flossmoor",
    "sg:classifiers":[
        {
            "category":"Health Services",
            "subcategory":"Nursing And Care Facility",
            "type":"Services"
        }
    ],
    "sg:phone":"+1 708 798 1600",
    "sg:postcode":"60422",
    "sg:province":"IL",
    "wof:name":"Flossmoor",
    "wof:placetype":"venue"
},
  "geometry": {"coordinates":[-87.696383,41.532151],"type":"Point"}
}