{
  "type": "Feature",
  "properties": {
    "iso:country":"US",
    "sg:address":"419 W American St",
    "sg:city":"Freeport",
    "sg:classifiers":[
        {
            "category":"Building & Trades",
            "subcategory":"Cleaning & Sanitation",
            "type":"Services"
        }
    ],
    "sg:phone":"+1 815 232 1915",
    "sg:postcode":"61032",
    "sg:province":"IL",
    "sg:tags":[
        "maintenance"
    ],
    "wof:name":"First Rate Cleaning",
    "wof:placetype":"venue"
},
  "geometry": {"coordinates":[-89.624024,42.28991],"type":"Point"}
}