{
  "type": "Feature",
  "properties": {
    "iso:country":"US",
    "sg:address":"1339 W 97th St",
    "sg:city":"Chicago",
    "sg:classifiers":[
        {
            "category":"Organizations",
            "subcategory":"Religious Organization",
            "type":"Services"
        }
    ],
    "sg:phone":"+1 773 238 7850",
    "sg:postcode":"60643",
    "sg:province":"IL",
    "wof:name":"Greater Tabernacle M B Church",
    "wof:placetype":"venue"
},
  "geometry": {"coordinates":[-87.65682099999999,41.718003],"type":"Point"}
}