{
  "type": "Feature",
  "properties": {
    "iso:country":"US",
    "sg:address":"8550 S Kedvale Ave",
    "sg:city":"Chicago",
    "sg:classifiers":[
        {
            "category":"Organizations",
            "subcategory":"Religious Organization",
            "type":"Services"
        }
    ],
    "sg:phone":"+1 773 582 0470",
    "sg:postcode":"60652",
    "sg:province":"IL",
    "wof:name":"St Peters Lutheran Church",
    "wof:placetype":"venue"
},
  "geometry": {"coordinates":[-87.725236,41.737554],"type":"Point"}
}