{
  "type": "Feature",
  "properties": {
    "addr:full":"1424 Cabot Ln Schaumburg IL 60193",
    "addr:housenumber":"1424",
    "addr:postcode":"60193",
    "addr:street":"Cabot Ln",
    "iso:country":"US",
    "sg:address":"1424 Cabot Ln",
    "sg:city":"Schaumburg",
    "sg:classifiers":[
        {
            "category":"Professional",
            "subcategory":"Engineering",
            "type":"Services"
        }
    ],
    "sg:phone":"+1 847 985 3886",
    "sg:postcode":"60193",
    "sg:province":"IL",
    "sg:tags":[
        "engineer"
    ],
    "wof:name":"Doherty & Assoc",
    "wof:placetype":"venue"
},
  "geometry": {"coordinates":[-88.11644200000001,42.014916],"type":"Point"}
}