{
  "type": "Feature",
  "properties": {
    "iso:country":"US",
    "sg:address":"1206 N Central Ave",
    "sg:city":"Chicago",
    "sg:classifiers":[
        {
            "category":"Restaurant",
            "type":"Food & Drink"
        }
    ],
    "sg:phone":"+1   ",
    "sg:postcode":"60651",
    "sg:province":"IL",
    "sg:tags":[
        "eating"
    ],
    "wof:name":"Charles Papa Restaurant",
    "wof:placetype":"venue"
},
  "geometry": {"coordinates":[-87.76575800000001,41.902932],"type":"Point"}
}