{
  "type": "Feature",
  "properties": {
    "addr:full":"365 Remington Blvd Bolingbrook IL 60440",
    "addr:housenumber":"365",
    "addr:postcode":"60440",
    "addr:street":"Remington Blvd",
    "iso:country":"US",
    "sg:address":"365 Remington Blvd",
    "sg:city":"Bolingbrook",
    "sg:classifiers":[
        {
            "category":"Wholesale",
            "subcategory":"Medical Equipment & Supplies",
            "type":"Manufacturing & Wholesale Goods"
        }
    ],
    "sg:phone":"+1 630 759 8500",
    "sg:postcode":"60440",
    "sg:province":"IL",
    "sg:tags":[
        "laboratory"
    ],
    "wof:name":"General Laboratory Products",
    "wof:placetype":"venue"
},
  "geometry": {"coordinates":[-88.07814999999999,41.68368],"type":"Point"}
}