{
  "type": "Feature",
  "properties": {
    "iso:country":"US",
    "sg:address":"5 Oaklawn Ct",
    "sg:city":"Danville",
    "sg:classifiers":[
        {
            "category":"Retail",
            "subcategory":"Auto Repair",
            "type":"Services"
        }
    ],
    "sg:phone":"+1 217 442 6105",
    "sg:postcode":"61832",
    "sg:province":"IL",
    "sg:tags":[
        "body",
        "automobile",
        "painting",
        "repairing"
    ],
    "wof:name":"Bob & Pat Fender",
    "wof:placetype":"venue"
},
  "geometry": {"coordinates":[-87.58049800000001,40.130821],"type":"Point"}
}