{
  "type": "Feature",
  "properties": {
    "iso:country":"US",
    "sg:address":"4824 W Belle Plaine Ave",
    "sg:city":"Chicago",
    "sg:classifiers":[
        {
            "category":"Social Services",
            "subcategory":"Adult Care",
            "type":"Services"
        }
    ],
    "sg:phone":"+1 773 685 3327",
    "sg:postcode":"60641",
    "sg:province":"IL",
    "sg:tags":[
        "residential",
        "aged",
        "homes-institutional"
    ],
    "wof:name":"Belle Plaine Group Home",
    "wof:placetype":"venue"
},
  "geometry": {"coordinates":[-87.747933,41.955232],"type":"Point"}
}