{
  "type": "Feature",
  "properties": {
    "addr:full":"1026 W Ainslie St Chicago IL 60640",
    "addr:housenumber":"1026",
    "addr:postcode":"60640",
    "addr:street":"W Ainslie St",
    "iso:country":"US",
    "sg:address":"1026 W Ainslie St",
    "sg:city":"Chicago",
    "sg:classifiers":[
        {
            "category":"Social Services",
            "subcategory":"Child Care",
            "type":"Services"
        }
    ],
    "sg:phone":"+1 773 275 7626",
    "sg:postcode":"60640",
    "sg:province":"IL",
    "sg:tags":[
        "day"
    ],
    "wof:name":"Hands & Mind Childcare",
    "wof:placetype":"venue"
},
  "geometry": {"coordinates":[-87.65584200000001,41.97164],"type":"Point"}
}