{
  "type": "Feature",
  "properties": {
    "addr:full":"1201 W New York St Aurora IL 60506",
    "addr:housenumber":"1201",
    "addr:postcode":"60506",
    "addr:street":"W New York St",
    "iso:country":"US",
    "sg:address":"1201 W New York St",
    "sg:city":"Aurora",
    "sg:classifiers":[
        {
            "category":"Recreation",
            "type":"Entertainment"
        }
    ],
    "sg:phone":"+1 630 844 4586",
    "sg:postcode":"60506",
    "sg:province":"IL",
    "sg:tags":[
        "club",
        "membership"
    ],
    "wof:name":"Blackhawk Club",
    "wof:placetype":"venue"
},
  "geometry": {"coordinates":[-88.341915,41.763577],"type":"Point"}
}