{
  "type": "Feature",
  "properties": {
    "iso:country":"US",
    "sg:address":"706 SE 3rd St",
    "sg:city":"Aledo",
    "sg:classifiers":[
        {
            "category":"Government",
            "subcategory":"Office",
            "type":"Public Place"
        }
    ],
    "sg:phone":"+1 309 582 2528",
    "sg:postcode":"61231",
    "sg:province":"IL",
    "sg:tags":[
        "state",
        "program"
    ],
    "wof:name":"Drivers License Bureau",
    "wof:placetype":"venue"
},
  "geometry": {"coordinates":[-90.74231899999999,41.199723],"type":"Point"}
}