{
  "type": "Feature",
  "properties": {
    "iso:country":"US",
    "sg:address":"1240 N Cedar Rd",
    "sg:city":"New Lenox",
    "sg:classifiers":[
        {
            "category":"Health Services",
            "subcategory":"Doctor",
            "type":"Services"
        }
    ],
    "sg:phone":"+1 815 485 8850",
    "sg:postcode":"60451",
    "sg:province":"IL",
    "sg:tags":[
        "dentist"
    ],
    "wof:name":"Frank G Hutton DDS",
    "wof:placetype":"venue"
},
  "geometry": {"coordinates":[-87.966241,41.527645],"type":"Point"}
}