{
  "type": "Feature",
  "properties": {
    "iso:country":"US",
    "sg:address":"4743 Keel Ct",
    "sg:city":"Lisle",
    "sg:classifiers":[
        {
            "category":"Banks & Credit Unions",
            "subcategory":"Bank",
            "type":"Services"
        }
    ],
    "sg:phone":"+1 630 579 8660",
    "sg:postcode":"60532",
    "sg:province":"IL",
    "sg:tags":[
        "foreign"
    ],
    "wof:name":"Ebridge",
    "wof:placetype":"venue"
},
  "geometry": {"coordinates":[-88.109801,41.799211],"type":"Point"}
}