{
  "type": "Feature",
  "properties": {
    "addr:full":"141 W Jackson Blvd Ste 4004 Chicago IL 60604",
    "addr:housenumber":"141",
    "addr:postcode":"60604",
    "addr:street":"W Jackson Blvd Ste 4004",
    "iso:country":"US",
    "sg:address":"141 W Jackson Blvd Ste 4004",
    "sg:city":"Chicago",
    "sg:classifiers":[
        {
            "category":"Professional",
            "subcategory":"Accounting & Tax Preparation",
            "type":"Services"
        }
    ],
    "sg:phone":"+1 312 461 0496",
    "sg:postcode":"60604",
    "sg:province":"IL",
    "sg:tags":[
        "accountant"
    ],
    "wof:name":"Wood Nadler & Co",
    "wof:placetype":"venue"
},
  "geometry": {"coordinates":[-87.63220200000001,41.878101],"type":"Point"}
}