{
  "type": "Feature",
  "properties": {
    "addr:full":"8679 Cambridge Rd Kingston IL 60145",
    "addr:housenumber":"8679",
    "addr:postcode":"60145",
    "addr:street":"Cambridge Rd",
    "iso:country":"US",
    "sg:address":"8679 Cambridge Rd",
    "sg:city":"Kingston",
    "sg:classifiers":[
        {
            "category":"Transit Center",
            "subcategory":"Freight",
            "type":"Transportation"
        },
        {
            "category":"Freight",
            "type":"Transportation"
        }
    ],
    "sg:phone":"+1 815 784 5212",
    "sg:postcode":"60145",
    "sg:province":"IL",
    "sg:tags":[
        "local",
        "trucking-motor",
        "trucking"
    ],
    "wof:name":"Triple B Trucking Inc",
    "wof:placetype":"venue"
},
  "geometry": {"coordinates":[-88.78027400000001,42.094811],"type":"Point"}
}