{
  "type": "Feature",
  "properties": {
    "iso:country":"US",
    "sg:address":"1301 Peoria St",
    "sg:city":"Peru",
    "sg:classifiers":[
        {
            "category":"Insurance",
            "subcategory":"Insurance Agent",
            "type":"Services"
        }
    ],
    "sg:phone":"+1 815 224 4242",
    "sg:postcode":"61354",
    "sg:province":"IL",
    "wof:name":"Payton Insurance & Investments",
    "wof:placetype":"venue"
},
  "geometry": {"coordinates":[-89.1292,41.33309],"type":"Point"}
}