{
  "type": "Feature",
  "properties": {
    "addr:full":"3364 N Pulaski Rd Chicago IL 60641",
    "addr:housenumber":"3364",
    "addr:postcode":"60641",
    "addr:street":"N Pulaski Rd",
    "iso:country":"US",
    "sg:address":"3364 N Pulaski Rd",
    "sg:city":"Chicago",
    "sg:classifiers":[
        {
            "category":"Building & Trades",
            "subcategory":"Construction",
            "type":"Services"
        }
    ],
    "sg:phone":"+1 773 205 9500",
    "sg:postcode":"60641",
    "sg:province":"IL",
    "sg:tags":[
        "general",
        "contractor"
    ],
    "wof:name":"Main Construction Inc",
    "wof:placetype":"venue"
},
  "geometry": {"coordinates":[-87.727378,41.943084],"type":"Point"}
}