{
  "type": "Feature",
  "properties": {
    "addr:full":"41 N Cass Ave Westmont IL 60559",
    "addr:housenumber":"41",
    "addr:postcode":"60559",
    "addr:street":"N Cass Ave",
    "iso:country":"US",
    "sg:address":"41 N Cass Ave",
    "sg:city":"Westmont",
    "sg:classifiers":[
        {
            "category":"Personal",
            "type":"Services"
        },
        {
            "category":"Shopping",
            "subcategory":"Florist",
            "type":"Retail Goods"
        }
    ],
    "sg:phone":"+1 630 241 4600",
    "sg:postcode":"60559",
    "sg:province":"IL",
    "sg:tags":[
        "party",
        "planning",
        "event"
    ],
    "wof:name":"Aria Floral Studio",
    "wof:placetype":"venue"
},
  "geometry": {"coordinates":[-87.975348,41.79606],"type":"Point"}
}