{
  "type": "Feature",
  "properties": {
    "iso:country":"US",
    "sg:address":"1643 Algonquin Rd",
    "sg:city":"Rolling Meadows",
    "sg:classifiers":[
        {
            "category":"Shopping",
            "subcategory":"Tobacco",
            "type":"Retail Goods"
        }
    ],
    "sg:phone":"+1   ",
    "sg:postcode":"60008",
    "sg:province":"IL",
    "wof:name":"Fair Price Tobacco Inc",
    "wof:placetype":"venue"
},
  "geometry": {"coordinates":[-87.99910800000001,42.055083],"type":"Point"}
}