{
  "type": "Feature",
  "properties": {
    "iso:country":"US",
    "sg:address":"1215 McHenry Rd",
    "sg:city":"Buffalo Grove",
    "sg:classifiers":[
        {
            "category":"Health Services",
            "subcategory":"Doctor",
            "type":"Services"
        }
    ],
    "sg:phone":"+1 847 634 1690",
    "sg:postcode":"60089",
    "sg:province":"IL",
    "sg:tags":[
        "physician",
        "surgeon"
    ],
    "wof:name":"Yasmeen S Bilimoria MD",
    "wof:placetype":"venue"
},
  "geometry": {"coordinates":[-87.98523400000001,42.174229],"type":"Point"}
}