{
  "type": "Feature",
  "properties": {
    "addr:full":"5860 N Lincoln Avenue Chicago IL 60659",
    "addr:housenumber":"5860",
    "addr:postcode":"60659",
    "addr:street":"N Lincoln Avenue",
    "iso:country":"US",
    "sg:address":"5860 N Lincoln Avenue",
    "sg:city":"Chicago",
    "sg:classifiers":[
        {
            "category":"Building & Trades",
            "subcategory":"Pest Control",
            "type":"Services"
        }
    ],
    "sg:phone":"+1 773 763 8100",
    "sg:postcode":"60659",
    "sg:province":"IL",
    "wof:name":"American Exterminators",
    "wof:placetype":"venue"
},
  "geometry": {"coordinates":[-87.70421399999999,41.991399],"type":"Point"}
}