{
  "type": "Feature",
  "properties": {
    "iso:country":"US",
    "sg:address":"1205 W Jefferson Ave",
    "sg:city":"Effingham",
    "sg:classifiers":[
        {
            "category":"Wholesale",
            "subcategory":"Sporting Goods",
            "type":"Manufacturing & Wholesale Goods"
        }
    ],
    "sg:phone":"+1 217 347 0777",
    "sg:postcode":"62401",
    "sg:province":"IL",
    "sg:tags":[
        "merchandise"
    ],
    "wof:name":"Leisure Times Pools & Spas",
    "wof:placetype":"venue"
},
  "geometry": {"coordinates":[-88.556814,39.121424],"type":"Point"}
}