{
  "type": "Feature",
  "properties": {
    "iso:country":"US",
    "sg:address":"18154 Harwood Ave",
    "sg:city":"Homewood",
    "sg:classifiers":[
        {
            "category":"Professional",
            "subcategory":"Engineering",
            "type":"Services"
        }
    ],
    "sg:phone":"+1 708 798 1234",
    "sg:postcode":"60430",
    "sg:province":"IL",
    "wof:name":"Terrafac Ltd",
    "wof:placetype":"venue"
},
  "geometry": {"coordinates":[-87.668386,41.560117],"type":"Point"}
}