{
  "type": "Feature",
  "properties": {
    "iso:country":"US",
    "sg:address":"301 Evans Ave",
    "sg:city":"Wood River",
    "sg:phone":"+1 618 254 0851",
    "sg:postcode":"62095",
    "sg:province":"IL",
    "sg:tags":[
        "oil"
    ],
    "wof:name":"Amoco",
    "wof:placetype":"venue"
},
  "geometry": {"coordinates":[-90.10288799999999,38.855958],"type":"Point"}
}