{
  "type": "Feature",
  "properties": {
    "iso:country":"US",
    "sg:address":"3833 Auburn St",
    "sg:city":"Rockford",
    "sg:classifiers":[
        {
            "category":"Shopping",
            "subcategory":"Computers & Home Electronics",
            "type":"Retail Goods"
        }
    ],
    "sg:phone":"+1   ",
    "sg:postcode":"61101",
    "sg:province":"IL",
    "sg:tags":[
        "television",
        "component",
        "rent",
        "related"
    ],
    "wof:name":"Vaughn Home Furnishings",
    "wof:placetype":"venue"
},
  "geometry": {"coordinates":[-89.116602,42.2884],"type":"Point"}
}