{
  "type": "Feature",
  "properties": {
    "iso:country":"US",
    "sg:address":"2840 W Armitage Ave",
    "sg:city":"Chicago",
    "sg:classifiers":[
        {
            "category":"Retail",
            "subcategory":"Portrait Studio",
            "type":"Services"
        },
        {
            "category":"Shopping",
            "subcategory":"Photographic Equipment",
            "type":"Retail Goods"
        }
    ],
    "sg:phone":"+1 773 227 3633",
    "sg:postcode":"60647",
    "sg:province":"IL",
    "sg:tags":[
        "photography",
        "store",
        "supply"
    ],
    "sg:website":"www.doddpro.com",
    "wof:name":"Dodd Camera",
    "wof:placetype":"venue"
},
  "geometry": {"coordinates":[-87.69881599999999,41.917784],"type":"Point"}
}