{
  "type": "Feature",
  "properties": {
    "addr:full":"1900 S Main St Eureka IL 61530",
    "addr:housenumber":"1900",
    "addr:postcode":"61530",
    "addr:street":"S Main St",
    "iso:country":"US",
    "sg:address":"1900 S Main St",
    "sg:city":"Eureka",
    "sg:classifiers":[
        {
            "category":"Autos & Motor Vehicles",
            "subcategory":"Fuel & Gas Station",
            "type":"Retail Goods"
        },
        {
            "category":"Wholesale",
            "subcategory":"Petroleum",
            "type":"Manufacturing & Wholesale Goods"
        },
        {
            "category":"Manufacturing",
            "subcategory":"Petroleum Products",
            "type":"Manufacturing & Wholesale Goods"
        },
        {
            "category":"Utilities",
            "subcategory":"Fuel Oil & Lpg",
            "type":"Services"
        }
    ],
    "sg:phone":"+1 309 467 2218",
    "sg:postcode":"61530",
    "sg:province":"IL",
    "sg:tags":[
        "oils-fuel",
        "diesel",
        "gasoline-wholesale",
        "oils-petroleum"
    ],
    "wof:name":"Yoder Oil Inc.",
    "wof:placetype":"venue"
},
  "geometry": {"coordinates":[-89.272614,40.70298],"type":"Point"}
}