{
  "type": "Feature",
  "properties": {
    "addr:full":"8747 W Bryn Mawr Ave Chicago IL 60631",
    "addr:housenumber":"8747",
    "addr:postcode":"60631",
    "addr:street":"W Bryn Mawr Ave",
    "iso:country":"US",
    "sg:address":"8747 W Bryn Mawr Ave",
    "sg:city":"Chicago",
    "sg:classifiers":[
        {
            "category":"Communications",
            "type":"Services"
        }
    ],
    "sg:phone":"+1 773 647 1620",
    "sg:postcode":"60631",
    "sg:province":"IL",
    "wof:name":"Communica Its",
    "wof:placetype":"venue"
},
  "geometry": {"coordinates":[-87.845024,41.980982],"type":"Point"}
}