{
  "type": "Feature",
  "properties": {
    "iso:country":"US",
    "sg:address":"2301 63rd St",
    "sg:city":"Woodridge",
    "sg:classifiers":[
        {
            "category":"Personal",
            "subcategory":"Beauty Salon",
            "type":"Services"
        },
        {
            "category":"Personal",
            "subcategory":"Barber",
            "type":"Services"
        }
    ],
    "sg:phone":"+1 331 481 7571",
    "sg:postcode":"60517",
    "sg:province":"IL",
    "sg:tags":[
        "hair",
        "accessory",
        "stylist",
        "supply"
    ],
    "sg:website":"http://www.haircuttery.com",
    "wof:name":"Hair Cuttery",
    "wof:placetype":"venue"
},
  "geometry": {"coordinates":[-88.037857,41.772339],"type":"Point"}
}