{
  "type": "Feature",
  "properties": {
    "addr:full":"4113 4th St East Moline IL 61244",
    "addr:housenumber":"4113",
    "addr:postcode":"61244",
    "addr:street":"4Th St",
    "iso:country":"US",
    "sg:address":"4113 4th St",
    "sg:city":"East Moline",
    "sg:classifiers":[
        {
            "category":"Building & Trades",
            "subcategory":"Plumbing",
            "type":"Services"
        }
    ],
    "sg:phone":"+1 309 752 0150",
    "sg:postcode":"61244",
    "sg:province":"IL",
    "wof:name":"Bagby Plumbing Service",
    "wof:placetype":"venue"
},
  "geometry": {"coordinates":[-90.45273400000001,41.490949],"type":"Point"}
}