{
  "type": "Feature",
  "properties": {
    "iso:country":"US",
    "sg:address":"1259 W 111th St",
    "sg:city":"Chicago",
    "sg:classifiers":[
        {
            "category":"Education",
            "subcategory":"School",
            "type":"Public Place"
        }
    ],
    "sg:phone":"+1 312 239 4000",
    "sg:postcode":"60643",
    "sg:province":"IL",
    "wof:name":"Mount Calvary Christn Academy",
    "wof:placetype":"venue"
},
  "geometry": {"coordinates":[-87.653341,41.692152],"type":"Point"}
}