{
  "type": "Feature",
  "properties": {
    "iso:country":"US",
    "sg:address":"222 S Racine Ave",
    "sg:city":"Chicago",
    "sg:classifiers":[
        {
            "category":"Shopping",
            "subcategory":"Computers & Home Electronics",
            "type":"Retail Goods"
        }
    ],
    "sg:phone":"+1 312 715 1970",
    "sg:postcode":"60661",
    "sg:province":"IL",
    "sg:website":"avintegrationgroup.com",
    "wof:name":"AV Integration Group, Inc.",
    "wof:placetype":"venue"
},
  "geometry": {"coordinates":[-87.657444,41.878424],"type":"Point"}
}