{
  "type": "Feature",
  "properties": {
    "addr:full":"121 W Kinzie St Chicago IL 60610",
    "addr:housenumber":"121",
    "addr:postcode":"60610",
    "addr:street":"W Kinzie St",
    "iso:country":"US",
    "sg:address":"121 W Kinzie St",
    "sg:city":"Chicago",
    "sg:classifiers":[
        {
            "category":"Shopping",
            "subcategory":"Pharmacy",
            "type":"Retail Goods"
        }
    ],
    "sg:phone":"+1 312 970 2880",
    "sg:postcode":"60610",
    "sg:province":"IL",
    "sg:tags":[
        "drugstore"
    ],
    "wof:name":"Cvs Pharmacy",
    "wof:placetype":"venue"
},
  "geometry": {"coordinates":[-87.63110399999999,41.889198],"type":"Point"}
}