{
  "type": "Feature",
  "properties": {
    "addr:full":"1103 N Neil St Champaign IL 61820",
    "addr:housenumber":"1103",
    "addr:postcode":"61820",
    "addr:street":"N Neil St",
    "iso:country":"US",
    "sg:address":"1103 N Neil St",
    "sg:city":"Champaign",
    "sg:classifiers":[
        {
            "category":"Education",
            "subcategory":"School",
            "type":"Public Place"
        }
    ],
    "sg:phone":"+1 217 352 8382",
    "sg:postcode":"61820",
    "sg:province":"IL",
    "wof:name":"Even Start",
    "wof:placetype":"venue"
},
  "geometry": {"coordinates":[-88.24369799999999,40.126701],"type":"Point"}
}