{
  "type": "Feature",
  "properties": {
    "iso:country":"US",
    "sg:address":"1107 S Willow St",
    "sg:city":"Effingham",
    "sg:classifiers":[
        {
            "category":"Retail",
            "subcategory":"Repair Shop",
            "type":"Services"
        }
    ],
    "sg:phone":"+1 217 347 9630",
    "sg:postcode":"62401",
    "sg:province":"IL",
    "sg:tags":[
        "lock",
        "locksmith"
    ],
    "wof:name":"Barlow Lock & Security Inc",
    "wof:placetype":"venue"
},
  "geometry": {"coordinates":[-88.536871,39.112002],"type":"Point"}
}