{
  "type": "Feature",
  "properties": {
    "addr:full":"1402 W Randolph St Vandalia IL 62471",
    "addr:housenumber":"1402",
    "addr:postcode":"62471",
    "addr:street":"W Randolph St",
    "iso:country":"US",
    "sg:address":"1402 W Randolph St",
    "sg:city":"Vandalia",
    "sg:classifiers":[
        {
            "category":"Retail",
            "subcategory":"Auto Repair",
            "type":"Services"
        }
    ],
    "sg:phone":"+1 618 283 3504",
    "sg:postcode":"62471",
    "sg:province":"IL",
    "sg:tags":[
        "muffler",
        "exhaust",
        "system"
    ],
    "wof:name":"Joe's Auto Repair",
    "wof:placetype":"venue"
},
  "geometry": {"coordinates":[-89.11065499999999,38.964083],"type":"Point"}
}