{
  "type": "Feature",
  "properties": {
    "iso:country":"US",
    "sg:address":"989 Fairway Cir",
    "sg:city":"Barrington",
    "sg:classifiers":[
        {
            "category":"Freight",
            "type":"Transportation"
        }
    ],
    "sg:phone":"+1 847 381 1206",
    "sg:postcode":"60010",
    "sg:province":"IL",
    "sg:tags":[
        "operator",
        "trucking"
    ],
    "wof:name":"American Lafrance",
    "wof:placetype":"venue"
},
  "geometry": {"coordinates":[-88.158134,42.214973],"type":"Point"}
}