{
  "type": "Feature",
  "properties": {
    "iso:country":"US",
    "sg:address":"1830 N Besly Court",
    "sg:city":"Chicago",
    "sg:classifiers":[
        {
            "category":"Home & Garden",
            "subcategory":"Garden Supply",
            "type":"Retail Goods"
        }
    ],
    "sg:phone":"+1 773 276 1001",
    "sg:postcode":"60622",
    "sg:province":"IL",
    "sg:website":"www.chicagoliquidators.com",
    "wof:name":"Chicago Liquidators",
    "wof:placetype":"venue"
},
  "geometry": {"coordinates":[-87.666612,41.915807],"type":"Point"}
}