{
  "type": "Feature",
  "properties": {
    "addr:full":"1400 N Cicero Ave Ste 1 Chicago IL 60651",
    "addr:housenumber":"1400",
    "addr:postcode":"60651",
    "addr:street":"N Cicero Ave Ste 1",
    "iso:country":"US",
    "sg:address":"1400 N Cicero Ave Ste 1",
    "sg:city":"Chicago",
    "sg:classifiers":[
        {
            "category":"Building & Trades",
            "subcategory":"Electrical",
            "type":"Services"
        }
    ],
    "sg:phone":"+1 773 921 6000",
    "sg:postcode":"60651",
    "sg:province":"IL",
    "sg:tags":[
        "transmission",
        "power",
        "equipment"
    ],
    "wof:name":"Parts Div",
    "wof:placetype":"venue"
},
  "geometry": {"coordinates":[-87.74603999999999,41.905991],"type":"Point"}
}