{
  "type": "Feature",
  "properties": {
    "addr:full":"1040 Dell Rd Northbrook IL 60062",
    "addr:housenumber":"1040",
    "addr:postcode":"60062",
    "addr:street":"Dell Rd",
    "iso:country":"US",
    "sg:address":"1040 Dell Rd",
    "sg:city":"Northbrook",
    "sg:classifiers":[
        {
            "category":"Real Estate",
            "subcategory":"Real Estate Agent",
            "type":"Services"
        }
    ],
    "sg:phone":"+1 847 564 4907",
    "sg:postcode":"60062",
    "sg:province":"IL",
    "wof:name":"Brenner Appraisal",
    "wof:placetype":"venue"
},
  "geometry": {"coordinates":[-87.794057,42.133483],"type":"Point"}
}