{
  "type": "Feature",
  "properties": {
    "iso:country":"US",
    "sg:address":"205 N Michigan Ave",
    "sg:city":"Chicago",
    "sg:classifiers":[
        {
            "category":"Professional",
            "subcategory":"Employment Agencies",
            "type":"Services"
        }
    ],
    "sg:phone":"+1 312 616 8200",
    "sg:postcode":"60601",
    "sg:province":"IL",
    "wof:name":"Robert Half",
    "wof:placetype":"venue"
},
  "geometry": {"coordinates":[-87.624657,41.886237],"type":"Point"}
}