{
  "type": "Feature",
  "properties": {
    "iso:country":"US",
    "sg:address":"25470 W Grass Lake Rd",
    "sg:city":"Antioch",
    "sg:classifiers":[
        {
            "category":"Building & Trades",
            "subcategory":"Electrical",
            "type":"Services"
        }
    ],
    "sg:phone":"+1 847 395 5364",
    "sg:postcode":"60002",
    "sg:province":"IL",
    "sg:tags":[
        "electrician"
    ],
    "wof:name":"Layton Electric",
    "wof:placetype":"venue"
},
  "geometry": {"coordinates":[-88.130135,42.447302],"type":"Point"}
}