{
  "type": "Feature",
  "properties": {
    "iso:country":"US",
    "sg:address":"100 Church St",
    "sg:city":"Peru",
    "sg:classifiers":[
        {
            "category":"Home & Garden",
            "subcategory":"Building Materials",
            "type":"Retail Goods"
        }
    ],
    "sg:phone":"+1 815 224 4000",
    "sg:postcode":"61354",
    "sg:province":"IL",
    "sg:tags":[
        "lumber"
    ],
    "wof:name":"Maze Lumber Time & Weather",
    "wof:placetype":"venue"
},
  "geometry": {"coordinates":[-89.138236,41.320475],"type":"Point"}
}