{
  "type": "Feature",
  "properties": {
    "iso:country":"US",
    "sg:address":"4113 Humbert Rd",
    "sg:city":"Alton",
    "sg:classifiers":[
        {
            "category":"Health Services",
            "subcategory":"Dentist",
            "type":"Services"
        }
    ],
    "sg:phone":"+1 618 465 7777",
    "sg:postcode":"62002",
    "sg:province":"IL",
    "wof:name":"Chapel, Kevin M",
    "wof:placetype":"venue"
},
  "geometry": {"coordinates":[-90.154764,38.934792],"type":"Point"}
}