{
  "type": "Feature",
  "properties": {
    "iso:country":"US",
    "sg:address":"7221 S 86th Ave",
    "sg:city":"Bedford Park",
    "sg:classifiers":[
        {
            "category":"Freight",
            "type":"Transportation"
        }
    ],
    "sg:phone":"+1 708 496 1201",
    "sg:postcode":"60458",
    "sg:province":"IL",
    "sg:tags":[
        "truck",
        "dump"
    ],
    "wof:name":"Lwp Motor Service Inc",
    "wof:placetype":"venue"
},
  "geometry": {"coordinates":[-87.834177,41.761831],"type":"Point"}
}