{
  "type": "Feature",
  "properties": {
    "iso:country":"US",
    "sg:address":"936 E 79th St",
    "sg:city":"Chicago",
    "sg:classifiers":[
        {
            "category":"Restaurant",
            "type":"Food & Drink"
        }
    ],
    "sg:phone":"+1 773 224 9050",
    "sg:postcode":"60619",
    "sg:province":"IL",
    "sg:tags":[
        "caribbean"
    ],
    "sg:website":"www.donsjerkspot.com",
    "wof:name":"Don's Caribbean Jerk Spot",
    "wof:placetype":"venue"
},
  "geometry": {"coordinates":[-87.601626,41.751299],"type":"Point"}
}