{
  "type": "Feature",
  "properties": {
    "addr:full":"3434 W B R Townline Rd Beloit IL 53511",
    "addr:housenumber":"3434",
    "addr:postcode":"53511",
    "addr:street":"W B R Townline Rd",
    "iso:country":"US",
    "sg:address":"3434 W B R Townline Rd",
    "sg:city":"Beloit",
    "sg:classifiers":[
        {
            "category":"Farming",
            "subcategory":"Farm",
            "type":"Manufacturing & Wholesale Goods"
        }
    ],
    "sg:phone":"+1 608 362 1480",
    "sg:postcode":"53511",
    "sg:province":"IL",
    "sg:tags":[
        "crop",
        "general"
    ],
    "wof:name":"Radtke Farm",
    "wof:placetype":"venue"
},
  "geometry": {"coordinates":[-89.066587,42.584495],"type":"Point"}
}