{
  "type": "Feature",
  "properties": {
    "iso:country":"US",
    "sg:address":"21952 W Pine Lake Cir",
    "sg:city":"Kildeer",
    "sg:classifiers":[
        {
            "category":"Professional",
            "subcategory":"Business Services",
            "type":"Services"
        }
    ],
    "sg:phone":"+1 847 438 3002",
    "sg:postcode":"60047",
    "sg:province":"IL",
    "sg:tags":[
        "holding"
    ],
    "wof:name":"Multisource Corporation",
    "wof:placetype":"venue"
},
  "geometry": {"coordinates":[-88.061834,42.175001],"type":"Point"}
}