{
  "type": "Feature",
  "properties": {
    "addr:full":"1829 Emerson St Evanston IL 60201",
    "addr:housenumber":"1829",
    "addr:postcode":"60201",
    "addr:street":"Emerson St",
    "iso:country":"US",
    "sg:address":"1829 Emerson St",
    "sg:city":"Evanston",
    "sg:classifiers":[
        {
            "category":"Personal",
            "subcategory":"Beauty Salon",
            "type":"Services"
        }
    ],
    "sg:phone":"+1 847 332 1688",
    "sg:postcode":"60201",
    "sg:province":"IL",
    "sg:tags":[
        "hair"
    ],
    "wof:name":"Hair By Paula",
    "wof:placetype":"venue"
},
  "geometry": {"coordinates":[-87.698511,42.05216],"type":"Point"}
}