{
  "type": "Feature",
  "properties": {
    "addr:full":"625 Woodcreek Dr Bolingbrook IL 60440",
    "addr:housenumber":"625",
    "addr:postcode":"60440",
    "addr:street":"Woodcreek Dr",
    "iso:country":"US",
    "sg:address":"625 Woodcreek Dr",
    "sg:city":"Bolingbrook",
    "sg:classifiers":[
        {
            "category":"Wholesale",
            "subcategory":"Chemicals & Plastics",
            "type":"Manufacturing & Wholesale Goods"
        }
    ],
    "sg:phone":"+1 630 759 1810",
    "sg:postcode":"60440",
    "sg:province":"IL",
    "sg:tags":[
        "carbide"
    ],
    "sg:website":"www.idealcarbide.com",
    "wof:name":"Ideal Carbide Die Co",
    "wof:placetype":"venue"
},
  "geometry": {"coordinates":[-88.07898,41.681725],"type":"Point"}
}