{
  "type": "Feature",
  "properties": {
    "iso:country":"US",
    "sg:address":"784 Saint Marys Pkwy",
    "sg:city":"Buffalo Grove",
    "sg:classifiers":[
        {
            "category":"Wholesale",
            "subcategory":"Machinery & Supplies",
            "type":"Manufacturing & Wholesale Goods"
        }
    ],
    "sg:phone":"+1 847 520 0130",
    "sg:postcode":"60089",
    "sg:province":"IL",
    "sg:tags":[
        "distributor",
        "equipment",
        "representative",
        "mfg"
    ],
    "wof:name":"Laganowski & Associates Inc",
    "wof:placetype":"venue"
},
  "geometry": {"coordinates":[-87.976237,42.151502],"type":"Point"}
}