{
  "type": "Feature",
  "properties": {
    "addr:full":"1188 Arbor Dr Romeoville IL 60446",
    "addr:housenumber":"1188",
    "addr:postcode":"60446",
    "addr:street":"Arbor Dr",
    "iso:country":"US",
    "sg:address":"1188 Arbor Dr",
    "sg:city":"Romeoville",
    "sg:classifiers":[
        {
            "category":"Freight",
            "type":"Transportation"
        }
    ],
    "sg:phone":"+1 630 378 1127",
    "sg:postcode":"60446",
    "sg:province":"IL",
    "sg:tags":[
        "commercial",
        "storage"
    ],
    "wof:name":"Pods Inc",
    "wof:placetype":"venue"
},
  "geometry": {"coordinates":[-88.11942000000001,41.667004],"type":"Point"}
}