{
  "type": "Feature",
  "properties": {
    "addr:full":"103 N Main St Port Byron IL 61275",
    "addr:housenumber":"103",
    "addr:postcode":"61275",
    "addr:street":"N Main St",
    "iso:country":"US",
    "sg:address":"103 N Main St",
    "sg:city":"Port Byron",
    "sg:classifiers":[
        {
            "category":"Personal",
            "subcategory":"Barber",
            "type":"Services"
        }
    ],
    "sg:phone":"+1 309 523 3815",
    "sg:postcode":"61275",
    "sg:province":"IL",
    "wof:name":"Hair Shop",
    "wof:placetype":"venue"
},
  "geometry": {"coordinates":[-90.336384,41.606678],"type":"Point"}
}