{
  "type": "Feature",
  "properties": {
    "addr:full":"Chgo Ohare Intl Air Chicago IL 60607",
    "addr:postcode":"60607",
    "iso:country":"US",
    "sg:address":"Chgo Ohare Intl Air",
    "sg:city":"Chicago",
    "sg:classifiers":[
        {
            "category":"Restaurant",
            "type":"Food & Drink"
        }
    ],
    "sg:phone":"+1 773 686 1540",
    "sg:postcode":"60607",
    "sg:province":"IL",
    "sg:website":"www.mcdonalds.com",
    "wof:name":"Mc Donald's",
    "wof:placetype":"venue"
},
  "geometry": {"coordinates":[-87.657501,41.873199],"type":"Point"}
}