{
  "type": "Feature",
  "properties": {
    "addr:full":"350 N Broadway St Joliet IL 60435",
    "addr:housenumber":"350",
    "addr:postcode":"60435",
    "addr:street":"N Broadway St",
    "iso:country":"US",
    "sg:address":"350 N Broadway St",
    "sg:city":"Joliet",
    "sg:classifiers":[
        {
            "category":"Social Services",
            "subcategory":"Child Care",
            "type":"Services"
        }
    ],
    "sg:phone":"+1 815 727 6239",
    "sg:postcode":"60435",
    "sg:province":"IL",
    "wof:name":"Broadway Child Care",
    "wof:placetype":"venue"
},
  "geometry": {"coordinates":[-88.08852400000001,41.527837],"type":"Point"}
}