{
  "type": "Feature",
  "properties": {
    "addr:full":"4149 Briargate Rd Rockford IL 61102",
    "addr:housenumber":"4149",
    "addr:postcode":"61102",
    "addr:street":"Briargate Rd",
    "iso:country":"US",
    "sg:address":"4149 Briargate Rd",
    "sg:city":"Rockford",
    "sg:classifiers":[
        {
            "category":"Professional",
            "subcategory":"Business Services",
            "type":"Services"
        }
    ],
    "sg:phone":"+1 815 961 6843",
    "sg:postcode":"61102",
    "sg:province":"IL",
    "sg:tags":[
        "recording",
        "video",
        "production",
        "studio"
    ],
    "sg:website":"www.jaricostudios.com",
    "wof:name":"Jarico Studios",
    "wof:placetype":"venue"
},
  "geometry": {"coordinates":[-89.127832,42.220913],"type":"Point"}
}