{
  "type": "Feature",
  "properties": {
    "iso:country":"US",
    "sg:address":"701 10th St",
    "sg:city":"North Chicago",
    "sg:classifiers":[
        {
            "category":"Health Services",
            "subcategory":"Doctor",
            "type":"Services"
        }
    ],
    "sg:phone":"+1 847 473 4030",
    "sg:postcode":"60064",
    "sg:province":"IL",
    "sg:tags":[
        "medical",
        "center"
    ],
    "wof:name":"Medical Outpatient Clinic",
    "wof:placetype":"venue"
},
  "geometry": {"coordinates":[-87.840721,42.341301],"type":"Point"}
}