{
  "type": "Feature",
  "properties": {
    "iso:country":"US",
    "sg:address":"5678 W Touhy Ave",
    "sg:city":"Niles",
    "sg:classifiers":[
        {
            "category":"Real Estate",
            "subcategory":"Real Estate Services",
            "type":"Services"
        },
        {
            "category":"Retail",
            "subcategory":"Laundry & Dry Cleaning",
            "type":"Services"
        },
        {
            "category":"Building & Trades",
            "subcategory":"Cleaning & Sanitation",
            "type":"Services"
        }
    ],
    "sg:phone":"+1 847 588 0920",
    "sg:postcode":"60714",
    "sg:province":"IL",
    "sg:tags":[
        "house",
        "maintenance",
        "cleaner"
    ],
    "wof:name":"Tdc Niles",
    "wof:placetype":"venue"
},
  "geometry": {"coordinates":[-87.769711,42.011951],"type":"Point"}
}