{
  "type": "Feature",
  "properties": {
    "addr:full":"3926 147th Pl Midlothian IL 60445",
    "addr:housenumber":"3926",
    "addr:postcode":"60445",
    "addr:street":"147Th Pl",
    "iso:country":"US",
    "sg:address":"3926 147th Pl",
    "sg:city":"Midlothian",
    "sg:classifiers":[
        {
            "category":"Restaurant",
            "type":"Food & Drink"
        }
    ],
    "sg:phone":"+1   ",
    "sg:postcode":"60445",
    "sg:province":"IL",
    "sg:tags":[
        "shop",
        "coffee"
    ],
    "wof:name":"Ethereal Ink Inc",
    "wof:placetype":"venue"
},
  "geometry": {"coordinates":[-87.716521,41.624725],"type":"Point"}
}