{
  "type": "Feature",
  "properties": {
    "addr:full":"118 E Main St Arcola IL 61910",
    "addr:housenumber":"118",
    "addr:postcode":"61910",
    "addr:street":"E Main St",
    "iso:country":"US",
    "sg:address":"118 E Main St",
    "sg:city":"Arcola",
    "sg:classifiers":[
        {
            "category":"Manufacturing",
            "subcategory":"Printing",
            "type":"Manufacturing & Wholesale Goods"
        }
    ],
    "sg:phone":"+1 217 268 4950",
    "sg:postcode":"61910",
    "sg:province":"IL",
    "sg:tags":[
        "newspaper"
    ],
    "wof:name":"Arcola Record Herald",
    "wof:placetype":"venue"
},
  "geometry": {"coordinates":[-88.307846,39.684327],"type":"Point"}
}