{
  "type": "Feature",
  "properties": {
    "iso:country":"US",
    "sg:address":"743 Chicago Ave",
    "sg:city":"Evanston",
    "sg:classifiers":[
        {
            "category":"Shopping",
            "subcategory":"Bicycles & Sporting Goods",
            "type":"Retail Goods"
        }
    ],
    "sg:phone":"+1   ",
    "sg:postcode":"60202",
    "sg:province":"IL",
    "wof:name":"Pony Shop",
    "wof:placetype":"venue"
},
  "geometry": {"coordinates":[-87.678405,42.029529],"type":"Point"}
}