{
  "type": "Feature",
  "properties": {
    "iso:country":"US",
    "sg:address":"737 Ficklin St",
    "sg:city":"Mount Carmel",
    "sg:classifiers":[
        {
            "category":"Social Services",
            "subcategory":"Child Care",
            "type":"Services"
        }
    ],
    "sg:phone":"+1 618 262 8225",
    "sg:postcode":"62863",
    "sg:province":"IL",
    "sg:tags":[
        "day"
    ],
    "wof:name":"Dolores Clenedenen",
    "wof:placetype":"venue"
},
  "geometry": {"coordinates":[-87.76875,38.401455],"type":"Point"}
}