{
  "type": "Feature",
  "properties": {
    "iso:country":"US",
    "sg:address":"400 E Washington St",
    "sg:city":"Ottawa",
    "sg:classifiers":[
        {
            "category":"Real Estate",
            "subcategory":"Real Estate Agent",
            "type":"Services"
        }
    ],
    "sg:phone":"+1 815 433 3956",
    "sg:postcode":"61350",
    "sg:province":"IL",
    "sg:tags":[
        "authorities",
        "housing"
    ],
    "wof:name":"Housing Authority For LA Salle",
    "wof:placetype":"venue"
},
  "geometry": {"coordinates":[-88.836218,41.351051],"type":"Point"}
}