{
  "type": "Feature",
  "properties": {
    "addr:full":"201 E Jackson St Ottawa IL 61350",
    "addr:housenumber":"201",
    "addr:postcode":"61350",
    "addr:street":"E Jackson St",
    "iso:country":"US",
    "sg:address":"201 E Jackson St",
    "sg:city":"Ottawa",
    "sg:classifiers":[
        {
            "category":"Recreation",
            "type":"Entertainment"
        }
    ],
    "sg:phone":"+1 815 433 2395",
    "sg:postcode":"61350",
    "sg:province":"IL",
    "sg:tags":[
        "association",
        "child"
    ],
    "wof:name":"YMCA",
    "wof:placetype":"venue"
},
  "geometry": {"coordinates":[-88.84037499999999,41.348866],"type":"Point"}
}