{
  "type": "Feature",
  "properties": {
    "iso:country":"US",
    "sg:address":"4625 W Wellington Ave",
    "sg:city":"Chicago",
    "sg:classifiers":[
        {
            "category":"Parking",
            "type":"Transportation"
        }
    ],
    "sg:phone":"+1 773 685 1454",
    "sg:postcode":"60641",
    "sg:province":"IL",
    "sg:tags":[
        "personal",
        "automobile"
    ],
    "wof:name":"Als Storage LLC",
    "wof:placetype":"venue"
},
  "geometry": {"coordinates":[-87.743471,41.935149],"type":"Point"}
}