{
  "type": "Feature",
  "properties": {
    "addr:full":"937 Moen Ave Rockdale IL 60436",
    "addr:housenumber":"937",
    "addr:postcode":"60436",
    "addr:street":"Moen Ave",
    "iso:country":"US",
    "sg:address":"937 Moen Ave",
    "sg:city":"Rockdale",
    "sg:classifiers":[
        {
            "category":"Building & Trades",
            "subcategory":"Construction",
            "type":"Services"
        }
    ],
    "sg:phone":"+1 815 919 5979",
    "sg:postcode":"60436",
    "sg:province":"IL",
    "sg:tags":[
        "paving",
        "contractor"
    ],
    "wof:name":"Anthonys Sealcoating Svc",
    "wof:placetype":"venue"
},
  "geometry": {"coordinates":[-88.12092,41.505046],"type":"Point"}
}