{
  "type": "Feature",
  "properties": {
    "addr:full":"4547 N Dover St Chicago IL 60640",
    "addr:housenumber":"4547",
    "addr:postcode":"60640",
    "addr:street":"N Dover St",
    "iso:country":"US",
    "sg:address":"4547 N Dover St",
    "sg:city":"Chicago",
    "sg:classifiers":[
        {
            "category":"Health Services",
            "subcategory":"Doctor",
            "type":"Services"
        }
    ],
    "sg:phone":"+1 773 293 4542",
    "sg:postcode":"60640",
    "sg:province":"IL",
    "sg:tags":[
        "medical"
    ],
    "wof:name":"Donna A Camit",
    "wof:placetype":"venue"
},
  "geometry": {"coordinates":[-87.66519700000001,41.964446],"type":"Point"}
}