{
  "type": "Feature",
  "properties": {
    "iso:country":"US",
    "sg:address":"3938 W Roosevelt Rd",
    "sg:city":"Chicago",
    "sg:classifiers":[
        {
            "category":"Shopping",
            "subcategory":"Mobile Phones",
            "type":"Retail Goods"
        }
    ],
    "sg:phone":"+1 773 826 8000",
    "sg:postcode":"60624",
    "sg:province":"IL",
    "wof:name":"Hot Line Wireless & More",
    "wof:placetype":"venue"
},
  "geometry": {"coordinates":[-87.724293,41.866324],"type":"Point"}
}