{
  "type": "Feature",
  "properties": {
    "addr:full":"900 N Shore Dr Lake Bluff IL 60044",
    "addr:housenumber":"900",
    "addr:postcode":"60044",
    "addr:street":"N Shore Dr",
    "iso:country":"US",
    "sg:address":"900 N Shore Dr",
    "sg:city":"Lake Bluff",
    "sg:classifiers":[
        {
            "category":"Insurance",
            "subcategory":"Insurance Agent",
            "type":"Services"
        }
    ],
    "sg:phone":"+1 847 604 7250",
    "sg:postcode":"60044",
    "sg:province":"IL",
    "wof:name":"Northwestern Mutual Insurance",
    "wof:placetype":"venue"
},
  "geometry": {"coordinates":[-87.874211,42.272572],"type":"Point"}
}