{
  "type": "Feature",
  "properties": {
    "iso:country":"US",
    "sg:address":"4646 N Marine Dr",
    "sg:city":"Chicago",
    "sg:classifiers":[
        {
            "category":"Health Services",
            "subcategory":"Doctor",
            "type":"Services"
        }
    ],
    "sg:phone":"+1 773 564 6025",
    "sg:postcode":"60640",
    "sg:province":"IL",
    "wof:name":"Shashoua Abraham MD",
    "wof:placetype":"venue"
},
  "geometry": {"coordinates":[-87.649191,41.966878],"type":"Point"}
}