{
  "type": "Feature",
  "properties": {
    "addr:full":"357 W Chicago Ave Ste 200 Chicago IL 60610",
    "addr:housenumber":"357",
    "addr:postcode":"60610",
    "addr:street":"W Chicago Ave Ste 200",
    "iso:country":"US",
    "sg:address":"357 W Chicago Ave Ste 200",
    "sg:city":"Chicago",
    "sg:classifiers":[
        {
            "category":"Building & Trades",
            "subcategory":"Construction",
            "type":"Services"
        }
    ],
    "sg:phone":"+1 312 787 6640",
    "sg:postcode":"60610",
    "sg:province":"IL",
    "sg:tags":[
        "contractor"
    ],
    "wof:name":"Thrush Construction Co",
    "wof:placetype":"venue"
},
  "geometry": {"coordinates":[-87.637497,41.8964],"type":"Point"}
}