{
  "type": "Feature",
  "properties": {
    "addr:full":"1105 Adams St Lawrenceville IL 62439",
    "addr:housenumber":"1105",
    "addr:postcode":"62439",
    "addr:street":"Adams St",
    "iso:country":"US",
    "sg:address":"1105 Adams St",
    "sg:city":"Lawrenceville",
    "sg:classifiers":[
        {
            "category":"Manufacturing",
            "subcategory":"Petroleum Products",
            "type":"Manufacturing & Wholesale Goods"
        }
    ],
    "sg:phone":"+1 618 943 2615",
    "sg:postcode":"62439",
    "sg:province":"IL",
    "sg:tags":[
        "asphalt"
    ],
    "wof:name":"Emulsions Inc",
    "wof:placetype":"venue"
},
  "geometry": {"coordinates":[-87.682455,38.716682],"type":"Point"}
}