{
  "type": "Feature",
  "properties": {
    "iso:country":"US",
    "sg:address":"4004 S Archer Ave",
    "sg:city":"Chicago",
    "sg:classifiers":[
        {
            "category":"Wholesale",
            "subcategory":"Office Equipment",
            "type":"Manufacturing & Wholesale Goods"
        },
        {
            "category":"Professional",
            "subcategory":"Accounting & Tax Preparation",
            "type":"Services"
        }
    ],
    "sg:phone":"+1 773 254 2900",
    "sg:postcode":"60632",
    "sg:province":"IL",
    "sg:tags":[
        "machine",
        "bookkeeping",
        "return",
        "supply"
    ],
    "wof:name":"Murillo's Tax Svc",
    "wof:placetype":"venue"
},
  "geometry": {"coordinates":[-87.69305199999999,41.820946],"type":"Point"}
}