{
  "type": "Feature",
  "properties": {
    "iso:country":"US",
    "sg:address":"2014 Oakdale Estates Dr",
    "sg:city":"Plainfield",
    "sg:classifiers":[
        {
            "category":"Real Estate",
            "subcategory":"Real Estate Services",
            "type":"Services"
        },
        {
            "category":"Real Estate",
            "subcategory":"Real Estate Agent",
            "type":"Services"
        }
    ],
    "sg:phone":"+1 815 254 3859",
    "sg:postcode":"60586",
    "sg:province":"IL",
    "sg:tags":[
        "buyer",
        "broker"
    ],
    "wof:name":"Collins' Realty",
    "wof:placetype":"venue"
},
  "geometry": {"coordinates":[-88.2106,41.558143],"type":"Point"}
}