{
  "type": "Feature",
  "properties": {
    "addr:full":"9201 Christine Ct Orland Park IL 60462",
    "addr:housenumber":"9201",
    "addr:postcode":"60462",
    "addr:street":"Christine Ct",
    "iso:country":"US",
    "sg:address":"9201 Christine Ct",
    "sg:city":"Orland Park",
    "sg:classifiers":[
        {
            "category":"Building & Trades",
            "subcategory":"Plumbing",
            "type":"Services"
        }
    ],
    "sg:phone":"+1 708 873 1876",
    "sg:postcode":"60462",
    "sg:province":"IL",
    "sg:tags":[
        "contractor"
    ],
    "wof:name":"Extra Plumbing Co",
    "wof:placetype":"venue"
},
  "geometry": {"coordinates":[-87.84461899999999,41.631671],"type":"Point"}
}