{
  "type": "Feature",
  "properties": {
    "addr:full":"12 S Dryden Pl Arlington Hts IL 60004",
    "addr:housenumber":"12",
    "addr:postcode":"60004",
    "addr:street":"S Dryden Pl",
    "iso:country":"US",
    "sg:address":"12 S Dryden Pl",
    "sg:city":"Arlington Hts",
    "sg:classifiers":[
        {
            "category":"Professional",
            "subcategory":"Business Services",
            "type":"Services"
        }
    ],
    "sg:phone":"+1 847 255 2500",
    "sg:postcode":"60004",
    "sg:province":"IL",
    "sg:tags":[
        "interior",
        "consultant",
        "design",
        "decorator"
    ],
    "wof:name":"Callalily Inc",
    "wof:placetype":"venue"
},
  "geometry": {"coordinates":[-87.97085800000001,42.081103],"type":"Point"}
}