{
  "type": "Feature",
  "properties": {
    "addr:full":"501 63rd St Downers Grove IL 60516",
    "addr:housenumber":"501",
    "addr:postcode":"60516",
    "addr:street":"63Rd St",
    "iso:country":"US",
    "sg:address":"501 63rd St",
    "sg:city":"Downers Grove",
    "sg:classifiers":[
        {
            "category":"Professional",
            "subcategory":"Computer Services",
            "type":"Services"
        }
    ],
    "sg:phone":"+1 630 512 0379",
    "sg:postcode":"60516",
    "sg:province":"IL",
    "sg:tags":[
        "processing",
        "datum"
    ],
    "wof:name":"ANS Uunet",
    "wof:placetype":"venue"
},
  "geometry": {"coordinates":[-87.99622599999999,41.773181],"type":"Point"}
}