{
  "type": "Feature",
  "properties": {
    "iso:country":"US",
    "sg:address":"205 S Northwest Hwy",
    "sg:city":"Park Ridge",
    "sg:classifiers":[
        {
            "category":"Professional",
            "subcategory":"Credit Reporting & Collection",
            "type":"Services"
        }
    ],
    "sg:phone":"+1 847 698 7700",
    "sg:postcode":"60068",
    "sg:province":"IL",
    "sg:tags":[
        "legal"
    ],
    "wof:name":"Cosmopolitan Service Corp",
    "wof:placetype":"venue"
},
  "geometry": {"coordinates":[-87.823284,42.007427],"type":"Point"}
}