{
  "type": "Feature",
  "properties": {
    "addr:full":"1707 24th St Rockford IL 61108",
    "addr:housenumber":"1707",
    "addr:postcode":"61108",
    "addr:street":"24Th St",
    "iso:country":"US",
    "sg:address":"1707 24th St",
    "sg:city":"Rockford",
    "sg:classifiers":[
        {
            "category":"Professional",
            "type":"Services"
        }
    ],
    "sg:phone":"+1 815 397 8941",
    "sg:postcode":"61108",
    "sg:province":"IL",
    "sg:tags":[
        "establishment"
    ],
    "wof:name":"Mary Mc Dade Premiere Designs",
    "wof:placetype":"venue"
},
  "geometry": {"coordinates":[-89.052091,42.24924],"type":"Point"}
}