{
  "type": "Feature",
  "properties": {
    "iso:country":"US",
    "sg:address":"342 E 35th St",
    "sg:city":"Chicago",
    "sg:classifiers":[
        {
            "category":"Building & Trades",
            "subcategory":"Locksmith",
            "type":"Services"
        }
    ],
    "sg:phone":"+1 312 577 7211",
    "sg:postcode":"60616",
    "sg:province":"IL",
    "sg:tags":[
        "key"
    ],
    "wof:name":"24Hr All Chicago Locksmith and Lockout",
    "wof:placetype":"venue"
},
  "geometry": {"coordinates":[-87.618094,41.831248],"type":"Point"}
}