{
  "type": "Feature",
  "properties": {
    "iso:country":"US",
    "sg:address":"1770 Birchwood Ave",
    "sg:city":"Des Plaines",
    "sg:classifiers":[
        {
            "category":"Manufacturing",
            "subcategory":"Metals",
            "type":"Manufacturing & Wholesale Goods"
        }
    ],
    "sg:phone":"+1 847 795 9555",
    "sg:postcode":"60018",
    "sg:province":"IL",
    "sg:tags":[
        "video",
        "audio",
        "electronic",
        "cable",
        "mfg"
    ],
    "sg:website":"www.gepco.com",
    "wof:name":"Gepco International Inc",
    "wof:placetype":"venue"
},
  "geometry": {"coordinates":[-87.886313,42.015009],"type":"Point"}
}