{
  "type": "Feature",
  "properties": {
    "addr:full":"103 W Main St Cary IL 60013",
    "addr:housenumber":"103",
    "addr:postcode":"60013",
    "addr:street":"W Main St",
    "iso:country":"US",
    "sg:address":"103 W Main St",
    "sg:city":"Cary",
    "sg:classifiers":[
        {
            "category":"Shopping",
            "subcategory":"Florist",
            "type":"Retail Goods"
        }
    ],
    "sg:phone":"+1   ",
    "sg:postcode":"60013",
    "sg:province":"IL",
    "wof:name":"Periwinkle Florals",
    "wof:placetype":"venue"
},
  "geometry": {"coordinates":[-88.24133999999999,42.208614],"type":"Point"}
}