{
  "type": "Feature",
  "properties": {
    "iso:country":"US",
    "sg:address":"2916 N Broadway Street",
    "sg:city":"Chicago",
    "sg:classifiers":[
        {
            "category":"Bars & Pubs",
            "type":"Food & Drink"
        },
        {
            "category":"Restaurant",
            "type":"Food & Drink"
        }
    ],
    "sg:phone":"+1 773 975 7000",
    "sg:postcode":"60657",
    "sg:province":"IL",
    "sg:tags":[
        "traditional",
        "american"
    ],
    "sg:website":"avenuetavern.com/",
    "wof:name":"The Avenue Tavern",
    "wof:placetype":"venue"
},
  "geometry": {"coordinates":[-87.64425,41.935112],"type":"Point"}
}