{
  "type": "Feature",
  "properties": {
    "addr:full":"1219 Parmele St Rockford IL 61104",
    "addr:housenumber":"1219",
    "addr:postcode":"61104",
    "addr:street":"Parmele St",
    "iso:country":"US",
    "sg:address":"1219 Parmele St",
    "sg:city":"Rockford",
    "sg:classifiers":[
        {
            "category":"Shopping",
            "subcategory":"Clothing, Apparel, & Fashions",
            "type":"Retail Goods"
        }
    ],
    "sg:phone":"+1 815 962 9894",
    "sg:postcode":"61104",
    "sg:province":"IL",
    "sg:tags":[
        "lingerie"
    ],
    "wof:name":"Curtisa's Lingerie",
    "wof:placetype":"venue"
},
  "geometry": {"coordinates":[-89.073707,42.254394],"type":"Point"}
}