{
  "type": "Feature",
  "properties": {
    "addr:full":"508 E State St Rockford IL 61104",
    "addr:housenumber":"508",
    "addr:postcode":"61104",
    "addr:street":"E State St",
    "iso:country":"US",
    "sg:address":"508 E State St",
    "sg:city":"Rockford",
    "sg:classifiers":[
        {
            "category":"Sports & Exercise",
            "subcategory":"Gym",
            "type":"Entertainment"
        }
    ],
    "sg:phone":"+1 815 966 3550",
    "sg:postcode":"61104",
    "sg:province":"IL",
    "sg:tags":[
        "fitness",
        "skin",
        "physical",
        "care",
        "facility"
    ],
    "sg:website":"http://www.5spa.com",
    "wof:name":"5 Spa",
    "wof:placetype":"venue"
},
  "geometry": {"coordinates":[-89.087497,42.267609],"type":"Point"}
}