{
  "type": "Feature",
  "properties": {
    "iso:country":"US",
    "sg:address":"6004 W Belmont Ave",
    "sg:city":"Chicago",
    "sg:classifiers":[
        {
            "category":"Bars & Pubs",
            "subcategory":"Lounge",
            "type":"Food & Drink"
        },
        {
            "category":"Restaurant",
            "type":"Food & Drink"
        }
    ],
    "sg:phone":"+1 773 777 7277",
    "sg:postcode":"60634",
    "sg:province":"IL",
    "wof:name":"Krokodile",
    "wof:placetype":"venue"
},
  "geometry": {"coordinates":[-87.77623699999999,41.938356],"type":"Point"}
}