{
  "type": "Feature",
  "properties": {
    "iso:country":"US",
    "sg:address":"315 W Illinois St",
    "sg:city":"Wheaton",
    "sg:classifiers":[
        {
            "category":"Professional",
            "subcategory":"Business Services",
            "type":"Services"
        }
    ],
    "sg:phone":"+1 630 665 2250",
    "sg:postcode":"60187",
    "sg:province":"IL",
    "sg:tags":[
        "organization",
        "religious"
    ],
    "wof:name":"St Michael Cathlic Church Schl",
    "wof:placetype":"venue"
},
  "geometry": {"coordinates":[-88.111288,41.862169],"type":"Point"}
}