{
  "type": "Feature",
  "properties": {
    "iso:country":"US",
    "sg:address":"927 S Mount Prospect Rd",
    "sg:city":"Des Plaines",
    "sg:classifiers":[
        {
            "category":"Building & Trades",
            "subcategory":"Construction",
            "type":"Services"
        }
    ],
    "sg:phone":"+1 847 297 8320",
    "sg:postcode":"60016",
    "sg:province":"IL",
    "sg:tags":[
        "residential",
        "general",
        "commercial",
        "contractor"
    ],
    "wof:name":"Richard R-B Construction Inc",
    "wof:placetype":"venue"
},
  "geometry": {"coordinates":[-87.920901,42.035105],"type":"Point"}
}