{
  "type": "Feature",
  "properties": {
    "addr:full":"163 N Humphrey Ave Oak Park IL 60302",
    "addr:housenumber":"163",
    "addr:postcode":"60302",
    "addr:street":"N Humphrey Ave",
    "iso:country":"US",
    "sg:address":"163 N Humphrey Ave",
    "sg:city":"Oak Park",
    "sg:classifiers":[
        {
            "category":"Health Services",
            "subcategory":"Clinic",
            "type":"Services"
        }
    ],
    "sg:phone":"+1 708 445 1651",
    "sg:postcode":"60302",
    "sg:province":"IL",
    "sg:tags":[
        "counseling",
        "mental"
    ],
    "sg:website":"www.zlmc.org",
    "wof:name":"Zen Life & Meditation Center Chicago",
    "wof:placetype":"venue"
},
  "geometry": {"coordinates":[-87.777045,41.889767],"type":"Point"}
}