{
  "type": "Feature",
  "properties": {
    "addr:full":"10661 S Roberts Rd Palos Hills IL 60465",
    "addr:housenumber":"10661",
    "addr:postcode":"60465",
    "addr:street":"S Roberts Rd",
    "iso:country":"US",
    "sg:address":"10661 S Roberts Rd",
    "sg:city":"Palos Hills",
    "sg:classifiers":[
        {
            "category":"Recreation",
            "subcategory":"Amusement Park",
            "type":"Entertainment"
        }
    ],
    "sg:phone":"+1 708 974 3380",
    "sg:postcode":"60465",
    "sg:province":"IL",
    "wof:name":"Bigtexamuesment LLC",
    "wof:placetype":"venue"
},
  "geometry": {"coordinates":[-87.817009,41.698104],"type":"Point"}
}