{
  "type": "Feature",
  "properties": {
    "iso:country":"US",
    "sg:address":"Chicago O'Hare Airport Terminal 3",
    "sg:city":"Chicago",
    "sg:classifiers":[
        {
            "category":"Restaurant",
            "type":"Food & Drink"
        }
    ],
    "sg:phone":"+1 773 686 6134",
    "sg:postcode":"60666",
    "sg:province":"IL",
    "sg:tags":[
        "new",
        "american"
    ],
    "sg:website":"www.wolfgangpuck.com",
    "wof:name":"Wolfgang Puck Gourmet Express",
    "wof:placetype":"venue"
},
  "geometry": {"coordinates":[-87.661377,41.677559],"type":"Point"}
}