{
  "type": "Feature",
  "properties": {
    "addr:full":"2 W Market St Shannon IL 61078",
    "addr:housenumber":"2",
    "addr:postcode":"61078",
    "addr:street":"W Market St",
    "iso:country":"US",
    "sg:address":"2 W Market St",
    "sg:city":"Shannon",
    "sg:classifiers":[
        {
            "category":"Personal",
            "type":"Services"
        }
    ],
    "sg:phone":"+1 815 864 3202",
    "sg:postcode":"61078",
    "sg:province":"IL",
    "sg:tags":[
        "program",
        "physical",
        "exercise",
        "fitness"
    ],
    "wof:name":"Tan & Tone",
    "wof:placetype":"venue"
},
  "geometry": {"coordinates":[-89.740371,42.154614],"type":"Point"}
}