{
  "type": "Feature",
  "properties": {
    "addr:full":"4961 W Diversey Ave Chicago IL 60639",
    "addr:housenumber":"4961",
    "addr:postcode":"60639",
    "addr:street":"W Diversey Ave",
    "iso:country":"US",
    "sg:address":"4961 W Diversey Ave",
    "sg:city":"Chicago",
    "sg:classifiers":[
        {
            "category":"Personal",
            "subcategory":"Psychics & Astrologers",
            "type":"Services"
        }
    ],
    "sg:phone":"+1 773 637 7715",
    "sg:postcode":"60639",
    "sg:province":"IL",
    "sg:tags":[
        "medium"
    ],
    "wof:name":"Psychic Readings By Pauline",
    "wof:placetype":"venue"
},
  "geometry": {"coordinates":[-87.750542,41.931492],"type":"Point"}
}