{
  "type": "Feature",
  "properties": {
    "addr:full":"202 W Court St Kankakee IL 60901",
    "addr:housenumber":"202",
    "addr:postcode":"60901",
    "addr:street":"W Court St",
    "iso:country":"US",
    "sg:address":"202 W Court St",
    "sg:city":"Kankakee",
    "sg:classifiers":[
        {
            "category":"Shopping",
            "subcategory":"Used Merchandise",
            "type":"Retail Goods"
        }
    ],
    "sg:phone":"+1 815 933 3171",
    "sg:postcode":"60901",
    "sg:province":"IL",
    "sg:tags":[
        "antique"
    ],
    "wof:name":"Treasure Cove",
    "wof:placetype":"venue"
},
  "geometry": {"coordinates":[-87.86893600000001,41.120814],"type":"Point"}
}