{
  "type": "Feature",
  "properties": {
    "addr:full":"690 W Echo Ln Palatine IL 60067",
    "addr:housenumber":"690",
    "addr:postcode":"60067",
    "addr:street":"W Echo Ln",
    "iso:country":"US",
    "sg:address":"690 W Echo Ln",
    "sg:city":"Palatine",
    "sg:classifiers":[
        {
            "category":"Building & Trades",
            "subcategory":"Construction",
            "type":"Services"
        }
    ],
    "sg:phone":"+1 847 358 6560",
    "sg:postcode":"60067",
    "sg:province":"IL",
    "sg:tags":[
        "house"
    ],
    "wof:name":"Rj Becker Construction Inc",
    "wof:placetype":"venue"
},
  "geometry": {"coordinates":[-88.060406,42.132219],"type":"Point"}
}