{
  "type": "Feature",
  "properties": {
    "addr:full":"2250 Point Blvd Elgin IL 60123",
    "addr:housenumber":"2250",
    "addr:postcode":"60123",
    "addr:street":"Point Blvd",
    "iso:country":"US",
    "sg:address":"2250 Point Blvd",
    "sg:city":"Elgin",
    "sg:classifiers":[
        {
            "category":"Restaurant",
            "type":"Food & Drink"
        }
    ],
    "sg:phone":"+1 847 844 1088",
    "sg:postcode":"60123",
    "sg:province":"IL",
    "sg:tags":[
        "delicatessen"
    ],
    "wof:name":"Panini Grill",
    "wof:placetype":"venue"
},
  "geometry": {"coordinates":[-88.331575,42.081202],"type":"Point"}
}