{
  "type": "Feature",
  "properties": {
    "addr:full":"375 Polo Club Dr Glendale Heights IL 60139",
    "addr:housenumber":"375",
    "addr:postcode":"60139",
    "addr:street":"Polo Club Dr",
    "iso:country":"US",
    "sg:address":"375 Polo Club Dr",
    "sg:city":"Glendale Heights",
    "sg:classifiers":[
        {
            "category":"Retail",
            "subcategory":"Repair Shop",
            "type":"Services"
        }
    ],
    "sg:phone":"+1 630 469 6332",
    "sg:postcode":"60139",
    "sg:province":"IL",
    "sg:tags":[
        "lock",
        "locksmith"
    ],
    "wof:name":"A & B Lock Svc LTD",
    "wof:placetype":"venue"
},
  "geometry": {"coordinates":[-88.073369,41.92177],"type":"Point"}
}