{
  "type": "Feature",
  "properties": {
    "iso:country":"US",
    "sg:address":"1212 N 12th Ave",
    "sg:city":"Melrose Park",
    "sg:classifiers":[
        {
            "category":"Building & Trades",
            "subcategory":"Construction",
            "type":"Services"
        }
    ],
    "sg:phone":"+1 708 344 8637",
    "sg:postcode":"60160",
    "sg:province":"IL",
    "sg:tags":[
        "contractor"
    ],
    "wof:name":"Fbc Construction & Remodeling",
    "wof:placetype":"venue"
},
  "geometry": {"coordinates":[-87.84845900000001,41.897965],"type":"Point"}
}