{
  "type": "Feature",
  "properties": {
    "addr:full":"553 S Arthur Ave Arlington Hts IL 60005",
    "addr:housenumber":"553",
    "addr:postcode":"60005",
    "addr:street":"S Arthur Ave",
    "iso:country":"US",
    "sg:address":"553 S Arthur Ave",
    "sg:city":"Arlington Hts",
    "sg:classifiers":[
        {
            "category":"Autos & Motor Vehicles",
            "subcategory":"Auto Supplies",
            "type":"Retail Goods"
        },
        {
            "category":"Retail",
            "subcategory":"Auto Repair",
            "type":"Services"
        }
    ],
    "sg:phone":"+1 847 259 6960",
    "sg:postcode":"60005",
    "sg:province":"IL",
    "sg:tags":[
        "equipment",
        "racing",
        "automobile",
        "car",
        "general"
    ],
    "wof:name":"Garage Kawi",
    "wof:placetype":"venue"
},
  "geometry": {"coordinates":[-87.96597800000001,42.075516],"type":"Point"}
}