{
  "type": "Feature",
  "properties": {
    "iso:country":"US",
    "sg:address":"3757 38th Ave",
    "sg:city":"Moline",
    "sg:classifiers":[
        {
            "category":"Health Services",
            "subcategory":"Health Practitioner",
            "type":"Services"
        },
        {
            "category":"Health Services",
            "subcategory":"Chiropractor",
            "type":"Services"
        }
    ],
    "sg:phone":"+1 309 762 9662",
    "sg:postcode":"61265",
    "sg:province":"IL",
    "sg:tags":[
        "naturopathic/holistic"
    ],
    "wof:name":"Leasenby Michael Dr",
    "wof:placetype":"venue"
},
  "geometry": {"coordinates":[-90.485266,41.472704],"type":"Point"}
}