{
  "type": "Feature",
  "properties": {
    "iso:country":"US",
    "sg:address":"1900 S 1st St",
    "sg:city":"Champaign",
    "sg:classifiers":[
        {
            "category":"Travel",
            "subcategory":"Hotels & Motels",
            "type":"Entertainment"
        },
        {
            "category":"Retail",
            "subcategory":"Event Space",
            "type":"Services"
        }
    ],
    "sg:phone":"+1 217 819 5000",
    "sg:postcode":"61820",
    "sg:province":"IL",
    "sg:tags":[
        "venue"
    ],
    "sg:website":"www.stayatthei.com",
    "wof:name":"I Hotel & Conference Center",
    "wof:placetype":"venue"
},
  "geometry": {"coordinates":[-88.238247,40.09266],"type":"Point"}
}