{
  "type": "Feature",
  "properties": {
    "iso:country":"US",
    "sg:address":"576 Red Hill Trl",
    "sg:city":"Carol Stream",
    "sg:classifiers":[
        {
            "category":"Professional",
            "subcategory":"Business Services",
            "type":"Services"
        }
    ],
    "sg:phone":"+1 630 281 1333",
    "sg:postcode":"60188",
    "sg:province":"IL",
    "sg:tags":[
        "interior",
        "design"
    ],
    "wof:name":"Designing Woman A",
    "wof:placetype":"venue"
},
  "geometry": {"coordinates":[-88.121109,41.918702],"type":"Point"}
}