{
  "type": "Feature",
  "properties": {
    "addr:full":"8260 W 95th St Hickory Hills IL 60457",
    "addr:housenumber":"8260",
    "addr:postcode":"60457",
    "addr:street":"W 95Th St",
    "iso:country":"US",
    "sg:address":"8260 W 95th St",
    "sg:city":"Hickory Hills",
    "sg:classifiers":[
        {
            "category":"Health Services",
            "subcategory":"Doctor",
            "type":"Services"
        }
    ],
    "sg:phone":"+1 708 599 7100",
    "sg:postcode":"60457",
    "sg:province":"IL",
    "sg:tags":[
        "surgeon",
        "oral"
    ],
    "wof:name":"Soltes Jas F DDS",
    "wof:placetype":"venue"
},
  "geometry": {"coordinates":[-87.823898,41.7183],"type":"Point"}
}