{
  "type": "Feature",
  "properties": {
    "iso:country":"US",
    "sg:address":"814 E 47th Pl Ste 1",
    "sg:city":"Chicago",
    "sg:classifiers":[
        {
            "category":"Organizations",
            "subcategory":"Community Association",
            "type":"Services"
        }
    ],
    "sg:phone":"+1 312 498 7175",
    "sg:postcode":"60615",
    "sg:province":"IL",
    "wof:name":"Chicago Transitional Services, Inc.",
    "wof:placetype":"venue"
},
  "geometry": {"coordinates":[-87.606345,41.80864],"type":"Point"}
}