{
  "type": "Feature",
  "properties": {
    "iso:country":"US",
    "sg:address":"712 S Louis St",
    "sg:city":"Mount Prospect",
    "sg:classifiers":[
        {
            "category":"Professional",
            "subcategory":"Lawyer & Legal Services",
            "type":"Services"
        }
    ],
    "sg:phone":"+1 847 870 7800",
    "sg:postcode":"60056",
    "sg:province":"IL",
    "wof:name":"Natoli Glria A Attorney At Law",
    "wof:placetype":"venue"
},
  "geometry": {"coordinates":[-87.92747,42.053909],"type":"Point"}
}