{
  "type": "Feature",
  "properties": {
    "addr:full":"8506 Kedvale Ave Skokie IL 60076",
    "addr:housenumber":"8506",
    "addr:postcode":"60076",
    "addr:street":"Kedvale Ave",
    "iso:country":"US",
    "sg:address":"8506 Kedvale Ave",
    "sg:city":"Skokie",
    "sg:classifiers":[
        {
            "category":"Building & Trades",
            "subcategory":"Electrical",
            "type":"Services"
        },
        {
            "category":"Building & Trades",
            "subcategory":"Plumbing",
            "type":"Services"
        }
    ],
    "sg:phone":"+1 847 675 5489",
    "sg:postcode":"60076",
    "sg:province":"IL",
    "sg:tags":[
        "installation",
        "lighting",
        "sprinkler",
        "landscape"
    ],
    "wof:name":"Chicago Sprinkler Company",
    "wof:placetype":"venue"
},
  "geometry": {"coordinates":[-87.731583,42.037026],"type":"Point"}
}