{
  "type": "Feature",
  "properties": {
    "addr:full":"633 E Fairchild St Danville IL 61832",
    "addr:housenumber":"633",
    "addr:postcode":"61832",
    "addr:street":"E Fairchild St",
    "iso:country":"US",
    "sg:address":"633 E Fairchild St",
    "sg:city":"Danville",
    "sg:classifiers":[
        {
            "category":"Personal",
            "subcategory":"Barber",
            "type":"Services"
        }
    ],
    "sg:phone":"+1 217 446 8592",
    "sg:postcode":"61832",
    "sg:province":"IL",
    "sg:tags":[
        "shop"
    ],
    "wof:name":"Reigle Barber Shop",
    "wof:placetype":"venue"
},
  "geometry": {"coordinates":[-87.618273,40.139002],"type":"Point"}
}