{
  "type": "Feature",
  "properties": {
    "addr:full":"695 Cole St Bushnell IL 61422",
    "addr:housenumber":"695",
    "addr:postcode":"61422",
    "addr:street":"Cole St",
    "iso:country":"US",
    "sg:address":"695 Cole St",
    "sg:city":"Bushnell",
    "sg:classifiers":[
        {
            "category":"Restaurant",
            "type":"Food & Drink"
        },
        {
            "category":"Food & Beverages",
            "subcategory":"Groceries & Convenience Stores",
            "type":"Retail Goods"
        }
    ],
    "sg:phone":"+1 309 772 3466",
    "sg:postcode":"61422",
    "sg:province":"IL",
    "sg:tags":[
        "pizza"
    ],
    "sg:website":"http://caseys.com",
    "wof:name":"Casey's General Store",
    "wof:placetype":"venue"
},
  "geometry": {"coordinates":[-90.501581,40.552228],"type":"Point"}
}