{
  "type": "Feature",
  "properties": {
    "iso:country":"US",
    "sg:address":"2711 W 71st Street",
    "sg:city":"Chicago",
    "sg:classifiers":[
        {
            "category":"Communications",
            "subcategory":"Radio Station",
            "type":"Services"
        }
    ],
    "sg:phone":"+1 773 476 2242",
    "sg:postcode":"60629",
    "sg:province":"IL",
    "wof:name":"Margutis Daily Radio",
    "wof:placetype":"venue"
},
  "geometry": {"coordinates":[-87.690899,41.764376],"type":"Point"}
}