{
  "type": "Feature",
  "properties": {
    "addr:full":"710 Washington Ave Cairo IL 62914",
    "addr:housenumber":"710",
    "addr:postcode":"62914",
    "addr:street":"Washington Ave",
    "iso:country":"US",
    "sg:address":"710 Washington Ave",
    "sg:city":"Cairo",
    "sg:classifiers":[
        {
            "category":"Building & Trades",
            "subcategory":"Construction",
            "type":"Services"
        }
    ],
    "sg:phone":"+1 618 734 0760",
    "sg:postcode":"62914",
    "sg:province":"IL",
    "sg:tags":[
        "residential",
        "remodeling"
    ],
    "wof:name":"Cairo Window & Siding Sales",
    "wof:placetype":"venue"
},
  "geometry": {"coordinates":[-89.167417,36.999855],"type":"Point"}
}