{
  "type": "Feature",
  "properties": {
    "addr:full":"203 N La Salle Street Chicago IL 60601",
    "addr:housenumber":"203",
    "addr:postcode":"60601",
    "addr:street":"N La Salle Street",
    "iso:country":"US",
    "sg:address":"203 N La Salle Street",
    "sg:city":"Chicago",
    "sg:classifiers":[
        {
            "category":"Shopping",
            "subcategory":"Florist",
            "type":"Retail Goods"
        }
    ],
    "sg:phone":"+1 312 263 6792",
    "sg:postcode":"60601",
    "sg:province":"IL",
    "wof:name":"Flower Island",
    "wof:placetype":"venue"
},
  "geometry": {"coordinates":[-87.632509,41.885807],"type":"Point"}
}