{
  "type": "Feature",
  "properties": {
    "addr:full":"3721 W 111th Street Chicago IL 60655",
    "addr:housenumber":"3721",
    "addr:postcode":"60655",
    "addr:street":"W 111Th Street",
    "iso:country":"US",
    "sg:address":"3721 W 111th Street",
    "sg:city":"Chicago",
    "sg:classifiers":[
        {
            "category":"Park",
            "type":"Public Place"
        }
    ],
    "sg:phone":"+1 312 747 6564",
    "sg:postcode":"60655",
    "sg:province":"IL",
    "wof:name":"Chicago Park District",
    "wof:placetype":"venue"
},
  "geometry": {"coordinates":[-87.726353,41.69107],"type":"Point"}
}