{
  "type": "Feature",
  "properties": {
    "addr:full":"1234 Saint Louis Rd Collinsville IL 62234",
    "addr:housenumber":"1234",
    "addr:postcode":"62234",
    "addr:street":"Saint Louis Rd",
    "iso:country":"US",
    "sg:address":"1234 Saint Louis Rd",
    "sg:city":"Collinsville",
    "sg:classifiers":[
        {
            "category":"Banks & Credit Unions",
            "subcategory":"Investment Brokerage",
            "type":"Services"
        },
        {
            "category":"Banks & Credit Unions",
            "subcategory":"Bank",
            "type":"Services"
        }
    ],
    "sg:phone":"+1 618 344 7153",
    "sg:postcode":"62234",
    "sg:province":"IL",
    "sg:tags":[
        "transfer",
        "stock",
        "broker",
        "agent",
        "bond"
    ],
    "wof:name":"Jedda Financial Services",
    "wof:placetype":"venue"
},
  "geometry": {"coordinates":[-90.010383,38.659106],"type":"Point"}
}