{
  "type": "Feature",
  "properties": {
    "iso:country":"US",
    "sg:address":"101 N Main St",
    "sg:city":"Columbia",
    "sg:classifiers":[
        {
            "category":"Shopping",
            "subcategory":"Pharmacy",
            "type":"Retail Goods"
        }
    ],
    "sg:phone":"+1 618 281 7133",
    "sg:postcode":"62236",
    "sg:province":"IL",
    "sg:tags":[
        "food",
        "supplement",
        "vitamin"
    ],
    "sg:website":"http://www.ronspharmacy.net",
    "wof:name":"Ron's Pharmacy",
    "wof:placetype":"venue"
},
  "geometry": {"coordinates":[-90.19982899999999,38.442909],"type":"Point"}
}