{
  "type": "Feature",
  "properties": {
    "addr:full":"117 W Center St Eureka IL 61530",
    "addr:housenumber":"117",
    "addr:postcode":"61530",
    "addr:street":"W Center St",
    "iso:country":"US",
    "sg:address":"117 W Center St",
    "sg:city":"Eureka",
    "sg:classifiers":[
        {
            "category":"Government",
            "subcategory":"Office",
            "type":"Public Place"
        }
    ],
    "sg:phone":"+1   ",
    "sg:postcode":"61530",
    "sg:province":"IL",
    "sg:tags":[
        "agricultural",
        "regulation",
        "marketing"
    ],
    "wof:name":"Co-Op Extension Ser",
    "wof:placetype":"venue"
},
  "geometry": {"coordinates":[-89.272847,40.721391],"type":"Point"}
}