{
  "type": "Feature",
  "properties": {
    "addr:full":"2220 N Ashland Ave Chicago IL 60614",
    "addr:housenumber":"2220",
    "addr:postcode":"60614",
    "addr:street":"N Ashland Ave",
    "iso:country":"US",
    "sg:address":"2220 N Ashland Ave",
    "sg:city":"Chicago",
    "sg:classifiers":[
        {
            "category":"Restaurant",
            "type":"Food & Drink"
        }
    ],
    "sg:menulink":"http://www.allmenus.com/il/chicago/22567-green-dolphin-street/menu/",
    "sg:phone":"+1 773 395 0066",
    "sg:postcode":"60614",
    "sg:province":"IL",
    "sg:tags":[
        "american"
    ],
    "wof:name":"Green Dolphin Street",
    "wof:placetype":"venue"
},
  "geometry": {"coordinates":[-87.668481,41.922628],"type":"Point"}
}