{
  "type": "Feature",
  "properties": {
    "addr:full":"10498 Weidner Rd Dalton City IL 61925",
    "addr:housenumber":"10498",
    "addr:postcode":"61925",
    "addr:street":"Weidner Rd",
    "iso:country":"US",
    "sg:address":"10498 Weidner Rd",
    "sg:city":"Dalton City",
    "sg:phone":"+1 217 874 2487",
    "sg:postcode":"61925",
    "sg:province":"IL",
    "sg:tags":[
        "farm",
        "corn",
        "soybean"
    ],
    "wof:name":"Fathauer Grainland Inc",
    "wof:placetype":"venue"
},
  "geometry": {"coordinates":[-88.78630099999999,39.740766],"type":"Point"}
}