{
  "type": "Feature",
  "properties": {
    "iso:country":"US",
    "sg:address":"611 1st Ave",
    "sg:city":"Rock Falls",
    "sg:classifiers":[
        {
            "category":"Health Services",
            "subcategory":"Chiropractor",
            "type":"Services"
        }
    ],
    "sg:phone":"+1 815 622 7800",
    "sg:postcode":"61071",
    "sg:province":"IL",
    "wof:name":"Bell Chiropractic Clinic",
    "wof:placetype":"venue"
},
  "geometry": {"coordinates":[-89.68936100000001,41.778769],"type":"Point"}
}