{
  "type": "Feature",
  "properties": {
    "iso:country":"US",
    "sg:address":"3615 27th St",
    "sg:city":"Moline",
    "sg:classifiers":[
        {
            "category":"Shopping",
            "subcategory":"Florist",
            "type":"Retail Goods"
        }
    ],
    "sg:phone":"+1   ",
    "sg:postcode":"61265",
    "sg:province":"IL",
    "wof:name":"Millers Floral Gardens",
    "wof:placetype":"venue"
},
  "geometry": {"coordinates":[-90.49944,41.475945],"type":"Point"}
}