{
  "type": "Feature",
  "properties": {
    "addr:full":"11 S Wolf Rd Prospect Heights IL 60070",
    "addr:housenumber":"11",
    "addr:postcode":"60070",
    "addr:street":"S Wolf Rd",
    "iso:country":"US",
    "sg:address":"11 S Wolf Rd",
    "sg:city":"Prospect Heights",
    "sg:classifiers":[
        {
            "category":"Shopping",
            "subcategory":"Computers & Home Electronics",
            "type":"Retail Goods"
        }
    ],
    "sg:phone":"+1 847 759 9337",
    "sg:postcode":"60070",
    "sg:province":"IL",
    "sg:tags":[
        "equipment",
        "satellite",
        "system"
    ],
    "wof:name":"Expert Communication Inc",
    "wof:placetype":"venue"
},
  "geometry": {"coordinates":[-87.908683,42.091438],"type":"Point"}
}