{
  "type": "Feature",
  "properties": {
    "iso:country":"US",
    "sg:address":"1950 Raymond Dr",
    "sg:city":"Northbrook",
    "sg:classifiers":[
        {
            "category":"Communications",
            "subcategory":"Film & Video Production",
            "type":"Services"
        },
        {
            "category":"Retail",
            "subcategory":"Portrait Studio",
            "type":"Services"
        }
    ],
    "sg:phone":"+1 847 498 2277",
    "sg:postcode":"60062",
    "sg:province":"IL",
    "sg:tags":[
        "photo",
        "taping"
    ],
    "sg:website":"www.fredfox.com",
    "wof:name":"Fred Fox Studios Ltd",
    "wof:placetype":"venue"
},
  "geometry": {"coordinates":[-87.826307,42.111943],"type":"Point"}
}