{
  "type": "Feature",
  "properties": {
    "iso:country":"US",
    "sg:address":"651 W Washington Blvd Ste 205",
    "sg:city":"Chicago",
    "sg:classifiers":[
        {
            "category":"Professional",
            "subcategory":"Lawyer & Legal Services",
            "type":"Services"
        }
    ],
    "sg:phone":"+1 312 357 1110",
    "sg:postcode":"60661",
    "sg:province":"IL",
    "wof:name":"Law Ofcs of Robert D Whitfield",
    "wof:placetype":"venue"
},
  "geometry": {"coordinates":[-87.644395,41.883152],"type":"Point"}
}