{
  "type": "Feature",
  "properties": {
    "addr:full":"3436 N Keating Ave Chicago IL 60641",
    "addr:housenumber":"3436",
    "addr:postcode":"60641",
    "addr:street":"N Keating Ave",
    "iso:country":"US",
    "sg:address":"3436 N Keating Ave",
    "sg:city":"Chicago",
    "sg:classifiers":[
        {
            "category":"Professional",
            "type":"Services"
        }
    ],
    "sg:phone":"+1 773 485 1591",
    "sg:postcode":"60641",
    "sg:province":"IL",
    "sg:tags":[
        "establishment"
    ],
    "wof:name":"Advance Comfort Solutions Inc",
    "wof:placetype":"venue"
},
  "geometry": {"coordinates":[-87.745418,41.943882],"type":"Point"}
}