{
  "type": "Feature",
  "properties": {
    "addr:full":"18661 Dixie Hwy Homewood IL 60430",
    "addr:housenumber":"18661",
    "addr:postcode":"60430",
    "addr:street":"Dixie Hwy",
    "iso:country":"US",
    "sg:address":"18661 Dixie Hwy",
    "sg:city":"Homewood",
    "sg:classifiers":[
        {
            "category":"Personal",
            "subcategory":"Beauty Salon",
            "type":"Services"
        }
    ],
    "sg:phone":"+1 708 798 4471",
    "sg:postcode":"60430",
    "sg:province":"IL",
    "sg:tags":[
        "shop"
    ],
    "wof:name":"Exclusively Yours Limited",
    "wof:placetype":"venue"
},
  "geometry": {"coordinates":[-87.665117,41.549718],"type":"Point"}
}