{
  "type": "Feature",
  "properties": {
    "addr:full":"5922 W Irving Park Rd Chicago IL 60634",
    "addr:housenumber":"5922",
    "addr:postcode":"60634",
    "addr:street":"W Irving Park Rd",
    "iso:country":"US",
    "sg:address":"5922 W Irving Park Rd",
    "sg:city":"Chicago",
    "sg:classifiers":[
        {
            "category":"Food & Beverages",
            "subcategory":"Groceries & Convenience Stores",
            "type":"Retail Goods"
        }
    ],
    "sg:phone":"+1 773 777 7800",
    "sg:postcode":"60634",
    "sg:province":"IL",
    "wof:name":"Boulevard Food Mart",
    "wof:placetype":"venue"
},
  "geometry": {"coordinates":[-87.7752,41.953098],"type":"Point"}
}