{
  "type": "Feature",
  "properties": {
    "iso:country":"US",
    "sg:address":"242 N 800E Rd",
    "sg:city":"Gibson City",
    "sg:phone":"+1 217 749 2284",
    "sg:postcode":"60936",
    "sg:province":"IL",
    "sg:tags":[
        "farm",
        "corn",
        "soybean"
    ],
    "wof:name":"Jerry Oyer",
    "wof:placetype":"venue"
},
  "geometry": {"coordinates":[-88.309906,40.434748],"type":"Point"}
}