{
  "type": "Feature",
  "properties": {
    "iso:country":"US",
    "sg:address":"1201 Franklin St",
    "sg:city":"Rock Falls",
    "sg:classifiers":[
        {
            "category":"Retail",
            "subcategory":"Repair Shop",
            "type":"Services"
        }
    ],
    "sg:phone":"+1 815 625 7930",
    "sg:postcode":"61071",
    "sg:province":"IL",
    "sg:tags":[
        "welding"
    ],
    "wof:name":"Morse Welding",
    "wof:placetype":"venue"
},
  "geometry": {"coordinates":[-89.667481,41.786795],"type":"Point"}
}