{
  "type": "Feature",
  "properties": {
    "addr:full":"2223 W 107th St Chicago IL 60643",
    "addr:housenumber":"2223",
    "addr:postcode":"60643",
    "addr:street":"W 107Th St",
    "iso:country":"US",
    "sg:address":"2223 W 107th St",
    "sg:city":"Chicago",
    "sg:classifiers":[
        {
            "category":"Building & Trades",
            "subcategory":"Electrical",
            "type":"Services"
        }
    ],
    "sg:phone":"+1 773 239 1924",
    "sg:postcode":"60643",
    "sg:province":"IL",
    "sg:tags":[
        "general",
        "electrical",
        "contractor"
    ],
    "wof:name":"Comm Test Electric Inc",
    "wof:placetype":"venue"
},
  "geometry": {"coordinates":[-87.676984,41.69904],"type":"Point"}
}