{
  "type": "Feature",
  "properties": {
    "addr:full":"3 Gundlach Pl Swansea IL 62226",
    "addr:housenumber":"3",
    "addr:postcode":"62226",
    "addr:street":"Gundlach Pl",
    "iso:country":"US",
    "sg:address":"3 Gundlach Pl",
    "sg:city":"Swansea",
    "sg:classifiers":[
        {
            "category":"Social Services",
            "subcategory":"Retirement Home",
            "type":"Services"
        }
    ],
    "sg:phone":"+1 618 233 9825",
    "sg:postcode":"62226",
    "sg:province":"IL",
    "sg:tags":[
        "living",
        "assisted",
        "convalescent",
        "nursing",
        "facility"
    ],
    "wof:name":"Parents & Friends Of Community",
    "wof:placetype":"venue"
},
  "geometry": {"coordinates":[-89.98606100000001,38.528493],"type":"Point"}
}