{
  "type": "Feature",
  "properties": {
    "iso:country":"US",
    "sg:address":"907 Edward Rd",
    "sg:city":"Prospect Heights",
    "sg:classifiers":[
        {
            "category":"Building & Trades",
            "subcategory":"Construction",
            "type":"Services"
        }
    ],
    "sg:phone":"+1 847 297 0046",
    "sg:postcode":"60070",
    "sg:province":"IL",
    "sg:tags":[
        "contractor"
    ],
    "wof:name":"Llewellyn Masonry Inc",
    "wof:placetype":"venue"
},
  "geometry": {"coordinates":[-87.911417,42.092378],"type":"Point"}
}