{
  "type": "Feature",
  "properties": {
    "addr:full":"227 N Hammes Ave Joliet IL 60435",
    "addr:housenumber":"227",
    "addr:postcode":"60435",
    "addr:street":"N Hammes Ave",
    "iso:country":"US",
    "sg:address":"227 N Hammes Ave",
    "sg:city":"Joliet",
    "sg:classifiers":[
        {
            "category":"Health Services",
            "subcategory":"Doctor",
            "type":"Services"
        }
    ],
    "sg:phone":"+1 815 744 2990",
    "sg:postcode":"60435",
    "sg:province":"IL",
    "wof:name":"Clarence J Red DDS Ltd",
    "wof:placetype":"venue"
},
  "geometry": {"coordinates":[-88.132143,41.529094],"type":"Point"}
}