{
  "type": "Feature",
  "properties": {
    "iso:country":"US",
    "sg:address":"1050 N Central Avenue",
    "sg:city":"Chicago",
    "sg:classifiers":[
        {
            "category":"Banks & Credit Unions",
            "subcategory":"Investment Brokerage",
            "type":"Services"
        }
    ],
    "sg:phone":"+1 773 921 4298",
    "sg:postcode":"60651",
    "sg:province":"IL",
    "sg:tags":[
        "investing"
    ],
    "wof:name":"Djs Investors Group",
    "wof:placetype":"venue"
},
  "geometry": {"coordinates":[-87.76531900000001,41.899948],"type":"Point"}
}