{
  "type": "Feature",
  "properties": {
    "addr:full":"20140 N 1400th St Effingham IL 62401",
    "addr:housenumber":"20140",
    "addr:postcode":"62401",
    "addr:street":"N 1400Th St",
    "iso:country":"US",
    "sg:address":"20140 N 1400th St",
    "sg:city":"Effingham",
    "sg:classifiers":[
        {
            "category":"Building & Trades",
            "subcategory":"Construction",
            "type":"Services"
        }
    ],
    "sg:phone":"+1 217 844 4465",
    "sg:postcode":"62401",
    "sg:province":"IL",
    "sg:tags":[
        "house",
        "contractor"
    ],
    "wof:name":"Mette Construction",
    "wof:placetype":"venue"
},
  "geometry": {"coordinates":[-88.545474,39.208806],"type":"Point"}
}