{
  "type": "Feature",
  "properties": {
    "addr:full":"876 Stradford Cir Buffalo Grove IL 60089",
    "addr:housenumber":"876",
    "addr:postcode":"60089",
    "addr:street":"Stradford Cir",
    "iso:country":"US",
    "sg:address":"876 Stradford Cir",
    "sg:city":"Buffalo Grove",
    "sg:classifiers":[
        {
            "category":"Professional",
            "subcategory":"Management & Consulting",
            "type":"Services"
        }
    ],
    "sg:phone":"+1 847 520 5526",
    "sg:postcode":"60089",
    "sg:province":"IL",
    "wof:name":"Bednarz Communications Inc",
    "wof:placetype":"venue"
},
  "geometry": {"coordinates":[-87.977529,42.142103],"type":"Point"}
}