{
  "type": "Feature",
  "properties": {
    "iso:country":"US",
    "sg:address":"5653 N. Clark St",
    "sg:city":"Chicago",
    "sg:classifiers":[
        {
            "category":"Home & Garden",
            "subcategory":"Home Furnishings",
            "type":"Retail Goods"
        }
    ],
    "sg:phone":"+1 773 989 6883",
    "sg:postcode":"60660",
    "sg:province":"IL",
    "sg:tags":[
        "decor"
    ],
    "sg:website":"www.homeaccentschicago.com",
    "wof:name":"Home Accents",
    "wof:placetype":"venue"
},
  "geometry": {"coordinates":[-87.66898399999999,41.984803],"type":"Point"}
}