{
  "type": "Feature",
  "properties": {
    "iso:country":"US",
    "sg:address":"211 Causemaker Dr",
    "sg:city":"Atkinson",
    "sg:classifiers":[
        {
            "category":"Personal",
            "subcategory":"Beauty Salon",
            "type":"Services"
        }
    ],
    "sg:phone":"+1 309 945 4846",
    "sg:postcode":"61235",
    "sg:province":"IL",
    "wof:name":"Shear Creations",
    "wof:placetype":"venue"
},
  "geometry": {"coordinates":[-90.02300099999999,41.419875],"type":"Point"}
}