{
  "type": "Feature",
  "properties": {
    "iso:country":"US",
    "sg:address":"PO Box 549",
    "sg:city":"East Saint Louis",
    "sg:classifiers":[
        {
            "category":"Museum",
            "type":"Entertainment"
        }
    ],
    "sg:phone":"+1 618 874 6480",
    "sg:postcode":"62202",
    "sg:province":"IL",
    "wof:name":"The Dunham Center",
    "wof:placetype":"venue"
},
  "geometry": {"coordinates":[-90.154099,38.622501],"type":"Point"}
}