{
  "type": "Feature",
  "properties": {
    "addr:full":"2189 W Bowler Street Chicago IL 60612",
    "addr:housenumber":"2189",
    "addr:postcode":"60612",
    "addr:street":"W Bowler Street",
    "iso:country":"US",
    "sg:address":"2189 W Bowler Street",
    "sg:city":"Chicago",
    "sg:classifiers":[
        {
            "category":"Education",
            "subcategory":"School",
            "type":"Public Place"
        }
    ],
    "sg:phone":"+1 312 491 1600",
    "sg:postcode":"60612",
    "sg:province":"IL",
    "sg:tags":[
        "high",
        "middle",
        "elementary"
    ],
    "sg:website":"www.chicagohopeacademy.com",
    "wof:name":"Chicago Hope Academy",
    "wof:placetype":"venue"
},
  "geometry": {"coordinates":[-87.680449,41.870292],"type":"Point"}
}