{
  "type": "Feature",
  "properties": {
    "addr:full":"310 Hill St Rockford IL 61107",
    "addr:housenumber":"310",
    "addr:postcode":"61107",
    "addr:street":"Hill St",
    "iso:country":"US",
    "sg:address":"310 Hill St",
    "sg:city":"Rockford",
    "sg:classifiers":[
        {
            "category":"Professional",
            "type":"Services"
        }
    ],
    "sg:phone":"+1 815 964 7416",
    "sg:postcode":"61107",
    "sg:province":"IL",
    "sg:tags":[
        "establishment"
    ],
    "wof:name":"Eckert & Eckert",
    "wof:placetype":"venue"
},
  "geometry": {"coordinates":[-89.085472,42.273281],"type":"Point"}
}