{
  "type": "Feature",
  "properties": {
    "addr:full":"450 Lily Cache Ln Bolingbrook IL 60440",
    "addr:housenumber":"450",
    "addr:postcode":"60440",
    "addr:street":"Lily Cache Ln",
    "iso:country":"US",
    "sg:address":"450 Lily Cache Ln",
    "sg:city":"Bolingbrook",
    "sg:classifiers":[
        {
            "category":"Retail",
            "subcategory":"Car Wash",
            "type":"Services"
        }
    ],
    "sg:phone":"+1 630 378 4983",
    "sg:postcode":"60440",
    "sg:province":"IL",
    "sg:tags":[
        "polishing",
        "washing"
    ],
    "wof:name":"Great Wash Inc",
    "wof:placetype":"venue"
},
  "geometry": {"coordinates":[-88.085194,41.690831],"type":"Point"}
}