{
  "type": "Feature",
  "properties": {
    "iso:country":"US",
    "sg:address":"9144 S Bennett Ave",
    "sg:city":"Chicago",
    "sg:classifiers":[
        {
            "category":"Professional",
            "subcategory":"Lawyer & Legal Services",
            "type":"Services"
        }
    ],
    "sg:phone":"+1 773 978 0909",
    "sg:postcode":"60617",
    "sg:province":"IL",
    "wof:name":"Brown June A Atty",
    "wof:placetype":"venue"
},
  "geometry": {"coordinates":[-87.578102,41.728298],"type":"Point"}
}