{
  "type": "Feature",
  "properties": {
    "iso:country":"US",
    "sg:address":"660 N Park Blvd",
    "sg:city":"Glen Ellyn",
    "sg:classifiers":[
        {
            "category":"Communications",
            "subcategory":"Film & Video Production",
            "type":"Services"
        }
    ],
    "sg:phone":"+1 630 469 8886",
    "sg:postcode":"60137",
    "sg:province":"IL",
    "sg:tags":[
        "merchandise"
    ],
    "wof:name":"New Line Cinema Corporation",
    "wof:placetype":"venue"
},
  "geometry": {"coordinates":[-88.06246899999999,41.884672],"type":"Point"}
}