{
  "type": "Feature",
  "properties": {
    "iso:country":"US",
    "sg:address":"3901 S California Avenue",
    "sg:city":"Chicago",
    "sg:classifiers":[
        {
            "category":"Restaurant",
            "type":"Food & Drink"
        }
    ],
    "sg:phone":"+1 773 927 9228",
    "sg:postcode":"60632",
    "sg:province":"IL",
    "wof:name":"New Happy Chop Suey",
    "wof:placetype":"venue"
},
  "geometry": {"coordinates":[-87.694455,41.82276],"type":"Point"}
}