{
  "type": "Feature",
  "properties": {
    "iso:country":"US",
    "sg:address":"1031 E Burville Rd",
    "sg:city":"Crete",
    "sg:phone":"+1 708 672 3135",
    "sg:postcode":"60417",
    "sg:province":"IL",
    "sg:tags":[
        "farm",
        "corn"
    ],
    "wof:name":"Hansen Mark Farm of",
    "wof:placetype":"venue"
},
  "geometry": {"coordinates":[-87.582993,41.435555],"type":"Point"}
}