{
  "type": "Feature",
  "properties": {
    "iso:country":"US",
    "sg:address":"472 N McLean Blvd",
    "sg:city":"Elgin",
    "sg:classifiers":[
        {
            "category":"Professional",
            "subcategory":"Management & Consulting",
            "type":"Services"
        }
    ],
    "sg:phone":"+1 847 697 2201",
    "sg:postcode":"60123",
    "sg:province":"IL",
    "sg:tags":[
        "resource",
        "search",
        "executive",
        "e",
        "human"
    ],
    "wof:name":"Britay China International Inc",
    "wof:placetype":"venue"
},
  "geometry": {"coordinates":[-88.312689,42.02202],"type":"Point"}
}