{
  "type": "Feature",
  "properties": {
    "addr:full":"5519 W 90th St Oak Lawn IL 60453",
    "addr:housenumber":"5519",
    "addr:postcode":"60453",
    "addr:street":"W 90Th St",
    "iso:country":"US",
    "sg:address":"5519 W 90th St",
    "sg:city":"Oak Lawn",
    "sg:classifiers":[
        {
            "category":"Personal",
            "type":"Services"
        }
    ],
    "sg:phone":"+1 708 423 1800",
    "sg:postcode":"60453",
    "sg:province":"IL",
    "sg:tags":[
        "party",
        "planning",
        "event"
    ],
    "wof:name":"K & R Enterprises of Ol Jump Snow Inc",
    "wof:placetype":"venue"
},
  "geometry": {"coordinates":[-87.75859800000001,41.7286],"type":"Point"}
}