{
  "type": "Feature",
  "properties": {
    "addr:full":"446 Willow Rd Manteno IL 60950",
    "addr:housenumber":"446",
    "addr:postcode":"60950",
    "addr:street":"Willow Rd",
    "iso:country":"US",
    "sg:address":"446 Willow Rd",
    "sg:city":"Manteno",
    "sg:classifiers":[
        {
            "category":"Building & Trades",
            "subcategory":"Construction",
            "type":"Services"
        }
    ],
    "sg:phone":"+1 708 514 1000",
    "sg:postcode":"60950",
    "sg:province":"IL",
    "sg:tags":[
        "contractor",
        "fence-sales"
    ],
    "wof:name":"Aluminum Pvc Fence Expert",
    "wof:placetype":"venue"
},
  "geometry": {"coordinates":[-87.84550400000001,41.255849],"type":"Point"}
}