{
  "type": "Feature",
  "properties": {
    "addr:full":"1745 S 5th Ave Kankakee IL 60901",
    "addr:housenumber":"1745",
    "addr:postcode":"60901",
    "addr:street":"S 5Th Ave",
    "iso:country":"US",
    "sg:address":"1745 S 5th Ave",
    "sg:city":"Kankakee",
    "sg:classifiers":[
        {
            "category":"Building & Trades",
            "subcategory":"Construction",
            "type":"Services"
        }
    ],
    "sg:phone":"+1 815 932 0508",
    "sg:postcode":"60901",
    "sg:province":"IL",
    "sg:tags":[
        "house"
    ],
    "wof:name":"Tutt Enterprises",
    "wof:placetype":"venue"
},
  "geometry": {"coordinates":[-87.87481099999999,41.100479],"type":"Point"}
}