{
  "type": "Feature",
  "properties": {
    "addr:full":"205 N Michigan Ave Ste 2500 Chicago IL 60601",
    "addr:housenumber":"205",
    "addr:postcode":"60601",
    "addr:street":"N Michigan Ave Ste 2500",
    "iso:country":"US",
    "sg:address":"205 N Michigan Ave Ste 2500",
    "sg:city":"Chicago",
    "sg:classifiers":[
        {
            "category":"Professional",
            "subcategory":"Lawyer & Legal Services",
            "type":"Services"
        }
    ],
    "sg:phone":"+1 312 803 7090",
    "sg:postcode":"60601",
    "sg:province":"IL",
    "sg:tags":[
        "attorney",
        "business",
        "tax",
        "planning",
        "plan",
        "real estate",
        "law"
    ],
    "wof:name":"Jones & Quinlisk",
    "wof:placetype":"venue"
},
  "geometry": {"coordinates":[-87.62442299999999,41.885795],"type":"Point"}
}