{
  "type": "Feature",
  "properties": {
    "iso:country":"US",
    "sg:address":"8042 Central Park Ave",
    "sg:city":"Skokie",
    "sg:classifiers":[
        {
            "category":"Retail",
            "subcategory":"Auto Repair",
            "type":"Services"
        }
    ],
    "sg:phone":"+1 847 675 3305",
    "sg:postcode":"60076",
    "sg:province":"IL",
    "sg:tags":[
        "body",
        "automobile",
        "top",
        "upholstery"
    ],
    "wof:name":"Advanced Auto Interiors",
    "wof:placetype":"venue"
},
  "geometry": {"coordinates":[-87.718552,42.027815],"type":"Point"}
}