{
  "type": "Feature",
  "properties": {
    "iso:country":"US",
    "sg:address":"783 Ayers St",
    "sg:city":"Bolingbrook",
    "sg:classifiers":[
        {
            "category":"Manufacturing",
            "subcategory":"Printing",
            "type":"Manufacturing & Wholesale Goods"
        }
    ],
    "sg:phone":"+1 815 609 3650",
    "sg:postcode":"60440",
    "sg:province":"IL",
    "sg:tags":[
        "printer"
    ],
    "wof:name":"Dynamic Printing Source",
    "wof:placetype":"venue"
},
  "geometry": {"coordinates":[-88.093824,41.721442],"type":"Point"}
}