{
  "type": "Feature",
  "properties": {
    "iso:country":"US",
    "sg:address":"2175 Coal Rd",
    "sg:city":"Victoria",
    "sg:phone":"+1 309 879 2731",
    "sg:postcode":"61485",
    "sg:province":"IL",
    "sg:tags":[
        "farm",
        "corn"
    ],
    "wof:name":"Bryan Rollins",
    "wof:placetype":"venue"
},
  "geometry": {"coordinates":[-90.020949,41.053934],"type":"Point"}
}