{
  "type": "Feature",
  "properties": {
    "addr:full":"2722 S King Drive Chicago IL 60616",
    "addr:housenumber":"2722",
    "addr:postcode":"60616",
    "addr:street":"S King Drive",
    "iso:country":"US",
    "sg:address":"2722 S King Drive",
    "sg:city":"Chicago",
    "sg:classifiers":[
        {
            "category":"Education",
            "subcategory":"School",
            "type":"Public Place"
        }
    ],
    "sg:phone":"+1 773 534 9129",
    "sg:postcode":"60616",
    "sg:province":"IL",
    "sg:tags":[
        "high",
        "middle",
        "elementary"
    ],
    "wof:name":"Schools Public",
    "wof:placetype":"venue"
},
  "geometry": {"coordinates":[-87.617552,41.841915],"type":"Point"}
}