{
  "type": "Feature",
  "properties": {
    "iso:country":"US",
    "sg:address":"4650 W Van Buren St",
    "sg:city":"Chicago",
    "sg:classifiers":[
        {
            "category":"Real Estate",
            "subcategory":"Real Estate Operator",
            "type":"Services"
        }
    ],
    "sg:phone":"+1 773 626 5320",
    "sg:postcode":"60644",
    "sg:province":"IL",
    "sg:tags":[
        "building",
        "apartment"
    ],
    "wof:name":"Elois McCoy Village Apts",
    "wof:placetype":"venue"
},
  "geometry": {"coordinates":[-87.741581,41.875141],"type":"Point"}
}