{
  "type": "Feature",
  "properties": {
    "iso:country":"US",
    "sg:address":"1214 S Bataan Rd",
    "sg:city":"Dixon",
    "sg:classifiers":[
        {
            "category":"Utilities",
            "subcategory":"Refuse",
            "type":"Services"
        }
    ],
    "sg:phone":"+1 815 284 7767",
    "sg:postcode":"61021",
    "sg:province":"IL",
    "sg:tags":[
        "disposal",
        "collection"
    ],
    "wof:name":"Finger Refuse Service Inc",
    "wof:placetype":"venue"
},
  "geometry": {"coordinates":[-89.397596,41.728386],"type":"Point"}
}