{
  "type": "Feature",
  "properties": {
    "iso:country":"US",
    "sg:address":"428 S Sheridan Rd",
    "sg:city":"Waukegan",
    "sg:classifiers":[
        {
            "category":"Social Services",
            "type":"Services"
        },
        {
            "category":"Place Of Worship",
            "type":"Public Place"
        },
        {
            "category":"Shopping",
            "subcategory":"Thrift Store",
            "type":"Retail Goods"
        },
        {
            "category":"Banks & Credit Unions",
            "subcategory":"Bank",
            "type":"Services"
        },
        {
            "category":"Shopping",
            "subcategory":"Used Merchandise",
            "type":"Retail Goods"
        }
    ],
    "sg:phone":"+1 847 623 6170",
    "sg:postcode":"60085",
    "sg:province":"IL",
    "sg:tags":[
        "shop",
        "resale",
        "second",
        "church",
        "hand"
    ],
    "sg:website":"http://www.salvationarmyusa.org",
    "wof:name":"Salvation Army",
    "wof:placetype":"venue"
},
  "geometry": {"coordinates":[-87.82951799999999,42.353702],"type":"Point"}
}