{
  "type": "Feature",
  "properties": {
    "addr:full":"4501 W Deyoung St Marion IL 62959",
    "addr:housenumber":"4501",
    "addr:postcode":"62959",
    "addr:street":"W Deyoung St",
    "iso:country":"US",
    "sg:address":"4501 W Deyoung St",
    "sg:city":"Marion",
    "sg:classifiers":[
        {
            "category":"Social Services",
            "type":"Services"
        },
        {
            "category":"Health Services",
            "subcategory":"Clinic",
            "type":"Services"
        },
        {
            "category":"Professional",
            "subcategory":"Employment Agencies",
            "type":"Services"
        },
        {
            "category":"Organizations",
            "subcategory":"Professional Association",
            "type":"Services"
        },
        {
            "category":"Organizations",
            "subcategory":"Community Association",
            "type":"Services"
        },
        {
            "category":"Organizations",
            "subcategory":"Non-profit Organization",
            "type":"Services"
        }
    ],
    "sg:phone":"+1 618 993 1777",
    "sg:postcode":"62959",
    "sg:province":"IL",
    "sg:tags":[
        "business",
        "trade",
        "fund",
        "welfare",
        "employer",
        "raising"
    ],
    "wof:name":"Arthritis Foundation",
    "wof:placetype":"venue"
},
  "geometry": {"coordinates":[-89.00981899999999,37.744961],"type":"Point"}
}