{
  "type": "Feature",
  "properties": {
    "iso:country":"US",
    "sg:address":"382 State Rte 116",
    "sg:city":"Saint Augustine",
    "sg:phone":"+1 309 462 3796",
    "sg:postcode":"61474",
    "sg:province":"IL",
    "sg:tags":[
        "farm",
        "corn",
        "soybean"
    ],
    "wof:name":"Larry Murk",
    "wof:placetype":"venue"
},
  "geometry": {"coordinates":[-90.374444,40.728664],"type":"Point"}
}