{
  "type": "Feature",
  "properties": {
    "addr:full":"215 S Broadway St Havana IL 62644",
    "addr:housenumber":"215",
    "addr:postcode":"62644",
    "addr:street":"S Broadway St",
    "iso:country":"US",
    "sg:address":"215 S Broadway St",
    "sg:city":"Havana",
    "sg:classifiers":[
        {
            "category":"Organizations",
            "subcategory":"Religious Organization",
            "type":"Services"
        }
    ],
    "sg:phone":"+1 309 543 3840",
    "sg:postcode":"62644",
    "sg:province":"IL",
    "wof:name":"Central Christian Church",
    "wof:placetype":"venue"
},
  "geometry": {"coordinates":[-90.06068999999999,40.298804],"type":"Point"}
}