{
  "type": "Feature",
  "properties": {
    "iso:country":"US",
    "sg:address":"305 Tiffany Ct",
    "sg:city":"Champaign",
    "sg:classifiers":[
        {
            "category":"Mining & Drilling",
            "type":"Manufacturing & Wholesale Goods"
        }
    ],
    "sg:phone":"+1 217 356 8111",
    "sg:postcode":"61821",
    "sg:province":"IL",
    "sg:tags":[
        "stone"
    ],
    "wof:name":"Blue Ridge Stone Co",
    "wof:placetype":"venue"
},
  "geometry": {"coordinates":[-88.31810900000001,40.114514],"type":"Point"}
}