{
  "type": "Feature",
  "properties": {
    "addr:full":"33266 Pearl St Kirkland IL 60146",
    "addr:housenumber":"33266",
    "addr:postcode":"60146",
    "addr:street":"Pearl St",
    "iso:country":"US",
    "sg:address":"33266 Pearl St",
    "sg:city":"Kirkland",
    "sg:phone":"+1 815 522 7781",
    "sg:postcode":"60146",
    "sg:province":"IL",
    "sg:tags":[
        "farm",
        "corn",
        "soybean"
    ],
    "wof:name":"Glenn Benson",
    "wof:placetype":"venue"
},
  "geometry": {"coordinates":[-88.84182199999999,42.115926],"type":"Point"}
}