{
  "type": "Feature",
  "properties": {
    "addr:full":"93 E Fabish Dr Buffalo Grove IL 60089",
    "addr:housenumber":"93",
    "addr:postcode":"60089",
    "addr:street":"E Fabish Dr",
    "iso:country":"US",
    "sg:address":"93 E Fabish Dr",
    "sg:city":"Buffalo Grove",
    "sg:classifiers":[
        {
            "category":"Manufacturing",
            "subcategory":"Tools & Machinery",
            "type":"Manufacturing & Wholesale Goods"
        }
    ],
    "sg:phone":"+1 847 520 7237",
    "sg:postcode":"60089",
    "sg:province":"IL",
    "sg:tags":[
        "filter",
        "product",
        "related",
        "mfg"
    ],
    "wof:name":"Machine Tool Filter Systems",
    "wof:placetype":"venue"
},
  "geometry": {"coordinates":[-87.953006,42.170928],"type":"Point"}
}