{
  "type": "Feature",
  "properties": {
    "iso:country":"US",
    "sg:address":"10034 S Princeton Ave",
    "sg:city":"Chicago",
    "sg:classifiers":[
        {
            "category":"Professional",
            "subcategory":"Detective & Security Services",
            "type":"Services"
        }
    ],
    "sg:phone":"+1 773 719 6606",
    "sg:postcode":"60628",
    "sg:province":"IL",
    "sg:tags":[
        "information",
        "bureau"
    ],
    "wof:name":"Kathy Tax Services",
    "wof:placetype":"venue"
},
  "geometry": {"coordinates":[-87.630835,41.711567],"type":"Point"}
}