{
  "type": "Feature",
  "properties": {
    "addr:full":"1348 Busch Pkwy Buffalo Grove IL 60089",
    "addr:housenumber":"1348",
    "addr:postcode":"60089",
    "addr:street":"Busch Pkwy",
    "iso:country":"US",
    "sg:address":"1348 Busch Pkwy",
    "sg:city":"Buffalo Grove",
    "sg:classifiers":[
        {
            "category":"Manufacturing",
            "subcategory":"Tools & Machinery",
            "type":"Manufacturing & Wholesale Goods"
        }
    ],
    "sg:phone":"+1 847 279 1925",
    "sg:postcode":"60089",
    "sg:province":"IL",
    "sg:tags":[
        "carbon",
        "product",
        "graphite",
        "mfg"
    ],
    "wof:name":"Graphtek LLC",
    "wof:placetype":"venue"
},
  "geometry": {"coordinates":[-87.931168,42.171431],"type":"Point"}
}