{
  "type": "Feature",
  "properties": {
    "iso:country":"US",
    "sg:address":"758 N Larrabee St",
    "sg:city":"Chicago",
    "sg:classifiers":[
        {
            "category":"Shopping",
            "type":"Retail Goods"
        }
    ],
    "sg:phone":"+1 917 459 1674",
    "sg:postcode":"60610",
    "sg:province":"IL",
    "sg:website":"www.cyndichan.com",
    "wof:name":"In Time, LLC - Cyndi Chan",
    "wof:placetype":"venue"
},
  "geometry": {"coordinates":[-87.64299699999999,41.896141],"type":"Point"}
}