{
  "type": "Feature",
  "properties": {
    "iso:country":"US",
    "sg:address":"812 Newport Dr",
    "sg:city":"Island Lake",
    "sg:classifiers":[
        {
            "category":"Social Services",
            "subcategory":"Child Care",
            "type":"Services"
        }
    ],
    "sg:phone":"+1 847 526 5305",
    "sg:postcode":"60042",
    "sg:province":"IL",
    "sg:tags":[
        "day"
    ],
    "wof:name":"Eve Veljasevic",
    "wof:placetype":"venue"
},
  "geometry": {"coordinates":[-88.21493599999999,42.277425],"type":"Point"}
}