{
  "type": "Feature",
  "properties": {
    "addr:full":"218 Washington St Waukegan IL 60085",
    "addr:housenumber":"218",
    "addr:postcode":"60085",
    "addr:street":"Washington St",
    "iso:country":"US",
    "sg:address":"218 Washington St",
    "sg:city":"Waukegan",
    "sg:classifiers":[
        {
            "category":"Shopping",
            "subcategory":"Clothing, Apparel, & Fashions",
            "type":"Retail Goods"
        }
    ],
    "sg:phone":"+1 847 249 9007",
    "sg:postcode":"60085",
    "sg:province":"IL",
    "sg:tags":[
        "infant",
        "wear"
    ],
    "wof:name":"Casa Flores",
    "wof:placetype":"venue"
},
  "geometry": {"coordinates":[-87.832446,42.359633],"type":"Point"}
}