{
  "type": "Feature",
  "properties": {
    "iso:country":"US",
    "sg:address":"1 S Northwest Hwy",
    "sg:city":"Park Ridge",
    "sg:classifiers":[
        {
            "category":"Professional",
            "subcategory":"Management & Consulting",
            "type":"Services"
        }
    ],
    "sg:phone":"+1 847 699 9510",
    "sg:postcode":"60068",
    "sg:province":"IL",
    "sg:tags":[
        "business"
    ],
    "wof:name":"Sports Terminal Inc",
    "wof:placetype":"venue"
},
  "geometry": {"coordinates":[-87.827992,42.010266],"type":"Point"}
}