{
  "type": "Feature",
  "properties": {
    "addr:full":"122 Peterson Rd Libertyville IL 60048",
    "addr:housenumber":"122",
    "addr:postcode":"60048",
    "addr:street":"Peterson Rd",
    "iso:country":"US",
    "sg:address":"122 Peterson Rd",
    "sg:city":"Libertyville",
    "sg:classifiers":[
        {
            "category":"Personal",
            "subcategory":"Beauty Salon",
            "type":"Services"
        }
    ],
    "sg:phone":"+1 847 362 0425",
    "sg:postcode":"60048",
    "sg:province":"IL",
    "wof:name":"Hairs 2-U",
    "wof:placetype":"venue"
},
  "geometry": {"coordinates":[-87.960894,42.306023],"type":"Point"}
}