{
  "type": "Feature",
  "properties": {
    "addr:full":"6423 S Cottage Grove Avenue Chicago IL 60637",
    "addr:housenumber":"6423",
    "addr:postcode":"60637",
    "addr:street":"S Cottage Grove Avenue",
    "iso:country":"US",
    "sg:address":"6423 S Cottage Grove Avenue",
    "sg:city":"Chicago",
    "sg:classifiers":[
        {
            "category":"Shopping",
            "subcategory":"Florist",
            "type":"Retail Goods"
        }
    ],
    "sg:phone":"+1 773 667 7353",
    "sg:postcode":"60637",
    "sg:province":"IL",
    "wof:name":"Faye's Flower Affayre",
    "wof:placetype":"venue"
},
  "geometry": {"coordinates":[-87.605653,41.778093],"type":"Point"}
}