{
  "type": "Feature",
  "properties": {
    "iso:country":"US",
    "sg:address":"940 Sheridan Rd",
    "sg:city":"Glencoe",
    "sg:classifiers":[
        {
            "category":"Shopping",
            "subcategory":"Gifts & Souvenirs",
            "type":"Retail Goods"
        }
    ],
    "sg:phone":"+1 847 835 2364",
    "sg:postcode":"60022",
    "sg:province":"IL",
    "sg:tags":[
        "shop"
    ],
    "wof:name":"Mitzi Oht Design Experience Ltd",
    "wof:placetype":"venue"
},
  "geometry": {"coordinates":[-87.75711200000001,42.143031],"type":"Point"}
}