{
  "type": "Feature",
  "properties": {
    "addr:full":"6616 W Irving Park Rd Chicago IL 60634",
    "addr:housenumber":"6616",
    "addr:postcode":"60634",
    "addr:street":"W Irving Park Rd",
    "iso:country":"US",
    "sg:address":"6616 W Irving Park Rd",
    "sg:city":"Chicago",
    "sg:classifiers":[
        {
            "category":"Building & Trades",
            "subcategory":"Electrical",
            "type":"Services"
        }
    ],
    "sg:phone":"+1 773 736 3333",
    "sg:postcode":"60634",
    "sg:province":"IL",
    "sg:tags":[
        "wire",
        "products-wholesale",
        "manufacturer"
    ],
    "sg:website":"http://www.wear-flex.com",
    "wof:name":"Mhs Ltd.",
    "wof:placetype":"venue"
},
  "geometry": {"coordinates":[-87.792011,41.952807],"type":"Point"}
}