{
  "type": "Feature",
  "properties": {
    "iso:country":"US",
    "sg:address":"211 Country Ln",
    "sg:city":"Quincy",
    "sg:classifiers":[
        {
            "category":"Building & Trades",
            "subcategory":"Construction",
            "type":"Services"
        }
    ],
    "sg:phone":"+1 217 885 3335",
    "sg:postcode":"62305",
    "sg:province":"IL",
    "sg:tags":[
        "house"
    ],
    "wof:name":"Weckbach Home Imp",
    "wof:placetype":"venue"
},
  "geometry": {"coordinates":[-91.265441,39.932991],"type":"Point"}
}