{
  "type": "Feature",
  "properties": {
    "iso:country":"US",
    "sg:address":"892 N State St",
    "sg:city":"Lockport",
    "sg:classifiers":[
        {
            "category":"Personal",
            "subcategory":"Beauty Salon",
            "type":"Services"
        }
    ],
    "sg:phone":"+1 815 838 5735",
    "sg:postcode":"60441",
    "sg:province":"IL",
    "sg:tags":[
        "shop"
    ],
    "wof:name":"Hair Downtown",
    "wof:placetype":"venue"
},
  "geometry": {"coordinates":[-88.045993,41.607912],"type":"Point"}
}