{
  "type": "Feature",
  "properties": {
    "iso:country":"US",
    "sg:address":"10450 S Western Ave",
    "sg:city":"Chicago",
    "sg:classifiers":[
        {
            "category":"Shopping",
            "subcategory":"Computers & Home Electronics",
            "type":"Retail Goods"
        }
    ],
    "sg:phone":"+1 773 779 8337",
    "sg:postcode":"60643",
    "sg:province":"IL",
    "sg:tags":[
        "parts",
        "supply"
    ],
    "wof:name":"B2B Supplies Inc",
    "wof:placetype":"venue"
},
  "geometry": {"coordinates":[-87.681603,41.703659],"type":"Point"}
}