{
  "type": "Feature",
  "properties": {
    "iso:country":"US",
    "sg:address":"45 Tower Ln",
    "sg:city":"Elgin",
    "sg:classifiers":[
        {
            "category":"Shopping",
            "subcategory":"Discount & Variety Stores",
            "type":"Retail Goods"
        }
    ],
    "sg:phone":"+1 847 289 5204",
    "sg:postcode":"60181",
    "sg:province":"IL",
    "wof:name":"Dollar Buster Plus Inc",
    "wof:placetype":"venue"
},
  "geometry": {"coordinates":[-87.952789,41.860759],"type":"Point"}
}