{
  "type": "Feature",
  "properties": {
    "addr:full":"32 E Randolph St Chicago IL 60601",
    "addr:housenumber":"32",
    "addr:postcode":"60601",
    "addr:street":"E Randolph St",
    "iso:country":"US",
    "sg:address":"32 E Randolph St",
    "sg:city":"Chicago",
    "sg:classifiers":[
        {
            "category":"Food Court",
            "type":"Food & Drink"
        },
        {
            "category":"Food & Beverages",
            "subcategory":"Groceries & Convenience Stores",
            "type":"Retail Goods"
        }
    ],
    "sg:phone":"+1 312 629 1002",
    "sg:postcode":"60601",
    "sg:province":"IL",
    "sg:tags":[
        "stand",
        "refreshment",
        "pretzel"
    ],
    "sg:website":"http://www.pretzeltime.com",
    "wof:name":"Pretzel Time",
    "wof:placetype":"venue"
},
  "geometry": {"coordinates":[-87.626932,41.884471],"type":"Point"}
}