{
  "type": "Feature",
  "properties": {
    "addr:full":"24198 W Grand Ave Lake Villa IL 60046",
    "addr:housenumber":"24198",
    "addr:postcode":"60046",
    "addr:street":"W Grand Ave",
    "iso:country":"US",
    "sg:address":"24198 W Grand Ave",
    "sg:city":"Lake Villa",
    "sg:classifiers":[
        {
            "category":"Professional",
            "subcategory":"Engineering",
            "type":"Services"
        },
        {
            "category":"Manufacturing",
            "subcategory":"Tools & Machinery",
            "type":"Manufacturing & Wholesale Goods"
        }
    ],
    "sg:phone":"+1 847 356 7298",
    "sg:postcode":"60046",
    "sg:province":"IL",
    "sg:tags":[
        "machine",
        "shop"
    ],
    "wof:name":"C L M Engineering Co",
    "wof:placetype":"venue"
},
  "geometry": {"coordinates":[-88.104049,42.41553],"type":"Point"}
}