{
  "type": "Feature",
  "properties": {
    "iso:country":"US",
    "sg:address":"320 N State St",
    "sg:city":"Belvidere",
    "sg:classifiers":[
        {
            "category":"Education",
            "subcategory":"Library",
            "type":"Public Place"
        }
    ],
    "sg:phone":"+1 815 544 3838",
    "sg:postcode":"61008",
    "sg:province":"IL",
    "sg:website":"http://www.idapubliclibrary.org",
    "wof:name":"Ida Public Library",
    "wof:placetype":"venue"
},
  "geometry": {"coordinates":[-88.84549699999999,42.2617],"type":"Point"}
}