{
  "type": "Feature",
  "properties": {
    "iso:country":"US",
    "sg:address":"15651 Rock Grove Rd",
    "sg:city":"Durand",
    "sg:classifiers":[
        {
            "category":"Freight",
            "type":"Transportation"
        }
    ],
    "sg:phone":"+1 815 248 3746",
    "sg:postcode":"61024",
    "sg:province":"IL",
    "sg:tags":[
        "operator",
        "local",
        "trucking"
    ],
    "wof:name":"T & T and Sons Trucking",
    "wof:placetype":"venue"
},
  "geometry": {"coordinates":[-89.352004,42.460261],"type":"Point"}
}