{
  "type": "Feature",
  "properties": {
    "iso:country":"US",
    "sg:address":"5899 N Belt W",
    "sg:city":"Belleville",
    "sg:classifiers":[
        {
            "category":"Health Services",
            "subcategory":"Medical Lab",
            "type":"Services"
        }
    ],
    "sg:phone":"+1 618 235 9141",
    "sg:postcode":"62226",
    "sg:province":"IL",
    "sg:tags":[
        "laboratory",
        "dental"
    ],
    "wof:name":"Liberty Dental Laboratories",
    "wof:placetype":"venue"
},
  "geometry": {"coordinates":[-90.035804,38.5417],"type":"Point"}
}