{
  "type": "Feature",
  "properties": {
    "iso:country":"US",
    "sg:address":"6 E Washington St",
    "sg:city":"Oswego",
    "sg:classifiers":[
        {
            "category":"Professional",
            "subcategory":"Lawyer & Legal Services",
            "type":"Services"
        },
        {
            "category":"Banks & Credit Unions",
            "subcategory":"Financial Services",
            "type":"Services"
        }
    ],
    "sg:phone":"+1 630 554 3065",
    "sg:postcode":"60543",
    "sg:province":"IL",
    "sg:tags":[
        "attorney",
        "trust",
        "estate",
        "family",
        "divorce",
        "wills",
        "planning",
        "law",
        "bankruptcy"
    ],
    "wof:name":"Ward, C. David - Law Offices of C. David Ward",
    "wof:placetype":"venue"
},
  "geometry": {"coordinates":[-88.351477,41.682931],"type":"Point"}
}