{
  "type": "Feature",
  "properties": {
    "iso:country":"US",
    "sg:address":"238 W Cermak Rd 3rd Floor, Unit D",
    "sg:city":"Chicago",
    "sg:classifiers":[
        {
            "category":"Health Services",
            "subcategory":"Clinic",
            "type":"Services"
        }
    ],
    "sg:phone":"+1 312 842 1229",
    "sg:postcode":"60616",
    "sg:province":"IL",
    "sg:tags":[
        "medical"
    ],
    "wof:name":"United Alternative Healing Center",
    "wof:placetype":"venue"
},
  "geometry": {"coordinates":[-87.633228,41.852881],"type":"Point"}
}