{
  "type": "Feature",
  "properties": {
    "addr:full":"1030 S 4th Ave Libertyville IL 60048",
    "addr:housenumber":"1030",
    "addr:postcode":"60048",
    "addr:street":"S 4Th Ave",
    "iso:country":"US",
    "sg:address":"1030 S 4th Ave",
    "sg:city":"Libertyville",
    "sg:classifiers":[
        {
            "category":"Recreation",
            "type":"Entertainment"
        }
    ],
    "sg:phone":"+1 847 362 6587",
    "sg:postcode":"60048",
    "sg:province":"IL",
    "sg:tags":[
        "riding",
        "academy"
    ],
    "sg:website":"www.ltf.com",
    "wof:name":"Care Academy",
    "wof:placetype":"venue"
},
  "geometry": {"coordinates":[-87.94266399999999,42.267756],"type":"Point"}
}