{
  "type": "Feature",
  "properties": {
    "addr:full":"250 E Laraway Rd Frankfort IL 60423",
    "addr:housenumber":"250",
    "addr:postcode":"60423",
    "addr:street":"E Laraway Rd",
    "iso:country":"US",
    "sg:address":"250 E Laraway Rd",
    "sg:city":"Frankfort",
    "sg:classifiers":[
        {
            "category":"Home & Garden",
            "subcategory":"Building Materials",
            "type":"Retail Goods"
        }
    ],
    "sg:phone":"+1 815 464 7253",
    "sg:postcode":"60423",
    "sg:province":"IL",
    "sg:tags":[
        "windows"
    ],
    "wof:name":"Richards Building Supply Co",
    "wof:placetype":"venue"
},
  "geometry": {"coordinates":[-87.836917,41.484521],"type":"Point"}
}