{
  "type": "Feature",
  "properties": {
    "addr:full":"301 E Fremont St Bement IL 61813",
    "addr:housenumber":"301",
    "addr:postcode":"61813",
    "addr:street":"E Fremont St",
    "iso:country":"US",
    "sg:address":"301 E Fremont St",
    "sg:city":"Bement",
    "sg:classifiers":[
        {
            "category":"Insurance",
            "subcategory":"Insurance Agent",
            "type":"Services"
        }
    ],
    "sg:phone":"+1 217 678 8439",
    "sg:postcode":"61813",
    "sg:province":"IL",
    "wof:name":"American Genl Financial Group",
    "wof:placetype":"venue"
},
  "geometry": {"coordinates":[-88.566514,39.919473],"type":"Point"}
}