{
  "type": "Feature",
  "properties": {
    "iso:country":"US",
    "sg:address":"350 N Cherry St",
    "sg:city":"Breese",
    "sg:classifiers":[
        {
            "category":"Building & Trades",
            "subcategory":"Construction",
            "type":"Services"
        }
    ],
    "sg:phone":"+1 618 526 4866",
    "sg:postcode":"62230",
    "sg:province":"IL",
    "sg:tags":[
        "house",
        "general",
        "nonresidential",
        "contractor"
    ],
    "wof:name":"Richter Construction Co",
    "wof:placetype":"venue"
},
  "geometry": {"coordinates":[-89.530098,38.610055],"type":"Point"}
}