{
  "type": "Feature",
  "properties": {
    "iso:country":"US",
    "sg:address":"314 W Vallette St Side 2",
    "sg:city":"Elmhurst",
    "sg:classifiers":[
        {
            "category":"Social Services",
            "subcategory":"Job Training",
            "type":"Services"
        },
        {
            "category":"Social Services",
            "subcategory":"Adult Care",
            "type":"Services"
        }
    ],
    "sg:phone":"+1 630 832 1788",
    "sg:postcode":"60126",
    "sg:province":"IL",
    "sg:tags":[
        "day",
        "centers-adult",
        "nursing",
        "homes-skilled",
        "facility"
    ],
    "wof:name":"Adult Christian Care, Inc",
    "wof:placetype":"venue"
},
  "geometry": {"coordinates":[-87.950199,41.882744],"type":"Point"}
}