{
  "type": "Feature",
  "properties": {
    "iso:country":"US",
    "sg:address":"13013 Western Ave",
    "sg:city":"Blue Island",
    "sg:classifiers":[
        {
            "category":"Shopping",
            "type":"Retail Goods"
        }
    ],
    "sg:phone":"+1   ",
    "sg:postcode":"60406",
    "sg:province":"IL",
    "sg:tags":[
        "merchandise"
    ],
    "wof:name":"Hopes Architectural Products",
    "wof:placetype":"venue"
},
  "geometry": {"coordinates":[-87.680003,41.656758],"type":"Point"}
}