{
  "type": "Feature",
  "properties": {
    "addr:full":"37325 Zilm Rd Wilmington IL 60481",
    "addr:postcode":"37325;60481",
    "addr:street":"Zilm Rd",
    "iso:country":"US",
    "sg:address":"37325 Zilm Rd",
    "sg:city":"Wilmington",
    "sg:classifiers":[
        {
            "category":"Building & Trades",
            "subcategory":"Plumbing",
            "type":"Services"
        }
    ],
    "sg:phone":"+1 815 458 2212",
    "sg:postcode":"60481",
    "sg:province":"IL",
    "sg:tags":[
        "contractor"
    ],
    "wof:name":"Bourkes Service",
    "wof:placetype":"venue"
},
  "geometry": {"coordinates":[-88.148256,41.204202],"type":"Point"}
}