{
  "type": "Feature",
  "properties": {
    "addr:full":"2330 W Saint Paul Chicago IL 60647",
    "addr:housenumber":"2330",
    "addr:postcode":"60647",
    "addr:street":"W",
    "iso:country":"US",
    "sg:address":"2330 W Saint Paul",
    "sg:city":"Chicago",
    "sg:classifiers":[
        {
            "category":"Professional",
            "subcategory":"Advertising",
            "type":"Services"
        }
    ],
    "sg:phone":"+1 630 915 2056",
    "sg:postcode":"60647",
    "sg:province":"IL",
    "sg:tags":[
        "videographers"
    ],
    "sg:website":"localvideomaster.com/",
    "wof:name":"Local Video Master",
    "wof:placetype":"venue"
},
  "geometry": {"coordinates":[-87.684708,41.913735],"type":"Point"}
}