{
  "type": "Feature",
  "properties": {
    "addr:full":"1 E Superior St Chicago IL 60611",
    "addr:housenumber":"1",
    "addr:postcode":"60611",
    "addr:street":"E Superior St",
    "iso:country":"US",
    "sg:address":"1 E Superior St",
    "sg:city":"Chicago",
    "sg:phone":"+1 312 943 6400",
    "sg:postcode":"60611",
    "sg:province":"IL",
    "sg:website":"http://www.nutrition-clinic.com",
    "wof:name":"Nutrition Clinic",
    "wof:placetype":"venue"
},
  "geometry": {"coordinates":[-87.628159,41.895679],"type":"Point"}
}