{
  "type": "Feature",
  "properties": {
    "iso:country":"US",
    "sg:address":"1512 N Cedar Lake Rd",
    "sg:city":"Lake Villa",
    "sg:classifiers":[
        {
            "category":"Health Services",
            "subcategory":"Chiropractor",
            "type":"Services"
        }
    ],
    "sg:phone":"+1 847 546 5255",
    "sg:postcode":"60046",
    "sg:province":"IL",
    "wof:name":"Lawrence G Needham DC",
    "wof:placetype":"venue"
},
  "geometry": {"coordinates":[-88.092187,42.398324],"type":"Point"}
}