{
  "type": "Feature",
  "properties": {
    "iso:country":"US",
    "sg:address":"111 E Locust St",
    "sg:city":"Fieldon",
    "sg:classifiers":[
        {
            "category":"Fast Food",
            "type":"Food & Drink"
        },
        {
            "category":"Restaurant",
            "type":"Food & Drink"
        }
    ],
    "sg:phone":"+1 618 376 3374",
    "sg:postcode":"62031",
    "sg:province":"IL",
    "sg:tags":[
        "take"
    ],
    "wof:name":"Mike Place",
    "wof:placetype":"venue"
},
  "geometry": {"coordinates":[-90.497803,39.108669],"type":"Point"}
}