{
  "type": "Feature",
  "properties": {
    "addr:full":"17878 Park View Dr Country Club Hls IL 60478",
    "addr:housenumber":"17878",
    "addr:postcode":"60478",
    "addr:street":"Park View Dr",
    "iso:country":"US",
    "sg:address":"17878 Park View Dr",
    "sg:city":"Country Club Hls",
    "sg:classifiers":[
        {
            "category":"Communications",
            "type":"Services"
        }
    ],
    "sg:phone":"+1 708 365 5250",
    "sg:postcode":"60478",
    "sg:province":"IL",
    "wof:name":"Communication Technologies",
    "wof:placetype":"venue"
},
  "geometry": {"coordinates":[-87.734194,41.56594],"type":"Point"}
}