{
  "type": "Feature",
  "properties": {
    "iso:country":"US",
    "sg:address":"1375 S Oakwood Ave",
    "sg:city":"Geneseo",
    "sg:classifiers":[
        {
            "category":"Travel",
            "subcategory":"Hotels & Motels",
            "type":"Entertainment"
        }
    ],
    "sg:phone":"+1 800 424 6423",
    "sg:postcode":"61254",
    "sg:province":"IL",
    "sg:tags":[
        "lodging"
    ],
    "sg:website":"http://www.comfortinn.com/hotel-geneseo-illinois-IL330?promo=yplocal",
    "wof:name":"Comfort Inn Geneseo",
    "wof:placetype":"venue"
},
  "geometry": {"coordinates":[-90.157127,41.435868],"type":"Point"}
}