{
  "type": "Feature",
  "properties": {
    "addr:full":"880 Sparta Ct Vernon Hills IL 60061",
    "addr:housenumber":"880",
    "addr:postcode":"60061",
    "addr:street":"Sparta Ct",
    "iso:country":"US",
    "sg:address":"880 Sparta Ct",
    "sg:city":"Vernon Hills",
    "sg:classifiers":[
        {
            "category":"Insurance",
            "subcategory":"Insurance Agent",
            "type":"Services"
        }
    ],
    "sg:phone":"+1 847 949 4607",
    "sg:postcode":"60061",
    "sg:province":"IL",
    "sg:tags":[
        "consultant"
    ],
    "wof:name":"Senior Financial Svc",
    "wof:placetype":"venue"
},
  "geometry": {"coordinates":[-87.986655,42.234928],"type":"Point"}
}