{
  "type": "Feature",
  "properties": {
    "addr:full":"529 S Williams Ave Palatine IL 60074",
    "addr:housenumber":"529",
    "addr:postcode":"60074",
    "addr:street":"S Williams Ave",
    "iso:country":"US",
    "sg:address":"529 S Williams Ave",
    "sg:city":"Palatine",
    "sg:classifiers":[
        {
            "category":"Health Services",
            "subcategory":"Doctor",
            "type":"Services"
        }
    ],
    "sg:phone":"+1 847 255 1940",
    "sg:postcode":"60074",
    "sg:province":"IL",
    "sg:tags":[
        "dentist"
    ],
    "wof:name":"H & L Dental Laboratory",
    "wof:placetype":"venue"
},
  "geometry": {"coordinates":[-88.00943700000001,42.101786],"type":"Point"}
}