{
  "type": "Feature",
  "properties": {
    "iso:country":"US",
    "sg:address":"1050 W Stearns Rd",
    "sg:city":"Bartlett",
    "sg:classifiers":[
        {
            "category":"Social Services",
            "subcategory":"Child Care",
            "type":"Services"
        },
        {
            "category":"Education",
            "subcategory":"Preschool",
            "type":"Public Place"
        },
        {
            "category":"Education",
            "subcategory":"School",
            "type":"Public Place"
        }
    ],
    "sg:phone":"+1 630 837 7511",
    "sg:postcode":"60103",
    "sg:province":"IL",
    "sg:tags":[
        "elementary",
        "day"
    ],
    "wof:name":"Children's World Learning Centers",
    "wof:placetype":"venue"
},
  "geometry": {"coordinates":[-88.200401,41.974499],"type":"Point"}
}