{
  "type": "Feature",
  "properties": {
    "addr:full":"929 S River St Aurora IL 60506",
    "addr:housenumber":"929",
    "addr:postcode":"60506",
    "addr:street":"S River St",
    "iso:country":"US",
    "sg:address":"929 S River St",
    "sg:city":"Aurora",
    "sg:classifiers":[
        {
            "category":"Personal",
            "subcategory":"Barber",
            "type":"Services"
        }
    ],
    "sg:phone":"+1 630 844 2020",
    "sg:postcode":"60506",
    "sg:province":"IL",
    "wof:name":"Bill's Barber Shop",
    "wof:placetype":"venue"
},
  "geometry": {"coordinates":[-88.33113899999999,41.739625],"type":"Point"}
}