{
  "type": "Feature",
  "properties": {
    "addr:full":"808 W Armitage Avenue Suite 1 Chicago IL 60614",
    "addr:housenumber":"808",
    "addr:postcode":"60614",
    "addr:street":"W Armitage Avenue Suite 1",
    "iso:country":"US",
    "sg:address":"808 W Armitage Avenue Suite 1",
    "sg:city":"Chicago",
    "sg:classifiers":[
        {
            "category":"Shopping",
            "subcategory":"Shoes",
            "type":"Retail Goods"
        }
    ],
    "sg:phone":"+1 773 404 0540",
    "sg:postcode":"60614",
    "sg:province":"IL",
    "sg:tags":[
        "store"
    ],
    "wof:name":"J Hale",
    "wof:placetype":"venue"
},
  "geometry": {"coordinates":[-87.648821,41.918171],"type":"Point"}
}