{
  "type": "Feature",
  "properties": {
    "addr:full":"23W500 Pine Dr Carol Stream IL 60188",
    "addr:housenumber":"23w500",
    "addr:postcode":"60188",
    "addr:street":"Pine Dr",
    "iso:country":"US",
    "sg:address":"23W500 Pine Dr",
    "sg:city":"Carol Stream",
    "sg:classifiers":[
        {
            "category":"Building & Trades",
            "subcategory":"Construction",
            "type":"Services"
        }
    ],
    "sg:phone":"+1 630 665 9007",
    "sg:postcode":"60188",
    "sg:province":"IL",
    "sg:tags":[
        "contractor"
    ],
    "wof:name":"Tisc Erectors",
    "wof:placetype":"venue"
},
  "geometry": {"coordinates":[-88.08470199999999,41.897999],"type":"Point"}
}