{
  "type": "Feature",
  "properties": {
    "iso:country":"US",
    "sg:address":"518 Spring Lake Dr",
    "sg:city":"Quincy",
    "sg:classifiers":[
        {
            "category":"Restaurant",
            "type":"Food & Drink"
        }
    ],
    "sg:phone":"+1 217 228 0012",
    "sg:postcode":"62305",
    "sg:province":"IL",
    "wof:name":"Midwest Seven Inc.",
    "wof:placetype":"venue"
},
  "geometry": {"coordinates":[-91.404073,39.987638],"type":"Point"}
}