{
  "type": "Feature",
  "properties": {
    "iso:country":"US",
    "sg:address":"2820 Plainfield Rd",
    "sg:city":"Joliet",
    "sg:classifiers":[
        {
            "category":"Education",
            "subcategory":"Special Training",
            "type":"Public Place"
        },
        {
            "category":"Education",
            "subcategory":"University",
            "type":"Public Place"
        }
    ],
    "sg:phone":"+1 815 630 4331",
    "sg:postcode":"60435",
    "sg:province":"IL",
    "sg:tags":[
        "educational",
        "college"
    ],
    "sg:website":"http://www.dettmanntutoringco.com",
    "wof:name":"Dettmann Tutoring Co",
    "wof:placetype":"venue"
},
  "geometry": {"coordinates":[-88.157516,41.576542],"type":"Point"}
}