{
  "type": "Feature",
  "properties": {
    "addr:full":"744 W Elk Grove Blvd Elk Grove Vlg IL 60007",
    "addr:housenumber":"744",
    "addr:postcode":"60007",
    "addr:street":"W Elk Grove Blvd",
    "iso:country":"US",
    "sg:address":"744 W Elk Grove Blvd",
    "sg:city":"Elk Grove Vlg",
    "sg:classifiers":[
        {
            "category":"Professional",
            "subcategory":"Management & Consulting",
            "type":"Services"
        }
    ],
    "sg:phone":"+1 847 364 6540",
    "sg:postcode":"60007",
    "sg:province":"IL",
    "sg:tags":[
        "marketing",
        "program"
    ],
    "wof:name":"Franz Collection LTD",
    "wof:placetype":"venue"
},
  "geometry": {"coordinates":[-87.994078,42.008872],"type":"Point"}
}