{
  "type": "Feature",
  "properties": {
    "addr:full":"800 Market St Saint Louis MO 63101",
    "addr:housenumber":"800",
    "addr:postcode":"63101",
    "addr:street":"Market St",
    "iso:country":"US",
    "sg:address":"800 Market St",
    "sg:city":"Saint Louis",
    "sg:classifiers":[
        {
            "category":"Restaurant",
            "type":"Food & Drink"
        }
    ],
    "sg:phone":"+1 314 241 2233",
    "sg:postcode":"63101",
    "sg:province":"MO",
    "wof:name":"Village Cafe",
    "wof:placetype":"venue"
},
  "geometry": {"coordinates":[-90.193298,38.626202],"type":"Point"}
}