{
  "type": "Feature",
  "properties": {
    "iso:country":"US",
    "sg:address":"3408 Maine St",
    "sg:city":"Quincy",
    "sg:classifiers":[
        {
            "category":"Farming",
            "subcategory":"Farm & Veterinary Services",
            "type":"Manufacturing & Wholesale Goods"
        }
    ],
    "sg:phone":"+1 217 228 0959",
    "sg:postcode":"62301",
    "sg:province":"IL",
    "sg:tags":[
        "protecting",
        "crop"
    ],
    "wof:name":"Dow Agrosciences LLC",
    "wof:placetype":"venue"
},
  "geometry": {"coordinates":[-91.360023,39.931511],"type":"Point"}
}