{
  "type": "Feature",
  "properties": {
    "iso:country":"US",
    "sg:address":"7003 N Alpine Rd",
    "sg:city":"Loves Park",
    "sg:classifiers":[
        {
            "category":"Recreation",
            "type":"Entertainment"
        }
    ],
    "sg:phone":"+1 815 877 9558",
    "sg:postcode":"61111",
    "sg:province":"IL",
    "sg:tags":[
        "soccer"
    ],
    "wof:name":"Soccer Enterprises Inc",
    "wof:placetype":"venue"
},
  "geometry": {"coordinates":[-89.028458,42.327059],"type":"Point"}
}