{
  "type": "Feature",
  "properties": {
    "addr:full":"1275 Marshall Blvd Aurora IL 60505",
    "addr:housenumber":"1275",
    "addr:postcode":"60505",
    "addr:street":"Marshall Blvd",
    "iso:country":"US",
    "sg:address":"1275 Marshall Blvd",
    "sg:city":"Aurora",
    "sg:phone":"+1 630 692 1169",
    "sg:postcode":"60505",
    "sg:province":"IL",
    "wof:name":"Marywood Apt Homes Lp",
    "wof:placetype":"venue"
},
  "geometry": {"coordinates":[-88.284526,41.789132],"type":"Point"}
}