{
  "type": "Feature",
  "properties": {
    "addr:full":"1200 Iroquois Ave Naperville IL 60563",
    "addr:housenumber":"1200",
    "addr:postcode":"60563",
    "addr:street":"Iroquois Ave",
    "iso:country":"US",
    "sg:address":"1200 Iroquois Ave",
    "sg:city":"Naperville",
    "sg:classifiers":[
        {
            "category":"Health Services",
            "subcategory":"Nursing And Care Facility",
            "type":"Services"
        },
        {
            "category":"Health Services",
            "subcategory":"Health Practitioner",
            "type":"Services"
        }
    ],
    "sg:phone":"+1 630 718 1970",
    "sg:postcode":"60563",
    "sg:province":"IL",
    "sg:tags":[
        "home",
        "eldercare-home"
    ],
    "sg:website":"http://www.homecarelinks.com",
    "wof:name":"Homecare Links Inc.",
    "wof:placetype":"venue"
},
  "geometry": {"coordinates":[-88.124847,41.795132],"type":"Point"}
}