{
  "type": "Feature",
  "properties": {
    "iso:country":"US",
    "sg:address":"3441 N Oaktree Rd",
    "sg:city":"Olney",
    "sg:classifiers":[
        {
            "category":"Shopping",
            "subcategory":"Jewelry",
            "type":"Retail Goods"
        }
    ],
    "sg:phone":"+1 618 869 2614",
    "sg:postcode":"62450",
    "sg:province":"IL",
    "sg:tags":[
        "jeweler"
    ],
    "wof:name":"Bj Junk And Jewelry",
    "wof:placetype":"venue"
},
  "geometry": {"coordinates":[-87.975031,38.69579],"type":"Point"}
}