{
  "type": "Feature",
  "properties": {
    "iso:country":"US",
    "sg:address":"655 W Lake Cook Rd",
    "sg:city":"Palatine",
    "sg:classifiers":[
        {
            "category":"Professional",
            "subcategory":"Detective & Security Services",
            "type":"Services"
        }
    ],
    "sg:phone":"+1 847 359 3043",
    "sg:postcode":"60074",
    "sg:province":"IL",
    "wof:name":"Cross Country Bureau",
    "wof:placetype":"venue"
},
  "geometry": {"coordinates":[-88.05922099999999,42.153768],"type":"Point"}
}