{
  "type": "Feature",
  "properties": {
    "addr:full":"3339 Dempster St Skokie IL 60076",
    "addr:housenumber":"3339",
    "addr:postcode":"60076",
    "addr:street":"Dempster St",
    "iso:country":"US",
    "sg:address":"3339 Dempster St",
    "sg:city":"Skokie",
    "sg:classifiers":[
        {
            "category":"Shopping",
            "subcategory":"Jewelry",
            "type":"Retail Goods"
        }
    ],
    "sg:phone":"+1   ",
    "sg:postcode":"60076",
    "sg:province":"IL",
    "wof:name":"Gift It Silver",
    "wof:placetype":"venue"
},
  "geometry": {"coordinates":[-87.71229099999999,42.040835],"type":"Point"}
}