{
  "type": "Feature",
  "properties": {
    "iso:country":"US",
    "sg:address":"7510 N Western Ave",
    "sg:city":"Chicago",
    "sg:classifiers":[
        {
            "category":"Shopping",
            "subcategory":"Pharmacy",
            "type":"Retail Goods"
        }
    ],
    "sg:phone":"+1   ",
    "sg:postcode":"60645",
    "sg:province":"IL",
    "wof:name":"Walgreens",
    "wof:placetype":"venue"
},
  "geometry": {"coordinates":[-87.690255,42.018943],"type":"Point"}
}