{
  "type": "Feature",
  "properties": {
    "addr:full":"1042 W Jackson Blvd Chicago IL 60607",
    "addr:housenumber":"1042",
    "addr:postcode":"60607",
    "addr:street":"W Jackson Blvd",
    "iso:country":"US",
    "sg:address":"1042 W Jackson Blvd",
    "sg:city":"Chicago",
    "sg:classifiers":[
        {
            "category":"Building & Trades",
            "subcategory":"Construction",
            "type":"Services"
        }
    ],
    "sg:phone":"+1 773 933 0808",
    "sg:postcode":"60607",
    "sg:province":"IL",
    "sg:tags":[
        "contractor"
    ],
    "sg:website":"www.hollub.com",
    "wof:name":"Hollub Heating and Air Conditioning",
    "wof:placetype":"venue"
},
  "geometry": {"coordinates":[-87.653702,41.877899],"type":"Point"}
}