{
  "type": "Feature",
  "properties": {
    "addr:full":"4920 159th St Oak Forest IL 60452",
    "addr:housenumber":"4920",
    "addr:postcode":"60452",
    "addr:street":"159Th St",
    "iso:country":"US",
    "sg:address":"4920 159th St",
    "sg:city":"Oak Forest",
    "sg:classifiers":[
        {
            "category":"Banks & Credit Unions",
            "subcategory":"Bank",
            "type":"Services"
        }
    ],
    "sg:phone":"+1 708 535 1035",
    "sg:postcode":"60452",
    "sg:province":"IL",
    "sg:website":"www.nationalcity.com",
    "wof:name":"National City Bank",
    "wof:placetype":"venue"
},
  "geometry": {"coordinates":[-87.739526,41.603369],"type":"Point"}
}