{
  "type": "Feature",
  "properties": {
    "iso:country":"US",
    "sg:address":"60 Chestnut Ct",
    "sg:city":"Champaign",
    "sg:classifiers":[
        {
            "category":"Real Estate",
            "subcategory":"Real Estate Operator",
            "type":"Services"
        }
    ],
    "sg:phone":"+1 217 493 6151",
    "sg:postcode":"61822",
    "sg:province":"IL",
    "sg:tags":[
        "apartment"
    ],
    "wof:name":"Olde Towne Centre Apts",
    "wof:placetype":"venue"
},
  "geometry": {"coordinates":[-88.239271,40.063709],"type":"Point"}
}