{
  "type": "Feature",
  "properties": {
    "addr:full":"662 N Western Ave Lake Forest IL 60045",
    "addr:housenumber":"662",
    "addr:postcode":"60045",
    "addr:street":"N Western Ave",
    "iso:country":"US",
    "sg:address":"662 N Western Ave",
    "sg:city":"Lake Forest",
    "sg:classifiers":[
        {
            "category":"Retail",
            "subcategory":"Repair Shop",
            "type":"Services"
        }
    ],
    "sg:phone":"+1 847 295 8655",
    "sg:postcode":"60045",
    "sg:province":"IL",
    "wof:name":"Emporium Luggage",
    "wof:placetype":"venue"
},
  "geometry": {"coordinates":[-87.839969,42.251873],"type":"Point"}
}