{
  "type": "Feature",
  "properties": {
    "iso:country":"US",
    "sg:address":"3224 171st St",
    "sg:city":"Lansing",
    "sg:classifiers":[
        {
            "category":"Food & Beverages",
            "subcategory":"Groceries & Convenience Stores",
            "type":"Retail Goods"
        }
    ],
    "sg:phone":"+1 708 474 6079",
    "sg:postcode":"60438",
    "sg:province":"IL",
    "wof:name":"Grand Food Mart",
    "wof:placetype":"venue"
},
  "geometry": {"coordinates":[-87.538542,41.584642],"type":"Point"}
}