{
  "type": "Feature",
  "properties": {
    "iso:country":"US",
    "sg:address":"2323 W State St",
    "sg:city":"Rockford",
    "sg:classifiers":[
        {
            "category":"Wholesale",
            "subcategory":"Machinery & Supplies",
            "type":"Manufacturing & Wholesale Goods"
        }
    ],
    "sg:phone":"+1 815 490 1275",
    "sg:postcode":"61102",
    "sg:province":"IL",
    "sg:tags":[
        "salon",
        "beauty"
    ],
    "wof:name":"Feel Effect",
    "wof:placetype":"venue"
},
  "geometry": {"coordinates":[-89.123215,42.276582],"type":"Point"}
}