{
  "type": "Feature",
  "properties": {
    "addr:full":"6124 W Plank Rd Peoria IL 61604",
    "addr:housenumber":"6124",
    "addr:postcode":"61604",
    "addr:street":"W Plank Rd",
    "iso:country":"US",
    "sg:address":"6124 W Plank Rd",
    "sg:city":"Peoria",
    "sg:classifiers":[
        {
            "category":"Restaurant",
            "type":"Food & Drink"
        }
    ],
    "sg:menulink":"http://www.allmenus.com/il/limestone/226170-caseys-general-store/menu/",
    "sg:phone":"+1 309 697 3299",
    "sg:postcode":"61604",
    "sg:province":"IL",
    "sg:tags":[
        "american",
        "pizza"
    ],
    "wof:name":"Casey's General Store",
    "wof:placetype":"venue"
},
  "geometry": {"coordinates":[-89.69075100000001,40.688008],"type":"Point"}
}