{
  "type": "Feature",
  "properties": {
    "iso:country":"US",
    "sg:address":"26 Ivanhoe Dr",
    "sg:city":"Urbana",
    "sg:phone":"+1 217 367 1314",
    "sg:postcode":"61802",
    "sg:province":"IL",
    "wof:name":"Ivanhoe Estates Inc",
    "wof:placetype":"venue"
},
  "geometry": {"coordinates":[-88.18943,40.12928],"type":"Point"}
}