{
  "type": "Feature",
  "properties": {
    "iso:country":"US",
    "sg:address":"4 Henson Pl",
    "sg:city":"Champaign",
    "sg:classifiers":[
        {
            "category":"Health Services",
            "subcategory":"Clinic",
            "type":"Services"
        }
    ],
    "sg:phone":"+1 217 356 1121",
    "sg:postcode":"61820",
    "sg:province":"IL",
    "sg:tags":[
        "home"
    ],
    "wof:name":"Addus Healthcare",
    "wof:placetype":"venue"
},
  "geometry": {"coordinates":[-88.247758,40.134419],"type":"Point"}
}