{
  "type": "Feature",
  "properties": {
    "addr:full":"900 N Court St Tuscola IL 61953",
    "addr:housenumber":"900",
    "addr:postcode":"61953",
    "addr:street":"N Court St",
    "iso:country":"US",
    "sg:address":"900 N Court St",
    "sg:city":"Tuscola",
    "sg:classifiers":[
        {
            "category":"Restaurant",
            "type":"Food & Drink"
        }
    ],
    "sg:menulink":"http://www.allmenus.com/il/tuscola/88391-monicals-pizza/menu/",
    "sg:phone":"+1 217 253 4749",
    "sg:postcode":"61953",
    "sg:province":"IL",
    "sg:tags":[
        "american",
        "pizza"
    ],
    "wof:name":"Monicals Pizza",
    "wof:placetype":"venue"
},
  "geometry": {"coordinates":[-88.28450100000001,39.806359],"type":"Point"}
}