{
  "type": "Feature",
  "properties": {
    "iso:country":"US",
    "sg:address":"1634 23rd Ave",
    "sg:city":"Moline",
    "sg:classifiers":[
        {
            "category":"Health Services",
            "subcategory":"Chiropractor",
            "type":"Services"
        }
    ],
    "sg:phone":"+1 309 762 7660",
    "sg:postcode":"61265",
    "sg:province":"IL",
    "sg:tags":[
        "chiropractic"
    ],
    "wof:name":"Quad City Wellness & Rehabilitation Ltd",
    "wof:placetype":"venue"
},
  "geometry": {"coordinates":[-90.513203,41.489553],"type":"Point"}
}