{
  "type": "Feature",
  "properties": {
    "addr:full":"19333 E Grant Hwy Marengo IL 60152",
    "addr:housenumber":"19333",
    "addr:postcode":"60152",
    "addr:street":"E Grant Hwy",
    "iso:country":"US",
    "sg:address":"19333 E Grant Hwy",
    "sg:city":"Marengo",
    "sg:classifiers":[
        {
            "category":"Government",
            "subcategory":"Police Station",
            "type":"Public Place"
        },
        {
            "category":"Professional",
            "subcategory":"Lawyer & Legal Services",
            "type":"Services"
        }
    ],
    "sg:phone":"+1 815 923 2107",
    "sg:postcode":"60152",
    "sg:province":"IL",
    "sg:tags":[
        "attorney",
        "partnership",
        "planning",
        "trust",
        "bankruptcy",
        "family",
        "corporation",
        "wills",
        "damage",
        "employee",
        "criminal",
        "compensation",
        "worker",
        "traffic",
        "law",
        "accident",
        "benefit",
        "real estate",
        "property"
    ],
    "sg:website":"http://www.fgmlaw.com",
    "wof:name":"Franks, Gerkin, & McKenna, P.C.",
    "wof:placetype":"venue"
},
  "geometry": {"coordinates":[-88.603756,42.247009],"type":"Point"}
}