{
  "type": "Feature",
  "properties": {
    "addr:full":"3145 S Ashland Ave Chicago IL 60608",
    "addr:housenumber":"3145",
    "addr:postcode":"60608",
    "addr:street":"S Ashland Ave",
    "iso:country":"US",
    "sg:address":"3145 S Ashland Ave",
    "sg:city":"Chicago",
    "sg:classifiers":[
        {
            "category":"Food & Beverages",
            "subcategory":"Specialty",
            "type":"Retail Goods"
        },
        {
            "category":"Food & Beverages",
            "subcategory":"Fruits & Vegetables",
            "type":"Retail Goods"
        },
        {
            "category":"Shopping",
            "subcategory":"Pharmacy",
            "type":"Retail Goods"
        }
    ],
    "sg:phone":"+1 773 247 7115",
    "sg:postcode":"60608",
    "sg:province":"IL",
    "sg:tags":[
        "product",
        "wellness",
        "vitamin",
        "diet",
        "supplement",
        "health",
        "herb"
    ],
    "sg:website":"http://www.gnc.com",
    "wof:name":"GNC",
    "wof:placetype":"venue"
},
  "geometry": {"coordinates":[-87.665712,41.836198],"type":"Point"}
}