{
  "type": "Feature",
  "properties": {
    "addr:full":"6351 W State St Charleston IL 61920",
    "addr:housenumber":"6351",
    "addr:postcode":"61920",
    "addr:street":"W State St",
    "iso:country":"US",
    "sg:address":"6351 W State St",
    "sg:city":"Charleston",
    "sg:classifiers":[
        {
            "category":"Utilities",
            "subcategory":"Refuse",
            "type":"Services"
        }
    ],
    "sg:phone":"+1 217 345 7414",
    "sg:postcode":"61920",
    "sg:province":"IL",
    "sg:tags":[
        "landfill"
    ],
    "wof:name":"Coles County Landfill & Cmpst",
    "wof:placetype":"venue"
},
  "geometry": {"coordinates":[-88.204205,39.503212],"type":"Point"}
}