{
  "type": "Feature",
  "properties": {
    "addr:full":"353 W Everett St Dixon IL 61021",
    "addr:housenumber":"353",
    "addr:postcode":"61021",
    "addr:street":"W Everett St",
    "iso:country":"US",
    "sg:address":"353 W Everett St",
    "sg:city":"Dixon",
    "sg:classifiers":[
        {
            "category":"Building & Trades",
            "subcategory":"Construction",
            "type":"Services"
        }
    ],
    "sg:phone":"+1 815 288 1318",
    "sg:postcode":"61021",
    "sg:province":"IL",
    "sg:tags":[
        "masonry",
        "contractor"
    ],
    "wof:name":"Eric E Helander Masonry Cnstr",
    "wof:placetype":"venue"
},
  "geometry": {"coordinates":[-89.489946,41.84797],"type":"Point"}
}