{
  "type": "Feature",
  "properties": {
    "iso:country":"US",
    "sg:address":"4799 S Center Rd",
    "sg:city":"Rochelle",
    "sg:classifiers":[
        {
            "category":"Retail",
            "subcategory":"Repair Shop",
            "type":"Services"
        }
    ],
    "sg:phone":"+1 815 562 3201",
    "sg:postcode":"61068",
    "sg:province":"IL",
    "wof:name":"Bruces Detailing Plus",
    "wof:placetype":"venue"
},
  "geometry": {"coordinates":[-89.12238499999999,41.942143],"type":"Point"}
}