{
  "type": "Feature",
  "properties": {
    "addr:full":"6940 W Grand Ave Chicago IL 60707",
    "addr:housenumber":"6940",
    "addr:postcode":"60707",
    "addr:street":"W Grand Ave",
    "iso:country":"US",
    "sg:address":"6940 W Grand Ave",
    "sg:city":"Chicago",
    "sg:classifiers":[
        {
            "category":"Autos & Motor Vehicles",
            "subcategory":"Automobile Sales",
            "type":"Retail Goods"
        },
        {
            "category":"Retail",
            "subcategory":"Auto Repair",
            "type":"Services"
        }
    ],
    "sg:phone":"+1 773 745 4600",
    "sg:postcode":"60707",
    "sg:province":"IL",
    "sg:tags":[
        "car"
    ],
    "wof:name":"Premier Chrysler Jeep",
    "wof:placetype":"venue"
},
  "geometry": {"coordinates":[-87.79940000000001,41.923599],"type":"Point"}
}