{
  "type": "Feature",
  "properties": {
    "addr:full":"2448 N Southport Ave Chicago IL 60614",
    "addr:housenumber":"2448",
    "addr:postcode":"60614",
    "addr:street":"N Southport Ave",
    "iso:country":"US",
    "sg:address":"2448 N Southport Ave",
    "sg:city":"Chicago",
    "sg:classifiers":[
        {
            "category":"Personal",
            "subcategory":"Beauty Salon",
            "type":"Services"
        },
        {
            "category":"Personal",
            "subcategory":"Skin Care",
            "type":"Services"
        }
    ],
    "sg:phone":"+1 773 472 4323",
    "sg:postcode":"60614",
    "sg:province":"IL",
    "sg:tags":[
        "hair"
    ],
    "wof:name":"Colorrific Coiffure",
    "wof:placetype":"venue"
},
  "geometry": {"coordinates":[-87.66350300000001,41.926639],"type":"Point"}
}