{
  "type": "Feature",
  "properties": {
    "addr:full":"4430 W Montrose Avenue Chicago IL 60641",
    "addr:housenumber":"4430",
    "addr:postcode":"60641",
    "addr:street":"W Montrose Avenue",
    "iso:country":"US",
    "sg:address":"4430 W Montrose Avenue",
    "sg:city":"Chicago",
    "sg:classifiers":[
        {
            "category":"Building & Trades",
            "subcategory":"Construction",
            "type":"Services"
        }
    ],
    "sg:phone":"+1 773 725 3122",
    "sg:postcode":"60641",
    "sg:province":"IL",
    "sg:tags":[
        "contractor"
    ],
    "wof:name":"Marc",
    "wof:placetype":"venue"
},
  "geometry": {"coordinates":[-87.73958399999999,41.960825],"type":"Point"}
}