{
  "type": "Feature",
  "properties": {
    "iso:country":"US",
    "sg:address":"2153 W 24th St",
    "sg:city":"Chicago",
    "sg:classifiers":[
        {
            "category":"Building & Trades",
            "subcategory":"Electrical",
            "type":"Services"
        }
    ],
    "sg:phone":"+1 773 523 0757",
    "sg:postcode":"60608",
    "sg:province":"IL",
    "sg:tags":[
        "electrician"
    ],
    "wof:name":"Mighty Electric",
    "wof:placetype":"venue"
},
  "geometry": {"coordinates":[-87.680099,41.8484],"type":"Point"}
}