{
  "type": "Feature",
  "properties": {
    "addr:full":"39070 N Green Bay Rd Waukegan IL 60087",
    "addr:housenumber":"39070",
    "addr:postcode":"60087",
    "addr:street":"N Green Bay Rd",
    "iso:country":"US",
    "sg:address":"39070 N Green Bay Rd",
    "sg:city":"Waukegan",
    "sg:classifiers":[
        {
            "category":"Building & Trades",
            "subcategory":"Construction",
            "type":"Services"
        }
    ],
    "sg:phone":"+1 847 746 7660",
    "sg:postcode":"60087",
    "sg:province":"IL",
    "sg:tags":[
        "excavation",
        "contractor"
    ],
    "wof:name":"Grasswick Enterprises Excvtg",
    "wof:placetype":"venue"
},
  "geometry": {"coordinates":[-87.876385,42.430861],"type":"Point"}
}