{
  "type": "Feature",
  "properties": {
    "iso:country":"US",
    "sg:address":"830 Broadway St",
    "sg:city":"Mount Vernon",
    "sg:classifiers":[
        {
            "category":"Retail",
            "subcategory":"Laundry & Dry Cleaning",
            "type":"Services"
        },
        {
            "category":"Shopping",
            "subcategory":"Clothing, Apparel, & Fashions",
            "type":"Retail Goods"
        }
    ],
    "sg:phone":"+1 618 242 7203",
    "sg:postcode":"62864",
    "sg:province":"IL",
    "sg:tags":[
        "tailor"
    ],
    "wof:name":"Sewing Basket",
    "wof:placetype":"venue"
},
  "geometry": {"coordinates":[-88.901207,38.317151],"type":"Point"}
}