{
  "type": "Feature",
  "properties": {
    "iso:country":"US",
    "sg:address":"2146 N Halsted",
    "sg:city":"Chicago",
    "sg:classifiers":[
        {
            "category":"Food & Beverages",
            "subcategory":"Bakery",
            "type":"Retail Goods"
        }
    ],
    "sg:phone":"+1 773 549 8710",
    "sg:postcode":"60614",
    "sg:province":"IL",
    "sg:tags":[
        "sandwich"
    ],
    "sg:website":"www.secondcitysubs.com",
    "wof:name":"Second City Subs",
    "wof:placetype":"venue"
},
  "geometry": {"coordinates":[-87.64896899999999,41.921351],"type":"Point"}
}