{
  "type": "Feature",
  "properties": {
    "addr:full":"2239 W Fullerton Ave Chicago IL 60647",
    "addr:housenumber":"2239",
    "addr:postcode":"60647",
    "addr:street":"W Fullerton Ave",
    "iso:country":"US",
    "sg:address":"2239 W Fullerton Ave",
    "sg:city":"Chicago",
    "sg:classifiers":[
        {
            "category":"Real Estate",
            "subcategory":"Real Estate Agent",
            "type":"Services"
        }
    ],
    "sg:phone":"+1 773 227 7609",
    "sg:postcode":"60647",
    "sg:province":"IL",
    "sg:tags":[
        "appraiser"
    ],
    "sg:website":"http://www.kinczelappraisals.com",
    "wof:name":"Kinczel Appraisal Services",
    "wof:placetype":"venue"
},
  "geometry": {"coordinates":[-87.684657,41.924942],"type":"Point"}
}