{
  "type": "Feature",
  "properties": {
    "iso:country":"US",
    "sg:address":"2121 Bloomingdale Rd",
    "sg:city":"Glendale Heights",
    "sg:classifiers":[
        {
            "category":"Restaurant",
            "type":"Food & Drink"
        }
    ],
    "sg:menulink":"http://www.allmenus.com/il/bloomingdale/167115-burger-king/menu/",
    "sg:phone":"+1 708 894 2510",
    "sg:postcode":"60139",
    "sg:province":"IL",
    "sg:tags":[
        "burger",
        "american"
    ],
    "wof:name":"Burger King",
    "wof:placetype":"venue"
},
  "geometry": {"coordinates":[-88.08016600000001,41.936635],"type":"Point"}
}