{
  "type": "Feature",
  "properties": {
    "iso:country":"US",
    "sg:address":"3000 W Deyoung St Ste 716",
    "sg:city":"Marion",
    "sg:classifiers":[
        {
            "category":"Shopping",
            "subcategory":"Clothing, Apparel, & Fashions",
            "type":"Retail Goods"
        }
    ],
    "sg:phone":"+1 618 997 8091",
    "sg:postcode":"62959",
    "sg:province":"IL",
    "sg:tags":[
        "accessory"
    ],
    "sg:website":"www.debshops.com",
    "wof:name":"Deb Shop",
    "wof:placetype":"venue"
},
  "geometry": {"coordinates":[-88.97689099999999,37.745043],"type":"Point"}
}