{
  "type": "Feature",
  "properties": {
    "addr:full":"2635 W 39th Pl Chicago IL 60632",
    "addr:housenumber":"2635",
    "addr:postcode":"60632",
    "addr:street":"W 39Th Pl",
    "iso:country":"US",
    "sg:address":"2635 W 39th Pl",
    "sg:city":"Chicago",
    "sg:classifiers":[
        {
            "category":"Banks & Credit Unions",
            "subcategory":"Financial Services",
            "type":"Services"
        }
    ],
    "sg:phone":"+1 773 927 8525",
    "sg:postcode":"60632",
    "sg:province":"IL",
    "sg:tags":[
        "money",
        "order",
        "transfer"
    ],
    "wof:name":"Mexico Transfers",
    "wof:placetype":"venue"
},
  "geometry": {"coordinates":[-87.69143699999999,41.821941],"type":"Point"}
}