{
  "type": "Feature",
  "properties": {
    "addr:full":"1290 Valley Rd Deerfield IL 60015",
    "addr:housenumber":"1290",
    "addr:postcode":"60015",
    "addr:street":"Valley Rd",
    "iso:country":"US",
    "sg:address":"1290 Valley Rd",
    "sg:city":"Deerfield",
    "sg:classifiers":[
        {
            "category":"Professional",
            "subcategory":"Computer Services",
            "type":"Services"
        }
    ],
    "sg:phone":"+1 847 317 0413",
    "sg:postcode":"60015",
    "sg:province":"IL",
    "sg:tags":[
        "prepackaged",
        "datum",
        "software"
    ],
    "wof:name":"Clear Communications",
    "wof:placetype":"venue"
},
  "geometry": {"coordinates":[-87.86120099999999,42.189908],"type":"Point"}
}