{
  "type": "Feature",
  "properties": {
    "iso:country":"US",
    "sg:address":"12524 N 300th St",
    "sg:city":"Wheeler",
    "sg:classifiers":[
        {
            "category":"Wholesale",
            "subcategory":"Meat",
            "type":"Manufacturing & Wholesale Goods"
        }
    ],
    "sg:phone":"+1 217 925 5619",
    "sg:postcode":"62479",
    "sg:province":"IL",
    "wof:name":"Probst Pork Inc",
    "wof:placetype":"venue"
},
  "geometry": {"coordinates":[-88.316519,39.029262],"type":"Point"}
}