{
  "type": "Feature",
  "properties": {
    "iso:country":"US",
    "sg:address":"218 E Garfield St",
    "sg:city":"Belleville",
    "sg:classifiers":[
        {
            "category":"Real Estate",
            "subcategory":"Real Estate Agent",
            "type":"Services"
        }
    ],
    "sg:phone":"+1 618 235 0300",
    "sg:postcode":"62220",
    "sg:province":"IL",
    "wof:name":"Daubach Real Estate",
    "wof:placetype":"venue"
},
  "geometry": {"coordinates":[-89.980424,38.509699],"type":"Point"}
}