{
  "type": "Feature",
  "properties": {
    "addr:full":"41339 N US Hwy 41 Wadsworth IL 60083",
    "addr:housenumber":"41339",
    "addr:postcode":"60083",
    "addr:street":"N Us Hwy 41",
    "iso:country":"US",
    "sg:address":"41339 N US Hwy 41",
    "sg:city":"Wadsworth",
    "sg:classifiers":[
        {
            "category":"Wholesale",
            "subcategory":"Auto Parts",
            "type":"Manufacturing & Wholesale Goods"
        }
    ],
    "sg:phone":"+1 847 395 7600",
    "sg:postcode":"60083",
    "sg:province":"IL",
    "sg:tags":[
        "automobile",
        "rebuilt"
    ],
    "sg:website":"www.greenleafauto.com",
    "wof:name":"Hy-Way Auto Parts Inc",
    "wof:placetype":"venue"
},
  "geometry": {"coordinates":[-87.94650799999999,42.462846],"type":"Point"}
}