{
  "type": "Feature",
  "properties": {
    "iso:country":"US",
    "sg:address":"5375 Walnut Ave",
    "sg:city":"Downers Grove",
    "sg:classifiers":[
        {
            "category":"Manufacturing",
            "subcategory":"Printing",
            "type":"Manufacturing & Wholesale Goods"
        }
    ],
    "sg:phone":"+1 630 968 5013",
    "sg:postcode":"60515",
    "sg:province":"IL",
    "sg:tags":[
        "bookbinding"
    ],
    "wof:name":"Adhesive Binding Corporation",
    "wof:placetype":"venue"
},
  "geometry": {"coordinates":[-88.051903,41.788556],"type":"Point"}
}