{
  "type": "Feature",
  "properties": {
    "iso:country":"US",
    "sg:address":"1125 119th St",
    "sg:city":"Lemont",
    "sg:classifiers":[
        {
            "category":"Shopping",
            "type":"Retail Goods"
        }
    ],
    "sg:phone":"+1 630 257 9075",
    "sg:postcode":"60439",
    "sg:province":"IL",
    "sg:tags":[
        "pet",
        "food",
        "supply"
    ],
    "wof:name":"Gone To The Dogs LTD",
    "wof:placetype":"venue"
},
  "geometry": {"coordinates":[-87.973902,41.671634],"type":"Point"}
}