{
  "type": "Feature",
  "properties": {
    "iso:country":"US",
    "sg:address":"217 S 1st St",
    "sg:city":"Monmouth",
    "sg:classifiers":[
        {
            "category":"Health Services",
            "subcategory":"Doctor",
            "type":"Services"
        }
    ],
    "sg:phone":"+1 309 734 5855",
    "sg:postcode":"61462",
    "sg:province":"IL",
    "sg:tags":[
        "physician",
        "medical",
        "surgeon"
    ],
    "wof:name":"Badia Jabdour MD",
    "wof:placetype":"venue"
},
  "geometry": {"coordinates":[-90.646962,40.910739],"type":"Point"}
}