{
  "type": "Feature",
  "properties": {
    "iso:country":"US",
    "sg:address":"1351 S Alpine Rd",
    "sg:city":"Rockford",
    "sg:classifiers":[
        {
            "category":"Shopping",
            "subcategory":"Jewelry",
            "type":"Retail Goods"
        }
    ],
    "sg:phone":"+1 815 399 6746",
    "sg:postcode":"61108",
    "sg:province":"IL",
    "sg:tags":[
        "jeweler"
    ],
    "wof:name":"Rowland's Jewelry Co",
    "wof:placetype":"venue"
},
  "geometry": {"coordinates":[-89.02916,42.253107],"type":"Point"}
}