{
  "type": "Feature",
  "properties": {
    "iso:country":"US",
    "sg:address":"7601 S Cicero Ave Ste 5501",
    "sg:city":"Chicago",
    "sg:classifiers":[
        {
            "category":"Shopping",
            "subcategory":"Beauty & Cosmetics",
            "type":"Retail Goods"
        }
    ],
    "sg:phone":"+1 773 767 7608",
    "sg:postcode":"60652",
    "sg:province":"IL",
    "sg:tags":[
        "supply"
    ],
    "wof:name":"Color Me Beautiful by Patricia",
    "wof:placetype":"venue"
},
  "geometry": {"coordinates":[-87.741236,41.75433],"type":"Point"}
}