{
  "type": "Feature",
  "properties": {
    "addr:full":"4811 W Orchard Dr Mc Henry IL 60050",
    "addr:housenumber":"4811",
    "addr:postcode":"60050",
    "addr:street":"W Orchard Dr",
    "iso:country":"US",
    "sg:address":"4811 W Orchard Dr",
    "sg:city":"Mc Henry",
    "sg:classifiers":[
        {
            "category":"Government",
            "subcategory":"Police Station",
            "type":"Public Place"
        }
    ],
    "sg:phone":"+1   ",
    "sg:postcode":"60050",
    "sg:province":"IL",
    "sg:tags":[
        "protection"
    ],
    "wof:name":"McCollom Lake Vlg Police Dept",
    "wof:placetype":"venue"
},
  "geometry": {"coordinates":[-88.290352,42.366291],"type":"Point"}
}