{
  "type": "Feature",
  "properties": {
    "iso:country":"US",
    "sg:address":"5300 S Wood Street",
    "sg:city":"Chicago",
    "sg:classifiers":[
        {
            "category":"Food & Beverages",
            "subcategory":"Groceries & Convenience Stores",
            "type":"Retail Goods"
        }
    ],
    "sg:phone":"+1 773 476 4584",
    "sg:postcode":"60609",
    "sg:province":"IL",
    "wof:name":"53 Quick Market",
    "wof:placetype":"venue"
},
  "geometry": {"coordinates":[-87.66959900000001,41.797488],"type":"Point"}
}