{
  "type": "Feature",
  "properties": {
    "iso:country":"US",
    "sg:address":"610 S Maple St",
    "sg:city":"Centralia",
    "sg:classifiers":[
        {
            "category":"Food & Beverages",
            "subcategory":"Groceries & Convenience Stores",
            "type":"Retail Goods"
        }
    ],
    "sg:phone":"+1 618 532 7851",
    "sg:postcode":"62801",
    "sg:province":"IL",
    "sg:tags":[
        "grocer"
    ],
    "wof:name":"Miller's Discount",
    "wof:placetype":"venue"
},
  "geometry": {"coordinates":[-89.131894,38.520449],"type":"Point"}
}