{
  "type": "Feature",
  "properties": {
    "iso:country":"US",
    "sg:address":"5309 Lincoln Ave",
    "sg:city":"Skokie",
    "sg:classifiers":[
        {
            "category":"Manufacturing",
            "subcategory":"Printing",
            "type":"Manufacturing & Wholesale Goods"
        }
    ],
    "sg:phone":"+1 847 673 4440",
    "sg:postcode":"60077",
    "sg:province":"IL",
    "sg:tags":[
        "publishing"
    ],
    "wof:name":"Tri-Media Publications",
    "wof:placetype":"venue"
},
  "geometry": {"coordinates":[-87.761224,42.03417],"type":"Point"}
}