{
  "type": "Feature",
  "properties": {
    "addr:full":"110 S Deerpath Dr Vernon Hills IL 60061",
    "addr:housenumber":"110",
    "addr:postcode":"60061",
    "addr:street":"S Deerpath Dr",
    "iso:country":"US",
    "sg:address":"110 S Deerpath Dr",
    "sg:city":"Vernon Hills",
    "sg:classifiers":[
        {
            "category":"Professional",
            "subcategory":"Business Services",
            "type":"Services"
        }
    ],
    "sg:phone":"+1 847 362 9524",
    "sg:postcode":"60061",
    "sg:province":"IL",
    "sg:tags":[
        "building",
        "inspection"
    ],
    "wof:name":"Know-Fault LTD Inc",
    "wof:placetype":"venue"
},
  "geometry": {"coordinates":[-87.965254,42.223288],"type":"Point"}
}