{
  "type": "Feature",
  "properties": {
    "addr:full":"22 Heritage Plz Bourbonnais IL 60914",
    "addr:housenumber":"22",
    "addr:postcode":"60914",
    "addr:street":"Heritage Plz Bourbonnais",
    "iso:country":"US",
    "sg:address":"22 Heritage Plz",
    "sg:city":"Bourbonnais",
    "sg:classifiers":[
        {
            "category":"Health Services",
            "subcategory":"Health Practitioner",
            "type":"Services"
        }
    ],
    "sg:phone":"+1 815 939 4978",
    "sg:postcode":"60914",
    "sg:province":"IL",
    "sg:tags":[
        "psychologist"
    ],
    "wof:name":"Attention Deficit",
    "wof:placetype":"venue"
},
  "geometry": {"coordinates":[-87.878524,41.164051],"type":"Point"}
}