{
  "type": "Feature",
  "properties": {
    "iso:country":"US",
    "sg:address":"2900 Old Creal Springs Rd",
    "sg:city":"Marion",
    "sg:classifiers":[
        {
            "category":"Transit Center",
            "subcategory":"Freight",
            "type":"Transportation"
        },
        {
            "category":"Freight",
            "type":"Transportation"
        }
    ],
    "sg:phone":"+1 618 993 3440",
    "sg:postcode":"62959",
    "sg:province":"IL",
    "sg:tags":[
        "local",
        "trucking-motor",
        "trucking"
    ],
    "sg:website":"http://www.dlwhiteconstruction.com",
    "wof:name":"D L White Company",
    "wof:placetype":"venue"
},
  "geometry": {"coordinates":[-88.893677,37.70742],"type":"Point"}
}