{
  "type": "Feature",
  "properties": {
    "iso:country":"US",
    "sg:address":"101 S Cross St",
    "sg:city":"Wheaton",
    "sg:classifiers":[
        {
            "category":"Banks & Credit Unions",
            "subcategory":"Bank",
            "type":"Services"
        }
    ],
    "sg:phone":"+1 630 510 6894",
    "sg:postcode":"60187",
    "sg:province":"IL",
    "wof:name":"Northern Trust",
    "wof:placetype":"venue"
},
  "geometry": {"coordinates":[-88.10498699999999,41.865066],"type":"Point"}
}