{
  "type": "Feature",
  "properties": {
    "addr:full":"670 Ruskin Dr Elk Grove Village IL 60007",
    "addr:housenumber":"670",
    "addr:postcode":"60007",
    "addr:street":"Ruskin Dr",
    "iso:country":"US",
    "sg:address":"670 Ruskin Dr",
    "sg:city":"Elk Grove Village",
    "sg:classifiers":[
        {
            "category":"Professional",
            "subcategory":"Accounting & Tax Preparation",
            "type":"Services"
        }
    ],
    "sg:phone":"+1 847 593 5478",
    "sg:postcode":"60007",
    "sg:province":"IL",
    "sg:tags":[
        "return"
    ],
    "wof:name":"Kenneth D Zaboth",
    "wof:placetype":"venue"
},
  "geometry": {"coordinates":[-88.018001,42.011949],"type":"Point"}
}