{
  "type": "Feature",
  "properties": {
    "addr:full":"501 Pingree Rd Crystal Lake IL 60014",
    "addr:housenumber":"501",
    "addr:postcode":"60014",
    "addr:street":"Pingree Rd",
    "iso:country":"US",
    "sg:address":"501 Pingree Rd",
    "sg:city":"Crystal Lake",
    "sg:classifiers":[
        {
            "category":"Ice Cream",
            "type":"Food & Drink"
        }
    ],
    "sg:menulink":"http://www.allmenus.com/il/algonquin/182690-culvers/menu/",
    "sg:phone":"+1 815 356 9090",
    "sg:postcode":"60014",
    "sg:province":"IL",
    "sg:tags":[
        "burger",
        "american"
    ],
    "wof:name":"Culver's",
    "wof:placetype":"venue"
},
  "geometry": {"coordinates":[-88.295958,42.216966],"type":"Point"}
}