{
  "type": "Feature",
  "properties": {
    "iso:country":"US",
    "sg:address":"220 N Highway Ave",
    "sg:city":"De Land",
    "sg:classifiers":[
        {
            "category":"Banks & Credit Unions",
            "subcategory":"Bank",
            "type":"Services"
        }
    ],
    "sg:phone":"+1 217 664 3311",
    "sg:postcode":"61839",
    "sg:province":"IL",
    "wof:name":"First Mid-Illinois Bank & Trst",
    "wof:placetype":"venue"
},
  "geometry": {"coordinates":[-88.647492,40.125487],"type":"Point"}
}