{
  "type": "Feature",
  "properties": {
    "addr:full":"2009 Fox Dr Champaign IL 61820",
    "addr:housenumber":"2009",
    "addr:postcode":"61820",
    "addr:street":"Fox Dr",
    "iso:country":"US",
    "sg:address":"2009 Fox Dr",
    "sg:city":"Champaign",
    "sg:classifiers":[
        {
            "category":"Real Estate",
            "subcategory":"Real Estate Agent",
            "type":"Services"
        }
    ],
    "sg:phone":"+1 217 373 4984",
    "sg:postcode":"61820",
    "sg:province":"IL",
    "sg:tags":[
        "appraiser"
    ],
    "wof:name":"Bamert & Assoc",
    "wof:placetype":"venue"
},
  "geometry": {"coordinates":[-88.250124,40.091924],"type":"Point"}
}