{
  "type": "Feature",
  "properties": {
    "addr:full":"1486 Miner St Des Plaines IL 60016",
    "addr:housenumber":"1486",
    "addr:postcode":"60016",
    "addr:street":"Miner St",
    "iso:country":"US",
    "sg:address":"1486 Miner St",
    "sg:city":"Des Plaines",
    "sg:classifiers":[
        {
            "category":"Personal",
            "subcategory":"Beauty Salon",
            "type":"Services"
        }
    ],
    "sg:phone":"+1 847 296 5753",
    "sg:postcode":"60016",
    "sg:province":"IL",
    "sg:tags":[
        "shop"
    ],
    "wof:name":"Lucia Debartolo Salon",
    "wof:placetype":"venue"
},
  "geometry": {"coordinates":[-87.886824,42.04135],"type":"Point"}
}