{
  "type": "Feature",
  "properties": {
    "addr:full":"2537 Vandalia St Collinsville IL 62234",
    "addr:housenumber":"2537",
    "addr:postcode":"62234",
    "addr:street":"Vandalia St",
    "iso:country":"US",
    "sg:address":"2537 Vandalia St",
    "sg:city":"Collinsville",
    "sg:classifiers":[
        {
            "category":"Restaurant",
            "type":"Food & Drink"
        }
    ],
    "sg:phone":"+1   ",
    "sg:postcode":"62234",
    "sg:province":"IL",
    "sg:tags":[
        "eating"
    ],
    "wof:name":"Sharkys",
    "wof:placetype":"venue"
},
  "geometry": {"coordinates":[-89.960295,38.703416],"type":"Point"}
}