{
  "type": "Feature",
  "properties": {
    "iso:country":"US",
    "sg:address":"613 1st St",
    "sg:city":"La Salle",
    "sg:classifiers":[
        {
            "category":"Insurance",
            "subcategory":"Insurance Agent",
            "type":"Services"
        }
    ],
    "sg:phone":"+1 815 223 7590",
    "sg:postcode":"61301",
    "sg:province":"IL",
    "wof:name":"Northwestern Mutual Financial",
    "wof:placetype":"venue"
},
  "geometry": {"coordinates":[-89.095546,41.328156],"type":"Point"}
}