{
  "type": "Feature",
  "properties": {
    "iso:country":"US",
    "sg:address":"1519 S Galena Ave",
    "sg:city":"Dixon",
    "sg:classifiers":[
        {
            "category":"Building & Trades",
            "subcategory":"Landscaping Services",
            "type":"Services"
        }
    ],
    "sg:phone":"+1 815 652 4626",
    "sg:postcode":"61021",
    "sg:province":"IL",
    "wof:name":"Roux Tree Service",
    "wof:placetype":"venue"
},
  "geometry": {"coordinates":[-89.47615,41.82917],"type":"Point"}
}