{
  "type": "Feature",
  "properties": {
    "addr:full":"1701 Wilson Rd Urbana IL 61802",
    "addr:housenumber":"1701",
    "addr:postcode":"61802",
    "addr:street":"Wilson Rd",
    "iso:country":"US",
    "sg:address":"1701 Wilson Rd",
    "sg:city":"Urbana",
    "sg:classifiers":[
        {
            "category":"Building & Trades",
            "subcategory":"Landscaping Services",
            "type":"Services"
        }
    ],
    "sg:phone":"+1 217 328 6499",
    "sg:postcode":"61802",
    "sg:province":"IL",
    "wof:name":"Burnett Mark S",
    "wof:placetype":"venue"
},
  "geometry": {"coordinates":[-88.186267,40.116231],"type":"Point"}
}