{
  "type": "Feature",
  "properties": {
    "iso:country":"US",
    "sg:address":"3774 E 1200th Ave",
    "sg:city":"Wheeler",
    "sg:classifiers":[
        {
            "category":"Freight",
            "type":"Transportation"
        }
    ],
    "sg:phone":"+1 618 783 3633",
    "sg:postcode":"62479",
    "sg:province":"IL",
    "sg:tags":[
        "trucking"
    ],
    "wof:name":"Emmerich Trucking Inc",
    "wof:placetype":"venue"
},
  "geometry": {"coordinates":[-88.302887,39.026076],"type":"Point"}
}