{
  "type": "Feature",
  "properties": {
    "addr:full":"305 Elmwood Rd Romeoville IL 60446",
    "addr:housenumber":"305",
    "addr:postcode":"60446",
    "addr:street":"Elmwood Rd",
    "iso:country":"US",
    "sg:address":"305 Elmwood Rd",
    "sg:city":"Romeoville",
    "sg:classifiers":[
        {
            "category":"Structure",
            "subcategory":"Warehouse",
            "type":"Public Place"
        },
        {
            "category":"Retail",
            "subcategory":"Storage",
            "type":"Services"
        }
    ],
    "sg:phone":"+1 815 886 1278",
    "sg:postcode":"60446",
    "sg:province":"IL",
    "sg:tags":[
        "self",
        "warehouses-public-commercial"
    ],
    "sg:website":"http://www.eurekaco.com",
    "wof:name":"Electrolux Home Products Inc",
    "wof:placetype":"venue"
},
  "geometry": {"coordinates":[-88.07933800000001,41.663689],"type":"Point"}
}