{
  "type": "Feature",
  "properties": {
    "iso:country":"US",
    "sg:address":"2319 Hartzell St",
    "sg:city":"Evanston",
    "sg:classifiers":[
        {
            "category":"Professional",
            "subcategory":"Business Services",
            "type":"Services"
        }
    ],
    "sg:phone":"+1 847 491 0188",
    "sg:postcode":"60201",
    "sg:province":"IL",
    "sg:tags":[
        "interior",
        "design"
    ],
    "wof:name":"Bck Interiors",
    "wof:placetype":"venue"
},
  "geometry": {"coordinates":[-87.707663,42.065565],"type":"Point"}
}