{
  "type": "Feature",
  "properties": {
    "iso:country":"US",
    "sg:address":"6732 Harrison Ave",
    "sg:city":"Rockford",
    "sg:classifiers":[
        {
            "category":"Organizations",
            "subcategory":"Religious Organization",
            "type":"Services"
        }
    ],
    "sg:phone":"+1 815 229 7600",
    "sg:postcode":"61108",
    "sg:province":"IL",
    "sg:website":"www.rockchurch.net",
    "wof:name":"Rock Church",
    "wof:placetype":"venue"
},
  "geometry": {"coordinates":[-88.985429,42.238792],"type":"Point"}
}