{
  "type": "Feature",
  "properties": {
    "addr:full":"1365 E Forest Ave Des Plaines IL 60018",
    "addr:housenumber":"1365",
    "addr:postcode":"60018",
    "addr:street":"E Forest Ave",
    "iso:country":"US",
    "sg:address":"1365 E Forest Ave",
    "sg:city":"Des Plaines",
    "sg:classifiers":[
        {
            "category":"Wholesale",
            "subcategory":"Machinery & Supplies",
            "type":"Manufacturing & Wholesale Goods"
        }
    ],
    "sg:phone":"+1 847 296 6379",
    "sg:postcode":"60018",
    "sg:province":"IL",
    "sg:tags":[
        "equipment",
        "paint"
    ],
    "wof:name":"Alfresco Enterprises Inc",
    "wof:placetype":"venue"
},
  "geometry": {"coordinates":[-87.890435,42.027682],"type":"Point"}
}