{
  "type": "Feature",
  "properties": {
    "addr:full":"2316 Etherton Rd Murphysboro IL 62966",
    "addr:housenumber":"2316",
    "addr:postcode":"62966",
    "addr:street":"Etherton Rd",
    "iso:country":"US",
    "sg:address":"2316 Etherton Rd",
    "sg:city":"Murphysboro",
    "sg:classifiers":[
        {
            "category":"Building & Trades",
            "subcategory":"Construction",
            "type":"Services"
        }
    ],
    "sg:phone":"+1 618 684 3919",
    "sg:postcode":"62966",
    "sg:province":"IL",
    "sg:tags":[
        "carpenter"
    ],
    "wof:name":"George Davis Carpentry",
    "wof:placetype":"venue"
},
  "geometry": {"coordinates":[-89.352335,37.687283],"type":"Point"}
}