{
  "type": "Feature",
  "properties": {
    "addr:full":"635 E Maple Ave Mundelein IL 60060",
    "addr:housenumber":"635",
    "addr:postcode":"60060",
    "addr:street":"E Maple Ave",
    "iso:country":"US",
    "sg:address":"635 E Maple Ave",
    "sg:city":"Mundelein",
    "sg:classifiers":[
        {
            "category":"Professional",
            "subcategory":"Computer Services",
            "type":"Services"
        }
    ],
    "sg:phone":"+1 847 566 8468",
    "sg:postcode":"60060",
    "sg:province":"IL",
    "sg:tags":[
        "consultant"
    ],
    "wof:name":"Cablenet Technology Inc",
    "wof:placetype":"venue"
},
  "geometry": {"coordinates":[-87.987771,42.274127],"type":"Point"}
}