{
  "type": "Feature",
  "properties": {
    "addr:full":"314 S Bureau Ave Ladd IL 61329",
    "addr:housenumber":"314",
    "addr:postcode":"61329",
    "addr:street":"S Bureau Ave",
    "iso:country":"US",
    "sg:address":"314 S Bureau Ave",
    "sg:city":"Ladd",
    "sg:classifiers":[
        {
            "category":"Organizations",
            "subcategory":"Religious Organization",
            "type":"Services"
        }
    ],
    "sg:phone":"+1 815 894 2319",
    "sg:postcode":"61329",
    "sg:province":"IL",
    "sg:tags":[
        "church"
    ],
    "wof:name":"St Benedict Catholic Church",
    "wof:placetype":"venue"
},
  "geometry": {"coordinates":[-89.22040200000001,41.379139],"type":"Point"}
}