{
  "type": "Feature",
  "properties": {
    "iso:country":"US",
    "sg:address":"1109 N State St",
    "sg:city":"Belvidere",
    "sg:classifiers":[
        {
            "category":"Retail",
            "subcategory":"Laundry & Dry Cleaning",
            "type":"Services"
        }
    ],
    "sg:phone":"+1 815 544 7766",
    "sg:postcode":"61008",
    "sg:province":"IL",
    "wof:name":"Belvidere Laundromat",
    "wof:placetype":"venue"
},
  "geometry": {"coordinates":[-88.850943,42.26735],"type":"Point"}
}