{
  "type": "Feature",
  "properties": {
    "iso:country":"US",
    "sg:address":"108 E Iowa St",
    "sg:city":"Oblong",
    "sg:classifiers":[
        {
            "category":"Manufacturing",
            "subcategory":"Food",
            "type":"Manufacturing & Wholesale Goods"
        },
        {
            "category":"Farming",
            "subcategory":"Livestock Farm",
            "type":"Manufacturing & Wholesale Goods"
        },
        {
            "category":"Farming",
            "subcategory":"Farm",
            "type":"Manufacturing & Wholesale Goods"
        }
    ],
    "sg:phone":"+1 618 592 3650",
    "sg:postcode":"62449",
    "sg:province":"IL",
    "sg:tags":[
        "product"
    ],
    "wof:name":"Meese Farms",
    "wof:placetype":"venue"
},
  "geometry": {"coordinates":[-87.908954,39.005959],"type":"Point"}
}