{
  "type": "Feature",
  "properties": {
    "iso:country":"US",
    "sg:address":"4018 Charleston Rd",
    "sg:city":"Matteson",
    "sg:classifiers":[
        {
            "category":"Shopping",
            "subcategory":"Beauty & Cosmetics",
            "type":"Retail Goods"
        }
    ],
    "sg:phone":"+1   ",
    "sg:postcode":"60443",
    "sg:province":"IL",
    "sg:tags":[
        "merchandise"
    ],
    "wof:name":"Wendy Wells Cosmetics",
    "wof:placetype":"venue"
},
  "geometry": {"coordinates":[-87.714091,41.49839],"type":"Point"}
}