{
  "type": "Feature",
  "properties": {
    "addr:full":"1825 N Winnebago Ave Chicago IL 60647",
    "addr:housenumber":"1825",
    "addr:postcode":"60647",
    "addr:street":"N Winnebago Ave",
    "iso:country":"US",
    "sg:address":"1825 N Winnebago Ave",
    "sg:city":"Chicago",
    "sg:classifiers":[
        {
            "category":"Home & Garden",
            "subcategory":"Kitchen Supply",
            "type":"Retail Goods"
        }
    ],
    "sg:phone":"+1 312 623 8415",
    "sg:postcode":"60647",
    "sg:province":"IL",
    "sg:tags":[
        "equipment",
        "restaurant"
    ],
    "wof:name":"Gm Exim",
    "wof:placetype":"venue"
},
  "geometry": {"coordinates":[-87.685348,41.914454],"type":"Point"}
}