{
  "type": "Feature",
  "properties": {
    "iso:country":"US",
    "sg:address":"20432 N 750th St",
    "sg:city":"Jewett",
    "sg:classifiers":[
        {
            "category":"Wholesale",
            "subcategory":"Farm Supplies",
            "type":"Manufacturing & Wholesale Goods"
        }
    ],
    "sg:phone":"+1 217 683 2613",
    "sg:postcode":"62436",
    "sg:province":"IL",
    "sg:tags":[
        "fertilizer"
    ],
    "wof:name":"Reisner Agri Sales & Service",
    "wof:placetype":"venue"
},
  "geometry": {"coordinates":[-88.236862,39.141718],"type":"Point"}
}