{
  "type": "Feature",
  "properties": {
    "iso:country":"US",
    "sg:address":"11002 Bartel Blvd",
    "sg:city":"Galena",
    "sg:classifiers":[
        {
            "category":"Retail",
            "subcategory":"Photofinishing",
            "type":"Services"
        },
        {
            "category":"Professional",
            "subcategory":"Printing & Photocopies",
            "type":"Services"
        },
        {
            "category":"Shopping",
            "subcategory":"Pharmacy",
            "type":"Retail Goods"
        }
    ],
    "sg:phone":"+1 815 777 2700",
    "sg:postcode":"61036",
    "sg:province":"IL",
    "sg:tags":[
        "laboratory",
        "photo",
        "finishing-custom",
        "laboratories-commercial"
    ],
    "sg:website":"http://www.hartigusadrug.com",
    "wof:name":"Hartig Drugs 5",
    "wof:placetype":"venue"
},
  "geometry": {"coordinates":[-90.447115,42.431802],"type":"Point"}
}