{
  "type": "Feature",
  "properties": {
    "addr:full":"1401 Eastland Dr Bloomington IL 61701",
    "addr:housenumber":"1401",
    "addr:postcode":"61701",
    "addr:street":"Eastland Dr",
    "iso:country":"US",
    "sg:address":"1401 Eastland Dr",
    "sg:city":"Bloomington",
    "sg:classifiers":[
        {
            "category":"Health Services",
            "subcategory":"Clinic",
            "type":"Services"
        }
    ],
    "sg:phone":"+1 309 663 9424",
    "sg:postcode":"61701",
    "sg:province":"IL",
    "sg:tags":[
        "welfare"
    ],
    "wof:name":"Kidney Stone Clinic",
    "wof:placetype":"venue"
},
  "geometry": {"coordinates":[-88.960701,40.483891],"type":"Point"}
}