{
  "type": "Feature",
  "properties": {
    "addr:full":"1441 S Meridian Rd Rockford IL 61102",
    "addr:housenumber":"1441",
    "addr:postcode":"61102",
    "addr:street":"S Meridian Rd",
    "iso:country":"US",
    "sg:address":"1441 S Meridian Rd",
    "sg:city":"Rockford",
    "sg:classifiers":[
        {
            "category":"Building & Trades",
            "subcategory":"Construction",
            "type":"Services"
        }
    ],
    "sg:phone":"+1 815 963 5916",
    "sg:postcode":"61102",
    "sg:province":"IL",
    "sg:tags":[
        "water",
        "well",
        "drilling"
    ],
    "wof:name":"Rosenquist & Sons",
    "wof:placetype":"venue"
},
  "geometry": {"coordinates":[-89.173649,42.263442],"type":"Point"}
}