{
  "type": "Feature",
  "properties": {
    "addr:full":"1446 Glenside Dr Bolingbrook IL 60490",
    "addr:housenumber":"1446",
    "addr:postcode":"60490",
    "addr:street":"Glenside Dr",
    "iso:country":"US",
    "sg:address":"1446 Glenside Dr",
    "sg:city":"Bolingbrook",
    "sg:classifiers":[
        {
            "category":"Manufacturing",
            "subcategory":"Printing",
            "type":"Manufacturing & Wholesale Goods"
        }
    ],
    "sg:phone":"+1 630 330 2480",
    "sg:postcode":"60490",
    "sg:province":"IL",
    "sg:tags":[
        "magazines-distributors"
    ],
    "wof:name":"Crei Magazine, Sam Jr Enterprises",
    "wof:placetype":"venue"
},
  "geometry": {"coordinates":[-88.135475,41.674357],"type":"Point"}
}