{
  "type": "Feature",
  "properties": {
    "addr:full":"4007 Tyler Dr Ottawa IL 61350",
    "addr:housenumber":"4007",
    "addr:postcode":"61350",
    "addr:street":"Tyler Dr",
    "iso:country":"US",
    "sg:address":"4007 Tyler Dr",
    "sg:city":"Ottawa",
    "sg:classifiers":[
        {
            "category":"Retail",
            "subcategory":"Repair Shop",
            "type":"Services"
        }
    ],
    "sg:phone":"+1 815 434 3488",
    "sg:postcode":"61350",
    "sg:province":"IL",
    "wof:name":"Artistic Finishes Inc",
    "wof:placetype":"venue"
},
  "geometry": {"coordinates":[-88.839052,41.377615],"type":"Point"}
}