{
  "type": "Feature",
  "properties": {
    "iso:country":"US",
    "sg:address":"170 N Oak St",
    "sg:city":"Crystal Lake",
    "sg:classifiers":[
        {
            "category":"Education",
            "subcategory":"School",
            "type":"Public Place"
        }
    ],
    "sg:phone":"+1 815 459 9210",
    "sg:postcode":"60014",
    "sg:province":"IL",
    "wof:name":"North Jr High School",
    "wof:placetype":"venue"
},
  "geometry": {"coordinates":[-88.335749,42.246808],"type":"Point"}
}