{
  "type": "Feature",
  "properties": {
    "iso:country":"US",
    "sg:address":"1500 S Schoolhouse Rd",
    "sg:city":"New Lenox",
    "sg:classifiers":[
        {
            "category":"Retail",
            "subcategory":"Auto Repair",
            "type":"Services"
        }
    ],
    "sg:phone":"+1 815 485 5422",
    "sg:postcode":"60451",
    "sg:province":"IL",
    "sg:tags":[
        "general"
    ],
    "wof:name":"Peak Truck Repair",
    "wof:placetype":"venue"
},
  "geometry": {"coordinates":[-87.925964,41.476451],"type":"Point"}
}