{
  "type": "Feature",
  "properties": {
    "addr:full":"2200 Sheridan Rd Pekin IL 61554",
    "addr:housenumber":"2200",
    "addr:postcode":"61554",
    "addr:street":"Sheridan Rd",
    "iso:country":"US",
    "sg:address":"2200 Sheridan Rd",
    "sg:city":"Pekin",
    "sg:classifiers":[
        {
            "category":"Health Services",
            "subcategory":"Health Practitioner",
            "type":"Services"
        },
        {
            "category":"Communications",
            "type":"Services"
        }
    ],
    "sg:phone":"+1 309 697 2169",
    "sg:postcode":"61554",
    "sg:province":"IL",
    "sg:tags":[
        "pathologist",
        "speech-language",
        "myofunctional",
        "therapy"
    ],
    "wof:name":"Darlene Roodhouse",
    "wof:placetype":"venue"
},
  "geometry": {"coordinates":[-89.6157,40.58239],"type":"Point"}
}