{
  "type": "Feature",
  "properties": {
    "addr:full":"150 W Half Day Rd Buffalo Grove IL 60089",
    "addr:housenumber":"150",
    "addr:postcode":"60089",
    "addr:street":"W Half Day Rd",
    "iso:country":"US",
    "sg:address":"150 W Half Day Rd",
    "sg:city":"Buffalo Grove",
    "sg:classifiers":[
        {
            "category":"Health Services",
            "subcategory":"Doctor",
            "type":"Services"
        }
    ],
    "sg:phone":"+1 847 913 8205",
    "sg:postcode":"60089",
    "sg:province":"IL",
    "sg:tags":[
        "dentist"
    ],
    "wof:name":"Arbor Dental Group PC",
    "wof:placetype":"venue"
},
  "geometry": {"coordinates":[-87.961009,42.195954],"type":"Point"}
}