{
  "type": "Feature",
  "properties": {
    "iso:country":"US",
    "sg:address":"6313 E State St",
    "sg:city":"Rockford",
    "sg:classifiers":[
        {
            "category":"Retail",
            "subcategory":"Laundry & Dry Cleaning",
            "type":"Services"
        }
    ],
    "sg:phone":"+1 815 229 3203",
    "sg:postcode":"61108",
    "sg:province":"IL",
    "sg:tags":[
        "drycleaning",
        "plant"
    ],
    "wof:name":"KS Cleaners",
    "wof:placetype":"venue"
},
  "geometry": {"coordinates":[-88.994846,42.267115],"type":"Point"}
}