{
  "type": "Feature",
  "properties": {
    "iso:country":"US",
    "sg:address":"719 S Batavia Ave",
    "sg:city":"Geneva",
    "sg:classifiers":[
        {
            "category":"Government",
            "subcategory":"Office",
            "type":"Public Place"
        }
    ],
    "sg:phone":"+1 630 232 5935",
    "sg:postcode":"60134",
    "sg:province":"IL",
    "wof:name":"KANE County Recorder",
    "wof:placetype":"venue"
},
  "geometry": {"coordinates":[-88.30918699999999,41.8804],"type":"Point"}
}