{
  "type": "Feature",
  "properties": {
    "iso:country":"US",
    "sg:address":"3507 S Glendale Dr",
    "sg:city":"Quincy",
    "sg:classifiers":[
        {
            "category":"Building & Trades",
            "subcategory":"Construction",
            "type":"Services"
        }
    ],
    "sg:phone":"+1 217 221 1950",
    "sg:postcode":"62301",
    "sg:province":"IL",
    "sg:tags":[
        "disability",
        "accessibility",
        "renovation"
    ],
    "wof:name":"Creative Mobility",
    "wof:placetype":"venue"
},
  "geometry": {"coordinates":[-91.358465,39.927048],"type":"Point"}
}