{
  "type": "Feature",
  "properties": {
    "iso:country":"US",
    "sg:address":"2851 Mound Rd",
    "sg:city":"Rockdale",
    "sg:classifiers":[
        {
            "category":"Professional",
            "subcategory":"Management & Consulting",
            "type":"Services"
        }
    ],
    "sg:phone":"+1 815 741 3406",
    "sg:postcode":"60436",
    "sg:province":"IL",
    "sg:tags":[
        "consultant",
        "energy",
        "conservation"
    ],
    "wof:name":"KMS-Joliet Power Partners",
    "wof:placetype":"venue"
},
  "geometry": {"coordinates":[-88.14676,41.499551],"type":"Point"}
}