{
  "type": "Feature",
  "properties": {
    "iso:country":"US",
    "sg:address":"6821 North Ave",
    "sg:city":"Oak Park",
    "sg:classifiers":[
        {
            "category":"Professional",
            "subcategory":"Lawyer & Legal Services",
            "type":"Services"
        }
    ],
    "sg:phone":"+1 708 524 3610",
    "sg:postcode":"60302",
    "sg:province":"IL",
    "wof:name":"Pellegrini & Cristiano",
    "wof:placetype":"venue"
},
  "geometry": {"coordinates":[-87.79613000000001,41.908694],"type":"Point"}
}