{
  "type": "Feature",
  "properties": {
    "iso:country":"US",
    "sg:address":"1010 E Walnut Ave",
    "sg:city":"Des Plaines",
    "sg:classifiers":[
        {
            "category":"Retail",
            "subcategory":"Repair Shop",
            "type":"Services"
        }
    ],
    "sg:phone":"+1 847 827 3990",
    "sg:postcode":"60016",
    "sg:province":"IL",
    "wof:name":"Geever Tennis",
    "wof:placetype":"venue"
},
  "geometry": {"coordinates":[-87.897929,42.03358],"type":"Point"}
}