{
  "type": "Feature",
  "properties": {
    "addr:full":"90 Toler Ln Goreville IL 62939",
    "addr:housenumber":"90",
    "addr:postcode":"62939",
    "addr:street":"Toler Ln",
    "iso:country":"US",
    "sg:address":"90 Toler Ln",
    "sg:city":"Goreville",
    "sg:classifiers":[
        {
            "category":"Shopping",
            "subcategory":"Gifts & Souvenirs",
            "type":"Retail Goods"
        }
    ],
    "sg:phone":"+1   ",
    "sg:postcode":"62939",
    "sg:province":"IL",
    "wof:name":"Lindas Gift Shoppe",
    "wof:placetype":"venue"
},
  "geometry": {"coordinates":[-89.011352,37.548336],"type":"Point"}
}