{
  "type": "Feature",
  "properties": {
    "iso:country":"US",
    "sg:address":"65 Surrey Ln",
    "sg:city":"Barrington",
    "sg:classifiers":[
        {
            "category":"Professional",
            "subcategory":"Business Services",
            "type":"Services"
        }
    ],
    "sg:phone":"+1 847 639 3646",
    "sg:postcode":"60010",
    "sg:province":"IL",
    "wof:name":"CMH Sales LLC",
    "wof:placetype":"venue"
},
  "geometry": {"coordinates":[-88.21161600000001,42.185197],"type":"Point"}
}