{
  "type": "Feature",
  "properties": {
    "iso:country":"US",
    "sg:address":"434 W 2nd St",
    "sg:city":"Elmhurst",
    "sg:classifiers":[
        {
            "category":"Professional",
            "subcategory":"Accounting & Tax Preparation",
            "type":"Services"
        }
    ],
    "sg:phone":"+1 630 261 8400",
    "sg:postcode":"60126",
    "sg:province":"IL",
    "wof:name":"Veiths Financial Services",
    "wof:placetype":"venue"
},
  "geometry": {"coordinates":[-87.957238,41.902809],"type":"Point"}
}