{
  "type": "Feature",
  "properties": {
    "iso:country":"US",
    "sg:address":"430 W Stephenson St",
    "sg:city":"Freeport",
    "sg:classifiers":[
        {
            "category":"Health Services",
            "subcategory":"Doctor",
            "type":"Services"
        }
    ],
    "sg:phone":"+1 815 235 2930",
    "sg:postcode":"61032",
    "sg:province":"IL",
    "sg:tags":[
        "dentist"
    ],
    "wof:name":"Michael De Gould DDS",
    "wof:placetype":"venue"
},
  "geometry": {"coordinates":[-89.624824,42.296533],"type":"Point"}
}