{
  "type": "Feature",
  "properties": {
    "addr:full":"819 W Keith Ave Waukegan IL 60085",
    "addr:housenumber":"819",
    "addr:postcode":"60085",
    "addr:street":"W Keith Ave",
    "iso:country":"US",
    "sg:address":"819 W Keith Ave",
    "sg:city":"Waukegan",
    "sg:classifiers":[
        {
            "category":"Arts & Performance",
            "subcategory":"Theater",
            "type":"Entertainment"
        }
    ],
    "sg:phone":"+1 847 623 9445",
    "sg:postcode":"60085",
    "sg:province":"IL",
    "sg:tags":[
        "group"
    ],
    "wof:name":"Jeanne Houle Music",
    "wof:placetype":"venue"
},
  "geometry": {"coordinates":[-87.841514,42.382836],"type":"Point"}
}