{
  "type": "Feature",
  "properties": {
    "addr:full":"303 S Mattis Ave Ste 100 Champaign IL 61821",
    "addr:housenumber":"303",
    "addr:postcode":"61821",
    "addr:street":"S Mattis Ave Ste 100",
    "iso:country":"US",
    "sg:address":"303 S Mattis Ave Ste 100",
    "sg:city":"Champaign",
    "sg:classifiers":[
        {
            "category":"Banks & Credit Unions",
            "subcategory":"Bank",
            "type":"Services"
        }
    ],
    "sg:phone":"+1 217 353 4428",
    "sg:postcode":"61821",
    "sg:province":"IL",
    "wof:name":"Chase",
    "wof:placetype":"venue"
},
  "geometry": {"coordinates":[-88.277045,40.114086],"type":"Point"}
}