{
  "type": "Feature",
  "properties": {
    "addr:full":"200 S Wacker Dr Ste 1500 Chicago IL 60606",
    "addr:housenumber":"200",
    "addr:postcode":"60606",
    "addr:street":"S Wacker Dr Ste 1500",
    "iso:country":"US",
    "sg:address":"200 S Wacker Dr Ste 1500",
    "sg:city":"Chicago",
    "sg:classifiers":[
        {
            "category":"Real Estate",
            "subcategory":"Developer",
            "type":"Services"
        }
    ],
    "sg:phone":"+1 312 924 1444",
    "sg:postcode":"60606",
    "sg:province":"IL",
    "sg:tags":[
        "investing"
    ],
    "wof:name":"Managed Agility",
    "wof:placetype":"venue"
},
  "geometry": {"coordinates":[-87.636948,41.879261],"type":"Point"}
}