{
  "type": "Feature",
  "properties": {
    "addr:full":"2812 N Clark St Chicago IL 60657",
    "addr:housenumber":"2812",
    "addr:postcode":"60657",
    "addr:street":"N Clark St",
    "iso:country":"US",
    "sg:address":"2812 N Clark St",
    "sg:city":"Chicago",
    "sg:classifiers":[
        {
            "category":"Shopping",
            "subcategory":"Optician",
            "type":"Retail Goods"
        }
    ],
    "sg:phone":"+1 773 665 4786",
    "sg:postcode":"60657",
    "sg:province":"IL",
    "sg:tags":[
        "eyewear"
    ],
    "sg:website":"www.squintsunglasses.com",
    "wof:name":"Squint Sunglasses & Watch",
    "wof:placetype":"venue"
},
  "geometry": {"coordinates":[-87.645472,41.933045],"type":"Point"}
}