{
  "type": "Feature",
  "properties": {
    "iso:country":"US",
    "sg:address":"11427 S Emerald Ave",
    "sg:city":"Chicago",
    "sg:classifiers":[
        {
            "category":"Building & Trades",
            "subcategory":"Pest Control",
            "type":"Services"
        }
    ],
    "sg:phone":"+1 773 874 3929",
    "sg:postcode":"60628",
    "sg:province":"IL",
    "wof:name":"Reasonable Exterminators",
    "wof:placetype":"venue"
},
  "geometry": {"coordinates":[-87.640613,41.686112],"type":"Point"}
}