{
  "type": "Feature",
  "properties": {
    "addr:full":"2000 N Neil St Champaign IL 61820",
    "addr:housenumber":"2000",
    "addr:postcode":"61820",
    "addr:street":"N Neil St",
    "iso:country":"US",
    "sg:address":"2000 N Neil St",
    "sg:city":"Champaign",
    "sg:classifiers":[
        {
            "category":"Shopping",
            "subcategory":"Clothing, Apparel, & Fashions",
            "type":"Retail Goods"
        }
    ],
    "sg:phone":"+1 217 355 2400",
    "sg:postcode":"61820",
    "sg:province":"IL",
    "sg:tags":[
        "lingerie"
    ],
    "sg:website":"www.victoriassecret.com",
    "wof:name":"Victoria's Secret",
    "wof:placetype":"venue"
},
  "geometry": {"coordinates":[-88.24369799999999,40.138],"type":"Point"}
}