{
  "type": "Feature",
  "properties": {
    "iso:country":"US",
    "sg:address":"2909 N Sheridan Rd",
    "sg:city":"Chicago",
    "sg:classifiers":[
        {
            "category":"Cinema",
            "subcategory":"Movie Theater",
            "type":"Entertainment"
        }
    ],
    "sg:phone":"+1 773 880 0207",
    "sg:postcode":"60657",
    "sg:province":"IL",
    "wof:name":"About Face Theater",
    "wof:placetype":"venue"
},
  "geometry": {"coordinates":[-87.639291,41.93466],"type":"Point"}
}