{
  "type": "Feature",
  "properties": {
    "addr:full":"1818 Fenwick Ct Schaumburg IL 60194",
    "addr:housenumber":"1818",
    "addr:postcode":"60194",
    "addr:street":"Fenwick Ct",
    "iso:country":"US",
    "sg:address":"1818 Fenwick Ct",
    "sg:city":"Schaumburg",
    "sg:classifiers":[
        {
            "category":"Shopping",
            "type":"Retail Goods"
        }
    ],
    "sg:phone":"+1   ",
    "sg:postcode":"60194",
    "sg:province":"IL",
    "sg:tags":[
        "merchandise"
    ],
    "wof:name":"Flash Decorating",
    "wof:placetype":"venue"
},
  "geometry": {"coordinates":[-88.12481200000001,42.042241],"type":"Point"}
}