{
  "type": "Feature",
  "properties": {
    "addr:full":"12255 Walker Rd Lemont IL 60439",
    "addr:housenumber":"12255",
    "addr:postcode":"60439",
    "addr:street":"Walker Rd",
    "iso:country":"US",
    "sg:address":"12255 Walker Rd",
    "sg:city":"Lemont",
    "sg:classifiers":[
        {
            "category":"Sports & Exercise",
            "subcategory":"Gym",
            "type":"Entertainment"
        }
    ],
    "sg:phone":"+1 630 243 9710",
    "sg:postcode":"60439",
    "sg:province":"IL",
    "sg:tags":[
        "spa",
        "health"
    ],
    "wof:name":"Ambiance Day Spa",
    "wof:placetype":"venue"
},
  "geometry": {"coordinates":[-87.970934,41.665308],"type":"Point"}
}