{
  "type": "Feature",
  "properties": {
    "addr:full":"220 S Bridge St Yorkville IL 60560",
    "addr:housenumber":"220",
    "addr:postcode":"60560",
    "addr:street":"S Bridge St",
    "iso:country":"US",
    "sg:address":"220 S Bridge St",
    "sg:city":"Yorkville",
    "sg:classifiers":[
        {
            "category":"Banks & Credit Unions",
            "subcategory":"Bank",
            "type":"Services"
        },
        {
            "category":"Shopping",
            "subcategory":"Used Merchandise",
            "type":"Retail Goods"
        }
    ],
    "sg:phone":"+1 630 553 1847",
    "sg:postcode":"60560",
    "sg:province":"IL",
    "sg:tags":[
        "resale",
        "shop",
        "second",
        "hand"
    ],
    "wof:name":"Caring Hands Thrift Store A Ministry Of Cross",
    "wof:placetype":"venue"
},
  "geometry": {"coordinates":[-88.446865,41.641828],"type":"Point"}
}