{
  "type": "Feature",
  "properties": {
    "iso:country":"US",
    "sg:address":"23 W Main St",
    "sg:city":"Mascoutah",
    "sg:classifiers":[
        {
            "category":"Personal",
            "subcategory":"Beauty Salon",
            "type":"Services"
        }
    ],
    "sg:phone":"+1 618 566 4244",
    "sg:postcode":"62258",
    "sg:province":"IL",
    "sg:tags":[
        "shop"
    ],
    "wof:name":"Anita's Hair Affair",
    "wof:placetype":"venue"
},
  "geometry": {"coordinates":[-89.799764,38.490361],"type":"Point"}
}