{
  "type": "Feature",
  "properties": {
    "addr:full":"4506 W Lawrence Avenue Chicago IL 60630",
    "addr:housenumber":"4506",
    "addr:postcode":"60630",
    "addr:street":"W Lawrence Avenue",
    "iso:country":"US",
    "sg:address":"4506 W Lawrence Avenue",
    "sg:city":"Chicago",
    "sg:classifiers":[
        {
            "category":"Wholesale",
            "subcategory":"Non-durable Goods",
            "type":"Manufacturing & Wholesale Goods"
        },
        {
            "category":"Shopping",
            "subcategory":"Jewelry",
            "type":"Retail Goods"
        },
        {
            "category":"Professional",
            "subcategory":"Business Services",
            "type":"Services"
        }
    ],
    "sg:phone":"+1 773 777 3520",
    "sg:postcode":"60630",
    "sg:province":"IL",
    "sg:tags":[
        "broker",
        "merchandise",
        "merchandise-wholesale"
    ],
    "wof:name":"Max 969 Trading",
    "wof:placetype":"venue"
},
  "geometry": {"coordinates":[-87.742064,41.968085],"type":"Point"}
}