{
  "type": "Feature",
  "properties": {
    "iso:country":"US",
    "sg:address":"36407 Gray Rd",
    "sg:city":"Wilmington",
    "sg:phone":"+1 815 458 6617",
    "sg:postcode":"60481",
    "sg:province":"IL",
    "sg:tags":[
        "farm",
        "corn",
        "soybean"
    ],
    "wof:name":"Willie Love",
    "wof:placetype":"venue"
},
  "geometry": {"coordinates":[-88.108998,41.223165],"type":"Point"}
}