{
  "type": "Feature",
  "properties": {
    "iso:country":"US",
    "sg:address":"3049 Nattier Rd",
    "sg:city":"Salem",
    "sg:classifiers":[
        {
            "category":"Freight",
            "type":"Transportation"
        }
    ],
    "sg:phone":"+1 618 548 4071",
    "sg:postcode":"62881",
    "sg:province":"IL",
    "sg:tags":[
        "yard",
        "stock"
    ],
    "wof:name":"United Producers Inc",
    "wof:placetype":"venue"
},
  "geometry": {"coordinates":[-88.892365,38.587382],"type":"Point"}
}