{
  "type": "Feature",
  "properties": {
    "addr:full":"14N630 Il Route 25 Dundee IL 60118",
    "addr:housenumber":"14n630",
    "addr:postcode":"60118",
    "addr:street":"Il Route 25",
    "iso:country":"US",
    "sg:address":"14N630 Il Route 25",
    "sg:city":"Dundee",
    "sg:classifiers":[
        {
            "category":"Restaurant",
            "type":"Food & Drink"
        },
        {
            "category":"Retail",
            "subcategory":"Event Space",
            "type":"Services"
        }
    ],
    "sg:phone":"+1 847 742 3379",
    "sg:postcode":"60118",
    "sg:province":"IL",
    "sg:tags":[
        "banquet",
        "hall",
        "reception",
        "facility"
    ],
    "sg:website":"http://www.themilkpail.com",
    "wof:name":"The Milk Pail",
    "wof:placetype":"venue"
},
  "geometry": {"coordinates":[-88.263187,42.066895],"type":"Point"}
}