{
  "type": "Feature",
  "properties": {
    "iso:country":"US",
    "sg:address":"1760 W Wilson Ave",
    "sg:city":"Chicago",
    "sg:classifiers":[
        {
            "category":"Social Services",
            "type":"Services"
        },
        {
            "category":"Professional",
            "subcategory":"Employment Agencies",
            "type":"Services"
        },
        {
            "category":"Organizations",
            "subcategory":"Community Association",
            "type":"Services"
        }
    ],
    "sg:phone":"+1 773 784 0400",
    "sg:postcode":"60640",
    "sg:province":"IL",
    "sg:tags":[
        "employer"
    ],
    "wof:name":"Ravenswood Community Council",
    "wof:placetype":"venue"
},
  "geometry": {"coordinates":[-87.673075,41.965189],"type":"Point"}
}