{
  "type": "Feature",
  "properties": {
    "iso:country":"US",
    "sg:address":"20655 Amherst Ct",
    "sg:city":"Joliet",
    "sg:classifiers":[
        {
            "category":"Manufacturing",
            "subcategory":"Tools & Machinery",
            "type":"Manufacturing & Wholesale Goods"
        },
        {
            "category":"Freight",
            "type":"Transportation"
        },
        {
            "category":"Building & Trades",
            "subcategory":"Construction",
            "type":"Services"
        }
    ],
    "sg:phone":"+1 815 726 6700",
    "sg:postcode":"60433",
    "sg:province":"IL",
    "sg:tags":[
        "conveying",
        "conveyor",
        "equipment-wholesale",
        "system",
        "equipment",
        "monorail",
        "manufacturer"
    ],
    "sg:website":"http://www.systemtechnologyinc.com",
    "wof:name":"System Technology Incorporated",
    "wof:placetype":"venue"
},
  "geometry": {"coordinates":[-88.018888,41.511831],"type":"Point"}
}