{
  "type": "Feature",
  "properties": {
    "iso:country":"US",
    "sg:address":"250 E Saint Charles Rd",
    "sg:city":"Villa Park",
    "sg:classifiers":[
        {
            "category":"Real Estate",
            "subcategory":"Real Estate Agent",
            "type":"Services"
        }
    ],
    "sg:phone":"+1 630 832 5020",
    "sg:postcode":"60181",
    "sg:province":"IL",
    "wof:name":"Fast Trac Real Estate",
    "wof:placetype":"venue"
},
  "geometry": {"coordinates":[-87.972962,41.889988],"type":"Point"}
}