{
  "type": "Feature",
  "properties": {
    "addr:full":"5014 N Lincoln Ave Chicago IL 60625",
    "addr:housenumber":"5014",
    "addr:postcode":"60625",
    "addr:street":"N Lincoln Ave",
    "iso:country":"US",
    "sg:address":"5014 N Lincoln Ave",
    "sg:city":"Chicago",
    "sg:classifiers":[
        {
            "category":"Social Services",
            "subcategory":"Child Care",
            "type":"Services"
        },
        {
            "category":"Education",
            "subcategory":"Preschool",
            "type":"Public Place"
        }
    ],
    "sg:phone":"+1 773 561 7206",
    "sg:postcode":"60625",
    "sg:province":"IL",
    "sg:tags":[
        "day"
    ],
    "sg:website":"littlefoxdayschoolchicago.com",
    "wof:name":"Little Fox Day School",
    "wof:placetype":"venue"
},
  "geometry": {"coordinates":[-87.691188,41.972256],"type":"Point"}
}