{
  "type": "Feature",
  "properties": {
    "addr:full":"415 N la Salle Dr Chicago IL 60610",
    "addr:housenumber":"415",
    "addr:postcode":"60610",
    "addr:street":"N La Salle Dr",
    "iso:country":"US",
    "sg:address":"415 N la Salle Dr",
    "sg:city":"Chicago",
    "sg:classifiers":[
        {
            "category":"Banks & Credit Unions",
            "subcategory":"Bank",
            "type":"Services"
        }
    ],
    "sg:phone":"+1 312 440 3034",
    "sg:postcode":"60610",
    "sg:province":"IL",
    "wof:name":"Banco Popular North America",
    "wof:placetype":"venue"
},
  "geometry": {"coordinates":[-87.632407,41.889508],"type":"Point"}
}