{
  "type": "Feature",
  "properties": {
    "iso:country":"US",
    "sg:address":"1505 Lowden Ave",
    "sg:city":"Wheaton",
    "sg:classifiers":[
        {
            "category":"Arts & Performance",
            "subcategory":"Theater",
            "type":"Entertainment"
        }
    ],
    "sg:phone":"+1 630 681 0059",
    "sg:postcode":"60187",
    "sg:province":"IL",
    "sg:tags":[
        "group"
    ],
    "wof:name":"Modern Relics",
    "wof:placetype":"venue"
},
  "geometry": {"coordinates":[-88.086328,41.852319],"type":"Point"}
}