{
  "type": "Feature",
  "properties": {
    "iso:country":"US",
    "sg:address":"408 E Oakwood Dr",
    "sg:city":"Barrington",
    "sg:classifiers":[
        {
            "category":"Professional",
            "subcategory":"Employment Agencies",
            "type":"Services"
        }
    ],
    "sg:phone":"+1 847 526 6848",
    "sg:postcode":"60010",
    "sg:province":"IL",
    "sg:tags":[
        "consultant",
        "search",
        "executive"
    ],
    "sg:website":"www.baltis.com",
    "wof:name":"Ray Baltis Consultants",
    "wof:placetype":"venue"
},
  "geometry": {"coordinates":[-88.12863299999999,42.228004],"type":"Point"}
}