{
  "type": "Feature",
  "properties": {
    "addr:full":"1500 E 75th St Chicago IL 60619",
    "addr:housenumber":"1500",
    "addr:postcode":"60619",
    "addr:street":"E 75Th St",
    "iso:country":"US",
    "sg:address":"1500 E 75th St",
    "sg:city":"Chicago",
    "sg:classifiers":[
        {
            "category":"Retail",
            "subcategory":"Auto Repair",
            "type":"Services"
        }
    ],
    "sg:phone":"+1 773 955 0704",
    "sg:postcode":"60619",
    "sg:province":"IL",
    "wof:name":"King Auto Repair",
    "wof:placetype":"venue"
},
  "geometry": {"coordinates":[-87.588097,41.758598],"type":"Point"}
}