{
  "type": "Feature",
  "properties": {
    "iso:country":"US",
    "sg:address":"6028 N Landers Ave",
    "sg:city":"Chicago",
    "sg:classifiers":[
        {
            "category":"Professional",
            "subcategory":"Advertising",
            "type":"Services"
        }
    ],
    "sg:phone":"+1 773 631 4250",
    "sg:postcode":"60646",
    "sg:province":"IL",
    "sg:tags":[
        "counselor"
    ],
    "wof:name":"3RS",
    "wof:placetype":"venue"
},
  "geometry": {"coordinates":[-87.752301,41.992045],"type":"Point"}
}