{
  "type": "Feature",
  "properties": {
    "addr:full":"4300 W 108th Pl Oak Lawn IL 60453",
    "addr:housenumber":"4300",
    "addr:postcode":"60453",
    "addr:street":"W 108Th Pl",
    "iso:country":"US",
    "sg:address":"4300 W 108th Pl",
    "sg:city":"Oak Lawn",
    "sg:classifiers":[
        {
            "category":"Education",
            "subcategory":"School",
            "type":"Public Place"
        }
    ],
    "sg:phone":"+1 708 423 9331",
    "sg:postcode":"60453",
    "sg:province":"IL",
    "sg:tags":[
        "high",
        "middle",
        "elementary"
    ],
    "wof:name":"Schools Public",
    "wof:placetype":"venue"
},
  "geometry": {"coordinates":[-87.728075,41.695874],"type":"Point"}
}