{
  "type": "Feature",
  "properties": {
    "iso:country":"US",
    "sg:address":"127 S Brighton Pl",
    "sg:city":"Arlington Heights",
    "sg:classifiers":[
        {
            "category":"Wholesale",
            "subcategory":"Groceries",
            "type":"Manufacturing & Wholesale Goods"
        }
    ],
    "sg:phone":"+1 847 870 7020",
    "sg:postcode":"60004",
    "sg:province":"IL",
    "sg:tags":[
        "general"
    ],
    "wof:name":"Brady Rudolph Inc",
    "wof:placetype":"venue"
},
  "geometry": {"coordinates":[-87.969521,42.079378],"type":"Point"}
}