{
  "type": "Feature",
  "properties": {
    "iso:country":"US",
    "sg:address":"3204 Scott St",
    "sg:city":"Franklin Park",
    "sg:classifiers":[
        {
            "category":"Professional",
            "subcategory":"Computer Services",
            "type":"Services"
        }
    ],
    "sg:phone":"+1 847 928 0067",
    "sg:postcode":"60131",
    "sg:province":"IL",
    "sg:tags":[
        "related"
    ],
    "wof:name":"Hoveke Consulting Inc",
    "wof:placetype":"venue"
},
  "geometry": {"coordinates":[-87.875346,41.937601],"type":"Point"}
}