{
  "type": "Feature",
  "properties": {
    "addr:full":"28W770 Warrenville Rd Warrenville IL 60555",
    "addr:housenumber":"28w770",
    "addr:postcode":"60555",
    "addr:street":"Warrenville Rd",
    "iso:country":"US",
    "sg:address":"28W770 Warrenville Rd",
    "sg:city":"Warrenville",
    "sg:classifiers":[
        {
            "category":"Place Of Worship",
            "subcategory":"Church",
            "type":"Public Place"
        },
        {
            "category":"Place Of Worship",
            "type":"Public Place"
        }
    ],
    "sg:phone":"+1 630 836 1319",
    "sg:postcode":"60555",
    "sg:province":"IL",
    "sg:tags":[
        "churches-eastern",
        "orthodox"
    ],
    "sg:website":"http://www.sacchall.com",
    "wof:name":"Holy Transfiguration Orthodox Church",
    "wof:placetype":"venue"
},
  "geometry": {"coordinates":[-88.166679,41.816231],"type":"Point"}
}