{
  "type": "Feature",
  "properties": {
    "iso:country":"US",
    "sg:address":"13092 N 2550th Ave",
    "sg:city":"Geneseo",
    "sg:classifiers":[
        {
            "category":"Retail",
            "subcategory":"Repair Shop",
            "type":"Services"
        }
    ],
    "sg:phone":"+1 309 944 3029",
    "sg:postcode":"61254",
    "sg:province":"IL",
    "sg:tags":[
        "appliance"
    ],
    "wof:name":"Geneseo Appliance Ctr",
    "wof:placetype":"venue"
},
  "geometry": {"coordinates":[-90.180745,41.520704],"type":"Point"}
}