{
  "type": "Feature",
  "properties": {
    "addr:full":"909 W Lincoln Ave Charleston IL 61920",
    "addr:housenumber":"909",
    "addr:postcode":"61920",
    "addr:street":"W Lincoln Ave",
    "iso:country":"US",
    "sg:address":"909 W Lincoln Ave",
    "sg:city":"Charleston",
    "sg:classifiers":[
        {
            "category":"Professional",
            "subcategory":"Credit Reporting & Collection",
            "type":"Services"
        }
    ],
    "sg:phone":"+1 217 348 6116",
    "sg:postcode":"61920",
    "sg:province":"IL",
    "sg:tags":[
        "agency"
    ],
    "wof:name":"New Age Recovery",
    "wof:placetype":"venue"
},
  "geometry": {"coordinates":[-88.196597,39.484338],"type":"Point"}
}