{
  "type": "Feature",
  "properties": {
    "addr:full":"287 Deer Trail Ct Barrington IL 60010",
    "addr:housenumber":"287",
    "addr:postcode":"60010",
    "addr:street":"Deer Trail Ct",
    "iso:country":"US",
    "sg:address":"287 Deer Trail Ct",
    "sg:city":"Barrington",
    "sg:classifiers":[
        {
            "category":"Building & Trades",
            "subcategory":"Construction",
            "type":"Services"
        }
    ],
    "sg:phone":"+1 847 381 1033",
    "sg:postcode":"60010",
    "sg:province":"IL",
    "sg:tags":[
        "home",
        "new",
        "general",
        "contractor"
    ],
    "wof:name":"Classic Home Designs Inc",
    "wof:placetype":"venue"
},
  "geometry": {"coordinates":[-88.14487699999999,42.217267],"type":"Point"}
}