{
  "type": "Feature",
  "properties": {
    "iso:country":"US",
    "sg:address":"9 Westport Ct",
    "sg:city":"Bloomington",
    "sg:phone":"+1 309 661 1464",
    "sg:postcode":"61704",
    "sg:province":"IL",
    "wof:name":"Speedy Auto Glass",
    "wof:placetype":"venue"
},
  "geometry": {"coordinates":[-88.941141,40.489282],"type":"Point"}
}