{
  "type": "Feature",
  "properties": {
    "iso:country":"US",
    "sg:address":"2431 Broadway St",
    "sg:city":"Quincy",
    "sg:classifiers":[
        {
            "category":"Restaurant",
            "type":"Food & Drink"
        }
    ],
    "sg:phone":"+1 217 223 8040",
    "sg:postcode":"62301",
    "sg:province":"IL",
    "wof:name":"Coach House Restaurant",
    "wof:placetype":"venue"
},
  "geometry": {"coordinates":[-91.377103,39.935491],"type":"Point"}
}