{
  "type": "Feature",
  "properties": {
    "iso:country":"US",
    "sg:address":"100 Drury Ln",
    "sg:city":"Oakbrook Terrace",
    "sg:classifiers":[
        {
            "category":"Arts & Performance",
            "subcategory":"Theater",
            "type":"Entertainment"
        }
    ],
    "sg:phone":"+1 630 530 8300",
    "sg:postcode":"60181",
    "sg:province":"IL",
    "sg:website":"www.drurylaneoakbrook.com",
    "wof:name":"Drury Lane",
    "wof:placetype":"venue"
},
  "geometry": {"coordinates":[-87.95264,41.859158],"type":"Point"}
}