{
  "type": "Feature",
  "properties": {
    "addr:full":"2329 W Chicago Ave Chicago IL 60622",
    "addr:housenumber":"2329",
    "addr:postcode":"60622",
    "addr:street":"W Chicago Ave",
    "iso:country":"US",
    "sg:address":"2329 W Chicago Ave",
    "sg:city":"Chicago",
    "sg:classifiers":[
        {
            "category":"Professional",
            "subcategory":"Lawyer & Legal Services",
            "type":"Services"
        }
    ],
    "sg:phone":"+1 773 486 6645",
    "sg:postcode":"60622",
    "sg:province":"IL",
    "wof:name":"Kulas Julian Edw Atty",
    "wof:placetype":"venue"
},
  "geometry": {"coordinates":[-87.685699,41.895599],"type":"Point"}
}