{
  "type": "Feature",
  "properties": {
    "addr:full":"6112 W 26th St Cicero IL 60804",
    "addr:housenumber":"6112",
    "addr:postcode":"60804",
    "addr:street":"W 26Th St",
    "iso:country":"US",
    "sg:address":"6112 W 26th St",
    "sg:city":"Cicero",
    "sg:classifiers":[
        {
            "category":"Personal",
            "subcategory":"Barber",
            "type":"Services"
        }
    ],
    "sg:phone":"+1 708 222 8996",
    "sg:postcode":"60804",
    "sg:province":"IL",
    "wof:name":"Exclusive Cuts",
    "wof:placetype":"venue"
},
  "geometry": {"coordinates":[-87.776608,41.843636],"type":"Point"}
}