{
  "type": "Feature",
  "properties": {
    "addr:full":"6560 N Sheridan Road Chicago IL 60626",
    "addr:housenumber":"6560",
    "addr:postcode":"60626",
    "addr:street":"N Sheridan Road",
    "iso:country":"US",
    "sg:address":"6560 N Sheridan Road",
    "sg:city":"Chicago",
    "sg:classifiers":[
        {
            "category":"Shopping",
            "subcategory":"Optician",
            "type":"Retail Goods"
        }
    ],
    "sg:phone":"+1 773 274 2020",
    "sg:postcode":"60626",
    "sg:province":"IL",
    "sg:tags":[
        "eyewear"
    ],
    "wof:name":"Sunshine Optical",
    "wof:placetype":"venue"
},
  "geometry": {"coordinates":[-87.660753,42.001752],"type":"Point"}
}