{
  "type": "Feature",
  "properties": {
    "iso:country":"US",
    "sg:address":"15 Oak Ave",
    "sg:city":"Aurora",
    "sg:classifiers":[
        {
            "category":"Organizations",
            "subcategory":"Religious Organization",
            "type":"Services"
        }
    ],
    "sg:phone":"+1 630 264 6313",
    "sg:postcode":"60506",
    "sg:province":"IL",
    "sg:tags":[
        "church"
    ],
    "wof:name":"Iglesia Misionera Shalom",
    "wof:placetype":"venue"
},
  "geometry": {"coordinates":[-88.31948800000001,41.761357],"type":"Point"}
}