{
  "type": "Feature",
  "properties": {
    "addr:full":"719 S Evergreen Ave Kankakee IL 60901",
    "addr:housenumber":"719",
    "addr:postcode":"60901",
    "addr:street":"S Evergreen Ave",
    "iso:country":"US",
    "sg:address":"719 S Evergreen Ave",
    "sg:city":"Kankakee",
    "sg:classifiers":[
        {
            "category":"Social Services",
            "subcategory":"Child Care",
            "type":"Services"
        }
    ],
    "sg:phone":"+1 815 933 7239",
    "sg:postcode":"60901",
    "sg:province":"IL",
    "sg:tags":[
        "day"
    ],
    "wof:name":"Elaine Jackson",
    "wof:placetype":"venue"
},
  "geometry": {"coordinates":[-87.85445199999999,41.110407],"type":"Point"}
}