{
  "type": "Feature",
  "properties": {
    "iso:country":"US",
    "sg:address":"11851 Heintz Rd",
    "sg:city":"Marissa",
    "sg:classifiers":[
        {
            "category":"Real Estate",
            "subcategory":"Real Estate Operator",
            "type":"Services"
        }
    ],
    "sg:phone":"+1 618 295 2594",
    "sg:postcode":"62257",
    "sg:province":"IL",
    "sg:tags":[
        "property",
        "lessor"
    ],
    "wof:name":"Irene Bollmeier",
    "wof:placetype":"venue"
},
  "geometry": {"coordinates":[-89.711013,38.305656],"type":"Point"}
}