{
  "type": "Feature",
  "properties": {
    "addr:full":"2702 Franklin Ct Lake Villa IL 60046",
    "addr:housenumber":"2702",
    "addr:postcode":"60046",
    "addr:street":"Franklin Ct",
    "iso:country":"US",
    "sg:address":"2702 Franklin Ct",
    "sg:city":"Lake Villa",
    "sg:classifiers":[
        {
            "category":"Shopping",
            "subcategory":"Gifts & Souvenirs",
            "type":"Retail Goods"
        }
    ],
    "sg:phone":"+1   ",
    "sg:postcode":"60046",
    "sg:province":"IL",
    "wof:name":"Happy Balloomers",
    "wof:placetype":"venue"
},
  "geometry": {"coordinates":[-88.016362,42.433884],"type":"Point"}
}