{
  "type": "Feature",
  "properties": {
    "addr:full":"2810 Old Willow Rd Northbrook IL 60062",
    "addr:housenumber":"2810",
    "addr:postcode":"60062",
    "addr:street":"Old Willow Rd",
    "iso:country":"US",
    "sg:address":"2810 Old Willow Rd",
    "sg:city":"Northbrook",
    "sg:classifiers":[
        {
            "category":"Manufacturing",
            "subcategory":"Metals",
            "type":"Manufacturing & Wholesale Goods"
        }
    ],
    "sg:phone":"+1 847 729 5744",
    "sg:postcode":"60062",
    "sg:province":"IL",
    "sg:tags":[
        "copper",
        "fabricator"
    ],
    "sg:website":"www.christymetals.com",
    "wof:name":"Christy Metals Co",
    "wof:placetype":"venue"
},
  "geometry": {"coordinates":[-87.814913,42.10107],"type":"Point"}
}