{
  "type": "Feature",
  "properties": {
    "addr:full":"333 N Michigan Ave Ste 1125 Chicago IL 60601",
    "addr:housenumber":"333",
    "addr:postcode":"60601",
    "addr:street":"N Michigan Ave Ste 1125",
    "iso:country":"US",
    "sg:address":"333 N Michigan Ave Ste 1125",
    "sg:city":"Chicago",
    "sg:classifiers":[
        {
            "category":"Health Services",
            "subcategory":"Doctor",
            "type":"Services"
        }
    ],
    "sg:phone":"+1 773 844 9668",
    "sg:postcode":"60601",
    "sg:province":"IL",
    "sg:tags":[
        "psychiatrist"
    ],
    "sg:website":"anneoscherwitzmd.thereviewbook.com",
    "wof:name":"Anne C Oscherwitz, \u00a0MD",
    "wof:placetype":"venue"
},
  "geometry": {"coordinates":[-87.624504,41.88761],"type":"Point"}
}