{
  "type": "Feature",
  "properties": {
    "iso:country":"US",
    "sg:address":"1505 N Center St",
    "sg:city":"Joliet",
    "sg:classifiers":[
        {
            "category":"Manufacturing",
            "subcategory":"Metals",
            "type":"Manufacturing & Wholesale Goods"
        }
    ],
    "sg:phone":"+1 815 600 1080",
    "sg:postcode":"60435",
    "sg:province":"IL",
    "sg:tags":[
        "copper"
    ],
    "wof:name":"Copper Rain Exteriors",
    "wof:placetype":"venue"
},
  "geometry": {"coordinates":[-88.092085,41.550651],"type":"Point"}
}