{
  "type": "Feature",
  "properties": {
    "iso:country":"US",
    "sg:address":"301 E Green St",
    "sg:city":"Champaign",
    "sg:classifiers":[
        {
            "category":"Restaurant",
            "type":"Food & Drink"
        }
    ],
    "sg:phone":"+1 217 365 9271",
    "sg:postcode":"61820",
    "sg:province":"IL",
    "sg:tags":[
        "greek"
    ],
    "wof:name":"Niro Gyro's",
    "wof:placetype":"venue"
},
  "geometry": {"coordinates":[-88.235388,40.110113],"type":"Point"}
}