{
  "type": "Feature",
  "properties": {
    "addr:full":"684 Co Rd 400 N Sadorus IL 61872",
    "addr:housenumber":"684",
    "addr:postcode":"61872",
    "addr:street":"Co Rd 400 N",
    "iso:country":"US",
    "sg:address":"684 Co Rd 400 N",
    "sg:city":"Sadorus",
    "sg:classifiers":[
        {
            "category":"Professional",
            "type":"Services"
        }
    ],
    "sg:phone":"+1 217 598 2343",
    "sg:postcode":"61872",
    "sg:province":"IL",
    "sg:tags":[
        "establishment"
    ],
    "wof:name":"Farm's Schroeder",
    "wof:placetype":"venue"
},
  "geometry": {"coordinates":[-88.335599,39.937245],"type":"Point"}
}