{
  "type": "Feature",
  "properties": {
    "addr:full":"22725 N Linden Dr Barrington IL 60010",
    "addr:housenumber":"22725",
    "addr:postcode":"60010",
    "addr:street":"N Linden Dr",
    "iso:country":"US",
    "sg:address":"22725 N Linden Dr",
    "sg:city":"Barrington",
    "sg:classifiers":[
        {
            "category":"Banks & Credit Unions",
            "subcategory":"Financial Services",
            "type":"Services"
        }
    ],
    "sg:phone":"+1 847 382 8628",
    "sg:postcode":"60010",
    "sg:province":"IL",
    "sg:tags":[
        "investment",
        "closed"
    ],
    "wof:name":"Marquinn Investments Inc",
    "wof:placetype":"venue"
},
  "geometry": {"coordinates":[-88.188081,42.191925],"type":"Point"}
}