{
  "type": "Feature",
  "properties": {
    "addr:full":"7261 Lake St River Forest IL 60305",
    "addr:housenumber":"7261",
    "addr:postcode":"60305",
    "addr:street":"Lake St",
    "iso:country":"US",
    "sg:address":"7261 Lake St",
    "sg:city":"River Forest",
    "sg:classifiers":[
        {
            "category":"Shopping",
            "subcategory":"Mobile Phones",
            "type":"Retail Goods"
        }
    ],
    "sg:phone":"+1 708 771 1864",
    "sg:postcode":"60305",
    "sg:province":"IL",
    "wof:name":"Cellular Connections",
    "wof:placetype":"venue"
},
  "geometry": {"coordinates":[-87.80629399999999,41.888416],"type":"Point"}
}