{
  "type": "Feature",
  "properties": {
    "addr:full":"802 E Cherry Ln Arlington Heights IL 60004",
    "addr:housenumber":"802",
    "addr:postcode":"60004",
    "addr:street":"E Cherry Ln",
    "iso:country":"US",
    "sg:address":"802 E Cherry Ln",
    "sg:city":"Arlington Heights",
    "sg:classifiers":[
        {
            "category":"Real Estate",
            "subcategory":"Real Estate Operator",
            "type":"Services"
        }
    ],
    "sg:phone":"+1 847 255 7630",
    "sg:postcode":"60004",
    "sg:province":"IL",
    "sg:tags":[
        "building",
        "nonresidential"
    ],
    "wof:name":"Samsar Properties LLC",
    "wof:placetype":"venue"
},
  "geometry": {"coordinates":[-87.97271600000001,42.113742],"type":"Point"}
}