{
  "type": "Feature",
  "properties": {
    "addr:full":"4 Club Centre Ct Edwardsville IL 62025",
    "addr:housenumber":"4",
    "addr:postcode":"62025",
    "addr:street":"Club Centre Ct",
    "iso:country":"US",
    "sg:address":"4 Club Centre Ct",
    "sg:city":"Edwardsville",
    "sg:classifiers":[
        {
            "category":"Restaurant",
            "type":"Food & Drink"
        }
    ],
    "sg:menulink":"http://www.allmenus.com/il/edwardsville/126385-subway/menu/",
    "sg:phone":"+1 618 656 6056",
    "sg:postcode":"62025",
    "sg:province":"IL",
    "sg:tags":[
        "american",
        "sandwich"
    ],
    "wof:name":"Subway",
    "wof:placetype":"venue"
},
  "geometry": {"coordinates":[-89.983543,38.77915],"type":"Point"}
}