{
  "type": "Feature",
  "properties": {
    "iso:country":"US",
    "sg:address":"1428 Sherman Rd",
    "sg:city":"Romeoville",
    "sg:classifiers":[
        {
            "category":"Utilities",
            "subcategory":"Telephone",
            "type":"Services"
        }
    ],
    "sg:phone":"+1 630 739 0546",
    "sg:postcode":"60446",
    "sg:province":"IL",
    "sg:tags":[
        "telecommunication"
    ],
    "sg:website":"www.adestagroup.com",
    "wof:name":"Adesta Communications Inc",
    "wof:placetype":"venue"
},
  "geometry": {"coordinates":[-88.056635,41.67859],"type":"Point"}
}