{
  "type": "Feature",
  "properties": {
    "iso:country":"US",
    "sg:address":"3681 Commercial Ave",
    "sg:city":"Northbrook",
    "sg:classifiers":[
        {
            "category":"Shopping",
            "type":"Retail Goods"
        }
    ],
    "sg:phone":"+1   ",
    "sg:postcode":"60062",
    "sg:province":"IL",
    "sg:tags":[
        "antique",
        "collectible",
        "auction"
    ],
    "wof:name":"Bestcollectorscom",
    "wof:placetype":"venue"
},
  "geometry": {"coordinates":[-87.868481,42.146497],"type":"Point"}
}