{
  "type": "Feature",
  "properties": {
    "iso:country":"US",
    "sg:address":"23552 W Milton Rd",
    "sg:city":"Wauconda",
    "sg:classifiers":[
        {
            "category":"Building & Trades",
            "subcategory":"Construction",
            "type":"Services"
        }
    ],
    "sg:phone":"+1 847 487 2727",
    "sg:postcode":"60084",
    "sg:province":"IL",
    "sg:tags":[
        "masonry",
        "contractor"
    ],
    "wof:name":"Ebben Masonry Inc",
    "wof:placetype":"venue"
},
  "geometry": {"coordinates":[-88.0889,42.246047],"type":"Point"}
}