{
  "type": "Feature",
  "properties": {
    "addr:full":"25W767 Durfee Rd Wheaton IL 60187",
    "addr:housenumber":"25w767",
    "addr:postcode":"60187",
    "addr:street":"Durfee Rd",
    "iso:country":"US",
    "sg:address":"25W767 Durfee Rd",
    "sg:city":"Wheaton",
    "sg:classifiers":[
        {
            "category":"Real Estate",
            "subcategory":"Architect",
            "type":"Services"
        }
    ],
    "sg:phone":"+1 630 690 8211",
    "sg:postcode":"60187",
    "sg:province":"IL",
    "wof:name":"Kollias Marc S",
    "wof:placetype":"venue"
},
  "geometry": {"coordinates":[-88.13110399999999,41.839802],"type":"Point"}
}