{
  "type": "Feature",
  "properties": {
    "addr:full":"10655 S Hale Ave Chicago IL 60643",
    "addr:housenumber":"10655",
    "addr:postcode":"60643",
    "addr:street":"S Hale Ave",
    "iso:country":"US",
    "sg:address":"10655 S Hale Ave",
    "sg:city":"Chicago",
    "sg:classifiers":[
        {
            "category":"Personal",
            "type":"Services"
        }
    ],
    "sg:phone":"+1 773 233 3441",
    "sg:postcode":"60643",
    "sg:province":"IL",
    "wof:name":"Relaxtion Stn Thrputic Massage",
    "wof:placetype":"venue"
},
  "geometry": {"coordinates":[-87.669111,41.702077],"type":"Point"}
}