{
  "type": "Feature",
  "properties": {
    "addr:full":"1055 W 16th St Chicago IL 60608",
    "addr:housenumber":"1055",
    "addr:postcode":"60608",
    "addr:street":"W 16Th St",
    "iso:country":"US",
    "sg:address":"1055 W 16th St",
    "sg:city":"Chicago",
    "sg:classifiers":[
        {
            "category":"Building & Trades",
            "subcategory":"Locksmith",
            "type":"Services"
        }
    ],
    "sg:phone":"+1 708 801 3044",
    "sg:postcode":"60608",
    "sg:province":"IL",
    "sg:tags":[
        "key"
    ],
    "wof:name":"A A Linny Locksmith",
    "wof:placetype":"venue"
},
  "geometry": {"coordinates":[-87.652804,41.859812],"type":"Point"}
}