{
  "type": "Feature",
  "properties": {
    "iso:country":"US",
    "sg:address":"4071 W Albany St",
    "sg:city":"Mchenry",
    "sg:classifiers":[
        {
            "category":"Manufacturing",
            "subcategory":"Tools & Machinery",
            "type":"Manufacturing & Wholesale Goods"
        },
        {
            "category":"Autos & Motor Vehicles",
            "subcategory":"Auto Supplies",
            "type":"Retail Goods"
        },
        {
            "category":"Manufacturing",
            "subcategory":"Electronics",
            "type":"Manufacturing & Wholesale Goods"
        }
    ],
    "sg:phone":"+1 815 363 3524",
    "sg:postcode":"60050",
    "sg:province":"IL",
    "sg:tags":[
        "forming",
        "consultant",
        "robotics",
        "metal",
        "automation"
    ],
    "sg:website":"http://www.kwikmark.com",
    "wof:name":"Kwik Mark, Inc.",
    "wof:placetype":"venue"
},
  "geometry": {"coordinates":[-88.275857,42.308021],"type":"Point"}
}