{
  "type": "Feature",
  "properties": {
    "iso:country":"US",
    "sg:address":"423 N Main St",
    "sg:city":"Carrollton",
    "sg:classifiers":[
        {
            "category":"Personal",
            "subcategory":"Barber",
            "type":"Services"
        }
    ],
    "sg:phone":"+1 217 942 5100",
    "sg:postcode":"62016",
    "sg:province":"IL",
    "sg:tags":[
        "shop"
    ],
    "wof:name":"Brooks Barber Shop Inc",
    "wof:placetype":"venue"
},
  "geometry": {"coordinates":[-90.406031,39.302151],"type":"Point"}
}