{
  "type": "Feature",
  "properties": {
    "iso:country":"US",
    "sg:address":"2150 W Addison St",
    "sg:city":"Chicago",
    "sg:classifiers":[
        {
            "category":"Wholesale",
            "subcategory":"Non-durable Goods",
            "type":"Manufacturing & Wholesale Goods"
        }
    ],
    "sg:phone":"+1 773 388 2380",
    "sg:postcode":"60618",
    "sg:province":"IL",
    "sg:tags":[
        "merchandise-wholesale"
    ],
    "wof:name":"Serrino Trading Ii",
    "wof:placetype":"venue"
},
  "geometry": {"coordinates":[-87.682557,41.946805],"type":"Point"}
}