{
  "type": "Feature",
  "properties": {
    "addr:full":"2556 N Cherry Cove Ln Round Lake IL 60073",
    "addr:housenumber":"2556",
    "addr:postcode":"60073",
    "addr:street":"N Cherry Cove Ln",
    "iso:country":"US",
    "sg:address":"2556 N Cherry Cove Ln",
    "sg:city":"Round Lake",
    "sg:classifiers":[
        {
            "category":"Building & Trades",
            "subcategory":"Cleaning & Sanitation",
            "type":"Services"
        }
    ],
    "sg:phone":"+1 847 356 9031",
    "sg:postcode":"60073",
    "sg:province":"IL",
    "sg:tags":[
        "maintenance"
    ],
    "wof:name":"Neat & Tidy Enterprises",
    "wof:placetype":"venue"
},
  "geometry": {"coordinates":[-88.07651,42.394092],"type":"Point"}
}