{
  "type": "Feature",
  "properties": {
    "iso:country":"US",
    "sg:address":"10047 S Western Ave",
    "sg:city":"Chicago",
    "sg:classifiers":[
        {
            "category":"Professional",
            "subcategory":"Lawyer & Legal Services",
            "type":"Services"
        }
    ],
    "sg:phone":"+1 312 913 1123",
    "sg:postcode":"60643",
    "sg:province":"IL",
    "wof:name":"Ohearn Martin Law Offices",
    "wof:placetype":"venue"
},
  "geometry": {"coordinates":[-87.68150300000001,41.710499],"type":"Point"}
}