{
  "type": "Feature",
  "properties": {
    "addr:full":"4300 S Mozart St Chicago IL 60632",
    "addr:housenumber":"4300",
    "addr:postcode":"60632",
    "addr:street":"S Mozart St",
    "iso:country":"US",
    "sg:address":"4300 S Mozart St",
    "sg:city":"Chicago",
    "sg:classifiers":[
        {
            "category":"Building & Trades",
            "subcategory":"Locksmith",
            "type":"Services"
        }
    ],
    "sg:phone":"+1 773 893 1464",
    "sg:postcode":"60632",
    "sg:province":"IL",
    "sg:tags":[
        "key"
    ],
    "wof:name":"123 All Day & Night Locksmith & Lockout",
    "wof:placetype":"venue"
},
  "geometry": {"coordinates":[-87.69579400000001,41.815418],"type":"Point"}
}