{
  "type": "Feature",
  "properties": {
    "iso:country":"US",
    "sg:address":"96 N Bokelman St",
    "sg:city":"Roselle",
    "sg:classifiers":[
        {
            "category":"Health Services",
            "subcategory":"Doctor",
            "type":"Services"
        },
        {
            "category":"Health Services",
            "subcategory":"Dentist",
            "type":"Services"
        }
    ],
    "sg:phone":"+1 630 582 7600",
    "sg:postcode":"60172",
    "sg:province":"IL",
    "sg:tags":[
        "surgeon",
        "oral",
        "cosmetic"
    ],
    "sg:website":"www.rosellecosmeticdentist.com",
    "wof:name":"Dr. William G Wolski, DDS",
    "wof:placetype":"venue"
},
  "geometry": {"coordinates":[-88.07880900000001,41.984573],"type":"Point"}
}