{
  "type": "Feature",
  "properties": {
    "iso:country":"US",
    "sg:address":"1017 Olive St",
    "sg:city":"Saint Louis",
    "sg:classifiers":[
        {
            "category":"Professional",
            "subcategory":"Employment Agencies",
            "type":"Services"
        }
    ],
    "sg:phone":"+1 314 589 8000",
    "sg:postcode":"63101",
    "sg:province":"MO",
    "wof:name":"St Louis Agency On Training and Employment",
    "wof:placetype":"venue"
},
  "geometry": {"coordinates":[-90.194801,38.6292],"type":"Point"}
}