{
  "type": "Feature",
  "properties": {
    "addr:full":"2009 N Brinton Ave Dixon IL 61021",
    "addr:housenumber":"2009",
    "addr:postcode":"61021",
    "addr:street":"N Brinton Ave",
    "iso:country":"US",
    "sg:address":"2009 N Brinton Ave",
    "sg:city":"Dixon",
    "sg:classifiers":[
        {
            "category":"Personal",
            "subcategory":"Beauty Salon",
            "type":"Services"
        }
    ],
    "sg:phone":"+1 815 285 1773",
    "sg:postcode":"61021",
    "sg:province":"IL",
    "sg:tags":[
        "hair",
        "stylist"
    ],
    "wof:name":"Ultimate Hair Design",
    "wof:placetype":"venue"
},
  "geometry": {"coordinates":[-89.486458,41.871197],"type":"Point"}
}