{
  "type": "Feature",
  "properties": {
    "addr:full":"2677 Coyle Ave Elk Grove Village IL 60007",
    "addr:housenumber":"2677",
    "addr:postcode":"60007",
    "addr:street":"Coyle Ave",
    "iso:country":"US",
    "sg:address":"2677 Coyle Ave",
    "sg:city":"Elk Grove Village",
    "sg:classifiers":[
        {
            "category":"Airline",
            "type":"Transportation"
        }
    ],
    "sg:phone":"+1 847 427 8070",
    "sg:postcode":"60007",
    "sg:province":"IL",
    "sg:tags":[
        "courier",
        "air"
    ],
    "wof:name":"Pace Air Freight Inc",
    "wof:placetype":"venue"
},
  "geometry": {"coordinates":[-87.939671,42.001465],"type":"Point"}
}