{
  "type": "Feature",
  "properties": {
    "iso:country":"US",
    "sg:address":"109 US Hwy 6",
    "sg:city":"Seatonville",
    "sg:classifiers":[
        {
            "category":"Bars & Pubs",
            "type":"Food & Drink"
        }
    ],
    "sg:phone":"+1 815 894 2341",
    "sg:postcode":"61359",
    "sg:province":"IL",
    "wof:name":"Brid's Tap",
    "wof:placetype":"venue"
},
  "geometry": {"coordinates":[-89.277643,41.364788],"type":"Point"}
}