{
  "type": "Feature",
  "properties": {
    "iso:country":"US",
    "sg:address":"14901 Artesian Ave",
    "sg:city":"Harvey",
    "sg:classifiers":[
        {
            "category":"Home & Garden",
            "subcategory":"Building Materials",
            "type":"Retail Goods"
        }
    ],
    "sg:phone":"+1 708 596 2130",
    "sg:postcode":"60426",
    "sg:province":"IL",
    "wof:name":"Dotties Home Daycare Center",
    "wof:placetype":"venue"
},
  "geometry": {"coordinates":[-87.67662,41.618961],"type":"Point"}
}