{
  "type": "Feature",
  "properties": {
    "iso:country":"US",
    "sg:address":"7855 S Coles Ave Apt C",
    "sg:city":"Chicago",
    "sg:classifiers":[
        {
            "category":"Manufacturing",
            "subcategory":"Petroleum Products",
            "type":"Manufacturing & Wholesale Goods"
        }
    ],
    "sg:phone":"+1 773 731 2596",
    "sg:postcode":"60649",
    "sg:province":"IL",
    "sg:tags":[
        "contract"
    ],
    "wof:name":"Astro Development",
    "wof:placetype":"venue"
},
  "geometry": {"coordinates":[-87.55149299999999,41.753177],"type":"Point"}
}