{
  "type": "Feature",
  "properties": {
    "addr:full":"9450 Lisbon Rd Yorkville IL 60560",
    "addr:housenumber":"9450",
    "addr:postcode":"60560",
    "addr:street":"Lisbon Rd",
    "iso:country":"US",
    "sg:address":"9450 Lisbon Rd",
    "sg:city":"Yorkville",
    "sg:classifiers":[
        {
            "category":"Insurance",
            "subcategory":"Hazard Insurance",
            "type":"Services"
        }
    ],
    "sg:phone":"+1 630 553 0608",
    "sg:postcode":"60560",
    "sg:province":"IL",
    "wof:name":"Myron F Steves",
    "wof:placetype":"venue"
},
  "geometry": {"coordinates":[-88.485489,41.58833],"type":"Point"}
}