{
  "type": "Feature",
  "properties": {
    "addr:full":"1155 W 79th St Chicago IL 60620",
    "addr:housenumber":"1155",
    "addr:postcode":"60620",
    "addr:street":"W 79Th St",
    "iso:country":"US",
    "sg:address":"1155 W 79th St",
    "sg:city":"Chicago",
    "sg:classifiers":[
        {
            "category":"Government",
            "subcategory":"Office",
            "type":"Public Place"
        }
    ],
    "sg:phone":"+1 773 224 2830",
    "sg:postcode":"60620",
    "sg:province":"IL",
    "wof:name":"Jacqueline Collins State Senator",
    "wof:placetype":"venue"
},
  "geometry": {"coordinates":[-87.65295500000001,41.750497],"type":"Point"}
}