{
  "type": "Feature",
  "properties": {
    "iso:country":"US",
    "sg:address":"304 S Broadway",
    "sg:city":"Centralia",
    "sg:classifiers":[
        {
            "category":"Organizations",
            "subcategory":"Religious Organization",
            "type":"Services"
        }
    ],
    "sg:phone":"+1 618 532 1210",
    "sg:postcode":"62801",
    "sg:province":"IL",
    "sg:tags":[
        "church",
        "baptist",
        "care",
        "center",
        "child"
    ],
    "wof:name":"Central City Baptist Church",
    "wof:placetype":"venue"
},
  "geometry": {"coordinates":[-89.129601,38.544394],"type":"Point"}
}