{
  "type": "Feature",
  "properties": {
    "addr:full":"1318 N Salem Blvd Arlington Heights IL 60004",
    "addr:housenumber":"1318",
    "addr:postcode":"60004",
    "addr:street":"N Salem Blvd",
    "iso:country":"US",
    "sg:address":"1318 N Salem Blvd",
    "sg:city":"Arlington Heights",
    "sg:classifiers":[
        {
            "category":"Professional",
            "subcategory":"Accounting & Tax Preparation",
            "type":"Services"
        }
    ],
    "sg:phone":"+1 847 590 9446",
    "sg:postcode":"60004",
    "sg:province":"IL",
    "wof:name":"Estate Accounting Services",
    "wof:placetype":"venue"
},
  "geometry": {"coordinates":[-87.995508,42.100156],"type":"Point"}
}