{
  "type": "Feature",
  "properties": {
    "iso:country":"US",
    "sg:address":"202 Springhill Rd",
    "sg:city":"Carpentersville",
    "sg:classifiers":[
        {
            "category":"Insurance",
            "subcategory":"Health Insurance",
            "type":"Services"
        }
    ],
    "sg:phone":"+1 847 551 3572",
    "sg:postcode":"60110",
    "sg:province":"IL",
    "sg:tags":[
        "market"
    ],
    "sg:website":"www.seattlesutton.com",
    "wof:name":"Seattle Sutton's Healthy Eating",
    "wof:placetype":"venue"
},
  "geometry": {"coordinates":[-88.29650100000001,42.106899],"type":"Point"}
}