{
  "type": "Feature",
  "properties": {
    "addr:full":"551 Lavina Dr Bolingbrook IL 60440",
    "addr:housenumber":"551",
    "addr:postcode":"60440",
    "addr:street":"Lavina Dr",
    "iso:country":"US",
    "sg:address":"551 Lavina Dr",
    "sg:city":"Bolingbrook",
    "sg:classifiers":[
        {
            "category":"Real Estate",
            "subcategory":"Real Estate Services",
            "type":"Services"
        },
        {
            "category":"Real Estate",
            "subcategory":"Real Estate Agent",
            "type":"Services"
        }
    ],
    "sg:phone":"+1 630 369 2450",
    "sg:postcode":"60440",
    "sg:province":"IL",
    "sg:tags":[
        "buyer",
        "broker"
    ],
    "wof:name":"The Wenonah Group",
    "wof:placetype":"venue"
},
  "geometry": {"coordinates":[-88.092921,41.72494],"type":"Point"}
}