{
  "type": "Feature",
  "properties": {
    "addr:full":"1846 N Milwaukee Ave Chicago IL 60647",
    "addr:housenumber":"1846",
    "addr:postcode":"60647",
    "addr:street":"N Milwaukee Ave",
    "iso:country":"US",
    "sg:address":"1846 N Milwaukee Ave",
    "sg:city":"Chicago",
    "sg:classifiers":[
        {
            "category":"Cafe",
            "type":"Food & Drink"
        }
    ],
    "sg:menulink":"http://www.allmenus.com/il/chicago/22412-cafe-matou/menu/",
    "sg:phone":"+1 773 384 8911",
    "sg:postcode":"60647",
    "sg:province":"IL",
    "sg:tags":[
        "french"
    ],
    "wof:name":"Cafe Matou",
    "wof:placetype":"venue"
},
  "geometry": {"coordinates":[-87.684641,41.915022],"type":"Point"}
}