{
  "type": "Feature",
  "properties": {
    "addr:full":"478 N Green Bay Rd Waukegan IL 60085",
    "addr:housenumber":"478",
    "addr:postcode":"60085",
    "addr:street":"N Green Bay Rd",
    "iso:country":"US",
    "sg:address":"478 N Green Bay Rd",
    "sg:city":"Waukegan",
    "sg:classifiers":[
        {
            "category":"Retail",
            "subcategory":"Auto Rental",
            "type":"Services"
        }
    ],
    "sg:phone":"+1 847 249 7886",
    "sg:postcode":"60085",
    "sg:province":"IL",
    "sg:tags":[
        "renting",
        "automobile"
    ],
    "wof:name":"Hertz Rent A Car",
    "wof:placetype":"venue"
},
  "geometry": {"coordinates":[-87.87883100000001,42.366255],"type":"Point"}
}