{
  "type": "Feature",
  "properties": {
    "addr:full":"140 S Hickory St Braidwood IL 60408",
    "addr:housenumber":"140",
    "addr:postcode":"60408",
    "addr:street":"S Hickory St",
    "iso:country":"US",
    "sg:address":"140 S Hickory St",
    "sg:city":"Braidwood",
    "sg:classifiers":[
        {
            "category":"Travel",
            "subcategory":"Hotels & Motels",
            "type":"Entertainment"
        }
    ],
    "sg:phone":"+1 815 458 2812",
    "sg:postcode":"60408",
    "sg:province":"IL",
    "wof:name":"Sun Motel",
    "wof:placetype":"venue"
},
  "geometry": {"coordinates":[-88.24387400000001,41.263794],"type":"Point"}
}