{
  "type": "Feature",
  "properties": {
    "addr:full":"303 E Wacker Dr Ste 1280 Chicago IL 60601",
    "addr:housenumber":"303",
    "addr:postcode":"60601",
    "addr:street":"E Wacker Dr Ste 1280",
    "iso:country":"US",
    "sg:address":"303 E Wacker Dr Ste 1280",
    "sg:city":"Chicago",
    "sg:classifiers":[
        {
            "category":"Real Estate",
            "subcategory":"Developer",
            "type":"Services"
        }
    ],
    "sg:phone":"+1 312 819 3750",
    "sg:postcode":"60601",
    "sg:province":"IL",
    "sg:website":"http://www.aspenhighlandsvillage.com",
    "wof:name":"Hines Interests",
    "wof:placetype":"venue"
},
  "geometry": {"coordinates":[-87.620605,41.88783],"type":"Point"}
}