{
  "type": "Feature",
  "properties": {
    "iso:country":"US",
    "sg:address":"510 S Day St",
    "sg:city":"West Frankfort",
    "sg:classifiers":[
        {
            "category":"Building & Trades",
            "subcategory":"Plumbing",
            "type":"Services"
        }
    ],
    "sg:phone":"+1 618 937 4173",
    "sg:postcode":"62896",
    "sg:province":"IL",
    "sg:tags":[
        "conditioning",
        "air",
        "system",
        "contractor"
    ],
    "wof:name":"Gardner Roy Htg & AC",
    "wof:placetype":"venue"
},
  "geometry": {"coordinates":[-88.912576,37.894367],"type":"Point"}
}