{
  "type": "Feature",
  "properties": {
    "addr:full":"2008 Main Street Rd Spring Grove IL 60081",
    "addr:housenumber":"2008",
    "addr:postcode":"60081",
    "addr:street":"Main Street Rd",
    "iso:country":"US",
    "sg:address":"2008 Main Street Rd",
    "sg:city":"Spring Grove",
    "sg:classifiers":[
        {
            "category":"Restaurant",
            "type":"Food & Drink"
        }
    ],
    "sg:phone":"+1 815 675 6294",
    "sg:postcode":"60081",
    "sg:province":"IL",
    "wof:name":"Town Pump",
    "wof:placetype":"venue"
},
  "geometry": {"coordinates":[-88.236143,42.443931],"type":"Point"}
}