{
  "type": "Feature",
  "properties": {
    "iso:country":"US",
    "sg:address":"1200 Peoria St",
    "sg:city":"Washington",
    "sg:classifiers":[
        {
            "category":"Autos & Motor Vehicles",
            "subcategory":"Automobile Sales",
            "type":"Retail Goods"
        }
    ],
    "sg:phone":"+1 309 444 9935",
    "sg:postcode":"61536",
    "sg:province":"IL",
    "sg:tags":[
        "car",
        "dealer"
    ],
    "wof:name":"Gary Uftring's Used Car Outlet",
    "wof:placetype":"venue"
},
  "geometry": {"coordinates":[-89.795724,40.694141],"type":"Point"}
}