{
  "type": "Feature",
  "properties": {
    "addr:full":"2511 W Schaumburg Rd Schaumburg IL 60194",
    "addr:housenumber":"2511",
    "addr:postcode":"60194",
    "addr:street":"W Schaumburg Rd",
    "iso:country":"US",
    "sg:address":"2511 W Schaumburg Rd",
    "sg:city":"Schaumburg",
    "sg:classifiers":[
        {
            "category":"Professional",
            "type":"Services"
        },
        {
            "category":"Professional",
            "subcategory":"Business Services",
            "type":"Services"
        },
        {
            "category":"Government",
            "subcategory":"Post Office",
            "type":"Public Place"
        },
        {
            "category":"Retail",
            "subcategory":"Pet Boarding",
            "type":"Services"
        }
    ],
    "sg:phone":"+1 847 524 3355",
    "sg:postcode":"60194",
    "sg:province":"IL",
    "sg:tags":[
        "crating",
        "mailbox-rental",
        "shipping",
        "packaging",
        "packing",
        "mail",
        "receiving"
    ],
    "sg:website":"http://www.pakmailschaumburg.com",
    "wof:name":"Pak Mail",
    "wof:placetype":"venue"
},
  "geometry": {"coordinates":[-88.14248499999999,42.024837],"type":"Point"}
}