{
  "type": "Feature",
  "properties": {
    "addr:full":"3555 N Ashland Ave Chicago IL 60657",
    "addr:housenumber":"3555",
    "addr:postcode":"60657",
    "addr:street":"N Ashland Ave",
    "iso:country":"US",
    "sg:address":"3555 N Ashland Ave",
    "sg:city":"Chicago",
    "sg:phone":"+1 773 296 1770",
    "sg:postcode":"60657",
    "sg:province":"IL",
    "wof:name":"My Bar",
    "wof:placetype":"venue"
},
  "geometry": {"coordinates":[-87.668854,41.946135],"type":"Point"}
}