{
  "type": "Feature",
  "properties": {
    "addr:full":"6425 E Sugar Grove Ln Dundas IL 62425",
    "addr:housenumber":"6425",
    "addr:postcode":"62425",
    "addr:street":"E Sugar Grove Ln",
    "iso:country":"US",
    "sg:address":"6425 E Sugar Grove Ln",
    "sg:city":"Dundas",
    "sg:classifiers":[
        {
            "category":"Farming",
            "subcategory":"Livestock Farm",
            "type":"Manufacturing & Wholesale Goods"
        },
        {
            "category":"Farming",
            "subcategory":"Farm",
            "type":"Manufacturing & Wholesale Goods"
        }
    ],
    "sg:phone":"+1 618 754 3790",
    "sg:postcode":"62425",
    "sg:province":"IL",
    "wof:name":"Bill Burgener",
    "wof:placetype":"venue"
},
  "geometry": {"coordinates":[-87.998062,38.8242],"type":"Point"}
}