{
  "type": "Feature",
  "properties": {
    "addr:full":"407 South St Lynn Center IL 61262",
    "addr:housenumber":"407",
    "addr:postcode":"61262",
    "addr:street":"South St",
    "iso:country":"US",
    "sg:address":"407 South St",
    "sg:city":"Lynn Center",
    "sg:classifiers":[
        {
            "category":"Wholesale",
            "subcategory":"Machinery & Supplies",
            "type":"Manufacturing & Wholesale Goods"
        }
    ],
    "sg:phone":"+1 309 521 8121",
    "sg:postcode":"61262",
    "sg:province":"IL",
    "sg:tags":[
        "farm",
        "equipment"
    ],
    "wof:name":"Lynn Center Implement",
    "wof:placetype":"venue"
},
  "geometry": {"coordinates":[-90.35943899999999,41.295699],"type":"Point"}
}