{
  "type": "Feature",
  "properties": {
    "addr:full":"18511 Torrence Ave Lansing IL 60438",
    "addr:postcode":"18511;60438",
    "addr:street":"Torrence Ave",
    "iso:country":"US",
    "sg:address":"18511 Torrence Ave",
    "sg:city":"Lansing",
    "sg:classifiers":[
        {
            "category":"Professional",
            "subcategory":"Lawyer & Legal Services",
            "type":"Services"
        }
    ],
    "sg:phone":"+1 708 889 9626",
    "sg:postcode":"60438",
    "sg:province":"IL",
    "wof:name":"Gianopolus Dennis Atty",
    "wof:placetype":"venue"
},
  "geometry": {"coordinates":[-87.558701,41.559101],"type":"Point"}
}