{
  "type": "Feature",
  "properties": {
    "iso:country":"US",
    "sg:address":"3419 Auburn St",
    "sg:city":"Rockford",
    "sg:classifiers":[
        {
            "category":"Retail",
            "subcategory":"Laundry & Dry Cleaning",
            "type":"Services"
        }
    ],
    "sg:phone":"+1 815 965 0174",
    "sg:postcode":"61101",
    "sg:province":"IL",
    "sg:tags":[
        "cleaner",
        "commercial"
    ],
    "wof:name":"Creases Cleaners",
    "wof:placetype":"venue"
},
  "geometry": {"coordinates":[-89.110682,42.288358],"type":"Point"}
}