{
  "type": "Feature",
  "properties": {
    "addr:full":"15001 Pulaski Rd Midlothian IL 60445",
    "addr:housenumber":"15001",
    "addr:postcode":"60445",
    "addr:street":"Pulaski Rd",
    "iso:country":"US",
    "sg:address":"15001 Pulaski Rd",
    "sg:city":"Midlothian",
    "sg:classifiers":[
        {
            "category":"Social Services",
            "subcategory":"Child Care",
            "type":"Services"
        }
    ],
    "sg:phone":"+1 708 389 6575",
    "sg:postcode":"60445",
    "sg:province":"IL",
    "sg:tags":[
        "day"
    ],
    "wof:name":"Joan Walko",
    "wof:placetype":"venue"
},
  "geometry": {"coordinates":[-87.717398,41.618224],"type":"Point"}
}