{
  "type": "Feature",
  "properties": {
    "addr:full":"821 W 69th St Chicago IL 60621",
    "addr:housenumber":"821",
    "addr:postcode":"60621",
    "addr:street":"W 69Th St",
    "iso:country":"US",
    "sg:address":"821 W 69th St",
    "sg:city":"Chicago",
    "sg:classifiers":[
        {
            "category":"Place Of Worship",
            "subcategory":"Church",
            "type":"Public Place"
        },
        {
            "category":"Organizations",
            "subcategory":"Religious Organization",
            "type":"Services"
        }
    ],
    "sg:phone":"+1 800 286 1249",
    "sg:postcode":"60621",
    "sg:province":"IL",
    "sg:tags":[
        "churches-pentecostal"
    ],
    "wof:name":"Unity Church of God in Christ Greater Chicagoland Toll Free",
    "wof:placetype":"venue"
},
  "geometry": {"coordinates":[-87.64537300000001,41.768805],"type":"Point"}
}