{
  "type": "Feature",
  "properties": {
    "addr:full":"5234 S Blackstone Ave Chicago IL 60615",
    "addr:housenumber":"5234",
    "addr:postcode":"60615",
    "addr:street":"S Blackstone Ave",
    "iso:country":"US",
    "sg:address":"5234 S Blackstone Ave",
    "sg:city":"Chicago",
    "sg:classifiers":[
        {
            "category":"Wholesale",
            "subcategory":"Computers",
            "type":"Manufacturing & Wholesale Goods"
        },
        {
            "category":"Banks & Credit Unions",
            "subcategory":"Financial Services",
            "type":"Services"
        },
        {
            "category":"Professional",
            "subcategory":"Computer Services",
            "type":"Services"
        }
    ],
    "sg:phone":"+1 773 288 8800",
    "sg:postcode":"60615",
    "sg:province":"IL",
    "sg:tags":[
        "repair",
        "broker",
        "mortgage"
    ],
    "wof:name":"Apollo Computers",
    "wof:placetype":"venue"
},
  "geometry": {"coordinates":[-87.590401,41.8004],"type":"Point"}
}