{
  "type": "Feature",
  "properties": {
    "iso:country":"US",
    "sg:address":"851 S York St",
    "sg:city":"Elmhurst",
    "sg:classifiers":[
        {
            "category":"Education",
            "subcategory":"Special Training",
            "type":"Public Place"
        },
        {
            "category":"Education",
            "subcategory":"School",
            "type":"Public Place"
        }
    ],
    "sg:phone":"+1 630 941 7785",
    "sg:postcode":"60126",
    "sg:province":"IL",
    "sg:tags":[
        "educational",
        "k-",
        "private"
    ],
    "wof:name":"Valentino Center Gym",
    "wof:placetype":"venue"
},
  "geometry": {"coordinates":[-87.935483,41.8731],"type":"Point"}
}