{
  "type": "Feature",
  "properties": {
    "iso:country":"US",
    "sg:address":"2614 N California Ave",
    "sg:city":"Chicago",
    "sg:classifiers":[
        {
            "category":"Communications",
            "type":"Services"
        }
    ],
    "sg:phone":"+1 312 823 8041",
    "sg:postcode":"60647",
    "sg:province":"IL",
    "sg:tags":[
        "recording",
        "rehearsal",
        "studio"
    ],
    "sg:website":"www.chicagorehearsalspace.com",
    "wof:name":"California Studios",
    "wof:placetype":"venue"
},
  "geometry": {"coordinates":[-87.697878,41.929311],"type":"Point"}
}