{
  "type": "Feature",
  "properties": {
    "iso:country":"US",
    "sg:address":"10241 Chestnut Ave",
    "sg:city":"Franklin Park",
    "sg:classifiers":[
        {
            "category":"Building & Trades",
            "subcategory":"Construction",
            "type":"Services"
        }
    ],
    "sg:phone":"+1 847 288 9113",
    "sg:postcode":"60131",
    "sg:province":"IL",
    "sg:tags":[
        "floor",
        "laying",
        "contractor"
    ],
    "wof:name":"Millennium Hardwood Flooring C",
    "wof:placetype":"venue"
},
  "geometry": {"coordinates":[-87.881682,41.931043],"type":"Point"}
}