{
  "type": "Feature",
  "properties": {
    "iso:country":"US",
    "sg:address":"3 Orland Square Dr",
    "sg:city":"Orland Park",
    "sg:classifiers":[
        {
            "category":"Ice Cream",
            "type":"Food & Drink"
        }
    ],
    "sg:menulink":"http://www.allmenus.com/il/orland/243136-baskin-robbins/menu/",
    "sg:phone":"+1 708 403 3331",
    "sg:postcode":"60462",
    "sg:province":"IL",
    "sg:tags":[
        "american"
    ],
    "wof:name":"Baskin-Robbins",
    "wof:placetype":"venue"
},
  "geometry": {"coordinates":[-87.85107000000001,41.618399],"type":"Point"}
}