{
  "type": "Feature",
  "properties": {
    "addr:full":"1120 W 122nd Street Chicago IL 60643",
    "addr:housenumber":"1120",
    "addr:postcode":"60643",
    "addr:street":"W 122Nd Street",
    "iso:country":"US",
    "sg:address":"1120 W 122nd Street",
    "sg:city":"Chicago",
    "sg:classifiers":[
        {
            "category":"Park",
            "type":"Public Place"
        }
    ],
    "sg:phone":"+1 312 747 7106",
    "sg:postcode":"60643",
    "sg:province":"IL",
    "sg:website":"www.chicagoparkdistrict.com",
    "wof:name":"Chicago Park District",
    "wof:placetype":"venue"
},
  "geometry": {"coordinates":[-87.650477,41.672302],"type":"Point"}
}