{
  "type": "Feature",
  "properties": {
    "iso:country":"US",
    "sg:address":"1951 Rohlwing Rd",
    "sg:city":"Rolling Meadows",
    "sg:classifiers":[
        {
            "category":"Manufacturing",
            "subcategory":"Printing",
            "type":"Manufacturing & Wholesale Goods"
        }
    ],
    "sg:phone":"+1 847 870 1576",
    "sg:postcode":"60008",
    "sg:province":"IL",
    "sg:tags":[
        "periodical"
    ],
    "wof:name":"Perkins Communications LLC",
    "wof:placetype":"venue"
},
  "geometry": {"coordinates":[-88.02679500000001,42.08871],"type":"Point"}
}