{
  "type": "Feature",
  "properties": {
    "iso:country":"US",
    "sg:address":"10 N Dearborn St Floor",
    "sg:city":"Chicago",
    "sg:classifiers":[
        {
            "category":"Professional",
            "subcategory":"Lawyer & Legal Services",
            "type":"Services"
        }
    ],
    "sg:phone":"+1 312 663 9400",
    "sg:postcode":"60602",
    "sg:province":"IL",
    "sg:tags":[
        "litigation",
        "attorney",
        "tort"
    ],
    "wof:name":"Mc Kee, Harold E - Riordan Mckee & Piper",
    "wof:placetype":"venue"
},
  "geometry": {"coordinates":[-87.629423,41.882211],"type":"Point"}
}