{
  "type": "Feature",
  "properties": {
    "addr:full":"1230 Hunters Ln Libertyville IL 60048",
    "addr:housenumber":"1230",
    "addr:postcode":"60048",
    "addr:street":"Hunters Ln",
    "iso:country":"US",
    "sg:address":"1230 Hunters Ln",
    "sg:city":"Libertyville",
    "sg:classifiers":[
        {
            "category":"Building & Trades",
            "subcategory":"Construction",
            "type":"Services"
        }
    ],
    "sg:phone":"+1 847 573 0510",
    "sg:postcode":"60048",
    "sg:province":"IL",
    "sg:tags":[
        "masonry",
        "contractor"
    ],
    "wof:name":"P W Masonry Inc",
    "wof:placetype":"venue"
},
  "geometry": {"coordinates":[-87.93353999999999,42.269361],"type":"Point"}
}