{
  "type": "Feature",
  "properties": {
    "iso:country":"US",
    "sg:address":"10158 E Hickory Ridge Dr",
    "sg:city":"Rochelle",
    "sg:classifiers":[
        {
            "category":"Building & Trades",
            "subcategory":"Cleaning & Sanitation",
            "type":"Services"
        }
    ],
    "sg:phone":"+1 815 562 2004",
    "sg:postcode":"61068",
    "sg:province":"IL",
    "sg:tags":[
        "janitor"
    ],
    "wof:name":"Mueller Janitorial & Carpet",
    "wof:placetype":"venue"
},
  "geometry": {"coordinates":[-89.144908,41.9439],"type":"Point"}
}