{
  "type": "Feature",
  "properties": {
    "iso:country":"US",
    "sg:address":"9731 S 89th Ave",
    "sg:city":"Palos Hills",
    "sg:classifiers":[
        {
            "category":"Shopping",
            "subcategory":"Gifts & Souvenirs",
            "type":"Retail Goods"
        }
    ],
    "sg:phone":"+1   ",
    "sg:postcode":"60465",
    "sg:province":"IL",
    "wof:name":"Roxies Dolls & Doll Hospital",
    "wof:placetype":"venue"
},
  "geometry": {"coordinates":[-87.839783,41.713232],"type":"Point"}
}