{
  "type": "Feature",
  "properties": {
    "addr:full":"3349 N Clark St Chicago IL 60657",
    "addr:housenumber":"3349",
    "addr:postcode":"60657",
    "addr:street":"N Clark St",
    "iso:country":"US",
    "sg:address":"3349 N Clark St",
    "sg:city":"Chicago",
    "sg:classifiers":[
        {
            "category":"Food & Beverages",
            "subcategory":"Groceries & Convenience Stores",
            "type":"Retail Goods"
        }
    ],
    "sg:phone":"+1   ",
    "sg:postcode":"60657",
    "sg:province":"IL",
    "sg:tags":[
        "japanese"
    ],
    "wof:name":"Star Market Grocery",
    "wof:placetype":"venue"
},
  "geometry": {"coordinates":[-87.652996,41.942923],"type":"Point"}
}