{
  "type": "Feature",
  "properties": {
    "addr:full":"11310 S Harlem Ave Worth IL 60482",
    "addr:housenumber":"11310",
    "addr:postcode":"60482",
    "addr:street":"S Harlem Ave",
    "iso:country":"US",
    "sg:address":"11310 S Harlem Ave",
    "sg:city":"Worth",
    "sg:classifiers":[
        {
            "category":"Retail",
            "subcategory":"Laundry & Dry Cleaning",
            "type":"Services"
        }
    ],
    "sg:phone":"+1 708 923 1131",
    "sg:postcode":"60482",
    "sg:province":"IL",
    "sg:tags":[
        "drycleaning",
        "plant"
    ],
    "wof:name":"Crystal Dry Cleaners & Tailors",
    "wof:placetype":"venue"
},
  "geometry": {"coordinates":[-87.79740099999999,41.6856],"type":"Point"}
}