{
  "type": "Feature",
  "properties": {
    "iso:country":"US",
    "sg:address":"6620 W Diversey Ave",
    "sg:city":"Chicago",
    "sg:classifiers":[
        {
            "category":"Banks & Credit Unions",
            "subcategory":"Atm",
            "type":"Services"
        }
    ],
    "sg:phone":"+1 773 286 1228",
    "sg:postcode":"60707",
    "sg:province":"IL",
    "sg:tags":[
        "bankruptcy"
    ],
    "wof:name":"Scelsa Christina Attorney At Law",
    "wof:placetype":"venue"
},
  "geometry": {"coordinates":[-87.791298,41.931],"type":"Point"}
}