{
  "type": "Feature",
  "properties": {
    "addr:full":"906 Olive St Saint Louis MO 63101",
    "addr:housenumber":"906",
    "addr:postcode":"63101",
    "addr:street":"Olive St",
    "iso:country":"US",
    "sg:address":"906 Olive St",
    "sg:city":"Saint Louis",
    "sg:classifiers":[
        {
            "category":"Professional",
            "subcategory":"Lawyer & Legal Services",
            "type":"Services"
        }
    ],
    "sg:phone":"+1 314 421 0350",
    "sg:postcode":"63101",
    "sg:province":"MO",
    "wof:name":"Schottel & Associates",
    "wof:placetype":"venue"
},
  "geometry": {"coordinates":[-90.194029,38.628971],"type":"Point"}
}