{
  "type": "Feature",
  "properties": {
    "iso:country":"US",
    "sg:address":"1137 Coventry Cir",
    "sg:city":"Glendale Heights",
    "sg:classifiers":[
        {
            "category":"Utilities",
            "subcategory":"Telephone",
            "type":"Services"
        }
    ],
    "sg:phone":"+1 630 534 4969",
    "sg:postcode":"60139",
    "sg:province":"IL",
    "sg:tags":[
        "communications"
    ],
    "wof:name":"Sell By Owner DOT Co",
    "wof:placetype":"venue"
},
  "geometry": {"coordinates":[-88.07088299999999,41.900365],"type":"Point"}
}