{
  "type": "Feature",
  "properties": {
    "iso:country":"US",
    "sg:address":"800 West Fifth Ave, Suite 211 Naperville, IL 60563 U.S.A.",
    "sg:classifiers":[
        {
            "category":"Professional",
            "subcategory":"Computer Services",
            "type":"Services"
        }
    ],
    "sg:phone":"+1 203 054 2200",
    "sg:postcode":"60563",
    "sg:province":"IL",
    "sg:website":"http://www.neilsoft.com",
    "wof:name":"Neilsoft Ltd",
    "wof:placetype":"venue"
},
  "geometry": {"coordinates":[-88.161074,41.780854],"type":"Point"}
}