{
  "type": "Feature",
  "properties": {
    "iso:country":"US",
    "sg:address":"2215 W Schaumburg Rd",
    "sg:city":"Schaumburg",
    "sg:classifiers":[
        {
            "category":"Health Services",
            "subcategory":"Doctor",
            "type":"Services"
        }
    ],
    "sg:phone":"+1 847 352 5410",
    "sg:postcode":"60194",
    "sg:province":"IL",
    "wof:name":"Swanson Clifford J DDS",
    "wof:placetype":"venue"
},
  "geometry": {"coordinates":[-88.148794,42.025893],"type":"Point"}
}