{
  "type": "Feature",
  "properties": {
    "addr:full":"655 Fairfield Dr Barrington IL 60010",
    "addr:housenumber":"655",
    "addr:postcode":"60010",
    "addr:street":"Fairfield Dr",
    "iso:country":"US",
    "sg:address":"655 Fairfield Dr",
    "sg:city":"Barrington",
    "sg:classifiers":[
        {
            "category":"Food & Beverages",
            "subcategory":"Groceries & Convenience Stores",
            "type":"Retail Goods"
        }
    ],
    "sg:phone":"+1 312 259 5713",
    "sg:postcode":"60010",
    "sg:province":"IL",
    "sg:tags":[
        "market"
    ],
    "wof:name":"Paris Market",
    "wof:placetype":"venue"
},
  "geometry": {"coordinates":[-88.112481,42.147609],"type":"Point"}
}