{
  "type": "Feature",
  "properties": {
    "iso:country":"US",
    "sg:address":"11011 SW Hwy",
    "sg:city":"Palos Hills",
    "sg:classifiers":[
        {
            "category":"Bars & Pubs",
            "type":"Food & Drink"
        }
    ],
    "sg:phone":"+1 708 974 9085",
    "sg:postcode":"60465",
    "sg:province":"IL",
    "sg:tags":[
        "tapa"
    ],
    "sg:website":"www.atredvelvet.com",
    "wof:name":"Red Velvet Lounge",
    "wof:placetype":"venue"
},
  "geometry": {"coordinates":[-87.80904700000001,41.692033],"type":"Point"}
}