{
  "type": "Feature",
  "properties": {
    "iso:country":"US",
    "sg:address":"1468 Louis Bork Dr",
    "sg:city":"Batavia",
    "sg:classifiers":[
        {
            "category":"Building & Trades",
            "subcategory":"Cleaning & Sanitation",
            "type":"Services"
        }
    ],
    "sg:phone":"+1 630 761 9056",
    "sg:postcode":"60510",
    "sg:province":"IL",
    "sg:tags":[
        "janitor"
    ],
    "sg:website":"www.dukaneservices.com",
    "wof:name":"Dukane Contract Svc Inc",
    "wof:placetype":"venue"
},
  "geometry": {"coordinates":[-88.263626,41.867862],"type":"Point"}
}