{
  "type": "Feature",
  "properties": {
    "iso:country":"US",
    "sg:address":"405 Gardenia Ln",
    "sg:city":"Buffalo Grove",
    "sg:classifiers":[
        {
            "category":"Professional",
            "subcategory":"Computer Services",
            "type":"Services"
        }
    ],
    "sg:phone":"+1 847 459 6505",
    "sg:postcode":"60089",
    "sg:province":"IL",
    "sg:tags":[
        "programing",
        "custom"
    ],
    "wof:name":"Inet Advisors",
    "wof:placetype":"venue"
},
  "geometry": {"coordinates":[-87.967855,42.161122],"type":"Point"}
}