{
  "type": "Feature",
  "properties": {
    "iso:country":"US",
    "sg:address":"10933 Saffron Ct",
    "sg:city":"Orland Park",
    "sg:classifiers":[
        {
            "category":"Freight",
            "type":"Transportation"
        }
    ],
    "sg:phone":"+1 708 906 8865",
    "sg:postcode":"60467",
    "sg:province":"IL",
    "sg:tags":[
        "operator",
        "trucking"
    ],
    "wof:name":"JP Transport Specialists Inc",
    "wof:placetype":"venue"
},
  "geometry": {"coordinates":[-87.884604,41.5859],"type":"Point"}
}