{
  "type": "Feature",
  "properties": {
    "addr:full":"216 W Pointe Dr Swansea IL 62226",
    "addr:housenumber":"216",
    "addr:postcode":"62226",
    "addr:street":"W Pointe Dr",
    "iso:country":"US",
    "sg:address":"216 W Pointe Dr",
    "sg:city":"Swansea",
    "sg:classifiers":[
        {
            "category":"Real Estate",
            "subcategory":"Real Estate Services",
            "type":"Services"
        }
    ],
    "sg:phone":"+1 618 239 0900",
    "sg:postcode":"62226",
    "sg:province":"IL",
    "sg:tags":[
        "company",
        "title"
    ],
    "wof:name":"NETCO",
    "wof:placetype":"venue"
},
  "geometry": {"coordinates":[-89.986875,38.564945],"type":"Point"}
}