{
  "type": "Feature",
  "properties": {
    "addr:full":"5901 Belmont Rd Downers Grove IL 60516",
    "addr:housenumber":"5901",
    "addr:postcode":"60516",
    "addr:street":"Belmont Rd",
    "iso:country":"US",
    "sg:address":"5901 Belmont Rd",
    "sg:city":"Downers Grove",
    "sg:classifiers":[
        {
            "category":"Government",
            "subcategory":"Fire Station",
            "type":"Public Place"
        }
    ],
    "sg:phone":"+1   ",
    "sg:postcode":"60516",
    "sg:province":"IL",
    "sg:tags":[
        "protection"
    ],
    "wof:name":"Station 2",
    "wof:placetype":"venue"
},
  "geometry": {"coordinates":[-88.03694900000001,41.777761],"type":"Point"}
}