{
  "type": "Feature",
  "properties": {
    "addr:full":"222 W Front St Wheaton IL 60187",
    "addr:housenumber":"222",
    "addr:postcode":"60187",
    "addr:street":"W Front St",
    "iso:country":"US",
    "sg:address":"222 W Front St",
    "sg:city":"Wheaton",
    "sg:classifiers":[
        {
            "category":"Personal",
            "type":"Services"
        }
    ],
    "sg:phone":"+1 630 653 5256",
    "sg:postcode":"60187",
    "sg:province":"IL",
    "sg:tags":[
        "hair",
        "salon"
    ],
    "sg:website":"www.marquizsalon.com/",
    "wof:name":"Marquiz Salons & Spa",
    "wof:placetype":"venue"
},
  "geometry": {"coordinates":[-88.109596,41.864899],"type":"Point"}
}