{
  "type": "Feature",
  "properties": {
    "addr:full":"262 E Deerpath Rd Lake Forest IL 60045",
    "addr:housenumber":"262",
    "addr:postcode":"60045",
    "addr:street":"E Deerpath Rd",
    "iso:country":"US",
    "sg:address":"262 E Deerpath Rd",
    "sg:city":"Lake Forest",
    "sg:classifiers":[
        {
            "category":"Government",
            "subcategory":"Office",
            "type":"Public Place"
        }
    ],
    "sg:phone":"+1 847 295 3555",
    "sg:postcode":"60045",
    "sg:province":"IL",
    "sg:tags":[
        "federal",
        "affairs"
    ],
    "wof:name":"Callisto Group",
    "wof:placetype":"venue"
},
  "geometry": {"coordinates":[-87.839911,42.251392],"type":"Point"}
}