{
  "type": "Feature",
  "properties": {
    "iso:country":"US",
    "sg:address":"619 W Miller Rd",
    "sg:city":"North Barrington",
    "sg:classifiers":[
        {
            "category":"Building & Trades",
            "subcategory":"Plumbing",
            "type":"Services"
        }
    ],
    "sg:phone":"+1 847 381 6805",
    "sg:postcode":"60010",
    "sg:province":"IL",
    "sg:tags":[
        "tank",
        "septic"
    ],
    "wof:name":"Rw Haas",
    "wof:placetype":"venue"
},
  "geometry": {"coordinates":[-88.144914,42.212092],"type":"Point"}
}