{
  "type": "Feature",
  "properties": {
    "addr:full":"2422 Enterprise Dr Westchester IL 60154",
    "addr:housenumber":"2422",
    "addr:postcode":"60154",
    "addr:street":"Enterprise Dr",
    "iso:country":"US",
    "sg:address":"2422 Enterprise Dr",
    "sg:city":"Westchester",
    "sg:classifiers":[
        {
            "category":"Cinema",
            "subcategory":"Movie Theater",
            "type":"Entertainment"
        }
    ],
    "sg:phone":"+1 708 562 5013",
    "sg:postcode":"60154",
    "sg:province":"IL",
    "sg:tags":[
        "motion",
        "picture"
    ],
    "wof:name":"Village Theaters",
    "wof:placetype":"venue"
},
  "geometry": {"coordinates":[-87.90877,41.846804],"type":"Point"}
}