{
  "type": "Feature",
  "properties": {
    "iso:country":"US",
    "sg:address":"4921 W Bloomingdale Ave",
    "sg:city":"Chicago",
    "sg:classifiers":[
        {
            "category":"Building & Trades",
            "subcategory":"Locksmith",
            "type":"Services"
        }
    ],
    "sg:phone":"+1 773 887 9503",
    "sg:postcode":"60639",
    "sg:province":"IL",
    "sg:tags":[
        "key"
    ],
    "wof:name":"Abcd Affordable Locksmith & Car Keys",
    "wof:placetype":"venue"
},
  "geometry": {"coordinates":[-87.749559,41.91308],"type":"Point"}
}