{
  "type": "Feature",
  "properties": {
    "iso:country":"US",
    "sg:address":"932 N Central Ave",
    "sg:city":"Chicago",
    "sg:classifiers":[
        {
            "category":"Education",
            "subcategory":"School",
            "type":"Public Place"
        }
    ],
    "sg:phone":"+1 773 534 6025",
    "sg:postcode":"60651",
    "sg:province":"IL",
    "sg:tags":[
        "high",
        "middle",
        "elementary"
    ],
    "wof:name":"Schools Public",
    "wof:placetype":"venue"
},
  "geometry": {"coordinates":[-87.765505,41.89761],"type":"Point"}
}