{
  "type": "Feature",
  "properties": {
    "iso:country":"US",
    "sg:address":"15125 S Meadow Ln",
    "sg:city":"Plainfield",
    "sg:classifiers":[
        {
            "category":"Manufacturing",
            "subcategory":"Tools & Machinery",
            "type":"Manufacturing & Wholesale Goods"
        },
        {
            "category":"Freight",
            "type":"Transportation"
        },
        {
            "category":"Building & Trades",
            "subcategory":"Construction",
            "type":"Services"
        }
    ],
    "sg:phone":"+1 815 436 9055",
    "sg:postcode":"60544",
    "sg:province":"IL",
    "sg:tags":[
        "conveying",
        "conveyor",
        "equipment-wholesale",
        "system",
        "equipment",
        "monorail",
        "manufacturer"
    ],
    "wof:name":"Epco",
    "wof:placetype":"venue"
},
  "geometry": {"coordinates":[-88.230988,41.606991],"type":"Point"}
}