{
  "type": "Feature",
  "properties": {
    "iso:country":"US",
    "sg:address":"4915 Oakton St",
    "sg:city":"Skokie",
    "sg:classifiers":[
        {
            "category":"Banks & Credit Unions",
            "subcategory":"Bank",
            "type":"Services"
        }
    ],
    "sg:phone":"+1 847 676 1700",
    "sg:postcode":"60077",
    "sg:province":"IL",
    "sg:tags":[
        "loan",
        "broker"
    ],
    "wof:name":"Dr Funding",
    "wof:placetype":"venue"
},
  "geometry": {"coordinates":[-87.751287,42.026209],"type":"Point"}
}