{
  "type": "Feature",
  "properties": {
    "addr:full":"116 Jasmine Ave Davis Junction IL 61020",
    "addr:housenumber":"116",
    "addr:postcode":"61020",
    "addr:street":"Jasmine Ave Davis",
    "iso:country":"US",
    "sg:address":"116 Jasmine Ave",
    "sg:city":"Davis Junction",
    "sg:classifiers":[
        {
            "category":"Building & Trades",
            "subcategory":"Construction",
            "type":"Services"
        }
    ],
    "sg:phone":"+1 815 298 2624",
    "sg:postcode":"61020",
    "sg:province":"IL",
    "sg:tags":[
        "mobile",
        "home"
    ],
    "wof:name":"A J Construction & Mobile Home",
    "wof:placetype":"venue"
},
  "geometry": {"coordinates":[-89.07201000000001,42.096176],"type":"Point"}
}