{
  "type": "Feature",
  "properties": {
    "iso:country":"US",
    "sg:address":"2705 Leyland Ln",
    "sg:city":"Aurora",
    "sg:classifiers":[
        {
            "category":"Retail",
            "subcategory":"Repair Shop",
            "type":"Services"
        }
    ],
    "sg:phone":"+1 630 898 1228",
    "sg:postcode":"60504",
    "sg:province":"IL",
    "wof:name":"Digmann Heavy Equipment Repair",
    "wof:placetype":"venue"
},
  "geometry": {"coordinates":[-88.247764,41.730869],"type":"Point"}
}