{
  "type": "Feature",
  "properties": {
    "iso:country":"US",
    "sg:address":"205 W Monroe St",
    "sg:city":"Chicago",
    "sg:classifiers":[
        {
            "category":"Professional",
            "subcategory":"Engineering",
            "type":"Services"
        }
    ],
    "sg:phone":"+1 312 629 9529",
    "sg:postcode":"60606",
    "sg:province":"IL",
    "sg:tags":[
        "consulting",
        "engineer"
    ],
    "wof:name":"Bread For The World Inc",
    "wof:placetype":"venue"
},
  "geometry": {"coordinates":[-87.633843,41.880679],"type":"Point"}
}