{
  "type": "Feature",
  "properties": {
    "iso:country":"US",
    "sg:address":"816 N Diamond Head Dr E",
    "sg:city":"Joliet",
    "sg:classifiers":[
        {
            "category":"Bus Station",
            "type":"Transportation"
        }
    ],
    "sg:phone":"+1 815 744 4812",
    "sg:postcode":"60431",
    "sg:province":"IL",
    "sg:tags":[
        "facility"
    ],
    "wof:name":"Scott M Zito & Associate",
    "wof:placetype":"venue"
},
  "geometry": {"coordinates":[-88.220367,41.504207],"type":"Point"}
}