{
  "type": "Feature",
  "properties": {
    "addr:full":"4051 Main St Skokie IL 60076",
    "addr:housenumber":"4051",
    "addr:postcode":"60076",
    "addr:street":"Main St",
    "iso:country":"US",
    "sg:address":"4051 Main St",
    "sg:city":"Skokie",
    "sg:classifiers":[
        {
            "category":"Food & Beverages",
            "subcategory":"Specialty",
            "type":"Retail Goods"
        }
    ],
    "sg:phone":"+1   ",
    "sg:postcode":"60076",
    "sg:province":"IL",
    "wof:name":"Seattle Suttons Healthy Eating",
    "wof:placetype":"venue"
},
  "geometry": {"coordinates":[-87.73007699999999,42.033434],"type":"Point"}
}