{
  "type": "Feature",
  "properties": {
    "addr:full":"899 S Weber Rd Bolingbrook IL 60490",
    "addr:housenumber":"899",
    "addr:postcode":"60490",
    "addr:street":"S Weber Rd",
    "iso:country":"US",
    "sg:address":"899 S Weber Rd",
    "sg:city":"Bolingbrook",
    "sg:classifiers":[
        {
            "category":"Personal",
            "subcategory":"Tanning Parlor",
            "type":"Services"
        }
    ],
    "sg:phone":"+1 630 759 2300",
    "sg:postcode":"60490",
    "sg:province":"IL",
    "sg:tags":[
        "salon"
    ],
    "sg:website":"www.beachhousetan.com",
    "wof:name":"Beach House",
    "wof:placetype":"venue"
},
  "geometry": {"coordinates":[-88.12545299999999,41.675263],"type":"Point"}
}