{
  "type": "Feature",
  "properties": {
    "addr:full":"601 Harlem Ave Forest Park IL 60130",
    "addr:housenumber":"601",
    "addr:postcode":"60130",
    "addr:street":"Harlem Ave",
    "iso:country":"US",
    "sg:address":"601 Harlem Ave",
    "sg:city":"Forest Park",
    "sg:classifiers":[
        {
            "category":"Autos & Motor Vehicles",
            "subcategory":"Fuel & Gas Station",
            "type":"Retail Goods"
        }
    ],
    "sg:phone":"+1   ",
    "sg:postcode":"60130",
    "sg:province":"IL",
    "sg:tags":[
        "station",
        "gasoline"
    ],
    "wof:name":"Thorntons Gas & Foodmart 18",
    "wof:placetype":"venue"
},
  "geometry": {"coordinates":[-87.80456100000001,41.875389],"type":"Point"}
}