{
  "type": "Feature",
  "properties": {
    "iso:country":"US",
    "sg:address":"36810 N Lake St",
    "sg:city":"Ingleside",
    "sg:classifiers":[
        {
            "category":"Building & Trades",
            "subcategory":"Plumbing",
            "type":"Services"
        }
    ],
    "sg:phone":"+1 847 973 2477",
    "sg:postcode":"60041",
    "sg:province":"IL",
    "sg:tags":[
        "heating",
        "contractor"
    ],
    "wof:name":"Engineered Comfort Systems",
    "wof:placetype":"venue"
},
  "geometry": {"coordinates":[-88.144621,42.39736],"type":"Point"}
}