{
  "type": "Feature",
  "properties": {
    "addr:full":"346 Taft Ave Glen Ellyn IL 60137",
    "addr:housenumber":"346",
    "addr:postcode":"60137",
    "addr:street":"Taft Ave",
    "iso:country":"US",
    "sg:address":"346 Taft Ave",
    "sg:city":"Glen Ellyn",
    "sg:classifiers":[
        {
            "category":"Health Services",
            "subcategory":"Medical Lab",
            "type":"Services"
        }
    ],
    "sg:phone":"+1 630 790 4008",
    "sg:postcode":"60137",
    "sg:province":"IL",
    "sg:tags":[
        "laboratory"
    ],
    "wof:name":"Genetic Service",
    "wof:placetype":"venue"
},
  "geometry": {"coordinates":[-88.071544,41.858481],"type":"Point"}
}