{
  "type": "Feature",
  "properties": {
    "addr:full":"M2 on Neil 301 N Neil St Ste 400 Champaign IL 61820",
    "addr:housenumber":"301",
    "addr:postcode":"61820",
    "addr:street":"N Neil St Ste 400",
    "iso:country":"US",
    "sg:address":"M2 on Neil 301 N Neil St Ste 400",
    "sg:city":"Champaign",
    "sg:classifiers":[
        {
            "category":"Professional",
            "subcategory":"Art Services",
            "type":"Services"
        },
        {
            "category":"Communications",
            "type":"Services"
        },
        {
            "category":"Professional",
            "subcategory":"Computer Services",
            "type":"Services"
        }
    ],
    "sg:phone":"+1 217 531 2966",
    "sg:postcode":"61820",
    "sg:province":"IL",
    "sg:tags":[
        "repair",
        "graphic",
        "design",
        "web"
    ],
    "sg:website":"www.accuraty.com",
    "wof:name":"Accuraty Solutions",
    "wof:placetype":"venue"
},
  "geometry": {"coordinates":[-88.243555,40.118286],"type":"Point"}
}