{
  "type": "Feature",
  "properties": {
    "iso:country":"US",
    "sg:address":"1802 Birchwood Ln",
    "sg:city":"Rockford",
    "sg:classifiers":[
        {
            "category":"Real Estate",
            "subcategory":"Real Estate Operator",
            "type":"Services"
        }
    ],
    "sg:phone":"+1 815 227 0928",
    "sg:postcode":"61107",
    "sg:province":"IL",
    "sg:tags":[
        "apartment"
    ],
    "wof:name":"Sinnissipi Apartments Inc",
    "wof:placetype":"venue"
},
  "geometry": {"coordinates":[-89.064235,42.284288],"type":"Point"}
}