{
  "type": "Feature",
  "properties": {
    "iso:country":"US",
    "sg:address":"19717 Twenhafel Rd",
    "sg:city":"Carlyle",
    "sg:classifiers":[
        {
            "category":"Manufacturing",
            "subcategory":"Food",
            "type":"Manufacturing & Wholesale Goods"
        },
        {
            "category":"Farming",
            "subcategory":"Farm",
            "type":"Manufacturing & Wholesale Goods"
        }
    ],
    "sg:phone":"+1 618 594 2164",
    "sg:postcode":"62231",
    "sg:province":"IL",
    "sg:tags":[
        "corn",
        "product"
    ],
    "wof:name":"Eugene Twenhafel",
    "wof:placetype":"venue"
},
  "geometry": {"coordinates":[-89.330487,38.544661],"type":"Point"}
}