{
  "type": "Feature",
  "properties": {
    "iso:country":"US",
    "sg:address":"298 S Harrison Ave",
    "sg:city":"Kankakee",
    "sg:classifiers":[
        {
            "category":"Place Of Worship",
            "subcategory":"Church",
            "type":"Public Place"
        },
        {
            "category":"Place Of Worship",
            "type":"Public Place"
        }
    ],
    "sg:phone":"+1 815 932 6611",
    "sg:postcode":"60901",
    "sg:province":"IL",
    "sg:tags":[
        "churches-episcopal-anglican",
        "churches-episcopal"
    ],
    "sg:website":"http://k3stpauls.homestead.com",
    "wof:name":"St Pauls Episcopal Church Inc",
    "wof:placetype":"venue"
},
  "geometry": {"coordinates":[-87.86019899999999,41.117271],"type":"Point"}
}