{
  "type": "Feature",
  "properties": {
    "iso:country":"US",
    "sg:address":"11950 S Central Ave",
    "sg:city":"Alsip",
    "sg:classifiers":[
        {
            "category":"Building & Trades",
            "subcategory":"Plumbing",
            "type":"Services"
        }
    ],
    "sg:phone":"+1 708 597 9700",
    "sg:postcode":"60803",
    "sg:province":"IL",
    "sg:tags":[
        "conditioning",
        "air",
        "system",
        "contractor"
    ],
    "wof:name":"Amber Heating & Air Cond",
    "wof:placetype":"venue"
},
  "geometry": {"coordinates":[-87.758651,41.672033],"type":"Point"}
}