{
  "type": "Feature",
  "properties": {
    "iso:country":"US",
    "sg:address":"3347 Dempster St",
    "sg:city":"Skokie",
    "sg:classifiers":[
        {
            "category":"Health Services",
            "subcategory":"Doctor",
            "type":"Services"
        }
    ],
    "sg:phone":"+1 847 674 0577",
    "sg:postcode":"60076",
    "sg:province":"IL",
    "wof:name":"Douglas R Hasegawa",
    "wof:placetype":"venue"
},
  "geometry": {"coordinates":[-87.711896,42.040841],"type":"Point"}
}