{
  "type": "Feature",
  "properties": {
    "iso:country":"US",
    "sg:address":"3030 Malmo Dr",
    "sg:city":"Arlington Hts",
    "sg:classifiers":[
        {
            "category":"Professional",
            "type":"Services"
        }
    ],
    "sg:phone":"+1 847 364 1222",
    "sg:postcode":"60005",
    "sg:province":"IL",
    "sg:tags":[
        "establishment"
    ],
    "sg:website":"www.associationfulfillment.com",
    "wof:name":"Association Publishing & Svc",
    "wof:placetype":"venue"
},
  "geometry": {"coordinates":[-87.947022,42.031524],"type":"Point"}
}