{
  "type": "Feature",
  "properties": {
    "iso:country":"US",
    "sg:address":"605 Keller St",
    "sg:city":"Plano",
    "sg:classifiers":[
        {
            "category":"Building & Trades",
            "subcategory":"Electrical",
            "type":"Services"
        }
    ],
    "sg:phone":"+1 630 399 9498",
    "sg:postcode":"60545",
    "sg:province":"IL",
    "sg:tags":[
        "electrician"
    ],
    "wof:name":"Colborn Electric",
    "wof:placetype":"venue"
},
  "geometry": {"coordinates":[-88.497511,41.669062],"type":"Point"}
}