{
  "type": "Feature",
  "properties": {
    "addr:full":"101 Southcreek Dr Manteno IL 60950",
    "addr:housenumber":"101",
    "addr:postcode":"60950",
    "addr:street":"Southcreek Dr",
    "iso:country":"US",
    "sg:address":"101 Southcreek Dr",
    "sg:city":"Manteno",
    "sg:classifiers":[
        {
            "category":"Autos & Motor Vehicles",
            "subcategory":"Fuel & Gas Station",
            "type":"Retail Goods"
        }
    ],
    "sg:phone":"+1 815 468 6544",
    "sg:postcode":"60950",
    "sg:province":"IL",
    "sg:website":"http://www.mkm.net",
    "wof:name":"Amoco",
    "wof:placetype":"venue"
},
  "geometry": {"coordinates":[-87.847382,41.250439],"type":"Point"}
}