{
  "type": "Feature",
  "properties": {
    "addr:full":"13832 Kostner Ave Crestwood IL 60445",
    "addr:housenumber":"13832",
    "addr:postcode":"60445",
    "addr:street":"Kostner Ave",
    "iso:country":"US",
    "sg:address":"13832 Kostner Ave",
    "sg:city":"Crestwood",
    "sg:classifiers":[
        {
            "category":"Wholesale",
            "subcategory":"Machinery & Supplies",
            "type":"Manufacturing & Wholesale Goods"
        }
    ],
    "sg:phone":"+1 708 824 0071",
    "sg:postcode":"60445",
    "sg:province":"IL",
    "wof:name":"Allied Waste Industries Inc",
    "wof:placetype":"venue"
},
  "geometry": {"coordinates":[-87.728208,41.642148],"type":"Point"}
}