{
  "type": "Feature",
  "properties": {
    "iso:country":"US",
    "sg:address":"1340 68th St",
    "sg:city":"Downers Grove",
    "sg:classifiers":[
        {
            "category":"Banks & Credit Unions",
            "subcategory":"Bank",
            "type":"Services"
        }
    ],
    "sg:phone":"+1 630 493 9981",
    "sg:postcode":"60516",
    "sg:province":"IL",
    "sg:tags":[
        "federal"
    ],
    "wof:name":"Pac Credit Union",
    "wof:placetype":"venue"
},
  "geometry": {"coordinates":[-88.01716399999999,41.763334],"type":"Point"}
}