{
  "type": "Feature",
  "properties": {
    "iso:country":"US",
    "sg:address":"3525 W Peterson Avenue",
    "sg:city":"Chicago",
    "sg:classifiers":[
        {
            "category":"Fast Food",
            "type":"Food & Drink"
        },
        {
            "category":"Food & Beverages",
            "subcategory":"Meat & Fish",
            "type":"Retail Goods"
        }
    ],
    "sg:phone":"+1 773 267 8180",
    "sg:postcode":"60659",
    "sg:province":"IL",
    "sg:tags":[
        "burger",
        "hot",
        "dog"
    ],
    "wof:name":"Gold Coast Dogs",
    "wof:placetype":"venue"
},
  "geometry": {"coordinates":[-87.717546,41.990131],"type":"Point"}
}