{
  "type": "Feature",
  "properties": {
    "addr:full":"2533 30th Ave Ct Moline IL 61265",
    "addr:housenumber":"2533",
    "addr:postcode":"61265",
    "addr:street":"30Th Ave Ct",
    "iso:country":"US",
    "sg:address":"2533 30th Ave Ct",
    "sg:city":"Moline",
    "sg:classifiers":[
        {
            "category":"Professional",
            "subcategory":"Engineering",
            "type":"Services"
        }
    ],
    "sg:phone":"+1 309 764 4701",
    "sg:postcode":"61265",
    "sg:province":"IL",
    "wof:name":"North Hill Assoc",
    "wof:placetype":"venue"
},
  "geometry": {"coordinates":[-90.537156,41.479497],"type":"Point"}
}