{
  "type": "Feature",
  "properties": {
    "iso:country":"US",
    "sg:address":"463 N Weber Rd",
    "sg:city":"Romeoville",
    "sg:classifiers":[
        {
            "category":"Restaurant",
            "type":"Food & Drink"
        }
    ],
    "sg:phone":"+1 815 293 2600",
    "sg:postcode":"60446",
    "sg:province":"IL",
    "sg:tags":[
        "pizza"
    ],
    "sg:website":"http://www.myrosatis.com/home/",
    "wof:name":"Rosati's Pizza",
    "wof:placetype":"venue"
},
  "geometry": {"coordinates":[-88.123081,41.605102],"type":"Point"}
}