{
  "type": "Feature",
  "properties": {
    "iso:country":"US",
    "sg:address":"1161 Barneswood Dr",
    "sg:city":"Downers Grove",
    "sg:classifiers":[
        {
            "category":"Wholesale",
            "subcategory":"Hardware",
            "type":"Manufacturing & Wholesale Goods"
        }
    ],
    "sg:phone":"+1 630 532 5322",
    "sg:postcode":"60515",
    "sg:province":"IL",
    "wof:name":"Bull Dog Tools & Fasteners",
    "wof:placetype":"venue"
},
  "geometry": {"coordinates":[-88.014978,41.821632],"type":"Point"}
}