{
  "type": "Feature",
  "properties": {
    "iso:country":"US",
    "sg:address":"8 Towncenter Dr",
    "sg:city":"Park Forest",
    "sg:classifiers":[
        {
            "category":"Real Estate",
            "subcategory":"Real Estate Agent",
            "type":"Services"
        }
    ],
    "sg:phone":"+1 708 534 3250",
    "sg:postcode":"60466",
    "sg:province":"IL",
    "wof:name":"Diversified Real Est Resources",
    "wof:placetype":"venue"
},
  "geometry": {"coordinates":[-87.690425,41.449039],"type":"Point"}
}