{
  "type": "Feature",
  "properties": {
    "iso:country":"US",
    "sg:address":"14067 Woodrow Rd",
    "sg:city":"Green Valley",
    "sg:phone":"+1 309 352 4761",
    "sg:postcode":"61534",
    "sg:province":"IL",
    "sg:tags":[
        "farm",
        "corn",
        "soybean"
    ],
    "wof:name":"Ruth Farms",
    "wof:placetype":"venue"
},
  "geometry": {"coordinates":[-89.661129,40.421472],"type":"Point"}
}