{
  "type": "Feature",
  "properties": {
    "iso:country":"US",
    "sg:address":"1102 State Rte 97",
    "sg:city":"Havana",
    "sg:classifiers":[
        {
            "category":"Manufacturing",
            "subcategory":"Tools & Machinery",
            "type":"Manufacturing & Wholesale Goods"
        }
    ],
    "sg:phone":"+1 309 543 4060",
    "sg:postcode":"62644",
    "sg:province":"IL",
    "sg:tags":[
        "machine",
        "shop"
    ],
    "wof:name":"Shadow Well Drilling",
    "wof:placetype":"venue"
},
  "geometry": {"coordinates":[-90.051303,40.289695],"type":"Point"}
}