{
  "type": "Feature",
  "properties": {
    "iso:country":"US",
    "sg:address":"431 N Dearborn St",
    "sg:city":"Chicago",
    "sg:classifiers":[
        {
            "category":"Restaurant",
            "type":"Food & Drink"
        }
    ],
    "sg:phone":"+1 312 321 2725",
    "sg:postcode":"60654",
    "sg:province":"IL",
    "sg:tags":[
        "steakhouse"
    ],
    "sg:website":"www.ruthschris.com/locations/chi...",
    "wof:name":"Ruth's Chris Steak House",
    "wof:placetype":"venue"
},
  "geometry": {"coordinates":[-87.62937700000001,41.890441],"type":"Point"}
}