{
  "type": "Feature",
  "properties": {
    "addr:full":"4209 W School St Chicago IL 60641",
    "addr:housenumber":"4209",
    "addr:postcode":"60641",
    "addr:street":"W School St",
    "iso:country":"US",
    "sg:address":"4209 W School St",
    "sg:city":"Chicago",
    "sg:classifiers":[
        {
            "category":"Building & Trades",
            "subcategory":"Construction",
            "type":"Services"
        }
    ],
    "sg:phone":"+1 773 685 4796",
    "sg:postcode":"60641",
    "sg:province":"IL",
    "sg:tags":[
        "house"
    ],
    "wof:name":"Family Contractors Inc",
    "wof:placetype":"venue"
},
  "geometry": {"coordinates":[-87.73391100000001,41.94075],"type":"Point"}
}