{
  "type": "Feature",
  "properties": {
    "iso:country":"US",
    "sg:address":"3330 Dundee Rd",
    "sg:city":"Northbrook",
    "sg:classifiers":[
        {
            "category":"Retail",
            "subcategory":"Portrait Studio",
            "type":"Services"
        }
    ],
    "sg:phone":"+1 847 498 6884",
    "sg:postcode":"60062",
    "sg:province":"IL",
    "sg:tags":[
        "photography"
    ],
    "wof:name":"Larry Rappeport Photography",
    "wof:placetype":"venue"
},
  "geometry": {"coordinates":[-87.861211,42.138425],"type":"Point"}
}