{
  "type": "Feature",
  "properties": {
    "addr:full":"3753 W Fullerton Ave Chicago IL 60647",
    "addr:housenumber":"3753",
    "addr:postcode":"60647",
    "addr:street":"W Fullerton Ave",
    "iso:country":"US",
    "sg:address":"3753 W Fullerton Ave",
    "sg:city":"Chicago",
    "sg:classifiers":[
        {
            "category":"Food & Beverages",
            "subcategory":"Liquor & Beverages",
            "type":"Retail Goods"
        }
    ],
    "sg:phone":"+1 773 486 7722",
    "sg:postcode":"60647",
    "sg:province":"IL",
    "sg:tags":[
        "alcoholic"
    ],
    "wof:name":"Economy Liquors Inc",
    "wof:placetype":"venue"
},
  "geometry": {"coordinates":[-87.72163,41.924469],"type":"Point"}
}