{
  "type": "Feature",
  "properties": {
    "iso:country":"US",
    "sg:address":"850 S Main St",
    "sg:city":"Jacksonville",
    "sg:classifiers":[
        {
            "category":"Shopping",
            "subcategory":"Department Store",
            "type":"Retail Goods"
        }
    ],
    "sg:phone":"+1 217 243 5958",
    "sg:postcode":"62650",
    "sg:province":"IL",
    "sg:tags":[
        "shop"
    ],
    "wof:name":"Family Dollar Store",
    "wof:placetype":"venue"
},
  "geometry": {"coordinates":[-90.229078,39.724912],"type":"Point"}
}