{
  "type": "Feature",
  "properties": {
    "iso:country":"US",
    "sg:address":"2308 Co Rd 900 E",
    "sg:city":"Champaign",
    "sg:classifiers":[
        {
            "category":"Building & Trades",
            "subcategory":"Construction",
            "type":"Services"
        }
    ],
    "sg:phone":"+1 217 351 4095",
    "sg:postcode":"61822",
    "sg:province":"IL",
    "sg:tags":[
        "residential"
    ],
    "wof:name":"Robert E Furtney Construction",
    "wof:placetype":"venue"
},
  "geometry": {"coordinates":[-88.295762,40.137761],"type":"Point"}
}