{
  "type": "Feature",
  "properties": {
    "iso:country":"US",
    "sg:address":"24921 W Mary Ln",
    "sg:city":"Plainfield",
    "sg:classifiers":[
        {
            "category":"Freight",
            "type":"Transportation"
        }
    ],
    "sg:phone":"+1 815 254 9907",
    "sg:postcode":"60586",
    "sg:province":"IL",
    "sg:tags":[
        "driver",
        "leasing",
        "truck"
    ],
    "wof:name":"Thomas Maher",
    "wof:placetype":"venue"
},
  "geometry": {"coordinates":[-88.22387000000001,41.570131],"type":"Point"}
}