{
  "type": "Feature",
  "properties": {
    "iso:country":"US",
    "sg:address":"5201 Walnut Ave",
    "sg:city":"Downers Grove",
    "sg:classifiers":[
        {
            "category":"Building & Trades",
            "subcategory":"Construction",
            "type":"Services"
        }
    ],
    "sg:phone":"+1 630 960 3750",
    "sg:postcode":"60515",
    "sg:province":"IL",
    "sg:tags":[
        "house"
    ],
    "wof:name":"Sievers Development Co",
    "wof:placetype":"venue"
},
  "geometry": {"coordinates":[-88.052067,41.79031],"type":"Point"}
}