{
  "type": "Feature",
  "properties": {
    "iso:country":"US",
    "sg:address":"8550 W Bryn Mawr Ave # 900",
    "sg:city":"Chicago",
    "sg:classifiers":[
        {
            "category":"Professional",
            "subcategory":"Engineering",
            "type":"Services"
        }
    ],
    "sg:phone":"+1 773 380 7900",
    "sg:postcode":"60631",
    "sg:province":"IL",
    "sg:tags":[
        "consulting",
        "engineer"
    ],
    "sg:website":"http://www.thehoytco.com",
    "wof:name":"Hdr",
    "wof:placetype":"venue"
},
  "geometry": {"coordinates":[-87.840293,41.981054],"type":"Point"}
}