{
  "type": "Feature",
  "properties": {
    "addr:full":"14754 el Vista Ave Oak Forest IL 60452",
    "addr:housenumber":"14754",
    "addr:postcode":"60452",
    "addr:street":"El Vista Ave",
    "iso:country":"US",
    "sg:address":"14754 el Vista Ave",
    "sg:city":"Oak Forest",
    "sg:classifiers":[
        {
            "category":"Building & Trades",
            "subcategory":"Cleaning & Sanitation",
            "type":"Services"
        }
    ],
    "sg:phone":"+1 708 535 9770",
    "sg:postcode":"60452",
    "sg:province":"IL",
    "sg:tags":[
        "janitor"
    ],
    "wof:name":"Dream Clean",
    "wof:placetype":"venue"
},
  "geometry": {"coordinates":[-87.754519,41.623709],"type":"Point"}
}