{
  "type": "Feature",
  "properties": {
    "iso:country":"US",
    "sg:address":"6238 W Addison St",
    "sg:city":"Chicago",
    "sg:classifiers":[
        {
            "category":"Professional",
            "subcategory":"Accounting & Tax Preparation",
            "type":"Services"
        }
    ],
    "sg:phone":"+1 773 777 7577",
    "sg:postcode":"60634",
    "sg:province":"IL",
    "sg:tags":[
        "accountant"
    ],
    "wof:name":"PJA Associates PC",
    "wof:placetype":"venue"
},
  "geometry": {"coordinates":[-87.78221499999999,41.945621],"type":"Point"}
}