{
  "type": "Feature",
  "properties": {
    "addr:full":"752 E US Hwy 34 Earlville IL 60518",
    "addr:housenumber":"752",
    "addr:postcode":"60518",
    "addr:street":"E Us Hwy 34",
    "iso:country":"US",
    "sg:address":"752 E US Hwy 34",
    "sg:city":"Earlville",
    "sg:phone":"+1 815 539 3008",
    "sg:postcode":"60518",
    "sg:province":"IL",
    "sg:tags":[
        "farm",
        "corn",
        "soybean"
    ],
    "wof:name":"Thomas Munson",
    "wof:placetype":"venue"
},
  "geometry": {"coordinates":[-89.000085,41.569387],"type":"Point"}
}