{
  "type": "Feature",
  "properties": {
    "iso:country":"US",
    "sg:address":"10511 N Bell School Rd",
    "sg:city":"Elmwood",
    "sg:classifiers":[
        {
            "category":"Manufacturing",
            "subcategory":"Food",
            "type":"Manufacturing & Wholesale Goods"
        },
        {
            "category":"Farming",
            "subcategory":"Farm",
            "type":"Manufacturing & Wholesale Goods"
        }
    ],
    "sg:phone":"+1 309 446 3054",
    "sg:postcode":"61529",
    "sg:province":"IL",
    "sg:tags":[
        "corn",
        "product"
    ],
    "wof:name":"Norman Streitmatter",
    "wof:placetype":"venue"
},
  "geometry": {"coordinates":[-89.927694,40.817107],"type":"Point"}
}