{
  "type": "Feature",
  "properties": {
    "addr:full":"4207 Park Ave Brookfield IL 60513",
    "addr:housenumber":"4207",
    "addr:postcode":"60513",
    "addr:street":"Park Ave",
    "iso:country":"US",
    "sg:address":"4207 Park Ave",
    "sg:city":"Brookfield",
    "sg:classifiers":[
        {
            "category":"Professional",
            "subcategory":"Computer Services",
            "type":"Services"
        }
    ],
    "sg:phone":"+1 708 485 6711",
    "sg:postcode":"60513",
    "sg:province":"IL",
    "sg:tags":[
        "consulting"
    ],
    "wof:name":"Cda Consulting Inc",
    "wof:placetype":"venue"
},
  "geometry": {"coordinates":[-87.848994,41.812879],"type":"Point"}
}