{
  "type": "Feature",
  "properties": {
    "iso:country":"US",
    "sg:address":"900 Corporate Grove Dr",
    "sg:city":"Buffalo Grove",
    "sg:classifiers":[
        {
            "category":"Professional",
            "type":"Services"
        }
    ],
    "sg:phone":"+1 847 777 3100",
    "sg:postcode":"60089",
    "sg:province":"IL",
    "sg:tags":[
        "scientist"
    ],
    "wof:name":"Baxter",
    "wof:placetype":"venue"
},
  "geometry": {"coordinates":[-87.931865,42.173708],"type":"Point"}
}