{
  "type": "Feature",
  "properties": {
    "iso:country":"US",
    "sg:address":"134 N Bloomingdale Rd",
    "sg:city":"Bloomingdale",
    "sg:classifiers":[
        {
            "category":"Professional",
            "subcategory":"Lawyer & Legal Services",
            "type":"Services"
        }
    ],
    "sg:phone":"+1 630 529 4750",
    "sg:postcode":"60108",
    "sg:province":"IL",
    "sg:website":"www.mevorahlaw.com",
    "wof:name":"Mevorah Steven H & Associates",
    "wof:placetype":"venue"
},
  "geometry": {"coordinates":[-88.08228099999999,41.960664],"type":"Point"}
}