{
  "type": "Feature",
  "properties": {
    "addr:full":"1125 N Old Rand Rd Wauconda IL 60084",
    "addr:housenumber":"1125",
    "addr:postcode":"60084",
    "addr:street":"N Old Rand Rd",
    "iso:country":"US",
    "sg:address":"1125 N Old Rand Rd",
    "sg:city":"Wauconda",
    "sg:classifiers":[
        {
            "category":"Banks & Credit Unions",
            "subcategory":"Investment Brokerage",
            "type":"Services"
        }
    ],
    "sg:phone":"+1 847 487 7639",
    "sg:postcode":"60084",
    "sg:province":"IL",
    "sg:tags":[
        "consultant",
        "planning",
        "financial"
    ],
    "wof:name":"Headstart Financial Concepts",
    "wof:placetype":"venue"
},
  "geometry": {"coordinates":[-88.148369,42.276293],"type":"Point"}
}