{
  "type": "Feature",
  "properties": {
    "iso:country":"US",
    "sg:address":"708 Milton Rd",
    "sg:city":"Alton",
    "sg:classifiers":[
        {
            "category":"Professional",
            "subcategory":"Computer Services",
            "type":"Services"
        }
    ],
    "sg:phone":"+1 618 463 9820",
    "sg:postcode":"62002",
    "sg:province":"IL",
    "sg:tags":[
        "programing",
        "custom"
    ],
    "sg:website":"www.cmpunet.com",
    "wof:name":"Compunet Inc",
    "wof:placetype":"venue"
},
  "geometry": {"coordinates":[-90.129178,38.889444],"type":"Point"}
}