{
  "type": "Feature",
  "properties": {
    "addr:full":"1209 W Berwyn Avenue Chicago IL 60640",
    "addr:housenumber":"1209",
    "addr:postcode":"60640",
    "addr:street":"W Berwyn Avenue",
    "iso:country":"US",
    "sg:address":"1209 W Berwyn Avenue",
    "sg:city":"Chicago",
    "sg:classifiers":[
        {
            "category":"Real Estate",
            "subcategory":"Architect",
            "type":"Services"
        }
    ],
    "sg:phone":"+1 773 271 1925",
    "sg:postcode":"60640",
    "sg:province":"IL",
    "wof:name":"Greene & Proppe Design",
    "wof:placetype":"venue"
},
  "geometry": {"coordinates":[-87.66036699999999,41.977963],"type":"Point"}
}