{
  "type": "Feature",
  "properties": {
    "addr:full":"2723 W Devon Avenue Chicago IL 60659",
    "addr:housenumber":"2723",
    "addr:postcode":"60659",
    "addr:street":"W Devon Avenue",
    "iso:country":"US",
    "sg:address":"2723 W Devon Avenue",
    "sg:city":"Chicago",
    "sg:classifiers":[
        {
            "category":"Professional",
            "subcategory":"Accounting & Tax Preparation",
            "type":"Services"
        }
    ],
    "sg:phone":"+1 773 262 5999",
    "sg:postcode":"60659",
    "sg:province":"IL",
    "sg:tags":[
        "accountant"
    ],
    "wof:name":"Tax Pro Associates",
    "wof:placetype":"venue"
},
  "geometry": {"coordinates":[-87.69808399999999,41.997385],"type":"Point"}
}