{
  "type": "Feature",
  "properties": {
    "addr:full":"2521 Nelson Sq Westchester IL 60154",
    "addr:housenumber":"2521",
    "addr:postcode":"60154",
    "addr:street":"Nelson Sq",
    "iso:country":"US",
    "sg:address":"2521 Nelson Sq",
    "sg:city":"Westchester",
    "sg:classifiers":[
        {
            "category":"Personal",
            "subcategory":"Beauty Salon",
            "type":"Services"
        }
    ],
    "sg:phone":"+1 708 562 7384",
    "sg:postcode":"60154",
    "sg:province":"IL",
    "wof:name":"Louise S Beauty Salon",
    "wof:placetype":"venue"
},
  "geometry": {"coordinates":[-87.89339,41.841908],"type":"Point"}
}