{
  "type": "Feature",
  "properties": {
    "addr:full":"8434 S Aberdeen St Chicago IL 60620",
    "addr:housenumber":"8434",
    "addr:postcode":"60620",
    "addr:street":"S Aberdeen St",
    "iso:country":"US",
    "sg:address":"8434 S Aberdeen St",
    "sg:city":"Chicago",
    "sg:classifiers":[
        {
            "category":"Place Of Worship",
            "subcategory":"Church",
            "type":"Public Place"
        },
        {
            "category":"Place Of Worship",
            "type":"Public Place"
        }
    ],
    "sg:phone":"+1 773 874 4343",
    "sg:postcode":"60620",
    "sg:province":"IL",
    "sg:tags":[
        "churches-pentecostal-independent",
        "churches-pentecostal"
    ],
    "wof:name":"New Hope Congregational Church Of God In Christ",
    "wof:placetype":"venue"
},
  "geometry": {"coordinates":[-87.65104100000001,41.740794],"type":"Point"}
}