{
  "type": "Feature",
  "properties": {
    "iso:country":"US",
    "sg:address":"320 E Liberty Dr",
    "sg:city":"Wheaton",
    "sg:classifiers":[
        {
            "category":"Professional",
            "type":"Services"
        }
    ],
    "sg:phone":"+1 630 665 1883",
    "sg:postcode":"60187",
    "sg:province":"IL",
    "sg:tags":[
        "establishment"
    ],
    "wof:name":"Dentechnica",
    "wof:placetype":"venue"
},
  "geometry": {"coordinates":[-88.101426,41.864302],"type":"Point"}
}