{
  "type": "Feature",
  "properties": {
    "addr:full":"1717 E West Rd Calumet City IL 60409",
    "addr:housenumber":"1717 e",
    "addr:postcode":"60409",
    "addr:street":"West Rd",
    "iso:country":"US",
    "sg:address":"1717 E West Rd",
    "sg:city":"Calumet City",
    "sg:classifiers":[
        {
            "category":"Shopping",
            "subcategory":"Department Store",
            "type":"Retail Goods"
        },
        {
            "category":"Shopping",
            "subcategory":"Pharmacy",
            "type":"Retail Goods"
        }
    ],
    "sg:phone":"+1 708 730 3101",
    "sg:postcode":"60409",
    "sg:province":"IL",
    "sg:tags":[
        "drugstore"
    ],
    "wof:name":"Target Stores",
    "wof:placetype":"venue"
},
  "geometry": {"coordinates":[-87.564903,41.5994],"type":"Point"}
}