{
  "type": "Feature",
  "properties": {
    "addr:full":"934 W 138th St Riverdale IL 60827",
    "addr:housenumber":"934",
    "addr:postcode":"60827",
    "addr:street":"W 138Th St",
    "iso:country":"US",
    "sg:address":"934 W 138th St",
    "sg:city":"Riverdale",
    "sg:classifiers":[
        {
            "category":"Communications",
            "subcategory":"Radio Station",
            "type":"Services"
        }
    ],
    "sg:phone":"+1 708 201 9600",
    "sg:postcode":"60827",
    "sg:province":"IL",
    "wof:name":"Wnwi Radio",
    "wof:placetype":"venue"
},
  "geometry": {"coordinates":[-87.6446,41.6446],"type":"Point"}
}