{
  "type": "Feature",
  "properties": {
    "addr:full":"5441 W Grace St Chicago IL 60641",
    "addr:housenumber":"5441",
    "addr:postcode":"60641",
    "addr:street":"W Grace St",
    "iso:country":"US",
    "sg:address":"5441 W Grace St",
    "sg:city":"Chicago",
    "sg:classifiers":[
        {
            "category":"Shopping",
            "subcategory":"Clothing, Apparel, & Fashions",
            "type":"Retail Goods"
        }
    ],
    "sg:phone":"+1   ",
    "sg:postcode":"60641",
    "sg:province":"IL",
    "wof:name":"Zvs Tailor Corp",
    "wof:placetype":"venue"
},
  "geometry": {"coordinates":[-87.763548,41.949605],"type":"Point"}
}