{
  "type": "Feature",
  "properties": {
    "iso:country":"US",
    "sg:address":"305 S Church St",
    "sg:city":"Gibson City",
    "sg:classifiers":[
        {
            "category":"Social Services",
            "subcategory":"Child Care",
            "type":"Services"
        }
    ],
    "sg:phone":"+1 217 784 4875",
    "sg:postcode":"60936",
    "sg:province":"IL",
    "sg:tags":[
        "day"
    ],
    "wof:name":"Nancy Coulter",
    "wof:placetype":"venue"
},
  "geometry": {"coordinates":[-88.37384900000001,40.462385],"type":"Point"}
}