{
  "type": "Feature",
  "properties": {
    "iso:country":"US",
    "sg:address":"7445 Newburg Rd",
    "sg:city":"Rockford",
    "sg:classifiers":[
        {
            "category":"Banks & Credit Unions",
            "subcategory":"Investment Brokerage",
            "type":"Services"
        }
    ],
    "sg:phone":"+1 815 332 5320",
    "sg:postcode":"61108",
    "sg:province":"IL",
    "sg:tags":[
        "advisory",
        "financial"
    ],
    "sg:website":"www.lrfinancial.com",
    "wof:name":"L R Financial Svc",
    "wof:placetype":"venue"
},
  "geometry": {"coordinates":[-88.971669,42.253402],"type":"Point"}
}