{
  "type": "Feature",
  "properties": {
    "addr:full":"7517 W Belmont Ave Chicago IL 60634",
    "addr:housenumber":"7517",
    "addr:postcode":"60634",
    "addr:street":"W Belmont Ave",
    "iso:country":"US",
    "sg:address":"7517 W Belmont Ave",
    "sg:city":"Chicago",
    "sg:classifiers":[
        {
            "category":"Professional",
            "subcategory":"Computer Services",
            "type":"Services"
        }
    ],
    "sg:phone":"+1 773 889 1818",
    "sg:postcode":"60634",
    "sg:province":"IL",
    "sg:tags":[
        "stereo",
        "installation"
    ],
    "wof:name":"Once Over Car Care",
    "wof:placetype":"venue"
},
  "geometry": {"coordinates":[-87.814598,41.937801],"type":"Point"}
}