{
  "type": "Feature",
  "properties": {
    "addr:full":"13 Crystal Lake Plz Crystal Lake IL 60014",
    "addr:housenumber":"13",
    "addr:postcode":"60014",
    "addr:street":"Crystal;Plz",
    "iso:country":"US",
    "sg:address":"13 Crystal Lake Plz",
    "sg:city":"Crystal Lake",
    "sg:classifiers":[
        {
            "category":"Travel",
            "subcategory":"Travel Agent",
            "type":"Entertainment"
        }
    ],
    "sg:phone":"+1 815 459 2500",
    "sg:postcode":"60014",
    "sg:province":"IL",
    "sg:tags":[
        "agency",
        "bureau"
    ],
    "wof:name":"Crystal Lake Travel Agency",
    "wof:placetype":"venue"
},
  "geometry": {"coordinates":[-88.32299399999999,42.227459],"type":"Point"}
}