{
  "type": "Feature",
  "properties": {
    "addr:full":"2655 Warrenville Rd Downers Grove IL 60515",
    "addr:housenumber":"2655",
    "addr:postcode":"60515",
    "addr:street":"Warrenville Rd",
    "iso:country":"US",
    "sg:address":"2655 Warrenville Rd",
    "sg:city":"Downers Grove",
    "sg:classifiers":[
        {
            "category":"Banks & Credit Unions",
            "subcategory":"Bank",
            "type":"Services"
        }
    ],
    "sg:phone":"+1 630 743 4486",
    "sg:postcode":"60515",
    "sg:province":"IL",
    "sg:tags":[
        "loan",
        "real estate"
    ],
    "wof:name":"Finance America",
    "wof:placetype":"venue"
},
  "geometry": {"coordinates":[-88.048952,41.807565],"type":"Point"}
}