{
  "type": "Feature",
  "properties": {
    "addr:full":"17930 Ellwood Rd Breese IL 62230",
    "addr:housenumber":"17930",
    "addr:postcode":"62230",
    "addr:street":"Ellwood Rd",
    "iso:country":"US",
    "sg:address":"17930 Ellwood Rd",
    "sg:city":"Breese",
    "sg:classifiers":[
        {
            "category":"Building & Trades",
            "subcategory":"Construction",
            "type":"Services"
        }
    ],
    "sg:phone":"+1 618 526 2342",
    "sg:postcode":"62230",
    "sg:province":"IL",
    "sg:tags":[
        "excavation",
        "contractor"
    ],
    "wof:name":"Straeter Excavating",
    "wof:placetype":"venue"
},
  "geometry": {"coordinates":[-89.535901,38.680718],"type":"Point"}
}