{
  "type": "Feature",
  "properties": {
    "addr:full":"138 S Locust St Manteno IL 60950",
    "addr:housenumber":"138",
    "addr:postcode":"60950",
    "addr:street":"S Locust St",
    "iso:country":"US",
    "sg:address":"138 S Locust St",
    "sg:city":"Manteno",
    "sg:classifiers":[
        {
            "category":"Manufacturing",
            "subcategory":"Buildings",
            "type":"Manufacturing & Wholesale Goods"
        },
        {
            "category":"Building & Trades",
            "subcategory":"Construction",
            "type":"Services"
        }
    ],
    "sg:phone":"+1 815 468 8213",
    "sg:postcode":"60950",
    "sg:province":"IL",
    "sg:tags":[
        "altering",
        "home",
        "builder",
        "remodeling",
        "contractor"
    ],
    "wof:name":"Barber Construction",
    "wof:placetype":"venue"
},
  "geometry": {"coordinates":[-87.833945,41.24659],"type":"Point"}
}