{
  "type": "Feature",
  "properties": {
    "addr:full":"32304 Prairie View Ln Mc Henry IL 60051",
    "addr:housenumber":"32304",
    "addr:postcode":"60051",
    "addr:street":"Prairie View Ln Mc Henry",
    "iso:country":"US",
    "sg:address":"32304 Prairie View Ln",
    "sg:city":"Mc Henry",
    "sg:classifiers":[
        {
            "category":"Professional",
            "subcategory":"Employment Agencies",
            "type":"Services"
        }
    ],
    "sg:phone":"+1 847 875 9918",
    "sg:postcode":"60051",
    "sg:province":"IL",
    "sg:tags":[
        "help",
        "supply"
    ],
    "wof:name":"Coalson Trucking",
    "wof:placetype":"venue"
},
  "geometry": {"coordinates":[-88.196107,42.332713],"type":"Point"}
}