{
  "type": "Feature",
  "properties": {
    "addr:full":"3347 Broadway St Quincy IL 62301",
    "addr:housenumber":"3347",
    "addr:postcode":"62301",
    "addr:street":"Broadway St",
    "iso:country":"US",
    "sg:address":"3347 Broadway St",
    "sg:city":"Quincy",
    "sg:classifiers":[
        {
            "category":"Shopping",
            "subcategory":"Department Store",
            "type":"Retail Goods"
        }
    ],
    "sg:phone":"+1 217 224 8300",
    "sg:postcode":"62301",
    "sg:province":"IL",
    "wof:name":"Bergner's Department Store",
    "wof:placetype":"venue"
},
  "geometry": {"coordinates":[-91.362296,39.935338],"type":"Point"}
}