{
  "type": "Feature",
  "properties": {
    "iso:country":"US",
    "sg:address":"108 Alder Ct",
    "sg:city":"Rolling Meadows",
    "sg:classifiers":[
        {
            "category":"Wholesale",
            "subcategory":"Machinery & Supplies",
            "type":"Manufacturing & Wholesale Goods"
        }
    ],
    "sg:phone":"+1 847 397 4070",
    "sg:postcode":"60008",
    "sg:province":"IL",
    "sg:tags":[
        "industrial"
    ],
    "wof:name":"J L Seals Inc",
    "wof:placetype":"venue"
},
  "geometry": {"coordinates":[-88.048855,42.081124],"type":"Point"}
}