{
  "type": "Feature",
  "properties": {
    "iso:country":"US",
    "sg:address":"6815 N Dowagiac Ave",
    "sg:city":"Chicago",
    "sg:classifiers":[
        {
            "category":"Building & Trades",
            "subcategory":"Construction",
            "type":"Services"
        }
    ],
    "sg:phone":"+1 773 774 0533",
    "sg:postcode":"60646",
    "sg:province":"IL",
    "sg:tags":[
        "house",
        "hanging"
    ],
    "wof:name":"Accomando Construction",
    "wof:placetype":"venue"
},
  "geometry": {"coordinates":[-87.766965,42.005404],"type":"Point"}
}