{
  "type": "Feature",
  "properties": {
    "iso:country":"US",
    "sg:address":"12842 N 2200th Ave",
    "sg:city":"Geneseo",
    "sg:classifiers":[
        {
            "category":"Professional",
            "type":"Services"
        }
    ],
    "sg:phone":"+1 309 944 3468",
    "sg:postcode":"61254",
    "sg:province":"IL",
    "sg:tags":[
        "harvesting-contract"
    ],
    "wof:name":"Steve Lalemam",
    "wof:placetype":"venue"
},
  "geometry": {"coordinates":[-90.182376,41.46929],"type":"Point"}
}