{
  "type": "Feature",
  "properties": {
    "addr:full":"826 Maple Ave Downers Grove IL 60515",
    "addr:housenumber":"826",
    "addr:postcode":"60515",
    "addr:street":"Maple Ave",
    "iso:country":"US",
    "sg:address":"826 Maple Ave",
    "sg:city":"Downers Grove",
    "sg:classifiers":[
        {
            "category":"Building & Trades",
            "subcategory":"Electrical",
            "type":"Services"
        }
    ],
    "sg:phone":"+1 630 434 9011",
    "sg:postcode":"60515",
    "sg:province":"IL",
    "sg:tags":[
        "electrical",
        "contractor"
    ],
    "wof:name":"Residential Upgrade Electric",
    "wof:placetype":"venue"
},
  "geometry": {"coordinates":[-88.003497,41.793714],"type":"Point"}
}