{
  "type": "Feature",
  "properties": {
    "addr:full":"20 Marryat Rd Cary IL 60013",
    "addr:housenumber":"20",
    "addr:postcode":"60013",
    "addr:street":"Marryat Rd",
    "iso:country":"US",
    "sg:address":"20 Marryat Rd",
    "sg:city":"Cary",
    "sg:classifiers":[
        {
            "category":"Professional",
            "subcategory":"Computer Services",
            "type":"Services"
        }
    ],
    "sg:phone":"+1 847 516 3416",
    "sg:postcode":"60013",
    "sg:province":"IL",
    "sg:tags":[
        "system",
        "integration"
    ],
    "wof:name":"Computer Systems Integration",
    "wof:placetype":"venue"
},
  "geometry": {"coordinates":[-88.25162899999999,42.198537],"type":"Point"}
}