{
  "type": "Feature",
  "properties": {
    "addr:full":"180 S 3rd St Belleville IL 62220",
    "addr:housenumber":"180",
    "addr:postcode":"62220",
    "addr:street":"S 3Rd St",
    "iso:country":"US",
    "sg:address":"180 S 3rd St",
    "sg:city":"Belleville",
    "sg:classifiers":[
        {
            "category":"Health Services",
            "subcategory":"Doctor",
            "type":"Services"
        }
    ],
    "sg:phone":"+1 618 233 0017",
    "sg:postcode":"62220",
    "sg:province":"IL",
    "sg:tags":[
        "physician",
        "surgeon"
    ],
    "wof:name":"Associates In Ob/Gyn",
    "wof:placetype":"venue"
},
  "geometry": {"coordinates":[-89.98816100000001,38.512463],"type":"Point"}
}