{
  "type": "Feature",
  "properties": {
    "addr:full":"1834 Walden Office Sq # 130 Schaumburg IL 60173",
    "addr:housenumber":"1834",
    "addr:postcode":"60173",
    "addr:street":"Walden Office Sq # 130",
    "iso:country":"US",
    "sg:address":"1834 Walden Office Sq # 130",
    "sg:city":"Schaumburg",
    "sg:classifiers":[
        {
            "category":"Fast Food",
            "type":"Food & Drink"
        },
        {
            "category":"Restaurant",
            "type":"Food & Drink"
        }
    ],
    "sg:phone":"+1 847 925 9700",
    "sg:postcode":"60173",
    "sg:province":"IL",
    "sg:tags":[
        "mexican"
    ],
    "sg:website":"http://www.tacobell.com",
    "wof:name":"Taco Bell",
    "wof:placetype":"venue"
},
  "geometry": {"coordinates":[-88.033996,42.062487],"type":"Point"}
}