{
  "type": "Feature",
  "properties": {
    "addr:full":"4300 W Chicago Ave Chicago IL 60651",
    "addr:housenumber":"4300",
    "addr:postcode":"60651",
    "addr:street":"W Chicago Ave",
    "iso:country":"US",
    "sg:address":"4300 W Chicago Ave",
    "sg:city":"Chicago",
    "sg:classifiers":[
        {
            "category":"Building & Trades",
            "subcategory":"Electrical",
            "type":"Services"
        }
    ],
    "sg:phone":"+1 773 489 4400",
    "sg:postcode":"60651",
    "sg:province":"IL",
    "sg:tags":[
        "electrical",
        "contractor"
    ],
    "wof:name":"Super Electric Construction",
    "wof:placetype":"venue"
},
  "geometry": {"coordinates":[-87.73471499999999,41.895209],"type":"Point"}
}