{
  "type": "Feature",
  "properties": {
    "addr:full":"279 Willow Ave Mundelein IL 60060",
    "addr:housenumber":"279",
    "addr:postcode":"60060",
    "addr:street":"Willow Ave",
    "iso:country":"US",
    "sg:address":"279 Willow Ave",
    "sg:city":"Mundelein",
    "sg:classifiers":[
        {
            "category":"Building & Trades",
            "subcategory":"Cleaning & Sanitation",
            "type":"Services"
        }
    ],
    "sg:phone":"+1 847 837 9908",
    "sg:postcode":"60060",
    "sg:province":"IL",
    "sg:tags":[
        "maintenance"
    ],
    "wof:name":"R & K Services",
    "wof:placetype":"venue"
},
  "geometry": {"coordinates":[-88.004617,42.244095],"type":"Point"}
}