{
  "type": "Feature",
  "properties": {
    "iso:country":"US",
    "sg:address":"1435 W Norwood",
    "sg:city":"Chicago",
    "sg:classifiers":[
        {
            "category":"Building & Trades",
            "subcategory":"Construction",
            "type":"Services"
        }
    ],
    "sg:phone":"+1 773 251 6836",
    "sg:postcode":"60660",
    "sg:province":"IL",
    "sg:tags":[
        "contractor"
    ],
    "wof:name":"HomeWorks",
    "wof:placetype":"venue"
},
  "geometry": {"coordinates":[-87.66656500000001,41.99134],"type":"Point"}
}