{
  "type": "Feature",
  "properties": {
    "addr:full":"1549 W Peru St Princeton IL 61356",
    "addr:housenumber":"1549",
    "addr:postcode":"61356",
    "addr:street":"W Peru St",
    "iso:country":"US",
    "sg:address":"1549 W Peru St",
    "sg:city":"Princeton",
    "sg:classifiers":[
        {
            "category":"Organizations",
            "subcategory":"Community Association",
            "type":"Services"
        }
    ],
    "sg:phone":"+1 815 872 1171",
    "sg:postcode":"61356",
    "sg:province":"IL",
    "wof:name":"American Legion Post 125",
    "wof:placetype":"venue"
},
  "geometry": {"coordinates":[-89.48460900000001,41.371647],"type":"Point"}
}