{
  "type": "Feature",
  "properties": {
    "addr:full":"2 N la Salle St Ste 1110 Chicago IL 60602",
    "addr:housenumber":"2",
    "addr:postcode":"60602",
    "addr:street":"N La Salle St Ste 1110",
    "iso:country":"US",
    "sg:address":"2 N la Salle St Ste 1110",
    "sg:city":"Chicago",
    "sg:classifiers":[
        {
            "category":"Insurance",
            "subcategory":"Insurance Agent",
            "type":"Services"
        },
        {
            "category":"Insurance",
            "subcategory":"Hazard Insurance",
            "type":"Services"
        }
    ],
    "sg:phone":"+1 312 580 7300",
    "sg:postcode":"60602",
    "sg:province":"IL",
    "sg:tags":[
        "adjuster"
    ],
    "wof:name":"Heineke Burke",
    "wof:placetype":"venue"
},
  "geometry": {"coordinates":[-87.632347,41.88195],"type":"Point"}
}