{
  "type": "Feature",
  "properties": {
    "iso:country":"US",
    "sg:address":"409 N Church St",
    "sg:city":"Albany",
    "sg:classifiers":[
        {
            "category":"Government",
            "subcategory":"Fire Station",
            "type":"Public Place"
        }
    ],
    "sg:phone":"+1   ",
    "sg:postcode":"61230",
    "sg:province":"IL",
    "sg:tags":[
        "protection"
    ],
    "wof:name":"Albany Fire Protection Ds",
    "wof:placetype":"venue"
},
  "geometry": {"coordinates":[-90.2169,41.790481],"type":"Point"}
}