{
  "type": "Feature",
  "properties": {
    "iso:country":"US",
    "sg:address":"1125 Lunt Ave",
    "sg:city":"Elk Grove Village",
    "sg:classifiers":[
        {
            "category":"Manufacturing",
            "subcategory":"Tools & Machinery",
            "type":"Manufacturing & Wholesale Goods"
        }
    ],
    "sg:phone":"+1 847 981 3000",
    "sg:postcode":"60007",
    "sg:province":"IL",
    "sg:tags":[
        "food",
        "equipment",
        "confectionery",
        "processing",
        "mfg"
    ],
    "wof:name":"Savage Bros Company",
    "wof:placetype":"venue"
},
  "geometry": {"coordinates":[-87.959838,42.001966],"type":"Point"}
}