{
  "type": "Feature",
  "properties": {
    "iso:country":"US",
    "sg:address":"4N637 Wescot Ln",
    "sg:city":"West Chicago",
    "sg:classifiers":[
        {
            "category":"Wholesale",
            "subcategory":"Stationery",
            "type":"Manufacturing & Wholesale Goods"
        }
    ],
    "sg:phone":"+1 630 213 7180",
    "sg:postcode":"60185",
    "sg:province":"IL",
    "sg:tags":[
        "card"
    ],
    "sg:website":"www.starglowstudios.com",
    "wof:name":"Starglow Studios Designer Invitations",
    "wof:placetype":"venue"
},
  "geometry": {"coordinates":[-88.196404,41.942101],"type":"Point"}
}