{
  "type": "Feature",
  "properties": {
    "addr:full":"743 Circle Ave Forest Park IL 60130",
    "addr:housenumber":"743",
    "addr:postcode":"60130",
    "addr:street":"Circle Ave",
    "iso:country":"US",
    "sg:address":"743 Circle Ave",
    "sg:city":"Forest Park",
    "sg:classifiers":[
        {
            "category":"Professional",
            "subcategory":"Business Services",
            "type":"Services"
        }
    ],
    "sg:phone":"+1 708 771 8091",
    "sg:postcode":"60130",
    "sg:province":"IL",
    "sg:tags":[
        "distributor",
        "add",
        "clothing",
        "specialty"
    ],
    "wof:name":"Stange Apparel Co Inc",
    "wof:placetype":"venue"
},
  "geometry": {"coordinates":[-87.808195,41.872492],"type":"Point"}
}