{
  "type": "Feature",
  "properties": {
    "addr:full":"643 Gundersen Dr Carol Stream IL 60188",
    "addr:housenumber":"643",
    "addr:postcode":"60188",
    "addr:street":"Gundersen Dr",
    "iso:country":"US",
    "sg:address":"643 Gundersen Dr",
    "sg:city":"Carol Stream",
    "sg:classifiers":[
        {
            "category":"Freight",
            "type":"Transportation"
        }
    ],
    "sg:phone":"+1 630 871 6503",
    "sg:postcode":"60188",
    "sg:province":"IL",
    "wof:name":"K & J Transport",
    "wof:placetype":"venue"
},
  "geometry": {"coordinates":[-88.09541900000001,41.893911],"type":"Point"}
}