{
  "type": "Feature",
  "properties": {
    "iso:country":"US",
    "sg:address":"3554 N Sheffield Ave",
    "sg:city":"Chicago",
    "sg:classifiers":[
        {
            "category":"Food & Beverages",
            "subcategory":"Groceries & Convenience Stores",
            "type":"Retail Goods"
        }
    ],
    "sg:phone":"+1 773 477 3774",
    "sg:postcode":"60657",
    "sg:province":"IL",
    "sg:website":"www.7-eleven.com",
    "wof:name":"7-Eleven",
    "wof:placetype":"venue"
},
  "geometry": {"coordinates":[-87.654326,41.946817],"type":"Point"}
}