{
  "type": "Feature",
  "properties": {
    "addr:full":"2300 Barrington Road Suite 700 Hoffman Estates IL 60169",
    "addr:housenumber":"2300",
    "addr:postcode":"60169",
    "addr:street":"Barrington Road Suite 700",
    "iso:country":"US",
    "sg:address":"2300 Barrington Road Suite 700",
    "sg:city":"Hoffman Estates",
    "sg:classifiers":[
        {
            "category":"Professional",
            "subcategory":"Computer Services",
            "type":"Services"
        }
    ],
    "sg:phone":"+1 866 260 2483",
    "sg:postcode":"60169",
    "sg:province":"IL",
    "sg:website":"http://www.vizioncore.com",
    "wof:name":"Visioncore",
    "wof:placetype":"venue"
},
  "geometry": {"coordinates":[-88.14457899999999,42.057432],"type":"Point"}
}