{
  "type": "Feature",
  "properties": {
    "addr:full":"7316 Sparrow Rd Hopedale IL 61747",
    "addr:housenumber":"7316",
    "addr:postcode":"61747",
    "addr:street":"Sparrow Rd",
    "iso:country":"US",
    "sg:address":"7316 Sparrow Rd",
    "sg:city":"Hopedale",
    "sg:classifiers":[
        {
            "category":"Building & Trades",
            "subcategory":"Construction",
            "type":"Services"
        }
    ],
    "sg:phone":"+1 309 449 3280",
    "sg:postcode":"61747",
    "sg:province":"IL",
    "sg:tags":[
        "excavating",
        "contractor"
    ],
    "wof:name":"Wayne Litwiller Excavating",
    "wof:placetype":"venue"
},
  "geometry": {"coordinates":[-89.437228,40.4315],"type":"Point"}
}