{
  "type": "Feature",
  "properties": {
    "iso:country":"US",
    "sg:address":"2001 W Wiesbrook Rd",
    "sg:city":"Wheaton",
    "sg:classifiers":[
        {
            "category":"Health Services",
            "subcategory":"Doctor",
            "type":"Services"
        }
    ],
    "sg:phone":"+1 630 510 7666",
    "sg:postcode":"60189",
    "sg:province":"IL",
    "sg:tags":[
        "physician",
        "pediatrics-orthopedic",
        "surgeons",
        "orthopedics",
        "surgery",
        "surgeon"
    ],
    "wof:name":"Orthopedics Trinity",
    "wof:placetype":"venue"
},
  "geometry": {"coordinates":[-88.13447499999999,41.843586],"type":"Point"}
}