{
  "type": "Feature",
  "properties": {
    "iso:country":"US",
    "sg:address":"7808 S South Shore Dr",
    "sg:city":"Chicago",
    "sg:classifiers":[
        {
            "category":"Shopping",
            "subcategory":"Music",
            "type":"Retail Goods"
        }
    ],
    "sg:phone":"+1 773 719 7331",
    "sg:postcode":"60649",
    "sg:province":"IL",
    "sg:tags":[
        "store"
    ],
    "wof:name":"Inferno Records",
    "wof:placetype":"venue"
},
  "geometry": {"coordinates":[-87.551192,41.754903],"type":"Point"}
}