{
  "type": "Feature",
  "properties": {
    "addr:full":"1595 N 8th St Vandalia IL 62471",
    "addr:housenumber":"1595",
    "addr:postcode":"62471",
    "addr:street":"N 8Th St",
    "iso:country":"US",
    "sg:address":"1595 N 8th St",
    "sg:city":"Vandalia",
    "sg:classifiers":[
        {
            "category":"Autos & Motor Vehicles",
            "subcategory":"Fuel & Gas Station",
            "type":"Retail Goods"
        }
    ],
    "sg:phone":"+1 618 283 0592",
    "sg:postcode":"62471",
    "sg:province":"IL",
    "sg:tags":[
        "oil"
    ],
    "wof:name":"Illico Mobil Svc",
    "wof:placetype":"venue"
},
  "geometry": {"coordinates":[-89.100278,38.97657],"type":"Point"}
}