{
  "type": "Feature",
  "properties": {
    "addr:full":"400 E Lincoln Hwy New Lenox IL 60451",
    "addr:housenumber":"400",
    "addr:postcode":"60451",
    "addr:street":"E Lincoln Hwy",
    "iso:country":"US",
    "sg:address":"400 E Lincoln Hwy",
    "sg:city":"New Lenox",
    "sg:classifiers":[
        {
            "category":"Professional",
            "subcategory":"Lawyer & Legal Services",
            "type":"Services"
        }
    ],
    "sg:phone":"+1 815 485 9300",
    "sg:postcode":"60451",
    "sg:province":"IL",
    "sg:tags":[
        "attorney"
    ],
    "wof:name":"Bruggeman Hurst & Assoc",
    "wof:placetype":"venue"
},
  "geometry": {"coordinates":[-87.957382,41.512295],"type":"Point"}
}