{
  "type": "Feature",
  "properties": {
    "iso:country":"US",
    "sg:address":"806 Manor Ct",
    "sg:city":"Joliet",
    "sg:classifiers":[
        {
            "category":"Retail",
            "subcategory":"Repair Shop",
            "type":"Services"
        }
    ],
    "sg:phone":"+1 815 735 1519",
    "sg:postcode":"60436",
    "sg:province":"IL",
    "sg:tags":[
        "upholsterer"
    ],
    "wof:name":"Scott's Upholstery",
    "wof:placetype":"venue"
},
  "geometry": {"coordinates":[-88.103786,41.520349],"type":"Point"}
}