{
  "type": "Feature",
  "properties": {
    "addr:full":"414 S Dilger Ave Waukegan IL 60085",
    "addr:housenumber":"414",
    "addr:postcode":"60085",
    "addr:street":"S Dilger Ave",
    "iso:country":"US",
    "sg:address":"414 S Dilger Ave",
    "sg:city":"Waukegan",
    "sg:classifiers":[
        {
            "category":"Organizations",
            "subcategory":"Religious Organization",
            "type":"Services"
        }
    ],
    "sg:phone":"+1 847 263 0462",
    "sg:postcode":"60085",
    "sg:province":"IL",
    "sg:tags":[
        "church"
    ],
    "wof:name":"Iglesia Christian Pacto Cncrst",
    "wof:placetype":"venue"
},
  "geometry": {"coordinates":[-87.87113600000001,42.353132],"type":"Point"}
}