{
  "type": "Feature",
  "properties": {
    "iso:country":"US",
    "sg:address":"3520 W Lawrence Ave",
    "sg:city":"Chicago",
    "sg:classifiers":[
        {
            "category":"Bakery",
            "type":"Food & Drink"
        }
    ],
    "sg:phone":"+1 773 539 9344",
    "sg:postcode":"60625",
    "sg:province":"IL",
    "wof:name":"Markellos Baking Co",
    "wof:placetype":"venue"
},
  "geometry": {"coordinates":[-87.716599,41.968399],"type":"Point"}
}