{
  "type": "Feature",
  "properties": {
    "iso:country":"US",
    "sg:address":"1944 Sybil Dr",
    "sg:city":"Crest Hill",
    "sg:classifiers":[
        {
            "category":"Shopping",
            "subcategory":"Gifts & Souvenirs",
            "type":"Retail Goods"
        }
    ],
    "sg:phone":"+1 815 207 4226",
    "sg:postcode":"60403",
    "sg:province":"IL",
    "sg:tags":[
        "shop"
    ],
    "wof:name":"Gifts By Maria",
    "wof:placetype":"venue"
},
  "geometry": {"coordinates":[-88.138253,41.556977],"type":"Point"}
}