{
  "type": "Feature",
  "properties": {
    "addr:full":"Steppenwolf Theatre 1650 N Halsted Chicago IL 60686",
    "addr:housenumber":"1650",
    "addr:postcode":"60686",
    "addr:street":"N Halsted",
    "iso:country":"US",
    "sg:address":"Steppenwolf Theatre 1650 N Halsted",
    "sg:city":"Chicago",
    "sg:classifiers":[
        {
            "category":"Arts & Performance",
            "subcategory":"Arts Center",
            "type":"Entertainment"
        }
    ],
    "sg:postcode":"60686",
    "sg:province":"IL",
    "sg:tags":[
        "performing"
    ],
    "sg:website":"www.steppenwolf.org/boxoffice/pr...",
    "wof:name":"The Nutcracker",
    "wof:placetype":"venue"
},
  "geometry": {"coordinates":[-87.64828199999999,41.911878],"type":"Point"}
}