{
  "type": "Feature",
  "properties": {
    "addr:full":"852 Sharp Dr Shorewood IL 60431",
    "addr:housenumber":"852",
    "addr:postcode":"60431",
    "addr:street":"Sharp Dr",
    "iso:country":"US",
    "sg:address":"852 Sharp Dr",
    "sg:city":"Shorewood",
    "sg:classifiers":[
        {
            "category":"Personal",
            "subcategory":"Beauty Salon",
            "type":"Services"
        }
    ],
    "sg:phone":"+1 815 725 3744",
    "sg:postcode":"60431",
    "sg:province":"IL",
    "wof:name":"Salon Idenity",
    "wof:placetype":"venue"
},
  "geometry": {"coordinates":[-88.19761099999999,41.535029],"type":"Point"}
}