{
  "type": "Feature",
  "properties": {
    "iso:country":"US",
    "sg:address":"852 Sharp Dr",
    "sg:city":"Shorewood",
    "sg:classifiers":[
        {
            "category":"Personal",
            "subcategory":"Beauty Salon",
            "type":"Services"
        }
    ],
    "sg:phone":"+1 815 725 3744",
    "sg:postcode":"60431",
    "sg:province":"IL",
    "wof:name":"Salon Idenity",
    "wof:placetype":"venue"
},
  "geometry": {"coordinates":[-88.197611,41.535029],"type":"Point"}
}