{
  "type": "Feature",
  "properties": {
    "addr:full":"901 Biesterfield Rd Elk Grove Village IL 60007",
    "addr:housenumber":"901",
    "addr:postcode":"60007",
    "addr:street":"Biesterfield Rd",
    "iso:country":"US",
    "sg:address":"901 Biesterfield Rd",
    "sg:city":"Elk Grove Village",
    "sg:classifiers":[
        {
            "category":"Health Services",
            "subcategory":"Doctor",
            "type":"Services"
        }
    ],
    "sg:phone":"+1 847 364 5188",
    "sg:postcode":"60007",
    "sg:province":"IL",
    "sg:tags":[
        "medical"
    ],
    "wof:name":"Khokha Salma",
    "wof:placetype":"venue"
},
  "geometry": {"coordinates":[-88.020071,42.003482],"type":"Point"}
}