{
  "type": "Feature",
  "properties": {
    "iso:country":"US",
    "sg:address":"715 S University Ave Ste 102",
    "sg:city":"Carbondale",
    "sg:classifiers":[
        {
            "category":"Arts & Performance",
            "subcategory":"Art Gallery",
            "type":"Entertainment"
        }
    ],
    "sg:phone":"+1 618 457 4743",
    "sg:postcode":"62901",
    "sg:province":"IL",
    "wof:name":"Associated Artist Gallery",
    "wof:placetype":"venue"
},
  "geometry": {"coordinates":[-89.21779600000001,37.720699],"type":"Point"}
}