{
  "type": "Feature",
  "properties": {
    "addr:full":"1325 N Old Rand Rd Wauconda IL 60084",
    "addr:housenumber":"1325",
    "addr:postcode":"60084",
    "addr:street":"N Old Rand Rd",
    "iso:country":"US",
    "sg:address":"1325 N Old Rand Rd",
    "sg:city":"Wauconda",
    "sg:classifiers":[
        {
            "category":"Manufacturing",
            "subcategory":"Chemicals & Compounds",
            "type":"Manufacturing & Wholesale Goods"
        }
    ],
    "sg:phone":"+1 847 487 2600",
    "sg:postcode":"60084",
    "sg:province":"IL",
    "sg:tags":[
        "preparation",
        "product",
        "plastic",
        "ink",
        "mfg"
    ],
    "wof:name":"Applegate Chemical Company",
    "wof:placetype":"venue"
},
  "geometry": {"coordinates":[-88.15153599999999,42.279534],"type":"Point"}
}