{
  "type": "Feature",
  "properties": {
    "addr:full":"480 Lakewood Blvd Park Forest IL 60466",
    "addr:housenumber":"480",
    "addr:postcode":"60466",
    "addr:street":"Lakewood;Park",
    "iso:country":"US",
    "sg:address":"480 Lakewood Blvd",
    "sg:city":"Park Forest",
    "sg:classifiers":[
        {
            "category":"Organizations",
            "subcategory":"Religious Organization",
            "type":"Services"
        }
    ],
    "sg:phone":"+1 708 748 5451",
    "sg:postcode":"60466",
    "sg:province":"IL",
    "wof:name":"St Pauls Good Shepherd United",
    "wof:placetype":"venue"
},
  "geometry": {"coordinates":[-87.690589,41.484811],"type":"Point"}
}