{
  "type": "Feature",
  "properties": {
    "iso:country":"US",
    "sg:address":"910 N 2nd St",
    "sg:city":"Swansea",
    "sg:classifiers":[
        {
            "category":"Building & Trades",
            "subcategory":"Construction",
            "type":"Services"
        }
    ],
    "sg:phone":"+1 618 939 5958",
    "sg:postcode":"62226",
    "sg:province":"IL",
    "sg:tags":[
        "roofing",
        "contractor"
    ],
    "wof:name":"P K Dependable Roofing",
    "wof:placetype":"venue"
},
  "geometry": {"coordinates":[-89.987927,38.52251],"type":"Point"}
}