{
  "type": "Feature",
  "properties": {
    "addr:full":"967 Waukegan Rd Glenview IL 60025",
    "addr:housenumber":"967",
    "addr:postcode":"60025",
    "addr:street":"Waukegan Rd",
    "iso:country":"US",
    "sg:address":"967 Waukegan Rd",
    "sg:city":"Glenview",
    "sg:classifiers":[
        {
            "category":"Ice Cream",
            "type":"Food & Drink"
        }
    ],
    "sg:menulink":"http://www.allmenus.com/il/northfield/153472-oberweis-dairy/menu/",
    "sg:phone":"+1 847 729 8700",
    "sg:postcode":"60025",
    "sg:province":"IL",
    "sg:tags":[
        "american"
    ],
    "wof:name":"Oberweis Dairy",
    "wof:placetype":"venue"
},
  "geometry": {"coordinates":[-87.799243,42.072011],"type":"Point"}
}