{
  "type": "Feature",
  "properties": {
    "addr:full":"3403 N Harlem Ave Chicago IL 60634",
    "addr:housenumber":"3403",
    "addr:postcode":"60634",
    "addr:street":"N Harlem Ave",
    "iso:country":"US",
    "sg:address":"3403 N Harlem Ave",
    "sg:city":"Chicago",
    "sg:classifiers":[
        {
            "category":"Communications",
            "subcategory":"Radio Station",
            "type":"Services"
        }
    ],
    "sg:phone":"+1 773 283 9276",
    "sg:postcode":"60634",
    "sg:province":"IL",
    "wof:name":"L'eco D'italia",
    "wof:placetype":"venue"
},
  "geometry": {"coordinates":[-87.8069,41.9417],"type":"Point"}
}