{
  "type": "Feature",
  "properties": {
    "iso:country":"US",
    "sg:address":"314 W State St",
    "sg:city":"Geneva",
    "sg:classifiers":[
        {
            "category":"Personal",
            "subcategory":"Beauty Salon",
            "type":"Services"
        }
    ],
    "sg:phone":"+1 630 208 7899",
    "sg:postcode":"60134",
    "sg:province":"IL",
    "sg:tags":[
        "hair",
        "stylist"
    ],
    "wof:name":"Cornerstone Hair Design Studio",
    "wof:placetype":"venue"
},
  "geometry": {"coordinates":[-88.308087,41.887948],"type":"Point"}
}