{
  "type": "Feature",
  "properties": {
    "iso:country":"US",
    "sg:address":"506 N Main St",
    "sg:city":"Carrollton",
    "sg:classifiers":[
        {
            "category":"Insurance",
            "subcategory":"Title Insurance",
            "type":"Services"
        },
        {
            "category":"Real Estate",
            "subcategory":"Real Estate Services",
            "type":"Services"
        }
    ],
    "sg:phone":"+1 217 942 3733",
    "sg:postcode":"62016",
    "sg:province":"IL",
    "sg:tags":[
        "company",
        "carrier"
    ],
    "wof:name":"O H Vivell Title Co Inc",
    "wof:placetype":"venue"
},
  "geometry": {"coordinates":[-90.408326,39.30222],"type":"Point"}
}