{
  "type": "Feature",
  "properties": {
    "addr:full":"751 N State St Elgin IL 60121",
    "addr:housenumber":"751",
    "addr:postcode":"60121",
    "addr:street":"N State St",
    "iso:country":"US",
    "sg:address":"751 N State St",
    "sg:city":"Elgin",
    "sg:classifiers":[
        {
            "category":"Fast Food",
            "type":"Food & Drink"
        },
        {
            "category":"Food & Beverages",
            "subcategory":"Bakery",
            "type":"Retail Goods"
        },
        {
            "category":"Food & Beverages",
            "subcategory":"Meat & Fish",
            "type":"Retail Goods"
        }
    ],
    "sg:phone":"+1 847 488 9988",
    "sg:postcode":"60121",
    "sg:province":"IL",
    "sg:tags":[
        "burger",
        "hot",
        "sandwich",
        "dog"
    ],
    "wof:name":"Swizzle Inn",
    "wof:placetype":"venue"
},
  "geometry": {"coordinates":[-88.29618600000001,42.051678],"type":"Point"}
}