{
  "type": "Feature",
  "properties": {
    "addr:full":"183 S Schmale Rd Carol Stream IL 60188",
    "addr:housenumber":"183",
    "addr:postcode":"60188",
    "addr:street":"S Schmale Rd",
    "iso:country":"US",
    "sg:address":"183 S Schmale Rd",
    "sg:city":"Carol Stream",
    "sg:classifiers":[
        {
            "category":"Professional",
            "subcategory":"Printing & Photocopies",
            "type":"Services"
        }
    ],
    "sg:phone":"+1 630 690 2700",
    "sg:postcode":"60188",
    "sg:province":"IL",
    "sg:website":"www.sirspeedy.com/Carolstream",
    "wof:name":"SIR Speedy Printing",
    "wof:placetype":"venue"
},
  "geometry": {"coordinates":[-88.101799,41.9002],"type":"Point"}
}