{
  "type": "Feature",
  "properties": {
    "iso:country":"US",
    "sg:address":"1955 Cherry Ln",
    "sg:city":"Northbrook",
    "sg:classifiers":[
        {
            "category":"Food & Beverages",
            "subcategory":"Bakery",
            "type":"Retail Goods"
        }
    ],
    "sg:phone":"+1   ",
    "sg:postcode":"60062",
    "sg:province":"IL",
    "wof:name":"Great Harvest Bread",
    "wof:placetype":"venue"
},
  "geometry": {"coordinates":[-87.82769500000001,42.131421],"type":"Point"}
}