{
  "type": "Feature",
  "properties": {
    "addr:full":"235 Centennial Dr Hainesville IL 60073",
    "addr:housenumber":"235",
    "addr:postcode":"60073",
    "addr:street":"Centennial Dr",
    "iso:country":"US",
    "sg:address":"235 Centennial Dr",
    "sg:city":"Hainesville",
    "sg:classifiers":[
        {
            "category":"Freight",
            "type":"Transportation"
        }
    ],
    "sg:phone":"+1 847 548 9436",
    "sg:postcode":"60073",
    "sg:province":"IL",
    "sg:tags":[
        "trucking"
    ],
    "wof:name":"RKI Transport Inc",
    "wof:placetype":"venue"
},
  "geometry": {"coordinates":[-88.068961,42.34866],"type":"Point"}
}