{
  "type": "Feature",
  "properties": {
    "iso:country":"US",
    "sg:address":"15 E 119th St",
    "sg:city":"Chicago",
    "sg:classifiers":[
        {
            "category":"Building & Trades",
            "subcategory":"Construction",
            "type":"Services"
        }
    ],
    "sg:phone":"+1 773 568 5747",
    "sg:postcode":"60628",
    "sg:province":"IL",
    "sg:tags":[
        "handyman"
    ],
    "wof:name":"Bumpy's Handyman Service Llc",
    "wof:placetype":"venue"
},
  "geometry": {"coordinates":[-87.622308,41.678139],"type":"Point"}
}