{
  "type": "Feature",
  "properties": {
    "addr:full":"168 N Ottawa St Joliet IL 60432",
    "addr:housenumber":"168",
    "addr:postcode":"60432",
    "addr:street":"N Ottawa St",
    "iso:country":"US",
    "sg:address":"168 N Ottawa St",
    "sg:city":"Joliet",
    "sg:classifiers":[
        {
            "category":"Professional",
            "subcategory":"Lawyer & Legal Services",
            "type":"Services"
        }
    ],
    "sg:phone":"+1 815 773 9040",
    "sg:postcode":"60432",
    "sg:province":"IL",
    "sg:tags":[
        "attorney"
    ],
    "wof:name":"K M Aeschliman LTD",
    "wof:placetype":"venue"
},
  "geometry": {"coordinates":[-88.08299,41.527465],"type":"Point"}
}