{
  "type": "Feature",
  "properties": {
    "iso:country":"US",
    "sg:address":"101 N Marion St",
    "sg:city":"Oak Park",
    "sg:classifiers":[
        {
            "category":"Health Services",
            "subcategory":"Clinic",
            "type":"Services"
        }
    ],
    "sg:phone":"+1 708 386 3681",
    "sg:postcode":"60301",
    "sg:province":"IL",
    "sg:tags":[
        "counseling",
        "mental"
    ],
    "wof:name":"Sherrell Kathleen",
    "wof:placetype":"venue"
},
  "geometry": {"coordinates":[-87.802498,41.888599],"type":"Point"}
}