{
  "type": "Feature",
  "properties": {
    "addr:full":"16539 Oak Park Ave Tinley Park IL 60477",
    "addr:housenumber":"16539",
    "addr:postcode":"60477",
    "addr:street":"Oak Park Ave",
    "iso:country":"US",
    "sg:address":"16539 Oak Park Ave",
    "sg:city":"Tinley Park",
    "sg:classifiers":[
        {
            "category":"Insurance",
            "subcategory":"Insurance Agent",
            "type":"Services"
        }
    ],
    "sg:phone":"+1 708 444 4100",
    "sg:postcode":"60477",
    "sg:province":"IL",
    "wof:name":"Donne Insurance Svc",
    "wof:placetype":"venue"
},
  "geometry": {"coordinates":[-87.784758,41.588876],"type":"Point"}
}