{
  "type": "Feature",
  "properties": {
    "iso:country":"US",
    "sg:address":"5800 Nursery Rd",
    "sg:city":"Albers",
    "sg:classifiers":[
        {
            "category":"Home & Garden",
            "subcategory":"Garden Supply",
            "type":"Retail Goods"
        }
    ],
    "sg:phone":"+1 618 248 5107",
    "sg:postcode":"62215",
    "sg:province":"IL",
    "sg:tags":[
        "nurseryman"
    ],
    "wof:name":"Home Nursery Albers Stock Shop",
    "wof:placetype":"venue"
},
  "geometry": {"coordinates":[-89.596874,38.509824],"type":"Point"}
}