{
  "type": "Feature",
  "properties": {
    "addr:full":"29007 73rd Ave N Hillsdale IL 61257",
    "addr:housenumber":"29007",
    "addr:postcode":"61257",
    "addr:street":"73Rd Ave N",
    "iso:country":"US",
    "sg:address":"29007 73rd Ave N",
    "sg:city":"Hillsdale",
    "sg:classifiers":[
        {
            "category":"Professional",
            "subcategory":"Management & Consulting",
            "type":"Services"
        }
    ],
    "sg:phone":"+1 309 658 2683",
    "sg:postcode":"61257",
    "sg:province":"IL",
    "sg:tags":[
        "farm"
    ],
    "wof:name":"Anthony Pollreisz",
    "wof:placetype":"venue"
},
  "geometry": {"coordinates":[-90.21661400000001,41.585419],"type":"Point"}
}