{
  "type": "Feature",
  "properties": {
    "iso:country":"US",
    "sg:address":"122 E Broadway",
    "sg:city":"Centralia",
    "sg:classifiers":[
        {
            "category":"Social Services",
            "type":"Services"
        }
    ],
    "sg:phone":"+1 618 533 1073",
    "sg:postcode":"62801",
    "sg:province":"IL",
    "sg:tags":[
        "senior",
        "citizen"
    ],
    "wof:name":"BCMW Project Bread Meal",
    "wof:placetype":"venue"
},
  "geometry": {"coordinates":[-89.13540399999999,38.527925],"type":"Point"}
}