{
  "type": "Feature",
  "properties": {
    "iso:country":"US",
    "sg:address":"11107 S Western Ave",
    "sg:city":"Chicago",
    "sg:classifiers":[
        {
            "category":"Arena",
            "subcategory":"Sports Club",
            "type":"Entertainment"
        }
    ],
    "sg:phone":"+1 773 629 6297",
    "sg:postcode":"60643",
    "sg:province":"IL",
    "sg:tags":[
        "martial art"
    ],
    "wof:name":"Tsai Kung Fu International",
    "wof:placetype":"venue"
},
  "geometry": {"coordinates":[-87.680899,41.691621],"type":"Point"}
}