{
  "type": "Feature",
  "properties": {
    "addr:full":"27 E Monroe St Ste 900 Chicago IL 60603",
    "addr:housenumber":"27",
    "addr:postcode":"60603",
    "addr:street":"E Monroe St Ste 900",
    "iso:country":"US",
    "sg:address":"27 E Monroe St Ste 900",
    "sg:city":"Chicago",
    "sg:classifiers":[
        {
            "category":"Professional",
            "subcategory":"Employment Agencies",
            "type":"Services"
        },
        {
            "category":"Organizations",
            "subcategory":"Community Association",
            "type":"Services"
        }
    ],
    "sg:phone":"+1 312 782 9160",
    "sg:postcode":"60603",
    "sg:province":"IL",
    "sg:tags":[
        "employer"
    ],
    "wof:name":"Chicago Loop Alliance",
    "wof:placetype":"venue"
},
  "geometry": {"coordinates":[-87.626875,41.880771],"type":"Point"}
}