{
  "type": "Feature",
  "properties": {
    "addr:full":"2333 N Harlem Ave Chicago IL 60707",
    "addr:housenumber":"2333",
    "addr:postcode":"60707",
    "addr:street":"N Harlem Ave",
    "iso:country":"US",
    "sg:address":"2333 N Harlem Ave",
    "sg:city":"Chicago",
    "sg:classifiers":[
        {
            "category":"Health Services",
            "subcategory":"Hospital",
            "type":"Services"
        }
    ],
    "sg:phone":"+1 773 637 2333",
    "sg:postcode":"60707",
    "sg:province":"IL",
    "wof:name":"Elmwood Park Immediate Health Care",
    "wof:placetype":"venue"
},
  "geometry": {"coordinates":[-87.80619799999999,41.922798],"type":"Point"}
}