{
  "type": "Feature",
  "properties": {
    "iso:country":"US",
    "sg:address":"2909 71st St",
    "sg:city":"Woodridge",
    "sg:classifiers":[
        {
            "category":"Building & Trades",
            "subcategory":"Electrical",
            "type":"Services"
        }
    ],
    "sg:phone":"+1 708 594 3636",
    "sg:postcode":"60517",
    "sg:province":"IL",
    "sg:tags":[
        "electrical",
        "contractor"
    ],
    "wof:name":"Grand Electric Company",
    "wof:placetype":"venue"
},
  "geometry": {"coordinates":[-88.051185,41.756648],"type":"Point"}
}