{
  "type": "Feature",
  "properties": {
    "iso:country":"US",
    "sg:address":"2052 Deland Monticello Rd",
    "sg:city":"De Land",
    "sg:phone":"+1 217 664 3614",
    "sg:postcode":"61856",
    "sg:province":"IL",
    "sg:tags":[
        "farm",
        "corn",
        "soybean"
    ],
    "wof:name":"Olsons Farms",
    "wof:placetype":"venue"
},
  "geometry": {"coordinates":[-88.626745,40.08415],"type":"Point"}
}