{
  "type": "Feature",
  "properties": {
    "iso:country":"US",
    "sg:address":"1026 Maple Ave",
    "sg:city":"Downers Grove",
    "sg:classifiers":[
        {
            "category":"Recreation",
            "type":"Entertainment"
        }
    ],
    "sg:phone":"+1 630 663 1945",
    "sg:postcode":"60515",
    "sg:province":"IL",
    "wof:name":"Ahns Academy of Tae Kwon Do",
    "wof:placetype":"venue"
},
  "geometry": {"coordinates":[-88.0115,41.790905],"type":"Point"}
}