{
  "type": "Feature",
  "properties": {
    "iso:country":"US",
    "sg:address":"360 W Rosalie Ln",
    "sg:city":"Palatine",
    "sg:classifiers":[
        {
            "category":"Manufacturing",
            "subcategory":"Printing",
            "type":"Manufacturing & Wholesale Goods"
        }
    ],
    "sg:phone":"+1 847 358 1342",
    "sg:postcode":"60074",
    "sg:province":"IL",
    "sg:tags":[
        "book"
    ],
    "wof:name":"Ray B Countryman",
    "wof:placetype":"venue"
},
  "geometry": {"coordinates":[-88.051136,42.153307],"type":"Point"}
}