{
  "type": "Feature",
  "properties": {
    "iso:country":"US",
    "sg:address":"735 Elm St",
    "sg:city":"Winnetka",
    "sg:classifiers":[
        {
            "category":"Food & Beverages",
            "subcategory":"Ethnic Foods",
            "type":"Retail Goods"
        }
    ],
    "sg:phone":"+1 847 441 7664",
    "sg:postcode":"60093",
    "sg:province":"IL",
    "sg:tags":[
        "grocers-ethnic"
    ],
    "wof:name":"Song O' Sixpence",
    "wof:placetype":"venue"
},
  "geometry": {"coordinates":[-87.732135,42.105901],"type":"Point"}
}