{
  "type": "Feature",
  "properties": {
    "addr:full":"403 N Main St Decatur IL 62523",
    "addr:housenumber":"403",
    "addr:postcode":"62523",
    "addr:street":"N Main St",
    "iso:country":"US",
    "sg:address":"403 N Main St",
    "sg:city":"Decatur",
    "sg:classifiers":[
        {
            "category":"Professional",
            "subcategory":"Management & Consulting",
            "type":"Services"
        },
        {
            "category":"Professional",
            "subcategory":"Business Services",
            "type":"Services"
        }
    ],
    "sg:phone":"+1 217 233 3391",
    "sg:postcode":"62523",
    "sg:province":"IL",
    "sg:tags":[
        "consultant",
        "coach"
    ],
    "wof:name":"C Deadrick Development",
    "wof:placetype":"venue"
},
  "geometry": {"coordinates":[-88.951859,39.841508],"type":"Point"}
}