{
  "type": "Feature",
  "properties": {
    "iso:country":"US",
    "sg:address":"217 S Main St",
    "sg:city":"Columbia",
    "sg:classifiers":[
        {
            "category":"Professional",
            "subcategory":"Lawyer & Legal Services",
            "type":"Services"
        }
    ],
    "sg:phone":"+1 618 281 7614",
    "sg:postcode":"62236",
    "sg:province":"IL",
    "sg:tags":[
        "attorney"
    ],
    "wof:name":"Traughber & Morris LTD",
    "wof:placetype":"venue"
},
  "geometry": {"coordinates":[-90.197464,38.441869],"type":"Point"}
}