{
  "type": "Feature",
  "properties": {
    "iso:country":"US",
    "sg:address":"1106 N Main St",
    "sg:city":"Kewanee",
    "sg:classifiers":[
        {
            "category":"Freight",
            "type":"Transportation"
        }
    ],
    "sg:phone":"+1 309 856 5656",
    "sg:postcode":"61443",
    "sg:province":"IL",
    "sg:tags":[
        "commercial",
        "storage",
        "general"
    ],
    "wof:name":"A-1 Mini Storage",
    "wof:placetype":"venue"
},
  "geometry": {"coordinates":[-89.924708,41.25411],"type":"Point"}
}