{
  "type": "Feature",
  "properties": {
    "addr:full":"7519 S Cicero Avenue Chicago IL 60652",
    "addr:housenumber":"7519",
    "addr:postcode":"60652",
    "addr:street":"S Cicero Avenue",
    "iso:country":"US",
    "sg:address":"7519 S Cicero Avenue",
    "sg:city":"Chicago",
    "sg:classifiers":[
        {
            "category":"Restaurant",
            "type":"Food & Drink"
        }
    ],
    "sg:phone":"+1 773 767 0711",
    "sg:postcode":"60652",
    "sg:province":"IL",
    "wof:name":"Applebee's Neighborhood Grill & Bar",
    "wof:placetype":"venue"
},
  "geometry": {"coordinates":[-87.74162099999999,41.756372],"type":"Point"}
}