{
  "type": "Feature",
  "properties": {
    "addr:full":"900 N Franklin St Ste 407 Chicago IL 60610",
    "addr:housenumber":"900",
    "addr:postcode":"60610",
    "addr:street":"N Franklin St Ste 407",
    "iso:country":"US",
    "sg:address":"900 N Franklin St Ste 407",
    "sg:city":"Chicago",
    "sg:classifiers":[
        {
            "category":"Community Center",
            "subcategory":"Social",
            "type":"Public Place"
        },
        {
            "category":"Organizations",
            "subcategory":"Professional Association",
            "type":"Services"
        }
    ],
    "sg:phone":"+1 312 664 0900",
    "sg:postcode":"60610",
    "sg:province":"IL",
    "sg:tags":[
        "club",
        "bridge",
        "instruction"
    ],
    "sg:website":"www.chicagobridgecenter.com",
    "wof:name":"The Chicago Bridge Center",
    "wof:placetype":"venue"
},
  "geometry": {"coordinates":[-87.636101,41.899228],"type":"Point"}
}