{
  "type": "Feature",
  "properties": {
    "addr:full":"121 W Main St West Dundee IL 60118",
    "addr:housenumber":"121",
    "addr:postcode":"60118",
    "addr:street":"W Main St",
    "iso:country":"US",
    "sg:address":"121 W Main St",
    "sg:city":"West Dundee",
    "sg:classifiers":[
        {
            "category":"Travel",
            "subcategory":"Travel Agent",
            "type":"Entertainment"
        }
    ],
    "sg:phone":"+1 630 792 1271",
    "sg:postcode":"60118",
    "sg:province":"IL",
    "sg:website":"www.honeymoonshowcase.com",
    "wof:name":"Honeymoon Travel & Cruise Center",
    "wof:placetype":"venue"
},
  "geometry": {"coordinates":[-88.278192,42.098066],"type":"Point"}
}