{
  "type": "Feature",
  "properties": {
    "iso:country":"US",
    "sg:address":"2825 W Devon Ave",
    "sg:city":"Chicago",
    "sg:classifiers":[
        {
            "category":"Shopping",
            "subcategory":"Pharmacy",
            "type":"Retail Goods"
        }
    ],
    "sg:phone":"+1   ",
    "sg:postcode":"60659",
    "sg:province":"IL",
    "wof:name":"Osco Drug 5637",
    "wof:placetype":"venue"
},
  "geometry": {"coordinates":[-87.70007099999999,41.99748],"type":"Point"}
}