{
  "type": "Feature",
  "properties": {
    "addr:full":"6535 N Maplewood Ave Chicago IL 60645",
    "addr:housenumber":"6535",
    "addr:postcode":"60645",
    "addr:street":"N Maplewood Ave",
    "iso:country":"US",
    "sg:address":"6535 N Maplewood Ave",
    "sg:city":"Chicago",
    "sg:classifiers":[
        {
            "category":"Shopping",
            "subcategory":"Gifts & Souvenirs",
            "type":"Retail Goods"
        }
    ],
    "sg:phone":"+1   ",
    "sg:postcode":"60645",
    "sg:province":"IL",
    "wof:name":"Mayet Beads & Buttons",
    "wof:placetype":"venue"
},
  "geometry": {"coordinates":[-87.693549,42.000673],"type":"Point"}
}