{
  "type": "Feature",
  "properties": {
    "iso:country":"US",
    "sg:address":"4904 W 29th Pl",
    "sg:city":"Cicero",
    "sg:classifiers":[
        {
            "category":"Organizations",
            "subcategory":"Religious Organization",
            "type":"Services"
        }
    ],
    "sg:phone":"+1 708 656 8443",
    "sg:postcode":"60804",
    "sg:province":"IL",
    "wof:name":"Jesus J Calderon",
    "wof:placetype":"venue"
},
  "geometry": {"coordinates":[-87.748751,41.839414],"type":"Point"}
}