{
  "type": "Feature",
  "properties": {
    "iso:country":"US",
    "sg:address":"2695 Stonegate Turn",
    "sg:city":"Kankakee",
    "sg:classifiers":[
        {
            "category":"Home & Garden",
            "subcategory":"Carpets & Floor Coverings",
            "type":"Retail Goods"
        }
    ],
    "sg:phone":"+1   ",
    "sg:postcode":"60901",
    "sg:province":"IL",
    "wof:name":"Soft & Safe Floors",
    "wof:placetype":"venue"
},
  "geometry": {"coordinates":[-87.926737,41.146017],"type":"Point"}
}