{
  "type": "Feature",
  "properties": {
    "iso:country":"US",
    "sg:address":"2000 Mall St",
    "sg:city":"Collinsville",
    "sg:classifiers":[
        {
            "category":"Banks & Credit Unions",
            "subcategory":"Bank",
            "type":"Services"
        }
    ],
    "sg:phone":"+1 618 344 0092",
    "sg:postcode":"62234",
    "sg:province":"IL",
    "sg:tags":[
        "federal",
        "state"
    ],
    "wof:name":"Electrical Worker's Credit Union",
    "wof:placetype":"venue"
},
  "geometry": {"coordinates":[-90.013496,38.672699],"type":"Point"}
}