{
  "type": "Feature",
  "properties": {
    "addr:full":"24637 Esmond Rd Malta IL 60150",
    "addr:postcode":"24637;60150",
    "addr:street":"Esmond Rd",
    "iso:country":"US",
    "sg:address":"24637 Esmond Rd",
    "sg:city":"Malta",
    "sg:classifiers":[
        {
            "category":"Home & Garden",
            "subcategory":"Garden Supply",
            "type":"Retail Goods"
        }
    ],
    "sg:phone":"+1 815 393 4593",
    "sg:postcode":"60150",
    "sg:province":"IL",
    "sg:tags":[
        "embroidery"
    ],
    "sg:website":"http://www.beedesigns.biz",
    "wof:name":"Bee Designs Embroidery & Scree",
    "wof:placetype":"venue"
},
  "geometry": {"coordinates":[-88.93662999999999,41.988237],"type":"Point"}
}