{
  "type": "Feature",
  "properties": {
    "iso:country":"US",
    "sg:address":"2101 Ballard Rd",
    "sg:city":"Des Plaines",
    "sg:classifiers":[
        {
            "category":"Government",
            "subcategory":"Office",
            "type":"Public Place"
        }
    ],
    "sg:phone":"+1 847 827 1164",
    "sg:postcode":"60016",
    "sg:province":"IL",
    "wof:name":"Cook County Hwy Maintenance",
    "wof:placetype":"venue"
},
  "geometry": {"coordinates":[-87.87271800000001,42.043986],"type":"Point"}
}