{
  "type": "Feature",
  "properties": {
    "iso:country":"US",
    "sg:address":"1030 N State St",
    "sg:city":"Chicago",
    "sg:classifiers":[
        {
            "category":"Bars & Pubs",
            "subcategory":"Lounge",
            "type":"Food & Drink"
        },
        {
            "category":"Restaurant",
            "type":"Food & Drink"
        }
    ],
    "sg:phone":"+1 312 642 6500",
    "sg:postcode":"60610",
    "sg:province":"IL",
    "sg:tags":[
        "hawaiian"
    ],
    "sg:website":"www.tradervicschicago.com",
    "wof:name":"Trader Vic's",
    "wof:placetype":"venue"
},
  "geometry": {"coordinates":[-87.628767,41.901611],"type":"Point"}
}