{
  "type": "Feature",
  "properties": {
    "iso:country":"US",
    "sg:address":"2551 N Clark St Suite 205",
    "sg:city":"Chicago",
    "sg:classifiers":[
        {
            "category":"Personal",
            "subcategory":"Beauty Salon",
            "type":"Services"
        }
    ],
    "sg:phone":"+1 773 248 2175",
    "sg:postcode":"60614",
    "sg:province":"IL",
    "sg:tags":[
        "hair"
    ],
    "sg:website":"www.sarahsstudiosalon.com",
    "wof:name":"Sarah's Studio Salon",
    "wof:placetype":"venue"
},
  "geometry": {"coordinates":[-87.64258599999999,41.929115],"type":"Point"}
}