{
  "type": "Feature",
  "properties": {
    "addr:full":"3508 Walkup Rd Crystal Lake IL 60012",
    "addr:housenumber":"3508",
    "addr:postcode":"60012",
    "addr:street":"Walkup Rd",
    "iso:country":"US",
    "sg:address":"3508 Walkup Rd",
    "sg:city":"Crystal Lake",
    "sg:classifiers":[
        {
            "category":"Building & Trades",
            "subcategory":"Construction",
            "type":"Services"
        }
    ],
    "sg:phone":"+1 815 356 6505",
    "sg:postcode":"60012",
    "sg:province":"IL",
    "sg:tags":[
        "concrete",
        "contractor"
    ],
    "wof:name":"F B Industries",
    "wof:placetype":"venue"
},
  "geometry": {"coordinates":[-88.32078799999999,42.27671],"type":"Point"}
}