{
  "type": "Feature",
  "properties": {
    "iso:country":"US",
    "sg:address":"2650 N Milwaukee Ave",
    "sg:city":"Chicago",
    "sg:classifiers":[
        {
            "category":"Shopping",
            "subcategory":"Clothing, Apparel, & Fashions",
            "type":"Retail Goods"
        }
    ],
    "sg:phone":"+1 773 252 5631",
    "sg:postcode":"60647",
    "sg:province":"IL",
    "sg:tags":[
        "accessory",
        "clothing",
        "women's"
    ],
    "wof:name":"Seven Days Fashion",
    "wof:placetype":"venue"
},
  "geometry": {"coordinates":[-87.70929700000001,41.930401],"type":"Point"}
}