{
  "type": "Feature",
  "properties": {
    "iso:country":"US",
    "sg:address":"340 W 113th St",
    "sg:city":"Chicago",
    "sg:classifiers":[
        {
            "category":"Professional",
            "type":"Services"
        }
    ],
    "sg:phone":"+1 773 785 2000",
    "sg:postcode":"60628",
    "sg:province":"IL",
    "sg:tags":[
        "caterer"
    ],
    "wof:name":"Sisters' Exotic",
    "wof:placetype":"venue"
},
  "geometry": {"coordinates":[-87.631511,41.688993],"type":"Point"}
}