{
  "type": "Feature",
  "properties": {
    "iso:country":"US",
    "sg:address":"630 E Springfield Rd",
    "sg:city":"Arcola",
    "sg:phone":"+1 217 268 4714",
    "sg:postcode":"61910",
    "sg:province":"IL",
    "sg:tags":[
        "oil"
    ],
    "wof:name":"Niebrugge Oil Co",
    "wof:placetype":"venue"
},
  "geometry": {"coordinates":[-88.29680399999999,39.680957],"type":"Point"}
}