{
  "type": "Feature",
  "properties": {
    "addr:full":"1981 Church St Hamilton IL 62341",
    "addr:housenumber":"1981",
    "addr:postcode":"62341",
    "addr:street":"Church St",
    "iso:country":"US",
    "sg:address":"1981 Church St",
    "sg:city":"Hamilton",
    "sg:classifiers":[
        {
            "category":"Professional",
            "subcategory":"Computer Services",
            "type":"Services"
        }
    ],
    "sg:phone":"+1 217 847 2435",
    "sg:postcode":"62341",
    "sg:province":"IL",
    "wof:name":"Grasshopper Computer Services",
    "wof:placetype":"venue"
},
  "geometry": {"coordinates":[-91.327924,40.39819],"type":"Point"}
}