{
  "type": "Feature",
  "properties": {
    "addr:full":"724 E State Rte 15 Mount Vernon IL 62864",
    "addr:housenumber":"724;15",
    "addr:postcode":"62864",
    "addr:street":"E State Rte",
    "iso:country":"US",
    "sg:address":"724 E State Rte 15",
    "sg:city":"Mount Vernon",
    "sg:classifiers":[
        {
            "category":"Real Estate",
            "subcategory":"Real Estate Operator",
            "type":"Services"
        }
    ],
    "sg:phone":"+1 618 244 7012",
    "sg:postcode":"62864",
    "sg:province":"IL",
    "sg:tags":[
        "property",
        "lessor"
    ],
    "wof:name":"Vance Rental Properties",
    "wof:placetype":"venue"
},
  "geometry": {"coordinates":[-88.89945400000001,38.317282],"type":"Point"}
}