{
  "type": "Feature",
  "properties": {
    "addr:full":"510 Whitehall Way Bolingbrook IL 60440",
    "addr:housenumber":"510",
    "addr:postcode":"60440",
    "addr:street":"Whitehall Way",
    "iso:country":"US",
    "sg:address":"510 Whitehall Way",
    "sg:city":"Bolingbrook",
    "sg:classifiers":[
        {
            "category":"Professional",
            "type":"Services"
        }
    ],
    "sg:phone":"+1 630 985 9654",
    "sg:postcode":"60440",
    "sg:province":"IL",
    "sg:tags":[
        "establishment"
    ],
    "wof:name":"Allert Enterprise Inc",
    "wof:placetype":"venue"
},
  "geometry": {"coordinates":[-88.048873,41.731783],"type":"Point"}
}