{
  "type": "Feature",
  "properties": {
    "addr:full":"960 E Northwest Hwy Mount Prospect IL 60056",
    "addr:housenumber":"960",
    "addr:postcode":"60056",
    "addr:street":"E Northwest Hwy",
    "iso:country":"US",
    "sg:address":"960 E Northwest Hwy",
    "sg:city":"Mount Prospect",
    "sg:classifiers":[
        {
            "category":"Shopping",
            "subcategory":"Computers & Home Electronics",
            "type":"Retail Goods"
        }
    ],
    "sg:phone":"+1   ",
    "sg:postcode":"60056",
    "sg:province":"IL",
    "wof:name":"Pro Mix Karaoke",
    "wof:placetype":"venue"
},
  "geometry": {"coordinates":[-87.923799,42.057877],"type":"Point"}
}