{
  "type": "Feature",
  "properties": {
    "addr:full":"925 W Belmont Ave Chicago IL 60657",
    "addr:housenumber":"925",
    "addr:postcode":"60657",
    "addr:street":"W Belmont Ave",
    "iso:country":"US",
    "sg:address":"925 W Belmont Ave",
    "sg:city":"Chicago",
    "sg:classifiers":[
        {
            "category":"Home & Garden",
            "subcategory":"Home Furnishings",
            "type":"Retail Goods"
        }
    ],
    "sg:phone":"+1 773 871 5827",
    "sg:postcode":"60657",
    "sg:province":"IL",
    "sg:tags":[
        "decor"
    ],
    "sg:website":"www.beyondthewall.com",
    "wof:name":"Beyond the Wall",
    "wof:placetype":"venue"
},
  "geometry": {"coordinates":[-87.65227,41.939708],"type":"Point"}
}