{
  "type": "Feature",
  "properties": {
    "addr:full":"9634 S Roberts Rd Hickory Hills IL 60457",
    "addr:housenumber":"9634",
    "addr:postcode":"60457",
    "addr:street":"S Roberts Rd",
    "iso:country":"US",
    "sg:address":"9634 S Roberts Rd",
    "sg:city":"Hickory Hills",
    "sg:classifiers":[
        {
            "category":"Education",
            "subcategory":"University",
            "type":"Public Place"
        }
    ],
    "sg:phone":"+1 708 233 9768",
    "sg:postcode":"60457",
    "sg:province":"IL",
    "sg:tags":[
        "college"
    ],
    "wof:name":"Lewis University",
    "wof:placetype":"venue"
},
  "geometry": {"coordinates":[-87.817823,41.71644],"type":"Point"}
}