{
  "type": "Feature",
  "properties": {
    "addr:full":"114 N Chestnut St Kewanee IL 61443",
    "addr:housenumber":"114",
    "addr:postcode":"61443",
    "addr:street":"N Chestnut St",
    "iso:country":"US",
    "sg:address":"114 N Chestnut St",
    "sg:city":"Kewanee",
    "sg:classifiers":[
        {
            "category":"Home & Garden",
            "subcategory":"Household Appliances",
            "type":"Retail Goods"
        }
    ],
    "sg:phone":"+1 309 856 5417",
    "sg:postcode":"61443",
    "sg:province":"IL",
    "wof:name":"Johnson Appliance & Cabinets",
    "wof:placetype":"venue"
},
  "geometry": {"coordinates":[-89.927735,41.244362],"type":"Point"}
}