{
  "type": "Feature",
  "properties": {
    "addr:full":"1480 Renaissance Dr Park Ridge IL 60068",
    "addr:housenumber":"1480",
    "addr:postcode":"60068",
    "addr:street":"Renaissance Dr",
    "iso:country":"US",
    "sg:address":"1480 Renaissance Dr",
    "sg:city":"Park Ridge",
    "sg:classifiers":[
        {
            "category":"Wholesale",
            "subcategory":"Meat",
            "type":"Manufacturing & Wholesale Goods"
        }
    ],
    "sg:phone":"+1 847 297 4642",
    "sg:postcode":"60068",
    "sg:province":"IL",
    "wof:name":"Chicagolnd FDS Mltry Cnsrtm",
    "wof:placetype":"venue"
},
  "geometry": {"coordinates":[-87.864605,42.033119],"type":"Point"}
}