{
  "type": "Feature",
  "properties": {
    "iso:country":"US",
    "sg:address":"807 Progressive Ln",
    "sg:city":"South Beloit",
    "sg:classifiers":[
        {
            "category":"Personal",
            "type":"Services"
        }
    ],
    "sg:phone":"+1 815 624 7663",
    "sg:postcode":"61080",
    "sg:province":"WI",
    "sg:tags":[
        "consultant",
        "program",
        "health",
        "fitness"
    ],
    "wof:name":"Fitness Zone",
    "wof:placetype":"venue"
},
  "geometry": {"coordinates":[-89.05701,42.469586],"type":"Point"}
}