{
  "type": "Feature",
  "properties": {
    "iso:country":"US",
    "sg:address":"1840 Industrial Dr",
    "sg:city":"Libertyville",
    "sg:classifiers":[
        {
            "category":"Shopping",
            "subcategory":"Catalog Store",
            "type":"Retail Goods"
        }
    ],
    "sg:phone":"+1   ",
    "sg:postcode":"60048",
    "sg:province":"IL",
    "sg:tags":[
        "mail",
        "house"
    ],
    "wof:name":"Vettehead Products",
    "wof:placetype":"venue"
},
  "geometry": {"coordinates":[-88.007251,42.307715],"type":"Point"}
}