{
  "type": "Feature",
  "properties": {
    "iso:country":"US",
    "sg:address":"900 W Foster Ave",
    "sg:city":"Chicago",
    "sg:classifiers":[
        {
            "category":"Shopping",
            "subcategory":"Bicycles & Sporting Goods",
            "type":"Retail Goods"
        }
    ],
    "sg:phone":"+1   ",
    "sg:postcode":"60640",
    "sg:province":"IL",
    "sg:tags":[
        "equipment",
        "tennis"
    ],
    "wof:name":"Scotts Tennis Enterprises",
    "wof:placetype":"venue"
},
  "geometry": {"coordinates":[-87.653675,41.976494],"type":"Point"}
}