{
  "type": "Feature",
  "properties": {
    "addr:full":"3859 Birchwood Ave Skokie IL 60076",
    "addr:housenumber":"3859",
    "addr:postcode":"60076",
    "addr:street":"Birchwood Ave",
    "iso:country":"US",
    "sg:address":"3859 Birchwood Ave",
    "sg:city":"Skokie",
    "sg:classifiers":[
        {
            "category":"Building & Trades",
            "subcategory":"Plumbing",
            "type":"Services"
        }
    ],
    "sg:phone":"+1 847 675 1304",
    "sg:postcode":"60076",
    "sg:province":"IL",
    "sg:tags":[
        "contractor"
    ],
    "wof:name":"AAA Air Control",
    "wof:placetype":"venue"
},
  "geometry": {"coordinates":[-87.72413400000001,42.017127],"type":"Point"}
}