{
  "type": "Feature",
  "properties": {
    "addr:full":"4190 S Pleasant Hill Rd Elizabeth IL 61028",
    "addr:housenumber":"4190",
    "addr:postcode":"61028",
    "addr:street":"S Pleasant Hill Rd",
    "iso:country":"US",
    "sg:address":"4190 S Pleasant Hill Rd",
    "sg:city":"Elizabeth",
    "sg:phone":"+1 815 858 3858",
    "sg:postcode":"61028",
    "sg:province":"IL",
    "sg:tags":[
        "farm",
        "field",
        "corn",
        "crop"
    ],
    "wof:name":"Keith Morehardt",
    "wof:placetype":"venue"
},
  "geometry": {"coordinates":[-90.22802,42.310411],"type":"Point"}
}