{
  "type": "Feature",
  "properties": {
    "iso:country":"US",
    "sg:address":"447 W Liberty St",
    "sg:city":"Wauconda",
    "sg:classifiers":[
        {
            "category":"Personal",
            "subcategory":"Beauty Salon",
            "type":"Services"
        }
    ],
    "sg:phone":"+1 847 487 8823",
    "sg:postcode":"60084",
    "sg:province":"IL",
    "wof:name":"Fashion & Style Hair Salon",
    "wof:placetype":"venue"
},
  "geometry": {"coordinates":[-88.147159,42.256827],"type":"Point"}
}