{
  "type": "Feature",
  "properties": {
    "iso:country":"US",
    "sg:address":"6615 W Roosevelt Rd",
    "sg:city":"Berwyn",
    "sg:classifiers":[
        {
            "category":"Education",
            "subcategory":"Music School",
            "type":"Public Place"
        }
    ],
    "sg:phone":"+1 708 903 4859",
    "sg:postcode":"60304",
    "sg:province":"IL",
    "sg:tags":[
        "instrument",
        "teacher",
        "musical"
    ],
    "sg:website":"www.goguitarplay.com",
    "wof:name":"Marshall Guitar Studios",
    "wof:placetype":"venue"
},
  "geometry": {"coordinates":[-87.789681,41.865232],"type":"Point"}
}