{
  "type": "Feature",
  "properties": {
    "addr:full":"804 Madelyn Ave Macomb IL 61455",
    "addr:housenumber":"804",
    "addr:postcode":"61455",
    "addr:street":"Madelyn Ave",
    "iso:country":"US",
    "sg:address":"804 Madelyn Ave",
    "sg:city":"Macomb",
    "sg:classifiers":[
        {
            "category":"Banks & Credit Unions",
            "subcategory":"Bank",
            "type":"Services"
        }
    ],
    "sg:phone":"+1 309 836 6932",
    "sg:postcode":"61455",
    "sg:province":"IL",
    "sg:tags":[
        "loan",
        "broker"
    ],
    "wof:name":"Bouslog Nye Agency",
    "wof:placetype":"venue"
},
  "geometry": {"coordinates":[-90.662994,40.450159],"type":"Point"}
}