{
  "type": "Feature",
  "properties": {
    "iso:country":"US",
    "sg:address":"2201 5th Ave",
    "sg:city":"Rock Island",
    "sg:classifiers":[
        {
            "category":"Social Services",
            "subcategory":"Child Care",
            "type":"Services"
        }
    ],
    "sg:phone":"+1 309 788 8843",
    "sg:postcode":"61201",
    "sg:province":"IL",
    "wof:name":"Jordan Day Care",
    "wof:placetype":"venue"
},
  "geometry": {"coordinates":[-90.567781,41.507835],"type":"Point"}
}