{
  "type": "Feature",
  "properties": {
    "iso:country":"US",
    "sg:address":"405 Jefferson St",
    "sg:city":"Walnut Hill",
    "sg:classifiers":[
        {
            "category":"Utilities",
            "subcategory":"Refuse",
            "type":"Services"
        }
    ],
    "sg:phone":"+1 618 533 5080",
    "sg:postcode":"62893",
    "sg:province":"IL",
    "sg:tags":[
        "garbage",
        "collection"
    ],
    "wof:name":"Southern Illinois Waste",
    "wof:placetype":"venue"
},
  "geometry": {"coordinates":[-89.04383,38.476862],"type":"Point"}
}