{
  "type": "Feature",
  "properties": {
    "addr:full":"1114 W Armory Ave Champaign IL 61821",
    "addr:housenumber":"1114",
    "addr:postcode":"61821",
    "addr:street":"W Armory Ave",
    "iso:country":"US",
    "sg:address":"1114 W Armory Ave",
    "sg:city":"Champaign",
    "sg:classifiers":[
        {
            "category":"Real Estate",
            "subcategory":"Real Estate Agent",
            "type":"Services"
        }
    ],
    "sg:phone":"+1 217 359 2117",
    "sg:postcode":"61821",
    "sg:province":"IL",
    "wof:name":"Donald Dodds Real Estate",
    "wof:placetype":"venue"
},
  "geometry": {"coordinates":[-88.264605,40.105536],"type":"Point"}
}