{
  "type": "Feature",
  "properties": {
    "addr:full":"101 Bonnie Ct Thornton IL 60476",
    "addr:housenumber":"101",
    "addr:postcode":"60476",
    "addr:street":"Bonnie Ct",
    "iso:country":"US",
    "sg:address":"101 Bonnie Ct",
    "sg:city":"Thornton",
    "sg:classifiers":[
        {
            "category":"Professional",
            "subcategory":"Computer Services",
            "type":"Services"
        }
    ],
    "sg:phone":"+1 708 877 1097",
    "sg:postcode":"60476",
    "sg:province":"IL",
    "sg:tags":[
        "processing",
        "datum"
    ],
    "wof:name":"Atkinson Consultants",
    "wof:placetype":"venue"
},
  "geometry": {"coordinates":[-87.611526,41.577839],"type":"Point"}
}