{
  "type": "Feature",
  "properties": {
    "addr:full":"3616 N Pulaski Rd Chicago IL 60641",
    "addr:housenumber":"3616",
    "addr:postcode":"60641",
    "addr:street":"N Pulaski Rd",
    "iso:country":"US",
    "sg:address":"3616 N Pulaski Rd",
    "sg:city":"Chicago",
    "sg:classifiers":[
        {
            "category":"Government",
            "subcategory":"Office",
            "type":"Public Place"
        }
    ],
    "sg:phone":"+1   ",
    "sg:postcode":"60641",
    "sg:province":"IL",
    "sg:tags":[
        "city"
    ],
    "wof:name":"30th Ward Office",
    "wof:placetype":"venue"
},
  "geometry": {"coordinates":[-87.72748900000001,41.94676],"type":"Point"}
}