{
  "type": "Feature",
  "properties": {
    "iso:country":"US",
    "sg:address":"5525 N 2nd St",
    "sg:city":"Loves Park",
    "sg:classifiers":[
        {
            "category":"Bars & Pubs",
            "type":"Food & Drink"
        }
    ],
    "sg:phone":"+1 815 877 1698",
    "sg:postcode":"61111",
    "sg:province":"IL",
    "wof:name":"Vic & Jim's",
    "wof:placetype":"venue"
},
  "geometry": {"coordinates":[-89.057779,42.310638],"type":"Point"}
}