{
  "type": "Feature",
  "properties": {
    "iso:country":"US",
    "sg:address":"112 S Waverly Pl",
    "sg:city":"Mount Prospect",
    "sg:classifiers":[
        {
            "category":"Professional",
            "subcategory":"Management & Consulting",
            "type":"Services"
        }
    ],
    "sg:phone":"+1 847 392 9589",
    "sg:postcode":"60056",
    "sg:province":"IL",
    "sg:tags":[
        "business"
    ],
    "wof:name":"Tolbert Assoc Inc",
    "wof:placetype":"venue"
},
  "geometry": {"coordinates":[-87.953818,42.0627],"type":"Point"}
}