{
  "type": "Feature",
  "properties": {
    "iso:country":"US",
    "sg:address":"1903 N Milwaukee Ave",
    "sg:city":"Chicago",
    "sg:classifiers":[
        {
            "category":"Professional",
            "subcategory":"Computer Services",
            "type":"Services"
        }
    ],
    "sg:phone":"+1 773 362 4656",
    "sg:postcode":"60647",
    "sg:province":"IL",
    "sg:tags":[
        "repair"
    ],
    "sg:website":"www.northsidetech.com",
    "wof:name":"Northside Tech Support",
    "wof:placetype":"venue"
},
  "geometry": {"coordinates":[-87.686082,41.916012],"type":"Point"}
}