{
  "type": "Feature",
  "properties": {
    "addr:full":"606 Bowald St Eureka IL 61530",
    "addr:housenumber":"606",
    "addr:postcode":"61530",
    "addr:street":"Bowald St",
    "iso:country":"US",
    "sg:address":"606 Bowald St",
    "sg:city":"Eureka",
    "sg:classifiers":[
        {
            "category":"Professional",
            "subcategory":"Business Services",
            "type":"Services"
        },
        {
            "category":"Manufacturing",
            "subcategory":"Apparel",
            "type":"Manufacturing & Wholesale Goods"
        }
    ],
    "sg:phone":"+1 309 467 6921",
    "sg:postcode":"61530",
    "sg:province":"IL",
    "sg:tags":[
        "embroidery"
    ],
    "wof:name":"C R Embroidery",
    "wof:placetype":"venue"
},
  "geometry": {"coordinates":[-89.27715999999999,40.726996],"type":"Point"}
}