{
  "type": "Feature",
  "properties": {
    "addr:full":"3534 N Ottawa Ave Chicago IL 60634",
    "addr:housenumber":"3534",
    "addr:postcode":"60634",
    "addr:street":"N Ottawa Ave",
    "iso:country":"US",
    "sg:address":"3534 N Ottawa Ave",
    "sg:city":"Chicago",
    "sg:classifiers":[
        {
            "category":"Home & Garden",
            "subcategory":"Hardware",
            "type":"Retail Goods"
        }
    ],
    "sg:phone":"+1 773 589 0104",
    "sg:postcode":"60634",
    "sg:province":"IL",
    "sg:tags":[
        "water",
        "filtration",
        "equipment",
        "purification"
    ],
    "wof:name":"David Dyczewski",
    "wof:placetype":"venue"
},
  "geometry": {"coordinates":[-87.817936,41.943939],"type":"Point"}
}