{
  "type": "Feature",
  "properties": {
    "iso:country":"US",
    "sg:address":"4421 W Main St",
    "sg:city":"Belleville",
    "sg:classifiers":[
        {
            "category":"Restaurant",
            "type":"Food & Drink"
        }
    ],
    "sg:menulink":"http://www.allmenus.com/il/belleville/159460-arbys/menu/",
    "sg:phone":"+1 618 233 0200",
    "sg:postcode":"62226",
    "sg:province":"IL",
    "sg:tags":[
        "burger",
        "american"
    ],
    "wof:name":"Arby's",
    "wof:placetype":"venue"
},
  "geometry": {"coordinates":[-90.022229,38.540223],"type":"Point"}
}