{
  "type": "Feature",
  "properties": {
    "addr:full":"1732 W Hubbard Street Chicago IL 60622",
    "addr:housenumber":"1732",
    "addr:postcode":"60622",
    "addr:street":"W Hubbard Street",
    "iso:country":"US",
    "sg:address":"1732 W Hubbard Street",
    "sg:city":"Chicago",
    "sg:classifiers":[
        {
            "category":"Real Estate",
            "subcategory":"Real Estate Services",
            "type":"Services"
        },
        {
            "category":"Real Estate",
            "subcategory":"Real Estate Agent",
            "type":"Services"
        }
    ],
    "sg:phone":"+1 312 492 7900",
    "sg:postcode":"60622",
    "sg:province":"IL",
    "sg:website":"www.daprilerealty.com/",
    "wof:name":"D'aprile Realty",
    "wof:placetype":"venue"
},
  "geometry": {"coordinates":[-87.670782,41.889847],"type":"Point"}
}