{
  "type": "Feature",
  "properties": {
    "iso:country":"US",
    "sg:address":"730 13th St",
    "sg:city":"East Moline",
    "sg:classifiers":[
        {
            "category":"Organizations",
            "subcategory":"Religious Organization",
            "type":"Services"
        }
    ],
    "sg:phone":"+1 309 752 0772",
    "sg:postcode":"61244",
    "sg:province":"IL",
    "sg:tags":[
        "church"
    ],
    "wof:name":"Prayer & Save Mission",
    "wof:placetype":"venue"
},
  "geometry": {"coordinates":[-90.430135,41.524976],"type":"Point"}
}