{
  "type": "Feature",
  "properties": {
    "addr:full":"17228 Lockwood Ave Tinley Park IL 60477",
    "addr:housenumber":"17228",
    "addr:postcode":"60477",
    "addr:street":"Lockwood Ave",
    "iso:country":"US",
    "sg:address":"17228 Lockwood Ave",
    "sg:city":"Tinley Park",
    "sg:classifiers":[
        {
            "category":"Building & Trades",
            "subcategory":"Plumbing",
            "type":"Services"
        }
    ],
    "sg:phone":"+1 708 560 0280",
    "sg:postcode":"60477",
    "sg:province":"IL",
    "sg:tags":[
        "contractor",
        "heating",
        "con"
    ],
    "wof:name":"Eppcor Heating & Sheet Metal",
    "wof:placetype":"venue"
},
  "geometry": {"coordinates":[-87.748546,41.577132],"type":"Point"}
}