{
  "type": "Feature",
  "properties": {
    "iso:country":"US",
    "sg:address":"1 Palos Ct",
    "sg:city":"Bolingbrook",
    "sg:classifiers":[
        {
            "category":"Real Estate",
            "subcategory":"Surveying",
            "type":"Services"
        }
    ],
    "sg:phone":"+1 630 679 1310",
    "sg:postcode":"60440",
    "sg:province":"IL",
    "sg:tags":[
        "surveyor"
    ],
    "sg:website":"www.assocsurvey.com",
    "wof:name":"Associated Surveying Group",
    "wof:placetype":"venue"
},
  "geometry": {"coordinates":[-88.09906,41.698598],"type":"Point"}
}