{
  "type": "Feature",
  "properties": {
    "addr:full":"26727 S Fox Wood Dr Monee IL 60449",
    "addr:housenumber":"26727",
    "addr:postcode":"60449",
    "addr:street":"S Fox Wood Dr",
    "iso:country":"US",
    "sg:address":"26727 S Fox Wood Dr",
    "sg:city":"Monee",
    "sg:classifiers":[
        {
            "category":"Building & Trades",
            "subcategory":"Cleaning & Sanitation",
            "type":"Services"
        }
    ],
    "sg:phone":"+1 708 534 3008",
    "sg:postcode":"60449",
    "sg:province":"IL",
    "wof:name":"B & R Exterior Cleaning Inc",
    "wof:placetype":"venue"
},
  "geometry": {"coordinates":[-87.738255,41.401916],"type":"Point"}
}