{
  "type": "Feature",
  "properties": {
    "iso:country":"US",
    "sg:address":"338 Park Ave",
    "sg:city":"Glencoe",
    "sg:classifiers":[
        {
            "category":"Professional",
            "type":"Services"
        },
        {
            "category":"Deli",
            "type":"Food & Drink"
        },
        {
            "category":"Restaurant",
            "type":"Food & Drink"
        }
    ],
    "sg:phone":"+1 847 835 5105",
    "sg:postcode":"60022",
    "sg:province":"IL",
    "sg:tags":[
        "style",
        "family",
        "delicatessen",
        "lunch",
        "caterer",
        "brunch",
        "breakfast"
    ],
    "wof:name":"Foodstuffs Gourmet Foods And Catering",
    "wof:placetype":"venue"
},
  "geometry": {"coordinates":[-87.75904300000001,42.134421],"type":"Point"}
}