{
  "type": "Feature",
  "properties": {
    "iso:country":"US",
    "sg:address":"304 8th St",
    "sg:city":"Charleston",
    "sg:classifiers":[
        {
            "category":"Professional",
            "subcategory":"Accounting & Tax Preparation",
            "type":"Services"
        }
    ],
    "sg:phone":"+1 217 345 2128",
    "sg:postcode":"61920",
    "sg:province":"IL",
    "sg:tags":[
        "accountant"
    ],
    "wof:name":"Gilbert Metzger & Madigan",
    "wof:placetype":"venue"
},
  "geometry": {"coordinates":[-88.174002,39.496966],"type":"Point"}
}