{
  "type": "Feature",
  "properties": {
    "iso:country":"US",
    "sg:address":"837 E Roosevelt Rd",
    "sg:city":"Lombard",
    "sg:classifiers":[
        {
            "category":"Food & Beverages",
            "subcategory":"Groceries & Convenience Stores",
            "type":"Retail Goods"
        }
    ],
    "sg:phone":"+1 630 261 9953",
    "sg:postcode":"60148",
    "sg:province":"IL",
    "wof:name":"Tajmahal",
    "wof:placetype":"venue"
},
  "geometry": {"coordinates":[-88.05168500000001,41.859409],"type":"Point"}
}