{
  "type": "Feature",
  "properties": {
    "iso:country":"US",
    "sg:address":"17 Spring Creek Dr",
    "sg:city":"South Barrington",
    "sg:classifiers":[
        {
            "category":"Real Estate",
            "subcategory":"Architect",
            "type":"Services"
        }
    ],
    "sg:phone":"+1 847 426 7233",
    "sg:postcode":"60010",
    "sg:province":"IL",
    "wof:name":"A & A Design Group Ltd",
    "wof:placetype":"venue"
},
  "geometry": {"coordinates":[-88.177498,42.0975],"type":"Point"}
}