{
  "type": "Feature",
  "properties": {
    "iso:country":"US",
    "sg:address":"300 E William St",
    "sg:city":"Bement",
    "sg:classifiers":[
        {
            "category":"Real Estate",
            "subcategory":"Real Estate Operator",
            "type":"Services"
        }
    ],
    "sg:phone":"+1 217 678 7091",
    "sg:postcode":"61813",
    "sg:province":"IL",
    "sg:tags":[
        "property",
        "lessor"
    ],
    "wof:name":"Carl Laley",
    "wof:placetype":"venue"
},
  "geometry": {"coordinates":[-88.567118,39.921272],"type":"Point"}
}