{
  "type": "Feature",
  "properties": {
    "iso:country":"US",
    "sg:address":"11218 S Ridgeland Ave",
    "sg:city":"Worth",
    "sg:classifiers":[
        {
            "category":"Education",
            "subcategory":"School",
            "type":"Public Place"
        }
    ],
    "sg:phone":"+1 708 448 2800",
    "sg:postcode":"60482",
    "sg:province":"IL",
    "wof:name":"Schools Public",
    "wof:placetype":"venue"
},
  "geometry": {"coordinates":[-87.778801,41.6875],"type":"Point"}
}