{
  "type": "Feature",
  "properties": {
    "addr:full":"272 W Lake St Elmhurst IL 60126",
    "addr:housenumber":"272",
    "addr:postcode":"60126",
    "addr:street":"W Lake St",
    "iso:country":"US",
    "sg:address":"272 W Lake St",
    "sg:city":"Elmhurst",
    "sg:classifiers":[
        {
            "category":"Building & Trades",
            "subcategory":"Plumbing",
            "type":"Services"
        }
    ],
    "sg:phone":"+1 630 833 2255",
    "sg:postcode":"60126",
    "sg:province":"IL",
    "sg:tags":[
        "repair",
        "installation",
        "wet",
        "plumbing",
        "concern",
        "he"
    ],
    "wof:name":"Stutz Leonard Plumbing",
    "wof:placetype":"venue"
},
  "geometry": {"coordinates":[-87.944163,41.914605],"type":"Point"}
}