{
  "type": "Feature",
  "properties": {
    "addr:full":"2841 Shadow Lawn Momence IL 60954",
    "addr:housenumber":"2841",
    "addr:postcode":"60954",
    "addr:street":"Shadow Lawn",
    "iso:country":"US",
    "sg:address":"2841 Shadow Lawn",
    "sg:city":"Momence",
    "sg:classifiers":[
        {
            "category":"Professional",
            "subcategory":"Management & Consulting",
            "type":"Services"
        },
        {
            "category":"Banks & Credit Unions",
            "subcategory":"Investment Brokerage",
            "type":"Services"
        },
        {
            "category":"Banks & Credit Unions",
            "subcategory":"Financial Services",
            "type":"Services"
        }
    ],
    "sg:phone":"+1 815 472 2103",
    "sg:postcode":"60954",
    "sg:province":"IL",
    "sg:tags":[
        "planning",
        "advisory",
        "financing",
        "planner",
        "consultant"
    ],
    "wof:name":"Allied Business Solutions Inc",
    "wof:placetype":"venue"
},
  "geometry": {"coordinates":[-87.574997,41.159779],"type":"Point"}
}