{
  "type": "Feature",
  "properties": {
    "iso:country":"US",
    "sg:address":"527 W 41st St",
    "sg:city":"Chicago",
    "sg:classifiers":[
        {
            "category":"Food & Beverages",
            "subcategory":"Meat & Fish",
            "type":"Retail Goods"
        }
    ],
    "sg:phone":"+1 773 285 5400",
    "sg:postcode":"60609",
    "sg:province":"IL",
    "sg:tags":[
        "shop"
    ],
    "wof:name":"L & L Packing Co",
    "wof:placetype":"venue"
},
  "geometry": {"coordinates":[-87.639397,41.82],"type":"Point"}
}