{
  "type": "Feature",
  "properties": {
    "iso:country":"US",
    "sg:address":"79 W Monroe St",
    "sg:city":"Chicago",
    "sg:classifiers":[
        {
            "category":"Personal",
            "subcategory":"Tattoo Parlor",
            "type":"Services"
        }
    ],
    "sg:phone":"+1 312 236 3366",
    "sg:postcode":"60603",
    "sg:province":"IL",
    "wof:name":"German & Scandinavian Transltrs & Intrprtrs Assctn",
    "wof:placetype":"venue"
},
  "geometry": {"coordinates":[-87.63009599999999,41.880699],"type":"Point"}
}