{
  "type": "Feature",
  "properties": {
    "iso:country":"US",
    "sg:address":"3605 216th St",
    "sg:city":"Matteson",
    "sg:classifiers":[
        {
            "category":"Retail",
            "subcategory":"Repair Shop",
            "type":"Services"
        }
    ],
    "sg:phone":"+1   ",
    "sg:postcode":"60443",
    "sg:province":"IL",
    "wof:name":"Dahlman-Stege TV",
    "wof:placetype":"venue"
},
  "geometry": {"coordinates":[-87.70517,41.497433],"type":"Point"}
}