{
  "type": "Feature",
  "properties": {
    "iso:country":"US",
    "sg:address":"3742 N Main St",
    "sg:city":"Rockford",
    "sg:classifiers":[
        {
            "category":"Shopping",
            "subcategory":"Gifts & Souvenirs",
            "type":"Retail Goods"
        }
    ],
    "sg:phone":"+1 815 877 9611",
    "sg:postcode":"61103",
    "sg:province":"IL",
    "sg:tags":[
        "shop"
    ],
    "wof:name":"Laurie's Gift",
    "wof:placetype":"venue"
},
  "geometry": {"coordinates":[-89.077339,42.317143],"type":"Point"}
}