{
  "type": "Feature",
  "properties": {
    "addr:full":"9410 S 79th Ct Hickory Hills IL 60457",
    "addr:housenumber":"9410",
    "addr:postcode":"60457",
    "addr:street":"S 79Th Ct",
    "iso:country":"US",
    "sg:address":"9410 S 79th Ct",
    "sg:city":"Hickory Hills",
    "sg:classifiers":[
        {
            "category":"Retail",
            "subcategory":"Auto Repair",
            "type":"Services"
        }
    ],
    "sg:phone":"+1 708 423 4405",
    "sg:postcode":"60457",
    "sg:province":"IL",
    "sg:tags":[
        "wrecker"
    ],
    "wof:name":"A T & T Towing",
    "wof:placetype":"venue"
},
  "geometry": {"coordinates":[-87.81676400000001,41.718757],"type":"Point"}
}