{
  "type": "Feature",
  "properties": {
    "addr:full":"5750 Lakeside Dr Lisle IL 60532",
    "addr:housenumber":"5750",
    "addr:postcode":"60532",
    "addr:street":"Lakeside Dr",
    "iso:country":"US",
    "sg:address":"5750 Lakeside Dr",
    "sg:city":"Lisle",
    "sg:phone":"+1 630 724 0450",
    "sg:postcode":"60532",
    "sg:province":"IL",
    "wof:name":"Lodge Pub & Grille",
    "wof:placetype":"venue"
},
  "geometry": {"coordinates":[-88.084699,41.782772],"type":"Point"}
}