{
  "type": "Feature",
  "properties": {
    "iso:country":"US",
    "sg:address":"280 Glen Ellyn Rd",
    "sg:city":"Bloomingdale",
    "sg:classifiers":[
        {
            "category":"Food & Beverages",
            "subcategory":"Groceries & Convenience Stores",
            "type":"Retail Goods"
        }
    ],
    "sg:phone":"+1 630 924 5429",
    "sg:postcode":"60108",
    "sg:province":"IL",
    "sg:website":"www.convenientfoodmart.com",
    "wof:name":"Convenient Food Mart",
    "wof:placetype":"venue"
},
  "geometry": {"coordinates":[-88.06240099999999,41.942299],"type":"Point"}
}