{
  "type": "Feature",
  "properties": {
    "addr:full":"420 Maine St Quincy IL 62301",
    "addr:housenumber":"420",
    "addr:postcode":"62301",
    "addr:street":"Maine St",
    "iso:country":"US",
    "sg:address":"420 Maine St",
    "sg:city":"Quincy",
    "sg:classifiers":[
        {
            "category":"Banks & Credit Unions",
            "subcategory":"Bank",
            "type":"Services"
        }
    ],
    "sg:phone":"+1 217 223 7676",
    "sg:postcode":"62301",
    "sg:province":"IL",
    "sg:tags":[
        "mortgage"
    ],
    "wof:name":"Mercantile Mortgage Center",
    "wof:placetype":"venue"
},
  "geometry": {"coordinates":[-91.408698,39.931845],"type":"Point"}
}