{
  "type": "Feature",
  "properties": {
    "addr:full":"7044 S King Dr Chicago IL 60637",
    "addr:housenumber":"7044",
    "addr:postcode":"60637",
    "addr:street":"S King Dr",
    "iso:country":"US",
    "sg:address":"7044 S King Dr",
    "sg:city":"Chicago",
    "sg:classifiers":[
        {
            "category":"Building & Trades",
            "subcategory":"Electrical",
            "type":"Services"
        }
    ],
    "sg:phone":"+1 773 783 0552",
    "sg:postcode":"60637",
    "sg:province":"IL",
    "sg:tags":[
        "industrial",
        "electrician",
        "contractors-commercial",
        "electric"
    ],
    "wof:name":"Bob Edwards",
    "wof:placetype":"venue"
},
  "geometry": {"coordinates":[-87.615222,41.766367],"type":"Point"}
}