{
  "type": "Feature",
  "properties": {
    "iso:country":"US",
    "sg:address":"106 W 7th St",
    "sg:city":"Neoga",
    "sg:classifiers":[
        {
            "category":"Food & Beverages",
            "subcategory":"Liquor & Beverages",
            "type":"Retail Goods"
        }
    ],
    "sg:phone":"+1 217 895 2877",
    "sg:postcode":"62447",
    "sg:province":"IL",
    "sg:tags":[
        "store"
    ],
    "wof:name":"Neoga Package Liquors",
    "wof:placetype":"venue"
},
  "geometry": {"coordinates":[-88.452814,39.320797],"type":"Point"}
}