{
  "type": "Feature",
  "properties": {
    "addr:full":"1229 N Clybourn Chicago IL 60654",
    "addr:housenumber":"1229",
    "addr:postcode":"60654",
    "addr:street":"N Clybourn",
    "iso:country":"US",
    "sg:address":"1229 N Clybourn",
    "sg:city":"Chicago",
    "sg:classifiers":[
        {
            "category":"Coffee & Tea",
            "type":"Food & Drink"
        }
    ],
    "sg:postcode":"60654",
    "sg:province":"IL",
    "wof:name":"Starbucks",
    "wof:placetype":"venue"
},
  "geometry": {"coordinates":[-87.63997999999999,41.904084],"type":"Point"}
}