{
  "type": "Feature",
  "properties": {
    "iso:country":"US",
    "sg:address":"149 S Genesee St",
    "sg:city":"Waukegan",
    "sg:classifiers":[
        {
            "category":"Organizations",
            "subcategory":"Political Organization",
            "type":"Services"
        }
    ],
    "sg:phone":"+1 847 782 9547",
    "sg:postcode":"60085",
    "sg:province":"IL",
    "wof:name":"Susan Garrett",
    "wof:placetype":"venue"
},
  "geometry": {"coordinates":[-87.831314,42.357415],"type":"Point"}
}