{
  "type": "Feature",
  "properties": {
    "addr:full":"3S517 Winfield Rd Warrenville IL 60555",
    "addr:housenumber":"3s517",
    "addr:postcode":"60555",
    "addr:street":"Winfield Rd",
    "iso:country":"US",
    "sg:address":"3S517 Winfield Rd",
    "sg:city":"Warrenville",
    "sg:classifiers":[
        {
            "category":"Health Services",
            "subcategory":"Chiropractor",
            "type":"Services"
        }
    ],
    "sg:phone":"+1 630 836 9121",
    "sg:postcode":"60555",
    "sg:province":"IL",
    "sg:tags":[
        "chiropractic"
    ],
    "wof:name":"Soltys, Jonathan Dc",
    "wof:placetype":"venue"
},
  "geometry": {"coordinates":[-88.168404,41.825871],"type":"Point"}
}