{
  "type": "Feature",
  "properties": {
    "iso:country":"US",
    "sg:address":"3S517 Winfield Rd",
    "sg:city":"Warrenville",
    "sg:classifiers":[
        {
            "category":"Health Services",
            "subcategory":"Chiropractor",
            "type":"Services"
        }
    ],
    "sg:phone":"+1 630 836 9121",
    "sg:postcode":"60555",
    "sg:province":"IL",
    "sg:tags":[
        "chiropractic"
    ],
    "wof:name":"Soltys, Jonathan Dc",
    "wof:placetype":"venue"
},
  "geometry": {"coordinates":[-88.168404,41.825871],"type":"Point"}
}