{
  "type": "Feature",
  "properties": {
    "iso:country":"US",
    "sg:address":"110 S Main St",
    "sg:city":"Dupo",
    "sg:classifiers":[
        {
            "category":"Food & Beverages",
            "subcategory":"Groceries & Convenience Stores",
            "type":"Retail Goods"
        }
    ],
    "sg:phone":"+1   ",
    "sg:postcode":"62239",
    "sg:province":"IL",
    "wof:name":"Hucks 310",
    "wof:placetype":"venue"
},
  "geometry": {"coordinates":[-90.210797,38.518465],"type":"Point"}
}