{
  "type": "Feature",
  "properties": {
    "addr:full":"230 Hastings Way SW Poplar Grove IL 61065",
    "addr:housenumber":"230",
    "addr:postcode":"61065",
    "addr:street":"Hastings Way Sw",
    "iso:country":"US",
    "sg:address":"230 Hastings Way SW",
    "sg:city":"Poplar Grove",
    "sg:classifiers":[
        {
            "category":"Sports & Exercise",
            "subcategory":"Gym",
            "type":"Entertainment"
        }
    ],
    "sg:phone":"+1 815 765 1849",
    "sg:postcode":"61065",
    "sg:province":"IL",
    "sg:tags":[
        "fitness",
        "physical",
        "facility"
    ],
    "wof:name":"A Therapeutic Solution",
    "wof:placetype":"venue"
},
  "geometry": {"coordinates":[-88.87505299999999,42.344727],"type":"Point"}
}