{
  "type": "Feature",
  "properties": {
    "iso:country":"US",
    "sg:address":"2330 N Verde Dr",
    "sg:city":"Arlington Heights",
    "sg:classifiers":[
        {
            "category":"Education",
            "subcategory":"School",
            "type":"Public Place"
        }
    ],
    "sg:phone":"+1 847 398 4272",
    "sg:postcode":"60004",
    "sg:province":"IL",
    "sg:tags":[
        "elementary"
    ],
    "wof:name":"Greenbriar Elementary School",
    "wof:placetype":"venue"
},
  "geometry": {"coordinates":[-87.997519,42.120233],"type":"Point"}
}