{
  "type": "Feature",
  "properties": {
    "addr:full":"3201 S State St Chicago IL 60616",
    "addr:housenumber":"3201",
    "addr:postcode":"60616",
    "addr:street":"S State St",
    "iso:country":"US",
    "sg:address":"3201 S State St",
    "sg:city":"Chicago",
    "sg:classifiers":[
        {
            "category":"Restaurant",
            "type":"Food & Drink"
        }
    ],
    "sg:phone":"+1 312 567 3716",
    "sg:postcode":"60616",
    "sg:province":"IL",
    "sg:tags":[
        "new",
        "american"
    ],
    "wof:name":"Pritzker Club",
    "wof:placetype":"venue"
},
  "geometry": {"coordinates":[-87.62653899999999,41.836217],"type":"Point"}
}