{
  "type": "Feature",
  "properties": {
    "addr:full":"920 Main St Batavia IL 60510",
    "addr:housenumber":"920",
    "addr:postcode":"60510",
    "addr:street":"Main St",
    "iso:country":"US",
    "sg:address":"920 Main St",
    "sg:city":"Batavia",
    "sg:classifiers":[
        {
            "category":"Building & Trades",
            "subcategory":"Construction",
            "type":"Services"
        }
    ],
    "sg:phone":"+1 630 879 0986",
    "sg:postcode":"60510",
    "sg:province":"IL",
    "sg:tags":[
        "well",
        "drilling"
    ],
    "wof:name":"Jedd's Well & Pump",
    "wof:placetype":"venue"
},
  "geometry": {"coordinates":[-88.322722,41.8468],"type":"Point"}
}