{
  "type": "Feature",
  "properties": {
    "iso:country":"US",
    "sg:address":"6419 Material Ave",
    "sg:city":"Loves Park",
    "sg:classifiers":[
        {
            "category":"Building & Trades",
            "subcategory":"Plumbing",
            "type":"Services"
        }
    ],
    "sg:phone":"+1 815 877 4134",
    "sg:postcode":"61111",
    "sg:province":"IL",
    "sg:tags":[
        "sheet",
        "metal",
        "heating",
        "air",
        "warm",
        "conditioning"
    ],
    "wof:name":"Larson Sheet Metal Inc",
    "wof:placetype":"venue"
},
  "geometry": {"coordinates":[-89.037986,42.319922],"type":"Point"}
}