{
  "type": "Feature",
  "properties": {
    "iso:country":"US",
    "sg:address":"610 Tollview Dr",
    "sg:city":"South Holland",
    "sg:classifiers":[
        {
            "category":"Travel",
            "subcategory":"Hotels & Motels",
            "type":"Entertainment"
        }
    ],
    "sg:phone":"+1 708 225 1300",
    "sg:postcode":"60473",
    "sg:province":"IL",
    "wof:name":"Hilton Garden Inn South Holland",
    "wof:placetype":"venue"
},
  "geometry": {"coordinates":[-87.63020299999999,41.579399],"type":"Point"}
}