{
  "type": "Feature",
  "properties": {
    "iso:country":"US",
    "sg:address":"4520 9th St",
    "sg:city":"Rock Island",
    "sg:classifiers":[
        {
            "category":"Real Estate",
            "subcategory":"Developer",
            "type":"Services"
        },
        {
            "category":"Real Estate",
            "subcategory":"Real Estate Operator",
            "type":"Services"
        }
    ],
    "sg:phone":"+1 309 786 5135",
    "sg:postcode":"61201",
    "sg:province":"IL",
    "sg:tags":[
        "mobile",
        "home",
        "site"
    ],
    "wof:name":"Michael's Mobile Home Park",
    "wof:placetype":"venue"
},
  "geometry": {"coordinates":[-90.584311,41.46582],"type":"Point"}
}