{
  "type": "Feature",
  "properties": {
    "iso:country":"US",
    "sg:address":"2200 E Eldorado St",
    "sg:city":"Decatur",
    "sg:classifiers":[
        {
            "category":"Food & Beverages",
            "subcategory":"Farmers Market",
            "type":"Retail Goods"
        },
        {
            "category":"Food & Beverages",
            "subcategory":"Groceries & Convenience Stores",
            "type":"Retail Goods"
        }
    ],
    "sg:phone":"+1 217 423 4411",
    "sg:postcode":"62521",
    "sg:province":"IL",
    "sg:tags":[
        "vegetable",
        "fruit"
    ],
    "wof:name":"A E Staley Manufacturing Company",
    "wof:placetype":"venue"
},
  "geometry": {"coordinates":[-88.926483,39.846636],"type":"Point"}
}