{
  "type": "Feature",
  "properties": {
    "iso:country":"US",
    "sg:address":"199 S Pearl St",
    "sg:city":"Waverly",
    "sg:classifiers":[
        {
            "category":"Food & Beverages",
            "subcategory":"Groceries & Convenience Stores",
            "type":"Retail Goods"
        }
    ],
    "sg:phone":"+1   ",
    "sg:postcode":"62692",
    "sg:province":"IL",
    "wof:name":"WAVERLY Family Foods",
    "wof:placetype":"venue"
},
  "geometry": {"coordinates":[-89.95338099999999,39.590724],"type":"Point"}
}