{
  "type": "Feature",
  "properties": {
    "addr:full":"1807 W Market St Bloomington IL 61701",
    "addr:housenumber":"1807",
    "addr:postcode":"61701",
    "addr:street":"W Market St",
    "iso:country":"US",
    "sg:address":"1807 W Market St",
    "sg:city":"Bloomington",
    "sg:classifiers":[
        {
            "category":"Ice Cream",
            "type":"Food & Drink"
        }
    ],
    "sg:menulink":"http://www.allmenus.com/il/bloomington-city/182680-culvers/menu/",
    "sg:phone":"+1 309 827 3527",
    "sg:postcode":"61701",
    "sg:province":"IL",
    "sg:tags":[
        "burger",
        "american"
    ],
    "wof:name":"Culver's",
    "wof:placetype":"venue"
},
  "geometry": {"coordinates":[-89.02069299999999,40.483819],"type":"Point"}
}