{
  "type": "Feature",
  "properties": {
    "iso:country":"US",
    "sg:address":"784 Wall St",
    "sg:city":"O Fallon",
    "sg:classifiers":[
        {
            "category":"Professional",
            "subcategory":"Lawyer & Legal Services",
            "type":"Services"
        }
    ],
    "sg:phone":"+1 618 632 8950",
    "sg:postcode":"62269",
    "sg:province":"IL",
    "wof:name":"Kasten Chadwick A",
    "wof:placetype":"venue"
},
  "geometry": {"coordinates":[-89.927002,38.5854],"type":"Point"}
}