{
  "type": "Feature",
  "properties": {
    "iso:country":"US",
    "sg:address":"2340 S Arlington Heights Rd",
    "sg:city":"Arlington Hts",
    "sg:classifiers":[
        {
            "category":"Home & Garden",
            "subcategory":"Household Appliances",
            "type":"Retail Goods"
        }
    ],
    "sg:phone":"+1 847 264 2642",
    "sg:postcode":"60005",
    "sg:province":"IL",
    "wof:name":"FCI Home Appliance",
    "wof:placetype":"venue"
},
  "geometry": {"coordinates":[-87.983628,42.042137],"type":"Point"}
}