{
  "type": "Feature",
  "properties": {
    "iso:country":"US",
    "sg:address":"1035 Parkview Dr",
    "sg:city":"Hanover Park",
    "sg:classifiers":[
        {
            "category":"Education",
            "subcategory":"School",
            "type":"Public Place"
        }
    ],
    "sg:phone":"+1 630 837 2430",
    "sg:postcode":"60133",
    "sg:province":"IL",
    "wof:name":"Fox School",
    "wof:placetype":"venue"
},
  "geometry": {"coordinates":[-88.134883,42.009274],"type":"Point"}
}