{
  "type": "Feature",
  "properties": {
    "iso:country":"US",
    "sg:address":"2220 W Shakespeare Ave",
    "sg:city":"Chicago",
    "sg:classifiers":[
        {
            "category":"Taxi",
            "type":"Transportation"
        }
    ],
    "sg:phone":"+1 773 252 2831",
    "sg:postcode":"60647",
    "sg:province":"IL",
    "sg:tags":[
        "taxicab"
    ],
    "wof:name":"Esmeralda Cab Co",
    "wof:placetype":"venue"
},
  "geometry": {"coordinates":[-87.683488,41.920686],"type":"Point"}
}