{
  "type": "Feature",
  "properties": {
    "iso:country":"US",
    "sg:address":"3939 W 127th St",
    "sg:city":"Alsip",
    "sg:classifiers":[
        {
            "category":"Retail",
            "subcategory":"Car Wash",
            "type":"Services"
        }
    ],
    "sg:phone":"+1 708 385 0864",
    "sg:postcode":"60803",
    "sg:province":"IL",
    "sg:tags":[
        "polishing",
        "washing"
    ],
    "wof:name":"Ameriwash Car Wash",
    "wof:placetype":"venue"
},
  "geometry": {"coordinates":[-87.718102,41.661999],"type":"Point"}
}