{
  "type": "Feature",
  "properties": {
    "addr:full":"14520 Highland Ave Orland Park IL 60462",
    "addr:housenumber":"14520",
    "addr:postcode":"60462",
    "addr:street":"Highland Ave",
    "iso:country":"US",
    "sg:address":"14520 Highland Ave",
    "sg:city":"Orland Park",
    "sg:classifiers":[
        {
            "category":"Shopping",
            "subcategory":"Bicycles & Sporting Goods",
            "type":"Retail Goods"
        }
    ],
    "sg:phone":"+1   ",
    "sg:postcode":"60462",
    "sg:province":"IL",
    "wof:name":"Snowcrest Ski Center",
    "wof:placetype":"venue"
},
  "geometry": {"coordinates":[-87.865785,41.625743],"type":"Point"}
}