{
  "type": "Feature",
  "properties": {
    "iso:country":"US",
    "sg:address":"5973 Redbird Rd",
    "sg:city":"Salem",
    "sg:classifiers":[
        {
            "category":"Government",
            "subcategory":"Office",
            "type":"Public Place"
        }
    ],
    "sg:phone":"+1   ",
    "sg:postcode":"62881",
    "sg:province":"IL",
    "sg:tags":[
        "executive"
    ],
    "wof:name":"Alma Township",
    "wof:placetype":"venue"
},
  "geometry": {"coordinates":[-88.864605,38.687046],"type":"Point"}
}