{
  "type": "Feature",
  "properties": {
    "iso:country":"US",
    "sg:address":"900 W Ainslie St",
    "sg:city":"Chicago",
    "sg:classifiers":[
        {
            "category":"Recreation",
            "type":"Entertainment"
        }
    ],
    "sg:phone":"+1 773 293 2255",
    "sg:postcode":"60640",
    "sg:province":"IL",
    "sg:tags":[
        "club",
        "membership"
    ],
    "wof:name":"Euro Soccer Club",
    "wof:placetype":"venue"
},
  "geometry": {"coordinates":[-87.653078,41.971681],"type":"Point"}
}