{
  "type": "Feature",
  "properties": {
    "addr:full":"148 S Bloomingdale Rd Bloomingdale IL 60108",
    "addr:housenumber":"148",
    "addr:postcode":"60108",
    "addr:street":"S Bloomingdale Rd",
    "iso:country":"US",
    "sg:address":"148 S Bloomingdale Rd",
    "sg:city":"Bloomingdale",
    "sg:classifiers":[
        {
            "category":"Retail",
            "subcategory":"Laundry & Dry Cleaning",
            "type":"Services"
        }
    ],
    "sg:phone":"+1 630 924 7373",
    "sg:postcode":"60108",
    "sg:province":"IL",
    "wof:name":"Old Town Cleaners",
    "wof:placetype":"venue"
},
  "geometry": {"coordinates":[-88.081001,41.9534],"type":"Point"}
}