{
  "type": "Feature",
  "properties": {
    "addr:full":"135 E Monterey Ave Schaumburg IL 60193",
    "addr:housenumber":"135",
    "addr:postcode":"60193",
    "addr:street":"E Monterey Ave",
    "iso:country":"US",
    "sg:address":"135 E Monterey Ave",
    "sg:city":"Schaumburg",
    "sg:classifiers":[
        {
            "category":"Wholesale",
            "subcategory":"Machinery & Supplies",
            "type":"Manufacturing & Wholesale Goods"
        }
    ],
    "sg:phone":"+1 847 891 0755",
    "sg:postcode":"60193",
    "sg:province":"IL",
    "sg:tags":[
        "machine",
        "tool",
        "metalworking"
    ],
    "wof:name":"Pre-Tech Manufacturing Inc",
    "wof:placetype":"venue"
},
  "geometry": {"coordinates":[-88.073609,42.002612],"type":"Point"}
}