{
  "type": "Feature",
  "properties": {
    "addr:full":"51 E State Pkwy Schaumburg IL 60173",
    "addr:housenumber":"51",
    "addr:postcode":"60173",
    "addr:street":"E State Pkwy",
    "iso:country":"US",
    "sg:address":"51 E State Pkwy",
    "sg:city":"Schaumburg",
    "sg:classifiers":[
        {
            "category":"Travel",
            "subcategory":"Hotels & Motels",
            "type":"Entertainment"
        }
    ],
    "sg:phone":"+1 847 882 6900",
    "sg:postcode":"60173",
    "sg:province":"IL",
    "sg:tags":[
        "corporate",
        "lodging"
    ],
    "sg:website":"http://redirect.searchignite.com/si/cm/tracking/DGTrackingRedirect.aspx?siclientid=2918&siredirect=http%3A%2F%2Fwww%2Ehomesteadhotels%2Ecom%2FSHB&sisearchengine=155&siproduct=HS+Chicago+%2D+Schaumburg&clearppc=1",
    "wof:name":"Homestead Studio Suites Chicago - Schaumburg",
    "wof:placetype":"venue"
},
  "geometry": {"coordinates":[-88.077414,42.05549],"type":"Point"}
}