{
  "type": "Feature",
  "properties": {
    "iso:country":"US",
    "sg:address":"7727 60th Ave",
    "sg:city":"Kenosha",
    "sg:classifiers":[
        {
            "category":"Recreation",
            "type":"Entertainment"
        }
    ],
    "sg:phone":"+1 262 694 8010",
    "sg:postcode":"53142",
    "sg:province":"IL",
    "sg:tags":[
        "repair",
        "eating"
    ],
    "wof:name":"Kenosha Ice Rink",
    "wof:placetype":"venue"
},
  "geometry": {"coordinates":[-87.880169,42.562765],"type":"Point"}
}