{
  "type": "Feature",
  "properties": {
    "addr:full":"39 N Union St Elgin IL 60123",
    "addr:housenumber":"39",
    "addr:postcode":"60123",
    "addr:street":"N Union St",
    "iso:country":"US",
    "sg:address":"39 N Union St",
    "sg:city":"Elgin",
    "sg:classifiers":[
        {
            "category":"Building & Trades",
            "subcategory":"Plumbing",
            "type":"Services"
        }
    ],
    "sg:phone":"+1 847 931 7330",
    "sg:postcode":"60123",
    "sg:province":"IL",
    "sg:tags":[
        "plumbing",
        "contractor"
    ],
    "wof:name":"Joe Bero Plumbing",
    "wof:placetype":"venue"
},
  "geometry": {"coordinates":[-88.296329,42.035538],"type":"Point"}
}