{
  "type": "Feature",
  "properties": {
    "addr:full":"402 S Galena Ave Dixon IL 61021",
    "addr:housenumber":"402",
    "addr:postcode":"61021",
    "addr:street":"S Galena Ave",
    "iso:country":"US",
    "sg:address":"402 S Galena Ave",
    "sg:city":"Dixon",
    "sg:classifiers":[
        {
            "category":"Banks & Credit Unions",
            "subcategory":"Bank",
            "type":"Services"
        }
    ],
    "sg:phone":"+1 815 288 3327",
    "sg:postcode":"61021",
    "sg:province":"IL",
    "sg:website":"www.sterlingfederal.com",
    "wof:name":"Sterling Federal Bank",
    "wof:placetype":"venue"
},
  "geometry": {"coordinates":[-89.481376,41.84078],"type":"Point"}
}