{
  "type": "Feature",
  "properties": {
    "iso:country":"US",
    "sg:address":"9415 Ogden Ave",
    "sg:city":"Brookfield",
    "sg:classifiers":[
        {
            "category":"Recreation",
            "subcategory":"Arcade",
            "type":"Entertainment"
        }
    ],
    "sg:phone":"+1 708 485 4700",
    "sg:postcode":"60513",
    "sg:province":"IL",
    "sg:tags":[
        "game",
        "video"
    ],
    "sg:website":"www.gallopingghostarcade.com/",
    "wof:name":"Galloping Ghost Arcade",
    "wof:placetype":"venue"
},
  "geometry": {"coordinates":[-87.855835,41.817162],"type":"Point"}
}