{
  "type": "Feature",
  "properties": {
    "iso:country":"US",
    "sg:address":"535 N 2nd Ave",
    "sg:city":"Carbon Cliff",
    "sg:classifiers":[
        {
            "category":"Building & Trades",
            "subcategory":"Construction",
            "type":"Services"
        }
    ],
    "sg:phone":"+1 309 792 8311",
    "sg:postcode":"61239",
    "sg:province":"IL",
    "sg:tags":[
        "excavating",
        "contractor"
    ],
    "wof:name":"Mc Dowell Excavating Inc",
    "wof:placetype":"venue"
},
  "geometry": {"coordinates":[-90.389826,41.490891],"type":"Point"}
}