{
  "type": "Feature",
  "properties": {
    "addr:full":"801 N Quentin Rd Palatine IL 60067",
    "addr:housenumber":"801",
    "addr:postcode":"60067",
    "addr:street":"N Quentin Rd",
    "iso:country":"US",
    "sg:address":"801 N Quentin Rd",
    "sg:city":"Palatine",
    "sg:classifiers":[
        {
            "category":"Restaurant",
            "type":"Food & Drink"
        }
    ],
    "sg:phone":"+1   ",
    "sg:postcode":"60067",
    "sg:province":"IL",
    "wof:name":"Sun Kwong Chop Suey Inc",
    "wof:placetype":"venue"
},
  "geometry": {"coordinates":[-88.063039,42.123876],"type":"Point"}
}