{
  "type": "Feature",
  "properties": {
    "addr:full":"2855 N Richmond St Chicago IL 60618",
    "addr:housenumber":"2855",
    "addr:postcode":"60618",
    "addr:street":"N Richmond St",
    "iso:country":"US",
    "sg:address":"2855 N Richmond St",
    "sg:city":"Chicago",
    "sg:classifiers":[
        {
            "category":"Real Estate",
            "subcategory":"Real Estate Services",
            "type":"Services"
        }
    ],
    "sg:phone":"+1 773 342 7556",
    "sg:postcode":"60618",
    "sg:province":"IL",
    "sg:tags":[
        "inspection"
    ],
    "sg:website":"http://www.propertyinspectionsva.com",
    "wof:name":"Property Inspections Of Chicago Inc",
    "wof:placetype":"venue"
},
  "geometry": {"coordinates":[-87.70129900000001,41.933082],"type":"Point"}
}