{
  "type": "Feature",
  "properties": {
    "addr:full":"1500 Washington Ave Cairo IL 62914",
    "addr:housenumber":"1500",
    "addr:postcode":"62914",
    "addr:street":"Washington Ave",
    "iso:country":"US",
    "sg:address":"1500 Washington Ave",
    "sg:city":"Cairo",
    "sg:classifiers":[
        {
            "category":"Professional",
            "subcategory":"Accounting & Tax Preparation",
            "type":"Services"
        }
    ],
    "sg:phone":"+1 618 734 9660",
    "sg:postcode":"62914",
    "sg:province":"IL",
    "sg:tags":[
        "return",
        "filing"
    ],
    "wof:name":"Patricia's Multi Svc",
    "wof:placetype":"venue"
},
  "geometry": {"coordinates":[-89.17316,37.003205],"type":"Point"}
}