{
  "type": "Feature",
  "properties": {
    "iso:country":"US",
    "sg:address":"9750 S Seeley Ave",
    "sg:city":"Chicago",
    "sg:classifiers":[
        {
            "category":"Freight",
            "type":"Transportation"
        }
    ],
    "sg:phone":"+1 773 239 2780",
    "sg:postcode":"60643",
    "sg:province":"IL",
    "sg:tags":[
        "operator",
        "truck",
        "local",
        "dump",
        "trucking"
    ],
    "wof:name":"Mcduffie, M J & Jason Cook Inc",
    "wof:placetype":"venue"
},
  "geometry": {"coordinates":[-87.673446,41.716483],"type":"Point"}
}