{
  "type": "Feature",
  "properties": {
    "iso:country":"US",
    "sg:address":"3265 W Palmer St",
    "sg:city":"Chicago",
    "sg:classifiers":[
        {
            "category":"Professional",
            "type":"Services"
        }
    ],
    "sg:phone":"+1 773 278 8946",
    "sg:postcode":"60647",
    "sg:province":"IL",
    "wof:name":"Wordzwork",
    "wof:placetype":"venue"
},
  "geometry": {"coordinates":[-87.710037,41.920949],"type":"Point"}
}