{
  "type": "Feature",
  "properties": {
    "addr:full":"19 N Hickory Ave Arlington Heights IL 60004",
    "addr:housenumber":"19",
    "addr:postcode":"60004",
    "addr:street":"N Hickory Ave",
    "iso:country":"US",
    "sg:address":"19 N Hickory Ave",
    "sg:city":"Arlington Heights",
    "sg:classifiers":[
        {
            "category":"Building & Trades",
            "subcategory":"Electrical",
            "type":"Services"
        }
    ],
    "sg:phone":"+1 847 392 2664",
    "sg:postcode":"60004",
    "sg:province":"IL",
    "sg:tags":[
        "electrical",
        "contractor"
    ],
    "wof:name":"Hintz Electrik Company Inc",
    "wof:placetype":"venue"
},
  "geometry": {"coordinates":[-87.974326,42.083013],"type":"Point"}
}