{
  "type": "Feature",
  "properties": {
    "addr:full":"9S181 Stearman Dr Naperville IL 60564",
    "addr:housenumber":"9s181",
    "addr:postcode":"60564",
    "addr:street":"Stearman Dr",
    "iso:country":"US",
    "sg:address":"9S181 Stearman Dr",
    "sg:city":"Naperville",
    "sg:classifiers":[
        {
            "category":"Shopping",
            "subcategory":"Pets & Pet Supplies",
            "type":"Retail Goods"
        },
        {
            "category":"Retail",
            "subcategory":"Animal Services",
            "type":"Services"
        }
    ],
    "sg:phone":"+1 630 961 3926",
    "sg:postcode":"60564",
    "sg:province":"IL",
    "sg:tags":[
        "grooming",
        "exercising",
        "cat",
        "dog",
        "sitting"
    ],
    "wof:name":"Pet Set",
    "wof:placetype":"venue"
},
  "geometry": {"coordinates":[-88.201534,41.73629],"type":"Point"}
}