{
  "type": "Feature",
  "properties": {
    "addr:full":"5522 Elevator Rd Roscoe IL 61073",
    "addr:housenumber":"5522",
    "addr:postcode":"61073",
    "addr:street":"Elevator Rd",
    "iso:country":"US",
    "sg:address":"5522 Elevator Rd",
    "sg:city":"Roscoe",
    "sg:classifiers":[
        {
            "category":"Restaurant",
            "type":"Food & Drink"
        }
    ],
    "sg:phone":"+1 815 623 8226",
    "sg:postcode":"61073",
    "sg:province":"IL",
    "wof:name":"Sabrosa, Inc.",
    "wof:placetype":"venue"
},
  "geometry": {"coordinates":[-89.00909900000001,42.427583],"type":"Point"}
}