{
  "type": "Feature",
  "properties": {
    "iso:country":"US",
    "sg:address":"29 Cherry Ln",
    "sg:city":"Bourbonnais",
    "sg:classifiers":[
        {
            "category":"Organizations",
            "subcategory":"Labor Organization",
            "type":"Services"
        }
    ],
    "sg:phone":"+1 815 936 1513",
    "sg:postcode":"60914",
    "sg:province":"IL",
    "wof:name":"Cte Engineering",
    "wof:placetype":"venue"
},
  "geometry": {"coordinates":[-87.871186,41.194433],"type":"Point"}
}