{
  "type": "Feature",
  "properties": {
    "addr:full":"1437 S Bell School Rd Rockford IL 61108",
    "addr:housenumber":"1437",
    "addr:postcode":"61108",
    "addr:street":"S Bell School Rd",
    "iso:country":"US",
    "sg:address":"1437 S Bell School Rd",
    "sg:city":"Rockford",
    "sg:classifiers":[
        {
            "category":"Wholesale",
            "subcategory":"Toys & Hobbies",
            "type":"Manufacturing & Wholesale Goods"
        }
    ],
    "sg:phone":"+1 815 227 4490",
    "sg:postcode":"61108",
    "sg:province":"IL",
    "sg:tags":[
        "game",
        "supply"
    ],
    "wof:name":"Great Ship LTD",
    "wof:placetype":"venue"
},
  "geometry": {"coordinates":[-88.970359,42.255241],"type":"Point"}
}