{
  "type": "Feature",
  "properties": {
    "iso:country":"US",
    "sg:address":"4708 8th Ave",
    "sg:city":"Moline",
    "sg:classifiers":[
        {
            "category":"Recreation",
            "type":"Entertainment"
        }
    ],
    "sg:phone":"+1 309 762 0238",
    "sg:postcode":"61265",
    "sg:province":"IL",
    "wof:name":"Spellious Tae Kwon Do",
    "wof:placetype":"venue"
},
  "geometry": {"coordinates":[-90.470544,41.506912],"type":"Point"}
}