{
  "type": "Feature",
  "properties": {
    "iso:country":"US",
    "sg:address":"20770 N Weatherstone Dr",
    "sg:city":"Kildeer",
    "sg:classifiers":[
        {
            "category":"Professional",
            "subcategory":"Business Services",
            "type":"Services"
        }
    ],
    "sg:phone":"+1 847 438 3790",
    "sg:postcode":"60047",
    "sg:province":"IL",
    "sg:tags":[
        "interior",
        "consultant",
        "design",
        "decorator"
    ],
    "wof:name":"Jane Irvine Interior Design",
    "wof:placetype":"venue"
},
  "geometry": {"coordinates":[-88.044876,42.165179],"type":"Point"}
}