{
  "type": "Feature",
  "properties": {
    "iso:country":"US",
    "sg:address":"1238 E 46th St",
    "sg:city":"Chicago",
    "sg:classifiers":[
        {
            "category":"Social Services",
            "type":"Services"
        }
    ],
    "sg:phone":"+1 773 548 7500",
    "sg:postcode":"60653",
    "sg:province":"IL",
    "sg:tags":[
        "center"
    ],
    "wof:name":"Koco",
    "wof:placetype":"venue"
},
  "geometry": {"coordinates":[-87.596854,41.810719],"type":"Point"}
}