{
  "type": "Feature",
  "properties": {
    "addr:full":"1238 E 46th St Chicago IL 60653",
    "addr:housenumber":"1238",
    "addr:postcode":"60653",
    "addr:street":"E 46Th St",
    "iso:country":"US",
    "sg:address":"1238 E 46th St",
    "sg:city":"Chicago",
    "sg:classifiers":[
        {
            "category":"Social Services",
            "type":"Services"
        }
    ],
    "sg:phone":"+1 773 548 7500",
    "sg:postcode":"60653",
    "sg:province":"IL",
    "sg:tags":[
        "center"
    ],
    "wof:name":"Koco",
    "wof:placetype":"venue"
},
  "geometry": {"coordinates":[-87.59685399999999,41.810719],"type":"Point"}
}