{
  "type": "Feature",
  "properties": {
    "iso:country":"US",
    "sg:address":"84 E Burlington St",
    "sg:city":"Riverside",
    "sg:classifiers":[
        {
            "category":"Professional",
            "subcategory":"Lawyer & Legal Services",
            "type":"Services"
        }
    ],
    "sg:phone":"+1 708 442 5215",
    "sg:postcode":"60546",
    "sg:province":"IL",
    "wof:name":"Fernandez Norma Atty",
    "wof:placetype":"venue"
},
  "geometry": {"coordinates":[-87.815804,41.8288],"type":"Point"}
}