{
  "type": "Feature",
  "properties": {
    "iso:country":"US",
    "sg:address":"1847 W Carroll Avenue",
    "sg:city":"Chicago",
    "sg:classifiers":[
        {
            "category":"Wholesale",
            "subcategory":"Fruits & Vegetables",
            "type":"Manufacturing & Wholesale Goods"
        },
        {
            "category":"Food & Beverages",
            "subcategory":"Meat & Fish",
            "type":"Retail Goods"
        }
    ],
    "sg:phone":"+1 312 491 3010",
    "sg:postcode":"60612",
    "sg:province":"IL",
    "sg:tags":[
        "seafood",
        "veggie",
        "market"
    ],
    "wof:name":"Martinez Products",
    "wof:placetype":"venue"
},
  "geometry": {"coordinates":[-87.672889,41.887625],"type":"Point"}
}