{
  "type": "Feature",
  "properties": {
    "iso:country":"US",
    "sg:address":"300 N Broadway",
    "sg:city":"St Louis",
    "sg:classifiers":[
        {
            "category":"Home & Garden",
            "subcategory":"Home Furnishings",
            "type":"Retail Goods"
        },
        {
            "category":"Home & Garden",
            "subcategory":"Furniture",
            "type":"Retail Goods"
        }
    ],
    "sg:phone":"+1 314 621 8131",
    "sg:postcode":"63102",
    "sg:province":"MO",
    "sg:tags":[
        "decor",
        "store"
    ],
    "sg:website":"www.nichestl.com",
    "wof:name":"Niche Furnishing and Design",
    "wof:placetype":"venue"
},
  "geometry": {"coordinates":[-90.188661,38.627798],"type":"Point"}
}