{
  "type": "Feature",
  "properties": {
    "addr:full":"110 Wauponsee St Morris IL 60450",
    "addr:housenumber":"110",
    "addr:postcode":"60450",
    "addr:street":"Wauponsee St",
    "iso:country":"US",
    "sg:address":"110 Wauponsee St",
    "sg:city":"Morris",
    "sg:classifiers":[
        {
            "category":"Restaurant",
            "type":"Food & Drink"
        }
    ],
    "sg:phone":"+1 815 942 5675",
    "sg:postcode":"60450",
    "sg:province":"IL",
    "sg:tags":[
        "eating"
    ],
    "wof:name":"Sam's Pizza",
    "wof:placetype":"venue"
},
  "geometry": {"coordinates":[-88.425054,41.357221],"type":"Point"}
}