{
  "type": "Feature",
  "properties": {
    "addr:full":"547 Bittersweet Trl Crystal Lake IL 60014",
    "addr:housenumber":"547",
    "addr:postcode":"60014",
    "addr:street":"Bittersweet Trl",
    "iso:country":"US",
    "sg:address":"547 Bittersweet Trl",
    "sg:city":"Crystal Lake",
    "sg:classifiers":[
        {
            "category":"Personal",
            "type":"Services"
        }
    ],
    "sg:phone":"+1 815 455 6003",
    "sg:postcode":"60014",
    "sg:province":"IL",
    "wof:name":"Heartfelt Massage Therapy",
    "wof:placetype":"venue"
},
  "geometry": {"coordinates":[-88.29954600000001,42.243945],"type":"Point"}
}