{
  "type": "Feature",
  "properties": {
    "addr:full":"306 Tiffany Ct Champaign IL 61822",
    "addr:housenumber":"306",
    "addr:postcode":"61822",
    "addr:street":"Tiffany Ct",
    "iso:country":"US",
    "sg:address":"306 Tiffany Ct",
    "sg:city":"Champaign",
    "sg:classifiers":[
        {
            "category":"Manufacturing",
            "subcategory":"Tools & Machinery",
            "type":"Manufacturing & Wholesale Goods"
        }
    ],
    "sg:phone":"+1 217 352 6983",
    "sg:postcode":"61822",
    "sg:province":"IL",
    "sg:tags":[
        "machine",
        "shop"
    ],
    "wof:name":"Delton's Cycle Machine Shop",
    "wof:placetype":"venue"
},
  "geometry": {"coordinates":[-88.317958,40.114493],"type":"Point"}
}