{
  "type": "Feature",
  "properties": {
    "addr:full":"1207 N Monroe St Marion IL 62959",
    "addr:housenumber":"1207",
    "addr:postcode":"62959",
    "addr:street":"N Monroe St",
    "iso:country":"US",
    "sg:address":"1207 N Monroe St",
    "sg:city":"Marion",
    "sg:classifiers":[
        {
            "category":"Home & Garden",
            "subcategory":"Home Furnishings",
            "type":"Retail Goods"
        }
    ],
    "sg:phone":"+1 618 993 1608",
    "sg:postcode":"62959",
    "sg:province":"IL",
    "sg:tags":[
        "candle"
    ],
    "wof:name":"Fragrant Memories Candle Shoppe",
    "wof:placetype":"venue"
},
  "geometry": {"coordinates":[-88.929715,37.741022],"type":"Point"}
}