{
  "type": "Feature",
  "properties": {
    "addr:full":"1645 W Jackson Blvd Chicago IL 60612",
    "addr:housenumber":"1645",
    "addr:postcode":"60612",
    "addr:street":"W Jackson Blvd",
    "iso:country":"US",
    "sg:address":"1645 W Jackson Blvd",
    "sg:city":"Chicago",
    "sg:classifiers":[
        {
            "category":"Health Services",
            "subcategory":"Medical Lab",
            "type":"Services"
        }
    ],
    "sg:phone":"+1 312 942 3368",
    "sg:postcode":"60612",
    "sg:province":"IL",
    "wof:name":"Metropolitan Chicago Breast Cancer Task Force",
    "wof:placetype":"venue"
},
  "geometry": {"coordinates":[-87.66797699999999,41.877605],"type":"Point"}
}