{
  "type": "Feature",
  "properties": {
    "iso:country":"US",
    "sg:address":"544 Lakeview Pkwy",
    "sg:city":"Vernon Hills",
    "sg:classifiers":[
        {
            "category":"Insurance",
            "subcategory":"Life Insurance",
            "type":"Services"
        }
    ],
    "sg:phone":"+1 847 247 6500",
    "sg:postcode":"60061",
    "sg:province":"IL",
    "sg:tags":[
        "company"
    ],
    "wof:name":"Allstate",
    "wof:placetype":"venue"
},
  "geometry": {"coordinates":[-87.94960399999999,42.236214],"type":"Point"}
}