{
  "type": "Feature",
  "properties": {
    "addr:full":"7977 Lake St River Forest IL 60305",
    "addr:housenumber":"7977",
    "addr:postcode":"60305",
    "addr:street":"Lake St",
    "iso:country":"US",
    "sg:address":"7977 Lake St",
    "sg:city":"River Forest",
    "sg:classifiers":[
        {
            "category":"Insurance",
            "subcategory":"Insurance Agent",
            "type":"Services"
        }
    ],
    "sg:phone":"+1 708 488 1110",
    "sg:postcode":"60305",
    "sg:province":"IL",
    "wof:name":"C & L Acceptance Corp",
    "wof:placetype":"venue"
},
  "geometry": {"coordinates":[-87.82432799999999,41.888058],"type":"Point"}
}