{
  "type": "Feature",
  "properties": {
    "addr:full":"108 E Hawthorne Dr Effingham IL 62401",
    "addr:housenumber":"108",
    "addr:postcode":"62401",
    "addr:street":"E Hawthorne Dr",
    "iso:country":"US",
    "sg:address":"108 E Hawthorne Dr",
    "sg:city":"Effingham",
    "sg:classifiers":[
        {
            "category":"Shopping",
            "subcategory":"Pharmacy",
            "type":"Retail Goods"
        }
    ],
    "sg:phone":"+1 217 347 7764",
    "sg:postcode":"62401",
    "sg:province":"IL",
    "sg:website":"www.brownsdrugstore.com",
    "wof:name":"Brown's Drug Stores",
    "wof:placetype":"venue"
},
  "geometry": {"coordinates":[-88.541296,39.097474],"type":"Point"}
}