{
  "type": "Feature",
  "properties": {
    "addr:full":"3700 Mannheim Rd Franklin Park IL 60131",
    "addr:housenumber":"3700",
    "addr:postcode":"60131",
    "addr:street":"Mannheim Rd",
    "iso:country":"US",
    "sg:address":"3700 Mannheim Rd",
    "sg:city":"Franklin Park",
    "sg:classifiers":[
        {
            "category":"Parking",
            "type":"Transportation"
        }
    ],
    "sg:phone":"+1 847 678 7275",
    "sg:postcode":"60131",
    "sg:province":"IL",
    "sg:tags":[
        "garage"
    ],
    "sg:website":"www.avistar.com",
    "wof:name":"Avistar Airport Parking",
    "wof:placetype":"venue"
},
  "geometry": {"coordinates":[-87.885395,41.945561],"type":"Point"}
}