{
  "type": "Feature",
  "properties": {
    "addr:full":"1955 N Damen Ave Chicago IL 60647",
    "addr:housenumber":"1955",
    "addr:postcode":"60647",
    "addr:street":"N Damen Ave",
    "iso:country":"US",
    "sg:address":"1955 N Damen Ave",
    "sg:city":"Chicago",
    "sg:classifiers":[
        {
            "category":"Banks & Credit Unions",
            "subcategory":"Bank",
            "type":"Services"
        }
    ],
    "sg:phone":"+1 773 665 5000",
    "sg:postcode":"60647",
    "sg:province":"IL",
    "wof:name":"Mid America Bank Fsb",
    "wof:placetype":"venue"
},
  "geometry": {"coordinates":[-87.677525,41.917095],"type":"Point"}
}