{
  "type": "Feature",
  "properties": {
    "addr:full":"900 N Franklin Street Chicago IL 60610",
    "addr:housenumber":"900",
    "addr:postcode":"60610",
    "addr:street":"N Franklin Street",
    "iso:country":"US",
    "sg:address":"900 N Franklin Street",
    "sg:city":"Chicago",
    "sg:classifiers":[
        {
            "category":"Personal",
            "type":"Services"
        }
    ],
    "sg:phone":"+1 312 951 8581",
    "sg:postcode":"60610",
    "sg:province":"IL",
    "sg:tags":[
        "party",
        "planning",
        "event"
    ],
    "wof:name":"City Access",
    "wof:placetype":"venue"
},
  "geometry": {"coordinates":[-87.63439,41.901525],"type":"Point"}
}