{
  "type": "Feature",
  "properties": {
    "iso:country":"US",
    "sg:address":"8711 Old State Rd",
    "sg:city":"Breese",
    "sg:classifiers":[
        {
            "category":"Farming",
            "subcategory":"Livestock Farm",
            "type":"Manufacturing & Wholesale Goods"
        }
    ],
    "sg:phone":"+1 618 526 7386",
    "sg:postcode":"62230",
    "sg:province":"IL",
    "sg:tags":[
        "hog",
        "or",
        "feedlot"
    ],
    "wof:name":"Paul Timmermann",
    "wof:placetype":"venue"
},
  "geometry": {"coordinates":[-89.553062,38.634582],"type":"Point"}
}