{
  "type": "Feature",
  "properties": {
    "addr:full":"227 E Garfield Blvd Chicago IL 60637",
    "addr:housenumber":"227",
    "addr:postcode":"60637",
    "addr:street":"E Garfield Blvd",
    "iso:country":"US",
    "sg:address":"227 E Garfield Blvd",
    "sg:city":"Chicago",
    "sg:classifiers":[
        {
            "category":"Home & Garden",
            "subcategory":"Hardware",
            "type":"Retail Goods"
        }
    ],
    "sg:phone":"+1 773 363 3178",
    "sg:postcode":"60637",
    "sg:province":"IL",
    "sg:tags":[
        "store"
    ],
    "sg:website":"www.acehardware.com",
    "wof:name":"Boulevard Ace Hardware",
    "wof:placetype":"venue"
},
  "geometry": {"coordinates":[-87.619499,41.794399],"type":"Point"}
}