{
  "type": "Feature",
  "properties": {
    "iso:country":"US",
    "sg:address":"2619 Elisha Ave",
    "sg:city":"Zion",
    "sg:classifiers":[
        {
            "category":"Real Estate",
            "subcategory":"Real Estate Services",
            "type":"Services"
        }
    ],
    "sg:phone":"+1 847 731 0310",
    "sg:postcode":"60099",
    "sg:province":"IL",
    "sg:tags":[
        "management",
        "condominium"
    ],
    "wof:name":"3400 North Janssen Condominium",
    "wof:placetype":"venue"
},
  "geometry": {"coordinates":[-87.826883,42.447565],"type":"Point"}
}