{
  "type": "Feature",
  "properties": {
    "iso:country":"US",
    "sg:address":"1700 N Farnsworth Ave",
    "sg:city":"Aurora",
    "sg:classifiers":[
        {
            "category":"Professional",
            "subcategory":"Lawyer & Legal Services",
            "type":"Services"
        }
    ],
    "sg:phone":"+1 630 820 0333",
    "sg:postcode":"60505",
    "sg:province":"IL",
    "sg:tags":[
        "attorney"
    ],
    "wof:name":"Ruddy & Varga",
    "wof:placetype":"venue"
},
  "geometry": {"coordinates":[-88.282025,41.789413],"type":"Point"}
}