{
  "type": "Feature",
  "properties": {
    "iso:country":"US",
    "sg:address":"1 N County St",
    "sg:city":"Waukegan",
    "sg:classifiers":[
        {
            "category":"Professional",
            "subcategory":"Lawyer & Legal Services",
            "type":"Services"
        }
    ],
    "sg:phone":"+1 847 662 4321",
    "sg:postcode":"60085",
    "sg:province":"IL",
    "sg:tags":[
        "attorney",
        "law",
        "family"
    ],
    "sg:website":"http://rosinglaw.com",
    "wof:name":"Anderson Karissa B",
    "wof:placetype":"venue"
},
  "geometry": {"coordinates":[-87.832657,42.35955],"type":"Point"}
}