{
  "type": "Feature",
  "properties": {
    "addr:full":"100 N Franklin St Dwight IL 60420",
    "addr:housenumber":"100",
    "addr:postcode":"60420",
    "addr:street":"N Franklin St",
    "iso:country":"US",
    "sg:address":"100 N Franklin St",
    "sg:city":"Dwight",
    "sg:classifiers":[
        {
            "category":"Shopping",
            "type":"Retail Goods"
        }
    ],
    "sg:phone":"+1   ",
    "sg:postcode":"60420",
    "sg:province":"IL",
    "sg:tags":[
        "merchandise"
    ],
    "wof:name":"Grieffs Precious Monuments",
    "wof:placetype":"venue"
},
  "geometry": {"coordinates":[-88.42603,41.09466],"type":"Point"}
}