{
  "type": "Feature",
  "properties": {
    "iso:country":"US",
    "sg:address":"310 N Washington St",
    "sg:city":"Salem",
    "sg:classifiers":[
        {
            "category":"Building & Trades",
            "subcategory":"Plumbing",
            "type":"Services"
        }
    ],
    "sg:phone":"+1 618 548 9420",
    "sg:postcode":"62881",
    "sg:province":"IL",
    "sg:tags":[
        "contractor"
    ],
    "wof:name":"Waste Water Management Illi",
    "wof:placetype":"venue"
},
  "geometry": {"coordinates":[-88.944542,38.629271],"type":"Point"}
}