{
  "type": "Feature",
  "properties": {
    "iso:country":"US",
    "sg:address":"21009 52nd Ave N",
    "sg:city":"Port Byron",
    "sg:classifiers":[
        {
            "category":"Building & Trades",
            "subcategory":"Construction",
            "type":"Services"
        }
    ],
    "sg:phone":"+1 309 496 2451",
    "sg:postcode":"61275",
    "sg:province":"IL",
    "sg:tags":[
        "contractor"
    ],
    "wof:name":"Frey Classic Home Builders Inc",
    "wof:placetype":"venue"
},
  "geometry": {"coordinates":[-90.336304,41.570801],"type":"Point"}
}