{
  "type": "Feature",
  "properties": {
    "iso:country":"US",
    "sg:address":"5511 W Diversey Ave",
    "sg:city":"Chicago",
    "sg:classifiers":[
        {
            "category":"Building & Trades",
            "subcategory":"Construction",
            "type":"Services"
        }
    ],
    "sg:phone":"+1 773 622 6060",
    "sg:postcode":"60639",
    "sg:province":"IL",
    "sg:tags":[
        "contractor"
    ],
    "sg:website":"flooring.com",
    "wof:name":"Maras Flooring",
    "wof:placetype":"venue"
},
  "geometry": {"coordinates":[-87.764229,41.931181],"type":"Point"}
}