{
  "type": "Feature",
  "properties": {
    "addr:full":"1514 Mayo Ave Wheaton IL 60187",
    "addr:housenumber":"1514",
    "addr:postcode":"60187",
    "addr:street":"Mayo Ave",
    "iso:country":"US",
    "sg:address":"1514 Mayo Ave",
    "sg:city":"Wheaton",
    "sg:classifiers":[
        {
            "category":"Health Services",
            "subcategory":"Health Practitioner",
            "type":"Services"
        }
    ],
    "sg:phone":"+1 630 510 1198",
    "sg:postcode":"60187",
    "sg:province":"IL",
    "wof:name":"Concord Physical Therapy",
    "wof:placetype":"venue"
},
  "geometry": {"coordinates":[-88.128586,41.851447],"type":"Point"}
}