{
  "type": "Feature",
  "properties": {
    "iso:country":"US",
    "sg:address":"204 Ken St",
    "sg:city":"Dwight",
    "sg:classifiers":[
        {
            "category":"Autos & Motor Vehicles",
            "subcategory":"Automobile Sales",
            "type":"Retail Goods"
        }
    ],
    "sg:phone":"+1 815 281 4739",
    "sg:postcode":"60420",
    "sg:province":"IL",
    "sg:tags":[
        "house",
        "construction"
    ],
    "wof:name":"Paulsen Homebuilders Inc",
    "wof:placetype":"venue"
},
  "geometry": {"coordinates":[-88.414355,41.092064],"type":"Point"}
}