{
  "type": "Feature",
  "properties": {
    "addr:full":"2555 W 95th St Evergreen Park IL 60805",
    "addr:housenumber":"2555",
    "addr:postcode":"60805",
    "addr:street":"W 95Th St",
    "iso:country":"US",
    "sg:address":"2555 W 95th St",
    "sg:city":"Evergreen Park",
    "sg:classifiers":[
        {
            "category":"Restaurant",
            "type":"Food & Drink"
        }
    ],
    "sg:phone":"+1   ",
    "sg:postcode":"60805",
    "sg:province":"IL",
    "sg:tags":[
        "eating"
    ],
    "wof:name":"White Castle",
    "wof:placetype":"venue"
},
  "geometry": {"coordinates":[-87.686167,41.720828],"type":"Point"}
}