{
  "type": "Feature",
  "properties": {
    "addr:full":"3507 Maple Ave Brookfield IL 60513",
    "addr:housenumber":"3507",
    "addr:postcode":"60513",
    "addr:street":"Maple Ave",
    "iso:country":"US",
    "sg:address":"3507 Maple Ave",
    "sg:city":"Brookfield",
    "sg:classifiers":[
        {
            "category":"Insurance",
            "subcategory":"Insurance Agent",
            "type":"Services"
        }
    ],
    "sg:phone":"+1 708 485 1247",
    "sg:postcode":"60513",
    "sg:province":"IL",
    "wof:name":"Carl S Laponte Ins",
    "wof:placetype":"venue"
},
  "geometry": {"coordinates":[-87.85141400000001,41.82697],"type":"Point"}
}