{
  "type": "Feature",
  "properties": {
    "iso:country":"US",
    "sg:address":"2650 W 95th",
    "sg:city":"Oak Lawn",
    "sg:classifiers":[
        {
            "category":"Cinema",
            "subcategory":"Movie Rental",
            "type":"Entertainment"
        }
    ],
    "sg:phone":"+1 708 423 0022",
    "sg:postcode":"60453",
    "sg:province":"IL",
    "sg:tags":[
        "game",
        "video"
    ],
    "wof:name":"Blockbuster Video",
    "wof:placetype":"venue"
},
  "geometry": {"coordinates":[-87.750298,41.715401],"type":"Point"}
}