{
  "type": "Feature",
  "properties": {
    "iso:country":"US",
    "sg:address":"102 E Main St Ste 300",
    "sg:city":"Urbana",
    "sg:classifiers":[
        {
            "category":"Professional",
            "subcategory":"Lawyer & Legal Services",
            "type":"Services"
        }
    ],
    "sg:phone":"+1 217 344 0060",
    "sg:postcode":"61801",
    "sg:province":"IL",
    "wof:name":"Wagner Edward M Atty",
    "wof:placetype":"venue"
},
  "geometry": {"coordinates":[-88.20639799999999,40.112499],"type":"Point"}
}