{
  "type": "Feature",
  "properties": {
    "iso:country":"US",
    "sg:address":"2709 Maple Ave",
    "sg:city":"Lisle",
    "sg:classifiers":[
        {
            "category":"Organizations",
            "subcategory":"Religious Organization",
            "type":"Services"
        }
    ],
    "sg:phone":"+1 630 548 0920",
    "sg:postcode":"60532",
    "sg:province":"IL",
    "sg:tags":[
        "church"
    ],
    "wof:name":"Chicago Church Of Christ",
    "wof:placetype":"venue"
},
  "geometry": {"coordinates":[-88.10693999999999,41.779713],"type":"Point"}
}