{
  "type": "Feature",
  "properties": {
    "iso:country":"US",
    "sg:address":"2412 Georgetown Rd",
    "sg:city":"Danville",
    "sg:classifiers":[
        {
            "category":"Autos & Motor Vehicles",
            "subcategory":"Automobile Sales",
            "type":"Retail Goods"
        }
    ],
    "sg:phone":"+1 217 431 8585",
    "sg:postcode":"61832",
    "sg:province":"IL",
    "sg:tags":[
        "car",
        "dealer"
    ],
    "wof:name":"Raceway Auto Sales",
    "wof:placetype":"venue"
},
  "geometry": {"coordinates":[-87.63506700000001,40.079544],"type":"Point"}
}