{
  "type": "Feature",
  "properties": {
    "iso:country":"US",
    "sg:address":"22 W Connacht Rd",
    "sg:city":"Lemont",
    "sg:classifiers":[
        {
            "category":"Building & Trades",
            "subcategory":"Construction",
            "type":"Services"
        }
    ],
    "sg:phone":"+1 708 479 4051",
    "sg:postcode":"60439",
    "sg:province":"IL",
    "sg:tags":[
        "house"
    ],
    "wof:name":"Castletown Homes Inc",
    "wof:placetype":"venue"
},
  "geometry": {"coordinates":[-88.007579,41.652913],"type":"Point"}
}