{
  "type": "Feature",
  "properties": {
    "iso:country":"US",
    "sg:address":"3254 Marlboro Rd",
    "sg:city":"Ava",
    "sg:classifiers":[
        {
            "category":"Building & Trades",
            "subcategory":"Landscaping Services",
            "type":"Services"
        }
    ],
    "sg:phone":"+1 618 687 3540",
    "sg:postcode":"62907",
    "sg:province":"IL",
    "wof:name":"Midwest Tree Service",
    "wof:placetype":"venue"
},
  "geometry": {"coordinates":[-89.412699,37.872838],"type":"Point"}
}