{
  "type": "Feature",
  "properties": {
    "iso:country":"US",
    "sg:address":"104 N Monroe St",
    "sg:city":"Rushville",
    "sg:classifiers":[
        {
            "category":"Education",
            "subcategory":"Library",
            "type":"Public Place"
        }
    ],
    "sg:phone":"+1 217 322 3030",
    "sg:postcode":"62681",
    "sg:province":"IL",
    "wof:name":"Rushville Public Library",
    "wof:placetype":"venue"
},
  "geometry": {"coordinates":[-90.565181,40.121457],"type":"Point"}
}