{
  "type": "Feature",
  "properties": {
    "iso:country":"US",
    "sg:address":"1928 12th St",
    "sg:city":"Rockford",
    "sg:classifiers":[
        {
            "category":"Manufacturing",
            "subcategory":"Metals",
            "type":"Manufacturing & Wholesale Goods"
        }
    ],
    "sg:phone":"+1 815 397 5586",
    "sg:postcode":"61104",
    "sg:province":"IL",
    "sg:tags":[
        "machine",
        "screw",
        "product",
        "mfg"
    ],
    "wof:name":"Sharon Screw Products",
    "wof:placetype":"venue"
},
  "geometry": {"coordinates":[-89.070368,42.246356],"type":"Point"}
}