{
  "type": "Feature",
  "properties": {
    "iso:country":"US",
    "sg:address":"220 S Emmett St",
    "sg:city":"Genoa",
    "sg:classifiers":[
        {
            "category":"Building & Trades",
            "subcategory":"Construction",
            "type":"Services"
        }
    ],
    "sg:phone":"+1 815 784 4651",
    "sg:postcode":"60135",
    "sg:province":"IL",
    "sg:tags":[
        "contractor"
    ],
    "wof:name":"Experience Tile Services",
    "wof:placetype":"venue"
},
  "geometry": {"coordinates":[-88.69514,42.09615],"type":"Point"}
}