{
  "type": "Feature",
  "properties": {
    "addr:full":"27861 Irma Lee Cir Lake Forest IL 60045",
    "addr:postcode":"27861;60045",
    "addr:street":"Lee Cir",
    "iso:country":"US",
    "sg:address":"27861 Irma Lee Cir",
    "sg:city":"Lake Forest",
    "sg:classifiers":[
        {
            "category":"Building & Trades",
            "subcategory":"Electrical",
            "type":"Services"
        }
    ],
    "sg:phone":"+1 847 247 4800",
    "sg:postcode":"60045",
    "sg:province":"IL",
    "sg:tags":[
        "home",
        "system",
        "automation"
    ],
    "sg:website":"www.allsmartsolutions.com",
    "wof:name":"Allsmart Solutions Inc",
    "wof:placetype":"venue"
},
  "geometry": {"coordinates":[-87.901619,42.26641],"type":"Point"}
}