{
  "type": "Feature",
  "properties": {
    "iso:country":"US",
    "sg:address":"1441 Lawrence Ave",
    "sg:city":"Lake Forest",
    "sg:classifiers":[
        {
            "category":"Shopping",
            "subcategory":"Clothing, Apparel, & Fashions",
            "type":"Retail Goods"
        }
    ],
    "sg:phone":"+1 847 295 8700",
    "sg:postcode":"60045",
    "sg:province":"IL",
    "wof:name":"Hjerthejem",
    "wof:placetype":"venue"
},
  "geometry": {"coordinates":[-87.884062,42.217434],"type":"Point"}
}