{
  "type": "Feature",
  "properties": {
    "addr:full":"5310 S Archer Ave Chicago IL 60632",
    "addr:housenumber":"5310",
    "addr:postcode":"60632",
    "addr:street":"S Archer Ave",
    "iso:country":"US",
    "sg:address":"5310 S Archer Ave",
    "sg:city":"Chicago",
    "sg:classifiers":[
        {
            "category":"Retail",
            "subcategory":"Repair Shop",
            "type":"Services"
        },
        {
            "category":"Shopping",
            "subcategory":"Computers & Home Electronics",
            "type":"Retail Goods"
        }
    ],
    "sg:phone":"+1 773 767 3653",
    "sg:postcode":"60632",
    "sg:province":"IL",
    "sg:tags":[
        "television",
        "radio-service"
    ],
    "sg:website":"http://archerelectronics.com",
    "wof:name":"Archer Electronics",
    "wof:placetype":"venue"
},
  "geometry": {"coordinates":[-87.7397,41.799198],"type":"Point"}
}