{
  "type": "Feature",
  "properties": {
    "iso:country":"US",
    "sg:address":"4032 N Kostner Ave",
    "sg:city":"Chicago",
    "sg:classifiers":[
        {
            "category":"Professional",
            "subcategory":"Computer Services",
            "type":"Services"
        }
    ],
    "sg:phone":"+1 773 202 9922",
    "sg:postcode":"60641",
    "sg:province":"IL",
    "sg:tags":[
        "datum"
    ],
    "wof:name":"London Net Studio",
    "wof:placetype":"venue"
},
  "geometry": {"coordinates":[-87.738264,41.956994],"type":"Point"}
}