{
  "type": "Feature",
  "properties": {
    "addr:full":"2425 Oakton St Evanston IL 60202",
    "addr:housenumber":"2425",
    "addr:postcode":"60202",
    "addr:street":"Oakton St",
    "iso:country":"US",
    "sg:address":"2425 Oakton St",
    "sg:city":"Evanston",
    "sg:classifiers":[
        {
            "category":"Manufacturing",
            "subcategory":"Jewelry",
            "type":"Manufacturing & Wholesale Goods"
        }
    ],
    "sg:phone":"+1 847 570 4700",
    "sg:postcode":"60202",
    "sg:province":"IL",
    "sg:tags":[
        "stone",
        "made",
        "mfg",
        "metal",
        "precious",
        "fine"
    ],
    "wof:name":"Harold J Ziegler",
    "wof:placetype":"venue"
},
  "geometry": {"coordinates":[-87.707195,42.026345],"type":"Point"}
}