{
  "type": "Feature",
  "properties": {
    "iso:country":"US",
    "sg:address":"5906 W 87th St",
    "sg:city":"Burbank",
    "sg:classifiers":[
        {
            "category":"Shopping",
            "subcategory":"Comic Books",
            "type":"Retail Goods"
        }
    ],
    "sg:phone":"+1 708 636 0944",
    "sg:postcode":"60459",
    "sg:province":"IL",
    "wof:name":"Rbi Sports Cards & Comics",
    "wof:placetype":"venue"
},
  "geometry": {"coordinates":[-87.7687,41.7341],"type":"Point"}
}