{
  "type": "Feature",
  "properties": {
    "iso:country":"US",
    "sg:address":"2637 N Cogan Ln",
    "sg:city":"Galena",
    "sg:classifiers":[
        {
            "category":"Shopping",
            "subcategory":"Florist",
            "type":"Retail Goods"
        }
    ],
    "sg:phone":"+1   ",
    "sg:postcode":"61036",
    "sg:province":"IL",
    "wof:name":"Cedardale Farm Flowers",
    "wof:placetype":"venue"
},
  "geometry": {"coordinates":[-90.302328,42.409167],"type":"Point"}
}