{
  "type": "Feature",
  "properties": {
    "addr:full":"2034 Ridge Rd Homewood IL 60430",
    "addr:housenumber":"2034",
    "addr:postcode":"60430",
    "addr:street":"Ridge Rd",
    "iso:country":"US",
    "sg:address":"2034 Ridge Rd",
    "sg:city":"Homewood",
    "sg:classifiers":[
        {
            "category":"Insurance",
            "subcategory":"Insurance Agent",
            "type":"Services"
        }
    ],
    "sg:phone":"+1 708 798 2009",
    "sg:postcode":"60430",
    "sg:province":"IL",
    "sg:website":"www.doerflerinsurance.com",
    "wof:name":"Doerfler Insurance Inc",
    "wof:placetype":"venue"
},
  "geometry": {"coordinates":[-87.667613,41.562135],"type":"Point"}
}