{
  "type": "Feature",
  "properties": {
    "addr:full":"8430 S Indiana Avenue Chicago IL 60619",
    "addr:housenumber":"8430",
    "addr:postcode":"60619",
    "addr:street":"S Indiana Avenue",
    "iso:country":"US",
    "sg:address":"8430 S Indiana Avenue",
    "sg:city":"Chicago",
    "sg:classifiers":[
        {
            "category":"Social Services",
            "subcategory":"Child Care",
            "type":"Services"
        }
    ],
    "sg:phone":"+1 773 488 8850",
    "sg:postcode":"60619",
    "sg:province":"IL",
    "sg:tags":[
        "day"
    ],
    "wof:name":"Lil-Peoples Palace Day Care",
    "wof:placetype":"venue"
},
  "geometry": {"coordinates":[-87.619569,41.740843],"type":"Point"}
}