{
  "type": "Feature",
  "properties": {
    "addr:full":"4658 S California Ave Chicago IL 60632",
    "addr:housenumber":"4658",
    "addr:postcode":"60632",
    "addr:street":"S California Ave",
    "iso:country":"US",
    "sg:address":"4658 S California Ave",
    "sg:city":"Chicago",
    "sg:classifiers":[
        {
            "category":"Autos & Motor Vehicles",
            "subcategory":"Fuel & Gas Station",
            "type":"Retail Goods"
        }
    ],
    "sg:phone":"+1 773 523 9907",
    "sg:postcode":"60632",
    "sg:province":"IL",
    "wof:name":"My Management Inc",
    "wof:placetype":"venue"
},
  "geometry": {"coordinates":[-87.69409899999999,41.8009],"type":"Point"}
}