{
  "type": "Feature",
  "properties": {
    "iso:country":"US",
    "sg:address":"10 S State St",
    "sg:city":"Elgin",
    "sg:classifiers":[
        {
            "category":"Food & Beverages",
            "subcategory":"Groceries & Convenience Stores",
            "type":"Retail Goods"
        }
    ],
    "sg:phone":"+1 847 608 0515",
    "sg:postcode":"60123",
    "sg:province":"IL",
    "sg:tags":[
        "grocer"
    ],
    "wof:name":"J J Peppers Food Store",
    "wof:placetype":"venue"
},
  "geometry": {"coordinates":[-88.286017,42.034524],"type":"Point"}
}