{
  "type": "Feature",
  "properties": {
    "iso:country":"US",
    "sg:address":"2711 Kishwaukee St",
    "sg:city":"Rockford",
    "sg:classifiers":[
        {
            "category":"Autos & Motor Vehicles",
            "subcategory":"Automobile Sales",
            "type":"Retail Goods"
        }
    ],
    "sg:phone":"+1 815 484 9808",
    "sg:postcode":"61109",
    "sg:province":"IL",
    "sg:tags":[
        "dealers-used",
        "car",
        "used",
        "cars-wholesale",
        "new"
    ],
    "wof:name":"Eltri Auto Sales",
    "wof:placetype":"venue"
},
  "geometry": {"coordinates":[-89.086929,42.236313],"type":"Point"}
}