{
  "type": "Feature",
  "properties": {
    "iso:country":"US",
    "sg:address":"1521 Jarvis Ave",
    "sg:city":"Elk Grove Village",
    "sg:classifiers":[
        {
            "category":"Manufacturing",
            "subcategory":"Tools & Machinery",
            "type":"Manufacturing & Wholesale Goods"
        }
    ],
    "sg:phone":"+1 847 357 9192",
    "sg:postcode":"60007",
    "sg:province":"IL",
    "sg:tags":[
        "industrial",
        "mfg"
    ],
    "wof:name":"Whale Mfg Inc",
    "wof:placetype":"venue"
},
  "geometry": {"coordinates":[-87.963393,42.013121],"type":"Point"}
}