{
  "type": "Feature",
  "properties": {
    "addr:full":"6404 N Claremont Ave Chicago IL 60645",
    "addr:housenumber":"6404",
    "addr:postcode":"60645",
    "addr:street":"N Claremont Ave",
    "iso:country":"US",
    "sg:address":"6404 N Claremont Ave",
    "sg:city":"Chicago",
    "sg:classifiers":[
        {
            "category":"Food & Beverages",
            "subcategory":"Groceries & Convenience Stores",
            "type":"Retail Goods"
        }
    ],
    "sg:phone":"+1   ",
    "sg:postcode":"60645",
    "sg:province":"IL",
    "wof:name":"A & J Grocery Store",
    "wof:placetype":"venue"
},
  "geometry": {"coordinates":[-87.688748,41.998098],"type":"Point"}
}