{
  "type": "Feature",
  "properties": {
    "addr:full":"1160 Robey Ave Downers Grove IL 60516",
    "addr:housenumber":"1160",
    "addr:postcode":"60516",
    "addr:street":"Robey Ave",
    "iso:country":"US",
    "sg:address":"1160 Robey Ave",
    "sg:city":"Downers Grove",
    "sg:classifiers":[
        {
            "category":"Professional",
            "subcategory":"Business Services",
            "type":"Services"
        }
    ],
    "sg:phone":"+1 630 719 1865",
    "sg:postcode":"60516",
    "sg:province":"IL",
    "wof:name":"Nancy S Country Crafts",
    "wof:placetype":"venue"
},
  "geometry": {"coordinates":[-88.01051,41.761245],"type":"Point"}
}