{
  "type": "Feature",
  "properties": {
    "addr:full":"2016 Central St Evanston IL 60201",
    "addr:housenumber":"2016",
    "addr:postcode":"60201",
    "addr:street":"Central St",
    "iso:country":"US",
    "sg:address":"2016 Central St",
    "sg:city":"Evanston",
    "sg:classifiers":[
        {
            "category":"Shopping",
            "subcategory":"Used Merchandise",
            "type":"Retail Goods"
        }
    ],
    "sg:phone":"+1 847 475 2300",
    "sg:postcode":"60201",
    "sg:province":"IL",
    "sg:tags":[
        "antique"
    ],
    "wof:name":"Etienne Vintage Home & Lghtg",
    "wof:placetype":"venue"
},
  "geometry": {"coordinates":[-87.701905,42.064281],"type":"Point"}
}