{
  "type": "Feature",
  "properties": {
    "addr:full":"1004 Claim St Aurora IL 60505",
    "addr:housenumber":"1004",
    "addr:postcode":"60505",
    "addr:street":"Claim St",
    "iso:country":"US",
    "sg:address":"1004 Claim St",
    "sg:city":"Aurora",
    "sg:classifiers":[
        {
            "category":"Autos & Motor Vehicles",
            "subcategory":"Auto Supplies",
            "type":"Retail Goods"
        }
    ],
    "sg:phone":"+1 630 851 3817",
    "sg:postcode":"60505",
    "sg:province":"IL",
    "sg:tags":[
        "transmission",
        "transmissions-other"
    ],
    "sg:website":"http://www.chicagofrontpage.com",
    "wof:name":"Ramirez Transmissions",
    "wof:placetype":"venue"
},
  "geometry": {"coordinates":[-88.291083,41.759753],"type":"Point"}
}