{
  "type": "Feature",
  "properties": {
    "addr:full":"708 S Sangamon Ave Gibson City IL 60936",
    "addr:housenumber":"708",
    "addr:postcode":"60936",
    "addr:street":"S Sangamon Ave",
    "iso:country":"US",
    "sg:address":"708 S Sangamon Ave",
    "sg:city":"Gibson City",
    "sg:classifiers":[
        {
            "category":"Restaurant",
            "type":"Food & Drink"
        }
    ],
    "sg:menulink":"http://www.allmenus.com/il/drummer/126495-subway/menu/",
    "sg:phone":"+1 217 784 8862",
    "sg:postcode":"60936",
    "sg:province":"IL",
    "sg:tags":[
        "american",
        "sandwich"
    ],
    "wof:name":"Subway",
    "wof:placetype":"venue"
},
  "geometry": {"coordinates":[-88.375349,40.458036],"type":"Point"}
}