{
  "type": "Feature",
  "properties": {
    "iso:country":"US",
    "sg:address":"3301 W Evergreen Ave",
    "sg:city":"Chicago",
    "sg:classifiers":[
        {
            "category":"Food & Beverages",
            "subcategory":"Groceries & Convenience Stores",
            "type":"Retail Goods"
        }
    ],
    "sg:phone":"+1 773 384 1350",
    "sg:postcode":"60651",
    "sg:province":"IL",
    "wof:name":"Payless Grocery",
    "wof:placetype":"venue"
},
  "geometry": {"coordinates":[-87.709396,41.905399],"type":"Point"}
}