{
  "type": "Feature",
  "properties": {
    "iso:country":"US",
    "sg:address":"200 Jeffery Ln",
    "sg:city":"Schaumburg",
    "sg:classifiers":[
        {
            "category":"Shopping",
            "subcategory":"Computers & Home Electronics",
            "type":"Retail Goods"
        }
    ],
    "sg:phone":"+1 847 524 6110",
    "sg:postcode":"60193",
    "sg:province":"IL",
    "sg:tags":[
        "software"
    ],
    "wof:name":"Calculated Technologies",
    "wof:placetype":"venue"
},
  "geometry": {"coordinates":[-88.103788,42.022168],"type":"Point"}
}