{
  "type": "Feature",
  "properties": {
    "addr:full":"2775 N Elston Ave Chicago IL 60647",
    "addr:housenumber":"2775",
    "addr:postcode":"60647",
    "addr:street":"N Elston Ave",
    "iso:country":"US",
    "sg:address":"2775 N Elston Ave",
    "sg:city":"Chicago",
    "sg:classifiers":[
        {
            "category":"Restaurant",
            "type":"Food & Drink"
        },
        {
            "category":"Food & Beverages",
            "subcategory":"Meat & Fish",
            "type":"Retail Goods"
        }
    ],
    "sg:phone":"+1 773 772 8100",
    "sg:postcode":"60647",
    "sg:province":"IL",
    "sg:tags":[
        "greek",
        "hot",
        "dog"
    ],
    "wof:name":"Niko's Gyros",
    "wof:placetype":"venue"
},
  "geometry": {"coordinates":[-87.68789700000001,41.931999],"type":"Point"}
}