{
  "type": "Feature",
  "properties": {
    "addr:full":"The Hilton Chicago 720 S Michigan Ave Chicago IL 60605",
    "addr:housenumber":"720",
    "addr:postcode":"60605",
    "addr:street":"S Michigan Ave",
    "iso:country":"US",
    "sg:address":"The Hilton Chicago 720 S Michigan Ave",
    "sg:city":"Chicago",
    "sg:classifiers":[
        {
            "category":"Personal",
            "subcategory":"Beauty Salon",
            "type":"Services"
        },
        {
            "category":"Personal",
            "subcategory":"Nail Salon",
            "type":"Services"
        }
    ],
    "sg:phone":"+1 312 341 9047",
    "sg:postcode":"60605",
    "sg:province":"IL",
    "sg:tags":[
        "hair"
    ],
    "sg:website":"basiahairdesigninc.com/",
    "wof:name":"Basia Hair Design",
    "wof:placetype":"venue"
},
  "geometry": {"coordinates":[-87.62478400000001,41.872526],"type":"Point"}
}