{
  "type": "Feature",
  "properties": {
    "iso:country":"US",
    "sg:address":"1205 Karl Ct",
    "sg:city":"Wauconda",
    "sg:classifiers":[
        {
            "category":"Autos & Motor Vehicles",
            "subcategory":"Auto Supplies",
            "type":"Retail Goods"
        },
        {
            "category":"Wholesale",
            "subcategory":"Auto Parts",
            "type":"Manufacturing & Wholesale Goods"
        }
    ],
    "sg:phone":"+1 847 487 7610",
    "sg:postcode":"60084",
    "sg:province":"IL",
    "sg:tags":[
        "automobile"
    ],
    "wof:name":"Keystone Automotive",
    "wof:placetype":"venue"
},
  "geometry": {"coordinates":[-88.14176999999999,42.281361],"type":"Point"}
}