{
  "type": "Feature",
  "properties": {
    "iso:country":"US",
    "sg:address":"600 E Grand Ave",
    "sg:city":"Chicago",
    "sg:classifiers":[
        {
            "category":"Landmark",
            "subcategory":"Tourist Information",
            "type":"Public Place"
        }
    ],
    "sg:phone":"+1 312 755 0488",
    "sg:postcode":"60611",
    "sg:province":"IL",
    "sg:tags":[
        "promoter",
        "tours-operators"
    ],
    "wof:name":"Bike Chicago Rental & Tours",
    "wof:placetype":"venue"
},
  "geometry": {"coordinates":[-87.609863,41.892109],"type":"Point"}
}