{
  "type": "Feature",
  "properties": {
    "addr:full":"23815 Raymond Dr Crete IL 60417",
    "addr:housenumber":"23815",
    "addr:postcode":"60417",
    "addr:street":"Raymond Dr",
    "iso:country":"US",
    "sg:address":"23815 Raymond Dr",
    "sg:city":"Crete",
    "sg:classifiers":[
        {
            "category":"Building & Trades",
            "subcategory":"Electrical",
            "type":"Services"
        }
    ],
    "sg:phone":"+1 708 672 8184",
    "sg:postcode":"60417",
    "sg:province":"IL",
    "sg:tags":[
        "electric",
        "contractor"
    ],
    "wof:name":"C E Electric Inc",
    "wof:placetype":"venue"
},
  "geometry": {"coordinates":[-87.555651,41.459851],"type":"Point"}
}