{
  "type": "Feature",
  "properties": {
    "addr:full":"1622 4th St Peru IL 61354",
    "addr:housenumber":"1622",
    "addr:postcode":"61354",
    "addr:street":"4Th St",
    "iso:country":"US",
    "sg:address":"1622 4th St",
    "sg:city":"Peru",
    "sg:classifiers":[
        {
            "category":"Wholesale",
            "subcategory":"Sporting Goods",
            "type":"Manufacturing & Wholesale Goods"
        }
    ],
    "sg:phone":"+1 815 224 2851",
    "sg:postcode":"61354",
    "sg:province":"IL",
    "wof:name":"Day Distributing Co",
    "wof:placetype":"venue"
},
  "geometry": {"coordinates":[-89.12755199999999,41.327553],"type":"Point"}
}