{
  "type": "Feature",
  "properties": {
    "addr:full":"2918 N Clark St Chicago IL 60657",
    "addr:housenumber":"2918",
    "addr:postcode":"60657",
    "addr:street":"N Clark St",
    "iso:country":"US",
    "sg:address":"2918 N Clark St",
    "sg:city":"Chicago",
    "sg:classifiers":[
        {
            "category":"Shopping",
            "subcategory":"Used Merchandise",
            "type":"Retail Goods"
        }
    ],
    "sg:phone":"+1 773 296 6630",
    "sg:postcode":"60657",
    "sg:province":"IL",
    "sg:tags":[
        "vintage",
        "consignment"
    ],
    "sg:website":"www.facebook.com/pages/Chicago-I...",
    "wof:name":"Clothes Optional Vintage",
    "wof:placetype":"venue"
},
  "geometry": {"coordinates":[-87.64727499999999,41.935705],"type":"Point"}
}