{
  "type": "Feature",
  "properties": {
    "addr:full":"4224 W Elm St Mchenry IL 60050",
    "addr:housenumber":"4224",
    "addr:postcode":"60050",
    "addr:street":"W Elm St",
    "iso:country":"US",
    "sg:address":"4224 W Elm St",
    "sg:city":"Mchenry",
    "sg:classifiers":[
        {
            "category":"Banks & Credit Unions",
            "subcategory":"Financial Services",
            "type":"Services"
        }
    ],
    "sg:phone":"+1 815 578 9224",
    "sg:postcode":"60050",
    "sg:province":"IL",
    "sg:tags":[
        "loan",
        "alternative",
        "payday"
    ],
    "sg:website":"http://www.cashstore.com/IL/Trademark/yp.com",
    "wof:name":"Cash Store",
    "wof:placetype":"venue"
},
  "geometry": {"coordinates":[-88.27976700000001,42.345952],"type":"Point"}
}