{
  "type": "Feature",
  "properties": {
    "addr:full":"Bldg Bldg 56 Carbondale IL 62901",
    "addr:postcode":"62901",
    "iso:country":"US",
    "sg:address":"Bldg Bldg 56",
    "sg:city":"Carbondale",
    "sg:classifiers":[
        {
            "category":"Education",
            "subcategory":"University",
            "type":"Public Place"
        }
    ],
    "sg:phone":"+1 618 453 2080",
    "sg:postcode":"62901",
    "sg:province":"IL",
    "sg:tags":[
        "college"
    ],
    "sg:website":"www.siuc.edu",
    "wof:name":"Southern Illinois University Carbondale",
    "wof:placetype":"venue"
},
  "geometry": {"coordinates":[-89.20301000000001,37.728417],"type":"Point"}
}