{
  "type": "Feature",
  "properties": {
    "addr:full":"233 W. Huron Street Chicago IL 60610",
    "addr:housenumber":"233",
    "addr:postcode":"60610",
    "addr:street":"W. Huron Street",
    "iso:country":"US",
    "sg:address":"233 W. Huron Street",
    "sg:city":"Chicago",
    "sg:classifiers":[
        {
            "category":"Museum",
            "type":"Entertainment"
        }
    ],
    "sg:phone":"+1 312 654 1968",
    "sg:postcode":"60610",
    "sg:province":"IL",
    "wof:name":"Arms Akimbo",
    "wof:placetype":"venue"
},
  "geometry": {"coordinates":[-87.634804,41.894699],"type":"Point"}
}