{
  "type": "Feature",
  "properties": {
    "iso:country":"US",
    "sg:address":"344 E Witchwood Ln",
    "sg:city":"Lake Bluff",
    "sg:classifiers":[
        {
            "category":"Real Estate",
            "subcategory":"Real Estate Agent",
            "type":"Services"
        }
    ],
    "sg:phone":"+1 847 234 3155",
    "sg:postcode":"60044",
    "sg:province":"IL",
    "wof:name":"Forest Bluff Properties LTD",
    "wof:placetype":"venue"
},
  "geometry": {"coordinates":[-87.836752,42.272971],"type":"Point"}
}