{
  "type": "Feature",
  "properties": {
    "iso:country":"US",
    "sg:address":"4 Meadowview Center",
    "sg:city":"Kankakee",
    "sg:classifiers":[
        {
            "category":"Restaurant",
            "type":"Food & Drink"
        }
    ],
    "sg:phone":"+1 815 933 3808",
    "sg:postcode":"60901",
    "sg:province":"IL",
    "sg:tags":[
        "parlor",
        "ice",
        "cream"
    ],
    "wof:name":"Hershey's Ice Cream",
    "wof:placetype":"venue"
},
  "geometry": {"coordinates":[-87.875799,41.135488],"type":"Point"}
}