{
  "type": "Feature",
  "properties": {
    "iso:country":"US",
    "sg:address":"411 Mulberry St",
    "sg:city":"Rockford",
    "sg:classifiers":[
        {
            "category":"Travel",
            "subcategory":"Hotels & Motels",
            "type":"Entertainment"
        }
    ],
    "sg:phone":"+1 815 964 5651",
    "sg:postcode":"61101",
    "sg:province":"IL",
    "sg:tags":[
        "building",
        "owner",
        "apartment",
        "commercial"
    ],
    "wof:name":"Lafayette Hotel",
    "wof:placetype":"venue"
},
  "geometry": {"coordinates":[-89.095236,42.272718],"type":"Point"}
}