{
  "type": "Feature",
  "properties": {
    "addr:full":"123 Collins St Joliet IL 60432",
    "addr:housenumber":"123",
    "addr:postcode":"60432",
    "addr:street":"Collins St",
    "iso:country":"US",
    "sg:address":"123 Collins St",
    "sg:city":"Joliet",
    "sg:classifiers":[
        {
            "category":"Professional",
            "subcategory":"Accounting & Tax Preparation",
            "type":"Services"
        },
        {
            "category":"Banks & Credit Unions",
            "subcategory":"Financial Services",
            "type":"Services"
        }
    ],
    "sg:phone":"+1 815 727 5166",
    "sg:postcode":"60432",
    "sg:province":"IL",
    "sg:tags":[
        "return",
        "preparation-business",
        "taxes-consultants",
        "loan",
        "reporting",
        "representative",
        "alternative",
        "bookkeeping"
    ],
    "sg:website":"http://www.hrblock.com",
    "wof:name":"H&R Block",
    "wof:placetype":"venue"
},
  "geometry": {"coordinates":[-88.072703,41.526367],"type":"Point"}
}