{
  "type": "Feature",
  "properties": {
    "iso:country":"US",
    "sg:address":"526 E Champaign Ave",
    "sg:city":"Rantoul",
    "sg:classifiers":[
        {
            "category":"Banks & Credit Unions",
            "subcategory":"Bank",
            "type":"Services"
        }
    ],
    "sg:phone":"+1 217 893 8201",
    "sg:postcode":"61866",
    "sg:province":"IL",
    "wof:name":"Credit Union Plus",
    "wof:placetype":"venue"
},
  "geometry": {"coordinates":[-88.150961,40.308139],"type":"Point"}
}