{
  "type": "Feature",
  "properties": {
    "iso:country":"US",
    "sg:address":"5429 E 1250 N Rd",
    "sg:city":"Gridley",
    "sg:classifiers":[
        {
            "category":"Manufacturing",
            "subcategory":"Apparel",
            "type":"Manufacturing & Wholesale Goods"
        }
    ],
    "sg:phone":"+1 309 747 2806",
    "sg:postcode":"61744",
    "sg:province":"IL",
    "wof:name":"Creative Impressions",
    "wof:placetype":"venue"
},
  "geometry": {"coordinates":[-88.81677500000001,40.806065],"type":"Point"}
}