{
  "type": "Feature",
  "properties": {
    "addr:full":"4343 Lincoln Hwy Matteson IL 60443",
    "addr:housenumber":"4343",
    "addr:postcode":"60443",
    "addr:street":"Lincoln Hwy",
    "iso:country":"US",
    "sg:address":"4343 Lincoln Hwy",
    "sg:city":"Matteson",
    "sg:classifiers":[
        {
            "category":"Professional",
            "subcategory":"Employment Agencies",
            "type":"Services"
        }
    ],
    "sg:phone":"+1 708 481 8808",
    "sg:postcode":"60443",
    "sg:province":"IL",
    "sg:tags":[
        "help",
        "supply"
    ],
    "wof:name":"Manpower",
    "wof:placetype":"venue"
},
  "geometry": {"coordinates":[-87.721394,41.506037],"type":"Point"}
}