{
  "type": "Feature",
  "properties": {
    "iso:country":"US",
    "sg:address":"205 S Lee St",
    "sg:city":"Bloomington",
    "sg:classifiers":[
        {
            "category":"Retail",
            "subcategory":"Laundry & Dry Cleaning",
            "type":"Services"
        }
    ],
    "sg:phone":"+1 309 827 4302",
    "sg:postcode":"61701",
    "sg:province":"IL",
    "sg:tags":[
        "laundries-self",
        "equipment",
        "supply"
    ],
    "sg:website":"http://www.hermesequipment.com",
    "wof:name":"Starcrest Cleaners",
    "wof:placetype":"venue"
},
  "geometry": {"coordinates":[-88.997366,40.477689],"type":"Point"}
}