{
  "type": "Feature",
  "properties": {
    "addr:full":"2184 Hawkey Dr Belvidere IL 61008",
    "addr:housenumber":"2184",
    "addr:postcode":"61008",
    "addr:street":"Hawkey Dr",
    "iso:country":"US",
    "sg:address":"2184 Hawkey Dr",
    "sg:city":"Belvidere",
    "sg:classifiers":[
        {
            "category":"Building & Trades",
            "subcategory":"Construction",
            "type":"Services"
        }
    ],
    "sg:phone":"+1 815 547 8994",
    "sg:postcode":"61008",
    "sg:province":"IL",
    "sg:tags":[
        "roofing",
        "sheet",
        "metal",
        "contractor"
    ],
    "wof:name":"County Roofing Inc",
    "wof:placetype":"venue"
},
  "geometry": {"coordinates":[-88.902692,42.248934],"type":"Point"}
}