{
  "type": "Feature",
  "properties": {
    "addr:full":"812 W 4th St Dixon IL 61021",
    "addr:housenumber":"812",
    "addr:postcode":"61021",
    "addr:street":"W 4Th St",
    "iso:country":"US",
    "sg:address":"812 W 4th St",
    "sg:city":"Dixon",
    "sg:classifiers":[
        {
            "category":"Social Services",
            "subcategory":"Child Care",
            "type":"Services"
        }
    ],
    "sg:phone":"+1 815 284 1648",
    "sg:postcode":"61021",
    "sg:province":"IL",
    "sg:tags":[
        "daycare"
    ],
    "wof:name":"Christine Mighell",
    "wof:placetype":"venue"
},
  "geometry": {"coordinates":[-89.490148,41.838533],"type":"Point"}
}