{
  "type": "Feature",
  "properties": {
    "addr:full":"1940 Lehigh Ave Glenview IL 60026",
    "addr:housenumber":"1940",
    "addr:postcode":"60026",
    "addr:street":"Lehigh Ave",
    "iso:country":"US",
    "sg:address":"1940 Lehigh Ave",
    "sg:city":"Glenview",
    "sg:classifiers":[
        {
            "category":"Sports & Exercise",
            "subcategory":"Gym",
            "type":"Entertainment"
        }
    ],
    "sg:phone":"+1 847 486 1704",
    "sg:postcode":"60026",
    "sg:province":"IL",
    "sg:tags":[
        "equipment",
        "fitness"
    ],
    "sg:website":"http://www.fitnesswear.com",
    "wof:name":"Fitness Wear",
    "wof:placetype":"venue"
},
  "geometry": {"coordinates":[-87.81203499999999,42.087959],"type":"Point"}
}