{
  "type": "Feature",
  "properties": {
    "iso:country":"US",
    "sg:address":"1530 E New York St",
    "sg:city":"Aurora",
    "sg:classifiers":[
        {
            "category":"Autos & Motor Vehicles",
            "subcategory":"Automobile Sales",
            "type":"Retail Goods"
        }
    ],
    "sg:phone":"+1 630 898 6200",
    "sg:postcode":"60505",
    "sg:province":"IL",
    "sg:tags":[
        "dealers-used",
        "car",
        "used",
        "cars-wholesale",
        "new"
    ],
    "wof:name":"New York Auto Sales Inc.",
    "wof:placetype":"venue"
},
  "geometry": {"coordinates":[-88.276802,41.757439],"type":"Point"}
}