{
  "type": "Feature",
  "properties": {
    "iso:country":"US",
    "sg:address":"1200 67th St",
    "sg:city":"Downers Grove",
    "sg:classifiers":[
        {
            "category":"Organizations",
            "subcategory":"Religious Organization",
            "type":"Services"
        }
    ],
    "sg:phone":"+1 630 969 1532",
    "sg:postcode":"60516",
    "sg:province":"IL",
    "sg:tags":[
        "church"
    ],
    "wof:name":"Divine Savior Catholic Church",
    "wof:placetype":"venue"
},
  "geometry": {"coordinates":[-88.014478,41.765639],"type":"Point"}
}