{
  "type": "Feature",
  "properties": {
    "addr:full":"405 Lake Cook Rd Deerfield IL 60015",
    "addr:housenumber":"405",
    "addr:postcode":"60015",
    "addr:street":"Lake Cook Rd",
    "iso:country":"US",
    "sg:address":"405 Lake Cook Rd",
    "sg:city":"Deerfield",
    "sg:classifiers":[
        {
            "category":"Health Services",
            "subcategory":"Hospital",
            "type":"Services"
        }
    ],
    "sg:phone":"+1 847 559 0369",
    "sg:postcode":"60015",
    "sg:province":"IL",
    "sg:tags":[
        "equipment",
        "supply"
    ],
    "wof:name":"Fresenius Medical Care (Northbrook Tel No)",
    "wof:placetype":"venue"
},
  "geometry": {"coordinates":[-87.839051,42.15276],"type":"Point"}
}