{
  "type": "Feature",
  "properties": {
    "addr:full":"2100 Sibley Blvd Calumet City IL 60409",
    "addr:housenumber":"2100",
    "addr:postcode":"60409",
    "addr:street":"Sibley Blvd",
    "iso:country":"US",
    "sg:address":"2100 Sibley Blvd",
    "sg:city":"Calumet City",
    "sg:classifiers":[
        {
            "category":"Local Transit",
            "type":"Transportation"
        }
    ],
    "sg:phone":"+1 708 899 3175",
    "sg:postcode":"60409",
    "sg:province":"IL",
    "sg:tags":[
        "passenger"
    ],
    "wof:name":"J & M Transportation",
    "wof:placetype":"venue"
},
  "geometry": {"coordinates":[-87.578858,41.62272],"type":"Point"}
}