{
  "type": "Feature",
  "properties": {
    "iso:country":"US",
    "sg:address":"314 S Arlington Heights Rd",
    "sg:city":"Arlington Hts",
    "sg:classifiers":[
        {
            "category":"Personal",
            "subcategory":"Beauty Salon",
            "type":"Services"
        }
    ],
    "sg:phone":"+1 847 870 0944",
    "sg:postcode":"60005",
    "sg:province":"IL",
    "wof:name":"Designs By Henna",
    "wof:placetype":"venue"
},
  "geometry": {"coordinates":[-87.980608,42.077501],"type":"Point"}
}