{
  "type": "Feature",
  "properties": {
    "iso:country":"US",
    "sg:address":"2425 Royal Blvd",
    "sg:city":"Elgin",
    "sg:classifiers":[
        {
            "category":"Professional",
            "subcategory":"Lawyer & Legal Services",
            "type":"Services"
        }
    ],
    "sg:phone":"+1 847 289 3390",
    "sg:postcode":"60123",
    "sg:province":"IL",
    "wof:name":"Richard E Travis",
    "wof:placetype":"venue"
},
  "geometry": {"coordinates":[-88.337751,42.052002],"type":"Point"}
}