{
  "type": "Feature",
  "properties": {
    "addr:full":"220 N Center St Bloomington IL 61701",
    "addr:housenumber":"220",
    "addr:postcode":"61701",
    "addr:street":"N Center St",
    "iso:country":"US",
    "sg:address":"220 N Center St",
    "sg:city":"Bloomington",
    "sg:classifiers":[
        {
            "category":"Bars & Pubs",
            "type":"Food & Drink"
        }
    ],
    "sg:phone":"+1 309 829 0002",
    "sg:postcode":"61701",
    "sg:province":"IL",
    "sg:tags":[
        "brew",
        "tavern"
    ],
    "wof:name":"Maguire's Bar & Grill",
    "wof:placetype":"venue"
},
  "geometry": {"coordinates":[-88.994634,40.479709],"type":"Point"}
}