{
  "type": "Feature",
  "properties": {
    "addr:full":"3021 E 80th St Chicago IL 60617",
    "addr:housenumber":"3021",
    "addr:postcode":"60617",
    "addr:street":"E 80Th St",
    "iso:country":"US",
    "sg:address":"3021 E 80th St",
    "sg:city":"Chicago",
    "sg:classifiers":[
        {
            "category":"Professional",
            "type":"Services"
        }
    ],
    "sg:phone":"+1 773 978 1141",
    "sg:postcode":"60617",
    "sg:province":"IL",
    "sg:tags":[
        "caterer"
    ],
    "wof:name":"Good Eats Personal Catering",
    "wof:placetype":"venue"
},
  "geometry": {"coordinates":[-87.550714,41.749989],"type":"Point"}
}