{
  "type": "Feature",
  "properties": {
    "iso:country":"US",
    "sg:address":"1315 N Church St",
    "sg:city":"Belleville",
    "sg:classifiers":[
        {
            "category":"Social Services",
            "subcategory":"Child Care",
            "type":"Services"
        }
    ],
    "sg:phone":"+1 618 235 0939",
    "sg:postcode":"62221",
    "sg:province":"IL",
    "wof:name":"Laura Garrett",
    "wof:placetype":"venue"
},
  "geometry": {"coordinates":[-89.973305,38.526429],"type":"Point"}
}