{
  "type": "Feature",
  "properties": {
    "addr:full":"40160 N Bluff Lake Rd Antioch IL 60002",
    "addr:housenumber":"40160",
    "addr:postcode":"60002",
    "addr:street":"N Bluff Lake Rd",
    "iso:country":"US",
    "sg:address":"40160 N Bluff Lake Rd",
    "sg:city":"Antioch",
    "sg:classifiers":[
        {
            "category":"Restaurant",
            "type":"Food & Drink"
        }
    ],
    "sg:phone":"+1   ",
    "sg:postcode":"60002",
    "sg:province":"IL",
    "sg:tags":[
        "independent",
        "family",
        "european"
    ],
    "wof:name":"Skandia House Ltd",
    "wof:placetype":"venue"
},
  "geometry": {"coordinates":[-88.13533,42.447043],"type":"Point"}
}