{
  "type": "Feature",
  "properties": {
    "addr:full":"14112 Catherine Dr Orland Park IL 60462",
    "addr:housenumber":"14112",
    "addr:postcode":"60462",
    "addr:street":"Catherine Dr",
    "iso:country":"US",
    "sg:address":"14112 Catherine Dr",
    "sg:city":"Orland Park",
    "sg:classifiers":[
        {
            "category":"Retail",
            "subcategory":"Auto Repair",
            "type":"Services"
        }
    ],
    "sg:phone":"+1 708 873 0297",
    "sg:postcode":"60462",
    "sg:province":"IL",
    "sg:tags":[
        "automotive"
    ],
    "wof:name":"S & F Towing",
    "wof:placetype":"venue"
},
  "geometry": {"coordinates":[-87.84689899999999,41.635131],"type":"Point"}
}