{
  "type": "Feature",
  "properties": {
    "addr:full":"155 Alderwood Ln Aurora IL 60504",
    "addr:housenumber":"155",
    "addr:postcode":"60504",
    "addr:street":"Alderwood Ln",
    "iso:country":"US",
    "sg:address":"155 Alderwood Ln",
    "sg:city":"Aurora",
    "sg:classifiers":[
        {
            "category":"Building & Trades",
            "subcategory":"Construction",
            "type":"Services"
        }
    ],
    "sg:phone":"+1 630 585 5700",
    "sg:postcode":"60504",
    "sg:province":"IL",
    "sg:tags":[
        "house"
    ],
    "wof:name":"Gladstone Bldrs Developers Inc",
    "wof:placetype":"venue"
},
  "geometry": {"coordinates":[-88.244722,41.751491],"type":"Point"}
}