{
  "type": "Feature",
  "properties": {
    "addr:full":"602 S Illinois Ave Carbondale IL 62901",
    "addr:housenumber":"602",
    "addr:postcode":"62901",
    "addr:street":"S Illinois Ave",
    "iso:country":"US",
    "sg:address":"602 S Illinois Ave",
    "sg:city":"Carbondale",
    "sg:classifiers":[
        {
            "category":"Restaurant",
            "type":"Food & Drink"
        }
    ],
    "sg:phone":"+1 618 529 3388",
    "sg:postcode":"62901",
    "sg:province":"IL",
    "sg:tags":[
        "drinking",
        "eating"
    ],
    "wof:name":"New Kahala Fast Foods",
    "wof:placetype":"venue"
},
  "geometry": {"coordinates":[-89.21639999999999,37.7215],"type":"Point"}
}