{
  "type": "Feature",
  "properties": {
    "iso:country":"US",
    "sg:address":"12827 Division St",
    "sg:city":"Blue Island",
    "sg:classifiers":[
        {
            "category":"Building & Trades",
            "subcategory":"Construction",
            "type":"Services"
        }
    ],
    "sg:phone":"+1 708 371 6131",
    "sg:postcode":"60406",
    "sg:province":"IL",
    "sg:tags":[
        "work",
        "carpentry"
    ],
    "wof:name":"Carapezza Construction Company",
    "wof:placetype":"venue"
},
  "geometry": {"coordinates":[-87.67043,41.660844],"type":"Point"}
}