{
  "type": "Feature",
  "properties": {
    "iso:country":"US",
    "sg:address":"109 Memphis Pl",
    "sg:city":"Vernon Hills",
    "sg:classifiers":[
        {
            "category":"Building & Trades",
            "subcategory":"Plumbing",
            "type":"Services"
        }
    ],
    "sg:phone":"+1 847 573 8907",
    "sg:postcode":"60061",
    "sg:province":"IL",
    "sg:tags":[
        "mechanical",
        "contractor"
    ],
    "wof:name":"S Ea Mechanical & Engrg Inc",
    "wof:placetype":"venue"
},
  "geometry": {"coordinates":[-87.967215,42.224525],"type":"Point"}
}