{
  "type": "Feature",
  "properties": {
    "addr:full":"321 E Glenwood Lansing Rd Glenwood IL 60425",
    "addr:housenumber":"321",
    "addr:postcode":"60425",
    "addr:street":"E Glenwood Lansing Rd",
    "iso:country":"US",
    "sg:address":"321 E Glenwood Lansing Rd",
    "sg:city":"Glenwood",
    "sg:classifiers":[
        {
            "category":"Shopping",
            "subcategory":"Beauty & Cosmetics",
            "type":"Retail Goods"
        }
    ],
    "sg:phone":"+1   ",
    "sg:postcode":"60425",
    "sg:province":"IL",
    "sg:tags":[
        "merchandise"
    ],
    "wof:name":"Thai Accessories",
    "wof:placetype":"venue"
},
  "geometry": {"coordinates":[-87.604327,41.54271],"type":"Point"}
}