{
  "type": "Feature",
  "properties": {
    "iso:country":"US",
    "sg:address":"18 Nottingham Dr",
    "sg:city":"Lincolnshire",
    "sg:classifiers":[
        {
            "category":"Professional",
            "type":"Services"
        }
    ],
    "sg:phone":"+1 847 945 9393",
    "sg:postcode":"60069",
    "sg:province":"IL",
    "sg:tags":[
        "establishment"
    ],
    "wof:name":"Clean Air Flow",
    "wof:placetype":"venue"
},
  "geometry": {"coordinates":[-87.898746,42.197174],"type":"Point"}
}