{
  "type": "Feature",
  "properties": {
    "iso:country":"US",
    "sg:address":"3443 W Peterson Ave",
    "sg:city":"Chicago",
    "sg:classifiers":[
        {
            "category":"Banks & Credit Unions",
            "subcategory":"Bank",
            "type":"Services"
        }
    ],
    "sg:phone":"+1 773 267 1354",
    "sg:postcode":"60659",
    "sg:province":"IL",
    "sg:tags":[
        "depository",
        "banking"
    ],
    "wof:name":"Pakistan Express Corp",
    "wof:placetype":"venue"
},
  "geometry": {"coordinates":[-87.716261,41.990222],"type":"Point"}
}