{
  "type": "Feature",
  "properties": {
    "iso:country":"US",
    "sg:address":"704 Florence Dr",
    "sg:city":"Park Ridge",
    "sg:classifiers":[
        {
            "category":"Health Services",
            "subcategory":"Doctor",
            "type":"Services"
        }
    ],
    "sg:phone":"+1 847 698 1200",
    "sg:postcode":"60068",
    "sg:province":"IL",
    "sg:tags":[
        "medical",
        "center"
    ],
    "wof:name":"Association For Promotion of A",
    "wof:placetype":"venue"
},
  "geometry": {"coordinates":[-87.861353,42.021076],"type":"Point"}
}