{
  "type": "Feature",
  "properties": {
    "addr:full":"6246 26th St Berwyn IL 60402",
    "addr:housenumber":"6246",
    "addr:postcode":"60402",
    "addr:street":"26Th St",
    "iso:country":"US",
    "sg:address":"6246 26th St",
    "sg:city":"Berwyn",
    "sg:classifiers":[
        {
            "category":"Restaurant",
            "type":"Food & Drink"
        }
    ],
    "sg:phone":"+1 708 749 9555",
    "sg:postcode":"60402",
    "sg:province":"IL",
    "sg:tags":[
        "deli",
        "grocery",
        "eating"
    ],
    "wof:name":"Sava Delicatessen",
    "wof:placetype":"venue"
},
  "geometry": {"coordinates":[-87.78029600000001,41.843498],"type":"Point"}
}