{
  "type": "Feature",
  "properties": {
    "addr:full":"111 W Greenwood Ave Waukegan IL 60087",
    "addr:housenumber":"111",
    "addr:postcode":"60087",
    "addr:street":"W Greenwood Ave",
    "iso:country":"US",
    "sg:address":"111 W Greenwood Ave",
    "sg:city":"Waukegan",
    "sg:classifiers":[
        {
            "category":"Manufacturing",
            "subcategory":"Tools & Machinery",
            "type":"Manufacturing & Wholesale Goods"
        }
    ],
    "sg:phone":"+1 847 625 0377",
    "sg:postcode":"60087",
    "sg:province":"IL",
    "sg:tags":[
        "machine",
        "shop"
    ],
    "wof:name":"T & F Machine & Tool",
    "wof:placetype":"venue"
},
  "geometry": {"coordinates":[-87.828339,42.384638],"type":"Point"}
}