{
  "type": "Feature",
  "properties": {
    "iso:country":"US",
    "sg:address":"910 E Old Elm Rd",
    "sg:city":"Lake Forest",
    "sg:classifiers":[
        {
            "category":"Wholesale",
            "subcategory":"Non-durable Goods",
            "type":"Manufacturing & Wholesale Goods"
        }
    ],
    "sg:phone":"+1 847 234 1375",
    "sg:postcode":"60045",
    "sg:province":"IL",
    "wof:name":"Top To Bottom",
    "wof:placetype":"venue"
},
  "geometry": {"coordinates":[-87.82526,42.218151],"type":"Point"}
}