{
  "type": "Feature",
  "properties": {
    "addr:full":"609 S 3rd St Geneva IL 60134",
    "addr:housenumber":"609",
    "addr:postcode":"60134",
    "addr:street":"S 3Rd St",
    "iso:country":"US",
    "sg:address":"609 S 3rd St",
    "sg:city":"Geneva",
    "sg:classifiers":[
        {
            "category":"Autos & Motor Vehicles",
            "subcategory":"Fuel & Gas Station",
            "type":"Retail Goods"
        },
        {
            "category":"Retail",
            "subcategory":"Auto Repair",
            "type":"Services"
        }
    ],
    "sg:phone":"+1 630 232 2532",
    "sg:postcode":"60134",
    "sg:province":"IL",
    "sg:tags":[
        "brake"
    ],
    "wof:name":"Duke & Lees Service Corp",
    "wof:placetype":"venue"
},
  "geometry": {"coordinates":[-88.309314,41.881733],"type":"Point"}
}