{
  "type": "Feature",
  "properties": {
    "iso:country":"US",
    "sg:address":"2 N Kenilworth Ave",
    "sg:city":"Mount Prospect",
    "sg:classifiers":[
        {
            "category":"Professional",
            "subcategory":"Computer Services",
            "type":"Services"
        }
    ],
    "sg:phone":"+1 847 222 0218",
    "sg:postcode":"60056",
    "sg:province":"IL",
    "sg:tags":[
        "programing",
        "custom"
    ],
    "wof:name":"Joan Just Inc",
    "wof:placetype":"venue"
},
  "geometry": {"coordinates":[-87.954886,42.068184],"type":"Point"}
}