{
  "type": "Feature",
  "properties": {
    "iso:country":"US",
    "sg:address":"1235 W George St Apt 111",
    "sg:city":"Chicago",
    "sg:classifiers":[
        {
            "category":"Mining & Drilling",
            "type":"Manufacturing & Wholesale Goods"
        },
        {
            "category":"Building & Trades",
            "subcategory":"Equipment Rental",
            "type":"Services"
        }
    ],
    "sg:phone":"+1 773 405 7788",
    "sg:postcode":"60657",
    "sg:province":"IL",
    "sg:tags":[
        "gravel",
        "sand",
        "handling",
        "supply"
    ],
    "wof:name":"Regency Equipment",
    "wof:placetype":"venue"
},
  "geometry": {"coordinates":[-87.659594,41.934319],"type":"Point"}
}