{
  "type": "Feature",
  "properties": {
    "addr:full":"1714 N Damen Ave Chicago IL 60647",
    "addr:housenumber":"1714",
    "addr:postcode":"60647",
    "addr:street":"N Damen Ave",
    "iso:country":"US",
    "sg:address":"1714 N Damen Ave",
    "sg:city":"Chicago",
    "sg:classifiers":[
        {
            "category":"Sports & Exercise",
            "subcategory":"Playing Field",
            "type":"Entertainment"
        }
    ],
    "sg:phone":"+1 773 904 8913",
    "sg:postcode":"60647",
    "sg:province":"IL",
    "sg:tags":[
        "instruction",
        "fitness"
    ],
    "sg:website":"www.thedaileymethod.com",
    "wof:name":"The Dailey Method",
    "wof:placetype":"venue"
},
  "geometry": {"coordinates":[-87.67716299999999,41.912839],"type":"Point"}
}