{
  "type": "Feature",
  "properties": {
    "iso:country":"US",
    "sg:address":"1037 W Hawthorn Dr",
    "sg:city":"Itasca",
    "sg:classifiers":[
        {
            "category":"Deli",
            "type":"Food & Drink"
        },
        {
            "category":"Restaurant",
            "type":"Food & Drink"
        },
        {
            "category":"Food & Beverages",
            "subcategory":"Groceries & Convenience Stores",
            "type":"Retail Goods"
        }
    ],
    "sg:phone":"+1 630 285 8902",
    "sg:postcode":"60143",
    "sg:province":"IL",
    "sg:tags":[
        "shop",
        "delicatessen",
        "sandwich"
    ],
    "wof:name":"Subway Dc Development",
    "wof:placetype":"venue"
},
  "geometry": {"coordinates":[-88.030185,41.966763],"type":"Point"}
}