{
  "type": "Feature",
  "properties": {
    "addr:full":"17 W 4th St Danville IL 61832",
    "addr:housenumber":"17",
    "addr:postcode":"61832",
    "addr:street":"W 4Th St",
    "iso:country":"US",
    "sg:address":"17 W 4th St",
    "sg:city":"Danville",
    "sg:classifiers":[
        {
            "category":"Wholesale",
            "subcategory":"Books, Periodicals, & Newspapers",
            "type":"Manufacturing & Wholesale Goods"
        }
    ],
    "sg:phone":"+1 217 446 4131",
    "sg:postcode":"61832",
    "sg:province":"IL",
    "sg:tags":[
        "magazine"
    ],
    "wof:name":"Anderson-Austin News Co",
    "wof:placetype":"venue"
},
  "geometry": {"coordinates":[-87.636653,40.113185],"type":"Point"}
}