{
  "type": "Feature",
  "properties": {
    "iso:country":"US",
    "sg:address":"1601 18th St",
    "sg:city":"Silvis",
    "sg:classifiers":[
        {
            "category":"Banks & Credit Unions",
            "subcategory":"Bank",
            "type":"Services"
        }
    ],
    "sg:phone":"+1 309 796 0358",
    "sg:postcode":"61282",
    "sg:province":"IL",
    "wof:name":"Woodforest Bank",
    "wof:placetype":"venue"
},
  "geometry": {"coordinates":[-90.406136,41.490714],"type":"Point"}
}