{
  "type": "Feature",
  "properties": {
    "addr:full":"1725 S Naperville Rd Wheaton IL 60187",
    "addr:housenumber":"1725",
    "addr:postcode":"60187",
    "addr:street":"S Naperville Rd",
    "iso:country":"US",
    "sg:address":"1725 S Naperville Rd",
    "sg:city":"Wheaton",
    "sg:classifiers":[
        {
            "category":"Health Services",
            "subcategory":"Doctor",
            "type":"Services"
        }
    ],
    "sg:phone":"+1 630 653 6441",
    "sg:postcode":"60187",
    "sg:province":"IL",
    "sg:tags":[
        "medical"
    ],
    "wof:name":"Genesis Clinical Services",
    "wof:placetype":"venue"
},
  "geometry": {"coordinates":[-88.101598,41.841521],"type":"Point"}
}