{
  "type": "Feature",
  "properties": {
    "iso:country":"US",
    "sg:address":"10540 W Cermak Rd",
    "sg:city":"Westchester",
    "sg:classifiers":[
        {
            "category":"Health Services",
            "subcategory":"Dentist",
            "type":"Services"
        }
    ],
    "sg:phone":"+1 708 562 4525",
    "sg:postcode":"60154",
    "sg:province":"IL",
    "wof:name":"Sheldon James F Dds",
    "wof:placetype":"venue"
},
  "geometry": {"coordinates":[-87.88562400000001,41.84856],"type":"Point"}
}