{
  "type": "Feature",
  "properties": {
    "iso:country":"US",
    "sg:address":"510 Old Skokie Hwy",
    "sg:city":"Park City",
    "sg:classifiers":[
        {
            "category":"Wholesale",
            "subcategory":"Auto Parts",
            "type":"Manufacturing & Wholesale Goods"
        }
    ],
    "sg:phone":"+1 847 244 2990",
    "sg:postcode":"60085",
    "sg:province":"IL",
    "sg:tags":[
        "equipment",
        "truck"
    ],
    "wof:name":"Lake County Truck Sales & Svc",
    "wof:placetype":"venue"
},
  "geometry": {"coordinates":[-87.891299,42.354696],"type":"Point"}
}