{
  "type": "Feature",
  "properties": {
    "iso:country":"US",
    "sg:address":"1706 6th St",
    "sg:city":"East Moline",
    "sg:classifiers":[
        {
            "category":"Social Services",
            "subcategory":"Child Care",
            "type":"Services"
        }
    ],
    "sg:phone":"+1 309 755 1028",
    "sg:postcode":"61244",
    "sg:province":"IL",
    "wof:name":"St Anne Daycare",
    "wof:placetype":"venue"
},
  "geometry": {"coordinates":[-90.447091,41.512957],"type":"Point"}
}