{
  "type": "Feature",
  "properties": {
    "addr:full":"11700 S Cottage Grove Ave Chicago IL 60628",
    "addr:housenumber":"11700",
    "addr:postcode":"60628",
    "addr:street":"S Cottage Grove Ave",
    "iso:country":"US",
    "sg:address":"11700 S Cottage Grove Ave",
    "sg:city":"Chicago",
    "sg:classifiers":[
        {
            "category":"Manufacturing",
            "subcategory":"Tools & Machinery",
            "type":"Manufacturing & Wholesale Goods"
        },
        {
            "category":"Building & Trades",
            "subcategory":"Construction",
            "type":"Services"
        },
        {
            "category":"Wholesale",
            "subcategory":"Painting Supplies",
            "type":"Manufacturing & Wholesale Goods"
        },
        {
            "category":"Home & Garden",
            "subcategory":"Building Materials",
            "type":"Retail Goods"
        },
        {
            "category":"Manufacturing",
            "subcategory":"Chemicals & Compounds",
            "type":"Manufacturing & Wholesale Goods"
        },
        {
            "category":"Autos & Motor Vehicles",
            "subcategory":"Auto Supplies",
            "type":"Retail Goods"
        },
        {
            "category":"Building & Trades",
            "subcategory":"Equipment Rental",
            "type":"Services"
        },
        {
            "category":"Manufacturing",
            "subcategory":"Building Materials",
            "type":"Manufacturing & Wholesale Goods"
        }
    ],
    "sg:phone":"+1 773 821 3107",
    "sg:postcode":"60628",
    "sg:province":"IL",
    "sg:tags":[
        "body",
        "shop",
        "paint",
        "wall",
        "wallcoverings-installation",
        "wallpaper",
        "coating",
        "contractor",
        "paint-wholesale",
        "spraying",
        "automobile",
        "wallcoverings",
        "equipment-renting",
        "painter",
        "manufacturer"
    ],
    "sg:website":"http://www.sherwin-williams.com/",
    "wof:name":"Sherwin-Williams",
    "wof:placetype":"venue"
},
  "geometry": {"coordinates":[-87.611587,41.683531],"type":"Point"}
}