{
  "type": "Feature",
  "properties": {
    "iso:country":"US",
    "sg:address":"6431 W. Cermak Rd.",
    "sg:city":"Berwyn",
    "sg:classifiers":[
        {
            "category":"Restaurant",
            "type":"Food & Drink"
        }
    ],
    "sg:phone":"+1 708 484 4689",
    "sg:postcode":"60402",
    "sg:province":"IL",
    "sg:tags":[
        "mexican"
    ],
    "wof:name":"La Quinta de los Reyes",
    "wof:placetype":"venue"
},
  "geometry": {"coordinates":[-87.785346,41.850204],"type":"Point"}
}