{
  "type": "Feature",
  "properties": {
    "addr:full":"330 Madison St Joliet IL 60435",
    "addr:housenumber":"330",
    "addr:postcode":"60435",
    "addr:street":"Madison St",
    "iso:country":"US",
    "sg:address":"330 Madison St",
    "sg:city":"Joliet",
    "sg:classifiers":[
        {
            "category":"Health Services",
            "subcategory":"Doctor",
            "type":"Services"
        }
    ],
    "sg:phone":"+1 815 725 5424",
    "sg:postcode":"60435",
    "sg:province":"IL",
    "sg:tags":[
        "physician",
        "surgeon"
    ],
    "wof:name":"Joliet Cardiology Ctr",
    "wof:placetype":"venue"
},
  "geometry": {"coordinates":[-88.134517,41.526472],"type":"Point"}
}