{
  "type": "Feature",
  "properties": {
    "iso:country":"US",
    "sg:address":"538 Price Ave",
    "sg:city":"Calumet City",
    "sg:classifiers":[
        {
            "category":"Organizations",
            "subcategory":"Religious Organization",
            "type":"Services"
        }
    ],
    "sg:phone":"+1 708 891 8937",
    "sg:postcode":"60409",
    "sg:province":"IL",
    "wof:name":"St Victor Church",
    "wof:placetype":"venue"
},
  "geometry": {"coordinates":[-87.537378,41.620491],"type":"Point"}
}