{
  "type": "Feature",
  "properties": {
    "iso:country":"US",
    "sg:address":"11124 31st St",
    "sg:city":"Westchester",
    "sg:classifiers":[
        {
            "category":"Restaurant",
            "type":"Food & Drink"
        }
    ],
    "sg:menulink":"http://www.allmenus.com/il/proviso/167251-burger-king/menu/",
    "sg:phone":"+1 708 531 1211",
    "sg:postcode":"60154",
    "sg:province":"IL",
    "sg:tags":[
        "burger",
        "american"
    ],
    "wof:name":"Burger King",
    "wof:placetype":"venue"
},
  "geometry": {"coordinates":[-87.89891799999999,41.833678],"type":"Point"}
}