{
  "type": "Feature",
  "properties": {
    "iso:country":"US",
    "sg:address":"7011 W 111th St Ste A",
    "sg:city":"Worth",
    "sg:classifiers":[
        {
            "category":"Coffee & Tea",
            "type":"Food & Drink"
        },
        {
            "category":"Restaurant",
            "type":"Food & Drink"
        }
    ],
    "sg:phone":"+1 708 361 4444",
    "sg:postcode":"60482",
    "sg:province":"IL",
    "sg:tags":[
        "espresso"
    ],
    "wof:name":"Havana Cafe & Hooka Inc",
    "wof:placetype":"venue"
},
  "geometry": {"coordinates":[-87.793854,41.690068],"type":"Point"}
}