{
  "type": "Feature",
  "properties": {
    "addr:full":"270 W Old Higgins Rd Des Plaines IL 60018",
    "addr:housenumber":"270",
    "addr:postcode":"60018",
    "addr:street":"W Old Higgins Rd Des",
    "iso:country":"US",
    "sg:address":"270 W Old Higgins Rd",
    "sg:city":"Des Plaines",
    "sg:classifiers":[
        {
            "category":"Building & Trades",
            "subcategory":"Construction",
            "type":"Services"
        }
    ],
    "sg:phone":"+1 847 635 9472",
    "sg:postcode":"60018",
    "sg:province":"IL",
    "sg:tags":[
        "fence",
        "contractor"
    ],
    "wof:name":"Bbf Erectors",
    "wof:placetype":"venue"
},
  "geometry": {"coordinates":[-87.928084,42.004889],"type":"Point"}
}