{
  "type": "Feature",
  "properties": {
    "addr:full":"208 E Main St Arcola IL 61910",
    "addr:housenumber":"208",
    "addr:postcode":"61910",
    "addr:street":"E Main St",
    "iso:country":"US",
    "sg:address":"208 E Main St",
    "sg:city":"Arcola",
    "sg:classifiers":[
        {
            "category":"Shopping",
            "subcategory":"Used Merchandise",
            "type":"Retail Goods"
        }
    ],
    "sg:phone":"+1 217 268 3306",
    "sg:postcode":"61910",
    "sg:province":"IL",
    "sg:tags":[
        "antique"
    ],
    "wof:name":"Up Front Antiques",
    "wof:placetype":"venue"
},
  "geometry": {"coordinates":[-88.30658,39.68422],"type":"Point"}
}