{
  "type": "Feature",
  "properties": {
    "addr:full":"1717 W 115th Street Chicago IL 60643",
    "addr:housenumber":"1717",
    "addr:postcode":"60643",
    "addr:street":"W 115Th Street",
    "iso:country":"US",
    "sg:address":"1717 W 115th Street",
    "sg:city":"Chicago",
    "sg:classifiers":[
        {
            "category":"Manufacturing",
            "subcategory":"Metals",
            "type":"Manufacturing & Wholesale Goods"
        },
        {
            "category":"Health Services",
            "subcategory":"Dentist",
            "type":"Services"
        }
    ],
    "sg:phone":"+1 773 239 7700",
    "sg:postcode":"60643",
    "sg:province":"IL",
    "sg:tags":[
        "foundry"
    ],
    "sg:website":"http://www.leavitt-tube.com",
    "wof:name":"Leavitt Tube Company",
    "wof:placetype":"venue"
},
  "geometry": {"coordinates":[-87.664959,41.684688],"type":"Point"}
}