{
  "type": "Feature",
  "properties": {
    "addr:full":"1301 Towne Ave Batavia IL 60510",
    "addr:housenumber":"1301",
    "addr:postcode":"60510",
    "addr:street":"Towne Ave",
    "iso:country":"US",
    "sg:address":"1301 Towne Ave",
    "sg:city":"Batavia",
    "sg:classifiers":[
        {
            "category":"Professional",
            "subcategory":"Management & Consulting",
            "type":"Services"
        }
    ],
    "sg:phone":"+1   ",
    "sg:postcode":"60510",
    "sg:province":"IL",
    "sg:tags":[
        "retail",
        "direct",
        "sales"
    ],
    "wof:name":"Nick Chrcaszcz",
    "wof:placetype":"venue"
},
  "geometry": {"coordinates":[-88.332105,41.837081],"type":"Point"}
}