{
  "type": "Feature",
  "properties": {
    "addr:full":"97 Christina Cir Wheaton IL 60187",
    "addr:housenumber":"97",
    "addr:postcode":"60187",
    "addr:street":"Christina Cir",
    "iso:country":"US",
    "sg:address":"97 Christina Cir",
    "sg:city":"Wheaton",
    "sg:classifiers":[
        {
            "category":"Personal",
            "type":"Services"
        }
    ],
    "sg:phone":"+1 630 260 4030",
    "sg:postcode":"60187",
    "sg:province":"IL",
    "wof:name":"Quilting Blue House",
    "wof:placetype":"venue"
},
  "geometry": {"coordinates":[-88.099901,41.840795],"type":"Point"}
}