{
  "type": "Feature",
  "properties": {
    "addr:full":"1105 Windham Pkwy Romeoville IL 60446",
    "addr:housenumber":"1105",
    "addr:postcode":"60446",
    "addr:street":"Windham Pkwy",
    "iso:country":"US",
    "sg:address":"1105 Windham Pkwy",
    "sg:city":"Romeoville",
    "sg:classifiers":[
        {
            "category":"Wholesale",
            "subcategory":"Electrical",
            "type":"Manufacturing & Wholesale Goods"
        }
    ],
    "sg:phone":"+1 630 759 5186",
    "sg:postcode":"60446",
    "sg:province":"IL",
    "sg:tags":[
        "disposal",
        "garbage",
        "equipment"
    ],
    "wof:name":"Windsor Republic",
    "wof:placetype":"venue"
},
  "geometry": {"coordinates":[-88.119624,41.662087],"type":"Point"}
}