{
  "type": "Feature",
  "properties": {
    "addr:full":"103 N Chestnut St Byron IL 61010",
    "addr:housenumber":"103",
    "addr:postcode":"61010",
    "addr:street":"N Chestnut St",
    "iso:country":"US",
    "sg:address":"103 N Chestnut St",
    "sg:city":"Byron",
    "sg:classifiers":[
        {
            "category":"Personal",
            "subcategory":"Beauty Salon",
            "type":"Services"
        }
    ],
    "sg:phone":"+1 815 234 8481",
    "sg:postcode":"61010",
    "sg:province":"IL",
    "wof:name":"Intermezzo Salon",
    "wof:placetype":"venue"
},
  "geometry": {"coordinates":[-89.254257,42.125466],"type":"Point"}
}