{
  "type": "Feature",
  "properties": {
    "addr:full":"1561 Division St Morris IL 60450",
    "addr:housenumber":"1561",
    "addr:postcode":"60450",
    "addr:street":"Division St",
    "iso:country":"US",
    "sg:address":"1561 Division St",
    "sg:city":"Morris",
    "sg:classifiers":[
        {
            "category":"Health Services",
            "subcategory":"Doctor",
            "type":"Services"
        }
    ],
    "sg:phone":"+1 815 942 1203",
    "sg:postcode":"60450",
    "sg:province":"IL",
    "sg:tags":[
        "gynecology",
        "physician",
        "surgeon",
        "surgeons",
        "obstetrics"
    ],
    "wof:name":"Mark Kijek Md",
    "wof:placetype":"venue"
},
  "geometry": {"coordinates":[-88.422012,41.37434],"type":"Point"}
}