{
  "type": "Feature",
  "properties": {
    "addr:full":"712 W 31st St Chicago IL 60616",
    "addr:housenumber":"712",
    "addr:postcode":"60616",
    "addr:street":"W 31St St",
    "iso:country":"US",
    "sg:address":"712 W 31st St",
    "sg:city":"Chicago",
    "sg:classifiers":[
        {
            "category":"Professional",
            "subcategory":"Business Services",
            "type":"Services"
        }
    ],
    "sg:phone":"+1 312 445 3400",
    "sg:postcode":"60616",
    "sg:province":"IL",
    "sg:tags":[
        "holding"
    ],
    "wof:name":"Cairo Holdings",
    "wof:placetype":"venue"
},
  "geometry": {"coordinates":[-87.644295,41.838081],"type":"Point"}
}