{
  "type": "Feature",
  "properties": {
    "addr:full":"6051 N Lincoln Avenue Chicago IL 60659",
    "addr:housenumber":"6051",
    "addr:postcode":"60659",
    "addr:street":"N Lincoln Avenue",
    "iso:country":"US",
    "sg:address":"6051 N Lincoln Avenue",
    "sg:city":"Chicago",
    "sg:classifiers":[
        {
            "category":"Health Services",
            "subcategory":"Dentist",
            "type":"Services"
        }
    ],
    "sg:phone":"+1 773 761 6623",
    "sg:postcode":"60659",
    "sg:province":"IL",
    "sg:website":"www.drlason.com",
    "wof:name":"Lason Donald R DDS Ltd",
    "wof:placetype":"venue"
},
  "geometry": {"coordinates":[-87.70895,41.991186],"type":"Point"}
}