{
  "type": "Feature",
  "properties": {
    "addr:full":"2630 W Belmont Ave Chicago IL 60618",
    "addr:housenumber":"2630",
    "addr:postcode":"60618",
    "addr:street":"W Belmont Ave",
    "iso:country":"US",
    "sg:address":"2630 W Belmont Ave",
    "sg:city":"Chicago",
    "sg:classifiers":[
        {
            "category":"Airline",
            "type":"Transportation"
        }
    ],
    "sg:phone":"+1 773 732 2802",
    "sg:postcode":"60618",
    "sg:province":"IL",
    "wof:name":"Maroc",
    "wof:placetype":"venue"
},
  "geometry": {"coordinates":[-87.693712,41.939413],"type":"Point"}
}