{
  "type": "Feature",
  "properties": {
    "addr:full":"3411 Auburn St Rockford IL 61101",
    "addr:housenumber":"3411",
    "addr:postcode":"61101",
    "addr:street":"Auburn St",
    "iso:country":"US",
    "sg:address":"3411 Auburn St",
    "sg:city":"Rockford",
    "sg:classifiers":[
        {
            "category":"Autos & Motor Vehicles",
            "subcategory":"Auto Supplies",
            "type":"Retail Goods"
        }
    ],
    "sg:phone":"+1 815 962 1207",
    "sg:postcode":"61101",
    "sg:province":"IL",
    "sg:tags":[
        "automobile",
        "parts"
    ],
    "wof:name":"Autozone",
    "wof:placetype":"venue"
},
  "geometry": {"coordinates":[-89.10893799999999,42.288382],"type":"Point"}
}