{
  "type": "Feature",
  "properties": {
    "addr:full":"635 N 1st Ave Canton IL 61520",
    "addr:housenumber":"635",
    "addr:postcode":"61520",
    "addr:street":"N 1St Ave",
    "iso:country":"US",
    "sg:address":"635 N 1st Ave",
    "sg:city":"Canton",
    "sg:classifiers":[
        {
            "category":"Building & Trades",
            "subcategory":"Construction",
            "type":"Services"
        }
    ],
    "sg:phone":"+1 309 647 7952",
    "sg:postcode":"61520",
    "sg:province":"IL",
    "sg:tags":[
        "contractor"
    ],
    "wof:name":"Sale Plastering",
    "wof:placetype":"venue"
},
  "geometry": {"coordinates":[-90.033406,40.563784],"type":"Point"}
}