{
  "type": "Feature",
  "properties": {
    "addr:full":"25680 Linder Ln Ingleside IL 60041",
    "addr:postcode":"25680;60041",
    "addr:street":"Linder Ln",
    "iso:country":"US",
    "sg:address":"25680 Linder Ln",
    "sg:city":"Ingleside",
    "sg:classifiers":[
        {
            "category":"Professional",
            "subcategory":"Art Services",
            "type":"Services"
        }
    ],
    "sg:phone":"+1 847 587 8352",
    "sg:postcode":"60041",
    "sg:province":"IL",
    "sg:tags":[
        "photographer"
    ],
    "wof:name":"Pierson Photography",
    "wof:placetype":"venue"
},
  "geometry": {"coordinates":[-88.134147,42.379915],"type":"Point"}
}