{
  "type": "Feature",
  "properties": {
    "iso:country":"US",
    "sg:address":"1927 W Fullerton Ave",
    "sg:city":"Chicago",
    "sg:classifiers":[
        {
            "category":"Donuts",
            "subcategory":"None",
            "type":"Food & Drink"
        }
    ],
    "sg:phone":"+1 773 227 0800",
    "sg:postcode":"60614",
    "sg:province":"IL",
    "sg:website":"www.dunkindonuts.com",
    "wof:name":"Dunkin' Donuts",
    "wof:placetype":"venue"
},
  "geometry": {"coordinates":[-87.67704000000001,41.925029],"type":"Point"}
}