{
  "type": "Feature",
  "properties": {
    "iso:country":"US",
    "sg:address":"3806 Village Dr",
    "sg:city":"Hazel Crest",
    "sg:classifiers":[
        {
            "category":"Professional",
            "subcategory":"Management & Consulting",
            "type":"Services"
        }
    ],
    "sg:phone":"+1 708 922 1654",
    "sg:postcode":"60429",
    "sg:province":"IL",
    "wof:name":"E & B Management",
    "wof:placetype":"venue"
},
  "geometry": {"coordinates":[-87.709272,41.552954],"type":"Point"}
}