{
  "type": "Feature",
  "properties": {
    "iso:country":"US",
    "sg:address":"5312 N Winthrop Ave",
    "sg:city":"Chicago",
    "sg:classifiers":[
        {
            "category":"Communications",
            "subcategory":"Film & Video Production",
            "type":"Services"
        }
    ],
    "sg:phone":"+1 773 271 8331",
    "sg:postcode":"60640",
    "sg:province":"IL",
    "sg:tags":[
        "motion"
    ],
    "wof:name":"Wagtail Productions LLC",
    "wof:placetype":"venue"
},
  "geometry": {"coordinates":[-87.657985,41.979779],"type":"Point"}
}