{
  "type": "Feature",
  "properties": {
    "addr:full":"2501 Barrington Rd Schaumburg IL 60192",
    "addr:housenumber":"2501",
    "addr:postcode":"60192",
    "addr:street":"Barrington Rd",
    "iso:country":"US",
    "sg:address":"2501 Barrington Rd",
    "sg:city":"Schaumburg",
    "sg:classifiers":[
        {
            "category":"Manufacturing",
            "subcategory":"Tools & Machinery",
            "type":"Manufacturing & Wholesale Goods"
        }
    ],
    "sg:phone":"+1 847 304 7400",
    "sg:postcode":"60192",
    "sg:province":"IL",
    "sg:tags":[
        "equipment",
        "medical",
        "mfg",
        "diagnostic"
    ],
    "wof:name":"Lockheed Martin",
    "wof:placetype":"venue"
},
  "geometry": {"coordinates":[-88.144667,42.062813],"type":"Point"}
}