{
  "type": "Feature",
  "properties": {
    "iso:country":"US",
    "sg:address":"1705 2nd Ave",
    "sg:city":"Rock Island",
    "sg:classifiers":[
        {
            "category":"Organizations",
            "subcategory":"Community Association",
            "type":"Services"
        }
    ],
    "sg:phone":"+1 309 788 2275",
    "sg:postcode":"61201",
    "sg:province":"IL",
    "sg:tags":[
        "fraternal"
    ],
    "wof:name":"Knights Of Columbus",
    "wof:placetype":"venue"
},
  "geometry": {"coordinates":[-90.57522899999999,41.511133],"type":"Point"}
}