{
  "type": "Feature",
  "properties": {
    "iso:country":"US",
    "sg:address":"372 Whitewater Dr",
    "sg:city":"Bolingbrook",
    "sg:classifiers":[
        {
            "category":"Professional",
            "subcategory":"Management & Consulting",
            "type":"Services"
        }
    ],
    "sg:phone":"+1 630 378 9299",
    "sg:postcode":"60440",
    "sg:province":"IL",
    "sg:tags":[
        "construction"
    ],
    "wof:name":"United Concepts",
    "wof:placetype":"venue"
},
  "geometry": {"coordinates":[-88.095015,41.70561],"type":"Point"}
}