{
  "type": "Feature",
  "properties": {
    "iso:country":"US",
    "sg:address":"2008 Cumberland St",
    "sg:city":"Rockford",
    "sg:classifiers":[
        {
            "category":"Health Services",
            "subcategory":"Health Practitioner",
            "type":"Services"
        }
    ],
    "sg:phone":"+1 815 543 3729",
    "sg:postcode":"61103",
    "sg:province":"IL",
    "wof:name":"Christine E Layng",
    "wof:placetype":"venue"
},
  "geometry": {"coordinates":[-89.068412,42.294411],"type":"Point"}
}