{
  "type": "Feature",
  "properties": {
    "iso:country":"US",
    "sg:address":"4829 Dempster St",
    "sg:city":"Skokie",
    "sg:classifiers":[
        {
            "category":"Retail",
            "subcategory":"Auto Repair",
            "type":"Services"
        }
    ],
    "sg:phone":"+1 847 677 4244",
    "sg:postcode":"60077",
    "sg:province":"IL",
    "sg:tags":[
        "transmission"
    ],
    "wof:name":"A Value Transmissions",
    "wof:placetype":"venue"
},
  "geometry": {"coordinates":[-87.747185,42.040677],"type":"Point"}
}