{
  "type": "Feature",
  "properties": {
    "iso:country":"US",
    "sg:address":"5568 Logan Rd",
    "sg:city":"West Frankfort",
    "sg:classifiers":[
        {
            "category":"Wholesale",
            "subcategory":"Machinery & Supplies",
            "type":"Manufacturing & Wholesale Goods"
        }
    ],
    "sg:phone":"+1 618 435 5811",
    "sg:postcode":"62896",
    "sg:province":"IL",
    "sg:tags":[
        "equipment",
        "well",
        "drilling"
    ],
    "wof:name":"Bit Brokers Intl",
    "wof:placetype":"venue"
},
  "geometry": {"coordinates":[-88.844977,37.944533],"type":"Point"}
}