{
  "type": "Feature",
  "properties": {
    "addr:full":"222 W Benton St Aurora IL 60506",
    "addr:housenumber":"222",
    "addr:postcode":"60506",
    "addr:street":"W Benton St",
    "iso:country":"US",
    "sg:address":"222 W Benton St",
    "sg:city":"Aurora",
    "sg:classifiers":[
        {
            "category":"Home & Garden",
            "subcategory":"Garden Supply",
            "type":"Retail Goods"
        }
    ],
    "sg:phone":"+1   ",
    "sg:postcode":"60506",
    "sg:province":"IL",
    "sg:tags":[
        "hardware",
        "repair"
    ],
    "wof:name":"Heimans Lawn Equipment",
    "wof:placetype":"venue"
},
  "geometry": {"coordinates":[-88.32102,41.758291],"type":"Point"}
}