{
  "type": "Feature",
  "properties": {
    "addr:full":"826 Joliet St West Chicago IL 60185",
    "addr:housenumber":"826",
    "addr:postcode":"60185",
    "addr:street":"Joliet St West",
    "iso:country":"US",
    "sg:address":"826 Joliet St",
    "sg:city":"West Chicago",
    "sg:classifiers":[
        {
            "category":"Sports & Exercise",
            "subcategory":"Gym",
            "type":"Entertainment"
        }
    ],
    "sg:phone":"+1 630 231 7819",
    "sg:postcode":"60185",
    "sg:province":"IL",
    "sg:tags":[
        "fitness",
        "physical",
        "facility"
    ],
    "wof:name":"Personal Image Studio",
    "wof:placetype":"venue"
},
  "geometry": {"coordinates":[-88.204657,41.871507],"type":"Point"}
}