{
  "type": "Feature",
  "properties": {
    "addr:full":"1681 Roosa Ln Elk Grove Village IL 60007",
    "addr:housenumber":"1681",
    "addr:postcode":"60007",
    "addr:street":"Roosa Ln",
    "iso:country":"US",
    "sg:address":"1681 Roosa Ln",
    "sg:city":"Elk Grove Village",
    "sg:classifiers":[
        {
            "category":"Freight",
            "type":"Transportation"
        }
    ],
    "sg:phone":"+1 847 985 0857",
    "sg:postcode":"60007",
    "sg:province":"IL",
    "wof:name":"Big G Logistics Inc",
    "wof:placetype":"venue"
},
  "geometry": {"coordinates":[-88.04115299999999,41.992483],"type":"Point"}
}