{
  "type": "Feature",
  "properties": {
    "addr:full":"102 1st St Coal Valley IL 61240",
    "addr:housenumber":"102",
    "addr:postcode":"61240",
    "addr:street":"1St St",
    "iso:country":"US",
    "sg:address":"102 1st St",
    "sg:city":"Coal Valley",
    "sg:classifiers":[
        {
            "category":"Autos & Motor Vehicles",
            "subcategory":"Automobile Sales",
            "type":"Retail Goods"
        }
    ],
    "sg:phone":"+1   ",
    "sg:postcode":"61240",
    "sg:province":"IL",
    "sg:tags":[
        "used"
    ],
    "wof:name":"Zieglers Auto Sales Inc",
    "wof:placetype":"venue"
},
  "geometry": {"coordinates":[-90.46086200000001,41.450081],"type":"Point"}
}