{
  "type": "Feature",
  "properties": {
    "addr:full":"163 N Latrobe Ave Chicago IL 60644",
    "addr:housenumber":"163",
    "addr:postcode":"60644",
    "addr:street":"N Latrobe Ave",
    "iso:country":"US",
    "sg:address":"163 N Latrobe Ave",
    "sg:city":"Chicago",
    "sg:classifiers":[
        {
            "category":"Personal",
            "subcategory":"Beauty Salon",
            "type":"Services"
        }
    ],
    "sg:phone":"+1 773 921 0381",
    "sg:postcode":"60644",
    "sg:province":"IL",
    "sg:tags":[
        "shop"
    ],
    "wof:name":"Sonias Unique Hair Studio",
    "wof:placetype":"venue"
},
  "geometry": {"coordinates":[-87.75639,41.885065],"type":"Point"}
}