{
  "type": "Feature",
  "properties": {
    "iso:country":"US",
    "sg:address":"7273 E 1550 North Rd",
    "sg:city":"Danvers",
    "sg:classifiers":[
        {
            "category":"Building & Trades",
            "subcategory":"Construction",
            "type":"Services"
        }
    ],
    "sg:phone":"+1 309 963 3944",
    "sg:postcode":"61732",
    "sg:province":"IL",
    "sg:tags":[
        "contractor"
    ],
    "wof:name":"Modern Day Log Homes Inc",
    "wof:placetype":"venue"
},
  "geometry": {"coordinates":[-89.130402,40.509201],"type":"Point"}
}