{
  "type": "Feature",
  "properties": {
    "iso:country":"US",
    "sg:address":"1802 W Berteau Ave Suite 209",
    "sg:city":"Chicago",
    "sg:classifiers":[
        {
            "category":"Communications",
            "type":"Services"
        }
    ],
    "sg:phone":"+1 773 348 4200",
    "sg:postcode":"60613",
    "sg:province":"IL",
    "sg:tags":[
        "web",
        "design"
    ],
    "sg:website":"www.sandstormdesign.com",
    "wof:name":"Sandstorm Design",
    "wof:placetype":"venue"
},
  "geometry": {"coordinates":[-87.674729,41.958157],"type":"Point"}
}