{
  "type": "Feature",
  "properties": {
    "iso:country":"US",
    "sg:address":"2633 N Pecatonica Rd",
    "sg:city":"Pecatonica",
    "sg:classifiers":[
        {
            "category":"Home & Garden",
            "subcategory":"Building Materials",
            "type":"Retail Goods"
        }
    ],
    "sg:phone":"+1 815 239 1671",
    "sg:postcode":"61063",
    "sg:province":"IL",
    "sg:tags":[
        "hardware",
        "lumber"
    ],
    "wof:name":"Top Notch Building Supply",
    "wof:placetype":"venue"
},
  "geometry": {"coordinates":[-89.359136,42.298297],"type":"Point"}
}