{
  "type": "Feature",
  "properties": {
    "iso:country":"US",
    "sg:address":"7215 Oak Ave",
    "sg:city":"River Forest",
    "sg:classifiers":[
        {
            "category":"Professional",
            "subcategory":"Lawyer & Legal Services",
            "type":"Services"
        }
    ],
    "sg:phone":"+1 708 366 5200",
    "sg:postcode":"60305",
    "sg:province":"IL",
    "wof:name":"Lauber Daniel Atty",
    "wof:placetype":"venue"
},
  "geometry": {"coordinates":[-87.805397,41.891998],"type":"Point"}
}