{
  "type": "Feature",
  "properties": {
    "addr:full":"15039 W 8000S Rd Buckingham IL 60917",
    "addr:housenumber":"15039",
    "addr:postcode":"60917",
    "addr:street":"W 8000S Rd",
    "iso:country":"US",
    "sg:address":"15039 W 8000S Rd",
    "sg:city":"Buckingham",
    "sg:classifiers":[
        {
            "category":"Farming",
            "subcategory":"Farm",
            "type":"Manufacturing & Wholesale Goods"
        }
    ],
    "sg:phone":"+1 815 949 1587",
    "sg:postcode":"60917",
    "sg:province":"IL",
    "sg:tags":[
        "crop",
        "general"
    ],
    "wof:name":"Richie John",
    "wof:placetype":"venue"
},
  "geometry": {"coordinates":[-88.151493,40.997175],"type":"Point"}
}