{
  "type": "Feature",
  "properties": {
    "iso:country":"US",
    "sg:address":"16695 W Stewart Rd",
    "sg:city":"Polo",
    "sg:classifiers":[
        {
            "category":"Farming",
            "subcategory":"Farm",
            "type":"Manufacturing & Wholesale Goods"
        }
    ],
    "sg:phone":"+1 815 946 3521",
    "sg:postcode":"61064",
    "sg:province":"IL",
    "sg:tags":[
        "crop",
        "general"
    ],
    "wof:name":"Keith Schryver",
    "wof:placetype":"venue"
},
  "geometry": {"coordinates":[-89.649525,42.016439],"type":"Point"}
}