{
  "type": "Feature",
  "properties": {
    "addr:full":"1547 Hoyle Rd Dixon IL 61021",
    "addr:housenumber":"1547",
    "addr:postcode":"61021",
    "addr:street":"Hoyle Rd",
    "iso:country":"US",
    "sg:address":"1547 Hoyle Rd",
    "sg:city":"Dixon",
    "sg:classifiers":[
        {
            "category":"Wholesale",
            "subcategory":"Construction Materials",
            "type":"Manufacturing & Wholesale Goods"
        },
        {
            "category":"Building & Trades",
            "subcategory":"Landscaping Services",
            "type":"Services"
        }
    ],
    "sg:phone":"+1 815 288 7261",
    "sg:postcode":"61021",
    "sg:province":"IL",
    "sg:tags":[
        "sand",
        "gravel",
        "landscape",
        "contractor"
    ],
    "wof:name":"Mel's Materials",
    "wof:placetype":"venue"
},
  "geometry": {"coordinates":[-89.51521099999999,41.806825],"type":"Point"}
}