{
  "type": "Feature",
  "properties": {
    "iso:country":"US",
    "sg:address":"4400 Greenwood St",
    "sg:city":"Skokie",
    "sg:classifiers":[
        {
            "category":"Government",
            "subcategory":"Office",
            "type":"Public Place"
        }
    ],
    "sg:phone":"+1   ",
    "sg:postcode":"60076",
    "sg:province":"IL",
    "sg:tags":[
        "center",
        "community",
        "activity"
    ],
    "wof:name":"Devonshire Cultural Center",
    "wof:placetype":"venue"
},
  "geometry": {"coordinates":[-87.73986600000001,42.042644],"type":"Point"}
}