{
  "type": "Feature",
  "properties": {
    "iso:country":"US",
    "sg:address":"11240 S Michigan Avenue",
    "sg:city":"Chicago",
    "sg:classifiers":[
        {
            "category":"Health Services",
            "subcategory":"Doctor",
            "type":"Services"
        },
        {
            "category":"Insurance",
            "subcategory":"Hazard Insurance",
            "type":"Services"
        }
    ],
    "sg:phone":"+1 773 468 2101",
    "sg:postcode":"60628",
    "sg:province":"IL",
    "sg:tags":[
        "group"
    ],
    "wof:name":"Shah Devina",
    "wof:placetype":"venue"
},
  "geometry": {"coordinates":[-87.621082,41.689593],"type":"Point"}
}