{
  "type": "Feature",
  "properties": {
    "iso:country":"US",
    "sg:address":"615 Garfield St",
    "sg:city":"Oak Park",
    "sg:classifiers":[
        {
            "category":"Museum",
            "subcategory":"Botanical Garden",
            "type":"Entertainment"
        }
    ],
    "sg:phone":"+1 708 386 4700",
    "sg:postcode":"60304",
    "sg:province":"IL",
    "sg:tags":[
        "park"
    ],
    "wof:name":"Oak Park Conservatory",
    "wof:placetype":"venue"
},
  "geometry": {"coordinates":[-87.78919999999999,41.871399],"type":"Point"}
}