{
  "type": "Feature",
  "properties": {
    "addr:city":"Oak Park",
    "addr:full":"615 Garfield Street Oak Park, Il 60304",
    "addr:house_number":"615",
    "addr:housenumber":"615",
    "addr:phone":"+1 708-386-4700",
    "addr:postcode":"60304",
    "addr:road":"Garfield Street",
    "addr:state":"IL",
    "addr:street":"Garfield St",
    "iso:country":"US",
    "sg:address":"615 Garfield St",
    "sg:city":"Oak Park",
    "sg:classifiers":[
        {
            "category":"Museum",
            "subcategory":"Botanical Garden",
            "type":"Entertainment"
        }
    ],
    "sg:phone":"+1 708 386 4700",
    "sg:postcode":"60304",
    "sg:province":"IL",
    "sg:tags":[
        "park"
    ],
    "wof:airports":[
        102531205,
        102533631
    ],
    "wof:name":"Oak Park Conservatory",
    "wof:placetype":"venue"
},
  "geometry": {"coordinates":[-87.78999,41.87159],"type":"Point"}
}