{
  "type": "Feature",
  "properties": {
    "addr:full":"1401 S Arlington Heights Rd Arlington Hts IL 60005",
    "addr:housenumber":"1401",
    "addr:postcode":"60005",
    "addr:street":"S Arlington Heights Rd",
    "iso:country":"US",
    "sg:address":"1401 S Arlington Heights Rd",
    "sg:city":"Arlington Hts",
    "sg:classifiers":[
        {
            "category":"Sports & Exercise",
            "subcategory":"Gym",
            "type":"Entertainment"
        }
    ],
    "sg:phone":"+1 847 437 7569",
    "sg:postcode":"60005",
    "sg:province":"IL",
    "sg:tags":[
        "club",
        "health",
        "studio",
        "gymnasium"
    ],
    "wof:name":"Exercise Coach",
    "wof:placetype":"venue"
},
  "geometry": {"coordinates":[-87.980403,42.058281],"type":"Point"}
}