{
  "type": "Feature",
  "properties": {
    "addr:full":"562 Randall Rd South Elgin IL 60177",
    "addr:housenumber":"562",
    "addr:postcode":"60177",
    "addr:street":"Randall Rd",
    "iso:country":"US",
    "sg:address":"562 Randall Rd",
    "sg:city":"South Elgin",
    "sg:classifiers":[
        {
            "category":"Ice Cream",
            "type":"Food & Drink"
        }
    ],
    "sg:menulink":"http://www.allmenus.com/il/st-charles/232247-maggie-moos/menu/",
    "sg:phone":"+1 847 760 6667",
    "sg:postcode":"60177",
    "sg:province":"IL",
    "sg:tags":[
        "american"
    ],
    "wof:name":"Maggie Moo's",
    "wof:placetype":"venue"
},
  "geometry": {"coordinates":[-88.340599,41.975264],"type":"Point"}
}