{
  "type": "Feature",
  "properties": {
    "addr:full":"36160 Ohlhues Rd Wilmington IL 60481",
    "addr:postcode":"36160;60481",
    "addr:street":"Ohlhues Rd",
    "iso:country":"US",
    "sg:address":"36160 Ohlhues Rd",
    "sg:city":"Wilmington",
    "sg:classifiers":[
        {
            "category":"Real Estate",
            "subcategory":"Real Estate Operator",
            "type":"Services"
        }
    ],
    "sg:phone":"+1 815 458 2923",
    "sg:postcode":"60481",
    "sg:province":"IL",
    "sg:tags":[
        "property",
        "lessor"
    ],
    "wof:name":"Love John",
    "wof:placetype":"venue"
},
  "geometry": {"coordinates":[-88.12989899999999,41.227061],"type":"Point"}
}