{
  "type": "Feature",
  "properties": {
    "addr:full":"605 Silver Leaf Dr Joliet IL 60431",
    "addr:housenumber":"605",
    "addr:postcode":"60431",
    "addr:street":"Silver Leaf Dr",
    "iso:country":"US",
    "sg:address":"605 Silver Leaf Dr",
    "sg:city":"Joliet",
    "sg:classifiers":[
        {
            "category":"Real Estate",
            "subcategory":"Real Estate Agent",
            "type":"Services"
        }
    ],
    "sg:phone":"+1 815 730 0008",
    "sg:postcode":"60431",
    "sg:province":"IL",
    "wof:name":"Silver Leaf",
    "wof:placetype":"venue"
},
  "geometry": {"coordinates":[-88.167801,41.509768],"type":"Point"}
}