{
  "type": "Feature",
  "properties": {
    "addr:full":"201 W Springfield Ave Champaign IL 61820",
    "addr:housenumber":"201",
    "addr:postcode":"61820",
    "addr:street":"W Springfield Ave",
    "iso:country":"US",
    "sg:address":"201 W Springfield Ave",
    "sg:city":"Champaign",
    "sg:classifiers":[
        {
            "category":"Real Estate",
            "subcategory":"Architect",
            "type":"Services"
        }
    ],
    "sg:phone":"+1 217 355 2700",
    "sg:postcode":"61820",
    "sg:province":"IL",
    "wof:name":"Moline Architecture Group the",
    "wof:placetype":"venue"
},
  "geometry": {"coordinates":[-88.245102,40.112598],"type":"Point"}
}