{
  "type": "Feature",
  "properties": {
    "addr:full":"2005 15th St Rockford IL 61104",
    "addr:housenumber":"2005",
    "addr:postcode":"61104",
    "addr:street":"15Th St",
    "iso:country":"US",
    "sg:address":"2005 15th St",
    "sg:city":"Rockford",
    "sg:classifiers":[
        {
            "category":"Manufacturing",
            "subcategory":"Metals",
            "type":"Manufacturing & Wholesale Goods"
        }
    ],
    "sg:phone":"+1 815 397 8848",
    "sg:postcode":"61104",
    "sg:province":"IL",
    "sg:tags":[
        "screw"
    ],
    "wof:name":"Elite Fastener Co",
    "wof:placetype":"venue"
},
  "geometry": {"coordinates":[-89.065225,42.246356],"type":"Point"}
}