{
  "type": "Feature",
  "properties": {
    "iso:country":"US",
    "sg:address":"1900 E Golf Rd",
    "sg:city":"Schaumburg",
    "sg:classifiers":[
        {
            "category":"Real Estate",
            "subcategory":"Real Estate Services",
            "type":"Services"
        }
    ],
    "sg:phone":"+1 847 592 6200",
    "sg:postcode":"60173",
    "sg:province":"IL",
    "sg:tags":[
        "vacancy",
        "rental",
        "listing"
    ],
    "wof:name":"Intelligent Office-Schaumburg",
    "wof:placetype":"venue"
},
  "geometry": {"coordinates":[-88.034004,42.050581],"type":"Point"}
}