{
  "type": "Feature",
  "properties": {
    "addr:full":"301 S Putnam St Bunker Hill IL 62014",
    "addr:housenumber":"301",
    "addr:postcode":"62014",
    "addr:street":"S Putnam St",
    "iso:country":"US",
    "sg:address":"301 S Putnam St",
    "sg:city":"Bunker Hill",
    "sg:classifiers":[
        {
            "category":"Retail",
            "subcategory":"Portrait Studio",
            "type":"Services"
        }
    ],
    "sg:phone":"+1 618 585 9821",
    "sg:postcode":"62014",
    "sg:province":"IL",
    "sg:tags":[
        "photographer"
    ],
    "wof:name":"Through A Lens Photography",
    "wof:placetype":"venue"
},
  "geometry": {"coordinates":[-89.95311100000001,39.041024],"type":"Point"}
}