{
  "type": "Feature",
  "properties": {
    "iso:country":"US",
    "sg:address":"100 N Main St",
    "sg:city":"Wood River",
    "sg:classifiers":[
        {
            "category":"Professional",
            "type":"Services"
        }
    ],
    "sg:phone":"+1 618 251 6025",
    "sg:postcode":"62095",
    "sg:province":"IL",
    "sg:tags":[
        "establishment"
    ],
    "wof:name":"CSD",
    "wof:placetype":"venue"
},
  "geometry": {"coordinates":[-90.105659,38.861731],"type":"Point"}
}