{
  "type": "Feature",
  "properties": {
    "addr:full":"328 E 75th St Chicago IL 60619",
    "addr:housenumber":"328",
    "addr:postcode":"60619",
    "addr:street":"E 75Th St",
    "iso:country":"US",
    "sg:address":"328 E 75th St",
    "sg:city":"Chicago",
    "sg:classifiers":[
        {
            "category":"Bakery",
            "type":"Food & Drink"
        }
    ],
    "sg:phone":"+1 773 224 6262",
    "sg:postcode":"60619",
    "sg:province":"IL",
    "sg:website":"www.ilovefoodgroup.com/BrownSuga...",
    "wof:name":"Brown Sugar Bakery",
    "wof:placetype":"venue"
},
  "geometry": {"coordinates":[-87.61721799999999,41.758241],"type":"Point"}
}