{
  "type": "Feature",
  "properties": {
    "iso:country":"US",
    "sg:address":"7200 Harrison Ave",
    "sg:city":"Rockford",
    "sg:classifiers":[
        {
            "category":"Shopping",
            "subcategory":"Clothing, Apparel, & Fashions",
            "type":"Retail Goods"
        }
    ],
    "sg:phone":"+1 815 332 3328",
    "sg:postcode":"61112",
    "sg:province":"IL",
    "sg:website":"www.christopherandbanks.com",
    "wof:name":"Christopher & Banks Inc",
    "wof:placetype":"venue"
},
  "geometry": {"coordinates":[-88.97232099999999,42.240767],"type":"Point"}
}