{
  "type": "Feature",
  "properties": {
    "addr:full":"1301 Copperfield Ave Ste 201 Joliet IL 60432",
    "addr:housenumber":"1301",
    "addr:postcode":"60432",
    "addr:street":"Copperfield Ave Ste 201",
    "iso:country":"US",
    "sg:address":"1301 Copperfield Ave Ste 201",
    "sg:city":"Joliet",
    "sg:classifiers":[
        {
            "category":"Health Services",
            "subcategory":"Doctor",
            "type":"Services"
        }
    ],
    "sg:phone":"+1 815 727 4434",
    "sg:postcode":"60432",
    "sg:province":"IL",
    "sg:tags":[
        "medicine",
        "physician",
        "practice",
        "surgeons",
        "family"
    ],
    "wof:name":"Hssi",
    "wof:placetype":"venue"
},
  "geometry": {"coordinates":[-88.050179,41.536547],"type":"Point"}
}