{
  "type": "Feature",
  "properties": {
    "iso:country":"US",
    "sg:address":"1305 Forest Ave",
    "sg:city":"Evanston",
    "sg:classifiers":[
        {
            "category":"Education",
            "subcategory":"Special Training",
            "type":"Public Place"
        }
    ],
    "sg:phone":"+1 847 864 0030",
    "sg:postcode":"60201",
    "sg:province":"IL",
    "wof:name":"Verhoog Music Institute",
    "wof:placetype":"venue"
},
  "geometry": {"coordinates":[-87.674835,42.042521],"type":"Point"}
}