{
  "type": "Feature",
  "properties": {
    "iso:country":"US",
    "sg:address":"929 E Palatine Rd",
    "sg:city":"Palatine",
    "sg:classifiers":[
        {
            "category":"Social Services",
            "subcategory":"Child Care",
            "type":"Services"
        },
        {
            "category":"Education",
            "subcategory":"Preschool",
            "type":"Public Place"
        }
    ],
    "sg:phone":"+1 847 358 2233",
    "sg:postcode":"60074",
    "sg:province":"IL",
    "sg:tags":[
        "kindergarten",
        "nursery",
        "day"
    ],
    "sg:website":"http://www.kindercare.com/our-centers/center-details/301067/?cid=YP_KC301067",
    "wof:name":"Palatine KinderCare",
    "wof:placetype":"venue"
},
  "geometry": {"coordinates":[-88.02146500000001,42.110207],"type":"Point"}
}