{
  "type": "Feature",
  "properties": {
    "iso:country":"US",
    "sg:address":"25091 Crabtree Ln",
    "sg:city":"Ingleside",
    "sg:classifiers":[
        {
            "category":"Home & Garden",
            "subcategory":"Building Materials",
            "type":"Retail Goods"
        },
        {
            "category":"Manufacturing",
            "subcategory":"Tools & Machinery",
            "type":"Manufacturing & Wholesale Goods"
        }
    ],
    "sg:phone":"+1 847 740 0274",
    "sg:postcode":"60041",
    "sg:province":"IL",
    "sg:tags":[
        "windows",
        "industry",
        "mfg"
    ],
    "wof:name":"Creators Stained Glass Inc",
    "wof:placetype":"venue"
},
  "geometry": {"coordinates":[-88.12212100000001,42.39019],"type":"Point"}
}