{
  "type": "Feature",
  "properties": {
    "iso:country":"US",
    "sg:address":"836 W Wellington Avenue",
    "sg:city":"Chicago",
    "sg:classifiers":[
        {
            "category":"Personal",
            "subcategory":"Adult",
            "type":"Services"
        }
    ],
    "sg:phone":"+1 773 296 7032",
    "sg:postcode":"60657",
    "sg:province":"IL",
    "sg:tags":[
        "midwife"
    ],
    "wof:name":"Nurses -Midwife Service of Illinois Masonic Medical Center",
    "wof:placetype":"venue"
},
  "geometry": {"coordinates":[-87.65079299999999,41.936338],"type":"Point"}
}