{
  "type": "Feature",
  "properties": {
    "addr:full":"1115 W Nevada St Urbana IL 61801",
    "addr:housenumber":"1115",
    "addr:postcode":"61801",
    "addr:street":"W Nevada St",
    "iso:country":"US",
    "sg:address":"1115 W Nevada St",
    "sg:city":"Urbana",
    "sg:classifiers":[
        {
            "category":"Education",
            "subcategory":"University",
            "type":"Public Place"
        }
    ],
    "sg:phone":"+1 217 244 7639",
    "sg:postcode":"61801",
    "sg:province":"IL",
    "sg:tags":[
        "college"
    ],
    "sg:website":"www.uillinois.edu",
    "wof:name":"University of Illinois",
    "wof:placetype":"venue"
},
  "geometry": {"coordinates":[-88.22186000000001,40.105843],"type":"Point"}
}