{
  "type": "Feature",
  "properties": {
    "addr:full":"7851 S Escanaba Ave Chicago IL 60649",
    "addr:housenumber":"7851",
    "addr:postcode":"60649",
    "addr:street":"S Escanaba Ave",
    "iso:country":"US",
    "sg:address":"7851 S Escanaba Ave",
    "sg:city":"Chicago",
    "sg:classifiers":[
        {
            "category":"Organizations",
            "subcategory":"Community Association",
            "type":"Services"
        }
    ],
    "sg:phone":"+1 773 374 0711",
    "sg:postcode":"60649",
    "sg:province":"IL",
    "sg:tags":[
        "veteran"
    ],
    "wof:name":"Chicago Vietnm Vet/Fmly Assist",
    "wof:placetype":"venue"
},
  "geometry": {"coordinates":[-87.553983,41.752967],"type":"Point"}
}