{
  "type": "Feature",
  "properties": {
    "addr:full":"287 Southwoods Center Columbia IL 62236",
    "addr:housenumber":"287",
    "addr:postcode":"62236",
    "addr:street":"Southwoods Center",
    "iso:country":"US",
    "sg:address":"287 Southwoods Center",
    "sg:city":"Columbia",
    "sg:classifiers":[
        {
            "category":"Retail",
            "subcategory":"Car Wash",
            "type":"Services"
        }
    ],
    "sg:phone":"+1 618 281 3213",
    "sg:postcode":"62236",
    "sg:province":"IL",
    "sg:tags":[
        "polishing",
        "washing"
    ],
    "wof:name":"Splash Carwash",
    "wof:placetype":"venue"
},
  "geometry": {"coordinates":[-90.195346,38.436067],"type":"Point"}
}