{
  "type": "Feature",
  "properties": {
    "iso:country":"US",
    "sg:address":"9231 159th St",
    "sg:city":"Tinley Park",
    "sg:classifiers":[
        {
            "category":"Home & Garden",
            "subcategory":"Household Appliances",
            "type":"Retail Goods"
        }
    ],
    "sg:phone":"+1   ",
    "sg:postcode":"60487",
    "sg:province":"IL",
    "wof:name":"Circuit City",
    "wof:placetype":"venue"
},
  "geometry": {"coordinates":[-87.845663,41.601395],"type":"Point"}
}