{
  "type": "Feature",
  "properties": {
    "addr:full":"9540 S Harvard Ave Chicago IL 60628",
    "addr:housenumber":"9540",
    "addr:postcode":"60628",
    "addr:street":"S Harvard Ave",
    "iso:country":"US",
    "sg:address":"9540 S Harvard Ave",
    "sg:city":"Chicago",
    "sg:classifiers":[
        {
            "category":"Place Of Worship",
            "subcategory":"Church",
            "type":"Public Place"
        },
        {
            "category":"Place Of Worship",
            "type":"Public Place"
        },
        {
            "category":"Education",
            "subcategory":"School",
            "type":"Public Place"
        }
    ],
    "sg:phone":"+1 773 568 7077",
    "sg:postcode":"60628",
    "sg:province":"IL",
    "sg:tags":[
        "churches-catholic-traditional",
        "churches-catholic",
        "private",
        "k-"
    ],
    "sg:website":"http://www.archdiocese-chgo.org",
    "wof:name":"St Thadeus Catholic School",
    "wof:placetype":"venue"
},
  "geometry": {"coordinates":[-87.632294,41.720834],"type":"Point"}
}