{
  "type": "Feature",
  "properties": {
    "iso:country":"US",
    "sg:address":"3808 N Olcott Ave",
    "sg:city":"Chicago",
    "sg:classifiers":[
        {
            "category":"Professional",
            "subcategory":"Detective & Security Services",
            "type":"Services"
        }
    ],
    "sg:phone":"+1 773 589 1121",
    "sg:postcode":"60634",
    "sg:province":"IL",
    "sg:tags":[
        "information",
        "bureau"
    ],
    "wof:name":"Gap Services Inc",
    "wof:placetype":"venue"
},
  "geometry": {"coordinates":[-87.814454,41.948833],"type":"Point"}
}