{
  "type": "Feature",
  "properties": {
    "addr:full":"2920 N Commonwealth Ave Chicago IL 60657",
    "addr:housenumber":"2920",
    "addr:postcode":"60657",
    "addr:street":"N Commonwealth Ave",
    "iso:country":"US",
    "sg:address":"2920 N Commonwealth Ave",
    "sg:city":"Chicago",
    "sg:classifiers":[
        {
            "category":"Banks & Credit Unions",
            "subcategory":"Investment Brokerage",
            "type":"Services"
        }
    ],
    "sg:phone":"+1 773 871 0072",
    "sg:postcode":"60657",
    "sg:province":"IL",
    "sg:tags":[
        "security"
    ],
    "wof:name":"Vaile Financial Group Inc",
    "wof:placetype":"venue"
},
  "geometry": {"coordinates":[-87.638087,41.934637],"type":"Point"}
}