{
  "type": "Feature",
  "properties": {
    "iso:country":"US",
    "sg:address":"137 W Railroad St",
    "sg:city":"Earlville",
    "sg:classifiers":[
        {
            "category":"Bars & Pubs",
            "type":"Food & Drink"
        },
        {
            "category":"Restaurant",
            "type":"Food & Drink"
        }
    ],
    "sg:phone":"+1 815 246 7050",
    "sg:postcode":"60518",
    "sg:province":"IL",
    "sg:tags":[
        "eating"
    ],
    "wof:name":"Pokas Bar & Grill",
    "wof:placetype":"venue"
},
  "geometry": {"coordinates":[-88.92225000000001,41.590338],"type":"Point"}
}