{
  "type": "Feature",
  "properties": {
    "iso:country":"US",
    "sg:address":"3559 N Pulaski Rd",
    "sg:city":"Chicago",
    "sg:classifiers":[
        {
            "category":"Food & Beverages",
            "subcategory":"Groceries & Convenience Stores",
            "type":"Retail Goods"
        }
    ],
    "sg:phone":"+1 773 463 0161",
    "sg:postcode":"60641",
    "sg:province":"IL",
    "sg:website":"www.7-eleven.com",
    "wof:name":"7-Eleven",
    "wof:placetype":"venue"
},
  "geometry": {"coordinates":[-87.727402,41.946098],"type":"Point"}
}