{
  "type": "Feature",
  "properties": {
    "iso:country":"US",
    "sg:address":"523 E Cedarville Rd",
    "sg:city":"Freeport",
    "sg:classifiers":[
        {
            "category":"Real Estate",
            "subcategory":"Real Estate Operator",
            "type":"Services"
        }
    ],
    "sg:phone":"+1 815 563 4991",
    "sg:postcode":"61032",
    "sg:province":"IL",
    "sg:tags":[
        "farm",
        "property",
        "management",
        "crop",
        "lessor"
    ],
    "wof:name":"Steve Monigold",
    "wof:placetype":"venue"
},
  "geometry": {"coordinates":[-89.602833,42.374199],"type":"Point"}
}