{
  "type": "Feature",
  "properties": {
    "iso:country":"US",
    "sg:address":"208 S Walnut St",
    "sg:city":"Georgetown",
    "sg:classifiers":[
        {
            "category":"Government",
            "subcategory":"Office",
            "type":"Public Place"
        }
    ],
    "sg:phone":"+1 217 662 2525",
    "sg:postcode":"61846",
    "sg:province":"IL",
    "sg:tags":[
        "city"
    ],
    "wof:name":"Georgetown City Hall",
    "wof:placetype":"venue"
},
  "geometry": {"coordinates":[-87.634542,39.974471],"type":"Point"}
}