{
  "type": "Feature",
  "properties": {
    "addr:full":"624 W Cedarville Rd Freeport IL 61032",
    "addr:housenumber":"624",
    "addr:postcode":"61032",
    "addr:street":"W Cedarville Rd",
    "iso:country":"US",
    "sg:address":"624 W Cedarville Rd",
    "sg:city":"Freeport",
    "sg:classifiers":[
        {
            "category":"Retail",
            "subcategory":"Repair Shop",
            "type":"Services"
        }
    ],
    "sg:phone":"+1 815 563 4331",
    "sg:postcode":"61032",
    "sg:province":"IL",
    "sg:tags":[
        "taxidermist"
    ],
    "wof:name":"Arrowhead Taxidermy",
    "wof:placetype":"venue"
},
  "geometry": {"coordinates":[-89.62960200000001,42.374299],"type":"Point"}
}