{
  "type": "Feature",
  "properties": {
    "addr:full":"8527 S Stony Island Ave Chicago IL 60617",
    "addr:housenumber":"8527",
    "addr:postcode":"60617",
    "addr:street":"S Stony Island Ave",
    "iso:country":"US",
    "sg:address":"8527 S Stony Island Ave",
    "sg:city":"Chicago",
    "sg:classifiers":[
        {
            "category":"Professional",
            "subcategory":"Lawyer & Legal Services",
            "type":"Services"
        }
    ],
    "sg:phone":"+1 312 419 1001",
    "sg:postcode":"60617",
    "sg:province":"IL",
    "sg:tags":[
        "clinic",
        "law",
        "attorney",
        "bankruptcy"
    ],
    "sg:website":"http://www.legalremedieschicago.com",
    "wof:name":"Legal Remedies, Chartered",
    "wof:placetype":"venue"
},
  "geometry": {"coordinates":[-87.585283,41.739848],"type":"Point"}
}