{
  "type": "Feature",
  "properties": {
    "iso:country":"US",
    "sg:address":"1338 W Irving Park Rd",
    "sg:city":"Chicago",
    "sg:classifiers":[
        {
            "category":"Travel",
            "subcategory":"Travel Agent",
            "type":"Entertainment"
        }
    ],
    "sg:phone":"+1 773 477 6347",
    "sg:postcode":"60613",
    "sg:province":"IL",
    "wof:name":"Travelfast Chicago",
    "wof:placetype":"venue"
},
  "geometry": {"coordinates":[-87.663979,41.954585],"type":"Point"}
}