{
  "type": "Feature",
  "properties": {
    "iso:country":"US",
    "sg:address":"1707 W Golf Rd",
    "sg:city":"Mount Prospect",
    "sg:classifiers":[
        {
            "category":"Restaurant",
            "type":"Food & Drink"
        }
    ],
    "sg:phone":"+1   ",
    "sg:postcode":"60056",
    "sg:province":"IL",
    "sg:tags":[
        "eating"
    ],
    "wof:name":"Lees Burger Hut",
    "wof:placetype":"venue"
},
  "geometry": {"coordinates":[-87.963425,42.048609],"type":"Point"}
}