{
  "type": "Feature",
  "properties": {
    "addr:full":"8 Heritage Plz Bourbonnais IL 60914",
    "addr:housenumber":"8",
    "addr:postcode":"60914",
    "addr:street":"Heritage Plz Bourbonnais",
    "iso:country":"US",
    "sg:address":"8 Heritage Plz",
    "sg:city":"Bourbonnais",
    "sg:classifiers":[
        {
            "category":"Social Services",
            "type":"Services"
        }
    ],
    "sg:phone":"+1 815 939 2001",
    "sg:postcode":"60914",
    "sg:province":"IL",
    "sg:tags":[
        "counseling"
    ],
    "wof:name":"Pathways Counseling Svc",
    "wof:placetype":"venue"
},
  "geometry": {"coordinates":[-87.878524,41.163981],"type":"Point"}
}