{
  "type": "Feature",
  "properties": {
    "addr:full":"507 S Broadway Ave Urbana IL 61801",
    "addr:housenumber":"507",
    "addr:postcode":"61801",
    "addr:street":"S Broadway Ave",
    "iso:country":"US",
    "sg:address":"507 S Broadway Ave",
    "sg:city":"Urbana",
    "sg:classifiers":[
        {
            "category":"Banks & Credit Unions",
            "subcategory":"Bank",
            "type":"Services"
        }
    ],
    "sg:phone":"+1 217 255 6950",
    "sg:postcode":"61801",
    "sg:province":"IL",
    "sg:website":"www.nationalcity.com",
    "wof:name":"National City",
    "wof:placetype":"venue"
},
  "geometry": {"coordinates":[-88.21199799999999,40.105499],"type":"Point"}
}