{
  "type": "Feature",
  "properties": {
    "iso:country":"US",
    "sg:address":"2090 Larkin Ave",
    "sg:city":"Elgin",
    "sg:classifiers":[
        {
            "category":"Health Services",
            "subcategory":"Doctor",
            "type":"Services"
        }
    ],
    "sg:phone":"+1 847 741 6217",
    "sg:postcode":"60123",
    "sg:province":"IL",
    "sg:tags":[
        "dentist"
    ],
    "wof:name":"Michael D Johnson DDS",
    "wof:placetype":"venue"
},
  "geometry": {"coordinates":[-88.327262,42.032602],"type":"Point"}
}