{
  "type": "Feature",
  "properties": {
    "addr:full":"109 Tree Ridge Dr Columbia IL 62236",
    "addr:housenumber":"109",
    "addr:postcode":"62236",
    "addr:street":"Tree Ridge Dr",
    "iso:country":"US",
    "sg:address":"109 Tree Ridge Dr",
    "sg:city":"Columbia",
    "sg:classifiers":[
        {
            "category":"Building & Trades",
            "subcategory":"Construction",
            "type":"Services"
        }
    ],
    "sg:phone":"+1 618 281 7499",
    "sg:postcode":"62236",
    "sg:province":"IL",
    "sg:tags":[
        "general",
        "contractor"
    ],
    "wof:name":"Precision Construction",
    "wof:placetype":"venue"
},
  "geometry": {"coordinates":[-90.22332299999999,38.445304],"type":"Point"}
}