{
  "type": "Feature",
  "properties": {
    "iso:country":"US",
    "sg:address":"109 Tree Ridge Dr",
    "sg:city":"Columbia",
    "sg:classifiers":[
        {
            "category":"Building & Trades",
            "subcategory":"Construction",
            "type":"Services"
        }
    ],
    "sg:phone":"+1 618 281 7499",
    "sg:postcode":"62236",
    "sg:province":"IL",
    "sg:tags":[
        "general",
        "contractor"
    ],
    "wof:name":"Precision Construction",
    "wof:placetype":"venue"
},
  "geometry": {"coordinates":[-90.223323,38.445304],"type":"Point"}
}