{
  "type": "Feature",
  "properties": {
    "iso:country":"US",
    "sg:address":"166 W Washington Street",
    "sg:city":"Chicago",
    "sg:classifiers":[
        {
            "category":"Building & Trades",
            "subcategory":"Construction",
            "type":"Services"
        }
    ],
    "sg:phone":"+1 312 364 9098",
    "sg:postcode":"60602",
    "sg:province":"IL",
    "sg:tags":[
        "contractor"
    ],
    "wof:name":"Construction Service Assoc",
    "wof:placetype":"venue"
},
  "geometry": {"coordinates":[-87.632704,41.883212],"type":"Point"}
}