{
  "type": "Feature",
  "properties": {
    "addr:full":"880 N Farnsworth Ave Aurora IL 60505",
    "addr:housenumber":"880",
    "addr:postcode":"60505",
    "addr:street":"N Farnsworth Ave",
    "iso:country":"US",
    "sg:address":"880 N Farnsworth Ave",
    "sg:city":"Aurora",
    "sg:classifiers":[
        {
            "category":"Restaurant",
            "type":"Food & Drink"
        }
    ],
    "sg:menulink":"http://www.allmenus.com/il/aurora/223469-el-burrito-loco/menu/",
    "sg:phone":"+1 630 585 9095",
    "sg:postcode":"60505",
    "sg:province":"IL",
    "sg:tags":[
        "mexican"
    ],
    "wof:name":"El Burrito Loco",
    "wof:placetype":"venue"
},
  "geometry": {"coordinates":[-88.28171399999999,41.77554],"type":"Point"}
}