{
  "type": "Feature",
  "properties": {
    "addr:full":"175 Lagoon Dr Northfield IL 60093",
    "addr:housenumber":"175",
    "addr:postcode":"60093",
    "addr:street":"Lagoon Dr",
    "iso:country":"US",
    "sg:address":"175 Lagoon Dr",
    "sg:city":"Northfield",
    "sg:classifiers":[
        {
            "category":"Building & Trades",
            "subcategory":"Construction",
            "type":"Services"
        },
        {
            "category":"Building & Trades",
            "subcategory":"Electrical",
            "type":"Services"
        }
    ],
    "sg:phone":"+1 847 446 4104",
    "sg:postcode":"60093",
    "sg:province":"IL",
    "sg:tags":[
        "industrial",
        "electrician",
        "electric",
        "specialty",
        "heating",
        "contractors-commercial",
        "contractor"
    ],
    "wof:name":"Corb Electric Inc",
    "wof:placetype":"venue"
},
  "geometry": {"coordinates":[-87.761292,42.095919],"type":"Point"}
}