{
  "type": "Feature",
  "properties": {
    "iso:country":"US",
    "sg:address":"5024 W 16th St",
    "sg:city":"Cicero",
    "sg:classifiers":[
        {
            "category":"Autos & Motor Vehicles",
            "subcategory":"Fuel & Gas Station",
            "type":"Retail Goods"
        }
    ],
    "sg:phone":"+1 708 652 2802",
    "sg:postcode":"60804",
    "sg:province":"IL",
    "wof:name":"Richart's Auto Repair",
    "wof:placetype":"venue"
},
  "geometry": {"coordinates":[-87.750198,41.8587],"type":"Point"}
}