{
  "type": "Feature",
  "properties": {
    "iso:country":"US",
    "sg:address":"6418 Ogden Ave",
    "sg:city":"Berwyn",
    "sg:classifiers":[
        {
            "category":"Professional",
            "subcategory":"Lawyer & Legal Services",
            "type":"Services"
        }
    ],
    "sg:phone":"+1 708 749 8600",
    "sg:postcode":"60402",
    "sg:province":"IL",
    "sg:tags":[
        "attorney",
        "practice"
    ],
    "wof:name":"Law Offices of Esperanza Rivera-Valenzuela",
    "wof:placetype":"venue"
},
  "geometry": {"coordinates":[-87.783826,41.830153],"type":"Point"}
}