{
  "type": "Feature",
  "properties": {
    "addr:full":"3270 S Archer Avenue Chicago IL 60608",
    "addr:housenumber":"3270",
    "addr:postcode":"60608",
    "addr:street":"S Archer Avenue",
    "iso:country":"US",
    "sg:address":"3270 S Archer Avenue",
    "sg:city":"Chicago",
    "sg:classifiers":[
        {
            "category":"Retail",
            "subcategory":"Auto Repair",
            "type":"Services"
        }
    ],
    "sg:phone":"+1 773 523 8299",
    "sg:postcode":"60608",
    "sg:province":"IL",
    "wof:name":"Master Auto Service",
    "wof:placetype":"venue"
},
  "geometry": {"coordinates":[-87.670827,41.834713],"type":"Point"}
}