{
  "type": "Feature",
  "properties": {
    "iso:country":"US",
    "sg:address":"3906 Harlem Ave",
    "sg:city":"Lyons",
    "sg:classifiers":[
        {
            "category":"Restaurant",
            "type":"Food & Drink"
        }
    ],
    "sg:phone":"+1 708 442 1610",
    "sg:postcode":"60534",
    "sg:province":"IL",
    "sg:tags":[
        "asian",
        "chinese",
        "pan"
    ],
    "wof:name":"Hong Kong Garden",
    "wof:placetype":"venue"
},
  "geometry": {"coordinates":[-87.802696,41.820202],"type":"Point"}
}