{
  "type": "Feature",
  "properties": {
    "addr:full":"1923 W Montrose Ave Ste 1 Chicago IL 60613",
    "addr:housenumber":"1923",
    "addr:postcode":"60613",
    "addr:street":"W Montrose Ave Ste 1",
    "iso:country":"US",
    "sg:address":"1923 W Montrose Ave Ste 1",
    "sg:city":"Chicago",
    "sg:classifiers":[
        {
            "category":"Health Services",
            "subcategory":"Doctor",
            "type":"Services"
        }
    ],
    "sg:phone":"+1 773 281 8855",
    "sg:postcode":"60613",
    "sg:province":"IL",
    "wof:name":"Montrose Clinic",
    "wof:placetype":"venue"
},
  "geometry": {"coordinates":[-87.676598,41.961399],"type":"Point"}
}