{
  "type": "Feature",
  "properties": {
    "iso:country":"US",
    "sg:address":"8 Danada Sq W",
    "sg:city":"Wheaton",
    "sg:classifiers":[
        {
            "category":"Shopping",
            "type":"Retail Goods"
        }
    ],
    "sg:phone":"+1   ",
    "sg:postcode":"60187",
    "sg:province":"IL",
    "sg:tags":[
        "merchandise"
    ],
    "wof:name":"Comm One Systex LLC",
    "wof:placetype":"venue"
},
  "geometry": {"coordinates":[-88.102957,41.833167],"type":"Point"}
}