{
  "type": "Feature",
  "properties": {
    "iso:country":"US",
    "sg:address":"3895 Anjou Ln",
    "sg:city":"Schaumburg",
    "sg:classifiers":[
        {
            "category":"Professional",
            "subcategory":"Management & Consulting",
            "type":"Services"
        }
    ],
    "sg:phone":"+1 847 991 3868",
    "sg:postcode":"60192",
    "sg:province":"IL",
    "wof:name":"J&S Consulting",
    "wof:placetype":"venue"
},
  "geometry": {"coordinates":[-88.116804,42.091705],"type":"Point"}
}