{
  "type": "Feature",
  "properties": {
    "iso:country":"US",
    "sg:address":"648 Colony Ave",
    "sg:city":"Lindenhurst",
    "sg:classifiers":[
        {
            "category":"Building & Trades",
            "subcategory":"Cleaning & Sanitation",
            "type":"Services"
        }
    ],
    "sg:phone":"+1 847 902 0802",
    "sg:postcode":"60046",
    "sg:province":"IL",
    "sg:tags":[
        "janitor",
        "maintenance"
    ],
    "wof:name":"Clean Choice",
    "wof:placetype":"venue"
},
  "geometry": {"coordinates":[-88.019058,42.433057],"type":"Point"}
}