{
  "type": "Feature",
  "properties": {
    "iso:country":"US",
    "sg:address":"7824 Renee Rue",
    "sg:city":"Dixon",
    "sg:classifiers":[
        {
            "category":"Building & Trades",
            "subcategory":"Construction",
            "type":"Services"
        }
    ],
    "sg:phone":"+1 815 288 4756",
    "sg:postcode":"61021",
    "sg:province":"IL",
    "sg:tags":[
        "house",
        "general",
        "contractor"
    ],
    "wof:name":"Briarwood Construction Co",
    "wof:placetype":"venue"
},
  "geometry": {"coordinates":[-89.49267,41.906495],"type":"Point"}
}