{
  "type": "Feature",
  "properties": {
    "addr:full":"207 Pamela Dr Bolingbrook IL 60440",
    "addr:housenumber":"207",
    "addr:postcode":"60440",
    "addr:street":"Pamela Dr",
    "iso:country":"US",
    "sg:address":"207 Pamela Dr",
    "sg:city":"Bolingbrook",
    "sg:classifiers":[
        {
            "category":"Professional",
            "subcategory":"Management & Consulting",
            "type":"Services"
        }
    ],
    "sg:phone":"+1 630 783 1880",
    "sg:postcode":"60440",
    "sg:province":"IL",
    "sg:tags":[
        "personnel",
        "consultant"
    ],
    "sg:website":"www.assetprofiles.com",
    "wof:name":"Asset Profilies",
    "wof:placetype":"venue"
},
  "geometry": {"coordinates":[-88.06378100000001,41.717111],"type":"Point"}
}