{
  "type": "Feature",
  "properties": {
    "addr:full":"9372 W Ballard Rd Des Plaines IL 60016",
    "addr:housenumber":"9372",
    "addr:postcode":"60016",
    "addr:street":"W Ballard Rd Des",
    "iso:country":"US",
    "sg:address":"9372 W Ballard Rd",
    "sg:city":"Des Plaines",
    "sg:classifiers":[
        {
            "category":"Banks & Credit Unions",
            "subcategory":"Bank",
            "type":"Services"
        }
    ],
    "sg:phone":"+1 847 227 5475",
    "sg:postcode":"60016",
    "sg:province":"IL",
    "wof:name":"All American Bank",
    "wof:placetype":"venue"
},
  "geometry": {"coordinates":[-87.858931,42.043351],"type":"Point"}
}