{
  "type": "Feature",
  "properties": {
    "iso:country":"US",
    "sg:address":"4546 Levis Ln",
    "sg:city":"Godfrey",
    "sg:classifiers":[
        {
            "category":"Building & Trades",
            "subcategory":"Locksmith",
            "type":"Services"
        }
    ],
    "sg:phone":"+1 618 467 7072",
    "sg:postcode":"62035",
    "sg:province":"IL",
    "sg:tags":[
        "lock"
    ],
    "wof:name":"Foreclosure Options Of St Loui",
    "wof:placetype":"venue"
},
  "geometry": {"coordinates":[-90.22167899999999,38.923922],"type":"Point"}
}