{
  "type": "Feature",
  "properties": {
    "addr:full":"6236 N Western Ave Chicago IL 60659",
    "addr:housenumber":"6236",
    "addr:postcode":"60659",
    "addr:street":"N Western Ave",
    "iso:country":"US",
    "sg:address":"6236 N Western Ave",
    "sg:city":"Chicago",
    "sg:classifiers":[
        {
            "category":"Retail",
            "subcategory":"Portrait Studio",
            "type":"Services"
        },
        {
            "category":"Shopping",
            "subcategory":"Pharmacy",
            "type":"Retail Goods"
        }
    ],
    "sg:phone":"+1 773 764 0050",
    "sg:postcode":"60659",
    "sg:province":"IL",
    "sg:tags":[
        "photography",
        "drugstore",
        "store"
    ],
    "wof:name":"Walgreen Drug Stores",
    "wof:placetype":"venue"
},
  "geometry": {"coordinates":[-87.690039,41.994746],"type":"Point"}
}