{
  "type": "Feature",
  "properties": {
    "iso:country":"US",
    "sg:address":"1875 Golden Pond Ln",
    "sg:city":"Wheaton",
    "sg:classifiers":[
        {
            "category":"Retail",
            "subcategory":"Repair Shop",
            "type":"Services"
        }
    ],
    "sg:phone":"+1 630 510 1989",
    "sg:postcode":"60187",
    "sg:province":"IL",
    "sg:tags":[
        "compressor"
    ],
    "wof:name":"Technical Compressor Services",
    "wof:placetype":"venue"
},
  "geometry": {"coordinates":[-88.121701,41.837971],"type":"Point"}
}