{
  "type": "Feature",
  "properties": {
    "iso:country":"US",
    "sg:address":"1315 W South St",
    "sg:city":"Kewanee",
    "sg:classifiers":[
        {
            "category":"Professional",
            "subcategory":"Business Services",
            "type":"Services"
        }
    ],
    "sg:phone":"+1 309 853 8256",
    "sg:postcode":"61443",
    "sg:province":"IL",
    "sg:tags":[
        "real estate"
    ],
    "wof:name":"Hier & Associates",
    "wof:placetype":"venue"
},
  "geometry": {"coordinates":[-89.9511,41.222115],"type":"Point"}
}