{
  "type": "Feature",
  "properties": {
    "addr:full":"1138 Bond Ave East St Louis IL 62201",
    "addr:housenumber":"1138",
    "addr:postcode":"62201",
    "addr:street":"Bond Ave",
    "iso:country":"US",
    "sg:address":"1138 Bond Ave",
    "sg:city":"East St Louis",
    "sg:classifiers":[
        {
            "category":"Restaurant",
            "type":"Food & Drink"
        }
    ],
    "sg:phone":"+1 618 274 7950",
    "sg:postcode":"62201",
    "sg:province":"IL",
    "wof:name":"Sun Moon Chop Suey Restaurant",
    "wof:placetype":"venue"
},
  "geometry": {"coordinates":[-90.15913500000001,38.615332],"type":"Point"}
}