{
  "type": "Feature",
  "properties": {
    "addr:full":"3077 W Jefferson St Joliet IL 60435",
    "addr:housenumber":"3077",
    "addr:postcode":"60435",
    "addr:street":"W Jefferson St",
    "iso:country":"US",
    "sg:address":"3077 W Jefferson St",
    "sg:city":"Joliet",
    "sg:phone":"+1 815 744 5556",
    "sg:postcode":"60435",
    "sg:province":"IL",
    "sg:website":"http://www.endoperio.com",
    "wof:name":"Endodontic & Periodontic Associates Ltd",
    "wof:placetype":"venue"
},
  "geometry": {"coordinates":[-88.11037399999999,41.523045],"type":"Point"}
}