{
  "type": "Feature",
  "properties": {
    "iso:country":"US",
    "sg:address":"218 E Winter Ave",
    "sg:city":"Danville",
    "sg:classifiers":[
        {
            "category":"Professional",
            "subcategory":"Accounting & Tax Preparation",
            "type":"Services"
        }
    ],
    "sg:phone":"+1 217 446 2793",
    "sg:postcode":"61832",
    "sg:province":"IL",
    "sg:tags":[
        "accountant"
    ],
    "wof:name":"Divan Accounting Tax Svc",
    "wof:placetype":"venue"
},
  "geometry": {"coordinates":[-87.626453,40.159909],"type":"Point"}
}