{
  "type": "Feature",
  "properties": {
    "iso:country":"US",
    "sg:address":"2110 Fox Dr",
    "sg:city":"Champaign",
    "sg:classifiers":[
        {
            "category":"Insurance",
            "subcategory":"Health Insurance",
            "type":"Services"
        }
    ],
    "sg:phone":"+1 217 366 1226",
    "sg:postcode":"61820",
    "sg:province":"IL",
    "sg:tags":[
        "provider"
    ],
    "wof:name":"Personalcare Health Management",
    "wof:placetype":"venue"
},
  "geometry": {"coordinates":[-88.25028500000001,40.089637],"type":"Point"}
}