{
  "type": "Feature",
  "properties": {
    "iso:country":"US",
    "sg:address":"301 W 31st St",
    "sg:city":"Chicago",
    "sg:classifiers":[
        {
            "category":"Autos & Motor Vehicles",
            "subcategory":"Automobile Sales",
            "type":"Retail Goods"
        },
        {
            "category":"Retail",
            "subcategory":"Auto Rental",
            "type":"Services"
        },
        {
            "category":"Local Transit",
            "type":"Transportation"
        }
    ],
    "sg:phone":"+1 708 599 2112",
    "sg:postcode":"60616",
    "sg:province":"IL",
    "sg:tags":[
        "shuttle",
        "limousine",
        "limo"
    ],
    "wof:name":"Diva Limousine",
    "wof:placetype":"venue"
},
  "geometry": {"coordinates":[-87.63408800000001,41.838093],"type":"Point"}
}