{
  "type": "Feature",
  "properties": {
    "addr:full":"1391 Knox Highway 20 Maquon IL 61458",
    "addr:housenumber":"1391",
    "addr:postcode":"61458",
    "addr:street":"Knox Highway 20",
    "iso:country":"US",
    "sg:address":"1391 Knox Highway 20",
    "sg:city":"Maquon",
    "sg:classifiers":[
        {
            "category":"Real Estate",
            "subcategory":"Real Estate Operator",
            "type":"Services"
        }
    ],
    "sg:phone":"+1 309 875 3491",
    "sg:postcode":"61458",
    "sg:province":"IL",
    "sg:tags":[
        "property",
        "lessor"
    ],
    "wof:name":"Arlyn Mitchell",
    "wof:placetype":"venue"
},
  "geometry": {"coordinates":[-90.195517,40.800978],"type":"Point"}
}