{
  "type": "Feature",
  "properties": {
    "addr:full":"17094 N 20th Ave Witt IL 62094",
    "addr:housenumber":"17094",
    "addr:postcode":"62094",
    "addr:street":"N 20Th Ave",
    "iso:country":"US",
    "sg:address":"17094 N 20th Ave",
    "sg:city":"Witt",
    "sg:classifiers":[
        {
            "category":"Real Estate",
            "subcategory":"Real Estate Operator",
            "type":"Services"
        }
    ],
    "sg:phone":"+1 217 563 8538",
    "sg:postcode":"62094",
    "sg:province":"IL",
    "sg:tags":[
        "property",
        "lessor"
    ],
    "wof:name":"Hanje Brothers",
    "wof:placetype":"venue"
},
  "geometry": {"coordinates":[-89.381024,39.290327],"type":"Point"}
}