{
  "type": "Feature",
  "properties": {
    "addr:full":"230 Joliet St La Salle IL 61301",
    "addr:housenumber":"230",
    "addr:postcode":"61301",
    "addr:street":"Joliet St",
    "iso:country":"US",
    "sg:address":"230 Joliet St",
    "sg:city":"La Salle",
    "sg:classifiers":[
        {
            "category":"Building & Trades",
            "subcategory":"Construction",
            "type":"Services"
        }
    ],
    "sg:phone":"+1 815 223 4925",
    "sg:postcode":"61301",
    "sg:province":"IL",
    "sg:tags":[
        "house",
        "general",
        "contractor"
    ],
    "wof:name":"B & B Remodeling Co",
    "wof:placetype":"venue"
},
  "geometry": {"coordinates":[-89.09426999999999,41.330106],"type":"Point"}
}