{
  "type": "Feature",
  "properties": {
    "addr:full":"57 E Park Blvd Villa Park IL 60181",
    "addr:housenumber":"57",
    "addr:postcode":"60181",
    "addr:street":"E Park Blvd",
    "iso:country":"US",
    "sg:address":"57 E Park Blvd",
    "sg:city":"Villa Park",
    "sg:classifiers":[
        {
            "category":"Wholesale",
            "subcategory":"Auto Parts",
            "type":"Manufacturing & Wholesale Goods"
        }
    ],
    "sg:phone":"+1 630 832 9860",
    "sg:postcode":"60181",
    "sg:province":"IL",
    "sg:tags":[
        "used"
    ],
    "wof:name":"Sr Sales Inc",
    "wof:placetype":"venue"
},
  "geometry": {"coordinates":[-87.974232,41.884395],"type":"Point"}
}