{
  "type": "Feature",
  "properties": {
    "addr:full":"200 Tomahawk Ct Bolingbrook IL 60440",
    "addr:housenumber":"200",
    "addr:postcode":"60440",
    "addr:street":"Tomahawk Ct",
    "iso:country":"US",
    "sg:address":"200 Tomahawk Ct",
    "sg:city":"Bolingbrook",
    "sg:classifiers":[
        {
            "category":"Social Services",
            "type":"Services"
        }
    ],
    "sg:phone":"+1 630 759 4863",
    "sg:postcode":"60440",
    "sg:province":"IL",
    "wof:name":"Cameron David M/Family VA",
    "wof:placetype":"venue"
},
  "geometry": {"coordinates":[-88.09291399999999,41.701323],"type":"Point"}
}