{
  "type": "Feature",
  "properties": {
    "iso:country":"US",
    "sg:address":"3347 Quincy Mall",
    "sg:city":"Quincy",
    "sg:classifiers":[
        {
            "category":"Food & Beverages",
            "subcategory":"Groceries & Convenience Stores",
            "type":"Retail Goods"
        }
    ],
    "sg:phone":"+1 217 221 9321",
    "sg:postcode":"62301",
    "sg:province":"IL",
    "wof:name":"Thieves Market",
    "wof:placetype":"venue"
},
  "geometry": {"coordinates":[-91.36254,39.935792],"type":"Point"}
}