{
  "type": "Feature",
  "properties": {
    "iso:country":"US",
    "sg:address":"26799 Commerce",
    "sg:city":"Round Lake",
    "sg:classifiers":[
        {
            "category":"Professional",
            "subcategory":"Management & Consulting",
            "type":"Services"
        }
    ],
    "sg:phone":"+1 847 740 0749",
    "sg:postcode":"60073",
    "sg:province":"IL",
    "sg:tags":[
        "development",
        "equipment",
        "consultant",
        "for",
        "software"
    ],
    "wof:name":"Don Johnston Incorporated",
    "wof:placetype":"venue"
},
  "geometry": {"coordinates":[-88.162419,42.323906],"type":"Point"}
}