{
  "type": "Feature",
  "properties": {
    "iso:country":"US",
    "sg:address":"214 W Menominee St",
    "sg:city":"Belvidere",
    "sg:classifiers":[
        {
            "category":"Professional",
            "subcategory":"Business Services",
            "type":"Services"
        }
    ],
    "sg:phone":"+1 815 544 3887",
    "sg:postcode":"61008",
    "sg:province":"IL",
    "wof:name":"Rock River Softners",
    "wof:placetype":"venue"
},
  "geometry": {"coordinates":[-88.849476,42.263453],"type":"Point"}
}