{
  "type": "Feature",
  "properties": {
    "addr:full":"701 N Addison Rd Villa Park IL 60181",
    "addr:housenumber":"701",
    "addr:postcode":"60181",
    "addr:street":"N Addison Rd",
    "iso:country":"US",
    "sg:address":"701 N Addison Rd",
    "sg:city":"Villa Park",
    "sg:classifiers":[
        {
            "category":"Shopping",
            "type":"Retail Goods"
        }
    ],
    "sg:phone":"+1   ",
    "sg:postcode":"60181",
    "sg:province":"IL",
    "sg:tags":[
        "merchandise"
    ],
    "wof:name":"Jims Pet World",
    "wof:placetype":"venue"
},
  "geometry": {"coordinates":[-87.98837399999999,41.90447],"type":"Point"}
}