{
  "type": "Feature",
  "properties": {
    "addr:full":"2402 39th Ave Moline IL 61265",
    "addr:housenumber":"2402",
    "addr:postcode":"61265",
    "addr:street":"39Th Ave",
    "iso:country":"US",
    "sg:address":"2402 39th Ave",
    "sg:city":"Moline",
    "sg:classifiers":[
        {
            "category":"Wholesale",
            "subcategory":"Vending Machines",
            "type":"Manufacturing & Wholesale Goods"
        }
    ],
    "sg:phone":"+1   ",
    "sg:postcode":"61265",
    "sg:province":"IL",
    "sg:tags":[
        "operator"
    ],
    "wof:name":"Aramark",
    "wof:placetype":"venue"
},
  "geometry": {"coordinates":[-90.502296,41.473346],"type":"Point"}
}