{
  "type": "Feature",
  "properties": {
    "addr:full":"922 N Bowman Ave Danville IL 61832",
    "addr:housenumber":"922",
    "addr:postcode":"61832",
    "addr:street":"N Bowman Ave",
    "iso:country":"US",
    "sg:address":"922 N Bowman Ave",
    "sg:city":"Danville",
    "sg:classifiers":[
        {
            "category":"Retail",
            "subcategory":"Portrait Studio",
            "type":"Services"
        }
    ],
    "sg:phone":"+1 217 446 2670",
    "sg:postcode":"61832",
    "sg:province":"IL",
    "sg:tags":[
        "photographer",
        "photo"
    ],
    "wof:name":"Lambert's Photography",
    "wof:placetype":"venue"
},
  "geometry": {"coordinates":[-87.611845,40.1405],"type":"Point"}
}