{
  "type": "Feature",
  "properties": {
    "iso:country":"US",
    "sg:address":"6405 Summerall Dr",
    "sg:city":"Woodridge",
    "sg:classifiers":[
        {
            "category":"Communications",
            "subcategory":"Film & Video Production",
            "type":"Services"
        }
    ],
    "sg:phone":"+1 630 960 2729",
    "sg:postcode":"60517",
    "sg:province":"IL",
    "sg:tags":[
        "television",
        "producer"
    ],
    "wof:name":"Prescott Productions",
    "wof:placetype":"venue"
},
  "geometry": {"coordinates":[-88.06836,41.768685],"type":"Point"}
}