{
  "type": "Feature",
  "properties": {
    "iso:country":"US",
    "sg:address":"4620 W Irving Park Road",
    "sg:city":"Chicago",
    "sg:classifiers":[
        {
            "category":"Shopping",
            "subcategory":"Hobbies, Toys, & Games",
            "type":"Retail Goods"
        }
    ],
    "sg:phone":"+1 773 283 4852",
    "sg:postcode":"60641",
    "sg:province":"IL",
    "sg:tags":[
        "toy",
        "store"
    ],
    "wof:name":"K B Toy Works",
    "wof:placetype":"venue"
},
  "geometry": {"coordinates":[-87.744212,41.953476],"type":"Point"}
}