{
  "type": "Feature",
  "properties": {
    "addr:full":"3950 W Madison Street Chicago IL 60624",
    "addr:housenumber":"3950",
    "addr:postcode":"60624",
    "addr:street":"W Madison Street",
    "iso:country":"US",
    "sg:address":"3950 W Madison Street",
    "sg:city":"Chicago",
    "sg:classifiers":[
        {
            "category":"Sports & Exercise",
            "subcategory":"Bicycle Rental",
            "type":"Entertainment"
        }
    ],
    "sg:phone":"+1 773 265 0110",
    "sg:postcode":"60624",
    "sg:province":"IL",
    "sg:tags":[
        "wear"
    ],
    "wof:name":"B Mw Sportswear",
    "wof:placetype":"venue"
},
  "geometry": {"coordinates":[-87.724895,41.880768],"type":"Point"}
}