{
  "type": "Feature",
  "properties": {
    "addr:full":"604 S Lincoln Ave Aurora IL 60505",
    "addr:housenumber":"604",
    "addr:postcode":"60505",
    "addr:street":"S Lincoln Ave",
    "iso:country":"US",
    "sg:address":"604 S Lincoln Ave",
    "sg:city":"Aurora",
    "sg:classifiers":[
        {
            "category":"Place Of Worship",
            "subcategory":"Church",
            "type":"Public Place"
        },
        {
            "category":"Place Of Worship",
            "type":"Public Place"
        },
        {
            "category":"Organizations",
            "subcategory":"Religious Organization",
            "type":"Services"
        }
    ],
    "sg:phone":"+1 630 896 4404",
    "sg:postcode":"60505",
    "sg:province":"IL",
    "sg:tags":[
        "churches-pentecostal-independent",
        "churches-pentecostal"
    ],
    "wof:name":"Iglesia Dedios Pentecostal",
    "wof:placetype":"venue"
},
  "geometry": {"coordinates":[-88.320976,41.744629],"type":"Point"}
}