{
  "type": "Feature",
  "properties": {
    "addr:full":"7138 Windsor Ave Berwyn IL 60402",
    "addr:housenumber":"7138",
    "addr:postcode":"60402",
    "addr:street":"Windsor Ave",
    "iso:country":"US",
    "sg:address":"7138 Windsor Ave",
    "sg:city":"Berwyn",
    "sg:classifiers":[
        {
            "category":"Bars & Pubs",
            "type":"Food & Drink"
        },
        {
            "category":"Restaurant",
            "type":"Food & Drink"
        }
    ],
    "sg:phone":"+1 708 795 1100",
    "sg:postcode":"60402",
    "sg:province":"IL",
    "sg:tags":[
        "irish"
    ],
    "sg:website":"www.thejamesjoyceirishpub.com",
    "wof:name":"James Joyce Irish Pub",
    "wof:placetype":"venue"
},
  "geometry": {"coordinates":[-87.801804,41.8311],"type":"Point"}
}