{
  "type": "Feature",
  "properties": {
    "addr:full":"13333 Cicero Ave Crestwood IL 60445",
    "addr:housenumber":"13333",
    "addr:postcode":"60445",
    "addr:street":"Cicero Ave",
    "iso:country":"US",
    "sg:address":"13333 Cicero Ave",
    "sg:city":"Crestwood",
    "sg:classifiers":[
        {
            "category":"Shopping",
            "type":"Retail Goods"
        },
        {
            "category":"Shopping",
            "subcategory":"Computers & Home Electronics",
            "type":"Retail Goods"
        }
    ],
    "sg:phone":"+1 708 389 0234",
    "sg:postcode":"60445",
    "sg:province":"IL",
    "sg:tags":[
        "telephone",
        "equipment",
        "supply",
        "system",
        "phone"
    ],
    "sg:website":"www.bsicom.com",
    "wof:name":"Business Suppliers Inc",
    "wof:placetype":"venue"
},
  "geometry": {"coordinates":[-87.73802999999999,41.6478],"type":"Point"}
}