{
  "type": "Feature",
  "properties": {
    "addr:full":"3738 S Halsted St Chicago IL 60609",
    "addr:housenumber":"3738",
    "addr:postcode":"60609",
    "addr:street":"S Halsted St",
    "iso:country":"US",
    "sg:address":"3738 S Halsted St",
    "sg:city":"Chicago",
    "sg:classifiers":[
        {
            "category":"Food & Beverages",
            "subcategory":"Liquor & Beverages",
            "type":"Retail Goods"
        }
    ],
    "sg:phone":"+1 773 847 7060",
    "sg:postcode":"60609",
    "sg:province":"IL",
    "sg:tags":[
        "store"
    ],
    "wof:name":"Brennan Liquors",
    "wof:placetype":"venue"
},
  "geometry": {"coordinates":[-87.646005,41.826406],"type":"Point"}
}