{
  "type": "Feature",
  "properties": {
    "iso:country":"US",
    "sg:address":"111 N Michigan Ave",
    "sg:city":"Bradley",
    "sg:classifiers":[
        {
            "category":"Professional",
            "subcategory":"Management & Consulting",
            "type":"Services"
        }
    ],
    "sg:phone":"+1 815 933 5977",
    "sg:postcode":"60915",
    "sg:province":"IL",
    "sg:tags":[
        "consultant",
        "business"
    ],
    "wof:name":"Sorensen Wilder & Assoc",
    "wof:placetype":"venue"
},
  "geometry": {"coordinates":[-87.86476399999999,41.143562],"type":"Point"}
}