{
  "type": "Feature",
  "properties": {
    "addr:full":"423 W Henry St Staunton IL 62088",
    "addr:housenumber":"423",
    "addr:postcode":"62088",
    "addr:street":"W Henry St",
    "iso:country":"US",
    "sg:address":"423 W Henry St",
    "sg:city":"Staunton",
    "sg:classifiers":[
        {
            "category":"Bars & Pubs",
            "type":"Food & Drink"
        }
    ],
    "sg:phone":"+1   ",
    "sg:postcode":"62088",
    "sg:province":"IL",
    "sg:tags":[
        "bar"
    ],
    "wof:name":"Sam & Dans",
    "wof:placetype":"venue"
},
  "geometry": {"coordinates":[-89.790684,39.009521],"type":"Point"}
}