{
  "type": "Feature",
  "properties": {
    "iso:country":"US",
    "sg:address":"512 Laurel Dr",
    "sg:city":"Rockford",
    "sg:classifiers":[
        {
            "category":"Insurance",
            "subcategory":"Insurance Agent",
            "type":"Services"
        }
    ],
    "sg:phone":"+1 815 398 6517",
    "sg:postcode":"61107",
    "sg:province":"IL",
    "wof:name":"Integrity Insurance Agency",
    "wof:placetype":"venue"
},
  "geometry": {"coordinates":[-89.038093,42.271733],"type":"Point"}
}