{
  "type": "Feature",
  "properties": {
    "addr:full":"141 W Jackson Blvd Chicago IL 60661",
    "addr:housenumber":"141",
    "addr:postcode":"60661",
    "addr:street":"W Jackson Blvd",
    "iso:country":"US",
    "sg:address":"141 W Jackson Blvd",
    "sg:city":"Chicago",
    "sg:classifiers":[
        {
            "category":"Banks & Credit Unions",
            "subcategory":"Investment Brokerage",
            "type":"Services"
        }
    ],
    "sg:phone":"+1 312 341 0834",
    "sg:postcode":"60661",
    "sg:province":"IL",
    "sg:tags":[
        "security",
        "commodity",
        "exchange"
    ],
    "sg:website":"www.eaglemarketmakers.com",
    "wof:name":"Eagle Market Makers Inc",
    "wof:placetype":"venue"
},
  "geometry": {"coordinates":[-87.631822,41.878137],"type":"Point"}
}