{
  "type": "Feature",
  "properties": {
    "addr:full":"17324 Torrence Ave Lansing IL 60438",
    "addr:housenumber":"17324",
    "addr:postcode":"60438",
    "addr:street":"Torrence Ave",
    "iso:country":"US",
    "sg:address":"17324 Torrence Ave",
    "sg:city":"Lansing",
    "sg:classifiers":[
        {
            "category":"Restaurant",
            "type":"Food & Drink"
        }
    ],
    "sg:phone":"+1 708 895 3311",
    "sg:postcode":"60438",
    "sg:province":"IL",
    "sg:tags":[
        "eating",
        "pizza"
    ],
    "wof:name":"Mama Rigetta's Pizzeria",
    "wof:placetype":"venue"
},
  "geometry": {"coordinates":[-87.55909699999999,41.580799],"type":"Point"}
}