{
  "type": "Feature",
  "properties": {
    "iso:country":"US",
    "sg:address":"643 N Oak Park Ave",
    "sg:city":"Oak Park",
    "sg:classifiers":[
        {
            "category":"Retail",
            "subcategory":"Repair Shop",
            "type":"Services"
        }
    ],
    "sg:phone":"+1 708 445 8506",
    "sg:postcode":"60302",
    "sg:province":"IL",
    "sg:tags":[
        "electrical"
    ],
    "wof:name":"Bills Appliance & Air",
    "wof:placetype":"venue"
},
  "geometry": {"coordinates":[-87.79482299999999,41.897276],"type":"Point"}
}