{
  "type": "Feature",
  "properties": {
    "iso:country":"US",
    "sg:address":"1946 W Armitage Ave",
    "sg:city":"Chicago",
    "sg:classifiers":[
        {
            "category":"Retail",
            "subcategory":"Auto Rental",
            "type":"Services"
        },
        {
            "category":"Local Transit",
            "type":"Transportation"
        }
    ],
    "sg:phone":"+1 312 782 2023",
    "sg:postcode":"60622",
    "sg:province":"IL",
    "sg:tags":[
        "shuttle",
        "limousine"
    ],
    "wof:name":"Aurora Limousine Svc",
    "wof:placetype":"venue"
},
  "geometry": {"coordinates":[-87.676979,41.917782],"type":"Point"}
}