{
  "type": "Feature",
  "properties": {
    "addr:full":"Lincoln Ave Chicago IL 60614",
    "addr:postcode":"60614",
    "addr:street":"Lincoln Ave",
    "iso:country":"US",
    "sg:address":"Lincoln Ave",
    "sg:city":"Chicago",
    "sg:classifiers":[
        {
            "category":"Restaurant",
            "type":"Food & Drink"
        }
    ],
    "sg:postcode":"60614",
    "sg:province":"IL",
    "sg:tags":[
        "flavor",
        "local"
    ],
    "sg:website":"www.wrightwoodneighbors.org/Tast...",
    "wof:name":"Taste of Lincoln Ave",
    "wof:placetype":"venue"
},
  "geometry": {"coordinates":[-87.646784,41.924047],"type":"Point"}
}