{
  "type": "Feature",
  "properties": {
    "iso:country":"US",
    "sg:address":"4980 S Main St",
    "sg:city":"Rockford",
    "sg:classifiers":[
        {
            "category":"Food & Beverages",
            "subcategory":"Groceries & Convenience Stores",
            "type":"Retail Goods"
        }
    ],
    "sg:phone":"+1   ",
    "sg:postcode":"61102",
    "sg:province":"IL",
    "wof:name":"Citgo",
    "wof:placetype":"venue"
},
  "geometry": {"coordinates":[-89.10858399999999,42.210026],"type":"Point"}
}