{
  "type": "Feature",
  "properties": {
    "iso:country":"US",
    "sg:address":"1700 Delaware Rd",
    "sg:city":"Waukegan",
    "sg:classifiers":[
        {
            "category":"Education",
            "subcategory":"School",
            "type":"Public Place"
        }
    ],
    "sg:phone":"+1 847 360 5467",
    "sg:postcode":"60087",
    "sg:province":"IL",
    "wof:name":"Clearview Elementary School",
    "wof:placetype":"venue"
},
  "geometry": {"coordinates":[-87.86075,42.386533],"type":"Point"}
}