{
  "type": "Feature",
  "properties": {
    "addr:full":"1487 Commerce Dr Algonquin IL 60102",
    "addr:housenumber":"1487",
    "addr:postcode":"60102",
    "addr:street":"Commerce Dr",
    "iso:country":"US",
    "sg:address":"1487 Commerce Dr",
    "sg:city":"Algonquin",
    "sg:classifiers":[
        {
            "category":"Health Services",
            "subcategory":"Dentist",
            "type":"Services"
        }
    ],
    "sg:phone":"+1 847 658 3355",
    "sg:postcode":"60102",
    "sg:province":"IL",
    "sg:tags":[
        "implant",
        "dentistry",
        "dentists-periodontists",
        "dentists-implantology"
    ],
    "wof:name":"Fiandaca Periodontics PC",
    "wof:placetype":"venue"
},
  "geometry": {"coordinates":[-88.334315,42.154286],"type":"Point"}
}