{
  "type": "Feature",
  "properties": {
    "addr:full":"2915 Maple St Franklin Park IL 60131",
    "addr:housenumber":"2915",
    "addr:postcode":"60131",
    "addr:street":"Maple St",
    "iso:country":"US",
    "sg:address":"2915 Maple St",
    "sg:city":"Franklin Park",
    "sg:classifiers":[
        {
            "category":"Personal",
            "type":"Services"
        },
        {
            "category":"Home & Garden",
            "subcategory":"Carpets & Floor Coverings",
            "type":"Retail Goods"
        }
    ],
    "sg:phone":"+1 847 455 2100",
    "sg:postcode":"60131",
    "sg:province":"IL",
    "sg:tags":[
        "party",
        "planning",
        "event",
        "mattress"
    ],
    "sg:website":"www.wssra.net",
    "wof:name":"West Suburban Special Recreation Assoc",
    "wof:placetype":"venue"
},
  "geometry": {"coordinates":[-87.852997,41.931702],"type":"Point"}
}