{
  "type": "Feature",
  "properties": {
    "iso:country":"US",
    "sg:address":"1012 4th St",
    "sg:city":"Orion",
    "sg:classifiers":[
        {
            "category":"Government",
            "subcategory":"Post Office",
            "type":"Public Place"
        }
    ],
    "sg:phone":"+1 309 526 8065",
    "sg:postcode":"61273",
    "sg:province":"IL",
    "wof:name":"US Post Office",
    "wof:placetype":"venue"
},
  "geometry": {"coordinates":[-90.381527,41.354676],"type":"Point"}
}