{
  "type": "Feature",
  "properties": {
    "iso:country":"US",
    "sg:address":"25 N Broadway",
    "sg:city":"Aurora",
    "sg:classifiers":[
        {
            "category":"Banks & Credit Unions",
            "subcategory":"Bank",
            "type":"Services"
        }
    ],
    "sg:phone":"+1 630 897 5570",
    "sg:postcode":"60505",
    "sg:province":"IL",
    "sg:tags":[
        "loan",
        "real estate"
    ],
    "wof:name":"American Fidelity Mortgage",
    "wof:placetype":"venue"
},
  "geometry": {"coordinates":[-88.31235599999999,41.757533],"type":"Point"}
}