{
  "type": "Feature",
  "properties": {
    "iso:country":"US",
    "sg:address":"9331 Parklane Ave",
    "sg:city":"Franklin Park",
    "sg:classifiers":[
        {
            "category":"Retail",
            "subcategory":"Repair Shop",
            "type":"Services"
        }
    ],
    "sg:phone":"+1 847 451 9736",
    "sg:postcode":"60131",
    "sg:province":"IL",
    "sg:tags":[
        "welding"
    ],
    "wof:name":"A1 Quality Welding",
    "wof:placetype":"venue"
},
  "geometry": {"coordinates":[-87.859095,41.932651],"type":"Point"}
}