{
  "type": "Feature",
  "properties": {
    "addr:full":"18025 Wentworth Ave Lansing IL 60438",
    "addr:housenumber":"18025",
    "addr:postcode":"60438",
    "addr:street":"Wentworth Ave",
    "iso:country":"US",
    "sg:address":"18025 Wentworth Ave",
    "sg:city":"Lansing",
    "sg:classifiers":[
        {
            "category":"Health Services",
            "subcategory":"Doctor",
            "type":"Services"
        }
    ],
    "sg:phone":"+1 708 862 5000",
    "sg:postcode":"60438",
    "sg:province":"IL",
    "sg:tags":[
        "dentist"
    ],
    "wof:name":"R V Carlson DDS",
    "wof:placetype":"venue"
},
  "geometry": {"coordinates":[-87.52958,41.567487],"type":"Point"}
}