{
  "type": "Feature",
  "properties": {
    "iso:country":"US",
    "sg:address":"3246 S Alpine Rd",
    "sg:city":"Rockford",
    "sg:classifiers":[
        {
            "category":"Restaurant",
            "type":"Food & Drink"
        }
    ],
    "sg:menulink":"http://www.allmenus.com/il/cherry-valley/127351-subway/menu/",
    "sg:phone":"+1 815 874 7827",
    "sg:postcode":"61109",
    "sg:province":"IL",
    "sg:tags":[
        "american",
        "sandwich"
    ],
    "wof:name":"Subway",
    "wof:placetype":"venue"
},
  "geometry": {"coordinates":[-89.028772,42.228928],"type":"Point"}
}