{
  "type": "Feature",
  "properties": {
    "iso:country":"US",
    "sg:address":"6 Bell Oak Ln",
    "sg:city":"Lemont",
    "sg:classifiers":[
        {
            "category":"Wholesale",
            "subcategory":"Fruits & Vegetables",
            "type":"Manufacturing & Wholesale Goods"
        }
    ],
    "sg:phone":"+1 312 733 6048",
    "sg:postcode":"60439",
    "sg:province":"IL",
    "wof:name":"Q S Corp",
    "wof:placetype":"venue"
},
  "geometry": {"coordinates":[-87.930172,41.671613],"type":"Point"}
}