{
  "type": "Feature",
  "properties": {
    "iso:country":"US",
    "sg:address":"112 W Main St",
    "sg:city":"Colfax",
    "sg:classifiers":[
        {
            "category":"Insurance",
            "subcategory":"Hazard Insurance",
            "type":"Services"
        },
        {
            "category":"Banks & Credit Unions",
            "subcategory":"Investment Brokerage",
            "type":"Services"
        },
        {
            "category":"Insurance",
            "subcategory":"Life Insurance",
            "type":"Services"
        },
        {
            "category":"Banks & Credit Unions",
            "subcategory":"Financial Services",
            "type":"Services"
        }
    ],
    "sg:phone":"+1 309 723 2741",
    "sg:postcode":"61728",
    "sg:province":"IL",
    "sg:website":"http://bloomington.citysearch.com/profile/external/35366118/colfax_il/country_financial_curtis_johnson.html?publisher=yellowpages&reference_id=1&placement=ypwebsitemip",
    "wof:name":"COUNTRY Financial - Curtis Johnson",
    "wof:placetype":"venue"
},
  "geometry": {"coordinates":[-88.616378,40.566994],"type":"Point"}
}