{
  "type": "Feature",
  "properties": {
    "addr:full":"113 S Grove Ave Elgin IL 60120",
    "addr:housenumber":"113",
    "addr:postcode":"60120",
    "addr:street":"S Grove Ave",
    "iso:country":"US",
    "sg:address":"113 S Grove Ave",
    "sg:city":"Elgin",
    "sg:classifiers":[
        {
            "category":"Government",
            "subcategory":"Office",
            "type":"Public Place"
        }
    ],
    "sg:phone":"+1 847 695 0848",
    "sg:postcode":"60120",
    "sg:province":"IL",
    "wof:name":"Prenatal Clinic",
    "wof:placetype":"venue"
},
  "geometry": {"coordinates":[-88.282753,42.035563],"type":"Point"}
}