{
  "type": "Feature",
  "properties": {
    "iso:country":"US",
    "sg:address":"5060 Ace Ln Ste 100",
    "sg:city":"Naperville",
    "sg:classifiers":[
        {
            "category":"Health Services",
            "subcategory":"Dentist",
            "type":"Services"
        }
    ],
    "sg:phone":"+1 630 904 4444",
    "sg:postcode":"60564",
    "sg:province":"IL",
    "sg:tags":[
        "dentists-orthodontists"
    ],
    "sg:website":"http://www.wheatlanddental.com",
    "wof:name":"Gruendeman Gary DDS PC",
    "wof:placetype":"venue"
},
  "geometry": {"coordinates":[-88.205563,41.678656],"type":"Point"}
}