{
  "type": "Feature",
  "properties": {
    "iso:country":"US",
    "sg:address":"20541 Emerald Rd",
    "sg:city":"Carlyle",
    "sg:classifiers":[
        {
            "category":"Wholesale",
            "subcategory":"Machinery & Supplies",
            "type":"Manufacturing & Wholesale Goods"
        },
        {
            "category":"Wholesale",
            "subcategory":"Hardware",
            "type":"Manufacturing & Wholesale Goods"
        }
    ],
    "sg:phone":"+1 618 749 5666",
    "sg:postcode":"62231",
    "sg:province":"IL",
    "sg:tags":[
        "refrigerating"
    ],
    "wof:name":"Dale Allen's Refrigeration Svc",
    "wof:placetype":"venue"
},
  "geometry": {"coordinates":[-89.31053900000001,38.712884],"type":"Point"}
}