{
  "type": "Feature",
  "properties": {
    "addr:full":"6216 W 79th St Burbank IL 60459",
    "addr:housenumber":"6216",
    "addr:postcode":"60459",
    "addr:street":"W 79Th St",
    "iso:country":"US",
    "sg:address":"6216 W 79th St",
    "sg:city":"Burbank",
    "sg:classifiers":[
        {
            "category":"Health Services",
            "subcategory":"Doctor",
            "type":"Services"
        }
    ],
    "sg:phone":"+1 708 430 0007",
    "sg:postcode":"60459",
    "sg:province":"IL",
    "sg:tags":[
        "surgeon",
        "oral"
    ],
    "wof:name":"Krafcisin Peter S DDS",
    "wof:placetype":"venue"
},
  "geometry": {"coordinates":[-87.776398,41.7486],"type":"Point"}
}