{
  "type": "Feature",
  "properties": {
    "addr:full":"404 N Green St Mc Henry IL 60050",
    "addr:housenumber":"404",
    "addr:postcode":"60050",
    "addr:street":"N Green St Mc Henry",
    "iso:country":"US",
    "sg:address":"404 N Green St",
    "sg:city":"Mc Henry",
    "sg:classifiers":[
        {
            "category":"Social Services",
            "subcategory":"Child Care",
            "type":"Services"
        }
    ],
    "sg:phone":"+1 815 385 3243",
    "sg:postcode":"60050",
    "sg:province":"IL",
    "sg:tags":[
        "day"
    ],
    "wof:name":"Mc Henry Head Start Day Care",
    "wof:placetype":"venue"
},
  "geometry": {"coordinates":[-88.267135,42.332847],"type":"Point"}
}