{
  "type": "Feature",
  "properties": {
    "addr:full":"936 E 100 North Rd Hammond IL 61929",
    "addr:housenumber":"936",
    "addr:postcode":"61929",
    "addr:street":"E 100 North Rd",
    "iso:country":"US",
    "sg:address":"936 E 100 North Rd",
    "sg:city":"Hammond",
    "sg:classifiers":[
        {
            "category":"Building & Trades",
            "subcategory":"Construction",
            "type":"Services"
        }
    ],
    "sg:phone":"+1 217 262 3363",
    "sg:postcode":"61929",
    "sg:province":"IL",
    "wof:name":"Universal Mechanical",
    "wof:placetype":"venue"
},
  "geometry": {"coordinates":[-88.56931299999999,39.80671],"type":"Point"}
}