{
  "type": "Feature",
  "properties": {
    "addr:full":"230 S Columbus Dr Chicago IL 60603",
    "addr:housenumber":"230",
    "addr:postcode":"60603",
    "addr:street":"S Columbus Dr",
    "iso:country":"US",
    "sg:address":"230 S Columbus Dr",
    "sg:city":"Chicago",
    "sg:classifiers":[
        {
            "category":"Education",
            "subcategory":"Special Training",
            "type":"Public Place"
        },
        {
            "category":"Education",
            "subcategory":"Vocational School",
            "type":"Public Place"
        }
    ],
    "sg:phone":"+1 888 350 6109",
    "sg:postcode":"60603",
    "sg:province":"IL",
    "sg:tags":[
        "instruction",
        "art",
        "business"
    ],
    "wof:name":"Art Institute of Chicago--Chicago Stock Exchange Room",
    "wof:placetype":"venue"
},
  "geometry": {"coordinates":[-87.620758,41.88009],"type":"Point"}
}