{
  "type": "Feature",
  "properties": {
    "addr:full":"5042 N Winthrop Ave Chicago IL 60640",
    "addr:housenumber":"5042",
    "addr:postcode":"60640",
    "addr:street":"N Winthrop Ave",
    "iso:country":"US",
    "sg:address":"5042 N Winthrop Ave",
    "sg:city":"Chicago",
    "sg:classifiers":[
        {
            "category":"Banks & Credit Unions",
            "subcategory":"Investment Brokerage",
            "type":"Services"
        },
        {
            "category":"Real Estate",
            "subcategory":"Developer",
            "type":"Services"
        }
    ],
    "sg:phone":"+1 773 852 7875",
    "sg:postcode":"60640",
    "sg:province":"IL",
    "sg:tags":[
        "investing"
    ],
    "wof:name":"Dejanere",
    "wof:placetype":"venue"
},
  "geometry": {"coordinates":[-87.65764,41.9741],"type":"Point"}
}