{
  "type": "Feature",
  "properties": {
    "addr:full":"6136 W 26th St Cicero IL 60804",
    "addr:housenumber":"6136",
    "addr:postcode":"60804",
    "addr:street":"W 26Th St",
    "iso:country":"US",
    "sg:address":"6136 W 26th St",
    "sg:city":"Cicero",
    "sg:classifiers":[
        {
            "category":"Building & Trades",
            "subcategory":"Cleaning & Sanitation",
            "type":"Services"
        }
    ],
    "sg:phone":"+1 708 656 1389",
    "sg:postcode":"60804",
    "sg:province":"IL",
    "sg:tags":[
        "ventilating",
        "system"
    ],
    "wof:name":"D & S Airduct Cleaning Svc",
    "wof:placetype":"venue"
},
  "geometry": {"coordinates":[-87.777638,41.843408],"type":"Point"}
}