{
  "type": "Feature",
  "properties": {
    "iso:country":"US",
    "sg:address":"15 Woodmar Ct",
    "sg:city":"Streamwood",
    "sg:classifiers":[
        {
            "category":"Professional",
            "subcategory":"Art Services",
            "type":"Services"
        }
    ],
    "sg:phone":"+1 630 372 0883",
    "sg:postcode":"60107",
    "sg:province":"IL",
    "sg:tags":[
        "designer",
        "display",
        "producer"
    ],
    "wof:name":"Baskets By Ducky Designs",
    "wof:placetype":"venue"
},
  "geometry": {"coordinates":[-88.16158900000001,42.03796],"type":"Point"}
}