{
  "type": "Feature",
  "properties": {
    "addr:full":"301 W Galena Blvd Aurora IL 60506",
    "addr:housenumber":"301",
    "addr:postcode":"60506",
    "addr:street":"W Galena Blvd",
    "iso:country":"US",
    "sg:address":"301 W Galena Blvd",
    "sg:city":"Aurora",
    "sg:classifiers":[
        {
            "category":"Organizations",
            "subcategory":"Non-profit Organization",
            "type":"Services"
        }
    ],
    "sg:phone":"+1 630 723 5000",
    "sg:postcode":"60506",
    "sg:province":"IL",
    "sg:tags":[
        "information",
        "alcoholism",
        "treatment"
    ],
    "wof:name":"Professional Consultations",
    "wof:placetype":"venue"
},
  "geometry": {"coordinates":[-88.321461,41.760689],"type":"Point"}
}