{
  "type": "Feature",
  "properties": {
    "addr:full":"410 S Michigan Ave Chicago IL 60605",
    "addr:housenumber":"410",
    "addr:postcode":"60605",
    "addr:street":"S Michigan Ave",
    "iso:country":"US",
    "sg:address":"410 S Michigan Ave",
    "sg:city":"Chicago",
    "sg:classifiers":[
        {
            "category":"Education",
            "subcategory":"Special Training",
            "type":"Public Place"
        }
    ],
    "sg:phone":"+1 847 914 9610",
    "sg:postcode":"60605",
    "sg:province":"IL",
    "sg:tags":[
        "adult"
    ],
    "sg:website":"www.ascendtraining.com",
    "wof:name":"Ascend Training & Consulting",
    "wof:placetype":"venue"
},
  "geometry": {"coordinates":[-87.624348,41.876846],"type":"Point"}
}