{
  "type": "Feature",
  "properties": {
    "addr:full":"3528 N Ashland Ave Chicago IL 60657",
    "addr:housenumber":"3528",
    "addr:postcode":"60657",
    "addr:street":"N Ashland Ave",
    "iso:country":"US",
    "sg:address":"3528 N Ashland Ave",
    "sg:city":"Chicago",
    "sg:classifiers":[
        {
            "category":"Professional",
            "subcategory":"Lawyer & Legal Services",
            "type":"Services"
        }
    ],
    "sg:phone":"+1 773 348 6400",
    "sg:postcode":"60657",
    "sg:province":"IL",
    "wof:name":"Abs Legal Service",
    "wof:placetype":"venue"
},
  "geometry": {"coordinates":[-87.66920500000001,41.946025],"type":"Point"}
}