{
  "type": "Feature",
  "properties": {
    "addr:full":"22909 W Mound Rd Joliet IL 60436",
    "addr:housenumber":"22909",
    "addr:postcode":"60436",
    "addr:street":"W Mound Rd",
    "iso:country":"US",
    "sg:address":"22909 W Mound Rd",
    "sg:city":"Joliet",
    "sg:classifiers":[
        {
            "category":"Utilities",
            "subcategory":"Refuse",
            "type":"Services"
        }
    ],
    "sg:phone":"+1 815 725 8880",
    "sg:postcode":"60436",
    "sg:province":"IL",
    "sg:tags":[
        "garbage",
        "collection"
    ],
    "wof:name":"Waste Box Inc",
    "wof:placetype":"venue"
},
  "geometry": {"coordinates":[-88.168603,41.488461],"type":"Point"}
}