{
  "type": "Feature",
  "properties": {
    "iso:country":"US",
    "sg:address":"1705 16th Ave",
    "sg:city":"Fulton",
    "sg:classifiers":[
        {
            "category":"Health Services",
            "subcategory":"Doctor",
            "type":"Services"
        }
    ],
    "sg:phone":"+1 815 589 2121",
    "sg:postcode":"61252",
    "sg:province":"IL",
    "sg:tags":[
        "medical"
    ],
    "wof:name":"Fulton Family Health Clinic",
    "wof:placetype":"venue"
},
  "geometry": {"coordinates":[-90.14861999999999,41.86194],"type":"Point"}
}