{
  "type": "Feature",
  "properties": {
    "iso:country":"US",
    "sg:address":"3802 E Frontage Rd",
    "sg:city":"Rolling Meadows",
    "sg:classifiers":[
        {
            "category":"Retail",
            "subcategory":"Auto Repair",
            "type":"Services"
        }
    ],
    "sg:phone":"+1 847 870 1371",
    "sg:postcode":"60008",
    "sg:province":"IL",
    "sg:tags":[
        "automotive"
    ],
    "wof:name":"James T Bielarz",
    "wof:placetype":"venue"
},
  "geometry": {"coordinates":[-88.027056,42.069521],"type":"Point"}
}