{
  "type": "Feature",
  "properties": {
    "addr:full":"634 N Greenwood Dr Palatine IL 60074",
    "addr:housenumber":"634",
    "addr:postcode":"60074",
    "addr:street":"N Greenwood Dr",
    "iso:country":"US",
    "sg:address":"634 N Greenwood Dr",
    "sg:city":"Palatine",
    "sg:classifiers":[
        {
            "category":"Professional",
            "subcategory":"Management & Consulting",
            "type":"Services"
        }
    ],
    "sg:phone":"+1 847 359 2731",
    "sg:postcode":"60074",
    "sg:province":"IL",
    "sg:tags":[
        "consultant",
        "business"
    ],
    "wof:name":"Anything Rail LTD",
    "wof:placetype":"venue"
},
  "geometry": {"coordinates":[-88.025294,42.123797],"type":"Point"}
}