{
  "type": "Feature",
  "properties": {
    "addr:full":"2936 W Belden Ave Chicago IL 60647",
    "addr:housenumber":"2936",
    "addr:postcode":"60647",
    "addr:street":"W Belden Ave",
    "iso:country":"US",
    "sg:address":"2936 W Belden Ave",
    "sg:city":"Chicago",
    "sg:classifiers":[
        {
            "category":"Retail",
            "subcategory":"Auto Rental",
            "type":"Services"
        },
        {
            "category":"Local Transit",
            "type":"Transportation"
        }
    ],
    "sg:phone":"+1 773 227 6903",
    "sg:postcode":"60647",
    "sg:province":"IL",
    "sg:tags":[
        "shuttle",
        "limousine"
    ],
    "wof:name":"Insight Limousine & Sedan",
    "wof:placetype":"venue"
},
  "geometry": {"coordinates":[-87.70091499999999,41.923274],"type":"Point"}
}