{
  "type": "Feature",
  "properties": {
    "iso:country":"US",
    "sg:address":"1500 Ogden Ave",
    "sg:city":"Downers Grove",
    "sg:classifiers":[
        {
            "category":"Retail",
            "subcategory":"Auto Repair",
            "type":"Services"
        }
    ],
    "sg:phone":"+1 630 964 6457",
    "sg:postcode":"60515",
    "sg:province":"IL",
    "sg:tags":[
        "automotive"
    ],
    "wof:name":"Fullserv Oil Change",
    "wof:placetype":"venue"
},
  "geometry": {"coordinates":[-88.021054,41.808251],"type":"Point"}
}