{
  "type": "Feature",
  "properties": {
    "addr:full":"309 E Jackson St Carbondale IL 62901",
    "addr:housenumber":"309",
    "addr:postcode":"62901",
    "addr:street":"E Jackson St",
    "iso:country":"US",
    "sg:address":"309 E Jackson St",
    "sg:city":"Carbondale",
    "sg:classifiers":[
        {
            "category":"Government",
            "subcategory":"Office",
            "type":"Public Place"
        }
    ],
    "sg:phone":"+1 618 457 2107",
    "sg:postcode":"62901",
    "sg:province":"IL",
    "sg:tags":[
        "state",
        "program"
    ],
    "wof:name":"Rehabilitation Services Dept",
    "wof:placetype":"venue"
},
  "geometry": {"coordinates":[-89.211596,37.728564],"type":"Point"}
}