{
  "type": "Feature",
  "properties": {
    "iso:country":"US",
    "sg:address":"4501 W 127th St",
    "sg:city":"Alsip",
    "sg:classifiers":[
        {
            "category":"Shopping",
            "subcategory":"Musical Instruments",
            "type":"Retail Goods"
        }
    ],
    "sg:phone":"+1 708 824 1642",
    "sg:postcode":"60803",
    "sg:province":"IL",
    "sg:tags":[
        "music",
        "dealer"
    ],
    "wof:name":"Asone Sound Music Group",
    "wof:placetype":"venue"
},
  "geometry": {"coordinates":[-87.73232299999999,41.661781],"type":"Point"}
}