{
  "type": "Feature",
  "properties": {
    "iso:country":"US",
    "sg:address":"3841 Saratoga Ave",
    "sg:city":"Downers Grove",
    "sg:classifiers":[
        {
            "category":"Professional",
            "subcategory":"Management & Consulting",
            "type":"Services"
        }
    ],
    "sg:phone":"+1 630 512 0191",
    "sg:postcode":"60515",
    "sg:province":"IL",
    "wof:name":"Association Ltd",
    "wof:placetype":"venue"
},
  "geometry": {"coordinates":[-88.015006,41.818572],"type":"Point"}
}