{
  "type": "Feature",
  "properties": {
    "iso:country":"US",
    "sg:address":"115 N Schrader St",
    "sg:city":"Havana",
    "sg:classifiers":[
        {
            "category":"Social Services",
            "subcategory":"Child Care",
            "type":"Services"
        }
    ],
    "sg:phone":"+1 309 543 3304",
    "sg:postcode":"62644",
    "sg:province":"IL",
    "sg:tags":[
        "day"
    ],
    "wof:name":"IGA",
    "wof:placetype":"venue"
},
  "geometry": {"coordinates":[-90.065059,40.301091],"type":"Point"}
}