{
  "type": "Feature",
  "properties": {
    "iso:country":"US",
    "sg:address":"15200 W Wadsworth Rd",
    "sg:city":"Wadsworth",
    "sg:classifiers":[
        {
            "category":"Real Estate",
            "subcategory":"Real Estate Services",
            "type":"Services"
        },
        {
            "category":"Banks & Credit Unions",
            "subcategory":"Investment Brokerage",
            "type":"Services"
        },
        {
            "category":"Banks & Credit Unions",
            "subcategory":"Financial Services",
            "type":"Services"
        }
    ],
    "sg:phone":"+1 847 244 3611",
    "sg:postcode":"60083",
    "sg:province":"IL",
    "sg:tags":[
        "management"
    ],
    "sg:website":"http://www.wadsworthrealtyco.com",
    "wof:name":"Kylar Investments",
    "wof:placetype":"venue"
},
  "geometry": {"coordinates":[-87.927361,42.428841],"type":"Point"}
}