{
  "type": "Feature",
  "properties": {
    "iso:country":"US",
    "sg:address":"6912 W Grand Ave Fl 1",
    "sg:city":"Chicago",
    "sg:classifiers":[
        {
            "category":"Building & Trades",
            "subcategory":"Construction",
            "type":"Services"
        }
    ],
    "sg:phone":"+1 773 237 2269",
    "sg:postcode":"60707",
    "sg:province":"IL",
    "sg:tags":[
        "contractor"
    ],
    "wof:name":"Carlson Bros Builders Inc",
    "wof:placetype":"venue"
},
  "geometry": {"coordinates":[-87.798103,41.923599],"type":"Point"}
}