{
  "type": "Feature",
  "properties": {
    "iso:country":"US",
    "sg:address":"2107 Irving Park Rd",
    "sg:city":"Bartlett",
    "sg:classifiers":[
        {
            "category":"Retail",
            "subcategory":"Auto Repair",
            "type":"Services"
        }
    ],
    "sg:phone":"+1 630 289 8030",
    "sg:postcode":"60133",
    "sg:province":"IL",
    "sg:tags":[
        "transmission"
    ],
    "wof:name":"Ace Transmission Inc",
    "wof:placetype":"venue"
},
  "geometry": {"coordinates":[-88.156092,42.008534],"type":"Point"}
}