{
  "type": "Feature",
  "properties": {
    "addr:full":"525 Wentworth Ave Calumet City IL 60409",
    "addr:housenumber":"525",
    "addr:postcode":"60409",
    "addr:street":"Wentworth Ave",
    "iso:country":"US",
    "sg:address":"525 Wentworth Ave",
    "sg:city":"Calumet City",
    "sg:classifiers":[
        {
            "category":"Social Services",
            "subcategory":"Child Care",
            "type":"Services"
        },
        {
            "category":"Education",
            "subcategory":"Preschool",
            "type":"Public Place"
        },
        {
            "category":"Education",
            "subcategory":"School",
            "type":"Public Place"
        }
    ],
    "sg:phone":"+1 708 868 5343",
    "sg:postcode":"60409",
    "sg:province":"IL",
    "sg:tags":[
        "elementary",
        "day"
    ],
    "wof:name":"Nurturing Develpmental & Learning Center",
    "wof:placetype":"venue"
},
  "geometry": {"coordinates":[-87.529571,41.62118],"type":"Point"}
}