{
  "type": "Feature",
  "properties": {
    "addr:full":"100 N Water Works Dr Belleville IL 62223",
    "addr:housenumber":"100",
    "addr:postcode":"62223",
    "addr:street":"N Water Works Dr",
    "iso:country":"US",
    "sg:address":"100 N Water Works Dr",
    "sg:city":"Belleville",
    "sg:classifiers":[
        {
            "category":"Utilities",
            "subcategory":"Water",
            "type":"Services"
        }
    ],
    "sg:phone":"+1 618 277 7498",
    "sg:postcode":"62223",
    "sg:province":"IL",
    "sg:tags":[
        "system",
        "supply"
    ],
    "wof:name":"Illinois American",
    "wof:placetype":"venue"
},
  "geometry": {"coordinates":[-90.039264,38.524679],"type":"Point"}
}