{
  "type": "Feature",
  "properties": {
    "addr:full":"289 S Schuyler Ave Bradley IL 60915",
    "addr:housenumber":"289",
    "addr:postcode":"60915",
    "addr:street":"S Schuyler Ave",
    "iso:country":"US",
    "sg:address":"289 S Schuyler Ave",
    "sg:city":"Bradley",
    "sg:classifiers":[
        {
            "category":"Food & Beverages",
            "subcategory":"Bakery",
            "type":"Retail Goods"
        }
    ],
    "sg:phone":"+1   ",
    "sg:postcode":"60915",
    "sg:province":"IL",
    "wof:name":"Butternut Bread",
    "wof:placetype":"venue"
},
  "geometry": {"coordinates":[-87.86001899999999,41.141171],"type":"Point"}
}