{
  "type": "Feature",
  "properties": {
    "iso:country":"US",
    "sg:address":"1400 Opus Pl",
    "sg:city":"Downers Grove",
    "sg:classifiers":[
        {
            "category":"Manufacturing",
            "subcategory":"Printing",
            "type":"Manufacturing & Wholesale Goods"
        }
    ],
    "sg:phone":"+1 847 756 4316",
    "sg:postcode":"60515",
    "sg:province":"IL",
    "sg:tags":[
        "publishing"
    ],
    "wof:name":"Medallion Press C/O Kpw Cpas",
    "wof:placetype":"venue"
},
  "geometry": {"coordinates":[-88.023252,41.829709],"type":"Point"}
}