{
  "type": "Feature",
  "properties": {
    "iso:country":"US",
    "sg:address":"224 S 1st Ave",
    "sg:city":"Canton",
    "sg:classifiers":[
        {
            "category":"Professional",
            "subcategory":"Accounting & Tax Preparation",
            "type":"Services"
        }
    ],
    "sg:phone":"+1 309 647 4414",
    "sg:postcode":"61520",
    "sg:province":"IL",
    "wof:name":"Accounting and Income Tax Svc",
    "wof:placetype":"venue"
},
  "geometry": {"coordinates":[-90.03363,40.553067],"type":"Point"}
}