{
  "type": "Feature",
  "properties": {
    "iso:country":"US",
    "sg:address":"2137 W. Belmont Ave.",
    "sg:city":"Chicago",
    "sg:classifiers":[
        {
            "category":"Personal",
            "subcategory":"Beauty Salon",
            "type":"Services"
        },
        {
            "category":"Personal",
            "subcategory":"Barber",
            "type":"Services"
        }
    ],
    "sg:phone":"+1 312 523 6298",
    "sg:postcode":"60618",
    "sg:province":"IL",
    "sg:tags":[
        "hair",
        "makeup",
        "artist"
    ],
    "wof:name":"Emmett Hodge",
    "wof:placetype":"venue"
},
  "geometry": {"coordinates":[-87.682215,41.939344],"type":"Point"}
}