{
  "type": "Feature",
  "properties": {
    "addr:full":"13809 198th St W Taylor Ridge IL 61284",
    "addr:housenumber":"13809",
    "addr:postcode":"61284",
    "addr:street":"198Th St W Taylor",
    "iso:country":"US",
    "sg:address":"13809 198th St W",
    "sg:city":"Taylor Ridge",
    "sg:classifiers":[
        {
            "category":"Farming",
            "subcategory":"Livestock Farm",
            "type":"Manufacturing & Wholesale Goods"
        }
    ],
    "sg:phone":"+1 309 795 1069",
    "sg:postcode":"61284",
    "sg:province":"IL",
    "sg:tags":[
        "feedlot",
        "hog",
        "corn",
        "or",
        "soybean"
    ],
    "wof:name":"Dale Preston",
    "wof:placetype":"venue"
},
  "geometry": {"coordinates":[-90.839896,41.38466],"type":"Point"}
}