{
  "type": "Feature",
  "properties": {
    "iso:country":"US",
    "sg:address":"5813 W Cermak Rd",
    "sg:city":"Cicero",
    "sg:classifiers":[
        {
            "category":"Real Estate",
            "subcategory":"Real Estate Agent",
            "type":"Services"
        }
    ],
    "sg:phone":"+1 708 780 8300",
    "sg:postcode":"60804",
    "sg:province":"IL",
    "wof:name":"Boardwalk Realty",
    "wof:placetype":"venue"
},
  "geometry": {"coordinates":[-87.76936499999999,41.850915],"type":"Point"}
}