{
  "type": "Feature",
  "properties": {
    "iso:country":"US",
    "sg:address":"6825 N Meridian Rd",
    "sg:city":"Rockford",
    "sg:classifiers":[
        {
            "category":"Shopping",
            "subcategory":"Bicycles & Sporting Goods",
            "type":"Retail Goods"
        }
    ],
    "sg:phone":"+1 815 968 1995",
    "sg:postcode":"61101",
    "sg:province":"IL",
    "sg:tags":[
        "gun",
        "gunsmith"
    ],
    "sg:website":"www.longrifles-pr.com",
    "wof:name":"Pecatonica River Rifle Supply",
    "wof:placetype":"venue"
},
  "geometry": {"coordinates":[-89.174224,42.35693],"type":"Point"}
}