{
  "type": "Feature",
  "properties": {
    "addr:full":"1902 3rd Ave East Moline IL 61244",
    "addr:housenumber":"1902",
    "addr:postcode":"61244",
    "addr:street":"3Rd Ave East",
    "iso:country":"US",
    "sg:address":"1902 3rd Ave",
    "sg:city":"East Moline",
    "sg:classifiers":[
        {
            "category":"Retail",
            "subcategory":"Funeral Services",
            "type":"Services"
        }
    ],
    "sg:phone":"+1 309 755 5271",
    "sg:postcode":"61244",
    "sg:province":"IL",
    "sg:tags":[
        "cemetery"
    ],
    "sg:website":"www.sullivanphillipsltd.com",
    "wof:name":"Sullivan-Phillips Mortuary Ltd",
    "wof:placetype":"venue"
},
  "geometry": {"coordinates":[-90.425201,41.5308],"type":"Point"}
}