{
  "type": "Feature",
  "properties": {
    "addr:full":"505 S Goodwin Ave Urbana IL 61801",
    "addr:housenumber":"505",
    "addr:postcode":"61801",
    "addr:street":"S Goodwin Ave",
    "iso:country":"US",
    "sg:address":"505 S Goodwin Ave",
    "sg:city":"Urbana",
    "sg:classifiers":[
        {
            "category":"Education",
            "subcategory":"College",
            "type":"Public Place"
        }
    ],
    "sg:phone":"+1 217 333 3047",
    "sg:postcode":"61801",
    "sg:province":"IL",
    "wof:name":"School of Life Sciences",
    "wof:placetype":"venue"
},
  "geometry": {"coordinates":[-88.22394799999999,40.108114],"type":"Point"}
}