{
  "type": "Feature",
  "properties": {
    "iso:country":"US",
    "sg:address":"9018 Odell Ave",
    "sg:city":"Bridgeview",
    "sg:classifiers":[
        {
            "category":"Wholesale",
            "subcategory":"Machinery & Supplies",
            "type":"Manufacturing & Wholesale Goods"
        }
    ],
    "sg:phone":"+1 708 599 2788",
    "sg:postcode":"60455",
    "sg:province":"IL",
    "sg:tags":[
        "equipment",
        "industrial",
        "parts",
        "repair"
    ],
    "wof:name":"UNI-Pac Equipment Inc",
    "wof:placetype":"venue"
},
  "geometry": {"coordinates":[-87.802603,41.72764],"type":"Point"}
}