{
  "type": "Feature",
  "properties": {
    "iso:country":"US",
    "sg:address":"4710 12th St",
    "sg:city":"Rock Island",
    "sg:classifiers":[
        {
            "category":"Autos & Motor Vehicles",
            "subcategory":"Automobile Sales",
            "type":"Retail Goods"
        }
    ],
    "sg:phone":"+1 309 786 2277",
    "sg:postcode":"61201",
    "sg:province":"IL",
    "sg:tags":[
        "car",
        "dealer"
    ],
    "wof:name":"Bill's Auto Sales",
    "wof:placetype":"venue"
},
  "geometry": {"coordinates":[-90.582722,41.46508],"type":"Point"}
}