{
  "type": "Feature",
  "properties": {
    "addr:full":"Bloomingdale Court 362 W Army Trail Rd Ste 230 Bloomingdale IL 60108",
    "addr:housenumber":"362",
    "addr:postcode":"60108",
    "addr:street":"Bloomingdale;W Army Trail Rd Ste 230",
    "iso:country":"US",
    "sg:address":"Bloomingdale Court 362 W Army Trail Rd Ste 230",
    "sg:city":"Bloomingdale",
    "sg:classifiers":[
        {
            "category":"Shopping",
            "subcategory":"Hobbies, Toys, & Games",
            "type":"Retail Goods"
        },
        {
            "category":"Shopping",
            "subcategory":"Crafts & Fabrics",
            "type":"Retail Goods"
        },
        {
            "category":"Professional",
            "subcategory":"Art Services",
            "type":"Services"
        }
    ],
    "sg:phone":"+1 630 924 0352",
    "sg:postcode":"60108",
    "sg:province":"IL",
    "sg:tags":[
        "shop",
        "hobby",
        "framing",
        "store"
    ],
    "sg:website":"www.joann.com",
    "wof:name":"Jo-Ann Fabrics & Crafts",
    "wof:placetype":"venue"
},
  "geometry": {"coordinates":[-88.11150499999999,41.939232],"type":"Point"}
}