{
  "type": "Feature",
  "properties": {
    "iso:country":"US",
    "sg:address":"1905 E Chestnut St",
    "sg:city":"Canton",
    "sg:classifiers":[
        {
            "category":"Personal",
            "subcategory":"Beauty Salon",
            "type":"Services"
        }
    ],
    "sg:phone":"+1 309 647 7500",
    "sg:postcode":"61520",
    "sg:province":"IL",
    "sg:tags":[
        "shop"
    ],
    "wof:name":"Studio Nail Salon",
    "wof:placetype":"venue"
},
  "geometry": {"coordinates":[-90.002225,40.55694],"type":"Point"}
}