{
  "type": "Feature",
  "properties": {
    "iso:country":"US",
    "sg:address":"109 E Bethalto Dr",
    "sg:city":"Bethalto",
    "sg:classifiers":[
        {
            "category":"Insurance",
            "subcategory":"Hazard Insurance",
            "type":"Services"
        }
    ],
    "sg:phone":"+1 618 377 2088",
    "sg:postcode":"62010",
    "sg:province":"IL",
    "sg:tags":[
        "commercial",
        "business"
    ],
    "wof:name":"Watters Insurance Agency",
    "wof:placetype":"venue"
},
  "geometry": {"coordinates":[-90.039368,38.901081],"type":"Point"}
}