{
  "type": "Feature",
  "properties": {
    "addr:full":"9919 Southwest Hwy Oak Lawn IL 60453",
    "addr:housenumber":"9919",
    "addr:postcode":"60453",
    "addr:street":"Southwest Hwy",
    "iso:country":"US",
    "sg:address":"9919 Southwest Hwy",
    "sg:city":"Oak Lawn",
    "sg:classifiers":[
        {
            "category":"Food & Beverages",
            "subcategory":"Bakery",
            "type":"Retail Goods"
        }
    ],
    "sg:phone":"+1 708 424 5655",
    "sg:postcode":"60453",
    "sg:province":"IL",
    "sg:website":"www.pepperidgefarm.com",
    "wof:name":"Pepperidge Farm Inc",
    "wof:placetype":"venue"
},
  "geometry": {"coordinates":[-87.77619900000001,41.712399],"type":"Point"}
}