{
  "type": "Feature",
  "properties": {
    "iso:country":"US",
    "sg:address":"1307 Lincolnshire Dr",
    "sg:city":"Champaign",
    "sg:classifiers":[
        {
            "category":"Education",
            "subcategory":"School",
            "type":"Public Place"
        }
    ],
    "sg:phone":"+1 217 359 8761",
    "sg:postcode":"61821",
    "sg:province":"IL",
    "sg:tags":[
        "high",
        "middle",
        "elementary"
    ],
    "wof:name":"St Matthew Religious Education Office",
    "wof:placetype":"venue"
},
  "geometry": {"coordinates":[-88.268997,40.097099],"type":"Point"}
}