{
  "type": "Feature",
  "properties": {
    "addr:full":"833 W Randolph St Chicago IL 60607",
    "addr:housenumber":"833",
    "addr:postcode":"60607",
    "addr:street":"W Randolph St",
    "iso:country":"US",
    "sg:address":"833 W Randolph St",
    "sg:city":"Chicago",
    "sg:classifiers":[
        {
            "category":"Restaurant",
            "type":"Food & Drink"
        }
    ],
    "sg:menulink":"http://www.allmenus.com/il/chicago/21976-marche/menu/",
    "sg:phone":"+1 312 226 8399",
    "sg:postcode":"60607",
    "sg:province":"IL",
    "sg:tags":[
        "french"
    ],
    "wof:name":"Marche",
    "wof:placetype":"venue"
},
  "geometry": {"coordinates":[-87.648758,41.88428],"type":"Point"}
}