{
  "type": "Feature",
  "properties": {
    "iso:country":"US",
    "sg:address":"500 S Dwyer Ave",
    "sg:city":"Arlington Heights",
    "sg:classifiers":[
        {
            "category":"Education",
            "subcategory":"School",
            "type":"Public Place"
        }
    ],
    "sg:phone":"+1 847 398 4292",
    "sg:postcode":"60005",
    "sg:province":"IL",
    "wof:name":"Westgate School",
    "wof:placetype":"venue"
},
  "geometry": {"coordinates":[-87.997639,42.076894],"type":"Point"}
}