{
  "type": "Feature",
  "properties": {
    "addr:full":"1207 N Randall Rd Aurora IL 60506",
    "addr:housenumber":"1207",
    "addr:postcode":"60506",
    "addr:street":"N Randall Rd",
    "iso:country":"US",
    "sg:address":"1207 N Randall Rd",
    "sg:city":"Aurora",
    "sg:classifiers":[
        {
            "category":"Wholesale",
            "subcategory":"Medical Equipment & Supplies",
            "type":"Manufacturing & Wholesale Goods"
        },
        {
            "category":"Shopping",
            "subcategory":"Pharmacy",
            "type":"Retail Goods"
        }
    ],
    "sg:phone":"+1 630 897 7112",
    "sg:postcode":"60506",
    "sg:province":"IL",
    "sg:tags":[
        "home",
        "care",
        "health",
        "first",
        "aid"
    ],
    "sg:website":"http://www.walgreens.com",
    "wof:name":"Walgreen Drug Stores",
    "wof:placetype":"venue"
},
  "geometry": {"coordinates":[-88.34976899999999,41.781112],"type":"Point"}
}