{
  "type": "Feature",
  "properties": {
    "iso:country":"US",
    "sg:address":"107 N Reed St",
    "sg:city":"Joliet",
    "sg:classifiers":[
        {
            "category":"Shopping",
            "subcategory":"Florist",
            "type":"Retail Goods"
        }
    ],
    "sg:phone":"+1 815 725 3470",
    "sg:postcode":"60435",
    "sg:province":"IL",
    "sg:tags":[
        "basket",
        "gift"
    ],
    "sg:website":"http://www.jolietfloral.com",
    "wof:name":"Joliet Floral Co",
    "wof:placetype":"venue"
},
  "geometry": {"coordinates":[-88.109184,41.524617],"type":"Point"}
}