{
  "type": "Feature",
  "properties": {
    "addr:full":"1001 W North Ave Chicago IL 60642",
    "addr:housenumber":"1001",
    "addr:postcode":"60642",
    "addr:street":"W North Ave",
    "iso:country":"US",
    "sg:address":"1001 W North Ave",
    "sg:city":"Chicago",
    "sg:classifiers":[
        {
            "category":"Personal",
            "subcategory":"Day Spa",
            "type":"Services"
        }
    ],
    "sg:phone":"+1 312 649 0707",
    "sg:postcode":"60642",
    "sg:province":"IL",
    "sg:website":"www.michaelanthonyspa.com",
    "wof:name":"Michael Anthony Salon",
    "wof:placetype":"venue"
},
  "geometry": {"coordinates":[-87.653493,41.910543],"type":"Point"}
}