{
  "type": "Feature",
  "properties": {
    "iso:country":"US",
    "sg:address":"801 N Walnut St",
    "sg:city":"Mount Carmel",
    "sg:classifiers":[
        {
            "category":"Restaurant",
            "type":"Food & Drink"
        }
    ],
    "sg:menulink":"http://www.allmenus.com/il/mount-carmel/126840-subway/menu/",
    "sg:phone":"+1 618 262 7774",
    "sg:postcode":"62863",
    "sg:province":"IL",
    "sg:tags":[
        "american",
        "sandwich"
    ],
    "wof:name":"Subway",
    "wof:placetype":"venue"
},
  "geometry": {"coordinates":[-87.767003,38.413389],"type":"Point"}
}