{
  "type": "Feature",
  "properties": {
    "iso:country":"US",
    "sg:address":"2030 State Rte 26",
    "sg:city":"Dixon",
    "sg:classifiers":[
        {
            "category":"Retail",
            "subcategory":"Portrait Studio",
            "type":"Services"
        }
    ],
    "sg:phone":"+1 815 288 1155",
    "sg:postcode":"61021",
    "sg:province":"IL",
    "sg:tags":[
        "photo"
    ],
    "wof:name":"Photography",
    "wof:placetype":"venue"
},
  "geometry": {"coordinates":[-89.51821099999999,41.879092],"type":"Point"}
}