{
  "type": "Feature",
  "properties": {
    "addr:full":"173 S Schmale Rd Carol Stream IL 60188",
    "addr:housenumber":"173",
    "addr:postcode":"60188",
    "addr:street":"S Schmale Rd",
    "iso:country":"US",
    "sg:address":"173 S Schmale Rd",
    "sg:city":"Carol Stream",
    "sg:classifiers":[
        {
            "category":"Food & Beverages",
            "subcategory":"Groceries & Convenience Stores",
            "type":"Retail Goods"
        }
    ],
    "sg:phone":"+1   ",
    "sg:postcode":"60188",
    "sg:province":"IL",
    "wof:name":"Kaveri Foods",
    "wof:placetype":"venue"
},
  "geometry": {"coordinates":[-88.101816,41.900541],"type":"Point"}
}