{
  "type": "Feature",
  "properties": {
    "iso:country":"US",
    "sg:address":"5904 Old Saint Louis Rd",
    "sg:city":"Belleville",
    "sg:classifiers":[
        {
            "category":"Autos & Motor Vehicles",
            "subcategory":"Fuel & Gas Station",
            "type":"Retail Goods"
        }
    ],
    "sg:phone":"+1 618 355 7834",
    "sg:postcode":"62223",
    "sg:province":"IL",
    "sg:tags":[
        "oil"
    ],
    "wof:name":"Dickerson Stations Inc",
    "wof:placetype":"venue"
},
  "geometry": {"coordinates":[-90.036891,38.53495],"type":"Point"}
}