{
  "type": "Feature",
  "properties": {
    "iso:country":"US",
    "sg:address":"316 N Fiore Pkwy",
    "sg:city":"Vernon Hills",
    "sg:classifiers":[
        {
            "category":"Professional",
            "type":"Services"
        }
    ],
    "sg:phone":"+1 847 918 1672",
    "sg:postcode":"60061",
    "sg:province":"IL",
    "wof:name":"H&H International",
    "wof:placetype":"venue"
},
  "geometry": {"coordinates":[-87.987969,42.232738],"type":"Point"}
}