{
  "type": "Feature",
  "properties": {
    "iso:country":"US",
    "sg:address":"106 N Division St",
    "sg:city":"Carterville",
    "sg:classifiers":[
        {
            "category":"Professional",
            "subcategory":"Lawyer & Legal Services",
            "type":"Services"
        },
        {
            "category":"Banks & Credit Unions",
            "subcategory":"Atm",
            "type":"Services"
        }
    ],
    "sg:phone":"+1 618 985 2819",
    "sg:postcode":"62918",
    "sg:province":"IL",
    "sg:tags":[
        "personal",
        "injury",
        "bankruptcy"
    ],
    "wof:name":"Eytalis Edward Atty",
    "wof:placetype":"venue"
},
  "geometry": {"coordinates":[-89.077003,37.760799],"type":"Point"}
}