{
  "type": "Feature",
  "properties": {
    "iso:country":"US",
    "sg:address":"8044 S Washtenaw Ave # 1",
    "sg:city":"Chicago",
    "sg:classifiers":[
        {
            "category":"Professional",
            "subcategory":"Engineering",
            "type":"Services"
        }
    ],
    "sg:phone":"+1 773 778 0175",
    "sg:postcode":"60652",
    "sg:province":"IL",
    "sg:tags":[
        "consulting",
        "engineer"
    ],
    "wof:name":"Inhiser Engineering",
    "wof:placetype":"venue"
},
  "geometry": {"coordinates":[-87.690096,41.747343],"type":"Point"}
}