{
  "type": "Feature",
  "properties": {
    "addr:full":"310 7th St Rockford IL 61104",
    "addr:housenumber":"310",
    "addr:postcode":"61104",
    "addr:street":"7Th St",
    "iso:country":"US",
    "sg:address":"310 7th St",
    "sg:city":"Rockford",
    "sg:classifiers":[
        {
            "category":"Health Services",
            "subcategory":"Nursing And Care Facility",
            "type":"Services"
        }
    ],
    "sg:phone":"+1 815 965 4090",
    "sg:postcode":"61104",
    "sg:province":"IL",
    "sg:tags":[
        "home",
        "retirement",
        "community"
    ],
    "wof:name":"Valkommen Plaza",
    "wof:placetype":"venue"
},
  "geometry": {"coordinates":[-89.080725,42.263823],"type":"Point"}
}