{
  "type": "Feature",
  "properties": {
    "addr:full":"1001 S Fairview Ave Park Ridge IL 60068",
    "addr:housenumber":"1001",
    "addr:postcode":"60068",
    "addr:street":"S Fairview Ave",
    "iso:country":"US",
    "sg:address":"1001 S Fairview Ave",
    "sg:city":"Park Ridge",
    "sg:classifiers":[
        {
            "category":"Education",
            "subcategory":"School",
            "type":"Public Place"
        }
    ],
    "sg:phone":"+1 847 318 4235",
    "sg:postcode":"60068",
    "sg:province":"IL",
    "sg:tags":[
        "high",
        "middle",
        "elementary"
    ],
    "wof:name":"Schools Public",
    "wof:placetype":"venue"
},
  "geometry": {"coordinates":[-87.83417799999999,41.998743],"type":"Point"}
}