{
  "type": "Feature",
  "properties": {
    "iso:country":"US",
    "sg:address":"5668 E State St",
    "sg:city":"Rockford",
    "sg:classifiers":[
        {
            "category":"Health Services",
            "subcategory":"Clinic",
            "type":"Services"
        }
    ],
    "sg:phone":"+1 815 397 7900",
    "sg:postcode":"61108",
    "sg:province":"IL",
    "sg:tags":[
        "medical",
        "group"
    ],
    "sg:website":"www.rockfordsurgical.com",
    "wof:name":"Rockford Surgical Svc",
    "wof:placetype":"venue"
},
  "geometry": {"coordinates":[-89.005081,42.266243],"type":"Point"}
}