{
  "type": "Feature",
  "properties": {
    "iso:country":"US",
    "sg:address":"562 6th Ave",
    "sg:city":"Aurora",
    "sg:classifiers":[
        {
            "category":"Building & Trades",
            "subcategory":"Cleaning & Sanitation",
            "type":"Services"
        }
    ],
    "sg:phone":"+1 630 585 6295",
    "sg:postcode":"60505",
    "sg:province":"IL",
    "sg:tags":[
        "maintenance"
    ],
    "wof:name":"Nancys Cleaning Service",
    "wof:placetype":"venue"
},
  "geometry": {"coordinates":[-88.30825900000001,41.744245],"type":"Point"}
}