{
  "type": "Feature",
  "properties": {
    "iso:country":"US",
    "sg:address":"3480 Prairie Flower Cir",
    "sg:city":"Rockford",
    "sg:classifiers":[
        {
            "category":"Food & Beverages",
            "subcategory":"Candy",
            "type":"Retail Goods"
        }
    ],
    "sg:phone":"+1 815 332 4671",
    "sg:postcode":"61114",
    "sg:province":"IL",
    "sg:tags":[
        "confectionery"
    ],
    "sg:website":"www.rockymountainchocolate.com",
    "wof:name":"Rocky Mountain Chocolate Fctry",
    "wof:placetype":"venue"
},
  "geometry": {"coordinates":[-88.975641,42.311022],"type":"Point"}
}