{
  "type": "Feature",
  "properties": {
    "iso:country":"US",
    "sg:address":"7810 W North Ave",
    "sg:city":"Elmwood Park",
    "sg:classifiers":[
        {
            "category":"Health Services",
            "subcategory":"Doctor",
            "type":"Services"
        }
    ],
    "sg:phone":"+1 708 452 2222",
    "sg:postcode":"60707",
    "sg:province":"IL",
    "wof:name":"Midwest Open Mri Inc",
    "wof:placetype":"venue"
},
  "geometry": {"coordinates":[-87.820702,41.908699],"type":"Point"}
}