{
  "type": "Feature",
  "properties": {
    "iso:country":"US",
    "sg:address":"2448 W 47th St",
    "sg:city":"Chicago",
    "sg:classifiers":[
        {
            "category":"Shopping",
            "subcategory":"Jewelry",
            "type":"Retail Goods"
        }
    ],
    "sg:phone":"+1 773 890 9527",
    "sg:postcode":"60632",
    "sg:province":"IL",
    "wof:name":"Saritas Flowers and Gifts",
    "wof:placetype":"venue"
},
  "geometry": {"coordinates":[-87.68589799999999,41.808399],"type":"Point"}
}