{
  "type": "Feature",
  "properties": {
    "iso:country":"US",
    "sg:address":"15807 Old Carlyle Rd",
    "sg:city":"Carlyle",
    "sg:classifiers":[
        {
            "category":"Freight",
            "type":"Transportation"
        }
    ],
    "sg:phone":"+1 618 227 8577",
    "sg:postcode":"62231",
    "sg:province":"IL",
    "sg:tags":[
        "operator",
        "trucking"
    ],
    "wof:name":"Richard G Holtgrave",
    "wof:placetype":"venue"
},
  "geometry": {"coordinates":[-89.419293,38.580063],"type":"Point"}
}