{
  "type": "Feature",
  "properties": {
    "iso:country":"US",
    "sg:address":"857 W Wise Rd",
    "sg:city":"Schaumburg",
    "sg:classifiers":[
        {
            "category":"Retail",
            "subcategory":"Auto Repair",
            "type":"Services"
        }
    ],
    "sg:phone":"+1 847 895 2723",
    "sg:postcode":"60193",
    "sg:province":"IL",
    "sg:tags":[
        "muffler",
        "brake"
    ],
    "wof:name":"Discount Muller  Brakes & More",
    "wof:placetype":"venue"
},
  "geometry": {"coordinates":[-88.10055,42.004467],"type":"Point"}
}