{
  "type": "Feature",
  "properties": {
    "iso:country":"US",
    "sg:address":"1378 Perry St",
    "sg:city":"Des Plaines",
    "sg:classifiers":[
        {
            "category":"Professional",
            "subcategory":"Research",
            "type":"Services"
        }
    ],
    "sg:phone":"+1 847 791 5942",
    "sg:postcode":"60016",
    "sg:province":"IL",
    "sg:tags":[
        "organization",
        "noncommercial"
    ],
    "wof:name":"Health Search Inc",
    "wof:placetype":"venue"
},
  "geometry": {"coordinates":[-87.891224,42.044176],"type":"Point"}
}