{
  "type": "Feature",
  "properties": {
    "iso:country":"US",
    "sg:address":"15515 S 70th Ct",
    "sg:city":"Orland Park",
    "sg:classifiers":[
        {
            "category":"Freight",
            "type":"Transportation"
        }
    ],
    "sg:phone":"+1 708 802 7000",
    "sg:postcode":"60462",
    "sg:province":"IL",
    "sg:tags":[
        "shipping",
        "agent"
    ],
    "sg:website":"www.alliance.com",
    "wof:name":"Alliance Shippers Inc",
    "wof:placetype":"venue"
},
  "geometry": {"coordinates":[-87.790869,41.606298],"type":"Point"}
}