{
  "type": "Feature",
  "properties": {
    "iso:country":"US",
    "sg:address":"283 N 3rd St",
    "sg:city":"Breese",
    "sg:classifiers":[
        {
            "category":"Wholesale",
            "subcategory":"Jewelry",
            "type":"Manufacturing & Wholesale Goods"
        }
    ],
    "sg:phone":"+1 618 526 8443",
    "sg:postcode":"62230",
    "sg:province":"IL",
    "sg:tags":[
        "silver",
        "ethnic"
    ],
    "wof:name":"Silver Jct Emporium & Trdg Co",
    "wof:placetype":"venue"
},
  "geometry": {"coordinates":[-89.531988,38.609982],"type":"Point"}
}