{
  "type": "Feature",
  "properties": {
    "iso:country":"US",
    "sg:address":"3812 N Lowell Ave",
    "sg:city":"Chicago",
    "sg:classifiers":[
        {
            "category":"Shopping",
            "subcategory":"Gifts & Souvenirs",
            "type":"Retail Goods"
        },
        {
            "category":"Manufacturing",
            "subcategory":"Retail Goods",
            "type":"Manufacturing & Wholesale Goods"
        }
    ],
    "sg:phone":"+1 773 282 6887",
    "sg:postcode":"60641",
    "sg:province":"IL",
    "sg:tags":[
        "shop",
        "giftware's-wholesale",
        "manufacturer"
    ],
    "wof:name":"G Maddi & Co Inc",
    "wof:placetype":"venue"
},
  "geometry": {"coordinates":[-87.736707,41.950132],"type":"Point"}
}