{
  "type": "Feature",
  "properties": {
    "iso:country":"US",
    "sg:address":"1579 Highpoint Dr",
    "sg:city":"Elgin",
    "sg:classifiers":[
        {
            "category":"Freight",
            "type":"Transportation"
        }
    ],
    "sg:phone":"+1 847 741 2930",
    "sg:postcode":"60123",
    "sg:province":"IL",
    "sg:tags":[
        "broker",
        "agent"
    ],
    "wof:name":"Unicity Custom Brokers Inc",
    "wof:placetype":"venue"
},
  "geometry": {"coordinates":[-88.27948499999999,42.069929],"type":"Point"}
}