{
  "type": "Feature",
  "properties": {
    "addr:full":"1309 Behan Rd Crystal Lake IL 60014",
    "addr:housenumber":"1309",
    "addr:postcode":"60014",
    "addr:street":"Behan Rd",
    "iso:country":"US",
    "sg:address":"1309 Behan Rd",
    "sg:city":"Crystal Lake",
    "sg:classifiers":[
        {
            "category":"Arts & Performance",
            "subcategory":"Theater",
            "type":"Entertainment"
        }
    ],
    "sg:phone":"+1 815 459 8313",
    "sg:postcode":"60014",
    "sg:province":"IL",
    "sg:tags":[
        "group"
    ],
    "wof:name":"Wooden Ship Studio",
    "wof:placetype":"venue"
},
  "geometry": {"coordinates":[-88.222002,42.260345],"type":"Point"}
}