{
  "type": "Feature",
  "properties": {
    "addr:full":"18037 Torrence Ave Lansing IL 60438",
    "addr:housenumber":"18037",
    "addr:postcode":"60438",
    "addr:street":"Torrence Ave",
    "iso:country":"US",
    "sg:address":"18037 Torrence Ave",
    "sg:city":"Lansing",
    "sg:classifiers":[
        {
            "category":"Health Services",
            "subcategory":"Clinic",
            "type":"Services"
        },
        {
            "category":"Health Services",
            "subcategory":"Health Practitioner",
            "type":"Services"
        },
        {
            "category":"Health Services",
            "subcategory":"Chiropractor",
            "type":"Services"
        }
    ],
    "sg:phone":"+1 708 895 3228",
    "sg:postcode":"60438",
    "sg:province":"IL",
    "sg:tags":[
        "acupuncture",
        "loss",
        "weight"
    ],
    "sg:website":"www.chirolansing.com",
    "wof:name":"Lansing Chiropractic Clinic",
    "wof:placetype":"venue"
},
  "geometry": {"coordinates":[-87.558601,41.566299],"type":"Point"}
}