{
  "type": "Feature",
  "properties": {
    "iso:country":"US",
    "sg:address":"708 W Cottonwood St",
    "sg:city":"Freeport",
    "sg:classifiers":[
        {
            "category":"Social Services",
            "subcategory":"Child Care",
            "type":"Services"
        }
    ],
    "sg:phone":"+1 815 235 1109",
    "sg:postcode":"61032",
    "sg:province":"IL",
    "sg:tags":[
        "day"
    ],
    "wof:name":"Rebecca Appelman",
    "wof:placetype":"venue"
},
  "geometry": {"coordinates":[-89.63072200000001,42.299498],"type":"Point"}
}