{
  "type": "Feature",
  "properties": {
    "addr:full":"454 Appleton Dr Batavia IL 60510",
    "addr:housenumber":"454",
    "addr:postcode":"60510",
    "addr:street":"Appleton Dr",
    "iso:country":"US",
    "sg:address":"454 Appleton Dr",
    "sg:city":"Batavia",
    "sg:classifiers":[
        {
            "category":"Professional",
            "subcategory":"Management & Consulting",
            "type":"Services"
        }
    ],
    "sg:phone":"+1 630 406 8112",
    "sg:postcode":"60510",
    "sg:province":"IL",
    "sg:tags":[
        "business"
    ],
    "wof:name":"About Training Inc",
    "wof:placetype":"venue"
},
  "geometry": {"coordinates":[-88.28992700000001,41.847073],"type":"Point"}
}