{
  "type": "Feature",
  "properties": {
    "addr:full":"1620 W Belmont Ave Chicago IL 60657",
    "addr:housenumber":"1620",
    "addr:postcode":"60657",
    "addr:street":"W Belmont Ave",
    "iso:country":"US",
    "sg:address":"1620 W Belmont Ave",
    "sg:city":"Chicago",
    "sg:classifiers":[
        {
            "category":"Real Estate",
            "subcategory":"Real Estate Services",
            "type":"Services"
        },
        {
            "category":"Real Estate",
            "subcategory":"Real Estate Agent",
            "type":"Services"
        }
    ],
    "sg:phone":"+1 312 513 5021",
    "sg:postcode":"60657",
    "sg:province":"IL",
    "wof:name":"Monique Sandberg",
    "wof:placetype":"venue"
},
  "geometry": {"coordinates":[-87.66951299999999,41.939913],"type":"Point"}
}