{
  "type": "Feature",
  "properties": {
    "addr:full":"1509 W Fullerton Avenue Chicago IL 60614",
    "addr:housenumber":"1509",
    "addr:postcode":"60614",
    "addr:street":"W Fullerton Avenue",
    "iso:country":"US",
    "sg:address":"1509 W Fullerton Avenue",
    "sg:city":"Chicago",
    "sg:classifiers":[
        {
            "category":"Arts & Performance",
            "subcategory":"Art Gallery",
            "type":"Entertainment"
        }
    ],
    "sg:phone":"+1 773 248 2738",
    "sg:postcode":"60614",
    "sg:province":"IL",
    "sg:website":"www.prints-posters.com",
    "wof:name":"Chicago Center For the Print",
    "wof:placetype":"venue"
},
  "geometry": {"coordinates":[-87.666006,41.925071],"type":"Point"}
}