{
  "type": "Feature",
  "properties": {
    "addr:full":"340 Renner Dr Elgin IL 60123",
    "addr:housenumber":"340",
    "addr:postcode":"60123",
    "addr:street":"Renner Dr",
    "iso:country":"US",
    "sg:address":"340 Renner Dr",
    "sg:city":"Elgin",
    "sg:classifiers":[
        {
            "category":"Manufacturing",
            "subcategory":"Rubber & Plastics",
            "type":"Manufacturing & Wholesale Goods"
        }
    ],
    "sg:phone":"+1 847 741 4900",
    "sg:postcode":"60123",
    "sg:province":"IL",
    "sg:tags":[
        "product",
        "parts",
        "mfg"
    ],
    "sg:website":"www.suburbanplastics.com",
    "wof:name":"Suburban Plastics Co",
    "wof:placetype":"venue"
},
  "geometry": {"coordinates":[-88.324735,42.023726],"type":"Point"}
}