{
  "type": "Feature",
  "properties": {
    "iso:country":"US",
    "sg:address":"770 Western Ave",
    "sg:city":"Glen Ellyn",
    "sg:phone":"+1 630 942 1190",
    "sg:postcode":"60137",
    "sg:province":"IL",
    "sg:tags":[
        "irrigation",
        "system"
    ],
    "wof:name":"Illinois Irrigation Co",
    "wof:placetype":"venue"
},
  "geometry": {"coordinates":[-88.072603,41.887544],"type":"Point"}
}