{
  "type": "Feature",
  "properties": {
    "iso:country":"US",
    "sg:address":"1001 S Main St",
    "sg:city":"Algonquin",
    "sg:classifiers":[
        {
            "category":"Autos & Motor Vehicles",
            "subcategory":"Fuel & Gas Station",
            "type":"Retail Goods"
        }
    ],
    "sg:phone":"+1 847 458 8787",
    "sg:postcode":"60102",
    "sg:province":"IL",
    "wof:name":"Cresent Petroleum Inc",
    "wof:placetype":"venue"
},
  "geometry": {"coordinates":[-88.297123,42.15918],"type":"Point"}
}