{
  "type": "Feature",
  "properties": {
    "iso:country":"US",
    "sg:address":"311 W University Ave",
    "sg:city":"Champaign",
    "sg:classifiers":[
        {
            "category":"Building & Trades",
            "subcategory":"Equipment Rental",
            "type":"Services"
        }
    ],
    "sg:phone":"+1 217 359 4466",
    "sg:postcode":"61820",
    "sg:province":"IL",
    "sg:tags":[
        "leasing"
    ],
    "wof:name":"Chelsea Management Group LTD",
    "wof:placetype":"venue"
},
  "geometry": {"coordinates":[-88.248334,40.116219],"type":"Point"}
}