{
  "type": "Feature",
  "properties": {
    "addr:full":"20 Bronze Pointe N Swansea IL 62226",
    "addr:housenumber":"20",
    "addr:postcode":"62226",
    "addr:street":"Bronze Pointe N",
    "iso:country":"US",
    "sg:address":"20 Bronze Pointe N",
    "sg:city":"Swansea",
    "sg:classifiers":[
        {
            "category":"Professional",
            "subcategory":"Lawyer & Legal Services",
            "type":"Services"
        }
    ],
    "sg:phone":"+1 618 277 8260",
    "sg:postcode":"62226",
    "sg:province":"IL",
    "sg:tags":[
        "personal",
        "injury"
    ],
    "wof:name":"Stubblefield Timothy C Atty",
    "wof:placetype":"venue"
},
  "geometry": {"coordinates":[-89.98629800000001,38.566399],"type":"Point"}
}