{
  "type": "Feature",
  "properties": {
    "addr:full":"214 W Monroe St Herrin IL 62948",
    "addr:housenumber":"214",
    "addr:postcode":"62948",
    "addr:street":"W Monroe St",
    "iso:country":"US",
    "sg:address":"214 W Monroe St",
    "sg:city":"Herrin",
    "sg:classifiers":[
        {
            "category":"Personal",
            "subcategory":"Tattoo Parlor",
            "type":"Services"
        },
        {
            "category":"Personal",
            "subcategory":"Piercing",
            "type":"Services"
        }
    ],
    "sg:phone":"+1 618 988 8836",
    "sg:postcode":"62948",
    "sg:province":"IL",
    "wof:name":"Darkside Tattoos",
    "wof:placetype":"venue"
},
  "geometry": {"coordinates":[-89.02919799999999,37.804501],"type":"Point"}
}