{
  "type": "Feature",
  "properties": {
    "iso:country":"US",
    "sg:address":"5112 Forest Ave",
    "sg:city":"Downers Grove",
    "sg:classifiers":[
        {
            "category":"Personal",
            "subcategory":"Beauty Salon",
            "type":"Services"
        }
    ],
    "sg:phone":"+1 630 964 6066",
    "sg:postcode":"60515",
    "sg:province":"IL",
    "sg:tags":[
        "shop"
    ],
    "wof:name":"Susan Waldschmidt Electrolysis",
    "wof:placetype":"venue"
},
  "geometry": {"coordinates":[-88.012168,41.793874],"type":"Point"}
}