{
  "type": "Feature",
  "properties": {
    "iso:country":"US",
    "sg:address":"408 Washington Blvd Ste A",
    "sg:city":"Mundelein",
    "sg:classifiers":[
        {
            "category":"Building & Trades",
            "subcategory":"Electrical",
            "type":"Services"
        }
    ],
    "sg:phone":"+1 847 566 8820",
    "sg:postcode":"60060",
    "sg:province":"IL",
    "sg:tags":[
        "control",
        "regulator",
        "system",
        "controls"
    ],
    "wof:name":"Fuel Management Systems",
    "wof:placetype":"venue"
},
  "geometry": {"coordinates":[-87.986395,42.258263],"type":"Point"}
}