{
  "type": "Feature",
  "properties": {
    "iso:country":"US",
    "sg:address":"7561 E State St",
    "sg:city":"Rockford",
    "sg:classifiers":[
        {
            "category":"Restaurant",
            "type":"Food & Drink"
        },
        {
            "category":"Ice Cream",
            "type":"Food & Drink"
        }
    ],
    "sg:menulink":"http://www.allmenus.com/il/rockford/92491-steak-n-shake/menu/",
    "sg:phone":"+1 815 395 1989",
    "sg:postcode":"61108",
    "sg:province":"IL",
    "sg:tags":[
        "american",
        "ice",
        "cream"
    ],
    "wof:name":"Steak 'n Shake",
    "wof:placetype":"venue"
},
  "geometry": {"coordinates":[-88.969172,42.270418],"type":"Point"}
}