{
  "type": "Feature",
  "properties": {
    "addr:full":"3077 W Jefferson St Joliet IL 60435",
    "addr:housenumber":"3077",
    "addr:postcode":"60435",
    "addr:street":"W Jefferson St",
    "iso:country":"US",
    "sg:address":"3077 W Jefferson St",
    "sg:city":"Joliet",
    "sg:classifiers":[
        {
            "category":"Insurance",
            "subcategory":"Insurance Agent",
            "type":"Services"
        }
    ],
    "sg:phone":"+1 815 730 3950",
    "sg:postcode":"60435",
    "sg:province":"IL",
    "sg:tags":[
        "broker"
    ],
    "wof:name":"Thrivent Fincl For Lutherans",
    "wof:placetype":"venue"
},
  "geometry": {"coordinates":[-88.15638,41.521921],"type":"Point"}
}