{
  "type": "Feature",
  "properties": {
    "iso:country":"US",
    "sg:address":"5538 W Belmont Ave",
    "sg:city":"Chicago",
    "sg:classifiers":[
        {
            "category":"Travel",
            "subcategory":"Travel Agent",
            "type":"Entertainment"
        }
    ],
    "sg:phone":"+1 773 736 5522",
    "sg:postcode":"60641",
    "sg:province":"IL",
    "sg:tags":[
        "automobile",
        "school",
        "agency",
        "driving"
    ],
    "sg:website":"www.cdltruck.com",
    "wof:name":"Progressive Driving School",
    "wof:placetype":"venue"
},
  "geometry": {"coordinates":[-87.764999,41.938599],"type":"Point"}
}