{
  "type": "Feature",
  "properties": {
    "iso:country":"US",
    "sg:address":"1405 E Kerr Ave",
    "sg:city":"Urbana",
    "sg:classifiers":[
        {
            "category":"Retail",
            "subcategory":"Auto Repair",
            "type":"Services"
        }
    ],
    "sg:phone":"+1 217 344 7010",
    "sg:postcode":"61802",
    "sg:province":"IL",
    "sg:tags":[
        "general"
    ],
    "wof:name":"Norms Auto Inc",
    "wof:placetype":"venue"
},
  "geometry": {"coordinates":[-88.192281,40.122095],"type":"Point"}
}