{
  "type": "Feature",
  "properties": {
    "addr:full":"9713 Old Lincoln Trl Fairview Heights IL 62208",
    "addr:housenumber":"9713",
    "addr:postcode":"62208",
    "addr:street":"Old Lincoln Trl",
    "iso:country":"US",
    "sg:address":"9713 Old Lincoln Trl",
    "sg:city":"Fairview Heights",
    "sg:classifiers":[
        {
            "category":"Retail",
            "subcategory":"Laundry & Dry Cleaning",
            "type":"Services"
        }
    ],
    "sg:phone":"+1 618 394 1723",
    "sg:postcode":"62208",
    "sg:province":"IL",
    "wof:name":"Dry Cleaning To Your Door",
    "wof:placetype":"venue"
},
  "geometry": {"coordinates":[-90.030474,38.584715],"type":"Point"}
}