{
  "type": "Feature",
  "properties": {
    "iso:country":"US",
    "sg:address":"1182 Preswyck Dr",
    "sg:city":"Belleville",
    "sg:classifiers":[
        {
            "category":"Shopping",
            "type":"Retail Goods"
        }
    ],
    "sg:phone":"+1   ",
    "sg:postcode":"62221",
    "sg:province":"IL",
    "sg:tags":[
        "merchandise"
    ],
    "wof:name":"Ramsa Midwest Inc",
    "wof:placetype":"venue"
},
  "geometry": {"coordinates":[-89.94438100000001,38.567747],"type":"Point"}
}