{
  "type": "Feature",
  "properties": {
    "iso:country":"US",
    "sg:address":"140 W Golf Rd",
    "sg:city":"Libertyville",
    "sg:classifiers":[
        {
            "category":"Wholesale",
            "subcategory":"Durable Goods & Equipment",
            "type":"Manufacturing & Wholesale Goods"
        }
    ],
    "sg:phone":"+1 847 573 9532",
    "sg:postcode":"60048",
    "sg:province":"IL",
    "sg:tags":[
        "importer"
    ],
    "wof:name":"Rainbow International Carpet",
    "wof:placetype":"venue"
},
  "geometry": {"coordinates":[-87.95176,42.269606],"type":"Point"}
}