{
  "type": "Feature",
  "properties": {
    "addr:full":"2325 W 24th Pl Chicago IL 60608",
    "addr:housenumber":"2325",
    "addr:postcode":"60608",
    "addr:street":"W 24Th Pl",
    "iso:country":"US",
    "sg:address":"2325 W 24th Pl",
    "sg:city":"Chicago",
    "sg:classifiers":[
        {
            "category":"Organizations",
            "subcategory":"Religious Organization",
            "type":"Services"
        }
    ],
    "sg:phone":"+1 773 847 8771",
    "sg:postcode":"60608",
    "sg:province":"IL",
    "wof:name":"Missionaries of Charity",
    "wof:placetype":"venue"
},
  "geometry": {"coordinates":[-87.68364800000001,41.847512],"type":"Point"}
}