{
  "type": "Feature",
  "properties": {
    "iso:country":"US",
    "sg:address":"7 W Central Park Plz",
    "sg:city":"Jacksonville",
    "sg:classifiers":[
        {
            "category":"Personal",
            "type":"Services"
        },
        {
            "category":"Professional",
            "subcategory":"Art Services",
            "type":"Services"
        }
    ],
    "sg:phone":"+1 217 243 2717",
    "sg:postcode":"62650",
    "sg:province":"IL",
    "sg:tags":[
        "photography",
        "videography",
        "wedding"
    ],
    "wof:name":"Merle Fox Photography Inc",
    "wof:placetype":"venue"
},
  "geometry": {"coordinates":[-90.229925,39.733715],"type":"Point"}
}