{
  "type": "Feature",
  "properties": {
    "iso:country":"US",
    "sg:address":"687 E Chicago St",
    "sg:city":"Elgin",
    "sg:classifiers":[
        {
            "category":"Building & Trades",
            "subcategory":"Landscaping Services",
            "type":"Services"
        }
    ],
    "sg:phone":"+1 847 608 9756",
    "sg:postcode":"60120",
    "sg:province":"IL",
    "sg:tags":[
        "landscape",
        "contractor"
    ],
    "wof:name":"Rozco Landscaping",
    "wof:placetype":"venue"
},
  "geometry": {"coordinates":[-88.264305,42.036742],"type":"Point"}
}