{
  "type": "Feature",
  "properties": {
    "addr:full":"12456 S McVickers Ave Palos Heights IL 60463",
    "addr:housenumber":"12456",
    "addr:postcode":"60463",
    "addr:street":"S Mcvickers Ave",
    "iso:country":"US",
    "sg:address":"12456 S McVickers Ave",
    "sg:city":"Palos Heights",
    "sg:classifiers":[
        {
            "category":"Building & Trades",
            "subcategory":"Plumbing",
            "type":"Services"
        }
    ],
    "sg:phone":"+1 708 389 8075",
    "sg:postcode":"60463",
    "sg:province":"IL",
    "wof:name":"Dee Plumbing",
    "wof:placetype":"venue"
},
  "geometry": {"coordinates":[-87.76953899999999,41.665153],"type":"Point"}
}