{
  "type": "Feature",
  "properties": {
    "iso:country":"US",
    "sg:address":"13535 S Torrence Ave",
    "sg:city":"Chicago",
    "sg:classifiers":[
        {
            "category":"Manufacturing",
            "subcategory":"Paper Products",
            "type":"Manufacturing & Wholesale Goods"
        }
    ],
    "sg:phone":"+1 773 646 1320",
    "sg:postcode":"60633",
    "sg:province":"IL",
    "sg:tags":[
        "products-wholesale",
        "manufacturer"
    ],
    "wof:name":"Chicago Enterprise Center",
    "wof:placetype":"venue"
},
  "geometry": {"coordinates":[-87.559319,41.650492],"type":"Point"}
}