{
  "type": "Feature",
  "properties": {
    "addr:full":"933 N Lake St Aurora IL 60506",
    "addr:housenumber":"933",
    "addr:postcode":"60506",
    "addr:street":"N Lake St",
    "iso:country":"US",
    "sg:address":"933 N Lake St",
    "sg:city":"Aurora",
    "sg:classifiers":[
        {
            "category":"Retail",
            "subcategory":"Photofinishing",
            "type":"Services"
        }
    ],
    "sg:phone":"+1 630 801 0012",
    "sg:postcode":"60506",
    "sg:province":"IL",
    "sg:tags":[
        "photo",
        "finishing"
    ],
    "wof:name":"Photo Express",
    "wof:placetype":"venue"
},
  "geometry": {"coordinates":[-88.315145,41.77764],"type":"Point"}
}