{
  "type": "Feature",
  "properties": {
    "addr:full":"807 Ridge Rd Wilmette IL 60091",
    "addr:housenumber":"807",
    "addr:postcode":"60091",
    "addr:street":"Ridge Rd",
    "iso:country":"US",
    "sg:address":"807 Ridge Rd",
    "sg:city":"Wilmette",
    "sg:classifiers":[
        {
            "category":"Shopping",
            "subcategory":"Gifts & Souvenirs",
            "type":"Retail Goods"
        }
    ],
    "sg:phone":"+1 847 920 9121",
    "sg:postcode":"60091",
    "sg:province":"IL",
    "sg:tags":[
        "shop"
    ],
    "wof:name":"Annabelle's Attic",
    "wof:placetype":"venue"
},
  "geometry": {"coordinates":[-87.72252400000001,42.078029],"type":"Point"}
}