{
  "type": "Feature",
  "properties": {
    "iso:country":"US",
    "sg:address":"298 Hollywood Heights Rd",
    "sg:city":"Caseyville",
    "sg:classifiers":[
        {
            "category":"Building & Trades",
            "subcategory":"Construction",
            "type":"Services"
        }
    ],
    "sg:phone":"+1 618 345 0559",
    "sg:postcode":"62232",
    "sg:province":"IL",
    "sg:tags":[
        "house"
    ],
    "wof:name":"Johnson Construction",
    "wof:placetype":"venue"
},
  "geometry": {"coordinates":[-90.01483399999999,38.636271],"type":"Point"}
}