{
  "type": "Feature",
  "properties": {
    "iso:country":"US",
    "sg:address":"201 N Arlington Heights Rd",
    "sg:city":"Arlington Hts",
    "sg:classifiers":[
        {
            "category":"Professional",
            "subcategory":"Lawyer & Legal Services",
            "type":"Services"
        }
    ],
    "sg:phone":"+1 847 255 8900",
    "sg:postcode":"60004",
    "sg:province":"IL",
    "sg:tags":[
        "attorney"
    ],
    "wof:name":"Richard M Adler",
    "wof:placetype":"venue"
},
  "geometry": {"coordinates":[-87.980463,42.08555],"type":"Point"}
}