{
  "type": "Feature",
  "properties": {
    "iso:country":"US",
    "sg:address":"1000 1st Ave",
    "sg:city":"Rock Falls",
    "sg:classifiers":[
        {
            "category":"Shopping",
            "subcategory":"Pharmacy",
            "type":"Retail Goods"
        }
    ],
    "sg:phone":"+1   ",
    "sg:postcode":"61071",
    "sg:province":"IL",
    "sg:tags":[
        "store"
    ],
    "wof:name":"Walgreens",
    "wof:placetype":"venue"
},
  "geometry": {"coordinates":[-89.68933699999999,41.77316],"type":"Point"}
}