{
  "type": "Feature",
  "properties": {
    "addr:full":"107 E Wilson St Batavia IL 60510",
    "addr:housenumber":"107",
    "addr:postcode":"60510",
    "addr:street":"E Wilson St",
    "iso:country":"US",
    "sg:address":"107 E Wilson St",
    "sg:city":"Batavia",
    "sg:classifiers":[
        {
            "category":"Professional",
            "subcategory":"Accounting & Tax Preparation",
            "type":"Services"
        }
    ],
    "sg:phone":"+1 630 879 5500",
    "sg:postcode":"60510",
    "sg:province":"IL",
    "sg:tags":[
        "accountant"
    ],
    "wof:name":"John J Malkowski & Co CPA",
    "wof:placetype":"venue"
},
  "geometry": {"coordinates":[-88.30491499999999,41.850095],"type":"Point"}
}