{
  "type": "Feature",
  "properties": {
    "addr:full":"2580 N Monroe St Decatur IL 62526",
    "addr:housenumber":"2580",
    "addr:postcode":"62526",
    "addr:street":"N Monroe St",
    "iso:country":"US",
    "sg:address":"2580 N Monroe St",
    "sg:city":"Decatur",
    "sg:classifiers":[
        {
            "category":"Social Services",
            "subcategory":"Child Care",
            "type":"Services"
        },
        {
            "category":"Education",
            "subcategory":"Preschool",
            "type":"Public Place"
        }
    ],
    "sg:phone":"+1 217 872 6602",
    "sg:postcode":"62526",
    "sg:province":"IL",
    "sg:tags":[
        "kindergarten"
    ],
    "sg:website":"http://www.kidscastlelearningcenter.com",
    "wof:name":"Kid's Castle Learning Center",
    "wof:placetype":"venue"
},
  "geometry": {"coordinates":[-88.963685,39.869785],"type":"Point"}
}