{
  "type": "Feature",
  "properties": {
    "addr:full":"711 W North Ave Chicago IL 60610",
    "addr:housenumber":"711",
    "addr:postcode":"60610",
    "addr:street":"W North Ave",
    "iso:country":"US",
    "sg:address":"711 W North Ave",
    "sg:city":"Chicago",
    "sg:classifiers":[
        {
            "category":"Health Services",
            "subcategory":"Doctor",
            "type":"Services"
        }
    ],
    "sg:phone":"+1 312 337 1982",
    "sg:postcode":"60610",
    "sg:province":"IL",
    "sg:tags":[
        "physician",
        "surgeon",
        "pediatrics",
        "surgeons"
    ],
    "wof:name":"Ramirez, Dana, Md - Seton Family Health Ctr",
    "wof:placetype":"venue"
},
  "geometry": {"coordinates":[-87.646303,41.910952],"type":"Point"}
}