{
  "type": "Feature",
  "properties": {
    "iso:country":"US",
    "sg:address":"7637 170th St",
    "sg:city":"Tinley Park",
    "sg:classifiers":[
        {
            "category":"Freight",
            "type":"Transportation"
        }
    ],
    "sg:phone":"+1 708 633 7818",
    "sg:postcode":"60477",
    "sg:province":"IL",
    "sg:tags":[
        "arrangement"
    ],
    "wof:name":"Tinsley Transport",
    "wof:placetype":"venue"
},
  "geometry": {"coordinates":[-87.802059,41.584731],"type":"Point"}
}