{
  "type": "Feature",
  "properties": {
    "iso:country":"US",
    "sg:address":"24341 Western Ave",
    "sg:city":"Park Forest",
    "sg:classifiers":[
        {
            "category":"Retail",
            "subcategory":"Veterinary Services",
            "type":"Services"
        }
    ],
    "sg:phone":"+1 708 672 6166",
    "sg:postcode":"60466",
    "sg:province":"IL",
    "sg:tags":[
        "veterinarian"
    ],
    "wof:name":"Forest South Animal Hospital",
    "wof:placetype":"venue"
},
  "geometry": {"coordinates":[-87.67090899999999,41.447347],"type":"Point"}
}