{
  "type": "Feature",
  "properties": {
    "addr:full":"26352 W Cuba Rd Barrington IL 60010",
    "addr:housenumber":"26352",
    "addr:postcode":"60010",
    "addr:street":"W Cuba Rd",
    "iso:country":"US",
    "sg:address":"26352 W Cuba Rd",
    "sg:city":"Barrington",
    "sg:classifiers":[
        {
            "category":"Professional",
            "subcategory":"Engineering",
            "type":"Services"
        }
    ],
    "sg:phone":"+1 847 382 2830",
    "sg:postcode":"60010",
    "sg:province":"IL",
    "wof:name":"Lloyds Engineering Ltd",
    "wof:placetype":"venue"
},
  "geometry": {"coordinates":[-88.14724699999999,42.176062],"type":"Point"}
}