{
  "type": "Feature",
  "properties": {
    "iso:country":"US",
    "sg:address":"7310 Old Saint Louis Rd",
    "sg:city":"Belleville",
    "sg:classifiers":[
        {
            "category":"Autos & Motor Vehicles",
            "subcategory":"Automobile Sales",
            "type":"Retail Goods"
        }
    ],
    "sg:phone":"+1 618 222 9737",
    "sg:postcode":"62223",
    "sg:province":"IL",
    "sg:tags":[
        "car",
        "dealer"
    ],
    "wof:name":"Kennedi Auto Sales",
    "wof:placetype":"venue"
},
  "geometry": {"coordinates":[-90.053697,38.54632],"type":"Point"}
}