{
  "type": "Feature",
  "properties": {
    "iso:country":"US",
    "sg:address":"1408 Main St",
    "sg:city":"Evanston",
    "sg:classifiers":[
        {
            "category":"Professional",
            "subcategory":"Management & Consulting",
            "type":"Services"
        }
    ],
    "sg:phone":"+1 847 869 1666",
    "sg:postcode":"60202",
    "sg:province":"IL",
    "sg:tags":[
        "consultant"
    ],
    "wof:name":"Human Relations Associates",
    "wof:placetype":"venue"
},
  "geometry": {"coordinates":[-87.691607,42.033931],"type":"Point"}
}