{
  "type": "Feature",
  "properties": {
    "addr:full":"17217 Throop St Hazel Crest IL 60429",
    "addr:housenumber":"17217",
    "addr:postcode":"60429",
    "addr:street":"Throop St",
    "iso:country":"US",
    "sg:address":"17217 Throop St",
    "sg:city":"Hazel Crest",
    "sg:classifiers":[
        {
            "category":"Building & Trades",
            "subcategory":"Construction",
            "type":"Services"
        }
    ],
    "sg:phone":"+1 708 957 7360",
    "sg:postcode":"60429",
    "sg:province":"IL",
    "sg:tags":[
        "marking",
        "maintenance",
        "parking"
    ],
    "wof:name":"East Hazel Crest Public Works",
    "wof:placetype":"venue"
},
  "geometry": {"coordinates":[-87.648478,41.575761],"type":"Point"}
}