{
  "type": "Feature",
  "properties": {
    "iso:country":"US",
    "sg:address":"140 Crosat St",
    "sg:city":"La Salle",
    "sg:classifiers":[
        {
            "category":"Retail",
            "subcategory":"Auto Repair",
            "type":"Services"
        }
    ],
    "sg:phone":"+1 815 223 0598",
    "sg:postcode":"61301",
    "sg:province":"IL",
    "sg:tags":[
        "body",
        "automobile",
        "wrecker"
    ],
    "wof:name":"LA Salle Body & Fender Shop",
    "wof:placetype":"venue"
},
  "geometry": {"coordinates":[-89.089995,41.32961],"type":"Point"}
}