{
  "type": "Feature",
  "properties": {
    "iso:country":"US",
    "sg:address":"3119 W 37th Pl",
    "sg:city":"Chicago",
    "sg:classifiers":[
        {
            "category":"Building & Trades",
            "subcategory":"Landscaping Services",
            "type":"Services"
        },
        {
            "category":"Home & Garden",
            "subcategory":"Building Materials",
            "type":"Retail Goods"
        },
        {
            "category":"Building & Trades",
            "subcategory":"Construction",
            "type":"Services"
        }
    ],
    "sg:phone":"+1 773 523 5119",
    "sg:postcode":"60632",
    "sg:province":"IL",
    "sg:tags":[
        "concrete",
        "staining",
        "landscape",
        "contractor"
    ],
    "wof:name":"Chicago Mix Concrete And Landscaping Inc",
    "wof:placetype":"venue"
},
  "geometry": {"coordinates":[-87.702456,41.825366],"type":"Point"}
}