{
  "type": "Feature",
  "properties": {
    "addr:full":"900 E 162nd St Ste 204 South Holland IL 60473",
    "addr:housenumber":"900",
    "addr:postcode":"60473",
    "addr:street":"E 162Nd St Ste 204",
    "iso:country":"US",
    "sg:address":"900 E 162nd St Ste 204",
    "sg:city":"South Holland",
    "sg:classifiers":[
        {
            "category":"Professional",
            "subcategory":"Accounting & Tax Preparation",
            "type":"Services"
        }
    ],
    "sg:phone":"+1 708 331 7567",
    "sg:postcode":"60473",
    "sg:province":"IL",
    "sg:tags":[
        "accountant"
    ],
    "wof:name":"Gehrig & Homberg CPA",
    "wof:placetype":"venue"
},
  "geometry": {"coordinates":[-87.595703,41.6008],"type":"Point"}
}