{
  "type": "Feature",
  "properties": {
    "addr:full":"321 Crooked Lake Ln Lindenhurst IL 60046",
    "addr:housenumber":"321",
    "addr:postcode":"60046",
    "addr:street":"Crooked Lake Ln",
    "iso:country":"US",
    "sg:address":"321 Crooked Lake Ln",
    "sg:city":"Lindenhurst",
    "sg:classifiers":[
        {
            "category":"Wholesale",
            "subcategory":"Machinery & Supplies",
            "type":"Manufacturing & Wholesale Goods"
        }
    ],
    "sg:phone":"+1 847 265 0025",
    "sg:postcode":"60046",
    "sg:province":"IL",
    "sg:tags":[
        "distributor",
        "tanning",
        "booth",
        "free"
    ],
    "wof:name":"Magic Tan Wisconsin LLC",
    "wof:placetype":"venue"
},
  "geometry": {"coordinates":[-88.056854,42.420903],"type":"Point"}
}