{
  "type": "Feature",
  "properties": {
    "iso:country":"US",
    "sg:address":"705 W Belden Ave",
    "sg:city":"Chicago",
    "sg:classifiers":[
        {
            "category":"Food & Beverages",
            "subcategory":"Candy",
            "type":"Retail Goods"
        },
        {
            "category":"Bakery",
            "type":"Food & Drink"
        }
    ],
    "sg:phone":"+1 773 404 2253",
    "sg:postcode":"60614",
    "sg:province":"IL",
    "sg:tags":[
        "dessert"
    ],
    "sg:website":"www.swirlzcupcakes.com/",
    "wof:name":"Swirlz Cupcakes",
    "wof:placetype":"venue"
},
  "geometry": {"coordinates":[-87.646469,41.923462],"type":"Point"}
}