{
  "type": "Feature",
  "properties": {
    "iso:country":"US",
    "sg:address":"1307 Carrington Ct",
    "sg:city":"Quincy",
    "sg:classifiers":[
        {
            "category":"Real Estate",
            "subcategory":"Real Estate Agent",
            "type":"Services"
        }
    ],
    "sg:phone":"+1 217 222 3473",
    "sg:postcode":"62305",
    "sg:province":"IL",
    "wof:name":"Cardinal Realty",
    "wof:placetype":"venue"
},
  "geometry": {"coordinates":[-91.396237,39.974579],"type":"Point"}
}