{
  "type": "Feature",
  "properties": {
    "iso:country":"US",
    "sg:address":"1200 Shermer Rd",
    "sg:city":"Northbrook",
    "sg:classifiers":[
        {
            "category":"Professional",
            "subcategory":"Employment Agencies",
            "type":"Services"
        }
    ],
    "sg:phone":"+1 847 291 4141",
    "sg:postcode":"60062",
    "sg:province":"IL",
    "sg:tags":[
        "firm",
        "consultant",
        "search",
        "executive"
    ],
    "sg:website":"www.breckenridgepartners.com",
    "wof:name":"Breckenridge Partners",
    "wof:placetype":"venue"
},
  "geometry": {"coordinates":[-87.824139,42.131124],"type":"Point"}
}