{
  "type": "Feature",
  "properties": {
    "addr:full":"2065 E 95th Pl Chicago IL 60617",
    "addr:housenumber":"2065",
    "addr:postcode":"60617",
    "addr:street":"E 95Th Pl",
    "iso:country":"US",
    "sg:address":"2065 E 95th Pl",
    "sg:city":"Chicago",
    "sg:classifiers":[
        {
            "category":"Restaurant",
            "type":"Food & Drink"
        },
        {
            "category":"Ice Cream",
            "type":"Food & Drink"
        }
    ],
    "sg:phone":"+1 773 978 3211",
    "sg:postcode":"60617",
    "sg:province":"IL",
    "sg:tags":[
        "frozen",
        "dessert"
    ],
    "sg:website":"http://www.baskinrobbins.com",
    "wof:name":"Baskin Robbins",
    "wof:placetype":"venue"
},
  "geometry": {"coordinates":[-87.574068,41.721514],"type":"Point"}
}