{
  "type": "Feature",
  "properties": {
    "iso:country":"US",
    "sg:address":"1877 W Downer Pl",
    "sg:city":"Aurora",
    "sg:classifiers":[
        {
            "category":"Health Services",
            "subcategory":"Health Practitioner",
            "type":"Services"
        }
    ],
    "sg:phone":"+1 630 906 5120",
    "sg:postcode":"60506",
    "sg:province":"IL",
    "wof:name":"Mary S Psyd Rudisill",
    "wof:placetype":"venue"
},
  "geometry": {"coordinates":[-88.362446,41.761906],"type":"Point"}
}