{
  "type": "Feature",
  "properties": {
    "iso:country":"US",
    "sg:address":"2223 Half Day Rd",
    "sg:city":"Bannockburn",
    "sg:classifiers":[
        {
            "category":"Professional",
            "subcategory":"Business Services",
            "type":"Services"
        }
    ],
    "sg:phone":"+1 847 948 5335",
    "sg:postcode":"60015",
    "sg:province":"IL",
    "sg:tags":[
        "interior",
        "consultant",
        "design",
        "decorator"
    ],
    "wof:name":"Sports Interior Inc",
    "wof:placetype":"venue"
},
  "geometry": {"coordinates":[-87.883421,42.20012],"type":"Point"}
}