{
  "type": "Feature",
  "properties": {
    "addr:full":"1316 Wisconsin St Joliet IL 60432",
    "addr:housenumber":"1316",
    "addr:postcode":"60432",
    "addr:street":"Wisconsin St",
    "iso:country":"US",
    "sg:address":"1316 Wisconsin St",
    "sg:city":"Joliet",
    "sg:classifiers":[
        {
            "category":"Organizations",
            "subcategory":"Religious Organization",
            "type":"Services"
        }
    ],
    "sg:phone":"+1 815 722 0898",
    "sg:postcode":"60432",
    "sg:province":"IL",
    "sg:tags":[
        "church"
    ],
    "wof:name":"Forest Park Church Inc",
    "wof:placetype":"venue"
},
  "geometry": {"coordinates":[-88.048632,41.544568],"type":"Point"}
}