{
  "type": "Feature",
  "properties": {
    "addr:full":"3300 W Flournoy Street Chicago IL 60624",
    "addr:housenumber":"3300",
    "addr:postcode":"60624",
    "addr:street":"W Flournoy Street",
    "iso:country":"US",
    "sg:address":"3300 W Flournoy Street",
    "sg:city":"Chicago",
    "sg:classifiers":[
        {
            "category":"Building & Trades",
            "subcategory":"Construction",
            "type":"Services"
        }
    ],
    "sg:phone":"+1 773 826 5625",
    "sg:postcode":"60624",
    "sg:province":"IL",
    "sg:tags":[
        "contractor"
    ],
    "wof:name":"Coco Moe Joe Construction",
    "wof:placetype":"venue"
},
  "geometry": {"coordinates":[-87.708446,41.872854],"type":"Point"}
}