{
  "type": "Feature",
  "properties": {
    "iso:country":"US",
    "sg:address":"5244 N Sheridan Rd",
    "sg:city":"Chicago",
    "sg:classifiers":[
        {
            "category":"Personal",
            "subcategory":"Massage",
            "type":"Services"
        }
    ],
    "sg:phone":"+1 773 989 9911",
    "sg:postcode":"60640",
    "sg:province":"IL",
    "sg:website":"www.bodyworkstudiochicagomassage...",
    "wof:name":"Bodywork Studio",
    "wof:placetype":"venue"
},
  "geometry": {"coordinates":[-87.6549,41.9781],"type":"Point"}
}