{
  "type": "Feature",
  "properties": {
    "addr:full":"134 N la Salle St Chicago IL 60602",
    "addr:housenumber":"134",
    "addr:postcode":"60602",
    "addr:street":"N La Salle St",
    "iso:country":"US",
    "sg:address":"134 N la Salle St",
    "sg:city":"Chicago",
    "sg:classifiers":[
        {
            "category":"Utilities",
            "subcategory":"Mobile Phone",
            "type":"Services"
        },
        {
            "category":"Coffee & Tea",
            "type":"Food & Drink"
        }
    ],
    "sg:phone":"+1 312 977 9701",
    "sg:postcode":"60602",
    "sg:province":"IL",
    "sg:tags":[
        "wi-fi",
        "espresso",
        "hotspot",
        "restaurant"
    ],
    "wof:name":"Lavazza Co.",
    "wof:placetype":"venue"
},
  "geometry": {"coordinates":[-87.632515,41.884084],"type":"Point"}
}