{
  "type": "Feature",
  "properties": {
    "iso:country":"US",
    "sg:address":"317 S Jackson St",
    "sg:city":"Batavia",
    "sg:classifiers":[
        {
            "category":"Building & Trades",
            "subcategory":"Construction",
            "type":"Services"
        }
    ],
    "sg:phone":"+1 630 879 8645",
    "sg:postcode":"60510",
    "sg:province":"IL",
    "sg:tags":[
        "hanging",
        "contractor"
    ],
    "wof:name":"Sury Painting Inc",
    "wof:placetype":"venue"
},
  "geometry": {"coordinates":[-88.318217,41.845601],"type":"Point"}
}