{
  "type": "Feature",
  "properties": {
    "addr:full":"607 E Oakton St Des Plaines IL 60018",
    "addr:housenumber":"607",
    "addr:postcode":"60018",
    "addr:street":"E Oakton St",
    "iso:country":"US",
    "sg:address":"607 E Oakton St",
    "sg:city":"Des Plaines",
    "sg:classifiers":[
        {
            "category":"Retail",
            "subcategory":"Auto Repair",
            "type":"Services"
        }
    ],
    "sg:phone":"+1 847 827 0273",
    "sg:postcode":"60018",
    "sg:province":"IL",
    "sg:tags":[
        "repairing",
        "automobile"
    ],
    "wof:name":"Elmer's Service",
    "wof:placetype":"venue"
},
  "geometry": {"coordinates":[-87.90792999999999,42.023383],"type":"Point"}
}