{
  "type": "Feature",
  "properties": {
    "addr:full":"6988 Milton Rd Rockford IL 61109",
    "addr:housenumber":"6988",
    "addr:postcode":"61109",
    "addr:street":"Milton Rd",
    "iso:country":"US",
    "sg:address":"6988 Milton Rd",
    "sg:city":"Rockford",
    "sg:classifiers":[
        {
            "category":"Building & Trades",
            "subcategory":"Construction",
            "type":"Services"
        }
    ],
    "sg:phone":"+1 815 874 9369",
    "sg:postcode":"61109",
    "sg:province":"IL",
    "sg:tags":[
        "contractor"
    ],
    "wof:name":"Total Roofing By Beck",
    "wof:placetype":"venue"
},
  "geometry": {"coordinates":[-89.07970299999999,42.181003],"type":"Point"}
}