{
  "type": "Feature",
  "properties": {
    "addr:full":"5045 N Sheridan Road Chicago IL 60640",
    "addr:housenumber":"5045",
    "addr:postcode":"60640",
    "addr:street":"N Sheridan Road",
    "iso:country":"US",
    "sg:address":"5045 N Sheridan Road",
    "sg:city":"Chicago",
    "sg:classifiers":[
        {
            "category":"Shopping",
            "subcategory":"Mobile Phones",
            "type":"Retail Goods"
        }
    ],
    "sg:phone":"+1 773 271 1888",
    "sg:postcode":"60640",
    "sg:province":"IL",
    "wof:name":"Laser Tech Studio",
    "wof:placetype":"venue"
},
  "geometry": {"coordinates":[-87.655097,41.974791],"type":"Point"}
}