{
  "type": "Feature",
  "properties": {
    "iso:country":"US",
    "sg:address":"11 N Skokie Hwy",
    "sg:city":"Lake Bluff",
    "sg:classifiers":[
        {
            "category":"Social Services",
            "type":"Services"
        }
    ],
    "sg:phone":"+1 847 295 8616",
    "sg:postcode":"60044",
    "sg:province":"IL",
    "sg:tags":[
        "counselor",
        "marriage",
        "family"
    ],
    "wof:name":"Family Counseling Svc",
    "wof:placetype":"venue"
},
  "geometry": {"coordinates":[-87.870449,42.281334],"type":"Point"}
}