{
  "type": "Feature",
  "properties": {
    "addr:full":"2222 W Diversey Ave Chicago IL 60647",
    "addr:housenumber":"2222",
    "addr:postcode":"60647",
    "addr:street":"W Diversey Ave",
    "iso:country":"US",
    "sg:address":"2222 W Diversey Ave",
    "sg:city":"Chicago",
    "sg:classifiers":[
        {
            "category":"Manufacturing",
            "subcategory":"Printing",
            "type":"Manufacturing & Wholesale Goods"
        }
    ],
    "sg:phone":"+1 773 772 9406",
    "sg:postcode":"60647",
    "sg:province":"IL",
    "sg:tags":[
        "retail",
        "promotional"
    ],
    "wof:name":"Online Imprint Inc",
    "wof:placetype":"venue"
},
  "geometry": {"coordinates":[-87.683666,41.932293],"type":"Point"}
}