{
  "type": "Feature",
  "properties": {
    "addr:full":"1600 Wabash Ave Springfield IL 62704",
    "addr:housenumber":"1600",
    "addr:postcode":"62704",
    "addr:street":"Wabash Ave",
    "iso:country":"US",
    "sg:address":"1600 Wabash Ave",
    "sg:city":"Springfield",
    "sg:classifiers":[
        {
            "category":"Home & Garden",
            "subcategory":"Hardware",
            "type":"Retail Goods"
        }
    ],
    "sg:phone":"+1 217 787 5100",
    "sg:postcode":"62704",
    "sg:province":"IL",
    "sg:tags":[
        "store"
    ],
    "sg:website":"http://www.acesetsthepace.com",
    "wof:name":"Ace Hardware",
    "wof:placetype":"venue"
},
  "geometry": {"coordinates":[-89.68047300000001,39.764172],"type":"Point"}
}