{
  "type": "Feature",
  "properties": {
    "addr:full":"418 E Jackson St Macomb IL 61455",
    "addr:housenumber":"418",
    "addr:postcode":"61455",
    "addr:street":"E Jackson St",
    "iso:country":"US",
    "sg:address":"418 E Jackson St",
    "sg:city":"Macomb",
    "sg:classifiers":[
        {
            "category":"Professional",
            "subcategory":"Business Services",
            "type":"Services"
        }
    ],
    "sg:phone":"+1 309 837 1872",
    "sg:postcode":"61455",
    "sg:province":"IL",
    "wof:name":"Renegade Dancers",
    "wof:placetype":"venue"
},
  "geometry": {"coordinates":[-90.667034,40.458776],"type":"Point"}
}