{
  "type": "Feature",
  "properties": {
    "iso:country":"US",
    "sg:address":"223 Farnham Ln",
    "sg:city":"Wheaton",
    "sg:classifiers":[
        {
            "category":"Professional",
            "subcategory":"Management & Consulting",
            "type":"Services"
        }
    ],
    "sg:phone":"+1 630 260 0787",
    "sg:postcode":"60187",
    "sg:province":"IL",
    "wof:name":"Fiduciary Training Institute",
    "wof:placetype":"venue"
},
  "geometry": {"coordinates":[-88.102216,41.849902],"type":"Point"}
}