{
  "type": "Feature",
  "properties": {
    "addr:full":"721 W Atlantic Ave Waukegan IL 60085",
    "addr:housenumber":"721",
    "addr:postcode":"60085",
    "addr:street":"W Atlantic Ave",
    "iso:country":"US",
    "sg:address":"721 W Atlantic Ave",
    "sg:city":"Waukegan",
    "sg:classifiers":[
        {
            "category":"Health Services",
            "subcategory":"Health Practitioner",
            "type":"Services"
        }
    ],
    "sg:phone":"+1 847 263 8958",
    "sg:postcode":"60085",
    "sg:province":"IL",
    "sg:tags":[
        "nurse",
        "registry"
    ],
    "wof:name":"Lisa Cianciolo Rn Lnc",
    "wof:placetype":"venue"
},
  "geometry": {"coordinates":[-87.840008,42.381923],"type":"Point"}
}