{
  "type": "Feature",
  "properties": {
    "iso:country":"US",
    "sg:address":"3344 N Orange Ave",
    "sg:city":"Chicago",
    "sg:classifiers":[
        {
            "category":"Building & Trades",
            "subcategory":"Plumbing",
            "type":"Services"
        },
        {
            "category":"Home & Garden",
            "subcategory":"Hardware",
            "type":"Retail Goods"
        }
    ],
    "sg:phone":"+1 773 804 0171",
    "sg:postcode":"60634",
    "sg:province":"IL",
    "sg:tags":[
        "filtration",
        "supply",
        "work",
        "purification",
        "water",
        "equipment"
    ],
    "wof:name":"Royal Prestige Of Chicago",
    "wof:placetype":"venue"
},
  "geometry": {"coordinates":[-87.82390100000001,41.940276],"type":"Point"}
}