{
  "type": "Feature",
  "properties": {
    "addr:full":"10600 W Higgins Rd Des Plaines IL 60018",
    "addr:housenumber":"10600",
    "addr:postcode":"60018",
    "addr:street":"W Higgins Rd Des",
    "iso:country":"US",
    "sg:address":"10600 W Higgins Rd",
    "sg:city":"Des Plaines",
    "sg:classifiers":[
        {
            "category":"Manufacturing",
            "subcategory":"Chemicals & Compounds",
            "type":"Manufacturing & Wholesale Goods"
        }
    ],
    "sg:phone":"+1 847 390 1998",
    "sg:postcode":"60018",
    "sg:province":"IL",
    "sg:tags":[
        "preparation",
        "toilet",
        "mfg"
    ],
    "wof:name":"Zotos International Inc",
    "wof:placetype":"venue"
},
  "geometry": {"coordinates":[-87.890418,41.999578],"type":"Point"}
}