{
  "type": "Feature",
  "properties": {
    "addr:full":"5900 N Sheridan Rd Apt 2F Chicago IL 60660",
    "addr:housenumber":"5900",
    "addr:postcode":"60660",
    "addr:street":"N Sheridan Rd Apt 2F",
    "iso:country":"US",
    "sg:address":"5900 N Sheridan Rd Apt 2F",
    "sg:city":"Chicago",
    "sg:classifiers":[
        {
            "category":"Home & Garden",
            "subcategory":"Home Furnishings",
            "type":"Retail Goods"
        }
    ],
    "sg:phone":"+1 773 931 5123",
    "sg:postcode":"60660",
    "sg:province":"IL",
    "sg:tags":[
        "candle"
    ],
    "wof:name":"Crafts-N-Things",
    "wof:placetype":"venue"
},
  "geometry": {"coordinates":[-87.655344,41.989453],"type":"Point"}
}