{
  "type": "Feature",
  "properties": {
    "iso:country":"US",
    "sg:address":"630 Winnebago Trl",
    "sg:city":"Batavia",
    "sg:classifiers":[
        {
            "category":"Building & Trades",
            "subcategory":"Plumbing",
            "type":"Services"
        }
    ],
    "sg:phone":"+1 630 482 2951",
    "sg:postcode":"60510",
    "sg:province":"IL",
    "sg:tags":[
        "contractor"
    ],
    "wof:name":"Enviro Mechanical",
    "wof:placetype":"venue"
},
  "geometry": {"coordinates":[-88.32894899999999,41.861382],"type":"Point"}
}