{
  "type": "Feature",
  "properties": {
    "iso:country":"US",
    "sg:address":"128 James St",
    "sg:city":"Geneva",
    "sg:classifiers":[
        {
            "category":"Banks & Credit Unions",
            "subcategory":"Investment Brokerage",
            "type":"Services"
        }
    ],
    "sg:phone":"+1 630 232 2204",
    "sg:postcode":"60134",
    "sg:province":"IL",
    "sg:tags":[
        "security"
    ],
    "wof:name":"Edward Jones 12954",
    "wof:placetype":"venue"
},
  "geometry": {"coordinates":[-88.30645699999999,41.886552],"type":"Point"}
}