{
  "type": "Feature",
  "properties": {
    "addr:full":"20 Wisner St Park Ridge IL 60068",
    "addr:housenumber":"20",
    "addr:postcode":"60068",
    "addr:street":"Wisner St",
    "iso:country":"US",
    "sg:address":"20 Wisner St",
    "sg:city":"Park Ridge",
    "sg:classifiers":[
        {
            "category":"Professional",
            "subcategory":"Management & Consulting",
            "type":"Services"
        }
    ],
    "sg:phone":"+1 847 518 0340",
    "sg:postcode":"60068",
    "sg:province":"IL",
    "sg:tags":[
        "business"
    ],
    "wof:name":"Jack Taddeo Communications",
    "wof:placetype":"venue"
},
  "geometry": {"coordinates":[-87.82477900000001,42.013316],"type":"Point"}
}