{
  "type": "Feature",
  "properties": {
    "addr:full":"2518 Co Rd 2600 E Penfield IL 61862",
    "addr:housenumber":"2518;2600 e",
    "addr:postcode":"61862",
    "addr:street":"Co Rd",
    "iso:country":"US",
    "sg:address":"2518 Co Rd 2600 E",
    "sg:city":"Penfield",
    "sg:phone":"+1 217 595 5528",
    "sg:postcode":"61862",
    "sg:province":"IL",
    "sg:tags":[
        "farm",
        "corn"
    ],
    "wof:name":"Gary Hovelin",
    "wof:placetype":"venue"
},
  "geometry": {"coordinates":[-87.967477,40.251936],"type":"Point"}
}