{
  "type": "Feature",
  "properties": {
    "iso:country":"US",
    "sg:address":"11800 S 75th Ave",
    "sg:city":"Palos Heights",
    "sg:classifiers":[
        {
            "category":"Professional",
            "subcategory":"Lawyer & Legal Services",
            "type":"Services"
        }
    ],
    "sg:phone":"+1 708 923 6340",
    "sg:postcode":"60463",
    "sg:province":"IL",
    "sg:tags":[
        "divorce",
        "law",
        "family"
    ],
    "wof:name":"Schmit Robert J Lwyr",
    "wof:placetype":"venue"
},
  "geometry": {"coordinates":[-87.804199,41.676701],"type":"Point"}
}