{
  "type": "Feature",
  "properties": {
    "addr:full":"2545 W Rascher Avenue Chicago IL 60625",
    "addr:housenumber":"2545",
    "addr:postcode":"60625",
    "addr:street":"W Rascher Avenue",
    "iso:country":"US",
    "sg:address":"2545 W Rascher Avenue",
    "sg:city":"Chicago",
    "sg:classifiers":[
        {
            "category":"Taxi",
            "type":"Transportation"
        }
    ],
    "sg:phone":"+1 773 293 2761",
    "sg:postcode":"60625",
    "sg:province":"IL",
    "wof:name":"Basko Cab Company",
    "wof:placetype":"venue"
},
  "geometry": {"coordinates":[-87.69333,41.980266],"type":"Point"}
}