{
  "type": "Feature",
  "properties": {
    "iso:country":"US",
    "sg:address":"2395 Greenleaf Ave",
    "sg:city":"Elk Grove Village",
    "sg:classifiers":[
        {
            "category":"Manufacturing",
            "subcategory":"Metals",
            "type":"Manufacturing & Wholesale Goods"
        }
    ],
    "sg:phone":"+1 847 439 5321",
    "sg:postcode":"60007",
    "sg:province":"IL",
    "sg:tags":[
        "sheet",
        "mfg"
    ],
    "wof:name":"National Metal Fabricators LLC",
    "wof:placetype":"venue"
},
  "geometry": {"coordinates":[-87.94587199999999,42.004172],"type":"Point"}
}