{
  "type": "Feature",
  "properties": {
    "addr:full":"238 W 33rd St Chicago IL 60616",
    "addr:housenumber":"238",
    "addr:postcode":"60616",
    "addr:street":"W 33Rd St",
    "iso:country":"US",
    "sg:address":"238 W 33rd St",
    "sg:city":"Chicago",
    "sg:classifiers":[
        {
            "category":"Bars & Pubs",
            "subcategory":"Sports Bar",
            "type":"Food & Drink"
        }
    ],
    "sg:phone":"+1 312 225 7333",
    "sg:postcode":"60616",
    "sg:province":"IL",
    "wof:name":"Turtle Bar and Grill",
    "wof:placetype":"venue"
},
  "geometry": {"coordinates":[-87.633145,41.83459],"type":"Point"}
}