{
  "type": "Feature",
  "properties": {
    "iso:country":"US",
    "sg:address":"712 S Maple St",
    "sg:city":"Staunton",
    "sg:classifiers":[
        {
            "category":"Building & Trades",
            "subcategory":"Construction",
            "type":"Services"
        }
    ],
    "sg:phone":"+1 618 635 5682",
    "sg:postcode":"62088",
    "sg:province":"IL",
    "sg:tags":[
        "carpentry",
        "contractor"
    ],
    "wof:name":"McDowells Custom Carpentry",
    "wof:placetype":"venue"
},
  "geometry": {"coordinates":[-89.784592,39.006379],"type":"Point"}
}