{
  "type": "Feature",
  "properties": {
    "addr:full":"19651 Beechnut Dr Mokena IL 60448",
    "addr:housenumber":"19651",
    "addr:postcode":"60448",
    "addr:street":"Beechnut Dr",
    "iso:country":"US",
    "sg:address":"19651 Beechnut Dr",
    "sg:city":"Mokena",
    "sg:classifiers":[
        {
            "category":"Education",
            "subcategory":"School",
            "type":"Public Place"
        }
    ],
    "sg:phone":"+1 708 479 2106",
    "sg:postcode":"60448",
    "sg:province":"IL",
    "wof:name":"Arbury Hills Elementary School",
    "wof:placetype":"venue"
},
  "geometry": {"coordinates":[-87.847404,41.532401],"type":"Point"}
}