{
  "type": "Feature",
  "properties": {
    "addr:full":"322 Illinois Ave Glenwood IL 60425",
    "addr:housenumber":"322",
    "addr:postcode":"60425",
    "addr:street":"Illinois Ave",
    "iso:country":"US",
    "sg:address":"322 Illinois Ave",
    "sg:city":"Glenwood",
    "sg:classifiers":[
        {
            "category":"Wholesale",
            "subcategory":"Durable Goods & Equipment",
            "type":"Manufacturing & Wholesale Goods"
        }
    ],
    "sg:phone":"+1 708 957 9926",
    "sg:postcode":"60425",
    "sg:province":"IL",
    "sg:tags":[
        "representative",
        "manufacturer"
    ],
    "wof:name":"Applications For Mfg Inc",
    "wof:placetype":"venue"
},
  "geometry": {"coordinates":[-87.640584,41.555229],"type":"Point"}
}