{
  "type": "Feature",
  "properties": {
    "iso:country":"US",
    "sg:address":"215 W Ontario",
    "sg:city":"Chicago",
    "sg:classifiers":[
        {
            "category":"Bars & Pubs",
            "subcategory":"Lounge",
            "type":"Food & Drink"
        }
    ],
    "sg:phone":"+1 773 456 9517",
    "sg:postcode":"60654",
    "sg:province":"IL",
    "sg:website":"tzarchicago.com",
    "wof:name":"Tzar Ultra Lounge",
    "wof:placetype":"venue"
},
  "geometry": {"coordinates":[-87.63483600000001,41.892943],"type":"Point"}
}