{
  "type": "Feature",
  "properties": {
    "iso:country":"US",
    "sg:address":"8940 Moody Ave",
    "sg:city":"Oak Lawn",
    "sg:classifiers":[
        {
            "category":"Professional",
            "type":"Services"
        }
    ],
    "sg:phone":"+1 708 598 1220",
    "sg:postcode":"60453",
    "sg:province":"IL",
    "sg:tags":[
        "establishment"
    ],
    "wof:name":"Hafez El Ramahi",
    "wof:placetype":"venue"
},
  "geometry": {"coordinates":[-87.774148,41.72761],"type":"Point"}
}