{
  "type": "Feature",
  "properties": {
    "iso:country":"US",
    "sg:address":"103 Grayson Rd",
    "sg:city":"Eldorado",
    "sg:classifiers":[
        {
            "category":"Organizations",
            "subcategory":"Religious Organization",
            "type":"Services"
        }
    ],
    "sg:phone":"+1 618 273 8172",
    "sg:postcode":"62930",
    "sg:province":"IL",
    "sg:tags":[
        "church"
    ],
    "wof:name":"Church Of Jesus Christ Of Lds",
    "wof:placetype":"venue"
},
  "geometry": {"coordinates":[-88.422692,37.799483],"type":"Point"}
}