{
  "type": "Feature",
  "properties": {
    "iso:country":"US",
    "sg:address":"10349 Franklin Ave",
    "sg:city":"Franklin Park",
    "sg:classifiers":[
        {
            "category":"Manufacturing",
            "subcategory":"Paper Products",
            "type":"Manufacturing & Wholesale Goods"
        }
    ],
    "sg:phone":"+1 847 671 0060",
    "sg:postcode":"60131",
    "sg:province":"IL",
    "sg:tags":[
        "mfg",
        "bobbin",
        "plastic"
    ],
    "wof:name":"T J Assemblies Inc",
    "wof:placetype":"venue"
},
  "geometry": {"coordinates":[-87.882941,41.940342],"type":"Point"}
}