{
  "type": "Feature",
  "properties": {
    "iso:country":"US",
    "sg:address":"11600 Francis Rd",
    "sg:city":"Mokena",
    "sg:classifiers":[
        {
            "category":"Education",
            "subcategory":"Special Training",
            "type":"Public Place"
        }
    ],
    "sg:phone":"+1 708 479 0028",
    "sg:postcode":"60448",
    "sg:province":"IL",
    "sg:tags":[
        "educational"
    ],
    "wof:name":"Trinity Services Mokena Center",
    "wof:placetype":"venue"
},
  "geometry": {"coordinates":[-87.899886,41.527414],"type":"Point"}
}