{
  "type": "Feature",
  "properties": {
    "addr:full":"10336 S Western Avenue Chicago IL 60643",
    "addr:housenumber":"10336",
    "addr:postcode":"60643",
    "addr:street":"S Western Avenue",
    "iso:country":"US",
    "sg:address":"10336 S Western Avenue",
    "sg:city":"Chicago",
    "sg:classifiers":[
        {
            "category":"Banks & Credit Unions",
            "subcategory":"Atm",
            "type":"Services"
        }
    ],
    "sg:phone":"+1 312 541 9052",
    "sg:postcode":"60643",
    "sg:province":"IL",
    "sg:tags":[
        "bankruptcy"
    ],
    "wof:name":"Feld Neal Attorney At Law",
    "wof:placetype":"venue"
},
  "geometry": {"coordinates":[-87.681663,41.705211],"type":"Point"}
}