{
  "type": "Feature",
  "properties": {
    "addr:full":"1120 Industrial St Danville IL 61832",
    "addr:housenumber":"1120",
    "addr:postcode":"61832",
    "addr:street":"Industrial St",
    "iso:country":"US",
    "sg:address":"1120 Industrial St",
    "sg:city":"Danville",
    "sg:classifiers":[
        {
            "category":"Manufacturing",
            "subcategory":"Tools & Machinery",
            "type":"Manufacturing & Wholesale Goods"
        }
    ],
    "sg:phone":"+1 217 431 3029",
    "sg:postcode":"61832",
    "sg:province":"IL",
    "sg:tags":[
        "machine",
        "shop"
    ],
    "wof:name":"Dines Machine & Mfg",
    "wof:placetype":"venue"
},
  "geometry": {"coordinates":[-87.605204,40.138475],"type":"Point"}
}