{
  "type": "Feature",
  "properties": {
    "addr:full":"1311 Palmer St Downers Grove IL 60516",
    "addr:housenumber":"1311",
    "addr:postcode":"60516",
    "addr:street":"Palmer St",
    "iso:country":"US",
    "sg:address":"1311 Palmer St",
    "sg:city":"Downers Grove",
    "sg:classifiers":[
        {
            "category":"Wholesale",
            "subcategory":"Machinery & Supplies",
            "type":"Manufacturing & Wholesale Goods"
        }
    ],
    "sg:phone":"+1 630 322 8550",
    "sg:postcode":"60516",
    "sg:province":"IL",
    "sg:tags":[
        "equipment",
        "transportation"
    ],
    "wof:name":"Satellite Office",
    "wof:placetype":"venue"
},
  "geometry": {"coordinates":[-88.01634199999999,41.767624],"type":"Point"}
}