{
  "type": "Feature",
  "properties": {
    "addr:full":"15000 S Cicero Ave Ste 202 Oak Forest IL 60452",
    "addr:housenumber":"15000",
    "addr:postcode":"60452",
    "addr:street":"S Cicero Ave Ste 202",
    "iso:country":"US",
    "sg:address":"15000 S Cicero Ave Ste 202",
    "sg:city":"Oak Forest",
    "sg:classifiers":[
        {
            "category":"Banks & Credit Unions",
            "subcategory":"Investment Brokerage",
            "type":"Services"
        },
        {
            "category":"Banks & Credit Unions",
            "subcategory":"Financial Services",
            "type":"Services"
        }
    ],
    "sg:phone":"+1 708 478 0939",
    "sg:postcode":"60452",
    "sg:province":"IL",
    "sg:tags":[
        "investing",
        "advising"
    ],
    "sg:website":"ameripriseadvisors.com",
    "wof:name":"Ameriprise Financial Advisors",
    "wof:placetype":"venue"
},
  "geometry": {"coordinates":[-87.737762,41.619538],"type":"Point"}
}