{
  "type": "Feature",
  "properties": {
    "addr:full":"845 E Rand Rd Arlington Hts IL 60004",
    "addr:housenumber":"845",
    "addr:postcode":"60004",
    "addr:street":"E Rand Rd",
    "iso:country":"US",
    "sg:address":"845 E Rand Rd",
    "sg:city":"Arlington Hts",
    "sg:classifiers":[
        {
            "category":"Health Services",
            "subcategory":"Optometrist",
            "type":"Services"
        }
    ],
    "sg:phone":"+1 847 670 0790",
    "sg:postcode":"60004",
    "sg:province":"IL",
    "wof:name":"Doc's Eyeglasses & Contacts",
    "wof:placetype":"venue"
},
  "geometry": {"coordinates":[-87.972206,42.106932],"type":"Point"}
}