{
  "type": "Feature",
  "properties": {
    "addr:full":"550 Heather Ln Frankfort IL 60423",
    "addr:housenumber":"550",
    "addr:postcode":"60423",
    "addr:street":"Heather Ln",
    "iso:country":"US",
    "sg:address":"550 Heather Ln",
    "sg:city":"Frankfort",
    "sg:classifiers":[
        {
            "category":"Building & Trades",
            "subcategory":"Construction",
            "type":"Services"
        }
    ],
    "sg:phone":"+1 815 469 4574",
    "sg:postcode":"60423",
    "sg:province":"IL",
    "sg:tags":[
        "house"
    ],
    "wof:name":"Katula Construction & Rmdlg",
    "wof:placetype":"venue"
},
  "geometry": {"coordinates":[-87.80323,41.493042],"type":"Point"}
}