{
  "type": "Feature",
  "properties": {
    "iso:country":"US",
    "sg:address":"25W253 Warrenville Rd",
    "sg:city":"Wheaton",
    "sg:classifiers":[
        {
            "category":"Sports & Exercise",
            "subcategory":"Golf",
            "type":"Entertainment"
        }
    ],
    "sg:phone":"+1 630 665 2988",
    "sg:postcode":"60187",
    "sg:province":"IL",
    "wof:name":"Chicago Golf Club",
    "wof:placetype":"venue"
},
  "geometry": {"coordinates":[-88.123683,41.846762],"type":"Point"}
}