{
  "type": "Feature",
  "properties": {
    "addr:full":"13055 W Pauling Rd Manhattan IL 60442",
    "addr:housenumber":"13055",
    "addr:postcode":"60442",
    "addr:street":"W Pauling Rd",
    "iso:country":"US",
    "sg:address":"13055 W Pauling Rd",
    "sg:city":"Manhattan",
    "sg:classifiers":[
        {
            "category":"Utilities",
            "subcategory":"Telephone",
            "type":"Services"
        }
    ],
    "sg:phone":"+1 815 478 5519",
    "sg:postcode":"60442",
    "sg:province":"IL",
    "sg:tags":[
        "communication"
    ],
    "wof:name":"Cygnus Telecommunications Corporation",
    "wof:placetype":"venue"
},
  "geometry": {"coordinates":[-87.928038,41.395725],"type":"Point"}
}