{
  "type": "Feature",
  "properties": {
    "addr:full":"7857 Ogden Ave Lyons IL 60534",
    "addr:housenumber":"7857",
    "addr:postcode":"60534",
    "addr:street":"Ogden Ave",
    "iso:country":"US",
    "sg:address":"7857 Ogden Ave",
    "sg:city":"Lyons",
    "sg:classifiers":[
        {
            "category":"Retail",
            "subcategory":"Auto Repair",
            "type":"Services"
        }
    ],
    "sg:phone":"+1 708 442 6022",
    "sg:postcode":"60534",
    "sg:province":"IL",
    "sg:tags":[
        "body",
        "shop",
        "automobile",
        "painting",
        "repairing"
    ],
    "wof:name":"Gutierrez Body Shop",
    "wof:placetype":"venue"
},
  "geometry": {"coordinates":[-87.81710099999999,41.819901],"type":"Point"}
}