{
  "type": "Feature",
  "properties": {
    "iso:country":"US",
    "sg:address":"105 E Main St",
    "sg:city":"Barrington",
    "sg:classifiers":[
        {
            "category":"Manufacturing",
            "subcategory":"Jewelry",
            "type":"Manufacturing & Wholesale Goods"
        }
    ],
    "sg:phone":"+1 847 381 7790",
    "sg:postcode":"60010",
    "sg:province":"IL",
    "wof:name":"Michal's Jewelry",
    "wof:placetype":"venue"
},
  "geometry": {"coordinates":[-88.13531399999999,42.154132],"type":"Point"}
}