{
  "type": "Feature",
  "properties": {
    "addr:full":"705 Bloomington Rd Champaign IL 61820",
    "addr:housenumber":"705",
    "addr:postcode":"61820",
    "addr:street":"Bloomington Rd",
    "iso:country":"US",
    "sg:address":"705 Bloomington Rd",
    "sg:city":"Champaign",
    "sg:classifiers":[
        {
            "category":"Education",
            "subcategory":"School",
            "type":"Public Place"
        }
    ],
    "sg:phone":"+1 217 351 3993",
    "sg:postcode":"61820",
    "sg:province":"IL",
    "sg:tags":[
        "high",
        "middle",
        "elementary"
    ],
    "wof:name":"Schools Public",
    "wof:placetype":"venue"
},
  "geometry": {"coordinates":[-88.25337500000001,40.129982],"type":"Point"}
}