{
  "type": "Feature",
  "properties": {
    "addr:full":"1250 Techny Rd Northbrook IL 60062",
    "addr:housenumber":"1250",
    "addr:postcode":"60062",
    "addr:street":"Techny Rd",
    "iso:country":"US",
    "sg:address":"1250 Techny Rd",
    "sg:city":"Northbrook",
    "sg:classifiers":[
        {
            "category":"Home & Garden",
            "subcategory":"Home Furnishings",
            "type":"Retail Goods"
        }
    ],
    "sg:phone":"+1   ",
    "sg:postcode":"60062",
    "sg:province":"IL",
    "sg:tags":[
        "housewares",
        "linen",
        "bedding",
        "gift",
        "furniture"
    ],
    "sg:website":"www.crate-and-barrel.com",
    "wof:name":"Crate & Barrel",
    "wof:placetype":"venue"
},
  "geometry": {"coordinates":[-87.812403,42.116454],"type":"Point"}
}