{
  "type": "Feature",
  "properties": {
    "iso:country":"US",
    "sg:address":"221 W Mill St Ste B",
    "sg:city":"Waterloo",
    "sg:classifiers":[
        {
            "category":"Personal",
            "subcategory":"Beauty Salon",
            "type":"Services"
        },
        {
            "category":"Personal",
            "subcategory":"Barber",
            "type":"Services"
        }
    ],
    "sg:phone":"+1 618 939 3111",
    "sg:postcode":"62298",
    "sg:province":"IL",
    "wof:name":"Designs Unlimited",
    "wof:placetype":"venue"
},
  "geometry": {"coordinates":[-90.15223,38.335876],"type":"Point"}
}