{
  "type": "Feature",
  "properties": {
    "iso:country":"US",
    "sg:address":"7351 W 93rd St",
    "sg:city":"Bridgeview",
    "sg:classifiers":[
        {
            "category":"Professional",
            "subcategory":"Computer Services",
            "type":"Services"
        }
    ],
    "sg:phone":"+1 414 463 5182",
    "sg:postcode":"60455",
    "sg:province":"IL",
    "sg:tags":[
        "cd-rom",
        "software"
    ],
    "wof:name":"Mt Technologies",
    "wof:placetype":"venue"
},
  "geometry": {"coordinates":[-87.802245,41.722489],"type":"Point"}
}