{
  "type": "Feature",
  "properties": {
    "iso:country":"US",
    "sg:address":"224 Pearl Ave",
    "sg:city":"Loves Park",
    "sg:classifiers":[
        {
            "category":"Building & Trades",
            "subcategory":"Construction",
            "type":"Services"
        }
    ],
    "sg:phone":"+1 815 877 5370",
    "sg:postcode":"61111",
    "sg:province":"IL",
    "sg:tags":[
        "awning",
        "railing",
        "contractor"
    ],
    "wof:name":"Shirley Railing Company",
    "wof:placetype":"venue"
},
  "geometry": {"coordinates":[-89.062851,42.306965],"type":"Point"}
}