{
  "type": "Feature",
  "properties": {
    "iso:country":"US",
    "sg:address":"123 Flinn St",
    "sg:city":"Batavia",
    "sg:classifiers":[
        {
            "category":"Professional",
            "subcategory":"Management & Consulting",
            "type":"Services"
        },
        {
            "category":"Professional",
            "subcategory":"Employment Agencies",
            "type":"Services"
        }
    ],
    "sg:phone":"+1 630 406 6100",
    "sg:postcode":"60510",
    "sg:province":"IL",
    "sg:tags":[
        "personnel",
        "executive",
        "placement",
        "consultant"
    ],
    "wof:name":"Mid America Attorney Search",
    "wof:placetype":"venue"
},
  "geometry": {"coordinates":[-88.30831000000001,41.847281],"type":"Point"}
}