{
  "type": "Feature",
  "properties": {
    "addr:full":"2804 Stinson St Poplar Grove IL 61065",
    "addr:housenumber":"2804",
    "addr:postcode":"61065",
    "addr:street":"Stinson St",
    "iso:country":"US",
    "sg:address":"2804 Stinson St",
    "sg:city":"Poplar Grove",
    "sg:classifiers":[
        {
            "category":"Shopping",
            "subcategory":"Clothing, Apparel, & Fashions",
            "type":"Retail Goods"
        }
    ],
    "sg:phone":"+1   ",
    "sg:postcode":"61065",
    "sg:province":"IL",
    "sg:tags":[
        "intimate",
        "costume",
        "accessory"
    ],
    "wof:name":"Tannis of Barrington",
    "wof:placetype":"venue"
},
  "geometry": {"coordinates":[-88.835902,42.318795],"type":"Point"}
}