{
  "type": "Feature",
  "properties": {
    "iso:country":"US",
    "sg:address":"707 W Colfax St",
    "sg:city":"Palatine",
    "sg:classifiers":[
        {
            "category":"Shopping",
            "subcategory":"Gifts & Souvenirs",
            "type":"Retail Goods"
        }
    ],
    "sg:phone":"+1 847 516 2910",
    "sg:postcode":"60067",
    "sg:province":"IL",
    "sg:tags":[
        "balloon",
        "artist"
    ],
    "wof:name":"Apple Balloon Co",
    "wof:placetype":"venue"
},
  "geometry": {"coordinates":[-88.06043099999999,42.118728],"type":"Point"}
}