{
  "type": "Feature",
  "properties": {
    "iso:country":"US",
    "sg:address":"7801 W 60th Pl",
    "sg:city":"Summit Argo",
    "sg:classifiers":[
        {
            "category":"Social Services",
            "subcategory":"Child Care",
            "type":"Services"
        }
    ],
    "sg:phone":"+1 708 924 9250",
    "sg:postcode":"60501",
    "sg:province":"IL",
    "sg:tags":[
        "day"
    ],
    "wof:name":"International Perfect Trading Corporation",
    "wof:placetype":"venue"
},
  "geometry": {"coordinates":[-87.813329,41.781521],"type":"Point"}
}