{
  "type": "Feature",
  "properties": {
    "iso:country":"US",
    "sg:address":"6467 N German Church Rd",
    "sg:city":"Byron",
    "sg:classifiers":[
        {
            "category":"Organizations",
            "subcategory":"Religious Organization",
            "type":"Services"
        }
    ],
    "sg:phone":"+1 815 234 8779",
    "sg:postcode":"61010",
    "sg:province":"IL",
    "sg:tags":[
        "church"
    ],
    "wof:name":"Byron Assembly Of God Church",
    "wof:placetype":"venue"
},
  "geometry": {"coordinates":[-89.253793,42.10649],"type":"Point"}
}