{
  "type": "Feature",
  "properties": {
    "addr:full":"2864 Washington St Waukegan IL 60085",
    "addr:housenumber":"2864",
    "addr:postcode":"60085",
    "addr:street":"Washington St",
    "iso:country":"US",
    "sg:address":"2864 Washington St",
    "sg:city":"Waukegan",
    "sg:classifiers":[
        {
            "category":"Food & Beverages",
            "subcategory":"Liquor & Beverages",
            "type":"Retail Goods"
        }
    ],
    "sg:phone":"+1 847 662 6161",
    "sg:postcode":"60085",
    "sg:province":"IL",
    "wof:name":"Derby Liquors",
    "wof:placetype":"venue"
},
  "geometry": {"coordinates":[-87.872462,42.359341],"type":"Point"}
}