{
  "type": "Feature",
  "properties": {
    "iso:country":"US",
    "sg:address":"566 W Adams St",
    "sg:city":"Chicago",
    "sg:classifiers":[
        {
            "category":"Professional",
            "subcategory":"Management & Consulting",
            "type":"Services"
        }
    ],
    "sg:phone":"+1 312 775 9393",
    "sg:postcode":"60661",
    "sg:province":"IL",
    "sg:tags":[
        "counselor",
        "relation",
        "public"
    ],
    "wof:name":"S & S Public Relations",
    "wof:placetype":"venue"
},
  "geometry": {"coordinates":[-87.64157899999999,41.879312],"type":"Point"}
}