{
  "type": "Feature",
  "properties": {
    "iso:country":"US",
    "sg:address":"1933 Wildcat Rd",
    "sg:city":"Dixon",
    "sg:classifiers":[
        {
            "category":"Building & Trades",
            "subcategory":"Plumbing",
            "type":"Services"
        }
    ],
    "sg:phone":"+1 815 285 3333",
    "sg:postcode":"61021",
    "sg:province":"IL",
    "sg:tags":[
        "contractor"
    ],
    "wof:name":"Most Plumbing & Mechanical LLC",
    "wof:placetype":"venue"
},
  "geometry": {"coordinates":[-89.519918,41.862751],"type":"Point"}
}