{
  "type": "Feature",
  "properties": {
    "iso:country":"US",
    "sg:address":"40 E Springfield Ave",
    "sg:city":"Champaign",
    "sg:classifiers":[
        {
            "category":"Restaurant",
            "type":"Food & Drink"
        }
    ],
    "sg:phone":"+1 217 351 7437",
    "sg:postcode":"61820",
    "sg:province":"IL",
    "wof:name":"Pie-Full Delight Restaurant",
    "wof:placetype":"venue"
},
  "geometry": {"coordinates":[-88.240196,40.112499],"type":"Point"}
}