{
  "type": "Feature",
  "properties": {
    "iso:country":"US",
    "sg:address":"540 Lake Cook Rd",
    "sg:city":"Deerfield",
    "sg:classifiers":[
        {
            "category":"Real Estate",
            "subcategory":"Real Estate Operator",
            "type":"Services"
        }
    ],
    "sg:phone":"+1 847 374 0002",
    "sg:postcode":"60015",
    "sg:province":"IL",
    "sg:tags":[
        "owner"
    ],
    "wof:name":"Grand Plaza Ltd Partnership",
    "wof:placetype":"venue"
},
  "geometry": {"coordinates":[-87.841216,42.152852],"type":"Point"}
}