{
  "type": "Feature",
  "properties": {
    "addr:full":"5145 N Leavitt Street Chicago IL 60625",
    "addr:housenumber":"5145",
    "addr:postcode":"60625",
    "addr:street":"N Leavitt Street",
    "iso:country":"US",
    "sg:address":"5145 N Leavitt Street",
    "sg:city":"Chicago",
    "sg:classifiers":[
        {
            "category":"Education",
            "subcategory":"School",
            "type":"Public Place"
        }
    ],
    "sg:phone":"+1 773 534 2390",
    "sg:postcode":"60625",
    "sg:province":"IL",
    "sg:tags":[
        "high",
        "middle",
        "elementary"
    ],
    "wof:name":"Schools Public",
    "wof:placetype":"venue"
},
  "geometry": {"coordinates":[-87.684088,41.974504],"type":"Point"}
}