{
  "type": "Feature",
  "properties": {
    "addr:full":"116 N York St Elmhurst IL 60126",
    "addr:housenumber":"116",
    "addr:postcode":"60126",
    "addr:street":"N York St",
    "iso:country":"US",
    "sg:address":"116 N York St",
    "sg:city":"Elmhurst",
    "sg:classifiers":[
        {
            "category":"Banks & Credit Unions",
            "subcategory":"Bank",
            "type":"Services"
        }
    ],
    "sg:phone":"+1 630 834 0828",
    "sg:postcode":"60126",
    "sg:province":"IL",
    "sg:tags":[
        "machine",
        "teller",
        "automated"
    ],
    "wof:name":"Atm USA LLC",
    "wof:placetype":"venue"
},
  "geometry": {"coordinates":[-87.940045,41.900557],"type":"Point"}
}