{
  "type": "Feature",
  "properties": {
    "iso:country":"US",
    "sg:address":"111 W Jackson Blvd",
    "sg:city":"Chicago",
    "sg:classifiers":[
        {
            "category":"Professional",
            "subcategory":"Lawyer & Legal Services",
            "type":"Services"
        }
    ],
    "sg:phone":"+1 312 322 9999",
    "sg:postcode":"60661",
    "sg:province":"IL",
    "wof:name":"Student Leadership Conference",
    "wof:placetype":"venue"
},
  "geometry": {"coordinates":[-87.631492,41.878066],"type":"Point"}
}