{
  "type": "Feature",
  "properties": {
    "addr:full":"1 Tiffany Pt Bloomingdale IL 60108",
    "addr:housenumber":"1",
    "addr:postcode":"60108",
    "addr:street":"Tiffany Pt",
    "iso:country":"US",
    "sg:address":"1 Tiffany Pt",
    "sg:city":"Bloomingdale",
    "sg:classifiers":[
        {
            "category":"Social Services",
            "type":"Services"
        },
        {
            "category":"Personal",
            "type":"Services"
        }
    ],
    "sg:phone":"+1 630 924 0600",
    "sg:postcode":"60108",
    "sg:province":"IL",
    "sg:tags":[
        "family",
        "individual",
        "marriage",
        "child",
        "counseling",
        "counselor"
    ],
    "sg:website":"http://www.afamilycounselor.com",
    "wof:name":"A Family Counseling & Wellness Center",
    "wof:placetype":"venue"
},
  "geometry": {"coordinates":[-88.081017,41.954891],"type":"Point"}
}