{
  "type": "Feature",
  "properties": {
    "iso:country":"US",
    "sg:address":"6930 Lorel Ave",
    "sg:city":"Skokie",
    "sg:classifiers":[
        {
            "category":"Professional",
            "subcategory":"Management & Consulting",
            "type":"Services"
        }
    ],
    "sg:phone":"+1 847 679 8351",
    "sg:postcode":"60077",
    "sg:province":"IL",
    "wof:name":"Rdl Marketing Inc",
    "wof:placetype":"venue"
},
  "geometry": {"coordinates":[-87.761039,42.007837],"type":"Point"}
}