{
  "type": "Feature",
  "properties": {
    "iso:country":"US",
    "sg:address":"1111 W Morton Ave",
    "sg:city":"Jacksonville",
    "sg:classifiers":[
        {
            "category":"Government",
            "subcategory":"Office",
            "type":"Public Place"
        }
    ],
    "sg:phone":"+1   ",
    "sg:postcode":"62650",
    "sg:province":"IL",
    "sg:tags":[
        "recruiting"
    ],
    "wof:name":"US Marine Corps Recruiting",
    "wof:placetype":"venue"
},
  "geometry": {"coordinates":[-90.244135,39.723148],"type":"Point"}
}