{
  "type": "Feature",
  "properties": {
    "iso:country":"US",
    "sg:address":"1548 E Palmer Ln",
    "sg:city":"Palatine",
    "sg:classifiers":[
        {
            "category":"Shopping",
            "subcategory":"Bicycles & Sporting Goods",
            "type":"Retail Goods"
        }
    ],
    "sg:phone":"+1   ",
    "sg:postcode":"60074",
    "sg:province":"IL",
    "sg:tags":[
        "repair",
        "accessory"
    ],
    "wof:name":"C C Cycle",
    "wof:placetype":"venue"
},
  "geometry": {"coordinates":[-88.00867700000001,42.142122],"type":"Point"}
}