{
  "type": "Feature",
  "properties": {
    "addr:full":"206 W Wesley St Wheaton IL 60187",
    "addr:housenumber":"206",
    "addr:postcode":"60187",
    "addr:street":"W Wesley St",
    "iso:country":"US",
    "sg:address":"206 W Wesley St",
    "sg:city":"Wheaton",
    "sg:classifiers":[
        {
            "category":"Personal",
            "subcategory":"Massage",
            "type":"Services"
        },
        {
            "category":"Personal",
            "subcategory":"Day Spa",
            "type":"Services"
        }
    ],
    "sg:phone":"+1 630 752 9600",
    "sg:postcode":"60187",
    "sg:province":"IL",
    "wof:name":"The Apothica Co",
    "wof:placetype":"venue"
},
  "geometry": {"coordinates":[-88.108902,41.866199],"type":"Point"}
}