{
  "type": "Feature",
  "properties": {
    "addr:full":"1671 Olive Ave Charleston IL 61920",
    "addr:housenumber":"1671",
    "addr:postcode":"61920",
    "addr:street":"Olive Ave",
    "iso:country":"US",
    "sg:address":"1671 Olive Ave",
    "sg:city":"Charleston",
    "sg:classifiers":[
        {
            "category":"Manufacturing",
            "subcategory":"Metals",
            "type":"Manufacturing & Wholesale Goods"
        }
    ],
    "sg:phone":"+1 217 348 9353",
    "sg:postcode":"61920",
    "sg:province":"IL",
    "sg:tags":[
        "plate",
        "s",
        "structural",
        "fabricated",
        "mfg"
    ],
    "wof:name":"Pro-Tran Inc",
    "wof:placetype":"venue"
},
  "geometry": {"coordinates":[-88.167036,39.499504],"type":"Point"}
}