{
  "type": "Feature",
  "properties": {
    "iso:country":"US",
    "sg:address":"1019 E Court St",
    "sg:city":"Hennepin",
    "sg:classifiers":[
        {
            "category":"Building & Trades",
            "subcategory":"Construction",
            "type":"Services"
        }
    ],
    "sg:phone":"+1 815 925 7169",
    "sg:postcode":"61327",
    "sg:province":"IL",
    "sg:tags":[
        "contractor"
    ],
    "wof:name":"Hundley Drywall",
    "wof:placetype":"venue"
},
  "geometry": {"coordinates":[-89.334308,41.251329],"type":"Point"}
}