{
  "type": "Feature",
  "properties": {
    "iso:country":"US",
    "sg:address":"Respiratory Health Association 1440 W. Washington Blvd.",
    "sg:city":"Chicago",
    "sg:classifiers":[
        {
            "category":"Restaurant",
            "type":"Food & Drink"
        },
        {
            "category":"Recreation",
            "type":"Entertainment"
        }
    ],
    "sg:phone":"+1 312 243 2000",
    "sg:postcode":"60607",
    "sg:province":"IL",
    "sg:tags":[
        "active",
        "flavor",
        "local",
        "life"
    ],
    "sg:website":"www.cowalunga.com/",
    "wof:name":"Cowalunga Bike Tour",
    "wof:placetype":"venue"
},
  "geometry": {"coordinates":[-87.663819,41.883213],"type":"Point"}
}