{
  "type": "Feature",
  "properties": {
    "iso:country":"US",
    "sg:address":"974 170th Ave",
    "sg:city":"Joy",
    "sg:classifiers":[
        {
            "category":"Farming",
            "subcategory":"Livestock Farm",
            "type":"Manufacturing & Wholesale Goods"
        }
    ],
    "sg:phone":"+1 309 537 3540",
    "sg:postcode":"61260",
    "sg:province":"IL",
    "sg:tags":[
        "hog",
        "or",
        "feedlot"
    ],
    "wof:name":"Jim Holmes",
    "wof:placetype":"venue"
},
  "geometry": {"coordinates":[-90.898928,41.317484],"type":"Point"}
}