{
  "type": "Feature",
  "properties": {
    "addr:full":"2430 E Rand Rd Arlington Hts IL 60004",
    "addr:housenumber":"2430",
    "addr:postcode":"60004",
    "addr:street":"E Rand Rd",
    "iso:country":"US",
    "sg:address":"2430 E Rand Rd",
    "sg:city":"Arlington Hts",
    "sg:classifiers":[
        {
            "category":"Sports & Exercise",
            "subcategory":"Gym",
            "type":"Entertainment"
        }
    ],
    "sg:phone":"+1 847 253 3000",
    "sg:postcode":"60004",
    "sg:province":"IL",
    "sg:tags":[
        "club",
        "health",
        "studio",
        "gymnasium"
    ],
    "wof:name":"Fit & Figure",
    "wof:placetype":"venue"
},
  "geometry": {"coordinates":[-87.94899599999999,42.091187],"type":"Point"}
}