{
  "type": "Feature",
  "properties": {
    "iso:country":"US",
    "sg:address":"2080 Springer Dr",
    "sg:city":"Lombard",
    "sg:classifiers":[
        {
            "category":"Health Services",
            "subcategory":"Clinic",
            "type":"Services"
        },
        {
            "category":"Health Services",
            "subcategory":"Medical Lab",
            "type":"Services"
        },
        {
            "category":"Personal",
            "type":"Services"
        }
    ],
    "sg:phone":"+1 866 867 0393",
    "sg:postcode":"60148",
    "sg:province":"IL",
    "sg:tags":[
        "laboratory",
        "testing",
        "paternity",
        "drug"
    ],
    "sg:website":"http://chicago.citysearch.com/profile/external/604045672/lombard_il/rapid_std_dna_drug_testing_lombard.html?publisher=yellowpages&reference_id=1&placement=ypwebsitemip",
    "wof:name":"Rapid STD DNA Drug Testing LOMBARD",
    "wof:placetype":"venue"
},
  "geometry": {"coordinates":[-88.02898,41.84686],"type":"Point"}
}