{
  "type": "Feature",
  "properties": {
    "iso:country":"US",
    "sg:address":"488 N Green Bay Rd",
    "sg:city":"Waukegan",
    "sg:classifiers":[
        {
            "category":"Restaurant",
            "type":"Food & Drink"
        }
    ],
    "sg:phone":"+1 847 336 7700",
    "sg:postcode":"60085",
    "sg:province":"IL",
    "sg:tags":[
        "style",
        "family",
        "lunch",
        "american",
        "brunch",
        "breakfast"
    ],
    "wof:name":"Emily's Pancake House",
    "wof:placetype":"venue"
},
  "geometry": {"coordinates":[-87.878925,42.366474],"type":"Point"}
}