{
  "type": "Feature",
  "properties": {
    "addr:full":"141 W Northwest Hwy Palatine IL 60067",
    "addr:housenumber":"141",
    "addr:postcode":"60067",
    "addr:street":"W Northwest Hwy",
    "iso:country":"US",
    "sg:address":"141 W Northwest Hwy",
    "sg:city":"Palatine",
    "sg:classifiers":[
        {
            "category":"Building & Trades",
            "subcategory":"Landscaping Services",
            "type":"Services"
        }
    ],
    "sg:phone":"+1 847 705 7816",
    "sg:postcode":"60067",
    "sg:province":"IL",
    "wof:name":"Quality Scapes",
    "wof:placetype":"venue"
},
  "geometry": {"coordinates":[-88.047408,42.122073],"type":"Point"}
}