{
  "type": "Feature",
  "properties": {
    "iso:country":"US",
    "sg:address":"8490 Forest Blvd",
    "sg:city":"Caseyville",
    "sg:phone":"+1 618 398 0097",
    "sg:postcode":"62232",
    "sg:province":"IL",
    "sg:tags":[
        "farm",
        "corn",
        "soybean"
    ],
    "wof:name":"Barry McMillin",
    "wof:placetype":"venue"
},
  "geometry": {"coordinates":[-90.048433,38.636686],"type":"Point"}
}