{
  "type": "Feature",
  "properties": {
    "iso:country":"US",
    "sg:address":"100 W Golf Rd",
    "sg:city":"Schaumburg",
    "sg:classifiers":[
        {
            "category":"Autos & Motor Vehicles",
            "subcategory":"Automobile Sales",
            "type":"Retail Goods"
        }
    ],
    "sg:phone":"+1   ",
    "sg:postcode":"60195",
    "sg:province":"IL",
    "wof:name":"Napletons Shaumburg Pontiac",
    "wof:placetype":"venue"
},
  "geometry": {"coordinates":[-88.080235,42.049484],"type":"Point"}
}