{
  "type": "Feature",
  "properties": {
    "iso:country":"US",
    "sg:address":"3331 W Deyoung St Ste 201",
    "sg:city":"Marion",
    "sg:classifiers":[
        {
            "category":"Health Services",
            "subcategory":"Doctor",
            "type":"Services"
        }
    ],
    "sg:phone":"+1 618 998 9888",
    "sg:postcode":"62959",
    "sg:province":"IL",
    "sg:tags":[
        "obstetrician",
        "gynecologist"
    ],
    "wof:name":"Sayavong Patrick DO",
    "wof:placetype":"venue"
},
  "geometry": {"coordinates":[-88.986603,37.7449],"type":"Point"}
}