{
  "type": "Feature",
  "properties": {
    "iso:country":"US",
    "sg:address":"15827 W Smithville Rd",
    "sg:city":"Glasford",
    "sg:classifiers":[
        {
            "category":"Farming",
            "subcategory":"Livestock Farm",
            "type":"Manufacturing & Wholesale Goods"
        },
        {
            "category":"Farming",
            "subcategory":"Farm",
            "type":"Manufacturing & Wholesale Goods"
        }
    ],
    "sg:phone":"+1 309 565 4808",
    "sg:postcode":"61533",
    "sg:province":"IL",
    "sg:tags":[
        "feeding"
    ],
    "wof:name":"Marion Grebner",
    "wof:placetype":"venue"
},
  "geometry": {"coordinates":[-89.844419,40.639069],"type":"Point"}
}