{
  "type": "Feature",
  "properties": {
    "addr:full":"2107 Belvidere Rd Waukegan IL 60085",
    "addr:housenumber":"2107",
    "addr:postcode":"60085",
    "addr:street":"Belvidere Rd",
    "iso:country":"US",
    "sg:address":"2107 Belvidere Rd",
    "sg:city":"Waukegan",
    "sg:classifiers":[
        {
            "category":"Shopping",
            "subcategory":"Clothing, Apparel, & Fashions",
            "type":"Retail Goods"
        }
    ],
    "sg:phone":"+1 847 599 9662",
    "sg:postcode":"60085",
    "sg:province":"IL",
    "sg:tags":[
        "infant",
        "wear"
    ],
    "wof:name":"Leslie's Childrens Wear",
    "wof:placetype":"venue"
},
  "geometry": {"coordinates":[-87.86224799999999,42.350275],"type":"Point"}
}