{
  "type": "Feature",
  "properties": {
    "addr:full":"8400 W 94th St Oak Lawn IL 60457",
    "addr:housenumber":"8400",
    "addr:postcode":"60457",
    "addr:street":"W 94Th St",
    "iso:country":"US",
    "sg:address":"8400 W 94th St",
    "sg:city":"Oak Lawn",
    "sg:classifiers":[
        {
            "category":"Utilities",
            "subcategory":"Electric",
            "type":"Services"
        }
    ],
    "sg:phone":"+1 847 814 8822",
    "sg:postcode":"60457",
    "sg:province":"IL",
    "wof:name":"Vafcon Inc",
    "wof:placetype":"venue"
},
  "geometry": {"coordinates":[-87.827967,41.720131],"type":"Point"}
}