{
  "type": "Feature",
  "properties": {
    "iso:country":"US",
    "sg:address":"331 Haddon Cir",
    "sg:city":"Vernon Hills",
    "sg:classifiers":[
        {
            "category":"Organizations",
            "subcategory":"Membership Organization",
            "type":"Services"
        }
    ],
    "sg:phone":"+1 847 816 0627",
    "sg:postcode":"60061",
    "sg:province":"IL",
    "wof:name":"Disorders of Chromosone",
    "wof:placetype":"venue"
},
  "geometry": {"coordinates":[-87.971691,42.216221],"type":"Point"}
}