{
  "type": "Feature",
  "properties": {
    "iso:country":"US",
    "sg:address":"340 Johnson St",
    "sg:city":"Carlinville",
    "sg:classifiers":[
        {
            "category":"Manufacturing",
            "subcategory":"Buildings",
            "type":"Manufacturing & Wholesale Goods"
        },
        {
            "category":"Building & Trades",
            "subcategory":"Construction",
            "type":"Services"
        }
    ],
    "sg:phone":"+1 217 854 3424",
    "sg:postcode":"62626",
    "sg:province":"IL",
    "sg:tags":[
        "industrial",
        "builder",
        "system",
        "specialty",
        "siding",
        "heating",
        "contractor",
        "contractors-commercial",
        "home",
        "air conditioning"
    ],
    "wof:name":"Tieman Construction",
    "wof:placetype":"venue"
},
  "geometry": {"coordinates":[-89.87514299999999,39.282702],"type":"Point"}
}