{
  "type": "Feature",
  "properties": {
    "iso:country":"US",
    "sg:address":"1000 Brown St",
    "sg:city":"Wauconda",
    "sg:classifiers":[
        {
            "category":"Wholesale",
            "subcategory":"Machinery & Supplies",
            "type":"Manufacturing & Wholesale Goods"
        }
    ],
    "sg:phone":"+1 847 487 4402",
    "sg:postcode":"60084",
    "sg:province":"IL",
    "sg:tags":[
        "packaging"
    ],
    "wof:name":"Zitropack Limited",
    "wof:placetype":"venue"
},
  "geometry": {"coordinates":[-88.151433,42.277561],"type":"Point"}
}