{
  "type": "Feature",
  "properties": {
    "iso:country":"US",
    "sg:address":"2653 Luzern Ct",
    "sg:city":"Woodridge",
    "sg:classifiers":[
        {
            "category":"Organizations",
            "subcategory":"Community Association",
            "type":"Services"
        }
    ],
    "sg:phone":"+1 630 985 7939",
    "sg:postcode":"60517",
    "sg:province":"IL",
    "wof:name":"Boy Scout Troop 510",
    "wof:placetype":"venue"
},
  "geometry": {"coordinates":[-88.04650700000001,41.736364],"type":"Point"}
}