{
  "type": "Feature",
  "properties": {
    "iso:country":"US",
    "sg:address":"1158 S Pecatonica Rd",
    "sg:city":"Pecatonica",
    "sg:phone":"+1 815 247 8647",
    "sg:postcode":"61063",
    "sg:province":"IL",
    "sg:tags":[
        "farm",
        "corn",
        "wheat"
    ],
    "wof:name":"Homer Green Trust",
    "wof:placetype":"venue"
},
  "geometry": {"coordinates":[-89.358474,42.265537],"type":"Point"}
}