{
  "type": "Feature",
  "properties": {
    "addr:full":"33 N County St Waukegan IL 60085",
    "addr:housenumber":"33",
    "addr:postcode":"60085",
    "addr:street":"N County St",
    "iso:country":"US",
    "sg:address":"33 N County St",
    "sg:city":"Waukegan",
    "sg:classifiers":[
        {
            "category":"Professional",
            "subcategory":"Lawyer & Legal Services",
            "type":"Services"
        }
    ],
    "sg:phone":"+1 847 336 2990",
    "sg:postcode":"60085",
    "sg:province":"IL",
    "wof:name":"James S Tukesbrey",
    "wof:placetype":"venue"
},
  "geometry": {"coordinates":[-87.832519,42.36049],"type":"Point"}
}