{
  "type": "Feature",
  "properties": {
    "addr:full":"500 Foss Park Ave North Chicago IL 60064",
    "addr:housenumber":"500",
    "addr:postcode":"60064",
    "addr:street":"Foss Park Ave",
    "iso:country":"US",
    "sg:address":"500 Foss Park Ave",
    "sg:city":"North Chicago",
    "sg:classifiers":[
        {
            "category":"Building & Trades",
            "subcategory":"Plumbing",
            "type":"Services"
        }
    ],
    "sg:phone":"+1 847 689 4723",
    "sg:postcode":"60064",
    "sg:province":"IL",
    "sg:tags":[
        "mechanical",
        "contractor"
    ],
    "wof:name":"Advanced Mechanical Contrs",
    "wof:placetype":"venue"
},
  "geometry": {"coordinates":[-87.83760599999999,42.329378],"type":"Point"}
}