{
  "type": "Feature",
  "properties": {
    "iso:country":"US",
    "sg:address":"1300 N Rand Rd",
    "sg:city":"Arlington Heights",
    "sg:classifiers":[
        {
            "category":"Manufacturing",
            "subcategory":"Signs",
            "type":"Manufacturing & Wholesale Goods"
        }
    ],
    "sg:phone":"+1 847 398 8239",
    "sg:postcode":"60004",
    "sg:province":"IL",
    "sg:tags":[
        "specialty",
        "mfg"
    ],
    "wof:name":"Sign Shop At Great Frame",
    "wof:placetype":"venue"
},
  "geometry": {"coordinates":[-87.999987,42.125923],"type":"Point"}
}