{
  "type": "Feature",
  "properties": {
    "iso:country":"US",
    "sg:address":"8520 Niles Center Rd",
    "sg:city":"Skokie",
    "sg:classifiers":[
        {
            "category":"Professional",
            "subcategory":"Business Services",
            "type":"Services"
        }
    ],
    "sg:phone":"+1 847 674 3172",
    "sg:postcode":"60077",
    "sg:province":"IL",
    "wof:name":"Royal Care Corp",
    "wof:placetype":"venue"
},
  "geometry": {"coordinates":[-87.75043,42.03533],"type":"Point"}
}