{
  "type": "Feature",
  "properties": {
    "iso:country":"US",
    "sg:address":"208 W North St",
    "sg:city":"Danville",
    "sg:classifiers":[
        {
            "category":"Professional",
            "subcategory":"Lawyer & Legal Services",
            "type":"Services"
        }
    ],
    "sg:phone":"+1 217 442 0244",
    "sg:postcode":"61832",
    "sg:province":"IL",
    "sg:tags":[
        "attorney"
    ],
    "wof:name":"Saikley Garrison & Colombo LTD",
    "wof:placetype":"venue"
},
  "geometry": {"coordinates":[-87.633103,40.12625],"type":"Point"}
}