{
  "type": "Feature",
  "properties": {
    "addr:full":"701 Devonshire Dr Ste C17 Champaign IL 61820",
    "addr:housenumber":"701",
    "addr:postcode":"61820",
    "addr:street":"Devonshire Dr Ste C17",
    "iso:country":"US",
    "sg:address":"701 Devonshire Dr Ste C17",
    "sg:city":"Champaign",
    "sg:classifiers":[
        {
            "category":"Real Estate",
            "subcategory":"Real Estate Services",
            "type":"Services"
        },
        {
            "category":"Banks & Credit Unions",
            "subcategory":"Financial Services",
            "type":"Services"
        }
    ],
    "sg:phone":"+1 217 239 6635",
    "sg:postcode":"61820",
    "sg:province":"IL",
    "sg:tags":[
        "loan",
        "processing",
        "broker",
        "mortgage"
    ],
    "wof:name":"1st Metropolitan Mortgage",
    "wof:placetype":"venue"
},
  "geometry": {"coordinates":[-88.253162,40.089343],"type":"Point"}
}