{
  "type": "Feature",
  "properties": {
    "addr:full":"1852 E Indiana Ave Beecher IL 60401",
    "addr:housenumber":"1852",
    "addr:postcode":"60401",
    "addr:street":"E Indiana Ave",
    "iso:country":"US",
    "sg:address":"1852 E Indiana Ave",
    "sg:city":"Beecher",
    "sg:classifiers":[
        {
            "category":"Farming",
            "subcategory":"Farm",
            "type":"Manufacturing & Wholesale Goods"
        }
    ],
    "sg:phone":"+1 708 946 3250",
    "sg:postcode":"60401",
    "sg:province":"IL",
    "sg:tags":[
        "food",
        "covered",
        "crop"
    ],
    "wof:name":"Jerry Vos Farm",
    "wof:placetype":"venue"
},
  "geometry": {"coordinates":[-87.572857,41.341249],"type":"Point"}
}