{
  "type": "Feature",
  "properties": {
    "iso:country":"US",
    "sg:address":"845 W Wilson Avenue",
    "sg:city":"Chicago",
    "sg:classifiers":[
        {
            "category":"Shopping",
            "subcategory":"Pharmacy",
            "type":"Retail Goods"
        }
    ],
    "sg:phone":"+1 773 275 7192",
    "sg:postcode":"60640",
    "sg:province":"IL",
    "sg:tags":[
        "drugstore"
    ],
    "sg:website":"www.cvs.com",
    "wof:name":"Cvs",
    "wof:placetype":"venue"
},
  "geometry": {"coordinates":[-87.650764,41.965372],"type":"Point"}
}