{
  "type": "Feature",
  "properties": {
    "iso:country":"US",
    "sg:address":"4610 N Illinois St",
    "sg:city":"Fairview Heights",
    "sg:classifiers":[
        {
            "category":"Personal",
            "subcategory":"Barber",
            "type":"Services"
        }
    ],
    "sg:phone":"+1 618 233 4300",
    "sg:postcode":"62226",
    "sg:province":"IL",
    "sg:website":"www.hairsaloon.com",
    "wof:name":"Hair Saloon for Men",
    "wof:placetype":"venue"
},
  "geometry": {"coordinates":[-89.984806,38.570709],"type":"Point"}
}