{
  "type": "Feature",
  "properties": {
    "iso:country":"US",
    "sg:address":"4871 Hydraulic Rd",
    "sg:city":"Rockford",
    "sg:classifiers":[
        {
            "category":"Manufacturing",
            "subcategory":"Tools & Machinery",
            "type":"Manufacturing & Wholesale Goods"
        }
    ],
    "sg:phone":"+1 815 873 8310",
    "sg:postcode":"61109",
    "sg:province":"IL",
    "sg:tags":[
        "machine",
        "shop"
    ],
    "wof:name":"Precise Extrusion Die",
    "wof:placetype":"venue"
},
  "geometry": {"coordinates":[-89.022484,42.227347],"type":"Point"}
}