{
  "type": "Feature",
  "properties": {
    "addr:full":"293 Terrace Pl Buffalo Grove IL 60089",
    "addr:housenumber":"293",
    "addr:postcode":"60089",
    "addr:street":"Terrace Pl",
    "iso:country":"US",
    "sg:address":"293 Terrace Pl",
    "sg:city":"Buffalo Grove",
    "sg:classifiers":[
        {
            "category":"Communications",
            "subcategory":"Film & Video Production",
            "type":"Services"
        }
    ],
    "sg:phone":"+1 847 520 0099",
    "sg:postcode":"60089",
    "sg:province":"IL",
    "sg:tags":[
        "motion"
    ],
    "wof:name":"Ron Ascher Productions Ltd",
    "wof:placetype":"venue"
},
  "geometry": {"coordinates":[-87.980593,42.148547],"type":"Point"}
}