{
  "type": "Feature",
  "properties": {
    "iso:country":"US",
    "sg:address":"3425 Sunset Ave",
    "sg:city":"Waukegan",
    "sg:classifiers":[
        {
            "category":"Real Estate",
            "subcategory":"Real Estate Agent",
            "type":"Services"
        }
    ],
    "sg:phone":"+1 847 336 7333",
    "sg:postcode":"60087",
    "sg:province":"IL",
    "wof:name":"Maki United",
    "wof:placetype":"venue"
},
  "geometry": {"coordinates":[-87.885018,42.392044],"type":"Point"}
}