{
  "type": "Feature",
  "properties": {
    "iso:country":"US",
    "sg:address":"702 Short Eighth St",
    "sg:city":"Lincoln",
    "sg:classifiers":[
        {
            "category":"Building & Trades",
            "subcategory":"Construction",
            "type":"Services"
        }
    ],
    "sg:phone":"+1 217 732 7621",
    "sg:postcode":"62656",
    "sg:province":"IL",
    "sg:tags":[
        "residential",
        "masonry",
        "general",
        "commercial",
        "contractor"
    ],
    "wof:name":"Krusz Construction",
    "wof:placetype":"venue"
},
  "geometry": {"coordinates":[-89.378934,40.149725],"type":"Point"}
}