{
  "type": "Feature",
  "properties": {
    "iso:country":"US",
    "sg:address":"301 E Marquardt Dr",
    "sg:city":"Wheeling",
    "sg:classifiers":[
        {
            "category":"Building & Trades",
            "subcategory":"Electrical",
            "type":"Services"
        }
    ],
    "sg:phone":"+1 847 808 1819",
    "sg:postcode":"60090",
    "sg:province":"IL",
    "sg:tags":[
        "transmission",
        "equipment",
        "power"
    ],
    "wof:name":"U S Tsubaki",
    "wof:placetype":"venue"
},
  "geometry": {"coordinates":[-87.90947799999999,42.116192],"type":"Point"}
}