{
  "type": "Feature",
  "properties": {
    "iso:country":"US",
    "sg:address":"1235 W Grand Ave",
    "sg:city":"Chicago",
    "sg:classifiers":[
        {
            "category":"Restaurant",
            "type":"Food & Drink"
        }
    ],
    "sg:phone":"+1 312 421 2000",
    "sg:postcode":"60622",
    "sg:province":"IL",
    "sg:tags":[
        "italian"
    ],
    "wof:name":"Amelia's Restaurant",
    "wof:placetype":"venue"
},
  "geometry": {"coordinates":[-87.658699,41.8909],"type":"Point"}
}