{
  "type": "Feature",
  "properties": {
    "iso:country":"US",
    "sg:address":"701 N Devils Ln",
    "sg:city":"Byron",
    "sg:classifiers":[
        {
            "category":"Building & Trades",
            "subcategory":"Construction",
            "type":"Services"
        }
    ],
    "sg:phone":"+1 815 234 5514",
    "sg:postcode":"61010",
    "sg:province":"IL",
    "sg:tags":[
        "handyman"
    ],
    "wof:name":"Ackerman's Handyman Svc",
    "wof:placetype":"venue"
},
  "geometry": {"coordinates":[-89.316457,42.093617],"type":"Point"}
}