{
  "type": "Feature",
  "properties": {
    "addr:full":"2820 W 48th Pl Chicago IL 60632",
    "addr:housenumber":"2820",
    "addr:postcode":"60632",
    "addr:street":"W 48Th Pl",
    "iso:country":"US",
    "sg:address":"2820 W 48th Pl",
    "sg:city":"Chicago",
    "sg:classifiers":[
        {
            "category":"Communications",
            "subcategory":"News Services",
            "type":"Services"
        },
        {
            "category":"Communications",
            "subcategory":"Newspaper",
            "type":"Services"
        },
        {
            "category":"Wholesale",
            "subcategory":"Books, Periodicals, & Newspapers",
            "type":"Manufacturing & Wholesale Goods"
        }
    ],
    "sg:phone":"+1 773 523 5831",
    "sg:postcode":"60632",
    "sg:province":"IL",
    "sg:tags":[
        "dealers-wholesale",
        "feature",
        "syndicate"
    ],
    "wof:name":"L S News Agency",
    "wof:placetype":"venue"
},
  "geometry": {"coordinates":[-87.69623,41.805548],"type":"Point"}
}