{
  "type": "Feature",
  "properties": {
    "iso:country":"US",
    "sg:address":"760 E Grand Ave",
    "sg:city":"Carbondale",
    "sg:classifiers":[
        {
            "category":"Bars & Pubs",
            "type":"Food & Drink"
        }
    ],
    "sg:phone":"+1 618 529 5494",
    "sg:postcode":"62901",
    "sg:province":"IL",
    "wof:name":"Callahan's Irish Pub",
    "wof:placetype":"venue"
},
  "geometry": {"coordinates":[-89.198367,37.717642],"type":"Point"}
}