{
  "type": "Feature",
  "properties": {
    "iso:country":"US",
    "sg:address":"106 7th St",
    "sg:city":"Rockford",
    "sg:classifiers":[
        {
            "category":"Shopping",
            "subcategory":"Clothing, Apparel, & Fashions",
            "type":"Retail Goods"
        }
    ],
    "sg:phone":"+1   ",
    "sg:postcode":"61104",
    "sg:province":"IL",
    "wof:name":"Chantilly Lace",
    "wof:placetype":"venue"
},
  "geometry": {"coordinates":[-89.080709,42.265831],"type":"Point"}
}