{
  "type": "Feature",
  "properties": {
    "addr:full":"125 W Dundee Rd Buffalo Grove IL 60089",
    "addr:housenumber":"125",
    "addr:postcode":"60089",
    "addr:street":"W Dundee Rd",
    "iso:country":"US",
    "sg:address":"125 W Dundee Rd",
    "sg:city":"Buffalo Grove",
    "sg:classifiers":[
        {
            "category":"Retail",
            "subcategory":"Animal Services",
            "type":"Services"
        }
    ],
    "sg:phone":"+1 847 537 3647",
    "sg:postcode":"60089",
    "sg:province":"IL",
    "wof:name":"Gussied Up Pup",
    "wof:placetype":"venue"
},
  "geometry": {"coordinates":[-87.96175700000001,42.138929],"type":"Point"}
}