{
  "type": "Feature",
  "properties": {
    "addr:full":"1628 W 47th Street Chicago IL 60609",
    "addr:housenumber":"1628",
    "addr:postcode":"60609",
    "addr:street":"W 47Th Street",
    "iso:country":"US",
    "sg:address":"1628 W 47th Street",
    "sg:city":"Chicago",
    "sg:classifiers":[
        {
            "category":"Food & Beverages",
            "subcategory":"Liquor & Beverages",
            "type":"Retail Goods"
        }
    ],
    "sg:phone":"+1 773 254 7923",
    "sg:postcode":"60609",
    "sg:province":"IL",
    "sg:tags":[
        "beer",
        "spirit",
        "wine"
    ],
    "wof:name":"Continental House",
    "wof:placetype":"venue"
},
  "geometry": {"coordinates":[-87.666302,41.808569],"type":"Point"}
}