{
  "type": "Feature",
  "properties": {
    "iso:country":"US",
    "sg:address":"1660 Rose Ln",
    "sg:city":"Romeoville",
    "sg:classifiers":[
        {
            "category":"Real Estate",
            "subcategory":"Real Estate Agent",
            "type":"Services"
        }
    ],
    "sg:phone":"+1 773 507 9112",
    "sg:postcode":"60446",
    "sg:province":"IL",
    "wof:name":"Recomm Realty",
    "wof:placetype":"venue"
},
  "geometry": {"coordinates":[-88.14259300000001,41.617561],"type":"Point"}
}