{
  "type": "Feature",
  "properties": {
    "addr:full":"1328 Teakwood Ln Crystal Lake IL 60014",
    "addr:housenumber":"1328",
    "addr:postcode":"60014",
    "addr:street":"Teakwood Ln",
    "iso:country":"US",
    "sg:address":"1328 Teakwood Ln",
    "sg:city":"Crystal Lake",
    "sg:classifiers":[
        {
            "category":"Building & Trades",
            "subcategory":"Construction",
            "type":"Services"
        }
    ],
    "sg:phone":"+1 815 477 0769",
    "sg:postcode":"60014",
    "sg:province":"IL",
    "sg:tags":[
        "floor",
        "laying",
        "contractor"
    ],
    "wof:name":"Wasberg Installations Inc",
    "wof:placetype":"venue"
},
  "geometry": {"coordinates":[-88.370491,42.241331],"type":"Point"}
}