{
  "type": "Feature",
  "properties": {
    "iso:country":"US",
    "sg:address":"7840 W Ogden Ave",
    "sg:city":"Lyons",
    "sg:classifiers":[
        {
            "category":"Shopping",
            "subcategory":"Bicycles & Sporting Goods",
            "type":"Retail Goods"
        },
        {
            "category":"Sports & Exercise",
            "subcategory":"Swimming Pool",
            "type":"Entertainment"
        }
    ],
    "sg:phone":"+1 708 442 4388",
    "sg:postcode":"60534",
    "sg:province":"IL",
    "sg:tags":[
        "diving",
        "outdoor",
        "instruction",
        "gear"
    ],
    "sg:website":"www.djscuba.com/",
    "wof:name":"DJ's Scuba Locker",
    "wof:placetype":"venue"
},
  "geometry": {"coordinates":[-87.817668,41.820298],"type":"Point"}
}