{
  "type": "Feature",
  "properties": {
    "iso:country":"US",
    "sg:address":"3047 N Honore St #1",
    "sg:city":"Chicago",
    "sg:classifiers":[
        {
            "category":"Real Estate",
            "subcategory":"Surveying",
            "type":"Services"
        }
    ],
    "sg:phone":"+1 866 400 0178",
    "sg:postcode":"60657",
    "sg:province":"IL",
    "sg:tags":[
        "appraiser"
    ],
    "wof:name":"Cityview Appraisals",
    "wof:placetype":"venue"
},
  "geometry": {"coordinates":[-87.674217,41.937113],"type":"Point"}
}