{
  "type": "Feature",
  "properties": {
    "iso:country":"US",
    "sg:address":"541 9th St",
    "sg:city":"Carlyle",
    "sg:classifiers":[
        {
            "category":"Professional",
            "subcategory":"Lawyer & Legal Services",
            "type":"Services"
        }
    ],
    "sg:phone":"+1 618 594 2418",
    "sg:postcode":"62231",
    "sg:province":"IL",
    "sg:tags":[
        "attorney"
    ],
    "wof:name":"Richard A Kuiken",
    "wof:placetype":"venue"
},
  "geometry": {"coordinates":[-89.369026,38.61077],"type":"Point"}
}