{
  "type": "Feature",
  "properties": {
    "addr:full":"4729 N Central Ave Chicago IL 60630",
    "addr:housenumber":"4729",
    "addr:postcode":"60630",
    "addr:street":"N Central Ave",
    "iso:country":"US",
    "sg:address":"4729 N Central Ave",
    "sg:city":"Chicago",
    "sg:classifiers":[
        {
            "category":"Banks & Credit Unions",
            "subcategory":"Bank",
            "type":"Services"
        }
    ],
    "sg:phone":"+1 800 823 2265",
    "sg:postcode":"60630",
    "sg:province":"IL",
    "sg:tags":[
        "commercial",
        "saving"
    ],
    "sg:website":"http://www.tcfbank.com",
    "wof:name":"TCF Bank",
    "wof:placetype":"venue"
},
  "geometry": {"coordinates":[-87.767471,41.966881],"type":"Point"}
}