{
  "type": "Feature",
  "properties": {
    "iso:country":"US",
    "sg:address":"4124 W Armitage Ave",
    "sg:city":"Chicago",
    "sg:classifiers":[
        {
            "category":"Restaurant",
            "type":"Food & Drink"
        }
    ],
    "sg:phone":"+1 773 252 1799",
    "sg:postcode":"60639",
    "sg:province":"IL",
    "sg:tags":[
        "mexican"
    ],
    "sg:website":"ElVigiaRestaurant.com",
    "wof:name":"El Vigia Restaurant",
    "wof:placetype":"venue"
},
  "geometry": {"coordinates":[-87.729917,41.917302],"type":"Point"}
}