{
  "type": "Feature",
  "properties": {
    "iso:country":"US",
    "sg:address":"821 Fair Ln",
    "sg:city":"Northbrook",
    "sg:classifiers":[
        {
            "category":"Travel",
            "subcategory":"Campground",
            "type":"Entertainment"
        }
    ],
    "sg:phone":"+1 847 562 9900",
    "sg:postcode":"60062",
    "sg:province":"IL",
    "sg:tags":[
        "camp"
    ],
    "wof:name":"Funtastic Summer Day Camp",
    "wof:placetype":"venue"
},
  "geometry": {"coordinates":[-87.832713,42.136955],"type":"Point"}
}