{
  "type": "Feature",
  "properties": {
    "iso:country":"US",
    "sg:address":"1070 N Milwaukee Avenue",
    "sg:city":"Chicago",
    "sg:classifiers":[
        {
            "category":"Banks & Credit Unions",
            "subcategory":"Financial Services",
            "type":"Services"
        }
    ],
    "sg:phone":"+1 773 772 5000",
    "sg:postcode":"60622",
    "sg:province":"IL",
    "sg:tags":[
        "broker",
        "mortgage"
    ],
    "wof:name":"Anchor Mortgage Corporation",
    "wof:placetype":"venue"
},
  "geometry": {"coordinates":[-87.663284,41.901233],"type":"Point"}
}