{
  "type": "Feature",
  "properties": {
    "addr:full":"534 N Sheridan Rd Waukegan IL 60085",
    "addr:housenumber":"534",
    "addr:postcode":"60085",
    "addr:street":"N Sheridan Rd",
    "iso:country":"US",
    "sg:address":"534 N Sheridan Rd",
    "sg:city":"Waukegan",
    "sg:classifiers":[
        {
            "category":"Home & Garden",
            "subcategory":"Carpets & Floor Coverings",
            "type":"Retail Goods"
        }
    ],
    "sg:phone":"+1   ",
    "sg:postcode":"60085",
    "sg:province":"IL",
    "wof:name":"Joel S Carpet Service",
    "wof:placetype":"venue"
},
  "geometry": {"coordinates":[-87.830016,42.367599],"type":"Point"}
}