{
  "type": "Feature",
  "properties": {
    "addr:full":"817 Elm St Ste 206 Winnetka IL 60093",
    "addr:housenumber":"817",
    "addr:postcode":"60093",
    "addr:street":"Elm St Ste 206",
    "iso:country":"US",
    "sg:address":"817 Elm St Ste 206",
    "sg:city":"Winnetka",
    "sg:classifiers":[
        {
            "category":"Communications",
            "type":"Services"
        }
    ],
    "sg:phone":"+1 847 446 2244",
    "sg:postcode":"60093",
    "sg:province":"IL",
    "sg:tags":[
        "consultant"
    ],
    "wof:name":"Fountainhead Communications",
    "wof:placetype":"venue"
},
  "geometry": {"coordinates":[-87.73511499999999,42.10582],"type":"Point"}
}