{
  "type": "Feature",
  "properties": {
    "addr:full":"7358 Finch St Rockford IL 61108",
    "addr:housenumber":"7358",
    "addr:postcode":"61108",
    "addr:street":"Finch St",
    "iso:country":"US",
    "sg:address":"7358 Finch St",
    "sg:city":"Rockford",
    "sg:classifiers":[
        {
            "category":"Real Estate",
            "subcategory":"Real Estate Operator",
            "type":"Services"
        }
    ],
    "sg:phone":"+1 815 226 0734",
    "sg:postcode":"61108",
    "sg:province":"IL",
    "sg:tags":[
        "apartment"
    ],
    "wof:name":"Jim Benjamin Apartments",
    "wof:placetype":"venue"
},
  "geometry": {"coordinates":[-88.97447699999999,42.25412],"type":"Point"}
}