{
  "type": "Feature",
  "properties": {
    "addr:full":"117 W Main St Stewardson IL 62463",
    "addr:housenumber":"117",
    "addr:postcode":"62463",
    "addr:street":"W Main St",
    "iso:country":"US",
    "sg:address":"117 W Main St",
    "sg:city":"Stewardson",
    "sg:classifiers":[
        {
            "category":"Restaurant",
            "type":"Food & Drink"
        }
    ],
    "sg:phone":"+1 217 682 3611",
    "sg:postcode":"62463",
    "sg:province":"IL",
    "sg:tags":[
        "eating"
    ],
    "wof:name":"Loretta's Cafe",
    "wof:placetype":"venue"
},
  "geometry": {"coordinates":[-88.627977,39.263663],"type":"Point"}
}