{
  "type": "Feature",
  "properties": {
    "addr:full":"1704 Berkley St Elgin IL 60123",
    "addr:housenumber":"1704",
    "addr:postcode":"60123",
    "addr:street":"Berkley St",
    "iso:country":"US",
    "sg:address":"1704 Berkley St",
    "sg:city":"Elgin",
    "sg:classifiers":[
        {
            "category":"Building & Trades",
            "subcategory":"Electrical",
            "type":"Services"
        }
    ],
    "sg:phone":"+1 847 741 0592",
    "sg:postcode":"60123",
    "sg:province":"IL",
    "sg:tags":[
        "equipment",
        "audio",
        "video",
        "installation"
    ],
    "sg:website":"www.pinnacleav.com",
    "wof:name":"Pinnacle Audio & Video Systems",
    "wof:placetype":"venue"
},
  "geometry": {"coordinates":[-88.320834,42.022716],"type":"Point"}
}