{
  "type": "Feature",
  "properties": {
    "addr:full":"100 S Water St Decatur IL 62523",
    "addr:housenumber":"100",
    "addr:postcode":"62523",
    "addr:street":"S Water St",
    "iso:country":"US",
    "sg:address":"100 S Water St",
    "sg:city":"Decatur",
    "sg:classifiers":[
        {
            "category":"Banks & Credit Unions",
            "subcategory":"Bank",
            "type":"Services"
        },
        {
            "category":"Banks & Credit Unions",
            "subcategory":"Financial Services",
            "type":"Services"
        }
    ],
    "sg:phone":"+1 217 429 4253",
    "sg:postcode":"62523",
    "sg:province":"IL",
    "sg:tags":[
        "saving",
        "loan",
        "commercial"
    ],
    "sg:website":"http://www.regionsbank.com",
    "wof:name":"Regions Bank",
    "wof:placetype":"venue"
},
  "geometry": {"coordinates":[-88.954399,39.84145],"type":"Point"}
}