{
  "type": "Feature",
  "properties": {
    "iso:country":"US",
    "sg:address":"307 W Main St",
    "sg:city":"Ottawa",
    "sg:classifiers":[
        {
            "category":"Industrial Area",
            "type":"Public Place"
        }
    ],
    "sg:phone":"+1 815 433 3862",
    "sg:postcode":"61350",
    "sg:province":"IL",
    "sg:tags":[
        "development"
    ],
    "wof:name":"Esther Carlson",
    "wof:placetype":"venue"
},
  "geometry": {"coordinates":[-88.84423700000001,41.345741],"type":"Point"}
}