{
  "type": "Feature",
  "properties": {
    "addr:full":"320 Saint Clair Sq Fairview Heights IL 62208",
    "addr:housenumber":"320",
    "addr:postcode":"62208",
    "addr:street":"Saint Clair Sq",
    "iso:country":"US",
    "sg:address":"320 Saint Clair Sq",
    "sg:city":"Fairview Heights",
    "sg:classifiers":[
        {
            "category":"Autos & Motor Vehicles",
            "subcategory":"Auto Supplies",
            "type":"Retail Goods"
        },
        {
            "category":"Retail",
            "subcategory":"Auto Repair",
            "type":"Services"
        }
    ],
    "sg:phone":"+1 618 632 3222",
    "sg:postcode":"62208",
    "sg:province":"IL",
    "sg:tags":[
        "tire"
    ],
    "sg:website":"www.ntb.com",
    "wof:name":"National Tire & Battery",
    "wof:placetype":"venue"
},
  "geometry": {"coordinates":[-89.982451,38.593609],"type":"Point"}
}