{
  "type": "Feature",
  "properties": {
    "addr:full":"107 Main St Maple Park IL 60151",
    "addr:housenumber":"107",
    "addr:postcode":"60151",
    "addr:street":"Main St",
    "iso:country":"US",
    "sg:address":"107 Main St",
    "sg:city":"Maple Park",
    "sg:classifiers":[
        {
            "category":"Restaurant",
            "type":"Food & Drink"
        }
    ],
    "sg:phone":"+1   ",
    "sg:postcode":"60151",
    "sg:province":"IL",
    "sg:tags":[
        "eating"
    ],
    "wof:name":"Cottis On Main",
    "wof:placetype":"venue"
},
  "geometry": {"coordinates":[-88.601291,41.907921],"type":"Point"}
}