{
  "type": "Feature",
  "properties": {
    "addr:full":"122 E Fayette St Pittsfield IL 62363",
    "addr:housenumber":"122",
    "addr:postcode":"62363",
    "addr:street":"E Fayette St",
    "iso:country":"US",
    "sg:address":"122 E Fayette St",
    "sg:city":"Pittsfield",
    "sg:classifiers":[
        {
            "category":"Banks & Credit Unions",
            "subcategory":"Bank",
            "type":"Services"
        }
    ],
    "sg:phone":"+1 217 285 4909",
    "sg:postcode":"62363",
    "sg:province":"IL",
    "sg:tags":[
        "loan"
    ],
    "wof:name":"Express Payday Loan",
    "wof:placetype":"venue"
},
  "geometry": {"coordinates":[-90.805772,39.605678],"type":"Point"}
}