{
  "type": "Feature",
  "properties": {
    "iso:country":"US",
    "sg:address":"660 N Ridge Ave",
    "sg:city":"Arlington Heights",
    "sg:classifiers":[
        {
            "category":"Recreation",
            "type":"Entertainment"
        }
    ],
    "sg:phone":"+1 847 577 3025",
    "sg:postcode":"60004",
    "sg:province":"IL",
    "sg:tags":[
        "club",
        "membership"
    ],
    "wof:name":"Arlington Heights Dist Olympic",
    "wof:placetype":"venue"
},
  "geometry": {"coordinates":[-87.990272,42.090582],"type":"Point"}
}