{
  "type": "Feature",
  "properties": {
    "addr:full":"931 Lois Pl Joliet IL 60435",
    "addr:housenumber":"931",
    "addr:postcode":"60435",
    "addr:street":"Lois Pl",
    "iso:country":"US",
    "sg:address":"931 Lois Pl",
    "sg:city":"Joliet",
    "sg:classifiers":[
        {
            "category":"Social Services",
            "subcategory":"Job Training",
            "type":"Services"
        }
    ],
    "sg:phone":"+1 815 725 9288",
    "sg:postcode":"60435",
    "sg:province":"IL",
    "sg:tags":[
        "career",
        "counseling",
        "vocational"
    ],
    "wof:name":"Career Finders",
    "wof:placetype":"venue"
},
  "geometry": {"coordinates":[-88.12716399999999,41.537495],"type":"Point"}
}