{
  "type": "Feature",
  "properties": {
    "iso:country":"US",
    "sg:address":"870 N Commons Dr",
    "sg:city":"Aurora",
    "sg:classifiers":[
        {
            "category":"Manufacturing",
            "subcategory":"Glass & Minerals",
            "type":"Manufacturing & Wholesale Goods"
        }
    ],
    "sg:phone":"+1 630 375 6631",
    "sg:postcode":"60504",
    "sg:province":"IL",
    "sg:tags":[
        "device",
        "abrasive",
        "product",
        "mfg"
    ],
    "wof:name":"Cabot Microelectronics Corp",
    "wof:placetype":"venue"
},
  "geometry": {"coordinates":[-88.223253,41.774025],"type":"Point"}
}