{
  "type": "Feature",
  "properties": {
    "iso:country":"US",
    "sg:address":"405 Main St",
    "sg:city":"New Boston",
    "sg:classifiers":[
        {
            "category":"Government",
            "subcategory":"Office",
            "type":"Public Place"
        }
    ],
    "sg:phone":"+1 309 587 8181",
    "sg:postcode":"61272",
    "sg:province":"IL",
    "sg:tags":[
        "city"
    ],
    "wof:name":"New Boston City Hall",
    "wof:placetype":"venue"
},
  "geometry": {"coordinates":[-90.99669,41.170527],"type":"Point"}
}