{
  "type": "Feature",
  "properties": {
    "iso:country":"US",
    "sg:address":"1570 N Damen Ave",
    "sg:city":"Chicago",
    "sg:classifiers":[
        {
            "category":"Restaurant",
            "type":"Food & Drink"
        }
    ],
    "sg:phone":"+1 773 772 1997",
    "sg:postcode":"60622",
    "sg:province":"IL",
    "sg:tags":[
        "mexican"
    ],
    "sg:website":"www.flashtacobucktown.com",
    "wof:name":"Flash Taco",
    "wof:placetype":"venue"
},
  "geometry": {"coordinates":[-87.677678,41.91025],"type":"Point"}
}