{
  "type": "Feature",
  "properties": {
    "iso:country":"US",
    "sg:address":"13758 Poplar Grove Rd",
    "sg:city":"Poplar Grove",
    "sg:classifiers":[
        {
            "category":"Sports & Exercise",
            "subcategory":"Race Track",
            "type":"Entertainment"
        }
    ],
    "sg:phone":"+1 815 765 1705",
    "sg:postcode":"61065",
    "sg:province":"IL",
    "sg:tags":[
        "operation",
        "racing",
        "or"
    ],
    "wof:name":"David Hayward",
    "wof:placetype":"venue"
},
  "geometry": {"coordinates":[-88.82222,42.353591],"type":"Point"}
}