{
  "type": "Feature",
  "properties": {
    "addr:full":"1351 W Foster Ave Chicago IL 60640",
    "addr:housenumber":"1351",
    "addr:postcode":"60640",
    "addr:street":"W Foster Ave",
    "iso:country":"US",
    "sg:address":"1351 W Foster Ave",
    "sg:city":"Chicago",
    "sg:classifiers":[
        {
            "category":"Building & Trades",
            "subcategory":"Electrical",
            "type":"Services"
        }
    ],
    "sg:phone":"+1 773 878 0703",
    "sg:postcode":"60640",
    "sg:province":"IL",
    "sg:tags":[
        "electrician",
        "contractor"
    ],
    "wof:name":"Hiram Electrical Contractors Inc",
    "wof:placetype":"venue"
},
  "geometry": {"coordinates":[-87.66439800000001,41.976101],"type":"Point"}
}