{
  "type": "Feature",
  "properties": {
    "addr:full":"611 W 69th St Chicago IL 60621",
    "addr:housenumber":"611",
    "addr:postcode":"60621",
    "addr:street":"W 69Th St",
    "iso:country":"US",
    "sg:address":"611 W 69th St",
    "sg:city":"Chicago",
    "sg:classifiers":[
        {
            "category":"Utilities",
            "subcategory":"Recycling",
            "type":"Services"
        }
    ],
    "sg:phone":"+1 312 747 0093",
    "sg:postcode":"60621",
    "sg:province":"IL",
    "sg:tags":[
        "reduction",
        "waste"
    ],
    "sg:website":"http://www.ci.chi.il.us",
    "wof:name":"Steets & Sanitation",
    "wof:placetype":"venue"
},
  "geometry": {"coordinates":[-87.640067,41.768905],"type":"Point"}
}