{
  "type": "Feature",
  "properties": {
    "iso:country":"US",
    "sg:address":"505 Hoselton Dr",
    "sg:city":"Chenoa",
    "sg:classifiers":[
        {
            "category":"Travel",
            "subcategory":"Hotels & Motels",
            "type":"Entertainment"
        }
    ],
    "sg:phone":"+1 815 945 5900",
    "sg:postcode":"61726",
    "sg:province":"IL",
    "sg:tags":[
        "lodging"
    ],
    "sg:website":"http://www.super8.com",
    "wof:name":"Super 8 Chenoa",
    "wof:placetype":"venue"
},
  "geometry": {"coordinates":[-88.73259400000001,40.742501],"type":"Point"}
}