{
  "type": "Feature",
  "properties": {
    "iso:country":"US",
    "sg:address":"733 N Prospect Ave",
    "sg:city":"Park Ridge",
    "sg:classifiers":[
        {
            "category":"Social Services",
            "subcategory":"Adult Care",
            "type":"Services"
        }
    ],
    "sg:phone":"+1 847 692 6130",
    "sg:postcode":"60068",
    "sg:province":"IL",
    "sg:tags":[
        "state",
        "licensed",
        "institution",
        "child"
    ],
    "wof:name":"Youth Campus",
    "wof:placetype":"venue"
},
  "geometry": {"coordinates":[-87.829447,42.020744],"type":"Point"}
}