{
  "type": "Feature",
  "properties": {
    "iso:country":"US",
    "sg:address":"6032 Lincoln Ave",
    "sg:city":"Morton Grove",
    "sg:classifiers":[
        {
            "category":"Professional",
            "subcategory":"Lawyer & Legal Services",
            "type":"Services"
        }
    ],
    "sg:phone":"+1 847 965 4440",
    "sg:postcode":"60053",
    "sg:province":"IL",
    "sg:tags":[
        "law"
    ],
    "wof:name":"Gene Eich",
    "wof:placetype":"venue"
},
  "geometry": {"coordinates":[-87.777836,42.035514],"type":"Point"}
}