{
  "type": "Feature",
  "properties": {
    "iso:country":"US",
    "sg:address":"135 W 79th St",
    "sg:city":"Chicago",
    "sg:classifiers":[
        {
            "category":"Social Services",
            "type":"Services"
        }
    ],
    "sg:phone":"+1 773 543 3486",
    "sg:postcode":"60620",
    "sg:province":"IL",
    "sg:tags":[
        "human"
    ],
    "wof:name":"The Center For Community Development Initiatives",
    "wof:placetype":"venue"
},
  "geometry": {"coordinates":[-87.62824999999999,41.750858],"type":"Point"}
}