{
  "type": "Feature",
  "properties": {
    "addr:full":"2006 E Maple St Kankakee IL 60901",
    "addr:housenumber":"2006",
    "addr:postcode":"60901",
    "addr:street":"E Maple St",
    "iso:country":"US",
    "sg:address":"2006 E Maple St",
    "sg:city":"Kankakee",
    "sg:classifiers":[
        {
            "category":"Recreation",
            "subcategory":"Arcade",
            "type":"Entertainment"
        }
    ],
    "sg:phone":"+1   ",
    "sg:postcode":"60901",
    "sg:province":"IL",
    "sg:tags":[
        "operated",
        "game",
        "coin",
        "operates"
    ],
    "wof:name":"Board Machine Inc",
    "wof:placetype":"venue"
},
  "geometry": {"coordinates":[-87.840639,41.112544],"type":"Point"}
}