{
  "type": "Feature",
  "properties": {
    "addr:full":"124 S 4th St Quincy IL 62301",
    "addr:housenumber":"124",
    "addr:postcode":"62301",
    "addr:street":"S 4Th St",
    "iso:country":"US",
    "sg:address":"124 S 4th St",
    "sg:city":"Quincy",
    "sg:classifiers":[
        {
            "category":"Retail",
            "subcategory":"Auto Repair",
            "type":"Services"
        }
    ],
    "sg:phone":"+1 217 222 0197",
    "sg:postcode":"62301",
    "sg:province":"IL",
    "sg:tags":[
        "body"
    ],
    "wof:name":"Hilbing Auto Body",
    "wof:placetype":"venue"
},
  "geometry": {"coordinates":[-91.40999600000001,39.931593],"type":"Point"}
}