{
  "type": "Feature",
  "properties": {
    "addr:full":"218 N Morgan Ave Wheaton IL 60187",
    "addr:housenumber":"218",
    "addr:postcode":"60187",
    "addr:street":"N Morgan Ave",
    "iso:country":"US",
    "sg:address":"218 N Morgan Ave",
    "sg:city":"Wheaton",
    "sg:classifiers":[
        {
            "category":"Building & Trades",
            "subcategory":"Construction",
            "type":"Services"
        }
    ],
    "sg:phone":"+1 630 668 3827",
    "sg:postcode":"60187",
    "sg:province":"IL",
    "sg:tags":[
        "house"
    ],
    "wof:name":"Faith Home Improvements",
    "wof:placetype":"venue"
},
  "geometry": {"coordinates":[-88.127565,41.865609],"type":"Point"}
}