{
  "type": "Feature",
  "properties": {
    "addr:full":"28 E Jackson Blvd Ste 1004 Chicago IL 60604",
    "addr:housenumber":"28",
    "addr:postcode":"60604",
    "addr:street":"E Jackson Blvd Ste 1004",
    "iso:country":"US",
    "sg:address":"28 E Jackson Blvd Ste 1004",
    "sg:city":"Chicago",
    "sg:classifiers":[
        {
            "category":"Education",
            "subcategory":"Special Training",
            "type":"Public Place"
        }
    ],
    "sg:phone":"+1 312 362 9302",
    "sg:postcode":"60604",
    "sg:province":"IL",
    "sg:tags":[
        "adult"
    ],
    "sg:website":"www.hgchicago.org",
    "wof:name":"Henry George School",
    "wof:placetype":"venue"
},
  "geometry": {"coordinates":[-87.62653400000001,41.878237],"type":"Point"}
}