{
  "type": "Feature",
  "properties": {
    "addr:full":"110 N Franklin St Kansas IL 61933",
    "addr:housenumber":"110",
    "addr:postcode":"il 61933",
    "addr:street":"N Franklin St",
    "iso:country":"US",
    "sg:address":"110 N Franklin St",
    "sg:city":"Kansas",
    "sg:classifiers":[
        {
            "category":"Organizations",
            "subcategory":"Religious Organization",
            "type":"Services"
        }
    ],
    "sg:phone":"+1 217 948 5131",
    "sg:postcode":"61933",
    "sg:province":"IL",
    "sg:tags":[
        "church"
    ],
    "wof:name":"Kansas Christian Church",
    "wof:placetype":"venue"
},
  "geometry": {"coordinates":[-87.936072,39.553491],"type":"Point"}
}