{
  "type": "Feature",
  "properties": {
    "iso:country":"US",
    "sg:address":"1902 Hancock St",
    "sg:city":"Rockford",
    "sg:classifiers":[
        {
            "category":"Professional",
            "subcategory":"Management & Consulting",
            "type":"Services"
        }
    ],
    "sg:phone":"+1 815 963 6817",
    "sg:postcode":"61103",
    "sg:province":"IL",
    "sg:tags":[
        "consultant",
        "business"
    ],
    "wof:name":"Christopher D Gilley",
    "wof:placetype":"venue"
},
  "geometry": {"coordinates":[-89.072628,42.292962],"type":"Point"}
}