{
  "type": "Feature",
  "properties": {
    "addr:full":"4900 W 30th St Cicero IL 60804",
    "addr:housenumber":"4900",
    "addr:postcode":"60804",
    "addr:street":"W 30Th St",
    "iso:country":"US",
    "sg:address":"4900 W 30th St",
    "sg:city":"Cicero",
    "sg:classifiers":[
        {
            "category":"Food & Beverages",
            "subcategory":"Groceries & Convenience Stores",
            "type":"Retail Goods"
        }
    ],
    "sg:phone":"+1 708 222 1225",
    "sg:postcode":"60804",
    "sg:province":"IL",
    "wof:name":"Tony's Foods",
    "wof:placetype":"venue"
},
  "geometry": {"coordinates":[-87.74720000000001,41.838501],"type":"Point"}
}