{
  "type": "Feature",
  "properties": {
    "iso:country":"US",
    "sg:address":"626 River Oaks Dr",
    "sg:city":"Calumet City",
    "sg:classifiers":[
        {
            "category":"Shopping",
            "subcategory":"Pharmacy",
            "type":"Retail Goods"
        }
    ],
    "sg:phone":"+1   ",
    "sg:postcode":"60409",
    "sg:province":"IL",
    "wof:name":"Walgreens",
    "wof:placetype":"venue"
},
  "geometry": {"coordinates":[-87.540278,41.599784],"type":"Point"}
}