{
  "type": "Feature",
  "properties": {
    "addr:full":"1243 Rickert Dr Naperville IL 60540",
    "addr:housenumber":"1243",
    "addr:postcode":"60540",
    "addr:street":"Rickert Dr",
    "iso:country":"US",
    "sg:address":"1243 Rickert Dr",
    "sg:city":"Naperville",
    "sg:classifiers":[
        {
            "category":"Health Services",
            "subcategory":"Doctor",
            "type":"Services"
        }
    ],
    "sg:phone":"+1 630 527 6450",
    "sg:postcode":"60540",
    "sg:province":"IL",
    "sg:tags":[
        "physician",
        "stomach",
        "gastroenterology",
        "surgeons",
        "surgeon",
        "intestines"
    ],
    "sg:website":"http://www.sgihealth.com",
    "wof:name":"Suburban Gastroenterology",
    "wof:placetype":"venue"
},
  "geometry": {"coordinates":[-88.171694,41.749746],"type":"Point"}
}