{
  "type": "Feature",
  "properties": {
    "iso:country":"US",
    "sg:address":"6972 W North Ave",
    "sg:city":"Chicago",
    "sg:classifiers":[
        {
            "category":"Building & Trades",
            "subcategory":"Construction",
            "type":"Services"
        }
    ],
    "sg:phone":"+1 773 745 1579",
    "sg:postcode":"60707",
    "sg:province":"IL",
    "sg:tags":[
        "excavation",
        "demolition",
        "contractor"
    ],
    "wof:name":"Paige Enterprises",
    "wof:placetype":"venue"
},
  "geometry": {"coordinates":[-87.799668,41.90897],"type":"Point"}
}