{
  "type": "Feature",
  "properties": {
    "iso:country":"US",
    "sg:address":"6914 State Rte 84",
    "sg:city":"Galena",
    "sg:classifiers":[
        {
            "category":"Farming",
            "subcategory":"Livestock Farm",
            "type":"Manufacturing & Wholesale Goods"
        }
    ],
    "sg:phone":"+1 815 777 0086",
    "sg:postcode":"61036",
    "sg:province":"IL",
    "sg:tags":[
        "animal",
        "general"
    ],
    "wof:name":"Mike Hoppman",
    "wof:placetype":"venue"
},
  "geometry": {"coordinates":[-90.35833700000001,42.376734],"type":"Point"}
}