{
  "type": "Feature",
  "properties": {
    "addr:full":"1104 Foster St Evanston IL 60201",
    "addr:housenumber":"1104",
    "addr:postcode":"60201",
    "addr:street":"Foster St",
    "iso:country":"US",
    "sg:address":"1104 Foster St",
    "sg:city":"Evanston",
    "sg:classifiers":[
        {
            "category":"Building & Trades",
            "subcategory":"Landscaping Services",
            "type":"Services"
        }
    ],
    "sg:phone":"+1 847 475 4294",
    "sg:postcode":"60201",
    "sg:province":"IL",
    "sg:tags":[
        "landscape"
    ],
    "wof:name":"Minear Landscaping",
    "wof:placetype":"venue"
},
  "geometry": {"coordinates":[-87.68643299999999,42.053867],"type":"Point"}
}