{
  "type": "Feature",
  "properties": {
    "addr:full":"1 Kraft Ct Glenview IL 60025",
    "addr:housenumber":"1",
    "addr:postcode":"60025",
    "addr:street":"Kraft Ct",
    "iso:country":"US",
    "sg:address":"1 Kraft Ct",
    "sg:city":"Glenview",
    "sg:classifiers":[
        {
            "category":"Banks & Credit Unions",
            "subcategory":"Financial Services",
            "type":"Services"
        }
    ],
    "sg:phone":"+1 847 646 7077",
    "sg:postcode":"60025",
    "sg:province":"IL",
    "sg:tags":[
        "card-merchant"
    ],
    "sg:website":"http://www.americanexpress.com",
    "wof:name":"American Express",
    "wof:placetype":"venue"
},
  "geometry": {"coordinates":[-87.799622,42.05891],"type":"Point"}
}