{
  "type": "Feature",
  "properties": {
    "iso:country":"US",
    "sg:address":"2030 Middlefield Ave",
    "sg:city":"Aurora",
    "sg:classifiers":[
        {
            "category":"Wholesale",
            "subcategory":"Electrical",
            "type":"Manufacturing & Wholesale Goods"
        }
    ],
    "sg:phone":"+1 630 897 5913",
    "sg:postcode":"60506",
    "sg:province":"IL",
    "sg:tags":[
        "equipment"
    ],
    "wof:name":"Technical Theater Services",
    "wof:placetype":"venue"
},
  "geometry": {"coordinates":[-88.36439300000001,41.745721],"type":"Point"}
}