{
  "type": "Feature",
  "properties": {
    "iso:country":"US",
    "sg:address":"851 S York St",
    "sg:city":"Elmhurst",
    "sg:classifiers":[
        {
            "category":"Education",
            "subcategory":"School",
            "type":"Public Place"
        }
    ],
    "sg:phone":"+1 630 834 4931",
    "sg:postcode":"60126",
    "sg:province":"IL",
    "sg:tags":[
        "elementary"
    ],
    "wof:name":"Visitation School",
    "wof:placetype":"venue"
},
  "geometry": {"coordinates":[-87.93541500000001,41.873087],"type":"Point"}
}