{
  "type": "Feature",
  "properties": {
    "iso:country":"US",
    "sg:address":"3478 S Lott Rd",
    "sg:city":"Pearl City",
    "sg:classifiers":[
        {
            "category":"Farming",
            "subcategory":"Dairy Farm",
            "type":"Manufacturing & Wholesale Goods"
        }
    ],
    "sg:phone":"+1 815 443 2277",
    "sg:postcode":"61062",
    "sg:province":"IL",
    "wof:name":"Vincent Edler",
    "wof:placetype":"venue"
},
  "geometry": {"coordinates":[-89.84563300000001,42.252276],"type":"Point"}
}