{
  "type": "Feature",
  "properties": {
    "addr:full":"4860 W Armitage Chicago IL 60639",
    "addr:housenumber":"4860",
    "addr:postcode":"60639",
    "addr:street":"W Armitage",
    "iso:country":"US",
    "sg:address":"4860 W Armitage",
    "sg:city":"Chicago",
    "sg:classifiers":[
        {
            "category":"Personal",
            "subcategory":"Beauty Salon",
            "type":"Services"
        }
    ],
    "sg:phone":"+1 773 664 0344",
    "sg:postcode":"60639",
    "sg:province":"IL",
    "sg:tags":[
        "hair"
    ],
    "wof:name":"Oneida Unisex",
    "wof:placetype":"venue"
},
  "geometry": {"coordinates":[-87.748497,41.916927],"type":"Point"}
}