{
  "type": "Feature",
  "properties": {
    "iso:country":"US",
    "sg:address":"600 E Rand Rd",
    "sg:city":"Arlington Hts",
    "sg:classifiers":[
        {
            "category":"Food & Beverages",
            "subcategory":"Groceries & Convenience Stores",
            "type":"Retail Goods"
        }
    ],
    "sg:phone":"+1 847 577 1770",
    "sg:postcode":"60004",
    "sg:province":"IL",
    "sg:tags":[
        "grocer"
    ],
    "sg:website":"www.cubfoods.com",
    "wof:name":"Cub Foods",
    "wof:placetype":"venue"
},
  "geometry": {"coordinates":[-87.97390799999999,42.108198],"type":"Point"}
}