{
  "type": "Feature",
  "properties": {
    "iso:country":"US",
    "sg:address":"28 Summertree Ln",
    "sg:city":"Collinsville",
    "sg:classifiers":[
        {
            "category":"Building & Trades",
            "subcategory":"Construction",
            "type":"Services"
        }
    ],
    "sg:phone":"+1 618 344 2036",
    "sg:postcode":"62234",
    "sg:province":"IL",
    "sg:tags":[
        "house"
    ],
    "wof:name":"We Construction",
    "wof:placetype":"venue"
},
  "geometry": {"coordinates":[-90.000867,38.721118],"type":"Point"}
}