{
  "type": "Feature",
  "properties": {
    "addr:full":"3705 Vail Ct New Lenox IL 60451",
    "addr:housenumber":"3705",
    "addr:postcode":"60451",
    "addr:street":"Vail Ct",
    "iso:country":"US",
    "sg:address":"3705 Vail Ct",
    "sg:city":"New Lenox",
    "sg:classifiers":[
        {
            "category":"Government",
            "subcategory":"Office",
            "type":"Public Place"
        }
    ],
    "sg:phone":"+1   ",
    "sg:postcode":"60451",
    "sg:province":"IL",
    "sg:tags":[
        "agricultural",
        "regulation",
        "marketing"
    ],
    "wof:name":"Dietmar R Pantachoschka",
    "wof:placetype":"venue"
},
  "geometry": {"coordinates":[-87.99345,41.54617],"type":"Point"}
}