{
  "type": "Feature",
  "properties": {
    "iso:country":"US",
    "sg:address":"538 S 12th St",
    "sg:city":"Quincy",
    "sg:classifiers":[
        {
            "category":"Restaurant",
            "type":"Food & Drink"
        }
    ],
    "sg:phone":"+1   ",
    "sg:postcode":"62301",
    "sg:province":"IL",
    "wof:name":"Mr Bills Bar & Grill",
    "wof:placetype":"venue"
},
  "geometry": {"coordinates":[-91.396519,39.925963],"type":"Point"}
}