{
  "type": "Feature",
  "properties": {
    "iso:country":"US",
    "sg:address":"1770 S Randall Rd",
    "sg:city":"Geneva",
    "sg:classifiers":[
        {
            "category":"Insurance",
            "subcategory":"Insurance Agent",
            "type":"Services"
        }
    ],
    "sg:phone":"+1 630 208 6400",
    "sg:postcode":"60134",
    "sg:province":"IL",
    "wof:name":"Barbara Portone Karvon & Assoc",
    "wof:placetype":"venue"
},
  "geometry": {"coordinates":[-88.340294,41.870274],"type":"Point"}
}