{
  "type": "Feature",
  "properties": {
    "addr:full":"1405 18th Ave Viola IL 61486",
    "addr:housenumber":"1405",
    "addr:postcode":"61486",
    "addr:street":"18Th Ave",
    "iso:country":"US",
    "sg:address":"1405 18th Ave",
    "sg:city":"Viola",
    "sg:classifiers":[
        {
            "category":"Organizations",
            "subcategory":"Religious Organization",
            "type":"Services"
        }
    ],
    "sg:phone":"+1 309 596 2157",
    "sg:postcode":"61486",
    "sg:province":"IL",
    "sg:tags":[
        "church"
    ],
    "wof:name":"Viola United Meth Chr Kitchen",
    "wof:placetype":"venue"
},
  "geometry": {"coordinates":[-90.585651,41.202171],"type":"Point"}
}