{
  "type": "Feature",
  "properties": {
    "iso:country":"US",
    "sg:address":"4535 N Illinois St",
    "sg:city":"Belleville",
    "sg:classifiers":[
        {
            "category":"Shopping",
            "type":"Retail Goods"
        }
    ],
    "sg:phone":"+1   ",
    "sg:postcode":"62226",
    "sg:province":"IL",
    "sg:tags":[
        "merchandise"
    ],
    "wof:name":"Watts Copy Systems Inc",
    "wof:placetype":"venue"
},
  "geometry": {"coordinates":[-89.984855,38.569387],"type":"Point"}
}