{
  "type": "Feature",
  "properties": {
    "addr:full":"15 S Buffalo Grove Rd Buffalo Grove IL 60089",
    "addr:housenumber":"15",
    "addr:postcode":"60089",
    "addr:street":"S Buffalo Grove Rd",
    "iso:country":"US",
    "sg:address":"15 S Buffalo Grove Rd",
    "sg:city":"Buffalo Grove",
    "sg:classifiers":[
        {
            "category":"Shopping",
            "subcategory":"Pharmacy",
            "type":"Retail Goods"
        }
    ],
    "sg:phone":"+1   ",
    "sg:postcode":"60089",
    "sg:province":"IL",
    "sg:tags":[
        "photofinishing",
        "laboratory"
    ],
    "wof:name":"Walgreens",
    "wof:placetype":"venue"
},
  "geometry": {"coordinates":[-87.96181900000001,42.153448],"type":"Point"}
}