{
  "type": "Feature",
  "properties": {
    "iso:country":"US",
    "sg:address":"215 Barrett Ln",
    "sg:city":"Harrisburg",
    "sg:classifiers":[
        {
            "category":"Real Estate",
            "subcategory":"Real Estate Services",
            "type":"Services"
        },
        {
            "category":"Real Estate",
            "subcategory":"Surveying",
            "type":"Services"
        }
    ],
    "sg:phone":"+1 618 253 3401",
    "sg:postcode":"62946",
    "sg:province":"IL",
    "sg:tags":[
        "industrial",
        "appraisers-commercial",
        "appraiser"
    ],
    "wof:name":"Patty Carlson Appraisal Svc",
    "wof:placetype":"venue"
},
  "geometry": {"coordinates":[-88.57736300000001,37.735721],"type":"Point"}
}