{
  "type": "Feature",
  "properties": {
    "iso:country":"US",
    "sg:address":"2046 W Lake Street",
    "sg:city":"Chicago",
    "sg:classifiers":[
        {
            "category":"Food & Beverages",
            "subcategory":"Groceries & Convenience Stores",
            "type":"Retail Goods"
        }
    ],
    "sg:phone":"+1 312 455 5000",
    "sg:postcode":"60612",
    "sg:province":"IL",
    "wof:name":"T & T Food Service",
    "wof:placetype":"venue"
},
  "geometry": {"coordinates":[-87.678359,41.88503],"type":"Point"}
}