{
  "type": "Feature",
  "properties": {
    "iso:country":"US",
    "sg:address":"9800 S Vanderpoel Ave",
    "sg:city":"Chicago",
    "sg:classifiers":[
        {
            "category":"Social Services",
            "subcategory":"Child Care",
            "type":"Services"
        }
    ],
    "sg:phone":"+1 773 445 0992",
    "sg:postcode":"60643",
    "sg:province":"IL",
    "wof:name":"Betty Carter",
    "wof:placetype":"venue"
},
  "geometry": {"coordinates":[-87.66584,41.716816],"type":"Point"}
}