{
  "type": "Feature",
  "properties": {
    "iso:country":"US",
    "sg:address":"18787 E 2900 N Rd",
    "sg:city":"Odell",
    "sg:classifiers":[
        {
            "category":"Professional",
            "subcategory":"Business Services",
            "type":"Services"
        }
    ],
    "sg:phone":"+1 815 998 2069",
    "sg:postcode":"60460",
    "sg:province":"IL",
    "wof:name":"Con Man Painting",
    "wof:placetype":"venue"
},
  "geometry": {"coordinates":[-88.575993,41.048844],"type":"Point"}
}