{
  "type": "Feature",
  "properties": {
    "iso:country":"US",
    "sg:address":"100 W Superior St",
    "sg:city":"Ottawa",
    "sg:classifiers":[
        {
            "category":"Health Services",
            "subcategory":"Health Practitioner",
            "type":"Services"
        }
    ],
    "sg:phone":"+1 815 434 4516",
    "sg:postcode":"61350",
    "sg:province":"IL",
    "sg:tags":[
        "hypnotist"
    ],
    "wof:name":"Hypnosis Office",
    "wof:placetype":"venue"
},
  "geometry": {"coordinates":[-88.84266599999999,41.352145],"type":"Point"}
}