{
  "type": "Feature",
  "properties": {
    "iso:country":"US",
    "sg:address":"3400 Dundee Rd",
    "sg:city":"Northbrook",
    "sg:classifiers":[
        {
            "category":"Professional",
            "type":"Services"
        }
    ],
    "sg:phone":"+1 847 480 0998",
    "sg:postcode":"60062",
    "sg:province":"IL",
    "sg:tags":[
        "establishment"
    ],
    "wof:name":"Bunch Corp",
    "wof:placetype":"venue"
},
  "geometry": {"coordinates":[-87.858252,42.138348],"type":"Point"}
}