{
  "type": "Feature",
  "properties": {
    "addr:full":"10007 N Main St Richmond IL 60071",
    "addr:housenumber":"10007",
    "addr:postcode":"60071",
    "addr:street":"N Main St",
    "iso:country":"US",
    "sg:address":"10007 N Main St",
    "sg:city":"Richmond",
    "sg:classifiers":[
        {
            "category":"Personal",
            "type":"Services"
        },
        {
            "category":"Sports & Exercise",
            "subcategory":"Gym",
            "type":"Entertainment"
        },
        {
            "category":"Arena",
            "subcategory":"Sports Club",
            "type":"Entertainment"
        }
    ],
    "sg:phone":"+1 815 678 7627",
    "sg:postcode":"60071",
    "sg:province":"IL",
    "sg:tags":[
        "trainer",
        "consultant",
        "gymnasium",
        "health",
        "fitness",
        "physical"
    ],
    "sg:website":"http://www.snapfitness.com/richmondil?utm_source=yellowpages&utm_campaign=localmaps",
    "wof:name":"Snap Fitness",
    "wof:placetype":"venue"
},
  "geometry": {"coordinates":[-88.306528,42.470746],"type":"Point"}
}