{
  "type": "Feature",
  "properties": {
    "addr:full":"709 Hingham Ln Schaumburg IL 60193",
    "addr:housenumber":"709",
    "addr:postcode":"60193",
    "addr:street":"Hingham Ln",
    "iso:country":"US",
    "sg:address":"709 Hingham Ln",
    "sg:city":"Schaumburg",
    "sg:classifiers":[
        {
            "category":"Personal",
            "type":"Services"
        },
        {
            "category":"Professional",
            "subcategory":"Art Services",
            "type":"Services"
        }
    ],
    "sg:phone":"+1 847 301 0991",
    "sg:postcode":"60193",
    "sg:province":"IL",
    "sg:tags":[
        "photography",
        "videography",
        "wedding"
    ],
    "wof:name":"Joel Photo",
    "wof:placetype":"venue"
},
  "geometry": {"coordinates":[-88.104266,42.013075],"type":"Point"}
}