{
  "type": "Feature",
  "properties": {
    "addr:full":"1500 Hemlock Knoll Ter Northbrook IL 60062",
    "addr:housenumber":"1500",
    "addr:postcode":"60062",
    "addr:street":"Hemlock Knoll Ter",
    "iso:country":"US",
    "sg:address":"1500 Hemlock Knoll Ter",
    "sg:city":"Northbrook",
    "sg:classifiers":[
        {
            "category":"Shopping",
            "subcategory":"Gifts & Souvenirs",
            "type":"Retail Goods"
        }
    ],
    "sg:phone":"+1 847 564 7704",
    "sg:postcode":"60062",
    "sg:province":"IL",
    "sg:tags":[
        "shop"
    ],
    "wof:name":"Special Gifts Theatre, Inc.",
    "wof:placetype":"venue"
},
  "geometry": {"coordinates":[-87.86034600000001,42.126199],"type":"Point"}
}