{
  "type": "Feature",
  "properties": {
    "iso:country":"US",
    "sg:address":"2132 W Fulton",
    "sg:city":"Chicago",
    "sg:classifiers":[
        {
            "category":"Shopping",
            "type":"Retail Goods"
        }
    ],
    "sg:phone":"+1 312 226 2221",
    "sg:postcode":"60302",
    "sg:province":"IL",
    "sg:website":"www.revisionchicago.com",
    "wof:name":"Revision Home",
    "wof:placetype":"venue"
},
  "geometry": {"coordinates":[-87.68114799999999,41.886727],"type":"Point"}
}