{
  "type": "Feature",
  "properties": {
    "iso:country":"US",
    "sg:address":"220 Alessio Dr",
    "sg:city":"Joliet",
    "sg:classifiers":[
        {
            "category":"Wholesale",
            "subcategory":"Machinery & Supplies",
            "type":"Manufacturing & Wholesale Goods"
        }
    ],
    "sg:phone":"+1 815 727 7776",
    "sg:postcode":"60433",
    "sg:province":"IL",
    "sg:tags":[
        "rope"
    ],
    "sg:website":"www.phoenixrope.com",
    "wof:name":"Phoenix Rope & Cordage Co Inc",
    "wof:placetype":"venue"
},
  "geometry": {"coordinates":[-88.072626,41.500465],"type":"Point"}
}