{
  "type": "Feature",
  "properties": {
    "addr:full":"1450 E Co Rd 300N Arcola IL 61910",
    "addr:housenumber":"1450;300n",
    "addr:postcode":"61910",
    "addr:street":"E Co Rd",
    "iso:country":"US",
    "sg:address":"1450 E Co Rd 300N",
    "sg:city":"Arcola",
    "sg:classifiers":[
        {
            "category":"Real Estate",
            "subcategory":"Real Estate Operator",
            "type":"Services"
        }
    ],
    "sg:phone":"+1 217 268 3253",
    "sg:postcode":"61910",
    "sg:province":"IL",
    "sg:tags":[
        "property",
        "lessor"
    ],
    "wof:name":"Barbara Eckstein",
    "wof:placetype":"venue"
},
  "geometry": {"coordinates":[-88.205482,39.695429],"type":"Point"}
}