{
  "type": "Feature",
  "properties": {
    "addr:full":"126 River Mist Dr Oswego IL 60543",
    "addr:housenumber":"126",
    "addr:postcode":"60543",
    "addr:street":"River Mist Dr",
    "iso:country":"US",
    "sg:address":"126 River Mist Dr",
    "sg:city":"Oswego",
    "sg:classifiers":[
        {
            "category":"Professional",
            "subcategory":"Accounting & Tax Preparation",
            "type":"Services"
        }
    ],
    "sg:phone":"+1 630 551 1097",
    "sg:postcode":"60543",
    "sg:province":"IL",
    "sg:tags":[
        "bookkeeping",
        "billing"
    ],
    "wof:name":"R.L. Billing",
    "wof:placetype":"venue"
},
  "geometry": {"coordinates":[-88.35199,41.694],"type":"Point"}
}