{
  "type": "Feature",
  "properties": {
    "addr:full":"7629 W Rascher Ave Chicago IL 60656",
    "addr:housenumber":"7629",
    "addr:postcode":"60656",
    "addr:street":"W Rascher Ave",
    "iso:country":"US",
    "sg:address":"7629 W Rascher Ave",
    "sg:city":"Chicago",
    "sg:classifiers":[
        {
            "category":"Building & Trades",
            "subcategory":"Landscaping Services",
            "type":"Services"
        }
    ],
    "sg:phone":"+1 773 631 5360",
    "sg:postcode":"60656",
    "sg:province":"IL",
    "sg:tags":[
        "lawn",
        "garden",
        "landscape"
    ],
    "wof:name":"Matts Landscaping Contrs Ltd",
    "wof:placetype":"venue"
},
  "geometry": {"coordinates":[-87.819193,41.97869],"type":"Point"}
}