{
  "type": "Feature",
  "properties": {
    "addr:full":"1400 W Hudson Dr Litchfield IL 62056",
    "addr:housenumber":"1400",
    "addr:postcode":"62056",
    "addr:street":"W Hudson Dr",
    "iso:country":"US",
    "sg:address":"1400 W Hudson Dr",
    "sg:city":"Litchfield",
    "sg:classifiers":[
        {
            "category":"Manufacturing",
            "subcategory":"Tools & Machinery",
            "type":"Manufacturing & Wholesale Goods"
        }
    ],
    "sg:phone":"+1 217 324 6527",
    "sg:postcode":"62056",
    "sg:province":"IL",
    "sg:tags":[
        "die",
        "maker"
    ],
    "wof:name":"County Tool & Die",
    "wof:placetype":"venue"
},
  "geometry": {"coordinates":[-89.672802,39.175268],"type":"Point"}
}