{
  "type": "Feature",
  "properties": {
    "addr:full":"1921 Raymond Dr Northbrook IL 60062",
    "addr:housenumber":"1921",
    "addr:postcode":"60062",
    "addr:street":"Raymond Dr",
    "iso:country":"US",
    "sg:address":"1921 Raymond Dr",
    "sg:city":"Northbrook",
    "sg:classifiers":[
        {
            "category":"Food & Beverages",
            "subcategory":"Groceries & Convenience Stores",
            "type":"Retail Goods"
        }
    ],
    "sg:phone":"+1   ",
    "sg:postcode":"60062",
    "sg:province":"IL",
    "wof:name":"Sunset Food & Central Kitchen",
    "wof:placetype":"venue"
},
  "geometry": {"coordinates":[-87.826809,42.111798],"type":"Point"}
}