{
  "type": "Feature",
  "properties": {
    "iso:country":"US",
    "sg:address":"16076 Marion Dr",
    "sg:city":"South Holland",
    "sg:classifiers":[
        {
            "category":"Professional",
            "subcategory":"Management & Consulting",
            "type":"Services"
        }
    ],
    "sg:phone":"+1 708 331 0020",
    "sg:postcode":"60473",
    "sg:province":"IL",
    "sg:tags":[
        "business"
    ],
    "wof:name":"Jurare Conference Group",
    "wof:placetype":"venue"
},
  "geometry": {"coordinates":[-87.593798,41.602753],"type":"Point"}
}