{
  "type": "Feature",
  "properties": {
    "addr:full":"18130 NW Frontage Rd Joliet IL 60404",
    "addr:housenumber":"18130",
    "addr:postcode":"60404",
    "addr:street":"Nw Frontage Rd",
    "iso:country":"US",
    "sg:address":"18130 NW Frontage Rd",
    "sg:city":"Joliet",
    "sg:classifiers":[
        {
            "category":"Building & Trades",
            "subcategory":"Construction",
            "type":"Services"
        }
    ],
    "sg:phone":"+1 815 439 8382",
    "sg:postcode":"60404",
    "sg:province":"IL",
    "sg:tags":[
        "contractor"
    ],
    "wof:name":"S & L Roofing Inc",
    "wof:placetype":"venue"
},
  "geometry": {"coordinates":[-89.642105,39.270151],"type":"Point"}
}