{
  "type": "Feature",
  "properties": {
    "iso:country":"US",
    "sg:address":"2655 W Huron St",
    "sg:city":"Chicago",
    "sg:classifiers":[
        {
            "category":"Bakery",
            "type":"Food & Drink"
        }
    ],
    "sg:phone":"+1 773 276 4233",
    "sg:postcode":"60612",
    "sg:province":"IL",
    "wof:name":"C& C Bakery",
    "wof:placetype":"venue"
},
  "geometry": {"coordinates":[-87.693258,41.893855],"type":"Point"}
}