{
  "type": "Feature",
  "properties": {
    "iso:country":"US",
    "sg:address":"7202 W 114th St",
    "sg:city":"Worth",
    "sg:classifiers":[
        {
            "category":"Home & Garden",
            "subcategory":"Household Appliances",
            "type":"Retail Goods"
        }
    ],
    "sg:phone":"+1   ",
    "sg:postcode":"60482",
    "sg:province":"IL",
    "sg:tags":[
        "repair",
        "electrical"
    ],
    "wof:name":"Toms Appliance Service",
    "wof:placetype":"venue"
},
  "geometry": {"coordinates":[-87.79785099999999,41.684491],"type":"Point"}
}