{
  "type": "Feature",
  "properties": {
    "addr:full":"3207 Howard St Skokie IL 60076",
    "addr:housenumber":"3207",
    "addr:postcode":"60076",
    "addr:street":"Howard St",
    "iso:country":"US",
    "sg:address":"3207 Howard St",
    "sg:city":"Skokie",
    "sg:classifiers":[
        {
            "category":"Insurance",
            "subcategory":"Insurance Agent",
            "type":"Services"
        }
    ],
    "sg:phone":"+1 847 410 0475",
    "sg:postcode":"60076",
    "sg:province":"IL",
    "wof:name":"American Family Insurance",
    "wof:placetype":"venue"
},
  "geometry": {"coordinates":[-87.710159,42.019041],"type":"Point"}
}