{
  "type": "Feature",
  "properties": {
    "addr:full":"58 N Ridgemoor Ave Mundelein IL 60060",
    "addr:housenumber":"58",
    "addr:postcode":"60060",
    "addr:street":"N Ridgemoor Ave",
    "iso:country":"US",
    "sg:address":"58 N Ridgemoor Ave",
    "sg:city":"Mundelein",
    "sg:classifiers":[
        {
            "category":"Retail",
            "subcategory":"Auto Repair",
            "type":"Services"
        }
    ],
    "sg:phone":"+1 847 566 7296",
    "sg:postcode":"60060",
    "sg:province":"IL",
    "sg:tags":[
        "automotive"
    ],
    "wof:name":"Behning Towing",
    "wof:placetype":"venue"
},
  "geometry": {"coordinates":[-88.016392,42.263282],"type":"Point"}
}