{
  "type": "Feature",
  "properties": {
    "addr:full":"2000 N Neil St Spc 708 Champaign IL 61820",
    "addr:housenumber":"2000",
    "addr:postcode":"708;61820",
    "addr:street":"N Neil St",
    "iso:country":"US",
    "sg:address":"2000 N Neil St Spc 708",
    "sg:city":"Champaign",
    "sg:classifiers":[
        {
            "category":"Restaurant",
            "type":"Food & Drink"
        }
    ],
    "sg:phone":"+1 217 355 1159",
    "sg:postcode":"61820",
    "sg:province":"IL",
    "sg:tags":[
        "pizza"
    ],
    "wof:name":"Sbarro Inc",
    "wof:placetype":"venue"
},
  "geometry": {"coordinates":[-88.243471,40.13797],"type":"Point"}
}