{
  "type": "Feature",
  "properties": {
    "addr:full":"3830 Wisman Ln Quincy IL 62305",
    "addr:housenumber":"3830",
    "addr:postcode":"62305",
    "addr:street":"Wisman Ln",
    "iso:country":"US",
    "sg:address":"3830 Wisman Ln",
    "sg:city":"Quincy",
    "sg:classifiers":[
        {
            "category":"Autos & Motor Vehicles",
            "subcategory":"Automobile Sales",
            "type":"Retail Goods"
        },
        {
            "category":"Manufacturing",
            "subcategory":"Motor Vehicles & Parts",
            "type":"Manufacturing & Wholesale Goods"
        },
        {
            "category":"Professional",
            "subcategory":"Employment Agencies",
            "type":"Services"
        },
        {
            "category":"Wholesale",
            "subcategory":"Auto Parts",
            "type":"Manufacturing & Wholesale Goods"
        },
        {
            "category":"Retail",
            "subcategory":"Auto Repair",
            "type":"Services"
        }
    ],
    "sg:phone":"+1 217 919 0137",
    "sg:postcode":"62305",
    "sg:province":"IL",
    "sg:tags":[
        "engines-diesel",
        "used",
        "recreational",
        "truck",
        "equipment",
        "buses-repair",
        "new",
        "campers-repair"
    ],
    "sg:website":"http://www.midwayfreightliner.com",
    "wof:name":"Midway Freightliner Inc",
    "wof:placetype":"venue"
},
  "geometry": {"coordinates":[-91.35140800000001,39.95715],"type":"Point"}
}