{
  "type": "Feature",
  "properties": {
    "addr:full":"3922 N Elston Ave Chicago IL 60618",
    "addr:housenumber":"3922",
    "addr:postcode":"60618",
    "addr:street":"N Elston Ave",
    "iso:country":"US",
    "sg:address":"3922 N Elston Ave",
    "sg:city":"Chicago",
    "sg:classifiers":[
        {
            "category":"Restaurant",
            "type":"Food & Drink"
        }
    ],
    "sg:menulink":"http://www.allmenus.com/il/chicago/214469-thai-thai-restaurant/menu/",
    "sg:phone":"+1 773 478 1079",
    "sg:postcode":"60618",
    "sg:province":"IL",
    "sg:tags":[
        "thai",
        "asian"
    ],
    "wof:name":"Thai Thai Restaurant",
    "wof:placetype":"venue"
},
  "geometry": {"coordinates":[-87.717124,41.952263],"type":"Point"}
}