{
  "type": "Feature",
  "properties": {
    "iso:country":"US",
    "sg:address":"105 3rd St",
    "sg:city":"Bloomingdale",
    "sg:classifiers":[
        {
            "category":"Health Services",
            "subcategory":"Doctor",
            "type":"Services"
        }
    ],
    "sg:phone":"+1 630 282 4546",
    "sg:postcode":"60108",
    "sg:province":"IL",
    "sg:tags":[
        "practice",
        "family"
    ],
    "sg:website":"www.familydoctor.net",
    "wof:name":"Davida Arthur I MD PC",
    "wof:placetype":"venue"
},
  "geometry": {"coordinates":[-88.082199,41.9575],"type":"Point"}
}