{
  "type": "Feature",
  "properties": {
    "addr:full":"1146 W Pratt Blvd Chicago IL 60626",
    "addr:housenumber":"1146",
    "addr:postcode":"60626",
    "addr:street":"W Pratt Blvd",
    "iso:country":"US",
    "sg:address":"1146 W Pratt Blvd",
    "sg:city":"Chicago",
    "sg:classifiers":[
        {
            "category":"Building & Trades",
            "subcategory":"Construction",
            "type":"Services"
        }
    ],
    "sg:phone":"+1 800 222 6815",
    "sg:postcode":"60626",
    "sg:province":"IL",
    "sg:tags":[
        "altering",
        "consultant",
        "remodeling",
        "contractor"
    ],
    "wof:name":"Rapid Restoration- Emergency Sewage Damage Clean-up, Water Damage Restoration",
    "wof:placetype":"venue"
},
  "geometry": {"coordinates":[-87.660134,42.005545],"type":"Point"}
}