{
  "type": "Feature",
  "properties": {
    "iso:country":"US",
    "sg:address":"1856 N Richmond St",
    "sg:city":"Chicago",
    "sg:classifiers":[
        {
            "category":"Food & Beverages",
            "subcategory":"Groceries & Convenience Stores",
            "type":"Retail Goods"
        }
    ],
    "sg:phone":"+1 773 252 0906",
    "sg:postcode":"60647",
    "sg:province":"IL",
    "wof:name":"Carniceria Y Taqueria Guerro",
    "wof:placetype":"venue"
},
  "geometry": {"coordinates":[-87.700542,41.914901],"type":"Point"}
}