{
  "type": "Feature",
  "properties": {
    "iso:country":"US",
    "sg:address":"2106 W Devon Ave",
    "sg:city":"Chicago",
    "sg:classifiers":[
        {
            "category":"Shopping",
            "subcategory":"Used Merchandise",
            "type":"Retail Goods"
        }
    ],
    "sg:phone":"+1 773 274 4653",
    "sg:postcode":"60659",
    "sg:province":"IL",
    "sg:tags":[
        "shop",
        "loan",
        "pawn"
    ],
    "wof:name":"Devon Pawn Shop Inc",
    "wof:placetype":"venue"
},
  "geometry": {"coordinates":[-87.683094,41.998086],"type":"Point"}
}