{
  "type": "Feature",
  "properties": {
    "addr:full":"2800 N Pine Grove Ave Chicago IL 60657",
    "addr:housenumber":"2800",
    "addr:postcode":"60657",
    "addr:street":"N Pine Grove Ave",
    "iso:country":"US",
    "sg:address":"2800 N Pine Grove Ave",
    "sg:city":"Chicago",
    "sg:classifiers":[
        {
            "category":"Professional",
            "subcategory":"Business Services",
            "type":"Services"
        }
    ],
    "sg:phone":"+1 312 551 1400",
    "sg:postcode":"60657",
    "sg:province":"IL",
    "sg:tags":[
        "home",
        "inspection"
    ],
    "wof:name":"Home Analysis Group Inc",
    "wof:placetype":"venue"
},
  "geometry": {"coordinates":[-87.641374,41.933389],"type":"Point"}
}