{
  "type": "Feature",
  "properties": {
    "iso:country":"US",
    "sg:address":"23851 N Lakeside Dr",
    "sg:city":"Lake Zurich",
    "sg:classifiers":[
        {
            "category":"Building & Trades",
            "subcategory":"Cleaning & Sanitation",
            "type":"Services"
        }
    ],
    "sg:phone":"+1 847 540 6065",
    "sg:postcode":"60047",
    "sg:province":"IL",
    "sg:tags":[
        "janitor"
    ],
    "wof:name":"Spirek Co",
    "wof:placetype":"venue"
},
  "geometry": {"coordinates":[-88.052158,42.210048],"type":"Point"}
}