{
  "type": "Feature",
  "properties": {
    "iso:country":"US",
    "sg:address":"302 Neuman Ct",
    "sg:city":"Lake Bluff",
    "sg:classifiers":[
        {
            "category":"Wholesale",
            "subcategory":"Stationery",
            "type":"Manufacturing & Wholesale Goods"
        },
        {
            "category":"Professional",
            "subcategory":"Business Services",
            "type":"Services"
        }
    ],
    "sg:phone":"+1 847 615 2121",
    "sg:postcode":"60044",
    "sg:province":"IL",
    "sg:tags":[
        "packaging",
        "material"
    ],
    "wof:name":"R C Packaging Co",
    "wof:placetype":"venue"
},
  "geometry": {"coordinates":[-87.839014,42.275857],"type":"Point"}
}