{
  "type": "Feature",
  "properties": {
    "iso:country":"US",
    "sg:address":"5050 N Cumberland Ave Ste 21",
    "sg:city":"Norridge",
    "sg:classifiers":[
        {
            "category":"Deli",
            "type":"Food & Drink"
        },
        {
            "category":"Food & Beverages",
            "subcategory":"Bakery",
            "type":"Retail Goods"
        }
    ],
    "sg:phone":"+1 708 452 6956",
    "sg:postcode":"60706",
    "sg:province":"IL",
    "sg:tags":[
        "sandwich"
    ],
    "wof:name":"Donna's Deli",
    "wof:placetype":"venue"
},
  "geometry": {"coordinates":[-87.836376,41.971391],"type":"Point"}
}