{
  "type": "Feature",
  "properties": {
    "iso:country":"US",
    "sg:address":"10 Executive Woods Ct",
    "sg:city":"Swansea",
    "sg:classifiers":[
        {
            "category":"Professional",
            "subcategory":"Lawyer & Legal Services",
            "type":"Services"
        }
    ],
    "sg:phone":"+1 618 277 1180",
    "sg:postcode":"62226",
    "sg:province":"IL",
    "wof:name":"Korein Tillery Llc",
    "wof:placetype":"venue"
},
  "geometry": {"coordinates":[-89.9842,38.562698],"type":"Point"}
}