{
  "type": "Feature",
  "properties": {
    "iso:country":"US",
    "sg:address":"100 Campus View Dr",
    "sg:city":"Lincoln",
    "sg:classifiers":[
        {
            "category":"Organizations",
            "subcategory":"Religious Organization",
            "type":"Services"
        }
    ],
    "sg:phone":"+1 217 732 6330",
    "sg:postcode":"62656",
    "sg:province":"IL",
    "wof:name":"Haitian Christian Outreach",
    "wof:placetype":"venue"
},
  "geometry": {"coordinates":[-89.34886,40.149746],"type":"Point"}
}