{
  "type": "Feature",
  "properties": {
    "addr:full":"1881 Commerce Dr Elk Grove Village IL 60007",
    "addr:housenumber":"1881",
    "addr:postcode":"60007",
    "addr:street":"Commerce Dr",
    "iso:country":"US",
    "sg:address":"1881 Commerce Dr",
    "sg:city":"Elk Grove Village",
    "sg:classifiers":[
        {
            "category":"Wholesale",
            "subcategory":"Stationery",
            "type":"Manufacturing & Wholesale Goods"
        }
    ],
    "sg:phone":"+1 847 718 1800",
    "sg:postcode":"60007",
    "sg:province":"IL",
    "sg:tags":[
        "business",
        "form"
    ],
    "wof:name":"Pinnacle Graphic & Promotions",
    "wof:placetype":"venue"
},
  "geometry": {"coordinates":[-87.95935799999999,42.020101],"type":"Point"}
}