{
  "type": "Feature",
  "properties": {
    "addr:full":"1812 E 1130 North Rd Milford IL 60953",
    "addr:housenumber":"1812",
    "addr:postcode":"60953",
    "addr:street":"E 1130 North Rd",
    "iso:country":"US",
    "sg:address":"1812 E 1130 North Rd",
    "sg:city":"Milford",
    "sg:classifiers":[
        {
            "category":"Place Of Worship",
            "subcategory":"Church",
            "type":"Public Place"
        },
        {
            "category":"Place Of Worship",
            "type":"Public Place"
        }
    ],
    "sg:phone":"+1 815 889 4750",
    "sg:postcode":"60953",
    "sg:province":"IL",
    "sg:tags":[
        "lutheran",
        "america",
        "churches-lutheran",
        "churches-lutheran-evangelical"
    ],
    "wof:name":"St John's Lutheran Church",
    "wof:placetype":"venue"
},
  "geometry": {"coordinates":[-87.78827200000001,40.661025],"type":"Point"}
}