{
  "type": "Feature",
  "properties": {
    "addr:full":"1110 Peoria St Washington IL 61536",
    "addr:housenumber":"1110",
    "addr:postcode":"61536",
    "addr:street":"Peoria St",
    "iso:country":"US",
    "sg:address":"1110 Peoria St",
    "sg:city":"Washington",
    "sg:classifiers":[
        {
            "category":"Banks & Credit Unions",
            "subcategory":"Bank",
            "type":"Services"
        }
    ],
    "sg:phone":"+1 309 444 2265",
    "sg:postcode":"61536",
    "sg:province":"IL",
    "wof:name":"Washington State Bank",
    "wof:placetype":"venue"
},
  "geometry": {"coordinates":[-89.79571900000001,40.694141],"type":"Point"}
}