{
  "type": "Feature",
  "properties": {
    "addr:full":"307 N Michigan Ave Ste 924 Chicago IL 60601",
    "addr:housenumber":"307",
    "addr:postcode":"60601",
    "addr:street":"N Michigan Ave Ste 924",
    "iso:country":"US",
    "sg:address":"307 N Michigan Ave Ste 924",
    "sg:city":"Chicago",
    "sg:classifiers":[
        {
            "category":"Professional",
            "subcategory":"Lawyer & Legal Services",
            "type":"Services"
        }
    ],
    "sg:phone":"+1 312 553 4419",
    "sg:postcode":"60601",
    "sg:province":"IL",
    "sg:tags":[
        "information",
        "attorney",
        "referral"
    ],
    "sg:website":"http://www.siebert-immigrationlaw.com",
    "wof:name":"William Siebert and Associates",
    "wof:placetype":"venue"
},
  "geometry": {"coordinates":[-87.624174,41.886989],"type":"Point"}
}