{
  "type": "Feature",
  "properties": {
    "iso:country":"US",
    "sg:address":"10385 E 1680 North Rd",
    "sg:city":"Oakwood",
    "sg:classifiers":[
        {
            "category":"Retail",
            "subcategory":"Auto Repair",
            "type":"Services"
        }
    ],
    "sg:phone":"+1 217 354 2330",
    "sg:postcode":"61858",
    "sg:province":"IL",
    "sg:tags":[
        "repairing",
        "automobile"
    ],
    "wof:name":"Rocky Acres Gas & Diesel Rpr",
    "wof:placetype":"venue"
},
  "geometry": {"coordinates":[-87.748153,40.114645],"type":"Point"}
}