{
  "type": "Feature",
  "properties": {
    "addr:full":"1 S Wacker Dr Ste 1750 Suite 2150 Chicago IL 60606",
    "addr:housenumber":"1;1750 suite 2150",
    "addr:postcode":"60606",
    "addr:street":"S;Dr Ste",
    "iso:country":"US",
    "sg:address":"1 S Wacker Dr Ste 1750 Suite 2150",
    "sg:city":"Chicago",
    "sg:classifiers":[
        {
            "category":"Professional",
            "subcategory":"Lawyer & Legal Services",
            "type":"Services"
        }
    ],
    "sg:phone":"+1 312 372 1010",
    "sg:postcode":"60606",
    "sg:province":"IL",
    "wof:name":"Major Lindsey & Africa",
    "wof:placetype":"venue"
},
  "geometry": {"coordinates":[-87.63673,41.881902],"type":"Point"}
}