{
  "type": "Feature",
  "properties": {
    "iso:country":"US",
    "sg:address":"529 Davis St",
    "sg:city":"Evanston",
    "sg:classifiers":[
        {
            "category":"Shopping",
            "subcategory":"Jewelry",
            "type":"Retail Goods"
        }
    ],
    "sg:phone":"+1 847 328 4567",
    "sg:postcode":"60201",
    "sg:province":"IL",
    "sg:tags":[
        "precious",
        "metal",
        "mfg"
    ],
    "wof:name":"Alston Jewelers & Mfg",
    "wof:placetype":"venue"
},
  "geometry": {"coordinates":[-87.678444,42.045941],"type":"Point"}
}