{
  "type": "Feature",
  "properties": {
    "addr:full":"1112 4th St Fulton IL 61252",
    "addr:housenumber":"1112",
    "addr:postcode":"61252",
    "addr:street":"4Th St",
    "iso:country":"US",
    "sg:address":"1112 4th St",
    "sg:city":"Fulton",
    "sg:classifiers":[
        {
            "category":"Bars & Pubs",
            "type":"Food & Drink"
        }
    ],
    "sg:phone":"+1   ",
    "sg:postcode":"61252",
    "sg:province":"IL",
    "sg:tags":[
        "drinking"
    ],
    "wof:name":"Paddle Wheel Pizza & Pub",
    "wof:placetype":"venue"
},
  "geometry": {"coordinates":[-90.165775,41.866171],"type":"Point"}
}