{
  "type": "Feature",
  "properties": {
    "iso:country":"US",
    "sg:address":"4216 W Division St",
    "sg:city":"Chicago",
    "sg:classifiers":[
        {
            "category":"Retail",
            "subcategory":"Auto Repair",
            "type":"Services"
        }
    ],
    "sg:phone":"+1 773 342 8284",
    "sg:postcode":"60651",
    "sg:province":"IL",
    "wof:name":"Moran Auto Repair",
    "wof:placetype":"venue"
},
  "geometry": {"coordinates":[-87.732399,41.902599],"type":"Point"}
}