{
  "type": "Feature",
  "properties": {
    "addr:full":"1 Dogwood St Park Forest IL 60466",
    "addr:housenumber":"1",
    "addr:postcode":"60466",
    "addr:street":"Dogwood St",
    "iso:country":"US",
    "sg:address":"1 Dogwood St",
    "sg:city":"Park Forest",
    "sg:classifiers":[
        {
            "category":"Social Services",
            "subcategory":"Child Care",
            "type":"Services"
        }
    ],
    "sg:phone":"+1 708 283 2625",
    "sg:postcode":"60466",
    "sg:province":"IL",
    "wof:name":"Bright Horizons Child Dev Ctr",
    "wof:placetype":"venue"
},
  "geometry": {"coordinates":[-87.671645,41.485938],"type":"Point"}
}