{
  "type": "Feature",
  "properties": {
    "iso:country":"US",
    "sg:address":"600 W Macarthur Dr",
    "sg:city":"Cottage Hills",
    "sg:classifiers":[
        {
            "category":"Home & Garden",
            "subcategory":"Building Materials",
            "type":"Retail Goods"
        }
    ],
    "sg:phone":"+1 618 258 7500",
    "sg:postcode":"62018",
    "sg:province":"IL",
    "sg:tags":[
        "lumber"
    ],
    "sg:website":"www.landreth.doitbest.com",
    "wof:name":"Landreth Lumber Company",
    "wof:placetype":"venue"
},
  "geometry": {"coordinates":[-90.08255200000001,38.906152],"type":"Point"}
}