{
  "type": "Feature",
  "properties": {
    "iso:country":"US",
    "sg:address":"210 E Walnut St",
    "sg:city":"Carbondale",
    "sg:classifiers":[
        {
            "category":"Home & Garden",
            "subcategory":"Garden Supply",
            "type":"Retail Goods"
        }
    ],
    "sg:phone":"+1 618 529 0181",
    "sg:postcode":"62901",
    "sg:province":"IL",
    "sg:tags":[
        "lawn",
        "mower"
    ],
    "wof:name":"Coleman Lawn",
    "wof:placetype":"venue"
},
  "geometry": {"coordinates":[-89.21355,37.725597],"type":"Point"}
}