{
  "type": "Feature",
  "properties": {
    "addr:full":"4654 Church St Skokie IL 60076",
    "addr:housenumber":"4654",
    "addr:postcode":"60076",
    "addr:street":"Church St",
    "iso:country":"US",
    "sg:address":"4654 Church St",
    "sg:city":"Skokie",
    "sg:classifiers":[
        {
            "category":"Restaurant",
            "type":"Food & Drink"
        }
    ],
    "sg:menulink":"http://www.allmenus.com/il/niles/283318-thai-pavillion/menu/",
    "sg:phone":"+1 847 677 1068",
    "sg:postcode":"60076",
    "sg:province":"IL",
    "sg:tags":[
        "thai",
        "asian"
    ],
    "wof:name":"Thai Pavillion",
    "wof:placetype":"venue"
},
  "geometry": {"coordinates":[-87.74376700000001,42.048191],"type":"Point"}
}