{
  "type": "Feature",
  "properties": {
    "addr:full":"845 Patricia Ave Elgin IL 60120",
    "addr:housenumber":"845",
    "addr:postcode":"60120",
    "addr:street":"Patricia Ave",
    "iso:country":"US",
    "sg:address":"845 Patricia Ave",
    "sg:city":"Elgin",
    "sg:classifiers":[
        {
            "category":"Education",
            "subcategory":"Special Training",
            "type":"Public Place"
        }
    ],
    "sg:phone":"+1 847 289 0540",
    "sg:postcode":"60120",
    "sg:province":"IL",
    "sg:tags":[
        "adult"
    ],
    "wof:name":"John Slimp Training and Development",
    "wof:placetype":"venue"
},
  "geometry": {"coordinates":[-88.258202,42.053939],"type":"Point"}
}