{
  "type": "Feature",
  "properties": {
    "addr:full":"155 Old Farm Middle Ct Bradley IL 60915",
    "addr:housenumber":"155",
    "addr:postcode":"60915",
    "addr:street":"Middle Ct",
    "iso:country":"US",
    "sg:address":"155 Old Farm Middle Ct",
    "sg:city":"Bradley",
    "sg:classifiers":[
        {
            "category":"Government",
            "subcategory":"Police Station",
            "type":"Public Place"
        }
    ],
    "sg:phone":"+1   ",
    "sg:postcode":"60915",
    "sg:province":"IL",
    "sg:tags":[
        "protection"
    ],
    "wof:name":"Manteno Police Dept",
    "wof:placetype":"venue"
},
  "geometry": {"coordinates":[-87.83921100000001,41.153542],"type":"Point"}
}