{
  "type": "Feature",
  "properties": {
    "addr:full":"7059 S South Shore Drive Chicago IL 60686",
    "addr:housenumber":"7059",
    "addr:postcode":"60686",
    "addr:street":"S South Shore Drive",
    "iso:country":"US",
    "sg:address":"7059 S South Shore Drive",
    "sg:city":"Chicago",
    "sg:classifiers":[
        {
            "category":"Sports & Exercise",
            "subcategory":"Golf",
            "type":"Entertainment"
        }
    ],
    "sg:phone":"+1 773 256 0986",
    "sg:postcode":"60686",
    "sg:province":"IL",
    "sg:website":"www.cpdgolf.com/layout10.asp?id=...",
    "wof:name":"South Shore Golf Course",
    "wof:placetype":"venue"
},
  "geometry": {"coordinates":[-87.566299,41.7668],"type":"Point"}
}