{
  "type": "Feature",
  "properties": {
    "addr:full":"5431 S Brookstone Dr Rochelle IL 61068",
    "addr:housenumber":"5431",
    "addr:postcode":"61068",
    "addr:street":"S Brookstone Dr",
    "iso:country":"US",
    "sg:address":"5431 S Brookstone Dr",
    "sg:city":"Rochelle",
    "sg:phone":"+1 815 562 2743",
    "sg:postcode":"61068",
    "sg:province":"IL",
    "sg:tags":[
        "farm",
        "corn",
        "grain",
        "cash"
    ],
    "wof:name":"Floyd Koch Trust",
    "wof:placetype":"venue"
},
  "geometry": {"coordinates":[-89.115364,41.941666],"type":"Point"}
}