{
  "type": "Feature",
  "properties": {
    "addr:full":"495 Bell Dr Des Plaines IL 60016",
    "addr:housenumber":"495",
    "addr:postcode":"60016",
    "addr:street":"Bell Dr",
    "iso:country":"US",
    "sg:address":"495 Bell Dr",
    "sg:city":"Des Plaines",
    "sg:classifiers":[
        {
            "category":"Banks & Credit Unions",
            "subcategory":"Investment Brokerage",
            "type":"Services"
        }
    ],
    "sg:phone":"+1 847 296 7848",
    "sg:postcode":"60016",
    "sg:province":"IL",
    "sg:tags":[
        "security"
    ],
    "wof:name":"Judge & Associates Inc",
    "wof:placetype":"venue"
},
  "geometry": {"coordinates":[-87.93030400000001,42.042192],"type":"Point"}
}