{
  "type": "Feature",
  "properties": {
    "addr:full":"55 North Ave Glendale Heights IL 60139",
    "addr:housenumber":"55",
    "addr:postcode":"60139",
    "addr:street":"North Ave",
    "iso:country":"US",
    "sg:address":"55 North Ave",
    "sg:city":"Glendale Heights",
    "sg:classifiers":[
        {
            "category":"Cinema",
            "subcategory":"Movie Rental",
            "type":"Entertainment"
        }
    ],
    "sg:phone":"+1 630 690 4446",
    "sg:postcode":"60139",
    "sg:province":"IL",
    "sg:tags":[
        "game",
        "video"
    ],
    "wof:name":"Hollywood Knights Video",
    "wof:placetype":"venue"
},
  "geometry": {"coordinates":[-88.0784,41.899101],"type":"Point"}
}