{
  "type": "Feature",
  "properties": {
    "iso:country":"US",
    "sg:address":"910 Hill Ave",
    "sg:city":"Aurora",
    "sg:classifiers":[
        {
            "category":"Restaurant",
            "type":"Food & Drink"
        }
    ],
    "sg:phone":"+1 630 820 3587",
    "sg:postcode":"60505",
    "sg:province":"IL",
    "wof:name":"Burrito Rico",
    "wof:placetype":"venue"
},
  "geometry": {"coordinates":[-88.28806299999999,41.74068],"type":"Point"}
}