{
  "type": "Feature",
  "properties": {
    "addr:full":"7530 S Stony Island Ave Chicago IL 60649",
    "addr:housenumber":"7530",
    "addr:postcode":"60649",
    "addr:street":"S Stony Island Ave",
    "iso:country":"US",
    "sg:address":"7530 S Stony Island Ave",
    "sg:city":"Chicago",
    "sg:classifiers":[
        {
            "category":"Food & Beverages",
            "subcategory":"Groceries & Convenience Stores",
            "type":"Retail Goods"
        }
    ],
    "sg:phone":"+1   ",
    "sg:postcode":"60649",
    "sg:province":"IL",
    "wof:name":"Jewel-Osco 3030",
    "wof:placetype":"venue"
},
  "geometry": {"coordinates":[-87.586089,41.756944],"type":"Point"}
}