{
  "type": "Feature",
  "properties": {
    "iso:country":"US",
    "sg:address":"6252 N Lincoln Ave",
    "sg:city":"Chicago",
    "sg:classifiers":[
        {
            "category":"Organizations",
            "subcategory":"Membership Organization",
            "type":"Services"
        }
    ],
    "sg:phone":"+1 773 539 4467",
    "sg:postcode":"60659",
    "sg:province":"IL",
    "sg:tags":[
        "meditation",
        "instruction"
    ],
    "wof:name":"Dahn Yoga Tai Chi Meditation",
    "wof:placetype":"venue"
},
  "geometry": {"coordinates":[-87.715891,41.995503],"type":"Point"}
}