{
  "type": "Feature",
  "properties": {
    "addr:full":"400 W Jackson St Ste B Marion IL 62959",
    "addr:housenumber":"400",
    "addr:postcode":"62959",
    "addr:street":"W Jackson St Ste B",
    "iso:country":"US",
    "sg:address":"400 W Jackson St Ste B",
    "sg:city":"Marion",
    "sg:classifiers":[
        {
            "category":"Professional",
            "subcategory":"Lawyer & Legal Services",
            "type":"Services"
        }
    ],
    "sg:phone":"+1 618 997 9766",
    "sg:postcode":"62959",
    "sg:province":"IL",
    "sg:tags":[
        "information",
        "attorney",
        "practice",
        "referral"
    ],
    "wof:name":"Therese H Thien",
    "wof:placetype":"venue"
},
  "geometry": {"coordinates":[-88.93038199999999,37.73283],"type":"Point"}
}