{
  "type": "Feature",
  "properties": {
    "iso:country":"US",
    "sg:address":"859 N Damen Ave",
    "sg:city":"Chicago",
    "sg:classifiers":[
        {
            "category":"Ice Cream",
            "type":"Food & Drink"
        }
    ],
    "sg:phone":"+1 773 235 3116",
    "sg:postcode":"60622",
    "sg:province":"IL",
    "sg:tags":[
        "frozen",
        "yogurt"
    ],
    "sg:website":"blackdogchicago.com/",
    "wof:name":"Black Dog Gelato",
    "wof:placetype":"venue"
},
  "geometry": {"coordinates":[-87.676734,41.897614],"type":"Point"}
}