{
  "type": "Feature",
  "properties": {
    "addr:full":"2140 N Lincoln Avenue Chicago IL 60614",
    "addr:housenumber":"2140",
    "addr:postcode":"60614",
    "addr:street":"N Lincoln Avenue",
    "iso:country":"US",
    "sg:address":"2140 N Lincoln Avenue",
    "sg:city":"Chicago",
    "sg:classifiers":[
        {
            "category":"Real Estate",
            "subcategory":"Real Estate Operator",
            "type":"Services"
        }
    ],
    "sg:phone":"+1 773 348 2150",
    "sg:postcode":"60614",
    "sg:province":"IL",
    "sg:tags":[
        "apartment"
    ],
    "wof:name":"Walpole Point Owners Association",
    "wof:placetype":"venue"
},
  "geometry": {"coordinates":[-87.64232699999999,41.920803],"type":"Point"}
}