{
  "type": "Feature",
  "properties": {
    "addr:full":"10543 E Aminoff Dr Effingham IL 62401",
    "addr:housenumber":"10543",
    "addr:postcode":"62401",
    "addr:street":"E Aminoff Dr",
    "iso:country":"US",
    "sg:address":"10543 E Aminoff Dr",
    "sg:city":"Effingham",
    "sg:classifiers":[
        {
            "category":"Farming",
            "subcategory":"Farm",
            "type":"Manufacturing & Wholesale Goods"
        }
    ],
    "sg:phone":"+1 217 868 5398",
    "sg:postcode":"62401",
    "sg:province":"IL",
    "sg:tags":[
        "crop",
        "general"
    ],
    "wof:name":"Dennis Homann",
    "wof:placetype":"venue"
},
  "geometry": {"coordinates":[-88.60102999999999,39.145517],"type":"Point"}
}