{
  "type": "Feature",
  "properties": {
    "iso:country":"US",
    "sg:address":"921 N la Salle Dr",
    "sg:city":"Chicago",
    "sg:classifiers":[
        {
            "category":"Professional",
            "subcategory":"Engineering",
            "type":"Services"
        }
    ],
    "sg:phone":"+1 312 266 1531",
    "sg:postcode":"60610",
    "sg:province":"IL",
    "sg:tags":[
        "consulting",
        "engineer"
    ],
    "wof:name":"Rice Huston Design & Engineering",
    "wof:placetype":"venue"
},
  "geometry": {"coordinates":[-87.632721,41.899498],"type":"Point"}
}