{
  "type": "Feature",
  "properties": {
    "iso:country":"US",
    "sg:address":"4 Wilshire Ct",
    "sg:city":"Mackinaw",
    "sg:classifiers":[
        {
            "category":"Shopping",
            "subcategory":"Bicycles & Sporting Goods",
            "type":"Retail Goods"
        }
    ],
    "sg:phone":"+1   ",
    "sg:postcode":"61755",
    "sg:province":"IL",
    "wof:name":"Riptide Powerski Inc",
    "wof:placetype":"venue"
},
  "geometry": {"coordinates":[-89.334903,40.550956],"type":"Point"}
}