{
  "type": "Feature",
  "properties": {
    "iso:country":"US",
    "sg:address":"520 S Northwest Hwy",
    "sg:city":"Barrington",
    "sg:classifiers":[
        {
            "category":"Retail",
            "subcategory":"Repair Shop",
            "type":"Services"
        }
    ],
    "sg:phone":"+1 847 382 1816",
    "sg:postcode":"60010",
    "sg:province":"IL",
    "sg:tags":[
        "related"
    ],
    "sg:website":"www.1sssi.com",
    "wof:name":"Systems & Software",
    "wof:placetype":"venue"
},
  "geometry": {"coordinates":[-88.128292,42.153065],"type":"Point"}
}