{
  "type": "Feature",
  "properties": {
    "iso:country":"US",
    "sg:address":"2508 State Rte 33",
    "sg:city":"Beecher City",
    "sg:classifiers":[
        {
            "category":"Professional",
            "type":"Services"
        }
    ],
    "sg:phone":"+1 618 487 5701",
    "sg:postcode":"62414",
    "sg:province":"IL",
    "sg:tags":[
        "establishment"
    ],
    "wof:name":"Clutter's Clean Up",
    "wof:placetype":"venue"
},
  "geometry": {"coordinates":[-88.763396,39.187049],"type":"Point"}
}