{
  "type": "Feature",
  "properties": {
    "addr:full":"361 Whirlaway Ct Wheaton IL 60187",
    "addr:housenumber":"361",
    "addr:postcode":"60187",
    "addr:street":"Whirlaway Ct",
    "iso:country":"US",
    "sg:address":"361 Whirlaway Ct",
    "sg:city":"Wheaton",
    "sg:classifiers":[
        {
            "category":"Professional",
            "subcategory":"Computer Services",
            "type":"Services"
        }
    ],
    "sg:phone":"+1 630 221 9987",
    "sg:postcode":"60187",
    "sg:province":"IL",
    "sg:tags":[
        "related"
    ],
    "wof:name":"Ra Consulting Inc",
    "wof:placetype":"venue"
},
  "geometry": {"coordinates":[-88.10912999999999,41.835652],"type":"Point"}
}