{
  "type": "Feature",
  "properties": {
    "iso:country":"US",
    "sg:address":"3933 Touhy Ave",
    "sg:city":"Lincolnwood",
    "sg:classifiers":[
        {
            "category":"Food & Beverages",
            "subcategory":"Groceries & Convenience Stores",
            "type":"Retail Goods"
        }
    ],
    "sg:phone":"+1 847 673 3055",
    "sg:postcode":"60712",
    "sg:province":"IL",
    "sg:tags":[
        "grocer"
    ],
    "wof:name":"Dong-A-Food",
    "wof:placetype":"venue"
},
  "geometry": {"coordinates":[-87.727851,42.011667],"type":"Point"}
}