{
  "type": "Feature",
  "properties": {
    "addr:full":"2544 S Illinois St Belleville IL 62220",
    "addr:housenumber":"2544",
    "addr:postcode":"62220",
    "addr:street":"S Illinois St",
    "iso:country":"US",
    "sg:address":"2544 S Illinois St",
    "sg:city":"Belleville",
    "sg:classifiers":[
        {
            "category":"Freight",
            "type":"Transportation"
        }
    ],
    "sg:phone":"+1 618 222 0135",
    "sg:postcode":"62220",
    "sg:province":"IL",
    "sg:tags":[
        "operator",
        "local",
        "trucking"
    ],
    "wof:name":"McRoberts Trucking Co",
    "wof:placetype":"venue"
},
  "geometry": {"coordinates":[-89.983323,38.474204],"type":"Point"}
}