{
  "type": "Feature",
  "properties": {
    "iso:country":"US",
    "sg:address":"702 Huntington Dr",
    "sg:city":"Carol Stream",
    "sg:classifiers":[
        {
            "category":"Building & Trades",
            "subcategory":"Construction",
            "type":"Services"
        }
    ],
    "sg:phone":"+1 630 372 6508",
    "sg:postcode":"60188",
    "sg:province":"IL",
    "sg:tags":[
        "house"
    ],
    "wof:name":"Als Home Improvements",
    "wof:placetype":"venue"
},
  "geometry": {"coordinates":[-88.141533,41.932525],"type":"Point"}
}