{
  "type": "Feature",
  "properties": {
    "addr:full":"9018 S Commercial Ave Chicago IL 60617",
    "addr:housenumber":"9018",
    "addr:postcode":"60617",
    "addr:street":"S Commercial Ave",
    "iso:country":"US",
    "sg:address":"9018 S Commercial Ave",
    "sg:city":"Chicago",
    "sg:classifiers":[
        {
            "category":"Personal",
            "subcategory":"Barber",
            "type":"Services"
        }
    ],
    "sg:phone":"+1 773 768 4668",
    "sg:postcode":"60617",
    "sg:province":"IL",
    "wof:name":"Ideal Barber Shop",
    "wof:placetype":"venue"
},
  "geometry": {"coordinates":[-87.55146999999999,41.731288],"type":"Point"}
}