{
  "type": "Feature",
  "properties": {
    "iso:country":"US",
    "sg:address":"43 W Slade St",
    "sg:city":"Palatine",
    "sg:classifiers":[
        {
            "category":"Shopping",
            "subcategory":"Gifts & Souvenirs",
            "type":"Retail Goods"
        }
    ],
    "sg:phone":"+1 847 934 4220",
    "sg:postcode":"60067",
    "sg:province":"IL",
    "sg:tags":[
        "shop",
        "furniture"
    ],
    "wof:name":"Country Cousins II",
    "wof:placetype":"venue"
},
  "geometry": {"coordinates":[-88.045793,42.111179],"type":"Point"}
}