{
  "type": "Feature",
  "properties": {
    "addr:full":"1605 E Chestnut St Canton IL 61520",
    "addr:housenumber":"1605",
    "addr:postcode":"61520",
    "addr:street":"E Chestnut St",
    "iso:country":"US",
    "sg:address":"1605 E Chestnut St",
    "sg:city":"Canton",
    "sg:classifiers":[
        {
            "category":"Professional",
            "subcategory":"Business Services",
            "type":"Services"
        }
    ],
    "sg:phone":"+1 309 647 4300",
    "sg:postcode":"61520",
    "sg:province":"IL",
    "sg:tags":[
        "telemarketing"
    ],
    "wof:name":"Apac Customer Svc",
    "wof:placetype":"venue"
},
  "geometry": {"coordinates":[-90.008606,40.557146],"type":"Point"}
}