{
  "type": "Feature",
  "properties": {
    "iso:country":"US",
    "sg:address":"5 N May St Ste 785",
    "sg:city":"Aurora",
    "sg:classifiers":[
        {
            "category":"Communications",
            "type":"Services"
        }
    ],
    "sg:phone":"+1 630 466 8008",
    "sg:postcode":"60506",
    "sg:province":"IL",
    "sg:tags":[
        "equipment",
        "data",
        "system"
    ],
    "sg:website":"http://www.amerinet.com",
    "wof:name":"Amerinet Of Michigan, Inc.",
    "wof:placetype":"venue"
},
  "geometry": {"coordinates":[-88.327597,41.761303],"type":"Point"}
}