{
  "type": "Feature",
  "properties": {
    "iso:country":"US",
    "sg:address":"1524 Locust St",
    "sg:city":"Quincy",
    "sg:classifiers":[
        {
            "category":"Social Services",
            "subcategory":"Child Care",
            "type":"Services"
        }
    ],
    "sg:phone":"+1 217 222 7129",
    "sg:postcode":"62301",
    "sg:province":"IL",
    "sg:tags":[
        "day"
    ],
    "wof:name":"Dolores ODear",
    "wof:placetype":"venue"
},
  "geometry": {"coordinates":[-91.39174300000001,39.950334],"type":"Point"}
}