{
  "type": "Feature",
  "properties": {
    "addr:full":"343 W Maple St New Lenox IL 60451",
    "addr:housenumber":"343",
    "addr:postcode":"60451",
    "addr:street":"W Maple St",
    "iso:country":"US",
    "sg:address":"343 W Maple St",
    "sg:city":"New Lenox",
    "sg:classifiers":[
        {
            "category":"Personal",
            "subcategory":"Barber",
            "type":"Services"
        }
    ],
    "sg:phone":"+1 815 485 6351",
    "sg:postcode":"60451",
    "sg:province":"IL",
    "wof:name":"Kings Barber Shop",
    "wof:placetype":"venue"
},
  "geometry": {"coordinates":[-87.973418,41.515624],"type":"Point"}
}