{
  "type": "Feature",
  "properties": {
    "addr:full":"1250 S Grove Ave Barrington IL 60010",
    "addr:housenumber":"1250",
    "addr:postcode":"60010",
    "addr:street":"S Grove Ave",
    "iso:country":"US",
    "sg:address":"1250 S Grove Ave",
    "sg:city":"Barrington",
    "sg:classifiers":[
        {
            "category":"Professional",
            "subcategory":"Lawyer & Legal Services",
            "type":"Services"
        }
    ],
    "sg:phone":"+1 847 381 7743",
    "sg:postcode":"60010",
    "sg:province":"IL",
    "sg:tags":[
        "attorney"
    ],
    "wof:name":"Thomas E Cusick LTD",
    "wof:placetype":"venue"
},
  "geometry": {"coordinates":[-88.13301800000001,42.136595],"type":"Point"}
}