{
  "type": "Feature",
  "properties": {
    "iso:country":"US",
    "sg:address":"935 S Main St",
    "sg:city":"Jacksonville",
    "sg:classifiers":[
        {
            "category":"Autos & Motor Vehicles",
            "subcategory":"Fuel & Gas Station",
            "type":"Retail Goods"
        }
    ],
    "sg:phone":"+1 217 243 9932",
    "sg:postcode":"62650",
    "sg:province":"IL",
    "sg:tags":[
        "oil"
    ],
    "wof:name":"Steve's Fuel & Auto Care Inc",
    "wof:placetype":"venue"
},
  "geometry": {"coordinates":[-90.229234,39.724061],"type":"Point"}
}