{
  "type": "Feature",
  "properties": {
    "iso:country":"US",
    "sg:address":"940 Carlyle Ave",
    "sg:city":"Belleville",
    "sg:classifiers":[
        {
            "category":"Restaurant",
            "type":"Food & Drink"
        }
    ],
    "sg:phone":"+1 618 277 2888",
    "sg:postcode":"62221",
    "sg:province":"IL",
    "sg:tags":[
        "eating"
    ],
    "wof:name":"A S I C Inc",
    "wof:placetype":"venue"
},
  "geometry": {"coordinates":[-89.947934,38.518142],"type":"Point"}
}