{
  "type": "Feature",
  "properties": {
    "addr:full":"2302 W Chicago Ave Chicago IL 60622",
    "addr:housenumber":"2302",
    "addr:postcode":"60622",
    "addr:street":"W Chicago Ave",
    "iso:country":"US",
    "sg:address":"2302 W Chicago Ave",
    "sg:city":"Chicago",
    "sg:classifiers":[
        {
            "category":"Real Estate",
            "subcategory":"Real Estate Services",
            "type":"Services"
        },
        {
            "category":"Real Estate",
            "subcategory":"Real Estate Agent",
            "type":"Services"
        },
        {
            "category":"Real Estate",
            "subcategory":"Real Estate Operator",
            "type":"Services"
        }
    ],
    "sg:phone":"+1 773 486 2100",
    "sg:postcode":"60622",
    "sg:province":"IL",
    "sg:tags":[
        "property",
        "management",
        "apartment"
    ],
    "sg:website":"www.cirquegroupe.com",
    "wof:name":"Cirque Groupe",
    "wof:placetype":"venue"
},
  "geometry": {"coordinates":[-87.68440200000001,41.895802],"type":"Point"}
}