{
  "type": "Feature",
  "properties": {
    "addr:full":"5627 Inverness Dr Rockford IL 61107",
    "addr:housenumber":"5627",
    "addr:postcode":"61107",
    "addr:street":"Inverness Dr",
    "iso:country":"US",
    "sg:address":"5627 Inverness Dr",
    "sg:city":"Rockford",
    "sg:classifiers":[
        {
            "category":"Wholesale",
            "subcategory":"Machinery & Supplies",
            "type":"Manufacturing & Wholesale Goods"
        },
        {
            "category":"Building & Trades",
            "subcategory":"Electrical",
            "type":"Services"
        }
    ],
    "sg:phone":"+1 815 399 6961",
    "sg:postcode":"61107",
    "sg:province":"IL",
    "sg:tags":[
        "industrial",
        "electrician",
        "electric",
        "generator",
        "contractors-commercial"
    ],
    "wof:name":"Stalite Corp",
    "wof:placetype":"venue"
},
  "geometry": {"coordinates":[-89.007307,42.275298],"type":"Point"}
}