{
  "type": "Feature",
  "properties": {
    "iso:country":"US",
    "sg:address":"190 S la Salle St",
    "sg:city":"Chicago",
    "sg:classifiers":[
        {
            "category":"Professional",
            "subcategory":"Management & Consulting",
            "type":"Services"
        }
    ],
    "sg:phone":"+1 312 781 9163",
    "sg:postcode":"60603",
    "sg:province":"IL",
    "sg:tags":[
        "counselor",
        "relation",
        "public"
    ],
    "sg:website":"http://www.sardverb.com",
    "wof:name":"Sard Verbinnen",
    "wof:placetype":"venue"
},
  "geometry": {"coordinates":[-87.632294,41.879554],"type":"Point"}
}