{
  "type": "Feature",
  "properties": {
    "addr:full":"2521 N Clark St Chicago IL 60614",
    "addr:housenumber":"2521",
    "addr:postcode":"60614",
    "addr:street":"N Clark St",
    "iso:country":"US",
    "sg:address":"2521 N Clark St",
    "sg:city":"Chicago",
    "sg:classifiers":[
        {
            "category":"Restaurant",
            "type":"Food & Drink"
        }
    ],
    "sg:menulink":"http://www.allmenus.com/il/chicago/193018-sultans/menu/",
    "sg:phone":"+1 312 638 9151",
    "sg:postcode":"60614",
    "sg:province":"IL",
    "sg:tags":[
        "mediterranean"
    ],
    "wof:name":"Sultan's",
    "wof:placetype":"venue"
},
  "geometry": {"coordinates":[-87.64208000000001,41.928316],"type":"Point"}
}