{
  "type": "Feature",
  "properties": {
    "addr:full":"20 N Park Rd Joliet IL 60433",
    "addr:housenumber":"20",
    "addr:postcode":"60433",
    "addr:street":"N Park Rd",
    "iso:country":"US",
    "sg:address":"20 N Park Rd",
    "sg:city":"Joliet",
    "sg:classifiers":[
        {
            "category":"Recreation",
            "type":"Entertainment"
        }
    ],
    "sg:phone":"+1 815 727 7217",
    "sg:postcode":"60433",
    "sg:province":"IL",
    "sg:tags":[
        "hall",
        "auditorium"
    ],
    "wof:name":"Ingalls Park AC",
    "wof:placetype":"venue"
},
  "geometry": {"coordinates":[-88.036281,41.526966],"type":"Point"}
}