{
  "type": "Feature",
  "properties": {
    "addr:full":"430 W Erie Street Chicago IL 60610",
    "addr:housenumber":"430",
    "addr:postcode":"60610",
    "addr:street":"W Erie Street",
    "iso:country":"US",
    "sg:address":"430 W Erie Street",
    "sg:city":"Chicago",
    "sg:classifiers":[
        {
            "category":"Shopping",
            "subcategory":"Mobile Phones",
            "type":"Retail Goods"
        },
        {
            "category":"Communications",
            "type":"Services"
        }
    ],
    "sg:phone":"+1 312 280 8949",
    "sg:postcode":"60610",
    "sg:province":"IL",
    "sg:tags":[
        "recording",
        "rehearsal",
        "studio"
    ],
    "wof:name":"V D I Multimedia Services",
    "wof:placetype":"venue"
},
  "geometry": {"coordinates":[-87.639734,41.89395],"type":"Point"}
}