{
  "type": "Feature",
  "properties": {
    "iso:country":"US",
    "sg:address":"100 Plaza Dr",
    "sg:city":"Carterville",
    "sg:classifiers":[
        {
            "category":"Autos & Motor Vehicles",
            "subcategory":"Fuel & Gas Station",
            "type":"Retail Goods"
        }
    ],
    "sg:phone":"+1   ",
    "sg:postcode":"62918",
    "sg:province":"IL",
    "sg:tags":[
        "grocery",
        "station",
        "gasoline"
    ],
    "wof:name":"Moto Mart",
    "wof:placetype":"venue"
},
  "geometry": {"coordinates":[-89.07797,37.745343],"type":"Point"}
}