{
  "type": "Feature",
  "properties": {
    "iso:country":"US",
    "sg:address":"820 W River Pl",
    "sg:city":"Kankakee",
    "sg:classifiers":[
        {
            "category":"Retail",
            "subcategory":"Auto Repair",
            "type":"Services"
        }
    ],
    "sg:phone":"+1 815 929 0213",
    "sg:postcode":"60901",
    "sg:province":"IL",
    "sg:tags":[
        "repairing",
        "automobile",
        "general"
    ],
    "wof:name":"Big Larry's Auto Repair",
    "wof:placetype":"venue"
},
  "geometry": {"coordinates":[-87.87606100000001,41.125544],"type":"Point"}
}