{
  "type": "Feature",
  "properties": {
    "addr:full":"611 S Milwaukee Ave Libertyville IL 60048",
    "addr:housenumber":"611",
    "addr:postcode":"60048",
    "addr:street":"S Milwaukee Ave",
    "iso:country":"US",
    "sg:address":"611 S Milwaukee Ave",
    "sg:city":"Libertyville",
    "sg:classifiers":[
        {
            "category":"Professional",
            "subcategory":"Secretarial Services",
            "type":"Services"
        }
    ],
    "sg:phone":"+1 847 367 8985",
    "sg:postcode":"60048",
    "sg:province":"IL",
    "sg:tags":[
        "reporting",
        "court"
    ],
    "wof:name":"SOS Inc",
    "wof:placetype":"venue"
},
  "geometry": {"coordinates":[-87.952011,42.276106],"type":"Point"}
}