{
  "type": "Feature",
  "properties": {
    "iso:country":"US",
    "sg:address":"224 Fairview Dr",
    "sg:city":"Manhattan",
    "sg:classifiers":[
        {
            "category":"Organizations",
            "subcategory":"Religious Organization",
            "type":"Services"
        }
    ],
    "sg:phone":"+1 815 478 5336",
    "sg:postcode":"60442",
    "sg:province":"IL",
    "wof:name":"Ron Sweedler Rev",
    "wof:placetype":"venue"
},
  "geometry": {"coordinates":[-87.996875,41.431408],"type":"Point"}
}