{
  "type": "Feature",
  "properties": {
    "addr:full":"233 N Michigan Ave # 3050 Chicago IL 60601",
    "addr:housenumber":"233",
    "addr:postcode":"60601",
    "addr:street":"N Michigan Ave # 3050",
    "iso:country":"US",
    "sg:address":"233 N Michigan Ave # 3050",
    "sg:city":"Chicago",
    "sg:classifiers":[
        {
            "category":"Professional",
            "subcategory":"Management & Consulting",
            "type":"Services"
        },
        {
            "category":"Professional",
            "subcategory":"Advertising",
            "type":"Services"
        }
    ],
    "sg:phone":"+1 312 970 5800",
    "sg:postcode":"60601",
    "sg:province":"IL",
    "sg:tags":[
        "agency",
        "specialty",
        "relation",
        "counselor",
        "public"
    ],
    "sg:website":"http://www.slackbarshinger.com",
    "wof:name":"Slack Barshinger & Partners, Inc.",
    "wof:placetype":"venue"
},
  "geometry": {"coordinates":[-87.62444499999999,41.886086],"type":"Point"}
}