{
  "type": "Feature",
  "properties": {
    "iso:country":"US",
    "sg:address":"500 E Constitution Dr",
    "sg:city":"Palatine",
    "sg:classifiers":[
        {
            "category":"Real Estate",
            "subcategory":"Real Estate Operator",
            "type":"Services"
        }
    ],
    "sg:phone":"+1 847 358 8888",
    "sg:postcode":"60074",
    "sg:province":"IL",
    "sg:tags":[
        "manages",
        "apartment",
        "complex"
    ],
    "sg:website":"www.equityapartments.com",
    "wof:name":"Bourbon Square Executive Apts",
    "wof:placetype":"venue"
},
  "geometry": {"coordinates":[-88.026292,42.151211],"type":"Point"}
}