{
  "type": "Feature",
  "properties": {
    "iso:country":"US",
    "sg:address":"557 N Hough St",
    "sg:city":"Barrington",
    "sg:classifiers":[
        {
            "category":"Personal",
            "subcategory":"Beauty Salon",
            "type":"Services"
        }
    ],
    "sg:phone":"+1 847 304 9205",
    "sg:postcode":"60010",
    "sg:province":"IL",
    "sg:tags":[
        "shop"
    ],
    "wof:name":"Nails Design Inc",
    "wof:placetype":"venue"
},
  "geometry": {"coordinates":[-88.135986,42.160267],"type":"Point"}
}