{
  "type": "Feature",
  "properties": {
    "iso:country":"US",
    "sg:address":"3 First National Plz",
    "sg:city":"Chicago",
    "sg:classifiers":[
        {
            "category":"Professional",
            "subcategory":"Lawyer & Legal Services",
            "type":"Services"
        }
    ],
    "sg:phone":"+1 312 977 4463",
    "sg:postcode":"60602",
    "sg:province":"IL",
    "wof:name":"Kritzmire Robert Atty",
    "wof:placetype":"venue"
},
  "geometry": {"coordinates":[-87.630284,41.882334],"type":"Point"}
}