{
  "type": "Feature",
  "properties": {
    "addr:full":"18617 Saint Rose Rd Breese IL 62230",
    "addr:housenumber":"18617",
    "addr:postcode":"62230",
    "addr:street":"Saint Rose Rd",
    "iso:country":"US",
    "sg:address":"18617 Saint Rose Rd",
    "sg:city":"Breese",
    "sg:classifiers":[
        {
            "category":"Real Estate",
            "subcategory":"Real Estate Operator",
            "type":"Services"
        }
    ],
    "sg:phone":"+1 618 526 7511",
    "sg:postcode":"62230",
    "sg:province":"IL",
    "sg:tags":[
        "property",
        "lessor"
    ],
    "wof:name":"Andrew Wilke",
    "wof:placetype":"venue"
},
  "geometry": {"coordinates":[-89.55474599999999,38.687737],"type":"Point"}
}