{
  "type": "Feature",
  "properties": {
    "iso:country":"US",
    "sg:address":"6650 N Northwest Hwy",
    "sg:city":"Chicago",
    "sg:classifiers":[
        {
            "category":"Professional",
            "subcategory":"Accounting & Tax Preparation",
            "type":"Services"
        }
    ],
    "sg:phone":"+1 773 631 3553",
    "sg:postcode":"60631",
    "sg:province":"IL",
    "sg:tags":[
        "accountant"
    ],
    "wof:name":"Leftakes Daniel Acct",
    "wof:placetype":"venue"
},
  "geometry": {"coordinates":[-87.814302,42.0016],"type":"Point"}
}