{
  "type": "Feature",
  "properties": {
    "addr:full":"866 Riverside Dr Dixon IL 61021",
    "addr:housenumber":"866",
    "addr:postcode":"61021",
    "addr:street":"Riverside Dr",
    "iso:country":"US",
    "sg:address":"866 Riverside Dr",
    "sg:city":"Dixon",
    "sg:classifiers":[
        {
            "category":"Health Services",
            "subcategory":"Doctor",
            "type":"Services"
        }
    ],
    "sg:phone":"+1 815 652 4446",
    "sg:postcode":"61021",
    "sg:province":"IL",
    "sg:tags":[
        "medical"
    ],
    "wof:name":"Imre G Almassy MD",
    "wof:placetype":"venue"
},
  "geometry": {"coordinates":[-89.467355,41.911026],"type":"Point"}
}