{
  "type": "Feature",
  "properties": {
    "addr:full":"24447 W Eames St Channahon IL 60410",
    "addr:housenumber":"24447",
    "addr:postcode":"60410",
    "addr:street":"W Eames St",
    "iso:country":"US",
    "sg:address":"24447 W Eames St",
    "sg:city":"Channahon",
    "sg:classifiers":[
        {
            "category":"Restaurant",
            "type":"Food & Drink"
        }
    ],
    "sg:phone":"+1 815 521 1690",
    "sg:postcode":"60410",
    "sg:province":"IL",
    "sg:tags":[
        "pizza"
    ],
    "sg:website":"www.rosatispizza.com",
    "wof:name":"Rosati's of Channahon",
    "wof:placetype":"venue"
},
  "geometry": {"coordinates":[-88.237317,41.421711],"type":"Point"}
}