{
  "type": "Feature",
  "properties": {
    "addr:full":"1587 N Milwaukee Avenue Chicago IL 60622",
    "addr:housenumber":"1587",
    "addr:postcode":"60622",
    "addr:street":"N Milwaukee Avenue",
    "iso:country":"US",
    "sg:address":"1587 N Milwaukee Avenue",
    "sg:city":"Chicago",
    "sg:classifiers":[
        {
            "category":"Winery",
            "type":"Food & Drink"
        },
        {
            "category":"Shopping",
            "subcategory":"Tobacco",
            "type":"Retail Goods"
        }
    ],
    "sg:phone":"+1 773 862 2226",
    "sg:postcode":"60622",
    "sg:province":"IL",
    "sg:tags":[
        "shop"
    ],
    "wof:name":"World Wide Tobacco",
    "wof:placetype":"venue"
},
  "geometry": {"coordinates":[-87.677334,41.910149],"type":"Point"}
}