{
  "type": "Feature",
  "properties": {
    "addr:full":"1926 S Wabash Avenue Chicago IL 60616",
    "addr:housenumber":"1926",
    "addr:postcode":"60616",
    "addr:street":"S Wabash Avenue",
    "iso:country":"US",
    "sg:address":"1926 S Wabash Avenue",
    "sg:city":"Chicago",
    "sg:classifiers":[
        {
            "category":"Shopping",
            "subcategory":"Clothing, Apparel, & Fashions",
            "type":"Retail Goods"
        },
        {
            "category":"Personal",
            "type":"Services"
        },
        {
            "category":"Shopping",
            "subcategory":"Shoes",
            "type":"Retail Goods"
        }
    ],
    "sg:phone":"+1 312 225 5423",
    "sg:postcode":"60616",
    "sg:province":"IL",
    "sg:tags":[
        "designer",
        "sewing",
        "alteration",
        "accessory",
        "women's",
        "clothing",
        "store"
    ],
    "wof:name":"La Collezion Studio",
    "wof:placetype":"venue"
},
  "geometry": {"coordinates":[-87.625575,41.856326],"type":"Point"}
}