{
  "type": "Feature",
  "properties": {
    "iso:country":"US",
    "sg:address":"706 Clarence Ave",
    "sg:city":"Oak Park",
    "sg:classifiers":[
        {
            "category":"Professional",
            "subcategory":"Management & Consulting",
            "type":"Services"
        }
    ],
    "sg:phone":"+1 708 906 3525",
    "sg:postcode":"60304",
    "sg:province":"IL",
    "wof:name":"Duran McKnight Marketing",
    "wof:placetype":"venue"
},
  "geometry": {"coordinates":[-87.790321,41.874459],"type":"Point"}
}