{
  "type": "Feature",
  "properties": {
    "iso:country":"US",
    "sg:address":"715 State Rte 173",
    "sg:city":"Antioch",
    "sg:classifiers":[
        {
            "category":"Autos & Motor Vehicles",
            "subcategory":"Automobile Sales",
            "type":"Retail Goods"
        }
    ],
    "sg:phone":"+1   ",
    "sg:postcode":"60002",
    "sg:province":"IL",
    "wof:name":"Country Pontiac-Buick",
    "wof:placetype":"venue"
},
  "geometry": {"coordinates":[-88.109289,42.476954],"type":"Point"}
}