{
  "type": "Feature",
  "properties": {
    "iso:country":"US",
    "sg:address":"509 N 4th St",
    "sg:city":"Chillicothe",
    "sg:classifiers":[
        {
            "category":"Professional",
            "type":"Services"
        }
    ],
    "sg:phone":"+1 309 274 3699",
    "sg:postcode":"61523",
    "sg:province":"IL",
    "sg:tags":[
        "establishment"
    ],
    "wof:name":"Efmark",
    "wof:placetype":"venue"
},
  "geometry": {"coordinates":[-89.49007,40.913675],"type":"Point"}
}