{
  "type": "Feature",
  "properties": {
    "addr:full":"2720 W Bryn Mawr Avenue Chicago IL 60659",
    "addr:housenumber":"2720",
    "addr:postcode":"60659",
    "addr:street":"W Bryn Mawr Avenue",
    "iso:country":"US",
    "sg:address":"2720 W Bryn Mawr Avenue",
    "sg:city":"Chicago",
    "sg:classifiers":[
        {
            "category":"Taxi",
            "type":"Transportation"
        }
    ],
    "sg:phone":"+1 773 271 9521",
    "sg:postcode":"60659",
    "sg:province":"IL",
    "wof:name":"A & A Cab Company",
    "wof:placetype":"venue"
},
  "geometry": {"coordinates":[-87.697478,41.98312],"type":"Point"}
}