{
  "type": "Feature",
  "properties": {
    "iso:country":"US",
    "sg:address":"1100 W Monroe St",
    "sg:city":"Chicago",
    "sg:classifiers":[
        {
            "category":"Sports & Exercise",
            "subcategory":"Tennis Court",
            "type":"Entertainment"
        }
    ],
    "sg:phone":"+1 312 733 6387",
    "sg:postcode":"60607",
    "sg:province":"IL",
    "sg:tags":[
        "equipment",
        "supply"
    ],
    "sg:website":"http://www.protectivesportsconcepts.com",
    "wof:name":"Protective Sports Concepts",
    "wof:placetype":"venue"
},
  "geometry": {"coordinates":[-87.654663,41.880379],"type":"Point"}
}