{
  "type": "Feature",
  "properties": {
    "iso:country":"US",
    "sg:address":"7510 W Heller Ln",
    "sg:city":"Galena",
    "sg:classifiers":[
        {
            "category":"Building & Trades",
            "subcategory":"Landscaping Services",
            "type":"Services"
        }
    ],
    "sg:phone":"+1 815 777 2993",
    "sg:postcode":"61036",
    "sg:province":"IL",
    "wof:name":"Kaiser Lawn Service",
    "wof:placetype":"venue"
},
  "geometry": {"coordinates":[-90.373083,42.416097],"type":"Point"}
}