{
  "type": "Feature",
  "properties": {
    "iso:country":"US",
    "sg:address":"22 Jerome Ln",
    "sg:city":"East Saint Louis",
    "sg:classifiers":[
        {
            "category":"Home & Garden",
            "subcategory":"Carpets & Floor Coverings",
            "type":"Retail Goods"
        }
    ],
    "sg:phone":"+1 618 337 4296",
    "sg:postcode":"62206",
    "sg:province":"IL",
    "sg:tags":[
        "carpeting"
    ],
    "wof:name":"Thrifty Carpet & Floor Coverings",
    "wof:placetype":"venue"
},
  "geometry": {"coordinates":[-90.180801,38.5807],"type":"Point"}
}