{
  "type": "Feature",
  "properties": {
    "iso:country":"US",
    "sg:address":"938 Cannon Rd",
    "sg:city":"Winchester",
    "sg:phone":"+1 217 742 3788",
    "sg:postcode":"62694",
    "sg:province":"IL",
    "sg:tags":[
        "farm",
        "soybean",
        "crop",
        "general"
    ],
    "wof:name":"James Hart",
    "wof:placetype":"venue"
},
  "geometry": {"coordinates":[-90.480464,39.651801],"type":"Point"}
}