{
  "type": "Feature",
  "properties": {
    "addr:full":"4701 South Woodlawn Ave. Ste F Chicago IL 60615",
    "addr:housenumber":"4701",
    "addr:postcode":"60615",
    "addr:street":"South Woodlawn Ave. Ste F",
    "iso:country":"US",
    "sg:address":"4701 South Woodlawn Ave. Ste F",
    "sg:city":"Chicago",
    "sg:classifiers":[
        {
            "category":"Professional",
            "type":"Services"
        }
    ],
    "sg:phone":"+1 773 285 1055",
    "sg:postcode":"60615",
    "sg:province":"IL",
    "wof:name":"Cultural Communications, LLC",
    "wof:placetype":"venue"
},
  "geometry": {"coordinates":[-87.59638099999999,41.80935],"type":"Point"}
}