{
  "type": "Feature",
  "properties": {
    "iso:country":"US",
    "sg:address":"4161 Columbus St",
    "sg:city":"Ottawa",
    "sg:classifiers":[
        {
            "category":"Education",
            "subcategory":"School",
            "type":"Public Place"
        }
    ],
    "sg:phone":"+1 815 433 3762",
    "sg:postcode":"61350",
    "sg:province":"IL",
    "sg:tags":[
        "elementary"
    ],
    "wof:name":"Ottawa Elementary School District 141",
    "wof:placetype":"venue"
},
  "geometry": {"coordinates":[-88.835942,41.380211],"type":"Point"}
}