{
  "type": "Feature",
  "properties": {
    "iso:country":"US",
    "sg:address":"1126 E Walnut St",
    "sg:city":"Carbondale",
    "sg:classifiers":[
        {
            "category":"Fast Food",
            "type":"Food & Drink"
        },
        {
            "category":"Coffee & Tea",
            "type":"Food & Drink"
        },
        {
            "category":"Restaurant",
            "type":"Food & Drink"
        },
        {
            "category":"Bakery",
            "type":"Food & Drink"
        },
        {
            "category":"Food & Beverages",
            "subcategory":"Groceries & Convenience Stores",
            "type":"Retail Goods"
        }
    ],
    "sg:phone":"+1 618 457 5755",
    "sg:postcode":"62901",
    "sg:province":"IL",
    "sg:tags":[
        "shop",
        "sandwich",
        "espresso",
        "take"
    ],
    "sg:website":"http://www.panerabread.com",
    "wof:name":"Panera Bread",
    "wof:placetype":"venue"
},
  "geometry": {"coordinates":[-89.194395,37.726929],"type":"Point"}
}