{
  "type": "Feature",
  "properties": {
    "iso:country":"US",
    "sg:address":"724 Saint Louis Rd Ste A",
    "sg:city":"Collinsville",
    "sg:classifiers":[
        {
            "category":"Health Services",
            "subcategory":"Optometrist",
            "type":"Services"
        }
    ],
    "sg:phone":"+1 618 345 0210",
    "sg:postcode":"62234",
    "sg:province":"IL",
    "wof:name":"Strieter James OD A Family Eye Clinic",
    "wof:placetype":"venue"
},
  "geometry": {"coordinates":[-90.003403,38.659901],"type":"Point"}
}