{
  "type": "Feature",
  "properties": {
    "iso:country":"US",
    "sg:address":"8337 Skokie Blvd",
    "sg:city":"Skokie",
    "sg:classifiers":[
        {
            "category":"Shopping",
            "type":"Retail Goods"
        }
    ],
    "sg:phone":"+1 847 220 7955",
    "sg:postcode":"60077",
    "sg:province":"IL",
    "sg:tags":[
        "equipment",
        "surgical",
        "orthopedic",
        "hospital",
        "supply"
    ],
    "sg:website":"http://koebersmedicalsupplies.com/index.htm",
    "wof:name":"Koeber's Medical Supplies",
    "wof:placetype":"venue"
},
  "geometry": {"coordinates":[-87.74732,42.032726],"type":"Point"}
}