{
  "type": "Feature",
  "properties": {
    "iso:country":"US",
    "sg:address":"3610 Clarence Ave",
    "sg:city":"Berwyn",
    "sg:classifiers":[
        {
            "category":"Building & Trades",
            "subcategory":"Construction",
            "type":"Services"
        }
    ],
    "sg:phone":"+1 708 705 5564",
    "sg:postcode":"60402",
    "sg:province":"IL",
    "sg:tags":[
        "wallcoverings-installation",
        "wallpaper",
        "painting",
        "contractor"
    ],
    "wof:name":"A Perfect Touch Painting",
    "wof:placetype":"venue"
},
  "geometry": {"coordinates":[-87.788927,41.826655],"type":"Point"}
}