{
  "type": "Feature",
  "properties": {
    "iso:country":"US",
    "sg:address":"7408 S Main St",
    "sg:city":"Rockford",
    "sg:classifiers":[
        {
            "category":"Building & Trades",
            "subcategory":"Construction",
            "type":"Services"
        }
    ],
    "sg:phone":"+1 815 987 9388",
    "sg:postcode":"61102",
    "sg:province":"IL",
    "sg:tags":[
        "hanging",
        "contractor"
    ],
    "wof:name":"Superior Electrostatic",
    "wof:placetype":"venue"
},
  "geometry": {"coordinates":[-89.151032,42.186621],"type":"Point"}
}