{
  "type": "Feature",
  "properties": {
    "iso:country":"US",
    "sg:address":"3816 Maple Ave",
    "sg:city":"Berwyn",
    "sg:classifiers":[
        {
            "category":"Building & Trades",
            "subcategory":"Cleaning & Sanitation",
            "type":"Services"
        }
    ],
    "sg:phone":"+1 708 795 9622",
    "sg:postcode":"60402",
    "sg:province":"IL",
    "sg:tags":[
        "maintenance"
    ],
    "wof:name":"Sparkling Clean Inc",
    "wof:placetype":"venue"
},
  "geometry": {"coordinates":[-87.80136,41.821952],"type":"Point"}
}