{
  "type": "Feature",
  "properties": {
    "addr:full":"2736 Maple Ave Downers Grove IL 60515",
    "addr:housenumber":"2736",
    "addr:postcode":"60515",
    "addr:street":"Maple Ave",
    "iso:country":"US",
    "sg:address":"2736 Maple Ave",
    "sg:city":"Downers Grove",
    "sg:classifiers":[
        {
            "category":"Health Services",
            "subcategory":"Chiropractor",
            "type":"Services"
        }
    ],
    "sg:phone":"+1 630 963 0080",
    "sg:postcode":"60515",
    "sg:province":"IL",
    "wof:name":"Maple Grove Chropractic Clinic",
    "wof:placetype":"venue"
},
  "geometry": {"coordinates":[-88.049712,41.7851],"type":"Point"}
}