{
  "type": "Feature",
  "properties": {
    "addr:full":"5411 E State St Rockford IL 61108",
    "addr:housenumber":"5411",
    "addr:postcode":"61108",
    "addr:street":"E State St",
    "iso:country":"US",
    "sg:address":"5411 E State St",
    "sg:city":"Rockford",
    "sg:classifiers":[
        {
            "category":"Organizations",
            "subcategory":"Professional Association",
            "type":"Services"
        }
    ],
    "sg:phone":"+1 815 229 1632",
    "sg:postcode":"61108",
    "sg:province":"IL",
    "wof:name":"Muscular Dystrophy Assn",
    "wof:placetype":"venue"
},
  "geometry": {"coordinates":[-89.00981,42.265211],"type":"Point"}
}