{
  "type": "Feature",
  "properties": {
    "addr:full":"2207 183rd St Homewood IL 60430",
    "addr:housenumber":"2207",
    "addr:postcode":"60430",
    "addr:street":"183Rd St",
    "iso:country":"US",
    "sg:address":"2207 183rd St",
    "sg:city":"Homewood",
    "sg:classifiers":[
        {
            "category":"Retail",
            "subcategory":"Veterinary Services",
            "type":"Services"
        }
    ],
    "sg:phone":"+1 708 798 1016",
    "sg:postcode":"60430",
    "sg:province":"IL",
    "wof:name":"Homewood Animal Hospital",
    "wof:placetype":"venue"
},
  "geometry": {"coordinates":[-87.66974500000001,41.557163],"type":"Point"}
}