{
  "type": "Feature",
  "properties": {
    "iso:country":"US",
    "sg:address":"2207 183rd St",
    "sg:city":"Homewood",
    "sg:classifiers":[
        {
            "category":"Retail",
            "subcategory":"Veterinary Services",
            "type":"Services"
        }
    ],
    "sg:phone":"+1 708 798 1016",
    "sg:postcode":"60430",
    "sg:province":"IL",
    "wof:name":"Homewood Animal Hospital",
    "wof:placetype":"venue"
},
  "geometry": {"coordinates":[-87.669745,41.557163],"type":"Point"}
}