{
  "type": "Feature",
  "properties": {
    "addr:full":"204 Lasalle Rd La Salle IL 61301",
    "addr:housenumber":"204",
    "addr:postcode":"61301",
    "addr:street":"Lasalle Rd",
    "iso:country":"US",
    "sg:address":"204 Lasalle Rd",
    "sg:city":"La Salle",
    "sg:classifiers":[
        {
            "category":"Autos & Motor Vehicles",
            "subcategory":"Fuel & Gas Station",
            "type":"Retail Goods"
        }
    ],
    "sg:phone":"+1 815 220 1393",
    "sg:postcode":"61301",
    "sg:province":"IL",
    "sg:tags":[
        "plaza",
        "truck",
        "stops"
    ],
    "wof:name":"Crazy D's Peru Inc",
    "wof:placetype":"venue"
},
  "geometry": {"coordinates":[-89.125462,41.368117],"type":"Point"}
}