{
  "type": "Feature",
  "properties": {
    "iso:country":"US",
    "sg:address":"253 Miami St",
    "sg:city":"Park Forest",
    "sg:classifiers":[
        {
            "category":"Building & Trades",
            "subcategory":"Construction",
            "type":"Services"
        }
    ],
    "sg:phone":"+1 708 748 0855",
    "sg:postcode":"60466",
    "sg:province":"IL",
    "sg:tags":[
        "remodeling",
        "contractor"
    ],
    "wof:name":"Workmanship Unlimited",
    "wof:placetype":"venue"
},
  "geometry": {"coordinates":[-87.696316,41.475655],"type":"Point"}
}