{
  "type": "Feature",
  "properties": {
    "addr:full":"11116 S Michigan Ave Chicago IL 60628",
    "addr:housenumber":"11116",
    "addr:postcode":"60628",
    "addr:street":"S Michigan Ave",
    "iso:country":"US",
    "sg:address":"11116 S Michigan Ave",
    "sg:city":"Chicago",
    "sg:classifiers":[
        {
            "category":"Banks & Credit Unions",
            "subcategory":"Bank",
            "type":"Services"
        }
    ],
    "sg:phone":"+1 773 568 7850",
    "sg:postcode":"60628",
    "sg:province":"IL",
    "wof:name":"Seaway National Bank",
    "wof:placetype":"venue"
},
  "geometry": {"coordinates":[-87.621244,41.69212],"type":"Point"}
}