{
  "type": "Feature",
  "properties": {
    "iso:country":"US",
    "sg:address":"2705 Dorothy Dr",
    "sg:city":"Aurora",
    "sg:classifiers":[
        {
            "category":"Building & Trades",
            "subcategory":"Plumbing",
            "type":"Services"
        },
        {
            "category":"Building & Trades",
            "subcategory":"Construction",
            "type":"Services"
        }
    ],
    "sg:phone":"+1 630 978 1764",
    "sg:postcode":"60504",
    "sg:province":"IL",
    "sg:tags":[
        "plumber",
        "industrial",
        "system",
        "specialty",
        "heating",
        "contractors-commercial",
        "contractor",
        "air conditioning"
    ],
    "wof:name":"Craftsman Plumbing",
    "wof:placetype":"venue"
},
  "geometry": {"coordinates":[-88.248965,41.725327],"type":"Point"}
}