{
  "type": "Feature",
  "properties": {
    "iso:country":"US",
    "sg:address":"5294 Fargo Rd",
    "sg:city":"Erie",
    "sg:classifiers":[
        {
            "category":"Farming",
            "subcategory":"Livestock Farm",
            "type":"Manufacturing & Wholesale Goods"
        }
    ],
    "sg:phone":"+1 309 659 7787",
    "sg:postcode":"61250",
    "sg:province":"IL",
    "sg:tags":[
        "beef",
        "feedlot",
        "cattle"
    ],
    "wof:name":"Lavine E Burdette",
    "wof:placetype":"venue"
},
  "geometry": {"coordinates":[-90.144373,41.642503],"type":"Point"}
}