{
  "type": "Feature",
  "properties": {
    "iso:country":"US",
    "sg:address":"14 N Main St",
    "sg:city":"Ewing",
    "sg:classifiers":[
        {
            "category":"Government",
            "subcategory":"Police Station",
            "type":"Public Place"
        }
    ],
    "sg:phone":"+1 618 629 2440",
    "sg:postcode":"62836",
    "sg:province":"IL",
    "sg:tags":[
        "department"
    ],
    "wof:name":"Ewing Police Department",
    "wof:placetype":"venue"
},
  "geometry": {"coordinates":[-88.852853,38.088637],"type":"Point"}
}