{
  "type": "Feature",
  "properties": {
    "iso:country":"US",
    "sg:address":"500 11th St",
    "sg:city":"Rock Island",
    "sg:classifiers":[
        {
            "category":"Organizations",
            "subcategory":"Community Association",
            "type":"Services"
        }
    ],
    "sg:phone":"+1 309 788 8050",
    "sg:postcode":"61201",
    "sg:province":"IL",
    "sg:tags":[
        "fraternal"
    ],
    "wof:name":"King Soloman Lodge F & AM",
    "wof:placetype":"venue"
},
  "geometry": {"coordinates":[-90.583412,41.504768],"type":"Point"}
}