{
  "type": "Feature",
  "properties": {
    "iso:country":"US",
    "sg:address":"229 S Main St",
    "sg:city":"Jacksonville",
    "sg:classifiers":[
        {
            "category":"Organizations",
            "subcategory":"Religious Organization",
            "type":"Services"
        }
    ],
    "sg:phone":"+1 217 243 8913",
    "sg:postcode":"62650",
    "sg:province":"IL",
    "wof:name":"Community Bible Church",
    "wof:placetype":"venue"
},
  "geometry": {"coordinates":[-90.229206,39.733322],"type":"Point"}
}