{
  "type": "Feature",
  "properties": {
    "addr:full":"127 E Scranton Ave Lake Bluff IL 60044",
    "addr:housenumber":"127",
    "addr:postcode":"60044",
    "addr:street":"E Scranton Ave",
    "iso:country":"US",
    "sg:address":"127 E Scranton Ave",
    "sg:city":"Lake Bluff",
    "sg:classifiers":[
        {
            "category":"Museum",
            "type":"Entertainment"
        }
    ],
    "sg:phone":"+1 847 482 1571",
    "sg:postcode":"60044",
    "sg:province":"IL",
    "wof:name":"Lake Bluff Museum",
    "wof:placetype":"venue"
},
  "geometry": {"coordinates":[-87.842291,42.279591],"type":"Point"}
}