{
  "type": "Feature",
  "properties": {
    "iso:country":"US",
    "sg:address":"208 Koch St",
    "sg:city":"Pekin",
    "sg:classifiers":[
        {
            "category":"Bars & Pubs",
            "type":"Food & Drink"
        },
        {
            "category":"Restaurant",
            "type":"Food & Drink"
        }
    ],
    "sg:phone":"+1 309 346 2994",
    "sg:postcode":"61554",
    "sg:province":"IL",
    "sg:tags":[
        "tavern",
        "grill",
        "brew"
    ],
    "wof:name":"Koch St Bar & Grill",
    "wof:placetype":"venue"
},
  "geometry": {"coordinates":[-89.66076099999999,40.552995],"type":"Point"}
}