{
  "type": "Feature",
  "properties": {
    "iso:country":"US",
    "sg:address":"8414 W 119th St",
    "sg:city":"Palos Park",
    "sg:classifiers":[
        {
            "category":"Professional",
            "subcategory":"Business Services",
            "type":"Services"
        }
    ],
    "sg:phone":"+1 708 707 5273",
    "sg:postcode":"60464",
    "sg:province":"IL",
    "wof:name":"Thomas J Glowski",
    "wof:placetype":"venue"
},
  "geometry": {"coordinates":[-87.828175,41.674736],"type":"Point"}
}