{
  "type": "Feature",
  "properties": {
    "iso:country":"US",
    "sg:address":"4710 Winchester Ave",
    "sg:city":"Lisle",
    "sg:classifiers":[
        {
            "category":"Social Services",
            "type":"Services"
        }
    ],
    "sg:phone":"+1 630 960 5402",
    "sg:postcode":"60532",
    "sg:province":"IL",
    "sg:tags":[
        "counselor",
        "marriage",
        "family"
    ],
    "wof:name":"M Laura Forbes",
    "wof:placetype":"venue"
},
  "geometry": {"coordinates":[-88.088921,41.796376],"type":"Point"}
}