{
  "type": "Feature",
  "properties": {
    "addr:full":"204 Ross Ln Belleville IL 62220",
    "addr:housenumber":"204",
    "addr:postcode":"62220",
    "addr:street":"Ross Ln",
    "iso:country":"US",
    "sg:address":"204 Ross Ln",
    "sg:city":"Belleville",
    "sg:classifiers":[
        {
            "category":"Shopping",
            "subcategory":"Gifts & Souvenirs",
            "type":"Retail Goods"
        }
    ],
    "sg:phone":"+1   ",
    "sg:postcode":"62220",
    "sg:province":"IL",
    "sg:website":"www.craftyeye.com",
    "wof:name":"Crafty Eye Photography LTD",
    "wof:placetype":"venue"
},
  "geometry": {"coordinates":[-89.98410199999999,38.490397],"type":"Point"}
}