{
  "type": "Feature",
  "properties": {
    "addr:full":"311 Nicholson St Joliet IL 60435",
    "addr:housenumber":"311",
    "addr:postcode":"60435",
    "addr:street":"Nicholson St",
    "iso:country":"US",
    "sg:address":"311 Nicholson St",
    "sg:city":"Joliet",
    "sg:classifiers":[
        {
            "category":"Building & Trades",
            "subcategory":"Construction",
            "type":"Services"
        }
    ],
    "sg:phone":"+1 815 726 8129",
    "sg:postcode":"60435",
    "sg:province":"IL",
    "sg:tags":[
        "house"
    ],
    "wof:name":"Webber Construction",
    "wof:placetype":"venue"
},
  "geometry": {"coordinates":[-88.093947,41.529797],"type":"Point"}
}