{
  "type": "Feature",
  "properties": {
    "iso:country":"US",
    "sg:address":"2841 Birch St",
    "sg:city":"Franklin Park",
    "sg:classifiers":[
        {
            "category":"Retail",
            "subcategory":"Repair Shop",
            "type":"Services"
        }
    ],
    "sg:phone":"+1 847 451 0830",
    "sg:postcode":"60131",
    "sg:province":"IL",
    "sg:tags":[
        "welding"
    ],
    "wof:name":"Pauls Welding",
    "wof:placetype":"venue"
},
  "geometry": {"coordinates":[-87.856756,41.931499],"type":"Point"}
}