{
  "type": "Feature",
  "properties": {
    "iso:country":"US",
    "sg:address":"1712 Belvidere St",
    "sg:city":"Waukegan",
    "sg:classifiers":[
        {
            "category":"Retail",
            "subcategory":"Auto Repair",
            "type":"Services"
        }
    ],
    "sg:phone":"+1 847 336 9616",
    "sg:postcode":"60085",
    "sg:province":"IL",
    "sg:tags":[
        "general"
    ],
    "wof:name":"Fausto Auto Repair",
    "wof:placetype":"venue"
},
  "geometry": {"coordinates":[-87.85456499999999,42.350987],"type":"Point"}
}