{
  "type": "Feature",
  "properties": {
    "addr:full":"1219 Mallard Dr Elgin IL 60123",
    "addr:housenumber":"1219",
    "addr:postcode":"60123",
    "addr:street":"Mallard Dr",
    "iso:country":"US",
    "sg:address":"1219 Mallard Dr",
    "sg:city":"Elgin",
    "sg:classifiers":[
        {
            "category":"Building & Trades",
            "subcategory":"Construction",
            "type":"Services"
        }
    ],
    "sg:phone":"+1 847 695 9670",
    "sg:postcode":"60123",
    "sg:province":"IL",
    "sg:tags":[
        "system",
        "contractor",
        "air conditioning"
    ],
    "wof:name":"Kujak Heating & Air Conditioning",
    "wof:placetype":"venue"
},
  "geometry": {"coordinates":[-88.31358,42.063199],"type":"Point"}
}