{
  "type": "Feature",
  "properties": {
    "addr:full":"9024 S Cicero Ave Oak Lawn IL 60453",
    "addr:housenumber":"9024",
    "addr:postcode":"60453",
    "addr:street":"S Cicero Ave",
    "iso:country":"US",
    "sg:address":"9024 S Cicero Ave",
    "sg:city":"Oak Lawn",
    "sg:classifiers":[
        {
            "category":"Banks & Credit Unions",
            "subcategory":"Bank",
            "type":"Services"
        }
    ],
    "sg:phone":"+1 708 423 1500",
    "sg:postcode":"60453",
    "sg:province":"IL",
    "sg:tags":[
        "loan",
        "real estate"
    ],
    "wof:name":"B & D Capital Mortgage",
    "wof:placetype":"venue"
},
  "geometry": {"coordinates":[-87.741128,41.727802],"type":"Point"}
}