{
  "type": "Feature",
  "properties": {
    "iso:country":"US",
    "sg:address":"55 W Golf Rd",
    "sg:city":"Des Plaines",
    "sg:classifiers":[
        {
            "category":"Organizations",
            "subcategory":"Religious Organization",
            "type":"Services"
        }
    ],
    "sg:phone":"+1 847 635 7776",
    "sg:postcode":"60016",
    "sg:province":"IL",
    "wof:name":"Des Plains Free Church",
    "wof:placetype":"venue"
},
  "geometry": {"coordinates":[-87.922471,42.048593],"type":"Point"}
}