{
  "type": "Feature",
  "properties": {
    "iso:country":"US",
    "sg:address":"1416 S Michigan Avenue",
    "sg:city":"Chicago",
    "sg:classifiers":[
        {
            "category":"Restaurant",
            "type":"Food & Drink"
        },
        {
            "category":"Bars & Pubs",
            "subcategory":"Nightclub",
            "type":"Food & Drink"
        }
    ],
    "sg:phone":"+1 312 588 1800",
    "sg:postcode":"60605",
    "sg:province":"IL",
    "sg:tags":[
        "american",
        "irish",
        "nightlife"
    ],
    "sg:website":"www.graceomalleychicago.com",
    "wof:name":"Grace O'malley's",
    "wof:placetype":"venue"
},
  "geometry": {"coordinates":[-87.624212,41.863591],"type":"Point"}
}