{
  "type": "Feature",
  "properties": {
    "iso:country":"US",
    "sg:address":"812 Lucas Ave",
    "sg:city":"Thomson",
    "sg:classifiers":[
        {
            "category":"Restaurant",
            "type":"Food & Drink"
        }
    ],
    "sg:phone":"+1 815 259 2013",
    "sg:postcode":"61285",
    "sg:province":"IL",
    "sg:tags":[
        "pizza"
    ],
    "wof:name":"Atherton Oil",
    "wof:placetype":"venue"
},
  "geometry": {"coordinates":[-90.099654,41.951023],"type":"Point"}
}