{
  "type": "Feature",
  "properties": {
    "iso:country":"US",
    "sg:address":"246 N Woodwork Ln",
    "sg:city":"Palatine",
    "sg:classifiers":[
        {
            "category":"Retail",
            "subcategory":"Auto Repair",
            "type":"Services"
        }
    ],
    "sg:phone":"+1 847 221 2323",
    "sg:postcode":"60067",
    "sg:province":"IL",
    "sg:tags":[
        "body",
        "automobile",
        "brake",
        "painting",
        "repairing"
    ],
    "sg:website":"http://www.collisionrebuilders.com",
    "wof:name":"Auto Collision Rebuilders Inc",
    "wof:placetype":"venue"
},
  "geometry": {"coordinates":[-88.05693599999999,42.114421],"type":"Point"}
}