{
  "type": "Feature",
  "properties": {
    "iso:country":"US",
    "sg:address":"720 W Main St",
    "sg:city":"Belleville",
    "sg:classifiers":[
        {
            "category":"Professional",
            "subcategory":"Engineering",
            "type":"Services"
        }
    ],
    "sg:phone":"+1 618 234 3400",
    "sg:postcode":"62220",
    "sg:province":"IL",
    "wof:name":"Camber Corp",
    "wof:placetype":"venue"
},
  "geometry": {"coordinates":[-89.994654,38.514032],"type":"Point"}
}