{
  "type": "Feature",
  "properties": {
    "iso:country":"US",
    "sg:address":"1954 W Irving Park Rd",
    "sg:city":"Chicago",
    "sg:classifiers":[
        {
            "category":"Health Services",
            "subcategory":"Clinic",
            "type":"Services"
        }
    ],
    "sg:phone":"+1 773 414 4577",
    "sg:postcode":"60613",
    "sg:province":"IL",
    "sg:tags":[
        "counseling",
        "mental"
    ],
    "sg:website":"www.psychotherapychicago.com",
    "wof:name":"Psychotherapy Associates of Chicago",
    "wof:placetype":"venue"
},
  "geometry": {"coordinates":[-87.678698,41.954246],"type":"Point"}
}