{
  "type": "Feature",
  "properties": {
    "iso:country":"US",
    "sg:address":"2040 N 8th St",
    "sg:city":"Springfield",
    "sg:classifiers":[
        {
            "category":"Education",
            "subcategory":"School",
            "type":"Public Place"
        }
    ],
    "sg:phone":"+1 217 525 3259",
    "sg:postcode":"62702",
    "sg:province":"IL",
    "sg:tags":[
        "elementary"
    ],
    "sg:website":"http://www.springfield.k12.il.us",
    "wof:name":"Ridgely Elementary School",
    "wof:placetype":"venue"
},
  "geometry": {"coordinates":[-89.644626,39.827879],"type":"Point"}
}