{
  "type": "Feature",
  "properties": {
    "addr:full":"2401 N Milwaukee Avenue Chicago IL 60647",
    "addr:housenumber":"2401",
    "addr:postcode":"60647",
    "addr:street":"N Milwaukee Avenue",
    "iso:country":"US",
    "sg:address":"2401 N Milwaukee Avenue",
    "sg:city":"Chicago",
    "sg:classifiers":[
        {
            "category":"Food & Beverages",
            "subcategory":"Groceries & Convenience Stores",
            "type":"Retail Goods"
        }
    ],
    "sg:phone":"+1 773 227 1694",
    "sg:postcode":"60647",
    "sg:province":"IL",
    "wof:name":"7 Eleven",
    "wof:placetype":"venue"
},
  "geometry": {"coordinates":[-87.700604,41.924762],"type":"Point"}
}