{
  "type": "Feature",
  "properties": {
    "addr:full":"236 W Talcott Rd Park Ridge IL 60068",
    "addr:housenumber":"236",
    "addr:postcode":"60068",
    "addr:street":"W Talcott Rd Park Ridge",
    "iso:country":"US",
    "sg:address":"236 W Talcott Rd",
    "sg:city":"Park Ridge",
    "sg:classifiers":[
        {
            "category":"Manufacturing",
            "subcategory":"Tools & Machinery",
            "type":"Manufacturing & Wholesale Goods"
        }
    ],
    "sg:phone":"+1 847 318 7515",
    "sg:postcode":"60068",
    "sg:province":"IL",
    "sg:tags":[
        "equipment",
        "mfg"
    ],
    "wof:name":"Spytek Aerospace",
    "wof:placetype":"venue"
},
  "geometry": {"coordinates":[-87.826007,41.994842],"type":"Point"}
}