{
  "type": "Feature",
  "properties": {
    "iso:country":"US",
    "sg:address":"173 W Northwest Hwy",
    "sg:city":"Palatine",
    "sg:classifiers":[
        {
            "category":"Personal",
            "subcategory":"Beauty Salon",
            "type":"Services"
        }
    ],
    "sg:phone":"+1 847 963 9874",
    "sg:postcode":"60067",
    "sg:province":"IL",
    "sg:tags":[
        "shop"
    ],
    "wof:name":"Natural Nail",
    "wof:placetype":"venue"
},
  "geometry": {"coordinates":[-88.04786900000001,42.122191],"type":"Point"}
}