{
  "type": "Feature",
  "properties": {
    "iso:country":"US",
    "sg:address":"520 Ruth Ave",
    "sg:city":"Cottage Hills",
    "sg:classifiers":[
        {
            "category":"Health Services",
            "subcategory":"Chiropractor",
            "type":"Services"
        }
    ],
    "sg:phone":"+1 618 258 0900",
    "sg:postcode":"62018",
    "sg:province":"IL",
    "wof:name":"Vetter Chiropractic Inc",
    "wof:placetype":"venue"
},
  "geometry": {"coordinates":[-90.077598,38.899992],"type":"Point"}
}