{
  "type": "Feature",
  "properties": {
    "iso:country":"US",
    "sg:address":"1917 South St",
    "sg:city":"Geneva",
    "sg:classifiers":[
        {
            "category":"Manufacturing",
            "subcategory":"Printing",
            "type":"Manufacturing & Wholesale Goods"
        }
    ],
    "sg:phone":"+1 630 845 9481",
    "sg:postcode":"60134",
    "sg:province":"IL",
    "sg:tags":[
        "publisher"
    ],
    "wof:name":"Gamit Enterprises Inc",
    "wof:placetype":"venue"
},
  "geometry": {"coordinates":[-88.331067,41.883357],"type":"Point"}
}