{
  "type": "Feature",
  "properties": {
    "iso:country":"US",
    "sg:address":"724 Paris Ave",
    "sg:city":"Rockford",
    "sg:classifiers":[
        {
            "category":"Retail",
            "subcategory":"Portrait Studio",
            "type":"Services"
        }
    ],
    "sg:phone":"+1 815 394 1632",
    "sg:postcode":"61107",
    "sg:province":"IL",
    "sg:tags":[
        "photo"
    ],
    "wof:name":"Jim Orlando Photography",
    "wof:placetype":"venue"
},
  "geometry": {"coordinates":[-89.061388,42.274996],"type":"Point"}
}