{
  "type": "Feature",
  "properties": {
    "iso:country":"US",
    "sg:address":"2009 Irving Park Rd",
    "sg:city":"Bartlett",
    "sg:classifiers":[
        {
            "category":"Food & Beverages",
            "subcategory":"Groceries & Convenience Stores",
            "type":"Retail Goods"
        }
    ],
    "sg:phone":"+1   ",
    "sg:postcode":"60133",
    "sg:province":"IL",
    "wof:name":"Zuli Disctoteca Y Regalos",
    "wof:placetype":"venue"
},
  "geometry": {"coordinates":[-88.15411899999999,42.008193],"type":"Point"}
}