{
  "type": "Feature",
  "properties": {
    "addr:full":"3918 N Milwaukee Ave Chicago IL 60641",
    "addr:housenumber":"3918",
    "addr:postcode":"60641",
    "addr:street":"N Milwaukee Ave",
    "iso:country":"US",
    "sg:address":"3918 N Milwaukee Ave",
    "sg:city":"Chicago",
    "sg:classifiers":[
        {
            "category":"Wholesale",
            "subcategory":"Auto Parts",
            "type":"Manufacturing & Wholesale Goods"
        }
    ],
    "sg:phone":"+1 773 736 6900",
    "sg:postcode":"60641",
    "sg:province":"IL",
    "sg:tags":[
        "automotive",
        "supply"
    ],
    "wof:name":"Portage Auto Parts Inc",
    "wof:placetype":"venue"
},
  "geometry": {"coordinates":[-87.74703599999999,41.953143],"type":"Point"}
}