{
  "type": "Feature",
  "properties": {
    "addr:full":"1 S Greenleaf St Ste E Gurnee IL 60031",
    "addr:housenumber":"1",
    "addr:postcode":"60031",
    "addr:street":"S Greenleaf St Ste E",
    "iso:country":"US",
    "sg:address":"1 S Greenleaf St Ste E",
    "sg:city":"Gurnee",
    "sg:classifiers":[
        {
            "category":"Health Services",
            "subcategory":"Doctor",
            "type":"Services"
        }
    ],
    "sg:phone":"+1 847 623 4010",
    "sg:postcode":"60031",
    "sg:province":"IL",
    "sg:tags":[
        "physician",
        "surgeon",
        "urology",
        "surgeons"
    ],
    "wof:name":"Urology Associates Ltd",
    "wof:placetype":"venue"
},
  "geometry": {"coordinates":[-87.902016,42.359631],"type":"Point"}
}