{
  "type": "Feature",
  "properties": {
    "addr:full":"1320 W Nelson St Chicago IL 60657",
    "addr:housenumber":"1320",
    "addr:postcode":"60657",
    "addr:street":"W Nelson St",
    "iso:country":"US",
    "sg:address":"1320 W Nelson St",
    "sg:city":"Chicago",
    "sg:classifiers":[
        {
            "category":"Health Services",
            "subcategory":"Doctor",
            "type":"Services"
        }
    ],
    "sg:phone":"+1 773 248 1222",
    "sg:postcode":"60657",
    "sg:province":"IL",
    "sg:tags":[
        "medical"
    ],
    "wof:name":"Leslie Zun MD Assoc",
    "wof:placetype":"venue"
},
  "geometry": {"coordinates":[-87.66270799999999,41.937122],"type":"Point"}
}