{
  "type": "Feature",
  "properties": {
    "addr:full":"3642 W 59th Street Chicago IL 60629",
    "addr:housenumber":"3642",
    "addr:postcode":"60629",
    "addr:street":"W 59Th Street",
    "iso:country":"US",
    "sg:address":"3642 W 59th Street",
    "sg:city":"Chicago",
    "sg:classifiers":[
        {
            "category":"Autos & Motor Vehicles",
            "subcategory":"Fuel & Gas Station",
            "type":"Retail Goods"
        }
    ],
    "sg:phone":"+1 773 838 8300",
    "sg:postcode":"60629",
    "sg:province":"IL",
    "wof:name":"E & A Oil Company",
    "wof:placetype":"venue"
},
  "geometry": {"coordinates":[-87.714826,41.78607],"type":"Point"}
}