{
  "type": "Feature",
  "properties": {
    "addr:full":"711 Spring St Collinsville IL 62234",
    "addr:housenumber":"711",
    "addr:postcode":"62234",
    "addr:street":"Spring St",
    "iso:country":"US",
    "sg:address":"711 Spring St",
    "sg:city":"Collinsville",
    "sg:classifiers":[
        {
            "category":"Autos & Motor Vehicles",
            "subcategory":"Motorcycle Sales",
            "type":"Retail Goods"
        },
        {
            "category":"Retail",
            "subcategory":"Auto Repair",
            "type":"Services"
        }
    ],
    "sg:phone":"+1 618 345 4102",
    "sg:postcode":"62234",
    "sg:province":"IL",
    "sg:tags":[
        "scooters-parts",
        "supply"
    ],
    "wof:name":"Spring Street Specialties",
    "wof:placetype":"venue"
},
  "geometry": {"coordinates":[-89.974998,38.6758],"type":"Point"}
}