{
  "type": "Feature",
  "properties": {
    "iso:country":"US",
    "sg:address":"4500 N Spaulding Ave",
    "sg:city":"Chicago",
    "sg:classifiers":[
        {
            "category":"Place Of Worship",
            "subcategory":"Church",
            "type":"Public Place"
        },
        {
            "category":"Place Of Worship",
            "type":"Public Place"
        }
    ],
    "sg:phone":"+1 773 539 3810",
    "sg:postcode":"60625",
    "sg:province":"IL",
    "sg:tags":[
        "churches-presbyterian-arp",
        "churches-presbyterian"
    ],
    "wof:name":"Chgo Milal Church",
    "wof:placetype":"venue"
},
  "geometry": {"coordinates":[-87.71077,41.962959],"type":"Point"}
}