{
  "type": "Feature",
  "properties": {
    "iso:country":"US",
    "sg:address":"517 Stice Rd",
    "sg:city":"Winchester",
    "sg:classifiers":[
        {
            "category":"Autos & Motor Vehicles",
            "subcategory":"Automobile Sales",
            "type":"Retail Goods"
        }
    ],
    "sg:phone":"+1   ",
    "sg:postcode":"62694",
    "sg:province":"IL",
    "wof:name":"Tranbarger Auto",
    "wof:placetype":"venue"
},
  "geometry": {"coordinates":[-90.56143400000001,39.599607],"type":"Point"}
}