{
  "type": "Feature",
  "properties": {
    "addr:full":"1255 S Wabash Ave Chicago IL 60605",
    "addr:housenumber":"1255",
    "addr:postcode":"60605",
    "addr:street":"S Wabash Ave",
    "iso:country":"US",
    "sg:address":"1255 S Wabash Ave",
    "sg:city":"Chicago",
    "sg:classifiers":[
        {
            "category":"Retail",
            "subcategory":"Storage",
            "type":"Services"
        }
    ],
    "sg:phone":"+1 312 986 8400",
    "sg:postcode":"60605",
    "sg:province":"IL",
    "sg:tags":[
        "self"
    ],
    "sg:website":"www.extraspace.com",
    "wof:name":"Extra Space Storage",
    "wof:placetype":"venue"
},
  "geometry": {"coordinates":[-87.62529499999999,41.865922],"type":"Point"}
}