{
  "type": "Feature",
  "properties": {
    "iso:country":"US",
    "sg:address":"9333 Lavergne Ave",
    "sg:city":"Skokie",
    "sg:classifiers":[
        {
            "category":"Wholesale",
            "subcategory":"Non-durable Goods",
            "type":"Manufacturing & Wholesale Goods"
        }
    ],
    "sg:phone":"+1 847 674 2093",
    "sg:postcode":"60077",
    "sg:province":"IL",
    "sg:tags":[
        "apparel",
        "to",
        "corporate",
        "market",
        "promotional"
    ],
    "wof:name":"Apparel Resources Inc",
    "wof:placetype":"venue"
},
  "geometry": {"coordinates":[-87.75166900000001,42.051069],"type":"Point"}
}