{
  "type": "Feature",
  "properties": {
    "iso:country":"US",
    "sg:address":"3600 Airport Dr",
    "sg:city":"Rockford",
    "sg:classifiers":[
        {
            "category":"Freight",
            "type":"Transportation"
        }
    ],
    "sg:phone":"+1 815 962 3400",
    "sg:postcode":"61109",
    "sg:province":"IL",
    "sg:tags":[
        "broker",
        "customs"
    ],
    "wof:name":"CBC Customhouse Brokers Inc",
    "wof:placetype":"venue"
},
  "geometry": {"coordinates":[-89.112647,42.201452],"type":"Point"}
}