{
  "type": "Feature",
  "properties": {
    "iso:country":"US",
    "sg:address":"15750 S Harlem Ave",
    "sg:city":"Orland Park",
    "sg:classifiers":[
        {
            "category":"Building & Trades",
            "subcategory":"Construction",
            "type":"Services"
        }
    ],
    "sg:phone":"+1 708 429 0210",
    "sg:postcode":"60462",
    "sg:province":"IL",
    "sg:tags":[
        "excavating",
        "grading",
        "contractor",
        "water",
        "sewer",
        "general"
    ],
    "wof:name":"Advance Construction Company",
    "wof:placetype":"venue"
},
  "geometry": {"coordinates":[-87.794327,41.605089],"type":"Point"}
}