{
  "type": "Feature",
  "properties": {
    "addr:full":"611 Division St Peotone IL 60468",
    "addr:housenumber":"611",
    "addr:postcode":"60468",
    "addr:street":"Division St",
    "iso:country":"US",
    "sg:address":"611 Division St",
    "sg:city":"Peotone",
    "sg:classifiers":[
        {
            "category":"Health Services",
            "subcategory":"Doctor",
            "type":"Services"
        }
    ],
    "sg:phone":"+1 708 258 9058",
    "sg:postcode":"60468",
    "sg:province":"IL",
    "sg:tags":[
        "physician",
        "surgeon"
    ],
    "wof:name":"Orthopedic Associates-Kankakee",
    "wof:placetype":"venue"
},
  "geometry": {"coordinates":[-87.801632,41.325156],"type":"Point"}
}