{
  "type": "Feature",
  "properties": {
    "iso:country":"US",
    "sg:address":"398 Bethel Rd",
    "sg:city":"Collinsville",
    "sg:classifiers":[
        {
            "category":"Retail",
            "subcategory":"Repair Shop",
            "type":"Services"
        }
    ],
    "sg:phone":"+1 618 345 3869",
    "sg:postcode":"62234",
    "sg:province":"IL",
    "wof:name":"Mikes Prop Sales & Repair",
    "wof:placetype":"venue"
},
  "geometry": {"coordinates":[-89.967736,38.65886],"type":"Point"}
}