{
  "type": "Feature",
  "properties": {
    "addr:full":"138 E Quincy St Westmont IL 60559",
    "addr:housenumber":"138 e",
    "addr:postcode":"60559",
    "addr:street":"Quincy St",
    "iso:country":"US",
    "sg:address":"138 E Quincy St",
    "sg:city":"Westmont",
    "sg:classifiers":[
        {
            "category":"Manufacturing",
            "subcategory":"Tools & Machinery",
            "type":"Manufacturing & Wholesale Goods"
        },
        {
            "category":"Retail",
            "subcategory":"Repair Shop",
            "type":"Services"
        },
        {
            "category":"Retail",
            "subcategory":"Auto Repair",
            "type":"Services"
        }
    ],
    "sg:phone":"+1 630 852 3419",
    "sg:postcode":"60559",
    "sg:province":"IL",
    "sg:tags":[
        "machine",
        "automobile",
        "machinery-rebuild"
    ],
    "wof:name":"Rebco Machine Specialties Inc",
    "wof:placetype":"venue"
},
  "geometry": {"coordinates":[-87.971934,41.795014],"type":"Point"}
}