{
  "type": "Feature",
  "properties": {
    "iso:country":"US",
    "sg:address":"1104 S Harvey Ave",
    "sg:city":"Oak Park",
    "sg:classifiers":[
        {
            "category":"Manufacturing",
            "subcategory":"Wood Products",
            "type":"Manufacturing & Wholesale Goods"
        }
    ],
    "sg:phone":"+1 708 848 7981",
    "sg:postcode":"60304",
    "sg:province":"IL",
    "sg:tags":[
        "mfg"
    ],
    "wof:name":"Yard It",
    "wof:placetype":"venue"
},
  "geometry": {"coordinates":[-87.780263,41.867356],"type":"Point"}
}