{
  "type": "Feature",
  "properties": {
    "iso:country":"US",
    "sg:address":"1104 E Rexford St",
    "sg:city":"Centralia",
    "sg:classifiers":[
        {
            "category":"Wholesale",
            "subcategory":"Groceries",
            "type":"Manufacturing & Wholesale Goods"
        }
    ],
    "sg:phone":"+1 618 532 7917",
    "sg:postcode":"62801",
    "sg:province":"IL",
    "wof:name":"Darwin D Smith",
    "wof:placetype":"venue"
},
  "geometry": {"coordinates":[-89.12008,38.532643],"type":"Point"}
}