{
  "type": "Feature",
  "properties": {
    "iso:country":"US",
    "sg:address":"746 N 1470 East Rd",
    "sg:city":"Cissna Park",
    "sg:classifiers":[
        {
            "category":"Building & Trades",
            "subcategory":"Electrical",
            "type":"Services"
        }
    ],
    "sg:phone":"+1 815 457 2543",
    "sg:postcode":"60924",
    "sg:province":"IL",
    "sg:tags":[
        "electric",
        "contractor"
    ],
    "wof:name":"J O Dan Svc",
    "wof:placetype":"venue"
},
  "geometry": {"coordinates":[-87.847155,40.60206],"type":"Point"}
}