{
  "type": "Feature",
  "properties": {
    "iso:country":"US",
    "sg:address":"2020 N State St",
    "sg:city":"Belvidere",
    "sg:classifiers":[
        {
            "category":"Home & Garden",
            "subcategory":"Furniture",
            "type":"Retail Goods"
        }
    ],
    "sg:phone":"+1 815 544 5323",
    "sg:postcode":"61008",
    "sg:province":"IL",
    "sg:tags":[
        "household",
        "dist",
        "electric",
        "major"
    ],
    "wof:name":"Home Town Furnishings",
    "wof:placetype":"venue"
},
  "geometry": {"coordinates":[-88.862533,42.272957],"type":"Point"}
}