{
  "type": "Feature",
  "properties": {
    "addr:full":"805 Estes Ave Schaumburg IL 60193",
    "addr:housenumber":"805",
    "addr:postcode":"60193",
    "addr:street":"Estes Ave",
    "iso:country":"US",
    "sg:address":"805 Estes Ave",
    "sg:city":"Schaumburg",
    "sg:classifiers":[
        {
            "category":"Home & Garden",
            "subcategory":"Building Materials",
            "type":"Retail Goods"
        },
        {
            "category":"Building & Trades",
            "subcategory":"Construction",
            "type":"Services"
        }
    ],
    "sg:phone":"+1 847 999 0336",
    "sg:postcode":"60193",
    "sg:province":"IL",
    "sg:tags":[
        "window",
        "siding",
        "contractor"
    ],
    "sg:website":"http://www.sunshinesidingandwindow.com",
    "wof:name":"Sunshine Siding & Window Co",
    "wof:placetype":"venue"
},
  "geometry": {"coordinates":[-88.09978,42.002747],"type":"Point"}
}