{
  "type": "Feature",
  "properties": {
    "iso:country":"US",
    "sg:address":"1502 Rivercrest Rd",
    "sg:city":"Danville",
    "sg:classifiers":[
        {
            "category":"Health Services",
            "subcategory":"Dentist",
            "type":"Services"
        }
    ],
    "sg:phone":"+1 217 431 1696",
    "sg:postcode":"61832",
    "sg:province":"IL",
    "wof:name":"Zundo, George R",
    "wof:placetype":"venue"
},
  "geometry": {"coordinates":[-87.64810900000001,40.149761],"type":"Point"}
}