{
  "type": "Feature",
  "properties": {
    "iso:country":"US",
    "sg:address":"609 Brainerd Ave",
    "sg:city":"Libertyville",
    "sg:classifiers":[
        {
            "category":"Wholesale",
            "subcategory":"Machinery & Supplies",
            "type":"Manufacturing & Wholesale Goods"
        }
    ],
    "sg:phone":"+1 847 918 7412",
    "sg:postcode":"60048",
    "sg:province":"IL",
    "sg:tags":[
        "equipment",
        "industrial"
    ],
    "sg:website":"www.austindavis.com",
    "wof:name":"Austin Davis Industries Inc",
    "wof:placetype":"venue"
},
  "geometry": {"coordinates":[-87.95656,42.28872],"type":"Point"}
}