{
  "type": "Feature",
  "properties": {
    "iso:country":"US",
    "sg:address":"830 E Higgins Rd",
    "sg:city":"Schaumburg",
    "sg:classifiers":[
        {
            "category":"Social Services",
            "type":"Services"
        },
        {
            "category":"Personal",
            "type":"Services"
        }
    ],
    "sg:phone":"+1 847 845 8696",
    "sg:postcode":"60173",
    "sg:province":"IL",
    "sg:tags":[
        "family",
        "counselors-licensed",
        "individual",
        "marriage",
        "child",
        "professional",
        "counselor"
    ],
    "wof:name":"William Visser",
    "wof:placetype":"venue"
},
  "geometry": {"coordinates":[-88.059642,42.040957],"type":"Point"}
}