{
  "type": "Feature",
  "properties": {
    "iso:country":"US",
    "sg:address":"207 W 7th St",
    "sg:city":"Metropolis",
    "sg:classifiers":[
        {
            "category":"Professional",
            "subcategory":"Lawyer & Legal Services",
            "type":"Services"
        }
    ],
    "sg:phone":"+1 618 524 8851",
    "sg:postcode":"62960",
    "sg:province":"IL",
    "sg:tags":[
        "attorney",
        "family",
        "divorce",
        "practice",
        "plan",
        "law"
    ],
    "wof:name":"Peters, Leslie J Attorney At Law",
    "wof:placetype":"venue"
},
  "geometry": {"coordinates":[-88.73166500000001,37.153634],"type":"Point"}
}