{
  "type": "Feature",
  "properties": {
    "iso:country":"US",
    "sg:address":"7514 N Diversey Avenue 1-C",
    "sg:city":"Elmwood Park",
    "sg:classifiers":[
        {
            "category":"Food & Beverages",
            "subcategory":"Groceries & Convenience Stores",
            "type":"Retail Goods"
        }
    ],
    "sg:phone":"+1 773 817 0743",
    "sg:postcode":"60707",
    "sg:province":"IL",
    "wof:name":"Tiangge",
    "wof:placetype":"venue"
},
  "geometry": {"coordinates":[-87.81430899999999,41.930633],"type":"Point"}
}