{
  "type": "Feature",
  "properties": {
    "addr:full":"801 W Adams St Chicago IL 60607",
    "addr:housenumber":"801",
    "addr:postcode":"60607",
    "addr:street":"W Adams St",
    "iso:country":"US",
    "sg:address":"801 W Adams St",
    "sg:city":"Chicago",
    "sg:classifiers":[
        {
            "category":"Social Services",
            "type":"Services"
        },
        {
            "category":"Organizations",
            "subcategory":"Community Association",
            "type":"Services"
        }
    ],
    "sg:phone":"+1 312 627 1821",
    "sg:postcode":"60607",
    "sg:province":"IL",
    "wof:name":"World Council Of Hellenes Abroad Sae",
    "wof:placetype":"venue"
},
  "geometry": {"coordinates":[-87.647263,41.879219],"type":"Point"}
}