{
  "type": "Feature",
  "properties": {
    "iso:country":"US",
    "sg:address":"2823 S Princeton Avenue",
    "sg:city":"Chicago",
    "sg:classifiers":[
        {
            "category":"Place Of Worship",
            "subcategory":"Church",
            "type":"Public Place"
        },
        {
            "category":"Place Of Worship",
            "type":"Public Place"
        },
        {
            "category":"Organizations",
            "subcategory":"Religious Organization",
            "type":"Services"
        }
    ],
    "sg:phone":"+1 312 842 1871",
    "sg:postcode":"60616",
    "sg:province":"IL",
    "sg:tags":[
        "churches-catholic-traditional",
        "churches-catholic"
    ],
    "sg:website":"www.stjeromecroatian.org/",
    "wof:name":"St Jerome's Church",
    "wof:placetype":"venue"
},
  "geometry": {"coordinates":[-87.634046,41.84238],"type":"Point"}
}