{
  "type": "Feature",
  "properties": {
    "addr:full":"3036 Hobson Rd Woodridge IL 60517",
    "addr:housenumber":"3036",
    "addr:postcode":"60517",
    "addr:street":"Hobson Rd",
    "iso:country":"US",
    "sg:address":"3036 Hobson Rd",
    "sg:city":"Woodridge",
    "sg:classifiers":[
        {
            "category":"Shopping",
            "subcategory":"Beauty & Cosmetics",
            "type":"Retail Goods"
        },
        {
            "category":"Personal",
            "subcategory":"Barber",
            "type":"Services"
        },
        {
            "category":"Personal",
            "subcategory":"Beauty Salon",
            "type":"Services"
        }
    ],
    "sg:phone":"+1 630 241 4696",
    "sg:postcode":"60517",
    "sg:province":"IL",
    "sg:tags":[
        "equipment",
        "perfume",
        "salons-equipment",
        "supply"
    ],
    "wof:name":"Victory Beauty Systems",
    "wof:placetype":"venue"
},
  "geometry": {"coordinates":[-88.059192,41.763406],"type":"Point"}
}