{
  "type": "Feature",
  "properties": {
    "iso:country":"US",
    "sg:address":"953 State St",
    "sg:city":"Chester",
    "sg:classifiers":[
        {
            "category":"Home & Garden",
            "subcategory":"Carpets & Floor Coverings",
            "type":"Retail Goods"
        }
    ],
    "sg:phone":"+1 618 826 3064",
    "sg:postcode":"62233",
    "sg:province":"IL",
    "sg:tags":[
        "flooring",
        "contractor"
    ],
    "sg:website":"http://www.nealandsonsflooring.com/",
    "wof:name":"Neal & Sons Flooring",
    "wof:placetype":"venue"
},
  "geometry": {"coordinates":[-89.824552,37.911026],"type":"Point"}
}