{
  "type": "Feature",
  "properties": {
    "iso:country":"US",
    "sg:address":"17368 E Randolph Rd",
    "sg:city":"Canton",
    "sg:phone":"+1 309 647 5265",
    "sg:postcode":"61520",
    "sg:province":"IL",
    "sg:tags":[
        "farm",
        "corn",
        "soybean"
    ],
    "wof:name":"Charles E Bump",
    "wof:placetype":"venue"
},
  "geometry": {"coordinates":[-90.114228,40.582335],"type":"Point"}
}