{
  "type": "Feature",
  "properties": {
    "addr:full":"6901 34th St Berwyn IL 60402",
    "addr:housenumber":"6901",
    "addr:postcode":"60402",
    "addr:street":"34Th St",
    "iso:country":"US",
    "sg:address":"6901 34th St",
    "sg:city":"Berwyn",
    "sg:classifiers":[
        {
            "category":"Building & Trades",
            "subcategory":"Plumbing",
            "type":"Services"
        }
    ],
    "sg:phone":"+1 708 788 1111",
    "sg:postcode":"60402",
    "sg:province":"IL",
    "sg:tags":[
        "conditioning",
        "air",
        "system",
        "contractor"
    ],
    "wof:name":"All Systems Svc",
    "wof:placetype":"venue"
},
  "geometry": {"coordinates":[-87.79637700000001,41.830405],"type":"Point"}
}