{
  "type": "Feature",
  "properties": {
    "addr:full":"210 Main St Lemont IL 60439",
    "addr:housenumber":"210",
    "addr:postcode":"60439",
    "addr:street":"Main St",
    "iso:country":"US",
    "sg:address":"210 Main St",
    "sg:city":"Lemont",
    "sg:classifiers":[
        {
            "category":"Restaurant",
            "type":"Food & Drink"
        }
    ],
    "sg:phone":"+1   ",
    "sg:postcode":"60439",
    "sg:province":"IL",
    "sg:tags":[
        "chinese"
    ],
    "wof:name":"Lemont House Restaurant",
    "wof:placetype":"venue"
},
  "geometry": {"coordinates":[-88.00027799999999,41.673942],"type":"Point"}
}