{
  "type": "Feature",
  "properties": {
    "addr:full":"165 Hawthorn Way Cary IL 60013",
    "addr:housenumber":"165",
    "addr:postcode":"60013",
    "addr:street":"Hawthorn Way",
    "iso:country":"US",
    "sg:address":"165 Hawthorn Way",
    "sg:city":"Cary",
    "sg:classifiers":[
        {
            "category":"Building & Trades",
            "subcategory":"Cleaning & Sanitation",
            "type":"Services"
        }
    ],
    "sg:phone":"+1 847 516 1849",
    "sg:postcode":"60013",
    "sg:province":"IL",
    "sg:tags":[
        "maintenance"
    ],
    "wof:name":"Nancys Final Touch Cleaning",
    "wof:placetype":"venue"
},
  "geometry": {"coordinates":[-88.258548,42.201736],"type":"Point"}
}