{
  "type": "Feature",
  "properties": {
    "addr:full":"9914 Derby Ln Westchester IL 60154",
    "addr:housenumber":"9914",
    "addr:postcode":"60154",
    "addr:street":"Derby Ln",
    "iso:country":"US",
    "sg:address":"9914 Derby Ln",
    "sg:city":"Westchester",
    "sg:classifiers":[
        {
            "category":"Professional",
            "subcategory":"Business Services",
            "type":"Services"
        }
    ],
    "sg:phone":"+1 708 345 0275",
    "sg:postcode":"60154",
    "sg:province":"IL",
    "sg:tags":[
        "printing",
        "broker"
    ],
    "wof:name":"Printing Impressions Direct",
    "wof:placetype":"venue"
},
  "geometry": {"coordinates":[-87.870656,41.862741],"type":"Point"}
}