{
  "type": "Feature",
  "properties": {
    "addr:full":"401 E Dundee Rd Wheeling IL 60090",
    "addr:housenumber":"401",
    "addr:postcode":"60090",
    "addr:street":"E Dundee Rd",
    "iso:country":"US",
    "sg:address":"401 E Dundee Rd",
    "sg:city":"Wheeling",
    "sg:phone":"+1 847 520 0666",
    "sg:postcode":"60090",
    "sg:province":"IL",
    "sg:website":"http://www.edwardos.com",
    "wof:name":"Edwardo's Natural Pizza",
    "wof:placetype":"venue"
},
  "geometry": {"coordinates":[-87.907382,42.139759],"type":"Point"}
}