{
  "type": "Feature",
  "properties": {
    "addr:full":"201 W High St Freeburg IL 62243",
    "addr:housenumber":"201",
    "addr:postcode":"62243",
    "addr:street":"W High St",
    "iso:country":"US",
    "sg:address":"201 W High St",
    "sg:city":"Freeburg",
    "sg:classifiers":[
        {
            "category":"Health Services",
            "subcategory":"Doctor",
            "type":"Services"
        }
    ],
    "sg:phone":"+1 618 539 5519",
    "sg:postcode":"62243",
    "sg:province":"IL",
    "sg:tags":[
        "dentist"
    ],
    "wof:name":"Burl W Hand III DDS",
    "wof:placetype":"venue"
},
  "geometry": {"coordinates":[-89.911079,38.425509],"type":"Point"}
}