{
  "type": "Feature",
  "properties": {
    "addr:full":"417 S Cedarwood Dr Danville IL 61832",
    "addr:housenumber":"417",
    "addr:postcode":"61832",
    "addr:street":"S Cedarwood Dr",
    "iso:country":"US",
    "sg:address":"417 S Cedarwood Dr",
    "sg:city":"Danville",
    "sg:classifiers":[
        {
            "category":"Organizations",
            "subcategory":"Religious Organization",
            "type":"Services"
        }
    ],
    "sg:phone":"+1 217 431 0747",
    "sg:postcode":"61832",
    "sg:province":"IL",
    "sg:tags":[
        "clergy"
    ],
    "wof:name":"Jerry Cummins",
    "wof:placetype":"venue"
},
  "geometry": {"coordinates":[-87.62117600000001,40.164444],"type":"Point"}
}