{
  "type": "Feature",
  "properties": {
    "addr:full":"120 W 4th St Delavan IL 61734",
    "addr:housenumber":"120",
    "addr:postcode":"61734",
    "addr:street":"W 4Th St",
    "iso:country":"US",
    "sg:address":"120 W 4th St",
    "sg:city":"Delavan",
    "sg:classifiers":[
        {
            "category":"Insurance",
            "subcategory":"Insurance Agent",
            "type":"Services"
        }
    ],
    "sg:phone":"+1 309 244 8528",
    "sg:postcode":"61734",
    "sg:province":"IL",
    "wof:name":"Donley Insurance Partnership",
    "wof:placetype":"venue"
},
  "geometry": {"coordinates":[-89.54778399999999,40.372448],"type":"Point"}
}