{
  "type": "Feature",
  "properties": {
    "iso:country":"US",
    "sg:address":"4040 Charles St",
    "sg:city":"Rockford",
    "sg:classifiers":[
        {
            "category":"Professional",
            "subcategory":"Accounting & Tax Preparation",
            "type":"Services"
        }
    ],
    "sg:phone":"+1 815 398 6022",
    "sg:postcode":"61108",
    "sg:province":"IL",
    "sg:tags":[
        "return",
        "filing"
    ],
    "wof:name":"M & J Tax Svc",
    "wof:placetype":"venue"
},
  "geometry": {"coordinates":[-89.035588,42.254547],"type":"Point"}
}