{
  "type": "Feature",
  "properties": {
    "iso:country":"US",
    "sg:address":"6532 Cermak Rd",
    "sg:city":"Berwyn",
    "sg:classifiers":[
        {
            "category":"Banks & Credit Unions",
            "subcategory":"Bank",
            "type":"Services"
        }
    ],
    "sg:phone":"+1 708 484 2250",
    "sg:postcode":"60402",
    "sg:province":"IL",
    "sg:website":"www.chase.com",
    "wof:name":"Chase Bank and ATM",
    "wof:placetype":"venue"
},
  "geometry": {"coordinates":[-87.787469,41.850953],"type":"Point"}
}