{
  "type": "Feature",
  "properties": {
    "addr:full":"47 Timberhill Dr Crystal Lake IL 60014",
    "addr:housenumber":"47",
    "addr:postcode":"60014",
    "addr:street":"Timberhill Dr",
    "iso:country":"US",
    "sg:address":"47 Timberhill Dr",
    "sg:city":"Crystal Lake",
    "sg:classifiers":[
        {
            "category":"Shopping",
            "subcategory":"Bicycles & Sporting Goods",
            "type":"Retail Goods"
        }
    ],
    "sg:phone":"+1   ",
    "sg:postcode":"60014",
    "sg:province":"IL",
    "wof:name":"Daves Sporting Goods Inc",
    "wof:placetype":"venue"
},
  "geometry": {"coordinates":[-88.365246,42.239498],"type":"Point"}
}