{
  "type": "Feature",
  "properties": {
    "addr:full":"619 Wentworth Ave Calumet City IL 60409",
    "addr:housenumber":"619",
    "addr:postcode":"60409",
    "addr:street":"Wentworth Ave",
    "iso:country":"US",
    "sg:address":"619 Wentworth Ave",
    "sg:city":"Calumet City",
    "sg:classifiers":[
        {
            "category":"Retail",
            "subcategory":"Veterinary Services",
            "type":"Services"
        }
    ],
    "sg:phone":"+1 708 862 1900",
    "sg:postcode":"60409",
    "sg:province":"IL",
    "sg:tags":[
        "veterinarian"
    ],
    "wof:name":"Calumet Animal Clinic",
    "wof:placetype":"venue"
},
  "geometry": {"coordinates":[-87.52979999999999,41.618301],"type":"Point"}
}