{
  "type": "Feature",
  "properties": {
    "addr:full":"520 N Dearborn St Chicago IL 60654",
    "addr:housenumber":"520",
    "addr:postcode":"60654",
    "addr:street":"N Dearborn St",
    "iso:country":"US",
    "sg:address":"520 N Dearborn St",
    "sg:city":"Chicago",
    "sg:classifiers":[
        {
            "category":"Restaurant",
            "type":"Food & Drink"
        }
    ],
    "sg:phone":"+1 312 521 5100",
    "sg:postcode":"60654",
    "sg:province":"IL",
    "sg:tags":[
        "steakhouse"
    ],
    "sg:website":"www.mastrosrestaurants.com",
    "wof:name":"Mastro's Steakhouse",
    "wof:placetype":"venue"
},
  "geometry": {"coordinates":[-87.629937,41.8915],"type":"Point"}
}