{
  "type": "Feature",
  "properties": {
    "addr:full":"1901 W Wellington Ave Chicago IL 60657",
    "addr:housenumber":"1901",
    "addr:postcode":"60657",
    "addr:street":"W Wellington Ave",
    "iso:country":"US",
    "sg:address":"1901 W Wellington Ave",
    "sg:city":"Chicago",
    "sg:classifiers":[
        {
            "category":"Communications",
            "subcategory":"Film & Video Production",
            "type":"Services"
        }
    ],
    "sg:phone":"+1 773 472 4366",
    "sg:postcode":"60657",
    "sg:province":"IL",
    "sg:tags":[
        "motion",
        "picture",
        "producer"
    ],
    "wof:name":"Educational Films",
    "wof:placetype":"venue"
},
  "geometry": {"coordinates":[-87.677628,41.935936],"type":"Point"}
}