{
  "type": "Feature",
  "properties": {
    "iso:country":"US",
    "sg:address":"1711 W Algonquin Rd",
    "sg:city":"Mount Prospect",
    "sg:classifiers":[
        {
            "category":"Cinema",
            "subcategory":"Movie Rental",
            "type":"Entertainment"
        }
    ],
    "sg:phone":"+1 847 640 9404",
    "sg:postcode":"60056",
    "sg:province":"IL",
    "sg:tags":[
        "video",
        "tape"
    ],
    "wof:name":"T J Video",
    "wof:placetype":"venue"
},
  "geometry": {"coordinates":[-87.963606,42.03677],"type":"Point"}
}