{
  "type": "Feature",
  "properties": {
    "addr:full":"2212 Kensington Dr Schaumburg IL 60194",
    "addr:housenumber":"2212",
    "addr:postcode":"60194",
    "addr:street":"Kensington Dr",
    "iso:country":"US",
    "sg:address":"2212 Kensington Dr",
    "sg:city":"Schaumburg",
    "sg:classifiers":[
        {
            "category":"Organizations",
            "subcategory":"Professional Association",
            "type":"Services"
        }
    ],
    "sg:phone":"+1 847 882 3051",
    "sg:postcode":"60194",
    "sg:province":"IL",
    "wof:name":"American Assoc of Univers",
    "wof:placetype":"venue"
},
  "geometry": {"coordinates":[-88.13367100000001,42.041029],"type":"Point"}
}