{
  "type": "Feature",
  "properties": {
    "iso:country":"US",
    "sg:address":"351 Buttercup Ln",
    "sg:city":"Villa Park",
    "sg:classifiers":[
        {
            "category":"Building & Trades",
            "subcategory":"Construction",
            "type":"Services"
        }
    ],
    "sg:phone":"+1 630 627 8132",
    "sg:postcode":"60181",
    "sg:province":"IL",
    "sg:tags":[
        "house"
    ],
    "wof:name":"Pro One Building & Remodeling",
    "wof:placetype":"venue"
},
  "geometry": {"coordinates":[-87.971205,41.854142],"type":"Point"}
}