{
  "type": "Feature",
  "properties": {
    "iso:country":"US",
    "sg:address":"1802 S Mattis Ave",
    "sg:city":"Champaign",
    "sg:classifiers":[
        {
            "category":"Personal",
            "type":"Services"
        }
    ],
    "sg:phone":"+1 217 373 1480",
    "sg:postcode":"61821",
    "sg:province":"IL",
    "sg:tags":[
        "control",
        "weight"
    ],
    "wof:name":"Carle Weight Management Center",
    "wof:placetype":"venue"
},
  "geometry": {"coordinates":[-88.276377,40.094299],"type":"Point"}
}