{
  "type": "Feature",
  "properties": {
    "addr:full":"27 North St Park Forest IL 60466",
    "addr:housenumber":"27",
    "addr:postcode":"60466",
    "addr:street":"North St",
    "iso:country":"US",
    "sg:address":"27 North St",
    "sg:city":"Park Forest",
    "sg:classifiers":[
        {
            "category":"Personal",
            "subcategory":"Beauty Salon",
            "type":"Services"
        }
    ],
    "sg:phone":"+1 708 481 4484",
    "sg:postcode":"60466",
    "sg:province":"IL",
    "sg:tags":[
        "shop"
    ],
    "wof:name":"Radiance Hair Studio",
    "wof:placetype":"venue"
},
  "geometry": {"coordinates":[-87.67640400000001,41.497559],"type":"Point"}
}