{
  "type": "Feature",
  "properties": {
    "iso:country":"US",
    "sg:address":"811 Cunningham Ave",
    "sg:city":"Danville",
    "sg:classifiers":[
        {
            "category":"Retail",
            "subcategory":"Auto Repair",
            "type":"Services"
        }
    ],
    "sg:phone":"+1 217 442 0203",
    "sg:postcode":"61832",
    "sg:province":"IL",
    "sg:tags":[
        "repairing",
        "automobile"
    ],
    "wof:name":"Kenny's Automotive & Cmprssr",
    "wof:placetype":"venue"
},
  "geometry": {"coordinates":[-87.66076,40.124704],"type":"Point"}
}