{
  "type": "Feature",
  "properties": {
    "addr:full":"1701 Gragg St Centralia IL 62801",
    "addr:housenumber":"1701",
    "addr:postcode":"62801",
    "addr:street":"Gragg St",
    "iso:country":"US",
    "sg:address":"1701 Gragg St",
    "sg:city":"Centralia",
    "sg:classifiers":[
        {
            "category":"Building & Trades",
            "subcategory":"Construction",
            "type":"Services"
        }
    ],
    "sg:phone":"+1 618 532 7919",
    "sg:postcode":"62801",
    "sg:province":"IL",
    "sg:tags":[
        "house"
    ],
    "wof:name":"Kracht Construction",
    "wof:placetype":"venue"
},
  "geometry": {"coordinates":[-89.10310200000001,38.536091],"type":"Point"}
}