{
  "type": "Feature",
  "properties": {
    "addr:full":"284 S Weber Rd Bolingbrook IL 60490",
    "addr:housenumber":"284",
    "addr:postcode":"60490",
    "addr:street":"S Weber Rd",
    "iso:country":"US",
    "sg:address":"284 S Weber Rd",
    "sg:city":"Bolingbrook",
    "sg:classifiers":[
        {
            "category":"Restaurant",
            "type":"Food & Drink"
        }
    ],
    "sg:menulink":"http://www.allmenus.com/il/du-page/88254-aurelios-pizza/menu/",
    "sg:phone":"+1 630 759 0033",
    "sg:postcode":"60490",
    "sg:province":"IL",
    "sg:tags":[
        "american",
        "pizza"
    ],
    "wof:name":"Aurelio's Pizza",
    "wof:placetype":"venue"
},
  "geometry": {"coordinates":[-88.12578600000001,41.690362],"type":"Point"}
}