{
  "type": "Feature",
  "properties": {
    "iso:country":"US",
    "sg:address":"247 Broadway St",
    "sg:city":"Quincy",
    "sg:classifiers":[
        {
            "category":"Retail",
            "subcategory":"Repair Shop",
            "type":"Services"
        }
    ],
    "sg:phone":"+1   ",
    "sg:postcode":"62301",
    "sg:province":"IL",
    "sg:tags":[
        "boat"
    ],
    "wof:name":"Aquatech Marine",
    "wof:placetype":"venue"
},
  "geometry": {"coordinates":[-91.412608,39.935917],"type":"Point"}
}