{
  "type": "Feature",
  "properties": {
    "iso:country":"US",
    "sg:address":"504 N Willow Wood Dr",
    "sg:city":"Palatine",
    "sg:classifiers":[
        {
            "category":"Banks & Credit Unions",
            "subcategory":"Bank",
            "type":"Services"
        }
    ],
    "sg:phone":"+1 847 925 5158",
    "sg:postcode":"60074",
    "sg:province":"IL",
    "wof:name":"Flash Cash Atm Services Inc",
    "wof:placetype":"venue"
},
  "geometry": {"coordinates":[-88.030756,42.119115],"type":"Point"}
}