{
  "type": "Feature",
  "properties": {
    "iso:country":"US",
    "sg:address":"177 N Ada St",
    "sg:city":"Chicago",
    "sg:classifiers":[
        {
            "category":"Retail",
            "subcategory":"Photofinishing",
            "type":"Services"
        }
    ],
    "sg:phone":"+1 312 942 0544",
    "sg:postcode":"60607",
    "sg:province":"IL",
    "sg:tags":[
        "photo",
        "restoration",
        "retouching"
    ],
    "wof:name":"David Zihlman",
    "wof:placetype":"venue"
},
  "geometry": {"coordinates":[-87.660732,41.884626],"type":"Point"}
}