{
  "type": "Feature",
  "properties": {
    "iso:country":"US",
    "sg:address":"2952 W Belmont Ave",
    "sg:city":"Chicago",
    "sg:classifiers":[
        {
            "category":"Personal",
            "subcategory":"Hair Removal",
            "type":"Services"
        }
    ],
    "sg:phone":"+1 773 267 3095",
    "sg:postcode":"60618",
    "sg:province":"IL",
    "wof:name":"Actualidades Beauty Salon",
    "wof:placetype":"venue"
},
  "geometry": {"coordinates":[-87.702277,41.93963],"type":"Point"}
}