{
  "type": "Feature",
  "properties": {
    "addr:full":"716 Cedar St Rockford IL 61102",
    "addr:housenumber":"716",
    "addr:postcode":"61102",
    "addr:street":"Cedar St",
    "iso:country":"US",
    "sg:address":"716 Cedar St",
    "sg:city":"Rockford",
    "sg:classifiers":[
        {
            "category":"Manufacturing",
            "subcategory":"Metals",
            "type":"Manufacturing & Wholesale Goods"
        }
    ],
    "sg:phone":"+1 815 963 4644",
    "sg:postcode":"61102",
    "sg:province":"IL",
    "sg:tags":[
        "finisher"
    ],
    "wof:name":"Illinois Metal Finishing",
    "wof:placetype":"venue"
},
  "geometry": {"coordinates":[-89.10287700000001,42.269783],"type":"Point"}
}