{
  "type": "Feature",
  "properties": {
    "addr:full":"2001 E Voorhees St Danville IL 61834",
    "addr:housenumber":"2001",
    "addr:postcode":"61834",
    "addr:street":"E Voorhees St",
    "iso:country":"US",
    "sg:address":"2001 E Voorhees St",
    "sg:city":"Danville",
    "sg:classifiers":[
        {
            "category":"Manufacturing",
            "subcategory":"Printing",
            "type":"Manufacturing & Wholesale Goods"
        }
    ],
    "sg:phone":"+1 217 442 4993",
    "sg:postcode":"61834",
    "sg:province":"IL",
    "sg:tags":[
        "commercial"
    ],
    "wof:name":"Faulstich Printing Co",
    "wof:placetype":"venue"
},
  "geometry": {"coordinates":[-87.587244,40.146925],"type":"Point"}
}