{
  "type": "Feature",
  "properties": {
    "iso:country":"US",
    "sg:address":"1275 Ensell Rd",
    "sg:city":"Lake Zurich",
    "sg:classifiers":[
        {
            "category":"Manufacturing",
            "subcategory":"Metals",
            "type":"Manufacturing & Wholesale Goods"
        }
    ],
    "sg:phone":"+1 847 540 2323",
    "sg:postcode":"60047",
    "sg:province":"IL",
    "sg:tags":[
        "stamping"
    ],
    "wof:name":"Parkview Metal Products",
    "wof:placetype":"venue"
},
  "geometry": {"coordinates":[-88.069158,42.204771],"type":"Point"}
}