{
  "type": "Feature",
  "properties": {
    "iso:country":"US",
    "sg:address":"229 Donlea Rd",
    "sg:city":"Barrington",
    "sg:classifiers":[
        {
            "category":"Building & Trades",
            "subcategory":"Plumbing",
            "type":"Services"
        }
    ],
    "sg:phone":"+1 815 356 5154",
    "sg:postcode":"60010",
    "sg:province":"IL",
    "sg:tags":[
        "plumber"
    ],
    "wof:name":"Suburban Residential Services Inc.",
    "wof:placetype":"venue"
},
  "geometry": {"coordinates":[-88.183026,42.152752],"type":"Point"}
}