{
  "type": "Feature",
  "properties": {
    "addr:full":"2705 S Broadway Salem IL 62881",
    "addr:housenumber":"2705",
    "addr:postcode":"62881",
    "addr:street":"S Broadway",
    "iso:country":"US",
    "sg:address":"2705 S Broadway",
    "sg:city":"Salem",
    "sg:classifiers":[
        {
            "category":"Autos & Motor Vehicles",
            "subcategory":"Boat Sales",
            "type":"Retail Goods"
        }
    ],
    "sg:phone":"+1   ",
    "sg:postcode":"62881",
    "sg:province":"IL",
    "sg:tags":[
        "trolling"
    ],
    "wof:name":"Qualls Rod & Reel Service",
    "wof:placetype":"venue"
},
  "geometry": {"coordinates":[-88.94026100000001,38.604575],"type":"Point"}
}