{
  "type": "Feature",
  "properties": {
    "iso:country":"US",
    "sg:address":"620 State St",
    "sg:city":"White Hall",
    "sg:classifiers":[
        {
            "category":"Restaurant",
            "type":"Food & Drink"
        }
    ],
    "sg:phone":"+1 217 589 5321",
    "sg:postcode":"62092",
    "sg:province":"IL",
    "sg:tags":[
        "pizza"
    ],
    "wof:name":"Casey's Carry Out",
    "wof:placetype":"venue"
},
  "geometry": {"coordinates":[-90.391515,39.44341],"type":"Point"}
}