{
  "type": "Feature",
  "properties": {
    "addr:full":"939 Hinman Ave Evanston IL 60202",
    "addr:housenumber":"939",
    "addr:postcode":"60202",
    "addr:street":"Hinman Ave",
    "iso:country":"US",
    "sg:address":"939 Hinman Ave",
    "sg:city":"Evanston",
    "sg:classifiers":[
        {
            "category":"Organizations",
            "subcategory":"Religious Organization",
            "type":"Services"
        }
    ],
    "sg:phone":"+1 847 475 3630",
    "sg:postcode":"60202",
    "sg:province":"IL",
    "wof:name":"Saint Lukes Episc Ch",
    "wof:placetype":"venue"
},
  "geometry": {"coordinates":[-87.67782,42.035009],"type":"Point"}
}