{
  "type": "Feature",
  "properties": {
    "addr:full":"5000 W Holiday Dr Peoria IL 61615",
    "addr:housenumber":"5000",
    "addr:postcode":"61615",
    "addr:street":"W Holiday Dr",
    "iso:country":"US",
    "sg:address":"5000 W Holiday Dr",
    "sg:city":"Peoria",
    "sg:classifiers":[
        {
            "category":"Shopping",
            "subcategory":"Hobbies, Toys, & Games",
            "type":"Retail Goods"
        },
        {
            "category":"Shopping",
            "subcategory":"Bicycles & Sporting Goods",
            "type":"Retail Goods"
        },
        {
            "category":"Bars & Pubs",
            "subcategory":"Champagne Bar",
            "type":"Food & Drink"
        },
        {
            "category":"Personal",
            "subcategory":"Day Spa",
            "type":"Services"
        },
        {
            "category":"Home & Garden",
            "subcategory":"Furniture",
            "type":"Retail Goods"
        }
    ],
    "sg:phone":"+1 309 691 7665",
    "sg:postcode":"61615",
    "sg:province":"IL",
    "sg:tags":[
        "outdoor",
        "supply",
        "fixture",
        "equipment",
        "hot",
        "billiard",
        "patio",
        "tub",
        "pool",
        "swimming"
    ],
    "sg:website":"http://www.shopthegreatescape.com",
    "wof:name":"The Great Escape",
    "wof:placetype":"venue"
},
  "geometry": {"coordinates":[-89.672112,40.774769],"type":"Point"}
}