{
  "type": "Feature",
  "properties": {
    "addr:full":"4201 W Victoria St Chicago IL 60646",
    "addr:housenumber":"4201",
    "addr:postcode":"60646",
    "addr:street":"W Victoria St",
    "iso:country":"US",
    "sg:address":"4201 W Victoria St",
    "sg:city":"Chicago",
    "sg:classifiers":[
        {
            "category":"Health Services",
            "subcategory":"Doctor",
            "type":"Services"
        },
        {
            "category":"Wholesale",
            "subcategory":"Medical Equipment & Supplies",
            "type":"Manufacturing & Wholesale Goods"
        },
        {
            "category":"Retail",
            "subcategory":"Repair Shop",
            "type":"Services"
        },
        {
            "category":"Health Services",
            "subcategory":"Health Practitioner",
            "type":"Services"
        }
    ],
    "sg:phone":"+1 773 583 3600",
    "sg:postcode":"60646",
    "sg:province":"IL",
    "sg:tags":[
        "sound",
        "level",
        "testing",
        "aids-parts",
        "hearing",
        "device",
        "assistive",
        "aid",
        "audiologists",
        "repairing"
    ],
    "sg:website":"http://www.beltone.com",
    "wof:name":"Beltone Hearing Aid Center",
    "wof:placetype":"venue"
},
  "geometry": {"coordinates":[-87.732277,41.984874],"type":"Point"}
}