{
  "type": "Feature",
  "properties": {
    "iso:country":"US",
    "sg:address":"15020 Cicero Ave",
    "sg:city":"Oak Forest",
    "sg:classifiers":[
        {
            "category":"Real Estate",
            "subcategory":"Real Estate Agent",
            "type":"Services"
        }
    ],
    "sg:phone":"+1 708 535 1313",
    "sg:postcode":"60452",
    "sg:province":"IL",
    "sg:tags":[
        "appraiser"
    ],
    "wof:name":"William H Metz & Associates",
    "wof:placetype":"venue"
},
  "geometry": {"coordinates":[-87.73715799999999,41.619696],"type":"Point"}
}