{
  "type": "Feature",
  "properties": {
    "addr:full":"856 Longmeadow Dr Carol Stream IL 60188",
    "addr:housenumber":"856",
    "addr:postcode":"60188",
    "addr:street":"Longmeadow Dr",
    "iso:country":"US",
    "sg:address":"856 Longmeadow Dr",
    "sg:city":"Carol Stream",
    "sg:classifiers":[
        {
            "category":"Shopping",
            "subcategory":"Clothing, Apparel, & Fashions",
            "type":"Retail Goods"
        }
    ],
    "sg:phone":"+1   ",
    "sg:postcode":"60188",
    "sg:province":"IL",
    "wof:name":"Sweet Dreams",
    "wof:placetype":"venue"
},
  "geometry": {"coordinates":[-88.14973999999999,41.922912],"type":"Point"}
}