{
  "type": "Feature",
  "properties": {
    "iso:country":"US",
    "sg:address":"1770 S Randall Rd",
    "sg:city":"Geneva",
    "sg:classifiers":[
        {
            "category":"Retail",
            "subcategory":"Laundry & Dry Cleaning",
            "type":"Services"
        }
    ],
    "sg:phone":"+1 630 232 7134",
    "sg:postcode":"60134",
    "sg:province":"IL",
    "sg:tags":[
        "cleaners",
        "plant",
        "drycleaning"
    ],
    "wof:name":"Bright Cleaners",
    "wof:placetype":"venue"
},
  "geometry": {"coordinates":[-88.340294,41.870274],"type":"Point"}
}