{
  "type": "Feature",
  "properties": {
    "addr:full":"1130 S Michigan Ave Fl 1 Chicago IL 60605",
    "addr:housenumber":"1130;1",
    "addr:postcode":"60605",
    "addr:street":"S Michigan Ave Fl",
    "iso:country":"US",
    "sg:address":"1130 S Michigan Ave Fl 1",
    "sg:city":"Chicago",
    "sg:classifiers":[
        {
            "category":"Wholesale",
            "subcategory":"Painting Supplies",
            "type":"Manufacturing & Wholesale Goods"
        },
        {
            "category":"Home & Garden",
            "subcategory":"Building Materials",
            "type":"Retail Goods"
        },
        {
            "category":"Building & Trades",
            "subcategory":"Construction",
            "type":"Services"
        }
    ],
    "sg:phone":"+1 312 939 9917",
    "sg:postcode":"60605",
    "sg:province":"IL",
    "sg:tags":[
        "wallcoverings-installation",
        "wallpaper",
        "wallcoverings",
        "paint",
        "contractor"
    ],
    "wof:name":"Design Angel",
    "wof:placetype":"venue"
},
  "geometry": {"coordinates":[-87.624092,41.868467],"type":"Point"}
}