{
  "type": "Feature",
  "properties": {
    "addr:full":"114 Peterson Rd Libertyville IL 60048",
    "addr:housenumber":"114",
    "addr:postcode":"60048",
    "addr:street":"Peterson Rd",
    "iso:country":"US",
    "sg:address":"114 Peterson Rd",
    "sg:city":"Libertyville",
    "sg:classifiers":[
        {
            "category":"Autos & Motor Vehicles",
            "subcategory":"Fuel & Gas Station",
            "type":"Retail Goods"
        }
    ],
    "sg:phone":"+1 847 680 8490",
    "sg:postcode":"60048",
    "sg:province":"IL",
    "sg:tags":[
        "oil"
    ],
    "wof:name":"Libertyville North Citgo",
    "wof:placetype":"venue"
},
  "geometry": {"coordinates":[-87.96060199999999,42.30602],"type":"Point"}
}