{
  "type": "Feature",
  "properties": {
    "addr:full":"3604 Progress Blvd Peru IL 61354",
    "addr:housenumber":"3604",
    "addr:postcode":"61354",
    "addr:street":"Progress Blvd",
    "iso:country":"US",
    "sg:address":"3604 Progress Blvd",
    "sg:city":"Peru",
    "sg:classifiers":[
        {
            "category":"Autos & Motor Vehicles",
            "subcategory":"Automobile Sales",
            "type":"Retail Goods"
        }
    ],
    "sg:phone":"+1   ",
    "sg:postcode":"61354",
    "sg:province":"IL",
    "sg:tags":[
        "used"
    ],
    "wof:name":"Prescott Bros of Illinas",
    "wof:placetype":"venue"
},
  "geometry": {"coordinates":[-89.12216100000001,41.356571],"type":"Point"}
}