{
  "type": "Feature",
  "properties": {
    "iso:country":"US",
    "sg:address":"3604 Progress Blvd",
    "sg:city":"Peru",
    "sg:classifiers":[
        {
            "category":"Autos & Motor Vehicles",
            "subcategory":"Automobile Sales",
            "type":"Retail Goods"
        }
    ],
    "sg:phone":"+1   ",
    "sg:postcode":"61354",
    "sg:province":"IL",
    "sg:tags":[
        "used"
    ],
    "wof:name":"Prescott Bros of Illinas",
    "wof:placetype":"venue"
},
  "geometry": {"coordinates":[-89.122161,41.356571],"type":"Point"}
}