{
  "type": "Feature",
  "properties": {
    "addr:full":"275 W Dundee Rd Buffalo Grove IL 60089",
    "addr:housenumber":"275",
    "addr:postcode":"60089",
    "addr:street":"W Dundee Rd",
    "iso:country":"US",
    "sg:address":"275 W Dundee Rd",
    "sg:city":"Buffalo Grove",
    "sg:classifiers":[
        {
            "category":"Wholesale",
            "subcategory":"Machinery & Supplies",
            "type":"Manufacturing & Wholesale Goods"
        }
    ],
    "sg:phone":"+1 847 215 8007",
    "sg:postcode":"60089",
    "sg:province":"IL",
    "sg:tags":[
        "equipment",
        "establishment"
    ],
    "wof:name":"Beauty Sampling Com",
    "wof:placetype":"venue"
},
  "geometry": {"coordinates":[-87.96401,42.138874],"type":"Point"}
}