{
  "type": "Feature",
  "properties": {
    "iso:country":"US",
    "sg:address":"5908 W 26th St",
    "sg:city":"Cicero",
    "sg:classifiers":[
        {
            "category":"Autos & Motor Vehicles",
            "subcategory":"Auto Supplies",
            "type":"Retail Goods"
        },
        {
            "category":"Building & Trades",
            "subcategory":"Electrical",
            "type":"Services"
        },
        {
            "category":"Retail",
            "subcategory":"Auto Repair",
            "type":"Services"
        }
    ],
    "sg:phone":"+1 708 683 5083",
    "sg:postcode":"60804",
    "sg:province":"IL",
    "sg:tags":[
        "alternator",
        "electrician",
        "electric",
        "automobile",
        "generators-automotive",
        "repairing"
    ],
    "wof:name":"Salomon Auto Electric Rebuilders & More",
    "wof:placetype":"venue"
},
  "geometry": {"coordinates":[-87.77145899999999,41.84358],"type":"Point"}
}