{
  "type": "Feature",
  "properties": {
    "iso:country":"US",
    "sg:address":"770 Church Rd",
    "sg:city":"Elmhurst",
    "sg:classifiers":[
        {
            "category":"Wholesale",
            "subcategory":"Drugs",
            "type":"Manufacturing & Wholesale Goods"
        }
    ],
    "sg:phone":"+1 630 782 1960",
    "sg:postcode":"60126",
    "sg:province":"IL",
    "sg:tags":[
        "cosmetic"
    ],
    "wof:name":"Chicago Wholesale Advancement",
    "wof:placetype":"venue"
},
  "geometry": {"coordinates":[-87.95356,41.924032],"type":"Point"}
}