{
  "type": "Feature",
  "properties": {
    "iso:country":"US",
    "sg:address":"6316 S Greenwood Ave",
    "sg:city":"Chicago",
    "sg:classifiers":[
        {
            "category":"Utilities",
            "subcategory":"Refuse",
            "type":"Services"
        }
    ],
    "sg:phone":"+1 773 643 2124",
    "sg:postcode":"60637",
    "sg:province":"IL",
    "sg:tags":[
        "collection",
        "garbage"
    ],
    "wof:name":"Kourtni Mulazim Roll Off",
    "wof:placetype":"venue"
},
  "geometry": {"coordinates":[-87.59914999999999,41.77999],"type":"Point"}
}