{
  "type": "Feature",
  "properties": {
    "iso:country":"US",
    "sg:address":"302 S 1st St",
    "sg:city":"Champaign",
    "sg:classifiers":[
        {
            "category":"Restaurant",
            "type":"Food & Drink"
        }
    ],
    "sg:phone":"+1 217 398 8400",
    "sg:postcode":"61820",
    "sg:province":"IL",
    "sg:tags":[
        "pakistani",
        "indian"
    ],
    "sg:website":"www.bombaygrill-cu.com",
    "wof:name":"Bombay Indian Grill",
    "wof:placetype":"venue"
},
  "geometry": {"coordinates":[-88.238739,40.113792],"type":"Point"}
}