{
  "type": "Feature",
  "properties": {
    "addr:full":"360 W Schick Rd Bloomingdale IL 60108",
    "addr:housenumber":"360",
    "addr:postcode":"60108",
    "addr:street":"W Schick Rd",
    "iso:country":"US",
    "sg:address":"360 W Schick Rd",
    "sg:city":"Bloomingdale",
    "sg:classifiers":[
        {
            "category":"Personal",
            "subcategory":"Nail Salon",
            "type":"Services"
        }
    ],
    "sg:phone":"+1 630 924 7175",
    "sg:postcode":"60108",
    "sg:province":"IL",
    "wof:name":"Perfect Ten Nail Boutique",
    "wof:placetype":"venue"
},
  "geometry": {"coordinates":[-88.08760100000001,41.951698],"type":"Point"}
}