{
  "type": "Feature",
  "properties": {
    "addr:full":"201 N Clark St Chicago IL 60601",
    "addr:housenumber":"201",
    "addr:postcode":"60601",
    "addr:street":"N Clark St",
    "iso:country":"US",
    "sg:address":"201 N Clark St",
    "sg:city":"Chicago",
    "sg:classifiers":[
        {
            "category":"Education",
            "subcategory":"Preschool",
            "type":"Public Place"
        },
        {
            "category":"Education",
            "subcategory":"School",
            "type":"Public Place"
        }
    ],
    "sg:phone":"+1 312 553 9100",
    "sg:postcode":"60601",
    "sg:province":"IL",
    "sg:tags":[
        "elementary"
    ],
    "wof:name":"Honey Tree Early Learning Center",
    "wof:placetype":"venue"
},
  "geometry": {"coordinates":[-87.630898,41.8857],"type":"Point"}
}