{
  "type": "Feature",
  "properties": {
    "iso:country":"US",
    "sg:address":"1000 E Higgins Rd",
    "sg:city":"Elk Grove Vlg",
    "sg:classifiers":[
        {
            "category":"Restaurant",
            "type":"Food & Drink"
        }
    ],
    "sg:phone":"+1 847 437 1440",
    "sg:postcode":"60007",
    "sg:province":"IL",
    "wof:name":"Bullfrog's Sports Bar",
    "wof:placetype":"venue"
},
  "geometry": {"coordinates":[-87.970838,42.026512],"type":"Point"}
}