{
  "type": "Feature",
  "properties": {
    "addr:full":"248 W Lincoln Hwy Frankfort IL 60423",
    "addr:housenumber":"248",
    "addr:postcode":"60423",
    "addr:street":"W Lincoln Hwy",
    "iso:country":"US",
    "sg:address":"248 W Lincoln Hwy",
    "sg:city":"Frankfort",
    "sg:classifiers":[
        {
            "category":"Health Services",
            "subcategory":"Doctor",
            "type":"Services"
        }
    ],
    "sg:phone":"+1 815 469 9336",
    "sg:postcode":"60423",
    "sg:province":"IL",
    "sg:tags":[
        "dentist"
    ],
    "wof:name":"Peter Kahlhammer DDS Inc",
    "wof:placetype":"venue"
},
  "geometry": {"coordinates":[-87.79153599999999,41.506327],"type":"Point"}
}