{
  "type": "Feature",
  "properties": {
    "iso:country":"US",
    "sg:address":"3411 N Alpine Rd",
    "sg:city":"Rockford",
    "sg:classifiers":[
        {
            "category":"Education",
            "subcategory":"School",
            "type":"Public Place"
        }
    ],
    "sg:phone":"+1 815 877 9551",
    "sg:postcode":"61114",
    "sg:province":"IL",
    "sg:tags":[
        "organization",
        "religious"
    ],
    "wof:name":"Luther Academy At Gloria Day",
    "wof:placetype":"venue"
},
  "geometry": {"coordinates":[-89.029285,42.307568],"type":"Point"}
}