{
  "type": "Feature",
  "properties": {
    "addr:full":"1300 15th St Lawrenceville IL 62439",
    "addr:housenumber":"1300",
    "addr:postcode":"62439",
    "addr:street":"15Th St",
    "iso:country":"US",
    "sg:address":"1300 15th St",
    "sg:city":"Lawrenceville",
    "sg:classifiers":[
        {
            "category":"Social Services",
            "type":"Services"
        }
    ],
    "sg:phone":"+1 618 943 5326",
    "sg:postcode":"62439",
    "sg:province":"IL",
    "sg:tags":[
        "organization",
        "welfare"
    ],
    "wof:name":"Cra-WA-LA Volunteers",
    "wof:placetype":"venue"
},
  "geometry": {"coordinates":[-87.68732,38.725142],"type":"Point"}
}