{
  "type": "Feature",
  "properties": {
    "iso:country":"US",
    "sg:address":"100 Chicago St",
    "sg:city":"West Chicago",
    "sg:classifiers":[
        {
            "category":"Organizations",
            "subcategory":"Religious Organization",
            "type":"Services"
        }
    ],
    "sg:phone":"+1 630 876 4584",
    "sg:postcode":"60185",
    "sg:province":"IL",
    "sg:tags":[
        "business"
    ],
    "wof:name":"Wycliffe Bible Translators",
    "wof:placetype":"venue"
},
  "geometry": {"coordinates":[-88.201115,41.882678],"type":"Point"}
}