{
  "type": "Feature",
  "properties": {
    "iso:country":"US",
    "sg:address":"2521 Gross Point Rd",
    "sg:city":"Evanston",
    "sg:classifiers":[
        {
            "category":"Professional",
            "subcategory":"Lawyer & Legal Services",
            "type":"Services"
        }
    ],
    "sg:phone":"+1 847 866 9150",
    "sg:postcode":"60201",
    "sg:province":"IL",
    "sg:tags":[
        "attorney"
    ],
    "wof:name":"Bradley & Jackson",
    "wof:placetype":"venue"
},
  "geometry": {"coordinates":[-87.728975,42.063748],"type":"Point"}
}