{
  "type": "Feature",
  "properties": {
    "addr:full":"6801 W Higgins Avenue Chicago IL 60656",
    "addr:housenumber":"6801",
    "addr:postcode":"60656",
    "addr:street":"W Higgins Avenue",
    "iso:country":"US",
    "sg:address":"6801 W Higgins Avenue",
    "sg:city":"Chicago",
    "sg:classifiers":[
        {
            "category":"Health Services",
            "subcategory":"Dentist",
            "type":"Services"
        }
    ],
    "sg:phone":"+1 773 763 0433",
    "sg:postcode":"60656",
    "sg:province":"IL",
    "sg:tags":[
        "dentists-cosmetic",
        "dentistry"
    ],
    "sg:website":"http://www.gggdds.com",
    "wof:name":"Gutsell Gerald G",
    "wof:placetype":"venue"
},
  "geometry": {"coordinates":[-87.797955,41.979016],"type":"Point"}
}