{
  "type": "Feature",
  "properties": {
    "iso:country":"US",
    "sg:address":"1500 S Western Avenue",
    "sg:city":"Chicago",
    "sg:classifiers":[
        {
            "category":"Shopping",
            "subcategory":"Books",
            "type":"Retail Goods"
        }
    ],
    "sg:phone":"+1 312 666 5880",
    "sg:postcode":"60608",
    "sg:province":"IL",
    "sg:tags":[
        "bookstore"
    ],
    "wof:name":"Powell's Wholesale",
    "wof:placetype":"venue"
},
  "geometry": {"coordinates":[-87.685912,41.861071],"type":"Point"}
}