{
  "type": "Feature",
  "properties": {
    "iso:country":"US",
    "sg:address":"2117 Ogden Ave",
    "sg:city":"Lisle",
    "sg:classifiers":[
        {
            "category":"Autos & Motor Vehicles",
            "subcategory":"Automobile Sales",
            "type":"Retail Goods"
        }
    ],
    "sg:phone":"+1 630 810 4330",
    "sg:postcode":"60532",
    "sg:province":"IL",
    "sg:tags":[
        "new",
        "car"
    ],
    "wof:name":"Volvo Sales & Service Center Inc.",
    "wof:placetype":"venue"
},
  "geometry": {"coordinates":[-88.093689,41.79907],"type":"Point"}
}