{
  "type": "Feature",
  "properties": {
    "iso:country":"US",
    "sg:address":"1200 Milwaukee Ave",
    "sg:city":"Glenview",
    "sg:classifiers":[
        {
            "category":"Home & Garden",
            "subcategory":"Household Appliances",
            "type":"Retail Goods"
        },
        {
            "category":"Shopping",
            "subcategory":"Jewelry",
            "type":"Retail Goods"
        },
        {
            "category":"Home & Garden",
            "subcategory":"Building Materials",
            "type":"Retail Goods"
        },
        {
            "category":"Shopping",
            "subcategory":"Computers & Home Electronics",
            "type":"Retail Goods"
        },
        {
            "category":"Communications",
            "type":"Services"
        }
    ],
    "sg:phone":"+1 847 544 2877",
    "sg:postcode":"60025",
    "sg:province":"IL",
    "sg:tags":[
        "water",
        "television",
        "theater",
        "heater",
        "watch",
        "satellite",
        "system",
        "high",
        "equipment",
        "stereophonic",
        "radio",
        "equipment-dealers",
        "major",
        "jeweler",
        "fidelity",
        "store"
    ],
    "sg:website":"http://www.abt.com",
    "wof:name":"Abt Electronics & Appliances",
    "wof:placetype":"venue"
},
  "geometry": {"coordinates":[-87.859741,42.076618],"type":"Point"}
}