{
  "type": "Feature",
  "properties": {
    "iso:country":"US",
    "sg:address":"2490 Concord Dr",
    "sg:city":"Woodridge",
    "sg:classifiers":[
        {
            "category":"Building & Trades",
            "subcategory":"Construction",
            "type":"Services"
        }
    ],
    "sg:phone":"+1 630 241 1030",
    "sg:postcode":"60517",
    "sg:province":"IL",
    "sg:tags":[
        "house"
    ],
    "wof:name":"KG Thornton Const Ltd",
    "wof:placetype":"venue"
},
  "geometry": {"coordinates":[-88.044614,41.757622],"type":"Point"}
}