{
  "type": "Feature",
  "properties": {
    "iso:country":"US",
    "sg:address":"1302 Hinman Ave",
    "sg:city":"Evanston",
    "sg:classifiers":[
        {
            "category":"Professional",
            "subcategory":"Accounting & Tax Preparation",
            "type":"Services"
        }
    ],
    "sg:phone":"+1 847 328 8950",
    "sg:postcode":"60201",
    "sg:province":"IL",
    "wof:name":"Kirk S Bennett",
    "wof:placetype":"venue"
},
  "geometry": {"coordinates":[-87.678819,42.042597],"type":"Point"}
}