{
  "type": "Feature",
  "properties": {
    "iso:country":"US",
    "sg:address":"1650 Lake Cook Rd",
    "sg:city":"Deerfield",
    "sg:classifiers":[
        {
            "category":"Real Estate",
            "subcategory":"Real Estate Agent",
            "type":"Services"
        }
    ],
    "sg:phone":"+1 847 940 7333",
    "sg:postcode":"60015",
    "sg:province":"IL",
    "sg:tags":[
        "management"
    ],
    "wof:name":"Quadrangle Development",
    "wof:placetype":"venue"
},
  "geometry": {"coordinates":[-87.870102,42.153014],"type":"Point"}
}