{
  "type": "Feature",
  "properties": {
    "addr:full":"1409 Apache Dr Rockford IL 61107",
    "addr:housenumber":"1409",
    "addr:postcode":"61107",
    "addr:street":"Apache Dr",
    "iso:country":"US",
    "sg:address":"1409 Apache Dr",
    "sg:city":"Rockford",
    "sg:classifiers":[
        {
            "category":"Retail",
            "subcategory":"Repair Shop",
            "type":"Services"
        }
    ],
    "sg:phone":"+1 815 543 0155",
    "sg:postcode":"61107",
    "sg:province":"IL",
    "sg:tags":[
        "repairing",
        "piano",
        "refinishing"
    ],
    "wof:name":"Collins Piano Lessons & Tuning",
    "wof:placetype":"venue"
},
  "geometry": {"coordinates":[-89.0219,42.283279],"type":"Point"}
}