{
  "type": "Feature",
  "properties": {
    "addr:full":"504 W Golf Rd Schaumburg IL 60195",
    "addr:housenumber":"504",
    "addr:postcode":"60195",
    "addr:street":"W Golf Rd",
    "iso:country":"US",
    "sg:address":"504 W Golf Rd",
    "sg:city":"Schaumburg",
    "sg:classifiers":[
        {
            "category":"Food & Beverages",
            "subcategory":"Groceries & Convenience Stores",
            "type":"Retail Goods"
        }
    ],
    "sg:phone":"+1   ",
    "sg:postcode":"60195",
    "sg:province":"IL",
    "wof:name":"Golf Mini Mart",
    "wof:placetype":"venue"
},
  "geometry": {"coordinates":[-88.092951,42.048922],"type":"Point"}
}