{
  "type": "Feature",
  "properties": {
    "addr:full":"3727 N Kedzie Ave Chicago IL 60618",
    "addr:housenumber":"3727",
    "addr:postcode":"60618",
    "addr:street":"N Kedzie Ave",
    "iso:country":"US",
    "sg:address":"3727 N Kedzie Ave",
    "sg:city":"Chicago",
    "sg:classifiers":[
        {
            "category":"Professional",
            "subcategory":"Lawyer & Legal Services",
            "type":"Services"
        }
    ],
    "sg:phone":"+1 312 878 7000",
    "sg:postcode":"60618",
    "sg:province":"IL",
    "sg:website":"www.insurance-claim-attorneys.com",
    "wof:name":"Hoag Law Group",
    "wof:placetype":"venue"
},
  "geometry": {"coordinates":[-87.707761,41.949301],"type":"Point"}
}