{
  "type": "Feature",
  "properties": {
    "iso:country":"US",
    "sg:address":"1759 S Blanchard St",
    "sg:city":"Wheaton",
    "sg:classifiers":[
        {
            "category":"Government",
            "subcategory":"Office",
            "type":"Public Place"
        }
    ],
    "sg:phone":"+1   ",
    "sg:postcode":"60187",
    "sg:province":"IL",
    "sg:tags":[
        "department",
        "recreation"
    ],
    "wof:name":"Recreation Dept",
    "wof:placetype":"venue"
},
  "geometry": {"coordinates":[-88.09569500000001,41.841434],"type":"Point"}
}