{
  "type": "Feature",
  "properties": {
    "iso:country":"US",
    "sg:address":"61 W Main St",
    "sg:city":"Lake Zurich",
    "sg:classifiers":[
        {
            "category":"Utilities",
            "subcategory":"Refuse",
            "type":"Services"
        }
    ],
    "sg:phone":"+1 847 438 2349",
    "sg:postcode":"60047",
    "sg:province":"IL",
    "sg:tags":[
        "fire",
        "protection",
        "system"
    ],
    "wof:name":"Lake Zurich Wastewater",
    "wof:placetype":"venue"
},
  "geometry": {"coordinates":[-88.092317,42.196981],"type":"Point"}
}