{
  "type": "Feature",
  "properties": {
    "addr:full":"224 W Elm St Canton IL 61520",
    "addr:housenumber":"224",
    "addr:postcode":"61520",
    "addr:street":"W Elm St",
    "iso:country":"US",
    "sg:address":"224 W Elm St",
    "sg:city":"Canton",
    "sg:classifiers":[
        {
            "category":"Wholesale",
            "subcategory":"Groceries",
            "type":"Manufacturing & Wholesale Goods"
        }
    ],
    "sg:phone":"+1 309 647 0338",
    "sg:postcode":"61520",
    "sg:province":"IL",
    "sg:tags":[
        "confectionery"
    ],
    "wof:name":"Ricks Distributing",
    "wof:placetype":"venue"
},
  "geometry": {"coordinates":[-90.038982,40.555674],"type":"Point"}
}