{
  "type": "Feature",
  "properties": {
    "addr:full":"311 S Wacker Dr Chicago IL 60606",
    "addr:housenumber":"311",
    "addr:postcode":"60606",
    "addr:street":"S Wacker Dr",
    "iso:country":"US",
    "sg:address":"311 S Wacker Dr",
    "sg:city":"Chicago",
    "sg:classifiers":[
        {
            "category":"Professional",
            "subcategory":"Lawyer & Legal Services",
            "type":"Services"
        }
    ],
    "sg:phone":"+1 312 360 6504",
    "sg:postcode":"60606",
    "sg:province":"IL",
    "sg:tags":[
        "attorney",
        "practice"
    ],
    "wof:name":"Krucks, William N",
    "wof:placetype":"venue"
},
  "geometry": {"coordinates":[-87.636645,41.877564],"type":"Point"}
}