{
  "type": "Feature",
  "properties": {
    "addr:full":"1408 Bloomingdale Rd Glendale Heights IL 60139",
    "addr:housenumber":"1408",
    "addr:postcode":"60139",
    "addr:street":"Bloomingdale Rd",
    "iso:country":"US",
    "sg:address":"1408 Bloomingdale Rd",
    "sg:city":"Glendale Heights",
    "sg:classifiers":[
        {
            "category":"Shopping",
            "subcategory":"Computers & Home Electronics",
            "type":"Retail Goods"
        }
    ],
    "sg:phone":"+1 847 453 3476",
    "sg:postcode":"60139",
    "sg:province":"IL",
    "sg:website":"www.dishnetwork.com",
    "wof:name":"Dish1 Network Sales",
    "wof:placetype":"venue"
},
  "geometry": {"coordinates":[-88.08158400000001,41.910582],"type":"Point"}
}