{
  "type": "Feature",
  "properties": {
    "iso:country":"US",
    "sg:address":"219 W Wrightwood Ave",
    "sg:city":"Elmhurst",
    "sg:classifiers":[
        {
            "category":"Wholesale",
            "subcategory":"Non-durable Goods",
            "type":"Manufacturing & Wholesale Goods"
        }
    ],
    "sg:phone":"+1 630 832 3750",
    "sg:postcode":"60126",
    "sg:province":"IL",
    "wof:name":"H & T Gift Imports Inc",
    "wof:placetype":"venue"
},
  "geometry": {"coordinates":[-87.945786,41.925288],"type":"Point"}
}