{
  "type": "Feature",
  "properties": {
    "addr:full":"1503 Sunset Ave Waukegan IL 60087",
    "addr:housenumber":"1503",
    "addr:postcode":"60087",
    "addr:street":"Sunset Ave",
    "iso:country":"US",
    "sg:address":"1503 Sunset Ave",
    "sg:city":"Waukegan",
    "sg:classifiers":[
        {
            "category":"Food & Beverages",
            "subcategory":"Fruits & Vegetables",
            "type":"Retail Goods"
        }
    ],
    "sg:phone":"+1 847 623 4500",
    "sg:postcode":"60087",
    "sg:province":"IL",
    "sg:tags":[
        "produce"
    ],
    "wof:name":"D J's Produces",
    "wof:placetype":"venue"
},
  "geometry": {"coordinates":[-87.850373,42.391876],"type":"Point"}
}