{
  "type": "Feature",
  "properties": {
    "iso:country":"US",
    "sg:address":"404 Colegrove St",
    "sg:city":"Assumption",
    "sg:classifiers":[
        {
            "category":"Education",
            "subcategory":"School",
            "type":"Public Place"
        }
    ],
    "sg:phone":"+1 217 226 4241",
    "sg:postcode":"62510",
    "sg:province":"IL",
    "sg:tags":[
        "middle"
    ],
    "sg:website":"http://www.cam.k12.il.us",
    "wof:name":"Central A & M Middle School",
    "wof:placetype":"venue"
},
  "geometry": {"coordinates":[-89.046638,39.514751],"type":"Point"}
}