{
  "type": "Feature",
  "properties": {
    "addr:full":"1312 E Broadway East Saint Louis IL 62201",
    "addr:housenumber":"1312",
    "addr:postcode":"62201",
    "addr:street":"E Broadway",
    "iso:country":"US",
    "sg:address":"1312 E Broadway",
    "sg:city":"East Saint Louis",
    "sg:classifiers":[
        {
            "category":"Food & Beverages",
            "subcategory":"Liquor & Beverages",
            "type":"Retail Goods"
        }
    ],
    "sg:phone":"+1   ",
    "sg:postcode":"62201",
    "sg:province":"IL",
    "sg:tags":[
        "alcoholic"
    ],
    "wof:name":"Four Aces",
    "wof:placetype":"venue"
},
  "geometry": {"coordinates":[-90.151462,38.61623],"type":"Point"}
}