{
  "type": "Feature",
  "properties": {
    "iso:country":"US",
    "sg:address":"2312 W Touhy Ave",
    "sg:city":"Chicago",
    "sg:classifiers":[
        {
            "category":"Wholesale",
            "subcategory":"Non-durable Goods",
            "type":"Manufacturing & Wholesale Goods"
        }
    ],
    "sg:phone":"+1 773 274 2620",
    "sg:postcode":"60645",
    "sg:province":"IL",
    "sg:tags":[
        "dry",
        "goods-wholesale"
    ],
    "wof:name":"Williamson & Co",
    "wof:placetype":"venue"
},
  "geometry": {"coordinates":[-87.68808,42.01227],"type":"Point"}
}