{
  "type": "Feature",
  "properties": {
    "addr:full":"2999 N 200 East Rd Clifton IL 60927",
    "addr:housenumber":"2999",
    "addr:postcode":"60927",
    "addr:street":"N 200 East Rd",
    "iso:country":"US",
    "sg:address":"2999 N 200 East Rd",
    "sg:city":"Clifton",
    "sg:classifiers":[
        {
            "category":"Government",
            "subcategory":"Office",
            "type":"Public Place"
        }
    ],
    "sg:phone":"+1 815 694 2770",
    "sg:postcode":"60927",
    "sg:province":"IL",
    "sg:tags":[
        "village"
    ],
    "wof:name":"Milk Grove Twp Community Bldg",
    "wof:placetype":"venue"
},
  "geometry": {"coordinates":[-88.092584,40.925547],"type":"Point"}
}