{
  "type": "Feature",
  "properties": {
    "addr:full":"437 Fremont St Woodstock IL 60098",
    "addr:housenumber":"437",
    "addr:postcode":"60098",
    "addr:street":"Fremont St",
    "iso:country":"US",
    "sg:address":"437 Fremont St",
    "sg:city":"Woodstock",
    "sg:classifiers":[
        {
            "category":"Organizations",
            "subcategory":"Professional Association",
            "type":"Services"
        },
        {
            "category":"Arts & Performance",
            "subcategory":"Theater",
            "type":"Entertainment"
        }
    ],
    "sg:phone":"+1 815 334 9338",
    "sg:postcode":"60098",
    "sg:province":"IL",
    "sg:tags":[
        "theatrical",
        "agency",
        "bureau"
    ],
    "sg:website":"http://www.devarcreative.com",
    "wof:name":"Devar Creative Inc",
    "wof:placetype":"venue"
},
  "geometry": {"coordinates":[-88.44336800000001,42.309858],"type":"Point"}
}