{
  "type": "Feature",
  "properties": {
    "iso:country":"US",
    "sg:address":"1969 W Ogden Ave",
    "sg:city":"Chicago",
    "sg:classifiers":[
        {
            "category":"Social Services",
            "type":"Services"
        },
        {
            "category":"Professional",
            "subcategory":"Employment Agencies",
            "type":"Services"
        }
    ],
    "sg:phone":"+1 312 864 6000",
    "sg:postcode":"60612",
    "sg:province":"IL",
    "sg:tags":[
        "workers'",
        "placement",
        "volunteer"
    ],
    "wof:name":"J H Strroger Hospital Of Cook County",
    "wof:placetype":"venue"
},
  "geometry": {"coordinates":[-87.675873,41.873211],"type":"Point"}
}