{
  "type": "Feature",
  "properties": {
    "iso:country":"US",
    "sg:address":"1008 Judy Ave",
    "sg:city":"Bridgeport",
    "sg:classifiers":[
        {
            "category":"Food & Beverages",
            "subcategory":"Groceries & Convenience Stores",
            "type":"Retail Goods"
        }
    ],
    "sg:phone":"+1   ",
    "sg:postcode":"62417",
    "sg:province":"IL",
    "wof:name":"Lous",
    "wof:placetype":"venue"
},
  "geometry": {"coordinates":[-87.759481,38.712326],"type":"Point"}
}