{
  "type": "Feature",
  "properties": {
    "iso:country":"US",
    "sg:address":"300 N 4th St Ste 206",
    "sg:city":"Saint Louis",
    "sg:classifiers":[
        {
            "category":"Real Estate",
            "subcategory":"Architect",
            "type":"Services"
        }
    ],
    "sg:phone":"+1 314 621 4160",
    "sg:postcode":"63102",
    "sg:province":"MO",
    "sg:website":"www.powersbowersox.com",
    "wof:name":"Powers Bowersox Associates Inc",
    "wof:placetype":"venue"
},
  "geometry": {"coordinates":[-90.1875,38.6283],"type":"Point"}
}