{
  "type": "Feature",
  "properties": {
    "addr:full":"3605 Bobolink Ln Rolling Meadows IL 60008",
    "addr:housenumber":"3605",
    "addr:postcode":"60008",
    "addr:street":"Bobolink Ln",
    "iso:country":"US",
    "sg:address":"3605 Bobolink Ln",
    "sg:city":"Rolling Meadows",
    "sg:classifiers":[
        {
            "category":"Communications",
            "type":"Services"
        }
    ],
    "sg:phone":"+1 847 342 9995",
    "sg:postcode":"60008",
    "sg:province":"IL",
    "sg:tags":[
        "communication"
    ],
    "wof:name":"Broad Focus Communications",
    "wof:placetype":"venue"
},
  "geometry": {"coordinates":[-88.026887,42.074944],"type":"Point"}
}