{
  "type": "Feature",
  "properties": {
    "iso:country":"US",
    "sg:address":"760 E Rollins Rd",
    "sg:city":"Round Lake Beach",
    "sg:classifiers":[
        {
            "category":"Restaurant",
            "type":"Food & Drink"
        }
    ],
    "sg:phone":"+1 847 740 3333",
    "sg:postcode":"60073",
    "sg:province":"IL",
    "sg:tags":[
        "eating"
    ],
    "wof:name":"Chang Jiang Buffet",
    "wof:placetype":"venue"
},
  "geometry": {"coordinates":[-88.066912,42.379083],"type":"Point"}
}