{
  "type": "Feature",
  "properties": {
    "addr:full":"2028 Briarcliffe Blvd Wheaton IL 60187",
    "addr:housenumber":"2028",
    "addr:postcode":"60187",
    "addr:street":"Briarcliffe Blvd",
    "iso:country":"US",
    "sg:address":"2028 Briarcliffe Blvd",
    "sg:city":"Wheaton",
    "sg:classifiers":[
        {
            "category":"Manufacturing",
            "subcategory":"Electronics",
            "type":"Manufacturing & Wholesale Goods"
        }
    ],
    "sg:phone":"+1 630 510 0959",
    "sg:postcode":"60187",
    "sg:province":"IL",
    "sg:tags":[
        "electronic",
        "component",
        "mfg"
    ],
    "wof:name":"Momak Sales",
    "wof:placetype":"venue"
},
  "geometry": {"coordinates":[-88.08438200000001,41.830758],"type":"Point"}
}