{
  "type": "Feature",
  "properties": {
    "iso:country":"US",
    "sg:address":"6418 S State St",
    "sg:city":"Chicago",
    "sg:classifiers":[
        {
            "category":"Home & Garden",
            "subcategory":"Home Furnishings",
            "type":"Retail Goods"
        },
        {
            "category":"Home & Garden",
            "subcategory":"Building Materials",
            "type":"Retail Goods"
        }
    ],
    "sg:phone":"+1 773 783 3600",
    "sg:postcode":"60621",
    "sg:province":"IL",
    "sg:tags":[
        "decor",
        "supply"
    ],
    "sg:website":"www.statestreetsteel.com",
    "wof:name":"State Street Steel",
    "wof:placetype":"venue"
},
  "geometry": {"coordinates":[-87.625356,41.777407],"type":"Point"}
}