{
  "type": "Feature",
  "properties": {
    "iso:country":"US",
    "sg:address":"95 Gates St",
    "sg:city":"Crystal Lake",
    "sg:classifiers":[
        {
            "category":"Manufacturing",
            "subcategory":"Printing",
            "type":"Manufacturing & Wholesale Goods"
        }
    ],
    "sg:phone":"+1 815 459 7121",
    "sg:postcode":"60014",
    "sg:province":"IL",
    "sg:tags":[
        "book"
    ],
    "sg:website":"www.frankcorey.com",
    "wof:name":"Frank Corey Corp",
    "wof:placetype":"venue"
},
  "geometry": {"coordinates":[-88.31653799999999,42.245199],"type":"Point"}
}