{
  "type": "Feature",
  "properties": {
    "iso:country":"US",
    "sg:address":"5561 Rotary Rd",
    "sg:city":"Cherry Valley",
    "sg:classifiers":[
        {
            "category":"Recreation",
            "type":"Entertainment"
        }
    ],
    "sg:phone":"+1 815 874 8700",
    "sg:postcode":"61016",
    "sg:province":"IL",
    "sg:tags":[
        "stable"
    ],
    "wof:name":"Cherry Valley Equestrian",
    "wof:placetype":"venue"
},
  "geometry": {"coordinates":[-89.006707,42.173276],"type":"Point"}
}