{
  "type": "Feature",
  "properties": {
    "iso:country":"US",
    "sg:address":"3500 N Cicero Ave",
    "sg:city":"Chicago",
    "sg:classifiers":[
        {
            "category":"Manufacturing",
            "subcategory":"Metals",
            "type":"Manufacturing & Wholesale Goods"
        }
    ],
    "sg:phone":"+1 773 283 1374",
    "sg:postcode":"60641",
    "sg:province":"IL",
    "sg:tags":[
        "engraver"
    ],
    "wof:name":"Acmetech Engraving",
    "wof:placetype":"venue"
},
  "geometry": {"coordinates":[-87.74704,41.945266],"type":"Point"}
}