{
  "type": "Feature",
  "properties": {
    "addr:full":"9406 Skokie Blvd Skokie IL 60077",
    "addr:housenumber":"9406",
    "addr:postcode":"60077",
    "addr:street":"Skokie Blvd",
    "iso:country":"US",
    "sg:address":"9406 Skokie Blvd",
    "sg:city":"Skokie",
    "sg:classifiers":[
        {
            "category":"Utilities",
            "subcategory":"Mobile Phone",
            "type":"Services"
        },
        {
            "category":"Shopping",
            "subcategory":"Mobile Phones",
            "type":"Retail Goods"
        }
    ],
    "sg:phone":"+1 847 763 9105",
    "sg:postcode":"60077",
    "sg:province":"IL",
    "sg:tags":[
        "supply",
        "communication",
        "telephone",
        "wireless",
        "equipment",
        "cellular"
    ],
    "sg:website":"http://www.sprint.com",
    "wof:name":"Sprint Store",
    "wof:placetype":"venue"
},
  "geometry": {"coordinates":[-87.74685599999999,42.051761],"type":"Point"}
}