{
  "type": "Feature",
  "properties": {
    "iso:country":"US",
    "sg:address":"926 Brook Forest Ave",
    "sg:city":"Shorewood",
    "sg:classifiers":[
        {
            "category":"Retail",
            "subcategory":"Laundry & Dry Cleaning",
            "type":"Services"
        }
    ],
    "sg:phone":"+1 815 439 1200",
    "sg:postcode":"60431",
    "sg:province":"IL",
    "sg:tags":[
        "cleaners"
    ],
    "wof:name":"All Cleaners",
    "wof:placetype":"venue"
},
  "geometry": {"coordinates":[-88.199229,41.538417],"type":"Point"}
}