{
  "type": "Feature",
  "properties": {
    "addr:full":"5622 Castlewood Ct Rockford IL 61108",
    "addr:housenumber":"5622",
    "addr:postcode":"61108",
    "addr:street":"Castlewood Ct",
    "iso:country":"US",
    "sg:address":"5622 Castlewood Ct",
    "sg:city":"Rockford",
    "sg:classifiers":[
        {
            "category":"Building & Trades",
            "subcategory":"Construction",
            "type":"Services"
        }
    ],
    "sg:phone":"+1 815 399 0950",
    "sg:postcode":"61108",
    "sg:province":"IL",
    "sg:tags":[
        "hanging",
        "contractor"
    ],
    "wof:name":"Steves Painting",
    "wof:placetype":"venue"
},
  "geometry": {"coordinates":[-89.005454,42.252011],"type":"Point"}
}