{
  "type": "Feature",
  "properties": {
    "iso:country":"US",
    "sg:address":"780 Barberry Ln",
    "sg:city":"Lake Forest",
    "sg:classifiers":[
        {
            "category":"Shopping",
            "subcategory":"Gifts & Souvenirs",
            "type":"Retail Goods"
        }
    ],
    "sg:phone":"+1   ",
    "sg:postcode":"60045",
    "sg:province":"IL",
    "sg:tags":[
        "accessory"
    ],
    "wof:name":"Impulse",
    "wof:placetype":"venue"
},
  "geometry": {"coordinates":[-87.828363,42.259028],"type":"Point"}
}