{
  "type": "Feature",
  "properties": {
    "iso:country":"US",
    "sg:address":"1522 N Ashland Avenue",
    "sg:city":"Chicago",
    "sg:classifiers":[
        {
            "category":"Personal",
            "subcategory":"Barber",
            "type":"Services"
        }
    ],
    "sg:phone":"+1 773 342 9132",
    "sg:postcode":"60622",
    "sg:province":"IL",
    "wof:name":"Robbins Barber Shop & Salon",
    "wof:placetype":"venue"
},
  "geometry": {"coordinates":[-87.667563,41.909687],"type":"Point"}
}