{
  "type": "Feature",
  "properties": {
    "iso:country":"US",
    "sg:address":"1101 S Smith St",
    "sg:city":"Palatine",
    "sg:classifiers":[
        {
            "category":"Health Services",
            "subcategory":"Medical Lab",
            "type":"Services"
        }
    ],
    "sg:phone":"+1 847 359 5153",
    "sg:postcode":"60067",
    "sg:province":"IL",
    "sg:tags":[
        "laboratory",
        "dental"
    ],
    "wof:name":"Chaplet Cross Dental Studio",
    "wof:placetype":"venue"
},
  "geometry": {"coordinates":[-88.048698,42.088598],"type":"Point"}
}