{
  "type": "Feature",
  "properties": {
    "iso:country":"US",
    "sg:address":"2921 Maryville Rd",
    "sg:city":"Maryville",
    "sg:classifiers":[
        {
            "category":"Banks & Credit Unions",
            "subcategory":"Bank",
            "type":"Services"
        }
    ],
    "sg:phone":"+1 618 343 4120",
    "sg:postcode":"62062",
    "sg:province":"IL",
    "wof:name":"Umb Bank",
    "wof:placetype":"venue"
},
  "geometry": {"coordinates":[-89.956929,38.712078],"type":"Point"}
}