{
  "type": "Feature",
  "properties": {
    "addr:full":"4813 W Irving Park Road Chicago IL 60641",
    "addr:housenumber":"4813",
    "addr:postcode":"60641",
    "addr:street":"W Irving Park Road",
    "iso:country":"US",
    "sg:address":"4813 W Irving Park Road",
    "sg:city":"Chicago",
    "sg:classifiers":[
        {
            "category":"Shopping",
            "subcategory":"Clothing, Apparel, & Fashions",
            "type":"Retail Goods"
        }
    ],
    "sg:phone":"+1 773 283 9041",
    "sg:postcode":"60641",
    "sg:province":"IL",
    "sg:tags":[
        "accessory",
        "clothing",
        "women's"
    ],
    "wof:name":"Eden Apparel",
    "wof:placetype":"venue"
},
  "geometry": {"coordinates":[-87.747494,41.953234],"type":"Point"}
}