{
  "type": "Feature",
  "properties": {
    "addr:full":"20400 S Green Meadow Ln Frankfort IL 60423",
    "addr:housenumber":"20400",
    "addr:postcode":"60423",
    "addr:street":"S Green Meadow Ln",
    "iso:country":"US",
    "sg:address":"20400 S Green Meadow Ln",
    "sg:city":"Frankfort",
    "sg:classifiers":[
        {
            "category":"Professional",
            "subcategory":"Business Services",
            "type":"Services"
        }
    ],
    "sg:phone":"+1 815 464 0785",
    "sg:postcode":"60423",
    "sg:province":"IL",
    "sg:tags":[
        "interior",
        "consultant",
        "design",
        "decorator"
    ],
    "wof:name":"Internation Interior Design",
    "wof:placetype":"venue"
},
  "geometry": {"coordinates":[-87.79947,41.517601],"type":"Point"}
}