{
  "type": "Feature",
  "properties": {
    "addr:full":"900 N Michigan Ave 4th Fl Chicago IL 60611",
    "addr:housenumber":"900",
    "addr:postcode":"60611",
    "addr:street":"N Michigan Ave",
    "iso:country":"US",
    "sg:address":"900 N Michigan Ave 4th Fl",
    "sg:city":"Chicago",
    "sg:classifiers":[
        {
            "category":"Shopping",
            "subcategory":"Clothing, Apparel, & Fashions",
            "type":"Retail Goods"
        },
        {
            "category":"Home & Garden",
            "subcategory":"Garden Supply",
            "type":"Retail Goods"
        }
    ],
    "sg:phone":"+1 312 423 9948",
    "sg:postcode":"60611",
    "sg:province":"IL",
    "sg:tags":[
        "accessory"
    ],
    "sg:website":"www.shop900.com/shop/genevieve-l...",
    "wof:name":"Genevieve Lethu",
    "wof:placetype":"venue"
},
  "geometry": {"coordinates":[-87.624208,41.899219],"type":"Point"}
}