{
  "type": "Feature",
  "properties": {
    "iso:country":"US",
    "sg:address":"649 Redwood Ln",
    "sg:city":"Lisle",
    "sg:classifiers":[
        {
            "category":"Building & Trades",
            "subcategory":"Cleaning & Sanitation",
            "type":"Services"
        }
    ],
    "sg:phone":"+1 630 322 8865",
    "sg:postcode":"60532",
    "sg:province":"IL",
    "sg:tags":[
        "janitor"
    ],
    "wof:name":"Alta Inc",
    "wof:placetype":"venue"
},
  "geometry": {"coordinates":[-88.063975,41.807545],"type":"Point"}
}