{
  "type": "Feature",
  "properties": {
    "addr:full":"3157 N California Ave Chicago IL 60618",
    "addr:housenumber":"3157",
    "addr:postcode":"60618",
    "addr:street":"N California Ave",
    "iso:country":"US",
    "sg:address":"3157 N California Ave",
    "sg:city":"Chicago",
    "sg:classifiers":[
        {
            "category":"Professional",
            "subcategory":"Lawyer & Legal Services",
            "type":"Services"
        }
    ],
    "sg:phone":"+1 773 409 4695",
    "sg:postcode":"60618",
    "sg:province":"IL",
    "sg:tags":[
        "divorce",
        "law",
        "family"
    ],
    "sg:website":"www.katzlawchicago.com",
    "wof:name":"Katz Law Office Ltd",
    "wof:placetype":"venue"
},
  "geometry": {"coordinates":[-87.697587,41.939094],"type":"Point"}
}