{
  "type": "Feature",
  "properties": {
    "iso:country":"US",
    "sg:address":"6135 S Monitor Ave",
    "sg:city":"Chicago",
    "sg:classifiers":[
        {
            "category":"Real Estate",
            "subcategory":"Real Estate Services",
            "type":"Services"
        },
        {
            "category":"Real Estate",
            "subcategory":"Real Estate Agent",
            "type":"Services"
        }
    ],
    "sg:phone":"+1 773 758 2033",
    "sg:postcode":"60638",
    "sg:province":"IL",
    "sg:tags":[
        "management"
    ],
    "wof:name":"In-House Realty",
    "wof:placetype":"venue"
},
  "geometry": {"coordinates":[-87.76791799999999,41.780978],"type":"Point"}
}