{
  "type": "Feature",
  "properties": {
    "addr:full":"1009 E Main St West Frankfort IL 62896",
    "addr:housenumber":"1009",
    "addr:postcode":"62896",
    "addr:street":"E Main St West",
    "iso:country":"US",
    "sg:address":"1009 E Main St",
    "sg:city":"West Frankfort",
    "sg:classifiers":[
        {
            "category":"Restaurant",
            "type":"Food & Drink"
        },
        {
            "category":"Ice Cream",
            "type":"Food & Drink"
        }
    ],
    "sg:menulink":"http://www.allmenus.com/il/frankfort/161775-dairy-queen/menu/",
    "sg:phone":"+1 618 932 3863",
    "sg:postcode":"62896",
    "sg:province":"IL",
    "sg:tags":[
        "burger",
        "american",
        "ice",
        "cream"
    ],
    "wof:name":"Dairy Queen",
    "wof:placetype":"venue"
},
  "geometry": {"coordinates":[-88.916684,37.898001],"type":"Point"}
}