{
  "type": "Feature",
  "properties": {
    "addr:full":"3841 N Kostner Ave Chicago IL 60641",
    "addr:housenumber":"3841",
    "addr:postcode":"60641",
    "addr:street":"N Kostner Ave",
    "iso:country":"US",
    "sg:address":"3841 N Kostner Ave",
    "sg:city":"Chicago",
    "sg:classifiers":[
        {
            "category":"Utilities",
            "subcategory":"Refuse",
            "type":"Services"
        }
    ],
    "sg:phone":"+1 773 286 9556",
    "sg:postcode":"60641",
    "sg:province":"IL",
    "sg:tags":[
        "garbage",
        "collection"
    ],
    "wof:name":"A Junk Express",
    "wof:placetype":"venue"
},
  "geometry": {"coordinates":[-87.738005,41.950976],"type":"Point"}
}