{
  "type": "Feature",
  "properties": {
    "addr:full":"1502 E Kensington Rd Arlington Hts IL 60004",
    "addr:housenumber":"1502",
    "addr:postcode":"60004",
    "addr:street":"E Kensington Rd",
    "iso:country":"US",
    "sg:address":"1502 E Kensington Rd",
    "sg:city":"Arlington Hts",
    "sg:classifiers":[
        {
            "category":"Retail",
            "subcategory":"Animal Services",
            "type":"Services"
        }
    ],
    "sg:phone":"+1 847 637 3413",
    "sg:postcode":"60004",
    "sg:province":"IL",
    "sg:tags":[
        "pet",
        "grooming",
        "washing"
    ],
    "wof:name":"Bird Groomings",
    "wof:placetype":"venue"
},
  "geometry": {"coordinates":[-87.964105,42.081001],"type":"Point"}
}