{
  "type": "Feature",
  "properties": {
    "addr:full":"342 Douglas Rd Oswego IL 60543",
    "addr:housenumber":"342",
    "addr:postcode":"60543",
    "addr:street":"Douglas Rd",
    "iso:country":"US",
    "sg:address":"342 Douglas Rd",
    "sg:city":"Oswego",
    "sg:classifiers":[
        {
            "category":"Restaurant",
            "type":"Food & Drink"
        }
    ],
    "sg:menulink":"http://www.allmenus.com/il/oswego/127200-subway/menu/",
    "sg:phone":"+1 630 897 5050",
    "sg:postcode":"60543",
    "sg:province":"IL",
    "sg:tags":[
        "american",
        "sandwich"
    ],
    "wof:name":"Subway",
    "wof:placetype":"venue"
},
  "geometry": {"coordinates":[-88.31945899999999,41.714618],"type":"Point"}
}