{
  "type": "Feature",
  "properties": {
    "addr:full":"19 N River St Batavia IL 60510",
    "addr:housenumber":"19",
    "addr:postcode":"60510",
    "addr:street":"N River St",
    "iso:country":"US",
    "sg:address":"19 N River St",
    "sg:city":"Batavia",
    "sg:classifiers":[
        {
            "category":"Professional",
            "subcategory":"Accounting & Tax Preparation",
            "type":"Services"
        }
    ],
    "sg:phone":"+1 630 406 9052",
    "sg:postcode":"60510",
    "sg:province":"IL",
    "sg:tags":[
        "accountant"
    ],
    "wof:name":"Olsen's Accounting & Tax Svc",
    "wof:placetype":"venue"
},
  "geometry": {"coordinates":[-88.3061,41.85083],"type":"Point"}
}