{
  "type": "Feature",
  "properties": {
    "addr:full":"2260 S Cicero Ave Cicero IL 60804",
    "addr:housenumber":"2260",
    "addr:postcode":"60804",
    "addr:street":"S Cicero Ave",
    "iso:country":"US",
    "sg:address":"2260 S Cicero Ave",
    "sg:city":"Cicero",
    "sg:classifiers":[
        {
            "category":"Health Services",
            "subcategory":"Doctor",
            "type":"Services"
        }
    ],
    "sg:phone":"+1 708 652 4910",
    "sg:postcode":"60804",
    "sg:province":"IL",
    "wof:name":"Macias C Patricia MD",
    "wof:placetype":"venue"
},
  "geometry": {"coordinates":[-87.76324200000001,41.909114],"type":"Point"}
}