{
  "type": "Feature",
  "properties": {
    "addr:full":"1910 Knox Road 560 E Galesburg IL 61401",
    "addr:housenumber":"1910",
    "addr:postcode":"61401",
    "addr:street":"Knox Road 560 E",
    "iso:country":"US",
    "sg:address":"1910 Knox Road 560 E",
    "sg:city":"Galesburg",
    "sg:classifiers":[
        {
            "category":"Wholesale",
            "subcategory":"Hardware",
            "type":"Manufacturing & Wholesale Goods"
        },
        {
            "category":"Home & Garden",
            "subcategory":"Garden Supply",
            "type":"Retail Goods"
        },
        {
            "category":"Retail",
            "subcategory":"Repair Shop",
            "type":"Services"
        }
    ],
    "sg:phone":"+1 309 342 3188",
    "sg:postcode":"61401",
    "sg:province":"IL",
    "sg:tags":[
        "renting",
        "lawn",
        "outdoor",
        "power",
        "landscaping",
        "equipment-sales",
        "equipment",
        "saw"
    ],
    "sg:website":"http://www.stihlusa.com/",
    "wof:name":"Kleine Equipment Inc.",
    "wof:placetype":"venue"
},
  "geometry": {"coordinates":[-90.335005,40.9933],"type":"Point"}
}