{
  "type": "Feature",
  "properties": {
    "iso:country":"US",
    "sg:address":"1950 S Morrison Ave",
    "sg:city":"Collinsville",
    "sg:classifiers":[
        {
            "category":"Building & Trades",
            "subcategory":"Landscaping Services",
            "type":"Services"
        }
    ],
    "sg:phone":"+1 618 346 1148",
    "sg:postcode":"62232",
    "sg:province":"IL",
    "sg:tags":[
        "lawn",
        "maintenance",
        "grounds"
    ],
    "wof:name":"Tucker Turf & Landscaping",
    "wof:placetype":"venue"
},
  "geometry": {"coordinates":[-89.997678,38.649259],"type":"Point"}
}