{
  "type": "Feature",
  "properties": {
    "addr:full":"4943 N Kenmore Ave Chicago IL 60640",
    "addr:housenumber":"4943",
    "addr:postcode":"60640",
    "addr:street":"N Kenmore Ave",
    "iso:country":"US",
    "sg:address":"4943 N Kenmore Ave",
    "sg:city":"Chicago",
    "sg:classifiers":[
        {
            "category":"Travel",
            "subcategory":"Hotels & Motels",
            "type":"Entertainment"
        }
    ],
    "sg:phone":"+1 773 561 4234",
    "sg:postcode":"60640",
    "sg:province":"IL",
    "sg:tags":[
        "operation"
    ],
    "wof:name":"Northmere the Sro Hotel",
    "wof:placetype":"venue"
},
  "geometry": {"coordinates":[-87.656403,41.972401],"type":"Point"}
}