{
  "type": "Feature",
  "properties": {
    "addr:full":"5533 East Dr Loves Park IL 61111",
    "addr:housenumber":"5533",
    "addr:postcode":"61111",
    "addr:street":"East Dr",
    "iso:country":"US",
    "sg:address":"5533 East Dr",
    "sg:city":"Loves Park",
    "sg:classifiers":[
        {
            "category":"Professional",
            "subcategory":"Management & Consulting",
            "type":"Services"
        }
    ],
    "sg:phone":"+1 815 654 7175",
    "sg:postcode":"61111",
    "sg:province":"IL",
    "wof:name":"A B & G Marketing Group Inc",
    "wof:placetype":"venue"
},
  "geometry": {"coordinates":[-89.065838,42.312189],"type":"Point"}
}