{
  "type": "Feature",
  "properties": {
    "iso:country":"US",
    "sg:address":"1010 Ferguson St",
    "sg:city":"Rockford",
    "sg:classifiers":[
        {
            "category":"Organizations",
            "subcategory":"Religious Organization",
            "type":"Services"
        }
    ],
    "sg:phone":"+1 815 963 7215",
    "sg:postcode":"61102",
    "sg:province":"IL",
    "sg:tags":[
        "monastery",
        "convent"
    ],
    "wof:name":"Franciscan Sisters",
    "wof:placetype":"venue"
},
  "geometry": {"coordinates":[-89.107585,42.262674],"type":"Point"}
}