{
  "type": "Feature",
  "properties": {
    "addr:full":"120 W Monroe St Chicago IL 60603",
    "addr:housenumber":"120",
    "addr:postcode":"60603",
    "addr:street":"W Monroe St",
    "iso:country":"US",
    "sg:address":"120 W Monroe St",
    "sg:city":"Chicago",
    "sg:classifiers":[
        {
            "category":"Shopping",
            "subcategory":"Shoes",
            "type":"Retail Goods"
        }
    ],
    "sg:phone":"+1 312 332 0667",
    "sg:postcode":"60603",
    "sg:province":"IL",
    "sg:tags":[
        "boots-retail",
        "store"
    ],
    "wof:name":"Altman's Mens Shoes & Boots",
    "wof:placetype":"venue"
},
  "geometry": {"coordinates":[-87.63145299999999,41.880683],"type":"Point"}
}