{
  "type": "Feature",
  "properties": {
    "iso:country":"US",
    "sg:address":"3016 N Kenneth Ave",
    "sg:city":"Chicago",
    "sg:classifiers":[
        {
            "category":"Arts & Performance",
            "subcategory":"Arts Center",
            "type":"Entertainment"
        },
        {
            "category":"Professional",
            "type":"Services"
        }
    ],
    "sg:phone":"+1 630 289 9449",
    "sg:postcode":"60641",
    "sg:province":"IL",
    "sg:tags":[
        "planning",
        "performing",
        "event"
    ],
    "sg:website":"www.balloonogram.com",
    "wof:name":"Sultan's Delight Belly Dancers",
    "wof:placetype":"venue"
},
  "geometry": {"coordinates":[-87.738501,41.935843],"type":"Point"}
}