{
  "type": "Feature",
  "properties": {
    "iso:country":"US",
    "sg:address":"35 Genesee St",
    "sg:city":"Lake Zurich",
    "sg:classifiers":[
        {
            "category":"Building & Trades",
            "subcategory":"Cleaning & Sanitation",
            "type":"Services"
        }
    ],
    "sg:phone":"+1 847 438 3882",
    "sg:postcode":"60047",
    "sg:province":"IL",
    "sg:tags":[
        "house"
    ],
    "wof:name":"Constant Care Cleaning Co",
    "wof:placetype":"venue"
},
  "geometry": {"coordinates":[-88.089586,42.194668],"type":"Point"}
}