{
  "type": "Feature",
  "properties": {
    "addr:full":"118 W State St Waverly IL 62692",
    "addr:housenumber":"118",
    "addr:postcode":"62692",
    "addr:street":"W State St",
    "iso:country":"US",
    "sg:address":"118 W State St",
    "sg:city":"Waverly",
    "sg:classifiers":[
        {
            "category":"Insurance",
            "subcategory":"Insurance Agent",
            "type":"Services"
        }
    ],
    "sg:phone":"+1 217 435 9786",
    "sg:postcode":"62692",
    "sg:province":"IL",
    "wof:name":"Whalen Insurance",
    "wof:placetype":"venue"
},
  "geometry": {"coordinates":[-89.953919,39.591727],"type":"Point"}
}