{
  "type": "Feature",
  "properties": {
    "iso:country":"US",
    "sg:address":"2731 Belvidere Rd",
    "sg:city":"Waukegan",
    "sg:classifiers":[
        {
            "category":"Health Services",
            "subcategory":"Clinic",
            "type":"Services"
        }
    ],
    "sg:phone":"+1 847 775 8001",
    "sg:postcode":"60085",
    "sg:province":"IL",
    "wof:name":"Health Ride System Inc",
    "wof:placetype":"venue"
},
  "geometry": {"coordinates":[-87.869122,42.349633],"type":"Point"}
}