{
  "type": "Feature",
  "properties": {
    "addr:full":"7855 Gross Point Rd Skokie IL 60077",
    "addr:housenumber":"7855",
    "addr:postcode":"60077",
    "addr:street":"Gross Point Rd",
    "iso:country":"US",
    "sg:address":"7855 Gross Point Rd",
    "sg:city":"Skokie",
    "sg:classifiers":[
        {
            "category":"Retail",
            "subcategory":"Laundry & Dry Cleaning",
            "type":"Services"
        },
        {
            "category":"Home & Garden",
            "subcategory":"Home Furnishings",
            "type":"Retail Goods"
        }
    ],
    "sg:phone":"+1 847 933 5756",
    "sg:postcode":"60077",
    "sg:province":"IL",
    "sg:tags":[
        "linen",
        "supply"
    ],
    "wof:name":"BBJ Boutique Linens",
    "wof:placetype":"venue"
},
  "geometry": {"coordinates":[-87.769267,42.023365],"type":"Point"}
}