{
  "type": "Feature",
  "properties": {
    "addr:full":"1637 E 87th St Ste 406 Chicago IL 60617",
    "addr:housenumber":"1637",
    "addr:postcode":"60617",
    "addr:street":"E 87Th St Ste 406",
    "iso:country":"US",
    "sg:address":"1637 E 87th St Ste 406",
    "sg:city":"Chicago",
    "sg:classifiers":[
        {
            "category":"Building & Trades",
            "subcategory":"Plumbing",
            "type":"Services"
        },
        {
            "category":"Building & Trades",
            "subcategory":"Construction",
            "type":"Services"
        }
    ],
    "sg:phone":"+1 773 488 5616",
    "sg:postcode":"60617",
    "sg:province":"IL",
    "sg:tags":[
        "plumber",
        "industrial",
        "contractor",
        "contractors-commercial",
        "mechanical"
    ],
    "wof:name":"Gilco Mechanical Contractors I",
    "wof:placetype":"venue"
},
  "geometry": {"coordinates":[-87.584118,41.736919],"type":"Point"}
}