{
  "type": "Feature",
  "properties": {
    "addr:full":"3320 W Hirsch Street Chicago IL 60651",
    "addr:housenumber":"3320",
    "addr:postcode":"60651",
    "addr:street":"W Hirsch Street",
    "iso:country":"US",
    "sg:address":"3320 W Hirsch Street",
    "sg:city":"Chicago",
    "sg:classifiers":[
        {
            "category":"Education",
            "subcategory":"School",
            "type":"Public Place"
        }
    ],
    "sg:phone":"+1 773 534 4300",
    "sg:postcode":"60651",
    "sg:province":"IL",
    "sg:tags":[
        "high",
        "middle",
        "elementary"
    ],
    "wof:name":"Schools Public",
    "wof:placetype":"venue"
},
  "geometry": {"coordinates":[-87.709808,41.906455],"type":"Point"}
}