{
  "type": "Feature",
  "properties": {
    "addr:full":"310 S Johnson Ave Mount Vernon IL 62864",
    "addr:housenumber":"310",
    "addr:postcode":"62864",
    "addr:street":"S Johnson Ave",
    "iso:country":"US",
    "sg:address":"310 S Johnson Ave",
    "sg:city":"Mount Vernon",
    "sg:classifiers":[
        {
            "category":"Recreation",
            "subcategory":"Arcade",
            "type":"Entertainment"
        }
    ],
    "sg:phone":"+1 618 242 7917",
    "sg:postcode":"62864",
    "sg:province":"IL",
    "sg:tags":[
        "device",
        "operator",
        "amusement"
    ],
    "wof:name":"Best Amusements",
    "wof:placetype":"venue"
},
  "geometry": {"coordinates":[-88.901415,38.315835],"type":"Point"}
}