{
  "type": "Feature",
  "properties": {
    "addr:full":"212 W Kinzie St Chicago IL 60654",
    "addr:housenumber":"212",
    "addr:postcode":"60654",
    "addr:street":"W Kinzie St",
    "iso:country":"US",
    "sg:address":"212 W Kinzie St",
    "sg:city":"Chicago",
    "sg:classifiers":[
        {
            "category":"Banks & Credit Unions",
            "subcategory":"Investment Brokerage",
            "type":"Services"
        },
        {
            "category":"Professional",
            "subcategory":"Employment Agencies",
            "type":"Services"
        }
    ],
    "sg:phone":"+1 312 329 0900",
    "sg:postcode":"60654",
    "sg:province":"IL",
    "sg:tags":[
        "investing"
    ],
    "sg:website":"www.cookassociates.com",
    "wof:name":"Cook Associates",
    "wof:placetype":"venue"
},
  "geometry": {"coordinates":[-87.63469000000001,41.889405],"type":"Point"}
}