{
  "type": "Feature",
  "properties": {
    "iso:country":"US",
    "sg:address":"42 Sherwood Ter",
    "sg:city":"Lake Bluff",
    "sg:classifiers":[
        {
            "category":"Manufacturing",
            "subcategory":"Food",
            "type":"Manufacturing & Wholesale Goods"
        },
        {
            "category":"Wholesale",
            "subcategory":"Groceries",
            "type":"Manufacturing & Wholesale Goods"
        }
    ],
    "sg:phone":"+1 847 283 9292",
    "sg:postcode":"60044",
    "sg:province":"IL",
    "sg:tags":[
        "bakery",
        "product",
        "baker",
        "related",
        "mfg"
    ],
    "wof:name":"Old Colony Baking Company",
    "wof:placetype":"venue"
},
  "geometry": {"coordinates":[-87.867651,42.271536],"type":"Point"}
}