{
  "type": "Feature",
  "properties": {
    "iso:country":"US",
    "sg:address":"1422 Pier Dr",
    "sg:city":"Davis",
    "sg:classifiers":[
        {
            "category":"Real Estate",
            "subcategory":"Real Estate Agent",
            "type":"Services"
        }
    ],
    "sg:phone":"+1 815 248 3131",
    "sg:postcode":"61019",
    "sg:province":"IL",
    "sg:tags":[
        "investment"
    ],
    "wof:name":"Rockford S & T Land Corp",
    "wof:placetype":"venue"
},
  "geometry": {"coordinates":[-89.38586,42.45305],"type":"Point"}
}