{
  "type": "Feature",
  "properties": {
    "iso:country":"US",
    "sg:address":"7929 S Cicero Ave",
    "sg:city":"Chicago",
    "sg:classifiers":[
        {
            "category":"Health Services",
            "subcategory":"Clinic",
            "type":"Services"
        }
    ],
    "sg:phone":"+1 773 582 8911",
    "sg:postcode":"60652",
    "sg:province":"IL",
    "sg:tags":[
        "kidney",
        "dialysis",
        "center"
    ],
    "wof:name":"Renal Care Group Inc",
    "wof:placetype":"venue"
},
  "geometry": {"coordinates":[-87.741171,41.746121],"type":"Point"}
}