{
  "type": "Feature",
  "properties": {
    "iso:country":"US",
    "sg:address":"206 N Randolph St",
    "sg:city":"Champaign",
    "sg:classifiers":[
        {
            "category":"Restaurant",
            "type":"Food & Drink"
        }
    ],
    "sg:menulink":"http://www.allmenus.com/il/champaign-city/17078-peking-garden-restaurant/menu/",
    "sg:phone":"+1 217 355 8888",
    "sg:postcode":"61820",
    "sg:province":"IL",
    "sg:tags":[
        "asian",
        "chinese"
    ],
    "wof:name":"Peking Garden Restaurant",
    "wof:placetype":"venue"
},
  "geometry": {"coordinates":[-88.245071,40.117351],"type":"Point"}
}