{
  "type": "Feature",
  "properties": {
    "iso:country":"US",
    "sg:address":"110 N Neil St",
    "sg:city":"Champaign",
    "sg:classifiers":[
        {
            "category":"Bakery",
            "type":"Food & Drink"
        }
    ],
    "sg:menulink":"http://www.allmenus.com/il/champaign-city/254680-pekala-bakery/menu/",
    "sg:phone":"+1 217 358 4500",
    "sg:postcode":"61820",
    "sg:province":"IL",
    "sg:tags":[
        "american",
        "pastry"
    ],
    "wof:name":"Pekala Bakery",
    "wof:placetype":"venue"
},
  "geometry": {"coordinates":[-88.243523,40.116785],"type":"Point"}
}