{
  "type": "Feature",
  "properties": {
    "iso:country":"US",
    "sg:address":"2501 S California Avenue",
    "sg:city":"Chicago",
    "sg:classifiers":[
        {
            "category":"Real Estate",
            "subcategory":"Real Estate Services",
            "type":"Services"
        }
    ],
    "sg:phone":"+1 773 376 7233",
    "sg:postcode":"60608",
    "sg:province":"IL",
    "sg:tags":[
        "management",
        "property"
    ],
    "wof:name":"Legum Norman",
    "wof:placetype":"venue"
},
  "geometry": {"coordinates":[-87.69511300000001,41.84638],"type":"Point"}
}