{
  "type": "Feature",
  "properties": {
    "iso:country":"US",
    "sg:address":"3104 Windsor Rd",
    "sg:city":"Champaign",
    "sg:classifiers":[
        {
            "category":"Place Of Worship",
            "subcategory":"Synagogue",
            "type":"Public Place"
        }
    ],
    "sg:phone":"+1 217 352 8140",
    "sg:postcode":"61822",
    "sg:province":"IL",
    "wof:name":"Sinai Temple Synagogue",
    "wof:placetype":"venue"
},
  "geometry": {"coordinates":[-88.29270200000001,40.0839],"type":"Point"}
}