{
  "type": "Feature",
  "properties": {
    "iso:country":"US",
    "sg:address":"3304 E Hidden Valley Ln",
    "sg:city":"Chillicothe",
    "sg:classifiers":[
        {
            "category":"Professional",
            "subcategory":"Detective & Security Services",
            "type":"Services"
        }
    ],
    "sg:phone":"+1 309 579 2699",
    "sg:postcode":"61523",
    "sg:province":"IL",
    "sg:tags":[
        "investigator"
    ],
    "wof:name":"David R Hirtz & Assoc Inc",
    "wof:placetype":"venue"
},
  "geometry": {"coordinates":[-89.538093,40.86208],"type":"Point"}
}