{
  "type": "Feature",
  "properties": {
    "iso:country":"US",
    "sg:address":"555 Weston Ridge Dr",
    "sg:city":"Naperville",
    "sg:phone":"+1 630 922 5799",
    "sg:postcode":"60563",
    "sg:province":"IL",
    "sg:website":"http://www.frankieandjohnniesgarage.com",
    "wof:name":"Frankie & Johnnie's Garage",
    "wof:placetype":"venue"
},
  "geometry": {"coordinates":[-88.213559,41.779445],"type":"Point"}
}