{
  "type": "Feature",
  "properties": {
    "iso:country":"US",
    "sg:address":"712 E 4th St",
    "sg:city":"West Frankfort",
    "sg:classifiers":[
        {
            "category":"Wholesale",
            "subcategory":"Motor Vehicles",
            "type":"Manufacturing & Wholesale Goods"
        }
    ],
    "sg:phone":"+1 618 937 1684",
    "sg:postcode":"62896",
    "sg:province":"IL",
    "sg:tags":[
        "body",
        "truck"
    ],
    "wof:name":"Everlite Inc",
    "wof:placetype":"venue"
},
  "geometry": {"coordinates":[-88.92036,37.901926],"type":"Point"}
}