{
  "type": "Feature",
  "properties": {
    "iso:country":"US",
    "sg:address":"307 S 1st St",
    "sg:city":"Oregon",
    "sg:classifiers":[
        {
            "category":"Shopping",
            "type":"Retail Goods"
        }
    ],
    "sg:phone":"+1 815 732 7777",
    "sg:postcode":"61061",
    "sg:province":"IL",
    "sg:tags":[
        "art",
        "craft",
        "instruction",
        "gallery"
    ],
    "sg:website":"http://www.harryspell.com",
    "wof:name":"Art Casting Of Il Inc",
    "wof:placetype":"venue"
},
  "geometry": {"coordinates":[-89.32884199999999,42.011842],"type":"Point"}
}