{
  "type": "Feature",
  "properties": {
    "iso:country":"US",
    "sg:address":"1117 Lakeland Blvd",
    "sg:city":"Mattoon",
    "sg:classifiers":[
        {
            "category":"Restaurant",
            "type":"Food & Drink"
        }
    ],
    "sg:phone":"+1   ",
    "sg:postcode":"61938",
    "sg:province":"IL",
    "sg:tags":[
        "eating"
    ],
    "wof:name":"Hardees",
    "wof:placetype":"venue"
},
  "geometry": {"coordinates":[-88.376453,39.473115],"type":"Point"}
}