{
  "type": "Feature",
  "properties": {
    "addr:full":"911 Fairfax St Carlyle IL 62231",
    "addr:housenumber":"911",
    "addr:postcode":"62231",
    "addr:street":"Fairfax St",
    "iso:country":"US",
    "sg:address":"911 Fairfax St",
    "sg:city":"Carlyle",
    "sg:classifiers":[
        {
            "category":"Restaurant",
            "type":"Food & Drink"
        }
    ],
    "sg:phone":"+1 618 594 5940",
    "sg:postcode":"62231",
    "sg:province":"IL",
    "wof:name":"Cruisers Diner",
    "wof:placetype":"venue"
},
  "geometry": {"coordinates":[-89.370154,38.611246],"type":"Point"}
}