{
  "type": "Feature",
  "properties": {
    "addr:full":"10756 S Green Bay Avenue Chicago IL 60617",
    "addr:housenumber":"10756",
    "addr:postcode":"60617",
    "addr:street":"S Green Bay Avenue",
    "iso:country":"US",
    "sg:address":"10756 S Green Bay Avenue",
    "sg:city":"Chicago",
    "sg:classifiers":[
        {
            "category":"Sports & Exercise",
            "subcategory":"Sports Center",
            "type":"Entertainment"
        }
    ],
    "sg:phone":"+1 773 978 4599",
    "sg:postcode":"60617",
    "sg:province":"IL",
    "sg:tags":[
        "amateur",
        "team"
    ],
    "wof:name":"Sokol Social & Athletic Club",
    "wof:placetype":"venue"
},
  "geometry": {"coordinates":[-87.541496,41.69927],"type":"Point"}
}