{
  "type": "Feature",
  "properties": {
    "iso:country":"US",
    "sg:address":"1135 Meadow Ln",
    "sg:city":"Elgin",
    "sg:classifiers":[
        {
            "category":"Farming",
            "subcategory":"Livestock Farm",
            "type":"Manufacturing & Wholesale Goods"
        }
    ],
    "sg:phone":"+1 847 742 0328",
    "sg:postcode":"60123",
    "sg:province":"IL",
    "sg:tags":[
        "beef",
        "feedlot",
        "cattle"
    ],
    "wof:name":"Paul Tanner",
    "wof:placetype":"venue"
},
  "geometry": {"coordinates":[-88.307695,42.061286],"type":"Point"}
}