{
  "type": "Feature",
  "properties": {
    "addr:full":"2114 S 18th Ave Broadview IL 60155",
    "addr:housenumber":"2114",
    "addr:postcode":"60155",
    "addr:street":"S 18Th Ave",
    "iso:country":"US",
    "sg:address":"2114 S 18th Ave",
    "sg:city":"Broadview",
    "sg:classifiers":[
        {
            "category":"Recreation",
            "type":"Entertainment"
        }
    ],
    "sg:phone":"+1 708 450 9133",
    "sg:postcode":"60155",
    "sg:province":"IL",
    "sg:tags":[
        "organization",
        "membership",
        "baseball"
    ],
    "wof:name":"Broadview Youth Baseball Inc",
    "wof:placetype":"venue"
},
  "geometry": {"coordinates":[-87.854281,41.864481],"type":"Point"}
}