{
  "type": "Feature",
  "properties": {
    "addr:full":"307 Melrose Ave Kenilworth IL 60043",
    "addr:housenumber":"307",
    "addr:postcode":"60043",
    "addr:street":"Melrose Ave",
    "iso:country":"US",
    "sg:address":"307 Melrose Ave",
    "sg:city":"Kenilworth",
    "sg:classifiers":[
        {
            "category":"Banks & Credit Unions",
            "subcategory":"Financial Services",
            "type":"Services"
        }
    ],
    "sg:phone":"+1 847 256 8191",
    "sg:postcode":"60043",
    "sg:province":"IL",
    "sg:tags":[
        "investor"
    ],
    "wof:name":"Lingle Investments LLC",
    "wof:placetype":"venue"
},
  "geometry": {"coordinates":[-87.715878,42.089458],"type":"Point"}
}