{
  "type": "Feature",
  "properties": {
    "addr:full":"14415 W Andover Rd Wadsworth IL 60083",
    "addr:housenumber":"14415",
    "addr:postcode":"60083",
    "addr:street":"W Andover Rd",
    "iso:country":"US",
    "sg:address":"14415 W Andover Rd",
    "sg:city":"Wadsworth",
    "sg:classifiers":[
        {
            "category":"Manufacturing",
            "subcategory":"Tools & Machinery",
            "type":"Manufacturing & Wholesale Goods"
        }
    ],
    "sg:phone":"+1 847 360 9927",
    "sg:postcode":"60083",
    "sg:province":"IL",
    "sg:tags":[
        "photographic",
        "mfg"
    ],
    "wof:name":"Entertainment Concepts",
    "wof:placetype":"venue"
},
  "geometry": {"coordinates":[-87.91237,42.440292],"type":"Point"}
}