{
  "type": "Feature",
  "properties": {
    "iso:country":"US",
    "sg:address":"1516 N 43rd St",
    "sg:city":"East Saint Louis",
    "sg:classifiers":[
        {
            "category":"Building & Trades",
            "subcategory":"Cleaning & Sanitation",
            "type":"Services"
        }
    ],
    "sg:phone":"+1 618 271 0370",
    "sg:postcode":"62204",
    "sg:province":"IL",
    "sg:tags":[
        "maintenance"
    ],
    "wof:name":"Wbs Janitorial Service",
    "wof:placetype":"venue"
},
  "geometry": {"coordinates":[-90.10509999999999,38.630288],"type":"Point"}
}