{
  "type": "Feature",
  "properties": {
    "iso:country":"US",
    "sg:address":"118 W 1st St",
    "sg:city":"Roxana",
    "sg:classifiers":[
        {
            "category":"Place Of Worship",
            "subcategory":"Church",
            "type":"Public Place"
        },
        {
            "category":"Place Of Worship",
            "type":"Public Place"
        }
    ],
    "sg:phone":"+1 618 254 8150",
    "sg:postcode":"62084",
    "sg:province":"IL",
    "sg:tags":[
        "testament",
        "christ-new",
        "churches-church",
        "christ"
    ],
    "wof:name":"Tri County Church Of Christ",
    "wof:placetype":"venue"
},
  "geometry": {"coordinates":[-90.07936,38.847788],"type":"Point"}
}