{
  "type": "Feature",
  "properties": {
    "iso:country":"US",
    "sg:address":"13801 S School St",
    "sg:city":"Riverdale",
    "sg:classifiers":[
        {
            "category":"Restaurant",
            "type":"Food & Drink"
        }
    ],
    "sg:phone":"+1 708 841 9272",
    "sg:postcode":"60827",
    "sg:province":"IL",
    "sg:tags":[
        "pizza"
    ],
    "wof:name":"Rene's Pizza",
    "wof:placetype":"venue"
},
  "geometry": {"coordinates":[-87.62930299999999,41.644501],"type":"Point"}
}