{
  "type": "Feature",
  "properties": {
    "iso:country":"US",
    "sg:address":"1753 E Oakton St",
    "sg:city":"Des Plaines",
    "sg:classifiers":[
        {
            "category":"Retail",
            "subcategory":"Laundry & Dry Cleaning",
            "type":"Services"
        }
    ],
    "sg:phone":"+1 847 827 0055",
    "sg:postcode":"60018",
    "sg:province":"IL",
    "wof:name":"Royal Cleaners",
    "wof:placetype":"venue"
},
  "geometry": {"coordinates":[-87.879609,42.024278],"type":"Point"}
}