{
  "type": "Feature",
  "properties": {
    "iso:country":"US",
    "sg:address":"508 S Cross St",
    "sg:city":"Robinson",
    "sg:classifiers":[
        {
            "category":"Shopping",
            "subcategory":"Clothing, Apparel, & Fashions",
            "type":"Retail Goods"
        }
    ],
    "sg:phone":"+1 618 553 2141",
    "sg:postcode":"62454",
    "sg:province":"IL",
    "sg:tags":[
        "tailor",
        "alterations-clothing"
    ],
    "wof:name":"Bender Alterations",
    "wof:placetype":"venue"
},
  "geometry": {"coordinates":[-87.739403,39.009642],"type":"Point"}
}