{
  "type": "Feature",
  "properties": {
    "iso:country":"US",
    "sg:address":"2306 Crane Dr",
    "sg:city":"Rockford",
    "sg:classifiers":[
        {
            "category":"Professional",
            "subcategory":"Management & Consulting",
            "type":"Services"
        }
    ],
    "sg:phone":"+1 815 637 6944",
    "sg:postcode":"61103",
    "sg:province":"IL",
    "sg:tags":[
        "technical",
        "scientific",
        "reseller"
    ],
    "wof:name":"Surplus Air Support",
    "wof:placetype":"venue"
},
  "geometry": {"coordinates":[-89.095626,42.312851],"type":"Point"}
}