{
  "type": "Feature",
  "properties": {
    "iso:country":"US",
    "sg:address":"77 N Gilbert St",
    "sg:city":"Danville",
    "sg:classifiers":[
        {
            "category":"Bars & Pubs",
            "type":"Food & Drink"
        }
    ],
    "sg:phone":"+1   ",
    "sg:postcode":"61832",
    "sg:province":"IL",
    "sg:tags":[
        "drinking",
        "eating"
    ],
    "wof:name":"Coachs Bar & Grille",
    "wof:placetype":"venue"
},
  "geometry": {"coordinates":[-87.635486,40.124847],"type":"Point"}
}