{
  "type": "Feature",
  "properties": {
    "iso:country":"US",
    "sg:address":"252 Lime St",
    "sg:city":"Dupo",
    "sg:classifiers":[
        {
            "category":"Organizations",
            "subcategory":"Religious Organization",
            "type":"Services"
        }
    ],
    "sg:phone":"+1 618 286 4773",
    "sg:postcode":"62239",
    "sg:province":"IL",
    "sg:tags":[
        "churches-baptist"
    ],
    "wof:name":"Trinity General Baptist Church",
    "wof:placetype":"venue"
},
  "geometry": {"coordinates":[-90.20146800000001,38.5338],"type":"Point"}
}