{
  "type": "Feature",
  "properties": {
    "iso:country":"US",
    "sg:address":"101 Commercial St",
    "sg:city":"Albers",
    "sg:classifiers":[
        {
            "category":"Shopping",
            "subcategory":"Discount & Variety Stores",
            "type":"Retail Goods"
        }
    ],
    "sg:phone":"+1 618 248 5117",
    "sg:postcode":"62257",
    "sg:province":"IL",
    "sg:tags":[
        "merchandise",
        "general"
    ],
    "wof:name":"Huegen Store",
    "wof:placetype":"venue"
},
  "geometry": {"coordinates":[-89.75415700000001,38.256347],"type":"Point"}
}