{
  "type": "Feature",
  "properties": {
    "iso:country":"US",
    "sg:address":"1744 Lincoln St",
    "sg:city":"North Chicago",
    "sg:classifiers":[
        {
            "category":"Building & Trades",
            "subcategory":"Construction",
            "type":"Services"
        }
    ],
    "sg:phone":"+1 847 689 0988",
    "sg:postcode":"60064",
    "sg:province":"IL",
    "sg:tags":[
        "general",
        "contractor"
    ],
    "wof:name":"Olivers Blacktop Services",
    "wof:placetype":"venue"
},
  "geometry": {"coordinates":[-87.842412,42.327618],"type":"Point"}
}