{
  "type": "Feature",
  "properties": {
    "addr:full":"2355 Sweets Dr Ste 2 Carbondale IL 62902",
    "addr:housenumber":"2355",
    "addr:postcode":"62902",
    "addr:street":"Sweets Dr Ste 2",
    "iso:country":"US",
    "sg:address":"2355 Sweets Dr Ste 2",
    "sg:city":"Carbondale",
    "sg:classifiers":[
        {
            "category":"Personal",
            "subcategory":"Tattoo Parlor",
            "type":"Services"
        }
    ],
    "sg:phone":"+1 618 549 2034",
    "sg:postcode":"62902",
    "sg:province":"IL",
    "wof:name":"Tuff Luck Tattoos",
    "wof:placetype":"venue"
},
  "geometry": {"coordinates":[-89.16194900000001,37.741942],"type":"Point"}
}