{
  "type": "Feature",
  "properties": {
    "iso:country":"US",
    "sg:address":"818 S Seminary Ave",
    "sg:city":"Park Ridge",
    "sg:classifiers":[
        {
            "category":"Professional",
            "subcategory":"Management & Consulting",
            "type":"Services"
        },
        {
            "category":"Shopping",
            "subcategory":"Music",
            "type":"Retail Goods"
        }
    ],
    "sg:phone":"+1 847 692 7265",
    "sg:postcode":"60068",
    "sg:province":"IL",
    "sg:tags":[
        "marketing",
        "consultant"
    ],
    "wof:name":"Angel Sing Records",
    "wof:placetype":"venue"
},
  "geometry": {"coordinates":[-87.848195,42.000765],"type":"Point"}
}