{
  "type": "Feature",
  "properties": {
    "iso:country":"US",
    "sg:address":"77 W Main St",
    "sg:city":"Cary",
    "sg:classifiers":[
        {
            "category":"Restaurant",
            "type":"Food & Drink"
        }
    ],
    "sg:phone":"+1 847 516 3777",
    "sg:postcode":"60013",
    "sg:province":"IL",
    "sg:tags":[
        "shop",
        "coffee"
    ],
    "wof:name":"Coffee Station The",
    "wof:placetype":"venue"
},
  "geometry": {"coordinates":[-88.240922,42.208712],"type":"Point"}
}