{
  "type": "Feature",
  "properties": {
    "iso:country":"US",
    "sg:address":"1970 Co Rd 2400 E",
    "sg:city":"Saint Joseph",
    "sg:phone":"+1 217 583 3283",
    "sg:postcode":"61873",
    "sg:province":"IL",
    "sg:tags":[
        "farm",
        "corn"
    ],
    "wof:name":"Ray Aden",
    "wof:placetype":"venue"
},
  "geometry": {"coordinates":[-88.00957099999999,40.1674],"type":"Point"}
}