{
  "type": "Feature",
  "properties": {
    "addr:full":"1612 Landmeier Rd Elk Grove Village IL 60007",
    "addr:housenumber":"1612",
    "addr:postcode":"60007",
    "addr:street":"Landmeier Rd",
    "iso:country":"US",
    "sg:address":"1612 Landmeier Rd",
    "sg:city":"Elk Grove Village",
    "sg:classifiers":[
        {
            "category":"Manufacturing",
            "subcategory":"Tools & Machinery",
            "type":"Manufacturing & Wholesale Goods"
        }
    ],
    "sg:phone":"+1 847 690 0111",
    "sg:postcode":"60007",
    "sg:province":"IL",
    "sg:tags":[
        "industrial",
        "mfg"
    ],
    "wof:name":"Ace Precision Tool",
    "wof:placetype":"venue"
},
  "geometry": {"coordinates":[-87.967731,42.011858],"type":"Point"}
}