{
  "type": "Feature",
  "properties": {
    "iso:country":"US",
    "sg:address":"1816 W War Memorial Dr",
    "sg:city":"Peoria",
    "sg:classifiers":[
        {
            "category":"Travel",
            "subcategory":"Hotels & Motels",
            "type":"Entertainment"
        }
    ],
    "sg:phone":"+1 309 688 8074",
    "sg:postcode":"61614",
    "sg:province":"IL",
    "wof:name":"Shivam Hotel",
    "wof:placetype":"venue"
},
  "geometry": {"coordinates":[-89.63081,40.745739],"type":"Point"}
}