{
  "type": "Feature",
  "properties": {
    "iso:country":"US",
    "sg:address":"963 N 400 East Rd",
    "sg:city":"Buckley",
    "sg:classifiers":[
        {
            "category":"Farming",
            "subcategory":"Farm",
            "type":"Manufacturing & Wholesale Goods"
        }
    ],
    "sg:phone":"+1 217 394 2503",
    "sg:postcode":"60918",
    "sg:province":"IL",
    "sg:tags":[
        "crop",
        "general"
    ],
    "wof:name":"Eric Steiner",
    "wof:placetype":"venue"
},
  "geometry": {"coordinates":[-88.044143,40.629629],"type":"Point"}
}