{
  "type": "Feature",
  "properties": {
    "iso:country":"US",
    "sg:address":"600 W Van Buren St # 903",
    "sg:city":"Chicago",
    "sg:classifiers":[
        {
            "category":"Professional",
            "subcategory":"Printing & Photocopies",
            "type":"Services"
        }
    ],
    "sg:phone":"+1 312 258 1178",
    "sg:postcode":"60607",
    "sg:province":"IL",
    "sg:tags":[
        "photographers-commercial"
    ],
    "wof:name":"Degrand Joel Photography",
    "wof:placetype":"venue"
},
  "geometry": {"coordinates":[-87.642471,41.876732],"type":"Point"}
}