{
  "type": "Feature",
  "properties": {
    "iso:country":"US",
    "sg:address":"1217 State Rte 117",
    "sg:city":"Eureka",
    "sg:phone":"+1 309 467 2790",
    "sg:postcode":"61530",
    "sg:province":"IL",
    "sg:tags":[
        "farm",
        "corn",
        "soybean"
    ],
    "wof:name":"Kenneth Fehr",
    "wof:placetype":"venue"
},
  "geometry": {"coordinates":[-89.272665,40.707951],"type":"Point"}
}