{
  "type": "Feature",
  "properties": {
    "addr:full":"11 S Lakewood Dr Effingham IL 62401",
    "addr:housenumber":"11",
    "addr:postcode":"62401",
    "addr:street":"S Lakewood Dr",
    "iso:country":"US",
    "sg:address":"11 S Lakewood Dr",
    "sg:city":"Effingham",
    "sg:classifiers":[
        {
            "category":"Professional",
            "subcategory":"Business Services",
            "type":"Services"
        }
    ],
    "sg:phone":"+1 217 821 1766",
    "sg:postcode":"62401",
    "sg:province":"IL",
    "wof:name":"Kismet Design Studio",
    "wof:placetype":"venue"
},
  "geometry": {"coordinates":[-88.558688,39.124169],"type":"Point"}
}