{
  "type": "Feature",
  "properties": {
    "iso:country":"US",
    "sg:address":"950 Busse Hwy",
    "sg:city":"Park Ridge",
    "sg:classifiers":[
        {
            "category":"Retail",
            "subcategory":"Car Wash",
            "type":"Services"
        }
    ],
    "sg:phone":"+1 847 825 1440",
    "sg:postcode":"60068",
    "sg:province":"IL",
    "sg:tags":[
        "polishing",
        "washing"
    ],
    "wof:name":"Boardwalk Detail & Audio",
    "wof:placetype":"venue"
},
  "geometry": {"coordinates":[-87.855797,42.024539],"type":"Point"}
}