{
  "type": "Feature",
  "properties": {
    "addr:full":"1711 E 71st St Chicago IL 60649",
    "addr:housenumber":"1711",
    "addr:postcode":"60649",
    "addr:street":"E 71St St",
    "iso:country":"US",
    "sg:address":"1711 E 71st St",
    "sg:city":"Chicago",
    "sg:classifiers":[
        {
            "category":"Banks & Credit Unions",
            "subcategory":"Bank",
            "type":"Services"
        }
    ],
    "sg:phone":"+1 773 363 7411",
    "sg:postcode":"60649",
    "sg:province":"IL",
    "sg:tags":[
        "company",
        "trust"
    ],
    "wof:name":"African American National",
    "wof:placetype":"venue"
},
  "geometry": {"coordinates":[-87.583264,41.766013],"type":"Point"}
}