{
  "type": "Feature",
  "properties": {
    "iso:country":"US",
    "sg:address":"2202 N Market St",
    "sg:city":"Champaign",
    "sg:classifiers":[
        {
            "category":"Freight",
            "type":"Transportation"
        }
    ],
    "sg:phone":"+1 217 356 4777",
    "sg:postcode":"61822",
    "sg:province":"IL",
    "sg:tags":[
        "general"
    ],
    "wof:name":"A A A Storage",
    "wof:placetype":"venue"
},
  "geometry": {"coordinates":[-88.238918,40.141457],"type":"Point"}
}