{
  "type": "Feature",
  "properties": {
    "iso:country":"US",
    "sg:address":"900 Noelle Bend",
    "sg:city":"Lake In The Hls",
    "sg:classifiers":[
        {
            "category":"Restaurant",
            "type":"Food & Drink"
        }
    ],
    "sg:phone":"+1 847 742 6272",
    "sg:postcode":"60156",
    "sg:province":"IL",
    "wof:name":"Huddle",
    "wof:placetype":"venue"
},
  "geometry": {"coordinates":[-88.386453,42.188918],"type":"Point"}
}