{
  "type": "Feature",
  "properties": {
    "addr:full":"9029 S Western Ave Chicago IL 60643",
    "addr:housenumber":"9029",
    "addr:postcode":"60643",
    "addr:street":"S Western Ave",
    "iso:country":"US",
    "sg:address":"9029 S Western Ave",
    "sg:city":"Chicago",
    "sg:classifiers":[
        {
            "category":"Wholesale",
            "subcategory":"Books, Periodicals, & Newspapers",
            "type":"Manufacturing & Wholesale Goods"
        }
    ],
    "sg:phone":"+1 773 445 2400",
    "sg:postcode":"60643",
    "sg:province":"IL",
    "sg:tags":[
        "magazine"
    ],
    "sg:website":"http://www.nau.edu",
    "wof:name":"Nasaba Magazine",
    "wof:placetype":"venue"
},
  "geometry": {"coordinates":[-87.682053,41.720915],"type":"Point"}
}