{
  "type": "Feature",
  "properties": {
    "iso:country":"US",
    "sg:address":"2735 N. Lincoln Ave #B",
    "sg:city":"Chicago",
    "sg:classifiers":[
        {
            "category":"Personal",
            "subcategory":"Nail Salon",
            "type":"Services"
        }
    ],
    "sg:phone":"+1 773 388 8810",
    "sg:postcode":"60614",
    "sg:province":"IL",
    "wof:name":"Cozy Nail Spa",
    "wof:placetype":"venue"
},
  "geometry": {"coordinates":[-87.657303,41.931801],"type":"Point"}
}