{
  "type": "Feature",
  "properties": {
    "iso:country":"US",
    "sg:address":"100 W Madison St",
    "sg:city":"Ottawa",
    "sg:classifiers":[
        {
            "category":"Restaurant",
            "type":"Food & Drink"
        }
    ],
    "sg:phone":"+1 815 434 6626",
    "sg:postcode":"61350",
    "sg:province":"IL",
    "wof:name":"Green Mill Cafe",
    "wof:placetype":"venue"
},
  "geometry": {"coordinates":[-88.84217099999999,41.34684],"type":"Point"}
}