{
  "type": "Feature",
  "properties": {
    "iso:country":"US",
    "sg:address":"10508 N Clark Rd",
    "sg:city":"Richmond",
    "sg:classifiers":[
        {
            "category":"Manufacturing",
            "subcategory":"Textiles",
            "type":"Manufacturing & Wholesale Goods"
        }
    ],
    "sg:phone":"+1 815 678 4461",
    "sg:postcode":"60071",
    "sg:province":"IL",
    "sg:tags":[
        "fabrics-wholesale",
        "manufacturer"
    ],
    "wof:name":"Alpacas Of Royal Crest",
    "wof:placetype":"venue"
},
  "geometry": {"coordinates":[-88.26230700000001,42.478004],"type":"Point"}
}