{
  "type": "Feature",
  "properties": {
    "addr:full":"1408 Brorson Ln Johnsburg IL 60051",
    "addr:housenumber":"1408",
    "addr:postcode":"60051",
    "addr:street":"Brorson Ln",
    "iso:country":"US",
    "sg:address":"1408 Brorson Ln",
    "sg:city":"Johnsburg",
    "sg:classifiers":[
        {
            "category":"Professional",
            "type":"Services"
        }
    ],
    "sg:phone":"+1 847 360 4826",
    "sg:postcode":"60051",
    "sg:province":"IL",
    "sg:tags":[
        "publication",
        "editorial"
    ],
    "wof:name":"Nosco",
    "wof:placetype":"venue"
},
  "geometry": {"coordinates":[-88.224842,42.395969],"type":"Point"}
}