{
  "type": "Feature",
  "properties": {
    "iso:country":"US",
    "sg:address":"103 Sell Rd",
    "sg:city":"Elk Grove Village",
    "sg:classifiers":[
        {
            "category":"Utilities",
            "subcategory":"Refuse",
            "type":"Services"
        }
    ],
    "sg:phone":"+1 847 884 7676",
    "sg:postcode":"60007",
    "sg:province":"IL",
    "sg:tags":[
        "disposal"
    ],
    "wof:name":"DMS",
    "wof:placetype":"venue"
},
  "geometry": {"coordinates":[-87.93311,42.004248],"type":"Point"}
}