{
  "type": "Feature",
  "properties": {
    "addr:full":"6430 N Hamlin Ave Lincolnwood IL 60712",
    "addr:housenumber":"6430",
    "addr:postcode":"60712",
    "addr:street":"N Hamlin Ave",
    "iso:country":"US",
    "sg:address":"6430 N Hamlin Ave",
    "sg:city":"Lincolnwood",
    "sg:classifiers":[
        {
            "category":"Manufacturing",
            "subcategory":"Tools & Machinery",
            "type":"Manufacturing & Wholesale Goods"
        },
        {
            "category":"Home & Garden",
            "subcategory":"Hardware",
            "type":"Retail Goods"
        },
        {
            "category":"Wholesale",
            "subcategory":"Home Furnishings",
            "type":"Manufacturing & Wholesale Goods"
        }
    ],
    "sg:phone":"+1 312 421 6080",
    "sg:postcode":"60712",
    "sg:province":"IL",
    "sg:tags":[
        "electric",
        "system",
        "equipment",
        "fixtures-wholesale",
        "lighting",
        "supplies-wholesale",
        "manufacturer"
    ],
    "wof:name":"Rgb Lights Inc.",
    "wof:placetype":"venue"
},
  "geometry": {"coordinates":[-87.724002,41.997823],"type":"Point"}
}