{
  "type": "Feature",
  "properties": {
    "addr:full":"11280 Elston Rd Fulton IL 61252",
    "addr:housenumber":"11280",
    "addr:postcode":"61252",
    "addr:street":"Elston Rd",
    "iso:country":"US",
    "sg:address":"11280 Elston Rd",
    "sg:city":"Fulton",
    "sg:classifiers":[
        {
            "category":"Retail",
            "subcategory":"Repair Shop",
            "type":"Services"
        }
    ],
    "sg:phone":"+1 309 887 4151",
    "sg:postcode":"61252",
    "sg:province":"IL",
    "sg:tags":[
        "welding"
    ],
    "wof:name":"J & B Welding LLC",
    "wof:placetype":"venue"
},
  "geometry": {"coordinates":[-90.151031,41.739325],"type":"Point"}
}