{
  "type": "Feature",
  "properties": {
    "iso:country":"US",
    "sg:address":"6859 Church St",
    "sg:city":"Morton Grove",
    "sg:classifiers":[
        {
            "category":"Retail",
            "subcategory":"Self-service Laundry",
            "type":"Services"
        }
    ],
    "sg:phone":"+1 847 581 1055",
    "sg:postcode":"60053",
    "sg:province":"IL",
    "sg:tags":[
        "coin"
    ],
    "wof:name":"1st Coin Laundry Inc",
    "wof:placetype":"venue"
},
  "geometry": {"coordinates":[-87.797525,42.048],"type":"Point"}
}