{
  "type": "Feature",
  "properties": {
    "addr:full":"311 S Merrill St Park Ridge IL 60068",
    "addr:housenumber":"311",
    "addr:postcode":"60068",
    "addr:street":"S Merrill St",
    "iso:country":"US",
    "sg:address":"311 S Merrill St",
    "sg:city":"Park Ridge",
    "sg:classifiers":[
        {
            "category":"Freight",
            "type":"Transportation"
        }
    ],
    "sg:phone":"+1 773 477 5736",
    "sg:postcode":"60068",
    "sg:province":"IL",
    "wof:name":"Double L Transit Inc",
    "wof:placetype":"venue"
},
  "geometry": {"coordinates":[-87.82217900000001,42.006939],"type":"Point"}
}