{
  "type": "Feature",
  "properties": {
    "addr:full":"842 W Taylor St Chicago IL 60607",
    "addr:housenumber":"842",
    "addr:postcode":"60607",
    "addr:street":"W Taylor St",
    "iso:country":"US",
    "sg:address":"842 W Taylor St",
    "sg:city":"Chicago",
    "sg:classifiers":[
        {
            "category":"Education",
            "subcategory":"University",
            "type":"Public Place"
        }
    ],
    "sg:phone":"+1 312 996 8421",
    "sg:postcode":"60607",
    "sg:province":"IL",
    "sg:tags":[
        "college"
    ],
    "wof:name":"University Of Illinois At Chicago, Mie",
    "wof:placetype":"venue"
},
  "geometry": {"coordinates":[-87.64982500000001,41.869619],"type":"Point"}
}