{
  "type": "Feature",
  "properties": {
    "addr:full":"260 Congress Pkwy Crystal Lake IL 60014",
    "addr:housenumber":"260",
    "addr:postcode":"60014",
    "addr:street":"Congress Pkwy",
    "iso:country":"US",
    "sg:address":"260 Congress Pkwy",
    "sg:city":"Crystal Lake",
    "sg:classifiers":[
        {
            "category":"Health Services",
            "subcategory":"Doctor",
            "type":"Services"
        }
    ],
    "sg:phone":"+1 815 459 4803",
    "sg:postcode":"60014",
    "sg:province":"IL",
    "sg:tags":[
        "dentist"
    ],
    "wof:name":"Henry Kay DDS",
    "wof:placetype":"venue"
},
  "geometry": {"coordinates":[-88.312336,42.231078],"type":"Point"}
}