{
  "type": "Feature",
  "properties": {
    "iso:country":"US",
    "sg:address":"8005 W 99th St",
    "sg:city":"Palos Hills",
    "sg:classifiers":[
        {
            "category":"Health Services",
            "subcategory":"Health Practitioner",
            "type":"Services"
        },
        {
            "category":"Health Services",
            "subcategory":"Chiropractor",
            "type":"Services"
        }
    ],
    "sg:phone":"+1 708 430 5440",
    "sg:postcode":"60465",
    "sg:province":"IL",
    "sg:tags":[
        "acupuncture"
    ],
    "sg:website":"palosnaturalhealth.com/",
    "wof:name":"Center for Natural Health",
    "wof:placetype":"venue"
},
  "geometry": {"coordinates":[-87.817803,41.711231],"type":"Point"}
}