{
  "type": "Feature",
  "properties": {
    "iso:country":"US",
    "sg:address":"8649 W 95th St",
    "sg:city":"Hickory Hills",
    "sg:classifiers":[
        {
            "category":"Shopping",
            "subcategory":"Discount & Variety Stores",
            "type":"Retail Goods"
        }
    ],
    "sg:phone":"+1 708 430 9601",
    "sg:postcode":"60457",
    "sg:province":"IL",
    "wof:name":"Dollar Store Plus",
    "wof:placetype":"venue"
},
  "geometry": {"coordinates":[-87.835284,41.718158],"type":"Point"}
}