{
  "type": "Feature",
  "properties": {
    "iso:country":"US",
    "sg:address":"1309 S Schoolhouse Rd",
    "sg:city":"New Lenox",
    "sg:classifiers":[
        {
            "category":"Building & Trades",
            "subcategory":"Construction",
            "type":"Services"
        }
    ],
    "sg:phone":"+1 815 485 2600",
    "sg:postcode":"60451",
    "sg:province":"IL",
    "sg:tags":[
        "general",
        "contractor"
    ],
    "wof:name":"Smenta Builders",
    "wof:placetype":"venue"
},
  "geometry": {"coordinates":[-87.926211,41.48484],"type":"Point"}
}