{
  "type": "Feature",
  "properties": {
    "iso:country":"US",
    "sg:address":"2345 W Hubbard St",
    "sg:city":"Chicago",
    "sg:classifiers":[
        {
            "category":"Shopping",
            "subcategory":"Gifts & Souvenirs",
            "type":"Retail Goods"
        }
    ],
    "sg:phone":"+1 312 413 7230",
    "sg:postcode":"60612",
    "sg:province":"IL",
    "sg:tags":[
        "material",
        "wrapping"
    ],
    "wof:name":"Crown Packaging Intl.",
    "wof:placetype":"venue"
},
  "geometry": {"coordinates":[-87.68568999999999,41.889591],"type":"Point"}
}