{
  "type": "Feature",
  "properties": {
    "addr:full":"1341 Co Rd 2100E Casey IL 62428",
    "addr:housenumber":"1341;2100e",
    "addr:postcode":"62428",
    "addr:street":"Co Rd",
    "iso:country":"US",
    "sg:address":"1341 Co Rd 2100E",
    "sg:city":"Casey",
    "sg:classifiers":[
        {
            "category":"Freight",
            "type":"Transportation"
        }
    ],
    "sg:phone":"+1 217 932 4563",
    "sg:postcode":"62428",
    "sg:province":"IL",
    "sg:tags":[
        "operator",
        "local",
        "trucking"
    ],
    "wof:name":"Repp Trucking",
    "wof:placetype":"venue"
},
  "geometry": {"coordinates":[-88.08332900000001,39.369475],"type":"Point"}
}