{
  "type": "Feature",
  "properties": {
    "iso:country":"US",
    "sg:address":"452 Acorn Dr",
    "sg:city":"Beloit",
    "sg:classifiers":[
        {
            "category":"Retail",
            "subcategory":"Auto Repair",
            "type":"Services"
        }
    ],
    "sg:phone":"+1 608 364 0330",
    "sg:postcode":"53511",
    "sg:province":"IL",
    "sg:tags":[
        "automotive"
    ],
    "wof:name":"D&J Towing LLC",
    "wof:placetype":"venue"
},
  "geometry": {"coordinates":[-89.034448,42.571187],"type":"Point"}
}