{
  "type": "Feature",
  "properties": {
    "addr:full":"3401 W Elm St Mchenry IL 60050",
    "addr:housenumber":"3401",
    "addr:postcode":"60050",
    "addr:street":"W Elm St",
    "iso:country":"US",
    "sg:address":"3401 W Elm St",
    "sg:city":"Mchenry",
    "sg:classifiers":[
        {
            "category":"Restaurant",
            "type":"Food & Drink"
        }
    ],
    "sg:phone":"+1 815 344 0580",
    "sg:postcode":"60050",
    "sg:province":"IL",
    "sg:tags":[
        "carry",
        "pizza"
    ],
    "wof:name":"Stucs Pizza",
    "wof:placetype":"venue"
},
  "geometry": {"coordinates":[-88.263847,42.345001],"type":"Point"}
}