{
  "type": "Feature",
  "properties": {
    "addr:full":"225 N 4th St Libertyville IL 60048",
    "addr:housenumber":"225",
    "addr:postcode":"60048",
    "addr:street":"N 4Th St",
    "iso:country":"US",
    "sg:address":"225 N 4th St",
    "sg:city":"Libertyville",
    "sg:classifiers":[
        {
            "category":"Freight",
            "type":"Transportation"
        }
    ],
    "sg:phone":"+1 847 367 5591",
    "sg:postcode":"60048",
    "sg:province":"IL",
    "sg:tags":[
        "hauler",
        "contract"
    ],
    "wof:name":"Schuett Transport Inc",
    "wof:placetype":"venue"
},
  "geometry": {"coordinates":[-87.945919,42.284582],"type":"Point"}
}