{
  "type": "Feature",
  "properties": {
    "addr:full":"2154 Vermont St Blue Island IL 60406",
    "addr:housenumber":"2154",
    "addr:postcode":"60406",
    "addr:street":"Vermont St",
    "iso:country":"US",
    "sg:address":"2154 Vermont St",
    "sg:city":"Blue Island",
    "sg:classifiers":[
        {
            "category":"Home & Garden",
            "subcategory":"Building Materials",
            "type":"Retail Goods"
        }
    ],
    "sg:phone":"+1 708 388 0045",
    "sg:postcode":"60406",
    "sg:province":"IL",
    "wof:name":"Wille Bros Co",
    "wof:placetype":"venue"
},
  "geometry": {"coordinates":[-87.67645899999999,41.655585],"type":"Point"}
}