{
  "type": "Feature",
  "properties": {
    "addr:full":"611 S Front St Okawville IL 62271",
    "addr:housenumber":"611",
    "addr:postcode":"62271",
    "addr:street":"S Front St",
    "iso:country":"US",
    "sg:address":"611 S Front St",
    "sg:city":"Okawville",
    "sg:classifiers":[
        {
            "category":"Insurance",
            "subcategory":"Hazard Insurance",
            "type":"Services"
        }
    ],
    "sg:phone":"+1 618 243 6416",
    "sg:postcode":"62271",
    "sg:province":"IL",
    "sg:tags":[
        "commercial",
        "business"
    ],
    "wof:name":"Leadendecker Insurance Agency",
    "wof:placetype":"venue"
},
  "geometry": {"coordinates":[-89.550522,38.424647],"type":"Point"}
}