{
  "type": "Feature",
  "properties": {
    "iso:country":"US",
    "sg:address":"1410 Higgins Rd",
    "sg:city":"Park Ridge",
    "sg:classifiers":[
        {
            "category":"Real Estate",
            "subcategory":"Architect",
            "type":"Services"
        }
    ],
    "sg:phone":"+1 847 698 3770",
    "sg:postcode":"60068",
    "sg:province":"IL",
    "wof:name":"Johnston Associates Inc",
    "wof:placetype":"venue"
},
  "geometry": {"coordinates":[-87.84520000000001,41.987598],"type":"Point"}
}