{
  "type": "Feature",
  "properties": {
    "iso:country":"US",
    "sg:address":"660 State Rte 142 S",
    "sg:city":"Eldorado",
    "sg:classifiers":[
        {
            "category":"Retail",
            "subcategory":"Repair Shop",
            "type":"Services"
        }
    ],
    "sg:phone":"+1 618 273 5968",
    "sg:postcode":"62930",
    "sg:province":"IL",
    "sg:tags":[
        "contractor"
    ],
    "wof:name":"Bart L Shults Instalation",
    "wof:placetype":"venue"
},
  "geometry": {"coordinates":[-88.434017,37.803847],"type":"Point"}
}