{
  "type": "Feature",
  "properties": {
    "addr:full":"10639 S Sangamon St Chicago IL 60643",
    "addr:housenumber":"10639",
    "addr:postcode":"60643",
    "addr:street":"S Sangamon St",
    "iso:country":"US",
    "sg:address":"10639 S Sangamon St",
    "sg:city":"Chicago",
    "sg:classifiers":[
        {
            "category":"Wholesale",
            "subcategory":"Books, Periodicals, & Newspapers",
            "type":"Manufacturing & Wholesale Goods"
        }
    ],
    "sg:phone":"+1 773 679 2993",
    "sg:postcode":"60643",
    "sg:province":"IL",
    "sg:tags":[
        "books-wholesale",
        "manufacturer"
    ],
    "wof:name":"Mind Materials",
    "wof:placetype":"venue"
},
  "geometry": {"coordinates":[-87.646282,41.700729],"type":"Point"}
}