{
  "type": "Feature",
  "properties": {
    "addr:full":"4601 N Springfield Ave Chicago IL 60625",
    "addr:housenumber":"4601",
    "addr:postcode":"60625",
    "addr:street":"N Springfield Ave",
    "iso:country":"US",
    "sg:address":"4601 N Springfield Ave",
    "sg:city":"Chicago",
    "sg:classifiers":[
        {
            "category":"Health Services",
            "subcategory":"Hospital",
            "type":"Services"
        }
    ],
    "sg:phone":"+1 773 267 3118",
    "sg:postcode":"60625",
    "sg:province":"IL",
    "sg:tags":[
        "nurse",
        "registry"
    ],
    "wof:name":"Polish Nurses Association",
    "wof:placetype":"venue"
},
  "geometry": {"coordinates":[-87.725471,41.964611],"type":"Point"}
}