{
  "type": "Feature",
  "properties": {
    "iso:country":"US",
    "sg:address":"2364 W Pines Rd",
    "sg:city":"Oregon",
    "sg:phone":"+1 815 732 7446",
    "sg:postcode":"61061",
    "sg:province":"IL",
    "sg:tags":[
        "farm",
        "field",
        "corn",
        "crop"
    ],
    "wof:name":"Edward & Karen Giese",
    "wof:placetype":"venue"
},
  "geometry": {"coordinates":[-89.377382,42.002768],"type":"Point"}
}