{
  "type": "Feature",
  "properties": {
    "iso:country":"US",
    "sg:address":"1998 1st Ave",
    "sg:city":"East Moline",
    "sg:classifiers":[
        {
            "category":"Building & Trades",
            "subcategory":"Equipment Rental",
            "type":"Services"
        }
    ],
    "sg:phone":"+1 309 797 0110",
    "sg:postcode":"61244",
    "sg:province":"IL",
    "sg:tags":[
        "appliance"
    ],
    "sg:website":"www.rentacenter.com",
    "wof:name":"Rent-A-Center",
    "wof:placetype":"venue"
},
  "geometry": {"coordinates":[-90.425073,41.534122],"type":"Point"}
}