{
  "type": "Feature",
  "properties": {
    "iso:country":"US",
    "sg:address":"1870 N Roselle Rd",
    "sg:city":"Schaumburg",
    "sg:classifiers":[
        {
            "category":"Professional",
            "subcategory":"Management & Consulting",
            "type":"Services"
        }
    ],
    "sg:phone":"+1 847 781 5353",
    "sg:postcode":"60195",
    "sg:province":"IL",
    "sg:tags":[
        "business"
    ],
    "wof:name":"Bloom Consultants LLC",
    "wof:placetype":"venue"
},
  "geometry": {"coordinates":[-88.079607,42.062313],"type":"Point"}
}