{
  "type": "Feature",
  "properties": {
    "iso:country":"US",
    "sg:address":"453 E 2200 North Rd",
    "sg:city":"Danforth",
    "sg:classifiers":[
        {
            "category":"Farming",
            "subcategory":"Dairy Farm",
            "type":"Manufacturing & Wholesale Goods"
        }
    ],
    "sg:phone":"+1 815 269 2453",
    "sg:postcode":"60930",
    "sg:province":"IL",
    "wof:name":"Tammen Dairy Farm",
    "wof:placetype":"venue"
},
  "geometry": {"coordinates":[-88.042174,40.822998],"type":"Point"}
}