{
  "type": "Feature",
  "properties": {
    "iso:country":"US",
    "sg:address":"4646 N Marine Drive",
    "sg:city":"Chicago",
    "sg:classifiers":[
        {
            "category":"Health Services",
            "subcategory":"Doctor",
            "type":"Services"
        }
    ],
    "sg:phone":"+1 773 564 5995",
    "sg:postcode":"60640",
    "sg:province":"IL",
    "sg:tags":[
        "practice",
        "family"
    ],
    "wof:name":"Vargish Thomas MD",
    "wof:placetype":"venue"
},
  "geometry": {"coordinates":[-87.64899,41.966929],"type":"Point"}
}