{
  "type": "Feature",
  "properties": {
    "iso:country":"US",
    "sg:address":"200 W Court St",
    "sg:city":"Kankakee",
    "sg:classifiers":[
        {
            "category":"Banks & Credit Unions",
            "subcategory":"Investment Brokerage",
            "type":"Services"
        }
    ],
    "sg:phone":"+1 815 928 9900",
    "sg:postcode":"60901",
    "sg:province":"IL",
    "sg:tags":[
        "advisory",
        "financial"
    ],
    "wof:name":"Consolidated Financial LLC",
    "wof:placetype":"venue"
},
  "geometry": {"coordinates":[-87.868937,41.120892],"type":"Point"}
}