{
  "type": "Feature",
  "properties": {
    "addr:full":"10316 S. Cicero Avenue Oak Lawn IL 60453",
    "addr:housenumber":"10316",
    "addr:postcode":"60453",
    "addr:street":"S. Cicero Avenue",
    "iso:country":"US",
    "sg:address":"10316 S. Cicero Avenue",
    "sg:city":"Oak Lawn",
    "sg:classifiers":[
        {
            "category":"Personal",
            "subcategory":"Beauty Salon",
            "type":"Services"
        }
    ],
    "sg:phone":"+1 708 425 0000",
    "sg:postcode":"60453",
    "sg:province":"IL",
    "sg:tags":[
        "spa"
    ],
    "sg:website":"www.studio21salons.com",
    "wof:name":"Studio 21 Salon and Spa",
    "wof:placetype":"venue"
},
  "geometry": {"coordinates":[-87.740348,41.70515],"type":"Point"}
}