{
  "type": "Feature",
  "properties": {
    "iso:country":"US",
    "sg:address":"641 Meacham Rd",
    "sg:city":"Elk Grove Village",
    "sg:classifiers":[
        {
            "category":"Shopping",
            "subcategory":"Pharmacy",
            "type":"Retail Goods"
        }
    ],
    "sg:phone":"+1   ",
    "sg:postcode":"60007",
    "sg:province":"IL",
    "wof:name":"Walgreens",
    "wof:placetype":"venue"
},
  "geometry": {"coordinates":[-88.04593,42.007954],"type":"Point"}
}