{
  "type": "Feature",
  "properties": {
    "iso:country":"US",
    "sg:address":"1036 W Hunting Dr",
    "sg:city":"Palatine",
    "sg:classifiers":[
        {
            "category":"Wholesale",
            "subcategory":"Electrical",
            "type":"Manufacturing & Wholesale Goods"
        }
    ],
    "sg:phone":"+1 847 934 0595",
    "sg:postcode":"60067",
    "sg:province":"IL",
    "sg:tags":[
        "electronic"
    ],
    "wof:name":"Megatron Inc",
    "wof:placetype":"venue"
},
  "geometry": {"coordinates":[-88.068821,42.097747],"type":"Point"}
}