{
  "type": "Feature",
  "properties": {
    "iso:country":"US",
    "sg:address":"6400 Sebring Way",
    "sg:city":"Loves Park",
    "sg:classifiers":[
        {
            "category":"Retail",
            "subcategory":"Auto Repair",
            "type":"Services"
        }
    ],
    "sg:phone":"+1 815 282 6400",
    "sg:postcode":"61111",
    "sg:province":"IL",
    "sg:tags":[
        "repairing",
        "automobile"
    ],
    "wof:name":"Powder's Automotive",
    "wof:placetype":"venue"
},
  "geometry": {"coordinates":[-88.991983,42.319777],"type":"Point"}
}