{
  "type": "Feature",
  "properties": {
    "addr:full":"8383 Kiowa Xing Roscoe IL 61073",
    "addr:housenumber":"8383",
    "addr:postcode":"61073",
    "addr:street":"Kiowa Xing",
    "iso:country":"US",
    "sg:address":"8383 Kiowa Xing",
    "sg:city":"Roscoe",
    "sg:classifiers":[
        {
            "category":"Building & Trades",
            "subcategory":"Construction",
            "type":"Services"
        }
    ],
    "sg:phone":"+1 815 389 1128",
    "sg:postcode":"61073",
    "sg:province":"IL",
    "sg:tags":[
        "house"
    ],
    "wof:name":"Alex Wasson Construction",
    "wof:placetype":"venue"
},
  "geometry": {"coordinates":[-88.952358,42.445764],"type":"Point"}
}