{
  "type": "Feature",
  "properties": {
    "iso:country":"US",
    "sg:address":"2203 E 29th Rd",
    "sg:city":"Seneca",
    "sg:classifiers":[
        {
            "category":"Manufacturing",
            "subcategory":"Food",
            "type":"Manufacturing & Wholesale Goods"
        },
        {
            "category":"Farming",
            "subcategory":"Farm",
            "type":"Manufacturing & Wholesale Goods"
        }
    ],
    "sg:phone":"+1 815 357 6319",
    "sg:postcode":"61360",
    "sg:province":"IL",
    "sg:tags":[
        "corn",
        "product"
    ],
    "wof:name":"Charles Maier",
    "wof:placetype":"venue"
},
  "geometry": {"coordinates":[-88.607355,41.253522],"type":"Point"}
}