{
  "type": "Feature",
  "properties": {
    "addr:full":"145 N Kennedy Dr Carpentersville IL 60110",
    "addr:housenumber":"145",
    "addr:postcode":"60110",
    "addr:street":"N Kennedy Dr",
    "iso:country":"US",
    "sg:address":"145 N Kennedy Dr",
    "sg:city":"Carpentersville",
    "sg:classifiers":[
        {
            "category":"Bars & Pubs",
            "type":"Food & Drink"
        },
        {
            "category":"Restaurant",
            "type":"Food & Drink"
        }
    ],
    "sg:phone":"+1 847 428 6678",
    "sg:postcode":"60110",
    "sg:province":"IL",
    "sg:tags":[
        "pizza"
    ],
    "sg:website":"villagepizzaandpub.com",
    "wof:name":"Village Pizza and Pub",
    "wof:placetype":"venue"
},
  "geometry": {"coordinates":[-88.25775,42.134606],"type":"Point"}
}