{
  "type": "Feature",
  "properties": {
    "iso:country":"US",
    "sg:address":"8401 Crawford Ave",
    "sg:city":"Skokie",
    "sg:classifiers":[
        {
            "category":"Travel",
            "subcategory":"Travel Agent",
            "type":"Entertainment"
        }
    ],
    "sg:phone":"+1 847 677 2021",
    "sg:postcode":"60076",
    "sg:province":"IL",
    "sg:tags":[
        "agency",
        "services-commercial"
    ],
    "wof:name":"Aero Travel",
    "wof:placetype":"venue"
},
  "geometry": {"coordinates":[-87.72792099999999,42.033569],"type":"Point"}
}