{
  "type": "Feature",
  "properties": {
    "iso:country":"US",
    "sg:address":"1245 Berry Ln",
    "sg:city":"Flossmoor",
    "sg:classifiers":[
        {
            "category":"Banks & Credit Unions",
            "subcategory":"Financial Services",
            "type":"Services"
        }
    ],
    "sg:phone":"+1 708 799 7332",
    "sg:postcode":"60422",
    "sg:province":"IL",
    "sg:tags":[
        "investment",
        "closed"
    ],
    "wof:name":"I Himmel & Sons Inc",
    "wof:placetype":"venue"
},
  "geometry": {"coordinates":[-87.686281,41.540056],"type":"Point"}
}