{
  "type": "Feature",
  "properties": {
    "iso:country":"US",
    "sg:address":"8140 S Burnham Ave",
    "sg:city":"Chicago",
    "sg:classifiers":[
        {
            "category":"Autos & Motor Vehicles",
            "subcategory":"Automobile Sales",
            "type":"Retail Goods"
        }
    ],
    "sg:phone":"+1 773 731 7446",
    "sg:postcode":"60617",
    "sg:province":"IL",
    "sg:tags":[
        "limo"
    ],
    "wof:name":"Superman",
    "wof:placetype":"venue"
},
  "geometry": {"coordinates":[-87.556566,41.74747],"type":"Point"}
}