{
  "type": "Feature",
  "properties": {
    "addr:full":"415 N La Salle Dr Chicago IL 60610",
    "addr:housenumber":"415",
    "addr:postcode":"60610",
    "addr:street":"N La Salle Dr",
    "iso:country":"US",
    "sg:address":"415 N La Salle Dr",
    "sg:city":"Chicago",
    "sg:classifiers":[
        {
            "category":"Professional",
            "subcategory":"Lawyer & Legal Services",
            "type":"Services"
        }
    ],
    "sg:phone":"+1 312 527 1100",
    "sg:postcode":"60610",
    "sg:province":"IL",
    "wof:name":"Adinamis James D Law Offices of",
    "wof:placetype":"venue"
},
  "geometry": {"coordinates":[-87.632401,41.889702],"type":"Point"}
}