{
  "type": "Feature",
  "properties": {
    "iso:country":"US",
    "sg:address":"7169 Farmhome Ln",
    "sg:city":"Cherry Valley",
    "sg:classifiers":[
        {
            "category":"Building & Trades",
            "subcategory":"Construction",
            "type":"Services"
        }
    ],
    "sg:phone":"+1 815 332 7612",
    "sg:postcode":"61016",
    "sg:province":"IL",
    "sg:tags":[
        "home",
        "improvement"
    ],
    "wof:name":"Joe's Minor Household Repair",
    "wof:placetype":"venue"
},
  "geometry": {"coordinates":[-88.97317,42.226185],"type":"Point"}
}