{
  "type": "Feature",
  "properties": {
    "addr:full":"100 W Randolph St Chicago IL 60601",
    "addr:housenumber":"100",
    "addr:postcode":"60601",
    "addr:street":"W Randolph St",
    "iso:country":"US",
    "sg:address":"100 W Randolph St",
    "sg:city":"Chicago",
    "sg:classifiers":[
        {
            "category":"Restaurant",
            "type":"Food & Drink"
        }
    ],
    "sg:phone":"+1 312 558 1117",
    "sg:postcode":"60601",
    "sg:province":"IL",
    "sg:tags":[
        "sushi",
        "bar",
        "japanese"
    ],
    "sg:website":"tokyolunchboxncatering.com",
    "wof:name":"Tokyo Lunch Boxes & Catering",
    "wof:placetype":"venue"
},
  "geometry": {"coordinates":[-87.631643,41.885271],"type":"Point"}
}