{
  "type": "Feature",
  "properties": {
    "iso:country":"US",
    "sg:address":"1203 Hidden Spring Dr",
    "sg:city":"Naperville",
    "sg:classifiers":[
        {
            "category":"Manufacturing",
            "subcategory":"Retail Goods",
            "type":"Manufacturing & Wholesale Goods"
        }
    ],
    "sg:phone":"+1 630 428 1515",
    "sg:postcode":"60540",
    "sg:province":"IL",
    "sg:tags":[
        "giftware's-wholesale",
        "manufacturer"
    ],
    "wof:name":"Rick Belle",
    "wof:placetype":"venue"
},
  "geometry": {"coordinates":[-88.17417,41.777238],"type":"Point"}
}