{
  "type": "Feature",
  "properties": {
    "iso:country":"US",
    "sg:address":"243 Flagg St",
    "sg:city":"Paw Paw",
    "sg:classifiers":[
        {
            "category":"Freight",
            "type":"Transportation"
        }
    ],
    "sg:phone":"+1 815 627 2071",
    "sg:postcode":"61353",
    "sg:province":"IL",
    "sg:tags":[
        "grain",
        "elevator"
    ],
    "wof:name":"Paw Paw Co-Op Grain Co",
    "wof:placetype":"venue"
},
  "geometry": {"coordinates":[-88.983393,41.687235],"type":"Point"}
}