{
  "type": "Feature",
  "properties": {
    "iso:country":"US",
    "sg:address":"2241 Madison Ave",
    "sg:city":"Granite City",
    "sg:classifiers":[
        {
            "category":"Bakery",
            "type":"Food & Drink"
        },
        {
            "category":"Insurance",
            "subcategory":"Health Insurance",
            "type":"Services"
        },
        {
            "category":"Donuts",
            "subcategory":"None",
            "type":"Food & Drink"
        }
    ],
    "sg:phone":"+1 618 876 1952",
    "sg:postcode":"62040",
    "sg:province":"IL",
    "sg:tags":[
        "market"
    ],
    "wof:name":"Seibold's Mrs Bake Shop",
    "wof:placetype":"venue"
},
  "geometry": {"coordinates":[-90.14119700000001,38.703899],"type":"Point"}
}