{
  "type": "Feature",
  "properties": {
    "iso:country":"US",
    "sg:address":"128 S Vine St",
    "sg:city":"Arthur",
    "sg:classifiers":[
        {
            "category":"Restaurant",
            "type":"Food & Drink"
        }
    ],
    "sg:phone":"+1 217 543 2332",
    "sg:postcode":"61911",
    "sg:province":"IL",
    "wof:name":"Berg",
    "wof:placetype":"venue"
},
  "geometry": {"coordinates":[-88.472365,39.716646],"type":"Point"}
}