{
  "type": "Feature",
  "properties": {
    "iso:country":"US",
    "sg:address":"2120 W Jefferson St",
    "sg:city":"Joliet",
    "sg:classifiers":[
        {
            "category":"Personal",
            "subcategory":"Beauty Salon",
            "type":"Services"
        }
    ],
    "sg:phone":"+1 815 729 9995",
    "sg:postcode":"60435",
    "sg:province":"IL",
    "sg:tags":[
        "manicuring"
    ],
    "wof:name":"Us Nails",
    "wof:placetype":"venue"
},
  "geometry": {"coordinates":[-88.135269,41.522286],"type":"Point"}
}