{
  "type": "Feature",
  "properties": {
    "iso:country":"US",
    "sg:address":"18709 Springfield Ave",
    "sg:city":"Flossmoor",
    "sg:classifiers":[
        {
            "category":"Building & Trades",
            "subcategory":"Construction",
            "type":"Services"
        }
    ],
    "sg:phone":"+1 708 799 2090",
    "sg:postcode":"60422",
    "sg:province":"IL",
    "sg:tags":[
        "contractor"
    ],
    "wof:name":"Affordable Gutters Service Inc",
    "wof:placetype":"venue"
},
  "geometry": {"coordinates":[-87.710943,41.548093],"type":"Point"}
}