{
  "type": "Feature",
  "properties": {
    "iso:country":"US",
    "sg:address":"2100 W Warren Blvd",
    "sg:city":"Chicago",
    "sg:classifiers":[
        {
            "category":"Social Services",
            "type":"Services"
        },
        {
            "category":"Building & Trades",
            "subcategory":"Landscaping Services",
            "type":"Services"
        }
    ],
    "sg:phone":"+1 312 738 1414",
    "sg:postcode":"60612",
    "sg:province":"IL",
    "sg:tags":[
        "aged",
        "homes-institutional"
    ],
    "wof:name":"Grace House",
    "wof:placetype":"venue"
},
  "geometry": {"coordinates":[-87.67910000000001,41.882198],"type":"Point"}
}