{
  "type": "Feature",
  "properties": {
    "iso:country":"US",
    "sg:address":"38 S Lake Rd",
    "sg:city":"Lincoln",
    "sg:classifiers":[
        {
            "category":"Building & Trades",
            "subcategory":"Construction",
            "type":"Services"
        }
    ],
    "sg:phone":"+1 217 314 0511",
    "sg:postcode":"62656",
    "sg:province":"IL",
    "sg:tags":[
        "downspouts",
        "gutter"
    ],
    "wof:name":"A-1 Seamless Gutters",
    "wof:placetype":"venue"
},
  "geometry": {"coordinates":[-89.379867,40.126788],"type":"Point"}
}