{
  "type": "Feature",
  "properties": {
    "addr:full":"934 Waterford Ln Northbrook IL 60062",
    "addr:housenumber":"934",
    "addr:postcode":"60062",
    "addr:street":"Waterford Ln",
    "iso:country":"US",
    "sg:address":"934 Waterford Ln",
    "sg:city":"Northbrook",
    "sg:classifiers":[
        {
            "category":"Shopping",
            "subcategory":"Shoes",
            "type":"Retail Goods"
        }
    ],
    "sg:phone":"+1   ",
    "sg:postcode":"60062",
    "sg:province":"IL",
    "wof:name":"Bcl Footwear",
    "wof:placetype":"venue"
},
  "geometry": {"coordinates":[-87.801213,42.114175],"type":"Point"}
}