{
  "type": "Feature",
  "properties": {
    "iso:country":"US",
    "sg:address":"150 N Michigan Ave",
    "sg:city":"Chicago",
    "sg:classifiers":[
        {
            "category":"Professional",
            "subcategory":"Business Services",
            "type":"Services"
        }
    ],
    "sg:phone":"+1 312 781 6222",
    "sg:postcode":"60601",
    "sg:province":"IL",
    "sg:tags":[
        "international",
        "consultant",
        "trade"
    ],
    "sg:website":"http://www.swedishtrade.se",
    "wof:name":"Swedish Trade Council",
    "wof:placetype":"venue"
},
  "geometry": {"coordinates":[-87.62442799999999,41.88446],"type":"Point"}
}