{
  "type": "Feature",
  "properties": {
    "iso:country":"US",
    "sg:address":"689 Avenue of the Cities",
    "sg:city":"East Moline",
    "sg:classifiers":[
        {
            "category":"Restaurant",
            "type":"Food & Drink"
        }
    ],
    "sg:phone":"+1 309 755 6957",
    "sg:postcode":"61244",
    "sg:province":"IL",
    "wof:name":"Maid Rite",
    "wof:placetype":"venue"
},
  "geometry": {"coordinates":[-90.44560199999999,41.489899],"type":"Point"}
}