{
  "type": "Feature",
  "properties": {
    "iso:country":"US",
    "sg:address":"6017 51st Ave",
    "sg:city":"Moline",
    "sg:classifiers":[
        {
            "category":"Home & Garden",
            "subcategory":"Building Materials",
            "type":"Retail Goods"
        },
        {
            "category":"Building & Trades",
            "subcategory":"Construction",
            "type":"Services"
        }
    ],
    "sg:phone":"+1 309 764 8672",
    "sg:postcode":"61265",
    "sg:province":"IL",
    "sg:tags":[
        "industrial",
        "chimneys-prefabricated",
        "mason",
        "contractors-commercial",
        "masonry",
        "contractor",
        "chimney"
    ],
    "wof:name":"Parks & Parks & Sons Masonry",
    "wof:placetype":"venue"
},
  "geometry": {"coordinates":[-90.45610499999999,41.462617],"type":"Point"}
}