{
  "type": "Feature",
  "properties": {
    "addr:full":"600 N Michigan Ave Lowr 3 Chicago IL 60611",
    "addr:housenumber":"600;3",
    "addr:postcode":"60611",
    "addr:street":"N Michigan Ave Lowr",
    "iso:country":"US",
    "sg:address":"600 N Michigan Ave Lowr 3",
    "sg:city":"Chicago",
    "sg:classifiers":[
        {
            "category":"Home & Garden",
            "subcategory":"Furniture",
            "type":"Retail Goods"
        }
    ],
    "sg:phone":"+1 312 787 3358",
    "sg:postcode":"60611",
    "sg:province":"IL",
    "sg:tags":[
        "store"
    ],
    "wof:name":"Home Element",
    "wof:placetype":"venue"
},
  "geometry": {"coordinates":[-87.624444,41.892557],"type":"Point"}
}