{
  "type": "Feature",
  "properties": {
    "iso:country":"US",
    "sg:address":"2215 N Seminary Ave",
    "sg:city":"Chicago",
    "sg:classifiers":[
        {
            "category":"Professional",
            "subcategory":"Business Services",
            "type":"Services"
        }
    ],
    "sg:phone":"+1 773 477 0634",
    "sg:postcode":"60614",
    "sg:province":"IL",
    "sg:tags":[
        "broker"
    ],
    "sg:website":"http://www.autoadvantage1.com",
    "wof:name":"Auto Advantage Corporation",
    "wof:placetype":"venue"
},
  "geometry": {"coordinates":[-87.655867,41.921926],"type":"Point"}
}