{
  "type": "Feature",
  "properties": {
    "iso:country":"US",
    "sg:address":"7645 Nottingham Dr",
    "sg:city":"Tinley Park",
    "sg:classifiers":[
        {
            "category":"Professional",
            "subcategory":"Business Services",
            "type":"Services"
        }
    ],
    "sg:phone":"+1 708 557 5614",
    "sg:postcode":"60477",
    "sg:province":"IL",
    "wof:name":"Scat Design LLC",
    "wof:placetype":"venue"
},
  "geometry": {"coordinates":[-87.805438,41.593068],"type":"Point"}
}