{
  "type": "Feature",
  "properties": {
    "addr:full":"1024 S Cypress Dr Mount Prospect IL 60056",
    "addr:housenumber":"1024",
    "addr:postcode":"60056",
    "addr:street":"S Cypress Dr",
    "iso:country":"US",
    "sg:address":"1024 S Cypress Dr",
    "sg:city":"Mount Prospect",
    "sg:classifiers":[
        {
            "category":"Professional",
            "subcategory":"Engineering",
            "type":"Services"
        }
    ],
    "sg:phone":"+1 847 364 6453",
    "sg:postcode":"60056",
    "sg:province":"IL",
    "sg:tags":[
        "consulting",
        "for",
        "power",
        "eng",
        "industry",
        "supply",
        "equipment",
        "con"
    ],
    "wof:name":"Ebill Inc",
    "wof:placetype":"venue"
},
  "geometry": {"coordinates":[-87.95265999999999,42.045115],"type":"Point"}
}