{
  "type": "Feature",
  "properties": {
    "addr:full":"1829 N Newcastle Ave Chicago IL 60707",
    "addr:housenumber":"1829",
    "addr:postcode":"60707",
    "addr:street":"N Newcastle Ave",
    "iso:country":"US",
    "sg:address":"1829 N Newcastle Ave",
    "sg:city":"Chicago",
    "sg:classifiers":[
        {
            "category":"Social Services",
            "subcategory":"Child Care",
            "type":"Services"
        }
    ],
    "sg:phone":"+1 773 622 7559",
    "sg:postcode":"60707",
    "sg:province":"IL",
    "sg:tags":[
        "day"
    ],
    "wof:name":"ABC Toon Town",
    "wof:placetype":"venue"
},
  "geometry": {"coordinates":[-87.79584800000001,41.913208],"type":"Point"}
}