{
  "type": "Feature",
  "properties": {
    "addr:full":"2132 S 60th Ct Cicero IL 60804",
    "addr:housenumber":"2132",
    "addr:postcode":"60804",
    "addr:street":"S 60Th Ct",
    "iso:country":"US",
    "sg:address":"2132 S 60th Ct",
    "sg:city":"Cicero",
    "sg:classifiers":[
        {
            "category":"Personal",
            "subcategory":"Beauty Salon",
            "type":"Services"
        }
    ],
    "sg:phone":"+1 708 656 4247",
    "sg:postcode":"60804",
    "sg:province":"IL",
    "sg:tags":[
        "shop"
    ],
    "wof:name":"Club Beverly Hills Hair Studio",
    "wof:placetype":"venue"
},
  "geometry": {"coordinates":[-87.77504399999999,41.851453],"type":"Point"}
}