{
  "type": "Feature",
  "properties": {
    "addr:full":"1760 College Ln S Wheaton IL 60189",
    "addr:housenumber":"1760",
    "addr:postcode":"60189",
    "addr:street":"College Ln",
    "iso:country":"US",
    "sg:address":"1760 College Ln S",
    "sg:city":"Wheaton",
    "sg:classifiers":[
        {
            "category":"Wholesale",
            "subcategory":"Books, Periodicals, & Newspapers",
            "type":"Manufacturing & Wholesale Goods"
        }
    ],
    "sg:phone":"+1 630 260 9233",
    "sg:postcode":"60189",
    "sg:province":"IL",
    "sg:tags":[
        "publisher",
        "book"
    ],
    "wof:name":"Freelance Academy Press Inc",
    "wof:placetype":"venue"
},
  "geometry": {"coordinates":[-88.08216400000001,41.830832],"type":"Point"}
}