{
  "type": "Feature",
  "properties": {
    "iso:country":"US",
    "sg:address":"1901 E Voorhees St",
    "sg:city":"Danville",
    "sg:classifiers":[
        {
            "category":"Professional",
            "subcategory":"Accounting & Tax Preparation",
            "type":"Services"
        }
    ],
    "sg:phone":"+1 217 477 1454",
    "sg:postcode":"61832",
    "sg:province":"IL",
    "wof:name":"Prg-Schultz International",
    "wof:placetype":"venue"
},
  "geometry": {"coordinates":[-87.58653,40.146869],"type":"Point"}
}