{
  "type": "Feature",
  "properties": {
    "addr:full":"5100 Dempster St Skokie IL 60077",
    "addr:housenumber":"5100",
    "addr:postcode":"60077",
    "addr:street":"Dempster St",
    "iso:country":"US",
    "sg:address":"5100 Dempster St",
    "sg:city":"Skokie",
    "sg:classifiers":[
        {
            "category":"Wholesale",
            "subcategory":"Dairy",
            "type":"Manufacturing & Wholesale Goods"
        }
    ],
    "sg:phone":"+1 847 674 4205",
    "sg:postcode":"60077",
    "sg:province":"IL",
    "sg:tags":[
        "distributor",
        "cheese",
        "gourmet",
        "food",
        "specialty"
    ],
    "wof:name":"Crossroads Trading Company",
    "wof:placetype":"venue"
},
  "geometry": {"coordinates":[-87.756062,42.040839],"type":"Point"}
}