{
  "type": "Feature",
  "properties": {
    "iso:country":"US",
    "sg:address":"3825 N Vermilion St",
    "sg:city":"Danville",
    "sg:classifiers":[
        {
            "category":"Organizations",
            "subcategory":"Religious Organization",
            "type":"Services"
        }
    ],
    "sg:phone":"+1 217 443 3448",
    "sg:postcode":"61832",
    "sg:province":"IL",
    "sg:tags":[
        "church"
    ],
    "wof:name":"Seventh-Day Adventist Church",
    "wof:placetype":"venue"
},
  "geometry": {"coordinates":[-87.63060900000001,40.1729],"type":"Point"}
}