{
  "type": "Feature",
  "properties": {
    "addr:full":"1915 N Harlem Ave Chicago IL 60707",
    "addr:housenumber":"1915",
    "addr:postcode":"60707",
    "addr:street":"N Harlem Ave",
    "iso:country":"US",
    "sg:address":"1915 N Harlem Ave",
    "sg:city":"Chicago",
    "sg:classifiers":[
        {
            "category":"Professional",
            "subcategory":"Lawyer & Legal Services",
            "type":"Services"
        }
    ],
    "sg:phone":"+1 773 309 6650",
    "sg:postcode":"60707",
    "sg:province":"IL",
    "wof:name":"Townsend Tom Attorney",
    "wof:placetype":"venue"
},
  "geometry": {"coordinates":[-87.80573,41.914607],"type":"Point"}
}