{
  "type": "Feature",
  "properties": {
    "iso:country":"US",
    "sg:address":"810 N Vaughn Dr",
    "sg:city":"Kankakee",
    "sg:classifiers":[
        {
            "category":"Organizations",
            "subcategory":"Membership Organization",
            "type":"Services"
        }
    ],
    "sg:phone":"+1 815 933 5828",
    "sg:postcode":"60901",
    "sg:province":"IL",
    "wof:name":"National Exchange Club",
    "wof:placetype":"venue"
},
  "geometry": {"coordinates":[-87.896081,41.133143],"type":"Point"}
}