{
  "type": "Feature",
  "properties": {
    "addr:full":"1408 Joliet Rd Romeoville IL 60446",
    "addr:housenumber":"1408",
    "addr:postcode":"60446",
    "addr:street":"Joliet Rd",
    "iso:country":"US",
    "sg:address":"1408 Joliet Rd",
    "sg:city":"Romeoville",
    "sg:classifiers":[
        {
            "category":"Freight",
            "type":"Transportation"
        }
    ],
    "sg:phone":"+1 630 719 9077",
    "sg:postcode":"60446",
    "sg:province":"IL",
    "sg:tags":[
        "arrangement"
    ],
    "wof:name":"Exel Transportation Services",
    "wof:placetype":"venue"
},
  "geometry": {"coordinates":[-88.055357,41.677235],"type":"Point"}
}