{
  "type": "Feature",
  "properties": {
    "iso:country":"US",
    "sg:address":"360 Walnut Hill Rd",
    "sg:city":"Centralia",
    "sg:classifiers":[
        {
            "category":"Freight",
            "type":"Transportation"
        }
    ],
    "sg:phone":"+1 618 533 0035",
    "sg:postcode":"62801",
    "sg:province":"IL",
    "sg:tags":[
        "courier"
    ],
    "sg:website":"www.ups.com",
    "wof:name":"UPS",
    "wof:placetype":"venue"
},
  "geometry": {"coordinates":[-89.125202,38.504222],"type":"Point"}
}