{
  "type": "Feature",
  "properties": {
    "iso:country":"US",
    "sg:address":"2020 Calamos Ct",
    "sg:city":"Naperville",
    "sg:classifiers":[
        {
            "category":"Real Estate",
            "subcategory":"Real Estate Services",
            "type":"Services"
        }
    ],
    "sg:phone":"+1 630 245 7200",
    "sg:postcode":"60563",
    "sg:province":"IL",
    "sg:tags":[
        "commercial"
    ],
    "wof:name":"Citygate Centre I",
    "wof:placetype":"venue"
},
  "geometry": {"coordinates":[-88.202141,41.805802],"type":"Point"}
}