{
  "type": "Feature",
  "properties": {
    "iso:country":"US",
    "sg:address":"401 N Main St",
    "sg:city":"Rochelle",
    "sg:classifiers":[
        {
            "category":"Professional",
            "subcategory":"Computer Services",
            "type":"Services"
        }
    ],
    "sg:phone":"+1 815 562 1885",
    "sg:postcode":"61068",
    "sg:province":"IL",
    "sg:tags":[
        "internet"
    ],
    "wof:name":"Inwave Internet",
    "wof:placetype":"venue"
},
  "geometry": {"coordinates":[-89.06511399999999,41.922453],"type":"Point"}
}