{
  "type": "Feature",
  "properties": {
    "addr:full":"4700 Old Oaks Dr Lisle IL 60532",
    "addr:housenumber":"4700",
    "addr:postcode":"60532",
    "addr:street":"Old Oaks Dr",
    "iso:country":"US",
    "sg:address":"4700 Old Oaks Dr",
    "sg:city":"Lisle",
    "sg:classifiers":[
        {
            "category":"Building & Trades",
            "subcategory":"Construction",
            "type":"Services"
        }
    ],
    "sg:phone":"+1 630 674 1159",
    "sg:postcode":"60532",
    "sg:province":"IL",
    "sg:tags":[
        "floor",
        "laying",
        "contractor"
    ],
    "wof:name":"P & J Flooring",
    "wof:placetype":"venue"
},
  "geometry": {"coordinates":[-88.10672700000001,41.797821],"type":"Point"}
}