{
  "type": "Feature",
  "properties": {
    "iso:country":"US",
    "sg:address":"3258 Quincy Mall",
    "sg:city":"Quincy",
    "sg:classifiers":[
        {
            "category":"Shopping",
            "subcategory":"Gifts & Souvenirs",
            "type":"Retail Goods"
        }
    ],
    "sg:phone":"+1 217 223 4222",
    "sg:postcode":"62301",
    "sg:province":"IL",
    "sg:tags":[
        "shop",
        "novelty"
    ],
    "wof:name":"Fadz",
    "wof:placetype":"venue"
},
  "geometry": {"coordinates":[-91.363418,39.935801],"type":"Point"}
}