{
  "type": "Feature",
  "properties": {
    "addr:full":"1051 E Co Rd 1900 Nauvoo IL 62354",
    "addr:housenumber":"1051",
    "addr:postcode":"1900;62354",
    "addr:street":"E Co Rd",
    "iso:country":"US",
    "sg:address":"1051 E Co Rd 1900",
    "sg:city":"Nauvoo",
    "sg:phone":"+1 217 453 6693",
    "sg:postcode":"62354",
    "sg:province":"IL",
    "sg:tags":[
        "wheat",
        "farm",
        "corn",
        "crop",
        "field",
        "soybean"
    ],
    "wof:name":"W Lavern Bolton",
    "wof:placetype":"venue"
},
  "geometry": {"coordinates":[-91.290133,40.477646],"type":"Point"}
}