{
  "type": "Feature",
  "properties": {
    "addr:full":"7269 S Harlem Ave Bridgeview IL 60455",
    "addr:housenumber":"7269",
    "addr:postcode":"60455",
    "addr:street":"S Harlem Ave",
    "iso:country":"US",
    "sg:address":"7269 S Harlem Ave",
    "sg:city":"Bridgeview",
    "sg:classifiers":[
        {
            "category":"Personal",
            "subcategory":"Tattoo Parlor",
            "type":"Services"
        }
    ],
    "sg:phone":"+1 708 496 8282",
    "sg:postcode":"60455",
    "sg:province":"IL",
    "sg:website":"www.firehousetattoos.com",
    "wof:name":"Firehouse Tattoos",
    "wof:placetype":"venue"
},
  "geometry": {"coordinates":[-87.800023,41.759569],"type":"Point"}
}