{
  "type": "Feature",
  "properties": {
    "addr:full":"44 Devonwood Ave Romeoville IL 60446",
    "addr:housenumber":"44",
    "addr:postcode":"60446",
    "addr:street":"Devonwood Ave",
    "iso:country":"US",
    "sg:address":"44 Devonwood Ave",
    "sg:city":"Romeoville",
    "sg:classifiers":[
        {
            "category":"Home & Garden",
            "subcategory":"Building Materials",
            "type":"Retail Goods"
        },
        {
            "category":"Mining & Drilling",
            "type":"Manufacturing & Wholesale Goods"
        }
    ],
    "sg:phone":"+1 815 886 3906",
    "sg:postcode":"60446",
    "sg:province":"IL",
    "sg:tags":[
        "steel",
        "stone",
        "structural"
    ],
    "wof:name":"Galassi Gary Stone & Steel",
    "wof:placetype":"venue"
},
  "geometry": {"coordinates":[-88.079185,41.654587],"type":"Point"}
}