{
  "type": "Feature",
  "properties": {
    "addr:full":"1123 N Ashland Ave Chicago IL 60622",
    "addr:housenumber":"1123",
    "addr:postcode":"60622",
    "addr:street":"N Ashland Ave",
    "iso:country":"US",
    "sg:address":"1123 N Ashland Ave",
    "sg:city":"Chicago",
    "sg:classifiers":[
        {
            "category":"Sports & Exercise",
            "subcategory":"Playing Field",
            "type":"Entertainment"
        }
    ],
    "sg:phone":"+1 773 252 7443",
    "sg:postcode":"60622",
    "sg:province":"IL",
    "sg:tags":[
        "chi",
        "tai"
    ],
    "sg:website":"www.stirlingtaichi.com",
    "wof:name":"Stirling's Wu Kung Tai Chi Society",
    "wof:placetype":"venue"
},
  "geometry": {"coordinates":[-87.667503,41.902],"type":"Point"}
}