{
  "type": "Feature",
  "properties": {
    "iso:country":"US",
    "sg:address":"3649 173rd Ct",
    "sg:city":"Lansing",
    "sg:classifiers":[
        {
            "category":"Real Estate",
            "subcategory":"Real Estate Operator",
            "type":"Services"
        }
    ],
    "sg:phone":"+1 877 510 2608",
    "sg:postcode":"60438",
    "sg:province":"IL",
    "sg:tags":[
        "apartment"
    ],
    "sg:website":"http://local.ingenio.com/Listings/Details.aspx?NUM=a%3a10307021%3a13%3a4859924%3a14%3a0%3a7",
    "wof:name":"Riverwood Apartment Homes",
    "wof:placetype":"venue"
},
  "geometry": {"coordinates":[-87.528659,41.579609],"type":"Point"}
}