{
  "type": "Feature",
  "properties": {
    "iso:country":"US",
    "sg:address":"6614 Barrington Rd",
    "sg:city":"Bartlett",
    "sg:classifiers":[
        {
            "category":"Shopping",
            "subcategory":"Department Store",
            "type":"Retail Goods"
        }
    ],
    "sg:phone":"+1   ",
    "sg:postcode":"60133",
    "sg:province":"IL",
    "wof:name":"Dollar Store The",
    "wof:placetype":"venue"
},
  "geometry": {"coordinates":[-88.144946,41.993447],"type":"Point"}
}