{
  "type": "Feature",
  "properties": {
    "addr:full":"3451 W Irving Park Rd Chicago IL 60618",
    "addr:housenumber":"3451",
    "addr:postcode":"60618",
    "addr:street":"W Irving Park Rd",
    "iso:country":"US",
    "sg:address":"3451 W Irving Park Rd",
    "sg:city":"Chicago",
    "sg:classifiers":[
        {
            "category":"Health Services",
            "subcategory":"Dentist",
            "type":"Services"
        }
    ],
    "sg:phone":"+1 773 588 4650",
    "sg:postcode":"60618",
    "sg:province":"IL",
    "sg:website":"greatsmilesdc.com/",
    "wof:name":"Great Smiles Dental Center Ltd",
    "wof:placetype":"venue"
},
  "geometry": {"coordinates":[-87.714906,41.953522],"type":"Point"}
}