{
  "type": "Feature",
  "properties": {
    "iso:country":"US",
    "sg:address":"411 Cherry Ave",
    "sg:city":"Rochelle",
    "sg:classifiers":[
        {
            "category":"Bars & Pubs",
            "type":"Food & Drink"
        }
    ],
    "sg:phone":"+1 815 562 6568",
    "sg:postcode":"61068",
    "sg:province":"IL",
    "sg:tags":[
        "drinking"
    ],
    "wof:name":"Chisums Lounge Inc",
    "wof:placetype":"venue"
},
  "geometry": {"coordinates":[-89.065199,41.922215],"type":"Point"}
}