{
  "type": "Feature",
  "properties": {
    "iso:country":"US",
    "sg:address":"810 S Longview Rd",
    "sg:city":"Monticello",
    "sg:classifiers":[
        {
            "category":"Organizations",
            "subcategory":"Community Association",
            "type":"Services"
        }
    ],
    "sg:phone":"+1 217 762 2265",
    "sg:postcode":"61856",
    "sg:province":"IL",
    "wof:name":"International Assoc of LI",
    "wof:placetype":"venue"
},
  "geometry": {"coordinates":[-88.568152,40.019377],"type":"Point"}
}