{
  "type": "Feature",
  "properties": {
    "addr:full":"2426 W Roosevelt Rd Chicago IL 60608",
    "addr:housenumber":"2426",
    "addr:postcode":"60608",
    "addr:street":"W Roosevelt Rd",
    "iso:country":"US",
    "sg:address":"2426 W Roosevelt Rd",
    "sg:city":"Chicago",
    "sg:classifiers":[
        {
            "category":"Professional",
            "subcategory":"Accounting & Tax Preparation",
            "type":"Services"
        }
    ],
    "sg:phone":"+1 773 309 4814",
    "sg:postcode":"60608",
    "sg:province":"IL",
    "sg:tags":[
        "bookkeeping",
        "return",
        "representative",
        "preparation-business",
        "taxes-consultants"
    ],
    "sg:website":"http://www.jacksonhewitt.com/",
    "wof:name":"Jackson Hewitt Tax Service",
    "wof:placetype":"venue"
},
  "geometry": {"coordinates":[-87.686729,41.866619],"type":"Point"}
}