{
  "type": "Feature",
  "properties": {
    "iso:country":"US",
    "sg:address":"2406 S Lowden Rd",
    "sg:city":"Oregon",
    "sg:classifiers":[
        {
            "category":"Professional",
            "subcategory":"Business Services",
            "type":"Services"
        }
    ],
    "sg:phone":"+1 815 732 2840",
    "sg:postcode":"61061",
    "sg:province":"IL",
    "sg:tags":[
        "auctioneer"
    ],
    "wof:name":"Mattison Auctioneering",
    "wof:placetype":"venue"
},
  "geometry": {"coordinates":[-89.317791,41.981788],"type":"Point"}
}