{
  "type": "Feature",
  "properties": {
    "addr:full":"1443 W Schaumburg Rd Schaumburg IL 60194",
    "addr:housenumber":"1443",
    "addr:postcode":"60194",
    "addr:street":"W Schaumburg Rd",
    "iso:country":"US",
    "sg:address":"1443 W Schaumburg Rd",
    "sg:city":"Schaumburg",
    "sg:classifiers":[
        {
            "category":"Personal",
            "subcategory":"Barber",
            "type":"Services"
        }
    ],
    "sg:phone":"+1 847 895 9557",
    "sg:postcode":"60194",
    "sg:province":"IL",
    "wof:name":"Continental Hair Styling",
    "wof:placetype":"venue"
},
  "geometry": {"coordinates":[-88.12347699999999,42.025584],"type":"Point"}
}