{
  "type": "Feature",
  "properties": {
    "addr:full":"PO Box 299 Shipman IL 62685",
    "addr:housenumber":"po",
    "addr:postcode":"62685",
    "addr:street":"Box 299",
    "iso:country":"US",
    "sg:address":"PO Box 299",
    "sg:city":"Shipman",
    "sg:classifiers":[
        {
            "category":"Education",
            "subcategory":"School",
            "type":"Public Place"
        }
    ],
    "sg:phone":"+1 618 836 5535",
    "sg:postcode":"62685",
    "sg:province":"IL",
    "sg:tags":[
        "high",
        "middle",
        "elementary"
    ],
    "wof:name":"Southwestern Community Unit School District 9",
    "wof:placetype":"venue"
},
  "geometry": {"coordinates":[-90.035004,39.116798],"type":"Point"}
}