{
  "type": "Feature",
  "properties": {
    "addr:full":"2004 W 102nd St Chicago IL 60643",
    "addr:housenumber":"2004",
    "addr:postcode":"60643",
    "addr:street":"W 102Nd St",
    "iso:country":"US",
    "sg:address":"2004 W 102nd St",
    "sg:city":"Chicago",
    "sg:classifiers":[
        {
            "category":"Building & Trades",
            "subcategory":"Electrical",
            "type":"Services"
        }
    ],
    "sg:phone":"+1 773 233 9073",
    "sg:postcode":"60643",
    "sg:province":"IL",
    "sg:tags":[
        "electrical",
        "contractor"
    ],
    "wof:name":"Greene Electric Co Inc",
    "wof:placetype":"venue"
},
  "geometry": {"coordinates":[-87.671215,41.708133],"type":"Point"}
}