{
  "type": "Feature",
  "properties": {
    "iso:country":"US",
    "sg:address":"636 Hampshire St",
    "sg:city":"Quincy",
    "sg:classifiers":[
        {
            "category":"Health Services",
            "subcategory":"Doctor",
            "type":"Services"
        }
    ],
    "sg:phone":"+1 217 223 9400",
    "sg:postcode":"62301",
    "sg:province":"IL",
    "sg:tags":[
        "physician",
        "medical",
        "surgeon"
    ],
    "wof:name":"Zakiah S Ali MD",
    "wof:placetype":"venue"
},
  "geometry": {"coordinates":[-91.406176,39.933131],"type":"Point"}
}