{
  "type": "Feature",
  "properties": {
    "addr:full":"42 N Vermilion St Danville IL 61832",
    "addr:housenumber":"42",
    "addr:postcode":"61832",
    "addr:street":"N Vermilion St",
    "iso:country":"US",
    "sg:address":"42 N Vermilion St",
    "sg:city":"Danville",
    "sg:classifiers":[
        {
            "category":"Real Estate",
            "subcategory":"Real Estate Services",
            "type":"Services"
        }
    ],
    "sg:phone":"+1 217 442 3100",
    "sg:postcode":"61832",
    "sg:province":"IL",
    "sg:tags":[
        "abstract",
        "escrow",
        "title"
    ],
    "sg:website":"http://www.alliedtitleservices.com",
    "wof:name":"Allied Title Services Inc",
    "wof:placetype":"venue"
},
  "geometry": {"coordinates":[-87.62998,40.125212],"type":"Point"}
}