{
  "type": "Feature",
  "properties": {
    "iso:country":"US",
    "sg:address":"419 S Giant City Rd",
    "sg:city":"Carbondale",
    "sg:classifiers":[
        {
            "category":"Organizations",
            "subcategory":"Religious Organization",
            "type":"Services"
        }
    ],
    "sg:phone":"+1 618 529 2681",
    "sg:postcode":"62902",
    "sg:province":"IL",
    "wof:name":"Heartland Christian Center",
    "wof:placetype":"venue"
},
  "geometry": {"coordinates":[-89.185371,37.722645],"type":"Point"}
}