{
  "type": "Feature",
  "properties": {
    "iso:country":"US",
    "sg:address":"103 S Washington St",
    "sg:city":"Bartelso",
    "sg:classifiers":[
        {
            "category":"Home & Garden",
            "subcategory":"Household Appliances",
            "type":"Retail Goods"
        }
    ],
    "sg:phone":"+1 618 765 2243",
    "sg:postcode":"62218",
    "sg:province":"IL",
    "wof:name":"Varel's Store",
    "wof:placetype":"venue"
},
  "geometry": {"coordinates":[-89.466872,38.537233],"type":"Point"}
}