{
  "type": "Feature",
  "properties": {
    "addr:full":"1606 Willow View Rd Urbana IL 61802",
    "addr:housenumber":"1606",
    "addr:postcode":"61802",
    "addr:street":"Willow View Rd",
    "iso:country":"US",
    "sg:address":"1606 Willow View Rd",
    "sg:city":"Urbana",
    "sg:classifiers":[
        {
            "category":"Shopping",
            "subcategory":"Clothing, Apparel, & Fashions",
            "type":"Retail Goods"
        }
    ],
    "sg:phone":"+1   ",
    "sg:postcode":"61802",
    "sg:province":"IL",
    "wof:name":"Leadaz Intl Sportswear",
    "wof:placetype":"venue"
},
  "geometry": {"coordinates":[-88.192848,40.127469],"type":"Point"}
}