{
  "type": "Feature",
  "properties": {
    "addr:full":"16553 Haven Ave Tinley Park IL 60487",
    "addr:housenumber":"16553",
    "addr:postcode":"60487",
    "addr:street":"Haven Ave",
    "iso:country":"US",
    "sg:address":"16553 Haven Ave",
    "sg:city":"Tinley Park",
    "sg:classifiers":[
        {
            "category":"Recreation",
            "type":"Entertainment"
        }
    ],
    "sg:phone":"+1 708 226 1412",
    "sg:postcode":"60487",
    "sg:province":"IL",
    "wof:name":"Recreation Department",
    "wof:placetype":"venue"
},
  "geometry": {"coordinates":[-87.84378599999999,41.590467],"type":"Point"}
}