{
  "type": "Feature",
  "properties": {
    "addr:full":"2423 Main St Evanston IL 60202",
    "addr:housenumber":"2423",
    "addr:postcode":"60202",
    "addr:street":"Main St",
    "iso:country":"US",
    "sg:address":"2423 Main St",
    "sg:city":"Evanston",
    "sg:classifiers":[
        {
            "category":"Shopping",
            "subcategory":"Department Store",
            "type":"Retail Goods"
        }
    ],
    "sg:phone":"+1   ",
    "sg:postcode":"60202",
    "sg:province":"IL",
    "wof:name":"Sear 5182",
    "wof:placetype":"venue"
},
  "geometry": {"coordinates":[-87.708181,42.03376],"type":"Point"}
}