{
  "type": "Feature",
  "properties": {
    "addr:full":"4135 W 126th St Alsip IL 60803",
    "addr:housenumber":"4135",
    "addr:postcode":"60803",
    "addr:street":"W 126Th St",
    "iso:country":"US",
    "sg:address":"4135 W 126th St",
    "sg:city":"Alsip",
    "sg:classifiers":[
        {
            "category":"Real Estate",
            "subcategory":"Real Estate Services",
            "type":"Services"
        }
    ],
    "sg:phone":"+1 708 489 5940",
    "sg:postcode":"60803",
    "sg:province":"IL",
    "sg:tags":[
        "management",
        "property"
    ],
    "wof:name":"Vip Alsip II Llc",
    "wof:placetype":"venue"
},
  "geometry": {"coordinates":[-87.72304699999999,41.663431],"type":"Point"}
}