{
  "type": "Feature",
  "properties": {
    "addr:full":"10 W Elm St Ofc Chicago IL 60610",
    "addr:housenumber":"10",
    "addr:postcode":"60610",
    "addr:street":"W Elm St",
    "iso:country":"US",
    "sg:address":"10 W Elm St Ofc",
    "sg:city":"Chicago",
    "sg:classifiers":[
        {
            "category":"Building & Trades",
            "subcategory":"Cleaning & Sanitation",
            "type":"Services"
        }
    ],
    "sg:phone":"+1 312 379 0588",
    "sg:postcode":"60610",
    "sg:province":"IL",
    "sg:tags":[
        "cleaning-industrial",
        "contractor"
    ],
    "wof:name":"Press The Cleaners",
    "wof:placetype":"venue"
},
  "geometry": {"coordinates":[-87.628995,41.903165],"type":"Point"}
}