{
  "type": "Feature",
  "properties": {
    "iso:country":"US",
    "sg:address":"103 Prospect Ct",
    "sg:city":"Prospect Heights",
    "sg:classifiers":[
        {
            "category":"Organizations",
            "subcategory":"Membership Organization",
            "type":"Services"
        }
    ],
    "sg:phone":"+1 847 394 3344",
    "sg:postcode":"60070",
    "sg:province":"IL",
    "wof:name":"Les Maisons Condominium Assn",
    "wof:placetype":"venue"
},
  "geometry": {"coordinates":[-87.943936,42.097708],"type":"Point"}
}