{
  "type": "Feature",
  "properties": {
    "addr:full":"9121 Keeler Ave Skokie IL 60076",
    "addr:housenumber":"9121",
    "addr:postcode":"60076",
    "addr:street":"Keeler Ave",
    "iso:country":"US",
    "sg:address":"9121 Keeler Ave",
    "sg:city":"Skokie",
    "sg:classifiers":[
        {
            "category":"Wholesale",
            "subcategory":"Drugs",
            "type":"Manufacturing & Wholesale Goods"
        }
    ],
    "sg:phone":"+1 847 674 2670",
    "sg:postcode":"60076",
    "sg:province":"IL",
    "sg:tags":[
        "hair",
        "preparation"
    ],
    "wof:name":"Protege Corporation",
    "wof:placetype":"venue"
},
  "geometry": {"coordinates":[-87.73239,42.047165],"type":"Point"}
}