{
  "type": "Feature",
  "properties": {
    "addr:full":"6471 N Northwest Hwy Chicago IL 60631",
    "addr:housenumber":"6471",
    "addr:postcode":"60631",
    "addr:street":"N Northwest Hwy",
    "iso:country":"US",
    "sg:address":"6471 N Northwest Hwy",
    "sg:city":"Chicago",
    "sg:classifiers":[
        {
            "category":"Retail",
            "subcategory":"Funeral Services",
            "type":"Services"
        }
    ],
    "sg:phone":"+1 708 848 4332",
    "sg:postcode":"60631",
    "sg:province":"IL",
    "sg:tags":[
        "cemetery"
    ],
    "wof:name":"Burke-Sullivan Funeral Home",
    "wof:placetype":"venue"
},
  "geometry": {"coordinates":[-87.80909699999999,41.998199],"type":"Point"}
}