{
  "type": "Feature",
  "properties": {
    "iso:country":"US",
    "sg:address":"4030 177th St",
    "sg:city":"Country Club Hills",
    "sg:classifiers":[
        {
            "category":"Professional",
            "subcategory":"Business Services",
            "type":"Services"
        }
    ],
    "sg:phone":"+1 708 799 8862",
    "sg:postcode":"60478",
    "sg:province":"IL",
    "wof:name":"Sy-S Strs Recording",
    "wof:placetype":"venue"
},
  "geometry": {"coordinates":[-87.714872,41.568009],"type":"Point"}
}