{
  "type": "Feature",
  "properties": {
    "addr:full":"3710 Commercial Ave Northbrook IL 60062",
    "addr:housenumber":"3710",
    "addr:postcode":"60062",
    "addr:street":"Commercial Ave",
    "iso:country":"US",
    "sg:address":"3710 Commercial Ave",
    "sg:city":"Northbrook",
    "sg:classifiers":[
        {
            "category":"Professional",
            "subcategory":"Accounting & Tax Preparation",
            "type":"Services"
        }
    ],
    "sg:phone":"+1 847 564 8133",
    "sg:postcode":"60062",
    "sg:province":"IL",
    "wof:name":"Cutler Alan L CPA",
    "wof:placetype":"venue"
},
  "geometry": {"coordinates":[-87.872553,42.146678],"type":"Point"}
}