{
  "type": "Feature",
  "properties": {
    "iso:country":"US",
    "sg:address":"5849 N Christiana Ave",
    "sg:city":"Chicago",
    "sg:classifiers":[
        {
            "category":"Health Services",
            "subcategory":"Clinic",
            "type":"Services"
        }
    ],
    "sg:phone":"+1 773 583 1433",
    "sg:postcode":"60659",
    "sg:province":"IL",
    "sg:tags":[
        "home",
        "care"
    ],
    "wof:name":"M & D Healthcare Inc",
    "wof:placetype":"venue"
},
  "geometry": {"coordinates":[-87.71260599999999,41.987585],"type":"Point"}
}