{
  "type": "Feature",
  "properties": {
    "addr:full":"2051 Ash Chicago IL 60607",
    "addr:housenumber":"2051",
    "addr:postcode":"60607",
    "addr:street":"Ash",
    "iso:country":"US",
    "sg:address":"2051 Ash",
    "sg:city":"Chicago",
    "sg:classifiers":[
        {
            "category":"Real Estate",
            "subcategory":"Real Estate Operator",
            "type":"Services"
        }
    ],
    "sg:phone":"+1 847 824 6970",
    "sg:postcode":"60607",
    "sg:province":"IL",
    "sg:tags":[
        "apartment"
    ],
    "wof:name":"Park Lane Apartments",
    "wof:placetype":"venue"
},
  "geometry": {"coordinates":[-87.657501,41.873199],"type":"Point"}
}