{
  "type": "Feature",
  "properties": {
    "addr:full":"3310 W Roosevelt Rd Chicago IL 60624",
    "addr:housenumber":"3310",
    "addr:postcode":"60624",
    "addr:street":"W Roosevelt Rd",
    "iso:country":"US",
    "sg:address":"3310 W Roosevelt Rd",
    "sg:city":"Chicago",
    "sg:classifiers":[
        {
            "category":"Autos & Motor Vehicles",
            "subcategory":"Auto Supplies",
            "type":"Retail Goods"
        },
        {
            "category":"Wholesale",
            "subcategory":"Electrical",
            "type":"Manufacturing & Wholesale Goods"
        },
        {
            "category":"Wholesale",
            "subcategory":"Auto Parts",
            "type":"Manufacturing & Wholesale Goods"
        }
    ],
    "sg:phone":"+1 773 265 1960",
    "sg:postcode":"60624",
    "sg:province":"IL",
    "sg:tags":[
        "body",
        "battery",
        "automobile",
        "accessory",
        "equipment",
        "truck"
    ],
    "sg:website":"http://www.oreillyauto.com?utm_source=yellowpages&utm_medium=iyp&utm_campaign=3384",
    "wof:name":"O'Reilly Auto Parts",
    "wof:placetype":"venue"
},
  "geometry": {"coordinates":[-87.708331,41.866386],"type":"Point"}
}