{
  "type": "Feature",
  "properties": {
    "iso:country":"US",
    "sg:address":"726 S Milwaukee Ave",
    "sg:city":"Libertyville",
    "sg:classifiers":[
        {
            "category":"Personal",
            "subcategory":"Beauty Salon",
            "type":"Services"
        }
    ],
    "sg:phone":"+1 847 816 9120",
    "sg:postcode":"60048",
    "sg:province":"IL",
    "wof:name":"Lase Hair Studio",
    "wof:placetype":"venue"
},
  "geometry": {"coordinates":[-87.951597,42.274999],"type":"Point"}
}