{
  "type": "Feature",
  "properties": {
    "addr:full":"1230 Midwest Ln Wheaton IL 60187",
    "addr:housenumber":"1230",
    "addr:postcode":"60187",
    "addr:street":"Midwest Ln",
    "iso:country":"US",
    "sg:address":"1230 Midwest Ln",
    "sg:city":"Wheaton",
    "sg:classifiers":[
        {
            "category":"Professional",
            "subcategory":"Business Services",
            "type":"Services"
        }
    ],
    "sg:phone":"+1 630 682 9589",
    "sg:postcode":"60187",
    "sg:province":"IL",
    "wof:name":"Concepts West Inc",
    "wof:placetype":"venue"
},
  "geometry": {"coordinates":[-88.122125,41.849672],"type":"Point"}
}