{
  "type": "Feature",
  "properties": {
    "iso:country":"US",
    "sg:address":"174 McHenry Rd",
    "sg:city":"Buffalo Grove",
    "sg:classifiers":[
        {
            "category":"Shopping",
            "subcategory":"Books",
            "type":"Retail Goods"
        }
    ],
    "sg:phone":"+1   ",
    "sg:postcode":"60089",
    "sg:province":"IL",
    "sg:tags":[
        "comic",
        "retailing"
    ],
    "wof:name":"Hero Headquarters",
    "wof:placetype":"venue"
},
  "geometry": {"coordinates":[-87.959829,42.15681],"type":"Point"}
}