{
  "type": "Feature",
  "properties": {
    "addr:full":"1144 N Hoyne Ave Chicago IL 60622",
    "addr:housenumber":"1144",
    "addr:postcode":"60622",
    "addr:street":"N Hoyne Ave",
    "iso:country":"US",
    "sg:address":"1144 N Hoyne Ave",
    "sg:city":"Chicago",
    "sg:classifiers":[
        {
            "category":"Wholesale",
            "subcategory":"Poultry",
            "type":"Manufacturing & Wholesale Goods"
        },
        {
            "category":"Farming",
            "subcategory":"Livestock Farm",
            "type":"Manufacturing & Wholesale Goods"
        }
    ],
    "sg:phone":"+1 773 384 8645",
    "sg:postcode":"60622",
    "sg:province":"IL",
    "sg:tags":[
        "auction",
        "market"
    ],
    "wof:name":"Goat Island",
    "wof:placetype":"venue"
},
  "geometry": {"coordinates":[-87.679654,41.902387],"type":"Point"}
}