{
  "type": "Feature",
  "properties": {
    "addr:full":"1903 Gross St Evansville IL 62242",
    "addr:housenumber":"1903",
    "addr:postcode":"62242",
    "addr:street":"Gross St",
    "iso:country":"US",
    "sg:address":"1903 Gross St",
    "sg:city":"Evansville",
    "sg:classifiers":[
        {
            "category":"Government",
            "subcategory":"Office",
            "type":"Public Place"
        }
    ],
    "sg:phone":"+1 618 853 4412",
    "sg:postcode":"62242",
    "sg:province":"IL",
    "sg:tags":[
        "village"
    ],
    "wof:name":"Evansville Village Government",
    "wof:placetype":"venue"
},
  "geometry": {"coordinates":[-89.93256100000001,38.092839],"type":"Point"}
}