{
  "type": "Feature",
  "properties": {
    "iso:country":"US",
    "sg:address":"514 Prairie Ave",
    "sg:city":"Barrington",
    "sg:classifiers":[
        {
            "category":"Building & Trades",
            "subcategory":"Construction",
            "type":"Services"
        }
    ],
    "sg:phone":"+1 847 381 4746",
    "sg:postcode":"60010",
    "sg:province":"IL",
    "sg:tags":[
        "carpentry",
        "contractor"
    ],
    "wof:name":"Kurcab Brothers Carpentry Inc",
    "wof:placetype":"venue"
},
  "geometry": {"coordinates":[-88.128389,42.148843],"type":"Point"}
}