{
  "type": "Feature",
  "properties": {
    "addr:full":"3323 N Ridge Ave Arlington Heights IL 60004",
    "addr:housenumber":"3323",
    "addr:postcode":"60004",
    "addr:street":"N Ridge Ave",
    "iso:country":"US",
    "sg:address":"3323 N Ridge Ave",
    "sg:city":"Arlington Heights",
    "sg:classifiers":[
        {
            "category":"Organizations",
            "subcategory":"Religious Organization",
            "type":"Services"
        }
    ],
    "sg:phone":"+1 847 394 4405",
    "sg:postcode":"60004",
    "sg:province":"IL",
    "wof:name":"Interntnal Mnistries To Israel",
    "wof:placetype":"venue"
},
  "geometry": {"coordinates":[-87.991336,42.137294],"type":"Point"}
}