{
  "type": "Feature",
  "properties": {
    "iso:country":"US",
    "sg:address":"1000 W Prairie Ave",
    "sg:city":"Wheaton",
    "sg:classifiers":[
        {
            "category":"Education",
            "subcategory":"Dance Studio",
            "type":"Public Place"
        }
    ],
    "sg:phone":"+1 630 682 3600",
    "sg:postcode":"60187",
    "sg:province":"IL",
    "sg:tags":[
        "instruction",
        "dancing"
    ],
    "wof:name":"Moves A Dance & Fitness Studio",
    "wof:placetype":"venue"
},
  "geometry": {"coordinates":[-88.120525,41.876675],"type":"Point"}
}