{
  "type": "Feature",
  "properties": {
    "iso:country":"US",
    "sg:address":"28324 E Big Barn Rd",
    "sg:city":"Canton",
    "sg:classifiers":[
        {
            "category":"Building & Trades",
            "subcategory":"Construction",
            "type":"Services"
        }
    ],
    "sg:phone":"+1 309 647 8647",
    "sg:postcode":"61520",
    "sg:province":"IL",
    "sg:tags":[
        "house"
    ],
    "wof:name":"D & D Home Improvement",
    "wof:placetype":"venue"
},
  "geometry": {"coordinates":[-89.906137,40.582319],"type":"Point"}
}