{
  "type": "Feature",
  "properties": {
    "iso:country":"US",
    "sg:address":"211 W Walnut St",
    "sg:city":"Carrier Mills",
    "sg:classifiers":[
        {
            "category":"Building & Trades",
            "subcategory":"Cleaning & Sanitation",
            "type":"Services"
        }
    ],
    "sg:phone":"+1 618 994 2232",
    "sg:postcode":"62917",
    "sg:province":"IL",
    "sg:tags":[
        "janitor"
    ],
    "wof:name":"Stephanie's Cleaning",
    "wof:placetype":"venue"
},
  "geometry": {"coordinates":[-88.637558,37.68495],"type":"Point"}
}