{
  "type": "Feature",
  "properties": {
    "iso:country":"US",
    "sg:address":"2826 N. Lincoln",
    "sg:city":"Chicago",
    "sg:classifiers":[
        {
            "category":"Restaurant",
            "type":"Food & Drink"
        }
    ],
    "sg:postcode":"60657",
    "sg:province":"IL",
    "sg:tags":[
        "african"
    ],
    "wof:name":"Mogadishu Grill",
    "wof:placetype":"venue"
},
  "geometry": {"coordinates":[-87.659831,41.933064],"type":"Point"}
}