{
  "type": "Feature",
  "properties": {
    "addr:full":"1600 Riverdale Rd Rock Falls IL 61071",
    "addr:housenumber":"1600",
    "addr:postcode":"61071",
    "addr:street":"Riverdale Rd",
    "iso:country":"US",
    "sg:address":"1600 Riverdale Rd",
    "sg:city":"Rock Falls",
    "sg:classifiers":[
        {
            "category":"Utilities",
            "subcategory":"Refuse",
            "type":"Services"
        }
    ],
    "sg:phone":"+1 815 625 2403",
    "sg:postcode":"61071",
    "sg:province":"IL",
    "sg:tags":[
        "system"
    ],
    "wof:name":"Steegs Haul Away Service Inc",
    "wof:placetype":"venue"
},
  "geometry": {"coordinates":[-89.73280699999999,41.764959],"type":"Point"}
}