{
  "type": "Feature",
  "properties": {
    "iso:country":"US",
    "sg:address":"3 Walnut Dr",
    "sg:city":"Hawthorn Woods",
    "sg:classifiers":[
        {
            "category":"Building & Trades",
            "subcategory":"Construction",
            "type":"Services"
        }
    ],
    "sg:phone":"+1 847 540 8292",
    "sg:postcode":"60047",
    "sg:province":"IL",
    "sg:tags":[
        "contractor"
    ],
    "wof:name":"Builders Connection Inc",
    "wof:placetype":"venue"
},
  "geometry": {"coordinates":[-88.04552700000001,42.217352],"type":"Point"}
}