{
  "type": "Feature",
  "properties": {
    "addr:full":"7532 Halesia Ct Orland Park IL 60462",
    "addr:housenumber":"7532",
    "addr:postcode":"60462",
    "addr:street":"Halesia Ct",
    "iso:country":"US",
    "sg:address":"7532 Halesia Ct",
    "sg:city":"Orland Park",
    "sg:classifiers":[
        {
            "category":"Wholesale",
            "subcategory":"Meat",
            "type":"Manufacturing & Wholesale Goods"
        }
    ],
    "sg:phone":"+1 708 429 2225",
    "sg:postcode":"60462",
    "sg:province":"IL",
    "wof:name":"Orland Meat Brokers",
    "wof:placetype":"venue"
},
  "geometry": {"coordinates":[-87.80294499999999,41.610673],"type":"Point"}
}