{
  "type": "Feature",
  "properties": {
    "iso:country":"US",
    "sg:address":"3325 Kennedy Dr",
    "sg:city":"East Moline",
    "sg:classifiers":[
        {
            "category":"Professional",
            "subcategory":"Computer Services",
            "type":"Services"
        }
    ],
    "sg:phone":"+1 309 755 8985",
    "sg:postcode":"61244",
    "sg:province":"IL",
    "wof:name":"Multi Media World",
    "wof:placetype":"venue"
},
  "geometry": {"coordinates":[-90.456064,41.498089],"type":"Point"}
}