{
  "type": "Feature",
  "properties": {
    "addr:full":"78 E Washington St Chicago IL 60602",
    "addr:housenumber":"78",
    "addr:postcode":"60602",
    "addr:street":"E Washington St",
    "iso:country":"US",
    "sg:address":"78 E Washington St",
    "sg:city":"Chicago",
    "sg:classifiers":[
        {
            "category":"Organizations",
            "subcategory":"Professional Association",
            "type":"Services"
        }
    ],
    "sg:phone":"+1 312 254 1800",
    "sg:postcode":"60602",
    "sg:province":"IL",
    "sg:tags":[
        "business",
        "trade"
    ],
    "sg:website":"http://www.ivcc.org",
    "wof:name":"Worldchicago",
    "wof:placetype":"venue"
},
  "geometry": {"coordinates":[-87.62524000000001,41.883221],"type":"Point"}
}