{
  "type": "Feature",
  "properties": {
    "iso:country":"US",
    "sg:address":"10523 N Main St",
    "sg:city":"Richmond",
    "sg:classifiers":[
        {
            "category":"Professional",
            "subcategory":"Art Services",
            "type":"Services"
        }
    ],
    "sg:phone":"+1 815 678 4386",
    "sg:postcode":"60071",
    "sg:province":"IL",
    "sg:tags":[
        "photographer"
    ],
    "wof:name":"Kielpinski Commercial Photo",
    "wof:placetype":"venue"
},
  "geometry": {"coordinates":[-88.306068,42.480322],"type":"Point"}
}