{
  "type": "Feature",
  "properties": {
    "addr:full":"1780 Capital St Elgin IL 60124",
    "addr:housenumber":"1780",
    "addr:postcode":"60124",
    "addr:street":"Capital St",
    "iso:country":"US",
    "sg:address":"1780 Capital St",
    "sg:city":"Elgin",
    "sg:classifiers":[
        {
            "category":"Travel",
            "subcategory":"Hotels & Motels",
            "type":"Entertainment"
        },
        {
            "category":"Retail",
            "subcategory":"Event Space",
            "type":"Services"
        }
    ],
    "sg:phone":"+1 877 660 8545",
    "sg:postcode":"60124",
    "sg:province":"IL",
    "sg:tags":[
        "facility",
        "banquet",
        "reception",
        "lodging",
        "corporate",
        "hall"
    ],
    "sg:website":"http://ad.doubleclick.net/clk;222817012;46581823;b?http://www.candlewoodsuites.com/redirect?path=hd&brandCode=cw&hotelCode=chirr&_PMID=99601036&cm_mmc=mdpr-_-yellowpages-_-cw-_-chirr",
    "wof:name":"Candlewood Suites Elgin Nw-Chicago",
    "wof:placetype":"venue"
},
  "geometry": {"coordinates":[-88.339707,42.080994],"type":"Point"}
}