{
  "type": "Feature",
  "properties": {
    "iso:country":"US",
    "sg:address":"1267 Rand Rd",
    "sg:city":"Des Plaines",
    "sg:classifiers":[
        {
            "category":"Shopping",
            "type":"Retail Goods"
        }
    ],
    "sg:phone":"+1   ",
    "sg:postcode":"60016",
    "sg:province":"IL",
    "sg:tags":[
        "machine",
        "equipment",
        "business"
    ],
    "wof:name":"Numbers Automation Inc",
    "wof:placetype":"venue"
},
  "geometry": {"coordinates":[-87.897688,42.053836],"type":"Point"}
}