{
  "type": "Feature",
  "properties": {
    "iso:country":"US",
    "sg:address":"550 N Frontage Rd",
    "sg:city":"Bolingbrook",
    "sg:classifiers":[
        {
            "category":"Personal",
            "subcategory":"Beauty Salon",
            "type":"Services"
        }
    ],
    "sg:phone":"+1 630 972 1399",
    "sg:postcode":"60440",
    "sg:province":"IL",
    "sg:tags":[
        "shop"
    ],
    "wof:name":"Touch Of Beauty Salon",
    "wof:placetype":"venue"
},
  "geometry": {"coordinates":[-88.088043,41.675242],"type":"Point"}
}