{
  "type": "Feature",
  "properties": {
    "iso:country":"US",
    "sg:address":"7201 Church Ln",
    "sg:city":"East Saint Louis",
    "sg:classifiers":[
        {
            "category":"Organizations",
            "subcategory":"Religious Organization",
            "type":"Services"
        }
    ],
    "sg:phone":"+1 618 398 2235",
    "sg:postcode":"62203",
    "sg:province":"IL",
    "sg:tags":[
        "church"
    ],
    "wof:name":"Saints Fellowship COGIC",
    "wof:placetype":"venue"
},
  "geometry": {"coordinates":[-90.071656,38.60449],"type":"Point"}
}