{
  "type": "Feature",
  "properties": {
    "addr:full":"1104 W 107th Pl Chicago IL 60643",
    "addr:housenumber":"1104",
    "addr:postcode":"60643",
    "addr:street":"W 107Th Pl",
    "iso:country":"US",
    "sg:address":"1104 W 107th Pl",
    "sg:city":"Chicago",
    "sg:classifiers":[
        {
            "category":"Travel",
            "subcategory":"Travel Agent",
            "type":"Entertainment"
        }
    ],
    "sg:phone":"+1 773 445 4310",
    "sg:postcode":"60643",
    "sg:province":"IL",
    "sg:tags":[
        "agency"
    ],
    "wof:name":"Escape 2 Eden",
    "wof:placetype":"venue"
},
  "geometry": {"coordinates":[-87.65079299999999,41.698703],"type":"Point"}
}