{
  "type": "Feature",
  "properties": {
    "addr:full":"6901 S US Hwy 45 Brookport IL 62910",
    "addr:housenumber":"6901",
    "addr:postcode":"62910",
    "addr:street":"S Us Hwy 45",
    "iso:country":"US",
    "sg:address":"6901 S US Hwy 45",
    "sg:city":"Brookport",
    "sg:classifiers":[
        {
            "category":"Autos & Motor Vehicles",
            "subcategory":"Motorcycle Sales",
            "type":"Retail Goods"
        }
    ],
    "sg:phone":"+1   ",
    "sg:postcode":"62910",
    "sg:province":"IL",
    "sg:tags":[
        "all"
    ],
    "wof:name":"Performance Cycle",
    "wof:placetype":"venue"
},
  "geometry": {"coordinates":[-88.630543,37.14475],"type":"Point"}
}