{
  "type": "Feature",
  "properties": {
    "addr:full":"3711 Calderwood Dr Rockford IL 61114",
    "addr:housenumber":"3711",
    "addr:postcode":"61114",
    "addr:street":"Calderwood Dr",
    "iso:country":"US",
    "sg:address":"3711 Calderwood Dr",
    "sg:city":"Rockford",
    "sg:classifiers":[
        {
            "category":"Insurance",
            "subcategory":"Insurance Agent",
            "type":"Services"
        }
    ],
    "sg:phone":"+1 815 636 8185",
    "sg:postcode":"61114",
    "sg:province":"IL",
    "wof:name":"Keystone Insurance Inc",
    "wof:placetype":"venue"
},
  "geometry": {"coordinates":[-88.991545,42.315611],"type":"Point"}
}