{
  "type": "Feature",
  "properties": {
    "iso:country":"US",
    "sg:address":"6805 Ogden Ave",
    "sg:city":"Berwyn",
    "sg:classifiers":[
        {
            "category":"Personal",
            "subcategory":"Beauty Salon",
            "type":"Services"
        }
    ],
    "sg:phone":"+1 708 749 1562",
    "sg:postcode":"60402",
    "sg:province":"IL",
    "sg:tags":[
        "hair"
    ],
    "wof:name":"Le Rouge Beauty Salon",
    "wof:placetype":"venue"
},
  "geometry": {"coordinates":[-87.79290899999999,41.827286],"type":"Point"}
}