{
  "type": "Feature",
  "properties": {
    "iso:country":"US",
    "sg:address":"1611 E 3000 North Rd",
    "sg:city":"Clifton",
    "sg:phone":"+1 815 694 2517",
    "sg:postcode":"60927",
    "sg:province":"IL",
    "sg:tags":[
        "farm",
        "corn",
        "soybean"
    ],
    "wof:name":"Ponton Eldon",
    "wof:placetype":"venue"
},
  "geometry": {"coordinates":[-87.820353,40.946337],"type":"Point"}
}