{
  "type": "Feature",
  "properties": {
    "iso:country":"US",
    "sg:address":"1010 Walnut St",
    "sg:city":"Highland",
    "sg:classifiers":[
        {
            "category":"Health Services",
            "subcategory":"Chiropractor",
            "type":"Services"
        }
    ],
    "sg:phone":"+1 618 654 3900",
    "sg:postcode":"62249",
    "sg:province":"IL",
    "wof:name":"Neck & Back Pain Relief Center",
    "wof:placetype":"venue"
},
  "geometry": {"coordinates":[-89.68163,38.740329],"type":"Point"}
}