{
  "type": "Feature",
  "properties": {
    "addr:full":"2218 W Medill Ave Chicago IL 60647",
    "addr:housenumber":"2218",
    "addr:postcode":"60647",
    "addr:street":"W Medill Ave",
    "iso:country":"US",
    "sg:address":"2218 W Medill Ave",
    "sg:city":"Chicago",
    "sg:classifiers":[
        {
            "category":"Wholesale",
            "subcategory":"Construction Materials",
            "type":"Manufacturing & Wholesale Goods"
        }
    ],
    "sg:phone":"+1 773 276 3298",
    "sg:postcode":"60647",
    "sg:province":"IL",
    "sg:tags":[
        "mixed",
        "concrete-ready"
    ],
    "wof:name":"Stitch & Mix Corp",
    "wof:placetype":"venue"
},
  "geometry": {"coordinates":[-87.68317999999999,41.924178],"type":"Point"}
}