{
  "type": "Feature",
  "properties": {
    "addr:full":"734 Dorchester Dr Bolingbrook IL 60440",
    "addr:housenumber":"734",
    "addr:postcode":"60440",
    "addr:street":"Dorchester Dr",
    "iso:country":"US",
    "sg:address":"734 Dorchester Dr",
    "sg:city":"Bolingbrook",
    "sg:classifiers":[
        {
            "category":"Personal",
            "subcategory":"Beauty Salon",
            "type":"Services"
        }
    ],
    "sg:phone":"+1 630 783 9477",
    "sg:postcode":"60440",
    "sg:province":"IL",
    "sg:tags":[
        "shop"
    ],
    "wof:name":"Hey Baby Salon",
    "wof:placetype":"venue"
},
  "geometry": {"coordinates":[-88.054506,41.726114],"type":"Point"}
}