{
  "type": "Feature",
  "properties": {
    "iso:country":"US",
    "sg:address":"1733 W 87th St",
    "sg:city":"Chicago",
    "sg:classifiers":[
        {
            "category":"Fast Food",
            "type":"Food & Drink"
        },
        {
            "category":"Restaurant",
            "type":"Food & Drink"
        }
    ],
    "sg:phone":"+1 773 429 1812",
    "sg:postcode":"60620",
    "sg:province":"IL",
    "sg:tags":[
        "take"
    ],
    "wof:name":"As Good As Mothers",
    "wof:placetype":"venue"
},
  "geometry": {"coordinates":[-87.66670999999999,41.735741],"type":"Point"}
}