{
  "type": "Feature",
  "properties": {
    "iso:country":"US",
    "sg:address":"440 Blackhawk Park Ave",
    "sg:city":"Rockford",
    "sg:classifiers":[
        {
            "category":"Manufacturing",
            "subcategory":"Building Materials",
            "type":"Manufacturing & Wholesale Goods"
        }
    ],
    "sg:phone":"+1 815 962 6654",
    "sg:postcode":"61104",
    "sg:province":"IL",
    "sg:tags":[
        "equipment",
        "painter",
        "supply"
    ],
    "sg:website":"http://www.testors.com",
    "wof:name":"The Testor Corporation",
    "wof:placetype":"venue"
},
  "geometry": {"coordinates":[-89.094612,42.245038],"type":"Point"}
}