{
  "type": "Feature",
  "properties": {
    "addr:full":"14 Walter Ct Lake In The Hls IL 60156",
    "addr:housenumber":"14",
    "addr:postcode":"60156",
    "addr:street":"Walter Ct",
    "iso:country":"US",
    "sg:address":"14 Walter Ct",
    "sg:city":"Lake In The Hls",
    "sg:classifiers":[
        {
            "category":"Manufacturing",
            "subcategory":"Rubber & Plastics",
            "type":"Manufacturing & Wholesale Goods"
        }
    ],
    "sg:phone":"+1 847 658 3938",
    "sg:postcode":"60156",
    "sg:province":"IL",
    "sg:tags":[
        "conveyor"
    ],
    "sg:website":"www.afconline.com",
    "wof:name":"Advanced Flexible Composites",
    "wof:placetype":"venue"
},
  "geometry": {"coordinates":[-88.304772,42.191304],"type":"Point"}
}