{
  "type": "Feature",
  "properties": {
    "iso:country":"US",
    "sg:address":"4844 N Lamon Ave",
    "sg:city":"Chicago",
    "sg:classifiers":[
        {
            "category":"Building & Trades",
            "subcategory":"Construction",
            "type":"Services"
        }
    ],
    "sg:phone":"+1 773 205 1444",
    "sg:postcode":"60630",
    "sg:province":"IL",
    "sg:tags":[
        "excavation",
        "demolition",
        "contractor"
    ],
    "wof:name":"Reilley Exc & Wrecking",
    "wof:placetype":"venue"
},
  "geometry": {"coordinates":[-87.750229,41.96908],"type":"Point"}
}