{
  "type": "Feature",
  "properties": {
    "addr:full":"5114 N Christiana Ave Chicago IL 60625",
    "addr:housenumber":"5114",
    "addr:postcode":"60625",
    "addr:street":"N Christiana Ave",
    "iso:country":"US",
    "sg:address":"5114 N Christiana Ave",
    "sg:city":"Chicago",
    "sg:classifiers":[
        {
            "category":"Education",
            "subcategory":"School",
            "type":"Public Place"
        }
    ],
    "sg:phone":"+1 773 244 5580",
    "sg:postcode":"60625",
    "sg:province":"IL",
    "sg:website":"www.northpark.edu/brandel-librar...",
    "wof:name":"North Park University Brandel Library",
    "wof:placetype":"venue"
},
  "geometry": {"coordinates":[-87.712324,41.974755],"type":"Point"}
}