{
  "type": "Feature",
  "properties": {
    "addr:full":"308 N Main St Eureka IL 61530",
    "addr:housenumber":"308",
    "addr:postcode":"61530",
    "addr:street":"N Main St",
    "iso:country":"US",
    "sg:address":"308 N Main St",
    "sg:city":"Eureka",
    "sg:classifiers":[
        {
            "category":"Freight",
            "type":"Transportation"
        }
    ],
    "sg:phone":"+1 309 467 6150",
    "sg:postcode":"61530",
    "sg:province":"IL",
    "sg:tags":[
        "commercial",
        "storage"
    ],
    "wof:name":"Access Storage",
    "wof:placetype":"venue"
},
  "geometry": {"coordinates":[-89.272969,40.723525],"type":"Point"}
}