{
  "type": "Feature",
  "properties": {
    "addr:full":"285 E Army Trail Rd Glendale Heights IL 60139",
    "addr:housenumber":"285",
    "addr:postcode":"60139",
    "addr:street":"E Army Trail Rd",
    "iso:country":"US",
    "sg:address":"285 E Army Trail Rd",
    "sg:city":"Glendale Heights",
    "sg:classifiers":[
        {
            "category":"Banks & Credit Unions",
            "subcategory":"Bank",
            "type":"Services"
        },
        {
            "category":"Banks & Credit Unions",
            "subcategory":"Financial Services",
            "type":"Services"
        }
    ],
    "sg:phone":"+1 630 295 5822",
    "sg:postcode":"60139",
    "sg:province":"IL",
    "sg:tags":[
        "broker",
        "mortgage"
    ],
    "sg:website":"www.bankofamerica.com",
    "wof:name":"Bank of America",
    "wof:placetype":"venue"
},
  "geometry": {"coordinates":[-88.071089,41.936124],"type":"Point"}
}