{
  "type": "Feature",
  "properties": {
    "addr:full":"25915 S Frontage Rd Channahon IL 60410",
    "addr:housenumber":"25915",
    "addr:postcode":"60410",
    "addr:street":"S Frontage Rd",
    "iso:country":"US",
    "sg:address":"25915 S Frontage Rd",
    "sg:city":"Channahon",
    "sg:classifiers":[
        {
            "category":"Wholesale",
            "subcategory":"Machinery & Supplies",
            "type":"Manufacturing & Wholesale Goods"
        }
    ],
    "sg:phone":"+1 815 423 5032",
    "sg:postcode":"60410",
    "sg:province":"IL",
    "sg:tags":[
        "equipment",
        "industrial"
    ],
    "sg:website":"http://www.airproducts.com",
    "wof:name":"Air Products",
    "wof:placetype":"venue"
},
  "geometry": {"coordinates":[-88.193831,41.432694],"type":"Point"}
}