{
  "type": "Feature",
  "properties": {
    "iso:country":"US",
    "sg:address":"1772 S Randall Rd Ste 250",
    "sg:city":"Geneva",
    "sg:classifiers":[
        {
            "category":"Personal",
            "subcategory":"Nail Salon",
            "type":"Services"
        }
    ],
    "sg:phone":"+1 630 262 8955",
    "sg:postcode":"60134",
    "sg:province":"IL",
    "wof:name":"Simply Nails",
    "wof:placetype":"venue"
},
  "geometry": {"coordinates":[-88.34043,41.869118],"type":"Point"}
}