{
  "type": "Feature",
  "properties": {
    "addr:full":"10 S Riverside Plaza Chicago IL 60606",
    "addr:housenumber":"10",
    "addr:postcode":"60606",
    "addr:street":"S Riverside Plaza",
    "iso:country":"US",
    "sg:address":"10 S Riverside Plaza",
    "sg:city":"Chicago",
    "sg:classifiers":[
        {
            "category":"Professional",
            "subcategory":"Accounting & Tax Preparation",
            "type":"Services"
        }
    ],
    "sg:phone":"+1 312 207 1040",
    "sg:postcode":"60606",
    "sg:province":"IL",
    "sg:tags":[
        "accountant"
    ],
    "wof:name":"Andersen Greg CPA",
    "wof:placetype":"venue"
},
  "geometry": {"coordinates":[-87.637139,41.882343],"type":"Point"}
}