{
  "type": "Feature",
  "properties": {
    "addr:full":"401 E Springfield Ave Champaign IL 61820",
    "addr:housenumber":"401",
    "addr:postcode":"61820",
    "addr:street":"E Springfield Ave",
    "iso:country":"US",
    "sg:address":"401 E Springfield Ave",
    "sg:city":"Champaign",
    "sg:classifiers":[
        {
            "category":"Professional",
            "subcategory":"Accounting & Tax Preparation",
            "type":"Services"
        }
    ],
    "sg:phone":"+1 217 352 4743",
    "sg:postcode":"61820",
    "sg:province":"IL",
    "sg:tags":[
        "return",
        "preparation-business",
        "billing",
        "accountants-certified",
        "accountant",
        "bookkeeping",
        "public"
    ],
    "wof:name":"Hays & Assocs PC CPA",
    "wof:placetype":"venue"
},
  "geometry": {"coordinates":[-88.233002,40.112701],"type":"Point"}
}