{
  "type": "Feature",
  "properties": {
    "iso:country":"US",
    "sg:address":"7601 McIntosh Dr",
    "sg:city":"Orland Park",
    "sg:classifiers":[
        {
            "category":"Building & Trades",
            "subcategory":"Construction",
            "type":"Services"
        }
    ],
    "sg:phone":"+1 708 361 4701",
    "sg:postcode":"60462",
    "sg:province":"IL",
    "sg:tags":[
        "builder",
        "industrial",
        "operative"
    ],
    "wof:name":"De Vries Cnsrt",
    "wof:placetype":"venue"
},
  "geometry": {"coordinates":[-87.808073,41.647304],"type":"Point"}
}