{
  "type": "Feature",
  "properties": {
    "iso:country":"US",
    "sg:address":"617 W Main St",
    "sg:city":"Collinsville",
    "sg:classifiers":[
        {
            "category":"Education",
            "subcategory":"Kindergarten",
            "type":"Public Place"
        },
        {
            "category":"Education",
            "subcategory":"School",
            "type":"Public Place"
        }
    ],
    "sg:phone":"+1 618 345 1919",
    "sg:postcode":"62234",
    "sg:province":"IL",
    "sg:tags":[
        "high",
        "middle",
        "elementary",
        "driving"
    ],
    "sg:website":"www.il-metrodriving.com",
    "wof:name":"Metro Driving School",
    "wof:placetype":"venue"
},
  "geometry": {"coordinates":[-89.992728,38.667891],"type":"Point"}
}