{
  "type": "Feature",
  "properties": {
    "iso:country":"US",
    "sg:address":"2304 Charles St",
    "sg:city":"Rockford",
    "sg:classifiers":[
        {
            "category":"Autos & Motor Vehicles",
            "subcategory":"Fuel & Gas Station",
            "type":"Retail Goods"
        },
        {
            "category":"Retail",
            "subcategory":"Auto Repair",
            "type":"Services"
        }
    ],
    "sg:phone":"+1 815 397 6770",
    "sg:postcode":"61104",
    "sg:province":"IL",
    "wof:name":"Plaza Auto Service",
    "wof:placetype":"venue"
},
  "geometry": {"coordinates":[-89.06013299999999,42.260944],"type":"Point"}
}