{
  "type": "Feature",
  "properties": {
    "addr:full":"1546 N Clark Chicago IL 60610",
    "addr:housenumber":"1546",
    "addr:postcode":"60610",
    "addr:street":"N Clark",
    "iso:country":"US",
    "sg:address":"1546 N Clark",
    "sg:city":"Chicago",
    "sg:classifiers":[
        {
            "category":"Building & Trades",
            "subcategory":"Construction",
            "type":"Services"
        }
    ],
    "sg:phone":"+1 312 915 0600",
    "sg:postcode":"60610",
    "sg:province":"IL",
    "sg:tags":[
        "interior",
        "design"
    ],
    "wof:name":"Classic Designs by Nike",
    "wof:placetype":"venue"
},
  "geometry": {"coordinates":[-87.631652,41.910768],"type":"Point"}
}