{
  "type": "Feature",
  "properties": {
    "iso:country":"US",
    "sg:address":"3023 N Broadway",
    "sg:city":"Chicago",
    "sg:classifiers":[
        {
            "category":"Personal",
            "subcategory":"Beauty Salon",
            "type":"Services"
        },
        {
            "category":"Personal",
            "subcategory":"Hair Removal",
            "type":"Services"
        },
        {
            "category":"Personal",
            "subcategory":"Barber",
            "type":"Services"
        }
    ],
    "sg:phone":"+1 773 281 8340",
    "sg:postcode":"60657",
    "sg:province":"IL",
    "wof:name":"Maria and Luis's Beauty Salon",
    "wof:placetype":"venue"
},
  "geometry": {"coordinates":[-87.644014,41.937225],"type":"Point"}
}