{
  "type": "Feature",
  "properties": {
    "iso:country":"US",
    "sg:address":"1838 E Belvidere Rd",
    "sg:city":"Grayslake",
    "sg:classifiers":[
        {
            "category":"Social Services",
            "subcategory":"Child Care",
            "type":"Services"
        }
    ],
    "sg:phone":"+1 847 548 3455",
    "sg:postcode":"60030",
    "sg:province":"IL",
    "sg:website":"http://www.primetimedaycare.com/contact.html",
    "wof:name":"Prime Time 2 Children's Center",
    "wof:placetype":"venue"
},
  "geometry": {"coordinates":[-88.005455,42.338736],"type":"Point"}
}