{
  "type": "Feature",
  "properties": {
    "addr:full":"3712 Jarvis Ave Skokie IL 60076",
    "addr:housenumber":"3712",
    "addr:postcode":"60076",
    "addr:street":"Jarvis Ave",
    "iso:country":"US",
    "sg:address":"3712 Jarvis Ave",
    "sg:city":"Skokie",
    "sg:classifiers":[
        {
            "category":"Home & Garden",
            "subcategory":"Furniture",
            "type":"Retail Goods"
        }
    ],
    "sg:phone":"+1 847 673 5097",
    "sg:postcode":"60076",
    "sg:province":"IL",
    "sg:tags":[
        "store"
    ],
    "wof:name":"Lighting Tech",
    "wof:placetype":"venue"
},
  "geometry": {"coordinates":[-87.721689,42.015414],"type":"Point"}
}