{
  "type": "Feature",
  "properties": {
    "addr:full":"628 Palace St Aurora IL 60506",
    "addr:housenumber":"628",
    "addr:postcode":"60506",
    "addr:street":"Palace St",
    "iso:country":"US",
    "sg:address":"628 Palace St",
    "sg:city":"Aurora",
    "sg:classifiers":[
        {
            "category":"Professional",
            "subcategory":"Computer Services",
            "type":"Services"
        }
    ],
    "sg:phone":"+1 708 288 6220",
    "sg:postcode":"60506",
    "sg:province":"IL",
    "sg:tags":[
        "related"
    ],
    "wof:name":"Lauck & Associates Inc",
    "wof:placetype":"venue"
},
  "geometry": {"coordinates":[-88.318273,41.768361],"type":"Point"}
}