{
  "type": "Feature",
  "properties": {
    "iso:country":"US",
    "sg:address":"133 W Roosevelt Rd",
    "sg:city":"West Chicago",
    "sg:classifiers":[
        {
            "category":"Food & Beverages",
            "subcategory":"Groceries & Convenience Stores",
            "type":"Retail Goods"
        }
    ],
    "sg:phone":"+1 630 231 0098",
    "sg:postcode":"60185",
    "sg:province":"IL",
    "wof:name":"Supermercado La Chiquita",
    "wof:placetype":"venue"
},
  "geometry": {"coordinates":[-88.20639799999999,41.865898],"type":"Point"}
}