{
  "type": "Feature",
  "properties": {
    "iso:country":"US",
    "sg:address":"4541 N Ravenswood Ave",
    "sg:city":"Chicago",
    "sg:classifiers":[
        {
            "category":"Social Services",
            "subcategory":"Job Training",
            "type":"Services"
        }
    ],
    "sg:phone":"+1 773 506 2100",
    "sg:postcode":"60640",
    "sg:province":"IL",
    "sg:tags":[
        "consultant"
    ],
    "sg:website":"http://www.mostconsulting.com",
    "wof:name":"Most Training And Consulting, Lp",
    "wof:placetype":"venue"
},
  "geometry": {"coordinates":[-87.67403899999999,41.964088],"type":"Point"}
}