{
  "type": "Feature",
  "properties": {
    "iso:country":"US",
    "sg:address":"13 W Weathersfield Way",
    "sg:city":"Schaumburg",
    "sg:classifiers":[
        {
            "category":"Organizations",
            "subcategory":"Membership Organization",
            "type":"Services"
        }
    ],
    "sg:phone":"+1 847 534 8255",
    "sg:postcode":"60193",
    "sg:province":"IL",
    "sg:tags":[
        "business"
    ],
    "wof:name":"Bostal One",
    "wof:placetype":"venue"
},
  "geometry": {"coordinates":[-88.080872,42.016181],"type":"Point"}
}