{
  "type": "Feature",
  "properties": {
    "addr:full":"526 Vandalia St Collinsville IL 62234",
    "addr:housenumber":"526",
    "addr:postcode":"62234",
    "addr:street":"Vandalia St",
    "iso:country":"US",
    "sg:address":"526 Vandalia St",
    "sg:city":"Collinsville",
    "sg:classifiers":[
        {
            "category":"Manufacturing",
            "subcategory":"Printing",
            "type":"Manufacturing & Wholesale Goods"
        }
    ],
    "sg:phone":"+1 618 345 5525",
    "sg:postcode":"62234",
    "sg:province":"IL",
    "sg:tags":[
        "commercial",
        "b",
        "printer",
        "lithographic",
        "typesetting"
    ],
    "wof:name":"M O W Printing Inc",
    "wof:placetype":"venue"
},
  "geometry": {"coordinates":[-89.983529,38.676617],"type":"Point"}
}