{
  "type": "Feature",
  "properties": {
    "iso:country":"US",
    "sg:address":"1 Tower Ln",
    "sg:city":"Elgin",
    "sg:classifiers":[
        {
            "category":"Food & Beverages",
            "subcategory":"Groceries & Convenience Stores",
            "type":"Retail Goods"
        }
    ],
    "sg:phone":"+1   ",
    "sg:postcode":"60181",
    "sg:province":"IL",
    "sg:tags":[
        "supermarket"
    ],
    "wof:name":"Butera Finer Foods Inc",
    "wof:placetype":"venue"
},
  "geometry": {"coordinates":[-87.951117,41.860913],"type":"Point"}
}