{
  "type": "Feature",
  "properties": {
    "iso:country":"US",
    "sg:address":"5678 N Milwaukee Ave",
    "sg:city":"Chicago",
    "sg:classifiers":[
        {
            "category":"Autos & Motor Vehicles",
            "subcategory":"Fuel & Gas Station",
            "type":"Retail Goods"
        },
        {
            "category":"Manufacturing",
            "subcategory":"Motor Vehicles & Parts",
            "type":"Manufacturing & Wholesale Goods"
        },
        {
            "category":"Autos & Motor Vehicles",
            "subcategory":"Auto Supplies",
            "type":"Retail Goods"
        },
        {
            "category":"Retail",
            "subcategory":"Auto Repair",
            "type":"Services"
        },
        {
            "category":"Autos & Motor Vehicles",
            "subcategory":"Automobile Sales",
            "type":"Retail Goods"
        },
        {
            "category":"Building & Trades",
            "subcategory":"Plumbing",
            "type":"Services"
        }
    ],
    "sg:phone":"+1 773 763 3788",
    "sg:postcode":"60646",
    "sg:province":"IL",
    "sg:tags":[
        "radiators-repairing",
        "rebuilding",
        "radiator",
        "automotive",
        "equipment",
        "truck",
        "radiators-wholesale",
        "equipment-service",
        "accessory",
        "air conditioning",
        "manufacturer"
    ],
    "wof:name":"Three Arrows Auto Radiator Svc",
    "wof:placetype":"venue"
},
  "geometry": {"coordinates":[-87.775977,41.984703],"type":"Point"}
}