{
  "type": "Feature",
  "properties": {
    "iso:country":"US",
    "sg:address":"6608 Greene Rd",
    "sg:city":"Woodridge",
    "sg:classifiers":[
        {
            "category":"Wholesale",
            "subcategory":"Drugs",
            "type":"Manufacturing & Wholesale Goods"
        }
    ],
    "sg:phone":"+1 630 548 2537",
    "sg:postcode":"60517",
    "sg:province":"IL",
    "sg:tags":[
        "chemical",
        "pharmaceutical"
    ],
    "wof:name":"Medicilon Chemicals",
    "wof:placetype":"venue"
},
  "geometry": {"coordinates":[-88.074843,41.762484],"type":"Point"}
}