{
  "type": "Feature",
  "properties": {
    "addr:full":"111 E Sangamon Ave Rantoul IL 61866",
    "addr:housenumber":"111",
    "addr:postcode":"61866",
    "addr:street":"E Sangamon Ave",
    "iso:country":"US",
    "sg:address":"111 E Sangamon Ave",
    "sg:city":"Rantoul",
    "sg:classifiers":[
        {
            "category":"Recreation",
            "type":"Entertainment"
        }
    ],
    "sg:phone":"+1 217 893 4153",
    "sg:postcode":"61866",
    "sg:province":"IL",
    "wof:name":"Mike Schlossers Martial Arts",
    "wof:placetype":"venue"
},
  "geometry": {"coordinates":[-88.15749599999999,40.310681],"type":"Point"}
}