{
  "type": "Feature",
  "properties": {
    "addr:full":"333 W 4th St Dallas City IL 62330",
    "addr:housenumber":"333",
    "addr:postcode":"62330",
    "addr:street":"W 4Th St",
    "iso:country":"US",
    "sg:address":"333 W 4th St",
    "sg:city":"Dallas City",
    "sg:classifiers":[
        {
            "category":"Retail",
            "subcategory":"Auto Repair",
            "type":"Services"
        }
    ],
    "sg:phone":"+1 217 852 3814",
    "sg:postcode":"62330",
    "sg:province":"IL",
    "sg:tags":[
        "body",
        "automobile",
        "painting"
    ],
    "wof:name":"Bill Hull Auto Body",
    "wof:placetype":"venue"
},
  "geometry": {"coordinates":[-91.171922,40.633748],"type":"Point"}
}