{
  "type": "Feature",
  "properties": {
    "iso:country":"US",
    "sg:address":"1451 Merchant Dr",
    "sg:city":"Algonquin",
    "sg:classifiers":[
        {
            "category":"Health Services",
            "subcategory":"Doctor",
            "type":"Services"
        },
        {
            "category":"Health Services",
            "subcategory":"Chiropractor",
            "type":"Services"
        }
    ],
    "sg:phone":"+1 847 741 8771",
    "sg:postcode":"60102",
    "sg:province":"IL",
    "wof:name":"Family Wellness Care PC",
    "wof:placetype":"venue"
},
  "geometry": {"coordinates":[-88.329903,42.164799],"type":"Point"}
}