{
  "type": "Feature",
  "properties": {
    "iso:country":"US",
    "sg:address":"630 E Walnut St",
    "sg:city":"Carbondale",
    "sg:classifiers":[
        {
            "category":"Shopping",
            "subcategory":"Books",
            "type":"Retail Goods"
        }
    ],
    "sg:phone":"+1 618 549 1632",
    "sg:postcode":"62902",
    "sg:province":"IL",
    "sg:tags":[
        "dealer"
    ],
    "sg:website":"www.gospeland.com",
    "wof:name":"Gospeland Book Store",
    "wof:placetype":"venue"
},
  "geometry": {"coordinates":[-89.206933,37.726069],"type":"Point"}
}