{
  "type": "Feature",
  "properties": {
    "iso:country":"US",
    "sg:address":"9901 S Winston Ave",
    "sg:city":"Chicago",
    "sg:classifiers":[
        {
            "category":"Organizations",
            "subcategory":"Religious Organization",
            "type":"Services"
        }
    ],
    "sg:phone":"+1 773 233 1775",
    "sg:postcode":"60643",
    "sg:province":"IL",
    "wof:name":"Zion Lutheran Church",
    "wof:placetype":"venue"
},
  "geometry": {"coordinates":[-87.65679799999999,41.712188],"type":"Point"}
}