{
  "type": "Feature",
  "properties": {
    "addr:full":"1634 W North Ave Chicago IL 60622",
    "addr:housenumber":"1634",
    "addr:postcode":"60622",
    "addr:street":"W North Ave",
    "iso:country":"US",
    "sg:address":"1634 W North Ave",
    "sg:city":"Chicago",
    "sg:classifiers":[
        {
            "category":"Sports & Exercise",
            "subcategory":"Bicycle Rental",
            "type":"Entertainment"
        }
    ],
    "sg:phone":"+1 773 395 2929",
    "sg:postcode":"60622",
    "sg:province":"IL",
    "sg:tags":[
        "wear"
    ],
    "sg:website":"www.runningawaymultisport.com",
    "wof:name":"Running Away",
    "wof:placetype":"venue"
},
  "geometry": {"coordinates":[-87.66909800000001,41.910702],"type":"Point"}
}