{
  "type": "Feature",
  "properties": {
    "iso:country":"US",
    "sg:address":"2049 E 1350 North Rd",
    "sg:city":"Assumption",
    "sg:classifiers":[
        {
            "category":"Building & Trades",
            "subcategory":"Construction",
            "type":"Services"
        }
    ],
    "sg:phone":"+1 217 226 4334",
    "sg:postcode":"62510",
    "sg:province":"IL",
    "sg:tags":[
        "excavation",
        "excavating",
        "contractor"
    ],
    "wof:name":"Hutchens Bulldozing Inc",
    "wof:placetype":"venue"
},
  "geometry": {"coordinates":[-89.147533,39.545815],"type":"Point"}
}