{
  "type": "Feature",
  "properties": {
    "iso:country":"US",
    "sg:address":"1835 Dixie Hwy",
    "sg:city":"Flossmoor",
    "sg:classifiers":[
        {
            "category":"Professional",
            "subcategory":"Lawyer & Legal Services",
            "type":"Services"
        }
    ],
    "sg:phone":"+1 708 206 0790",
    "sg:postcode":"60422",
    "sg:province":"IL",
    "wof:name":"Timothy R Mc Avoy Attorney",
    "wof:placetype":"venue"
},
  "geometry": {"coordinates":[-87.656729,41.527843],"type":"Point"}
}