{
  "type": "Feature",
  "properties": {
    "iso:country":"US",
    "sg:address":"300 S Wacker Dr",
    "sg:city":"Chicago",
    "sg:classifiers":[
        {
            "category":"Government",
            "subcategory":"Embassy",
            "type":"Public Place"
        }
    ],
    "sg:phone":"+1 312 377 5050",
    "sg:postcode":"60606",
    "sg:province":"IL",
    "sg:tags":[
        "governmental",
        "offices-foreign",
        "representative",
        "consulate",
        "foreign"
    ],
    "sg:website":"http://www.norway.org",
    "wof:name":"Norwegian Consulate General",
    "wof:placetype":"venue"
},
  "geometry": {"coordinates":[-87.636871,41.87767],"type":"Point"}
}