{
  "type": "Feature",
  "properties": {
    "addr:full":"1610 E Empire St Bloomington IL 61701",
    "addr:housenumber":"1610",
    "addr:postcode":"61701",
    "addr:street":"E Empire St",
    "iso:country":"US",
    "sg:address":"1610 E Empire St",
    "sg:city":"Bloomington",
    "sg:classifiers":[
        {
            "category":"Restaurant",
            "type":"Food & Drink"
        }
    ],
    "sg:menulink":"http://www.allmenus.com/il/bloomington-city/212158-mcdonalds/menu/",
    "sg:postcode":"61701",
    "sg:province":"IL",
    "sg:tags":[
        "burger",
        "american"
    ],
    "wof:name":"McDonald's",
    "wof:placetype":"venue"
},
  "geometry": {"coordinates":[-88.95597600000001,40.488349],"type":"Point"}
}