{
  "type": "Feature",
  "properties": {
    "iso:country":"US",
    "sg:address":"817 Cutter Ln",
    "sg:city":"Elk Grove Village",
    "sg:classifiers":[
        {
            "category":"Professional",
            "subcategory":"Business Services",
            "type":"Services"
        }
    ],
    "sg:phone":"+1 847 524 0289",
    "sg:postcode":"60007",
    "sg:province":"IL",
    "wof:name":"Marselle Sales",
    "wof:placetype":"venue"
},
  "geometry": {"coordinates":[-88.05273099999999,42.000513],"type":"Point"}
}