{
  "type": "Feature",
  "properties": {
    "iso:country":"US",
    "sg:address":"110 N Peoria St",
    "sg:city":"Chicago",
    "sg:classifiers":[
        {
            "category":"Arts & Performance",
            "subcategory":"Art Gallery",
            "type":"Entertainment"
        }
    ],
    "sg:phone":"+1 312 563 9240",
    "sg:postcode":"60607",
    "sg:province":"IL",
    "sg:website":"grnnamdi.com",
    "wof:name":"G.R. N'Namdi Gallery",
    "wof:placetype":"venue"
},
  "geometry": {"coordinates":[-87.650255,41.883648],"type":"Point"}
}