{
  "type": "Feature",
  "properties": {
    "addr:full":"7733 S Saginaw Ave Chicago IL 60649",
    "addr:housenumber":"7733",
    "addr:postcode":"60649",
    "addr:street":"S Saginaw Ave",
    "iso:country":"US",
    "sg:address":"7733 S Saginaw Ave",
    "sg:city":"Chicago",
    "sg:classifiers":[
        {
            "category":"Professional",
            "subcategory":"Computer Services",
            "type":"Services"
        }
    ],
    "sg:phone":"+1 773 734 6858",
    "sg:postcode":"60649",
    "sg:province":"IL",
    "sg:tags":[
        "development",
        "software",
        "printing",
        "for",
        "desktop"
    ],
    "wof:name":"Printbox Technologies Ltd",
    "wof:placetype":"venue"
},
  "geometry": {"coordinates":[-87.559884,41.75422],"type":"Point"}
}