{
  "type": "Feature",
  "properties": {
    "iso:country":"US",
    "sg:address":"220 Division St",
    "sg:city":"Elgin",
    "sg:classifiers":[
        {
            "category":"Education",
            "subcategory":"Special Training",
            "type":"Public Place"
        }
    ],
    "sg:phone":"+1 847 468 8207",
    "sg:postcode":"60120",
    "sg:province":"IL",
    "wof:name":"Fox Valley Lutheran Academy",
    "wof:placetype":"venue"
},
  "geometry": {"coordinates":[-88.28149999999999,42.038742],"type":"Point"}
}