{
  "type": "Feature",
  "properties": {
    "addr:full":"1824 E Lincoln Hwy New Lenox IL 60451",
    "addr:housenumber":"1824",
    "addr:postcode":"60451",
    "addr:street":"E Lincoln Hwy",
    "iso:country":"US",
    "sg:address":"1824 E Lincoln Hwy",
    "sg:city":"New Lenox",
    "sg:classifiers":[
        {
            "category":"Personal",
            "subcategory":"Beauty Salon",
            "type":"Services"
        }
    ],
    "sg:phone":"+1 815 462 5042",
    "sg:postcode":"60451",
    "sg:province":"IL",
    "sg:website":"www.charlesmorrissalon.com",
    "wof:name":"Charles Morris Salon",
    "wof:placetype":"venue"
},
  "geometry": {"coordinates":[-87.92882899999999,41.510913],"type":"Point"}
}