{
  "type": "Feature",
  "properties": {
    "iso:country":"US",
    "sg:address":"412 W North St",
    "sg:city":"Peotone",
    "sg:classifiers":[
        {
            "category":"Personal",
            "type":"Services"
        }
    ],
    "sg:phone":"+1 708 258 3970",
    "sg:postcode":"60468",
    "sg:province":"IL",
    "sg:tags":[
        "miscellaneous"
    ],
    "wof:name":"Patient Empowerment Svc",
    "wof:placetype":"venue"
},
  "geometry": {"coordinates":[-87.796567,41.334284],"type":"Point"}
}