{
  "type": "Feature",
  "properties": {
    "iso:country":"US",
    "sg:address":"22049 Howell Dr",
    "sg:city":"New Lenox",
    "sg:classifiers":[
        {
            "category":"Building & Trades",
            "subcategory":"Plumbing",
            "type":"Services"
        }
    ],
    "sg:phone":"+1 708 479 7878",
    "sg:postcode":"60451",
    "sg:province":"IL",
    "sg:tags":[
        "plumbing",
        "irrigation",
        "work",
        "sprinkler",
        "system"
    ],
    "sg:website":"www.carefreesystems.com",
    "wof:name":"Carefree Lawn Sprinklers Inc",
    "wof:placetype":"venue"
},
  "geometry": {"coordinates":[-87.927792,41.489171],"type":"Point"}
}