{
  "type": "Feature",
  "properties": {
    "iso:country":"US",
    "sg:address":"16649 Vfw Rd",
    "sg:city":"Pekin",
    "sg:classifiers":[
        {
            "category":"Retail",
            "subcategory":"Storage",
            "type":"Services"
        }
    ],
    "sg:phone":"+1 309 267 5594",
    "sg:postcode":"61554",
    "sg:province":"IL",
    "sg:tags":[
        "self",
        "commercial",
        "household"
    ],
    "wof:name":"Affordable Self Storage",
    "wof:placetype":"venue"
},
  "geometry": {"coordinates":[-89.61482100000001,40.531273],"type":"Point"}
}