{
  "type": "Feature",
  "properties": {
    "addr:full":"1475 E Belvidere Rd Grayslake IL 60030",
    "addr:housenumber":"1475",
    "addr:postcode":"60030",
    "addr:street":"E Belvidere Rd",
    "iso:country":"US",
    "sg:address":"1475 E Belvidere Rd",
    "sg:city":"Grayslake",
    "sg:classifiers":[
        {
            "category":"Health Services",
            "subcategory":"Doctor",
            "type":"Services"
        }
    ],
    "sg:phone":"+1 847 548 8430",
    "sg:postcode":"60030",
    "sg:province":"IL",
    "sg:tags":[
        "physician",
        "family",
        "practice",
        "surgeons",
        "medicine",
        "surgeon"
    ],
    "wof:name":"Grayslake Family Health Center",
    "wof:placetype":"venue"
},
  "geometry": {"coordinates":[-88.01159699999999,42.338741],"type":"Point"}
}