{
  "type": "Feature",
  "properties": {
    "addr:full":"4340 N Keystone Ave Chicago IL 60641",
    "addr:housenumber":"4340",
    "addr:postcode":"60641",
    "addr:street":"N Keystone Ave",
    "iso:country":"US",
    "sg:address":"4340 N Keystone Ave",
    "sg:city":"Chicago",
    "sg:classifiers":[
        {
            "category":"Health Services",
            "subcategory":"Health Practitioner",
            "type":"Services"
        }
    ],
    "sg:phone":"+1 773 545 8700",
    "sg:postcode":"60641",
    "sg:province":"IL",
    "sg:tags":[
        "therapy",
        "physical"
    ],
    "sg:website":"glenelstonrehab.com",
    "wof:name":"Glen Elston Nursing and Rehabilitation Centre",
    "wof:placetype":"venue"
},
  "geometry": {"coordinates":[-87.72922800000001,41.95966],"type":"Point"}
}