{
  "type": "Feature",
  "properties": {
    "addr:full":"5743 W Division St Chicago IL 60651",
    "addr:housenumber":"5743",
    "addr:postcode":"60651",
    "addr:street":"W Division St",
    "iso:country":"US",
    "sg:address":"5743 W Division St",
    "sg:city":"Chicago",
    "sg:classifiers":[
        {
            "category":"Social Services",
            "subcategory":"Child Care",
            "type":"Services"
        }
    ],
    "sg:phone":"+1 773 626 3151",
    "sg:postcode":"60651",
    "sg:province":"IL",
    "wof:name":"McKinneys Home Day Care Center",
    "wof:placetype":"venue"
},
  "geometry": {"coordinates":[-87.76978699999999,41.902008],"type":"Point"}
}