{
  "type": "Feature",
  "properties": {
    "addr:full":"13457 Michael Rd Highland IL 62249",
    "addr:housenumber":"13457",
    "addr:postcode":"62249",
    "addr:street":"Michael Rd",
    "iso:country":"US",
    "sg:address":"13457 Michael Rd",
    "sg:city":"Highland",
    "sg:classifiers":[
        {
            "category":"Personal",
            "subcategory":"Beauty Salon",
            "type":"Services"
        }
    ],
    "sg:phone":"+1 618 654 8266",
    "sg:postcode":"62249",
    "sg:province":"IL",
    "sg:tags":[
        "shop"
    ],
    "wof:name":"Bonnie's Cut & Style",
    "wof:placetype":"venue"
},
  "geometry": {"coordinates":[-89.64832699999999,38.742745],"type":"Point"}
}