{
  "type": "Feature",
  "properties": {
    "iso:country":"US",
    "sg:address":"175 E Hawthorn Pkwy",
    "sg:city":"Vernon Hills",
    "sg:classifiers":[
        {
            "category":"Building & Trades",
            "subcategory":"Construction",
            "type":"Services"
        }
    ],
    "sg:phone":"+1 847 816 8500",
    "sg:postcode":"60061",
    "sg:province":"IL",
    "sg:tags":[
        "house",
        "builder",
        "home"
    ],
    "wof:name":"Kevin Charles Homes Inc",
    "wof:placetype":"venue"
},
  "geometry": {"coordinates":[-87.961423,42.241629],"type":"Point"}
}