{
  "type": "Feature",
  "properties": {
    "iso:country":"US",
    "sg:address":"8501 W Higgins Rd Ste 440",
    "sg:city":"Chicago",
    "sg:classifiers":[
        {
            "category":"Professional",
            "subcategory":"Lawyer & Legal Services",
            "type":"Services"
        }
    ],
    "sg:phone":"+1 773 399 1919",
    "sg:postcode":"60631",
    "sg:province":"IL",
    "wof:name":"Galvin Lewis Watson Galvin",
    "wof:placetype":"venue"
},
  "geometry": {"coordinates":[-87.8283,41.9851],"type":"Point"}
}