{
  "type": "Feature",
  "properties": {
    "addr:full":"4502 27th St Moline IL 61265",
    "addr:housenumber":"4502",
    "addr:postcode":"61265",
    "addr:street":"27Th St",
    "iso:country":"US",
    "sg:address":"4502 27th St",
    "sg:city":"Moline",
    "sg:classifiers":[
        {
            "category":"Banks & Credit Unions",
            "subcategory":"Bank",
            "type":"Services"
        }
    ],
    "sg:phone":"+1 309 794 1414",
    "sg:postcode":"61265",
    "sg:province":"IL",
    "sg:tags":[
        "federal",
        "state"
    ],
    "wof:name":"Rock Islnd Pstl Emplyee Crd Un",
    "wof:placetype":"venue"
},
  "geometry": {"coordinates":[-90.499152,41.471202],"type":"Point"}
}