{
  "type": "Feature",
  "properties": {
    "addr:full":"3300 Finley Rd Downers Grove IL 60515",
    "addr:housenumber":"3300",
    "addr:postcode":"60515",
    "addr:street":"Finley Rd",
    "iso:country":"US",
    "sg:address":"3300 Finley Rd",
    "sg:city":"Downers Grove",
    "sg:classifiers":[
        {
            "category":"Shopping",
            "type":"Retail Goods"
        },
        {
            "category":"Shopping",
            "subcategory":"Computers & Home Electronics",
            "type":"Retail Goods"
        }
    ],
    "sg:phone":"+1 630 390 2100",
    "sg:postcode":"60515",
    "sg:province":"IL",
    "sg:tags":[
        "equipment",
        "product",
        "electronic",
        "supply"
    ],
    "wof:name":"Fry's Electronics",
    "wof:placetype":"venue"
},
  "geometry": {"coordinates":[-88.02538699999999,41.827959],"type":"Point"}
}