{
  "type": "Feature",
  "properties": {
    "iso:country":"US",
    "sg:address":"1300 S Wabash Ave",
    "sg:city":"Chicago",
    "sg:classifiers":[
        {
            "category":"Building & Trades",
            "subcategory":"Construction",
            "type":"Services"
        }
    ],
    "sg:phone":"+1 312 408 2000",
    "sg:postcode":"60605",
    "sg:province":"IL",
    "sg:tags":[
        "industrial",
        "contractors-commercial",
        "contractor"
    ],
    "wof:name":"Syte Jenkins Joint Venture",
    "wof:placetype":"venue"
},
  "geometry": {"coordinates":[-87.625778,41.865749],"type":"Point"}
}