{
  "type": "Feature",
  "properties": {
    "iso:country":"US",
    "sg:address":"1318 E State Rte 140",
    "sg:city":"Greenville",
    "sg:classifiers":[
        {
            "category":"Retail",
            "subcategory":"Veterinary Services",
            "type":"Services"
        }
    ],
    "sg:phone":"+1 618 664 4420",
    "sg:postcode":"62246",
    "sg:province":"IL",
    "wof:name":"Countryside Pet Clinic",
    "wof:placetype":"venue"
},
  "geometry": {"coordinates":[-89.394721,38.901803],"type":"Point"}
}