{
  "type": "Feature",
  "properties": {
    "addr:full":"42 E North Ave Northlake IL 60164",
    "addr:housenumber":"42",
    "addr:postcode":"60164",
    "addr:street":"E North Ave",
    "iso:country":"US",
    "sg:address":"42 E North Ave",
    "sg:city":"Northlake",
    "sg:classifiers":[
        {
            "category":"Banks & Credit Unions",
            "subcategory":"Investment Brokerage",
            "type":"Services"
        },
        {
            "category":"Shopping",
            "subcategory":"Computers & Home Electronics",
            "type":"Retail Goods"
        }
    ],
    "sg:phone":"+1 708 562 4169",
    "sg:postcode":"60164",
    "sg:province":"IL",
    "sg:tags":[
        "dvd",
        "video",
        "tape",
        "sale",
        "dvds-rental"
    ],
    "wof:name":"Hollywood Videos",
    "wof:placetype":"venue"
},
  "geometry": {"coordinates":[-87.901151,41.907341],"type":"Point"}
}