{
  "type": "Feature",
  "properties": {
    "addr:full":"8902 N 1850 East Rd Georgetown IL 61846",
    "addr:housenumber":"8902;1850",
    "addr:postcode":"61846",
    "addr:street":"N;East Rd",
    "iso:country":"US",
    "sg:address":"8902 N 1850 East Rd",
    "sg:city":"Georgetown",
    "sg:phone":"+1 217 662 8378",
    "sg:postcode":"61846",
    "sg:province":"IL",
    "sg:tags":[
        "farm",
        "grain",
        "cash"
    ],
    "wof:name":"Elizabeth Ann Smith",
    "wof:placetype":"venue"
},
  "geometry": {"coordinates":[-87.58904,39.999919],"type":"Point"}
}