{
  "type": "Feature",
  "properties": {
    "addr:full":"1430 Hickory St Waukegan IL 60085",
    "addr:housenumber":"1430",
    "addr:postcode":"60085",
    "addr:street":"Hickory St",
    "iso:country":"US",
    "sg:address":"1430 Hickory St",
    "sg:city":"Waukegan",
    "sg:classifiers":[
        {
            "category":"Professional",
            "subcategory":"Detective & Security Services",
            "type":"Services"
        }
    ],
    "sg:phone":"+1 847 623 1160",
    "sg:postcode":"60085",
    "sg:province":"IL",
    "sg:tags":[
        "information",
        "bureau"
    ],
    "wof:name":"Holistic Services Inc",
    "wof:placetype":"venue"
},
  "geometry": {"coordinates":[-87.83732500000001,42.379704],"type":"Point"}
}