{
  "type": "Feature",
  "properties": {
    "addr:full":"5510 N Sheridan Road Chicago IL 60640",
    "addr:housenumber":"5510",
    "addr:postcode":"60640",
    "addr:street":"N Sheridan Road",
    "iso:country":"US",
    "sg:address":"5510 N Sheridan Road",
    "sg:city":"Chicago",
    "sg:classifiers":[
        {
            "category":"Professional",
            "subcategory":"Lawyer & Legal Services",
            "type":"Services"
        }
    ],
    "sg:phone":"+1 773 769 0598",
    "sg:postcode":"60640",
    "sg:province":"IL",
    "wof:name":"Mogul Edward Atty",
    "wof:placetype":"venue"
},
  "geometry": {"coordinates":[-87.663839,41.972603],"type":"Point"}
}