{
  "type": "Feature",
  "properties": {
    "iso:country":"US",
    "sg:address":"1621 S Cicero Ave",
    "sg:city":"Cicero",
    "sg:classifiers":[
        {
            "category":"Health Services",
            "subcategory":"Health Practitioner",
            "type":"Services"
        }
    ],
    "sg:phone":"+1 708 652 1621",
    "sg:postcode":"60804",
    "sg:province":"IL",
    "sg:tags":[
        "therapy",
        "physical"
    ],
    "wof:name":"Accelerated Rehab Centers",
    "wof:placetype":"venue"
},
  "geometry": {"coordinates":[-87.74431,41.858418],"type":"Point"}
}