{
  "type": "Feature",
  "properties": {
    "addr:full":"570 Locust St Elgin IL 60123",
    "addr:housenumber":"570",
    "addr:postcode":"60123",
    "addr:street":"Locust St",
    "iso:country":"US",
    "sg:address":"570 Locust St",
    "sg:city":"Elgin",
    "sg:classifiers":[
        {
            "category":"Professional",
            "type":"Services"
        }
    ],
    "sg:phone":"+1 847 697 6560",
    "sg:postcode":"60123",
    "sg:province":"IL",
    "sg:tags":[
        "establishment"
    ],
    "wof:name":"Quality Clean",
    "wof:placetype":"venue"
},
  "geometry": {"coordinates":[-88.292495,42.031887],"type":"Point"}
}