{
  "type": "Feature",
  "properties": {
    "iso:country":"US",
    "sg:address":"413 Main St",
    "sg:city":"Savanna",
    "sg:classifiers":[
        {
            "category":"Health Services",
            "subcategory":"Optometrist",
            "type":"Services"
        }
    ],
    "sg:phone":"+1 815 273 2422",
    "sg:postcode":"61074",
    "sg:province":"IL",
    "wof:name":"Optometric Center Of Illinois",
    "wof:placetype":"venue"
},
  "geometry": {"coordinates":[-90.156752,42.094445],"type":"Point"}
}