{
  "type": "Feature",
  "properties": {
    "iso:country":"US",
    "sg:address":"232 E Main St",
    "sg:city":"Barrington",
    "sg:classifiers":[
        {
            "category":"Professional",
            "subcategory":"Employment Agencies",
            "type":"Services"
        }
    ],
    "sg:phone":"+1 847 277 0000",
    "sg:postcode":"60010",
    "sg:province":"IL",
    "wof:name":"Izs Executive Search",
    "wof:placetype":"venue"
},
  "geometry": {"coordinates":[-88.133375,42.154277],"type":"Point"}
}