{
  "type": "Feature",
  "properties": {
    "iso:country":"US",
    "sg:address":"17920 Kedzie Ave",
    "sg:city":"Hazel Crest",
    "sg:classifiers":[
        {
            "category":"Freight",
            "type":"Transportation"
        }
    ],
    "sg:phone":"+1 708 798 1863",
    "sg:postcode":"60429",
    "sg:province":"IL",
    "sg:tags":[
        "local",
        "trucking"
    ],
    "wof:name":"Norm Schilling Enterprises",
    "wof:placetype":"venue"
},
  "geometry": {"coordinates":[-87.694382,41.562503],"type":"Point"}
}