{
  "type": "Feature",
  "properties": {
    "iso:country":"US",
    "sg:address":"141 Lochhead Dr",
    "sg:city":"Chester",
    "sg:phone":"+1 618 826 4697",
    "sg:postcode":"62233",
    "sg:province":"IL",
    "sg:tags":[
        "farm",
        "soybean"
    ],
    "wof:name":"Steve Niermann",
    "wof:placetype":"venue"
},
  "geometry": {"coordinates":[-89.83575,37.927606],"type":"Point"}
}