{
  "type": "Feature",
  "properties": {
    "addr:full":"655 Landwehr Rd Northbrook IL 60062",
    "addr:housenumber":"655",
    "addr:postcode":"60062",
    "addr:street":"Landwehr Rd",
    "iso:country":"US",
    "sg:address":"655 Landwehr Rd",
    "sg:city":"Northbrook",
    "sg:classifiers":[
        {
            "category":"Health Services",
            "subcategory":"Health Practitioner",
            "type":"Services"
        }
    ],
    "sg:phone":"+1 847 498 1699",
    "sg:postcode":"60062",
    "sg:province":"IL",
    "wof:name":"North Shore Ctr Cnslng Therapy",
    "wof:placetype":"venue"
},
  "geometry": {"coordinates":[-87.859803,42.141161],"type":"Point"}
}