{
  "type": "Feature",
  "properties": {
    "iso:country":"US",
    "sg:address":"488 W Liberty St",
    "sg:city":"Wauconda",
    "sg:classifiers":[
        {
            "category":"Restaurant",
            "type":"Food & Drink"
        }
    ],
    "sg:phone":"+1 847 526 9797",
    "sg:postcode":"60084",
    "sg:province":"IL",
    "wof:name":"O'Fournos Rotissary Chicken",
    "wof:placetype":"venue"
},
  "geometry": {"coordinates":[-88.15441300000001,42.258088],"type":"Point"}
}