{
  "type": "Feature",
  "properties": {
    "iso:country":"US",
    "sg:address":"2135 175th St",
    "sg:city":"Lansing",
    "sg:classifiers":[
        {
            "category":"Organizations",
            "subcategory":"Religious Organization",
            "type":"Services"
        }
    ],
    "sg:phone":"+1 773 487 8000",
    "sg:postcode":"60438",
    "sg:province":"IL",
    "sg:tags":[
        "church"
    ],
    "wof:name":"Church Of Jesus Christ",
    "wof:placetype":"venue"
},
  "geometry": {"coordinates":[-87.564775,41.577414],"type":"Point"}
}