{
  "type": "Feature",
  "properties": {
    "addr:full":"3825 Highland Ave Downers Grove IL 60515",
    "addr:housenumber":"3825",
    "addr:postcode":"60515",
    "addr:street":"Highland Ave",
    "iso:country":"US",
    "sg:address":"3825 Highland Ave",
    "sg:city":"Downers Grove",
    "sg:classifiers":[
        {
            "category":"Shopping",
            "subcategory":"Pharmacy",
            "type":"Retail Goods"
        }
    ],
    "sg:phone":"+1 630 275 5878",
    "sg:postcode":"60515",
    "sg:province":"IL",
    "wof:name":"Good Samaritan Hospital Phrmcy",
    "wof:placetype":"venue"
},
  "geometry": {"coordinates":[-88.01015700000001,41.818916],"type":"Point"}
}