{
  "type": "Feature",
  "properties": {
    "addr:full":"8549 Primrose Rd Addieville IL 62214",
    "addr:housenumber":"8549",
    "addr:postcode":"62214",
    "addr:street":"Primrose Rd",
    "iso:country":"US",
    "sg:address":"8549 Primrose Rd",
    "sg:city":"Addieville",
    "sg:classifiers":[
        {
            "category":"Farming",
            "subcategory":"Dairy Farm",
            "type":"Manufacturing & Wholesale Goods"
        }
    ],
    "sg:phone":"+1 618 824 6335",
    "sg:postcode":"62214",
    "sg:province":"IL",
    "wof:name":"Schneider Farm",
    "wof:placetype":"venue"
},
  "geometry": {"coordinates":[-89.667142,38.342319],"type":"Point"}
}