{
  "type": "Feature",
  "properties": {
    "addr:full":"1056 Lincoln Hwy Rochelle IL 61068",
    "addr:housenumber":"1056",
    "addr:postcode":"61068",
    "addr:street":"Lincoln Hwy",
    "iso:country":"US",
    "sg:address":"1056 Lincoln Hwy",
    "sg:city":"Rochelle",
    "sg:classifiers":[
        {
            "category":"Health Services",
            "subcategory":"Doctor",
            "type":"Services"
        }
    ],
    "sg:phone":"+1 815 562 2474",
    "sg:postcode":"61068",
    "sg:province":"IL",
    "sg:tags":[
        "dentist"
    ],
    "wof:name":"Scott R Wilson DDS",
    "wof:placetype":"venue"
},
  "geometry": {"coordinates":[-89.066649,41.932603],"type":"Point"}
}