{
  "type": "Feature",
  "properties": {
    "addr:full":"101 American Pride Ln New Lenox IL 60451",
    "addr:housenumber":"101",
    "addr:postcode":"60451",
    "addr:street":"American Pride Ln",
    "iso:country":"US",
    "sg:address":"101 American Pride Ln",
    "sg:city":"New Lenox",
    "sg:classifiers":[
        {
            "category":"Autos & Motor Vehicles",
            "subcategory":"Fuel & Gas Station",
            "type":"Retail Goods"
        }
    ],
    "sg:phone":"+1 815 485 8900",
    "sg:postcode":"60451",
    "sg:province":"IL",
    "sg:tags":[
        "oil"
    ],
    "wof:name":"Mobil Oil Corp",
    "wof:placetype":"venue"
},
  "geometry": {"coordinates":[-87.948308,41.51247],"type":"Point"}
}