{
  "type": "Feature",
  "properties": {
    "iso:country":"US",
    "sg:address":"1116 W Barry Ave",
    "sg:city":"Chicago",
    "sg:classifiers":[
        {
            "category":"Manufacturing",
            "subcategory":"Buildings",
            "type":"Manufacturing & Wholesale Goods"
        },
        {
            "category":"Building & Trades",
            "subcategory":"Construction",
            "type":"Services"
        }
    ],
    "sg:phone":"+1 773 935 6500",
    "sg:postcode":"60657",
    "sg:province":"IL",
    "sg:tags":[
        "altering",
        "home",
        "builder",
        "remodeling",
        "contractor"
    ],
    "wof:name":"Grimsley Group",
    "wof:placetype":"venue"
},
  "geometry": {"coordinates":[-87.657077,41.938014],"type":"Point"}
}