{
  "type": "Feature",
  "properties": {
    "addr:full":"323 W Galena Blvd Aurora IL 60506",
    "addr:housenumber":"323",
    "addr:postcode":"60506",
    "addr:street":"W Galena Blvd",
    "iso:country":"US",
    "sg:address":"323 W Galena Blvd",
    "sg:city":"Aurora",
    "sg:classifiers":[
        {
            "category":"Organizations",
            "subcategory":"Religious Organization",
            "type":"Services"
        }
    ],
    "sg:phone":"+1 630 966 0724",
    "sg:postcode":"60506",
    "sg:province":"IL",
    "sg:tags":[
        "church"
    ],
    "sg:website":"www.house-of-praise.net",
    "wof:name":"House Of Praise Ministries",
    "wof:placetype":"venue"
},
  "geometry": {"coordinates":[-88.321022,41.7607],"type":"Point"}
}