{
  "type": "Feature",
  "properties": {
    "iso:country":"US",
    "sg:address":"2200 Empress Rd",
    "sg:city":"Joliet",
    "sg:classifiers":[
        {
            "category":"Travel",
            "subcategory":"Hotels & Motels",
            "type":"Entertainment"
        }
    ],
    "sg:phone":"+1 815 744 9400",
    "sg:postcode":"60436",
    "sg:province":"IL",
    "wof:name":"Empress Hotel",
    "wof:placetype":"venue"
},
  "geometry": {"coordinates":[-88.165555,41.490035],"type":"Point"}
}