{
  "type": "Feature",
  "properties": {
    "iso:country":"US",
    "sg:address":"2902 Eastrock Dr",
    "sg:city":"Rockford",
    "sg:classifiers":[
        {
            "category":"Manufacturing",
            "subcategory":"Tools & Machinery",
            "type":"Manufacturing & Wholesale Goods"
        },
        {
            "category":"Retail",
            "subcategory":"Repair Shop",
            "type":"Services"
        },
        {
            "category":"Retail",
            "subcategory":"Auto Repair",
            "type":"Services"
        }
    ],
    "sg:phone":"+1 815 226 0016",
    "sg:postcode":"61109",
    "sg:province":"IL",
    "sg:tags":[
        "machine",
        "automobile",
        "machinery-rebuild"
    ],
    "sg:website":"http://www.dialmachine.com",
    "wof:name":"Dial Machine, Inc.",
    "wof:placetype":"venue"
},
  "geometry": {"coordinates":[-89.01247100000001,42.232968],"type":"Point"}
}