{
  "type": "Feature",
  "properties": {
    "iso:country":"US",
    "sg:address":"230 S Wabash Ave Ste 1",
    "sg:city":"Chicago",
    "sg:classifiers":[
        {
            "category":"Retail",
            "subcategory":"Portrait Studio",
            "type":"Services"
        }
    ],
    "sg:phone":"+1 312 427 5580",
    "sg:postcode":"60604",
    "sg:province":"IL",
    "sg:tags":[
        "photography",
        "store"
    ],
    "sg:website":"centralcamera.com",
    "wof:name":"Central Camera Co",
    "wof:placetype":"venue"
},
  "geometry": {"coordinates":[-87.62659499999999,41.878866],"type":"Point"}
}