{
  "type": "Feature",
  "properties": {
    "iso:country":"US",
    "sg:address":"15 Oak Ridge Dr",
    "sg:city":"La Salle",
    "sg:classifiers":[
        {
            "category":"Building & Trades",
            "subcategory":"Plumbing",
            "type":"Services"
        }
    ],
    "sg:phone":"+1 815 223 6400",
    "sg:postcode":"61301",
    "sg:province":"IL",
    "sg:tags":[
        "heating",
        "contractor"
    ],
    "wof:name":"Phelps Energy Svc Inc",
    "wof:placetype":"venue"
},
  "geometry": {"coordinates":[-89.034998,41.347893],"type":"Point"}
}