{
  "type": "Feature",
  "properties": {
    "addr:full":"1257 S Sarah Blvd Vernon Hills IL 60061",
    "addr:housenumber":"1257",
    "addr:postcode":"60061",
    "addr:street":"S Sarah Blvd",
    "iso:country":"US",
    "sg:address":"1257 S Sarah Blvd",
    "sg:city":"Vernon Hills",
    "sg:classifiers":[
        {
            "category":"Autos & Motor Vehicles",
            "subcategory":"Automobile Sales",
            "type":"Retail Goods"
        }
    ],
    "sg:phone":"+1   ",
    "sg:postcode":"60061",
    "sg:province":"IL",
    "sg:tags":[
        "used"
    ],
    "wof:name":"Bavarian Auto Sales",
    "wof:placetype":"venue"
},
  "geometry": {"coordinates":[-87.93753700000001,42.203039],"type":"Point"}
}