{
  "type": "Feature",
  "properties": {
    "iso:country":"US",
    "sg:address":"125 E Central Rd",
    "sg:city":"Arlington Hts",
    "sg:classifiers":[
        {
            "category":"Health Services",
            "subcategory":"Podiatrist",
            "type":"Services"
        }
    ],
    "sg:phone":"+1 847 255 0330",
    "sg:postcode":"60005",
    "sg:province":"IL",
    "wof:name":"Central Podiatry",
    "wof:placetype":"venue"
},
  "geometry": {"coordinates":[-87.982018,42.066524],"type":"Point"}
}