{
  "type": "Feature",
  "properties": {
    "iso:country":"US",
    "sg:address":"4831 Kingston Ave",
    "sg:city":"Lisle",
    "sg:classifiers":[
        {
            "category":"Insurance",
            "subcategory":"Hazard Insurance",
            "type":"Services"
        }
    ],
    "sg:phone":"+1 630 964 2126",
    "sg:postcode":"60532",
    "sg:province":"IL",
    "sg:tags":[
        "fidelity",
        "bond"
    ],
    "wof:name":"Dow Insurance",
    "wof:placetype":"venue"
},
  "geometry": {"coordinates":[-88.067883,41.797114],"type":"Point"}
}