{
  "type": "Feature",
  "properties": {
    "iso:country":"US",
    "sg:address":"4401 20th St",
    "sg:city":"Rockford",
    "sg:classifiers":[
        {
            "category":"Organizations",
            "subcategory":"Religious Organization",
            "type":"Services"
        }
    ],
    "sg:phone":"+1 815 874 9440",
    "sg:postcode":"61109",
    "sg:province":"IL",
    "sg:tags":[
        "church"
    ],
    "wof:name":"Silver Hill Pentecostal Church",
    "wof:placetype":"venue"
},
  "geometry": {"coordinates":[-89.05753199999999,42.219425],"type":"Point"}
}