{
  "type": "Feature",
  "properties": {
    "addr:full":"139 W Elm St Brownstown IL 62418",
    "addr:housenumber":"139",
    "addr:postcode":"62418",
    "addr:street":"W Elm St",
    "iso:country":"US",
    "sg:address":"139 W Elm St",
    "sg:city":"Brownstown",
    "sg:classifiers":[
        {
            "category":"Shopping",
            "subcategory":"Clothing, Apparel, & Fashions",
            "type":"Retail Goods"
        }
    ],
    "sg:phone":"+1 618 427 5340",
    "sg:postcode":"62418",
    "sg:province":"IL",
    "sg:tags":[
        "t"
    ],
    "wof:name":"T's-N-Things",
    "wof:placetype":"venue"
},
  "geometry": {"coordinates":[-88.95298099999999,38.992759],"type":"Point"}
}