{
  "type": "Feature",
  "properties": {
    "iso:country":"US",
    "sg:address":"141 Danada Sq E",
    "sg:city":"Wheaton",
    "sg:classifiers":[
        {
            "category":"Cinema",
            "subcategory":"Movie Rental",
            "type":"Entertainment"
        }
    ],
    "sg:phone":"+1 630 682 1700",
    "sg:postcode":"60187",
    "sg:province":"IL",
    "sg:tags":[
        "video",
        "tape"
    ],
    "wof:name":"Blockbuster",
    "wof:placetype":"venue"
},
  "geometry": {"coordinates":[-88.09987,41.832858],"type":"Point"}
}