{
  "type": "Feature",
  "properties": {
    "addr:full":"114 S Race St Urbana IL 61801",
    "addr:housenumber":"114",
    "addr:postcode":"61801",
    "addr:street":"S Race St",
    "iso:country":"US",
    "sg:address":"114 S Race St",
    "sg:city":"Urbana",
    "sg:classifiers":[
        {
            "category":"Bars & Pubs",
            "type":"Food & Drink"
        }
    ],
    "sg:phone":"+1 217 384 9526",
    "sg:postcode":"61801",
    "sg:province":"IL",
    "sg:tags":[
        "tavern"
    ],
    "wof:name":"Embassy Tavern Inc",
    "wof:placetype":"venue"
},
  "geometry": {"coordinates":[-88.20886,40.111697],"type":"Point"}
}