{
  "type": "Feature",
  "properties": {
    "iso:country":"US",
    "sg:address":"3430 N Southport Ave",
    "sg:city":"Chicago",
    "sg:classifiers":[
        {
            "category":"Restaurant",
            "type":"Food & Drink"
        }
    ],
    "sg:menulink":"http://www.allmenus.com/il/chicago/209656-homemade-pizza-co/menu/",
    "sg:phone":"+1 773 529 5900",
    "sg:postcode":"60657",
    "sg:province":"IL",
    "sg:tags":[
        "american",
        "pizza"
    ],
    "wof:name":"Homemade Pizza Co.",
    "wof:placetype":"venue"
},
  "geometry": {"coordinates":[-87.663927,41.944332],"type":"Point"}
}