{
  "type": "Feature",
  "properties": {
    "iso:country":"US",
    "sg:address":"843 West Chicago Ave",
    "sg:city":"Chicago",
    "sg:classifiers":[
        {
            "category":"Shopping",
            "type":"Retail Goods"
        }
    ],
    "sg:phone":"+1 312 988 7500",
    "sg:postcode":"60622",
    "sg:province":"IL",
    "sg:website":"www.postercorner.com",
    "wof:name":"Vintage Poster Graphics, Inc",
    "wof:placetype":"venue"
},
  "geometry": {"coordinates":[-87.649311,41.896376],"type":"Point"}
}