{
  "type": "Feature",
  "properties": {
    "iso:country":"US",
    "sg:address":"363 Jefferson Ct",
    "sg:city":"Vernon Hills",
    "sg:classifiers":[
        {
            "category":"Wholesale",
            "subcategory":"Hardware",
            "type":"Manufacturing & Wholesale Goods"
        }
    ],
    "sg:phone":"+1 847 459 6410",
    "sg:postcode":"60061",
    "sg:province":"IL",
    "wof:name":"Bella Star",
    "wof:placetype":"venue"
},
  "geometry": {"coordinates":[-87.973217,42.244185],"type":"Point"}
}