{
  "type": "Feature",
  "properties": {
    "iso:country":"US",
    "sg:address":"2227 N Central Ave",
    "sg:city":"Rockford",
    "sg:classifiers":[
        {
            "category":"Retail",
            "subcategory":"Repair Shop",
            "type":"Services"
        }
    ],
    "sg:phone":"+1 815 962 9319",
    "sg:postcode":"61101",
    "sg:province":"IL",
    "wof:name":"T-Boys Product Inc",
    "wof:placetype":"venue"
},
  "geometry": {"coordinates":[-89.116413,42.302927],"type":"Point"}
}