{
  "type": "Feature",
  "properties": {
    "addr:full":"2227 N Central Ave Rockford IL 61101",
    "addr:housenumber":"2227",
    "addr:postcode":"61101",
    "addr:street":"N Central Ave",
    "iso:country":"US",
    "sg:address":"2227 N Central Ave",
    "sg:city":"Rockford",
    "sg:classifiers":[
        {
            "category":"Retail",
            "subcategory":"Repair Shop",
            "type":"Services"
        }
    ],
    "sg:phone":"+1 815 962 9319",
    "sg:postcode":"61101",
    "sg:province":"IL",
    "wof:name":"T-Boys Product Inc",
    "wof:placetype":"venue"
},
  "geometry": {"coordinates":[-89.11641299999999,42.302927],"type":"Point"}
}