{
  "type": "Feature",
  "properties": {
    "iso:country":"US",
    "sg:address":"5836 Monroe St",
    "sg:city":"Morton Grove",
    "sg:classifiers":[
        {
            "category":"Banks & Credit Unions",
            "subcategory":"Investment Brokerage",
            "type":"Services"
        }
    ],
    "sg:phone":"+1 847 965 2511",
    "sg:postcode":"60053",
    "sg:province":"IL",
    "sg:tags":[
        "trader",
        "commodity"
    ],
    "wof:name":"Jpd Enterprises Inc",
    "wof:placetype":"venue"
},
  "geometry": {"coordinates":[-87.77340599999999,42.031035],"type":"Point"}
}