{
  "type": "Feature",
  "properties": {
    "addr:full":"75 W Harrison St Chicago IL 60605",
    "addr:housenumber":"75",
    "addr:postcode":"60605",
    "addr:street":"W Harrison St",
    "iso:country":"US",
    "sg:address":"75 W Harrison St",
    "sg:city":"Chicago",
    "sg:classifiers":[
        {
            "category":"Restaurant",
            "type":"Food & Drink"
        }
    ],
    "sg:phone":"+1 312 447 1000",
    "sg:postcode":"60605",
    "sg:province":"IL",
    "sg:tags":[
        "style",
        "family",
        "lunch",
        "american",
        "brunch",
        "breakfast"
    ],
    "wof:name":"Orange",
    "wof:placetype":"venue"
},
  "geometry": {"coordinates":[-87.63003999999999,41.874527],"type":"Point"}
}