{
  "type": "Feature",
  "properties": {
    "iso:country":"US",
    "sg:address":"8812 Klamath Rd",
    "sg:city":"Argenta",
    "sg:classifiers":[
        {
            "category":"Professional",
            "type":"Services"
        }
    ],
    "sg:phone":"+1 217 795 4400",
    "sg:postcode":"62501",
    "sg:province":"IL",
    "wof:name":"Melistymart Oreana Ill LLC",
    "wof:placetype":"venue"
},
  "geometry": {"coordinates":[-88.773855,39.957354],"type":"Point"}
}