{
  "type": "Feature",
  "properties": {
    "iso:country":"US",
    "sg:address":"497 20th Ave",
    "sg:city":"Roseville",
    "sg:classifiers":[
        {
            "category":"Manufacturing",
            "subcategory":"Food",
            "type":"Manufacturing & Wholesale Goods"
        },
        {
            "category":"Farming",
            "subcategory":"Farm",
            "type":"Manufacturing & Wholesale Goods"
        }
    ],
    "sg:phone":"+1 309 774 4235",
    "sg:postcode":"61473",
    "sg:province":"IL",
    "sg:tags":[
        "corn",
        "product"
    ],
    "wof:name":"Jim Grant",
    "wof:placetype":"venue"
},
  "geometry": {"coordinates":[-90.692874,40.661289],"type":"Point"}
}