{
  "type": "Feature",
  "properties": {
    "iso:country":"US",
    "sg:address":"3860 Swanson Ct",
    "sg:city":"Gurnee",
    "sg:classifiers":[
        {
            "category":"Retail",
            "subcategory":"Auto Repair",
            "type":"Services"
        }
    ],
    "sg:phone":"+1 847 249 2929",
    "sg:postcode":"60031",
    "sg:province":"IL",
    "sg:tags":[
        "body",
        "repairing",
        "classic",
        "automobile",
        "painting",
        "restoration-antique"
    ],
    "sg:website":"http://www.posematosbodyworks.net",
    "wof:name":"Posemato's BodyWorks & Restorations",
    "wof:placetype":"venue"
},
  "geometry": {"coordinates":[-87.895405,42.387387],"type":"Point"}
}