{
  "type": "Feature",
  "properties": {
    "addr:full":"6737 S Pulaski Rd Chicago IL 60629",
    "addr:housenumber":"6737",
    "addr:postcode":"60629",
    "addr:street":"S Pulaski Rd",
    "iso:country":"US",
    "sg:address":"6737 S Pulaski Rd",
    "sg:city":"Chicago",
    "sg:classifiers":[
        {
            "category":"Fast Food",
            "type":"Food & Drink"
        }
    ],
    "sg:phone":"+1 773 284 9350",
    "sg:postcode":"60629",
    "sg:province":"IL",
    "sg:tags":[
        "burger"
    ],
    "sg:website":"www.mcdonalds.com",
    "wof:name":"McDonald's",
    "wof:placetype":"venue"
},
  "geometry": {"coordinates":[-87.72229799999999,41.7701],"type":"Point"}
}