{
  "type": "Feature",
  "properties": {
    "iso:country":"US",
    "sg:address":"1142 S Ridgeland Ave",
    "sg:city":"Oak Park",
    "sg:classifiers":[
        {
            "category":"Building & Trades",
            "subcategory":"Electrical",
            "type":"Services"
        }
    ],
    "sg:phone":"+1 708 848 5125",
    "sg:postcode":"60304",
    "sg:province":"IL",
    "sg:tags":[
        "electrical",
        "contractor"
    ],
    "wof:name":"Fifth Avenue Electric Co",
    "wof:placetype":"venue"
},
  "geometry": {"coordinates":[-87.783998,41.868747],"type":"Point"}
}