{
  "type": "Feature",
  "properties": {
    "iso:country":"US",
    "sg:address":"115 Jefferson Dr",
    "sg:city":"Breese",
    "sg:classifiers":[
        {
            "category":"Building & Trades",
            "subcategory":"Construction",
            "type":"Services"
        }
    ],
    "sg:phone":"+1 618 526 8273",
    "sg:postcode":"62230",
    "sg:province":"IL",
    "sg:tags":[
        "painting",
        "contractor"
    ],
    "wof:name":"T & M Taping & Painting",
    "wof:placetype":"venue"
},
  "geometry": {"coordinates":[-89.508264,38.607046],"type":"Point"}
}