{
  "type": "Feature",
  "properties": {
    "addr:full":"1120 Warren Ave Downers Grove IL 60515",
    "addr:housenumber":"1120",
    "addr:postcode":"60515",
    "addr:street":"Warren Ave",
    "iso:country":"US",
    "sg:address":"1120 Warren Ave",
    "sg:city":"Downers Grove",
    "sg:classifiers":[
        {
            "category":"Real Estate",
            "subcategory":"Real Estate Operator",
            "type":"Services"
        }
    ],
    "sg:phone":"+1 630 964 6600",
    "sg:postcode":"60515",
    "sg:province":"IL",
    "sg:tags":[
        "building",
        "apartment"
    ],
    "wof:name":"Oak Tree Towers",
    "wof:placetype":"venue"
},
  "geometry": {"coordinates":[-88.01351,41.796282],"type":"Point"}
}