{
  "type": "Feature",
  "properties": {
    "iso:country":"US",
    "sg:address":"12808 S Ashland Ave",
    "sg:city":"Calumet Park",
    "sg:classifiers":[
        {
            "category":"Travel",
            "subcategory":"Hotels & Motels",
            "type":"Entertainment"
        }
    ],
    "sg:phone":"+1 708 385 9100",
    "sg:postcode":"60827",
    "sg:province":"IL",
    "wof:name":"Heritage Inn",
    "wof:placetype":"venue"
},
  "geometry": {"coordinates":[-87.66104900000001,41.660936],"type":"Point"}
}