{
  "type": "Feature",
  "properties": {
    "addr:full":"6 E 2300 North Rd Danforth IL 60930",
    "addr:housenumber":"6",
    "addr:postcode":"2300;60930",
    "addr:street":"E;North Rd",
    "iso:country":"US",
    "sg:address":"6 E 2300 North Rd",
    "sg:city":"Danforth",
    "sg:phone":"+1 815 686 2647",
    "sg:postcode":"60930",
    "sg:province":"IL",
    "sg:tags":[
        "hog",
        "farm",
        "corn",
        "soybean",
        "or",
        "feedlot"
    ],
    "wof:name":"Cor-By Farms",
    "wof:placetype":"venue"
},
  "geometry": {"coordinates":[-88.10994700000001,40.836594],"type":"Point"}
}