{
  "type": "Feature",
  "properties": {
    "addr:full":"525 Winsor Dr Antioch IL 60002",
    "addr:housenumber":"525",
    "addr:postcode":"60002",
    "addr:street":"Winsor Dr",
    "iso:country":"US",
    "sg:address":"525 Winsor Dr",
    "sg:city":"Antioch",
    "sg:classifiers":[
        {
            "category":"Professional",
            "subcategory":"Management & Consulting",
            "type":"Services"
        }
    ],
    "sg:phone":"+1 847 395 7204",
    "sg:postcode":"60002",
    "sg:province":"IL",
    "sg:tags":[
        "business"
    ],
    "wof:name":"James K Beatty",
    "wof:placetype":"venue"
},
  "geometry": {"coordinates":[-88.099799,42.484179],"type":"Point"}
}