{
  "type": "Feature",
  "properties": {
    "iso:country":"US",
    "sg:address":"141 W Jackson Boulevard Suite 3602",
    "sg:city":"Chicago",
    "sg:classifiers":[
        {
            "category":"Banks & Credit Unions",
            "subcategory":"Financial Services",
            "type":"Services"
        }
    ],
    "sg:phone":"+1 312 669 0808",
    "sg:postcode":"60604",
    "sg:province":"IL",
    "sg:tags":[
        "broker",
        "mortgage"
    ],
    "wof:name":"Hawthorne Financial",
    "wof:placetype":"venue"
},
  "geometry": {"coordinates":[-87.6297,41.877516],"type":"Point"}
}