{
  "type": "Feature",
  "properties": {
    "addr:full":"419 Burnley Cir Schaumburg IL 60193",
    "addr:housenumber":"419",
    "addr:postcode":"60193",
    "addr:street":"Burnley Cir",
    "iso:country":"US",
    "sg:address":"419 Burnley Cir",
    "sg:city":"Schaumburg",
    "sg:classifiers":[
        {
            "category":"Personal",
            "subcategory":"Beauty Salon",
            "type":"Services"
        }
    ],
    "sg:phone":"+1 847 352 4002",
    "sg:postcode":"60193",
    "sg:province":"IL",
    "sg:tags":[
        "manicuring"
    ],
    "wof:name":"Golden Hands Inc",
    "wof:placetype":"venue"
},
  "geometry": {"coordinates":[-88.069236,42.022442],"type":"Point"}
}