{
  "type": "Feature",
  "properties": {
    "iso:country":"US",
    "sg:address":"107 5th St",
    "sg:city":"Colona",
    "sg:classifiers":[
        {
            "category":"Autos & Motor Vehicles",
            "subcategory":"Automobile Sales",
            "type":"Retail Goods"
        }
    ],
    "sg:phone":"+1   ",
    "sg:postcode":"61241",
    "sg:province":"IL",
    "sg:tags":[
        "used"
    ],
    "wof:name":"Auto Trend Car Sales",
    "wof:placetype":"venue"
},
  "geometry": {"coordinates":[-90.363891,41.481877],"type":"Point"}
}