{
  "type": "Feature",
  "properties": {
    "addr:full":"453 Waukegan Rd Northbrook IL 60062",
    "addr:housenumber":"453",
    "addr:postcode":"60062",
    "addr:street":"Waukegan Rd",
    "iso:country":"US",
    "sg:address":"453 Waukegan Rd",
    "sg:city":"Northbrook",
    "sg:classifiers":[
        {
            "category":"Food & Beverages",
            "subcategory":"Bakery",
            "type":"Retail Goods"
        }
    ],
    "sg:phone":"+1   ",
    "sg:postcode":"60062",
    "sg:province":"IL",
    "wof:name":"Sara Lee Bakery Outlet",
    "wof:placetype":"venue"
},
  "geometry": {"coordinates":[-87.83034499999999,42.145352],"type":"Point"}
}