{
  "type": "Feature",
  "properties": {
    "addr:full":"2217 S Perryville Rd Rockford IL 61108",
    "addr:housenumber":"2217",
    "addr:postcode":"61108",
    "addr:street":"S Perryville Rd",
    "iso:country":"US",
    "sg:address":"2217 S Perryville Rd",
    "sg:city":"Rockford",
    "sg:classifiers":[
        {
            "category":"Shopping",
            "subcategory":"Tobacco",
            "type":"Retail Goods"
        }
    ],
    "sg:phone":"+1 815 332 4656",
    "sg:postcode":"61108",
    "sg:province":"IL",
    "sg:tags":[
        "cigarette",
        "cigar",
        "dealer"
    ],
    "wof:name":"Tinder Box",
    "wof:placetype":"venue"
},
  "geometry": {"coordinates":[-88.97998699999999,42.243439],"type":"Point"}
}