{
  "type": "Feature",
  "properties": {
    "addr:full":"5200 Main St Skokie IL 60077",
    "addr:housenumber":"5200",
    "addr:postcode":"60077",
    "addr:street":"Main St",
    "iso:country":"US",
    "sg:address":"5200 Main St",
    "sg:city":"Skokie",
    "sg:classifiers":[
        {
            "category":"Professional",
            "subcategory":"Accounting & Tax Preparation",
            "type":"Services"
        }
    ],
    "sg:phone":"+1 847 679 0181",
    "sg:postcode":"60077",
    "sg:province":"IL",
    "wof:name":"Levin Mark I CPA PC",
    "wof:placetype":"venue"
},
  "geometry": {"coordinates":[-87.758245,42.033604],"type":"Point"}
}