{
  "type": "Feature",
  "properties": {
    "addr:full":"3774 N Clark St Chicago IL 60613",
    "addr:housenumber":"3774",
    "addr:postcode":"60613",
    "addr:street":"N Clark St",
    "iso:country":"US",
    "sg:address":"3774 N Clark St",
    "sg:city":"Chicago",
    "sg:classifiers":[
        {
            "category":"Retail",
            "subcategory":"Laundry & Dry Cleaning",
            "type":"Services"
        }
    ],
    "sg:phone":"+1 773 404 0497",
    "sg:postcode":"60613",
    "sg:province":"IL",
    "wof:name":"Wrigleyview Cleaners",
    "wof:placetype":"venue"
},
  "geometry": {"coordinates":[-87.659302,41.950901],"type":"Point"}
}