{
  "type": "Feature",
  "properties": {
    "iso:country":"US",
    "sg:address":"730 W Randolph St Ste 6",
    "sg:city":"Chicago",
    "sg:classifiers":[
        {
            "category":"Professional",
            "subcategory":"Lawyer & Legal Services",
            "type":"Services"
        }
    ],
    "sg:phone":"+1 312 454 0015",
    "sg:postcode":"60661",
    "sg:province":"IL",
    "wof:name":"Synergy Law Group",
    "wof:placetype":"venue"
},
  "geometry": {"coordinates":[-87.64679700000001,41.884399],"type":"Point"}
}