{
  "type": "Feature",
  "properties": {
    "addr:full":"893 Industrial Dr Elmhurst IL 60126",
    "addr:housenumber":"893",
    "addr:postcode":"60126",
    "addr:street":"Industrial Dr",
    "iso:country":"US",
    "sg:address":"893 Industrial Dr",
    "sg:city":"Elmhurst",
    "sg:classifiers":[
        {
            "category":"Building & Trades",
            "subcategory":"Construction",
            "type":"Services"
        }
    ],
    "sg:phone":"+1 630 559 8060",
    "sg:postcode":"60126",
    "sg:province":"IL",
    "sg:tags":[
        "contractor"
    ],
    "wof:name":"FPI",
    "wof:placetype":"venue"
},
  "geometry": {"coordinates":[-87.946265,41.927132],"type":"Point"}
}