{
  "type": "Feature",
  "properties": {
    "addr:full":"1870 Coleta Rd Tampico IL 61283",
    "addr:postcode":"1870;61283",
    "addr:street":"Coleta Rd",
    "iso:country":"US",
    "sg:address":"1870 Coleta Rd",
    "sg:city":"Tampico",
    "sg:classifiers":[
        {
            "category":"Manufacturing",
            "subcategory":"Tools & Machinery",
            "type":"Manufacturing & Wholesale Goods"
        }
    ],
    "sg:phone":"+1 815 438 6431",
    "sg:postcode":"61283",
    "sg:province":"IL",
    "sg:tags":[
        "repair",
        "power",
        "mfg",
        "fluid",
        "general",
        "mach"
    ],
    "wof:name":"Farm Track Mch & Hydraulic Sp",
    "wof:placetype":"venue"
},
  "geometry": {"coordinates":[-89.804815,41.602637],"type":"Point"}
}