{
  "type": "Feature",
  "properties": {
    "iso:country":"US",
    "sg:address":"2716 Grovelin St",
    "sg:city":"Godfrey",
    "sg:phone":"+1 618 467 9999",
    "sg:postcode":"62035",
    "sg:province":"IL",
    "wof:name":"Carvers",
    "wof:placetype":"venue"
},
  "geometry": {"coordinates":[-90.188507,38.922309],"type":"Point"}
}