{
  "type": "Feature",
  "properties": {
    "addr:full":"421 Brown Blvd Bourbonnais IL 60914",
    "addr:housenumber":"421",
    "addr:postcode":"60914",
    "addr:street":"Brown Blvd",
    "iso:country":"US",
    "sg:address":"421 Brown Blvd",
    "sg:city":"Bourbonnais",
    "sg:classifiers":[
        {
            "category":"Banks & Credit Unions",
            "subcategory":"Bank",
            "type":"Services"
        }
    ],
    "sg:phone":"+1 815 937 1300",
    "sg:postcode":"60914",
    "sg:province":"IL",
    "wof:name":"Capstone Bank, National Association",
    "wof:placetype":"venue"
},
  "geometry": {"coordinates":[-87.883683,41.158298],"type":"Point"}
}