{
  "type": "Feature",
  "properties": {
    "iso:country":"US",
    "sg:address":"1401 May Ave",
    "sg:city":"Mc Henry",
    "sg:classifiers":[
        {
            "category":"Personal",
            "subcategory":"Beauty Salon",
            "type":"Services"
        }
    ],
    "sg:phone":"+1 815 385 5725",
    "sg:postcode":"60051",
    "sg:province":"IL",
    "sg:tags":[
        "shop"
    ],
    "wof:name":"Independent Beauty Consul",
    "wof:placetype":"venue"
},
  "geometry": {"coordinates":[-88.223742,42.390329],"type":"Point"}
}