{
  "type": "Feature",
  "properties": {
    "addr:full":"108 S Main St Albany IL 61230",
    "addr:housenumber":"108",
    "addr:postcode":"61230",
    "addr:street":"S Main St",
    "iso:country":"US",
    "sg:address":"108 S Main St",
    "sg:city":"Albany",
    "sg:classifiers":[
        {
            "category":"Restaurant",
            "type":"Food & Drink"
        }
    ],
    "sg:phone":"+1 309 887 4320",
    "sg:postcode":"61230",
    "sg:province":"IL",
    "wof:name":"Julies Cafe",
    "wof:placetype":"venue"
},
  "geometry": {"coordinates":[-90.22187599999999,41.788876],"type":"Point"}
}