{
  "type": "Feature",
  "properties": {
    "iso:country":"US",
    "sg:address":"3906 N Main St",
    "sg:city":"Rockford",
    "sg:classifiers":[
        {
            "category":"Health Services",
            "subcategory":"Doctor",
            "type":"Services"
        }
    ],
    "sg:phone":"+1 815 282 0159",
    "sg:postcode":"61103",
    "sg:province":"IL",
    "sg:tags":[
        "medical"
    ],
    "wof:name":"Pedro De Guzman Jr MD",
    "wof:placetype":"venue"
},
  "geometry": {"coordinates":[-89.077347,42.317891],"type":"Point"}
}