{
  "type": "Feature",
  "properties": {
    "addr:full":"6500 S Cottage Grove Avenue Chicago IL 60637",
    "addr:housenumber":"6500",
    "addr:postcode":"60637",
    "addr:street":"S Cottage Grove Avenue",
    "iso:country":"US",
    "sg:address":"6500 S Cottage Grove Avenue",
    "sg:city":"Chicago",
    "sg:classifiers":[
        {
            "category":"Restaurant",
            "type":"Food & Drink"
        }
    ],
    "sg:phone":"+1 773 955 4333",
    "sg:postcode":"60637",
    "sg:province":"IL",
    "wof:name":"Jamaican Jerk Choice Restaurant",
    "wof:placetype":"venue"
},
  "geometry": {"coordinates":[-87.605906,41.776282],"type":"Point"}
}