{
  "type": "Feature",
  "properties": {
    "iso:country":"US",
    "sg:address":"1551 Plainfield Rd Ste D",
    "sg:city":"Joliet",
    "sg:classifiers":[
        {
            "category":"Personal",
            "subcategory":"Beauty Salon",
            "type":"Services"
        }
    ],
    "sg:phone":"+1 815 725 4198",
    "sg:postcode":"60435",
    "sg:province":"IL",
    "sg:tags":[
        "hair",
        "stylist"
    ],
    "wof:name":"Sochic Hair Salon",
    "wof:placetype":"venue"
},
  "geometry": {"coordinates":[-88.120045,41.551088],"type":"Point"}
}