{
  "type": "Feature",
  "properties": {
    "iso:country":"US",
    "sg:address":"725 Kent St",
    "sg:city":"Rockford",
    "sg:classifiers":[
        {
            "category":"Restaurant",
            "type":"Food & Drink"
        }
    ],
    "sg:phone":"+1   ",
    "sg:postcode":"61102",
    "sg:province":"IL",
    "sg:tags":[
        "eating"
    ],
    "wof:name":"Zammuto Drive-Inn",
    "wof:placetype":"venue"
},
  "geometry": {"coordinates":[-89.10649,42.263644],"type":"Point"}
}