{
  "type": "Feature",
  "properties": {
    "addr:full":"755 Bennett Ave Oglesby IL 61348",
    "addr:housenumber":"755",
    "addr:postcode":"61348",
    "addr:street":"Bennett Ave",
    "iso:country":"US",
    "sg:address":"755 Bennett Ave",
    "sg:city":"Oglesby",
    "sg:classifiers":[
        {
            "category":"Education",
            "subcategory":"School",
            "type":"Public Place"
        }
    ],
    "sg:phone":"+1 815 883 8932",
    "sg:postcode":"61348",
    "sg:province":"IL",
    "wof:name":"Lincoln School",
    "wof:placetype":"venue"
},
  "geometry": {"coordinates":[-89.070526,41.306815],"type":"Point"}
}