{
  "type": "Feature",
  "properties": {
    "iso:country":"US",
    "sg:address":"998 Robin Ln",
    "sg:city":"Arcola",
    "sg:classifiers":[
        {
            "category":"Retail",
            "subcategory":"Auto Repair",
            "type":"Services"
        }
    ],
    "sg:phone":"+1 217 268 3638",
    "sg:postcode":"61910",
    "sg:province":"IL",
    "sg:tags":[
        "repairing",
        "automobile",
        "general"
    ],
    "wof:name":"Shammy's Shade Tree",
    "wof:placetype":"venue"
},
  "geometry": {"coordinates":[-88.284667,39.6828],"type":"Point"}
}