{
  "type": "Feature",
  "properties": {
    "iso:country":"US",
    "sg:address":"2502 S Race St",
    "sg:city":"Urbana",
    "sg:classifiers":[
        {
            "category":"Organizations",
            "subcategory":"Religious Organization",
            "type":"Services"
        }
    ],
    "sg:phone":"+1 217 344 5455",
    "sg:postcode":"61801",
    "sg:province":"IL",
    "sg:tags":[
        "k",
        "church",
        "day",
        "care"
    ],
    "wof:name":"Urbana Assembly of God",
    "wof:placetype":"venue"
},
  "geometry": {"coordinates":[-88.209358,40.08486],"type":"Point"}
}