{
  "type": "Feature",
  "properties": {
    "iso:country":"US",
    "sg:address":"6504 Fernwood Dr",
    "sg:city":"Lisle",
    "sg:classifiers":[
        {
            "category":"Professional",
            "subcategory":"Advertising",
            "type":"Services"
        }
    ],
    "sg:phone":"+1 630 430 6897",
    "sg:postcode":"60532",
    "sg:province":"IL",
    "sg:tags":[
        "telemarketing"
    ],
    "wof:name":"Cms",
    "wof:placetype":"venue"
},
  "geometry": {"coordinates":[-88.10111999999999,41.766731],"type":"Point"}
}