{
  "type": "Feature",
  "properties": {
    "addr:full":"2502 Lockner Blvd Joliet IL 60431",
    "addr:housenumber":"2502",
    "addr:postcode":"60431",
    "addr:street":"Lockner Blvd",
    "iso:country":"US",
    "sg:address":"2502 Lockner Blvd",
    "sg:city":"Joliet",
    "sg:classifiers":[
        {
            "category":"Shopping",
            "subcategory":"Gifts & Souvenirs",
            "type":"Retail Goods"
        }
    ],
    "sg:phone":"+1   ",
    "sg:postcode":"60431",
    "sg:province":"IL",
    "wof:name":"All Chicago Sport Card",
    "wof:placetype":"venue"
},
  "geometry": {"coordinates":[-88.1725,41.571428],"type":"Point"}
}