{
  "type": "Feature",
  "properties": {
    "iso:country":"US",
    "sg:address":"800 Edwards Dr Apt A",
    "sg:city":"Glenview",
    "sg:classifiers":[
        {
            "category":"Shopping",
            "type":"Retail Goods"
        }
    ],
    "sg:phone":"+1 847 729 8304",
    "sg:postcode":"60026",
    "sg:province":"IL",
    "sg:tags":[
        "merchandising"
    ],
    "wof:name":"Quixtar Inc",
    "wof:placetype":"venue"
},
  "geometry": {"coordinates":[-87.83446499999999,42.093643],"type":"Point"}
}