{
  "type": "Feature",
  "properties": {
    "addr:full":"1010 Dewey Ave Kewanee IL 61443",
    "addr:housenumber":"1010",
    "addr:postcode":"61443",
    "addr:street":"Dewey Ave",
    "iso:country":"US",
    "sg:address":"1010 Dewey Ave",
    "sg:city":"Kewanee",
    "sg:classifiers":[
        {
            "category":"Freight",
            "type":"Transportation"
        }
    ],
    "sg:phone":"+1 309 852 0925",
    "sg:postcode":"61443",
    "sg:province":"IL",
    "sg:tags":[
        "commercial",
        "storage"
    ],
    "wof:name":"West End Storage",
    "wof:placetype":"venue"
},
  "geometry": {"coordinates":[-89.946895,41.233595],"type":"Point"}
}