{
  "type": "Feature",
  "properties": {
    "iso:country":"US",
    "sg:address":"119 Bethel Dr",
    "sg:city":"Bourbonnais",
    "sg:classifiers":[
        {
            "category":"Organizations",
            "subcategory":"Religious Organization",
            "type":"Services"
        }
    ],
    "sg:phone":"+1 815 932 9814",
    "sg:postcode":"60914",
    "sg:province":"IL",
    "sg:website":"www.bethelbourbonnais.org",
    "wof:name":"Bethel Baptist Church",
    "wof:placetype":"venue"
},
  "geometry": {"coordinates":[-87.87724900000001,41.170068],"type":"Point"}
}