{
  "type": "Feature",
  "properties": {
    "iso:country":"US",
    "sg:address":"12858 Western Ave",
    "sg:city":"Blue Island",
    "sg:classifiers":[
        {
            "category":"Retail",
            "subcategory":"Repair Shop",
            "type":"Services"
        }
    ],
    "sg:phone":"+1 708 389 3232",
    "sg:postcode":"60406",
    "sg:province":"IL",
    "sg:tags":[
        "key",
        "locksmith"
    ],
    "wof:name":"Certified Locksmithing",
    "wof:placetype":"venue"
},
  "geometry": {"coordinates":[-87.680199,41.659302],"type":"Point"}
}