{
  "type": "Feature",
  "properties": {
    "iso:country":"US",
    "sg:address":"3036 W Chicago Ave",
    "sg:city":"Chicago",
    "sg:classifiers":[
        {
            "category":"Real Estate",
            "subcategory":"Real Estate Services",
            "type":"Services"
        }
    ],
    "sg:phone":"+1 773 826 8957",
    "sg:postcode":"60622",
    "sg:province":"IL",
    "sg:tags":[
        "apartment",
        "vacancy",
        "listing",
        "rental",
        "finder"
    ],
    "wof:name":"The Sop Studios",
    "wof:placetype":"venue"
},
  "geometry": {"coordinates":[-87.702957,41.895625],"type":"Point"}
}