{
  "type": "Feature",
  "properties": {
    "addr:full":"557 N Hicks Rd Palatine IL 60067",
    "addr:housenumber":"557",
    "addr:postcode":"60067",
    "addr:street":"N Hicks Rd",
    "iso:country":"US",
    "sg:address":"557 N Hicks Rd",
    "sg:city":"Palatine",
    "sg:classifiers":[
        {
            "category":"Social Services",
            "subcategory":"Child Care",
            "type":"Services"
        }
    ],
    "sg:phone":"+1 847 359 5437",
    "sg:postcode":"60067",
    "sg:province":"IL",
    "sg:tags":[
        "center",
        "day"
    ],
    "wof:name":"Learning Loft Inc",
    "wof:placetype":"venue"
},
  "geometry": {"coordinates":[-88.033815,42.119945],"type":"Point"}
}