{
  "type": "Feature",
  "properties": {
    "iso:country":"US",
    "sg:address":"4935 Dempster St",
    "sg:city":"Skokie",
    "sg:classifiers":[
        {
            "category":"Shopping",
            "subcategory":"Jewelry",
            "type":"Retail Goods"
        },
        {
            "category":"Manufacturing",
            "subcategory":"Jewelry",
            "type":"Manufacturing & Wholesale Goods"
        }
    ],
    "sg:phone":"+1 847 677 4288",
    "sg:postcode":"60077",
    "sg:province":"IL",
    "sg:tags":[
        "designer",
        "jeweler"
    ],
    "wof:name":"Norman's Jewelry",
    "wof:placetype":"venue"
},
  "geometry": {"coordinates":[-87.75067900000001,42.040792],"type":"Point"}
}