{
  "type": "Feature",
  "properties": {
    "addr:full":"1847 Armour Rd Bourbonnais IL 60914",
    "addr:housenumber":"1847",
    "addr:postcode":"60914",
    "addr:street":"Armour Rd",
    "iso:country":"US",
    "sg:address":"1847 Armour Rd",
    "sg:city":"Bourbonnais",
    "sg:classifiers":[
        {
            "category":"Freight",
            "type":"Transportation"
        }
    ],
    "sg:phone":"+1 815 928 5000",
    "sg:postcode":"60914",
    "sg:province":"IL",
    "sg:tags":[
        "commercial",
        "storage"
    ],
    "wof:name":"Central Self Storage",
    "wof:placetype":"venue"
},
  "geometry": {"coordinates":[-87.853672,41.162711],"type":"Point"}
}