{
  "type": "Feature",
  "properties": {
    "addr:full":"566 Cambridge Ave Elmhurst IL 60126",
    "addr:housenumber":"566",
    "addr:postcode":"60126",
    "addr:street":"Cambridge Ave",
    "iso:country":"US",
    "sg:address":"566 Cambridge Ave",
    "sg:city":"Elmhurst",
    "sg:classifiers":[
        {
            "category":"Professional",
            "subcategory":"Management & Consulting",
            "type":"Services"
        }
    ],
    "sg:phone":"+1 630 941 1696",
    "sg:postcode":"60126",
    "sg:province":"IL",
    "wof:name":"Precision Products & Service",
    "wof:placetype":"venue"
},
  "geometry": {"coordinates":[-87.93371500000001,41.882858],"type":"Point"}
}