{
  "type": "Feature",
  "properties": {
    "addr:full":"820 N Orleans St Chicago IL 60610",
    "addr:housenumber":"820",
    "addr:postcode":"60610",
    "addr:street":"N Orleans St",
    "iso:country":"US",
    "sg:address":"820 N Orleans St",
    "sg:city":"Chicago",
    "sg:classifiers":[
        {
            "category":"Education",
            "subcategory":"Special Training",
            "type":"Public Place"
        }
    ],
    "sg:phone":"+1 312 440 3440",
    "sg:postcode":"60610",
    "sg:province":"IL",
    "sg:tags":[
        "educational"
    ],
    "wof:name":"Landmark Education",
    "wof:placetype":"venue"
},
  "geometry": {"coordinates":[-87.63716700000001,41.897134],"type":"Point"}
}