{
  "type": "Feature",
  "properties": {
    "iso:country":"US",
    "sg:address":"805 Seibert Rd",
    "sg:city":"Belleville",
    "sg:classifiers":[
        {
            "category":"Food & Beverages",
            "subcategory":"Specialty",
            "type":"Retail Goods"
        },
        {
            "category":"Wholesale",
            "subcategory":"Groceries",
            "type":"Manufacturing & Wholesale Goods"
        }
    ],
    "sg:phone":"+1 618 746 4294",
    "sg:postcode":"62225",
    "sg:province":"IL",
    "sg:tags":[
        "oriental",
        "general"
    ],
    "wof:name":"International Oriental Fd Mkt",
    "wof:placetype":"venue"
},
  "geometry": {"coordinates":[-89.871886,38.548372],"type":"Point"}
}