{
  "type": "Feature",
  "properties": {
    "iso:country":"US",
    "sg:address":"3805 S Rising Rd",
    "sg:city":"Champaign",
    "sg:phone":"+1 217 352 2744",
    "sg:postcode":"61822",
    "sg:province":"IL",
    "sg:tags":[
        "farm",
        "corn",
        "soybean"
    ],
    "wof:name":"Betty R Barnes-Gaitros",
    "wof:placetype":"venue"
},
  "geometry": {"coordinates":[-88.33390900000001,40.161836],"type":"Point"}
}