{
  "type": "Feature",
  "properties": {
    "iso:country":"US",
    "sg:address":"1138 Wayne Ave",
    "sg:city":"Deerfield",
    "sg:classifiers":[
        {
            "category":"Retail",
            "subcategory":"Auto Repair",
            "type":"Services"
        }
    ],
    "sg:phone":"+1 847 374 9427",
    "sg:postcode":"60015",
    "sg:province":"IL",
    "sg:tags":[
        "general"
    ],
    "wof:name":"Nates Garage",
    "wof:placetype":"venue"
},
  "geometry": {"coordinates":[-87.857303,42.174518],"type":"Point"}
}