{
  "type": "Feature",
  "properties": {
    "iso:country":"US",
    "sg:address":"800 S Oak Park Ave",
    "sg:city":"Oak Park",
    "sg:classifiers":[
        {
            "category":"Building & Trades",
            "subcategory":"Construction",
            "type":"Services"
        }
    ],
    "sg:phone":"+1 708 524 0970",
    "sg:postcode":"60304",
    "sg:province":"IL",
    "sg:tags":[
        "carpentry",
        "contractor",
        "furniture"
    ],
    "wof:name":"Icon",
    "wof:placetype":"venue"
},
  "geometry": {"coordinates":[-87.794007,41.872797],"type":"Point"}
}