{
  "type": "Feature",
  "properties": {
    "iso:country":"US",
    "sg:address":"1726 Main St",
    "sg:city":"Alton",
    "sg:classifiers":[
        {
            "category":"Personal",
            "subcategory":"Beauty Salon",
            "type":"Services"
        }
    ],
    "sg:phone":"+1 618 465 9121",
    "sg:postcode":"62002",
    "sg:province":"IL",
    "sg:tags":[
        "shop"
    ],
    "wof:name":"Solutions Hair & Nail Salon",
    "wof:placetype":"venue"
},
  "geometry": {"coordinates":[-90.148229,38.904636],"type":"Point"}
}