{
  "type": "Feature",
  "properties": {
    "iso:country":"US",
    "sg:address":"6000 W 79th St Ste 103",
    "sg:city":"Burbank",
    "sg:classifiers":[
        {
            "category":"Insurance",
            "subcategory":"Hazard Insurance",
            "type":"Services"
        }
    ],
    "sg:phone":"+1 708 237 3700",
    "sg:postcode":"60459",
    "sg:province":"IL",
    "sg:tags":[
        "commercial",
        "business"
    ],
    "wof:name":"Globe Insurance Agency",
    "wof:placetype":"venue"
},
  "geometry": {"coordinates":[-87.77089700000001,41.748631],"type":"Point"}
}