{
  "type": "Feature",
  "properties": {
    "iso:country":"US",
    "sg:address":"723 Wiltshire Ct",
    "sg:city":"Crystal Lake",
    "sg:classifiers":[
        {
            "category":"Professional",
            "subcategory":"Computer Services",
            "type":"Services"
        }
    ],
    "sg:phone":"+1 815 455 6837",
    "sg:postcode":"60014",
    "sg:province":"IL",
    "sg:tags":[
        "processing",
        "datum"
    ],
    "wof:name":"Ontime Data Solutions",
    "wof:placetype":"venue"
},
  "geometry": {"coordinates":[-88.325132,42.220833],"type":"Point"}
}