{
  "type": "Feature",
  "properties": {
    "iso:country":"US",
    "sg:address":"320 W Union St",
    "sg:city":"West Union",
    "sg:classifiers":[
        {
            "category":"Utilities",
            "subcategory":"Fuel Oil & Lpg",
            "type":"Services"
        }
    ],
    "sg:phone":"+1 217 279 3612",
    "sg:postcode":"62477",
    "sg:province":"IL",
    "sg:tags":[
        "propane",
        "gas"
    ],
    "wof:name":"Ferrellgas",
    "wof:placetype":"venue"
},
  "geometry": {"coordinates":[-87.669177,39.215895],"type":"Point"}
}