{
  "type": "Feature",
  "properties": {
    "addr:full":"24157 Apple Creek Ln Plainfield IL 60586",
    "addr:housenumber":"24157",
    "addr:postcode":"60586",
    "addr:street":"Apple Creek Ln",
    "iso:country":"US",
    "sg:address":"24157 Apple Creek Ln",
    "sg:city":"Plainfield",
    "sg:classifiers":[
        {
            "category":"Professional",
            "subcategory":"Business Services",
            "type":"Services"
        }
    ],
    "sg:phone":"+1 708 305 1987",
    "sg:postcode":"60586",
    "sg:province":"IL",
    "sg:tags":[
        "holding"
    ],
    "wof:name":"O'malley Holdings",
    "wof:placetype":"venue"
},
  "geometry": {"coordinates":[-88.205626,41.582075],"type":"Point"}
}