{
  "type": "Feature",
  "properties": {
    "iso:country":"US",
    "sg:address":"11372 Bridgeport Pl",
    "sg:city":"Belvidere",
    "sg:classifiers":[
        {
            "category":"Manufacturing",
            "subcategory":"Rubber & Plastics",
            "type":"Manufacturing & Wholesale Goods"
        }
    ],
    "sg:phone":"+1 815 885 3965",
    "sg:postcode":"61008",
    "sg:province":"IL",
    "sg:tags":[
        "product",
        "mfg"
    ],
    "wof:name":"Tri-Glass Plastics Inc",
    "wof:placetype":"venue"
},
  "geometry": {"coordinates":[-88.926777,42.316393],"type":"Point"}
}