{
  "type": "Feature",
  "properties": {
    "iso:country":"US",
    "sg:address":"799 River Oaks Dr",
    "sg:city":"Calumet City",
    "sg:classifiers":[
        {
            "category":"Restaurant",
            "type":"Food & Drink"
        }
    ],
    "sg:menulink":"http://www.allmenus.com/il/thornton/174903-popeyes-chicken--biscuits/menu/",
    "sg:phone":"+1 708 891 0020",
    "sg:postcode":"60409",
    "sg:province":"IL",
    "sg:tags":[
        "american",
        "wing"
    ],
    "wof:name":"Popeyes Chicken & Biscuits",
    "wof:placetype":"venue"
},
  "geometry": {"coordinates":[-87.54446,41.600785],"type":"Point"}
}