{
  "type": "Feature",
  "properties": {
    "iso:country":"US",
    "sg:address":"4404 Mccauley Rd",
    "sg:city":"Woodstock",
    "sg:classifiers":[
        {
            "category":"Building & Trades",
            "subcategory":"Construction",
            "type":"Services"
        }
    ],
    "sg:phone":"+1 815 382 4828",
    "sg:postcode":"60098",
    "sg:province":"IL",
    "sg:tags":[
        "repair",
        "handyman",
        "maintenance",
        "home"
    ],
    "wof:name":"Jims Handyman Services",
    "wof:placetype":"venue"
},
  "geometry": {"coordinates":[-88.47709399999999,42.389781],"type":"Point"}
}