{
  "type": "Feature",
  "properties": {
    "addr:full":"2147 S Lumber St Unit 219 Chicago IL 60616",
    "addr:housenumber":"2147;219",
    "addr:postcode":"60616",
    "addr:street":"S Lumber St Unit",
    "iso:country":"US",
    "sg:address":"2147 S Lumber St Unit 219",
    "sg:city":"Chicago",
    "sg:classifiers":[
        {
            "category":"Sports & Exercise",
            "subcategory":"Gym",
            "type":"Entertainment"
        }
    ],
    "sg:phone":"+1 708 310 0987",
    "sg:postcode":"60616",
    "sg:province":"IL",
    "sg:tags":[
        "trainer"
    ],
    "sg:website":"www.kobrafitness.net",
    "wof:name":"Kobra Fitness",
    "wof:placetype":"venue"
},
  "geometry": {"coordinates":[-87.64068,41.853495],"type":"Point"}
}