{
  "type": "Feature",
  "properties": {
    "addr:full":"2146 W Division St Chicago IL 60622",
    "addr:housenumber":"2146",
    "addr:postcode":"60622",
    "addr:street":"W Division St",
    "iso:country":"US",
    "sg:address":"2146 W Division St",
    "sg:city":"Chicago",
    "sg:classifiers":[
        {
            "category":"Restaurant",
            "type":"Food & Drink"
        }
    ],
    "sg:menulink":"http://www.allmenus.com/il/chicago/272863-enoteca-roma/menu/",
    "sg:phone":"+1 773 342 1011",
    "sg:postcode":"60622",
    "sg:province":"IL",
    "sg:tags":[
        "italian"
    ],
    "wof:name":"Enoteca Roma",
    "wof:placetype":"venue"
},
  "geometry": {"coordinates":[-87.68086599999999,41.903246],"type":"Point"}
}