{
  "type": "Feature",
  "properties": {
    "iso:country":"US",
    "sg:address":"213 S Larkin Ave",
    "sg:city":"Joliet",
    "sg:classifiers":[
        {
            "category":"Restaurant",
            "type":"Food & Drink"
        }
    ],
    "sg:phone":"+1 815 725 0802",
    "sg:postcode":"60436",
    "sg:province":"IL",
    "wof:name":"J & J Fish",
    "wof:placetype":"venue"
},
  "geometry": {"coordinates":[-88.12460799999999,41.519239],"type":"Point"}
}