{
  "type": "Feature",
  "properties": {
    "iso:country":"US",
    "sg:address":"1200 W Hawthorne Lane",
    "sg:city":"West Chicago",
    "sg:classifiers":[
        {
            "category":"Bars & Pubs",
            "type":"Food & Drink"
        },
        {
            "category":"Restaurant",
            "type":"Food & Drink"
        }
    ],
    "sg:phone":"+1 630 293 6700",
    "sg:postcode":"60185",
    "sg:province":"IL",
    "sg:website":"www.hawthornesbackyard.com/",
    "wof:name":"Hawthorne's Backyard Bar & Grill",
    "wof:placetype":"venue"
},
  "geometry": {"coordinates":[-88.22479800000001,41.899399],"type":"Point"}
}