{
  "type": "Feature",
  "properties": {
    "iso:country":"US",
    "sg:address":"853 Spring Ridge Ct",
    "sg:city":"Belvidere",
    "sg:classifiers":[
        {
            "category":"Professional",
            "subcategory":"Research",
            "type":"Services"
        }
    ],
    "sg:phone":"+1 815 885 2088",
    "sg:postcode":"61008",
    "sg:province":"IL",
    "sg:tags":[
        "commercial",
        "physical"
    ],
    "wof:name":"Powernetics Inc",
    "wof:placetype":"venue"
},
  "geometry": {"coordinates":[-88.92303699999999,42.302637],"type":"Point"}
}