{
  "type": "Feature",
  "properties": {
    "addr:full":"2507 Grand Ave Waukegan IL 60085",
    "addr:housenumber":"2507",
    "addr:postcode":"60085",
    "addr:street":"Grand Ave",
    "iso:country":"US",
    "sg:address":"2507 Grand Ave",
    "sg:city":"Waukegan",
    "sg:classifiers":[
        {
            "category":"Autos & Motor Vehicles",
            "subcategory":"Auto Supplies",
            "type":"Retail Goods"
        }
    ],
    "sg:phone":"+1 847 360 0012",
    "sg:postcode":"60085",
    "sg:province":"IL",
    "sg:tags":[
        "automobile",
        "parts"
    ],
    "wof:name":"Murray's Discount Auto Store",
    "wof:placetype":"venue"
},
  "geometry": {"coordinates":[-87.86532200000001,42.370241],"type":"Point"}
}