{
  "type": "Feature",
  "properties": {
    "iso:country":"US",
    "sg:address":"729 Larry Power Rd",
    "sg:city":"Bourbonnais",
    "sg:classifiers":[
        {
            "category":"Professional",
            "subcategory":"Employment Agencies",
            "type":"Services"
        }
    ],
    "sg:phone":"+1 815 935 3288",
    "sg:postcode":"60914",
    "sg:province":"IL",
    "sg:tags":[
        "help",
        "contractor"
    ],
    "wof:name":"Triangle Employment Svc Inc",
    "wof:placetype":"venue"
},
  "geometry": {"coordinates":[-87.864727,41.177301],"type":"Point"}
}