{
  "type": "Feature",
  "properties": {
    "addr:full":"525 E Irving Park Rd Roselle IL 60172",
    "addr:housenumber":"525",
    "addr:postcode":"60172",
    "addr:street":"E Irving Park Rd",
    "iso:country":"US",
    "sg:address":"525 E Irving Park Rd",
    "sg:city":"Roselle",
    "sg:classifiers":[
        {
            "category":"Food & Beverages",
            "subcategory":"Supermarket",
            "type":"Retail Goods"
        },
        {
            "category":"Food & Beverages",
            "subcategory":"Groceries & Convenience Stores",
            "type":"Retail Goods"
        }
    ],
    "sg:phone":"+1 630 529 5901",
    "sg:postcode":"60172",
    "sg:province":"IL",
    "sg:tags":[
        "super"
    ],
    "wof:name":"Pik-Kwik Foods",
    "wof:placetype":"venue"
},
  "geometry": {"coordinates":[-88.068703,41.9813],"type":"Point"}
}