{
  "type": "Feature",
  "properties": {
    "iso:country":"US",
    "sg:address":"242 Perth Rd",
    "sg:city":"Cary",
    "sg:classifiers":[
        {
            "category":"Professional",
            "subcategory":"Computer Services",
            "type":"Services"
        }
    ],
    "sg:phone":"+1 847 639 5531",
    "sg:postcode":"60013",
    "sg:province":"IL",
    "sg:tags":[
        "consultant",
        "designer"
    ],
    "wof:name":"Microview Technologies Inc",
    "wof:placetype":"venue"
},
  "geometry": {"coordinates":[-88.246752,42.203808],"type":"Point"}
}