{
  "type": "Feature",
  "properties": {
    "iso:country":"US",
    "sg:address":"1776 S Hance Dr",
    "sg:city":"Freeport",
    "sg:classifiers":[
        {
            "category":"Professional",
            "type":"Services"
        },
        {
            "category":"Health Services",
            "subcategory":"Clinic",
            "type":"Services"
        }
    ],
    "sg:phone":"+1 815 235 7920",
    "sg:postcode":"61032",
    "sg:province":"IL",
    "sg:tags":[
        "agency",
        "welfare"
    ],
    "wof:name":"Bethesda Lutheran Hm & Svc Inc",
    "wof:placetype":"venue"
},
  "geometry": {"coordinates":[-89.635679,42.276993],"type":"Point"}
}