{
  "type": "Feature",
  "properties": {
    "addr:full":"939 Arlington Heights Rd Arlington Heights IL 60005",
    "addr:housenumber":"939",
    "addr:postcode":"60005",
    "addr:street":"Arlington Heights Rd",
    "iso:country":"US",
    "sg:address":"939 Arlington Heights Rd",
    "sg:city":"Arlington Heights",
    "sg:classifiers":[
        {
            "category":"Building & Trades",
            "subcategory":"Construction",
            "type":"Services"
        }
    ],
    "sg:phone":"+1 312 909 5315",
    "sg:postcode":"60005",
    "sg:province":"IL",
    "sg:tags":[
        "contractor"
    ],
    "wof:name":"Identity Sign & Lighting",
    "wof:placetype":"venue"
},
  "geometry": {"coordinates":[-87.98013899999999,42.067257],"type":"Point"}
}