{
  "type": "Feature",
  "properties": {
    "addr:full":"1414 Taft Ave Wheaton IL 60187",
    "addr:housenumber":"1414",
    "addr:postcode":"60187",
    "addr:street":"Taft Ave",
    "iso:country":"US",
    "sg:address":"1414 Taft Ave",
    "sg:city":"Wheaton",
    "sg:classifiers":[
        {
            "category":"Building & Trades",
            "subcategory":"Plumbing",
            "type":"Services"
        }
    ],
    "sg:phone":"+1 630 682 0001",
    "sg:postcode":"60187",
    "sg:province":"IL",
    "sg:tags":[
        "contractor"
    ],
    "wof:name":"Aris",
    "wof:placetype":"venue"
},
  "geometry": {"coordinates":[-88.08481,41.858129],"type":"Point"}
}