{
  "type": "Feature",
  "properties": {
    "addr:full":"40 Dakota Rd Carbondale IL 62902",
    "addr:housenumber":"40",
    "addr:postcode":"62902",
    "addr:street":"Dakota Rd",
    "iso:country":"US",
    "sg:address":"40 Dakota Rd",
    "sg:city":"Carbondale",
    "sg:classifiers":[
        {
            "category":"Professional",
            "subcategory":"Accounting & Tax Preparation",
            "type":"Services"
        }
    ],
    "sg:phone":"+1 618 457 8132",
    "sg:postcode":"62902",
    "sg:province":"IL",
    "wof:name":"Susan M Daily",
    "wof:placetype":"venue"
},
  "geometry": {"coordinates":[-89.209479,37.688906],"type":"Point"}
}