{
  "type": "Feature",
  "properties": {
    "iso:country":"US",
    "sg:address":"8103 Wilmot Rd",
    "sg:city":"Spring Grove",
    "sg:classifiers":[
        {
            "category":"Retail",
            "subcategory":"Funeral Services",
            "type":"Services"
        }
    ],
    "sg:phone":"+1 815 675 0550",
    "sg:postcode":"60081",
    "sg:province":"IL",
    "sg:tags":[
        "chapel"
    ],
    "wof:name":"Spring Grove Funeral Chapel",
    "wof:placetype":"venue"
},
  "geometry": {"coordinates":[-88.217655,42.439029],"type":"Point"}
}