{
  "type": "Feature",
  "properties": {
    "iso:country":"US",
    "sg:address":"3737 Gina Ter",
    "sg:city":"Rockford",
    "sg:classifiers":[
        {
            "category":"Shopping",
            "subcategory":"Clothing, Apparel, & Fashions",
            "type":"Retail Goods"
        }
    ],
    "sg:phone":"+1   ",
    "sg:postcode":"61114",
    "sg:province":"IL",
    "wof:name":"Puu Gear",
    "wof:placetype":"venue"
},
  "geometry": {"coordinates":[-89.040357,42.30917],"type":"Point"}
}