{
  "type": "Feature",
  "properties": {
    "addr:full":"203 N la Salle St # 2100 Chicago IL 60601",
    "addr:housenumber":"203",
    "addr:postcode":"60601",
    "addr:street":"N La Salle St # 2100",
    "iso:country":"US",
    "sg:address":"203 N la Salle St # 2100",
    "sg:city":"Chicago",
    "sg:classifiers":[
        {
            "category":"Professional",
            "subcategory":"Lawyer & Legal Services",
            "type":"Services"
        }
    ],
    "sg:phone":"+1 312 558 1361",
    "sg:postcode":"60601",
    "sg:province":"IL",
    "sg:tags":[
        "clinic"
    ],
    "wof:name":"Beringer & Associates",
    "wof:placetype":"venue"
},
  "geometry": {"coordinates":[-87.632378,41.885811],"type":"Point"}
}