{
  "type": "Feature",
  "properties": {
    "addr:full":"1812 Washington Blvd Maywood IL 60153",
    "addr:housenumber":"1812",
    "addr:postcode":"60153",
    "addr:street":"Washington Blvd",
    "iso:country":"US",
    "sg:address":"1812 Washington Blvd",
    "sg:city":"Maywood",
    "sg:classifiers":[
        {
            "category":"Education",
            "subcategory":"College",
            "type":"Public Place"
        }
    ],
    "sg:phone":"+1 708 681 0281",
    "sg:postcode":"60153",
    "sg:province":"IL",
    "sg:tags":[
        "housing",
        "student"
    ],
    "wof:name":"Delta Sigma Theta Sororit",
    "wof:placetype":"venue"
},
  "geometry": {"coordinates":[-87.85526299999999,41.882227],"type":"Point"}
}