{
  "type": "Feature",
  "properties": {
    "addr:full":"2800 W 55th Street Chicago IL 60632",
    "addr:housenumber":"2800",
    "addr:postcode":"60632",
    "addr:street":"W 55Th Street",
    "iso:country":"US",
    "sg:address":"2800 W 55th Street",
    "sg:city":"Chicago",
    "sg:classifiers":[
        {
            "category":"Autos & Motor Vehicles",
            "subcategory":"Fuel & Gas Station",
            "type":"Retail Goods"
        }
    ],
    "sg:phone":"+1 773 476 3619",
    "sg:postcode":"60632",
    "sg:province":"IL",
    "wof:name":"We R 7",
    "wof:placetype":"venue"
},
  "geometry": {"coordinates":[-87.693809,41.7937],"type":"Point"}
}