{
  "type": "Feature",
  "properties": {
    "addr:full":"306 N River St Aurora IL 60506",
    "addr:housenumber":"306",
    "addr:postcode":"60506",
    "addr:street":"N River St",
    "iso:country":"US",
    "sg:address":"306 N River St",
    "sg:city":"Aurora",
    "sg:classifiers":[
        {
            "category":"Travel",
            "subcategory":"Hotels & Motels",
            "type":"Entertainment"
        }
    ],
    "sg:phone":"+1 630 892 3700",
    "sg:postcode":"60506",
    "sg:province":"IL",
    "wof:name":"Fox River Hotel",
    "wof:placetype":"venue"
},
  "geometry": {"coordinates":[-88.31385899999999,41.762364],"type":"Point"}
}