{
  "type": "Feature",
  "properties": {
    "addr:full":"562 Stonegate Ter Glencoe IL 60022",
    "addr:housenumber":"562",
    "addr:postcode":"60022",
    "addr:street":"Stonegate Ter",
    "iso:country":"US",
    "sg:address":"562 Stonegate Ter",
    "sg:city":"Glencoe",
    "sg:classifiers":[
        {
            "category":"Professional",
            "subcategory":"Testing Lab",
            "type":"Services"
        }
    ],
    "sg:phone":"+1 847 835 0120",
    "sg:postcode":"60022",
    "sg:province":"IL",
    "sg:tags":[
        "chemist"
    ],
    "wof:name":"Chemgate Inc",
    "wof:placetype":"venue"
},
  "geometry": {"coordinates":[-87.770369,42.134414],"type":"Point"}
}