{
  "type": "Feature",
  "properties": {
    "iso:country":"US",
    "sg:address":"15215 Eyre Cir",
    "sg:city":"Plainfield",
    "sg:classifiers":[
        {
            "category":"Building & Trades",
            "subcategory":"Construction",
            "type":"Services"
        }
    ],
    "sg:phone":"+1 815 577 9858",
    "sg:postcode":"60544",
    "sg:province":"IL",
    "sg:tags":[
        "altering",
        "remodeling",
        "contractor"
    ],
    "wof:name":"Aaction Home Repair",
    "wof:placetype":"venue"
},
  "geometry": {"coordinates":[-88.21596,41.603615],"type":"Point"}
}