{
  "type": "Feature",
  "properties": {
    "addr:full":"1343 S Lewis Ave Waukegan IL 60085",
    "addr:housenumber":"1343",
    "addr:postcode":"60085",
    "addr:street":"S Lewis Ave",
    "iso:country":"US",
    "sg:address":"1343 S Lewis Ave",
    "sg:city":"Waukegan",
    "sg:classifiers":[
        {
            "category":"Autos & Motor Vehicles",
            "subcategory":"Fuel & Gas Station",
            "type":"Retail Goods"
        },
        {
            "category":"Food & Beverages",
            "subcategory":"Groceries & Convenience Stores",
            "type":"Retail Goods"
        }
    ],
    "sg:phone":"+1 847 599 1578",
    "sg:postcode":"60085",
    "sg:province":"IL",
    "wof:name":"J N Mini Mart",
    "wof:placetype":"venue"
},
  "geometry": {"coordinates":[-87.855881,42.33516],"type":"Point"}
}