{
  "type": "Feature",
  "properties": {
    "addr:full":"2142 S Archer Ave Chicago IL 60616",
    "addr:housenumber":"2142",
    "addr:postcode":"60616",
    "addr:street":"S Archer Ave",
    "iso:country":"US",
    "sg:address":"2142 S Archer Ave",
    "sg:city":"Chicago",
    "sg:classifiers":[
        {
            "category":"Health Services",
            "subcategory":"Clinic",
            "type":"Services"
        },
        {
            "category":"Health Services",
            "subcategory":"Nursing And Care Facility",
            "type":"Services"
        },
        {
            "category":"Health Services",
            "subcategory":"Health Practitioner",
            "type":"Services"
        },
        {
            "category":"Health Services",
            "subcategory":"Hospice",
            "type":"Services"
        }
    ],
    "sg:phone":"+1 312 842 8889",
    "sg:postcode":"60616",
    "sg:province":"IL",
    "sg:tags":[
        "home",
        "eldercare-home",
        "welfare"
    ],
    "wof:name":"National Home Health Care Svc",
    "wof:placetype":"venue"
},
  "geometry": {"coordinates":[-87.63386,41.853318],"type":"Point"}
}