{
  "type": "Feature",
  "properties": {
    "iso:country":"US",
    "sg:address":"2800 Seminary St",
    "sg:city":"Alton",
    "sg:classifiers":[
        {
            "category":"Building & Trades",
            "subcategory":"Construction",
            "type":"Services"
        }
    ],
    "sg:phone":"+1 618 462 4110",
    "sg:postcode":"62002",
    "sg:province":"IL",
    "sg:tags":[
        "excavation",
        "demolition"
    ],
    "wof:name":"Midwest Grinding",
    "wof:placetype":"venue"
},
  "geometry": {"coordinates":[-90.142319,38.919025],"type":"Point"}
}