{
  "type": "Feature",
  "properties": {
    "iso:country":"US",
    "sg:address":"309 S Mccoy St",
    "sg:city":"Granville",
    "sg:classifiers":[
        {
            "category":"Health Services",
            "subcategory":"Doctor",
            "type":"Services"
        }
    ],
    "sg:phone":"+1 815 339 6245",
    "sg:postcode":"61326",
    "sg:province":"IL",
    "sg:tags":[
        "physician",
        "family",
        "practice",
        "surgeons",
        "medicine",
        "surgeon"
    ],
    "wof:name":"Bailey Shawn MD",
    "wof:placetype":"venue"
},
  "geometry": {"coordinates":[-89.228081,41.26099],"type":"Point"}
}