{
  "type": "Feature",
  "properties": {
    "iso:country":"US",
    "sg:address":"528 S Main St",
    "sg:city":"Princeton",
    "sg:classifiers":[
        {
            "category":"Shopping",
            "subcategory":"Gifts & Souvenirs",
            "type":"Retail Goods"
        }
    ],
    "sg:phone":"+1 815 875 2793",
    "sg:postcode":"61356",
    "sg:province":"IL",
    "sg:tags":[
        "shop"
    ],
    "wof:name":"Lodestone",
    "wof:placetype":"venue"
},
  "geometry": {"coordinates":[-89.465113,41.370084],"type":"Point"}
}