{
  "type": "Feature",
  "properties": {
    "addr:full":"6161 N Broadway St Chicago IL 60660",
    "addr:housenumber":"6161",
    "addr:postcode":"60660",
    "addr:street":"N Broadway St",
    "iso:country":"US",
    "sg:address":"6161 N Broadway St",
    "sg:city":"Chicago",
    "sg:classifiers":[
        {
            "category":"Professional",
            "subcategory":"Business Services",
            "type":"Services"
        }
    ],
    "sg:phone":"+1 312 236 3838",
    "sg:postcode":"60660",
    "sg:province":"IL",
    "wof:name":"Adams Press",
    "wof:placetype":"venue"
},
  "geometry": {"coordinates":[-87.660307,41.993729],"type":"Point"}
}