{
  "type": "Feature",
  "properties": {
    "iso:country":"US",
    "sg:address":"21950 S Old Rand Rd",
    "sg:city":"Lake Zurich",
    "sg:classifiers":[
        {
            "category":"Freight",
            "type":"Transportation"
        }
    ],
    "sg:phone":"+1 847 438 5911",
    "sg:postcode":"60047",
    "sg:province":"IL",
    "sg:tags":[
        "general"
    ],
    "wof:name":"Drake Enterprises",
    "wof:placetype":"venue"
},
  "geometry": {"coordinates":[-88.079449,42.182208],"type":"Point"}
}