{
  "type": "Feature",
  "properties": {
    "addr:full":"12803 Irving Ave Blue Island IL 60406",
    "addr:housenumber":"12803",
    "addr:postcode":"60406",
    "addr:street":"Irving Ave",
    "iso:country":"US",
    "sg:address":"12803 Irving Ave",
    "sg:city":"Blue Island",
    "sg:classifiers":[
        {
            "category":"Arena",
            "subcategory":"Sports Club",
            "type":"Entertainment"
        }
    ],
    "sg:phone":"+1 708 389 3343",
    "sg:postcode":"60406",
    "sg:province":"IL",
    "sg:tags":[
        "association"
    ],
    "wof:name":"Club Morelia Inc",
    "wof:placetype":"venue"
},
  "geometry": {"coordinates":[-87.676534,41.659936],"type":"Point"}
}