{
  "type": "Feature",
  "properties": {
    "addr:full":"3302 W Glenlake Ave Chicago IL 60659",
    "addr:housenumber":"3302",
    "addr:postcode":"60659",
    "addr:street":"W Glenlake Ave",
    "iso:country":"US",
    "sg:address":"3302 W Glenlake Ave",
    "sg:city":"Chicago",
    "sg:classifiers":[
        {
            "category":"Taxi",
            "type":"Transportation"
        }
    ],
    "sg:phone":"+1 773 267 5178",
    "sg:postcode":"60659",
    "sg:province":"IL",
    "sg:tags":[
        "taxicab"
    ],
    "wof:name":"Assets Investment Taxi Cab",
    "wof:placetype":"venue"
},
  "geometry": {"coordinates":[-87.712131,41.992139],"type":"Point"}
}