{
  "type": "Feature",
  "properties": {
    "addr:full":"750 Chestnut Ave Park City IL 60085",
    "addr:housenumber":"750",
    "addr:postcode":"60085",
    "addr:street":"Chestnut Ave",
    "iso:country":"US",
    "sg:address":"750 Chestnut Ave",
    "sg:city":"Park City",
    "sg:classifiers":[
        {
            "category":"Wholesale",
            "subcategory":"Groceries",
            "type":"Manufacturing & Wholesale Goods"
        }
    ],
    "sg:phone":"+1 847 263 0700",
    "sg:postcode":"60085",
    "sg:province":"IL",
    "sg:tags":[
        "beverage"
    ],
    "sg:website":"www.cokecce.com",
    "wof:name":"Coca-Cola Bottling Co",
    "wof:placetype":"venue"
},
  "geometry": {"coordinates":[-87.885082,42.346993],"type":"Point"}
}