{
  "type": "Feature",
  "properties": {
    "iso:country":"US",
    "sg:address":"2601 W Peterson Avenue",
    "sg:city":"Chicago",
    "sg:classifiers":[
        {
            "category":"Autos & Motor Vehicles",
            "subcategory":"Automobile Sales",
            "type":"Retail Goods"
        },
        {
            "category":"Taxi",
            "type":"Transportation"
        },
        {
            "category":"Retail",
            "subcategory":"Auto Rental",
            "type":"Services"
        },
        {
            "category":"Local Transit",
            "type":"Transportation"
        }
    ],
    "sg:phone":"+1 773 561 6600",
    "sg:postcode":"60659",
    "sg:province":"IL",
    "sg:tags":[
        "shuttle",
        "limousine",
        "limo"
    ],
    "wof:name":"A Top Hat Limousine Corporation",
    "wof:placetype":"venue"
},
  "geometry": {"coordinates":[-87.694638,41.990245],"type":"Point"}
}