{
  "type": "Feature",
  "properties": {
    "iso:country":"US",
    "sg:address":"2443 W 16th St",
    "sg:city":"Chicago",
    "sg:classifiers":[
        {
            "category":"Coffee & Tea",
            "type":"Food & Drink"
        }
    ],
    "sg:phone":"+1 312 432 9644",
    "sg:postcode":"60608",
    "sg:province":"IL",
    "sg:website":"www.starbucks.com",
    "wof:name":"Starbucks",
    "wof:placetype":"venue"
},
  "geometry": {"coordinates":[-87.686605,41.859365],"type":"Point"}
}