{
  "type": "Feature",
  "properties": {
    "addr:full":"150 Hastings Dr Buffalo Grove IL 60089",
    "addr:housenumber":"150",
    "addr:postcode":"60089",
    "addr:street":"Hastings Dr",
    "iso:country":"US",
    "sg:address":"150 Hastings Dr",
    "sg:city":"Buffalo Grove",
    "sg:classifiers":[
        {
            "category":"Freight",
            "type":"Transportation"
        }
    ],
    "sg:phone":"+1 847 808 0123",
    "sg:postcode":"60089",
    "sg:province":"IL",
    "sg:tags":[
        "opera",
        "arrangement",
        "local",
        "trucking"
    ],
    "wof:name":"Graebel Movers Intl Inc",
    "wof:placetype":"venue"
},
  "geometry": {"coordinates":[-87.939189,42.155985],"type":"Point"}
}