{
  "type": "Feature",
  "properties": {
    "addr:full":"2100 N Lincoln Park W Cs Chicago IL 60614",
    "addr:housenumber":"2100",
    "addr:postcode":"60614",
    "addr:street":"N Lincoln Park W Cs",
    "iso:country":"US",
    "sg:address":"2100 N Lincoln Park W Cs",
    "sg:city":"Chicago",
    "sg:classifiers":[
        {
            "category":"Communications",
            "subcategory":"Film & Video Production",
            "type":"Services"
        }
    ],
    "sg:phone":"+1 773 871 8483",
    "sg:postcode":"60614",
    "sg:province":"IL",
    "sg:tags":[
        "services-commercial"
    ],
    "wof:name":"Evidence Video",
    "wof:placetype":"venue"
},
  "geometry": {"coordinates":[-87.641319,41.920109],"type":"Point"}
}