{
  "type": "Feature",
  "properties": {
    "iso:country":"US",
    "sg:address":"1309 Caton Ave",
    "sg:city":"Joliet",
    "sg:classifiers":[
        {
            "category":"Professional",
            "type":"Services"
        }
    ],
    "sg:phone":"+1 815 730 9534",
    "sg:postcode":"60435",
    "sg:province":"IL",
    "sg:tags":[
        "caterer"
    ],
    "wof:name":"Dukes Catering",
    "wof:placetype":"venue"
},
  "geometry": {"coordinates":[-88.113439,41.534713],"type":"Point"}
}