{
  "type": "Feature",
  "properties": {
    "iso:country":"US",
    "sg:address":"308 Bethany Park Dr",
    "sg:city":"Rantoul",
    "sg:classifiers":[
        {
            "category":"Social Services",
            "subcategory":"Child Care",
            "type":"Services"
        }
    ],
    "sg:phone":"+1 217 892 4308",
    "sg:postcode":"61866",
    "sg:province":"IL",
    "sg:tags":[
        "nursery",
        "day"
    ],
    "wof:name":"Sharon Abner",
    "wof:placetype":"venue"
},
  "geometry": {"coordinates":[-88.133788,40.313314],"type":"Point"}
}