{
  "type": "Feature",
  "properties": {
    "iso:country":"US",
    "sg:address":"214 W Washington St",
    "sg:city":"Ottawa",
    "sg:classifiers":[
        {
            "category":"Personal",
            "subcategory":"Barber",
            "type":"Services"
        }
    ],
    "sg:phone":"+1 815 433 5366",
    "sg:postcode":"61350",
    "sg:province":"IL",
    "sg:tags":[
        "shop"
    ],
    "wof:name":"Mort's Barber Shop",
    "wof:placetype":"venue"
},
  "geometry": {"coordinates":[-88.84398400000001,41.351082],"type":"Point"}
}