{
  "type": "Feature",
  "properties": {
    "iso:country":"US",
    "sg:address":"3250 W North Ave",
    "sg:city":"Chicago",
    "sg:classifiers":[
        {
            "category":"Personal",
            "subcategory":"Beauty Salon",
            "type":"Services"
        }
    ],
    "sg:phone":"+1 773 227 4380",
    "sg:postcode":"60647",
    "sg:province":"IL",
    "sg:tags":[
        "shop"
    ],
    "wof:name":"Fashionation Hair Salon",
    "wof:placetype":"venue"
},
  "geometry": {"coordinates":[-87.70936500000001,41.910224],"type":"Point"}
}