{
  "type": "Feature",
  "properties": {
    "addr:full":"10712 Brookridge Dr Frankfort IL 60423",
    "addr:housenumber":"10712",
    "addr:postcode":"60423",
    "addr:street":"Brookridge Dr",
    "iso:country":"US",
    "sg:address":"10712 Brookridge Dr",
    "sg:city":"Frankfort",
    "sg:classifiers":[
        {
            "category":"Autos & Motor Vehicles",
            "subcategory":"Automobile Sales",
            "type":"Retail Goods"
        }
    ],
    "sg:phone":"+1   ",
    "sg:postcode":"60423",
    "sg:province":"IL",
    "sg:tags":[
        "used"
    ],
    "wof:name":"J&N Auto Sales Inc",
    "wof:placetype":"venue"
},
  "geometry": {"coordinates":[-87.87096,41.504123],"type":"Point"}
}