{
  "type": "Feature",
  "properties": {
    "addr:full":"175 W Jackson Blvd Ste 240 Chicago IL 60604",
    "addr:housenumber":"175",
    "addr:postcode":"60604",
    "addr:street":"W Jackson Blvd Ste 240",
    "iso:country":"US",
    "sg:address":"175 W Jackson Blvd Ste 240",
    "sg:city":"Chicago",
    "sg:classifiers":[
        {
            "category":"Professional",
            "subcategory":"Lawyer & Legal Services",
            "type":"Services"
        }
    ],
    "sg:phone":"+1 312 986 3228",
    "sg:postcode":"60604",
    "sg:province":"IL",
    "wof:name":"Teeple \u00a0Leonard & Erdman",
    "wof:placetype":"venue"
},
  "geometry": {"coordinates":[-87.633197,41.877997],"type":"Point"}
}