{
  "type": "Feature",
  "properties": {
    "addr:full":"339 4th St Downers Grove IL 60515",
    "addr:housenumber":"339",
    "addr:postcode":"60515",
    "addr:street":"4Th St",
    "iso:country":"US",
    "sg:address":"339 4th St",
    "sg:city":"Downers Grove",
    "sg:classifiers":[
        {
            "category":"Organizations",
            "subcategory":"Religious Organization",
            "type":"Services"
        }
    ],
    "sg:phone":"+1 630 968 5432",
    "sg:postcode":"60515",
    "sg:province":"IL",
    "sg:tags":[
        "church"
    ],
    "sg:website":"www.firstpresdg.org",
    "wof:name":"First Presbyterian Church",
    "wof:placetype":"venue"
},
  "geometry": {"coordinates":[-87.99373900000001,41.792341],"type":"Point"}
}