{
  "type": "Feature",
  "properties": {
    "iso:country":"US",
    "sg:address":"733 W 79th St",
    "sg:city":"Chicago",
    "sg:classifiers":[
        {
            "category":"Food & Beverages",
            "subcategory":"Bakery",
            "type":"Retail Goods"
        }
    ],
    "sg:phone":"+1 773 723 5855",
    "sg:postcode":"60620",
    "sg:province":"IL",
    "sg:tags":[
        "sandwich"
    ],
    "wof:name":"Jb Gyros",
    "wof:placetype":"venue"
},
  "geometry": {"coordinates":[-87.642832,41.750503],"type":"Point"}
}