{
  "type": "Feature",
  "properties": {
    "iso:country":"US",
    "sg:address":"4937 N Scout Camp Rd",
    "sg:city":"Apple River",
    "sg:classifiers":[
        {
            "category":"Recreation",
            "type":"Entertainment"
        }
    ],
    "sg:phone":"+1 815 492 2301",
    "sg:postcode":"61001",
    "sg:province":"IL",
    "wof:name":"Puttin Place & Driving Range",
    "wof:placetype":"venue"
},
  "geometry": {"coordinates":[-90.132772,42.431449],"type":"Point"}
}