{
  "type": "Feature",
  "properties": {
    "iso:country":"US",
    "sg:address":"9742 S Roberts Rd",
    "sg:city":"Palos Hills",
    "sg:classifiers":[
        {
            "category":"Professional",
            "subcategory":"Accounting & Tax Preparation",
            "type":"Services"
        }
    ],
    "sg:phone":"+1 708 430 1711",
    "sg:postcode":"60465",
    "sg:province":"IL",
    "sg:tags":[
        "accountant"
    ],
    "wof:name":"Ipema & Assocs PC",
    "wof:placetype":"venue"
},
  "geometry": {"coordinates":[-87.81770299999999,41.713299],"type":"Point"}
}