{
  "type": "Feature",
  "properties": {
    "iso:country":"US",
    "sg:address":"4152 W Chicago Ave",
    "sg:city":"Chicago",
    "sg:classifiers":[
        {
            "category":"Restaurant",
            "type":"Food & Drink"
        }
    ],
    "sg:phone":"+1   ",
    "sg:postcode":"60651",
    "sg:province":"IL",
    "sg:tags":[
        "eating"
    ],
    "wof:name":"Hawthorne Grill",
    "wof:placetype":"venue"
},
  "geometry": {"coordinates":[-87.730659,41.895356],"type":"Point"}
}