{
  "type": "Feature",
  "properties": {
    "addr:full":"111 N County St Waukegan IL 60085",
    "addr:housenumber":"111",
    "addr:postcode":"60085",
    "addr:street":"N County St",
    "iso:country":"US",
    "sg:address":"111 N County St",
    "sg:city":"Waukegan",
    "sg:classifiers":[
        {
            "category":"Professional",
            "subcategory":"Detective & Security Services",
            "type":"Services"
        }
    ],
    "sg:phone":"+1 847 599 9110",
    "sg:postcode":"60085",
    "sg:province":"IL",
    "sg:tags":[
        "guard",
        "patrol"
    ],
    "sg:website":"www.andyfrain.com",
    "wof:name":"Andy Frain Svc",
    "wof:placetype":"venue"
},
  "geometry": {"coordinates":[-87.83247900000001,42.362157],"type":"Point"}
}