{
  "type": "Feature",
  "properties": {
    "iso:country":"US",
    "sg:address":"2061 Clover Rd",
    "sg:city":"Northbrook",
    "sg:classifiers":[
        {
            "category":"Professional",
            "type":"Services"
        }
    ],
    "sg:phone":"+1 847 291 9439",
    "sg:postcode":"60062",
    "sg:province":"IL",
    "wof:name":"David Pinzur",
    "wof:placetype":"venue"
},
  "geometry": {"coordinates":[-87.854315,42.11638],"type":"Point"}
}