{
  "type": "Feature",
  "properties": {
    "addr:full":"2010 Arlington Heights Rd Arlington Heights IL 60005",
    "addr:housenumber":"2010",
    "addr:postcode":"60005",
    "addr:street":"Arlington Heights Rd",
    "iso:country":"US",
    "sg:address":"2010 Arlington Heights Rd",
    "sg:city":"Arlington Heights",
    "sg:classifiers":[
        {
            "category":"Health Services",
            "subcategory":"Chiropractor",
            "type":"Services"
        }
    ],
    "sg:phone":"+1 847 593 3342",
    "sg:postcode":"60005",
    "sg:province":"IL",
    "wof:name":"First Health Associates",
    "wof:placetype":"venue"
},
  "geometry": {"coordinates":[-87.982281,42.048941],"type":"Point"}
}