{
  "type": "Feature",
  "properties": {
    "addr:full":"500 5th St Crete IN 60417",
    "addr:housenumber":"500",
    "addr:postcode":"60417",
    "addr:street":"5Th St",
    "iso:country":"US",
    "sg:address":"500 5th St",
    "sg:city":"Crete",
    "sg:classifiers":[
        {
            "category":"Shopping",
            "subcategory":"Gifts & Souvenirs",
            "type":"Retail Goods"
        }
    ],
    "sg:phone":"+1   ",
    "sg:postcode":"60417",
    "sg:province":"IN",
    "wof:name":"Olde Village Shoppe",
    "wof:placetype":"venue"
},
  "geometry": {"coordinates":[-87.63185,41.44963],"type":"Point"}
}