{
  "type": "Feature",
  "properties": {
    "iso:country":"US",
    "sg:address":"115 W Main St",
    "sg:city":"Urbana",
    "sg:classifiers":[
        {
            "category":"Bars & Pubs",
            "type":"Food & Drink"
        },
        {
            "category":"Restaurant",
            "type":"Food & Drink"
        }
    ],
    "sg:phone":"+1 217 384 7526",
    "sg:postcode":"61801",
    "sg:province":"IL",
    "sg:tags":[
        "traditional",
        "american"
    ],
    "sg:website":"crane-alley.com/",
    "wof:name":"Crane Alley",
    "wof:placetype":"venue"
},
  "geometry": {"coordinates":[-88.207808,40.11246],"type":"Point"}
}