{
  "type": "Feature",
  "properties": {
    "iso:country":"US",
    "sg:address":"1874 N Oakley Ave",
    "sg:city":"Chicago",
    "sg:classifiers":[
        {
            "category":"Professional",
            "type":"Services"
        }
    ],
    "sg:phone":"+1 773 227 9970",
    "sg:postcode":"60647",
    "sg:province":"IL",
    "sg:tags":[
        "publication",
        "editorial"
    ],
    "wof:name":"Lisa B Inc",
    "wof:placetype":"venue"
},
  "geometry": {"coordinates":[-87.684887,41.915537],"type":"Point"}
}