{
  "type": "Feature",
  "properties": {
    "addr:full":"10813 Torrance Rd Carbondale IL 62901",
    "addr:housenumber":"10813",
    "addr:postcode":"62901",
    "addr:street":"Torrance Rd",
    "iso:country":"US",
    "sg:address":"10813 Torrance Rd",
    "sg:city":"Carbondale",
    "sg:classifiers":[
        {
            "category":"Home & Garden",
            "subcategory":"Mobile Homes",
            "type":"Retail Goods"
        }
    ],
    "sg:phone":"+1   ",
    "sg:postcode":"62901",
    "sg:province":"IL",
    "wof:name":"Rawls Inc",
    "wof:placetype":"venue"
},
  "geometry": {"coordinates":[-89.14782099999999,37.75075],"type":"Point"}
}