{
  "type": "Feature",
  "properties": {
    "addr:full":"1116 Auburn St Rockford IL 61103",
    "addr:housenumber":"1116",
    "addr:postcode":"61103",
    "addr:street":"Auburn St",
    "iso:country":"US",
    "sg:address":"1116 Auburn St",
    "sg:city":"Rockford",
    "sg:classifiers":[
        {
            "category":"Restaurant",
            "type":"Food & Drink"
        }
    ],
    "sg:phone":"+1   ",
    "sg:postcode":"61103",
    "sg:province":"IL",
    "sg:tags":[
        "shop",
        "sandwich"
    ],
    "wof:name":"Auburn Maid Rite",
    "wof:placetype":"venue"
},
  "geometry": {"coordinates":[-89.07941,42.288577],"type":"Point"}
}