{
  "type": "Feature",
  "properties": {
    "iso:country":"US",
    "sg:address":"4908 W Montrose Ave",
    "sg:city":"Chicago",
    "sg:classifiers":[
        {
            "category":"Building & Trades",
            "subcategory":"Construction",
            "type":"Services"
        }
    ],
    "sg:phone":"+1 773 545 9553",
    "sg:postcode":"60630",
    "sg:province":"IL",
    "sg:tags":[
        "contractor"
    ],
    "sg:website":"www.deltastargroup.com",
    "wof:name":"Delta Star Group",
    "wof:placetype":"venue"
},
  "geometry": {"coordinates":[-87.750455,41.960975],"type":"Point"}
}