{
  "type": "Feature",
  "properties": {
    "iso:country":"US",
    "sg:address":"2415 W Devon Avenue",
    "sg:city":"Chicago",
    "sg:classifiers":[
        {
            "category":"Building & Trades",
            "subcategory":"Pest Control",
            "type":"Services"
        }
    ],
    "sg:phone":"+1 773 274 7400",
    "sg:postcode":"60659",
    "sg:province":"IL",
    "wof:name":"Low Cost & Appliance & Pest",
    "wof:placetype":"venue"
},
  "geometry": {"coordinates":[-87.690725,41.997495],"type":"Point"}
}