{
  "type": "Feature",
  "properties": {
    "iso:country":"US",
    "sg:address":"3471 E Houston Rd",
    "sg:city":"Woodlawn",
    "sg:phone":"+1 618 735 2624",
    "sg:postcode":"62898",
    "sg:province":"IL",
    "sg:tags":[
        "farm",
        "corn",
        "soybean"
    ],
    "wof:name":"Raymond Koy",
    "wof:placetype":"venue"
},
  "geometry": {"coordinates":[-89.080522,38.372357],"type":"Point"}
}