{
  "type": "Feature",
  "properties": {
    "iso:country":"US",
    "sg:address":"1065 Sesame St",
    "sg:city":"Franklin Park",
    "sg:classifiers":[
        {
            "category":"Manufacturing",
            "subcategory":"Metals",
            "type":"Manufacturing & Wholesale Goods"
        }
    ],
    "sg:phone":"+1 630 694 0300",
    "sg:postcode":"60131",
    "sg:province":"IL",
    "sg:tags":[
        "stampings",
        "sheet",
        "metalwork",
        "mfg"
    ],
    "sg:website":"www.classic-sheet-metal.com",
    "wof:name":"Classic Sheet Metal Inc",
    "wof:placetype":"venue"
},
  "geometry": {"coordinates":[-87.918364,41.94409],"type":"Point"}
}