{
  "type": "Feature",
  "properties": {
    "addr:full":"15825 W Baker Rd Manhattan IL 60442",
    "addr:housenumber":"15825",
    "addr:postcode":"60442",
    "addr:street":"W Baker Rd",
    "iso:country":"US",
    "sg:address":"15825 W Baker Rd",
    "sg:city":"Manhattan",
    "sg:classifiers":[
        {
            "category":"Insurance",
            "subcategory":"Insurance Agent",
            "type":"Services"
        }
    ],
    "sg:phone":"+1 815 478 3772",
    "sg:postcode":"60442",
    "sg:province":"IL",
    "sg:website":"http://www.mchughinsurance.com",
    "wof:name":"McHugh Insurance Agency",
    "wof:placetype":"venue"
},
  "geometry": {"coordinates":[-87.998065,41.453448],"type":"Point"}
}