{
  "type": "Feature",
  "properties": {
    "addr:full":"4410 N Prospect Rd Peoria IL 61616",
    "addr:housenumber":"4410",
    "addr:postcode":"61616",
    "addr:street":"N Prospect Rd",
    "iso:country":"US",
    "sg:address":"4410 N Prospect Rd",
    "sg:city":"Peoria",
    "sg:classifiers":[
        {
            "category":"Restaurant",
            "type":"Food & Drink"
        }
    ],
    "sg:menulink":"http://www.allmenus.com/il/richwoods/127258-subway/menu/",
    "sg:phone":"+1 309 688 7280",
    "sg:postcode":"61616",
    "sg:province":"IL",
    "sg:tags":[
        "american",
        "sandwich"
    ],
    "wof:name":"Subway",
    "wof:placetype":"venue"
},
  "geometry": {"coordinates":[-89.57412100000001,40.740499],"type":"Point"}
}