{
  "type": "Feature",
  "properties": {
    "addr:full":"360 E South Water St Ste 2302 Chicago IL 60601",
    "addr:housenumber":"360 e",
    "addr:postcode":"60601",
    "addr:street":"South Water St Ste 2302",
    "iso:country":"US",
    "sg:address":"360 E South Water St Ste 2302",
    "sg:city":"Chicago",
    "sg:classifiers":[
        {
            "category":"Professional",
            "subcategory":"Art Services",
            "type":"Services"
        }
    ],
    "sg:phone":"+1 773 677 2467",
    "sg:postcode":"60601",
    "sg:province":"IL",
    "sg:tags":[
        "photographer"
    ],
    "sg:website":"www.photorexit.com",
    "wof:name":"Photorexit Photography",
    "wof:placetype":"venue"
},
  "geometry": {"coordinates":[-87.616845,41.889545],"type":"Point"}
}