{
  "type": "Feature",
  "properties": {
    "iso:country":"US",
    "sg:address":"1045 University St",
    "sg:city":"Henry",
    "sg:classifiers":[
        {
            "category":"Restaurant",
            "type":"Food & Drink"
        }
    ],
    "sg:phone":"+1 309 364 4555",
    "sg:postcode":"61537",
    "sg:province":"IL",
    "wof:name":"Henry Fast Stop",
    "wof:placetype":"venue"
},
  "geometry": {"coordinates":[-89.369624,41.116762],"type":"Point"}
}