{
  "type": "Feature",
  "properties": {
    "iso:country":"US",
    "sg:address":"21505 St Clair Dr",
    "sg:city":"Joliet",
    "sg:classifiers":[
        {
            "category":"Local Transit",
            "type":"Transportation"
        }
    ],
    "sg:phone":"+1 815 609 0117",
    "sg:postcode":"60403",
    "sg:province":"IL",
    "sg:tags":[
        "passenger"
    ],
    "wof:name":"Specialty Limousine",
    "wof:placetype":"venue"
},
  "geometry": {"coordinates":[-90.248485,38.935117],"type":"Point"}
}