{
  "type": "Feature",
  "properties": {
    "iso:country":"US",
    "sg:address":"3203 Landstrom Rd",
    "sg:city":"Rockford",
    "sg:classifiers":[
        {
            "category":"Professional",
            "subcategory":"Engineering",
            "type":"Services"
        }
    ],
    "sg:phone":"+1 815 877 8500",
    "sg:postcode":"61107",
    "sg:province":"IL",
    "wof:name":"Charles & Joan Bradley Ch",
    "wof:placetype":"venue"
},
  "geometry": {"coordinates":[-89.046678,42.296075],"type":"Point"}
}