{
  "type": "Feature",
  "properties": {
    "iso:country":"US",
    "sg:address":"4549 W Belmont Avenue",
    "sg:city":"Chicago",
    "sg:classifiers":[
        {
            "category":"Building & Trades",
            "subcategory":"Construction",
            "type":"Services"
        }
    ],
    "sg:phone":"+1 773 202 0055",
    "sg:postcode":"60641",
    "sg:province":"IL",
    "sg:tags":[
        "contractor"
    ],
    "wof:name":"Chicagoland Metal Fabrication & Supply",
    "wof:placetype":"venue"
},
  "geometry": {"coordinates":[-87.741612,41.938803],"type":"Point"}
}