{
  "type": "Feature",
  "properties": {
    "iso:country":"US",
    "sg:address":"1475 Brummel Ave",
    "sg:city":"Elk Grove Vlg",
    "sg:classifiers":[
        {
            "category":"Professional",
            "subcategory":"Engineering",
            "type":"Services"
        },
        {
            "category":"Building & Trades",
            "subcategory":"Electrical",
            "type":"Services"
        }
    ],
    "sg:phone":"+1 847 981 9980",
    "sg:postcode":"60007",
    "sg:province":"IL",
    "sg:tags":[
        "general",
        "contractor",
        "electrical",
        "engineer"
    ],
    "sg:website":"www.avondaleelectric.com",
    "wof:name":"Avondale Electric",
    "wof:placetype":"venue"
},
  "geometry": {"coordinates":[-87.962632,42.017347],"type":"Point"}
}