{
  "type": "Feature",
  "properties": {
    "iso:country":"US",
    "sg:address":"698 Armour Rd",
    "sg:city":"Bourbonnais",
    "sg:classifiers":[
        {
            "category":"Health Services",
            "subcategory":"Doctor",
            "type":"Services"
        }
    ],
    "sg:phone":"+1 815 935 7977",
    "sg:postcode":"60914",
    "sg:province":"IL",
    "sg:tags":[
        "medical",
        "insurance"
    ],
    "wof:name":"Secure Care of America Inc",
    "wof:placetype":"venue"
},
  "geometry": {"coordinates":[-87.87217099999999,41.162604],"type":"Point"}
}