{
  "type": "Feature",
  "properties": {
    "addr:full":"328 Army Trail Rd Glendale Heights IL 60139",
    "addr:housenumber":"328",
    "addr:postcode":"60139",
    "addr:street":"Army Trail Rd",
    "iso:country":"US",
    "sg:address":"328 Army Trail Rd",
    "sg:city":"Glendale Heights",
    "sg:classifiers":[
        {
            "category":"Health Services",
            "subcategory":"Doctor",
            "type":"Services"
        }
    ],
    "sg:phone":"+1 630 529 8852",
    "sg:postcode":"60139",
    "sg:province":"IL",
    "sg:tags":[
        "dentist"
    ],
    "wof:name":"Bloomingdale Family Dental",
    "wof:placetype":"venue"
},
  "geometry": {"coordinates":[-88.076391,41.936728],"type":"Point"}
}