{
  "type": "Feature",
  "properties": {
    "iso:country":"US",
    "sg:address":"11403 Catholic Springs Rd",
    "sg:city":"Bunker Hill",
    "sg:classifiers":[
        {
            "category":"Farming",
            "subcategory":"Farm",
            "type":"Manufacturing & Wholesale Goods"
        }
    ],
    "sg:phone":"+1 618 585 3025",
    "sg:postcode":"62014",
    "sg:province":"IL",
    "sg:tags":[
        "crop",
        "general"
    ],
    "wof:name":"Jarden Farms",
    "wof:placetype":"venue"
},
  "geometry": {"coordinates":[-89.92586,39.005863],"type":"Point"}
}