{
  "type": "Feature",
  "properties": {
    "iso:country":"US",
    "sg:address":"898 Tipperary St",
    "sg:city":"Gilberts",
    "sg:classifiers":[
        {
            "category":"Utilities",
            "subcategory":"Telephone",
            "type":"Services"
        },
        {
            "category":"Communications",
            "type":"Services"
        }
    ],
    "sg:phone":"+1 847 289 3200",
    "sg:postcode":"60136",
    "sg:province":"IL",
    "sg:tags":[
        "equipment",
        "consultant",
        "telecommunication",
        "system"
    ],
    "wof:name":"Hotline Tele Communications",
    "wof:placetype":"venue"
},
  "geometry": {"coordinates":[-88.356292,42.075672],"type":"Point"}
}