{
  "type": "Feature",
  "properties": {
    "iso:country":"US",
    "sg:address":"112 E Winter Ave",
    "sg:city":"Danville",
    "sg:classifiers":[
        {
            "category":"Retail",
            "subcategory":"Auto Repair",
            "type":"Services"
        }
    ],
    "sg:phone":"+1 217 443 1577",
    "sg:postcode":"61832",
    "sg:province":"IL",
    "sg:tags":[
        "automotive"
    ],
    "wof:name":"D A Customs",
    "wof:placetype":"venue"
},
  "geometry": {"coordinates":[-87.628553,40.159872],"type":"Point"}
}