{
  "type": "Feature",
  "properties": {
    "addr:full":"6 E Washington St Oswego IL 60543",
    "addr:housenumber":"6",
    "addr:postcode":"60543",
    "addr:street":"E Washington St",
    "iso:country":"US",
    "sg:address":"6 E Washington St",
    "sg:city":"Oswego",
    "sg:classifiers":[
        {
            "category":"Insurance",
            "subcategory":"Hazard Insurance",
            "type":"Services"
        },
        {
            "category":"Insurance",
            "subcategory":"Insurance Agent",
            "type":"Services"
        },
        {
            "category":"Insurance",
            "subcategory":"Life Insurance",
            "type":"Services"
        },
        {
            "category":"Insurance",
            "subcategory":"Title Insurance",
            "type":"Services"
        }
    ],
    "sg:phone":"+1 630 554 2035",
    "sg:postcode":"60543",
    "sg:province":"IL",
    "sg:tags":[
        "auto",
        "commercial",
        "business",
        "homeowner"
    ],
    "sg:website":"http://www.countryfinancial.com/dennis.prentice",
    "wof:name":"COUNTRY Financial Dennis Prentice",
    "wof:placetype":"venue"
},
  "geometry": {"coordinates":[-88.351477,41.682931],"type":"Point"}
}