{
  "type": "Feature",
  "properties": {
    "iso:country":"US",
    "sg:address":"1655 Jarvis Ave",
    "sg:city":"Elk Grove Village",
    "sg:classifiers":[
        {
            "category":"Wholesale",
            "subcategory":"Machinery & Supplies",
            "type":"Manufacturing & Wholesale Goods"
        }
    ],
    "sg:phone":"+1 847 758 1972",
    "sg:postcode":"60007",
    "sg:province":"IL",
    "sg:tags":[
        "equipment",
        "establishment"
    ],
    "wof:name":"Platinum Fire Supply Inc",
    "wof:placetype":"venue"
},
  "geometry": {"coordinates":[-87.965404,42.013094],"type":"Point"}
}