{
  "type": "Feature",
  "properties": {
    "addr:full":"500 S West Ave Freeport IL 61032",
    "addr:housenumber":"500",
    "addr:postcode":"61032",
    "addr:street":"S West Ave",
    "iso:country":"US",
    "sg:address":"500 S West Ave",
    "sg:city":"Freeport",
    "sg:classifiers":[
        {
            "category":"Personal",
            "type":"Services"
        },
        {
            "category":"Professional",
            "subcategory":"Art Services",
            "type":"Services"
        }
    ],
    "sg:phone":"+1 815 266 8999",
    "sg:postcode":"61032",
    "sg:province":"IL",
    "sg:tags":[
        "photography",
        "videography",
        "wedding"
    ],
    "wof:name":"Photography By Grabrielle",
    "wof:placetype":"venue"
},
  "geometry": {"coordinates":[-89.631958,42.29467],"type":"Point"}
}