{
  "type": "Feature",
  "properties": {
    "iso:country":"US",
    "sg:address":"212 E Green St",
    "sg:city":"Champaign",
    "sg:classifiers":[
        {
            "category":"Real Estate",
            "subcategory":"Real Estate Operator",
            "type":"Services"
        }
    ],
    "sg:phone":"+1 217 328 1223",
    "sg:postcode":"61820",
    "sg:province":"IL",
    "sg:tags":[
        "apartment"
    ],
    "wof:name":"Roland Realty",
    "wof:placetype":"venue"
},
  "geometry": {"coordinates":[-88.23684799999999,40.110378],"type":"Point"}
}