{
  "type": "Feature",
  "properties": {
    "iso:country":"US",
    "sg:address":"13811 Western Ave",
    "sg:city":"Blue Island",
    "sg:classifiers":[
        {
            "category":"Professional",
            "subcategory":"Engineering",
            "type":"Services"
        }
    ],
    "sg:phone":"+1 708 371 4738",
    "sg:postcode":"60406",
    "sg:province":"IL",
    "wof:name":"Charlottes Catering Pe",
    "wof:placetype":"venue"
},
  "geometry": {"coordinates":[-87.679434,41.640912],"type":"Point"}
}