{
  "type": "Feature",
  "properties": {
    "addr:full":"325 E Dundee Rd Palatine IL 60074",
    "addr:housenumber":"325",
    "addr:postcode":"60074",
    "addr:street":"E Dundee Rd",
    "iso:country":"US",
    "sg:address":"325 E Dundee Rd",
    "sg:city":"Palatine",
    "sg:classifiers":[
        {
            "category":"Shopping",
            "type":"Retail Goods"
        }
    ],
    "sg:phone":"+1   ",
    "sg:postcode":"60074",
    "sg:province":"IL",
    "sg:tags":[
        "merchandise"
    ],
    "wof:name":"Christian Shop LTD",
    "wof:placetype":"venue"
},
  "geometry": {"coordinates":[-88.034437,42.139165],"type":"Point"}
}