{
  "type": "Feature",
  "properties": {
    "addr:full":"106 W Wilson St Batavia IL 60510",
    "addr:housenumber":"106",
    "addr:postcode":"60510",
    "addr:street":"W Wilson St",
    "iso:country":"US",
    "sg:address":"106 W Wilson St",
    "sg:city":"Batavia",
    "sg:classifiers":[
        {
            "category":"Real Estate",
            "subcategory":"Real Estate Agent",
            "type":"Services"
        }
    ],
    "sg:phone":"+1 630 406 5750",
    "sg:postcode":"60510",
    "sg:province":"IL",
    "wof:name":"Western Realty Inc",
    "wof:placetype":"venue"
},
  "geometry": {"coordinates":[-88.309603,41.849899],"type":"Point"}
}