{
  "type": "Feature",
  "properties": {
    "addr:full":"5926 S Pulaski Rd Chicago IL 60629",
    "addr:housenumber":"5926",
    "addr:postcode":"60629",
    "addr:street":"S Pulaski Rd",
    "iso:country":"US",
    "sg:address":"5926 S Pulaski Rd",
    "sg:city":"Chicago",
    "sg:classifiers":[
        {
            "category":"Education",
            "subcategory":"Kindergarten",
            "type":"Public Place"
        }
    ],
    "sg:phone":"+1 773 735 1199",
    "sg:postcode":"60629",
    "sg:province":"IL",
    "sg:tags":[
        "school",
        "driving"
    ],
    "sg:website":"www.bluehorizoncdlschool.com",
    "wof:name":"Blue Horizon Driving School",
    "wof:placetype":"venue"
},
  "geometry": {"coordinates":[-87.723,41.7855],"type":"Point"}
}