{
  "type": "Feature",
  "properties": {
    "iso:country":"US",
    "sg:address":"29 E Main St",
    "sg:city":"Roselle",
    "sg:classifiers":[
        {
            "category":"Shopping",
            "subcategory":"Pets & Pet Supplies",
            "type":"Retail Goods"
        },
        {
            "category":"Retail",
            "subcategory":"Animal Services",
            "type":"Services"
        }
    ],
    "sg:phone":"+1 630 529 9663",
    "sg:postcode":"60172",
    "sg:province":"IL",
    "sg:tags":[
        "grooming",
        "dog",
        "store",
        "cat"
    ],
    "wof:name":"All Things Woof Meow Too Inc",
    "wof:placetype":"venue"
},
  "geometry": {"coordinates":[-88.07941599999999,41.983663],"type":"Point"}
}