{
  "type": "Feature",
  "properties": {
    "iso:country":"US",
    "sg:address":"850 Nicholas Blvd",
    "sg:city":"Elk Grove Village",
    "sg:classifiers":[
        {
            "category":"Manufacturing",
            "subcategory":"Chemicals & Compounds",
            "type":"Manufacturing & Wholesale Goods"
        }
    ],
    "sg:phone":"+1 847 593 3044",
    "sg:postcode":"60007",
    "sg:province":"IL",
    "sg:tags":[
        "preparation",
        "toilet",
        "mfg"
    ],
    "wof:name":"Meta International Inc",
    "wof:placetype":"venue"
},
  "geometry": {"coordinates":[-87.950658,42.011762],"type":"Point"}
}