{
  "type": "Feature",
  "properties": {
    "addr:full":"814 W. Randolph Chicago IL 60607",
    "addr:housenumber":"814",
    "addr:postcode":"60607",
    "addr:street":"W. Randolph",
    "iso:country":"US",
    "sg:address":"814 W. Randolph",
    "sg:city":"Chicago",
    "sg:classifiers":[
        {
            "category":"Restaurant",
            "type":"Food & Drink"
        }
    ],
    "sg:phone":"+1 312 455 8114",
    "sg:postcode":"60607",
    "sg:province":"IL",
    "sg:tags":[
        "mexican",
        "tex-mex"
    ],
    "sg:website":"www.decerotaqueria.com",
    "wof:name":"De Cero Taqueria",
    "wof:placetype":"venue"
},
  "geometry": {"coordinates":[-87.648104,41.884522],"type":"Point"}
}