{
  "type": "Feature",
  "properties": {
    "addr:full":"6622 W 87th Pl Oak Lawn IL 60453",
    "addr:housenumber":"6622",
    "addr:postcode":"60453",
    "addr:street":"W 87Th Pl",
    "iso:country":"US",
    "sg:address":"6622 W 87th Pl",
    "sg:city":"Oak Lawn",
    "sg:classifiers":[
        {
            "category":"Building & Trades",
            "subcategory":"Construction",
            "type":"Services"
        }
    ],
    "sg:phone":"+1 708 599 0544",
    "sg:postcode":"60453",
    "sg:province":"IL",
    "sg:tags":[
        "hanging",
        "contractor"
    ],
    "wof:name":"De Francesco Decorating",
    "wof:placetype":"venue"
},
  "geometry": {"coordinates":[-87.78642000000001,41.732729],"type":"Point"}
}