{
  "type": "Feature",
  "properties": {
    "iso:country":"US",
    "sg:address":"5917 N Illinois St",
    "sg:city":"Fairview Heights",
    "sg:classifiers":[
        {
            "category":"Restaurant",
            "type":"Food & Drink"
        }
    ],
    "sg:phone":"+1 618 222 9630",
    "sg:postcode":"62208",
    "sg:province":"IL",
    "wof:name":"Panera Bread",
    "wof:placetype":"venue"
},
  "geometry": {"coordinates":[-89.985001,38.586498],"type":"Point"}
}