{
  "type": "Feature",
  "properties": {
    "addr:full":"1471 Ring Rd Calumet City IL 60409",
    "addr:housenumber":"1471",
    "addr:postcode":"60409",
    "addr:street":"Ring Rd",
    "iso:country":"US",
    "sg:address":"1471 Ring Rd",
    "sg:city":"Calumet City",
    "sg:classifiers":[
        {
            "category":"Professional",
            "subcategory":"Accounting & Tax Preparation",
            "type":"Services"
        }
    ],
    "sg:phone":"+1 708 862 2262",
    "sg:postcode":"60409",
    "sg:province":"IL",
    "sg:tags":[
        "accountant"
    ],
    "wof:name":"Kasperek John J Jr CPA",
    "wof:placetype":"venue"
},
  "geometry": {"coordinates":[-87.559601,41.595501],"type":"Point"}
}