{
  "type": "Feature",
  "properties": {
    "iso:country":"US",
    "sg:address":"1250 S Grove Ave",
    "sg:city":"Barrington",
    "sg:classifiers":[
        {
            "category":"Professional",
            "subcategory":"Engineering",
            "type":"Services"
        }
    ],
    "sg:phone":"+1 847 842 9663",
    "sg:postcode":"60010",
    "sg:province":"IL",
    "sg:tags":[
        "water",
        "landscaping",
        "resource",
        "engineer"
    ],
    "wof:name":"Kabbes Engineering Inc",
    "wof:placetype":"venue"
},
  "geometry": {"coordinates":[-88.133018,42.136595],"type":"Point"}
}