{
  "type": "Feature",
  "properties": {
    "addr:full":"1250 Busch Pkwy Buffalo Grove IL 60089",
    "addr:housenumber":"1250",
    "addr:postcode":"60089",
    "addr:street":"Busch Pkwy",
    "iso:country":"US",
    "sg:address":"1250 Busch Pkwy",
    "sg:city":"Buffalo Grove",
    "sg:classifiers":[
        {
            "category":"Manufacturing",
            "subcategory":"Tools & Machinery",
            "type":"Manufacturing & Wholesale Goods"
        }
    ],
    "sg:phone":"+1 847 465 0300",
    "sg:postcode":"60089",
    "sg:province":"IL",
    "sg:tags":[
        "machine",
        "shop",
        "mfg",
        "testing",
        "equipment"
    ],
    "wof:name":"Schultes Precision Mfg",
    "wof:placetype":"venue"
},
  "geometry": {"coordinates":[-87.939892,42.171664],"type":"Point"}
}