{
  "type": "Feature",
  "properties": {
    "iso:country":"US",
    "sg:address":"7074 W Penn Corner Rd",
    "sg:city":"Polo",
    "sg:classifiers":[
        {
            "category":"Professional",
            "subcategory":"Business Services",
            "type":"Services"
        }
    ],
    "sg:phone":"+1 815 946 2660",
    "sg:postcode":"61064",
    "sg:province":"IL",
    "sg:tags":[
        "auction"
    ],
    "wof:name":"Public Auction Service",
    "wof:placetype":"venue"
},
  "geometry": {"coordinates":[-89.476837,41.945448],"type":"Point"}
}