{
  "type": "Feature",
  "properties": {
    "iso:country":"US",
    "sg:address":"302 W Washington St",
    "sg:city":"Freeburg",
    "sg:classifiers":[
        {
            "category":"Health Services",
            "subcategory":"Doctor",
            "type":"Services"
        }
    ],
    "sg:phone":"+1 618 539 0067",
    "sg:postcode":"62243",
    "sg:province":"IL",
    "sg:tags":[
        "medical"
    ],
    "wof:name":"Rural Family Medicine Assoc",
    "wof:placetype":"venue"
},
  "geometry": {"coordinates":[-89.913237,38.424624],"type":"Point"}
}