{
  "type": "Feature",
  "properties": {
    "iso:country":"US",
    "sg:address":"102 Mac Gregor Rd",
    "sg:city":"Lockport",
    "sg:classifiers":[
        {
            "category":"Education",
            "subcategory":"Dance Studio",
            "type":"Public Place"
        }
    ],
    "sg:phone":"+1 630 243 9860",
    "sg:postcode":"60441",
    "sg:province":"IL",
    "sg:tags":[
        "instruction",
        "dancing"
    ],
    "wof:name":"Dancestyles Academy",
    "wof:placetype":"venue"
},
  "geometry": {"coordinates":[-88.035363,41.598436],"type":"Point"}
}