{
  "type": "Feature",
  "properties": {
    "iso:country":"US",
    "sg:address":"1020 N McLean Blvd",
    "sg:city":"Elgin",
    "sg:classifiers":[
        {
            "category":"Retail",
            "subcategory":"Laundry & Dry Cleaning",
            "type":"Services"
        }
    ],
    "sg:phone":"+1 847 888 2389",
    "sg:postcode":"60123",
    "sg:province":"IL",
    "sg:tags":[
        "cleaners"
    ],
    "wof:name":"First Cleaners",
    "wof:placetype":"venue"
},
  "geometry": {"coordinates":[-88.314504,42.015228],"type":"Point"}
}