{
  "type": "Feature",
  "properties": {
    "iso:country":"US",
    "sg:address":"6257 Sherman Rd",
    "sg:city":"Sherman",
    "sg:classifiers":[
        {
            "category":"Farming",
            "subcategory":"Livestock Farm",
            "type":"Manufacturing & Wholesale Goods"
        }
    ],
    "sg:phone":"+1 217 566 3440",
    "sg:postcode":"62684",
    "sg:province":"IL",
    "sg:tags":[
        "hog",
        "or",
        "feedlot"
    ],
    "wof:name":"Muench Eldon",
    "wof:placetype":"venue"
},
  "geometry": {"coordinates":[-89.531565,39.896254],"type":"Point"}
}