{
  "type": "Feature",
  "properties": {
    "addr:full":"1201 S Main St Jacksonville IL 62650",
    "addr:housenumber":"1201",
    "addr:postcode":"62650",
    "addr:street":"S Main St",
    "iso:country":"US",
    "sg:address":"1201 S Main St",
    "sg:city":"Jacksonville",
    "sg:classifiers":[
        {
            "category":"Health Services",
            "subcategory":"Hospital",
            "type":"Services"
        }
    ],
    "sg:phone":"+1   ",
    "sg:postcode":"62650",
    "sg:province":"IL",
    "sg:tags":[
        "residential",
        "public",
        "psychiatric"
    ],
    "wof:name":"Jacksonville Developmental Ctr",
    "wof:placetype":"venue"
},
  "geometry": {"coordinates":[-90.22918,39.719656],"type":"Point"}
}