{
  "type": "Feature",
  "properties": {
    "iso:country":"US",
    "sg:address":"321 S Main St",
    "sg:city":"Kewanee",
    "sg:classifiers":[
        {
            "category":"Health Services",
            "subcategory":"Doctor",
            "type":"Services"
        }
    ],
    "sg:phone":"+1   ",
    "sg:postcode":"61443",
    "sg:province":"IL",
    "sg:tags":[
        "medical",
        "optical",
        "good"
    ],
    "wof:name":"Noy Soti MD",
    "wof:placetype":"venue"
},
  "geometry": {"coordinates":[-89.924989,41.240785],"type":"Point"}
}