{
  "type": "Feature",
  "properties": {
    "addr:full":"225 S Century Blvd Rantoul IL 61866",
    "addr:housenumber":"225",
    "addr:postcode":"61866",
    "addr:street":"S Century Blvd",
    "iso:country":"US",
    "sg:address":"225 S Century Blvd",
    "sg:city":"Rantoul",
    "sg:classifiers":[
        {
            "category":"Education",
            "subcategory":"Library",
            "type":"Public Place"
        }
    ],
    "sg:phone":"+1 217 893 3955",
    "sg:postcode":"61866",
    "sg:province":"IL",
    "wof:name":"Rantoul Public Library",
    "wof:placetype":"venue"
},
  "geometry": {"coordinates":[-88.15580799999999,40.308803],"type":"Point"}
}