{
  "type": "Feature",
  "properties": {
    "iso:country":"US",
    "sg:address":"111 W 87th St",
    "sg:city":"Chicago",
    "sg:classifiers":[
        {
            "category":"Shopping",
            "subcategory":"Jewelry",
            "type":"Retail Goods"
        },
        {
            "category":"Shopping",
            "subcategory":"Pawn Shop",
            "type":"Retail Goods"
        }
    ],
    "sg:phone":"+1 773 487 9100",
    "sg:postcode":"60620",
    "sg:province":"IL",
    "sg:website":"bigpawn-freemanjewelers.com",
    "wof:name":"Freeman Jewelers Inc",
    "wof:placetype":"venue"
},
  "geometry": {"coordinates":[-87.62750200000001,41.736241],"type":"Point"}
}