{
  "type": "Feature",
  "properties": {
    "addr:full":"646 S Flack Rd Pearl City IL 61062",
    "addr:housenumber":"646",
    "addr:postcode":"61062",
    "addr:street":"S Flack Rd",
    "iso:country":"US",
    "sg:address":"646 S Flack Rd",
    "sg:city":"Pearl City",
    "sg:phone":"+1 815 443 2370",
    "sg:postcode":"61062",
    "sg:province":"IL",
    "sg:tags":[
        "farm",
        "corn"
    ],
    "wof:name":"Richard Fergusen",
    "wof:placetype":"venue"
},
  "geometry": {"coordinates":[-89.85610800000001,42.288645],"type":"Point"}
}