{
  "type": "Feature",
  "properties": {
    "iso:country":"US",
    "sg:address":"502 1st St",
    "sg:city":"La Salle",
    "sg:classifiers":[
        {
            "category":"Building & Trades",
            "subcategory":"Plumbing",
            "type":"Services"
        }
    ],
    "sg:phone":"+1 815 223 7363",
    "sg:postcode":"61301",
    "sg:province":"IL",
    "sg:tags":[
        "plumbing",
        "contractor"
    ],
    "wof:name":"Globe Heating & Plumbing",
    "wof:placetype":"venue"
},
  "geometry": {"coordinates":[-89.096802,41.327897],"type":"Point"}
}