{
  "type": "Feature",
  "properties": {
    "iso:country":"US",
    "sg:address":"2309 N Damen Ave",
    "sg:city":"Chicago",
    "sg:classifiers":[
        {
            "category":"Real Estate",
            "subcategory":"Real Estate Services",
            "type":"Services"
        }
    ],
    "sg:phone":"+1 773 489 4488",
    "sg:postcode":"60647",
    "sg:province":"IL",
    "sg:website":"www.primechicago.com",
    "wof:name":"Prime Properties Realty",
    "wof:placetype":"venue"
},
  "geometry": {"coordinates":[-87.677295,41.923338],"type":"Point"}
}