{
  "type": "Feature",
  "properties": {
    "iso:country":"US",
    "sg:address":"1036 W Bryn Mawr Ave",
    "sg:city":"Chicago",
    "sg:classifiers":[
        {
            "category":"Food & Beverages",
            "subcategory":"Groceries & Convenience Stores",
            "type":"Retail Goods"
        }
    ],
    "sg:phone":"+1 773 275 3451",
    "sg:postcode":"60660",
    "sg:province":"IL",
    "wof:name":"Express Pantry",
    "wof:placetype":"venue"
},
  "geometry": {"coordinates":[-87.656898,41.9837],"type":"Point"}
}