{
  "type": "Feature",
  "properties": {
    "iso:country":"US",
    "sg:address":"907 Arrow Rd Ste 2",
    "sg:city":"Champaign",
    "sg:classifiers":[
        {
            "category":"Personal",
            "subcategory":"Barber",
            "type":"Services"
        },
        {
            "category":"Personal",
            "subcategory":"Nail Salon",
            "type":"Services"
        }
    ],
    "sg:phone":"+1 217 359 8310",
    "sg:postcode":"61821",
    "sg:province":"IL",
    "wof:name":"My Salon",
    "wof:placetype":"venue"
},
  "geometry": {"coordinates":[-88.257752,40.097115],"type":"Point"}
}