{
  "type": "Feature",
  "properties": {
    "iso:country":"US",
    "sg:address":"447 South Blvd.",
    "sg:city":"Oak Park",
    "sg:classifiers":[
        {
            "category":"Sports & Exercise",
            "subcategory":"Gym",
            "type":"Entertainment"
        }
    ],
    "sg:phone":"+1 708 386 5011",
    "sg:postcode":"60302",
    "sg:province":"IL",
    "sg:tags":[
        "trainer"
    ],
    "sg:website":"www.bfit-fitness.com",
    "wof:name":"BFit-Fitness",
    "wof:placetype":"venue"
},
  "geometry": {"coordinates":[-87.786959,41.886913],"type":"Point"}
}