{
  "type": "Feature",
  "properties": {
    "addr:full":"28615 W Park Dr Barrington IL 60010",
    "addr:housenumber":"28615",
    "addr:postcode":"60010",
    "addr:street":"W Park Dr",
    "iso:country":"US",
    "sg:address":"28615 W Park Dr",
    "sg:city":"Barrington",
    "sg:classifiers":[
        {
            "category":"Home & Garden",
            "subcategory":"Household Appliances",
            "type":"Retail Goods"
        },
        {
            "category":"Building & Trades",
            "subcategory":"Cleaning & Sanitation",
            "type":"Services"
        },
        {
            "category":"Building & Trades",
            "subcategory":"Construction",
            "type":"Services"
        }
    ],
    "sg:phone":"+1 847 550 9373",
    "sg:postcode":"60010",
    "sg:province":"IL",
    "sg:tags":[
        "site-clean-up",
        "floor",
        "waxing",
        "contractor",
        "window",
        "cleaning-industrial",
        "vacuum",
        "polishing",
        "janitorial"
    ],
    "sg:website":"https://smclean.custhelp.com/cgi-bin/smclean.cfg/php/enduser/doc_serve.php?2=BSYellowPages09",
    "wof:name":"ServiceMaster Clean",
    "wof:placetype":"venue"
},
  "geometry": {"coordinates":[-88.191824,42.202277],"type":"Point"}
}