{
  "type": "Feature",
  "properties": {
    "iso:country":"US",
    "sg:address":"945 S Bartlett Rd Ste A",
    "sg:city":"Streamwood",
    "sg:classifiers":[
        {
            "category":"Health Services",
            "subcategory":"Dentist",
            "type":"Services"
        }
    ],
    "sg:phone":"+1 630 837 0887",
    "sg:postcode":"60107",
    "sg:province":"IL",
    "sg:website":"http://hi-techdental.com",
    "wof:name":"Arnold, Jos A Dds",
    "wof:placetype":"venue"
},
  "geometry": {"coordinates":[-88.18329,42.014597],"type":"Point"}
}