{
  "type": "Feature",
  "properties": {
    "iso:country":"US",
    "sg:address":"5265 Killdeer Pl",
    "sg:city":"Rockford",
    "sg:classifiers":[
        {
            "category":"Social Services",
            "subcategory":"Child Care",
            "type":"Services"
        }
    ],
    "sg:phone":"+1 815 636 2200",
    "sg:postcode":"61114",
    "sg:province":"IL",
    "sg:tags":[
        "day"
    ],
    "wof:name":"Knowledge Learning Corporation",
    "wof:placetype":"venue"
},
  "geometry": {"coordinates":[-89.014441,42.314269],"type":"Point"}
}