{
  "type": "Feature",
  "properties": {
    "addr:full":"500 S Goodwin Ave Urbana IL 61801",
    "addr:housenumber":"500",
    "addr:postcode":"61801",
    "addr:street":"S Goodwin Ave",
    "iso:country":"US",
    "sg:address":"500 S Goodwin Ave",
    "sg:city":"Urbana",
    "sg:classifiers":[
        {
            "category":"Education",
            "subcategory":"University",
            "type":"Public Place"
        }
    ],
    "sg:phone":"+1 217 333 6700",
    "sg:postcode":"61801",
    "sg:province":"IL",
    "sg:tags":[
        "college"
    ],
    "sg:website":"www.krannertcenter.com",
    "wof:name":"University of Illinois",
    "wof:placetype":"venue"
},
  "geometry": {"coordinates":[-88.223721,40.109063],"type":"Point"}
}