{
  "type": "Feature",
  "properties": {
    "iso:country":"US",
    "sg:address":"101 Broadway St",
    "sg:city":"Cave In Rock",
    "sg:classifiers":[
        {
            "category":"Home & Garden",
            "subcategory":"Home Furnishings",
            "type":"Retail Goods"
        }
    ],
    "sg:phone":"+1 618 289 4513",
    "sg:postcode":"62933",
    "sg:province":"IL",
    "sg:tags":[
        "quilting"
    ],
    "wof:name":"Nancy's Riverside Quilting",
    "wof:placetype":"venue"
},
  "geometry": {"coordinates":[-89.02790899999999,37.771636],"type":"Point"}
}