{
  "type": "Feature",
  "properties": {
    "iso:country":"US",
    "sg:address":"2110 1st St",
    "sg:city":"East Carondelet",
    "sg:classifiers":[
        {
            "category":"Recreation",
            "type":"Entertainment"
        }
    ],
    "sg:phone":"+1 618 286 1980",
    "sg:postcode":"62240",
    "sg:province":"IL",
    "sg:tags":[
        "historical"
    ],
    "wof:name":"Martin/Boismenue House",
    "wof:placetype":"venue"
},
  "geometry": {"coordinates":[-90.200022,38.546259],"type":"Point"}
}