{
  "type": "Feature",
  "properties": {
    "iso:country":"US",
    "sg:address":"7417 Madison St",
    "sg:city":"Forest Park",
    "sg:classifiers":[
        {
            "category":"Health Services",
            "subcategory":"Optometrist",
            "type":"Services"
        }
    ],
    "sg:phone":"+1 708 366 9700",
    "sg:postcode":"60130",
    "sg:province":"IL",
    "wof:name":"Joseph B Jackson O D",
    "wof:placetype":"venue"
},
  "geometry": {"coordinates":[-87.810093,41.879613],"type":"Point"}
}