{
  "type": "Feature",
  "properties": {
    "addr:full":"577 Burnham Ave Calumet City IL 60409",
    "addr:housenumber":"577",
    "addr:postcode":"60409",
    "addr:street":"Burnham Ave",
    "iso:country":"US",
    "sg:address":"577 Burnham Ave",
    "sg:city":"Calumet City",
    "sg:classifiers":[
        {
            "category":"Retail",
            "subcategory":"Laundry & Dry Cleaning",
            "type":"Services"
        }
    ],
    "sg:phone":"+1 708 862 4906",
    "sg:postcode":"60409",
    "sg:province":"IL",
    "sg:tags":[
        "drycleaning",
        "plant"
    ],
    "wof:name":"Your Town Cleaners",
    "wof:placetype":"venue"
},
  "geometry": {"coordinates":[-87.53939800000001,41.618],"type":"Point"}
}