{
  "type": "Feature",
  "properties": {
    "addr:full":"101 E Clinton Ave Patoka IL 62875",
    "addr:housenumber":"101",
    "addr:postcode":"62875",
    "addr:street":"E Clinton Ave",
    "iso:country":"US",
    "sg:address":"101 E Clinton Ave",
    "sg:city":"Patoka",
    "sg:classifiers":[
        {
            "category":"Retail",
            "subcategory":"Funeral Services",
            "type":"Services"
        }
    ],
    "sg:phone":"+1 618 432 5324",
    "sg:postcode":"62875",
    "sg:province":"IL",
    "sg:tags":[
        "director"
    ],
    "wof:name":"Day Funeral Homes LTD",
    "wof:placetype":"venue"
},
  "geometry": {"coordinates":[-89.09584700000001,38.750813],"type":"Point"}
}