{
  "type": "Feature",
  "properties": {
    "iso:country":"US",
    "sg:address":"375 W Erie St Apt 601",
    "sg:city":"Chicago",
    "sg:classifiers":[
        {
            "category":"Professional",
            "subcategory":"Printing & Photocopies",
            "type":"Services"
        }
    ],
    "sg:phone":"+1 312 624 8408",
    "sg:postcode":"60654",
    "sg:province":"IL",
    "sg:tags":[
        "lithographer"
    ],
    "wof:name":"Print Dog",
    "wof:placetype":"venue"
},
  "geometry": {"coordinates":[-87.63851200000001,41.893921],"type":"Point"}
}