{
  "type": "Feature",
  "properties": {
    "iso:country":"US",
    "sg:address":"1300 S 9th St",
    "sg:city":"Springfield",
    "sg:classifiers":[
        {
            "category":"Government",
            "subcategory":"Office",
            "type":"Public Place"
        }
    ],
    "sg:phone":"+1 217 524 7818",
    "sg:postcode":"62703",
    "sg:province":"IL",
    "sg:tags":[
        "parish",
        "government-county"
    ],
    "sg:website":"http://www.illinoisskillsmatch.com",
    "wof:name":"Field Auditors",
    "wof:placetype":"venue"
},
  "geometry": {"coordinates":[-89.644703,39.76897],"type":"Point"}
}