{
  "type": "Feature",
  "properties": {
    "addr:full":"1885 N Farnsworth Ave Ste 8 Aurora IL 60505",
    "addr:housenumber":"1885",
    "addr:postcode":"60505",
    "addr:street":"N Farnsworth Ave Ste 8",
    "iso:country":"US",
    "sg:address":"1885 N Farnsworth Ave Ste 8",
    "sg:city":"Aurora",
    "sg:classifiers":[
        {
            "category":"Organizations",
            "subcategory":"Labor Organization",
            "type":"Services"
        }
    ],
    "sg:phone":"+1 630 820 3950",
    "sg:postcode":"60505",
    "sg:province":"IL",
    "sg:website":"http://www.ibew.org",
    "wof:name":"Ibew",
    "wof:placetype":"venue"
},
  "geometry": {"coordinates":[-88.28200699999999,41.794375],"type":"Point"}
}