{
  "type": "Feature",
  "properties": {
    "iso:country":"US",
    "sg:address":"477 S 3rd St",
    "sg:city":"Geneva",
    "sg:classifiers":[
        {
            "category":"Banks & Credit Unions",
            "subcategory":"Investment Brokerage",
            "type":"Services"
        }
    ],
    "sg:phone":"+1 630 397 5200",
    "sg:postcode":"60134",
    "sg:province":"IL",
    "sg:tags":[
        "advisory"
    ],
    "wof:name":"On Path Financial LLC",
    "wof:placetype":"venue"
},
  "geometry": {"coordinates":[-88.308863,41.883528],"type":"Point"}
}