{
  "type": "Feature",
  "properties": {
    "addr:full":"5046 W Armitage Ave Chicago IL 60639",
    "addr:housenumber":"5046",
    "addr:postcode":"60639",
    "addr:street":"W Armitage Ave",
    "iso:country":"US",
    "sg:address":"5046 W Armitage Ave",
    "sg:city":"Chicago",
    "sg:classifiers":[
        {
            "category":"Restaurant",
            "type":"Food & Drink"
        }
    ],
    "sg:phone":"+1 773 237 3351",
    "sg:postcode":"60639",
    "sg:province":"IL",
    "sg:tags":[
        "traditional",
        "american"
    ],
    "wof:name":"Haydee's Grill",
    "wof:placetype":"venue"
},
  "geometry": {"coordinates":[-87.75272200000001,41.917046],"type":"Point"}
}