{
  "type": "Feature",
  "properties": {
    "iso:country":"US",
    "sg:address":"1321 Maple Dr",
    "sg:city":"Peru",
    "sg:classifiers":[
        {
            "category":"Freight",
            "type":"Transportation"
        }
    ],
    "sg:phone":"+1 815 220 0359",
    "sg:postcode":"61354",
    "sg:province":"IL",
    "wof:name":"R & D Delivery Services",
    "wof:placetype":"venue"
},
  "geometry": {"coordinates":[-89.12288700000001,41.339722],"type":"Point"}
}