{
  "type": "Feature",
  "properties": {
    "iso:country":"US",
    "sg:address":"5235 W Main St",
    "sg:city":"Monee",
    "sg:classifiers":[
        {
            "category":"Professional",
            "subcategory":"Computer Services",
            "type":"Services"
        }
    ],
    "sg:phone":"+1 708 534 7968",
    "sg:postcode":"60449",
    "sg:province":"IL",
    "sg:tags":[
        "consultant",
        "designer",
        "system"
    ],
    "wof:name":"Wc Engineering",
    "wof:placetype":"venue"
},
  "geometry": {"coordinates":[-87.739126,41.418859],"type":"Point"}
}