{
  "type": "Feature",
  "properties": {
    "addr:full":"210 W Elk St Geneseo IL 61254",
    "addr:housenumber":"210",
    "addr:postcode":"61254",
    "addr:street":"W Elk St",
    "iso:country":"US",
    "sg:address":"210 W Elk St",
    "sg:city":"Geneseo",
    "sg:classifiers":[
        {
            "category":"Building & Trades",
            "subcategory":"Construction",
            "type":"Services"
        }
    ],
    "sg:phone":"+1 309 944 6407",
    "sg:postcode":"61254",
    "sg:province":"IL",
    "sg:tags":[
        "contractor"
    ],
    "wof:name":"Turner Construction Co",
    "wof:placetype":"venue"
},
  "geometry": {"coordinates":[-90.158312,41.460099],"type":"Point"}
}