{
  "type": "Feature",
  "properties": {
    "iso:country":"US",
    "sg:address":"610 S Darst St",
    "sg:city":"Eureka",
    "sg:classifiers":[
        {
            "category":"Retail",
            "subcategory":"Car Wash",
            "type":"Services"
        }
    ],
    "sg:phone":"+1 309 635 3977",
    "sg:postcode":"61530",
    "sg:province":"IL",
    "sg:tags":[
        "carwash"
    ],
    "wof:name":"Mobile Auto Detailg",
    "wof:placetype":"venue"
},
  "geometry": {"coordinates":[-89.27019199999999,40.715737],"type":"Point"}
}