{
  "type": "Feature",
  "properties": {
    "addr:full":"1003 W Chatham Dr Palatine IL 60067",
    "addr:housenumber":"1003",
    "addr:postcode":"60067",
    "addr:street":"W Chatham Dr",
    "iso:country":"US",
    "sg:address":"1003 W Chatham Dr",
    "sg:city":"Palatine",
    "sg:classifiers":[
        {
            "category":"Professional",
            "subcategory":"Management & Consulting",
            "type":"Services"
        }
    ],
    "sg:phone":"+1 773 348 1600",
    "sg:postcode":"60067",
    "sg:province":"IL",
    "sg:tags":[
        "business"
    ],
    "wof:name":"Sterling Tlmanagement Cons LLC",
    "wof:placetype":"venue"
},
  "geometry": {"coordinates":[-88.06809800000001,42.100864],"type":"Point"}
}