{
  "type": "Feature",
  "properties": {
    "addr:full":"9935 S 76th Ave Bridgeview IL 60455",
    "addr:housenumber":"9935",
    "addr:postcode":"60455",
    "addr:street":"S 76Th Ave",
    "iso:country":"US",
    "sg:address":"9935 S 76th Ave",
    "sg:city":"Bridgeview",
    "sg:classifiers":[
        {
            "category":"Manufacturing",
            "subcategory":"Tools & Machinery",
            "type":"Manufacturing & Wholesale Goods"
        }
    ],
    "sg:phone":"+1 708 599 4766",
    "sg:postcode":"60455",
    "sg:province":"IL",
    "sg:tags":[
        "mfg",
        "repair",
        "industrial",
        "welding"
    ],
    "wof:name":"J & W Machining",
    "wof:placetype":"venue"
},
  "geometry": {"coordinates":[-87.808333,41.709344],"type":"Point"}
}