{
  "type": "Feature",
  "properties": {
    "addr:full":"808 E Pleasant St Belvidere IL 61008",
    "addr:housenumber":"808",
    "addr:postcode":"61008",
    "addr:street":"E Pleasant St",
    "iso:country":"US",
    "sg:address":"808 E Pleasant St",
    "sg:city":"Belvidere",
    "sg:classifiers":[
        {
            "category":"Manufacturing",
            "subcategory":"Tools & Machinery",
            "type":"Manufacturing & Wholesale Goods"
        }
    ],
    "sg:phone":"+1 815 544 0967",
    "sg:postcode":"61008",
    "sg:province":"IL",
    "sg:tags":[
        "machine",
        "shop"
    ],
    "wof:name":"Dodge Machine Shop",
    "wof:placetype":"venue"
},
  "geometry": {"coordinates":[-88.832933,42.260813],"type":"Point"}
}