{
  "type": "Feature",
  "properties": {
    "addr:full":"3101 N Sheffield Ave Chicago IL 60657",
    "addr:housenumber":"3101",
    "addr:postcode":"60657",
    "addr:street":"N Sheffield Ave",
    "iso:country":"US",
    "sg:address":"3101 N Sheffield Ave",
    "sg:city":"Chicago",
    "sg:classifiers":[
        {
            "category":"Restaurant",
            "type":"Food & Drink"
        }
    ],
    "sg:menulink":"http://www.allmenus.com/il/chicago/273443-matilda/menu/",
    "sg:phone":"+1 773 883 4400",
    "sg:postcode":"60657",
    "sg:province":"IL",
    "sg:tags":[
        "new",
        "american"
    ],
    "wof:name":"Matilda",
    "wof:placetype":"venue"
},
  "geometry": {"coordinates":[-87.653942,41.938161],"type":"Point"}
}