{
  "type": "Feature",
  "properties": {
    "addr:full":"382 Northwest Hwy Cary IL 60013",
    "addr:housenumber":"382",
    "addr:postcode":"60013",
    "addr:street":"Northwest Hwy",
    "iso:country":"US",
    "sg:address":"382 Northwest Hwy",
    "sg:city":"Cary",
    "sg:classifiers":[
        {
            "category":"Food & Beverages",
            "subcategory":"Liquor & Beverages",
            "type":"Retail Goods"
        }
    ],
    "sg:phone":"+1   ",
    "sg:postcode":"60013",
    "sg:province":"IL",
    "sg:tags":[
        "store"
    ],
    "wof:name":"Volume Liquors",
    "wof:placetype":"venue"
},
  "geometry": {"coordinates":[-88.247642,42.212675],"type":"Point"}
}