{
  "type": "Feature",
  "properties": {
    "addr:full":"401 N Kirk Rd Geneva IL 60134",
    "addr:housenumber":"401",
    "addr:postcode":"60134",
    "addr:street":"N Kirk Rd",
    "iso:country":"US",
    "sg:address":"401 N Kirk Rd",
    "sg:city":"Geneva",
    "sg:classifiers":[
        {
            "category":"Wholesale",
            "subcategory":"Electrical",
            "type":"Manufacturing & Wholesale Goods"
        }
    ],
    "sg:phone":"+1 630 262 8300",
    "sg:postcode":"60134",
    "sg:province":"IL",
    "sg:tags":[
        "communication",
        "facsimile",
        "equipment"
    ],
    "sg:website":"www.gflesch.com",
    "wof:name":"Gordon Flesch Co",
    "wof:placetype":"venue"
},
  "geometry": {"coordinates":[-88.277095,41.890733],"type":"Point"}
}