{
  "type": "Feature",
  "properties": {
    "iso:country":"US",
    "sg:address":"39 Country Pl",
    "sg:city":"Springfield",
    "sg:classifiers":[
        {
            "category":"Professional",
            "subcategory":"Accounting & Tax Preparation",
            "type":"Services"
        }
    ],
    "sg:phone":"+1 217 585 6660",
    "sg:postcode":"62703",
    "sg:province":"IL",
    "sg:tags":[
        "public",
        "accountants-certified"
    ],
    "wof:name":"Byron L Wingate Cpa",
    "wof:placetype":"venue"
},
  "geometry": {"coordinates":[-89.63700900000001,39.718079],"type":"Point"}
}