{
  "type": "Feature",
  "properties": {
    "iso:country":"US",
    "sg:address":"845 N. Michigan Avenue",
    "sg:city":"Chicago",
    "sg:classifiers":[
        {
            "category":"Shopping",
            "subcategory":"Clothing, Apparel, & Fashions",
            "type":"Retail Goods"
        }
    ],
    "sg:phone":"+1 312 335 7700",
    "sg:postcode":"60610",
    "sg:province":"IL",
    "sg:tags":[
        "accessory",
        "clothing",
        "women's"
    ],
    "wof:name":"Rampage",
    "wof:placetype":"venue"
},
  "geometry": {"coordinates":[-87.623901,41.898102],"type":"Point"}
}