{
  "type": "Feature",
  "properties": {
    "iso:country":"US",
    "sg:address":"11000 S Nagle Ave",
    "sg:city":"Worth",
    "sg:classifiers":[
        {
            "category":"Building & Trades",
            "subcategory":"Construction",
            "type":"Services"
        }
    ],
    "sg:phone":"+1 708 361 2893",
    "sg:postcode":"60482",
    "sg:province":"IL",
    "sg:tags":[
        "pointing",
        "tuck"
    ],
    "wof:name":"Casto Bros",
    "wof:placetype":"venue"
},
  "geometry": {"coordinates":[-87.78009,41.692169],"type":"Point"}
}