{
  "type": "Feature",
  "properties": {
    "addr:full":"1525 E Riverside Blvd Loves Park IL 61111",
    "addr:housenumber":"1525",
    "addr:postcode":"61111",
    "addr:street":"E Riverside Blvd",
    "iso:country":"US",
    "sg:address":"1525 E Riverside Blvd",
    "sg:city":"Loves Park",
    "sg:classifiers":[
        {
            "category":"Restaurant",
            "type":"Food & Drink"
        }
    ],
    "sg:menulink":"http://www.allmenus.com/il/rockford/196260-taco-bell/menu/",
    "sg:postcode":"61111",
    "sg:province":"IL",
    "sg:tags":[
        "mexican"
    ],
    "wof:name":"Taco Bell",
    "wof:placetype":"venue"
},
  "geometry": {"coordinates":[-89.038376,42.318043],"type":"Point"}
}