{
  "type": "Feature",
  "properties": {
    "addr:full":"2202 N Halsted Chicago IL 60614",
    "addr:housenumber":"2202",
    "addr:postcode":"60614",
    "addr:street":"N Halsted",
    "iso:country":"US",
    "sg:address":"2202 N Halsted",
    "sg:city":"Chicago",
    "sg:classifiers":[
        {
            "category":"Shopping",
            "subcategory":"Clothing, Apparel, & Fashions",
            "type":"Retail Goods"
        }
    ],
    "sg:phone":"+1 773 281 9590",
    "sg:postcode":"60614",
    "sg:province":"IL",
    "sg:tags":[
        "men's",
        "clothing",
        "accessory",
        "women's"
    ],
    "sg:website":"www.truereligionbrandjeans.com",
    "wof:name":"True Religion Brand Jeans",
    "wof:placetype":"venue"
},
  "geometry": {"coordinates":[-87.64879500000001,41.922006],"type":"Point"}
}