{
  "type": "Feature",
  "properties": {
    "iso:country":"US",
    "sg:address":"22 Brandywine Rd",
    "sg:city":"Barrington",
    "sg:classifiers":[
        {
            "category":"Professional",
            "type":"Services"
        }
    ],
    "sg:phone":"+1 312 321 0653",
    "sg:postcode":"60010",
    "sg:province":"IL",
    "wof:name":"Illinois Insurance Info Svcs",
    "wof:placetype":"venue"
},
  "geometry": {"coordinates":[-88.176291,42.092391],"type":"Point"}
}