{
  "type": "Feature",
  "properties": {
    "iso:country":"US",
    "sg:address":"2050 N Broadmoor Ln",
    "sg:city":"Vernon Hills",
    "sg:classifiers":[
        {
            "category":"Utilities",
            "subcategory":"Mobile Phone",
            "type":"Services"
        }
    ],
    "sg:phone":"+1 847 680 4443",
    "sg:postcode":"60061",
    "sg:province":"IL",
    "sg:tags":[
        "telephone",
        "cellular"
    ],
    "wof:name":"Corporate Cellular",
    "wof:placetype":"venue"
},
  "geometry": {"coordinates":[-87.969323,42.263701],"type":"Point"}
}