{
  "type": "Feature",
  "properties": {
    "iso:country":"US",
    "sg:address":"16828 Robin Ln",
    "sg:city":"Orland Park",
    "sg:classifiers":[
        {
            "category":"Professional",
            "subcategory":"Computer Services",
            "type":"Services"
        }
    ],
    "sg:phone":"+1 847 331 2805",
    "sg:postcode":"60467",
    "sg:province":"IL",
    "sg:tags":[
        "related"
    ],
    "wof:name":"Tigroup",
    "wof:placetype":"venue"
},
  "geometry": {"coordinates":[-87.874601,41.582125],"type":"Point"}
}