{
  "type": "Feature",
  "properties": {
    "addr:full":"125 E State Rd Island Lake IL 60042",
    "addr:housenumber":"125",
    "addr:postcode":"60042",
    "addr:street":"E State Rd",
    "iso:country":"US",
    "sg:address":"125 E State Rd",
    "sg:city":"Island Lake",
    "sg:classifiers":[
        {
            "category":"Restaurant",
            "type":"Food & Drink"
        },
        {
            "category":"Ice Cream",
            "type":"Food & Drink"
        }
    ],
    "sg:menulink":"http://www.allmenus.com/il/wauconda/161813-dairy-queen/menu/",
    "sg:phone":"+1 847 487 1919",
    "sg:postcode":"60042",
    "sg:province":"IL",
    "sg:tags":[
        "burger",
        "american",
        "ice",
        "cream"
    ],
    "wof:name":"Dairy Queen",
    "wof:placetype":"venue"
},
  "geometry": {"coordinates":[-88.196879,42.271985],"type":"Point"}
}