{
  "type": "Feature",
  "properties": {
    "iso:country":"US",
    "sg:address":"1041 Grace Ave",
    "sg:city":"Aurora",
    "sg:classifiers":[
        {
            "category":"Manufacturing",
            "subcategory":"Tools & Machinery",
            "type":"Manufacturing & Wholesale Goods"
        }
    ],
    "sg:phone":"+1 630 859 2638",
    "sg:postcode":"60506",
    "sg:province":"IL",
    "sg:website":"www.auroracustom.com",
    "wof:name":"Aurora Custom Machining Inc",
    "wof:placetype":"venue"
},
  "geometry": {"coordinates":[-88.34107299999999,41.742334],"type":"Point"}
}