{
  "type": "Feature",
  "properties": {
    "addr:full":"11 Harrington Ct Lake Zurich IL 60047",
    "addr:housenumber":"11",
    "addr:postcode":"60047",
    "addr:street":"Harrington Ct",
    "iso:country":"US",
    "sg:address":"11 Harrington Ct",
    "sg:city":"Lake Zurich",
    "sg:classifiers":[
        {
            "category":"Building & Trades",
            "subcategory":"Construction",
            "type":"Services"
        }
    ],
    "sg:phone":"+1 847 719 2557",
    "sg:postcode":"60047",
    "sg:province":"IL",
    "sg:tags":[
        "roofing",
        "contractor"
    ],
    "wof:name":"New Way Roofing",
    "wof:placetype":"venue"
},
  "geometry": {"coordinates":[-88.02893899999999,42.21841],"type":"Point"}
}