{
  "type": "Feature",
  "properties": {
    "addr:full":"1924 E State St Rockford IL 61104",
    "addr:housenumber":"1924",
    "addr:postcode":"61104",
    "addr:street":"E State St",
    "iso:country":"US",
    "sg:address":"1924 E State St",
    "sg:city":"Rockford",
    "sg:classifiers":[
        {
            "category":"Manufacturing",
            "subcategory":"Printing",
            "type":"Manufacturing & Wholesale Goods"
        }
    ],
    "sg:phone":"+1 815 229 0207",
    "sg:postcode":"61104",
    "sg:province":"IL",
    "sg:tags":[
        "commercial"
    ],
    "wof:name":"TS R US Inc",
    "wof:placetype":"venue"
},
  "geometry": {"coordinates":[-89.06261499999999,42.267072],"type":"Point"}
}