{
  "type": "Feature",
  "properties": {
    "iso:country":"US",
    "sg:address":"49 W Rand Rd",
    "sg:city":"Arlington Heights",
    "sg:classifiers":[
        {
            "category":"Shopping",
            "type":"Retail Goods"
        }
    ],
    "sg:phone":"+1   ",
    "sg:postcode":"60004",
    "sg:province":"IL",
    "sg:tags":[
        "pet",
        "food",
        "supply"
    ],
    "wof:name":"Petsmart",
    "wof:placetype":"venue"
},
  "geometry": {"coordinates":[-87.98267,42.114049],"type":"Point"}
}