{
  "type": "Feature",
  "properties": {
    "addr:full":"4021 183rd St Country Club Hills IL 60478",
    "addr:housenumber":"4021",
    "addr:postcode":"60478",
    "addr:street":"183Rd St",
    "iso:country":"US",
    "sg:address":"4021 183rd St",
    "sg:city":"Country Club Hills",
    "sg:classifiers":[
        {
            "category":"Restaurant",
            "type":"Food & Drink"
        }
    ],
    "sg:phone":"+1   ",
    "sg:postcode":"60478",
    "sg:province":"IL",
    "sg:tags":[
        "fast",
        "chain"
    ],
    "wof:name":"Hardees",
    "wof:placetype":"venue"
},
  "geometry": {"coordinates":[-87.713989,41.557056],"type":"Point"}
}