{
  "type": "Feature",
  "properties": {
    "iso:country":"US",
    "sg:address":"308 S 3rd St",
    "sg:city":"Greenville",
    "sg:classifiers":[
        {
            "category":"Professional",
            "subcategory":"Business Services",
            "type":"Services"
        }
    ],
    "sg:phone":"+1 618 664 4232",
    "sg:postcode":"62246",
    "sg:province":"IL",
    "sg:tags":[
        "appraiser"
    ],
    "wof:name":"Tri County Real Estate Svc",
    "wof:placetype":"venue"
},
  "geometry": {"coordinates":[-89.413381,38.890482],"type":"Point"}
}