{
  "type": "Feature",
  "properties": {
    "iso:country":"US",
    "sg:address":"360 E Butterfield Rd",
    "sg:city":"Elmhurst",
    "sg:classifiers":[
        {
            "category":"Banks & Credit Unions",
            "subcategory":"Bank",
            "type":"Services"
        }
    ],
    "sg:phone":"+1 630 384 3925",
    "sg:postcode":"60126",
    "sg:province":"IL",
    "wof:name":"Bank Of American",
    "wof:placetype":"venue"
},
  "geometry": {"coordinates":[-87.925112,41.871855],"type":"Point"}
}