{
  "type": "Feature",
  "properties": {
    "addr:full":"3000 Wireton Rd Blue Island IL 60406",
    "addr:postcode":"3000;60406",
    "addr:street":"Wireton Rd",
    "iso:country":"US",
    "sg:address":"3000 Wireton Rd",
    "sg:city":"Blue Island",
    "sg:classifiers":[
        {
            "category":"Manufacturing",
            "subcategory":"Food",
            "type":"Manufacturing & Wholesale Goods"
        }
    ],
    "sg:phone":"+1 708 388 3223",
    "sg:postcode":"60406",
    "sg:province":"IL",
    "sg:tags":[
        "feed",
        "mfg",
        "local",
        "prepared"
    ],
    "wof:name":"Darling International Inc",
    "wof:placetype":"venue"
},
  "geometry": {"coordinates":[-87.69421699999999,41.656666],"type":"Point"}
}