{
  "type": "Feature",
  "properties": {
    "iso:country":"US",
    "sg:address":"1655 Felton St",
    "sg:city":"Aurora",
    "sg:classifiers":[
        {
            "category":"Social Services",
            "subcategory":"Child Care",
            "type":"Services"
        }
    ],
    "sg:phone":"+1 630 820 2454",
    "sg:postcode":"60505",
    "sg:province":"IL",
    "wof:name":"Makel's Day Care",
    "wof:placetype":"venue"
},
  "geometry": {"coordinates":[-88.26961799999999,41.793561],"type":"Point"}
}