{
  "type": "Feature",
  "properties": {
    "iso:country":"US",
    "sg:address":"4545 N Beacon St.",
    "sg:city":"Chicago",
    "sg:classifiers":[
        {
            "category":"Real Estate",
            "subcategory":"Real Estate Operator",
            "type":"Services"
        }
    ],
    "sg:postcode":"60640",
    "sg:province":"IL",
    "sg:tags":[
        "apartment"
    ],
    "wof:name":"Bertsch Properties",
    "wof:placetype":"venue"
},
  "geometry": {"coordinates":[-87.663381,41.964872],"type":"Point"}
}