{
  "type": "Feature",
  "properties": {
    "iso:country":"US",
    "sg:address":"2496 N Co Rd 2600",
    "sg:city":"La Harpe",
    "sg:classifiers":[
        {
            "category":"Building & Trades",
            "subcategory":"Construction",
            "type":"Services"
        }
    ],
    "sg:phone":"+1 217 659 3050",
    "sg:postcode":"61450",
    "sg:province":"IL",
    "sg:tags":[
        "house",
        "contractor",
        "concrete"
    ],
    "wof:name":"Larry Mynatt Construction Co",
    "wof:placetype":"venue"
},
  "geometry": {"coordinates":[-91.002713,40.547606],"type":"Point"}
}