{
  "type": "Feature",
  "properties": {
    "addr:full":"3117 N Knox Ave Chicago IL 60641",
    "addr:housenumber":"3117",
    "addr:postcode":"60641",
    "addr:street":"N Knox Ave",
    "iso:country":"US",
    "sg:address":"3117 N Knox Ave",
    "sg:city":"Chicago",
    "sg:classifiers":[
        {
            "category":"Manufacturing",
            "subcategory":"Chemicals & Compounds",
            "type":"Manufacturing & Wholesale Goods"
        }
    ],
    "sg:phone":"+1 773 427 7644",
    "sg:postcode":"60641",
    "sg:province":"IL",
    "sg:tags":[
        "polishing",
        "preparation",
        "specialty",
        "sanitation",
        "cleaning"
    ],
    "wof:name":"Medallion Products Inc",
    "wof:placetype":"venue"
},
  "geometry": {"coordinates":[-87.743133,41.93813],"type":"Point"}
}