{
  "type": "Feature",
  "properties": {
    "iso:country":"US",
    "sg:address":"1333 N Delany Rd",
    "sg:city":"Gurnee",
    "sg:classifiers":[
        {
            "category":"Restaurant",
            "type":"Food & Drink"
        }
    ],
    "sg:menulink":"http://www.allmenus.com/il/warren/126538-subway/menu/",
    "sg:phone":"+1 847 263 9202",
    "sg:postcode":"60031",
    "sg:province":"IL",
    "sg:tags":[
        "american",
        "sandwich"
    ],
    "wof:name":"Subway",
    "wof:placetype":"venue"
},
  "geometry": {"coordinates":[-87.90386599999999,42.379257],"type":"Point"}
}