{
  "type": "Feature",
  "properties": {
    "iso:country":"US",
    "sg:address":"43373 N Mildred Ave",
    "sg:city":"Antioch",
    "sg:classifiers":[
        {
            "category":"Building & Trades",
            "subcategory":"Landscaping Services",
            "type":"Services"
        }
    ],
    "sg:phone":"+1 847 395 2192",
    "sg:postcode":"60002",
    "sg:province":"IL",
    "wof:name":"C S Lawn & Landscape Inc",
    "wof:placetype":"venue"
},
  "geometry": {"coordinates":[-88.128888,42.494956],"type":"Point"}
}