{
  "type": "Feature",
  "properties": {
    "iso:country":"US",
    "sg:address":"40W825 Hidden Lakes Dr",
    "sg:city":"Elgin",
    "sg:classifiers":[
        {
            "category":"Real Estate",
            "subcategory":"Real Estate Services",
            "type":"Services"
        },
        {
            "category":"Real Estate",
            "subcategory":"Real Estate Agent",
            "type":"Services"
        }
    ],
    "sg:phone":"+1 847 464 1400",
    "sg:postcode":"60124",
    "sg:province":"IL",
    "sg:tags":[
        "buyer",
        "broker"
    ],
    "wof:name":"Wolf Realty",
    "wof:placetype":"venue"
},
  "geometry": {"coordinates":[-88.41048000000001,42.024786],"type":"Point"}
}