{
  "type": "Feature",
  "properties": {
    "iso:country":"US",
    "sg:address":"35 N Bennett St",
    "sg:city":"Geneva",
    "sg:classifiers":[
        {
            "category":"Retail",
            "subcategory":"Repair Shop",
            "type":"Services"
        }
    ],
    "sg:phone":"+1 630 232 8848",
    "sg:postcode":"60134",
    "sg:province":"IL",
    "sg:tags":[
        "trimmer",
        "snow",
        "removal",
        "equipment",
        "lawnmowers",
        "blower"
    ],
    "wof:name":"Mower-Blower Sales & Repair",
    "wof:placetype":"venue"
},
  "geometry": {"coordinates":[-88.300376,41.887118],"type":"Point"}
}