{
  "type": "Feature",
  "properties": {
    "addr:full":"1463 W Hubbard St Chicago IL 60622",
    "addr:housenumber":"1463",
    "addr:postcode":"60622",
    "addr:street":"W Hubbard St",
    "iso:country":"US",
    "sg:address":"1463 W Hubbard St",
    "sg:city":"Chicago",
    "sg:classifiers":[
        {
            "category":"Arts & Performance",
            "subcategory":"Arts Center",
            "type":"Entertainment"
        }
    ],
    "sg:phone":"+1 312 850 8440",
    "sg:postcode":"60622",
    "sg:province":"IL",
    "sg:tags":[
        "performing"
    ],
    "sg:website":"www.redmoon.org",
    "wof:name":"Redmoon Theater",
    "wof:placetype":"venue"
},
  "geometry": {"coordinates":[-87.664542,41.889921],"type":"Point"}
}