{
  "type": "Feature",
  "properties": {
    "addr:full":"5519 W Montrose Ave Chicago IL 60641",
    "addr:housenumber":"5519",
    "addr:postcode":"60641",
    "addr:street":"W Montrose Ave",
    "iso:country":"US",
    "sg:address":"5519 W Montrose Ave",
    "sg:city":"Chicago",
    "sg:classifiers":[
        {
            "category":"Banks & Credit Unions",
            "subcategory":"Investment Brokerage",
            "type":"Services"
        }
    ],
    "sg:phone":"+1 773 282 5657",
    "sg:postcode":"60641",
    "sg:province":"IL",
    "sg:tags":[
        "advisory"
    ],
    "wof:name":"Personal Financial Strategies",
    "wof:placetype":"venue"
},
  "geometry": {"coordinates":[-87.766306,41.960421],"type":"Point"}
}