{
  "type": "Feature",
  "properties": {
    "iso:country":"US",
    "sg:address":"2505 W Bainter Ln",
    "sg:city":"Peoria",
    "sg:classifiers":[
        {
            "category":"Wholesale",
            "subcategory":"Machinery & Supplies",
            "type":"Manufacturing & Wholesale Goods"
        }
    ],
    "sg:phone":"+1 309 688 3300",
    "sg:postcode":"61615",
    "sg:province":"IL",
    "sg:tags":[
        "equipment",
        "industrial"
    ],
    "wof:name":"Marquette Industrial Materials",
    "wof:placetype":"venue"
},
  "geometry": {"coordinates":[-89.631885,40.735761],"type":"Point"}
}