{
  "type": "Feature",
  "properties": {
    "iso:country":"US",
    "sg:address":"4244 N Brandywine Dr",
    "sg:city":"Peoria",
    "sg:classifiers":[
        {
            "category":"Travel",
            "subcategory":"Hotels & Motels",
            "type":"Entertainment"
        }
    ],
    "sg:phone":"+1 309 682 3322",
    "sg:postcode":"61614",
    "sg:province":"IL",
    "sg:tags":[
        "lodging"
    ],
    "sg:website":"http://www.sleepinn.com/hotel-peoria-illinois-IL162",
    "wof:name":"Sleep Inn Peoria",
    "wof:placetype":"venue"
},
  "geometry": {"coordinates":[-89.62333700000001,40.740529],"type":"Point"}
}