{
  "type": "Feature",
  "properties": {
    "iso:country":"US",
    "sg:address":"1311 N Galena Ave",
    "sg:city":"Dixon",
    "sg:classifiers":[
        {
            "category":"Personal",
            "subcategory":"Beauty Salon",
            "type":"Services"
        }
    ],
    "sg:phone":"+1 815 285 0306",
    "sg:postcode":"61021",
    "sg:province":"IL",
    "sg:tags":[
        "manicuring"
    ],
    "wof:name":"Star Nail",
    "wof:placetype":"venue"
},
  "geometry": {"coordinates":[-89.496894,41.860611],"type":"Point"}
}