{
  "type": "Feature",
  "properties": {
    "iso:country":"US",
    "sg:address":"4345 S Verona Rd",
    "sg:city":"Verona",
    "sg:classifiers":[
        {
            "category":"Wholesale",
            "subcategory":"Scrap",
            "type":"Manufacturing & Wholesale Goods"
        }
    ],
    "sg:phone":"+1 815 287 2445",
    "sg:postcode":"60479",
    "sg:province":"IL",
    "sg:tags":[
        "refuse",
        "material",
        "system"
    ],
    "wof:name":"Hierz Scrap Service",
    "wof:placetype":"venue"
},
  "geometry": {"coordinates":[-88.492291,41.219892],"type":"Point"}
}