{
  "type": "Feature",
  "properties": {
    "addr:full":"1207 3rd St Mc Henry IL 60050",
    "addr:housenumber":"1207",
    "addr:postcode":"60050",
    "addr:street":"3Rd St Mc Henry",
    "iso:country":"US",
    "sg:address":"1207 3rd St",
    "sg:city":"Mc Henry",
    "sg:classifiers":[
        {
            "category":"Retail",
            "subcategory":"Laundry & Dry Cleaning",
            "type":"Services"
        }
    ],
    "sg:phone":"+1 815 385 2011",
    "sg:postcode":"60050",
    "sg:province":"IL",
    "sg:tags":[
        "cleaners"
    ],
    "wof:name":"Mr Don's Cleaners Inc",
    "wof:placetype":"venue"
},
  "geometry": {"coordinates":[-88.27000200000001,42.345364],"type":"Point"}
}