{
  "type": "Feature",
  "properties": {
    "iso:country":"US",
    "sg:address":"3501 Nameoki Rd",
    "sg:city":"Granite City",
    "sg:classifiers":[
        {
            "category":"Restaurant",
            "type":"Food & Drink"
        }
    ],
    "sg:menulink":"http://www.allmenus.com/il/granite-city/159509-arbys/menu/",
    "sg:phone":"+1 618 798 9763",
    "sg:postcode":"62040",
    "sg:province":"IL",
    "sg:tags":[
        "burger",
        "american"
    ],
    "wof:name":"Arby's",
    "wof:placetype":"venue"
},
  "geometry": {"coordinates":[-90.12319100000001,38.725653],"type":"Point"}
}