{
  "type": "Feature",
  "properties": {
    "addr:full":"5327 Galloway Dr Schaumburg IL 60192",
    "addr:housenumber":"5327",
    "addr:postcode":"60192",
    "addr:street":"Galloway Dr",
    "iso:country":"US",
    "sg:address":"5327 Galloway Dr",
    "sg:city":"Schaumburg",
    "sg:classifiers":[
        {
            "category":"Organizations",
            "subcategory":"Religious Organization",
            "type":"Services"
        }
    ],
    "sg:phone":"+1 847 717 4990",
    "sg:postcode":"60192",
    "sg:province":"IL",
    "wof:name":"New Life Ministries",
    "wof:placetype":"venue"
},
  "geometry": {"coordinates":[-88.210562,42.061311],"type":"Point"}
}