{
  "type": "Feature",
  "properties": {
    "iso:country":"US",
    "sg:address":"5511 Gardner Expy",
    "sg:city":"Quincy",
    "sg:classifiers":[
        {
            "category":"Building & Trades",
            "subcategory":"Electrical",
            "type":"Services"
        }
    ],
    "sg:phone":"+1 217 223 5422",
    "sg:postcode":"62305",
    "sg:province":"IL",
    "sg:tags":[
        "industrial",
        "contractors-commercial",
        "electric"
    ],
    "wof:name":"Niekamp, Bud",
    "wof:placetype":"venue"
},
  "geometry": {"coordinates":[-91.38944,39.863454],"type":"Point"}
}