{
  "type": "Feature",
  "properties": {
    "addr:full":"2906 N Oak St Urbana IL 61802",
    "addr:housenumber":"2906",
    "addr:postcode":"61802",
    "addr:street":"N Oak St",
    "iso:country":"US",
    "sg:address":"2906 N Oak St",
    "sg:city":"Urbana",
    "sg:classifiers":[
        {
            "category":"Wholesale",
            "subcategory":"Hardware",
            "type":"Manufacturing & Wholesale Goods"
        },
        {
            "category":"Wholesale",
            "subcategory":"Construction Materials",
            "type":"Manufacturing & Wholesale Goods"
        },
        {
            "category":"Home & Garden",
            "subcategory":"Hardware",
            "type":"Retail Goods"
        }
    ],
    "sg:phone":"+1 217 355 1307",
    "sg:postcode":"61802",
    "sg:province":"IL",
    "sg:tags":[
        "equipment",
        "masonry",
        "hardware-builders",
        "store",
        "supply"
    ],
    "wof:name":"Vulcan Materials",
    "wof:placetype":"venue"
},
  "geometry": {"coordinates":[-88.22687500000001,40.142604],"type":"Point"}
}