{
  "type": "Feature",
  "properties": {
    "addr:full":"2000 Carmel Blvd Zion IL 60099",
    "addr:housenumber":"2000",
    "addr:postcode":"60099",
    "addr:street":"Carmel Blvd",
    "iso:country":"US",
    "sg:address":"2000 Carmel Blvd",
    "sg:city":"Zion",
    "sg:classifiers":[
        {
            "category":"Professional",
            "subcategory":"Employment Agencies",
            "type":"Services"
        }
    ],
    "sg:phone":"+1 847 731 8391",
    "sg:postcode":"60099",
    "sg:province":"IL",
    "sg:tags":[
        "contractor"
    ],
    "wof:name":"Sweet Fenique A Strongchance",
    "wof:placetype":"venue"
},
  "geometry": {"coordinates":[-87.83921100000001,42.43726],"type":"Point"}
}