{
  "type": "Feature",
  "properties": {
    "addr:full":"7262 S Coles Ave Chicago IL 60649",
    "addr:housenumber":"7262",
    "addr:postcode":"60649",
    "addr:street":"S Coles Ave",
    "iso:country":"US",
    "sg:address":"7262 S Coles Ave",
    "sg:city":"Chicago",
    "sg:classifiers":[
        {
            "category":"Organizations",
            "subcategory":"Religious Organization",
            "type":"Services"
        }
    ],
    "sg:phone":"+1 773 768 8423",
    "sg:postcode":"60649",
    "sg:province":"IL",
    "sg:tags":[
        "clergy"
    ],
    "wof:name":"Slaughter, James",
    "wof:placetype":"venue"
},
  "geometry": {"coordinates":[-87.562534,41.76404],"type":"Point"}
}