{
  "type": "Feature",
  "properties": {
    "addr:full":"40 Porter St Round Lake IL 60088",
    "addr:housenumber":"40",
    "addr:postcode":"60088",
    "addr:street":"Porter St",
    "iso:country":"US",
    "sg:address":"40 Porter St",
    "sg:city":"Round Lake",
    "sg:classifiers":[
        {
            "category":"Home & Garden",
            "subcategory":"Building Materials",
            "type":"Retail Goods"
        }
    ],
    "sg:phone":"+1 847 201 1090",
    "sg:postcode":"60088",
    "sg:province":"IL",
    "wof:name":"Stock Building Supply",
    "wof:placetype":"venue"
},
  "geometry": {"coordinates":[-87.838886,42.313548],"type":"Point"}
}