{
  "type": "Feature",
  "properties": {
    "iso:country":"US",
    "sg:address":"415 S Highway Ave",
    "sg:city":"De Land",
    "sg:classifiers":[
        {
            "category":"Government",
            "subcategory":"Office",
            "type":"Public Place"
        }
    ],
    "sg:phone":"+1 217 664 3613",
    "sg:postcode":"61839",
    "sg:province":"IL",
    "sg:tags":[
        "village"
    ],
    "wof:name":"Goose Creek Twp Office",
    "wof:placetype":"venue"
},
  "geometry": {"coordinates":[-88.645304,40.11699],"type":"Point"}
}