{
  "type": "Feature",
  "properties": {
    "iso:country":"US",
    "sg:address":"182 S 4th St",
    "sg:city":"Breese",
    "sg:classifiers":[
        {
            "category":"Social Services",
            "subcategory":"Child Care",
            "type":"Services"
        }
    ],
    "sg:phone":"+1 618 526 2757",
    "sg:postcode":"62230",
    "sg:province":"IL",
    "sg:tags":[
        "day"
    ],
    "wof:name":"Siblings and Company",
    "wof:placetype":"venue"
},
  "geometry": {"coordinates":[-89.533345,38.602995],"type":"Point"}
}