{
  "type": "Feature",
  "properties": {
    "iso:country":"US",
    "sg:address":"4421 Harrison St",
    "sg:city":"Hillside",
    "sg:classifiers":[
        {
            "category":"Professional",
            "subcategory":"Engineering",
            "type":"Services"
        }
    ],
    "sg:phone":"+1 708 449 0500",
    "sg:postcode":"60162",
    "sg:province":"IL",
    "sg:tags":[
        "consulting",
        "engineer"
    ],
    "sg:website":"http://www.psiusa.com",
    "wof:name":"Psi",
    "wof:placetype":"venue"
},
  "geometry": {"coordinates":[-87.893368,41.870157],"type":"Point"}
}