{
  "type": "Feature",
  "properties": {
    "iso:country":"US",
    "sg:address":"1506 N Rockton Ave",
    "sg:city":"Rockford",
    "sg:classifiers":[
        {
            "category":"Shopping",
            "subcategory":"Optical Goods",
            "type":"Retail Goods"
        }
    ],
    "sg:phone":"+1   ",
    "sg:postcode":"61103",
    "sg:province":"IL",
    "wof:name":"Rush Optical",
    "wof:placetype":"venue"
},
  "geometry": {"coordinates":[-89.096733,42.288932],"type":"Point"}
}