{
  "type": "Feature",
  "properties": {
    "iso:country":"US",
    "sg:address":"18 Devalle Dr",
    "sg:city":"Belleville",
    "sg:classifiers":[
        {
            "category":"Building & Trades",
            "subcategory":"Construction",
            "type":"Services"
        }
    ],
    "sg:phone":"+1 618 235 2596",
    "sg:postcode":"62234",
    "sg:province":"IL",
    "sg:tags":[
        "general",
        "commercial",
        "contractor"
    ],
    "wof:name":"B Shively Builders Inc",
    "wof:placetype":"venue"
},
  "geometry": {"coordinates":[-89.98768200000001,38.695653],"type":"Point"}
}