{
  "type": "Feature",
  "properties": {
    "addr:full":"2925 W Carroll Ave Chicago IL 60612",
    "addr:housenumber":"2925",
    "addr:postcode":"60612",
    "addr:street":"W Carroll Ave",
    "iso:country":"US",
    "sg:address":"2925 W Carroll Ave",
    "sg:city":"Chicago",
    "sg:classifiers":[
        {
            "category":"Professional",
            "subcategory":"Credit Reporting & Collection",
            "type":"Services"
        }
    ],
    "sg:phone":"+1 773 533 1590",
    "sg:postcode":"60612",
    "sg:province":"IL",
    "sg:tags":[
        "perforated",
        "material"
    ],
    "sg:website":"http://www.johnstonandchapman.com",
    "wof:name":"Chicago Flyhouse Inc",
    "wof:placetype":"venue"
},
  "geometry": {"coordinates":[-87.699528,41.887612],"type":"Point"}
}