{
  "type": "Feature",
  "properties": {
    "iso:country":"US",
    "sg:address":"5544 W Belmont Ave",
    "sg:city":"Chicago",
    "sg:classifiers":[
        {
            "category":"Health Services",
            "subcategory":"Clinic",
            "type":"Services"
        }
    ],
    "sg:phone":"+1 773 685 7816",
    "sg:postcode":"60641",
    "sg:province":"IL",
    "sg:tags":[
        "medical",
        "group"
    ],
    "wof:name":"Belmont Central Med Ctr",
    "wof:placetype":"venue"
},
  "geometry": {"coordinates":[-87.764188,41.93868],"type":"Point"}
}