{
  "type": "Feature",
  "properties": {
    "iso:country":"US",
    "sg:address":"6127 State St",
    "sg:city":"East St Louis",
    "sg:classifiers":[
        {
            "category":"Restaurant",
            "type":"Food & Drink"
        }
    ],
    "sg:phone":"+1 618 397 4626",
    "sg:postcode":"62203",
    "sg:province":"IL",
    "wof:name":"Muchies",
    "wof:placetype":"venue"
},
  "geometry": {"coordinates":[-90.08937,38.603641],"type":"Point"}
}