{
  "type": "Feature",
  "properties": {
    "iso:country":"US",
    "sg:address":"3846 E Solon Rd",
    "sg:city":"Richmond",
    "sg:classifiers":[
        {
            "category":"Shopping",
            "subcategory":"Gifts & Souvenirs",
            "type":"Retail Goods"
        }
    ],
    "sg:phone":"+1 815 675 6463",
    "sg:postcode":"60071",
    "sg:province":"IL",
    "sg:tags":[
        "shop"
    ],
    "wof:name":"Unique Expressions",
    "wof:placetype":"venue"
},
  "geometry": {"coordinates":[-88.272009,42.442943],"type":"Point"}
}