{
  "type": "Feature",
  "properties": {
    "addr:full":"1732 S Randall Rd Algonquin IL 60102",
    "addr:housenumber":"1732",
    "addr:postcode":"60102",
    "addr:street":"S Randall Rd",
    "iso:country":"US",
    "sg:address":"1732 S Randall Rd",
    "sg:city":"Algonquin",
    "sg:classifiers":[
        {
            "category":"Health Services",
            "subcategory":"Optometrist",
            "type":"Services"
        },
        {
            "category":"Shopping",
            "subcategory":"Optician",
            "type":"Retail Goods"
        }
    ],
    "sg:phone":"+1 847 658 7661",
    "sg:postcode":"60102",
    "sg:province":"IL",
    "sg:tags":[
        "eyewear"
    ],
    "sg:website":"www.eyeboutique.com",
    "wof:name":"Eye Boutique",
    "wof:placetype":"venue"
},
  "geometry": {"coordinates":[-88.335947,42.153425],"type":"Point"}
}