{
  "type": "Feature",
  "properties": {
    "addr:full":"2008 W Montrose Ave Chicago IL 60618",
    "addr:housenumber":"2008",
    "addr:postcode":"60618",
    "addr:street":"W Montrose Ave",
    "iso:country":"US",
    "sg:address":"2008 W Montrose Ave",
    "sg:city":"Chicago",
    "sg:classifiers":[
        {
            "category":"Retail",
            "subcategory":"Laundry & Dry Cleaning",
            "type":"Services"
        }
    ],
    "sg:phone":"+1 773 275 1331",
    "sg:postcode":"60618",
    "sg:province":"IL",
    "wof:name":"Coin Laundry",
    "wof:placetype":"venue"
},
  "geometry": {"coordinates":[-87.679331,41.96148],"type":"Point"}
}