{
  "type": "Feature",
  "properties": {
    "iso:country":"US",
    "sg:address":"3467 S King Dr",
    "sg:city":"Chicago",
    "sg:classifiers":[
        {
            "category":"Manufacturing",
            "subcategory":"Retail Goods",
            "type":"Manufacturing & Wholesale Goods"
        }
    ],
    "sg:phone":"+1 312 225 5692",
    "sg:postcode":"60653",
    "sg:province":"IL",
    "sg:tags":[
        "product",
        "mfg"
    ],
    "wof:name":"Neleh Artistic Expressions",
    "wof:placetype":"venue"
},
  "geometry": {"coordinates":[-87.616907,41.832512],"type":"Point"}
}