{
  "type": "Feature",
  "properties": {
    "iso:country":"US",
    "sg:address":"555 E Co Rd 500N",
    "sg:city":"Arcola",
    "sg:phone":"+1 217 268 3604",
    "sg:postcode":"61910",
    "sg:province":"IL",
    "sg:tags":[
        "farm",
        "corn",
        "soybean"
    ],
    "wof:name":"Bergfield Ebby",
    "wof:placetype":"venue"
},
  "geometry": {"coordinates":[-88.360895,39.724506],"type":"Point"}
}