{
  "type": "Feature",
  "properties": {
    "addr:full":"588 2nd Ave Aurora IL 60505",
    "addr:housenumber":"588",
    "addr:postcode":"60505",
    "addr:street":"2Nd Ave",
    "iso:country":"US",
    "sg:address":"588 2nd Ave",
    "sg:city":"Aurora",
    "sg:classifiers":[
        {
            "category":"Professional",
            "subcategory":"Management & Consulting",
            "type":"Services"
        }
    ],
    "sg:phone":"+1 630 373 3315",
    "sg:postcode":"60505",
    "sg:province":"IL",
    "wof:name":"Maria Heredia",
    "wof:placetype":"venue"
},
  "geometry": {"coordinates":[-88.306428,41.75072],"type":"Point"}
}