{
  "type": "Feature",
  "properties": {
    "addr:full":"2215 Belvidere Rd Waukegan IL 60085",
    "addr:housenumber":"2215",
    "addr:postcode":"60085",
    "addr:street":"Belvidere Rd",
    "iso:country":"US",
    "sg:address":"2215 Belvidere Rd",
    "sg:city":"Waukegan",
    "sg:classifiers":[
        {
            "category":"Personal",
            "subcategory":"Beauty Salon",
            "type":"Services"
        }
    ],
    "sg:phone":"+1 847 249 7776",
    "sg:postcode":"60085",
    "sg:province":"IL",
    "wof:name":"Perfection Hair Salon",
    "wof:placetype":"venue"
},
  "geometry": {"coordinates":[-87.86108900000001,42.350409],"type":"Point"}
}