{
  "type": "Feature",
  "properties": {
    "addr:full":"26118 Simotes Ln Wilmington IL 60481",
    "addr:housenumber":"26118",
    "addr:postcode":"60481",
    "addr:street":"Simotes Ln",
    "iso:country":"US",
    "sg:address":"26118 Simotes Ln",
    "sg:city":"Wilmington",
    "sg:classifiers":[
        {
            "category":"Shopping",
            "subcategory":"Computers & Home Electronics",
            "type":"Retail Goods"
        }
    ],
    "sg:phone":"+1   ",
    "sg:postcode":"60481",
    "sg:province":"IL",
    "sg:tags":[
        "consumer"
    ],
    "wof:name":"Radio Shack",
    "wof:placetype":"venue"
},
  "geometry": {"coordinates":[-88.24233099999999,41.381005],"type":"Point"}
}