{
  "type": "Feature",
  "properties": {
    "addr:full":"3263 Chicago Rd Paw Paw IL 61353",
    "addr:housenumber":"3263",
    "addr:postcode":"61353",
    "addr:street":"Chicago Rd",
    "iso:country":"US",
    "sg:address":"3263 Chicago Rd",
    "sg:city":"Paw Paw",
    "sg:classifiers":[
        {
            "category":"Real Estate",
            "subcategory":"Real Estate Agent",
            "type":"Services"
        }
    ],
    "sg:phone":"+1 815 627 8833",
    "sg:postcode":"61353",
    "sg:province":"IL",
    "wof:name":"Nicholson Real Estate",
    "wof:placetype":"venue"
},
  "geometry": {"coordinates":[-89.005454,41.693615],"type":"Point"}
}