{
  "type": "Feature",
  "properties": {
    "iso:country":"US",
    "sg:address":"353 Willard Ave",
    "sg:city":"Elgin",
    "sg:classifiers":[
        {
            "category":"Retail",
            "subcategory":"Auto Repair",
            "type":"Services"
        }
    ],
    "sg:phone":"+1 847 888 2050",
    "sg:postcode":"60120",
    "sg:province":"IL",
    "sg:tags":[
        "body",
        "automobile",
        "painting"
    ],
    "wof:name":"Brian's Auto Body",
    "wof:placetype":"venue"
},
  "geometry": {"coordinates":[-88.260306,42.028983],"type":"Point"}
}