{
  "type": "Feature",
  "properties": {
    "addr:full":"1721 Homer M Adams Pkwy Alton IL 62002",
    "addr:housenumber":"1721",
    "addr:postcode":"62002",
    "addr:street":"Homer M Adams Pkwy",
    "iso:country":"US",
    "sg:address":"1721 Homer M Adams Pkwy",
    "sg:city":"Alton",
    "sg:classifiers":[
        {
            "category":"Food & Beverages",
            "subcategory":"Groceries & Convenience Stores",
            "type":"Retail Goods"
        }
    ],
    "sg:phone":"+1 618 462 0056",
    "sg:postcode":"62002",
    "sg:province":"IL",
    "sg:tags":[
        "grocer"
    ],
    "wof:name":"Shop 'n Save",
    "wof:placetype":"venue"
},
  "geometry": {"coordinates":[-90.16135199999999,38.91751],"type":"Point"}
}