{
  "type": "Feature",
  "properties": {
    "addr:full":"1212 N Lake Shore Drive Chicago IL 60610",
    "addr:housenumber":"1212",
    "addr:postcode":"60610",
    "addr:street":"N Lake Shore Drive",
    "iso:country":"US",
    "sg:address":"1212 N Lake Shore Drive",
    "sg:city":"Chicago",
    "sg:classifiers":[
        {
            "category":"Retail",
            "subcategory":"Laundry & Dry Cleaning",
            "type":"Services"
        }
    ],
    "sg:phone":"+1 312 787 5398",
    "sg:postcode":"60610",
    "sg:province":"IL",
    "wof:name":"Nicole's Cleaners",
    "wof:placetype":"venue"
},
  "geometry": {"coordinates":[-87.62506,41.904333],"type":"Point"}
}