{
  "type": "Feature",
  "properties": {
    "addr:full":"2545 Dorothy Dr Aurora IL 60504",
    "addr:housenumber":"2545",
    "addr:postcode":"60504",
    "addr:street":"Dorothy Dr",
    "iso:country":"US",
    "sg:address":"2545 Dorothy Dr",
    "sg:city":"Aurora",
    "sg:classifiers":[
        {
            "category":"Bars & Pubs",
            "type":"Food & Drink"
        }
    ],
    "sg:phone":"+1   ",
    "sg:postcode":"60504",
    "sg:province":"IL",
    "sg:tags":[
        "drinking"
    ],
    "wof:name":"Lucky Penny Productions Inc",
    "wof:placetype":"venue"
},
  "geometry": {"coordinates":[-88.25375699999999,41.726516],"type":"Point"}
}