{
  "type": "Feature",
  "properties": {
    "iso:country":"US",
    "sg:address":"10860 Emerald Mound Grange Rd",
    "sg:city":"Lebanon",
    "sg:classifiers":[
        {
            "category":"Professional",
            "type":"Services"
        }
    ],
    "sg:phone":"+1 618 537 2967",
    "sg:postcode":"62254",
    "sg:province":"IL",
    "sg:tags":[
        "establishment"
    ],
    "wof:name":"Unisight Inc",
    "wof:placetype":"venue"
},
  "geometry": {"coordinates":[-89.779755,38.613445],"type":"Point"}
}