{
  "type": "Feature",
  "properties": {
    "addr:full":"920 N Hickory St Joliet IL 60435",
    "addr:housenumber":"920",
    "addr:postcode":"60435",
    "addr:street":"N Hickory St",
    "iso:country":"US",
    "sg:address":"920 N Hickory St",
    "sg:city":"Joliet",
    "sg:classifiers":[
        {
            "category":"Building & Trades",
            "subcategory":"Construction",
            "type":"Services"
        }
    ],
    "sg:phone":"+1 815 727 9650",
    "sg:postcode":"60435",
    "sg:province":"IL",
    "sg:tags":[
        "painter"
    ],
    "wof:name":"Smego's Complete Decorating",
    "wof:placetype":"venue"
},
  "geometry": {"coordinates":[-88.08677400000001,41.541388],"type":"Point"}
}