{
  "type": "Feature",
  "properties": {
    "addr:full":"900 E Market St Somonauk IL 60552",
    "addr:housenumber":"900",
    "addr:postcode":"60552",
    "addr:street":"E Market St",
    "iso:country":"US",
    "sg:address":"900 E Market St",
    "sg:city":"Somonauk",
    "sg:classifiers":[
        {
            "category":"Restaurant",
            "type":"Food & Drink"
        }
    ],
    "sg:menulink":"http://www.allmenus.com/il/somonauk/226429-caseys-general-store/menu/",
    "sg:phone":"+1 815 498 1938",
    "sg:postcode":"60552",
    "sg:province":"IL",
    "sg:tags":[
        "american",
        "pizza"
    ],
    "wof:name":"Casey's General Store",
    "wof:placetype":"venue"
},
  "geometry": {"coordinates":[-88.673399,41.634197],"type":"Point"}
}