{
  "type": "Feature",
  "properties": {
    "iso:country":"US",
    "sg:address":"1465 Keokuk St",
    "sg:city":"Hamilton",
    "sg:classifiers":[
        {
            "category":"Health Services",
            "subcategory":"Doctor",
            "type":"Services"
        }
    ],
    "sg:phone":"+1 217 847 3376",
    "sg:postcode":"62341",
    "sg:province":"IL",
    "sg:tags":[
        "physician",
        "surgeon"
    ],
    "wof:name":"Senen R Dalisay MD",
    "wof:placetype":"venue"
},
  "geometry": {"coordinates":[-91.33827599999999,40.396548],"type":"Point"}
}