{
  "type": "Feature",
  "properties": {
    "iso:country":"US",
    "sg:address":"424 Piper Ln",
    "sg:city":"Pittsfield",
    "sg:classifiers":[
        {
            "category":"Real Estate",
            "subcategory":"Real Estate Agent",
            "type":"Services"
        }
    ],
    "sg:phone":"+1 217 285 2126",
    "sg:postcode":"62363",
    "sg:province":"IL",
    "wof:name":"Appraisal Enterprises",
    "wof:placetype":"venue"
},
  "geometry": {"coordinates":[-90.800325,39.601806],"type":"Point"}
}