{
  "type": "Feature",
  "properties": {
    "addr:full":"2020 E 71st Street Chicago IL 60649",
    "addr:housenumber":"2020",
    "addr:postcode":"60649",
    "addr:street":"E 71St Street",
    "iso:country":"US",
    "sg:address":"2020 E 71st Street",
    "sg:city":"Chicago",
    "sg:classifiers":[
        {
            "category":"Restaurant",
            "type":"Food & Drink"
        }
    ],
    "sg:phone":"+1 773 288 0202",
    "sg:postcode":"60649",
    "sg:province":"IL",
    "wof:name":"Jeffrey Restaurant",
    "wof:placetype":"venue"
},
  "geometry": {"coordinates":[-87.575619,41.766127],"type":"Point"}
}