{
  "type": "Feature",
  "properties": {
    "iso:country":"US",
    "sg:address":"711 Tomaszewski St",
    "sg:city":"Lemont",
    "sg:classifiers":[
        {
            "category":"Professional",
            "subcategory":"Detective & Security Services",
            "type":"Services"
        }
    ],
    "sg:phone":"+1 630 453 1669",
    "sg:postcode":"60439",
    "sg:province":"IL",
    "sg:tags":[
        "information",
        "bureau"
    ],
    "wof:name":"English Olde Gardens",
    "wof:placetype":"venue"
},
  "geometry": {"coordinates":[-87.98867799999999,41.668123],"type":"Point"}
}