{
  "type": "Feature",
  "properties": {
    "addr:full":"719 S Batavia Ave Geneva IL 60134",
    "addr:housenumber":"719",
    "addr:postcode":"60134",
    "addr:street":"S Batavia Ave",
    "iso:country":"US",
    "sg:address":"719 S Batavia Ave",
    "sg:city":"Geneva",
    "sg:classifiers":[
        {
            "category":"Government",
            "subcategory":"Office",
            "type":"Public Place"
        }
    ],
    "sg:phone":"+1 630 232 3565",
    "sg:postcode":"60134",
    "sg:province":"IL",
    "sg:tags":[
        "county",
        "taxation"
    ],
    "wof:name":"KANE County Treasurer",
    "wof:placetype":"venue"
},
  "geometry": {"coordinates":[-88.30918699999999,41.8804],"type":"Point"}
}