{
  "type": "Feature",
  "properties": {
    "iso:country":"US",
    "sg:address":"Randolph/ Millenium Park Train Station 151 N Michigan Ave, Unit C-17",
    "sg:city":"Chicago",
    "sg:classifiers":[
        {
            "category":"Restaurant",
            "type":"Food & Drink"
        }
    ],
    "sg:phone":"+1 312 938 1111",
    "sg:postcode":"60601",
    "sg:province":"IL",
    "sg:tags":[
        "pizza"
    ],
    "wof:name":"Chi-Town Pizza Express",
    "wof:placetype":"venue"
},
  "geometry": {"coordinates":[-87.62426000000001,41.885154],"type":"Point"}
}