{
  "type": "Feature",
  "properties": {
    "iso:country":"US",
    "sg:address":"2642 Havens Dr",
    "sg:city":"West Chicago",
    "sg:classifiers":[
        {
            "category":"Sports & Exercise",
            "subcategory":"Gym",
            "type":"Entertainment"
        }
    ],
    "sg:phone":"+1 630 443 8232",
    "sg:postcode":"60185",
    "sg:province":"IL",
    "sg:tags":[
        "fitness",
        "physical",
        "facility"
    ],
    "wof:name":"1 2 1 Fitness",
    "wof:placetype":"venue"
},
  "geometry": {"coordinates":[-88.25959400000001,41.934813],"type":"Point"}
}