{
  "type": "Feature",
  "properties": {
    "iso:country":"US",
    "sg:address":"6743 S Cornell Ave",
    "sg:city":"Chicago",
    "sg:classifiers":[
        {
            "category":"Professional",
            "subcategory":"Computer Services",
            "type":"Services"
        }
    ],
    "sg:phone":"+1 312 924 5784",
    "sg:postcode":"60649",
    "sg:province":"IL",
    "sg:tags":[
        "information",
        "consulting",
        "technology"
    ],
    "wof:name":"Mytechiescom Corp",
    "wof:placetype":"venue"
},
  "geometry": {"coordinates":[-87.584982,41.77259],"type":"Point"}
}