{
  "type": "Feature",
  "properties": {
    "iso:country":"US",
    "sg:address":"638 Cemetery Rd",
    "sg:city":"Grayville",
    "sg:classifiers":[
        {
            "category":"Autos & Motor Vehicles",
            "subcategory":"Auto Supplies",
            "type":"Retail Goods"
        },
        {
            "category":"Retail",
            "subcategory":"Auto Repair",
            "type":"Services"
        }
    ],
    "sg:phone":"+1 618 375 9244",
    "sg:postcode":"62844",
    "sg:province":"IL",
    "sg:tags":[
        "body",
        "automobile",
        "truck",
        "painting",
        "repairing"
    ],
    "wof:name":"Tony's Auto Body Repair & Custom Painting",
    "wof:placetype":"venue"
},
  "geometry": {"coordinates":[-88.006418,38.26254],"type":"Point"}
}