{
  "type": "Feature",
  "properties": {
    "addr:full":"17652 Western Ave Homewood IL 60430",
    "addr:housenumber":"17652",
    "addr:postcode":"60430",
    "addr:street":"Western Ave",
    "iso:country":"US",
    "sg:address":"17652 Western Ave",
    "sg:city":"Homewood",
    "sg:classifiers":[
        {
            "category":"Travel",
            "subcategory":"Resort",
            "type":"Entertainment"
        }
    ],
    "sg:phone":"+1 708 921 2301",
    "sg:postcode":"60430",
    "sg:province":"IL",
    "wof:name":"First Resort",
    "wof:placetype":"venue"
},
  "geometry": {"coordinates":[-87.674978,41.568973],"type":"Point"}
}