{
  "type": "Feature",
  "properties": {
    "iso:country":"US",
    "sg:address":"2034 Caton Rd",
    "sg:city":"Ottawa",
    "sg:classifiers":[
        {
            "category":"Building & Trades",
            "subcategory":"Construction",
            "type":"Services"
        }
    ],
    "sg:phone":"+1 815 434 4566",
    "sg:postcode":"61350",
    "sg:province":"IL",
    "sg:tags":[
        "home",
        "improvement"
    ],
    "wof:name":"Smith Electric Co",
    "wof:placetype":"venue"
},
  "geometry": {"coordinates":[-88.84768,41.363842],"type":"Point"}
}