{
  "type": "Feature",
  "properties": {
    "addr:full":"5747 Carpenter St Downers Grove IL 60516",
    "addr:housenumber":"5747",
    "addr:postcode":"60516",
    "addr:street":"Carpenter St",
    "iso:country":"US",
    "sg:address":"5747 Carpenter St",
    "sg:city":"Downers Grove",
    "sg:classifiers":[
        {
            "category":"Professional",
            "subcategory":"Research",
            "type":"Services"
        }
    ],
    "sg:phone":"+1 630 434 8665",
    "sg:postcode":"60516",
    "sg:province":"IL",
    "sg:tags":[
        "commercial",
        "physical"
    ],
    "wof:name":"Advanced Research Tools Inc",
    "wof:placetype":"venue"
},
  "geometry": {"coordinates":[-88.01117000000001,41.781105],"type":"Point"}
}