{
  "type": "Feature",
  "properties": {
    "addr:full":"731 Silver St Alton IL 62002",
    "addr:housenumber":"731",
    "addr:postcode":"62002",
    "addr:street":"Silver St",
    "iso:country":"US",
    "sg:address":"731 Silver St",
    "sg:city":"Alton",
    "sg:classifiers":[
        {
            "category":"Organizations",
            "subcategory":"Professional Association",
            "type":"Services"
        }
    ],
    "sg:phone":"+1 618 465 1621",
    "sg:postcode":"62002",
    "sg:province":"IL",
    "wof:name":"NAACP",
    "wof:placetype":"venue"
},
  "geometry": {"coordinates":[-90.166578,38.894551],"type":"Point"}
}