{
  "type": "Feature",
  "properties": {
    "iso:country":"US",
    "sg:address":"703 Rand Rd",
    "sg:city":"Lakemoor",
    "sg:classifiers":[
        {
            "category":"Health Services",
            "subcategory":"Chiropractor",
            "type":"Services"
        }
    ],
    "sg:phone":"+1 815 363 1947",
    "sg:postcode":"60051",
    "sg:province":"IL",
    "wof:name":"Stowe Chiropractic Ctr",
    "wof:placetype":"venue"
},
  "geometry": {"coordinates":[-88.21003399999999,42.333307],"type":"Point"}
}