{
  "type": "Feature",
  "properties": {
    "iso:country":"US",
    "sg:address":"403 S Central Ave",
    "sg:city":"Casey",
    "sg:classifiers":[
        {
            "category":"Freight",
            "type":"Transportation"
        }
    ],
    "sg:phone":"+1 217 932 2151",
    "sg:postcode":"62420",
    "sg:province":"IL",
    "sg:tags":[
        "grain",
        "elevator"
    ],
    "wof:name":"Huisinga Grain Inc",
    "wof:placetype":"venue"
},
  "geometry": {"coordinates":[-87.992802,39.295675],"type":"Point"}
}