{
  "type": "Feature",
  "properties": {
    "iso:country":"US",
    "sg:address":"1514 W Devon Avenue",
    "sg:city":"Chicago",
    "sg:classifiers":[
        {
            "category":"Health Services",
            "subcategory":"Dentist",
            "type":"Services"
        }
    ],
    "sg:phone":"+1 773 761 2521",
    "sg:postcode":"60660",
    "sg:province":"IL",
    "wof:name":"Nima Sanai DDS",
    "wof:placetype":"venue"
},
  "geometry": {"coordinates":[-87.668218,41.998114],"type":"Point"}
}