{
  "type": "Feature",
  "properties": {
    "addr:full":"3456 Washington St Park City IL 60085",
    "addr:housenumber":"3456",
    "addr:postcode":"60085",
    "addr:street":"Washington St Park",
    "iso:country":"US",
    "sg:address":"3456 Washington St",
    "sg:city":"Park City",
    "sg:classifiers":[
        {
            "category":"Building & Trades",
            "subcategory":"Construction",
            "type":"Services"
        }
    ],
    "sg:phone":"+1 847 662 7272",
    "sg:postcode":"60085",
    "sg:province":"IL",
    "sg:tags":[
        "excavation",
        "excavating",
        "contractor"
    ],
    "wof:name":"Ehlers & Juhrend Enterprises",
    "wof:placetype":"venue"
},
  "geometry": {"coordinates":[-87.88650199999999,42.359669],"type":"Point"}
}