{
  "type": "Feature",
  "properties": {
    "addr:full":"6827 Stanley Ave Ste 2 Berwyn IL 60402",
    "addr:housenumber":"6827",
    "addr:postcode":"60402",
    "addr:street":"Stanley Ave Ste 2",
    "iso:country":"US",
    "sg:address":"6827 Stanley Ave Ste 2",
    "sg:city":"Berwyn",
    "sg:classifiers":[
        {
            "category":"Health Services",
            "subcategory":"Doctor",
            "type":"Services"
        }
    ],
    "sg:phone":"+1 708 749 4617",
    "sg:postcode":"60402",
    "sg:province":"IL",
    "sg:tags":[
        "physician",
        "surgeons",
        "nephrology",
        "surgeon",
        "kidneys"
    ],
    "wof:name":"Midwest Nephrology Assoc Of Il",
    "wof:placetype":"venue"
},
  "geometry": {"coordinates":[-87.794099,41.833365],"type":"Point"}
}