{
  "type": "Feature",
  "properties": {
    "iso:country":"US",
    "sg:address":"1723 N Lotus Ave Fl 1",
    "sg:city":"Chicago",
    "sg:classifiers":[
        {
            "category":"Personal",
            "type":"Services"
        }
    ],
    "sg:phone":"+1 773 637 5045",
    "sg:postcode":"60639",
    "sg:province":"IL",
    "sg:tags":[
        "dressmaker"
    ],
    "wof:name":"Beverly R Taylor",
    "wof:placetype":"venue"
},
  "geometry": {"coordinates":[-87.76182,41.911661],"type":"Point"}
}