{
  "type": "Feature",
  "properties": {
    "addr:full":"1338 Park Ave River Forest IL 60305",
    "addr:housenumber":"1338",
    "addr:postcode":"60305",
    "addr:street":"Park Ave",
    "iso:country":"US",
    "sg:address":"1338 Park Ave",
    "sg:city":"River Forest",
    "sg:classifiers":[
        {
            "category":"Insurance",
            "subcategory":"Insurance Agent",
            "type":"Services"
        }
    ],
    "sg:phone":"+1 708 771 3553",
    "sg:postcode":"60305",
    "sg:province":"IL",
    "sg:tags":[
        "agency"
    ],
    "wof:name":"Brooks & Associates",
    "wof:placetype":"venue"
},
  "geometry": {"coordinates":[-87.820318,41.904845],"type":"Point"}
}