{
  "type": "Feature",
  "properties": {
    "iso:country":"US",
    "sg:address":"316 Franklin St",
    "sg:city":"Geneva",
    "sg:classifiers":[
        {
            "category":"Professional",
            "subcategory":"Management & Consulting",
            "type":"Services"
        }
    ],
    "sg:phone":"+1 630 262 2000",
    "sg:postcode":"60134",
    "sg:province":"IL",
    "sg:tags":[
        "consultant",
        "resource",
        "human"
    ],
    "wof:name":"Wellington Group Inc",
    "wof:placetype":"venue"
},
  "geometry": {"coordinates":[-88.309822,41.884879],"type":"Point"}
}