{
  "type": "Feature",
  "properties": {
    "addr:full":"4820 22nd Ave Moline IL 61265",
    "addr:housenumber":"4820",
    "addr:postcode":"61265",
    "addr:street":"22Nd Ave",
    "iso:country":"US",
    "sg:address":"4820 22nd Ave",
    "sg:city":"Moline",
    "sg:classifiers":[
        {
            "category":"Health Services",
            "subcategory":"Chiropractor",
            "type":"Services"
        }
    ],
    "sg:phone":"+1 309 762 2273",
    "sg:postcode":"61265",
    "sg:province":"IL",
    "sg:tags":[
        "chiropractic"
    ],
    "wof:name":"Hurst Chiropractic",
    "wof:placetype":"venue"
},
  "geometry": {"coordinates":[-90.468391,41.490585],"type":"Point"}
}