{
  "type": "Feature",
  "properties": {
    "addr:full":"5333 N Milwaukee Ave Chicago IL 60630",
    "addr:housenumber":"5333",
    "addr:postcode":"60630",
    "addr:street":"N Milwaukee Ave",
    "iso:country":"US",
    "sg:address":"5333 N Milwaukee Ave",
    "sg:city":"Chicago",
    "sg:classifiers":[
        {
            "category":"Bars & Pubs",
            "type":"Food & Drink"
        }
    ],
    "sg:phone":"+1 773 792 2072",
    "sg:postcode":"60630",
    "sg:province":"IL",
    "wof:name":"Ham Tree Inn",
    "wof:placetype":"venue"
},
  "geometry": {"coordinates":[-87.769302,41.9772],"type":"Point"}
}