{
  "type": "Feature",
  "properties": {
    "iso:country":"US",
    "sg:address":"1575 Commerce Dr",
    "sg:city":"Bourbonnais",
    "sg:classifiers":[
        {
            "category":"Retail",
            "subcategory":"Auto Repair",
            "type":"Services"
        }
    ],
    "sg:phone":"+1 815 937 1266",
    "sg:postcode":"60914",
    "sg:province":"IL",
    "sg:tags":[
        "towing",
        "vehicle"
    ],
    "wof:name":"Larry Menz Towing Service",
    "wof:placetype":"venue"
},
  "geometry": {"coordinates":[-87.859508,41.174611],"type":"Point"}
}