{
  "type": "Feature",
  "properties": {
    "iso:country":"US",
    "sg:address":"104 Idlebrook Dr",
    "sg:city":"Collinsville",
    "sg:classifiers":[
        {
            "category":"Personal",
            "subcategory":"Beauty Salon",
            "type":"Services"
        }
    ],
    "sg:phone":"+1 618 344 4332",
    "sg:postcode":"62234",
    "sg:province":"IL",
    "wof:name":"Andreas Hair Salon",
    "wof:placetype":"venue"
},
  "geometry": {"coordinates":[-89.985904,38.660046],"type":"Point"}
}