{
  "type": "Feature",
  "properties": {
    "addr:full":"1715 13th St Waukegan IL 60085",
    "addr:housenumber":"1715",
    "addr:postcode":"60085",
    "addr:street":"13Th St",
    "iso:country":"US",
    "sg:address":"1715 13th St",
    "sg:city":"Waukegan",
    "sg:classifiers":[
        {
            "category":"Social Services",
            "subcategory":"Child Care",
            "type":"Services"
        }
    ],
    "sg:phone":"+1 847 360 1153",
    "sg:postcode":"60085",
    "sg:province":"IL",
    "sg:tags":[
        "day"
    ],
    "wof:name":"Tiny Tots Daycare",
    "wof:placetype":"venue"
},
  "geometry": {"coordinates":[-87.85644499999999,42.335965],"type":"Point"}
}