{
  "type": "Feature",
  "properties": {
    "iso:country":"US",
    "sg:address":"420 W Kerry Ct",
    "sg:city":"Palatine",
    "sg:classifiers":[
        {
            "category":"Manufacturing",
            "subcategory":"Tools & Machinery",
            "type":"Manufacturing & Wholesale Goods"
        }
    ],
    "sg:phone":"+1 847 310 0894",
    "sg:postcode":"60067",
    "sg:province":"IL",
    "sg:tags":[
        "manufacture",
        "dental",
        "material",
        "sale"
    ],
    "wof:name":"Apex Dental Materials Inc",
    "wof:placetype":"venue"
},
  "geometry": {"coordinates":[-88.05373,42.095391],"type":"Point"}
}