{
  "type": "Feature",
  "properties": {
    "iso:country":"US",
    "sg:address":"228 E Holden St",
    "sg:city":"Virden",
    "sg:classifiers":[
        {
            "category":"Farming",
            "subcategory":"Farm",
            "type":"Manufacturing & Wholesale Goods"
        }
    ],
    "sg:phone":"+1 217 965 5114",
    "sg:postcode":"62690",
    "sg:province":"IL",
    "wof:name":"Jackson Farms",
    "wof:placetype":"venue"
},
  "geometry": {"coordinates":[-89.766676,39.497814],"type":"Point"}
}