{
  "type": "Feature",
  "properties": {
    "iso:country":"US",
    "sg:address":"450 E Waterside Dr D",
    "sg:city":"Chicago",
    "sg:classifiers":[
        {
            "category":"Professional",
            "subcategory":"Research",
            "type":"Services"
        }
    ],
    "sg:phone":"+1 312 861 4006",
    "sg:postcode":"60601",
    "sg:province":"IL",
    "sg:tags":[
        "information",
        "medical"
    ],
    "wof:name":"Supernova Clinical Research, Inc.",
    "wof:placetype":"venue"
},
  "geometry": {"coordinates":[-87.616157,41.886909],"type":"Point"}
}