{
  "type": "Feature",
  "properties": {
    "addr:full":"8310 S Kedzie Ave Chicago IL 60652",
    "addr:housenumber":"8310",
    "addr:postcode":"60652",
    "addr:street":"S Kedzie Ave",
    "iso:country":"US",
    "sg:address":"8310 S Kedzie Ave",
    "sg:city":"Chicago",
    "sg:classifiers":[
        {
            "category":"Shopping",
            "subcategory":"Clothing, Apparel, & Fashions",
            "type":"Retail Goods"
        }
    ],
    "sg:phone":"+1 773 776 8843",
    "sg:postcode":"60652",
    "sg:province":"IL",
    "wof:name":"Gina's Fashions",
    "wof:placetype":"venue"
},
  "geometry": {"coordinates":[-87.70226700000001,41.742322],"type":"Point"}
}