{
  "type": "Feature",
  "properties": {
    "addr:full":"6033 N Kedzie Ave Chicago IL 60659",
    "addr:housenumber":"6033",
    "addr:postcode":"60659",
    "addr:street":"N Kedzie Ave",
    "iso:country":"US",
    "sg:address":"6033 N Kedzie Ave",
    "sg:city":"Chicago",
    "sg:classifiers":[
        {
            "category":"Professional",
            "subcategory":"Accounting & Tax Preparation",
            "type":"Services"
        }
    ],
    "sg:phone":"+1 773 465 0033",
    "sg:postcode":"60659",
    "sg:province":"IL",
    "wof:name":"Arnold B Chang & Co",
    "wof:placetype":"venue"
},
  "geometry": {"coordinates":[-87.70912,41.992464],"type":"Point"}
}