{
  "type": "Feature",
  "properties": {
    "iso:country":"US",
    "sg:address":"410 E Clay St",
    "sg:city":"Joliet",
    "sg:classifiers":[
        {
            "category":"Organizations",
            "subcategory":"Religious Organization",
            "type":"Services"
        }
    ],
    "sg:phone":"+1 815 722 4308",
    "sg:postcode":"60432",
    "sg:province":"IL",
    "sg:tags":[
        "church"
    ],
    "sg:website":"www.redeemcogic.com",
    "wof:name":"Redeem Church Of God In Christ",
    "wof:placetype":"venue"
},
  "geometry": {"coordinates":[-88.070429,41.532525],"type":"Point"}
}