{
  "type": "Feature",
  "properties": {
    "iso:country":"US",
    "sg:address":"1401 N Bell School Rd",
    "sg:city":"Rockford",
    "sg:classifiers":[
        {
            "category":"Education",
            "subcategory":"School",
            "type":"Public Place"
        }
    ],
    "sg:phone":"+1 815 399 3465",
    "sg:postcode":"61107",
    "sg:province":"IL",
    "sg:tags":[
        "organization",
        "religious"
    ],
    "sg:website":"www.rockfordchristian.org",
    "wof:name":"Rockford Christian Schools",
    "wof:placetype":"venue"
},
  "geometry": {"coordinates":[-88.970178,42.28327],"type":"Point"}
}