{
  "type": "Feature",
  "properties": {
    "iso:country":"US",
    "sg:address":"200 N Milwaukee Ave",
    "sg:city":"Vernon Hills",
    "sg:classifiers":[
        {
            "category":"Shopping",
            "subcategory":"Computers & Home Electronics",
            "type":"Retail Goods"
        }
    ],
    "sg:phone":"+1 847 680 6249",
    "sg:postcode":"60061",
    "sg:province":"IL",
    "sg:tags":[
        "software"
    ],
    "wof:name":"Computer Discount Warehouse",
    "wof:placetype":"venue"
},
  "geometry": {"coordinates":[-87.941785,42.228342],"type":"Point"}
}