{
  "type": "Feature",
  "properties": {
    "iso:country":"US",
    "sg:address":"107 W State St",
    "sg:city":"Geneva",
    "sg:classifiers":[
        {
            "category":"Travel",
            "subcategory":"Travel Agent",
            "type":"Entertainment"
        }
    ],
    "sg:phone":"+1 630 232 8430",
    "sg:postcode":"60134",
    "sg:province":"IL",
    "sg:tags":[
        "agency",
        "bureau"
    ],
    "sg:website":"www.travstor.com",
    "wof:name":"Travel Store Inc",
    "wof:placetype":"venue"
},
  "geometry": {"coordinates":[-88.305045,41.887618],"type":"Point"}
}