{
  "type": "Feature",
  "properties": {
    "iso:country":"US",
    "sg:address":"1111 N Plaza Dr",
    "sg:city":"Schaumburg",
    "sg:classifiers":[
        {
            "category":"Insurance",
            "subcategory":"Insurance Agent",
            "type":"Services"
        },
        {
            "category":"Insurance",
            "subcategory":"Hazard Insurance",
            "type":"Services"
        },
        {
            "category":"Insurance",
            "subcategory":"Title Insurance",
            "type":"Services"
        },
        {
            "category":"Insurance",
            "subcategory":"Life Insurance",
            "type":"Services"
        }
    ],
    "sg:phone":"+1 847 605 8200",
    "sg:postcode":"60173",
    "sg:province":"IL",
    "sg:tags":[
        "business",
        "auto",
        "commercial",
        "homeowner",
        "motorcycle",
        "renter"
    ],
    "wof:name":"Allstate Insurance Company - William Maday",
    "wof:placetype":"venue"
},
  "geometry": {"coordinates":[-88.043216,42.049259],"type":"Point"}
}