{
  "type": "Feature",
  "properties": {
    "iso:country":"US",
    "sg:address":"1325 Howard St",
    "sg:city":"Evanston",
    "sg:classifiers":[
        {
            "category":"Health Services",
            "subcategory":"Doctor",
            "type":"Services"
        }
    ],
    "sg:phone":"+1 847 869 4300",
    "sg:postcode":"60202",
    "sg:province":"IL",
    "sg:tags":[
        "medical"
    ],
    "wof:name":"Benuck Irwin MD",
    "wof:placetype":"venue"
},
  "geometry": {"coordinates":[-87.690483,42.019599],"type":"Point"}
}