{
  "type": "Feature",
  "properties": {
    "addr:full":"540 Kingsway Dr Aurora IL 60506",
    "addr:housenumber":"540",
    "addr:postcode":"60506",
    "addr:street":"Kingsway Dr",
    "iso:country":"US",
    "sg:address":"540 Kingsway Dr",
    "sg:city":"Aurora",
    "sg:classifiers":[
        {
            "category":"Wholesale",
            "subcategory":"Medical Equipment & Supplies",
            "type":"Manufacturing & Wholesale Goods"
        }
    ],
    "sg:phone":"+1 630 906 6680",
    "sg:postcode":"60506",
    "sg:province":"IL",
    "sg:tags":[
        "handicapped"
    ],
    "wof:name":"Association For Individual Dev",
    "wof:placetype":"venue"
},
  "geometry": {"coordinates":[-88.35974899999999,41.748578],"type":"Point"}
}