{
  "type": "Feature",
  "properties": {
    "iso:country":"US",
    "sg:address":"11815 S Verona Rd",
    "sg:city":"Dwight",
    "sg:phone":"+1 815 584 1954",
    "sg:postcode":"60444",
    "sg:province":"IL",
    "sg:tags":[
        "farm",
        "corn",
        "soybean"
    ],
    "wof:name":"Keith Pokarney",
    "wof:placetype":"venue"
},
  "geometry": {"coordinates":[-88.490309,41.111279],"type":"Point"}
}