{
  "type": "Feature",
  "properties": {
    "addr:full":"222 S. Riverside Plaza  Suite 2750 Chicago IL 60606",
    "addr:housenumber":"222",
    "addr:postcode":"60606",
    "addr:street":"S. Riverside Plaza Suite 2750",
    "iso:country":"US",
    "sg:address":"222 S. Riverside Plaza  Suite 2750",
    "sg:city":"Chicago",
    "sg:classifiers":[
        {
            "category":"Professional",
            "subcategory":"Research",
            "type":"Services"
        }
    ],
    "sg:postcode":"60606",
    "sg:province":"IL",
    "sg:tags":[
        "energy",
        "clean-energy",
        "coal",
        "natural-gas",
        "bluegas",
        "cleantech",
        "hydromethanation",
        "funded",
        "andrew-perlman",
        "massachusetts",
        "daniel-goldman",
        "dow-chemical",
        "dow"
    ],
    "sg:website":"http://www.greatpointenergy.com",
    "wof:name":"GreatPoint Energy",
    "wof:placetype":"venue"
},
  "geometry": {"coordinates":[-87.63840500000001,41.878328],"type":"Point"}
}