{
  "type": "Feature",
  "properties": {
    "iso:country":"US",
    "sg:address":"607 S Sangamon Ave",
    "sg:city":"Gibson City",
    "sg:classifiers":[
        {
            "category":"Communications",
            "subcategory":"Radio Station",
            "type":"Services"
        }
    ],
    "sg:phone":"+1 217 784 8661",
    "sg:postcode":"60936",
    "sg:province":"IL",
    "sg:tags":[
        "company",
        "broadcasting"
    ],
    "wof:name":"WGCY",
    "wof:placetype":"venue"
},
  "geometry": {"coordinates":[-88.37539700000001,40.458818],"type":"Point"}
}