{
  "type": "Feature",
  "properties": {
    "addr:full":"400 W Grand Ave Carterville IL 62918",
    "addr:housenumber":"400",
    "addr:postcode":"62918",
    "addr:street":"W Grand Ave",
    "iso:country":"US",
    "sg:address":"400 W Grand Ave",
    "sg:city":"Carterville",
    "sg:classifiers":[
        {
            "category":"Health Services",
            "subcategory":"Clinic",
            "type":"Services"
        }
    ],
    "sg:phone":"+1 618 985 9140",
    "sg:postcode":"62918",
    "sg:province":"IL",
    "sg:tags":[
        "osteopathic"
    ],
    "wof:name":"Karen Strack Do",
    "wof:placetype":"venue"
},
  "geometry": {"coordinates":[-89.080101,37.760151],"type":"Point"}
}