{
  "type": "Feature",
  "properties": {
    "addr:full":"8047 Kildare Ave Skokie IL 60076",
    "addr:housenumber":"8047",
    "addr:postcode":"60076",
    "addr:street":"Kildare Ave",
    "iso:country":"US",
    "sg:address":"8047 Kildare Ave",
    "sg:city":"Skokie",
    "sg:classifiers":[
        {
            "category":"Wholesale",
            "subcategory":"Groceries",
            "type":"Manufacturing & Wholesale Goods"
        }
    ],
    "sg:phone":"+1 847 673 0092",
    "sg:postcode":"60076",
    "sg:province":"IL",
    "sg:tags":[
        "food",
        "natural"
    ],
    "wof:name":"Organic Matters Inc",
    "wof:placetype":"venue"
},
  "geometry": {"coordinates":[-87.73539,42.027109],"type":"Point"}
}