{
  "type": "Feature",
  "properties": {
    "iso:country":"US",
    "sg:address":"406 E Johnson Ave",
    "sg:city":"Altamont",
    "sg:classifiers":[
        {
            "category":"Restaurant",
            "type":"Food & Drink"
        }
    ],
    "sg:phone":"+1 618 483 9309",
    "sg:postcode":"62411",
    "sg:province":"IL",
    "wof:name":"Chesty's Inc",
    "wof:placetype":"venue"
},
  "geometry": {"coordinates":[-88.74238200000001,39.05778],"type":"Point"}
}