{
  "type": "Feature",
  "properties": {
    "addr:full":"4501 N Cumberland Ave Norridge IL 60706",
    "addr:housenumber":"4501",
    "addr:postcode":"60706",
    "addr:street":"N Cumberland Ave",
    "iso:country":"US",
    "sg:address":"4501 N Cumberland Ave",
    "sg:city":"Norridge",
    "sg:classifiers":[
        {
            "category":"Cinema",
            "subcategory":"Movie Rental",
            "type":"Entertainment"
        }
    ],
    "sg:phone":"+1 708 453 4144",
    "sg:postcode":"60706",
    "sg:province":"IL",
    "sg:tags":[
        "game",
        "video"
    ],
    "wof:name":"Video Champ",
    "wof:placetype":"venue"
},
  "geometry": {"coordinates":[-87.836502,41.961498],"type":"Point"}
}