{
  "type": "Feature",
  "properties": {
    "iso:country":"US",
    "sg:address":"1383 Kysor Dr",
    "sg:city":"Byron",
    "sg:classifiers":[
        {
            "category":"Retail",
            "subcategory":"Auto Repair",
            "type":"Services"
        }
    ],
    "sg:phone":"+1 815 234 7675",
    "sg:postcode":"61010",
    "sg:province":"IL",
    "sg:tags":[
        "repairing",
        "automobile"
    ],
    "wof:name":"Nielsen Automotive",
    "wof:placetype":"venue"
},
  "geometry": {"coordinates":[-89.23788999999999,42.128322],"type":"Point"}
}