{
  "type": "Feature",
  "properties": {
    "iso:country":"US",
    "sg:address":"1038 N Grove St",
    "sg:city":"Virden",
    "sg:classifiers":[
        {
            "category":"Retail",
            "subcategory":"Auto Repair",
            "type":"Services"
        }
    ],
    "sg:phone":"+1 217 965 3975",
    "sg:postcode":"62690",
    "sg:province":"IL",
    "sg:tags":[
        "body",
        "equipment",
        "manufacturer",
        "automobile",
        "supply"
    ],
    "wof:name":"Midwest Auto Body",
    "wof:placetype":"venue"
},
  "geometry": {"coordinates":[-89.770413,39.513227],"type":"Point"}
}