{
  "type": "Feature",
  "properties": {
    "iso:country":"US",
    "sg:address":"570 12th St",
    "sg:city":"Carlyle",
    "sg:classifiers":[
        {
            "category":"Travel",
            "subcategory":"Hotels & Motels",
            "type":"Entertainment"
        }
    ],
    "sg:phone":"+1 618 594 8100",
    "sg:postcode":"62231",
    "sg:province":"IL",
    "wof:name":"Motel Carlyle",
    "wof:placetype":"venue"
},
  "geometry": {"coordinates":[-89.372757,38.610456],"type":"Point"}
}