{
  "type": "Feature",
  "properties": {
    "addr:full":"2007 Bridge St  Yorkville IL 60560",
    "addr:housenumber":"2007",
    "addr:postcode":"60560",
    "addr:street":"Bridge St",
    "iso:country":"US",
    "sg:address":"2007 Bridge St ",
    "sg:city":"Yorkville",
    "sg:classifiers":[
        {
            "category":"Restaurant",
            "type":"Food & Drink"
        }
    ],
    "sg:menulink":"http://www.allmenus.com/il/bristol/212666-mcdonalds/menu/",
    "sg:postcode":"60560",
    "sg:province":"IL",
    "sg:tags":[
        "burger",
        "american"
    ],
    "wof:name":"McDonald's",
    "wof:placetype":"venue"
},
  "geometry": {"coordinates":[-88.44183700000001,41.668065],"type":"Point"}
}