{
  "type": "Feature",
  "properties": {
    "iso:country":"US",
    "sg:address":"10540 Vonder Haar Ln",
    "sg:city":"Breese",
    "sg:classifiers":[
        {
            "category":"Transit Center",
            "subcategory":"Freight",
            "type":"Transportation"
        },
        {
            "category":"Freight",
            "type":"Transportation"
        }
    ],
    "sg:phone":"+1 618 526 0587",
    "sg:postcode":"62230",
    "sg:province":"IL",
    "sg:tags":[
        "local",
        "trucking-motor",
        "trucking"
    ],
    "wof:name":"Shanfeld And Silverman Truckin",
    "wof:placetype":"venue"
},
  "geometry": {"coordinates":[-89.505343,38.614773],"type":"Point"}
}