{
  "type": "Feature",
  "properties": {
    "addr:full":"6340 N Rockwell Street Chicago IL 60659",
    "addr:housenumber":"6340",
    "addr:postcode":"60659",
    "addr:street":"N Rockwell Street",
    "iso:country":"US",
    "sg:address":"6340 N Rockwell Street",
    "sg:city":"Chicago",
    "sg:classifiers":[
        {
            "category":"Personal",
            "type":"Services"
        }
    ],
    "sg:phone":"+1 773 274 4717",
    "sg:postcode":"60659",
    "sg:province":"IL",
    "sg:tags":[
        "sewing",
        "alteration"
    ],
    "wof:name":"Chander Subhash",
    "wof:placetype":"venue"
},
  "geometry": {"coordinates":[-87.694548,41.997233],"type":"Point"}
}