{
  "type": "Feature",
  "properties": {
    "iso:country":"US",
    "sg:address":"236 W 5th St",
    "sg:city":"Minonk",
    "sg:classifiers":[
        {
            "category":"Place Of Worship",
            "subcategory":"Church",
            "type":"Public Place"
        },
        {
            "category":"Place Of Worship",
            "type":"Public Place"
        }
    ],
    "sg:phone":"+1 309 432 2992",
    "sg:postcode":"61760",
    "sg:province":"IL",
    "sg:tags":[
        "christ",
        "denomination",
        "testament",
        "churches-church",
        "churches-interdenominational",
        "christ-new",
        "churches-various"
    ],
    "wof:name":"St Pauls United Church Of Christ",
    "wof:placetype":"venue"
},
  "geometry": {"coordinates":[-89.03483900000001,40.901728],"type":"Point"}
}