{
  "type": "Feature",
  "properties": {
    "addr:full":"45 N St Chicago IL 60619",
    "addr:housenumber":"45",
    "addr:postcode":"60619",
    "addr:street":"N St",
    "iso:country":"US",
    "sg:address":"45 N St",
    "sg:city":"Chicago",
    "sg:classifiers":[
        {
            "category":"Building & Trades",
            "subcategory":"Locksmith",
            "type":"Services"
        }
    ],
    "sg:phone":"+1 312 962 5554",
    "sg:postcode":"60619",
    "sg:province":"IL",
    "sg:tags":[
        "key"
    ],
    "wof:name":"Locksmith AAA",
    "wof:placetype":"venue"
},
  "geometry": {"coordinates":[-87.62791799999999,41.911086],"type":"Point"}
}