{
  "type": "Feature",
  "properties": {
    "addr:full":"1808 Janke Dr Northbrook IL 60062",
    "addr:housenumber":"1808",
    "addr:postcode":"60062",
    "addr:street":"Janke Dr",
    "iso:country":"US",
    "sg:address":"1808 Janke Dr",
    "sg:city":"Northbrook",
    "sg:classifiers":[
        {
            "category":"Real Estate",
            "subcategory":"Real Estate Services",
            "type":"Services"
        }
    ],
    "sg:phone":"+1 224 723 5540",
    "sg:postcode":"60062",
    "sg:province":"IL",
    "sg:tags":[
        "building",
        "maintenance"
    ],
    "wof:name":"Cardinal Building Maintenance",
    "wof:placetype":"venue"
},
  "geometry": {"coordinates":[-87.824692,42.113869],"type":"Point"}
}