{
  "type": "Feature",
  "properties": {
    "iso:country":"US",
    "sg:address":"8193 W Main St",
    "sg:city":"Belleville",
    "sg:classifiers":[
        {
            "category":"Food & Beverages",
            "subcategory":"Groceries & Convenience Stores",
            "type":"Retail Goods"
        }
    ],
    "sg:phone":"+1 618 397 1600",
    "sg:postcode":"62223",
    "sg:province":"IL",
    "sg:tags":[
        "grocer"
    ],
    "wof:name":"Main Street Mkt",
    "wof:placetype":"venue"
},
  "geometry": {"coordinates":[-90.050201,38.566399],"type":"Point"}
}