{
  "type": "Feature",
  "properties": {
    "addr:full":"106 N 2nd St West Dundee IL 60118",
    "addr:housenumber":"106",
    "addr:postcode":"60118",
    "addr:street":"N 2Nd St",
    "iso:country":"US",
    "sg:address":"106 N 2nd St",
    "sg:city":"West Dundee",
    "sg:classifiers":[
        {
            "category":"Personal",
            "subcategory":"Beauty Salon",
            "type":"Services"
        }
    ],
    "sg:phone":"+1 847 426 3656",
    "sg:postcode":"60118",
    "sg:province":"IL",
    "sg:tags":[
        "hair"
    ],
    "sg:website":"www.spa-bleu.com",
    "wof:name":"Spa Bleu",
    "wof:placetype":"venue"
},
  "geometry": {"coordinates":[-88.27861,42.098354],"type":"Point"}
}