{
  "type": "Feature",
  "properties": {
    "iso:country":"US",
    "sg:address":"211 Kenmore Ave",
    "sg:city":"Deerfield",
    "sg:classifiers":[
        {
            "category":"Manufacturing",
            "subcategory":"Apparel",
            "type":"Manufacturing & Wholesale Goods"
        }
    ],
    "sg:phone":"+1 847 940 1010",
    "sg:postcode":"60015",
    "sg:province":"IL",
    "sg:tags":[
        "flag",
        "banner"
    ],
    "wof:name":"Sales Promotion Svc",
    "wof:placetype":"venue"
},
  "geometry": {"coordinates":[-87.86477600000001,42.158176],"type":"Point"}
}