{
  "type": "Feature",
  "properties": {
    "addr:full":"14515 E 2600th St Annawan IL 61234",
    "addr:housenumber":"14515",
    "addr:postcode":"61234",
    "addr:street":"E 2600Th St",
    "iso:country":"US",
    "sg:address":"14515 E 2600th St",
    "sg:city":"Annawan",
    "sg:phone":"+1 309 935 6960",
    "sg:postcode":"61234",
    "sg:province":"IL",
    "sg:tags":[
        "farm",
        "corn",
        "soybean"
    ],
    "wof:name":"Witte Farms",
    "wof:placetype":"venue"
},
  "geometry": {"coordinates":[-89.93395700000001,41.364321],"type":"Point"}
}