{
  "type": "Feature",
  "properties": {
    "iso:country":"US",
    "sg:address":"1501 State St",
    "sg:city":"East Saint Louis",
    "sg:classifiers":[
        {
            "category":"Manufacturing",
            "subcategory":"Printing",
            "type":"Manufacturing & Wholesale Goods"
        }
    ],
    "sg:phone":"+1 618 271 0468",
    "sg:postcode":"62205",
    "sg:province":"IL",
    "sg:tags":[
        "print",
        "newspaper",
        "medium"
    ],
    "wof:name":"East St Louis Monitor",
    "wof:placetype":"venue"
},
  "geometry": {"coordinates":[-90.141502,38.621498],"type":"Point"}
}