{
  "type": "Feature",
  "properties": {
    "addr:full":"3930 N Pulaski Rd Chicago IL 60641",
    "addr:housenumber":"3930",
    "addr:postcode":"60641",
    "addr:street":"N Pulaski Rd",
    "iso:country":"US",
    "sg:address":"3930 N Pulaski Rd",
    "sg:city":"Chicago",
    "sg:classifiers":[
        {
            "category":"Building & Trades",
            "subcategory":"Construction",
            "type":"Services"
        }
    ],
    "sg:phone":"+1 773 777 2982",
    "sg:postcode":"60641",
    "sg:province":"IL",
    "sg:tags":[
        "designer"
    ],
    "wof:name":"Designs By Larissa Inc",
    "wof:placetype":"venue"
},
  "geometry": {"coordinates":[-87.727662,41.952698],"type":"Point"}
}