{
  "type": "Feature",
  "properties": {
    "iso:country":"US",
    "sg:address":"591 Waikiki Dr",
    "sg:city":"Des Plaines",
    "sg:classifiers":[
        {
            "category":"Home & Garden",
            "subcategory":"Building Materials",
            "type":"Retail Goods"
        }
    ],
    "sg:phone":"+1 847 298 2100",
    "sg:postcode":"60016",
    "sg:province":"IL",
    "sg:tags":[
        "glass",
        "window",
        "plate"
    ],
    "wof:name":"Direct Service Auto Glass",
    "wof:placetype":"venue"
},
  "geometry": {"coordinates":[-87.906184,42.059212],"type":"Point"}
}