{
  "type": "Feature",
  "properties": {
    "addr:full":"1358 N Campbell Ave Chicago IL 60622",
    "addr:housenumber":"1358",
    "addr:postcode":"60622",
    "addr:street":"N Campbell Ave",
    "iso:country":"US",
    "sg:address":"1358 N Campbell Ave",
    "sg:city":"Chicago",
    "sg:classifiers":[
        {
            "category":"Communications",
            "subcategory":"Film & Video Production",
            "type":"Services"
        }
    ],
    "sg:phone":"+1 847 564 3066",
    "sg:postcode":"60622",
    "sg:province":"IL",
    "sg:tags":[
        "services-commercial"
    ],
    "wof:name":"Larry Wayne Productions",
    "wof:placetype":"venue"
},
  "geometry": {"coordinates":[-87.68955200000001,41.90589],"type":"Point"}
}