{
  "type": "Feature",
  "properties": {
    "iso:country":"US",
    "sg:address":"1200 Spaulding Rd",
    "sg:city":"Elgin",
    "sg:classifiers":[
        {
            "category":"Utilities",
            "subcategory":"Fuel Oil & Lpg",
            "type":"Services"
        }
    ],
    "sg:phone":"+1 847 876 0111",
    "sg:postcode":"60120",
    "sg:province":"IL",
    "sg:tags":[
        "firewood"
    ],
    "wof:name":"Sure Green Landscape Supply",
    "wof:placetype":"venue"
},
  "geometry": {"coordinates":[-88.24712599999999,42.003105],"type":"Point"}
}