{
  "type": "Feature",
  "properties": {
    "iso:country":"US",
    "sg:address":"3831 W 95th St",
    "sg:city":"Evergreen Park",
    "sg:classifiers":[
        {
            "category":"Autos & Motor Vehicles",
            "subcategory":"Fuel & Gas Station",
            "type":"Retail Goods"
        }
    ],
    "sg:phone":"+1   ",
    "sg:postcode":"60805",
    "sg:province":"IL",
    "sg:tags":[
        "station",
        "gasoline"
    ],
    "wof:name":"Jai Laxmi Mata LLC",
    "wof:placetype":"venue"
},
  "geometry": {"coordinates":[-87.718889,41.720425],"type":"Point"}
}