{
  "type": "Feature",
  "properties": {
    "iso:country":"US",
    "sg:address":"108 S Century Blvd",
    "sg:city":"Rantoul",
    "sg:classifiers":[
        {
            "category":"Retail",
            "subcategory":"Repair Shop",
            "type":"Services"
        }
    ],
    "sg:phone":"+1 217 892 8384",
    "sg:postcode":"61866",
    "sg:province":"IL",
    "sg:tags":[
        "ope",
        "local",
        "merchandise",
        "trucking"
    ],
    "wof:name":"Security Systems of Rantoul",
    "wof:placetype":"venue"
},
  "geometry": {"coordinates":[-88.15589900000001,40.310374],"type":"Point"}
}