{
  "type": "Feature",
  "properties": {
    "iso:country":"US",
    "sg:address":"3042 N Broadway St",
    "sg:city":"Chicago",
    "sg:classifiers":[
        {
            "category":"Restaurant",
            "type":"Food & Drink"
        }
    ],
    "sg:phone":"+1   ",
    "sg:postcode":"60657",
    "sg:province":"IL",
    "sg:tags":[
        "eating"
    ],
    "wof:name":"Wheel-A-Round Restaurant",
    "wof:placetype":"venue"
},
  "geometry": {"coordinates":[-87.644404,41.937891],"type":"Point"}
}