{
  "type": "Feature",
  "properties": {
    "addr:full":"3042 N Broadway St Chicago IL 60657",
    "addr:housenumber":"3042",
    "addr:postcode":"60657",
    "addr:street":"N Broadway St",
    "iso:country":"US",
    "sg:address":"3042 N Broadway St",
    "sg:city":"Chicago",
    "sg:classifiers":[
        {
            "category":"Restaurant",
            "type":"Food & Drink"
        }
    ],
    "sg:phone":"+1   ",
    "sg:postcode":"60657",
    "sg:province":"IL",
    "sg:tags":[
        "eating"
    ],
    "wof:name":"Wheel-A-Round Restaurant",
    "wof:placetype":"venue"
},
  "geometry": {"coordinates":[-87.64440399999999,41.937891],"type":"Point"}
}