{
  "type": "Feature",
  "properties": {
    "iso:country":"US",
    "sg:address":"4713 N Knox Ave",
    "sg:city":"Chicago",
    "sg:classifiers":[
        {
            "category":"Building & Trades",
            "subcategory":"Construction",
            "type":"Services"
        }
    ],
    "sg:phone":"+1 773 685 2418",
    "sg:postcode":"60630",
    "sg:province":"IL",
    "sg:tags":[
        "contractor"
    ],
    "wof:name":"First Quality Builders Inc",
    "wof:placetype":"venue"
},
  "geometry": {"coordinates":[-87.743757,41.9665],"type":"Point"}
}