{
  "type": "Feature",
  "properties": {
    "addr:full":"2510 Franklin St Carlyle IL 62231",
    "addr:housenumber":"2510",
    "addr:postcode":"62231",
    "addr:street":"Franklin St",
    "iso:country":"US",
    "sg:address":"2510 Franklin St",
    "sg:city":"Carlyle",
    "sg:classifiers":[
        {
            "category":"Manufacturing",
            "subcategory":"Rubber & Plastics",
            "type":"Manufacturing & Wholesale Goods"
        }
    ],
    "sg:phone":"+1 618 594 3692",
    "sg:postcode":"62231",
    "sg:province":"IL",
    "sg:website":"www.pulsarplastics.com",
    "wof:name":"Pulsar Plastics",
    "wof:placetype":"venue"
},
  "geometry": {"coordinates":[-89.38999099999999,38.60996],"type":"Point"}
}