{
  "type": "Feature",
  "properties": {
    "iso:country":"US",
    "sg:address":"2901 Peoria St",
    "sg:city":"Peru",
    "sg:classifiers":[
        {
            "category":"Wholesale",
            "subcategory":"Office Equipment",
            "type":"Manufacturing & Wholesale Goods"
        }
    ],
    "sg:phone":"+1 815 224 1116",
    "sg:postcode":"61354",
    "sg:province":"IL",
    "sg:tags":[
        "machine",
        "duplicating",
        "copying"
    ],
    "wof:name":"Copy All Svc",
    "wof:placetype":"venue"
},
  "geometry": {"coordinates":[-89.130156,41.350124],"type":"Point"}
}