{
  "type": "Feature",
  "properties": {
    "iso:country":"US",
    "sg:address":"941 Warwick Ln",
    "sg:city":"Lake Zurich",
    "sg:classifiers":[
        {
            "category":"Professional",
            "subcategory":"Management & Consulting",
            "type":"Services"
        }
    ],
    "sg:phone":"+1 847 540 7401",
    "sg:postcode":"60047",
    "sg:province":"IL",
    "sg:tags":[
        "employee",
        "consultant",
        "benefit"
    ],
    "wof:name":"Fidelity Benefits Advisors Inc",
    "wof:placetype":"venue"
},
  "geometry": {"coordinates":[-88.063303,42.182179],"type":"Point"}
}