{
  "type": "Feature",
  "properties": {
    "addr:full":"2407 N Central Ave Rockford IL 61101",
    "addr:housenumber":"2407",
    "addr:postcode":"61101",
    "addr:street":"N Central Ave",
    "iso:country":"US",
    "sg:address":"2407 N Central Ave",
    "sg:city":"Rockford",
    "sg:classifiers":[
        {
            "category":"Sports & Exercise",
            "subcategory":"Bowling",
            "type":"Entertainment"
        }
    ],
    "sg:phone":"+1 815 963 7210",
    "sg:postcode":"61101",
    "sg:province":"IL",
    "wof:name":"Westmor Lanes",
    "wof:placetype":"venue"
},
  "geometry": {"coordinates":[-89.116084,42.302323],"type":"Point"}
}