{
  "type": "Feature",
  "properties": {
    "addr:full":"4108 Lindley St Downers Grove IL 60515",
    "addr:housenumber":"4108",
    "addr:postcode":"60515",
    "addr:street":"Lindley St",
    "iso:country":"US",
    "sg:address":"4108 Lindley St",
    "sg:city":"Downers Grove",
    "sg:classifiers":[
        {
            "category":"Professional",
            "subcategory":"Management & Consulting",
            "type":"Services"
        }
    ],
    "sg:phone":"+1 630 969 4382",
    "sg:postcode":"60515",
    "sg:province":"IL",
    "wof:name":"Tmt Inc",
    "wof:placetype":"venue"
},
  "geometry": {"coordinates":[-88.008447,41.811141],"type":"Point"}
}