{
  "type": "Feature",
  "properties": {
    "addr:full":"6636 N Loron Ave Chicago IL 60646",
    "addr:housenumber":"6636",
    "addr:postcode":"60646",
    "addr:street":"N Loron Ave",
    "iso:country":"US",
    "sg:address":"6636 N Loron Ave",
    "sg:city":"Chicago",
    "sg:classifiers":[
        {
            "category":"Communications",
            "subcategory":"Newspaper",
            "type":"Services"
        }
    ],
    "sg:phone":"+1 773 792 1830",
    "sg:postcode":"60646",
    "sg:province":"IL",
    "sg:tags":[
        "print",
        "medium"
    ],
    "wof:name":"Contract Magazines",
    "wof:placetype":"venue"
},
  "geometry": {"coordinates":[-87.774101,42.001701],"type":"Point"}
}