{
  "type": "Feature",
  "properties": {
    "iso:country":"US",
    "sg:address":"319 E Monroe St",
    "sg:city":"Springfield",
    "sg:classifiers":[
        {
            "category":"Personal",
            "subcategory":"Massage",
            "type":"Services"
        },
        {
            "category":"Health Services",
            "subcategory":"Clinic",
            "type":"Services"
        },
        {
            "category":"Health Services",
            "subcategory":"Health Practitioner",
            "type":"Services"
        }
    ],
    "sg:phone":"+1 217 788 8299",
    "sg:postcode":"62701",
    "sg:province":"IL",
    "sg:tags":[
        "therapist",
        "therapy",
        "physical"
    ],
    "wof:name":"Moxie Massage",
    "wof:placetype":"venue"
},
  "geometry": {"coordinates":[-89.651613,39.799503],"type":"Point"}
}