{
  "type": "Feature",
  "properties": {
    "iso:country":"US",
    "sg:address":"2654 N Lincoln Ave",
    "sg:city":"Chicago",
    "sg:classifiers":[
        {
            "category":"Health Services",
            "subcategory":"Chiropractor",
            "type":"Services"
        }
    ],
    "sg:phone":"+1 773 696 5523",
    "sg:postcode":"60614",
    "sg:province":"IL",
    "sg:website":"www.4sportinjurycenters.com",
    "wof:name":"Dr. Chris Bocci",
    "wof:placetype":"venue"
},
  "geometry": {"coordinates":[-87.655534,41.930125],"type":"Point"}
}