{
  "type": "Feature",
  "properties": {
    "iso:country":"US",
    "sg:address":"1792 Kelley Dr",
    "sg:city":"Schaumburg",
    "sg:classifiers":[
        {
            "category":"Real Estate",
            "subcategory":"Real Estate Operator",
            "type":"Services"
        }
    ],
    "sg:phone":"+1 847 742 6722",
    "sg:postcode":"60192",
    "sg:province":"IL",
    "sg:tags":[
        "building",
        "nonresidential"
    ],
    "wof:name":"T&D Properties LLC",
    "wof:placetype":"venue"
},
  "geometry": {"coordinates":[-88.209873,42.059067],"type":"Point"}
}