{
  "type": "Feature",
  "properties": {
    "addr:full":"9150 S Harlem Ave Bridgeview IL 60455",
    "addr:housenumber":"9150",
    "addr:postcode":"60455",
    "addr:street":"S Harlem Ave",
    "iso:country":"US",
    "sg:address":"9150 S Harlem Ave",
    "sg:city":"Bridgeview",
    "sg:classifiers":[
        {
            "category":"Retail",
            "subcategory":"Car Wash",
            "type":"Services"
        }
    ],
    "sg:phone":"+1 708 599 2200",
    "sg:postcode":"60455",
    "sg:province":"IL",
    "sg:tags":[
        "polishing",
        "washing"
    ],
    "sg:website":"www.bluemarlincarwash.com",
    "wof:name":"Blue Marlin Car",
    "wof:placetype":"venue"
},
  "geometry": {"coordinates":[-87.798897,41.7253],"type":"Point"}
}