{
  "type": "Feature",
  "properties": {
    "addr:full":"5249 N Broadway St Chicago IL 60640",
    "addr:housenumber":"5249",
    "addr:postcode":"60640",
    "addr:street":"N Broadway St",
    "iso:country":"US",
    "sg:address":"5249 N Broadway St",
    "sg:city":"Chicago",
    "sg:classifiers":[
        {
            "category":"Retail",
            "subcategory":"Self-service Laundry",
            "type":"Services"
        }
    ],
    "sg:phone":"+1 773 506 1350",
    "sg:postcode":"60640",
    "sg:province":"IL",
    "sg:tags":[
        "dry",
        "coin",
        "cleaning"
    ],
    "wof:name":"Perfect Laundry",
    "wof:placetype":"venue"
},
  "geometry": {"coordinates":[-87.66010300000001,41.977699],"type":"Point"}
}