{
  "type": "Feature",
  "properties": {
    "addr:full":"319 S Main St Bourbonnais IL 60914",
    "addr:housenumber":"319",
    "addr:postcode":"60914",
    "addr:street":"S Main St",
    "iso:country":"US",
    "sg:address":"319 S Main St",
    "sg:city":"Bourbonnais",
    "sg:classifiers":[
        {
            "category":"Manufacturing",
            "subcategory":"Printing",
            "type":"Manufacturing & Wholesale Goods"
        }
    ],
    "sg:phone":"+1 815 928 8910",
    "sg:postcode":"60914",
    "sg:province":"IL",
    "sg:tags":[
        "newspaper"
    ],
    "wof:name":"Kankakee Conservation",
    "wof:placetype":"venue"
},
  "geometry": {"coordinates":[-87.877225,41.153303],"type":"Point"}
}