{
  "type": "Feature",
  "properties": {
    "iso:country":"US",
    "sg:address":"5844 W Higgins Ave",
    "sg:city":"Chicago",
    "sg:classifiers":[
        {
            "category":"Building & Trades",
            "subcategory":"Plumbing",
            "type":"Services"
        },
        {
            "category":"Home & Garden",
            "subcategory":"Hardware",
            "type":"Retail Goods"
        }
    ],
    "sg:phone":"+1 773 283 3414",
    "sg:postcode":"60630",
    "sg:province":"IL",
    "sg:tags":[
        "filtration",
        "supply",
        "work",
        "purification",
        "water",
        "equipment"
    ],
    "wof:name":"Jms Group Inc",
    "wof:placetype":"venue"
},
  "geometry": {"coordinates":[-87.77485900000001,41.972281],"type":"Point"}
}