{
  "type": "Feature",
  "properties": {
    "iso:country":"US",
    "sg:address":"4448 N German Church Rd",
    "sg:city":"Byron",
    "sg:classifiers":[
        {
            "category":"Government",
            "subcategory":"Office",
            "type":"Public Place"
        }
    ],
    "sg:phone":"+1 815 234 5451",
    "sg:postcode":"61010",
    "sg:province":"IL",
    "sg:tags":[
        "federal",
        "govt"
    ],
    "wof:name":"US Nuclear Regulatory Comm",
    "wof:placetype":"venue"
},
  "geometry": {"coordinates":[-89.277494,42.08457],"type":"Point"}
}