{
  "type": "Feature",
  "properties": {
    "iso:country":"US",
    "sg:address":"1819 E 880th St",
    "sg:city":"Quincy",
    "sg:phone":"+1 217 964 2561",
    "sg:postcode":"62305",
    "sg:province":"IL",
    "sg:tags":[
        "farm",
        "corn",
        "soybean"
    ],
    "wof:name":"Shriver Farm",
    "wof:placetype":"venue"
},
  "geometry": {"coordinates":[-91.341752,40.028907],"type":"Point"}
}