{
  "type": "Feature",
  "properties": {
    "addr:full":"315 W State St Jacksonville IL 62650",
    "addr:housenumber":"315",
    "addr:postcode":"62650",
    "addr:street":"W State St",
    "iso:country":"US",
    "sg:address":"315 W State St",
    "sg:city":"Jacksonville",
    "sg:classifiers":[
        {
            "category":"Bars & Pubs",
            "type":"Food & Drink"
        }
    ],
    "sg:phone":"+1 217 245 8021",
    "sg:postcode":"62650",
    "sg:province":"IL",
    "sg:tags":[
        "drinking"
    ],
    "wof:name":"Bill's West State Tavern",
    "wof:placetype":"venue"
},
  "geometry": {"coordinates":[-90.23195699999999,39.734223],"type":"Point"}
}