{
  "type": "Feature",
  "properties": {
    "iso:country":"US",
    "sg:address":"3534 S Kostner Ave",
    "sg:city":"Chicago",
    "sg:classifiers":[
        {
            "category":"Retail",
            "subcategory":"Storage",
            "type":"Services"
        }
    ],
    "sg:phone":"+1 773 843 3200",
    "sg:postcode":"60632",
    "sg:province":"IL",
    "sg:tags":[
        "warehouse",
        "household",
        "commercial",
        "cold"
    ],
    "wof:name":"Chicago Cold Storage Corporation",
    "wof:placetype":"venue"
},
  "geometry": {"coordinates":[-87.73538499999999,41.830636],"type":"Point"}
}