{
  "type": "Feature",
  "properties": {
    "iso:country":"US",
    "sg:address":"3344 N Ashland Ave",
    "sg:city":"Chicago",
    "sg:classifiers":[
        {
            "category":"Insurance",
            "subcategory":"Insurance Agent",
            "type":"Services"
        }
    ],
    "sg:phone":"+1 773 871 8720",
    "sg:postcode":"60657",
    "sg:province":"IL",
    "wof:name":"American Family Insurance",
    "wof:placetype":"venue"
},
  "geometry": {"coordinates":[-87.668834,41.943174],"type":"Point"}
}