{
  "type": "Feature",
  "properties": {
    "addr:full":"515 E Roosevelt Rd Glen Ellyn IL 60137",
    "addr:housenumber":"515",
    "addr:postcode":"60137",
    "addr:street":"E Roosevelt Rd",
    "iso:country":"US",
    "sg:address":"515 E Roosevelt Rd",
    "sg:city":"Glen Ellyn",
    "sg:classifiers":[
        {
            "category":"Banks & Credit Unions",
            "subcategory":"Bank",
            "type":"Services"
        }
    ],
    "sg:phone":"+1 630 858 5000",
    "sg:postcode":"60137",
    "sg:province":"IL",
    "sg:website":"www.bankone.com",
    "wof:name":"Bank One",
    "wof:placetype":"venue"
},
  "geometry": {"coordinates":[-88.06600899999999,41.859262],"type":"Point"}
}