{
  "type": "Feature",
  "properties": {
    "iso:country":"US",
    "sg:address":"810 W 10th St",
    "sg:city":"Metropolis",
    "sg:classifiers":[
        {
            "category":"Bars & Pubs",
            "type":"Food & Drink"
        },
        {
            "category":"Restaurant",
            "type":"Food & Drink"
        },
        {
            "category":"Bars & Pubs",
            "subcategory":"Lounge",
            "type":"Food & Drink"
        }
    ],
    "sg:phone":"+1 618 524 5106",
    "sg:postcode":"62960",
    "sg:province":"IL",
    "sg:tags":[
        "grill",
        "cocktail"
    ],
    "wof:name":"Diamond Lil's",
    "wof:placetype":"venue"
},
  "geometry": {"coordinates":[-88.733077,37.158353],"type":"Point"}
}