{
  "type": "Feature",
  "properties": {
    "addr:full":"630 N Rush Street Chicago IL 60611",
    "addr:housenumber":"630",
    "addr:postcode":"60611",
    "addr:street":"N Rush Street",
    "iso:country":"US",
    "sg:address":"630 N Rush Street",
    "sg:city":"Chicago",
    "sg:classifiers":[
        {
            "category":"Travel",
            "subcategory":"Hotels & Motels",
            "type":"Entertainment"
        }
    ],
    "sg:phone":"+1 312 981 6600",
    "sg:postcode":"60611",
    "sg:province":"IL",
    "sg:website":"www.fourpointschicago.com",
    "wof:name":"Four Points by Sheraton",
    "wof:placetype":"venue"
},
  "geometry": {"coordinates":[-87.625696,41.893271],"type":"Point"}
}