{
  "type": "Feature",
  "properties": {
    "iso:country":"US",
    "sg:address":"1841 Hicks Rd",
    "sg:city":"Rolling Meadows",
    "sg:classifiers":[
        {
            "category":"Professional",
            "subcategory":"Accounting & Tax Preparation",
            "type":"Services"
        }
    ],
    "sg:phone":"+1 847 358 3909",
    "sg:postcode":"60008",
    "sg:province":"IL",
    "wof:name":"Accounting & Sftwr Solutions",
    "wof:placetype":"venue"
},
  "geometry": {"coordinates":[-88.034085,42.091613],"type":"Point"}
}