{
  "type": "Feature",
  "properties": {
    "addr:full":"601 S Main St Princeton IL 61356",
    "addr:housenumber":"601",
    "addr:postcode":"61356",
    "addr:street":"S Main St",
    "iso:country":"US",
    "sg:address":"601 S Main St",
    "sg:city":"Princeton",
    "sg:classifiers":[
        {
            "category":"Banks & Credit Unions",
            "subcategory":"Bank",
            "type":"Services"
        }
    ],
    "sg:phone":"+1 815 879 2622",
    "sg:postcode":"61356",
    "sg:province":"IL",
    "sg:tags":[
        "national",
        "commercial"
    ],
    "sg:website":"www.ubcd.com",
    "wof:name":"Union Bank",
    "wof:placetype":"venue"
},
  "geometry": {"coordinates":[-89.465058,41.369454],"type":"Point"}
}