{
  "type": "Feature",
  "properties": {
    "iso:country":"US",
    "sg:address":"535 Fairway Dr Ste 107",
    "sg:city":"Naperville",
    "sg:classifiers":[
        {
            "category":"Health Services",
            "subcategory":"Clinic",
            "type":"Services"
        }
    ],
    "sg:phone":"+1 630 548 5936",
    "sg:postcode":"60563",
    "sg:province":"IL",
    "sg:tags":[
        "welfare"
    ],
    "wof:name":"Lincoln Medical Associates, S.C.",
    "wof:placetype":"venue"
},
  "geometry": {"coordinates":[-88.210571,41.780689],"type":"Point"}
}