{
  "type": "Feature",
  "properties": {
    "addr:full":"12610 Rockland Rd Lake Bluff IL 60044",
    "addr:housenumber":"12610",
    "addr:postcode":"60044",
    "addr:street":"Rockland Rd",
    "iso:country":"US",
    "sg:address":"12610 Rockland Rd",
    "sg:city":"Lake Bluff",
    "sg:classifiers":[
        {
            "category":"Restaurant",
            "type":"Food & Drink"
        }
    ],
    "sg:phone":"+1 847 295 7797",
    "sg:postcode":"60044",
    "sg:province":"IL",
    "wof:name":"Scooters",
    "wof:placetype":"venue"
},
  "geometry": {"coordinates":[-87.880685,42.279817],"type":"Point"}
}