{
  "type": "Feature",
  "properties": {
    "iso:country":"US",
    "sg:address":"15524 S 70th Ct",
    "sg:city":"Orland Park",
    "sg:phone":"+1 708 429 5151",
    "sg:postcode":"60462",
    "sg:province":"IL",
    "sg:tags":[
        "equipment",
        "commercial",
        "establishment"
    ],
    "wof:name":"Robert Gill & Co Inc",
    "wof:placetype":"venue"
},
  "geometry": {"coordinates":[-87.791023,41.606457],"type":"Point"}
}