{
  "type": "Feature",
  "properties": {
    "addr:full":"4 Tyler Creek Plz Elgin IL 60123",
    "addr:housenumber":"4",
    "addr:postcode":"60123",
    "addr:street":"Tyler Creek Plz",
    "iso:country":"US",
    "sg:address":"4 Tyler Creek Plz",
    "sg:city":"Elgin",
    "sg:classifiers":[
        {
            "category":"Food & Beverages",
            "subcategory":"Groceries & Convenience Stores",
            "type":"Retail Goods"
        }
    ],
    "sg:phone":"+1 847 468 7411",
    "sg:postcode":"60123",
    "sg:province":"IL",
    "wof:name":"De La Rosa Market",
    "wof:placetype":"venue"
},
  "geometry": {"coordinates":[-88.314246,42.058432],"type":"Point"}
}