{
  "type": "Feature",
  "properties": {
    "addr:full":"4117 W Madison St Chicago IL 60624",
    "addr:housenumber":"4117",
    "addr:postcode":"60624",
    "addr:street":"W Madison St",
    "iso:country":"US",
    "sg:address":"4117 W Madison St",
    "sg:city":"Chicago",
    "sg:classifiers":[
        {
            "category":"Professional",
            "subcategory":"Computer Services",
            "type":"Services"
        }
    ],
    "sg:phone":"+1 773 265 6666",
    "sg:postcode":"60624",
    "sg:province":"IL",
    "sg:tags":[
        "repair"
    ],
    "sg:website":"cccc.us",
    "wof:name":"Chicago Computer Club",
    "wof:placetype":"venue"
},
  "geometry": {"coordinates":[-87.72847,41.88051],"type":"Point"}
}