{
  "type": "Feature",
  "properties": {
    "addr:full":"1173 Home Ave Oak Park IL 60304",
    "addr:housenumber":"1173",
    "addr:postcode":"60304",
    "addr:street":"Home Ave",
    "iso:country":"US",
    "sg:address":"1173 Home Ave",
    "sg:city":"Oak Park",
    "sg:classifiers":[
        {
            "category":"Personal",
            "type":"Services"
        }
    ],
    "sg:phone":"+1 708 383 4325",
    "sg:postcode":"60304",
    "sg:province":"IL",
    "sg:tags":[
        "therapist",
        "massage"
    ],
    "wof:name":"Alternative Insights",
    "wof:placetype":"venue"
},
  "geometry": {"coordinates":[-87.799093,41.866369],"type":"Point"}
}