{
  "type": "Feature",
  "properties": {
    "addr:full":"561 Welch Cir Lake Barrington IL 60010",
    "addr:housenumber":"561",
    "addr:postcode":"60010",
    "addr:street":"Welch Cir",
    "iso:country":"US",
    "sg:address":"561 Welch Cir",
    "sg:city":"Lake Barrington",
    "sg:classifiers":[
        {
            "category":"Banks & Credit Unions",
            "subcategory":"Investment Brokerage",
            "type":"Services"
        }
    ],
    "sg:phone":"+1 847 382 7903",
    "sg:postcode":"60010",
    "sg:province":"IL",
    "sg:tags":[
        "commodity"
    ],
    "wof:name":"Barrington Commodity Brokers",
    "wof:placetype":"venue"
},
  "geometry": {"coordinates":[-88.191847,42.209711],"type":"Point"}
}