{
  "type": "Feature",
  "properties": {
    "addr:full":"626 Library Pl Evanston IL 60201",
    "addr:housenumber":"626",
    "addr:postcode":"60201",
    "addr:street":"Library Pl",
    "iso:country":"US",
    "sg:address":"626 Library Pl",
    "sg:city":"Evanston",
    "sg:classifiers":[
        {
            "category":"Education",
            "subcategory":"College",
            "type":"Public Place"
        }
    ],
    "sg:phone":"+1 847 467 3041",
    "sg:postcode":"60201",
    "sg:province":"IL",
    "wof:name":"Inter University Seminar",
    "wof:placetype":"venue"
},
  "geometry": {"coordinates":[-87.677438,42.054942],"type":"Point"}
}