{
  "type": "Feature",
  "properties": {
    "iso:country":"US",
    "sg:address":"213 N Pearl St",
    "sg:city":"Salem",
    "sg:classifiers":[
        {
            "category":"Building & Trades",
            "subcategory":"Construction",
            "type":"Services"
        }
    ],
    "sg:phone":"+1 618 548 1140",
    "sg:postcode":"62881",
    "sg:province":"IL",
    "sg:tags":[
        "painter"
    ],
    "wof:name":"Jerold Henson Painting",
    "wof:placetype":"venue"
},
  "geometry": {"coordinates":[-88.948626,38.628537],"type":"Point"}
}