{
  "type": "Feature",
  "properties": {
    "addr:full":"330 W Maple St New Lenox IL 60451",
    "addr:housenumber":"330",
    "addr:postcode":"60451",
    "addr:street":"W Maple St",
    "iso:country":"US",
    "sg:address":"330 W Maple St",
    "sg:city":"New Lenox",
    "sg:classifiers":[
        {
            "category":"Utilities",
            "subcategory":"Mobile Phone",
            "type":"Services"
        }
    ],
    "sg:phone":"+1 815 463 0099",
    "sg:postcode":"60451",
    "sg:province":"IL",
    "sg:tags":[
        "telephone",
        "cellular"
    ],
    "wof:name":"K C Wireless",
    "wof:placetype":"venue"
},
  "geometry": {"coordinates":[-87.97329499999999,41.515555],"type":"Point"}
}