{
  "type": "Feature",
  "properties": {
    "addr:full":"49 Sherwood Ter Lake Bluff IL 60044",
    "addr:housenumber":"49",
    "addr:postcode":"60044",
    "addr:street":"Sherwood Ter",
    "iso:country":"US",
    "sg:address":"49 Sherwood Ter",
    "sg:city":"Lake Bluff",
    "sg:classifiers":[
        {
            "category":"Building & Trades",
            "subcategory":"Electrical",
            "type":"Services"
        }
    ],
    "sg:phone":"+1 847 295 2185",
    "sg:postcode":"60044",
    "sg:province":"IL",
    "sg:tags":[
        "electrical",
        "electric",
        "contractor"
    ],
    "wof:name":"Northern Illinois Electric",
    "wof:placetype":"venue"
},
  "geometry": {"coordinates":[-87.867451,42.271334],"type":"Point"}
}