{
  "type": "Feature",
  "properties": {
    "iso:country":"US",
    "sg:address":"10511 S Prairie Ave",
    "sg:city":"Chicago",
    "sg:classifiers":[
        {
            "category":"Building & Trades",
            "subcategory":"Construction",
            "type":"Services"
        }
    ],
    "sg:phone":"+1 773 995 5335",
    "sg:postcode":"60628",
    "sg:province":"IL",
    "sg:tags":[
        "contractor"
    ],
    "wof:name":"Gw Contracting & Property Preservation",
    "wof:placetype":"venue"
},
  "geometry": {"coordinates":[-87.61712300000001,41.703408],"type":"Point"}
}