{
  "type": "Feature",
  "properties": {
    "addr:full":"1034 W Devon Ave Elk Grove Vlg IL 60007",
    "addr:housenumber":"1034",
    "addr:postcode":"60007",
    "addr:street":"W Devon Ave",
    "iso:country":"US",
    "sg:address":"1034 W Devon Ave",
    "sg:city":"Elk Grove Vlg",
    "sg:classifiers":[
        {
            "category":"Building & Trades",
            "subcategory":"Electrical",
            "type":"Services"
        }
    ],
    "sg:phone":"+1 847 524 1976",
    "sg:postcode":"60007",
    "sg:province":"IL",
    "sg:tags":[
        "electric",
        "contractor"
    ],
    "wof:name":"Action Electric Inc",
    "wof:placetype":"venue"
},
  "geometry": {"coordinates":[-88.028659,41.99258],"type":"Point"}
}