{
  "type": "Feature",
  "properties": {
    "addr:full":"4717 Oregon Trl Mc Henry IL 60050",
    "addr:housenumber":"4717",
    "addr:postcode":"60050",
    "addr:street":"Oregon Trl Mc Henry",
    "iso:country":"US",
    "sg:address":"4717 Oregon Trl",
    "sg:city":"Mc Henry",
    "sg:classifiers":[
        {
            "category":"Retail",
            "subcategory":"Repair Shop",
            "type":"Services"
        }
    ],
    "sg:phone":"+1 815 363 9855",
    "sg:postcode":"60050",
    "sg:province":"IL",
    "sg:tags":[
        "welding"
    ],
    "wof:name":"J W Welding",
    "wof:placetype":"venue"
},
  "geometry": {"coordinates":[-88.29036499999999,42.327601],"type":"Point"}
}