{
  "type": "Feature",
  "properties": {
    "addr:full":"105 S Broad St Lanark IL 61046",
    "addr:housenumber":"105",
    "addr:postcode":"61046",
    "addr:street":"S Broad St",
    "iso:country":"US",
    "sg:address":"105 S Broad St",
    "sg:city":"Lanark",
    "sg:classifiers":[
        {
            "category":"Insurance",
            "subcategory":"Insurance Agent",
            "type":"Services"
        },
        {
            "category":"Insurance",
            "subcategory":"Hazard Insurance",
            "type":"Services"
        },
        {
            "category":"Insurance",
            "subcategory":"Title Insurance",
            "type":"Services"
        },
        {
            "category":"Insurance",
            "subcategory":"Life Insurance",
            "type":"Services"
        }
    ],
    "sg:phone":"+1 815 493 2544",
    "sg:postcode":"61046",
    "sg:province":"IL",
    "sg:tags":[
        "auto",
        "commercial",
        "business",
        "homeowner"
    ],
    "sg:website":"http://www.countryfinancial.com/rhett.coatney",
    "wof:name":"COUNTRY Financial Rhett Coatney",
    "wof:placetype":"venue"
},
  "geometry": {"coordinates":[-89.832932,42.102097],"type":"Point"}
}