{
  "type": "Feature",
  "properties": {
    "iso:country":"US",
    "sg:address":"320 W Roosevelt St",
    "sg:city":"Dekalb",
    "sg:classifiers":[
        {
            "category":"Building & Trades",
            "subcategory":"Landscaping Services",
            "type":"Services"
        }
    ],
    "sg:phone":"+1 847 322 9557",
    "sg:postcode":"60115",
    "sg:province":"IL",
    "sg:tags":[
        "lawn",
        "maintenance"
    ],
    "wof:name":"Mule Barn Mowers",
    "wof:placetype":"venue"
},
  "geometry": {"coordinates":[-88.75955,41.926555],"type":"Point"}
}