{
  "type": "Feature",
  "properties": {
    "addr:full":"324 Rocbaar Dr Romeoville IL 60446",
    "addr:housenumber":"324",
    "addr:postcode":"60446",
    "addr:street":"Rocbaar Dr",
    "iso:country":"US",
    "sg:address":"324 Rocbaar Dr",
    "sg:city":"Romeoville",
    "sg:classifiers":[
        {
            "category":"Building & Trades",
            "subcategory":"Construction",
            "type":"Services"
        }
    ],
    "sg:phone":"+1 815 886 5544",
    "sg:postcode":"60446",
    "sg:province":"IL",
    "sg:tags":[
        "painting",
        "contractor"
    ],
    "wof:name":"McCahill Painting Company",
    "wof:placetype":"venue"
},
  "geometry": {"coordinates":[-88.072152,41.657617],"type":"Point"}
}