{
  "type": "Feature",
  "properties": {
    "addr:full":"8030 S Cicero Ave Burbank IL 60459",
    "addr:housenumber":"8030",
    "addr:postcode":"60459",
    "addr:street":"S Cicero Ave",
    "iso:country":"US",
    "sg:address":"8030 S Cicero Ave",
    "sg:city":"Burbank",
    "sg:classifiers":[
        {
            "category":"Utilities",
            "subcategory":"Mobile Phone",
            "type":"Services"
        },
        {
            "category":"Shopping",
            "subcategory":"Mobile Phones",
            "type":"Retail Goods"
        },
        {
            "category":"Utilities",
            "subcategory":"Telephone",
            "type":"Services"
        },
        {
            "category":"Professional",
            "subcategory":"Computer Services",
            "type":"Services"
        }
    ],
    "sg:phone":"+1 708 499 0990",
    "sg:postcode":"60459",
    "sg:province":"IL",
    "sg:tags":[
        "telecommunication",
        "supply",
        "communication",
        "system",
        "wireless",
        "equipment",
        "cellular"
    ],
    "sg:website":"http://clickserve.dartsearch.net/link/click?lid=43000000308049899",
    "wof:name":"T-Mobile",
    "wof:placetype":"venue"
},
  "geometry": {"coordinates":[-87.741285,41.746736],"type":"Point"}
}