{
  "type": "Feature",
  "properties": {
    "iso:country":"US",
    "sg:address":"6107 W Kennedy Rd",
    "sg:city":"Peotone",
    "sg:classifiers":[
        {
            "category":"Autos & Motor Vehicles",
            "subcategory":"Automobile Sales",
            "type":"Retail Goods"
        }
    ],
    "sg:phone":"+1 708 258 3363",
    "sg:postcode":"60468",
    "sg:province":"IL",
    "sg:tags":[
        "new",
        "used",
        "car"
    ],
    "wof:name":"Robert J Edwards Motors",
    "wof:placetype":"venue"
},
  "geometry": {"coordinates":[-87.764538,41.31053],"type":"Point"}
}