{
  "type": "Feature",
  "properties": {
    "iso:country":"US",
    "sg:address":"511 S 51st St",
    "sg:city":"Alorton",
    "sg:classifiers":[
        {
            "category":"Organizations",
            "subcategory":"Religious Organization",
            "type":"Services"
        }
    ],
    "sg:phone":"+1 618 337 5710",
    "sg:postcode":"62207",
    "sg:province":"IL",
    "sg:tags":[
        "church"
    ],
    "wof:name":"Purpose World Outreach Church",
    "wof:placetype":"venue"
},
  "geometry": {"coordinates":[-90.117628,38.576214],"type":"Point"}
}