{
  "type": "Feature",
  "properties": {
    "iso:country":"US",
    "sg:address":"11645 S Merrion Ln",
    "sg:city":"Alsip",
    "sg:classifiers":[
        {
            "category":"Wholesale",
            "subcategory":"Hardware",
            "type":"Manufacturing & Wholesale Goods"
        }
    ],
    "sg:phone":"+1 708 596 4300",
    "sg:postcode":"60803",
    "sg:province":"IL",
    "sg:tags":[
        "pipe",
        "distributor",
        "fitting",
        "valve"
    ],
    "wof:name":"Independent Pipe & Supply Co",
    "wof:placetype":"venue"
},
  "geometry": {"coordinates":[-87.70382600000001,41.681055],"type":"Point"}
}