{
  "type": "Feature",
  "properties": {
    "iso:country":"US",
    "sg:address":"221 E Broadway Ste 104",
    "sg:city":"Centralia",
    "sg:classifiers":[
        {
            "category":"Insurance",
            "subcategory":"Hazard Insurance",
            "type":"Services"
        }
    ],
    "sg:phone":"+1 618 533 3166",
    "sg:postcode":"62801",
    "sg:province":"IL",
    "sg:tags":[
        "commercial",
        "business"
    ],
    "sg:website":"http://www.countryfinancial.com",
    "wof:name":"Country Co Insur & Fincl Svcs",
    "wof:placetype":"venue"
},
  "geometry": {"coordinates":[-89.133927,38.527577],"type":"Point"}
}