{
  "type": "Feature",
  "properties": {
    "addr:full":"104 Chestnut St Ste 320 Hinsdale IL 60521",
    "addr:housenumber":"104",
    "addr:postcode":"60521",
    "addr:street":"Chestnut St Ste 320",
    "iso:country":"US",
    "sg:address":"104 Chestnut St Ste 320",
    "sg:city":"Hinsdale",
    "sg:classifiers":[
        {
            "category":"Real Estate",
            "subcategory":"Real Estate Services",
            "type":"Services"
        },
        {
            "category":"Real Estate",
            "subcategory":"Real Estate Agent",
            "type":"Services"
        }
    ],
    "sg:phone":"+1 708 785 3200",
    "sg:postcode":"60521",
    "sg:province":"IL",
    "sg:tags":[
        "buyer",
        "broker"
    ],
    "wof:name":"Accurate Real Estate Appraisals",
    "wof:placetype":"venue"
},
  "geometry": {"coordinates":[-87.930876,41.802853],"type":"Point"}
}