{
  "type": "Feature",
  "properties": {
    "iso:country":"US",
    "sg:address":"7321 S South Shore Dr",
    "sg:city":"Chicago",
    "sg:classifiers":[
        {
            "category":"Professional",
            "subcategory":"Computer Services",
            "type":"Services"
        }
    ],
    "sg:phone":"+1 773 933 1768",
    "sg:postcode":"60649",
    "sg:province":"IL",
    "sg:tags":[
        "web",
        "design",
        "hosting",
        "site"
    ],
    "wof:name":"Arielcej 2 Inc",
    "wof:placetype":"venue"
},
  "geometry": {"coordinates":[-87.56004900000001,41.763486],"type":"Point"}
}