{
  "type": "Feature",
  "properties": {
    "addr:full":"2754 Columbus St Ottawa IL 61350",
    "addr:housenumber":"2754",
    "addr:postcode":"61350",
    "addr:street":"Columbus St",
    "iso:country":"US",
    "sg:address":"2754 Columbus St",
    "sg:city":"Ottawa",
    "sg:classifiers":[
        {
            "category":"Restaurant",
            "type":"Food & Drink"
        }
    ],
    "sg:menulink":"http://www.allmenus.com/il/dayton/222170-country-kitchen/menu/",
    "sg:phone":"+1 815 431 0844",
    "sg:postcode":"61350",
    "sg:province":"IL",
    "sg:tags":[
        "american",
        "southern"
    ],
    "wof:name":"Country Kitchen",
    "wof:placetype":"venue"
},
  "geometry": {"coordinates":[-88.835866,41.370425],"type":"Point"}
}