{
  "type": "Feature",
  "properties": {
    "addr:full":"925 Burlington Ave Lisle IL 60532",
    "addr:housenumber":"925",
    "addr:postcode":"60532",
    "addr:street":"Burlington Ave",
    "iso:country":"US",
    "sg:address":"925 Burlington Ave",
    "sg:city":"Lisle",
    "sg:classifiers":[
        {
            "category":"Government",
            "subcategory":"Office",
            "type":"Public Place"
        }
    ],
    "sg:phone":"+1   ",
    "sg:postcode":"60532",
    "sg:province":"IL",
    "sg:tags":[
        "executive",
        "mayor"
    ],
    "wof:name":"Village of Lisle",
    "wof:placetype":"venue"
},
  "geometry": {"coordinates":[-88.071106,41.79901],"type":"Point"}
}