{
  "type": "Feature",
  "properties": {
    "iso:country":"US",
    "sg:address":"24101 S Municipal Dr",
    "sg:city":"Channahon",
    "sg:classifiers":[
        {
            "category":"Building & Trades",
            "subcategory":"Construction",
            "type":"Services"
        }
    ],
    "sg:phone":"+1 815 521 0900",
    "sg:postcode":"60410",
    "sg:province":"IL",
    "sg:tags":[
        "contractor"
    ],
    "sg:website":"www.brieserconstruction.com",
    "wof:name":"Brieser Construction",
    "wof:placetype":"venue"
},
  "geometry": {"coordinates":[-88.204399,41.445099],"type":"Point"}
}