{
  "type": "Feature",
  "properties": {
    "addr:full":"302 Bird Ave Lawrenceville IL 62439",
    "addr:housenumber":"302",
    "addr:postcode":"62439",
    "addr:street":"Bird Ave",
    "iso:country":"US",
    "sg:address":"302 Bird Ave",
    "sg:city":"Lawrenceville",
    "sg:classifiers":[
        {
            "category":"Professional",
            "subcategory":"Art Services",
            "type":"Services"
        }
    ],
    "sg:phone":"+1 618 943 5644",
    "sg:postcode":"62439",
    "sg:province":"IL",
    "sg:tags":[
        "interior",
        "designer",
        "decorator"
    ],
    "wof:name":"Interiors By Janet",
    "wof:placetype":"venue"
},
  "geometry": {"coordinates":[-87.698821,38.731741],"type":"Point"}
}