{
  "type": "Feature",
  "properties": {
    "addr:full":"111 S Pekin Ln South Pekin IL 61536",
    "addr:housenumber":"111",
    "addr:postcode":"61536",
    "addr:street":"S Pekin Ln South",
    "iso:country":"US",
    "sg:address":"111 S Pekin Ln",
    "sg:city":"South Pekin",
    "sg:classifiers":[
        {
            "category":"Retail",
            "subcategory":"Repair Shop",
            "type":"Services"
        }
    ],
    "sg:phone":"+1 309 348 3626",
    "sg:postcode":"61536",
    "sg:province":"IL",
    "wof:name":"Authentic Taxidermy",
    "wof:placetype":"venue"
},
  "geometry": {"coordinates":[-89.79996,40.689839],"type":"Point"}
}