{
  "type": "Feature",
  "properties": {
    "iso:country":"US",
    "sg:address":"29697 E 825 N Rd",
    "sg:city":"Forrest",
    "sg:classifiers":[
        {
            "category":"Wholesale",
            "subcategory":"Farm Supplies",
            "type":"Manufacturing & Wholesale Goods"
        }
    ],
    "sg:phone":"+1 815 657 8311",
    "sg:postcode":"61741",
    "sg:province":"IL",
    "sg:tags":[
        "feed"
    ],
    "wof:name":"Zimmerman Brothers Feed Inc",
    "wof:placetype":"venue"
},
  "geometry": {"coordinates":[-88.35401,40.750547],"type":"Point"}
}