{
  "type": "Feature",
  "properties": {
    "iso:country":"US",
    "sg:address":"2706 S 9th Ave",
    "sg:city":"Broadview",
    "sg:classifiers":[
        {
            "category":"Building & Trades",
            "subcategory":"Landscaping Services",
            "type":"Services"
        }
    ],
    "sg:phone":"+1 708 344 7756",
    "sg:postcode":"60155",
    "sg:province":"IL",
    "sg:tags":[
        "landscape",
        "contractor"
    ],
    "wof:name":"Bartolini Brothers Landscaping",
    "wof:placetype":"venue"
},
  "geometry": {"coordinates":[-87.842992,41.854083],"type":"Point"}
}