{
  "type": "Feature",
  "properties": {
    "iso:country":"US",
    "sg:address":"3500 S Giles Ave",
    "sg:city":"Chicago",
    "sg:classifiers":[
        {
            "category":"Social Services",
            "subcategory":"Job Training",
            "type":"Services"
        },
        {
            "category":"Health Services",
            "subcategory":"Nursing And Care Facility",
            "type":"Services"
        },
        {
            "category":"Social Services",
            "subcategory":"Retirement Home",
            "type":"Services"
        }
    ],
    "sg:phone":"+1 312 326 2000",
    "sg:postcode":"60653",
    "sg:province":"IL",
    "sg:tags":[
        "living",
        "assisted",
        "convalescent",
        "homes-intermediate",
        "homes-skilled"
    ],
    "sg:website":"http://www.wldnursing.com",
    "wof:name":"Dawson William L Convalescent & Nursing Center",
    "wof:placetype":"venue"
},
  "geometry": {"coordinates":[-87.619308,41.831081],"type":"Point"}
}