{
  "type": "Feature",
  "properties": {
    "iso:country":"US",
    "sg:address":"10941 S Western Ave",
    "sg:city":"Chicago",
    "sg:classifiers":[
        {
            "category":"Personal",
            "subcategory":"Shoe Repair & Shine",
            "type":"Services"
        }
    ],
    "sg:phone":"+1 773 239 4431",
    "sg:postcode":"60643",
    "sg:province":"IL",
    "sg:tags":[
        "repairing",
        "parlor",
        "boot"
    ],
    "wof:name":"Fox's Shoe Repair Clinic",
    "wof:placetype":"venue"
},
  "geometry": {"coordinates":[-87.681252,41.694684],"type":"Point"}
}