{
  "type": "Feature",
  "properties": {
    "iso:country":"US",
    "sg:address":"4554 S Archer Ave",
    "sg:city":"Chicago",
    "sg:classifiers":[
        {
            "category":"Health Services",
            "subcategory":"Doctor",
            "type":"Services"
        }
    ],
    "sg:phone":"+1 773 847 6784",
    "sg:postcode":"60632",
    "sg:province":"IL",
    "sg:tags":[
        "podiatrist"
    ],
    "wof:name":"Buividas Alex J DPM",
    "wof:placetype":"venue"
},
  "geometry": {"coordinates":[-87.710701,41.8102],"type":"Point"}
}