{
  "type": "Feature",
  "properties": {
    "iso:country":"US",
    "sg:address":"1314 W 31st",
    "sg:city":"Chicago",
    "sg:classifiers":[
        {
            "category":"Food & Beverages",
            "subcategory":"Groceries & Convenience Stores",
            "type":"Retail Goods"
        }
    ],
    "sg:phone":"+1 773 847 7884",
    "sg:postcode":"60607",
    "sg:province":"IL",
    "wof:name":"Fruteria Los Panchos",
    "wof:placetype":"venue"
},
  "geometry": {"coordinates":[-87.65875800000001,41.837129],"type":"Point"}
}