{
  "type": "Feature",
  "properties": {
    "iso:country":"US",
    "sg:address":"2500 S 8th St",
    "sg:city":"Quincy",
    "sg:classifiers":[
        {
            "category":"Freight",
            "type":"Transportation"
        }
    ],
    "sg:phone":"+1 217 224 6838",
    "sg:postcode":"62305",
    "sg:province":"IL",
    "sg:tags":[
        "fencing",
        "self",
        "storage",
        "unit",
        "contractor"
    ],
    "wof:name":"Southside Mini Storage",
    "wof:placetype":"venue"
},
  "geometry": {"coordinates":[-91.403213,39.902003],"type":"Point"}
}