{
  "type": "Feature",
  "properties": {
    "addr:full":"1100 Beech St Ste 10 Normal IL 61761",
    "addr:housenumber":"1100",
    "addr:postcode":"61761",
    "addr:street":"Beech St Ste 10",
    "iso:country":"US",
    "sg:address":"1100 Beech St Ste 10",
    "sg:city":"Normal",
    "sg:classifiers":[
        {
            "category":"Health Services",
            "subcategory":"Doctor",
            "type":"Services"
        }
    ],
    "sg:phone":"+1 309 454 2112",
    "sg:postcode":"61761",
    "sg:province":"IL",
    "sg:tags":[
        "psychiatry",
        "physician",
        "surgeon",
        "surgeons"
    ],
    "wof:name":"Telot Gabriel MD",
    "wof:placetype":"venue"
},
  "geometry": {"coordinates":[-88.97792099999999,40.52042],"type":"Point"}
}