{
  "type": "Feature",
  "properties": {
    "addr:full":"4925 Cal Sag Rd Crestwood IL 60445",
    "addr:housenumber":"4925",
    "addr:postcode":"60445",
    "addr:street":"Cal Sag Rd",
    "iso:country":"US",
    "sg:address":"4925 Cal Sag Rd",
    "sg:city":"Crestwood",
    "sg:classifiers":[
        {
            "category":"Wholesale",
            "subcategory":"Computers",
            "type":"Manufacturing & Wholesale Goods"
        }
    ],
    "sg:phone":"+1 708 396 0133",
    "sg:postcode":"60445",
    "sg:province":"IL",
    "sg:website":"www.bestbuy.com",
    "wof:name":"Best Buy",
    "wof:placetype":"venue"
},
  "geometry": {"coordinates":[-87.74374400000001,41.6553],"type":"Point"}
}