{
  "type": "Feature",
  "properties": {
    "iso:country":"US",
    "sg:address":"1780 Co Rd 925 N",
    "sg:city":"Greenup",
    "sg:phone":"+1 217 923 5016",
    "sg:postcode":"62428",
    "sg:province":"IL",
    "sg:tags":[
        "farm",
        "corn",
        "soybean"
    ],
    "wof:name":"Marty May",
    "wof:placetype":"venue"
},
  "geometry": {"coordinates":[-88.143792,39.306678],"type":"Point"}
}