{
  "type": "Feature",
  "properties": {
    "iso:country":"US",
    "sg:address":"228 N Genesee St",
    "sg:city":"Waukegan",
    "sg:classifiers":[
        {
            "category":"Professional",
            "subcategory":"Detective & Security Services",
            "type":"Services"
        }
    ],
    "sg:phone":"+1 847 596 4311",
    "sg:postcode":"60085",
    "sg:province":"IL",
    "sg:tags":[
        "guard",
        "patrol"
    ],
    "wof:name":"Twin City Security Inc",
    "wof:placetype":"venue"
},
  "geometry": {"coordinates":[-87.831338,42.363338],"type":"Point"}
}