{
  "type": "Feature",
  "properties": {
    "iso:country":"US",
    "sg:address":"202 N Monroe St",
    "sg:city":"Gardner",
    "sg:classifiers":[
        {
            "category":"Organizations",
            "subcategory":"Religious Organization",
            "type":"Services"
        }
    ],
    "sg:phone":"+1 815 237 8312",
    "sg:postcode":"60424",
    "sg:province":"IL",
    "sg:tags":[
        "church"
    ],
    "wof:name":"Church Of Hope",
    "wof:placetype":"venue"
},
  "geometry": {"coordinates":[-88.309977,41.18849],"type":"Point"}
}