{
  "type": "Feature",
  "properties": {
    "iso:country":"US",
    "sg:address":"3731 Grand Blvd",
    "sg:city":"Brookfield",
    "sg:classifiers":[
        {
            "category":"Shopping",
            "subcategory":"Hobbies, Toys, & Games",
            "type":"Retail Goods"
        }
    ],
    "sg:phone":"+1 708 387 0890",
    "sg:postcode":"60513",
    "sg:province":"IL",
    "sg:tags":[
        "toy",
        "store"
    ],
    "wof:name":"Wonderland Multivintage",
    "wof:placetype":"venue"
},
  "geometry": {"coordinates":[-87.845574,41.82362],"type":"Point"}
}