{
  "type": "Feature",
  "properties": {
    "addr:full":"201 W Main St Collinsville IL 62234",
    "addr:housenumber":"201",
    "addr:postcode":"62234",
    "addr:street":"W Main St",
    "iso:country":"US",
    "sg:address":"201 W Main St",
    "sg:city":"Collinsville",
    "sg:classifiers":[
        {
            "category":"Shopping",
            "subcategory":"Crafts & Fabrics",
            "type":"Retail Goods"
        }
    ],
    "sg:phone":"+1 618 345 7225",
    "sg:postcode":"62234",
    "sg:province":"IL",
    "sg:tags":[
        "art",
        "supply"
    ],
    "wof:name":"A-Plus Service Heating & Cooling",
    "wof:placetype":"venue"
},
  "geometry": {"coordinates":[-89.987503,38.669498],"type":"Point"}
}