{
  "type": "Feature",
  "properties": {
    "iso:country":"US",
    "sg:address":"430 30th Ave",
    "sg:city":"East Moline",
    "sg:classifiers":[
        {
            "category":"Social Services",
            "subcategory":"Adult Care",
            "type":"Services"
        }
    ],
    "sg:phone":"+1 309 755 3466",
    "sg:postcode":"61244",
    "sg:province":"IL",
    "sg:tags":[
        "residential"
    ],
    "wof:name":"Mitchell Pk Convelescence Ctr",
    "wof:placetype":"venue"
},
  "geometry": {"coordinates":[-90.454882,41.500083],"type":"Point"}
}