{
  "type": "Feature",
  "properties": {
    "iso:country":"US",
    "sg:address":"1730 E 1700th Ave",
    "sg:city":"Teutopolis",
    "sg:classifiers":[
        {
            "category":"Farming",
            "subcategory":"Dairy Farm",
            "type":"Manufacturing & Wholesale Goods"
        }
    ],
    "sg:phone":"+1 217 683 2264",
    "sg:postcode":"62467",
    "sg:province":"IL",
    "wof:name":"Jansen Dairy Farms Inc",
    "wof:placetype":"venue"
},
  "geometry": {"coordinates":[-88.339805,39.102681],"type":"Point"}
}