{
  "type": "Feature",
  "properties": {
    "iso:country":"US",
    "sg:address":"2520 Happy Hollow Rd",
    "sg:city":"Glenview",
    "sg:classifiers":[
        {
            "category":"Building & Trades",
            "subcategory":"Landscaping Services",
            "type":"Services"
        }
    ],
    "sg:phone":"+1 847 272 6528",
    "sg:postcode":"60026",
    "sg:province":"IL",
    "sg:tags":[
        "consultant",
        "designer",
        "landscape"
    ],
    "wof:name":"Charles Dimarco Landscape Contractors",
    "wof:placetype":"venue"
},
  "geometry": {"coordinates":[-87.842827,42.100393],"type":"Point"}
}