{
  "type": "Feature",
  "properties": {
    "iso:country":"US",
    "sg:address":"9031 W 151st St",
    "sg:city":"Orland Park",
    "sg:classifiers":[
        {
            "category":"Real Estate",
            "subcategory":"Real Estate Operator",
            "type":"Services"
        }
    ],
    "sg:phone":"+1 708 226 9510",
    "sg:postcode":"60462",
    "sg:province":"IL",
    "sg:tags":[
        "condominium"
    ],
    "wof:name":"Charleton Group",
    "wof:placetype":"venue"
},
  "geometry": {"coordinates":[-87.839388,41.616148],"type":"Point"}
}