{
  "type": "Feature",
  "properties": {
    "iso:country":"US",
    "sg:address":"3203 Green Dale Dr",
    "sg:city":"Rockford",
    "sg:classifiers":[
        {
            "category":"Health Services",
            "subcategory":"Health Practitioner",
            "type":"Services"
        }
    ],
    "sg:phone":"+1 815 398 7241",
    "sg:postcode":"61109",
    "sg:province":"IL",
    "sg:tags":[
        "nurse",
        "registry"
    ],
    "sg:website":"www.mysilvercare.com",
    "wof:name":"Silvercare",
    "wof:placetype":"venue"
},
  "geometry": {"coordinates":[-89.042204,42.234954],"type":"Point"}
}