{
  "type": "Feature",
  "properties": {
    "addr:full":"110 S State St Marengo IL 60152",
    "addr:housenumber":"110",
    "addr:postcode":"60152",
    "addr:street":"S State St",
    "iso:country":"US",
    "sg:address":"110 S State St",
    "sg:city":"Marengo",
    "sg:classifiers":[
        {
            "category":"Coffee & Tea",
            "type":"Food & Drink"
        },
        {
            "category":"Restaurant",
            "type":"Food & Drink"
        }
    ],
    "sg:phone":"+1 815 568 5341",
    "sg:postcode":"60152",
    "sg:province":"IL",
    "sg:tags":[
        "espresso"
    ],
    "wof:name":"Marengo Cafe",
    "wof:placetype":"venue"
},
  "geometry": {"coordinates":[-88.608498,42.249911],"type":"Point"}
}