{
  "type": "Feature",
  "properties": {
    "addr:full":"108 E Keely St Creal Springs IL 62922",
    "addr:housenumber":"108",
    "addr:postcode":"62922",
    "addr:street":"E Keely St",
    "iso:country":"US",
    "sg:address":"108 E Keely St",
    "sg:city":"Creal Springs",
    "sg:classifiers":[
        {
            "category":"Organizations",
            "subcategory":"Religious Organization",
            "type":"Services"
        }
    ],
    "sg:phone":"+1 618 996 2300",
    "sg:postcode":"62922",
    "sg:province":"IL",
    "sg:tags":[
        "church"
    ],
    "wof:name":"Creal Springs First Baptist",
    "wof:placetype":"venue"
},
  "geometry": {"coordinates":[-88.83651999999999,37.619499],"type":"Point"}
}