{
  "type": "Feature",
  "properties": {
    "addr:full":"9502 Cary Algonquin Rd Cary IL 60013",
    "addr:housenumber":"9502",
    "addr:postcode":"60013",
    "addr:street":"Cary Algonquin Rd",
    "iso:country":"US",
    "sg:address":"9502 Cary Algonquin Rd",
    "sg:city":"Cary",
    "sg:classifiers":[
        {
            "category":"Education",
            "subcategory":"Library",
            "type":"Public Place"
        }
    ],
    "sg:phone":"+1 847 854 6862",
    "sg:postcode":"60013",
    "sg:province":"IL",
    "sg:tags":[
        "research"
    ],
    "wof:name":"L/C Process,",
    "wof:placetype":"venue"
},
  "geometry": {"coordinates":[-88.266167,42.195831],"type":"Point"}
}