{
  "type": "Feature",
  "properties": {
    "iso:country":"US",
    "sg:address":"13 Park Pl",
    "sg:city":"Swansea",
    "sg:classifiers":[
        {
            "category":"Banks & Credit Unions",
            "subcategory":"Investment Brokerage",
            "type":"Services"
        }
    ],
    "sg:phone":"+1 618 233 5758",
    "sg:postcode":"62226",
    "sg:province":"IL",
    "sg:tags":[
        "security"
    ],
    "wof:name":"Hilliard Lyons",
    "wof:placetype":"venue"
},
  "geometry": {"coordinates":[-89.983982,38.539946],"type":"Point"}
}