{
  "type": "Feature",
  "properties": {
    "addr:full":"1030 S La Grange Rd La Grange IL 60525",
    "addr:housenumber":"1030",
    "addr:postcode":"60525",
    "addr:street":"S La Grange Rd",
    "iso:country":"US",
    "sg:address":"1030 S La Grange Rd",
    "sg:city":"La Grange",
    "sg:classifiers":[
        {
            "category":"Health Services",
            "subcategory":"Clinic",
            "type":"Services"
        }
    ],
    "sg:phone":"+1 708 352 2597",
    "sg:postcode":"60525",
    "sg:province":"IL",
    "sg:tags":[
        "counseling",
        "mental"
    ],
    "wof:name":"Stevenson & Assoc",
    "wof:placetype":"venue"
},
  "geometry": {"coordinates":[-87.86900300000001,41.797798],"type":"Point"}
}