{
  "type": "Feature",
  "properties": {
    "iso:country":"US",
    "sg:address":"1540 N Green Bay Rd",
    "sg:city":"Waukegan",
    "sg:classifiers":[
        {
            "category":"Bars & Pubs",
            "type":"Food & Drink"
        }
    ],
    "sg:phone":"+1 847 662 0112",
    "sg:postcode":"60085",
    "sg:province":"IL",
    "sg:tags":[
        "drinking"
    ],
    "wof:name":"Casey's Corner",
    "wof:placetype":"venue"
},
  "geometry": {"coordinates":[-87.883962,42.381546],"type":"Point"}
}