{
  "type": "Feature",
  "properties": {
    "addr:full":"16619 E Edson Rd Rockford IL 61109",
    "addr:housenumber":"16619",
    "addr:postcode":"61109",
    "addr:street":"E Edson Rd",
    "iso:country":"US",
    "sg:address":"16619 E Edson Rd",
    "sg:city":"Rockford",
    "sg:classifiers":[
        {
            "category":"Manufacturing",
            "subcategory":"Food",
            "type":"Manufacturing & Wholesale Goods"
        },
        {
            "category":"Farming",
            "subcategory":"Farm",
            "type":"Manufacturing & Wholesale Goods"
        }
    ],
    "sg:phone":"+1 815 874 5834",
    "sg:postcode":"61109",
    "sg:province":"IL",
    "sg:tags":[
        "corn",
        "product"
    ],
    "wof:name":"Joe Troutman",
    "wof:placetype":"venue"
},
  "geometry": {"coordinates":[-89.025915,42.151333],"type":"Point"}
}