{
  "type": "Feature",
  "properties": {
    "iso:country":"US",
    "sg:address":"1951 Townsley Ln",
    "sg:city":"Caseyville",
    "sg:classifiers":[
        {
            "category":"Retail",
            "subcategory":"Animal Services",
            "type":"Services"
        }
    ],
    "sg:phone":"+1 618 293 1750",
    "sg:postcode":"62232",
    "sg:province":"IL",
    "sg:tags":[
        "pet"
    ],
    "sg:website":"www.dogsportsatkims.com",
    "wof:name":"Kim's Canine Club",
    "wof:placetype":"venue"
},
  "geometry": {"coordinates":[-90.062096,38.621672],"type":"Point"}
}