{
  "type": "Feature",
  "properties": {
    "addr:full":"7333 Northgate Way Downers Grove IL 60516",
    "addr:housenumber":"7333",
    "addr:postcode":"60516",
    "addr:street":"Northgate Way",
    "iso:country":"US",
    "sg:address":"7333 Northgate Way",
    "sg:city":"Downers Grove",
    "sg:classifiers":[
        {
            "category":"Professional",
            "type":"Services"
        }
    ],
    "sg:phone":"+1 630 969 7981",
    "sg:postcode":"60516",
    "sg:province":"IL",
    "sg:tags":[
        "establishment"
    ],
    "wof:name":"Courts Of The Falling Waters",
    "wof:placetype":"venue"
},
  "geometry": {"coordinates":[-87.999754,41.755368],"type":"Point"}
}