{
  "type": "Feature",
  "properties": {
    "addr:full":"750 W State Rte 173 Antioch IL 60002",
    "addr:housenumber":"750",
    "addr:postcode":"60002",
    "addr:street":"W State Rte 173",
    "iso:country":"US",
    "sg:address":"750 W State Rte 173",
    "sg:city":"Antioch",
    "sg:classifiers":[
        {
            "category":"Sports & Exercise",
            "subcategory":"Bowling",
            "type":"Entertainment"
        }
    ],
    "sg:phone":"+1   ",
    "sg:postcode":"60002",
    "sg:province":"IL",
    "sg:tags":[
        "lounge",
        "alley"
    ],
    "wof:name":"Antioch Bowl",
    "wof:placetype":"venue"
},
  "geometry": {"coordinates":[-88.110131,42.477178],"type":"Point"}
}