{
  "type": "Feature",
  "properties": {
    "iso:country":"US",
    "sg:address":"19862 Kedzie Ave",
    "sg:city":"Flossmoor",
    "sg:classifiers":[
        {
            "category":"Retail",
            "subcategory":"Laundry & Dry Cleaning",
            "type":"Services"
        }
    ],
    "sg:phone":"+1 708 799 9988",
    "sg:postcode":"60422",
    "sg:province":"IL",
    "sg:tags":[
        "garment",
        "plant",
        "agent",
        "drycleaning"
    ],
    "wof:name":"Charm Cleaners",
    "wof:placetype":"venue"
},
  "geometry": {"coordinates":[-87.693963,41.529274],"type":"Point"}
}