{
  "type": "Feature",
  "properties": {
    "iso:country":"US",
    "sg:address":"595 Lakeview Pkwy",
    "sg:city":"Vernon Hills",
    "sg:classifiers":[
        {
            "category":"Recreation",
            "type":"Entertainment"
        }
    ],
    "sg:phone":"+1 847 549 6577",
    "sg:postcode":"60061",
    "sg:province":"IL",
    "sg:tags":[
        "balloon"
    ],
    "sg:website":"www.8004balloons.com",
    "wof:name":"800 4 Balloons",
    "wof:placetype":"venue"
},
  "geometry": {"coordinates":[-87.947711,42.236286],"type":"Point"}
}