{
  "type": "Feature",
  "properties": {
    "addr:full":"5230 N Milwaukee Ave Chicago IL 60630",
    "addr:housenumber":"5230",
    "addr:postcode":"60630",
    "addr:street":"N Milwaukee Ave",
    "iso:country":"US",
    "sg:address":"5230 N Milwaukee Ave",
    "sg:city":"Chicago",
    "sg:classifiers":[
        {
            "category":"Health Services",
            "subcategory":"Optometrist",
            "type":"Services"
        },
        {
            "category":"Shopping",
            "subcategory":"Optician",
            "type":"Retail Goods"
        },
        {
            "category":"Shopping",
            "subcategory":"Pharmacy",
            "type":"Retail Goods"
        }
    ],
    "sg:phone":"+1 773 736 1740",
    "sg:postcode":"60630",
    "sg:province":"IL",
    "sg:tags":[
        "drugstore",
        "eyewear"
    ],
    "wof:name":"Walgreen Drug Stores",
    "wof:placetype":"venue"
},
  "geometry": {"coordinates":[-87.767681,41.975261],"type":"Point"}
}