{
  "type": "Feature",
  "properties": {
    "addr:full":"4112 46th Ave Rock Island IL 61201",
    "addr:housenumber":"4112",
    "addr:postcode":"61201",
    "addr:street":"46Th Ave",
    "iso:country":"US",
    "sg:address":"4112 46th Ave",
    "sg:city":"Rock Island",
    "sg:classifiers":[
        {
            "category":"Social Services",
            "subcategory":"Job Training",
            "type":"Services"
        },
        {
            "category":"Education",
            "subcategory":"Special Training",
            "type":"Public Place"
        }
    ],
    "sg:phone":"+1 309 779 2828",
    "sg:postcode":"61201",
    "sg:province":"IL",
    "sg:tags":[
        "driving",
        "facility",
        "instruction",
        "specialty",
        "outpatient",
        "rehabilitation"
    ],
    "wof:name":"Trinity Outpatient Rehab Svcs",
    "wof:placetype":"venue"
},
  "geometry": {"coordinates":[-90.542655,41.468216],"type":"Point"}
}