{
  "type": "Feature",
  "properties": {
    "iso:country":"US",
    "sg:address":"1830 Howard St",
    "sg:city":"Elk Grove Village",
    "sg:classifiers":[
        {
            "category":"Retail",
            "subcategory":"Repair Shop",
            "type":"Services"
        }
    ],
    "sg:phone":"+1 847 290 8300",
    "sg:postcode":"60007",
    "sg:province":"IL",
    "wof:name":"Millar Elevator Service Co",
    "wof:placetype":"venue"
},
  "geometry": {"coordinates":[-87.95840800000001,42.016136],"type":"Point"}
}