{
  "type": "Feature",
  "properties": {
    "iso:country":"US",
    "sg:address":"101 W Vandalia St Ste 225",
    "sg:city":"Edwardsville",
    "sg:classifiers":[
        {
            "category":"Professional",
            "subcategory":"Lawyer & Legal Services",
            "type":"Services"
        }
    ],
    "sg:phone":"+1 618 655 9500",
    "sg:postcode":"62025",
    "sg:province":"IL",
    "sg:tags":[
        "plan"
    ],
    "wof:name":"Polsinelli Shalton & Welte, A Professional Corporation",
    "wof:placetype":"venue"
},
  "geometry": {"coordinates":[-89.955772,38.81134],"type":"Point"}
}