{
  "type": "Feature",
  "properties": {
    "iso:country":"US",
    "sg:address":"5036 N Sheridan Rd",
    "sg:city":"Chicago",
    "sg:classifiers":[
        {
            "category":"Real Estate",
            "subcategory":"Real Estate Agent",
            "type":"Services"
        }
    ],
    "sg:phone":"+1 773 878 5071",
    "sg:postcode":"60640",
    "sg:province":"IL",
    "wof:name":"Carmen Sheridan Apartments",
    "wof:placetype":"venue"
},
  "geometry": {"coordinates":[-87.655054,41.975248],"type":"Point"}
}