{
  "type": "Feature",
  "properties": {
    "iso:country":"US",
    "sg:address":"12232 Squirrel Tree Ln",
    "sg:city":"Belvidere",
    "sg:classifiers":[
        {
            "category":"Shopping",
            "subcategory":"Clothing, Apparel, & Fashions",
            "type":"Retail Goods"
        }
    ],
    "sg:phone":"+1 815 547 5938",
    "sg:postcode":"61008",
    "sg:province":"IL",
    "sg:tags":[
        "apparel",
        "women's"
    ],
    "wof:name":"Helen S Fashion Flair",
    "wof:placetype":"venue"
},
  "geometry": {"coordinates":[-88.864332,42.329691],"type":"Point"}
}