{
  "type": "Feature",
  "properties": {
    "iso:country":"US",
    "sg:address":"113 W Mason St",
    "sg:city":"Polo",
    "sg:classifiers":[
        {
            "category":"Bars & Pubs",
            "type":"Food & Drink"
        }
    ],
    "sg:phone":"+1 815 946 2860",
    "sg:postcode":"61064",
    "sg:province":"IL",
    "wof:name":"Jeff's Refs",
    "wof:placetype":"venue"
},
  "geometry": {"coordinates":[-89.578728,41.986069],"type":"Point"}
}