{
  "type": "Feature",
  "properties": {
    "addr:full":"1438 Centreville Ave Belleville IL 62220",
    "addr:housenumber":"1438",
    "addr:postcode":"62220",
    "addr:street":"Centreville Ave",
    "iso:country":"US",
    "sg:address":"1438 Centreville Ave",
    "sg:city":"Belleville",
    "sg:classifiers":[
        {
            "category":"Travel",
            "subcategory":"Hotels & Motels",
            "type":"Entertainment"
        }
    ],
    "sg:phone":"+1 618 233 7410",
    "sg:postcode":"62220",
    "sg:province":"IL",
    "wof:name":"Cinderella Motel",
    "wof:placetype":"venue"
},
  "geometry": {"coordinates":[-90.005905,38.502853],"type":"Point"}
}