{
  "type": "Feature",
  "properties": {
    "addr:full":"603 W High St Elmwood IL 61529",
    "addr:housenumber":"603",
    "addr:postcode":"61529",
    "addr:street":"W High St",
    "iso:country":"US",
    "sg:address":"603 W High St",
    "sg:city":"Elmwood",
    "sg:classifiers":[
        {
            "category":"Social Services",
            "type":"Services"
        }
    ],
    "sg:phone":"+1 309 742 7300",
    "sg:postcode":"61529",
    "sg:province":"IL",
    "sg:tags":[
        "organization",
        "welfare"
    ],
    "wof:name":"Mosaic",
    "wof:placetype":"venue"
},
  "geometry": {"coordinates":[-89.974317,40.780218],"type":"Point"}
}