{
  "type": "Feature",
  "properties": {
    "iso:country":"US",
    "sg:address":"8121 Salisbury Ave",
    "sg:city":"Lyons",
    "sg:classifiers":[
        {
            "category":"Personal",
            "subcategory":"Beauty Salon",
            "type":"Services"
        }
    ],
    "sg:phone":"+1 708 442 6635",
    "sg:postcode":"60534",
    "sg:province":"IL",
    "wof:name":"Opals Beauty Shop",
    "wof:placetype":"venue"
},
  "geometry": {"coordinates":[-87.82364200000001,41.816099],"type":"Point"}
}