{
  "type": "Feature",
  "properties": {
    "iso:country":"US",
    "sg:address":"1277 Naperville Dr",
    "sg:city":"Romeoville",
    "sg:classifiers":[
        {
            "category":"Retail",
            "subcategory":"Laundry & Dry Cleaning",
            "type":"Services"
        }
    ],
    "sg:phone":"+1 630 771 1179",
    "sg:postcode":"60446",
    "sg:province":"IL",
    "sg:tags":[
        "cleaners",
        "rug",
        "carpet"
    ],
    "wof:name":"Stanley Steemer Carpet Cleaner",
    "wof:placetype":"venue"
},
  "geometry": {"coordinates":[-88.071469,41.664963],"type":"Point"}
}