{
  "type": "Feature",
  "properties": {
    "iso:country":"US",
    "sg:address":"6655 E Riverside Blvd",
    "sg:city":"Rockford",
    "sg:classifiers":[
        {
            "category":"Retail",
            "subcategory":"Auto Repair",
            "type":"Services"
        }
    ],
    "sg:phone":"+1 815 877 6666",
    "sg:postcode":"61114",
    "sg:province":"IL",
    "sg:tags":[
        "muffler",
        "exhaust",
        "system"
    ],
    "wof:name":"Mufflers 4 Less",
    "wof:placetype":"venue"
},
  "geometry": {"coordinates":[-88.986982,42.318671],"type":"Point"}
}