{
  "type": "Feature",
  "properties": {
    "addr:full":"222 S 4th St Aurora IL 60505",
    "addr:housenumber":"222",
    "addr:postcode":"60505",
    "addr:street":"S 4Th St",
    "iso:country":"US",
    "sg:address":"222 S 4th St",
    "sg:city":"Aurora",
    "sg:classifiers":[
        {
            "category":"Education",
            "subcategory":"Vocational School",
            "type":"Public Place"
        }
    ],
    "sg:phone":"+1 630 947 7429",
    "sg:postcode":"60505",
    "sg:province":"IL",
    "sg:tags":[
        "training",
        "computer"
    ],
    "wof:name":"JCT Svc",
    "wof:placetype":"venue"
},
  "geometry": {"coordinates":[-88.313419,41.750388],"type":"Point"}
}