{
  "type": "Feature",
  "properties": {
    "addr:full":"27088 N Mack Dr Wauconda IL 60084",
    "addr:housenumber":"27088",
    "addr:postcode":"60084",
    "addr:street":"N Mack Dr",
    "iso:country":"US",
    "sg:address":"27088 N Mack Dr",
    "sg:city":"Wauconda",
    "sg:classifiers":[
        {
            "category":"Building & Trades",
            "subcategory":"Plumbing",
            "type":"Services"
        }
    ],
    "sg:phone":"+1 847 526 9019",
    "sg:postcode":"60084",
    "sg:province":"IL",
    "sg:tags":[
        "contractor"
    ],
    "wof:name":"Sersen Contracting Co",
    "wof:placetype":"venue"
},
  "geometry": {"coordinates":[-88.164362,42.257334],"type":"Point"}
}