{
  "type": "Feature",
  "properties": {
    "addr:full":"1012 W Jefferson St Joliet IL 60435",
    "addr:housenumber":"1012",
    "addr:postcode":"60435",
    "addr:street":"W Jefferson St",
    "iso:country":"US",
    "sg:address":"1012 W Jefferson St",
    "sg:city":"Joliet",
    "sg:classifiers":[
        {
            "category":"Shopping",
            "type":"Retail Goods"
        }
    ],
    "sg:phone":"+1   ",
    "sg:postcode":"60435",
    "sg:province":"IL",
    "sg:tags":[
        "merchandise"
    ],
    "wof:name":"Pro Wireless Communication",
    "wof:placetype":"venue"
},
  "geometry": {"coordinates":[-88.107996,41.523113],"type":"Point"}
}