{
  "type": "Feature",
  "properties": {
    "iso:country":"US",
    "sg:address":"130 E Randolph Dr Ste 11",
    "sg:city":"Chicago",
    "sg:classifiers":[
        {
            "category":"Government",
            "subcategory":"City Hall",
            "type":"Public Place"
        },
        {
            "category":"Professional",
            "subcategory":"Lawyer & Legal Services",
            "type":"Services"
        }
    ],
    "sg:postcode":"60689",
    "sg:province":"IL",
    "sg:website":"www.iardc.org/index.html",
    "wof:name":"Illinois Attorney Registration and Disciplinary Commission",
    "wof:placetype":"venue"
},
  "geometry": {"coordinates":[-87.623572,41.88445],"type":"Point"}
}