{
  "type": "Feature",
  "properties": {
    "iso:country":"US",
    "sg:address":"5755 Forest Preserve Rd",
    "sg:city":"Rockton",
    "sg:classifiers":[
        {
            "category":"Building & Trades",
            "subcategory":"Construction",
            "type":"Services"
        }
    ],
    "sg:phone":"+1 815 629 2466",
    "sg:postcode":"61072",
    "sg:province":"IL",
    "sg:tags":[
        "painter"
    ],
    "wof:name":"Richard's Painting & Wallpaper",
    "wof:placetype":"venue"
},
  "geometry": {"coordinates":[-89.15310100000001,42.45966],"type":"Point"}
}