{
  "type": "Feature",
  "properties": {
    "addr:full":"2625 Ogden Ave Downers Grove IL 60515",
    "addr:housenumber":"2625",
    "addr:postcode":"60515",
    "addr:street":"Ogden Ave",
    "iso:country":"US",
    "sg:address":"2625 Ogden Ave",
    "sg:city":"Downers Grove",
    "sg:classifiers":[
        {
            "category":"Building & Trades",
            "subcategory":"Equipment Rental",
            "type":"Services"
        }
    ],
    "sg:phone":"+1 630 964 1850",
    "sg:postcode":"60515",
    "sg:province":"IL",
    "sg:tags":[
        "tool"
    ],
    "wof:name":"Rentalmax 5",
    "wof:placetype":"venue"
},
  "geometry": {"coordinates":[-88.04875199999999,41.804559],"type":"Point"}
}