{
  "type": "Feature",
  "properties": {
    "addr:full":"114 N Division Ave Polo IL 61064",
    "addr:housenumber":"114",
    "addr:postcode":"61064",
    "addr:street":"N Division Ave Polo",
    "iso:country":"US",
    "sg:address":"114 N Division Ave",
    "sg:city":"Polo",
    "sg:classifiers":[
        {
            "category":"Building & Trades",
            "subcategory":"Plumbing",
            "type":"Services"
        }
    ],
    "sg:phone":"+1 815 946 4050",
    "sg:postcode":"61064",
    "sg:province":"IL",
    "sg:tags":[
        "plumbing",
        "contractor"
    ],
    "wof:name":"Karrow Bob Plumbing & Heating",
    "wof:placetype":"venue"
},
  "geometry": {"coordinates":[-89.578739,41.986787],"type":"Point"}
}