{
  "type": "Feature",
  "properties": {
    "iso:country":"US",
    "sg:address":"1821 Edgebrook Dr",
    "sg:city":"Rockford",
    "sg:classifiers":[
        {
            "category":"Manufacturing",
            "subcategory":"Tools & Machinery",
            "type":"Manufacturing & Wholesale Goods"
        }
    ],
    "sg:phone":"+1 815 964 4913",
    "sg:postcode":"61107",
    "sg:province":"IL",
    "sg:tags":[
        "industrial",
        "mfg",
        "pattern",
        "accessory",
        "machine",
        "maker"
    ],
    "wof:name":"Acme Pattern Corporation",
    "wof:placetype":"venue"
},
  "geometry": {"coordinates":[-89.039969,42.286072],"type":"Point"}
}