{
  "type": "Feature",
  "properties": {
    "addr:full":"730 Lake St Oak Park IL 60301",
    "addr:housenumber":"730",
    "addr:postcode":"60301",
    "addr:street":"Lake St",
    "iso:country":"US",
    "sg:address":"730 Lake St",
    "sg:city":"Oak Park",
    "sg:classifiers":[
        {
            "category":"Shopping",
            "subcategory":"Gifts & Souvenirs",
            "type":"Retail Goods"
        }
    ],
    "sg:phone":"+1   ",
    "sg:postcode":"60301",
    "sg:province":"IL",
    "wof:name":"Kates Garden",
    "wof:placetype":"venue"
},
  "geometry": {"coordinates":[-87.79303299999999,41.888662],"type":"Point"}
}