{
  "type": "Feature",
  "properties": {
    "addr:full":"308 S Brush Ave Ladd IL 61329",
    "addr:housenumber":"308",
    "addr:postcode":"61329",
    "addr:street":"S Brush Ave",
    "iso:country":"US",
    "sg:address":"308 S Brush Ave",
    "sg:city":"Ladd",
    "sg:classifiers":[
        {
            "category":"Building & Trades",
            "subcategory":"Construction",
            "type":"Services"
        }
    ],
    "sg:phone":"+1 217 537 3133",
    "sg:postcode":"61329",
    "sg:province":"IL",
    "sg:tags":[
        "home",
        "improvement"
    ],
    "wof:name":"John's Home Repair",
    "wof:placetype":"venue"
},
  "geometry": {"coordinates":[-89.21070899999999,41.379663],"type":"Point"}
}