{
  "type": "Feature",
  "properties": {
    "iso:country":"US",
    "sg:address":"308 S Brush Ave",
    "sg:city":"Ladd",
    "sg:classifiers":[
        {
            "category":"Building & Trades",
            "subcategory":"Construction",
            "type":"Services"
        }
    ],
    "sg:phone":"+1 217 537 3133",
    "sg:postcode":"61329",
    "sg:province":"IL",
    "sg:tags":[
        "home",
        "improvement"
    ],
    "wof:name":"John's Home Repair",
    "wof:placetype":"venue"
},
  "geometry": {"coordinates":[-89.210709,41.379663],"type":"Point"}
}