{
  "type": "Feature",
  "properties": {
    "addr:full":"2201 W Cortez St Chicago IL 60622",
    "addr:housenumber":"2201",
    "addr:postcode":"60622",
    "addr:street":"W Cortez St",
    "iso:country":"US",
    "sg:address":"2201 W Cortez St",
    "sg:city":"Chicago",
    "sg:classifiers":[
        {
            "category":"Wholesale",
            "subcategory":"Machinery & Supplies",
            "type":"Manufacturing & Wholesale Goods"
        }
    ],
    "sg:phone":"+1 773 278 4206",
    "sg:postcode":"60622",
    "sg:province":"IL",
    "sg:tags":[
        "equipment",
        "irrigation",
        "system"
    ],
    "wof:name":"Masterimage",
    "wof:placetype":"venue"
},
  "geometry": {"coordinates":[-87.68206000000001,41.900379],"type":"Point"}
}