{
  "type": "Feature",
  "properties": {
    "addr:full":"7854 S South Shore Dr Chicago IL 60649",
    "addr:housenumber":"7854",
    "addr:postcode":"60649",
    "addr:street":"S South Shore Dr",
    "iso:country":"US",
    "sg:address":"7854 S South Shore Dr",
    "sg:city":"Chicago",
    "sg:classifiers":[
        {
            "category":"Banks & Credit Unions",
            "subcategory":"Financial Services",
            "type":"Services"
        }
    ],
    "sg:phone":"+1 773 221 0225",
    "sg:postcode":"60649",
    "sg:province":"IL",
    "sg:tags":[
        "trust",
        "investment",
        "real estate"
    ],
    "wof:name":"Rainbow Road Inc",
    "wof:placetype":"venue"
},
  "geometry": {"coordinates":[-87.548249,41.752026],"type":"Point"}
}