{
  "type": "Feature",
  "properties": {
    "addr:full":"117 Maple St Neponset IL 61345",
    "addr:housenumber":"117",
    "addr:postcode":"61345",
    "addr:street":"Maple St",
    "iso:country":"US",
    "sg:address":"117 Maple St",
    "sg:city":"Neponset",
    "sg:classifiers":[
        {
            "category":"Wholesale",
            "subcategory":"Machinery & Supplies",
            "type":"Manufacturing & Wholesale Goods"
        }
    ],
    "sg:phone":"+1 309 594 2543",
    "sg:postcode":"61345",
    "sg:province":"IL",
    "sg:tags":[
        "equipment",
        "industrial"
    ],
    "wof:name":"Industrial Enterprises",
    "wof:placetype":"venue"
},
  "geometry": {"coordinates":[-89.787387,41.296772],"type":"Point"}
}