{
  "type": "Feature",
  "properties": {
    "addr:full":"814 Stratford Sq Mall Bloomingdale IL 60108",
    "addr:housenumber":"814",
    "addr:postcode":"60108",
    "addr:street":"Stratford Sq Mall",
    "iso:country":"US",
    "sg:address":"814 Stratford Sq Mall",
    "sg:city":"Bloomingdale",
    "sg:classifiers":[
        {
            "category":"Shopping",
            "subcategory":"Hobbies, Toys, & Games",
            "type":"Retail Goods"
        }
    ],
    "sg:phone":"+1 630 980 4412",
    "sg:postcode":"60108",
    "sg:province":"IL",
    "sg:tags":[
        "shop",
        "hobby"
    ],
    "wof:name":"Gamers Paradise",
    "wof:placetype":"venue"
},
  "geometry": {"coordinates":[-88.115402,41.952301],"type":"Point"}
}