{
  "type": "Feature",
  "properties": {
    "iso:country":"US",
    "sg:address":"437 Anthony St",
    "sg:city":"Glen Ellyn",
    "sg:classifiers":[
        {
            "category":"Professional",
            "subcategory":"Lawyer & Legal Services",
            "type":"Services"
        }
    ],
    "sg:phone":"+1 630 790 0001",
    "sg:postcode":"60137",
    "sg:province":"IL",
    "wof:name":"Jeffrey R Diver PC",
    "wof:placetype":"venue"
},
  "geometry": {"coordinates":[-88.0705,41.87861],"type":"Point"}
}