{
  "type": "Feature",
  "properties": {
    "iso:country":"US",
    "sg:address":"915 W Main St",
    "sg:city":"Salem",
    "sg:classifiers":[
        {
            "category":"Health Services",
            "subcategory":"Doctor",
            "type":"Services"
        }
    ],
    "sg:phone":"+1 618 548 1100",
    "sg:postcode":"62881",
    "sg:province":"IL",
    "sg:tags":[
        "dentist"
    ],
    "wof:name":"Alan D Willis DDS Msd",
    "wof:placetype":"venue"
},
  "geometry": {"coordinates":[-88.95524399999999,38.626941],"type":"Point"}
}