{
  "type": "Feature",
  "properties": {
    "addr:full":"2000 E Cass St Joliet IL 60432",
    "addr:housenumber":"2000",
    "addr:postcode":"60432",
    "addr:street":"E Cass St",
    "iso:country":"US",
    "sg:address":"2000 E Cass St",
    "sg:city":"Joliet",
    "sg:classifiers":[
        {
            "category":"Building & Trades",
            "subcategory":"Construction",
            "type":"Services"
        }
    ],
    "sg:phone":"+1 815 722 1951",
    "sg:postcode":"60432",
    "sg:province":"IL",
    "sg:tags":[
        "excavating",
        "contractor",
        "local",
        "trucker"
    ],
    "wof:name":"Gould Excavating and Trucking",
    "wof:placetype":"venue"
},
  "geometry": {"coordinates":[-88.03510199999999,41.530404],"type":"Point"}
}