{
  "type": "Feature",
  "properties": {
    "iso:country":"US",
    "sg:address":"1100 W Lake St",
    "sg:city":"Chicago",
    "sg:classifiers":[
        {
            "category":"Organizations",
            "subcategory":"Professional Association",
            "type":"Services"
        }
    ],
    "sg:phone":"+1 312 337 2337",
    "sg:postcode":"60607",
    "sg:province":"IL",
    "sg:tags":[
        "sale"
    ],
    "wof:name":"River North Sales Svc",
    "wof:placetype":"venue"
},
  "geometry": {"coordinates":[-87.654472,41.885521],"type":"Point"}
}