{
  "type": "Feature",
  "properties": {
    "iso:country":"US",
    "sg:address":"1910 Lincoln Hwy",
    "sg:city":"Saint Charles",
    "sg:classifiers":[
        {
            "category":"Deli",
            "type":"Food & Drink"
        }
    ],
    "sg:menulink":"http://www.allmenus.com/il/st-charles/233473-browns-chicken--pasta/menu/",
    "sg:phone":"+1 630 584 2411",
    "sg:postcode":"60174",
    "sg:province":"IL",
    "sg:tags":[
        "american"
    ],
    "wof:name":"Brown's Chicken & Pasta",
    "wof:placetype":"venue"
},
  "geometry": {"coordinates":[-88.333848,41.899782],"type":"Point"}
}