{
  "type": "Feature",
  "properties": {
    "addr:full":"316 S Harlem Ave Peotone IL 60468",
    "addr:housenumber":"316",
    "addr:postcode":"60468",
    "addr:street":"S Harlem Ave",
    "iso:country":"US",
    "sg:address":"316 S Harlem Ave",
    "sg:city":"Peotone",
    "sg:classifiers":[
        {
            "category":"Retail",
            "subcategory":"Auto Repair",
            "type":"Services"
        }
    ],
    "sg:phone":"+1 708 258 9974",
    "sg:postcode":"60468",
    "sg:province":"IL",
    "sg:tags":[
        "repairing",
        "automobile"
    ],
    "wof:name":"Purdy Auto",
    "wof:placetype":"venue"
},
  "geometry": {"coordinates":[-87.785358,41.331022],"type":"Point"}
}