{
  "type": "Feature",
  "properties": {
    "iso:country":"US",
    "sg:address":"4730 W Irving Park Rd",
    "sg:city":"Chicago",
    "sg:classifiers":[
        {
            "category":"Retail",
            "subcategory":"Portrait Studio",
            "type":"Services"
        }
    ],
    "sg:phone":"+1 773 202 2379",
    "sg:postcode":"60641",
    "sg:province":"IL",
    "sg:tags":[
        "photo"
    ],
    "wof:name":"Sears Portrait Studio 872",
    "wof:placetype":"venue"
},
  "geometry": {"coordinates":[-87.74681,41.953506],"type":"Point"}
}