{
  "type": "Feature",
  "properties": {
    "addr:full":"21532 W Douglas Ct Plainfield IL 60544",
    "addr:housenumber":"21532",
    "addr:postcode":"60544",
    "addr:street":"W Douglas Ct",
    "iso:country":"US",
    "sg:address":"21532 W Douglas Ct",
    "sg:city":"Plainfield",
    "sg:classifiers":[
        {
            "category":"Manufacturing",
            "subcategory":"Tools & Machinery",
            "type":"Manufacturing & Wholesale Goods"
        }
    ],
    "sg:phone":"+1 815 293 1247",
    "sg:postcode":"60544",
    "sg:province":"IL",
    "wof:name":"M R Tool Inc",
    "wof:placetype":"venue"
},
  "geometry": {"coordinates":[-88.145974,41.638122],"type":"Point"}
}