{
  "type": "Feature",
  "properties": {
    "iso:country":"US",
    "sg:address":"925 W Randolph St",
    "sg:city":"Chicago",
    "sg:classifiers":[
        {
            "category":"Restaurant",
            "type":"Food & Drink"
        }
    ],
    "sg:phone":"+1 312 666 5833",
    "sg:postcode":"60607",
    "sg:province":"IL",
    "sg:tags":[
        "mexican"
    ],
    "wof:name":"Mexica Grill",
    "wof:placetype":"venue"
},
  "geometry": {"coordinates":[-87.65072600000001,41.884246],"type":"Point"}
}