{
  "type": "Feature",
  "properties": {
    "iso:country":"US",
    "sg:address":"107 W Main St",
    "sg:city":"Atkinson",
    "sg:classifiers":[
        {
            "category":"Government",
            "subcategory":"Police Station",
            "type":"Public Place"
        }
    ],
    "sg:phone":"+1 309 936 7600",
    "sg:postcode":"61235",
    "sg:province":"IL",
    "sg:tags":[
        "department"
    ],
    "wof:name":"Police Station",
    "wof:placetype":"venue"
},
  "geometry": {"coordinates":[-90.016875,41.421259],"type":"Point"}
}