{
  "type": "Feature",
  "properties": {
    "addr:full":"220 Gerry Dr Wood Dale IL 60191",
    "addr:housenumber":"220",
    "addr:postcode":"60191",
    "addr:street":"Gerry Dr",
    "iso:country":"US",
    "sg:address":"220 Gerry Dr",
    "sg:city":"Wood Dale",
    "sg:classifiers":[
        {
            "category":"Travel",
            "subcategory":"Travel Agent",
            "type":"Entertainment"
        }
    ],
    "sg:phone":"+1 630 766 7146",
    "sg:postcode":"60191",
    "sg:province":"IL",
    "sg:tags":[
        "agency"
    ],
    "wof:name":"Garbers Travel Agency",
    "wof:placetype":"venue"
},
  "geometry": {"coordinates":[-87.983436,41.978773],"type":"Point"}
}