{
  "type": "Feature",
  "properties": {
    "iso:country":"US",
    "sg:address":"207 N 1st St",
    "sg:city":"Rockford",
    "sg:classifiers":[
        {
            "category":"Professional",
            "subcategory":"Management & Consulting",
            "type":"Services"
        }
    ],
    "sg:phone":"+1 815 965 8920",
    "sg:postcode":"61107",
    "sg:province":"IL",
    "sg:tags":[
        "for",
        "owned",
        "specifically",
        "real estate"
    ],
    "wof:name":"Tlc Learning Center The",
    "wof:placetype":"venue"
},
  "geometry": {"coordinates":[-89.087163,42.270019],"type":"Point"}
}