{
  "type": "Feature",
  "properties": {
    "iso:country":"US",
    "sg:address":"2144 Ashland Ave",
    "sg:city":"Evanston",
    "sg:classifiers":[
        {
            "category":"Shopping",
            "subcategory":"Gifts & Souvenirs",
            "type":"Retail Goods"
        }
    ],
    "sg:phone":"+1   ",
    "sg:postcode":"60201",
    "sg:province":"IL",
    "wof:name":"Dream Spirits",
    "wof:placetype":"venue"
},
  "geometry": {"coordinates":[-87.69422900000001,42.057407],"type":"Point"}
}