{
  "type": "Feature",
  "properties": {
    "addr:full":"1457 N State Rte 2 Oregon IL 61061",
    "addr:housenumber":"1457",
    "addr:postcode":"61061",
    "addr:street":"N State Rte 2",
    "iso:country":"US",
    "sg:address":"1457 N State Rte 2",
    "sg:city":"Oregon",
    "sg:classifiers":[
        {
            "category":"Travel",
            "subcategory":"Hotels & Motels",
            "type":"Entertainment"
        }
    ],
    "sg:phone":"+1 815 732 4540",
    "sg:postcode":"61061",
    "sg:province":"IL",
    "wof:name":"Paddle Wheel Inn",
    "wof:placetype":"venue"
},
  "geometry": {"coordinates":[-89.340932,42.038157],"type":"Point"}
}