{
  "type": "Feature",
  "properties": {
    "addr:full":"608 State Rte 130 Greenup IL 62428",
    "addr:housenumber":"608",
    "addr:postcode":"62428",
    "addr:street":"State Rte 130",
    "iso:country":"US",
    "sg:address":"608 State Rte 130",
    "sg:city":"Greenup",
    "sg:classifiers":[
        {
            "category":"Farming",
            "subcategory":"Orchard",
            "type":"Manufacturing & Wholesale Goods"
        }
    ],
    "sg:phone":"+1 217 923 3736",
    "sg:postcode":"62428",
    "sg:province":"IL",
    "sg:tags":[
        "grove",
        "management",
        "fruit",
        "tree"
    ],
    "wof:name":"Grissom Lost Creek Orchard",
    "wof:placetype":"venue"
},
  "geometry": {"coordinates":[-88.150558,39.263718],"type":"Point"}
}