{
  "type": "Feature",
  "properties": {
    "addr:full":"10300 S Cicero Ave Oak Lawn IL 60453",
    "addr:housenumber":"10300",
    "addr:postcode":"60453",
    "addr:street":"S Cicero Ave",
    "iso:country":"US",
    "sg:address":"10300 S Cicero Ave",
    "sg:city":"Oak Lawn",
    "sg:classifiers":[
        {
            "category":"Building & Trades",
            "subcategory":"Plumbing",
            "type":"Services"
        }
    ],
    "sg:phone":"+1 708 444 1111",
    "sg:postcode":"60453",
    "sg:province":"IL",
    "sg:tags":[
        "heating",
        "contractor"
    ],
    "wof:name":"Four Seasons Heating & Air",
    "wof:placetype":"venue"
},
  "geometry": {"coordinates":[-87.74025399999999,41.705086],"type":"Point"}
}