{
  "type": "Feature",
  "properties": {
    "addr:full":"3256 N Pulaski Rd Chicago IL 60641",
    "addr:housenumber":"3256",
    "addr:postcode":"60641",
    "addr:street":"N Pulaski Rd",
    "iso:country":"US",
    "sg:address":"3256 N Pulaski Rd",
    "sg:city":"Chicago",
    "sg:classifiers":[
        {
            "category":"Professional",
            "subcategory":"Employment Agencies",
            "type":"Services"
        }
    ],
    "sg:phone":"+1 773 278 3424",
    "sg:postcode":"60641",
    "sg:province":"IL",
    "sg:tags":[
        "opportunity"
    ],
    "wof:name":"Eurocare",
    "wof:placetype":"venue"
},
  "geometry": {"coordinates":[-87.727301,41.94056],"type":"Point"}
}