{
  "type": "Feature",
  "properties": {
    "addr:full":"17183 Ashwood Ln Orland Park IL 60467",
    "addr:housenumber":"17183",
    "addr:postcode":"60467",
    "addr:street":"Ashwood Ln",
    "iso:country":"US",
    "sg:address":"17183 Ashwood Ln",
    "sg:city":"Orland Park",
    "sg:classifiers":[
        {
            "category":"Professional",
            "subcategory":"Business Services",
            "type":"Services"
        }
    ],
    "sg:phone":"+1 708 478 0339",
    "sg:postcode":"60467",
    "sg:province":"IL",
    "wof:name":"Gak Enterprises",
    "wof:placetype":"venue"
},
  "geometry": {"coordinates":[-87.899838,41.578368],"type":"Point"}
}