{
  "type": "Feature",
  "properties": {
    "iso:country":"US",
    "sg:address":"2031 Schuyler Dr",
    "sg:city":"Peru",
    "sg:classifiers":[
        {
            "category":"Social Services",
            "subcategory":"Child Care",
            "type":"Services"
        }
    ],
    "sg:phone":"+1 815 223 1155",
    "sg:postcode":"61354",
    "sg:province":"IL",
    "sg:tags":[
        "day"
    ],
    "wof:name":"Kiddie Kastle Day Care",
    "wof:placetype":"venue"
},
  "geometry": {"coordinates":[-89.131774,41.338677],"type":"Point"}
}