{
  "type": "Feature",
  "properties": {
    "iso:country":"US",
    "sg:address":"602 Allen St",
    "sg:city":"Crescent City",
    "sg:classifiers":[
        {
            "category":"Building & Trades",
            "subcategory":"Electrical",
            "type":"Services"
        }
    ],
    "sg:phone":"+1 815 683 2404",
    "sg:postcode":"60928",
    "sg:province":"IL",
    "sg:tags":[
        "electric",
        "contractor"
    ],
    "wof:name":"Bell Electric",
    "wof:placetype":"venue"
},
  "geometry": {"coordinates":[-87.854786,40.772076],"type":"Point"}
}