{
  "type": "Feature",
  "properties": {
    "addr:full":"507 E Church St Sparta IL 62286",
    "addr:housenumber":"507",
    "addr:postcode":"62286",
    "addr:street":"E Church St",
    "iso:country":"US",
    "sg:address":"507 E Church St",
    "sg:city":"Sparta",
    "sg:classifiers":[
        {
            "category":"Social Services",
            "subcategory":"Child Care",
            "type":"Services"
        }
    ],
    "sg:phone":"+1 618 443 2439",
    "sg:postcode":"62286",
    "sg:province":"IL",
    "sg:tags":[
        "nursery",
        "day"
    ],
    "wof:name":"Judy Schilling",
    "wof:placetype":"venue"
},
  "geometry": {"coordinates":[-89.69663300000001,38.127208],"type":"Point"}
}