{
  "type": "Feature",
  "properties": {
    "iso:country":"US",
    "sg:address":"2716 W 90th St",
    "sg:city":"Evergreen Park",
    "sg:classifiers":[
        {
            "category":"Retail",
            "subcategory":"Repair Shop",
            "type":"Services"
        }
    ],
    "sg:phone":"+1 708 423 3315",
    "sg:postcode":"60805",
    "sg:province":"IL",
    "sg:tags":[
        "television",
        "camera",
        "video"
    ],
    "wof:name":"Kirchner Video Repair Inc",
    "wof:placetype":"venue"
},
  "geometry": {"coordinates":[-87.691852,41.730027],"type":"Point"}
}