{
  "type": "Feature",
  "properties": {
    "addr:full":"2035 Arlington Heights Rd Arlington Heights IL 60005",
    "addr:housenumber":"2035",
    "addr:postcode":"60005",
    "addr:street":"Arlington Heights Rd",
    "iso:country":"US",
    "sg:address":"2035 Arlington Heights Rd",
    "sg:city":"Arlington Heights",
    "sg:classifiers":[
        {
            "category":"Home & Garden",
            "subcategory":"Furniture",
            "type":"Retail Goods"
        }
    ],
    "sg:phone":"+1   ",
    "sg:postcode":"60005",
    "sg:province":"IL",
    "wof:name":"Office Sekkei",
    "wof:placetype":"venue"
},
  "geometry": {"coordinates":[-87.982213,42.048522],"type":"Point"}
}