{
  "type": "Feature",
  "properties": {
    "iso:country":"US",
    "sg:address":"3501 Falling Springs Rd",
    "sg:city":"East Saint Louis",
    "sg:classifiers":[
        {
            "category":"Retail",
            "subcategory":"Auto Repair",
            "type":"Services"
        }
    ],
    "sg:phone":"+1 618 337 2407",
    "sg:postcode":"62206",
    "sg:province":"IL",
    "wof:name":"Alan's Automotive Repairs",
    "wof:placetype":"venue"
},
  "geometry": {"coordinates":[-90.172956,38.580397],"type":"Point"}
}