{
  "type": "Feature",
  "properties": {
    "addr:full":"47 Willow Cir Cary IL 60013",
    "addr:housenumber":"47",
    "addr:postcode":"60013",
    "addr:street":"Willow Cir",
    "iso:country":"US",
    "sg:address":"47 Willow Cir",
    "sg:city":"Cary",
    "sg:classifiers":[
        {
            "category":"Real Estate",
            "subcategory":"Real Estate Agent",
            "type":"Services"
        }
    ],
    "sg:phone":"+1 847 516 7011",
    "sg:postcode":"60013",
    "sg:province":"IL",
    "wof:name":"Eagle Appraisal Group Inc",
    "wof:placetype":"venue"
},
  "geometry": {"coordinates":[-88.253727,42.225742],"type":"Point"}
}