{
  "type": "Feature",
  "properties": {
    "iso:country":"US",
    "sg:address":"6501 Wells St",
    "sg:city":"Downers Grove",
    "sg:classifiers":[
        {
            "category":"Professional",
            "subcategory":"Management & Consulting",
            "type":"Services"
        }
    ],
    "sg:phone":"+1 630 353 0117",
    "sg:postcode":"60516",
    "sg:province":"IL",
    "sg:tags":[
        "business"
    ],
    "wof:name":"Rmg Consulting Inc",
    "wof:placetype":"venue"
},
  "geometry": {"coordinates":[-88.025266,41.768724],"type":"Point"}
}