{
  "type": "Feature",
  "properties": {
    "iso:country":"US",
    "sg:address":"36400 Essex Rd",
    "sg:city":"Wilmington",
    "sg:classifiers":[
        {
            "category":"Building & Trades",
            "subcategory":"Cleaning & Sanitation",
            "type":"Services"
        }
    ],
    "sg:phone":"+1 815 458 7550",
    "sg:postcode":"60481",
    "sg:province":"IL",
    "sg:tags":[
        "nuclear",
        "plant",
        "maintenance"
    ],
    "wof:name":"Newburg Perini Stone & Webster",
    "wof:placetype":"venue"
},
  "geometry": {"coordinates":[-88.187308,41.222168],"type":"Point"}
}