{
  "type": "Feature",
  "properties": {
    "addr:full":"2600 N Elston Ave Chicago IL 60647",
    "addr:housenumber":"2600",
    "addr:postcode":"60647",
    "addr:street":"N Elston Ave",
    "iso:country":"US",
    "sg:address":"2600 N Elston Ave",
    "sg:city":"Chicago",
    "sg:classifiers":[
        {
            "category":"Insurance",
            "subcategory":"Hazard Insurance",
            "type":"Services"
        }
    ],
    "sg:phone":"+1 312 822 7503",
    "sg:postcode":"60647",
    "sg:province":"IL",
    "wof:name":"Continental Casualty Company",
    "wof:placetype":"venue"
},
  "geometry": {"coordinates":[-87.682405,41.928489],"type":"Point"}
}