{
  "type": "Feature",
  "properties": {
    "addr:full":"203 SW 5th St Aledo IL 61231",
    "addr:housenumber":"203",
    "addr:postcode":"61231",
    "addr:street":"Sw 5Th St",
    "iso:country":"US",
    "sg:address":"203 SW 5th St",
    "sg:city":"Aledo",
    "sg:classifiers":[
        {
            "category":"Local Transit",
            "type":"Transportation"
        }
    ],
    "sg:phone":"+1 309 582 1154",
    "sg:postcode":"61231",
    "sg:province":"IL",
    "sg:tags":[
        "ambulance"
    ],
    "wof:name":"Advanced Medical Transport",
    "wof:placetype":"venue"
},
  "geometry": {"coordinates":[-90.751671,41.198266],"type":"Point"}
}