{
  "type": "Feature",
  "properties": {
    "addr:full":"3325 Bristol Rd Waukegan IL 60087",
    "addr:housenumber":"3325",
    "addr:postcode":"60087",
    "addr:street":"Bristol Rd",
    "iso:country":"US",
    "sg:address":"3325 Bristol Rd",
    "sg:city":"Waukegan",
    "sg:classifiers":[
        {
            "category":"Real Estate",
            "subcategory":"Real Estate Agent",
            "type":"Services"
        }
    ],
    "sg:phone":"+1 847 336 9123",
    "sg:postcode":"60087",
    "sg:province":"IL",
    "wof:name":"Z&K Properties Incorporat",
    "wof:placetype":"venue"
},
  "geometry": {"coordinates":[-87.85722699999999,42.411205],"type":"Point"}
}