{
  "type": "Feature",
  "properties": {
    "addr:full":"211 W Pickwick Rd Arlington Hts IL 60005",
    "addr:housenumber":"211",
    "addr:postcode":"60005",
    "addr:street":"W Pickwick Rd",
    "iso:country":"US",
    "sg:address":"211 W Pickwick Rd",
    "sg:city":"Arlington Hts",
    "sg:classifiers":[
        {
            "category":"Manufacturing",
            "subcategory":"Tools & Machinery",
            "type":"Manufacturing & Wholesale Goods"
        }
    ],
    "sg:phone":"+1 847 577 2863",
    "sg:postcode":"60005",
    "sg:province":"IL",
    "sg:tags":[
        "equipment",
        "system",
        "automation"
    ],
    "wof:name":"Epsilon Instruments Inc",
    "wof:placetype":"venue"
},
  "geometry": {"coordinates":[-87.984708,42.056059],"type":"Point"}
}