{
  "type": "Feature",
  "properties": {
    "iso:country":"US",
    "sg:address":"1000 Pleasant View Ave",
    "sg:city":"Kewanee",
    "sg:classifiers":[
        {
            "category":"Real Estate",
            "subcategory":"Developer",
            "type":"Services"
        }
    ],
    "sg:phone":"+1 309 853 4649",
    "sg:postcode":"61443",
    "sg:province":"IL",
    "sg:tags":[
        "cemetery"
    ],
    "wof:name":"Pleasant View Cementery",
    "wof:placetype":"venue"
},
  "geometry": {"coordinates":[-89.912276,41.243373],"type":"Point"}
}