{
  "type": "Feature",
  "properties": {
    "iso:country":"US",
    "sg:address":"21 W Jackson Blvd",
    "sg:city":"Chicago",
    "sg:classifiers":[
        {
            "category":"Restaurant",
            "type":"Food & Drink"
        },
        {
            "category":"Food & Beverages",
            "subcategory":"Bakery",
            "type":"Retail Goods"
        }
    ],
    "sg:phone":"+1 312 360 1409",
    "sg:postcode":"60604",
    "sg:province":"IL",
    "sg:tags":[
        "new",
        "american",
        "sandwich"
    ],
    "sg:website":"chicken-planet.com",
    "wof:name":"Chicken Planet",
    "wof:placetype":"venue"
},
  "geometry": {"coordinates":[-87.628426,41.877699],"type":"Point"}
}