{
  "type": "Feature",
  "properties": {
    "addr:full":"216 W Stephenson St Freeport IL 61032",
    "addr:housenumber":"216",
    "addr:postcode":"61032",
    "addr:street":"W Stephenson St",
    "iso:country":"US",
    "sg:address":"216 W Stephenson St",
    "sg:city":"Freeport",
    "sg:classifiers":[
        {
            "category":"Professional",
            "subcategory":"Lawyer & Legal Services",
            "type":"Services"
        }
    ],
    "sg:phone":"+1 815 233 0915",
    "sg:postcode":"61032",
    "sg:province":"IL",
    "wof:name":"Howard Prestwich",
    "wof:placetype":"venue"
},
  "geometry": {"coordinates":[-89.622123,42.297628],"type":"Point"}
}