{
  "type": "Feature",
  "properties": {
    "addr:full":"109 11th Ave Orion IL 61273",
    "addr:housenumber":"109",
    "addr:postcode":"61273",
    "addr:street":"11Th Ave",
    "iso:country":"US",
    "sg:address":"109 11th Ave",
    "sg:city":"Orion",
    "sg:classifiers":[
        {
            "category":"Retail",
            "subcategory":"Auto Repair",
            "type":"Services"
        }
    ],
    "sg:phone":"+1 309 526 3181",
    "sg:postcode":"61273",
    "sg:province":"IL",
    "sg:tags":[
        "body",
        "automobile",
        "painting"
    ],
    "wof:name":"Larson's Body Shop",
    "wof:placetype":"venue"
},
  "geometry": {"coordinates":[-90.38435200000001,41.353853],"type":"Point"}
}