{
  "type": "Feature",
  "properties": {
    "iso:country":"US",
    "sg:address":"201 Mccrosky Professional Park",
    "sg:city":"Columbia",
    "sg:classifiers":[
        {
            "category":"Retail",
            "subcategory":"Veterinary Services",
            "type":"Services"
        }
    ],
    "sg:phone":"+1 618 281 7161",
    "sg:postcode":"62236",
    "sg:province":"IL",
    "sg:tags":[
        "clinic",
        "hospital",
        "veterinarian",
        "specialty"
    ],
    "sg:website":"http://www.columbiaanimalhospital.com",
    "wof:name":"Columbia Animal Hospital",
    "wof:placetype":"venue"
},
  "geometry": {"coordinates":[-90.191895,38.437485],"type":"Point"}
}