{
  "type": "Feature",
  "properties": {
    "iso:country":"US",
    "sg:address":"353 Grand Ave",
    "sg:city":"Loves Park",
    "sg:classifiers":[
        {
            "category":"Building & Trades",
            "subcategory":"Plumbing",
            "type":"Services"
        }
    ],
    "sg:phone":"+1 815 639 1018",
    "sg:postcode":"61111",
    "sg:province":"IL",
    "sg:tags":[
        "conditioning",
        "air",
        "system",
        "contractor"
    ],
    "wof:name":"Precision Heating & AC",
    "wof:placetype":"venue"
},
  "geometry": {"coordinates":[-89.05797200000001,42.312234],"type":"Point"}
}