{
  "type": "Feature",
  "properties": {
    "iso:country":"US",
    "sg:address":"1408 Joliet Rd",
    "sg:city":"Romeoville",
    "sg:classifiers":[
        {
            "category":"Government",
            "subcategory":"Office",
            "type":"Public Place"
        }
    ],
    "sg:phone":"+1   ",
    "sg:postcode":"60446",
    "sg:province":"IL",
    "sg:tags":[
        "executive"
    ],
    "wof:name":"Brent Hassert State Rprsnttive",
    "wof:placetype":"venue"
},
  "geometry": {"coordinates":[-88.055357,41.677235],"type":"Point"}
}