{
  "type": "Feature",
  "properties": {
    "addr:full":"841 Hillandale Dr Antioch IL 60002",
    "addr:housenumber":"841",
    "addr:postcode":"60002",
    "addr:street":"Hillandale Dr",
    "iso:country":"US",
    "sg:address":"841 Hillandale Dr",
    "sg:city":"Antioch",
    "sg:classifiers":[
        {
            "category":"Manufacturing",
            "subcategory":"Printing",
            "type":"Manufacturing & Wholesale Goods"
        }
    ],
    "sg:phone":"+1 847 395 8937",
    "sg:postcode":"60002",
    "sg:province":"IL",
    "sg:tags":[
        "commercial"
    ],
    "wof:name":"Pratte Publications",
    "wof:placetype":"venue"
},
  "geometry": {"coordinates":[-88.106022,42.479154],"type":"Point"}
}