{
  "type": "Feature",
  "properties": {
    "iso:country":"US",
    "sg:address":"3519 N Hermitage Ave",
    "sg:city":"Chicago",
    "sg:classifiers":[
        {
            "category":"Professional",
            "subcategory":"Management & Consulting",
            "type":"Services"
        }
    ],
    "sg:phone":"+1 773 472 1110",
    "sg:postcode":"60657",
    "sg:province":"IL",
    "wof:name":"Good Management",
    "wof:placetype":"venue"
},
  "geometry": {"coordinates":[-87.672426,41.94613],"type":"Point"}
}