{
  "type": "Feature",
  "properties": {
    "iso:country":"US",
    "sg:address":"13235 Windward Trl",
    "sg:city":"Orland Park",
    "sg:classifiers":[
        {
            "category":"Wholesale",
            "subcategory":"Stationery",
            "type":"Manufacturing & Wholesale Goods"
        }
    ],
    "sg:phone":"+1 708 671 0828",
    "sg:postcode":"60462",
    "sg:province":"IL",
    "sg:tags":[
        "business",
        "full",
        "sales",
        "form"
    ],
    "wof:name":"Assistance Graphics",
    "wof:placetype":"venue"
},
  "geometry": {"coordinates":[-87.824261,41.64999],"type":"Point"}
}