{
  "type": "Feature",
  "properties": {
    "addr:full":"109 W Sibley Blvd South Holland IL 60473",
    "addr:housenumber":"109",
    "addr:postcode":"60473",
    "addr:street":"W Sibley Blvd",
    "iso:country":"US",
    "sg:address":"109 W Sibley Blvd",
    "sg:city":"South Holland",
    "sg:classifiers":[
        {
            "category":"Personal",
            "subcategory":"Nail Salon",
            "type":"Services"
        }
    ],
    "sg:phone":"+1 708 596 8330",
    "sg:postcode":"60473",
    "sg:province":"IL",
    "wof:name":"Eagle Nails",
    "wof:placetype":"venue"
},
  "geometry": {"coordinates":[-87.62339799999999,41.622501],"type":"Point"}
}