{
  "type": "Feature",
  "properties": {
    "addr:full":"9801 W Higgins Rd Rosemont IL 60018",
    "addr:housenumber":"9801",
    "addr:postcode":"60018",
    "addr:street":"W Higgins Rd",
    "iso:country":"US",
    "sg:address":"9801 W Higgins Rd",
    "sg:city":"Rosemont",
    "sg:classifiers":[
        {
            "category":"Manufacturing",
            "subcategory":"Toys & Sporting Goods",
            "type":"Manufacturing & Wholesale Goods"
        }
    ],
    "sg:phone":"+1 847 292 1472",
    "sg:postcode":"60018",
    "sg:province":"IL",
    "sg:tags":[
        "goods-wholesale",
        "manufacturer"
    ],
    "sg:website":"http://www.riddellsports.com",
    "wof:name":"Riddell Sports",
    "wof:placetype":"venue"
},
  "geometry": {"coordinates":[-87.870482,41.994541],"type":"Point"}
}