{
  "type": "Feature",
  "properties": {
    "iso:country":"US",
    "sg:address":"1131 2nd Ave",
    "sg:city":"Rockford",
    "sg:classifiers":[
        {
            "category":"Home & Garden",
            "subcategory":"Hardware",
            "type":"Retail Goods"
        }
    ],
    "sg:phone":"+1 815 963 4821",
    "sg:postcode":"61104",
    "sg:province":"IL",
    "sg:website":"http://www.nicholsonhardware.com",
    "wof:name":"Nicholson Hardware",
    "wof:placetype":"venue"
},
  "geometry": {"coordinates":[-89.080201,42.264773],"type":"Point"}
}