{
  "type": "Feature",
  "properties": {
    "addr:full":"4341 Golf Rd Skokie IL 60076",
    "addr:housenumber":"4341",
    "addr:postcode":"60076",
    "addr:street":"Golf Rd",
    "iso:country":"US",
    "sg:address":"4341 Golf Rd",
    "sg:city":"Skokie",
    "sg:classifiers":[
        {
            "category":"Organizations",
            "subcategory":"Religious Organization",
            "type":"Services"
        }
    ],
    "sg:phone":"+1 847 679 9800",
    "sg:postcode":"60076",
    "sg:province":"IL",
    "wof:name":"Casmiro",
    "wof:placetype":"venue"
},
  "geometry": {"coordinates":[-87.737008,42.055175],"type":"Point"}
}