{
  "type": "Feature",
  "properties": {
    "iso:country":"US",
    "sg:address":"915 Sard Ave",
    "sg:city":"Aurora",
    "sg:classifiers":[
        {
            "category":"Education",
            "subcategory":"School",
            "type":"Public Place"
        }
    ],
    "sg:phone":"+1 630 892 1283",
    "sg:postcode":"60506",
    "sg:province":"IL",
    "wof:name":"St Peter's School",
    "wof:placetype":"venue"
},
  "geometry": {"coordinates":[-88.333278,41.741689],"type":"Point"}
}