{
  "type": "Feature",
  "properties": {
    "iso:country":"US",
    "sg:address":"310 46th Ave",
    "sg:city":"East Moline",
    "sg:classifiers":[
        {
            "category":"Health Services",
            "subcategory":"Doctor",
            "type":"Services"
        }
    ],
    "sg:phone":"+1 309 792 2815",
    "sg:postcode":"61244",
    "sg:province":"IL",
    "sg:tags":[
        "surgeon",
        "oral"
    ],
    "wof:name":"Hanlin Brent DDS",
    "wof:placetype":"venue"
},
  "geometry": {"coordinates":[-90.451599,41.4814],"type":"Point"}
}