{
  "type": "Feature",
  "properties": {
    "iso:country":"US",
    "sg:address":"115 Ash St",
    "sg:city":"Frankfort",
    "sg:classifiers":[
        {
            "category":"Building & Trades",
            "subcategory":"Construction",
            "type":"Services"
        }
    ],
    "sg:phone":"+1 815 469 9361",
    "sg:postcode":"60423",
    "sg:province":"IL",
    "sg:tags":[
        "general",
        "contractor"
    ],
    "wof:name":"RSM Builders Inc",
    "wof:placetype":"venue"
},
  "geometry": {"coordinates":[-87.849839,41.497249],"type":"Point"}
}