{
  "type": "Feature",
  "properties": {
    "iso:country":"US",
    "sg:address":"10232 S Kenton Ave",
    "sg:city":"Oak Lawn",
    "sg:classifiers":[
        {
            "category":"Shopping",
            "type":"Retail Goods"
        }
    ],
    "sg:phone":"+1 708 952 4865",
    "sg:postcode":"60453",
    "sg:province":"IL",
    "sg:tags":[
        "equipment",
        "telephone",
        "supply"
    ],
    "wof:name":"Chicago Cardinal Communication",
    "wof:placetype":"venue"
},
  "geometry": {"coordinates":[-87.735471,41.705734],"type":"Point"}
}