{
  "type": "Feature",
  "properties": {
    "iso:country":"US",
    "sg:address":"1321 N 7th St",
    "sg:city":"Rochelle",
    "sg:classifiers":[
        {
            "category":"Social Services",
            "type":"Services"
        }
    ],
    "sg:phone":"+1 815 562 3801",
    "sg:postcode":"61068",
    "sg:province":"IL",
    "sg:tags":[
        "counselor",
        "marriage",
        "family"
    ],
    "wof:name":"Sinnissippi Centers Inc",
    "wof:placetype":"venue"
},
  "geometry": {"coordinates":[-89.068017,41.939187],"type":"Point"}
}