{
  "type": "Feature",
  "properties": {
    "addr:full":"3407 N Halsted St Chicago IL 60657",
    "addr:housenumber":"3407",
    "addr:postcode":"60657",
    "addr:street":"N Halsted St",
    "iso:country":"US",
    "sg:address":"3407 N Halsted St",
    "sg:city":"Chicago",
    "sg:classifiers":[
        {
            "category":"Building & Trades",
            "subcategory":"Locksmith",
            "type":"Services"
        }
    ],
    "sg:phone":"+1 773 799 9293",
    "sg:postcode":"60657",
    "sg:province":"IL",
    "sg:tags":[
        "key"
    ],
    "wof:name":"Twenty Four Hours Seven Days A Week Locksmith and Locks",
    "wof:placetype":"venue"
},
  "geometry": {"coordinates":[-87.64919,41.944259],"type":"Point"}
}