{
  "type": "Feature",
  "properties": {
    "addr:full":"852 S 17th Ave Maywood IL 60153",
    "addr:housenumber":"852",
    "addr:postcode":"60153",
    "addr:street":"S 17Th Ave",
    "iso:country":"US",
    "sg:address":"852 S 17th Ave",
    "sg:city":"Maywood",
    "sg:classifiers":[
        {
            "category":"Restaurant",
            "type":"Food & Drink"
        }
    ],
    "sg:phone":"+1   ",
    "sg:postcode":"60153",
    "sg:province":"IL",
    "sg:tags":[
        "eating"
    ],
    "wof:name":"Golden Bowl",
    "wof:placetype":"venue"
},
  "geometry": {"coordinates":[-87.853904,41.879912],"type":"Point"}
}