{
  "type": "Feature",
  "properties": {
    "addr:full":"2032 E Mulberry Ln Arlington Heights IL 60004",
    "addr:housenumber":"2032",
    "addr:postcode":"60004",
    "addr:street":"E Mulberry Ln",
    "iso:country":"US",
    "sg:address":"2032 E Mulberry Ln",
    "sg:city":"Arlington Heights",
    "sg:classifiers":[
        {
            "category":"Professional",
            "subcategory":"Accounting & Tax Preparation",
            "type":"Services"
        }
    ],
    "sg:phone":"+1 847 577 6760",
    "sg:postcode":"60004",
    "sg:province":"IL",
    "wof:name":"Skowronski & Skowronski PC",
    "wof:placetype":"venue"
},
  "geometry": {"coordinates":[-87.958786,42.112241],"type":"Point"}
}