{
  "type": "Feature",
  "properties": {
    "addr:full":"261 S Hamilton St Sullivan IL 61951",
    "addr:housenumber":"261",
    "addr:postcode":"61951",
    "addr:street":"S Hamilton St",
    "iso:country":"US",
    "sg:address":"261 S Hamilton St",
    "sg:city":"Sullivan",
    "sg:classifiers":[
        {
            "category":"Restaurant",
            "type":"Food & Drink"
        }
    ],
    "sg:menulink":"http://www.allmenus.com/il/sullivan/79801-pizza-hut/menu/",
    "sg:phone":"+1 217 728 8359",
    "sg:postcode":"61951",
    "sg:province":"IL",
    "sg:tags":[
        "american",
        "pizza"
    ],
    "wof:name":"Pizza Hut",
    "wof:placetype":"venue"
},
  "geometry": {"coordinates":[-88.609326,39.597098],"type":"Point"}
}