{
  "type": "Feature",
  "properties": {
    "iso:country":"US",
    "sg:address":"8511 S Harlem Ave",
    "sg:city":"Burbank",
    "sg:classifiers":[
        {
            "category":"Insurance",
            "subcategory":"Insurance Agent",
            "type":"Services"
        }
    ],
    "sg:phone":"+1 708 735 4688",
    "sg:postcode":"60455",
    "sg:province":"IL",
    "wof:name":"Gott Insurance",
    "wof:placetype":"venue"
},
  "geometry": {"coordinates":[-87.799128,41.735428],"type":"Point"}
}