{
  "type": "Feature",
  "properties": {
    "iso:country":"US",
    "sg:address":"105 N 7th St",
    "sg:city":"Wyoming",
    "sg:classifiers":[
        {
            "category":"Shopping",
            "subcategory":"Pharmacy",
            "type":"Retail Goods"
        }
    ],
    "sg:phone":"+1 309 695 3881",
    "sg:postcode":"61491",
    "sg:province":"IL",
    "wof:name":"Johnson's Drug Store",
    "wof:placetype":"venue"
},
  "geometry": {"coordinates":[-89.773075,41.062458],"type":"Point"}
}