{
  "type": "Feature",
  "properties": {
    "iso:country":"US",
    "sg:address":"607 Orchard St",
    "sg:city":"West Frankfort",
    "sg:classifiers":[
        {
            "category":"Building & Trades",
            "subcategory":"Landscaping Services",
            "type":"Services"
        }
    ],
    "sg:phone":"+1 618 937 2801",
    "sg:postcode":"62896",
    "sg:province":"IL",
    "sg:tags":[
        "tree"
    ],
    "wof:name":"Dan Payne Tree & Stump Removal",
    "wof:placetype":"venue"
},
  "geometry": {"coordinates":[-88.927388,37.904256],"type":"Point"}
}