{
  "type": "Feature",
  "properties": {
    "addr:full":"350 N Co Rd 1675E Hindsboro IL 61930",
    "addr:housenumber":"350",
    "addr:postcode":"61930",
    "addr:street":"N Co Rd",
    "iso:country":"US",
    "sg:address":"350 N Co Rd 1675E",
    "sg:city":"Hindsboro",
    "sg:phone":"+1 217 346 2778",
    "sg:postcode":"61930",
    "sg:province":"IL",
    "sg:tags":[
        "farm",
        "corn",
        "soybean"
    ],
    "wof:name":"Richard Weller",
    "wof:placetype":"venue"
},
  "geometry": {"coordinates":[-88.158306,39.708948],"type":"Point"}
}