{
  "type": "Feature",
  "properties": {
    "iso:country":"US",
    "sg:address":"350 N Co Rd 1675E",
    "sg:city":"Hindsboro",
    "sg:phone":"+1 217 346 2778",
    "sg:postcode":"61930",
    "sg:province":"IL",
    "sg:tags":[
        "farm",
        "corn",
        "soybean"
    ],
    "wof:name":"Richard Weller",
    "wof:placetype":"venue"
},
  "geometry": {"coordinates":[-88.158306,39.708948],"type":"Point"}
}