{
  "type": "Feature",
  "properties": {
    "addr:full":"9220 Ogden Ave Brookfield IL 60513",
    "addr:housenumber":"9220",
    "addr:postcode":"60513",
    "addr:street":"Ogden Ave",
    "iso:country":"US",
    "sg:address":"9220 Ogden Ave",
    "sg:city":"Brookfield",
    "sg:classifiers":[
        {
            "category":"Shopping",
            "subcategory":"Hobbies, Toys, & Games",
            "type":"Retail Goods"
        },
        {
            "category":"Recreation",
            "subcategory":"Gun Range",
            "type":"Entertainment"
        }
    ],
    "sg:phone":"+1 708 485 4080",
    "sg:postcode":"60513",
    "sg:province":"IL",
    "sg:tags":[
        "safety",
        "instruction",
        "marksmanship",
        "gunsmith"
    ],
    "wof:name":"Friendship Trade Co",
    "wof:placetype":"venue"
},
  "geometry": {"coordinates":[-87.852577,41.817009],"type":"Point"}
}