{
  "type": "Feature",
  "properties": {
    "iso:country":"US",
    "sg:address":"3239 W 108th St",
    "sg:city":"Chicago",
    "sg:classifiers":[
        {
            "category":"Arena",
            "subcategory":"Sports Club",
            "type":"Entertainment"
        }
    ],
    "sg:phone":"+1 773 779 5167",
    "sg:postcode":"60655",
    "sg:province":"IL",
    "wof:name":"Marian Catholic Basketball",
    "wof:placetype":"venue"
},
  "geometry": {"coordinates":[-87.701328,41.696966],"type":"Point"}
}