{
  "type": "Feature",
  "properties": {
    "iso:country":"US",
    "sg:address":"1104 Longhi Rd",
    "sg:city":"Collinsville",
    "sg:classifiers":[
        {
            "category":"Mining & Drilling",
            "type":"Manufacturing & Wholesale Goods"
        }
    ],
    "sg:phone":"+1 618 667 3320",
    "sg:postcode":"62234",
    "sg:province":"IL",
    "sg:tags":[
        "oil",
        "gas",
        "producer"
    ],
    "wof:name":"Van Fossan Oil Corp",
    "wof:placetype":"venue"
},
  "geometry": {"coordinates":[-89.923742,38.698386],"type":"Point"}
}