{
  "type": "Feature",
  "properties": {
    "iso:country":"US",
    "sg:address":"14950 Laramie Ave",
    "sg:city":"Oak Forest",
    "sg:classifiers":[
        {
            "category":"Education",
            "subcategory":"School",
            "type":"Public Place"
        }
    ],
    "sg:phone":"+1 708 687 3334",
    "sg:postcode":"60452",
    "sg:province":"IL",
    "sg:tags":[
        "high",
        "middle",
        "elementary"
    ],
    "wof:name":"Schools Public",
    "wof:placetype":"venue"
},
  "geometry": {"coordinates":[-87.746972,41.620374],"type":"Point"}
}