{
  "type": "Feature",
  "properties": {
    "addr:full":"1005 S Locust St Centralia IL 62801",
    "addr:housenumber":"1005",
    "addr:postcode":"62801",
    "addr:street":"S Locust St",
    "iso:country":"US",
    "sg:address":"1005 S Locust St",
    "sg:city":"Centralia",
    "sg:classifiers":[
        {
            "category":"Shopping",
            "subcategory":"Used Merchandise",
            "type":"Retail Goods"
        }
    ],
    "sg:phone":"+1   ",
    "sg:postcode":"62801",
    "sg:province":"IL",
    "wof:name":"Second Time Around",
    "wof:placetype":"venue"
},
  "geometry": {"coordinates":[-89.137085,38.516898],"type":"Point"}
}