{
  "type": "Feature",
  "properties": {
    "iso:country":"US",
    "sg:address":"29406 Orange Tree Rd",
    "sg:city":"Richview",
    "sg:classifiers":[
        {
            "category":"Farming",
            "subcategory":"Farm",
            "type":"Manufacturing & Wholesale Goods"
        }
    ],
    "sg:phone":"+1 618 249 8512",
    "sg:postcode":"62877",
    "sg:province":"IL",
    "wof:name":"Wacker & Hanke Farms",
    "wof:placetype":"venue"
},
  "geometry": {"coordinates":[-89.15310700000001,38.398111],"type":"Point"}
}