{
  "type": "Feature",
  "properties": {
    "addr:full":"8707 Skokie Blvd Skokie IL 60077",
    "addr:housenumber":"8707",
    "addr:postcode":"60077",
    "addr:street":"Skokie Blvd",
    "iso:country":"US",
    "sg:address":"8707 Skokie Blvd",
    "sg:city":"Skokie",
    "sg:classifiers":[
        {
            "category":"Organizations",
            "subcategory":"Political Organization",
            "type":"Services"
        }
    ],
    "sg:phone":"+1 847 675 1677",
    "sg:postcode":"60077",
    "sg:province":"IL",
    "wof:name":"Habonim Labor Zionist Youth",
    "wof:placetype":"venue"
},
  "geometry": {"coordinates":[-87.747041,42.039621],"type":"Point"}
}