{
  "type": "Feature",
  "properties": {
    "addr:full":"110 Royce Rd Bolingbrook IL 60440",
    "addr:housenumber":"110",
    "addr:postcode":"60440",
    "addr:street":"Royce Rd",
    "iso:country":"US",
    "sg:address":"110 Royce Rd",
    "sg:city":"Bolingbrook",
    "sg:classifiers":[
        {
            "category":"Freight",
            "type":"Transportation"
        }
    ],
    "sg:phone":"+1 630 759 4450",
    "sg:postcode":"60440",
    "sg:province":"IL",
    "sg:tags":[
        "trucking"
    ],
    "wof:name":"E D Siebert Trucking Svc Inc",
    "wof:placetype":"venue"
},
  "geometry": {"coordinates":[-88.069807,41.717842],"type":"Point"}
}