{
  "type": "Feature",
  "properties": {
    "addr:full":"2601 North Ave Metropolis IL 62960",
    "addr:housenumber":"2601",
    "addr:postcode":"62960",
    "addr:street":"North Ave",
    "iso:country":"US",
    "sg:address":"2601 North Ave",
    "sg:city":"Metropolis",
    "sg:classifiers":[
        {
            "category":"Place Of Worship",
            "subcategory":"Church",
            "type":"Public Place"
        },
        {
            "category":"Place Of Worship",
            "type":"Public Place"
        }
    ],
    "sg:phone":"+1 618 524 4628",
    "sg:postcode":"62960",
    "sg:province":"IL",
    "sg:tags":[
        "lutheran",
        "america",
        "churches-lutheran",
        "churches-lutheran-evangelical"
    ],
    "wof:name":"Evanglical Lutheran Ch Ofcross",
    "wof:placetype":"venue"
},
  "geometry": {"coordinates":[-88.729218,37.170987],"type":"Point"}
}