{
  "type": "Feature",
  "properties": {
    "addr:full":"246 E Deerpath Rd Lake Forest IL 60045",
    "addr:housenumber":"246",
    "addr:postcode":"60045",
    "addr:street":"E Deerpath Rd",
    "iso:country":"US",
    "sg:address":"246 E Deerpath Rd",
    "sg:city":"Lake Forest",
    "sg:classifiers":[
        {
            "category":"Health Services",
            "subcategory":"Health Practitioner",
            "type":"Services"
        }
    ],
    "sg:phone":"+1 847 234 8490",
    "sg:postcode":"60045",
    "sg:province":"IL",
    "sg:tags":[
        "therapist",
        "physical"
    ],
    "wof:name":"Body Evolve Pilates & Physical",
    "wof:placetype":"venue"
},
  "geometry": {"coordinates":[-87.841199,42.251172],"type":"Point"}
}