{
  "type": "Feature",
  "properties": {
    "iso:country":"US",
    "sg:address":"430 N Damen Avenue",
    "sg:city":"Chicago",
    "sg:classifiers":[
        {
            "category":"Home & Garden",
            "subcategory":"Building Materials",
            "type":"Retail Goods"
        },
        {
            "category":"Building & Trades",
            "subcategory":"Construction",
            "type":"Services"
        }
    ],
    "sg:phone":"+1 312 733 6600",
    "sg:postcode":"60622",
    "sg:province":"IL",
    "sg:tags":[
        "contractor",
        "supply"
    ],
    "wof:name":"Zechman Supply",
    "wof:placetype":"venue"
},
  "geometry": {"coordinates":[-87.676698,41.889346],"type":"Point"}
}