{
  "type": "Feature",
  "properties": {
    "addr:full":"257 Cardinal Dr Bloomingdale IL 60108",
    "addr:housenumber":"257",
    "addr:postcode":"60108",
    "addr:street":"Cardinal Dr",
    "iso:country":"US",
    "sg:address":"257 Cardinal Dr",
    "sg:city":"Bloomingdale",
    "sg:classifiers":[
        {
            "category":"Building & Trades",
            "subcategory":"Landscaping Services",
            "type":"Services"
        }
    ],
    "sg:phone":"+1 847 451 1591",
    "sg:postcode":"60108",
    "sg:province":"IL",
    "sg:website":"www.rossandjacks.com",
    "wof:name":"Ross & Jacks Landscaping Inc",
    "wof:placetype":"venue"
},
  "geometry": {"coordinates":[-88.0942,41.945202],"type":"Point"}
}