{
  "type": "Feature",
  "properties": {
    "iso:country":"US",
    "sg:address":"22619 N Riverwoods Rd",
    "sg:city":"Lincolnshire",
    "sg:classifiers":[
        {
            "category":"Real Estate",
            "subcategory":"Real Estate Agent",
            "type":"Services"
        }
    ],
    "sg:phone":"+1 847 405 0449",
    "sg:postcode":"60069",
    "sg:province":"IL",
    "wof:name":"Illinois Best Investment LTD",
    "wof:placetype":"venue"
},
  "geometry": {"coordinates":[-87.906059,42.200506],"type":"Point"}
}