{
  "type": "Feature",
  "properties": {
    "iso:country":"US",
    "sg:address":"8916 Ogden Ave",
    "sg:city":"Brookfield",
    "sg:classifiers":[
        {
            "category":"Manufacturing",
            "subcategory":"Printing",
            "type":"Manufacturing & Wholesale Goods"
        }
    ],
    "sg:phone":"+1 708 387 0111",
    "sg:postcode":"60513",
    "sg:province":"IL",
    "sg:tags":[
        "multimedia"
    ],
    "wof:name":"E Z Media",
    "wof:placetype":"venue"
},
  "geometry": {"coordinates":[-87.844498,41.816687],"type":"Point"}
}