{
  "type": "Feature",
  "properties": {
    "iso:country":"US",
    "sg:address":"4722 S Ashland Ave",
    "sg:city":"Chicago",
    "sg:classifiers":[
        {
            "category":"Shopping",
            "subcategory":"Clothing, Apparel, & Fashions",
            "type":"Retail Goods"
        }
    ],
    "sg:phone":"+1 773 847 0757",
    "sg:postcode":"60609",
    "sg:province":"IL",
    "sg:tags":[
        "accessory",
        "clothing",
        "women's"
    ],
    "wof:name":"Street Life",
    "wof:placetype":"venue"
},
  "geometry": {"coordinates":[-87.665001,41.808201],"type":"Point"}
}