{
  "type": "Feature",
  "properties": {
    "iso:country":"US",
    "sg:address":"354 W Maple St",
    "sg:city":"New Lenox",
    "sg:classifiers":[
        {
            "category":"Shopping",
            "subcategory":"Florist",
            "type":"Retail Goods"
        }
    ],
    "sg:phone":"+1 815 485 8250",
    "sg:postcode":"60451",
    "sg:province":"IL",
    "wof:name":"A Country Florist",
    "wof:placetype":"venue"
},
  "geometry": {"coordinates":[-87.97360500000001,41.515557],"type":"Point"}
}