{
  "type": "Feature",
  "properties": {
    "iso:country":"US",
    "sg:address":"117 N Main St",
    "sg:city":"Wheaton",
    "sg:classifiers":[
        {
            "category":"Personal",
            "subcategory":"Nail Salon",
            "type":"Services"
        }
    ],
    "sg:phone":"+1 630 790 5007",
    "sg:postcode":"60187",
    "sg:province":"IL",
    "wof:name":"Ivy Nails & Massage",
    "wof:placetype":"venue"
},
  "geometry": {"coordinates":[-88.106656,41.865052],"type":"Point"}
}