{
  "type": "Feature",
  "properties": {
    "iso:country":"US",
    "sg:address":"248 N Montclair Ave",
    "sg:city":"Glen Ellyn",
    "sg:classifiers":[
        {
            "category":"Professional",
            "subcategory":"Business Services",
            "type":"Services"
        }
    ],
    "sg:phone":"+1 630 858 0207",
    "sg:postcode":"60137",
    "sg:province":"IL",
    "wof:name":"Leila Schumann Designs",
    "wof:placetype":"venue"
},
  "geometry": {"coordinates":[-88.058099,41.868776],"type":"Point"}
}