{
  "type": "Feature",
  "properties": {
    "iso:country":"US",
    "sg:address":"4710 W 95th St",
    "sg:city":"Oak Lawn",
    "sg:classifiers":[
        {
            "category":"Freight",
            "type":"Transportation"
        },
        {
            "category":"Professional",
            "subcategory":"Printing & Photocopies",
            "type":"Services"
        }
    ],
    "sg:phone":"+1 708 425 1309",
    "sg:postcode":"60453",
    "sg:province":"IL",
    "sg:tags":[
        "shipping"
    ],
    "sg:website":"www.fedex.com/us/office/",
    "wof:name":"Signs & Graphics By FedEx Office",
    "wof:placetype":"venue"
},
  "geometry": {"coordinates":[-87.73853800000001,41.720719],"type":"Point"}
}