{
  "type": "Feature",
  "properties": {
    "addr:full":"2117 63rd St Downers Grove IL 60516",
    "addr:housenumber":"2117",
    "addr:postcode":"60516",
    "addr:street":"63Rd St",
    "iso:country":"US",
    "sg:address":"2117 63rd St",
    "sg:city":"Downers Grove",
    "sg:classifiers":[
        {
            "category":"Restaurant",
            "type":"Food & Drink"
        }
    ],
    "sg:phone":"+1   ",
    "sg:postcode":"60516",
    "sg:province":"IL",
    "sg:tags":[
        "eating"
    ],
    "wof:name":"Mayflower Chinese Restaurant",
    "wof:placetype":"venue"
},
  "geometry": {"coordinates":[-88.048277,41.771608],"type":"Point"}
}