{
  "type": "Feature",
  "properties": {
    "iso:country":"US",
    "sg:address":"375 E Potter St",
    "sg:city":"Wood Dale",
    "sg:classifiers":[
        {
            "category":"Building & Trades",
            "subcategory":"Construction",
            "type":"Services"
        }
    ],
    "sg:phone":"+1 630 860 9030",
    "sg:postcode":"60191",
    "sg:province":"IL",
    "sg:tags":[
        "line",
        "sewer"
    ],
    "wof:name":"J C Mc Cabe Sewer Cnstr Inc",
    "wof:placetype":"venue"
},
  "geometry": {"coordinates":[-87.967009,41.960236],"type":"Point"}
}