{
  "type": "Feature",
  "properties": {
    "addr:full":"2001 W Howard St Chicago IL 60645",
    "addr:housenumber":"2001",
    "addr:postcode":"60645",
    "addr:street":"W Howard St",
    "iso:country":"US",
    "sg:address":"2001 W Howard St",
    "sg:city":"Chicago",
    "sg:classifiers":[
        {
            "category":"Deli",
            "type":"Food & Drink"
        }
    ],
    "sg:menulink":"http://www.allmenus.com/il/chicago/223427-tasty-sub/menu/",
    "sg:phone":"+1 773 381 4600",
    "sg:postcode":"60645",
    "sg:province":"IL",
    "sg:tags":[
        "american"
    ],
    "wof:name":"Tasty Sub",
    "wof:placetype":"venue"
},
  "geometry": {"coordinates":[-87.680369,42.019319],"type":"Point"}
}