{
  "type": "Feature",
  "properties": {
    "iso:country":"US",
    "sg:address":"0S668 Forest St",
    "sg:city":"Winfield",
    "sg:classifiers":[
        {
            "category":"Real Estate",
            "subcategory":"Real Estate Services",
            "type":"Services"
        },
        {
            "category":"Real Estate",
            "subcategory":"Real Estate Agent",
            "type":"Services"
        }
    ],
    "sg:phone":"+1 630 244 9581",
    "sg:postcode":"60190",
    "sg:province":"IL",
    "sg:tags":[
        "management"
    ],
    "wof:name":"Sunrise Ventures",
    "wof:placetype":"venue"
},
  "geometry": {"coordinates":[-88.15521200000001,41.865299],"type":"Point"}
}