{
  "type": "Feature",
  "properties": {
    "iso:country":"US",
    "sg:address":"111 N Hickory Ave",
    "sg:city":"Arlington Hts",
    "sg:classifiers":[
        {
            "category":"Professional",
            "subcategory":"Business Services",
            "type":"Services"
        }
    ],
    "sg:phone":"+1 847 506 0600",
    "sg:postcode":"60004",
    "sg:province":"IL",
    "sg:tags":[
        "recording",
        "studio"
    ],
    "sg:website":"www.cassetteservices.com",
    "wof:name":"Cassette Services Inc",
    "wof:placetype":"venue"
},
  "geometry": {"coordinates":[-87.974321,42.084584],"type":"Point"}
}