{
  "type": "Feature",
  "properties": {
    "iso:country":"US",
    "sg:address":"5600 Virginia Ave",
    "sg:city":"Clarendon Hills",
    "sg:classifiers":[
        {
            "category":"Building & Trades",
            "subcategory":"Plumbing",
            "type":"Services"
        }
    ],
    "sg:phone":"+1 630 323 8220",
    "sg:postcode":"60514",
    "sg:province":"IL",
    "sg:tags":[
        "contractor"
    ],
    "wof:name":"Petrik & Son Inc",
    "wof:placetype":"venue"
},
  "geometry": {"coordinates":[-87.95917799999999,41.784897],"type":"Point"}
}