{
  "type": "Feature",
  "properties": {
    "addr:full":"1046 Wisher Rd Patoka IL 62875",
    "addr:housenumber":"1046",
    "addr:postcode":"62875",
    "addr:street":"Wisher Rd",
    "iso:country":"US",
    "sg:address":"1046 Wisher Rd",
    "sg:city":"Patoka",
    "sg:phone":"+1 618 432 5334",
    "sg:postcode":"62875",
    "sg:province":"IL",
    "sg:tags":[
        "farm",
        "corn",
        "wheat",
        "soybean"
    ],
    "wof:name":"Bowen Farm Trust",
    "wof:placetype":"venue"
},
  "geometry": {"coordinates":[-89.086939,38.721262],"type":"Point"}
}