{
  "type": "Feature",
  "properties": {
    "addr:full":"1827 E Main St Danville IL 61832",
    "addr:housenumber":"1827",
    "addr:postcode":"61832",
    "addr:street":"E Main St",
    "iso:country":"US",
    "sg:address":"1827 E Main St",
    "sg:city":"Danville",
    "sg:classifiers":[
        {
            "category":"Bars & Pubs",
            "type":"Food & Drink"
        }
    ],
    "sg:phone":"+1   ",
    "sg:postcode":"61832",
    "sg:province":"IL",
    "sg:tags":[
        "drinking"
    ],
    "wof:name":"Mad Hatter Lounge",
    "wof:placetype":"venue"
},
  "geometry": {"coordinates":[-87.59582899999999,40.131679],"type":"Point"}
}