{
  "type": "Feature",
  "properties": {
    "addr:full":"1218 Caton Ave Joliet IL 60435",
    "addr:housenumber":"1218",
    "addr:postcode":"60435",
    "addr:street":"Caton Ave",
    "iso:country":"US",
    "sg:address":"1218 Caton Ave",
    "sg:city":"Joliet",
    "sg:classifiers":[
        {
            "category":"Real Estate",
            "subcategory":"Real Estate Agent",
            "type":"Services"
        }
    ],
    "sg:phone":"+1 815 725 7182",
    "sg:postcode":"60435",
    "sg:province":"IL",
    "sg:tags":[
        "appraiser"
    ],
    "wof:name":"James E Batis & Associates",
    "wof:placetype":"venue"
},
  "geometry": {"coordinates":[-88.115264,41.534597],"type":"Point"}
}