{
  "type": "Feature",
  "properties": {
    "addr:full":"2300 Cabot Dr Lisle IL 60532",
    "addr:housenumber":"2300",
    "addr:postcode":"60532",
    "addr:street":"Cabot Dr",
    "iso:country":"US",
    "sg:address":"2300 Cabot Dr",
    "sg:city":"Lisle",
    "sg:classifiers":[
        {
            "category":"Professional",
            "subcategory":"Lawyer & Legal Services",
            "type":"Services"
        }
    ],
    "sg:phone":"+1 630 955 0555",
    "sg:postcode":"60532",
    "sg:province":"IL",
    "wof:name":"Wildman Harrold Allen & Dixon",
    "wof:placetype":"venue"
},
  "geometry": {"coordinates":[-88.098716,41.809527],"type":"Point"}
}