{
  "type": "Feature",
  "properties": {
    "addr:full":"4901 Forest Ave Downers Grove IL 60515",
    "addr:housenumber":"4901",
    "addr:postcode":"60515",
    "addr:street":"Forest Ave",
    "iso:country":"US",
    "sg:address":"4901 Forest Ave",
    "sg:city":"Downers Grove",
    "sg:classifiers":[
        {
            "category":"Professional",
            "type":"Services"
        }
    ],
    "sg:phone":"+1 630 512 9280",
    "sg:postcode":"60515",
    "sg:province":"IL",
    "sg:tags":[
        "establishment"
    ],
    "wof:name":"Daniel N Myers PC",
    "wof:placetype":"venue"
},
  "geometry": {"coordinates":[-88.01188399999999,41.796212],"type":"Point"}
}