{
  "type": "Feature",
  "properties": {
    "iso:country":"US",
    "sg:address":"1843 S 54th Ave",
    "sg:city":"Cicero",
    "sg:classifiers":[
        {
            "category":"Manufacturing",
            "subcategory":"Metals",
            "type":"Manufacturing & Wholesale Goods"
        }
    ],
    "sg:phone":"+1 708 652 2037",
    "sg:postcode":"60804",
    "sg:province":"IL",
    "sg:tags":[
        "telecommunication",
        "for",
        "mfg",
        "industry",
        "fabricated",
        "hardware",
        "sh",
        "structural"
    ],
    "wof:name":"Central Steel Fabricators Inc",
    "wof:placetype":"venue"
},
  "geometry": {"coordinates":[-87.758973,41.85308],"type":"Point"}
}