{
  "type": "Feature",
  "properties": {
    "iso:country":"US",
    "sg:address":"657 Herkimer St",
    "sg:city":"Joliet",
    "sg:classifiers":[
        {
            "category":"Building & Trades",
            "subcategory":"Construction",
            "type":"Services"
        }
    ],
    "sg:phone":"+1 815 722 8773",
    "sg:postcode":"60432",
    "sg:province":"IL",
    "sg:tags":[
        "contractor"
    ],
    "wof:name":"Home Roofing Co",
    "wof:placetype":"venue"
},
  "geometry": {"coordinates":[-88.074021,41.53704],"type":"Point"}
}