{
  "type": "Feature",
  "properties": {
    "iso:country":"US",
    "sg:address":"6454 N Leavitt St",
    "sg:city":"Chicago",
    "sg:classifiers":[
        {
            "category":"Professional",
            "subcategory":"Management & Consulting",
            "type":"Services"
        }
    ],
    "sg:phone":"+1 773 392 4822",
    "sg:postcode":"60645",
    "sg:province":"IL",
    "sg:tags":[
        "counselor",
        "relation",
        "public"
    ],
    "wof:name":"Green Room Events And Marketing",
    "wof:placetype":"venue"
},
  "geometry": {"coordinates":[-87.685034,41.998801],"type":"Point"}
}