{
  "type": "Feature",
  "properties": {
    "addr:full":"501 Forest Dr Collinsville IL 62234",
    "addr:housenumber":"501",
    "addr:postcode":"62234",
    "addr:street":"Forest Dr",
    "iso:country":"US",
    "sg:address":"501 Forest Dr",
    "sg:city":"Collinsville",
    "sg:classifiers":[
        {
            "category":"Travel",
            "subcategory":"Travel Agent",
            "type":"Entertainment"
        }
    ],
    "sg:phone":"+1 618 345 7589",
    "sg:postcode":"62234",
    "sg:province":"IL",
    "sg:tags":[
        "agency"
    ],
    "wof:name":"Creative Travel Center Inc",
    "wof:placetype":"venue"
},
  "geometry": {"coordinates":[-89.990301,38.659777],"type":"Point"}
}