{
  "type": "Feature",
  "properties": {
    "iso:country":"US",
    "sg:address":"49 Smethwick Ln",
    "sg:city":"Elk Grove Village",
    "sg:classifiers":[
        {
            "category":"Professional",
            "subcategory":"Business Services",
            "type":"Services"
        }
    ],
    "sg:phone":"+1 847 439 6922",
    "sg:postcode":"60007",
    "sg:province":"IL",
    "wof:name":"Hobbytime Inc",
    "wof:placetype":"venue"
},
  "geometry": {"coordinates":[-88.006979,42.00945],"type":"Point"}
}