{
  "type": "Feature",
  "properties": {
    "addr:full":"700 Merrill Dr Belvidere IL 61008",
    "addr:housenumber":"700",
    "addr:postcode":"61008",
    "addr:street":"Merrill Dr",
    "iso:country":"US",
    "sg:address":"700 Merrill Dr",
    "sg:city":"Belvidere",
    "sg:classifiers":[
        {
            "category":"Building & Trades",
            "subcategory":"Construction",
            "type":"Services"
        }
    ],
    "sg:phone":"+1 815 544 9663",
    "sg:postcode":"61008",
    "sg:province":"IL",
    "sg:tags":[
        "fence",
        "contractor"
    ],
    "wof:name":"Creative Fencing",
    "wof:placetype":"venue"
},
  "geometry": {"coordinates":[-88.858801,42.261407],"type":"Point"}
}