{
  "type": "Feature",
  "properties": {
    "iso:country":"US",
    "sg:address":"534 Milford Rd",
    "sg:city":"Deerfield",
    "sg:classifiers":[
        {
            "category":"Professional",
            "subcategory":"Computer Services",
            "type":"Services"
        }
    ],
    "sg:phone":"+1 847 236 1598",
    "sg:postcode":"60015",
    "sg:province":"IL",
    "sg:tags":[
        "prepackaged",
        "software"
    ],
    "wof:name":"Bi Software Inc",
    "wof:placetype":"venue"
},
  "geometry": {"coordinates":[-87.843301,42.1618],"type":"Point"}
}