{
  "type": "Feature",
  "properties": {
    "addr:full":"2301 S Lake Shore Dr Chicago IL 60616",
    "addr:housenumber":"2301",
    "addr:postcode":"60616",
    "addr:street":"S Lake Shore Dr",
    "iso:country":"US",
    "sg:address":"2301 S Lake Shore Dr",
    "sg:city":"Chicago",
    "sg:classifiers":[
        {
            "category":"Restaurant",
            "type":"Food & Drink"
        }
    ],
    "sg:phone":"+1 312 742 7529",
    "sg:postcode":"60616",
    "sg:province":"IL",
    "sg:tags":[
        "flavor",
        "local"
    ],
    "wof:name":"McCormick Place Bird Sanctuary",
    "wof:placetype":"venue"
},
  "geometry": {"coordinates":[-87.612685,41.851504],"type":"Point"}
}