{
  "type": "Feature",
  "properties": {
    "iso:country":"US",
    "sg:address":"5140 N California Avenue Suite 605",
    "sg:city":"Chicago",
    "sg:classifiers":[
        {
            "category":"Health Services",
            "subcategory":"Doctor",
            "type":"Services"
        }
    ],
    "sg:phone":"+1 773 907 7500",
    "sg:postcode":"60625",
    "sg:province":"IL",
    "wof:name":"Glodek Thomas W MD",
    "wof:placetype":"venue"
},
  "geometry": {"coordinates":[-87.698925,41.975155],"type":"Point"}
}