{
  "type": "Feature",
  "properties": {
    "iso:country":"US",
    "sg:address":"2501 S Veterans Pkwy",
    "sg:city":"Springfield",
    "sg:classifiers":[
        {
            "category":"Banks & Credit Unions",
            "subcategory":"Investment Brokerage",
            "type":"Services"
        }
    ],
    "sg:phone":"+1 217 862 7313",
    "sg:postcode":"62704",
    "sg:province":"IL",
    "sg:tags":[
        "advisory"
    ],
    "wof:name":"Peter Earnes",
    "wof:placetype":"venue"
},
  "geometry": {"coordinates":[-89.706897,39.784266],"type":"Point"}
}