{
  "type": "Feature",
  "properties": {
    "iso:country":"US",
    "sg:address":"501 W Jefferson Ave",
    "sg:city":"Effingham",
    "sg:classifiers":[
        {
            "category":"Banks & Credit Unions",
            "subcategory":"Investment Brokerage",
            "type":"Services"
        }
    ],
    "sg:phone":"+1 217 347 0110",
    "sg:postcode":"62401",
    "sg:province":"IL",
    "sg:tags":[
        "management"
    ],
    "wof:name":"Accelerated Investment Mgmt",
    "wof:placetype":"venue"
},
  "geometry": {"coordinates":[-88.548906,39.121987],"type":"Point"}
}