{
  "type": "Feature",
  "properties": {
    "iso:country":"US",
    "sg:address":"854 N Heitter Rd",
    "sg:city":"Freeport",
    "sg:classifiers":[
        {
            "category":"Farming",
            "subcategory":"Farm & Veterinary Services",
            "type":"Manufacturing & Wholesale Goods"
        }
    ],
    "sg:phone":"+1 815 235 4000",
    "sg:postcode":"61032",
    "sg:province":"IL",
    "sg:tags":[
        "crop"
    ],
    "wof:name":"Bissell Painting",
    "wof:placetype":"venue"
},
  "geometry": {"coordinates":[-89.768383,42.301435],"type":"Point"}
}