{
  "type": "Feature",
  "properties": {
    "iso:country":"US",
    "sg:address":"10525 Waveland Ave",
    "sg:city":"Franklin Park",
    "sg:classifiers":[
        {
            "category":"Building & Trades",
            "subcategory":"Equipment Rental",
            "type":"Services"
        }
    ],
    "sg:phone":"+1 847 678 8561",
    "sg:postcode":"60131",
    "sg:province":"IL",
    "sg:tags":[
        "company",
        "holding"
    ],
    "wof:name":"Franklin Park 230",
    "wof:placetype":"venue"
},
  "geometry": {"coordinates":[-87.888083,41.946543],"type":"Point"}
}