{
  "type": "Feature",
  "properties": {
    "iso:country":"US",
    "sg:address":"115 Susan Dr Ste A",
    "sg:city":"Normal",
    "sg:classifiers":[
        {
            "category":"Fast Food",
            "type":"Food & Drink"
        },
        {
            "category":"Restaurant",
            "type":"Food & Drink"
        }
    ],
    "sg:phone":"+1 309 452 4046",
    "sg:postcode":"61761",
    "sg:province":"IL",
    "sg:tags":[
        "greek",
        "american",
        "take"
    ],
    "wof:name":"Super Gyros",
    "wof:placetype":"venue"
},
  "geometry": {"coordinates":[-88.949395,40.510896],"type":"Point"}
}