{
  "type": "Feature",
  "properties": {
    "iso:country":"US",
    "sg:address":"444 N Barrington Rd",
    "sg:city":"North Barrington",
    "sg:classifiers":[
        {
            "category":"Professional",
            "subcategory":"Accounting & Tax Preparation",
            "type":"Services"
        }
    ],
    "sg:phone":"+1 847 277 9002",
    "sg:postcode":"60010",
    "sg:province":"IL",
    "sg:tags":[
        "return",
        "filing"
    ],
    "sg:website":"www.folisisamz.com",
    "wof:name":"Folisi Samz & Co",
    "wof:placetype":"venue"
},
  "geometry": {"coordinates":[-88.14473,42.063576],"type":"Point"}
}