{
  "type": "Feature",
  "properties": {
    "iso:country":"US",
    "sg:address":"7655 N Ashland Ave",
    "sg:city":"Chicago",
    "sg:classifiers":[
        {
            "category":"Real Estate",
            "subcategory":"Real Estate Services",
            "type":"Services"
        },
        {
            "category":"Real Estate",
            "subcategory":"Real Estate Operator",
            "type":"Services"
        }
    ],
    "sg:phone":"+1 773 262 4979",
    "sg:postcode":"60626",
    "sg:province":"IL",
    "sg:tags":[
        "management",
        "vacancy",
        "apartment",
        "listing",
        "rental",
        "finder"
    ],
    "wof:name":"North Point Apartments",
    "wof:placetype":"venue"
},
  "geometry": {"coordinates":[-87.67069600000001,42.020881],"type":"Point"}
}