{
  "type": "Feature",
  "properties": {
    "addr:full":"1809 E 71st St Chicago IL 60649",
    "addr:housenumber":"1809",
    "addr:postcode":"60649",
    "addr:street":"E 71St St",
    "iso:country":"US",
    "sg:address":"1809 E 71st St",
    "sg:city":"Chicago",
    "sg:classifiers":[
        {
            "category":"Wholesale",
            "subcategory":"Machinery & Supplies",
            "type":"Manufacturing & Wholesale Goods"
        }
    ],
    "sg:phone":"+1 773 955 2510",
    "sg:postcode":"60649",
    "sg:province":"IL",
    "sg:tags":[
        "equipment",
        "farming"
    ],
    "wof:name":"Consortium of Ghanaworld",
    "wof:placetype":"venue"
},
  "geometry": {"coordinates":[-87.580912,41.766186],"type":"Point"}
}