{
  "type": "Feature",
  "properties": {
    "addr:full":"621 W Belmont Ave Chicago IL 60657",
    "addr:housenumber":"621",
    "addr:postcode":"60657",
    "addr:street":"W Belmont Ave",
    "iso:country":"US",
    "sg:address":"621 W Belmont Ave",
    "sg:city":"Chicago",
    "sg:classifiers":[
        {
            "category":"Place Of Worship",
            "subcategory":"Church",
            "type":"Public Place"
        }
    ],
    "sg:phone":"+1 773 525 0844",
    "sg:postcode":"60657",
    "sg:province":"IL",
    "sg:website":"www.stpeterschicago.org",
    "wof:name":"St. Peter's Episcopal Church",
    "wof:placetype":"venue"
},
  "geometry": {"coordinates":[-87.644897,41.940039],"type":"Point"}
}