{
  "type": "Feature",
  "properties": {
    "iso:country":"US",
    "sg:address":"1015 W Jackson St",
    "sg:city":"Macomb",
    "sg:classifiers":[
        {
            "category":"Restaurant",
            "type":"Food & Drink"
        }
    ],
    "sg:phone":"+1   ",
    "sg:postcode":"61455",
    "sg:province":"IL",
    "sg:tags":[
        "eating"
    ],
    "wof:name":"Hardees",
    "wof:placetype":"venue"
},
  "geometry": {"coordinates":[-90.686452,40.458853],"type":"Point"}
}