{
  "type": "Feature",
  "properties": {
    "iso:country":"US",
    "sg:address":"8339 Raptor Trl",
    "sg:city":"Vlg Of Lakewood",
    "sg:classifiers":[
        {
            "category":"Professional",
            "subcategory":"Engineering",
            "type":"Services"
        }
    ],
    "sg:phone":"+1 815 477 8030",
    "sg:postcode":"60014",
    "sg:province":"IL",
    "sg:tags":[
        "engineer"
    ],
    "wof:name":"Russell L King & Assoc",
    "wof:placetype":"venue"
},
  "geometry": {"coordinates":[-88.373561,42.208073],"type":"Point"}
}