{
  "type": "Feature",
  "properties": {
    "addr:full":"3152 W Montrose Chicago IL 60625",
    "addr:housenumber":"3152",
    "addr:postcode":"60625",
    "addr:street":"W Montrose",
    "iso:country":"US",
    "sg:address":"3152 W Montrose",
    "sg:city":"Chicago",
    "sg:classifiers":[
        {
            "category":"Restaurant",
            "type":"Food & Drink"
        }
    ],
    "sg:phone":"+1 773 583 4117",
    "sg:postcode":"60625",
    "sg:province":"IL",
    "sg:tags":[
        "mexican"
    ],
    "wof:name":"Taqueria El Aguila Real",
    "wof:placetype":"venue"
},
  "geometry": {"coordinates":[-87.707452,41.961189],"type":"Point"}
}