{
  "type": "Feature",
  "properties": {
    "addr:full":"527 E Main St Ottawa IL 61350",
    "addr:housenumber":"527",
    "addr:postcode":"61350",
    "addr:street":"E Main St",
    "iso:country":"US",
    "sg:address":"527 E Main St",
    "sg:city":"Ottawa",
    "sg:classifiers":[
        {
            "category":"Building & Trades",
            "subcategory":"Construction",
            "type":"Services"
        }
    ],
    "sg:phone":"+1 815 434 3976",
    "sg:postcode":"61350",
    "sg:province":"IL",
    "sg:tags":[
        "concrete",
        "contractor"
    ],
    "wof:name":"Muffler Construction Co",
    "wof:placetype":"venue"
},
  "geometry": {"coordinates":[-88.834244,41.345709],"type":"Point"}
}