{
  "type": "Feature",
  "properties": {
    "iso:country":"US",
    "sg:address":"2600 Winterbottom Rd",
    "sg:city":"Morris",
    "sg:classifiers":[
        {
            "category":"Organizations",
            "subcategory":"Community Association",
            "type":"Services"
        }
    ],
    "sg:phone":"+1 815 942 1793",
    "sg:postcode":"60450",
    "sg:province":"IL",
    "wof:name":"Boy Scouts of America 702",
    "wof:placetype":"venue"
},
  "geometry": {"coordinates":[-88.34348799999999,41.325306],"type":"Point"}
}