{
  "type": "Feature",
  "properties": {
    "iso:country":"US",
    "sg:address":"507 Depot St",
    "sg:city":"Mazon",
    "sg:classifiers":[
        {
            "category":"Personal",
            "subcategory":"Beauty Salon",
            "type":"Services"
        }
    ],
    "sg:phone":"+1 815 448 2800",
    "sg:postcode":"60444",
    "sg:province":"IL",
    "sg:tags":[
        "shop"
    ],
    "wof:name":"Tawny's New Generations",
    "wof:placetype":"venue"
},
  "geometry": {"coordinates":[-88.424128,41.240034],"type":"Point"}
}