{
  "type": "Feature",
  "properties": {
    "addr:full":"407 State St Lawrenceville IL 62439",
    "addr:housenumber":"407",
    "addr:postcode":"62439",
    "addr:street":"State St",
    "iso:country":"US",
    "sg:address":"407 State St",
    "sg:city":"Lawrenceville",
    "sg:classifiers":[
        {
            "category":"Travel",
            "subcategory":"Hotels & Motels",
            "type":"Entertainment"
        }
    ],
    "sg:phone":"+1 618 943 5112",
    "sg:postcode":"62439",
    "sg:province":"IL",
    "wof:name":"Mr K's Motel",
    "wof:placetype":"venue"
},
  "geometry": {"coordinates":[-87.675488,38.729481],"type":"Point"}
}