{
  "type": "Feature",
  "properties": {
    "iso:country":"US",
    "sg:address":"447 E College Ave",
    "sg:city":"Jacksonville",
    "sg:classifiers":[
        {
            "category":"Education",
            "subcategory":"College",
            "type":"Public Place"
        }
    ],
    "sg:phone":"+1 217 479 7000",
    "sg:postcode":"62650",
    "sg:province":"IL",
    "wof:name":"MACMURRAY COLLEGE BOOKSTORE",
    "wof:placetype":"venue"
},
  "geometry": {"coordinates":[-90.223649,39.732354],"type":"Point"}
}