{
  "type": "Feature",
  "properties": {
    "iso:country":"US",
    "sg:address":"809 S 5th St.",
    "sg:city":"Champaign",
    "sg:classifiers":[
        {
            "category":"Coffee & Tea",
            "type":"Food & Drink"
        }
    ],
    "sg:postcode":"61820",
    "sg:province":"IL",
    "wof:name":"The Serene Bean Cafe",
    "wof:placetype":"venue"
},
  "geometry": {"coordinates":[-88.232201,40.108898],"type":"Point"}
}