{
  "type": "Feature",
  "properties": {
    "addr:full":"400 Creekside Dr Vernon Hills IL 60061",
    "addr:housenumber":"400",
    "addr:postcode":"60061",
    "addr:street":"Creekside Dr",
    "iso:country":"US",
    "sg:address":"400 Creekside Dr",
    "sg:city":"Vernon Hills",
    "sg:classifiers":[
        {
            "category":"Recreation",
            "type":"Entertainment"
        }
    ],
    "sg:phone":"+1 847 367 8113",
    "sg:postcode":"60061",
    "sg:province":"IL",
    "sg:tags":[
        "club",
        "membership"
    ],
    "wof:name":"Westwood Umbrella Pool",
    "wof:placetype":"venue"
},
  "geometry": {"coordinates":[-87.974846,42.230642],"type":"Point"}
}