{
  "type": "Feature",
  "properties": {
    "iso:country":"US",
    "sg:address":"3601 W 95th St",
    "sg:city":"Evergreen Park",
    "sg:classifiers":[
        {
            "category":"Retail",
            "subcategory":"Auto Repair",
            "type":"Services"
        }
    ],
    "sg:phone":"+1 708 425 0133",
    "sg:postcode":"60805",
    "sg:province":"IL",
    "wof:name":"Arh Enterprises",
    "wof:placetype":"venue"
},
  "geometry": {"coordinates":[-87.711617,41.720463],"type":"Point"}
}