{
  "type": "Feature",
  "properties": {
    "iso:country":"US",
    "sg:address":"3043 W 159th St",
    "sg:city":"Markham",
    "sg:classifiers":[
        {
            "category":"Shopping",
            "subcategory":"Clothing, Apparel, & Fashions",
            "type":"Retail Goods"
        }
    ],
    "sg:phone":"+1 708 331 6752",
    "sg:postcode":"60428",
    "sg:province":"IL",
    "sg:tags":[
        "accessory",
        "clothing",
        "women's"
    ],
    "sg:website":"www.avenue.com",
    "wof:name":"Avenue the",
    "wof:placetype":"venue"
},
  "geometry": {"coordinates":[-87.69341300000001,41.600714],"type":"Point"}
}