{
  "type": "Feature",
  "properties": {
    "addr:full":"475 Hinman St Aurora IL 60505",
    "addr:housenumber":"475",
    "addr:postcode":"60505",
    "addr:street":"Hinman St",
    "iso:country":"US",
    "sg:address":"475 Hinman St",
    "sg:city":"Aurora",
    "sg:classifiers":[
        {
            "category":"Bars & Pubs",
            "type":"Food & Drink"
        }
    ],
    "sg:phone":"+1 630 898 5499",
    "sg:postcode":"60505",
    "sg:province":"IL",
    "wof:name":"Mickey's Tavern",
    "wof:placetype":"venue"
},
  "geometry": {"coordinates":[-88.305719,41.747786],"type":"Point"}
}