{
  "type": "Feature",
  "properties": {
    "addr:full":"192 Alton Sq Alton IL 62002",
    "addr:housenumber":"192",
    "addr:postcode":"62002",
    "addr:street":"Alton Sq",
    "iso:country":"US",
    "sg:address":"192 Alton Sq",
    "sg:city":"Alton",
    "sg:classifiers":[
        {
            "category":"Shopping",
            "subcategory":"Music",
            "type":"Retail Goods"
        }
    ],
    "sg:phone":"+1 618 462 7361",
    "sg:postcode":"62002",
    "sg:province":"IL",
    "sg:tags":[
        "compact",
        "record",
        "disc",
        "tape"
    ],
    "wof:name":"Music Biz",
    "wof:placetype":"venue"
},
  "geometry": {"coordinates":[-90.174633,38.927227],"type":"Point"}
}