{
  "type": "Feature",
  "properties": {
    "iso:country":"US",
    "sg:address":"14275 Wolf Rd",
    "sg:city":"Orland Park",
    "sg:classifiers":[
        {
            "category":"Personal",
            "type":"Services"
        }
    ],
    "sg:phone":"+1 708 226 6870",
    "sg:postcode":"60467",
    "sg:province":"IL",
    "sg:tags":[
        "leather"
    ],
    "wof:name":"World Tanning Inc",
    "wof:placetype":"venue"
},
  "geometry": {"coordinates":[-87.892359,41.62977],"type":"Point"}
}