{
  "type": "Feature",
  "properties": {
    "iso:country":"US",
    "sg:address":"312 W 8th St",
    "sg:city":"Gibson City",
    "sg:classifiers":[
        {
            "category":"Manufacturing",
            "subcategory":"Motor Vehicles & Parts",
            "type":"Manufacturing & Wholesale Goods"
        }
    ],
    "sg:phone":"+1 217 784 4020",
    "sg:postcode":"60936",
    "sg:province":"IL",
    "sg:tags":[
        "mfg",
        "business",
        "trimming"
    ],
    "wof:name":"Kearfott Graphix",
    "wof:placetype":"venue"
},
  "geometry": {"coordinates":[-88.37940999999999,40.465067],"type":"Point"}
}