{
  "type": "Feature",
  "properties": {
    "iso:country":"US",
    "sg:address":"1504 Miner St",
    "sg:city":"Des Plaines",
    "sg:classifiers":[
        {
            "category":"Restaurant",
            "type":"Food & Drink"
        }
    ],
    "sg:phone":"+1   ",
    "sg:postcode":"60016",
    "sg:province":"IL",
    "sg:tags":[
        "independent",
        "pizzeria",
        "italian"
    ],
    "wof:name":"Leonas Pizzeria Inc",
    "wof:placetype":"venue"
},
  "geometry": {"coordinates":[-87.88702499999999,42.041459],"type":"Point"}
}