{
  "type": "Feature",
  "properties": {
    "iso:country":"US",
    "sg:address":"524 Buchanan St",
    "sg:city":"Carthage",
    "sg:classifiers":[
        {
            "category":"Health Services",
            "subcategory":"Chiropractor",
            "type":"Services"
        }
    ],
    "sg:phone":"+1 217 357 2133",
    "sg:postcode":"62321",
    "sg:province":"IL",
    "sg:tags":[
        "chiropractic"
    ],
    "wof:name":"Carthage Chiropractic And Wellness Center, P.C.",
    "wof:placetype":"venue"
},
  "geometry": {"coordinates":[-91.136261,40.416283],"type":"Point"}
}