{
  "type": "Feature",
  "properties": {
    "iso:country":"US",
    "sg:address":"5150 W Roosevelt Rd",
    "sg:city":"Chicago",
    "sg:classifiers":[
        {
            "category":"Government",
            "subcategory":"Office",
            "type":"Public Place"
        }
    ],
    "sg:phone":"+1 773 854 5151",
    "sg:postcode":"60644",
    "sg:province":"IL",
    "sg:tags":[
        "government-state"
    ],
    "wof:name":"Stores Reproductions & Whse",
    "wof:placetype":"venue"
},
  "geometry": {"coordinates":[-87.75375,41.865755],"type":"Point"}
}