{
  "type": "Feature",
  "properties": {
    "iso:country":"US",
    "sg:address":"17149 Harlem Ave",
    "sg:city":"Tinley Park",
    "sg:classifiers":[
        {
            "category":"Retail",
            "subcategory":"Veterinary Services",
            "type":"Services"
        }
    ],
    "sg:phone":"+1 708 614 6500",
    "sg:postcode":"60477",
    "sg:province":"IL",
    "wof:name":"Family Pet Clinic",
    "wof:placetype":"venue"
},
  "geometry": {"coordinates":[-87.793298,41.57774],"type":"Point"}
}