{
  "type": "Feature",
  "properties": {
    "iso:country":"US",
    "sg:address":"209 W University Ave",
    "sg:city":"Champaign",
    "sg:classifiers":[
        {
            "category":"Real Estate",
            "subcategory":"Real Estate Operator",
            "type":"Services"
        }
    ],
    "sg:phone":"+1 217 359 2783",
    "sg:postcode":"61820",
    "sg:province":"IL",
    "sg:tags":[
        "apartment"
    ],
    "wof:name":"McMahon Realty Inc",
    "wof:placetype":"venue"
},
  "geometry": {"coordinates":[-88.245305,40.116193],"type":"Point"}
}