{
  "type": "Feature",
  "properties": {
    "iso:country":"US",
    "sg:address":"14590 N 1600th St",
    "sg:city":"Teutopolis",
    "sg:classifiers":[
        {
            "category":"Building & Trades",
            "subcategory":"Construction",
            "type":"Services"
        }
    ],
    "sg:phone":"+1 217 857 3109",
    "sg:postcode":"62467",
    "sg:province":"IL",
    "sg:tags":[
        "general",
        "contractor"
    ],
    "sg:website":"www.akrabuilders.com",
    "wof:name":"Akra Builders Inc",
    "wof:placetype":"venue"
},
  "geometry": {"coordinates":[-88.504606,39.128958],"type":"Point"}
}