{
  "type": "Feature",
  "properties": {
    "addr:full":"5 Harmon Ln Collinsville IL 62234",
    "addr:housenumber":"5",
    "addr:postcode":"62234",
    "addr:street":"Harmon Ln",
    "iso:country":"US",
    "sg:address":"5 Harmon Ln",
    "sg:city":"Collinsville",
    "sg:classifiers":[
        {
            "category":"Building & Trades",
            "subcategory":"Construction",
            "type":"Services"
        }
    ],
    "sg:phone":"+1 618 876 4309",
    "sg:postcode":"62234",
    "sg:province":"IL",
    "sg:tags":[
        "roofing",
        "contractor"
    ],
    "wof:name":"Madison County Roofing & Home",
    "wof:placetype":"venue"
},
  "geometry": {"coordinates":[-89.990342,38.731038],"type":"Point"}
}