{
  "type": "Feature",
  "properties": {
    "addr:full":"108 W Germania Pl Chicago IL 60610",
    "addr:housenumber":"108",
    "addr:postcode":"60610",
    "addr:street":"W Germania Pl",
    "iso:country":"US",
    "sg:address":"108 W Germania Pl",
    "sg:city":"Chicago",
    "sg:classifiers":[
        {
            "category":"Education",
            "subcategory":"Preschool",
            "type":"Public Place"
        },
        {
            "category":"Education",
            "subcategory":"School",
            "type":"Public Place"
        }
    ],
    "sg:phone":"+1 312 482 9009",
    "sg:postcode":"60610",
    "sg:province":"IL",
    "sg:tags":[
        "elementary"
    ],
    "sg:website":"www.lincolnparkprep.com",
    "wof:name":"Lincoln Park Preparatory & Kindergarten",
    "wof:placetype":"venue"
},
  "geometry": {"coordinates":[-87.63206,41.910374],"type":"Point"}
}