{
  "type": "Feature",
  "properties": {
    "iso:country":"US",
    "sg:address":"6101 Capulina Ave",
    "sg:city":"Morton Grove",
    "sg:classifiers":[
        {
            "category":"Government",
            "subcategory":"Office",
            "type":"Public Place"
        }
    ],
    "sg:phone":"+1   ",
    "sg:postcode":"60053",
    "sg:province":"IL",
    "sg:tags":[
        "city"
    ],
    "wof:name":"Morton Grove Village of",
    "wof:placetype":"venue"
},
  "geometry": {"coordinates":[-87.77946300000001,42.03808],"type":"Point"}
}