{
  "type": "Feature",
  "properties": {
    "addr:full":"4152 W 123rd St Alsip IL 60803",
    "addr:housenumber":"4152",
    "addr:postcode":"60803",
    "addr:street":"W 123Rd St",
    "iso:country":"US",
    "sg:address":"4152 W 123rd St",
    "sg:city":"Alsip",
    "sg:classifiers":[
        {
            "category":"Wholesale",
            "subcategory":"Metals & Minerals",
            "type":"Manufacturing & Wholesale Goods"
        }
    ],
    "sg:phone":"+1 708 388 9600",
    "sg:postcode":"60803",
    "sg:province":"IL",
    "sg:tags":[
        "steel",
        "warehouse"
    ],
    "sg:website":"www.admiralsteel.com",
    "wof:name":"Admiral Steel Corp",
    "wof:placetype":"venue"
},
  "geometry": {"coordinates":[-87.723935,41.669357],"type":"Point"}
}