{
  "type": "Feature",
  "properties": {
    "iso:country":"US",
    "sg:address":"410 S Linn St",
    "sg:city":"Shannon",
    "sg:classifiers":[
        {
            "category":"Home & Garden",
            "subcategory":"Household Appliances",
            "type":"Retail Goods"
        }
    ],
    "sg:phone":"+1 815 864 2666",
    "sg:postcode":"61078",
    "sg:province":"IL",
    "wof:name":"Ken's Appliance & Refrig Svc",
    "wof:placetype":"venue"
},
  "geometry": {"coordinates":[-89.738326,42.150517],"type":"Point"}
}