{
  "type": "Feature",
  "properties": {
    "iso:country":"US",
    "sg:address":"2215 N MIlwaukee Ave",
    "sg:city":"Chicago",
    "sg:classifiers":[
        {
            "category":"Home & Garden",
            "subcategory":"Household Appliances",
            "type":"Retail Goods"
        },
        {
            "category":"Personal",
            "type":"Services"
        }
    ],
    "sg:phone":"+1 773 235 5336",
    "sg:postcode":"60647",
    "sg:province":"IL",
    "sg:tags":[
        "repair"
    ],
    "wof:name":"K.A. Vogel Sons Inc",
    "wof:placetype":"venue"
},
  "geometry": {"coordinates":[-87.694255,41.92108],"type":"Point"}
}