{
  "type": "Feature",
  "properties": {
    "addr:full":"3443 N Pulaski Rd Chicago IL 60641",
    "addr:housenumber":"3443",
    "addr:postcode":"60641",
    "addr:street":"N Pulaski Rd",
    "iso:country":"US",
    "sg:address":"3443 N Pulaski Rd",
    "sg:city":"Chicago",
    "sg:classifiers":[
        {
            "category":"Wholesale",
            "subcategory":"Vending Machines",
            "type":"Manufacturing & Wholesale Goods"
        }
    ],
    "sg:phone":"+1   ",
    "sg:postcode":"60641",
    "sg:province":"IL",
    "sg:tags":[
        "operator"
    ],
    "wof:name":"Classic Vending Inc",
    "wof:placetype":"venue"
},
  "geometry": {"coordinates":[-87.72724599999999,41.943714],"type":"Point"}
}