{
  "type": "Feature",
  "properties": {
    "iso:country":"US",
    "sg:address":"629 State Ave",
    "sg:city":"Hampton",
    "sg:classifiers":[
        {
            "category":"Banks & Credit Unions",
            "subcategory":"Bank",
            "type":"Services"
        }
    ],
    "sg:phone":"+1 309 752 9275",
    "sg:postcode":"61256",
    "sg:province":"IL",
    "sg:website":"www.thenb.com",
    "wof:name":"National Bank the",
    "wof:placetype":"venue"
},
  "geometry": {"coordinates":[-90.409204,41.556283],"type":"Point"}
}