{
  "type": "Feature",
  "properties": {
    "iso:country":"US",
    "sg:address":"9 S Columbia St",
    "sg:city":"Naperville",
    "sg:classifiers":[
        {
            "category":"Government",
            "subcategory":"Fire Station",
            "type":"Public Place"
        },
        {
            "category":"Retail",
            "subcategory":"Laundry & Dry Cleaning",
            "type":"Services"
        }
    ],
    "sg:phone":"+1 630 357 7086",
    "sg:postcode":"60540",
    "sg:province":"IL",
    "sg:tags":[
        "cleaner",
        "disaster",
        "recovery",
        "rug",
        "relief",
        "carpet"
    ],
    "wof:name":"Clean Usa",
    "wof:placetype":"venue"
},
  "geometry": {"coordinates":[-88.138081,41.774749],"type":"Point"}
}