{
  "type": "Feature",
  "properties": {
    "iso:country":"US",
    "sg:address":"6501 W 127th St",
    "sg:city":"Palos Heights",
    "sg:classifiers":[
        {
            "category":"Restaurant",
            "type":"Food & Drink"
        }
    ],
    "sg:phone":"+1 708 239 1983",
    "sg:postcode":"60463",
    "sg:province":"IL",
    "sg:tags":[
        "sushi",
        "bar"
    ],
    "wof:name":"Sushi of Nagoya",
    "wof:placetype":"venue"
},
  "geometry": {"coordinates":[-87.78022300000001,41.660836],"type":"Point"}
}