{
  "type": "Feature",
  "properties": {
    "addr:full":"188 Co Rd 100 E Ivesdale IL 61851",
    "addr:housenumber":"188",
    "addr:postcode":"61851",
    "addr:street":"Co Rd 100 E",
    "iso:country":"US",
    "sg:address":"188 Co Rd 100 E",
    "sg:city":"Ivesdale",
    "sg:classifiers":[
        {
            "category":"Banks & Credit Unions",
            "subcategory":"Investment Brokerage",
            "type":"Services"
        }
    ],
    "sg:phone":"+1 217 564 2429",
    "sg:postcode":"61851",
    "sg:province":"IL",
    "sg:tags":[
        "commodity"
    ],
    "wof:name":"Gary Ellis Commodities",
    "wof:placetype":"venue"
},
  "geometry": {"coordinates":[-88.443896,39.895362],"type":"Point"}
}