{
  "type": "Feature",
  "properties": {
    "iso:country":"US",
    "sg:address":"1950 Hickory Rd",
    "sg:city":"Homewood",
    "sg:classifiers":[
        {
            "category":"Professional",
            "subcategory":"Lawyer & Legal Services",
            "type":"Services"
        }
    ],
    "sg:phone":"+1 708 799 7676",
    "sg:postcode":"60430",
    "sg:province":"IL",
    "sg:tags":[
        "attorney"
    ],
    "wof:name":"John T Doody Jr",
    "wof:placetype":"venue"
},
  "geometry": {"coordinates":[-87.663771,41.560576],"type":"Point"}
}