{
  "type": "Feature",
  "properties": {
    "iso:country":"US",
    "sg:address":"1407 Wood Creek Bend",
    "sg:city":"Rockford",
    "sg:classifiers":[
        {
            "category":"Retail",
            "subcategory":"Photofinishing",
            "type":"Services"
        }
    ],
    "sg:phone":"+1 815 397 7005",
    "sg:postcode":"61108",
    "sg:province":"IL",
    "sg:tags":[
        "laboratory"
    ],
    "wof:name":"Engle & Assoc",
    "wof:placetype":"venue"
},
  "geometry": {"coordinates":[-88.990575,42.254595],"type":"Point"}
}