{
  "type": "Feature",
  "properties": {
    "iso:country":"US",
    "sg:address":"921 Sherwood Dr",
    "sg:city":"Lake Bluff",
    "sg:classifiers":[
        {
            "category":"Manufacturing",
            "subcategory":"Furniture",
            "type":"Manufacturing & Wholesale Goods"
        }
    ],
    "sg:phone":"+1 847 234 5855",
    "sg:postcode":"60044",
    "sg:province":"IL",
    "sg:tags":[
        "household",
        "wood",
        "mfg"
    ],
    "wof:name":"Ecologic Furniture",
    "wof:placetype":"venue"
},
  "geometry": {"coordinates":[-87.872343,42.269828],"type":"Point"}
}