{
  "type": "Feature",
  "properties": {
    "addr:full":"522 W Wildspring Rd Round Lake IL 60073",
    "addr:housenumber":"522",
    "addr:postcode":"60073",
    "addr:street":"W Wildspring Rd",
    "iso:country":"US",
    "sg:address":"522 W Wildspring Rd",
    "sg:city":"Round Lake",
    "sg:classifiers":[
        {
            "category":"Wholesale",
            "subcategory":"Apparel",
            "type":"Manufacturing & Wholesale Goods"
        }
    ],
    "sg:phone":"+1 847 740 1961",
    "sg:postcode":"60073",
    "sg:province":"IL",
    "sg:tags":[
        "clothing"
    ],
    "wof:name":"Tapper Boy",
    "wof:placetype":"venue"
},
  "geometry": {"coordinates":[-88.095832,42.345024],"type":"Point"}
}