{
  "type": "Feature",
  "properties": {
    "iso:country":"US",
    "sg:address":"4400 S Western Ave",
    "sg:city":"Chicago",
    "sg:classifiers":[
        {
            "category":"Retail",
            "subcategory":"Auto Repair",
            "type":"Services"
        }
    ],
    "sg:phone":"+1 773 376 4410",
    "sg:postcode":"60609",
    "sg:province":"IL",
    "wof:name":"Mexico Mufflers & Brakes",
    "wof:placetype":"venue"
},
  "geometry": {"coordinates":[-87.684754,41.813896],"type":"Point"}
}