{
  "type": "Feature",
  "properties": {
    "iso:country":"US",
    "sg:address":"320 W Wood St",
    "sg:city":"Palatine",
    "sg:classifiers":[
        {
            "category":"Professional",
            "subcategory":"Detective & Security Services",
            "type":"Services"
        }
    ],
    "sg:phone":"+1 847 577 6074",
    "sg:postcode":"60067",
    "sg:province":"IL",
    "sg:tags":[
        "information",
        "bureau"
    ],
    "sg:website":"http://www.parallelmediaservices.com",
    "wof:name":"Parallel Media Services",
    "wof:placetype":"venue"
},
  "geometry": {"coordinates":[-88.05226500000001,42.113979],"type":"Point"}
}