{
  "type": "Feature",
  "properties": {
    "iso:country":"US",
    "sg:address":"4313 W Irving Park Rd",
    "sg:city":"Chicago",
    "sg:classifiers":[
        {
            "category":"Real Estate",
            "subcategory":"Real Estate Agent",
            "type":"Services"
        }
    ],
    "sg:phone":"+1 773 286 6200",
    "sg:postcode":"60641",
    "sg:province":"IL",
    "wof:name":"Citywide J M D Realty Inc",
    "wof:placetype":"venue"
},
  "geometry": {"coordinates":[-87.73543600000001,41.953559],"type":"Point"}
}