{
  "type": "Feature",
  "properties": {
    "addr:full":"2595 E Ogden Ave Lisle IL 60532",
    "addr:housenumber":"2595",
    "addr:postcode":"60532",
    "addr:street":"E Ogden Ave",
    "iso:country":"US",
    "sg:address":"2595 E Ogden Ave",
    "sg:city":"Lisle",
    "sg:classifiers":[
        {
            "category":"Autos & Motor Vehicles",
            "subcategory":"Motorcycle Sales",
            "type":"Retail Goods"
        }
    ],
    "sg:phone":"+1   ",
    "sg:postcode":"60532",
    "sg:province":"IL",
    "sg:tags":[
        "repair",
        "parts",
        "accessory"
    ],
    "wof:name":"Heritage Harley-Davidson Inc",
    "wof:placetype":"venue"
},
  "geometry": {"coordinates":[-88.103877,41.797232],"type":"Point"}
}