{
  "type": "Feature",
  "properties": {
    "addr:full":"13323 S Baltimore Ave Chicago IL 60633",
    "addr:housenumber":"13323",
    "addr:postcode":"60633",
    "addr:street":"S Baltimore Ave",
    "iso:country":"US",
    "sg:address":"13323 S Baltimore Ave",
    "sg:city":"Chicago",
    "sg:classifiers":[
        {
            "category":"Banks & Credit Unions",
            "subcategory":"Bank",
            "type":"Services"
        }
    ],
    "sg:phone":"+1 773 646 1000",
    "sg:postcode":"60633",
    "sg:province":"IL",
    "wof:name":"Citizens Financial Bank",
    "wof:placetype":"venue"
},
  "geometry": {"coordinates":[-87.546997,41.653301],"type":"Point"}
}