{
  "type": "Feature",
  "properties": {
    "iso:country":"US",
    "sg:address":"2335 Lake Ave",
    "sg:city":"Vlg Of Lakewood",
    "sg:classifiers":[
        {
            "category":"Professional",
            "subcategory":"Art Services",
            "type":"Services"
        }
    ],
    "sg:phone":"+1 815 477 0966",
    "sg:postcode":"60014",
    "sg:province":"IL",
    "sg:tags":[
        "artist"
    ],
    "wof:name":"Swanson Design Assoc",
    "wof:placetype":"venue"
},
  "geometry": {"coordinates":[-88.365348,42.233468],"type":"Point"}
}