{
  "type": "Feature",
  "properties": {
    "iso:country":"US",
    "sg:address":"705 S Forest Park Dr",
    "sg:city":"Eureka",
    "sg:classifiers":[
        {
            "category":"Organizations",
            "subcategory":"Religious Organization",
            "type":"Services"
        }
    ],
    "sg:phone":"+1 309 467 3460",
    "sg:postcode":"61530",
    "sg:province":"IL",
    "wof:name":"Roanoke Mennonite Church",
    "wof:placetype":"venue"
},
  "geometry": {"coordinates":[-89.27655,40.712768],"type":"Point"}
}