{
  "type": "Feature",
  "properties": {
    "iso:country":"US",
    "sg:address":"1180 E Higgins Rd",
    "sg:city":"Schaumburg",
    "sg:classifiers":[
        {
            "category":"Banks & Credit Unions",
            "subcategory":"Bank",
            "type":"Services"
        }
    ],
    "sg:phone":"+1 847 273 3500",
    "sg:postcode":"60173",
    "sg:province":"IL",
    "sg:website":"http://www.citizensfirststatebank.com",
    "wof:name":"Harris National",
    "wof:placetype":"venue"
},
  "geometry": {"coordinates":[-88.050633,42.039806],"type":"Point"}
}