{
  "type": "Feature",
  "properties": {
    "addr:full":"1614 Arlington Heights Rd Arlington Heights IL 60005",
    "addr:housenumber":"1614",
    "addr:postcode":"60005",
    "addr:street":"Arlington Heights Rd",
    "iso:country":"US",
    "sg:address":"1614 Arlington Heights Rd",
    "sg:city":"Arlington Heights",
    "sg:classifiers":[
        {
            "category":"Health Services",
            "subcategory":"Doctor",
            "type":"Services"
        }
    ],
    "sg:phone":"+1 847 818 1184",
    "sg:postcode":"60005",
    "sg:province":"IL",
    "sg:tags":[
        "medical"
    ],
    "wof:name":"North Shore Lung Specialists",
    "wof:placetype":"venue"
},
  "geometry": {"coordinates":[-87.981689,42.054618],"type":"Point"}
}