{
  "type": "Feature",
  "properties": {
    "addr:full":"708 Theodore St Joliet IL 60435",
    "addr:housenumber":"708",
    "addr:postcode":"60435",
    "addr:street":"Theodore St",
    "iso:country":"US",
    "sg:address":"708 Theodore St",
    "sg:city":"Joliet",
    "sg:classifiers":[
        {
            "category":"Restaurant",
            "type":"Food & Drink"
        }
    ],
    "sg:phone":"+1   ",
    "sg:postcode":"60435",
    "sg:province":"IL",
    "sg:tags":[
        "eating"
    ],
    "wof:name":"J TS Restaurant",
    "wof:placetype":"venue"
},
  "geometry": {"coordinates":[-88.10021399999999,41.552246],"type":"Point"}
}