{
  "type": "Feature",
  "properties": {
    "iso:country":"US",
    "sg:address":"708 Theodore St",
    "sg:city":"Joliet",
    "sg:classifiers":[
        {
            "category":"Restaurant",
            "type":"Food & Drink"
        }
    ],
    "sg:phone":"+1   ",
    "sg:postcode":"60435",
    "sg:province":"IL",
    "sg:tags":[
        "eating"
    ],
    "wof:name":"J TS Restaurant",
    "wof:placetype":"venue"
},
  "geometry": {"coordinates":[-88.100214,41.552246],"type":"Point"}
}