{
  "type": "Feature",
  "properties": {
    "addr:full":"56 Birchwood Ave Deerfield IL 60015",
    "addr:housenumber":"56",
    "addr:postcode":"60015",
    "addr:street":"Birchwood Ave",
    "iso:country":"US",
    "sg:address":"56 Birchwood Ave",
    "sg:city":"Deerfield",
    "sg:classifiers":[
        {
            "category":"Professional",
            "subcategory":"Management & Consulting",
            "type":"Services"
        }
    ],
    "sg:phone":"+1 847 945 1891",
    "sg:postcode":"60015",
    "sg:province":"IL",
    "sg:tags":[
        "communications",
        "consultant"
    ],
    "wof:name":"Scholl Communications Inc",
    "wof:placetype":"venue"
},
  "geometry": {"coordinates":[-87.86256299999999,42.154387],"type":"Point"}
}