{
  "type": "Feature",
  "properties": {
    "iso:country":"US",
    "sg:address":"1311 N Jackson St",
    "sg:city":"Waukegan",
    "sg:classifiers":[
        {
            "category":"Professional",
            "subcategory":"Secretarial Services",
            "type":"Services"
        }
    ],
    "sg:phone":"+1 847 244 3468",
    "sg:postcode":"60085",
    "sg:province":"IL",
    "sg:tags":[
        "reporting",
        "court"
    ],
    "wof:name":"Lucy's Secretarial",
    "wof:placetype":"venue"
},
  "geometry": {"coordinates":[-87.841711,42.379102],"type":"Point"}
}