{
  "type": "Feature",
  "properties": {
    "iso:country":"US",
    "sg:address":"1900 18th St",
    "sg:city":"Charleston",
    "sg:classifiers":[
        {
            "category":"Restaurant",
            "type":"Food & Drink"
        }
    ],
    "sg:menulink":"http://www.allmenus.com/il/charleston/226203-caseys-general-store/menu/",
    "sg:phone":"+1 217 345 1006",
    "sg:postcode":"61920",
    "sg:province":"IL",
    "sg:tags":[
        "american",
        "pizza"
    ],
    "wof:name":"Casey's General Store",
    "wof:placetype":"venue"
},
  "geometry": {"coordinates":[-88.162927,39.48076],"type":"Point"}
}