{
  "type": "Feature",
  "properties": {
    "addr:full":"1825 American Way Kankakee IL 60901",
    "addr:housenumber":"1825",
    "addr:postcode":"60901",
    "addr:street":"American Way",
    "iso:country":"US",
    "sg:address":"1825 American Way",
    "sg:city":"Kankakee",
    "sg:classifiers":[
        {
            "category":"Manufacturing",
            "subcategory":"Rubber & Plastics",
            "type":"Manufacturing & Wholesale Goods"
        }
    ],
    "sg:phone":"+1 815 939 7270",
    "sg:postcode":"60901",
    "sg:province":"IL",
    "sg:tags":[
        "bottle",
        "mfg"
    ],
    "wof:name":"Ring Can",
    "wof:placetype":"venue"
},
  "geometry": {"coordinates":[-87.838438,41.138698],"type":"Point"}
}