{
  "type": "Feature",
  "properties": {
    "addr:full":"1255 Lincoln Dr Carbondale IL 62901",
    "addr:housenumber":"1255",
    "addr:postcode":"62901",
    "addr:street":"Lincoln Dr",
    "iso:country":"US",
    "sg:address":"1255 Lincoln Dr",
    "sg:city":"Carbondale",
    "sg:classifiers":[
        {
            "category":"Education",
            "subcategory":"University",
            "type":"Public Place"
        }
    ],
    "sg:phone":"+1 618 453 2121",
    "sg:postcode":"62901",
    "sg:province":"IL",
    "sg:tags":[
        "college"
    ],
    "wof:name":"Environmental Alternatives Inc",
    "wof:placetype":"venue"
},
  "geometry": {"coordinates":[-89.218073,37.711886],"type":"Point"}
}