{
  "type": "Feature",
  "properties": {
    "addr:full":"8930 S Octavia Ave Bridgeview IL 60455",
    "addr:housenumber":"8930",
    "addr:postcode":"60455",
    "addr:street":"S Octavia Ave",
    "iso:country":"US",
    "sg:address":"8930 S Octavia Ave",
    "sg:city":"Bridgeview",
    "sg:classifiers":[
        {
            "category":"Retail",
            "subcategory":"Auto Repair",
            "type":"Services"
        }
    ],
    "sg:phone":"+1 708 598 8220",
    "sg:postcode":"60455",
    "sg:province":"IL",
    "sg:tags":[
        "lubricating"
    ],
    "wof:name":"B & T Pump & Lube Svc Inc",
    "wof:placetype":"venue"
},
  "geometry": {"coordinates":[-87.801413,41.728392],"type":"Point"}
}