{
  "type": "Feature",
  "properties": {
    "iso:country":"US",
    "sg:address":"1820 Carlisle Ct",
    "sg:city":"Schaumburg",
    "sg:classifiers":[
        {
            "category":"Building & Trades",
            "subcategory":"Construction",
            "type":"Services"
        }
    ],
    "sg:phone":"+1 847 884 7934",
    "sg:postcode":"60194",
    "sg:province":"IL",
    "sg:tags":[
        "house"
    ],
    "wof:name":"L Eckman Inc",
    "wof:placetype":"venue"
},
  "geometry": {"coordinates":[-88.125292,42.042009],"type":"Point"}
}