{
  "type": "Feature",
  "properties": {
    "addr:full":"7016 W Cermak Road Berwyn IL 60402",
    "addr:housenumber":"7016",
    "addr:postcode":"60402",
    "addr:street":"W Cermak Road",
    "iso:country":"US",
    "sg:address":"7016 W Cermak Road",
    "sg:city":"Berwyn",
    "sg:classifiers":[
        {
            "category":"Restaurant",
            "type":"Food & Drink"
        }
    ],
    "sg:phone":"+1 708 795 6555",
    "sg:postcode":"60402",
    "sg:province":"IL",
    "sg:tags":[
        "modern",
        "european"
    ],
    "sg:website":"czechplaza.com/",
    "wof:name":"Czech Plaza Restaurant",
    "wof:placetype":"venue"
},
  "geometry": {"coordinates":[-87.799269,41.850544],"type":"Point"}
}