{
  "type": "Feature",
  "properties": {
    "addr:full":"910 E 131st St Riverdale IL 60827",
    "addr:housenumber":"910",
    "addr:postcode":"60827",
    "addr:street":"E 131St St",
    "iso:country":"US",
    "sg:address":"910 E 131st St",
    "sg:city":"Riverdale",
    "sg:classifiers":[
        {
            "category":"Health Services",
            "subcategory":"Medical Lab",
            "type":"Services"
        }
    ],
    "sg:phone":"+1 773 291 0035",
    "sg:postcode":"60827",
    "sg:province":"IL",
    "sg:tags":[
        "laboratory"
    ],
    "wof:name":"Christian E Okezie MD",
    "wof:placetype":"venue"
},
  "geometry": {"coordinates":[-87.59992,41.65734],"type":"Point"}
}