{
  "type": "Feature",
  "properties": {
    "addr:full":"301 Charles St South Beloit WI 61080",
    "addr:housenumber":"301",
    "addr:postcode":"61080",
    "addr:street":"Charles St",
    "iso:country":"US",
    "sg:address":"301 Charles St",
    "sg:city":"South Beloit",
    "sg:classifiers":[
        {
            "category":"Retail",
            "subcategory":"Auto Repair",
            "type":"Services"
        }
    ],
    "sg:phone":"+1 815 389 8613",
    "sg:postcode":"61080",
    "sg:province":"WI",
    "sg:tags":[
        "repairing",
        "automobile"
    ],
    "wof:name":"King's Auto Repair",
    "wof:placetype":"venue"
},
  "geometry": {"coordinates":[-89.039473,42.490897],"type":"Point"}
}