{
  "type": "Feature",
  "properties": {
    "iso:country":"US",
    "sg:address":"4001 W Devon Ave Ste 404",
    "sg:city":"Chicago",
    "sg:classifiers":[
        {
            "category":"Real Estate",
            "subcategory":"Real Estate Services",
            "type":"Services"
        }
    ],
    "sg:phone":"+1 773 286 3300",
    "sg:postcode":"60646",
    "sg:province":"IL",
    "sg:tags":[
        "management",
        "property"
    ],
    "wof:name":"Landmeir Enterprises",
    "wof:placetype":"venue"
},
  "geometry": {"coordinates":[-87.728798,41.997101],"type":"Point"}
}