{
  "type": "Feature",
  "properties": {
    "iso:country":"US",
    "sg:address":"1200 W Algonquin Rd",
    "sg:city":"Palatine",
    "sg:classifiers":[
        {
            "category":"Education",
            "subcategory":"University",
            "type":"Public Place"
        }
    ],
    "sg:phone":"+1 847 925 6707",
    "sg:postcode":"60067",
    "sg:province":"IL",
    "sg:tags":[
        "college"
    ],
    "wof:name":"Communityfaith.Com Inc.",
    "wof:placetype":"venue"
},
  "geometry": {"coordinates":[-88.070938,42.076618],"type":"Point"}
}