{
  "type": "Feature",
  "properties": {
    "iso:country":"US",
    "sg:address":"113 E Sherwood Dr",
    "sg:city":"Cary",
    "sg:classifiers":[
        {
            "category":"Shopping",
            "subcategory":"Gifts & Souvenirs",
            "type":"Retail Goods"
        }
    ],
    "sg:phone":"+1 847 516 3481",
    "sg:postcode":"60013",
    "sg:province":"IL",
    "sg:tags":[
        "material",
        "mfg"
    ],
    "wof:name":"Baskets Plus",
    "wof:placetype":"venue"
},
  "geometry": {"coordinates":[-88.233242,42.212293],"type":"Point"}
}