{
  "type": "Feature",
  "properties": {
    "iso:country":"US",
    "sg:address":"9500 S Western Ave",
    "sg:city":"Evergreen Park",
    "sg:classifiers":[
        {
            "category":"Personal",
            "subcategory":"Nail Salon",
            "type":"Services"
        }
    ],
    "sg:phone":"+1 708 499 6443",
    "sg:postcode":"60805",
    "sg:province":"IL",
    "wof:name":"Generation Nails",
    "wof:placetype":"venue"
},
  "geometry": {"coordinates":[-87.681999,41.720901],"type":"Point"}
}