{
  "type": "Feature",
  "properties": {
    "iso:country":"US",
    "sg:address":"4008 W Cornelia Ave",
    "sg:city":"Chicago",
    "sg:classifiers":[
        {
            "category":"Wholesale",
            "subcategory":"Vending Machines",
            "type":"Manufacturing & Wholesale Goods"
        }
    ],
    "sg:phone":"+1   ",
    "sg:postcode":"60641",
    "sg:province":"IL",
    "sg:tags":[
        "operator"
    ],
    "wof:name":"Vending Retailers Inc",
    "wof:placetype":"venue"
},
  "geometry": {"coordinates":[-87.727835,41.944872],"type":"Point"}
}