{
  "type": "Feature",
  "properties": {
    "addr:full":"1433 N 1st Ave Melrose Park IL 60160",
    "addr:housenumber":"1433",
    "addr:postcode":"60160",
    "addr:street":"N 1St Ave;Park",
    "iso:country":"US",
    "sg:address":"1433 N 1st Ave",
    "sg:city":"Melrose Park",
    "sg:classifiers":[
        {
            "category":"Retail",
            "subcategory":"Auto Repair",
            "type":"Services"
        }
    ],
    "sg:phone":"+1 708 450 9515",
    "sg:postcode":"60160",
    "sg:province":"IL",
    "sg:tags":[
        "body",
        "shop"
    ],
    "wof:name":"1st Auto Body Llc",
    "wof:placetype":"venue"
},
  "geometry": {"coordinates":[-87.834801,41.900101],"type":"Point"}
}