{
  "type": "Feature",
  "properties": {
    "addr:full":"730 S Dearborn St Chicago IL 60605",
    "addr:housenumber":"730",
    "addr:postcode":"60605",
    "addr:street":"S Dearborn St",
    "iso:country":"US",
    "sg:address":"730 S Dearborn St",
    "sg:city":"Chicago",
    "sg:classifiers":[
        {
            "category":"Food & Beverages",
            "subcategory":"Specialty",
            "type":"Retail Goods"
        },
        {
            "category":"Food & Beverages",
            "subcategory":"Fruits & Vegetables",
            "type":"Retail Goods"
        },
        {
            "category":"Shopping",
            "subcategory":"Pharmacy",
            "type":"Retail Goods"
        }
    ],
    "sg:phone":"+1 412 288 4600",
    "sg:postcode":"60605",
    "sg:province":"IL",
    "sg:tags":[
        "product",
        "wellness",
        "vitamin",
        "diet",
        "supplement",
        "health",
        "herb"
    ],
    "sg:website":"http://www.gnc.com",
    "wof:name":"GNC",
    "wof:placetype":"venue"
},
  "geometry": {"coordinates":[-87.629149,41.873068],"type":"Point"}
}