{
  "type": "Feature",
  "properties": {
    "iso:country":"US",
    "sg:address":"3101 W Devon Ave",
    "sg:city":"Chicago",
    "sg:classifiers":[
        {
            "category":"Health Services",
            "subcategory":"Doctor",
            "type":"Services"
        }
    ],
    "sg:phone":"+1 773 274 9000",
    "sg:postcode":"60659",
    "sg:province":"IL",
    "sg:tags":[
        "physician",
        "surgeon"
    ],
    "wof:name":"Devon-Albany Medical Ctr",
    "wof:placetype":"venue"
},
  "geometry": {"coordinates":[-87.706942,41.997431],"type":"Point"}
}