{
  "type": "Feature",
  "properties": {
    "addr:full":"128 N 6th St Geneva IL 60134",
    "addr:housenumber":"128",
    "addr:postcode":"60134",
    "addr:street":"N 6Th St",
    "iso:country":"US",
    "sg:address":"128 N 6th St",
    "sg:city":"Geneva",
    "sg:classifiers":[
        {
            "category":"Building & Trades",
            "subcategory":"Construction",
            "type":"Services"
        }
    ],
    "sg:phone":"+1 630 232 4802",
    "sg:postcode":"60134",
    "sg:province":"IL",
    "sg:tags":[
        "contractor",
        "painting",
        "hanging"
    ],
    "wof:name":"The Emmett Group",
    "wof:placetype":"venue"
},
  "geometry": {"coordinates":[-88.31163599999999,41.889811],"type":"Point"}
}