{
  "type": "Feature",
  "properties": {
    "iso:country":"US",
    "sg:address":"311 W Depot St Ste H",
    "sg:city":"Antioch",
    "sg:classifiers":[
        {
            "category":"Health Services",
            "subcategory":"Doctor",
            "type":"Services"
        }
    ],
    "sg:phone":"+1 847 395 5854",
    "sg:postcode":"60002",
    "sg:province":"IL",
    "wof:name":"Fresenius Medical",
    "wof:placetype":"venue"
},
  "geometry": {"coordinates":[-88.099475,42.480653],"type":"Point"}
}