{
  "type": "Feature",
  "properties": {
    "addr:full":"61 Otis Rd Barrington IL 60010",
    "addr:housenumber":"61",
    "addr:postcode":"60010",
    "addr:street":"Otis Rd",
    "iso:country":"US",
    "sg:address":"61 Otis Rd",
    "sg:city":"Barrington",
    "sg:classifiers":[
        {
            "category":"Professional",
            "type":"Services"
        }
    ],
    "sg:phone":"+1 847 382 3055",
    "sg:postcode":"60010",
    "sg:province":"IL",
    "wof:name":"Palmer Concept Prod",
    "wof:placetype":"venue"
},
  "geometry": {"coordinates":[-88.155694,42.139109],"type":"Point"}
}