{
  "type": "Feature",
  "properties": {
    "iso:country":"US",
    "sg:address":"15949 Telegraph Rd",
    "sg:city":"Pecatonica",
    "sg:classifiers":[
        {
            "category":"Building & Trades",
            "subcategory":"Plumbing",
            "type":"Services"
        }
    ],
    "sg:phone":"+1 815 239 2731",
    "sg:postcode":"61063",
    "sg:province":"IL",
    "sg:tags":[
        "plumbing",
        "contractor",
        "general"
    ],
    "wof:name":"Dale's Plumbing",
    "wof:placetype":"venue"
},
  "geometry": {"coordinates":[-89.348488,42.311552],"type":"Point"}
}