{
  "type": "Feature",
  "properties": {
    "iso:country":"US",
    "sg:address":"2423 S Austin Blvd",
    "sg:city":"Cicero",
    "sg:classifiers":[
        {
            "category":"Health Services",
            "subcategory":"Health Practitioner",
            "type":"Services"
        }
    ],
    "sg:phone":"+1 708 863 2272",
    "sg:postcode":"60804",
    "sg:province":"IL",
    "sg:tags":[
        "gambling",
        "addiction-information",
        "treatment"
    ],
    "wof:name":"Dept of Rehabilitation Services Wsase",
    "wof:placetype":"venue"
},
  "geometry": {"coordinates":[-87.77360299999999,41.846784],"type":"Point"}
}