{
  "type": "Feature",
  "properties": {
    "addr:full":"509 11th Ave Orion IL 61273",
    "addr:housenumber":"509",
    "addr:postcode":"61273",
    "addr:street":"11Th Ave",
    "iso:country":"US",
    "sg:address":"509 11th Ave",
    "sg:city":"Orion",
    "sg:classifiers":[
        {
            "category":"Health Services",
            "subcategory":"Doctor",
            "type":"Services"
        }
    ],
    "sg:phone":"+1 309 526 8071",
    "sg:postcode":"61273",
    "sg:province":"IL",
    "sg:tags":[
        "medical"
    ],
    "wof:name":"River Vally Heaslth Care",
    "wof:placetype":"venue"
},
  "geometry": {"coordinates":[-90.378445,41.353708],"type":"Point"}
}