{
  "type": "Feature",
  "properties": {
    "addr:full":"2018 N Prospect Ave Champaign IL 61822",
    "addr:housenumber":"2018",
    "addr:postcode":"61822",
    "addr:street":"N Prospect Ave",
    "iso:country":"US",
    "sg:address":"2018 N Prospect Ave",
    "sg:city":"Champaign",
    "sg:classifiers":[
        {
            "category":"Personal",
            "subcategory":"Tanning Parlor",
            "type":"Services"
        },
        {
            "category":"Personal",
            "subcategory":"Barber",
            "type":"Services"
        }
    ],
    "sg:phone":"+1 217 355 8443",
    "sg:postcode":"61822",
    "sg:province":"IL",
    "wof:name":"Cost Cutters Family Hair Care",
    "wof:placetype":"venue"
},
  "geometry": {"coordinates":[-88.257698,40.1399],"type":"Point"}
}