{
  "type": "Feature",
  "properties": {
    "addr:full":"1301 W Main St Peoria IL 61606",
    "addr:housenumber":"1301",
    "addr:postcode":"61606",
    "addr:street":"W Main St",
    "iso:country":"US",
    "sg:address":"1301 W Main St",
    "sg:city":"Peoria",
    "sg:classifiers":[
        {
            "category":"Restaurant",
            "type":"Food & Drink"
        }
    ],
    "sg:menulink":"http://www.allmenus.com/il/peoria-city/276133-avantis-italian-restaurant/menu/",
    "sg:phone":"+1 309 674 4923",
    "sg:postcode":"61606",
    "sg:province":"IL",
    "sg:tags":[
        "italian"
    ],
    "wof:name":"Avanti's Italian Restaurant",
    "wof:placetype":"venue"
},
  "geometry": {"coordinates":[-89.613339,40.699895],"type":"Point"}
}