{
  "type": "Feature",
  "properties": {
    "addr:full":"3443 W 71st St Chicago IL 60629",
    "addr:housenumber":"3443",
    "addr:postcode":"60629",
    "addr:street":"W 71St St",
    "iso:country":"US",
    "sg:address":"3443 W 71st St",
    "sg:city":"Chicago",
    "sg:classifiers":[
        {
            "category":"Building & Trades",
            "subcategory":"Construction",
            "type":"Services"
        }
    ],
    "sg:phone":"+1 773 927 8700",
    "sg:postcode":"60629",
    "sg:province":"IL",
    "sg:tags":[
        "roofing",
        "contractor"
    ],
    "wof:name":"A Affiliated Roofing Co",
    "wof:placetype":"venue"
},
  "geometry": {"coordinates":[-87.708737,41.764302],"type":"Point"}
}