{
  "type": "Feature",
  "properties": {
    "iso:country":"US",
    "sg:address":"841 N Galena Ave # 200",
    "sg:city":"Dixon",
    "sg:classifiers":[
        {
            "category":"Health Services",
            "subcategory":"Doctor",
            "type":"Services"
        }
    ],
    "sg:phone":"+1 815 285 2273",
    "sg:postcode":"61021",
    "sg:province":"IL",
    "sg:tags":[
        "physician",
        "surgeon"
    ],
    "wof:name":"Now Care",
    "wof:placetype":"venue"
},
  "geometry": {"coordinates":[-89.48813699999999,41.854779],"type":"Point"}
}