{
  "type": "Feature",
  "properties": {
    "iso:country":"US",
    "sg:address":"2944 Alexander Cres",
    "sg:city":"Flossmoor",
    "sg:classifiers":[
        {
            "category":"Professional",
            "subcategory":"Business Services",
            "type":"Services"
        }
    ],
    "sg:phone":"+1 708 922 0210",
    "sg:postcode":"60422",
    "sg:province":"IL",
    "wof:name":"First Steps",
    "wof:placetype":"venue"
},
  "geometry": {"coordinates":[-87.685627,41.53259],"type":"Point"}
}