{
  "type": "Feature",
  "properties": {
    "addr:full":"730 Maine St Quincy IL 62301",
    "addr:housenumber":"730",
    "addr:postcode":"62301",
    "addr:street":"Maine St",
    "iso:country":"US",
    "sg:address":"730 Maine St",
    "sg:city":"Quincy",
    "sg:classifiers":[
        {
            "category":"Utilities",
            "subcategory":"Water",
            "type":"Services"
        }
    ],
    "sg:phone":"+1 217 228 4500",
    "sg:postcode":"62301",
    "sg:province":"IL",
    "sg:tags":[
        "department",
        "municipal"
    ],
    "wof:name":"Quincy City Water Department",
    "wof:placetype":"venue"
},
  "geometry": {"coordinates":[-91.40437799999999,39.931822],"type":"Point"}
}