{
  "type": "Feature",
  "properties": {
    "addr:full":"340 Longfellow Dr Wheaton IL 60187",
    "addr:housenumber":"340",
    "addr:postcode":"60187",
    "addr:street":"Longfellow Dr",
    "iso:country":"US",
    "sg:address":"340 Longfellow Dr",
    "sg:city":"Wheaton",
    "sg:classifiers":[
        {
            "category":"Banks & Credit Unions",
            "subcategory":"Bank",
            "type":"Services"
        }
    ],
    "sg:phone":"+1 630 690 0569",
    "sg:postcode":"60187",
    "sg:province":"IL",
    "sg:tags":[
        "mortgage"
    ],
    "wof:name":"Thomas Tran",
    "wof:placetype":"venue"
},
  "geometry": {"coordinates":[-88.10118,41.84467],"type":"Point"}
}