{
  "type": "Feature",
  "properties": {
    "iso:country":"US",
    "sg:address":"4616 N Kedzie Ave",
    "sg:city":"Chicago",
    "sg:classifiers":[
        {
            "category":"Food & Beverages",
            "subcategory":"Liquor & Beverages",
            "type":"Retail Goods"
        }
    ],
    "sg:phone":"+1 773 267 6210",
    "sg:postcode":"60625",
    "sg:province":"IL",
    "sg:tags":[
        "beer",
        "spirit",
        "store",
        "wine"
    ],
    "wof:name":"Foremost Liquor Stores",
    "wof:placetype":"venue"
},
  "geometry": {"coordinates":[-87.708298,41.965302],"type":"Point"}
}