{
  "type": "Feature",
  "properties": {
    "iso:country":"US",
    "sg:address":"6048 Broadcast Pkwy",
    "sg:city":"Loves Park",
    "sg:classifiers":[
        {
            "category":"Professional",
            "subcategory":"Advertising",
            "type":"Services"
        }
    ],
    "sg:phone":"+1 815 997 1460",
    "sg:postcode":"61111",
    "sg:province":"IL",
    "sg:tags":[
        "guide"
    ],
    "sg:website":"www.yellowbook.com",
    "wof:name":"Yellow Book USA",
    "wof:placetype":"venue"
},
  "geometry": {"coordinates":[-88.99808299999999,42.32489],"type":"Point"}
}