{
  "type": "Feature",
  "properties": {
    "iso:country":"US",
    "sg:address":"694 Grand Ave",
    "sg:city":"Elgin",
    "sg:classifiers":[
        {
            "category":"Real Estate",
            "subcategory":"Real Estate Agent",
            "type":"Services"
        }
    ],
    "sg:phone":"+1 847 343 4226",
    "sg:postcode":"60120",
    "sg:province":"IL",
    "sg:tags":[
        "appraiser"
    ],
    "wof:name":"Rwp & Assoc Inc",
    "wof:placetype":"venue"
},
  "geometry": {"coordinates":[-88.26199800000001,42.044964],"type":"Point"}
}