{
  "type": "Feature",
  "properties": {
    "iso:country":"US",
    "sg:address":"2706 46th Ave",
    "sg:city":"Rock Island",
    "sg:classifiers":[
        {
            "category":"Wholesale",
            "subcategory":"Machinery & Supplies",
            "type":"Manufacturing & Wholesale Goods"
        }
    ],
    "sg:phone":"+1 309 794 1615",
    "sg:postcode":"61201",
    "sg:province":"IL",
    "wof:name":"Lesco Service Center 601",
    "wof:placetype":"venue"
},
  "geometry": {"coordinates":[-90.560605,41.464537],"type":"Point"}
}