{
  "type": "Feature",
  "properties": {
    "addr:full":"275 S Canal St Chicago IL 60607",
    "addr:housenumber":"275",
    "addr:postcode":"60607",
    "addr:street":"S Canal St",
    "iso:country":"US",
    "sg:address":"275 S Canal St",
    "sg:city":"Chicago",
    "sg:classifiers":[
        {
            "category":"Building & Trades",
            "subcategory":"Locksmith",
            "type":"Services"
        }
    ],
    "sg:phone":"+1 773 253 3990",
    "sg:postcode":"60607",
    "sg:province":"IL",
    "sg:tags":[
        "key"
    ],
    "wof:name":"007 Locksmith Services 24 7",
    "wof:placetype":"venue"
},
  "geometry": {"coordinates":[-87.639416,41.878354],"type":"Point"}
}