{
  "type": "Feature",
  "properties": {
    "iso:country":"US",
    "sg:address":"2982 W Wadsworth Rd",
    "sg:city":"Waukegan",
    "sg:classifiers":[
        {
            "category":"Autos & Motor Vehicles",
            "subcategory":"Recreational Vehicle Sales",
            "type":"Retail Goods"
        }
    ],
    "sg:phone":"+1 847 244 5590",
    "sg:postcode":"60087",
    "sg:province":"IL",
    "sg:tags":[
        "canopy",
        "shell",
        "truck",
        "cap"
    ],
    "wof:name":"Bell's Ultimate Truck Outfttrs",
    "wof:placetype":"venue"
},
  "geometry": {"coordinates":[-87.873922,42.428479],"type":"Point"}
}