{
  "type": "Feature",
  "properties": {
    "addr:full":"1749 W Golf Rd Mount Prospect IL 60056",
    "addr:housenumber":"1749",
    "addr:postcode":"60056",
    "addr:street":"W Golf Rd",
    "iso:country":"US",
    "sg:address":"1749 W Golf Rd",
    "sg:city":"Mount Prospect",
    "sg:classifiers":[
        {
            "category":"Insurance",
            "subcategory":"Insurance Agent",
            "type":"Services"
        }
    ],
    "sg:phone":"+1 847 217 5444",
    "sg:postcode":"60056",
    "sg:province":"IL",
    "wof:name":"Go One Marketing Group",
    "wof:placetype":"venue"
},
  "geometry": {"coordinates":[-87.96220599999999,42.048413],"type":"Point"}
}