{
  "type": "Feature",
  "properties": {
    "addr:full":"1701 S Prospect Ave Champaign IL 61820",
    "addr:housenumber":"1701",
    "addr:postcode":"61820",
    "addr:street":"S Prospect Ave",
    "iso:country":"US",
    "sg:address":"1701 S Prospect Ave",
    "sg:city":"Champaign",
    "sg:classifiers":[
        {
            "category":"Health Services",
            "subcategory":"Dentist",
            "type":"Services"
        }
    ],
    "sg:phone":"+1 217 352 4100",
    "sg:postcode":"61820",
    "sg:province":"IL",
    "wof:name":"Ruffatto Michael R DMD",
    "wof:placetype":"venue"
},
  "geometry": {"coordinates":[-88.257784,40.096333],"type":"Point"}
}