{
  "type": "Feature",
  "properties": {
    "addr:full":"2015 W Randolph St Vandalia IL 62471",
    "addr:housenumber":"2015",
    "addr:postcode":"62471",
    "addr:street":"W Randolph St",
    "iso:country":"US",
    "sg:address":"2015 W Randolph St",
    "sg:city":"Vandalia",
    "sg:classifiers":[
        {
            "category":"Personal",
            "subcategory":"Beauty Salon",
            "type":"Services"
        }
    ],
    "sg:phone":"+1 618 283 2299",
    "sg:postcode":"62471",
    "sg:province":"IL",
    "sg:tags":[
        "shop"
    ],
    "wof:name":"Hair Company",
    "wof:placetype":"venue"
},
  "geometry": {"coordinates":[-89.11619399999999,38.964278],"type":"Point"}
}