{
  "type": "Feature",
  "properties": {
    "addr:full":"1205 W Morton Ave Jacksonville IL 62650",
    "addr:housenumber":"1205",
    "addr:postcode":"62650",
    "addr:street":"W Morton Ave",
    "iso:country":"US",
    "sg:address":"1205 W Morton Ave",
    "sg:city":"Jacksonville",
    "sg:classifiers":[
        {
            "category":"Restaurant",
            "type":"Food & Drink"
        }
    ],
    "sg:menulink":"http://www.allmenus.com/il/jacksonville-no-11/126618-subway/menu/",
    "sg:phone":"+1 217 291 0705",
    "sg:postcode":"62650",
    "sg:province":"IL",
    "sg:tags":[
        "american",
        "sandwich"
    ],
    "wof:name":"Subway",
    "wof:placetype":"venue"
},
  "geometry": {"coordinates":[-90.248099,39.7232],"type":"Point"}
}