{
  "type": "Feature",
  "properties": {
    "addr:full":"361 Town Sq Wheaton IL 60187",
    "addr:housenumber":"361",
    "addr:postcode":"60187",
    "addr:street":"Town Sq",
    "iso:country":"US",
    "sg:address":"361 Town Sq",
    "sg:city":"Wheaton",
    "sg:classifiers":[
        {
            "category":"Shopping",
            "subcategory":"Jewelry",
            "type":"Retail Goods"
        }
    ],
    "sg:phone":"+1   ",
    "sg:postcode":"60187",
    "sg:province":"IL",
    "wof:name":"Altobello Fine Jewelers",
    "wof:placetype":"venue"
},
  "geometry": {"coordinates":[-88.100746,41.835473],"type":"Point"}
}