{
  "type": "Feature",
  "properties": {
    "addr:full":"2485 Anderson Dr Belvidere IL 61008",
    "addr:housenumber":"2485",
    "addr:postcode":"61008",
    "addr:street":"Anderson Dr",
    "iso:country":"US",
    "sg:address":"2485 Anderson Dr",
    "sg:city":"Belvidere",
    "sg:classifiers":[
        {
            "category":"Personal",
            "subcategory":"Beauty Salon",
            "type":"Services"
        }
    ],
    "sg:phone":"+1 815 547 7616",
    "sg:postcode":"61008",
    "sg:province":"IL",
    "wof:name":"Aileen & Co Hair Nails",
    "wof:placetype":"venue"
},
  "geometry": {"coordinates":[-88.891391,42.272759],"type":"Point"}
}