{
  "type": "Feature",
  "properties": {
    "addr:full":"3853 E State St Rockford IL 61108",
    "addr:housenumber":"3853",
    "addr:postcode":"61108",
    "addr:street":"E State St",
    "iso:country":"US",
    "sg:address":"3853 E State St",
    "sg:city":"Rockford",
    "sg:classifiers":[
        {
            "category":"Banks & Credit Unions",
            "subcategory":"Bank",
            "type":"Services"
        }
    ],
    "sg:phone":"+1 815 231 0055",
    "sg:postcode":"61108",
    "sg:province":"IL",
    "sg:tags":[
        "loan"
    ],
    "wof:name":"Heights Finance Corp",
    "wof:placetype":"venue"
},
  "geometry": {"coordinates":[-89.029906,42.264187],"type":"Point"}
}