{
  "type": "Feature",
  "properties": {
    "iso:country":"US",
    "sg:address":"960 Woodlands Pkwy",
    "sg:city":"Vernon Hills",
    "sg:classifiers":[
        {
            "category":"Building & Trades",
            "subcategory":"Equipment Rental",
            "type":"Services"
        }
    ],
    "sg:phone":"+1 847 913 1511",
    "sg:postcode":"60061",
    "sg:province":"IL",
    "sg:tags":[
        "leasing"
    ],
    "wof:name":"Rent A Lab",
    "wof:placetype":"venue"
},
  "geometry": {"coordinates":[-87.938977,42.208092],"type":"Point"}
}