{
  "type": "Feature",
  "properties": {
    "addr:full":"250 E Maple St New Lenox IL 60451",
    "addr:housenumber":"250",
    "addr:postcode":"60451",
    "addr:street":"E Maple St",
    "iso:country":"US",
    "sg:address":"250 E Maple St",
    "sg:city":"New Lenox",
    "sg:classifiers":[
        {
            "category":"Health Services",
            "subcategory":"Health Practitioner",
            "type":"Services"
        }
    ],
    "sg:phone":"+1 815 463 6123",
    "sg:postcode":"60451",
    "sg:province":"IL",
    "sg:tags":[
        "therapist",
        "physical"
    ],
    "wof:name":"Silver Cross Medworks",
    "wof:placetype":"venue"
},
  "geometry": {"coordinates":[-87.96526,41.513609],"type":"Point"}
}