{
  "type": "Feature",
  "properties": {
    "addr:full":"1610 N Co Rd 1200 Hamilton IL 62341",
    "addr:housenumber":"1610",
    "addr:postcode":"62341",
    "addr:street":"N Co Rd 1200",
    "iso:country":"US",
    "sg:address":"1610 N Co Rd 1200",
    "sg:city":"Hamilton",
    "sg:classifiers":[
        {
            "category":"Real Estate",
            "subcategory":"Real Estate Operator",
            "type":"Services"
        }
    ],
    "sg:phone":"+1 217 845 4311",
    "sg:postcode":"62341",
    "sg:province":"IL",
    "sg:tags":[
        "property",
        "lessor"
    ],
    "wof:name":"Harold Iutzi",
    "wof:placetype":"venue"
},
  "geometry": {"coordinates":[-91.27134599999999,40.438789],"type":"Point"}
}