{
  "type": "Feature",
  "properties": {
    "iso:country":"US",
    "sg:address":"805 W Jefferson St",
    "sg:city":"Shorewood",
    "sg:classifiers":[
        {
            "category":"Shopping",
            "subcategory":"Jewelry",
            "type":"Retail Goods"
        }
    ],
    "sg:phone":"+1 815 744 6000",
    "sg:postcode":"60435",
    "sg:province":"IL",
    "sg:tags":[
        "jeweler"
    ],
    "wof:name":"Spencer's Jewelry",
    "wof:placetype":"venue"
},
  "geometry": {"coordinates":[-88.101597,41.523289],"type":"Point"}
}