{
  "type": "Feature",
  "properties": {
    "iso:country":"US",
    "sg:address":"19990 Hidden Lakes Ln",
    "sg:city":"Brighton",
    "sg:classifiers":[
        {
            "category":"Manufacturing",
            "subcategory":"Food",
            "type":"Manufacturing & Wholesale Goods"
        },
        {
            "category":"Farming",
            "subcategory":"Farm",
            "type":"Manufacturing & Wholesale Goods"
        }
    ],
    "sg:phone":"+1 618 372 3225",
    "sg:postcode":"62012",
    "sg:province":"IL",
    "sg:tags":[
        "corn",
        "product"
    ],
    "wof:name":"Herbert Rothe",
    "wof:placetype":"venue"
},
  "geometry": {"coordinates":[-90.174059,39.072769],"type":"Point"}
}