{
  "type": "Feature",
  "properties": {
    "addr:full":"21 N Wabash Ave Ste 1 Chicago IL 60602",
    "addr:housenumber":"21",
    "addr:postcode":"60602",
    "addr:street":"N Wabash Ave Ste 1",
    "iso:country":"US",
    "sg:address":"21 N Wabash Ave Ste 1",
    "sg:city":"Chicago",
    "sg:classifiers":[
        {
            "category":"Shopping",
            "subcategory":"Jewelry",
            "type":"Retail Goods"
        }
    ],
    "sg:phone":"+1 312 750 0940",
    "sg:postcode":"60602",
    "sg:province":"IL",
    "sg:website":"www.DonnaJewelryCo.com",
    "wof:name":"Donna Jewelry Co",
    "wof:placetype":"venue"
},
  "geometry": {"coordinates":[-87.626181,41.882751],"type":"Point"}
}