{
  "type": "Feature",
  "properties": {
    "iso:country":"US",
    "sg:address":"7778 E Lindenwood Rd",
    "sg:city":"Chana",
    "sg:classifiers":[
        {
            "category":"Building & Trades",
            "subcategory":"Construction",
            "type":"Services"
        }
    ],
    "sg:phone":"+1 815 645 8027",
    "sg:postcode":"61015",
    "sg:province":"IL",
    "sg:tags":[
        "house"
    ],
    "wof:name":"Lantz Construction",
    "wof:placetype":"venue"
},
  "geometry": {"coordinates":[-89.186736,42.033987],"type":"Point"}
}