{
  "type": "Feature",
  "properties": {
    "addr:full":"26161 W Cuba Rd Barrington IL 60010",
    "addr:housenumber":"26161",
    "addr:postcode":"60010",
    "addr:street":"W Cuba Rd",
    "iso:country":"US",
    "sg:address":"26161 W Cuba Rd",
    "sg:city":"Barrington",
    "sg:classifiers":[
        {
            "category":"Professional",
            "subcategory":"Business Services",
            "type":"Services"
        }
    ],
    "sg:phone":"+1 847 304 6903",
    "sg:postcode":"60010",
    "sg:province":"IL",
    "sg:tags":[
        "interior",
        "consultant",
        "design",
        "decorator"
    ],
    "wof:name":"No Problem Decorating & Constr",
    "wof:placetype":"venue"
},
  "geometry": {"coordinates":[-88.14321700000001,42.175873],"type":"Point"}
}