{
  "type": "Feature",
  "properties": {
    "addr:full":"1467 W Montrose Ave Chicago IL 60613",
    "addr:housenumber":"1467",
    "addr:postcode":"60613",
    "addr:street":"W Montrose Ave",
    "iso:country":"US",
    "sg:address":"1467 W Montrose Ave",
    "sg:city":"Chicago",
    "sg:classifiers":[
        {
            "category":"Restaurant",
            "type":"Food & Drink"
        }
    ],
    "sg:menulink":"http://www.allmenus.com/il/chicago/20941-andies/menu/",
    "sg:phone":"+1 773 348 0654",
    "sg:postcode":"60613",
    "sg:province":"IL",
    "sg:tags":[
        "mediterranean"
    ],
    "wof:name":"Andies",
    "wof:placetype":"venue"
},
  "geometry": {"coordinates":[-87.667064,41.961619],"type":"Point"}
}