{
  "type": "Feature",
  "properties": {
    "addr:full":"2805 Mannheim Rd Franklin Park IL 60131",
    "addr:housenumber":"2805",
    "addr:postcode":"60131",
    "addr:street":"Mannheim Rd",
    "iso:country":"US",
    "sg:address":"2805 Mannheim Rd",
    "sg:city":"Franklin Park",
    "sg:classifiers":[
        {
            "category":"Restaurant",
            "type":"Food & Drink"
        }
    ],
    "sg:menulink":"http://www.allmenus.com/il/leyden/126471-subway/menu/",
    "sg:phone":"+1 847 451 9229",
    "sg:postcode":"60131",
    "sg:province":"IL",
    "sg:tags":[
        "american",
        "sandwich"
    ],
    "wof:name":"Subway",
    "wof:placetype":"venue"
},
  "geometry": {"coordinates":[-87.884604,41.930357],"type":"Point"}
}