{
  "type": "Feature",
  "properties": {
    "iso:country":"US",
    "sg:address":"677 Luda St",
    "sg:city":"Elgin",
    "sg:classifiers":[
        {
            "category":"Organizations",
            "subcategory":"Religious Organization",
            "type":"Services"
        }
    ],
    "sg:phone":"+1 847 742 6636",
    "sg:postcode":"60120",
    "sg:province":"IL",
    "sg:tags":[
        "pentecostal",
        "church"
    ],
    "wof:name":"Jubilee Christian Centre",
    "wof:placetype":"venue"
},
  "geometry": {"coordinates":[-88.264197,42.060295],"type":"Point"}
}