{
  "type": "Feature",
  "properties": {
    "iso:country":"US",
    "sg:address":"517 Rush St",
    "sg:city":"Roselle",
    "sg:classifiers":[
        {
            "category":"Transit Center",
            "subcategory":"Freight",
            "type":"Transportation"
        },
        {
            "category":"Freight",
            "type":"Transportation"
        }
    ],
    "sg:phone":"+1 630 307 8370",
    "sg:postcode":"60172",
    "sg:province":"IL",
    "sg:tags":[
        "local",
        "trucking-motor",
        "trucking"
    ],
    "wof:name":"Kacper Trucking",
    "wof:placetype":"venue"
},
  "geometry": {"coordinates":[-88.07481799999999,41.974401],"type":"Point"}
}