{
  "type": "Feature",
  "properties": {
    "iso:country":"US",
    "sg:address":"1111 3rd St",
    "sg:city":"Orion",
    "sg:classifiers":[
        {
            "category":"Professional",
            "subcategory":"Business Services",
            "type":"Services"
        }
    ],
    "sg:phone":"+1 309 526 3331",
    "sg:postcode":"61273",
    "sg:province":"IL",
    "sg:tags":[
        "license"
    ],
    "wof:name":"Welborn Licensing Svc",
    "wof:placetype":"venue"
},
  "geometry": {"coordinates":[-90.382864,41.353656],"type":"Point"}
}