{
  "type": "Feature",
  "properties": {
    "addr:full":"7385 Waterford Dr Rockford IL 61108",
    "addr:housenumber":"7385",
    "addr:postcode":"61108",
    "addr:street":"Waterford Dr",
    "iso:country":"US",
    "sg:address":"7385 Waterford Dr",
    "sg:city":"Rockford",
    "sg:classifiers":[
        {
            "category":"Professional",
            "subcategory":"Accounting & Tax Preparation",
            "type":"Services"
        }
    ],
    "sg:phone":"+1 815 398 8010",
    "sg:postcode":"61108",
    "sg:province":"IL",
    "sg:tags":[
        "consultant",
        "return"
    ],
    "wof:name":"Carlson Tax & Financial Ser",
    "wof:placetype":"venue"
},
  "geometry": {"coordinates":[-88.972802,42.260223],"type":"Point"}
}