{
  "type": "Feature",
  "properties": {
    "iso:country":"US",
    "sg:address":"618 Jackson Ave",
    "sg:city":"Charleston",
    "sg:classifiers":[
        {
            "category":"Manufacturing",
            "subcategory":"Retail Goods",
            "type":"Manufacturing & Wholesale Goods"
        }
    ],
    "sg:phone":"+1 217 348 0401",
    "sg:postcode":"61920",
    "sg:province":"IL",
    "sg:tags":[
        "lead",
        "mfg"
    ],
    "wof:name":"Girls In Mist Inc",
    "wof:placetype":"venue"
},
  "geometry": {"coordinates":[-88.174664,39.494488],"type":"Point"}
}