{
  "type": "Feature",
  "properties": {
    "iso:country":"US",
    "sg:address":"8006 Lincoln Ave",
    "sg:city":"Skokie",
    "sg:classifiers":[
        {
            "category":"Shopping",
            "subcategory":"Pharmacy",
            "type":"Retail Goods"
        }
    ],
    "sg:phone":"+1   ",
    "sg:postcode":"60077",
    "sg:province":"IL",
    "wof:name":"Oakton Drug Co",
    "wof:placetype":"venue"
},
  "geometry": {"coordinates":[-87.75467,42.027063],"type":"Point"}
}