{
  "type": "Feature",
  "properties": {
    "addr:full":"123 N Bench St Galena IL 61036",
    "addr:housenumber":"123",
    "addr:postcode":"61036",
    "addr:street":"N Bench St",
    "iso:country":"US",
    "sg:address":"123 N Bench St",
    "sg:city":"Galena",
    "sg:classifiers":[
        {
            "category":"Health Services",
            "subcategory":"Doctor",
            "type":"Services"
        }
    ],
    "sg:phone":"+1 815 777 0449",
    "sg:postcode":"61036",
    "sg:province":"IL",
    "sg:tags":[
        "dentist"
    ],
    "wof:name":"Robert F Chorak DDS",
    "wof:placetype":"venue"
},
  "geometry": {"coordinates":[-90.42794499999999,42.417184],"type":"Point"}
}