{
  "type": "Feature",
  "properties": {
    "iso:country":"US",
    "sg:address":"1102 Morse Ave",
    "sg:city":"Schaumburg",
    "sg:classifiers":[
        {
            "category":"Home & Garden",
            "subcategory":"Furniture",
            "type":"Retail Goods"
        }
    ],
    "sg:phone":"+1   ",
    "sg:postcode":"60193",
    "sg:province":"IL",
    "wof:name":"Counter Designs LTD",
    "wof:placetype":"venue"
},
  "geometry": {"coordinates":[-88.105164,42.00012],"type":"Point"}
}