{
  "type": "Feature",
  "properties": {
    "iso:country":"US",
    "sg:address":"504 N 58th St",
    "sg:city":"East Saint Louis",
    "sg:classifiers":[
        {
            "category":"Shopping",
            "subcategory":"Catalog Store",
            "type":"Retail Goods"
        }
    ],
    "sg:phone":"+1   ",
    "sg:postcode":"62203",
    "sg:province":"IL",
    "sg:tags":[
        "house",
        "mail"
    ],
    "wof:name":"Global Image Special Gifts",
    "wof:placetype":"venue"
},
  "geometry": {"coordinates":[-90.093628,38.604408],"type":"Point"}
}