{
  "type": "Feature",
  "properties": {
    "addr:full":"6914 S Western Ave Chicago IL 60636",
    "addr:housenumber":"6914",
    "addr:postcode":"60636",
    "addr:street":"S Western Ave",
    "iso:country":"US",
    "sg:address":"6914 S Western Ave",
    "sg:city":"Chicago",
    "sg:classifiers":[
        {
            "category":"Food & Beverages",
            "subcategory":"Liquor & Beverages",
            "type":"Retail Goods"
        }
    ],
    "sg:phone":"+1 773 776 8496",
    "sg:postcode":"60636",
    "sg:province":"IL",
    "sg:tags":[
        "beer",
        "spirit",
        "wine"
    ],
    "wof:name":"Issa Food & Liquor",
    "wof:placetype":"venue"
},
  "geometry": {"coordinates":[-87.683403,41.7673],"type":"Point"}
}