{
  "type": "Feature",
  "properties": {
    "iso:country":"US",
    "sg:address":"799 Roosevelt Rd",
    "sg:city":"Glen Ellyn",
    "sg:classifiers":[
        {
            "category":"Banks & Credit Unions",
            "subcategory":"Financial Services",
            "type":"Services"
        }
    ],
    "sg:phone":"+1 630 790 4600",
    "sg:postcode":"60137",
    "sg:province":"IL",
    "sg:tags":[
        "broker",
        "mortgage"
    ],
    "wof:name":"Trinity Mortgage Company",
    "wof:placetype":"venue"
},
  "geometry": {"coordinates":[-88.052803,41.859402],"type":"Point"}
}