{
  "type": "Feature",
  "properties": {
    "addr:full":"150 W Vienna St Anna IL 62906",
    "addr:housenumber":"150",
    "addr:postcode":"62906",
    "addr:street":"W Vienna",
    "iso:country":"US",
    "sg:address":"150 W Vienna St",
    "sg:city":"Anna",
    "sg:classifiers":[
        {
            "category":"Home & Garden",
            "subcategory":"Garden Supply",
            "type":"Retail Goods"
        }
    ],
    "sg:phone":"+1 618 833 7657",
    "sg:postcode":"62906",
    "sg:province":"IL",
    "sg:tags":[
        "equipment",
        "industrial"
    ],
    "wof:name":"A J Lawn & Garden",
    "wof:placetype":"venue"
},
  "geometry": {"coordinates":[-89.248317,37.461148],"type":"Point"}
}