{
  "type": "Feature",
  "properties": {
    "addr:full":"8012 S Crandon Ave Chicago IL 60617",
    "addr:housenumber":"8012",
    "addr:postcode":"60617",
    "addr:street":"S Crandon Ave",
    "iso:country":"US",
    "sg:address":"8012 S Crandon Ave",
    "sg:city":"Chicago",
    "sg:classifiers":[
        {
            "category":"Health Services",
            "subcategory":"Doctor",
            "type":"Services"
        }
    ],
    "sg:phone":"+1 773 734 1117",
    "sg:postcode":"60617",
    "sg:province":"IL",
    "sg:tags":[
        "cardiologist"
    ],
    "wof:name":"South Shore Cardiology Group",
    "wof:placetype":"venue"
},
  "geometry": {"coordinates":[-87.568703,41.749699],"type":"Point"}
}