{
  "type": "Feature",
  "properties": {
    "iso:country":"US",
    "sg:address":"585 6th St",
    "sg:city":"La Salle",
    "sg:classifiers":[
        {
            "category":"Freight",
            "type":"Transportation"
        }
    ],
    "sg:phone":"+1 815 223 4802",
    "sg:postcode":"61301",
    "sg:province":"IL",
    "sg:tags":[
        "consultant"
    ],
    "wof:name":"Zibert Transport Co",
    "wof:placetype":"venue"
},
  "geometry": {"coordinates":[-89.098828,41.333447],"type":"Point"}
}