{
  "type": "Feature",
  "properties": {
    "addr:full":"1052 W Monroe St Chicago IL 60607",
    "addr:housenumber":"1052",
    "addr:postcode":"60607",
    "addr:street":"W Monroe St",
    "iso:country":"US",
    "sg:address":"1052 W Monroe St",
    "sg:city":"Chicago",
    "sg:classifiers":[
        {
            "category":"Restaurant",
            "type":"Food & Drink"
        }
    ],
    "sg:menulink":"http://www.allmenus.com/il/chicago/272891-carmichaels-chicago-steakhouse/menu/",
    "sg:phone":"+1 312 433 0025",
    "sg:postcode":"60607",
    "sg:province":"IL",
    "sg:tags":[
        "american",
        "steakhouse"
    ],
    "wof:name":"Carmichael's Chicago Steakhouse",
    "wof:placetype":"venue"
},
  "geometry": {"coordinates":[-87.653381,41.880529],"type":"Point"}
}