{
  "type": "Feature",
  "properties": {
    "addr:full":"1900 E Perkins Rd Urbana IL 61802",
    "addr:housenumber":"1900",
    "addr:postcode":"61802",
    "addr:street":"E Perkins Rd",
    "iso:country":"US",
    "sg:address":"1900 E Perkins Rd",
    "sg:city":"Urbana",
    "sg:classifiers":[
        {
            "category":"Professional",
            "subcategory":"Employment Agencies",
            "type":"Services"
        }
    ],
    "sg:phone":"+1 217 384 0109",
    "sg:postcode":"61802",
    "sg:province":"IL",
    "sg:tags":[
        "opportunity"
    ],
    "wof:name":"Wolf Exec Search Inc",
    "wof:placetype":"venue"
},
  "geometry": {"coordinates":[-88.18507,40.127476],"type":"Point"}
}