{
  "type": "Feature",
  "properties": {
    "iso:country":"US",
    "sg:address":"14115 S Bell Rd",
    "sg:city":"Homer Glen",
    "sg:classifiers":[
        {
            "category":"Restaurant",
            "type":"Food & Drink"
        }
    ],
    "sg:phone":"+1 708 301 9206",
    "sg:postcode":"60491",
    "sg:province":"IL",
    "wof:name":"Wendy's",
    "wof:placetype":"venue"
},
  "geometry": {"coordinates":[-87.931169,41.630401],"type":"Point"}
}