{
  "type": "Feature",
  "properties": {
    "iso:country":"US",
    "sg:address":"185 Detroit St",
    "sg:city":"Cary",
    "sg:classifiers":[
        {
            "category":"Manufacturing",
            "subcategory":"Electronics",
            "type":"Manufacturing & Wholesale Goods"
        }
    ],
    "sg:phone":"+1 847 639 4646",
    "sg:postcode":"60013",
    "sg:province":"IL",
    "sg:tags":[
        "mfg",
        "equipment",
        "musical",
        "instrument",
        "home"
    ],
    "sg:website":"www.morleypedals.com",
    "wof:name":"Sound Enhancements Inc",
    "wof:placetype":"venue"
},
  "geometry": {"coordinates":[-88.232615,42.200248],"type":"Point"}
}