{
  "type": "Feature",
  "properties": {
    "addr:full":"180 N Co Rd 1675E Hindsboro IL 61930",
    "addr:housenumber":"180",
    "addr:postcode":"61930",
    "addr:street":"N Co Rd",
    "iso:country":"US",
    "sg:address":"180 N Co Rd 1675E",
    "sg:city":"Hindsboro",
    "sg:classifiers":[
        {
            "category":"Real Estate",
            "subcategory":"Real Estate Operator",
            "type":"Services"
        }
    ],
    "sg:phone":"+1 217 346 2652",
    "sg:postcode":"61930",
    "sg:province":"IL",
    "sg:tags":[
        "farm",
        "property",
        "lessor",
        "soybean"
    ],
    "wof:name":"Pauline Tuttle",
    "wof:placetype":"venue"
},
  "geometry": {"coordinates":[-88.158373,39.671428],"type":"Point"}
}