{
  "type": "Feature",
  "properties": {
    "iso:country":"US",
    "sg:address":"539 W Diversey Pkwy",
    "sg:city":"Chicago",
    "sg:classifiers":[
        {
            "category":"Personal",
            "subcategory":"Beauty Salon",
            "type":"Services"
        }
    ],
    "sg:phone":"+1 773 281 2926",
    "sg:postcode":"60686",
    "sg:province":"IL",
    "sg:tags":[
        "hair"
    ],
    "wof:name":"Great Clips",
    "wof:placetype":"venue"
},
  "geometry": {"coordinates":[-87.642786,41.932836],"type":"Point"}
}