{
  "type": "Feature",
  "properties": {
    "iso:country":"US",
    "sg:address":"280 Main St",
    "sg:city":"Park Forest",
    "sg:classifiers":[
        {
            "category":"Professional",
            "type":"Services"
        }
    ],
    "sg:phone":"+1 708 283 0951",
    "sg:postcode":"60466",
    "sg:province":"IL",
    "sg:tags":[
        "establishment"
    ],
    "wof:name":"Dunlap & Assoc",
    "wof:placetype":"venue"
},
  "geometry": {"coordinates":[-87.67920599999999,41.483373],"type":"Point"}
}