{
  "type": "Feature",
  "properties": {
    "addr:full":"16771 Torrence Ave Lansing IL 60438",
    "addr:housenumber":"16771",
    "addr:postcode":"60438",
    "addr:street":"Torrence Ave",
    "iso:country":"US",
    "sg:address":"16771 Torrence Ave",
    "sg:city":"Lansing",
    "sg:classifiers":[
        {
            "category":"Personal",
            "subcategory":"Nail Salon",
            "type":"Services"
        }
    ],
    "sg:phone":"+1 708 474 1103",
    "sg:postcode":"60438",
    "sg:province":"IL",
    "sg:website":"www.regalnails.com",
    "wof:name":"Regal Nails",
    "wof:placetype":"venue"
},
  "geometry": {"coordinates":[-87.558459,41.591425],"type":"Point"}
}