{
  "type": "Feature",
  "properties": {
    "iso:country":"US",
    "sg:address":"9517 S Cicero Ave",
    "sg:city":"Oak Lawn",
    "sg:classifiers":[
        {
            "category":"Shopping",
            "subcategory":"Stationery & Office Supplies",
            "type":"Retail Goods"
        }
    ],
    "sg:phone":"+1 708 229 9256",
    "sg:postcode":"60453",
    "sg:province":"IL",
    "sg:tags":[
        "album",
        "scrapbook"
    ],
    "wof:name":"A Scrapbooker's Legacy",
    "wof:placetype":"venue"
},
  "geometry": {"coordinates":[-87.740666,41.71857],"type":"Point"}
}