{
  "type": "Feature",
  "properties": {
    "iso:country":"US",
    "sg:address":"310 S 2nd St",
    "sg:city":"Greenville",
    "sg:classifiers":[
        {
            "category":"Organizations",
            "subcategory":"Religious Organization",
            "type":"Services"
        }
    ],
    "sg:phone":"+1 618 664 1566",
    "sg:postcode":"62246",
    "sg:province":"IL",
    "sg:tags":[
        "clergy"
    ],
    "wof:name":"First United Methodist Church",
    "wof:placetype":"venue"
},
  "geometry": {"coordinates":[-89.412392,38.890473],"type":"Point"}
}