{
  "type": "Feature",
  "properties": {
    "iso:country":"US",
    "sg:address":"708 N Raynor Ave",
    "sg:city":"Joliet",
    "sg:classifiers":[
        {
            "category":"Shopping",
            "subcategory":"Catalog Store",
            "type":"Retail Goods"
        }
    ],
    "sg:phone":"+1   ",
    "sg:postcode":"60435",
    "sg:province":"IL",
    "sg:tags":[
        "mail",
        "house"
    ],
    "wof:name":"Bison Enterprises",
    "wof:placetype":"venue"
},
  "geometry": {"coordinates":[-88.101277,41.536274],"type":"Point"}
}