{
  "type": "Feature",
  "properties": {
    "iso:country":"US",
    "sg:address":"375 Mitchell Ave",
    "sg:city":"Elmhurst",
    "sg:classifiers":[
        {
            "category":"Professional",
            "subcategory":"Art Services",
            "type":"Services"
        }
    ],
    "sg:phone":"+1 630 530 9903",
    "sg:postcode":"60126",
    "sg:province":"IL",
    "sg:tags":[
        "artist"
    ],
    "sg:website":"www.chicagogifts.com",
    "wof:name":"Brad Bennett Studio",
    "wof:placetype":"venue"
},
  "geometry": {"coordinates":[-87.946354,41.889594],"type":"Point"}
}