{
  "type": "Feature",
  "properties": {
    "iso:country":"US",
    "sg:address":"1118 N Laramie Ave",
    "sg:city":"Chicago",
    "sg:classifiers":[
        {
            "category":"Shopping",
            "type":"Retail Goods"
        }
    ],
    "sg:phone":"+1 773 841 1153",
    "sg:postcode":"60651",
    "sg:province":"IL",
    "sg:tags":[
        "merchandise"
    ],
    "wof:name":"Bonds Candy Store",
    "wof:placetype":"venue"
},
  "geometry": {"coordinates":[-87.755735,41.900753],"type":"Point"}
}