{
  "type": "Feature",
  "properties": {
    "iso:country":"US",
    "sg:address":"308 N Central Ave",
    "sg:city":"Casey",
    "sg:classifiers":[
        {
            "category":"Autos & Motor Vehicles",
            "subcategory":"Automobile Sales",
            "type":"Retail Goods"
        }
    ],
    "sg:phone":"+1 217 342 4252",
    "sg:postcode":"62420",
    "sg:province":"IL",
    "sg:tags":[
        "car",
        "dealer"
    ],
    "wof:name":"J Mitchell Auto Ctr",
    "wof:placetype":"venue"
},
  "geometry": {"coordinates":[-87.992859,39.302464],"type":"Point"}
}