{
  "type": "Feature",
  "properties": {
    "addr:full":"1848 N Humboldt Blvd Chicago IL 60647",
    "addr:housenumber":"1848",
    "addr:postcode":"60647",
    "addr:street":"N Humboldt Blvd",
    "iso:country":"US",
    "sg:address":"1848 N Humboldt Blvd",
    "sg:city":"Chicago",
    "sg:classifiers":[
        {
            "category":"Building & Trades",
            "subcategory":"Construction",
            "type":"Services"
        }
    ],
    "sg:phone":"+1 773 252 5292",
    "sg:postcode":"60647",
    "sg:province":"IL",
    "sg:tags":[
        "roofing",
        "contractor"
    ],
    "wof:name":"H & E Roofing & Waterproofing",
    "wof:placetype":"venue"
},
  "geometry": {"coordinates":[-87.70243499999999,41.914762],"type":"Point"}
}