{
  "type": "Feature",
  "properties": {
    "iso:country":"US",
    "sg:address":"1930 N Fairfield #1F",
    "sg:city":"Chicago",
    "sg:classifiers":[
        {
            "category":"Shopping",
            "subcategory":"Clothing, Apparel, & Fashions",
            "type":"Retail Goods"
        }
    ],
    "sg:phone":"+1 773 278 1668",
    "sg:postcode":"60647",
    "sg:province":"IL",
    "sg:tags":[
        "accessory"
    ],
    "sg:website":"www.brynncapella.com",
    "wof:name":"Brynn Capella Handbags",
    "wof:placetype":"venue"
},
  "geometry": {"coordinates":[-87.696275,41.916572],"type":"Point"}
}