{
  "type": "Feature",
  "properties": {
    "addr:full":"457 LAKE COOK RD DEERFIELD IL 60015",
    "addr:housenumber":"457",
    "addr:postcode":"60015",
    "addr:street":"Lake Cook Rd",
    "iso:country":"US",
    "sg:address":"457 LAKE COOK RD",
    "sg:city":"DEERFIELD",
    "sg:classifiers":[
        {
            "category":"Community Center",
            "type":"Public Place"
        },
        {
            "category":"Health Services",
            "subcategory":"Dentist",
            "type":"Services"
        }
    ],
    "sg:phone":"+1 847 847 4496",
    "sg:postcode":"60015",
    "sg:province":"IL",
    "sg:tags":[
        "laboratories-medical",
        "dental",
        "mri",
        "resonance",
        "magnetic",
        "x-ray",
        "imaging"
    ],
    "sg:website":"http://www.uprightmrideerfield.com",
    "wof:name":"Up-Right Imaging Center, LLC",
    "wof:placetype":"venue"
},
  "geometry": {"coordinates":[-87.840344,42.152769],"type":"Point"}
}