{
  "type": "Feature",
  "properties": {
    "addr:full":"1490 E Walnut St Watseka IL 60970",
    "addr:housenumber":"1490",
    "addr:postcode":"60970",
    "addr:street":"E Walnut St",
    "iso:country":"US",
    "sg:address":"1490 E Walnut St",
    "sg:city":"Watseka",
    "sg:classifiers":[
        {
            "category":"Personal",
            "subcategory":"Tanning Parlor",
            "type":"Services"
        },
        {
            "category":"Banks & Credit Unions",
            "subcategory":"Investment Brokerage",
            "type":"Services"
        },
        {
            "category":"Shopping",
            "subcategory":"Computers & Home Electronics",
            "type":"Retail Goods"
        }
    ],
    "sg:phone":"+1 815 432 4386",
    "sg:postcode":"60970",
    "sg:province":"IL",
    "sg:tags":[
        "salon",
        "dvd",
        "sale",
        "dvds-rental",
        "tape",
        "video"
    ],
    "wof:name":"Familifun Video",
    "wof:placetype":"venue"
},
  "geometry": {"coordinates":[-87.703078,40.775392],"type":"Point"}
}