{
  "type": "Feature",
  "properties": {
    "iso:country":"US",
    "sg:address":"4117 5th Ave",
    "sg:city":"Moline",
    "sg:classifiers":[
        {
            "category":"Retail",
            "subcategory":"Auto Repair",
            "type":"Services"
        }
    ],
    "sg:phone":"+1 309 743 0282",
    "sg:postcode":"61265",
    "sg:province":"IL",
    "sg:tags":[
        "body"
    ],
    "wof:name":"Penas Body Shop Inc",
    "wof:placetype":"venue"
},
  "geometry": {"coordinates":[-90.478666,41.510555],"type":"Point"}
}