{
  "type": "Feature",
  "properties": {
    "iso:country":"US",
    "sg:address":"207 Astoria Ct",
    "sg:city":"Barrington",
    "sg:classifiers":[
        {
            "category":"Health Services",
            "subcategory":"Doctor",
            "type":"Services"
        }
    ],
    "sg:phone":"+1 847 228 0712",
    "sg:postcode":"60010",
    "sg:province":"IL",
    "sg:tags":[
        "physician",
        "surgeon"
    ],
    "wof:name":"Steven Pector DO",
    "wof:placetype":"venue"
},
  "geometry": {"coordinates":[-88.140946,42.130284],"type":"Point"}
}