{
  "type": "Feature",
  "properties": {
    "iso:country":"US",
    "sg:address":"479 N Main St Ste 200",
    "sg:city":"Glen Ellyn",
    "sg:classifiers":[
        {
            "category":"Professional",
            "subcategory":"Lawyer & Legal Services",
            "type":"Services"
        }
    ],
    "sg:phone":"+1 630 469 4200",
    "sg:postcode":"60137",
    "sg:province":"IL",
    "wof:name":"Gilbert Jay Atty",
    "wof:placetype":"venue"
},
  "geometry": {"coordinates":[-88.066704,41.876598],"type":"Point"}
}