{
  "type": "Feature",
  "properties": {
    "addr:full":"846 N Menard Ave Chicago IL 60651",
    "addr:housenumber":"846",
    "addr:postcode":"60651",
    "addr:street":"N Menard Ave",
    "iso:country":"US",
    "sg:address":"846 N Menard Ave",
    "sg:city":"Chicago",
    "sg:classifiers":[
        {
            "category":"Place Of Worship",
            "subcategory":"Church",
            "type":"Public Place"
        },
        {
            "category":"Place Of Worship",
            "type":"Public Place"
        },
        {
            "category":"Education",
            "subcategory":"School",
            "type":"Public Place"
        }
    ],
    "sg:phone":"+1 773 378 7881",
    "sg:postcode":"60651",
    "sg:province":"IL",
    "sg:tags":[
        "lutheran",
        "k-",
        "private",
        "churches-lutheran-evangelical",
        "america",
        "churches-lutheran"
    ],
    "wof:name":"Evangelical Lutheran Church Of Saint Paul",
    "wof:placetype":"venue"
},
  "geometry": {"coordinates":[-87.770267,41.895868],"type":"Point"}
}