{
  "type": "Feature",
  "properties": {
    "iso:country":"US",
    "sg:address":"2975 W Forest Rd",
    "sg:city":"Freeport",
    "sg:classifiers":[
        {
            "category":"Real Estate",
            "subcategory":"Real Estate Agent",
            "type":"Services"
        }
    ],
    "sg:phone":"+1 815 232 6369",
    "sg:postcode":"61032",
    "sg:province":"IL",
    "wof:name":"Otte Realtors",
    "wof:placetype":"venue"
},
  "geometry": {"coordinates":[-89.67015,42.270035],"type":"Point"}
}