{
  "type": "Feature",
  "properties": {
    "addr:full":"16301 Oak Park Ave Tinley Park IL 60477",
    "addr:housenumber":"16301",
    "addr:postcode":"60477",
    "addr:street":"Oak Park Ave",
    "iso:country":"US",
    "sg:address":"16301 Oak Park Ave",
    "sg:city":"Tinley Park",
    "sg:classifiers":[
        {
            "category":"Organizations",
            "subcategory":"Religious Organization",
            "type":"Services"
        }
    ],
    "sg:phone":"+1 708 532 6570",
    "sg:postcode":"60477",
    "sg:province":"IL",
    "wof:name":"Saint Boniface Episcpal Church",
    "wof:placetype":"venue"
},
  "geometry": {"coordinates":[-87.784971,41.594949],"type":"Point"}
}