{
  "type": "Feature",
  "properties": {
    "iso:country":"US",
    "sg:address":"16406 Hillcrest Dr",
    "sg:city":"Tinley Park",
    "sg:classifiers":[
        {
            "category":"Building & Trades",
            "subcategory":"Construction",
            "type":"Services"
        }
    ],
    "sg:phone":"+1 708 532 6438",
    "sg:postcode":"60477",
    "sg:province":"IL",
    "sg:tags":[
        "floor",
        "laying",
        "contractor"
    ],
    "wof:name":"S & S Floor Covering Inc",
    "wof:placetype":"venue"
},
  "geometry": {"coordinates":[-87.817682,41.589854],"type":"Point"}
}