{
  "type": "Feature",
  "properties": {
    "iso:country":"US",
    "sg:address":"1034 Busse Hwy",
    "sg:city":"Park Ridge",
    "sg:classifiers":[
        {
            "category":"Wholesale",
            "subcategory":"Electrical",
            "type":"Manufacturing & Wholesale Goods"
        }
    ],
    "sg:phone":"+1 847 318 1001",
    "sg:postcode":"60068",
    "sg:province":"IL",
    "sg:tags":[
        "electronic"
    ],
    "wof:name":"RCM & Associates",
    "wof:placetype":"venue"
},
  "geometry": {"coordinates":[-87.860013,42.0265],"type":"Point"}
}