{
  "type": "Feature",
  "properties": {
    "iso:country":"US",
    "sg:address":"6409 N 200th St",
    "sg:city":"Altamont",
    "sg:classifiers":[
        {
            "category":"Education",
            "subcategory":"School",
            "type":"Public Place"
        }
    ],
    "sg:phone":"+1 618 483 3710",
    "sg:postcode":"62411",
    "sg:province":"IL",
    "wof:name":"Altamont Headstart Ctr",
    "wof:placetype":"venue"
},
  "geometry": {"coordinates":[-88.76732,39.011215],"type":"Point"}
}