{
  "type": "Feature",
  "properties": {
    "iso:country":"US",
    "sg:address":"5901 N Campbell Avenue",
    "sg:city":"Chicago",
    "sg:classifiers":[
        {
            "category":"Building & Trades",
            "subcategory":"Construction",
            "type":"Services"
        }
    ],
    "sg:phone":"+1 773 561 8559",
    "sg:postcode":"60659",
    "sg:province":"IL",
    "sg:tags":[
        "interior",
        "design"
    ],
    "wof:name":"Divine Design Interiors For Your Lifestyle",
    "wof:placetype":"venue"
},
  "geometry": {"coordinates":[-87.691986,41.988528],"type":"Point"}
}