{
  "type": "Feature",
  "properties": {
    "addr:full":"3656 N Central Avenue Chicago IL 60634",
    "addr:housenumber":"3656",
    "addr:postcode":"60634",
    "addr:street":"N Central Avenue",
    "iso:country":"US",
    "sg:address":"3656 N Central Avenue",
    "sg:city":"Chicago",
    "sg:classifiers":[
        {
            "category":"Restaurant",
            "type":"Food & Drink"
        }
    ],
    "sg:phone":"+1 773 736 1429",
    "sg:postcode":"60634",
    "sg:province":"IL",
    "sg:tags":[
        "italian",
        "pizza"
    ],
    "sg:website":"www.trattoriaporretta.com/",
    "wof:name":"Trattoria Porretta",
    "wof:placetype":"venue"
},
  "geometry": {"coordinates":[-87.76671,41.947054],"type":"Point"}
}