{
  "type": "Feature",
  "properties": {
    "iso:country":"US",
    "sg:address":"5590 N Lynch Ave",
    "sg:city":"Chicago",
    "sg:classifiers":[
        {
            "category":"Retail",
            "subcategory":"Laundry & Dry Cleaning",
            "type":"Services"
        }
    ],
    "sg:phone":"+1 773 631 0469",
    "sg:postcode":"60630",
    "sg:province":"IL",
    "sg:tags":[
        "commercial"
    ],
    "wof:name":"Sanatex Corp Inc",
    "wof:placetype":"venue"
},
  "geometry": {"coordinates":[-87.758971,41.98273],"type":"Point"}
}