{
  "type": "Feature",
  "properties": {
    "iso:country":"US",
    "sg:address":"1411 S Crescent Ave",
    "sg:city":"Park Ridge",
    "sg:classifiers":[
        {
            "category":"Building & Trades",
            "subcategory":"Construction",
            "type":"Services"
        }
    ],
    "sg:phone":"+1 847 698 1786",
    "sg:postcode":"60068",
    "sg:province":"IL",
    "sg:tags":[
        "carpet",
        "laying",
        "contractor"
    ],
    "wof:name":"Vinces Carpet Service Inc",
    "wof:placetype":"venue"
},
  "geometry": {"coordinates":[-87.829886,41.992978],"type":"Point"}
}