{
  "type": "Feature",
  "properties": {
    "addr:full":"806 N 3rd St Effingham IL 62401",
    "addr:housenumber":"806",
    "addr:postcode":"62401",
    "addr:street":"N 3Rd St",
    "iso:country":"US",
    "sg:address":"806 N 3rd St",
    "sg:city":"Effingham",
    "sg:classifiers":[
        {
            "category":"Shopping",
            "subcategory":"Used Merchandise",
            "type":"Retail Goods"
        }
    ],
    "sg:phone":"+1 217 347 1090",
    "sg:postcode":"62401",
    "sg:province":"IL",
    "sg:tags":[
        "antique"
    ],
    "wof:name":"Daisy Lane Antique Mall",
    "wof:placetype":"venue"
},
  "geometry": {"coordinates":[-88.540485,39.13049],"type":"Point"}
}