{
  "type": "Feature",
  "properties": {
    "iso:country":"US",
    "sg:address":"1166 Ardmore Ct",
    "sg:city":"Schaumburg",
    "sg:classifiers":[
        {
            "category":"Building & Trades",
            "subcategory":"Construction",
            "type":"Services"
        }
    ],
    "sg:phone":"+1 847 895 0916",
    "sg:postcode":"60193",
    "sg:province":"IL",
    "sg:tags":[
        "contractor"
    ],
    "wof:name":"Quality Stucco",
    "wof:placetype":"venue"
},
  "geometry": {"coordinates":[-88.10837600000001,42.009185],"type":"Point"}
}