{
  "type": "Feature",
  "properties": {
    "iso:country":"US",
    "sg:address":"1318 Marquette Dr",
    "sg:city":"Romeoville",
    "sg:classifiers":[
        {
            "category":"Retail",
            "subcategory":"Auto Repair",
            "type":"Services"
        }
    ],
    "sg:phone":"+1 815 886 4156",
    "sg:postcode":"60446",
    "sg:province":"IL",
    "sg:tags":[
        "wrecker"
    ],
    "wof:name":"Split Second Towing",
    "wof:placetype":"venue"
},
  "geometry": {"coordinates":[-88.074579,41.671679],"type":"Point"}
}