{
  "type": "Feature",
  "properties": {
    "iso:country":"US",
    "sg:address":"4650 Stone Church Rd",
    "sg:city":"Addieville",
    "sg:classifiers":[
        {
            "category":"Building & Trades",
            "subcategory":"Construction",
            "type":"Services"
        }
    ],
    "sg:phone":"+1 618 824 6522",
    "sg:postcode":"62214",
    "sg:province":"IL",
    "sg:tags":[
        "general",
        "contractor"
    ],
    "wof:name":"Lake Contracting Inc",
    "wof:placetype":"venue"
},
  "geometry": {"coordinates":[-89.618211,38.350202],"type":"Point"}
}