{
  "type": "Feature",
  "properties": {
    "iso:country":"US",
    "sg:address":"1006 Auburn St",
    "sg:city":"Rockford",
    "sg:classifiers":[
        {
            "category":"Insurance",
            "subcategory":"Insurance Agent",
            "type":"Services"
        }
    ],
    "sg:phone":"+1 815 964 2440",
    "sg:postcode":"61103",
    "sg:province":"IL",
    "wof:name":"Jim Truninger Insurance Inc",
    "wof:placetype":"venue"
},
  "geometry": {"coordinates":[-89.077685,42.288595],"type":"Point"}
}