{
  "type": "Feature",
  "properties": {
    "addr:full":"1461 W Fullerton Avenue Chicago IL 60614",
    "addr:housenumber":"1461",
    "addr:postcode":"60614",
    "addr:street":"W Fullerton Avenue",
    "iso:country":"US",
    "sg:address":"1461 W Fullerton Avenue",
    "sg:city":"Chicago",
    "sg:classifiers":[
        {
            "category":"Arts & Performance",
            "subcategory":"Art Gallery",
            "type":"Entertainment"
        },
        {
            "category":"Professional",
            "subcategory":"Art Services",
            "type":"Services"
        }
    ],
    "sg:phone":"+1 773 871 9900",
    "sg:postcode":"60614",
    "sg:province":"IL",
    "sg:tags":[
        "framing"
    ],
    "wof:name":"Prints Unlimited Galleries",
    "wof:placetype":"venue"
},
  "geometry": {"coordinates":[-87.664925,41.925174],"type":"Point"}
}