{
  "type": "Feature",
  "properties": {
    "addr:full":"2140 Lincoln Park W Chicago IL 60614",
    "addr:housenumber":"2140",
    "addr:postcode":"60614",
    "addr:street":"Lincoln Park W",
    "iso:country":"US",
    "sg:address":"2140 Lincoln Park W",
    "sg:city":"Chicago",
    "sg:classifiers":[
        {
            "category":"Real Estate",
            "subcategory":"Real Estate Agent",
            "type":"Services"
        }
    ],
    "sg:phone":"+1 773 255 1287",
    "sg:postcode":"60614",
    "sg:province":"IL",
    "wof:name":"Drew Shreeves",
    "wof:placetype":"venue"
},
  "geometry": {"coordinates":[-87.636893,41.921331],"type":"Point"}
}