{
  "type": "Feature",
  "properties": {
    "addr:full":"7500 W Talcott Avenue Chicago IL 60631",
    "addr:housenumber":"7500",
    "addr:postcode":"60631",
    "addr:street":"W Talcott Avenue",
    "iso:country":"US",
    "sg:address":"7500 W Talcott Avenue",
    "sg:city":"Chicago",
    "sg:classifiers":[
        {
            "category":"Education",
            "subcategory":"School",
            "type":"Public Place"
        },
        {
            "category":"Organizations",
            "subcategory":"Religious Organization",
            "type":"Services"
        }
    ],
    "sg:phone":"+1 773 775 6616",
    "sg:postcode":"60631",
    "sg:province":"IL",
    "sg:tags":[
        "high",
        "middle",
        "elementary"
    ],
    "wof:name":"Resurrection High Schl",
    "wof:placetype":"venue"
},
  "geometry": {"coordinates":[-87.814143,41.989398],"type":"Point"}
}