{
  "type": "Feature",
  "properties": {
    "addr:full":"390 Kent Ave Elk Grove Village IL 60007",
    "addr:housenumber":"390",
    "addr:postcode":"60007",
    "addr:street":"Kent Ave",
    "iso:country":"US",
    "sg:address":"390 Kent Ave",
    "sg:city":"Elk Grove Village",
    "sg:classifiers":[
        {
            "category":"Wholesale",
            "subcategory":"Electrical",
            "type":"Manufacturing & Wholesale Goods"
        }
    ],
    "sg:phone":"+1 847 640 1595",
    "sg:postcode":"60007",
    "sg:province":"IL",
    "sg:tags":[
        "ind",
        "industrial",
        "supply"
    ],
    "wof:name":"Mib Machine Industrial Bus",
    "wof:placetype":"venue"
},
  "geometry": {"coordinates":[-87.97389,42.021994],"type":"Point"}
}