{
  "type": "Feature",
  "properties": {
    "iso:country":"US",
    "sg:address":"7312 Cunningham Rd",
    "sg:city":"Rockford",
    "sg:classifiers":[
        {
            "category":"Manufacturing",
            "subcategory":"Petroleum Products",
            "type":"Manufacturing & Wholesale Goods"
        }
    ],
    "sg:phone":"+1 815 963 7125",
    "sg:postcode":"61102",
    "sg:province":"IL",
    "sg:tags":[
        "oil",
        "refiner"
    ],
    "wof:name":"Robert Gillian",
    "wof:placetype":"venue"
},
  "geometry": {"coordinates":[-89.18007799999999,42.260076],"type":"Point"}
}