{
  "type": "Feature",
  "properties": {
    "iso:country":"US",
    "sg:address":"1614 Broadway St",
    "sg:city":"Pekin",
    "sg:classifiers":[
        {
            "category":"Restaurant",
            "type":"Food & Drink"
        }
    ],
    "sg:phone":"+1 309 353 5392",
    "sg:postcode":"61554",
    "sg:province":"IL",
    "wof:name":"Java Tropics",
    "wof:placetype":"venue"
},
  "geometry": {"coordinates":[-89.628996,40.567808],"type":"Point"}
}