{
  "type": "Feature",
  "properties": {
    "iso:country":"US",
    "sg:address":"66 E 1300 North Rd",
    "sg:city":"Cisco",
    "sg:classifiers":[
        {
            "category":"Shopping",
            "subcategory":"Clothing, Apparel, & Fashions",
            "type":"Retail Goods"
        }
    ],
    "sg:phone":"+1 217 669 2270",
    "sg:postcode":"61830",
    "sg:province":"IL",
    "sg:tags":[
        "clothing",
        "store"
    ],
    "wof:name":"Garb Of Ages",
    "wof:placetype":"venue"
},
  "geometry": {"coordinates":[-88.73104499999999,39.982185],"type":"Point"}
}