{
  "type": "Feature",
  "properties": {
    "addr:full":"13215 Cicero Ave Midlothian IL 60445",
    "addr:housenumber":"13215",
    "addr:postcode":"60445",
    "addr:street":"Cicero Ave",
    "iso:country":"US",
    "sg:address":"13215 Cicero Ave",
    "sg:city":"Midlothian",
    "sg:classifiers":[
        {
            "category":"Banks & Credit Unions",
            "subcategory":"Financial Services",
            "type":"Services"
        }
    ],
    "sg:phone":"+1 708 239 0860",
    "sg:postcode":"60445",
    "sg:province":"IL",
    "sg:tags":[
        "patent"
    ],
    "wof:name":"Great Clips",
    "wof:placetype":"venue"
},
  "geometry": {"coordinates":[-87.738158,41.651099],"type":"Point"}
}