{
  "type": "Feature",
  "properties": {
    "iso:country":"US",
    "sg:address":"175 Lively Blvd",
    "sg:city":"Elk Grove Village",
    "sg:classifiers":[
        {
            "category":"Wholesale",
            "subcategory":"Machinery & Supplies",
            "type":"Manufacturing & Wholesale Goods"
        }
    ],
    "sg:phone":"+1 847 545 1918",
    "sg:postcode":"60007",
    "sg:province":"IL",
    "sg:tags":[
        "equipment",
        "industrial",
        "commercial"
    ],
    "wof:name":"Jay Mark Group Ltd",
    "wof:placetype":"venue"
},
  "geometry": {"coordinates":[-87.968872,42.024474],"type":"Point"}
}