{
  "type": "Feature",
  "properties": {
    "iso:country":"US",
    "sg:address":"6545 W 92nd St",
    "sg:city":"Oak Lawn",
    "sg:classifiers":[
        {
            "category":"Retail",
            "subcategory":"Auto Repair",
            "type":"Services"
        }
    ],
    "sg:phone":"+1 708 598 3050",
    "sg:postcode":"60453",
    "sg:province":"IL",
    "sg:tags":[
        "motorcycle"
    ],
    "wof:name":"Larry's Motorcycle & Machine",
    "wof:placetype":"venue"
},
  "geometry": {"coordinates":[-87.781898,41.724201],"type":"Point"}
}