{
  "type": "Feature",
  "properties": {
    "addr:full":"3943 N Pulaski Road Chicago IL 60641",
    "addr:housenumber":"3943",
    "addr:postcode":"60641",
    "addr:street":"N Pulaski Road",
    "iso:country":"US",
    "sg:address":"3943 N Pulaski Road",
    "sg:city":"Chicago",
    "sg:classifiers":[
        {
            "category":"Building & Trades",
            "subcategory":"Construction",
            "type":"Services"
        }
    ],
    "sg:phone":"+1 773 739 2361",
    "sg:postcode":"60641",
    "sg:province":"IL",
    "sg:tags":[
        "contractor"
    ],
    "wof:name":"Carsons Shop At Home",
    "wof:placetype":"venue"
},
  "geometry": {"coordinates":[-87.727604,41.953122],"type":"Point"}
}