{
  "type": "Feature",
  "properties": {
    "iso:country":"US",
    "sg:address":"135 N Oak St",
    "sg:city":"Hinsdale",
    "sg:classifiers":[
        {
            "category":"Health Services",
            "subcategory":"Doctor",
            "type":"Services"
        }
    ],
    "sg:phone":"+1 630 856 8900",
    "sg:postcode":"60521",
    "sg:province":"IL",
    "sg:tags":[
        "physician",
        "family",
        "practice",
        "surgeons",
        "medicine",
        "surgeon"
    ],
    "wof:name":"Hinsdale Family Medicine Center",
    "wof:placetype":"venue"
},
  "geometry": {"coordinates":[-87.92008300000001,41.805759],"type":"Point"}
}