{
  "type": "Feature",
  "properties": {
    "iso:country":"US",
    "sg:address":"2148 E State St",
    "sg:city":"Jacksonville",
    "sg:classifiers":[
        {
            "category":"Building & Trades",
            "subcategory":"Landscaping Services",
            "type":"Services"
        }
    ],
    "sg:phone":"+1 217 245 6227",
    "sg:postcode":"62650",
    "sg:province":"IL",
    "sg:tags":[
        "florist"
    ],
    "wof:name":"Hembrough Tree & Lawn Care",
    "wof:placetype":"venue"
},
  "geometry": {"coordinates":[-90.199061,39.735172],"type":"Point"}
}