{
  "type": "Feature",
  "properties": {
    "iso:country":"US",
    "sg:address":"601 S Broadway",
    "sg:city":"Aurora",
    "sg:classifiers":[
        {
            "category":"Retail",
            "subcategory":"Auto Repair",
            "type":"Services"
        }
    ],
    "sg:phone":"+1 630 897 0071",
    "sg:postcode":"60505",
    "sg:province":"IL",
    "sg:tags":[
        "body",
        "automobile",
        "painting"
    ],
    "wof:name":"On The Mark Carstar",
    "wof:placetype":"venue"
},
  "geometry": {"coordinates":[-88.325321,41.74483],"type":"Point"}
}