{
  "type": "Feature",
  "properties": {
    "addr:full":"1 South Broadway St Louis MO 63102",
    "addr:housenumber":"1",
    "addr:postcode":"63102",
    "addr:street":"South Broadway",
    "iso:country":"US",
    "sg:address":"1 South Broadway",
    "sg:city":"St Louis",
    "sg:classifiers":[
        {
            "category":"Travel",
            "subcategory":"Hotels & Motels",
            "type":"Entertainment"
        }
    ],
    "sg:phone":"+1 314 421 1776",
    "sg:postcode":"63102",
    "sg:province":"MO",
    "wof:name":"Hilton St Louis at the Ballpark",
    "wof:placetype":"venue"
},
  "geometry": {"coordinates":[-90.190056,38.625278],"type":"Point"}
}