{
  "type": "Feature",
  "properties": {
    "iso:country":"US",
    "sg:address":"100 S York St",
    "sg:city":"Elmhurst",
    "sg:classifiers":[
        {
            "category":"Restaurant",
            "type":"Food & Drink"
        }
    ],
    "sg:phone":"+1 630 782 9091",
    "sg:postcode":"60126",
    "sg:province":"IL",
    "sg:tags":[
        "eating"
    ],
    "sg:website":"www.100south.com",
    "wof:name":"100 South Chop House & Grille",
    "wof:placetype":"venue"
},
  "geometry": {"coordinates":[-87.940001,41.898554],"type":"Point"}
}