{
  "type": "Feature",
  "properties": {
    "addr:full":"4051 E Main St Saint Charles IL 60174",
    "addr:housenumber":"4051",
    "addr:postcode":"60174",
    "addr:street":"E Main St",
    "iso:country":"US",
    "sg:address":"4051 E Main St",
    "sg:city":"Saint Charles",
    "sg:classifiers":[
        {
            "category":"Cafe",
            "type":"Food & Drink"
        }
    ],
    "sg:menulink":"http://www.allmenus.com/il/wayne/22608-terrace-cafe/menu/",
    "sg:phone":"+1 630 584 6300",
    "sg:postcode":"60174",
    "sg:province":"IL",
    "sg:tags":[
        "american"
    ],
    "wof:name":"Terrace Cafe",
    "wof:placetype":"venue"
},
  "geometry": {"coordinates":[-88.262559,41.921314],"type":"Point"}
}