{
  "type": "Feature",
  "properties": {
    "addr:full":"755 N Henderson St Galesburg IL 61401",
    "addr:housenumber":"755",
    "addr:postcode":"61401",
    "addr:street":"N Henderson St",
    "iso:country":"US",
    "sg:address":"755 N Henderson St",
    "sg:city":"Galesburg",
    "sg:classifiers":[
        {
            "category":"Retail",
            "subcategory":"Repair Shop",
            "type":"Services"
        },
        {
            "category":"Shopping",
            "subcategory":"Computers & Home Electronics",
            "type":"Retail Goods"
        },
        {
            "category":"Internet Cafe",
            "subcategory":"None",
            "type":"Food & Drink"
        },
        {
            "category":"Professional",
            "subcategory":"Computer Services",
            "type":"Services"
        },
        {
            "category":"Professional",
            "subcategory":"Engineering",
            "type":"Services"
        },
        {
            "category":"Wholesale",
            "subcategory":"Computers",
            "type":"Manufacturing & Wholesale Goods"
        }
    ],
    "sg:phone":"+1 309 342 7177",
    "sg:postcode":"61401",
    "sg:province":"IL",
    "sg:tags":[
        "product",
        "printer",
        "supply",
        "technical",
        "repair-business",
        "assistance",
        "provider",
        "system",
        "integration",
        "hardware",
        "equipment",
        "consultant",
        "designer",
        "isp",
        "equipment-service",
        "support",
        "engineer"
    ],
    "sg:website":"http://www.trilutions.net",
    "wof:name":"Trilutions Computer & Internet Center",
    "wof:placetype":"venue"
},
  "geometry": {"coordinates":[-90.383638,40.938128],"type":"Point"}
}