{
  "type": "Feature",
  "properties": {
    "addr:full":"84 Bright Oaks Cir Cary IL 60013",
    "addr:housenumber":"84",
    "addr:postcode":"60013",
    "addr:street":"Bright Oaks Cir",
    "iso:country":"US",
    "sg:address":"84 Bright Oaks Cir",
    "sg:city":"Cary",
    "sg:classifiers":[
        {
            "category":"Manufacturing",
            "subcategory":"Retail Goods",
            "type":"Manufacturing & Wholesale Goods"
        }
    ],
    "sg:phone":"+1 847 516 5447",
    "sg:postcode":"60013",
    "sg:province":"IL",
    "sg:tags":[
        "spool"
    ],
    "wof:name":"Wire Packaging Inc",
    "wof:placetype":"venue"
},
  "geometry": {"coordinates":[-88.253776,42.221602],"type":"Point"}
}