{
  "type": "Feature",
  "properties": {
    "iso:country":"US",
    "sg:address":"1204 Whispering Hills Ct",
    "sg:city":"Naperville",
    "sg:classifiers":[
        {
            "category":"Communications",
            "type":"Services"
        }
    ],
    "sg:phone":"+1 630 355 9930",
    "sg:postcode":"60540",
    "sg:province":"IL",
    "sg:tags":[
        "carrier",
        "radiotelephone",
        "communications-common"
    ],
    "wof:name":"AT&T Corp.",
    "wof:placetype":"venue"
},
  "geometry": {"coordinates":[-88.175825,41.777634],"type":"Point"}
}