{
  "type": "Feature",
  "properties": {
    "addr:full":"2105 S China Place Chicago IL 60616",
    "addr:housenumber":"2105",
    "addr:postcode":"60616",
    "addr:street":"S China Place",
    "iso:country":"US",
    "sg:address":"2105 S China Place",
    "sg:city":"Chicago",
    "sg:classifiers":[
        {
            "category":"Health Services",
            "subcategory":"Doctor",
            "type":"Services"
        }
    ],
    "sg:phone":"+1 312 808 1100",
    "sg:postcode":"60616",
    "sg:province":"IL",
    "wof:name":"Wu Wei T MD",
    "wof:placetype":"venue"
},
  "geometry": {"coordinates":[-87.634103,41.854057],"type":"Point"}
}