{
  "type": "Feature",
  "properties": {
    "addr:full":"833 North Ave Des Plaines IL 60016",
    "addr:housenumber":"833",
    "addr:postcode":"60016",
    "addr:street":"North Ave",
    "iso:country":"US",
    "sg:address":"833 North Ave",
    "sg:city":"Des Plaines",
    "sg:classifiers":[
        {
            "category":"Building & Trades",
            "subcategory":"Construction",
            "type":"Services"
        }
    ],
    "sg:phone":"+1 847 824 7383",
    "sg:postcode":"60016",
    "sg:province":"IL",
    "sg:tags":[
        "painting",
        "contractor"
    ],
    "wof:name":"Bob Cappelen & Son Inc",
    "wof:placetype":"venue"
},
  "geometry": {"coordinates":[-87.902424,42.044855],"type":"Point"}
}