{
  "type": "Feature",
  "properties": {
    "addr:full":"4813 Hyacinth Ct Plainfield IL 60586",
    "addr:housenumber":"4813",
    "addr:postcode":"60586",
    "addr:street":"Hyacinth Ct",
    "iso:country":"US",
    "sg:address":"4813 Hyacinth Ct",
    "sg:city":"Plainfield",
    "sg:classifiers":[
        {
            "category":"Organizations",
            "subcategory":"Membership Organization",
            "type":"Services"
        }
    ],
    "sg:phone":"+1 815 230 3516",
    "sg:postcode":"60586",
    "sg:province":"IL",
    "sg:tags":[
        "environmental",
        "ecological",
        "conservation"
    ],
    "wof:name":"Regenesis",
    "wof:placetype":"venue"
},
  "geometry": {"coordinates":[-88.20179,41.557678],"type":"Point"}
}