{
  "type": "Feature",
  "properties": {
    "iso:country":"US",
    "sg:address":"839 W Cornelia Ave",
    "sg:city":"Chicago",
    "sg:classifiers":[
        {
            "category":"Arts & Performance",
            "subcategory":"Theater",
            "type":"Entertainment"
        }
    ],
    "sg:phone":"+1 773 348 0966",
    "sg:postcode":"60657",
    "sg:province":"IL",
    "sg:tags":[
        "group"
    ],
    "wof:name":"World Percussion & Rhythm Mag",
    "wof:placetype":"venue"
},
  "geometry": {"coordinates":[-87.65098,41.945376],"type":"Point"}
}