{
  "type": "Feature",
  "properties": {
    "addr:full":"318 W Half Day Rd Buffalo Grove IL 60089",
    "addr:housenumber":"318",
    "addr:postcode":"60089",
    "addr:street":"W Half Day Rd",
    "iso:country":"US",
    "sg:address":"318 W Half Day Rd",
    "sg:city":"Buffalo Grove",
    "sg:classifiers":[
        {
            "category":"Professional",
            "subcategory":"Management & Consulting",
            "type":"Services"
        }
    ],
    "sg:phone":"+1 847 909 1356",
    "sg:postcode":"60089",
    "sg:province":"IL",
    "sg:tags":[
        "business"
    ],
    "wof:name":"Ajg Consulting",
    "wof:placetype":"venue"
},
  "geometry": {"coordinates":[-87.964573,42.19607],"type":"Point"}
}