{
  "type": "Feature",
  "properties": {
    "addr:full":"415 Saginaw Ave Calumet City IL 60409",
    "addr:housenumber":"415",
    "addr:postcode":"60409",
    "addr:street":"Saginaw Ave",
    "iso:country":"US",
    "sg:address":"415 Saginaw Ave",
    "sg:city":"Calumet City",
    "sg:classifiers":[
        {
            "category":"Organizations",
            "subcategory":"Religious Organization",
            "type":"Services"
        }
    ],
    "sg:phone":"+1 708 862 4829",
    "sg:postcode":"60409",
    "sg:province":"IL",
    "wof:name":"Higher Ground Community Church",
    "wof:placetype":"venue"
},
  "geometry": {"coordinates":[-87.55792099999999,41.626311],"type":"Point"}
}