{
  "type": "Feature",
  "properties": {
    "iso:country":"US",
    "sg:address":"1424 Old West Main St",
    "sg:city":"Carbondale",
    "sg:classifiers":[
        {
            "category":"Professional",
            "subcategory":"Lawyer & Legal Services",
            "type":"Services"
        }
    ],
    "sg:phone":"+1 618 457 4440",
    "sg:postcode":"62901",
    "sg:province":"IL",
    "wof:name":"Moyer Thomas W Atty",
    "wof:placetype":"venue"
},
  "geometry": {"coordinates":[-89.234497,37.726898],"type":"Point"}
}