{
  "type": "Feature",
  "properties": {
    "iso:country":"US",
    "sg:address":"815 1st Ave",
    "sg:city":"Rock Falls",
    "sg:classifiers":[
        {
            "category":"Food & Beverages",
            "subcategory":"Candy",
            "type":"Retail Goods"
        }
    ],
    "sg:phone":"+1   ",
    "sg:postcode":"61071",
    "sg:province":"IL",
    "wof:name":"Cakes Of Distinction",
    "wof:placetype":"venue"
},
  "geometry": {"coordinates":[-89.689335,41.775824],"type":"Point"}
}