{
  "type": "Feature",
  "properties": {
    "addr:full":"4350 W 129th St Alsip IL 60803",
    "addr:housenumber":"4350",
    "addr:postcode":"60803",
    "addr:street":"W 129Th St",
    "iso:country":"US",
    "sg:address":"4350 W 129th St",
    "sg:city":"Alsip",
    "sg:phone":"+1 708 344 7300",
    "sg:postcode":"60803",
    "sg:province":"IL",
    "sg:website":"www.swap-o-rama.com/swap/alsip.html",
    "wof:name":"Alsip Swap-O-Rama Flea Market",
    "wof:placetype":"venue"
},
  "geometry": {"coordinates":[-87.729207,41.655549],"type":"Point"}
}