{
  "type": "Feature",
  "properties": {
    "addr:full":"150 W Roosevelt Rd Chicago IL 60605",
    "addr:housenumber":"150",
    "addr:postcode":"60605",
    "addr:street":"W Roosevelt Rd",
    "iso:country":"US",
    "sg:address":"150 W Roosevelt Rd",
    "sg:city":"Chicago",
    "sg:classifiers":[
        {
            "category":"Bars & Pubs",
            "type":"Food & Drink"
        },
        {
            "category":"Cinema",
            "subcategory":"Movie Theater",
            "type":"Entertainment"
        }
    ],
    "sg:phone":"+1 312 564 2104",
    "sg:postcode":"60605",
    "sg:province":"IL",
    "sg:website":"www.showplaceicon.com",
    "wof:name":"ShowPlace Icon",
    "wof:placetype":"venue"
},
  "geometry": {"coordinates":[-87.630467,41.867451],"type":"Point"}
}