{
  "type": "Feature",
  "properties": {
    "iso:country":"US",
    "sg:address":"118 S Clinton St",
    "sg:city":"Chicago",
    "sg:classifiers":[
        {
            "category":"Banks & Credit Unions",
            "subcategory":"Investment Brokerage",
            "type":"Services"
        },
        {
            "category":"Insurance",
            "subcategory":"Hazard Insurance",
            "type":"Services"
        },
        {
            "category":"Banks & Credit Unions",
            "subcategory":"Financial Services",
            "type":"Services"
        }
    ],
    "sg:phone":"+1 312 879 1079",
    "sg:postcode":"60661",
    "sg:province":"IL",
    "sg:tags":[
        "annuity",
        "retirement",
        "plan"
    ],
    "sg:website":"http://www.5starmgrs.com",
    "wof:name":"Five Star Managers",
    "wof:placetype":"venue"
},
  "geometry": {"coordinates":[-87.641114,41.88034],"type":"Point"}
}