{
  "type": "Feature",
  "properties": {
    "iso:country":"US",
    "sg:address":"1310 E Algonquin Rd",
    "sg:city":"Algonquin",
    "sg:classifiers":[
        {
            "category":"Shopping",
            "subcategory":"Florist",
            "type":"Retail Goods"
        }
    ],
    "sg:phone":"+1 847 658 3181",
    "sg:postcode":"60102",
    "sg:province":"IL",
    "sg:website":"www.algonquinflowershoppe.com",
    "wof:name":"Algonquin Flower Shoppe",
    "wof:placetype":"venue"
},
  "geometry": {"coordinates":[-88.27619900000001,42.161201],"type":"Point"}
}