{
  "type": "Feature",
  "properties": {
    "iso:country":"US",
    "sg:address":"1138 1250th Ave",
    "sg:city":"Lincoln",
    "sg:classifiers":[
        {
            "category":"Building & Trades",
            "subcategory":"Landscaping Services",
            "type":"Services"
        }
    ],
    "sg:phone":"+1 217 732 8328",
    "sg:postcode":"62656",
    "sg:province":"IL",
    "sg:tags":[
        "farm"
    ],
    "wof:name":"Wilmert Farms Inc",
    "wof:placetype":"venue"
},
  "geometry": {"coordinates":[-89.358029,40.087888],"type":"Point"}
}