{
  "type": "Feature",
  "properties": {
    "addr:full":"4257 S Rockwell St Chicago IL 60632",
    "addr:housenumber":"4257",
    "addr:postcode":"60632",
    "addr:street":"S Rockwell St",
    "iso:country":"US",
    "sg:address":"4257 S Rockwell St",
    "sg:city":"Chicago",
    "sg:classifiers":[
        {
            "category":"Food & Beverages",
            "subcategory":"Groceries & Convenience Stores",
            "type":"Retail Goods"
        }
    ],
    "sg:phone":"+1 773 376 2701",
    "sg:postcode":"60632",
    "sg:province":"IL",
    "wof:name":"Moroleon Foods 2",
    "wof:placetype":"venue"
},
  "geometry": {"coordinates":[-87.689358,41.816882],"type":"Point"}
}