{
  "type": "Feature",
  "properties": {
    "addr:full":"509 S 7th St Coulterville IL 62237",
    "addr:housenumber":"509",
    "addr:postcode":"62237",
    "addr:street":"S 7Th St",
    "iso:country":"US",
    "sg:address":"509 S 7th St",
    "sg:city":"Coulterville",
    "sg:classifiers":[
        {
            "category":"Wholesale",
            "subcategory":"Sporting Goods",
            "type":"Manufacturing & Wholesale Goods"
        }
    ],
    "sg:phone":"+1 618 758 1806",
    "sg:postcode":"62237",
    "sg:province":"IL",
    "wof:name":"Cornfield Products Inc",
    "wof:placetype":"venue"
},
  "geometry": {"coordinates":[-89.607034,38.183082],"type":"Point"}
}