{
  "type": "Feature",
  "properties": {
    "addr:full":"8921 Fairview Ave Brookfield IL 60513",
    "addr:housenumber":"8921",
    "addr:postcode":"60513",
    "addr:street":"Fairview Ave",
    "iso:country":"US",
    "sg:address":"8921 Fairview Ave",
    "sg:city":"Brookfield",
    "sg:classifiers":[
        {
            "category":"Health Services",
            "subcategory":"Doctor",
            "type":"Services"
        }
    ],
    "sg:phone":"+1 708 485 1755",
    "sg:postcode":"60513",
    "sg:province":"IL",
    "wof:name":"Isaac Alan H DDS PC",
    "wof:placetype":"venue"
},
  "geometry": {"coordinates":[-87.844662,41.822164],"type":"Point"}
}