{
  "type": "Feature",
  "properties": {
    "iso:country":"US",
    "sg:address":"314 Alana Dr",
    "sg:city":"New Lenox",
    "sg:classifiers":[
        {
            "category":"Retail",
            "subcategory":"Laundry & Dry Cleaning",
            "type":"Services"
        }
    ],
    "sg:phone":"+1 815 423 5047",
    "sg:postcode":"60451",
    "sg:province":"IL",
    "sg:tags":[
        "cleaners",
        "rug",
        "carpet"
    ],
    "wof:name":"Crystal Clean Carpets",
    "wof:placetype":"venue"
},
  "geometry": {"coordinates":[-87.976723,41.517571],"type":"Point"}
}