{
  "type": "Feature",
  "properties": {
    "addr:full":"5551 Weymouth Dr Rockford IL 61114",
    "addr:housenumber":"5551",
    "addr:postcode":"61114",
    "addr:street":"Weymouth Dr",
    "iso:country":"US",
    "sg:address":"5551 Weymouth Dr",
    "sg:city":"Rockford",
    "sg:classifiers":[
        {
            "category":"Building & Trades",
            "subcategory":"Construction",
            "type":"Services"
        }
    ],
    "sg:phone":"+1 815 282 1418",
    "sg:postcode":"61114",
    "sg:province":"IL",
    "sg:tags":[
        "general",
        "contractor"
    ],
    "wof:name":"Swanson Construction Co",
    "wof:placetype":"venue"
},
  "geometry": {"coordinates":[-89.006248,42.309132],"type":"Point"}
}