{
  "type": "Feature",
  "properties": {
    "iso:country":"US",
    "sg:address":"3501 W Montrose Ave",
    "sg:city":"Chicago",
    "sg:classifiers":[
        {
            "category":"Food & Beverages",
            "subcategory":"Groceries & Convenience Stores",
            "type":"Retail Goods"
        }
    ],
    "sg:phone":"+1 773 478 2616",
    "sg:postcode":"60618",
    "sg:province":"IL",
    "wof:name":"J & P Fine Foods & Meats",
    "wof:placetype":"venue"
},
  "geometry": {"coordinates":[-87.715599,41.960899],"type":"Point"}
}