{
  "type": "Feature",
  "properties": {
    "iso:country":"US",
    "sg:address":"1725 W Harrison Street",
    "sg:city":"Chicago",
    "sg:classifiers":[
        {
            "category":"Health Services",
            "subcategory":"Optometrist",
            "type":"Services"
        },
        {
            "category":"Shopping",
            "subcategory":"Optician",
            "type":"Retail Goods"
        }
    ],
    "sg:phone":"+1 312 733 7566",
    "sg:postcode":"60612",
    "sg:province":"IL",
    "sg:tags":[
        "eyewear"
    ],
    "sg:website":"www.rosineyecare.com",
    "wof:name":"Rosin Eyecare",
    "wof:placetype":"venue"
},
  "geometry": {"coordinates":[-87.669901,41.87413],"type":"Point"}
}