{
  "type": "Feature",
  "properties": {
    "iso:country":"US",
    "sg:address":"2145 175th St",
    "sg:city":"Lansing",
    "sg:classifiers":[
        {
            "category":"Education",
            "subcategory":"Vocational School",
            "type":"Public Place"
        }
    ],
    "sg:phone":"+1 815 464 9623",
    "sg:postcode":"60438",
    "sg:province":"IL",
    "sg:tags":[
        "training",
        "computer"
    ],
    "wof:name":"D Computer Dynamics Inc",
    "wof:placetype":"venue"
},
  "geometry": {"coordinates":[-87.566649,41.577006],"type":"Point"}
}