{
  "type": "Feature",
  "properties": {
    "iso:country":"US",
    "sg:address":"2600 S Michigan Ave",
    "sg:city":"Chicago",
    "sg:classifiers":[
        {
            "category":"Professional",
            "subcategory":"Detective & Security Services",
            "type":"Services"
        }
    ],
    "sg:phone":"+1 312 567 0318",
    "sg:postcode":"60616",
    "sg:province":"IL",
    "sg:tags":[
        "guard",
        "patrol"
    ],
    "sg:website":"http://www.skytechenterprisesltd.com",
    "wof:name":"Skytech Security Services",
    "wof:placetype":"venue"
},
  "geometry": {"coordinates":[-87.623627,41.845638],"type":"Point"}
}