{
  "type": "Feature",
  "properties": {
    "addr:full":"111 North Ave Barrington IL 60010",
    "addr:housenumber":"111",
    "addr:postcode":"60010",
    "addr:street":"North Ave",
    "iso:country":"US",
    "sg:address":"111 North Ave",
    "sg:city":"Barrington",
    "sg:classifiers":[
        {
            "category":"Health Services",
            "subcategory":"Doctor",
            "type":"Services"
        }
    ],
    "sg:phone":"+1 847 713 2119",
    "sg:postcode":"60010",
    "sg:province":"IL",
    "sg:tags":[
        "physician",
        "surgeon"
    ],
    "wof:name":"Adult Child & Adolescent Psych",
    "wof:placetype":"venue"
},
  "geometry": {"coordinates":[-88.131197,42.155215],"type":"Point"}
}