{
  "type": "Feature",
  "properties": {
    "addr:full":"2011 Lebanon Ave Belleville IL 62221",
    "addr:housenumber":"2011",
    "addr:postcode":"62221",
    "addr:street":"Lebanon Ave",
    "iso:country":"US",
    "sg:address":"2011 Lebanon Ave",
    "sg:city":"Belleville",
    "sg:classifiers":[
        {
            "category":"Building & Trades",
            "subcategory":"Plumbing",
            "type":"Services"
        }
    ],
    "sg:phone":"+1 618 222 1823",
    "sg:postcode":"62221",
    "sg:province":"IL",
    "sg:tags":[
        "contractor"
    ],
    "wof:name":"Hayden Heating & Cooling Inc",
    "wof:placetype":"venue"
},
  "geometry": {"coordinates":[-89.956413,38.538948],"type":"Point"}
}