{
  "type": "Feature",
  "properties": {
    "addr:full":"318 S Prairie St Champaign IL 61820",
    "addr:housenumber":"318",
    "addr:postcode":"61820",
    "addr:street":"S Prairie St",
    "iso:country":"US",
    "sg:address":"318 S Prairie St",
    "sg:city":"Champaign",
    "sg:classifiers":[
        {
            "category":"Real Estate",
            "subcategory":"Architect",
            "type":"Services"
        }
    ],
    "sg:phone":"+1 217 352 2448",
    "sg:postcode":"61820",
    "sg:province":"IL",
    "sg:tags":[
        "architectural"
    ],
    "wof:name":"Gower Rondal Associates",
    "wof:placetype":"venue"
},
  "geometry": {"coordinates":[-88.248372,40.112936],"type":"Point"}
}