{
  "type": "Feature",
  "properties": {
    "addr:full":"620 Lake Rd Lake Forest IL 60045",
    "addr:housenumber":"620",
    "addr:postcode":"60045",
    "addr:street":"Lake Rd",
    "iso:country":"US",
    "sg:address":"620 Lake Rd",
    "sg:city":"Lake Forest",
    "sg:classifiers":[
        {
            "category":"Banks & Credit Unions",
            "subcategory":"Investment Brokerage",
            "type":"Services"
        }
    ],
    "sg:phone":"+1 847 604 9500",
    "sg:postcode":"60045",
    "sg:province":"IL",
    "sg:tags":[
        "advisory",
        "financial"
    ],
    "wof:name":"Minotaur Capital Mgmt",
    "wof:placetype":"venue"
},
  "geometry": {"coordinates":[-87.821395,42.251491],"type":"Point"}
}