{
  "type": "Feature",
  "properties": {
    "addr:full":"3319 N Ridge Ave Arlington Heights IL 60004",
    "addr:housenumber":"3319",
    "addr:postcode":"60004",
    "addr:street":"N Ridge Ave",
    "iso:country":"US",
    "sg:address":"3319 N Ridge Ave",
    "sg:city":"Arlington Heights",
    "sg:classifiers":[
        {
            "category":"Wholesale",
            "subcategory":"Durable Goods & Equipment",
            "type":"Manufacturing & Wholesale Goods"
        }
    ],
    "sg:phone":"+1 847 398 5444",
    "sg:postcode":"60004",
    "sg:province":"IL",
    "sg:tags":[
        "instrument",
        "mfg",
        "musical",
        "luggage"
    ],
    "wof:name":"Advantage Worldwide Wholesale",
    "wof:placetype":"venue"
},
  "geometry": {"coordinates":[-87.991336,42.137353],"type":"Point"}
}