{
  "type": "Feature",
  "properties": {
    "addr:full":"2310 16th Ave Moline IL 61265",
    "addr:housenumber":"2310",
    "addr:postcode":"61265",
    "addr:street":"16Th Ave",
    "iso:country":"US",
    "sg:address":"2310 16th Ave",
    "sg:city":"Moline",
    "sg:classifiers":[
        {
            "category":"Organizations",
            "subcategory":"Community Association",
            "type":"Services"
        }
    ],
    "sg:phone":"+1 309 762 2083",
    "sg:postcode":"61265",
    "sg:province":"IL",
    "wof:name":"Assoc of Notre Dame Clubs",
    "wof:placetype":"venue"
},
  "geometry": {"coordinates":[-90.502747,41.496277],"type":"Point"}
}