{
  "type": "Feature",
  "properties": {
    "addr:full":"3180 Woodhaven Dr Bourbonnais IL 60914",
    "addr:housenumber":"3180",
    "addr:postcode":"60914",
    "addr:street":"Woodhaven Dr",
    "iso:country":"US",
    "sg:address":"3180 Woodhaven Dr",
    "sg:city":"Bourbonnais",
    "sg:classifiers":[
        {
            "category":"Professional",
            "subcategory":"Accounting & Tax Preparation",
            "type":"Services"
        }
    ],
    "sg:phone":"+1 815 933 1467",
    "sg:postcode":"60914",
    "sg:province":"IL",
    "wof:name":"Mona Tyson Bookkeeping Service",
    "wof:placetype":"venue"
},
  "geometry": {"coordinates":[-87.938754,41.172362],"type":"Point"}
}