{
  "type": "Feature",
  "properties": {
    "addr:full":"2857 Co Rd 800 E Dewey IL 61840",
    "addr:housenumber":"2857",
    "addr:postcode":"61840",
    "addr:street":"Co Rd 800 E",
    "iso:country":"US",
    "sg:address":"2857 Co Rd 800 E",
    "sg:city":"Dewey",
    "sg:classifiers":[
        {
            "category":"Building & Trades",
            "subcategory":"Construction",
            "type":"Services"
        }
    ],
    "sg:phone":"+1 217 897 1919",
    "sg:postcode":"61840",
    "sg:province":"IL",
    "sg:tags":[
        "excavation",
        "contractor"
    ],
    "wof:name":"Tom Hewerdine & Son Inc",
    "wof:placetype":"venue"
},
  "geometry": {"coordinates":[-88.30873800000001,40.288332],"type":"Point"}
}