{
  "type": "Feature",
  "properties": {
    "iso:country":"US",
    "sg:address":"2857 Co Rd 800 E",
    "sg:city":"Dewey",
    "sg:classifiers":[
        {
            "category":"Building & Trades",
            "subcategory":"Construction",
            "type":"Services"
        }
    ],
    "sg:phone":"+1 217 897 1919",
    "sg:postcode":"61840",
    "sg:province":"IL",
    "sg:tags":[
        "excavation",
        "contractor"
    ],
    "wof:name":"Tom Hewerdine & Son Inc",
    "wof:placetype":"venue"
},
  "geometry": {"coordinates":[-88.308738,40.288332],"type":"Point"}
}