{
  "type": "Feature",
  "properties": {
    "iso:country":"US",
    "sg:address":"5853 S Halsted Street",
    "sg:city":"Chicago",
    "sg:classifiers":[
        {
            "category":"Shopping",
            "subcategory":"Used Merchandise",
            "type":"Retail Goods"
        },
        {
            "category":"Home & Garden",
            "subcategory":"Furniture",
            "type":"Retail Goods"
        }
    ],
    "sg:phone":"+1 773 783 3100",
    "sg:postcode":"60621",
    "sg:province":"IL",
    "sg:tags":[
        "store"
    ],
    "wof:name":"Landmark Liquidation",
    "wof:placetype":"venue"
},
  "geometry": {"coordinates":[-87.644744,41.78726],"type":"Point"}
}