{
  "type": "Feature",
  "properties": {
    "iso:country":"US",
    "sg:address":"511 2nd Ave",
    "sg:city":"Rochelle",
    "sg:classifiers":[
        {
            "category":"Autos & Motor Vehicles",
            "subcategory":"Auto Supplies",
            "type":"Retail Goods"
        }
    ],
    "sg:phone":"+1 815 562 4575",
    "sg:postcode":"61068",
    "sg:province":"IL",
    "sg:tags":[
        "tire"
    ],
    "wof:name":"Frank's Goodyear Svc",
    "wof:placetype":"venue"
},
  "geometry": {"coordinates":[-89.066562,41.920492],"type":"Point"}
}