{
  "type": "Feature",
  "properties": {
    "iso:country":"US",
    "sg:address":"3326 183rd St",
    "sg:city":"Hazel Crest",
    "sg:classifiers":[
        {
            "category":"Shopping",
            "subcategory":"Clothing, Apparel, & Fashions",
            "type":"Retail Goods"
        }
    ],
    "sg:phone":"+1 708 206 0225",
    "sg:postcode":"60429",
    "sg:province":"IL",
    "sg:tags":[
        "clothes"
    ],
    "wof:name":"Blaze",
    "wof:placetype":"venue"
},
  "geometry": {"coordinates":[-87.696354,41.557235],"type":"Point"}
}