{
  "type": "Feature",
  "properties": {
    "iso:country":"US",
    "sg:address":"2619 Ridgeland Ave",
    "sg:city":"Berwyn",
    "sg:classifiers":[
        {
            "category":"Arts & Performance",
            "subcategory":"Arts Center",
            "type":"Entertainment"
        }
    ],
    "sg:phone":"+1 708 484 0840",
    "sg:postcode":"60402",
    "sg:province":"IL",
    "sg:tags":[
        "performing"
    ],
    "wof:name":"Kulik School of Dance Arts",
    "wof:placetype":"venue"
},
  "geometry": {"coordinates":[-87.793098,41.8438],"type":"Point"}
}