{
  "type": "Feature",
  "properties": {
    "iso:country":"US",
    "sg:address":"1400 W 79th Street",
    "sg:city":"Chicago",
    "sg:classifiers":[
        {
            "category":"Restaurant",
            "type":"Food & Drink"
        }
    ],
    "sg:phone":"+1 773 651 1763",
    "sg:postcode":"60620",
    "sg:province":"IL",
    "wof:name":"White Castle System",
    "wof:placetype":"venue"
},
  "geometry": {"coordinates":[-87.658799,41.750443],"type":"Point"}
}