{
  "type": "Feature",
  "properties": {
    "addr:full":"13122 S Ellis Ave Chicago IL 60827",
    "addr:housenumber":"13122",
    "addr:postcode":"60827",
    "addr:street":"S Ellis Ave",
    "iso:country":"US",
    "sg:address":"13122 S Ellis Ave",
    "sg:city":"Chicago",
    "sg:classifiers":[
        {
            "category":"Food & Beverages",
            "subcategory":"Liquor & Beverages",
            "type":"Retail Goods"
        }
    ],
    "sg:phone":"+1 773 568 4488",
    "sg:postcode":"60827",
    "sg:province":"IL",
    "wof:name":"Altgeld Garden Liquor",
    "wof:placetype":"venue"
},
  "geometry": {"coordinates":[-87.597374,41.656632],"type":"Point"}
}