{
  "type": "Feature",
  "properties": {
    "iso:country":"US",
    "sg:address":"3151 Glenwood Dyer Rd",
    "sg:city":"Lynwood",
    "sg:phone":"+1 708 757 9636",
    "sg:postcode":"60411",
    "sg:province":"IL",
    "wof:name":"Royal Auto",
    "wof:placetype":"venue"
},
  "geometry": {"coordinates":[-87.539635,41.514475],"type":"Point"}
}