{
  "type": "Feature",
  "properties": {
    "addr:full":"2852 N Campbell Avenue Chicago IL 60618",
    "addr:housenumber":"2852",
    "addr:postcode":"60618",
    "addr:street":"N Campbell Avenue",
    "iso:country":"US",
    "sg:address":"2852 N Campbell Avenue",
    "sg:city":"Chicago",
    "sg:classifiers":[
        {
            "category":"Professional",
            "subcategory":"Lawyer & Legal Services",
            "type":"Services"
        }
    ],
    "sg:phone":"+1 773 289 3902",
    "sg:postcode":"60618",
    "sg:province":"IL",
    "wof:name":"Rosalind Pando",
    "wof:placetype":"venue"
},
  "geometry": {"coordinates":[-87.690235,41.933901],"type":"Point"}
}