{
  "type": "Feature",
  "properties": {
    "iso:country":"US",
    "sg:address":"8834 S Cottage Grove Ave",
    "sg:city":"Chicago",
    "sg:classifiers":[
        {
            "category":"Shopping",
            "subcategory":"Clothing, Apparel, & Fashions",
            "type":"Retail Goods"
        }
    ],
    "sg:phone":"+1 773 994 8975",
    "sg:postcode":"60619",
    "sg:province":"IL",
    "sg:tags":[
        "accessory",
        "clothing",
        "women's"
    ],
    "wof:name":"Allison's La Parisienne",
    "wof:placetype":"venue"
},
  "geometry": {"coordinates":[-87.60489699999999,41.733601],"type":"Point"}
}