{
  "type": "Feature",
  "properties": {
    "addr:full":"12015 Maple Ave Blue Island IL 60406",
    "addr:housenumber":"12015",
    "addr:postcode":"60406",
    "addr:street":"Maple Ave",
    "iso:country":"US",
    "sg:address":"12015 Maple Ave",
    "sg:city":"Blue Island",
    "sg:classifiers":[
        {
            "category":"Education",
            "subcategory":"School",
            "type":"Public Place"
        }
    ],
    "sg:phone":"+1 708 385 2915",
    "sg:postcode":"60406",
    "sg:province":"IL",
    "sg:tags":[
        "high",
        "middle",
        "elementary"
    ],
    "wof:name":"Greenbriar Parent Education Programs",
    "wof:placetype":"venue"
},
  "geometry": {"coordinates":[-87.68532999999999,41.674853],"type":"Point"}
}