{
  "type": "Feature",
  "properties": {
    "iso:country":"US",
    "sg:address":"100 N Elm St",
    "sg:city":"Granville",
    "sg:classifiers":[
        {
            "category":"Building & Trades",
            "subcategory":"Construction",
            "type":"Services"
        }
    ],
    "sg:phone":"+1 815 339 2424",
    "sg:postcode":"61326",
    "sg:province":"IL",
    "sg:tags":[
        "painter"
    ],
    "wof:name":"Kenneth Bouxsein",
    "wof:placetype":"venue"
},
  "geometry": {"coordinates":[-89.221498,41.263911],"type":"Point"}
}