{
  "type": "Feature",
  "properties": {
    "iso:country":"US",
    "sg:address":"128 N Plum St",
    "sg:city":"Havana",
    "sg:classifiers":[
        {
            "category":"Personal",
            "subcategory":"Beauty Salon",
            "type":"Services"
        }
    ],
    "sg:phone":"+1 309 543 2961",
    "sg:postcode":"62644",
    "sg:province":"IL",
    "sg:tags":[
        "shop"
    ],
    "wof:name":"Shear Techniques",
    "wof:placetype":"venue"
},
  "geometry": {"coordinates":[-90.062342,40.30091],"type":"Point"}
}