{
  "type": "Feature",
  "properties": {
    "iso:country":"US",
    "sg:address":"116 N Monroe St",
    "sg:city":"Pittsfield",
    "sg:classifiers":[
        {
            "category":"Organizations",
            "subcategory":"Non-profit Organization",
            "type":"Services"
        }
    ],
    "sg:phone":"+1 217 285 6353",
    "sg:postcode":"62363",
    "sg:province":"IL",
    "sg:tags":[
        "information",
        "alcoholism",
        "treatment"
    ],
    "wof:name":"Hopewell Clinical",
    "wof:placetype":"venue"
},
  "geometry": {"coordinates":[-90.804502,39.607714],"type":"Point"}
}