{
  "type": "Feature",
  "properties": {
    "addr:full":"16440 76th Ave Tinley Park IL 60477",
    "addr:housenumber":"16440",
    "addr:postcode":"60477",
    "addr:street":"76Th Ave",
    "iso:country":"US",
    "sg:address":"16440 76th Ave",
    "sg:city":"Tinley Park",
    "sg:classifiers":[
        {
            "category":"Organizations",
            "subcategory":"Membership Organization",
            "type":"Services"
        }
    ],
    "sg:phone":"+1 708 429 5409",
    "sg:postcode":"60477",
    "sg:province":"IL",
    "sg:tags":[
        "athletic"
    ],
    "wof:name":"Brementowne Youth",
    "wof:placetype":"venue"
},
  "geometry": {"coordinates":[-87.803769,41.591865],"type":"Point"}
}