{
  "type": "Feature",
  "properties": {
    "iso:country":"US",
    "sg:address":"14396 Dearborn Ave",
    "sg:city":"South Beloit",
    "sg:classifiers":[
        {
            "category":"Autos & Motor Vehicles",
            "subcategory":"Automobile Sales",
            "type":"Retail Goods"
        }
    ],
    "sg:phone":"+1 815 389 2630",
    "sg:postcode":"61080",
    "sg:province":"WI",
    "sg:tags":[
        "car",
        "dealer"
    ],
    "wof:name":"Bill King's Used Cars",
    "wof:placetype":"venue"
},
  "geometry": {"coordinates":[-89.019952,42.464352],"type":"Point"}
}