{
  "type": "Feature",
  "properties": {
    "iso:country":"US",
    "sg:address":"1806 Gleasman Rd",
    "sg:city":"Rockford",
    "sg:classifiers":[
        {
            "category":"Recreation",
            "subcategory":"Marina",
            "type":"Entertainment"
        }
    ],
    "sg:phone":"+1 815 624 7961",
    "sg:postcode":"61103",
    "sg:province":"IL",
    "sg:tags":[
        "operation"
    ],
    "wof:name":"Leon & Patricia Moreford",
    "wof:placetype":"venue"
},
  "geometry": {"coordinates":[-89.07600100000001,42.397362],"type":"Point"}
}