{
  "type": "Feature",
  "properties": {
    "addr:full":"1300 W Devon Ave Chicago IL 60660",
    "addr:housenumber":"1300",
    "addr:postcode":"60660",
    "addr:street":"W Devon Ave",
    "iso:country":"US",
    "sg:address":"1300 W Devon Ave",
    "sg:city":"Chicago",
    "sg:classifiers":[
        {
            "category":"Retail",
            "subcategory":"Funeral Services",
            "type":"Services"
        }
    ],
    "sg:phone":"+1 312 256 5700",
    "sg:postcode":"60660",
    "sg:province":"IL",
    "wof:name":"Waynestay Family Services",
    "wof:placetype":"venue"
},
  "geometry": {"coordinates":[-87.66361499999999,41.998155],"type":"Point"}
}