{
  "type": "Feature",
  "properties": {
    "iso:country":"US",
    "sg:address":"1300 W Devon Ave",
    "sg:city":"Chicago",
    "sg:classifiers":[
        {
            "category":"Retail",
            "subcategory":"Funeral Services",
            "type":"Services"
        }
    ],
    "sg:phone":"+1 312 256 5700",
    "sg:postcode":"60660",
    "sg:province":"IL",
    "wof:name":"Waynestay Family Services",
    "wof:placetype":"venue"
},
  "geometry": {"coordinates":[-87.663615,41.998155],"type":"Point"}
}