{
  "type": "Feature",
  "properties": {
    "addr:full":"130 S Jefferson Street Chicago IL 60661",
    "addr:housenumber":"130",
    "addr:postcode":"60661",
    "addr:street":"S Jefferson Street",
    "iso:country":"US",
    "sg:address":"130 S Jefferson Street",
    "sg:city":"Chicago",
    "sg:classifiers":[
        {
            "category":"Professional",
            "subcategory":"Lawyer & Legal Services",
            "type":"Services"
        }
    ],
    "sg:phone":"+1 312 876 0600",
    "sg:postcode":"60661",
    "sg:province":"IL",
    "wof:name":"Jeffrey G Liss PC",
    "wof:placetype":"venue"
},
  "geometry": {"coordinates":[-87.642618,41.880152],"type":"Point"}
}