{
  "type": "Feature",
  "properties": {
    "iso:country":"US",
    "sg:address":"24 Oakwood Dr",
    "sg:city":"Prospect Heights",
    "sg:classifiers":[
        {
            "category":"Building & Trades",
            "subcategory":"Construction",
            "type":"Services"
        }
    ],
    "sg:phone":"+1 847 215 9816",
    "sg:postcode":"60070",
    "sg:province":"IL",
    "sg:tags":[
        "contractor"
    ],
    "wof:name":"Project Partners",
    "wof:placetype":"venue"
},
  "geometry": {"coordinates":[-87.944589,42.115843],"type":"Point"}
}