{
  "type": "Feature",
  "properties": {
    "addr:full":"5501 N Ashland Ave Chicago IL 60640",
    "addr:housenumber":"5501",
    "addr:postcode":"60640",
    "addr:street":"N Ashland Ave",
    "iso:country":"US",
    "sg:address":"5501 N Ashland Ave",
    "sg:city":"Chicago",
    "sg:classifiers":[
        {
            "category":"Banks & Credit Unions",
            "subcategory":"Bank",
            "type":"Services"
        }
    ],
    "sg:phone":"+1 773 878 5905",
    "sg:postcode":"60640",
    "sg:province":"IL",
    "sg:website":"www.53.com",
    "wof:name":"Fifth Third Bank",
    "wof:placetype":"venue"
},
  "geometry": {"coordinates":[-87.669669,41.981576],"type":"Point"}
}