{
  "type": "Feature",
  "properties": {
    "iso:country":"US",
    "sg:address":"233 E State Rte 38",
    "sg:city":"Rochelle",
    "sg:classifiers":[
        {
            "category":"Insurance",
            "subcategory":"Insurance Agent",
            "type":"Services"
        }
    ],
    "sg:phone":"+1 815 562 8164",
    "sg:postcode":"61068",
    "sg:province":"IL",
    "wof:name":"Country Insurance & Financial",
    "wof:placetype":"venue"
},
  "geometry": {"coordinates":[-89.06295,41.934161],"type":"Point"}
}