{
  "type": "Feature",
  "properties": {
    "addr:full":"151 E Highland Ave Elgin IL 60120",
    "addr:housenumber":"151",
    "addr:postcode":"60120",
    "addr:street":"E Highland Ave",
    "iso:country":"US",
    "sg:address":"151 E Highland Ave",
    "sg:city":"Elgin",
    "sg:classifiers":[
        {
            "category":"Personal",
            "subcategory":"Beauty Salon",
            "type":"Services"
        }
    ],
    "sg:phone":"+1 847 695 9590",
    "sg:postcode":"60120",
    "sg:province":"IL",
    "sg:tags":[
        "wig",
        "hair",
        "piece",
        "shop"
    ],
    "wof:name":"Studio One Hair Design",
    "wof:placetype":"venue"
},
  "geometry": {"coordinates":[-88.283997,42.0382],"type":"Point"}
}