{
  "type": "Feature",
  "properties": {
    "addr:full":"6139 W Ogden Ave Cicero IL 60804",
    "addr:housenumber":"6139",
    "addr:postcode":"60804",
    "addr:street":"W Ogden Ave",
    "iso:country":"US",
    "sg:address":"6139 W Ogden Ave",
    "sg:city":"Cicero",
    "sg:classifiers":[
        {
            "category":"Local Transit",
            "type":"Transportation"
        }
    ],
    "sg:phone":"+1 708 222 9228",
    "sg:postcode":"60804",
    "sg:province":"IL",
    "sg:tags":[
        "limousine"
    ],
    "wof:name":"American A-One Limousine Svc",
    "wof:placetype":"venue"
},
  "geometry": {"coordinates":[-87.77730200000001,41.832677],"type":"Point"}
}