{
  "type": "Feature",
  "properties": {
    "iso:country":"US",
    "sg:address":"8100 W 157th St",
    "sg:city":"Orland Park",
    "sg:classifiers":[
        {
            "category":"Professional",
            "subcategory":"Advertising",
            "type":"Services"
        }
    ],
    "sg:phone":"+1 708 226 0994",
    "sg:postcode":"60462",
    "sg:province":"IL",
    "sg:tags":[
        "mail",
        "direct"
    ],
    "wof:name":"Mail Experts",
    "wof:placetype":"venue"
},
  "geometry": {"coordinates":[-87.816355,41.605528],"type":"Point"}
}