{
  "type": "Feature",
  "properties": {
    "addr:full":"348 E Moultrie St Bement IL 61813",
    "addr:housenumber":"348",
    "addr:postcode":"61813",
    "addr:street":"E Moultrie St",
    "iso:country":"US",
    "sg:address":"348 E Moultrie St",
    "sg:city":"Bement",
    "sg:classifiers":[
        {
            "category":"Professional",
            "type":"Services"
        }
    ],
    "sg:phone":"+1 217 678 3302",
    "sg:postcode":"61813",
    "sg:province":"IL",
    "wof:name":"Fair Consturction Services",
    "wof:placetype":"venue"
},
  "geometry": {"coordinates":[-88.56671900000001,39.918531],"type":"Point"}
}