{
  "type": "Feature",
  "properties": {
    "iso:country":"US",
    "sg:address":"117 E University Ave",
    "sg:city":"Champaign",
    "sg:classifiers":[
        {
            "category":"Arts & Performance",
            "subcategory":"Theater",
            "type":"Entertainment"
        }
    ],
    "sg:phone":"+1   ",
    "sg:postcode":"61820",
    "sg:province":"IL",
    "sg:tags":[
        "group",
        "jewelry"
    ],
    "wof:name":"Bryan Jewelery and Sound & Ltg",
    "wof:placetype":"venue"
},
  "geometry": {"coordinates":[-88.237286,40.116257],"type":"Point"}
}