{
  "type": "Feature",
  "properties": {
    "iso:country":"US",
    "sg:address":"235 S Kenilworth Ave",
    "sg:city":"Elmhurst",
    "sg:classifiers":[
        {
            "category":"Organizations",
            "subcategory":"Religious Organization",
            "type":"Services"
        }
    ],
    "sg:phone":"+1 630 832 2580",
    "sg:postcode":"60126",
    "sg:province":"IL",
    "sg:tags":[
        "church"
    ],
    "wof:name":"First Congregational Church",
    "wof:placetype":"venue"
},
  "geometry": {"coordinates":[-87.93837000000001,41.893002],"type":"Point"}
}