{
  "type": "Feature",
  "properties": {
    "addr:full":"12 Emerald Ter Belleville IL 62226",
    "addr:housenumber":"12",
    "addr:postcode":"62226",
    "addr:street":"Emerald Ter",
    "iso:country":"US",
    "sg:address":"12 Emerald Ter",
    "sg:city":"Belleville",
    "sg:classifiers":[
        {
            "category":"Utilities",
            "subcategory":"Telephone",
            "type":"Services"
        },
        {
            "category":"Professional",
            "subcategory":"Computer Services",
            "type":"Services"
        }
    ],
    "sg:phone":"+1 618 257 3737",
    "sg:postcode":"62226",
    "sg:province":"IL",
    "sg:tags":[
        "internet",
        "provider"
    ],
    "wof:name":"Htc Technologies Inc",
    "wof:placetype":"venue"
},
  "geometry": {"coordinates":[-89.98501400000001,38.547602],"type":"Point"}
}