{
  "type": "Feature",
  "properties": {
    "iso:country":"US",
    "sg:address":"120 Dekalb St",
    "sg:city":"Joliet",
    "sg:classifiers":[
        {
            "category":"Wholesale",
            "subcategory":"Stationery",
            "type":"Manufacturing & Wholesale Goods"
        },
        {
            "category":"Professional",
            "subcategory":"Business Services",
            "type":"Services"
        }
    ],
    "sg:phone":"+1 815 726 2421",
    "sg:postcode":"60436",
    "sg:province":"IL",
    "sg:tags":[
        "packaging",
        "paper"
    ],
    "wof:name":"Retail Packaging Outlet Inc",
    "wof:placetype":"venue"
},
  "geometry": {"coordinates":[-88.0844,41.521043],"type":"Point"}
}