{
  "type": "Feature",
  "properties": {
    "iso:country":"US",
    "sg:address":"2638 United Ln",
    "sg:city":"Elk Grove Village",
    "sg:classifiers":[
        {
            "category":"Manufacturing",
            "subcategory":"Metals",
            "type":"Manufacturing & Wholesale Goods"
        }
    ],
    "sg:phone":"+1 847 350 0118",
    "sg:postcode":"60007",
    "sg:province":"IL",
    "sg:tags":[
        "machine",
        "screw",
        "product",
        "mfg"
    ],
    "wof:name":"Tpps Co",
    "wof:placetype":"venue"
},
  "geometry": {"coordinates":[-87.946005,41.989737],"type":"Point"}
}