{
  "type": "Feature",
  "properties": {
    "addr:full":"9661 W 143rd St Orland Park IL 60462",
    "addr:housenumber":"9661",
    "addr:postcode":"60462",
    "addr:street":"W 143Rd St",
    "iso:country":"US",
    "sg:address":"9661 W 143rd St",
    "sg:city":"Orland Park",
    "sg:classifiers":[
        {
            "category":"Health Services",
            "subcategory":"Doctor",
            "type":"Services"
        }
    ],
    "sg:phone":"+1 708 403 8611",
    "sg:postcode":"60462",
    "sg:province":"IL",
    "wof:name":"Seper William A DDS PC",
    "wof:placetype":"venue"
},
  "geometry": {"coordinates":[-87.856185,41.630373],"type":"Point"}
}