{
  "type": "Feature",
  "properties": {
    "addr:full":"2323 So. Wentworth Avenue Chicago IL 60616",
    "addr:housenumber":"2323",
    "addr:postcode":"60616",
    "addr:street":"So. Wentworth Avenue",
    "iso:country":"US",
    "sg:address":"2323 So. Wentworth Avenue",
    "sg:city":"Chicago",
    "sg:classifiers":[
        {
            "category":"Restaurant",
            "type":"Food & Drink"
        }
    ],
    "sg:postcode":"60616",
    "sg:province":"IL",
    "sg:tags":[
        "chinese"
    ],
    "wof:name":"Chiam Restaurant",
    "wof:placetype":"venue"
},
  "geometry": {"coordinates":[-87.631612,41.850287],"type":"Point"}
}