{
  "type": "Feature",
  "properties": {
    "iso:country":"US",
    "sg:address":"2685 Coyle Ave",
    "sg:city":"Elk Grove Village",
    "sg:classifiers":[
        {
            "category":"Wholesale",
            "subcategory":"Machinery & Supplies",
            "type":"Manufacturing & Wholesale Goods"
        }
    ],
    "sg:phone":"+1 847 956 8692",
    "sg:postcode":"60007",
    "sg:province":"IL",
    "sg:tags":[
        "equipment",
        "industrial"
    ],
    "wof:name":"Halm Industries Co Inc",
    "wof:placetype":"venue"
},
  "geometry": {"coordinates":[-87.939742,42.001463],"type":"Point"}
}