{
  "type": "Feature",
  "properties": {
    "iso:country":"US",
    "sg:address":"3475 County Road 450 E",
    "sg:city":"Foosland",
    "sg:classifiers":[
        {
            "category":"Manufacturing",
            "subcategory":"Food",
            "type":"Manufacturing & Wholesale Goods"
        },
        {
            "category":"Farming",
            "subcategory":"Farm",
            "type":"Manufacturing & Wholesale Goods"
        }
    ],
    "sg:phone":"+1 217 784 4145",
    "sg:postcode":"61845",
    "sg:province":"IL",
    "sg:tags":[
        "corn",
        "product"
    ],
    "wof:name":"Bud Barnes",
    "wof:placetype":"venue"
},
  "geometry": {"coordinates":[-88.375362,40.376949],"type":"Point"}
}