{
  "type": "Feature",
  "properties": {
    "iso:country":"US",
    "sg:address":"9756 S Indiana Ave",
    "sg:city":"Chicago",
    "sg:classifiers":[
        {
            "category":"Wholesale",
            "subcategory":"Construction Materials",
            "type":"Manufacturing & Wholesale Goods"
        }
    ],
    "sg:phone":"+1 773 370 5437",
    "sg:postcode":"60628",
    "sg:province":"IL",
    "sg:tags":[
        "straw"
    ],
    "wof:name":"Blu And Straw",
    "wof:placetype":"venue"
},
  "geometry": {"coordinates":[-87.618905,41.717115],"type":"Point"}
}