{
  "type": "Feature",
  "properties": {
    "iso:country":"US",
    "sg:address":"501 63rd St",
    "sg:city":"Downers Grove",
    "sg:classifiers":[
        {
            "category":"Utilities",
            "subcategory":"Telephone",
            "type":"Services"
        }
    ],
    "sg:phone":"+1 630 719 5294",
    "sg:postcode":"60516",
    "sg:province":"IL",
    "sg:tags":[
        "communications",
        "radiotelephone",
        "communication"
    ],
    "wof:name":"MCI",
    "wof:placetype":"venue"
},
  "geometry": {"coordinates":[-87.99622599999999,41.773181],"type":"Point"}
}