{
  "type": "Feature",
  "properties": {
    "addr:full":"650 Church St Lake Zurich IL 60047",
    "addr:housenumber":"650",
    "addr:postcode":"60047",
    "addr:street":"Church St",
    "iso:country":"US",
    "sg:address":"650 Church St",
    "sg:city":"Lake Zurich",
    "sg:classifiers":[
        {
            "category":"Wholesale",
            "subcategory":"Construction Materials",
            "type":"Manufacturing & Wholesale Goods"
        }
    ],
    "sg:phone":"+1 847 438 5965",
    "sg:postcode":"60047",
    "sg:province":"IL",
    "sg:tags":[
        "equipment",
        "roofing",
        "supply"
    ],
    "wof:name":"Gulf Eagle Supply Inc",
    "wof:placetype":"venue"
},
  "geometry": {"coordinates":[-88.085066,42.205506],"type":"Point"}
}