{
  "type": "Feature",
  "properties": {
    "addr:full":"123 W Walnut St Watseka IL 60970",
    "addr:housenumber":"123",
    "addr:postcode":"60970",
    "addr:street":"W Walnut St",
    "iso:country":"US",
    "sg:address":"123 W Walnut St",
    "sg:city":"Watseka",
    "sg:classifiers":[
        {
            "category":"Restaurant",
            "type":"Food & Drink"
        }
    ],
    "sg:menulink":"http://www.allmenus.com/il/middleport/225361-caseys-general-store/menu/",
    "sg:phone":"+1 815 432 6670",
    "sg:postcode":"60970",
    "sg:province":"IL",
    "sg:tags":[
        "american",
        "pizza"
    ],
    "wof:name":"Casey's General Store",
    "wof:placetype":"venue"
},
  "geometry": {"coordinates":[-87.73492400000001,40.776256],"type":"Point"}
}