{
  "type": "Feature",
  "properties": {
    "addr:full":"2207 S Route 59 Plainfield IL 60586",
    "addr:housenumber":"2207",
    "addr:postcode":"60586",
    "addr:street":"S Route 59",
    "iso:country":"US",
    "sg:address":"2207 S Route 59",
    "sg:city":"Plainfield",
    "sg:classifiers":[
        {
            "category":"Real Estate",
            "subcategory":"Real Estate Services",
            "type":"Services"
        }
    ],
    "sg:phone":"+1 815 436 3250",
    "sg:postcode":"60586",
    "sg:province":"IL",
    "sg:tags":[
        "management"
    ],
    "wof:name":"Brentwood Cove Shopping Center",
    "wof:placetype":"venue"
},
  "geometry": {"coordinates":[-88.200214,41.562027],"type":"Point"}
}