{
  "type": "Feature",
  "properties": {
    "addr:full":"401 Townline Rd Mundelein IL 60060",
    "addr:housenumber":"401",
    "addr:postcode":"60060",
    "addr:street":"Townline Rd",
    "iso:country":"US",
    "sg:address":"401 Townline Rd",
    "sg:city":"Mundelein",
    "sg:classifiers":[
        {
            "category":"Autos & Motor Vehicles",
            "subcategory":"Auto Supplies",
            "type":"Retail Goods"
        },
        {
            "category":"Wholesale",
            "subcategory":"Electrical",
            "type":"Manufacturing & Wholesale Goods"
        },
        {
            "category":"Wholesale",
            "subcategory":"Auto Parts",
            "type":"Manufacturing & Wholesale Goods"
        }
    ],
    "sg:phone":"+1 847 566 6509",
    "sg:postcode":"60060",
    "sg:province":"IL",
    "sg:tags":[
        "body",
        "battery",
        "automobile",
        "accessory",
        "equipment",
        "truck"
    ],
    "sg:website":"http://www.oreillyauto.com?utm_source=yellowpages&utm_medium=iyp&utm_campaign=3412",
    "wof:name":"O'Reilly Auto Parts",
    "wof:placetype":"venue"
},
  "geometry": {"coordinates":[-87.998283,42.239882],"type":"Point"}
}