{
  "type": "Feature",
  "properties": {
    "addr:full":"2800 W Sherwin Ave Chicago IL 60645",
    "addr:housenumber":"2800",
    "addr:postcode":"60645",
    "addr:street":"W Sherwin Ave",
    "iso:country":"US",
    "sg:address":"2800 W Sherwin Ave",
    "sg:city":"Chicago",
    "sg:classifiers":[
        {
            "category":"Organizations",
            "subcategory":"Religious Organization",
            "type":"Services"
        }
    ],
    "sg:phone":"+1 773 761 5700",
    "sg:postcode":"60645",
    "sg:province":"IL",
    "sg:tags":[
        "church",
        "related",
        "activity"
    ],
    "wof:name":"Temple Menorah",
    "wof:placetype":"venue"
},
  "geometry": {"coordinates":[-87.70028000000001,42.014779],"type":"Point"}
}