{
  "type": "Feature",
  "properties": {
    "addr:full":"2740 Cable Pl North Chicago IL 60064",
    "addr:housenumber":"2740",
    "addr:postcode":"60064",
    "addr:street":"Cable Pl",
    "iso:country":"US",
    "sg:address":"2740 Cable Pl",
    "sg:city":"North Chicago",
    "sg:classifiers":[
        {
            "category":"Professional",
            "subcategory":"Employment Agencies",
            "type":"Services"
        }
    ],
    "sg:phone":"+1 847 689 2100",
    "sg:postcode":"60064",
    "sg:province":"IL",
    "sg:tags":[
        "opportunity"
    ],
    "wof:name":"Temps Now Employment & Plcmnt",
    "wof:placetype":"venue"
},
  "geometry": {"coordinates":[-87.84799700000001,42.313279],"type":"Point"}
}