{
  "type": "Feature",
  "properties": {
    "addr:full":"317 Oak St Waukegan IL 60085",
    "addr:housenumber":"317",
    "addr:postcode":"60085",
    "addr:street":"Oak St",
    "iso:country":"US",
    "sg:address":"317 Oak St",
    "sg:city":"Waukegan",
    "sg:classifiers":[
        {
            "category":"Banks & Credit Unions",
            "subcategory":"Financial Services",
            "type":"Services"
        }
    ],
    "sg:phone":"+1 847 332 2488",
    "sg:postcode":"60085",
    "sg:province":"IL",
    "sg:tags":[
        "investment",
        "closed"
    ],
    "wof:name":"Middlechild & Co",
    "wof:placetype":"venue"
},
  "geometry": {"coordinates":[-87.83185899999999,42.354062],"type":"Point"}
}