{
  "type": "Feature",
  "properties": {
    "iso:country":"US",
    "sg:address":"1575 S Barrington Rd",
    "sg:city":"Hoffman Estates",
    "sg:classifiers":[
        {
            "category":"Health Services",
            "subcategory":"Doctor",
            "type":"Services"
        }
    ],
    "sg:phone":"+1 847 839 8164",
    "sg:postcode":"60194",
    "sg:province":"IL",
    "sg:tags":[
        "physician",
        "surgeon"
    ],
    "wof:name":"Grabowski Surgical Assoc",
    "wof:placetype":"venue"
},
  "geometry": {"coordinates":[-88.144537,42.05061],"type":"Point"}
}