{
  "type": "Feature",
  "properties": {
    "addr:full":"437 Cumberland Ln Bolingbrook IL 60440",
    "addr:housenumber":"437",
    "addr:postcode":"60440",
    "addr:street":"Cumberland Ln",
    "iso:country":"US",
    "sg:address":"437 Cumberland Ln",
    "sg:city":"Bolingbrook",
    "sg:classifiers":[
        {
            "category":"Health Services",
            "subcategory":"Clinic",
            "type":"Services"
        }
    ],
    "sg:phone":"+1 630 759 5494",
    "sg:postcode":"60440",
    "sg:province":"IL",
    "sg:tags":[
        "wellness",
        "program"
    ],
    "wof:name":"New World Wellness",
    "wof:placetype":"venue"
},
  "geometry": {"coordinates":[-88.085784,41.694745],"type":"Point"}
}