{
  "type": "Feature",
  "properties": {
    "addr:full":"43 Jacobsen Ave Glendale Heights IL 60139",
    "addr:housenumber":"43",
    "addr:postcode":"60139",
    "addr:street":"Jacobsen Ave",
    "iso:country":"US",
    "sg:address":"43 Jacobsen Ave",
    "sg:city":"Glendale Heights",
    "sg:classifiers":[
        {
            "category":"Shopping",
            "subcategory":"Optical Goods",
            "type":"Retail Goods"
        }
    ],
    "sg:phone":"+1   ",
    "sg:postcode":"60139",
    "sg:province":"IL",
    "wof:name":"Larkin Vision Center",
    "wof:placetype":"venue"
},
  "geometry": {"coordinates":[-88.08805599999999,41.911533],"type":"Point"}
}