{
  "type": "Feature",
  "properties": {
    "addr:full":"4420 W Madison St Chicago IL 60624",
    "addr:housenumber":"4420",
    "addr:postcode":"60624",
    "addr:street":"W Madison St",
    "iso:country":"US",
    "sg:address":"4420 W Madison St",
    "sg:city":"Chicago",
    "sg:classifiers":[
        {
            "category":"Community Center",
            "subcategory":"Social",
            "type":"Public Place"
        }
    ],
    "sg:phone":"+1 773 379 0138",
    "sg:postcode":"60624",
    "sg:province":"IL",
    "sg:tags":[
        "club"
    ],
    "wof:name":"Chicago Born Losers Motorcycle Club",
    "wof:placetype":"venue"
},
  "geometry": {"coordinates":[-87.735944,41.880803],"type":"Point"}
}