{
  "type": "Feature",
  "properties": {
    "iso:country":"US",
    "sg:address":"1605 Lincoln Rd",
    "sg:city":"Champaign",
    "sg:classifiers":[
        {
            "category":"Shopping",
            "subcategory":"Pharmacy",
            "type":"Retail Goods"
        }
    ],
    "sg:phone":"+1 217 359 3640",
    "sg:postcode":"61821",
    "sg:province":"IL",
    "sg:tags":[
        "medicines-patent",
        "proprietary"
    ],
    "sg:website":"http://www.shaklee.com",
    "wof:name":"Shaklee Distributor",
    "wof:placetype":"venue"
},
  "geometry": {"coordinates":[-88.265092,40.098153],"type":"Point"}
}