{
  "type": "Feature",
  "properties": {
    "addr:full":"9139 S Pulaski Rd Evergreen Park IL 60805",
    "addr:housenumber":"9139",
    "addr:postcode":"60805",
    "addr:street":"S Pulaski Rd",
    "iso:country":"US",
    "sg:address":"9139 S Pulaski Rd",
    "sg:city":"Evergreen Park",
    "sg:classifiers":[
        {
            "category":"Professional",
            "subcategory":"Management & Consulting",
            "type":"Services"
        }
    ],
    "sg:phone":"+1 708 857 4790",
    "sg:postcode":"60805",
    "sg:province":"IL",
    "wof:name":"Fep Enterprises",
    "wof:placetype":"venue"
},
  "geometry": {"coordinates":[-87.72152199999999,41.726387],"type":"Point"}
}