{
  "type": "Feature",
  "properties": {
    "addr:full":"3815 Rfd Lake Zurich IL 60047",
    "addr:housenumber":"3815",
    "addr:postcode":"60047",
    "addr:street":"Rfd",
    "iso:country":"US",
    "sg:address":"3815 Rfd",
    "sg:city":"Lake Zurich",
    "sg:classifiers":[
        {
            "category":"Shopping",
            "type":"Retail Goods"
        }
    ],
    "sg:phone":"+1   ",
    "sg:postcode":"60047",
    "sg:province":"IL",
    "sg:tags":[
        "merchandise"
    ],
    "wof:name":"Crystal Clear Communications",
    "wof:placetype":"venue"
},
  "geometry": {"coordinates":[-88.028088,42.182599],"type":"Point"}
}