{
  "type": "Feature",
  "properties": {
    "iso:country":"US",
    "sg:address":"3036 W Irving Park Road",
    "sg:city":"Chicago",
    "sg:classifiers":[
        {
            "category":"Health Services",
            "subcategory":"Doctor",
            "type":"Services"
        },
        {
            "category":"Personal",
            "subcategory":"Hair Removal",
            "type":"Services"
        },
        {
            "category":"Health Services",
            "subcategory":"Chiropractor",
            "type":"Services"
        },
        {
            "category":"Health Services",
            "subcategory":"Dentist",
            "type":"Services"
        }
    ],
    "sg:phone":"+1 773 267 2255",
    "sg:postcode":"60618",
    "sg:province":"IL",
    "sg:tags":[
        "practice",
        "family"
    ],
    "wof:name":"Diversey Dental Care",
    "wof:placetype":"venue"
},
  "geometry": {"coordinates":[-87.704556,41.954114],"type":"Point"}
}