{
  "type": "Feature",
  "properties": {
    "addr:full":"150 Ernest Mooney Dr Bourbonnais IL 60914",
    "addr:housenumber":"150",
    "addr:postcode":"60914",
    "addr:street":"Ernest Mooney Dr",
    "iso:country":"US",
    "sg:address":"150 Ernest Mooney Dr",
    "sg:city":"Bourbonnais",
    "sg:classifiers":[
        {
            "category":"Manufacturing",
            "subcategory":"Lumber",
            "type":"Manufacturing & Wholesale Goods"
        }
    ],
    "sg:phone":"+1 815 933 8059",
    "sg:postcode":"60914",
    "sg:province":"IL",
    "sg:tags":[
        "chemical",
        "preparation",
        "mill",
        "po",
        "mfg"
    ],
    "wof:name":"Armstrong World Industries",
    "wof:placetype":"venue"
},
  "geometry": {"coordinates":[-87.861689,41.161524],"type":"Point"}
}