{
  "type": "Feature",
  "properties": {
    "addr:full":"426 N Main St Wheaton IL 60187",
    "addr:housenumber":"426",
    "addr:postcode":"60187",
    "addr:street":"N Main St",
    "iso:country":"US",
    "sg:address":"426 N Main St",
    "sg:city":"Wheaton",
    "sg:classifiers":[
        {
            "category":"Building & Trades",
            "subcategory":"Construction",
            "type":"Services"
        }
    ],
    "sg:phone":"+1 630 462 9334",
    "sg:postcode":"60187",
    "sg:province":"IL",
    "sg:tags":[
        "carpenter"
    ],
    "wof:name":"Thomas Dunn Inc",
    "wof:placetype":"venue"
},
  "geometry": {"coordinates":[-88.106669,41.868557],"type":"Point"}
}