{
  "type": "Feature",
  "properties": {
    "addr:full":"359 Evergreen Ave Bensenville IL 60106",
    "addr:housenumber":"359",
    "addr:postcode":"60106",
    "addr:street":"Evergreen Ave",
    "iso:country":"US",
    "sg:address":"359 Evergreen Ave",
    "sg:city":"Bensenville",
    "sg:classifiers":[
        {
            "category":"Building & Trades",
            "subcategory":"Construction",
            "type":"Services"
        }
    ],
    "sg:phone":"+1 630 766 6834",
    "sg:postcode":"60106",
    "sg:province":"IL",
    "sg:tags":[
        "welder"
    ],
    "wof:name":"Leco Welding Inc",
    "wof:placetype":"venue"
},
  "geometry": {"coordinates":[-87.930109,41.951023],"type":"Point"}
}