{
  "type": "Feature",
  "properties": {
    "addr:full":"419 S 2nd St Geneva IL 60134",
    "addr:housenumber":"419",
    "addr:postcode":"60134",
    "addr:street":"S 2Nd St",
    "iso:country":"US",
    "sg:address":"419 S 2nd St",
    "sg:city":"Geneva",
    "sg:classifiers":[
        {
            "category":"Professional",
            "subcategory":"Lawyer & Legal Services",
            "type":"Services"
        }
    ],
    "sg:phone":"+1 630 262 1222",
    "sg:postcode":"60134",
    "sg:province":"IL",
    "sg:tags":[
        "attorney"
    ],
    "wof:name":"Paul Conarty Ltd",
    "wof:placetype":"venue"
},
  "geometry": {"coordinates":[-88.30749400000001,41.883399],"type":"Point"}
}