{
  "type": "Feature",
  "properties": {
    "addr:full":"3000 N Halsted St Suite 703 Chicago IL 60657",
    "addr:housenumber":"3000",
    "addr:postcode":"60657",
    "addr:street":"N Halsted St Suite 703",
    "iso:country":"US",
    "sg:address":"3000 N Halsted St Suite 703",
    "sg:city":"Chicago",
    "sg:classifiers":[
        {
            "category":"Health Services",
            "subcategory":"Doctor",
            "type":"Services"
        },
        {
            "category":"Health Services",
            "subcategory":"Health Practitioner",
            "type":"Services"
        }
    ],
    "sg:phone":"+1 773 327 6624",
    "sg:postcode":"60657",
    "sg:province":"IL",
    "sg:tags":[
        "nutritionist"
    ],
    "sg:website":"www.olivera.com/",
    "wof:name":"Olivera Nutrition and Weight Management SC",
    "wof:placetype":"venue"
},
  "geometry": {"coordinates":[-87.649134,41.937136],"type":"Point"}
}