{
  "type": "Feature",
  "properties": {
    "iso:country":"US",
    "sg:address":"2827 N Broadway St",
    "sg:city":"Chicago",
    "sg:classifiers":[
        {
            "category":"Restaurant",
            "type":"Food & Drink"
        }
    ],
    "sg:menulink":"http://www.allmenus.com/il/chicago/209719-renaldis-pizza/menu/",
    "sg:phone":"+1 773 248 2448",
    "sg:postcode":"60657",
    "sg:province":"IL",
    "sg:tags":[
        "italian"
    ],
    "wof:name":"Renaldi's Pizza",
    "wof:placetype":"venue"
},
  "geometry": {"coordinates":[-87.644696,41.933479],"type":"Point"}
}