{
  "type": "Feature",
  "properties": {
    "addr:full":"9327 S Loomis St Chicago IL 60620",
    "addr:housenumber":"9327",
    "addr:postcode":"60620",
    "addr:street":"S Loomis St",
    "iso:country":"US",
    "sg:address":"9327 S Loomis St",
    "sg:city":"Chicago",
    "sg:classifiers":[
        {
            "category":"Building & Trades",
            "subcategory":"Landscaping Services",
            "type":"Services"
        }
    ],
    "sg:phone":"+1 773 445 5680",
    "sg:postcode":"60620",
    "sg:province":"IL",
    "sg:tags":[
        "lawn",
        "landscape",
        "contractor"
    ],
    "wof:name":"O'wallace Lanscaping Inc",
    "wof:placetype":"venue"
},
  "geometry": {"coordinates":[-87.657871,41.724428],"type":"Point"}
}