{
  "type": "Feature",
  "properties": {
    "addr:full":"4631 N Lincoln Ave Chicago IL 60625",
    "addr:housenumber":"4631",
    "addr:postcode":"60625",
    "addr:street":"N Lincoln Ave",
    "iso:country":"US",
    "sg:address":"4631 N Lincoln Ave",
    "sg:city":"Chicago",
    "sg:classifiers":[
        {
            "category":"Building & Trades",
            "subcategory":"Locksmith",
            "type":"Services"
        }
    ],
    "sg:phone":"+1 773 681 5715",
    "sg:postcode":"60625",
    "sg:province":"IL",
    "sg:tags":[
        "key"
    ],
    "wof:name":"0101 Emergency Locksmith & Car Keys",
    "wof:placetype":"venue"
},
  "geometry": {"coordinates":[-87.686627,41.966057],"type":"Point"}
}