{
  "type": "Feature",
  "properties": {
    "addr:full":"36 E 100th St Chicago IL 60628",
    "addr:housenumber":"36",
    "addr:postcode":"60628",
    "addr:street":"E 100Th St",
    "iso:country":"US",
    "sg:address":"36 E 100th St",
    "sg:city":"Chicago",
    "sg:classifiers":[
        {
            "category":"Real Estate",
            "subcategory":"Real Estate Services",
            "type":"Services"
        },
        {
            "category":"Banks & Credit Unions",
            "subcategory":"Financial Services",
            "type":"Services"
        }
    ],
    "sg:phone":"+1 773 416 2803",
    "sg:postcode":"60628",
    "sg:province":"IL",
    "sg:tags":[
        "loan",
        "processing"
    ],
    "wof:name":"Mortgage Fraud Recovery Act",
    "wof:placetype":"venue"
},
  "geometry": {"coordinates":[-87.622392,41.712645],"type":"Point"}
}