{
  "type": "Feature",
  "properties": {
    "iso:country":"US",
    "sg:address":"650 West Lake St Lower Level",
    "sg:city":"Chicago",
    "sg:classifiers":[
        {
            "category":"Arts & Performance",
            "subcategory":"Art Gallery",
            "type":"Entertainment"
        }
    ],
    "sg:phone":"+1 312 234 9091",
    "sg:postcode":"60661",
    "sg:province":"IL",
    "sg:website":"robertbillscontemporary.com/",
    "wof:name":"Robert Bills Contemporary",
    "wof:placetype":"venue"
},
  "geometry": {"coordinates":[-87.644853,41.885834],"type":"Point"}
}