{
  "type": "Feature",
  "properties": {
    "iso:country":"US",
    "sg:address":"4731 N State Rte 23",
    "sg:city":"Leland",
    "sg:phone":"+1 815 498 2356",
    "sg:postcode":"60531",
    "sg:province":"IL",
    "sg:tags":[
        "farm",
        "corn",
        "cash",
        "crop",
        "field",
        "grain"
    ],
    "wof:name":"Harold & Dorothy Parks",
    "wof:placetype":"venue"
},
  "geometry": {"coordinates":[-88.81824400000001,41.626906],"type":"Point"}
}