{
  "type": "Feature",
  "properties": {
    "iso:country":"US",
    "sg:address":"505 S Neil St",
    "sg:city":"Champaign",
    "sg:classifiers":[
        {
            "category":"Fast Food",
            "type":"Food & Drink"
        },
        {
            "category":"Restaurant",
            "type":"Food & Drink"
        },
        {
            "category":"Food & Beverages",
            "subcategory":"Bakery",
            "type":"Retail Goods"
        }
    ],
    "sg:phone":"+1 217 356 1930",
    "sg:postcode":"61820",
    "sg:province":"IL",
    "sg:tags":[
        "traditional",
        "burger",
        "american",
        "sandwich",
        "diner"
    ],
    "wof:name":"Pickles",
    "wof:placetype":"venue"
},
  "geometry": {"coordinates":[-88.2435,40.111446],"type":"Point"}
}