{
  "type": "Feature",
  "properties": {
    "addr:full":"14227 Lavergne Ave Midlothian IL 60445",
    "addr:postcode":"14227;60445",
    "addr:street":"Lavergne Ave",
    "iso:country":"US",
    "sg:address":"14227 Lavergne Ave",
    "sg:city":"Midlothian",
    "sg:classifiers":[
        {
            "category":"Recreation",
            "subcategory":"Amusement Park",
            "type":"Entertainment"
        }
    ],
    "sg:phone":"+1 708 385 5260",
    "sg:postcode":"60445",
    "sg:province":"IL",
    "wof:name":"Accurate Services",
    "wof:placetype":"venue"
},
  "geometry": {"coordinates":[-87.742262,41.633774],"type":"Point"}
}