{
  "type": "Feature",
  "properties": {
    "addr:full":"6287 S Archer Ave Chicago IL 60638",
    "addr:housenumber":"6287",
    "addr:postcode":"60638",
    "addr:street":"S Archer Ave",
    "iso:country":"US",
    "sg:address":"6287 S Archer Ave",
    "sg:city":"Chicago",
    "sg:classifiers":[
        {
            "category":"Social Services",
            "subcategory":"Child Care",
            "type":"Services"
        }
    ],
    "sg:phone":"+1 773 767 8522",
    "sg:postcode":"60638",
    "sg:province":"IL",
    "sg:tags":[
        "day"
    ],
    "wof:name":"Kid's Colony",
    "wof:placetype":"venue"
},
  "geometry": {"coordinates":[-87.777901,41.793201],"type":"Point"}
}