{
  "type": "Feature",
  "properties": {
    "addr:full":"4235 N Kedzie Ave Apt 3D Chicago IL 60618",
    "addr:housenumber":"4235",
    "addr:postcode":"60618",
    "addr:street":"N Kedzie Ave Apt 3D",
    "iso:country":"US",
    "sg:address":"4235 N Kedzie Ave Apt 3D",
    "sg:city":"Chicago",
    "sg:classifiers":[
        {
            "category":"Wholesale",
            "subcategory":"Non-durable Goods",
            "type":"Manufacturing & Wholesale Goods"
        }
    ],
    "sg:phone":"+1 773 329 5832",
    "sg:postcode":"60618",
    "sg:province":"IL",
    "sg:tags":[
        "merchandise-wholesale"
    ],
    "wof:name":"Costa Del Sol Imports",
    "wof:placetype":"venue"
},
  "geometry": {"coordinates":[-87.70814799999999,41.958182],"type":"Point"}
}