{
  "type": "Feature",
  "properties": {
    "addr:full":"500 W Madison Street Suite 2950 Chicago IL 60661",
    "addr:housenumber":"500",
    "addr:postcode":"60661",
    "addr:street":"W Madison Street Suite 2950",
    "iso:country":"US",
    "sg:address":"500 W Madison Street Suite 2950",
    "sg:city":"Chicago",
    "sg:classifiers":[
        {
            "category":"Professional",
            "subcategory":"Employment Agencies",
            "type":"Services"
        }
    ],
    "sg:phone":"+1 312 648 0583",
    "sg:postcode":"60661",
    "sg:province":"IL",
    "wof:name":"Manpower",
    "wof:placetype":"venue"
},
  "geometry": {"coordinates":[-87.639675,41.881896],"type":"Point"}
}