{
  "type": "Feature",
  "properties": {
    "iso:country":"US",
    "sg:address":"375 N Milwaukee Ave",
    "sg:city":"Vernon Hills",
    "sg:classifiers":[
        {
            "category":"Restaurant",
            "type":"Food & Drink"
        }
    ],
    "sg:menulink":"http://www.allmenus.com/il/vernon/221774-chipotle/menu/",
    "sg:phone":"+1 847 478 0883",
    "sg:postcode":"60061",
    "sg:province":"IL",
    "sg:tags":[
        "mexican"
    ],
    "wof:name":"Chipotle",
    "wof:placetype":"venue"
},
  "geometry": {"coordinates":[-87.943251,42.234089],"type":"Point"}
}