{
  "type": "Feature",
  "properties": {
    "addr:full":"300 Green St Odin IL 62870",
    "addr:housenumber":"300",
    "addr:postcode":"62870",
    "addr:street":"Green St",
    "iso:country":"US",
    "sg:address":"300 Green St",
    "sg:city":"Odin",
    "sg:classifiers":[
        {
            "category":"Health Services",
            "subcategory":"Nursing And Care Facility",
            "type":"Services"
        }
    ],
    "sg:phone":"+1 618 775 6444",
    "sg:postcode":"62870",
    "sg:province":"IL",
    "sg:tags":[
        "home",
        "convalescent"
    ],
    "wof:name":"Odin Care Ctr",
    "wof:placetype":"venue"
},
  "geometry": {"coordinates":[-89.05117300000001,38.621314],"type":"Point"}
}