{
  "type": "Feature",
  "properties": {
    "iso:country":"US",
    "sg:address":"2104 N Western Ave",
    "sg:city":"Chicago",
    "sg:classifiers":[
        {
            "category":"Restaurant",
            "type":"Food & Drink"
        }
    ],
    "sg:phone":"+1 773 384 1755",
    "sg:postcode":"60647",
    "sg:province":"IL",
    "sg:tags":[
        "italian",
        "pizza"
    ],
    "wof:name":"John's Pizzeria Ristorante & Lounge",
    "wof:placetype":"venue"
},
  "geometry": {"coordinates":[-87.68752000000001,41.920399],"type":"Point"}
}