{
  "type": "Feature",
  "properties": {
    "iso:country":"US",
    "sg:address":"4450 N Central Ave",
    "sg:city":"Chicago",
    "sg:classifiers":[
        {
            "category":"Professional",
            "subcategory":"Lawyer & Legal Services",
            "type":"Services"
        }
    ],
    "sg:phone":"+1 773 283 7803",
    "sg:postcode":"60630",
    "sg:province":"IL",
    "wof:name":"Lukacek Richard A Atty",
    "wof:placetype":"venue"
},
  "geometry": {"coordinates":[-87.76743,41.961682],"type":"Point"}
}