{
  "type": "Feature",
  "properties": {
    "addr:full":"40126 N Il Route 83 Antioch IL 60002",
    "addr:housenumber":"40126",
    "addr:postcode":"60002",
    "addr:street":"N Il Route 83",
    "iso:country":"US",
    "sg:address":"40126 N Il Route 83",
    "sg:city":"Antioch",
    "sg:classifiers":[
        {
            "category":"Real Estate",
            "subcategory":"Real Estate Services",
            "type":"Services"
        },
        {
            "category":"Real Estate",
            "subcategory":"Real Estate Agent",
            "type":"Services"
        }
    ],
    "sg:phone":"+1 847 395 7997",
    "sg:postcode":"60002",
    "sg:province":"IL",
    "sg:tags":[
        "buyer",
        "management",
        "broker"
    ],
    "wof:name":"Peter Lehman Inc",
    "wof:placetype":"venue"
},
  "geometry": {"coordinates":[-88.09058899999999,42.446398],"type":"Point"}
}