{
  "type": "Feature",
  "properties": {
    "addr:full":"2438 S Main St Bloomington IL 61704",
    "addr:housenumber":"2438",
    "addr:postcode":"61704",
    "addr:street":"S Main St",
    "iso:country":"US",
    "sg:address":"2438 S Main St",
    "sg:city":"Bloomington",
    "sg:classifiers":[
        {
            "category":"Insurance",
            "subcategory":"Hazard Insurance",
            "type":"Services"
        }
    ],
    "sg:phone":"+1 309 828 7800",
    "sg:postcode":"61704",
    "sg:province":"IL",
    "sg:tags":[
        "commercial",
        "business"
    ],
    "sg:website":"http://www.aflac.com",
    "wof:name":"Aflac",
    "wof:placetype":"venue"
},
  "geometry": {"coordinates":[-88.991213,40.44644],"type":"Point"}
}