{
  "type": "Feature",
  "properties": {
    "iso:country":"US",
    "sg:address":"8458 S Pulaski Rd",
    "sg:city":"Chicago",
    "sg:classifiers":[
        {
            "category":"Retail",
            "subcategory":"Auto Rental",
            "type":"Services"
        },
        {
            "category":"Building & Trades",
            "subcategory":"Equipment Rental",
            "type":"Services"
        },
        {
            "category":"Retail",
            "subcategory":"Storage",
            "type":"Services"
        }
    ],
    "sg:phone":"+1 773 585 5350",
    "sg:postcode":"60652",
    "sg:province":"IL",
    "sg:tags":[
        "renting",
        "moving-self",
        "van",
        "truck",
        "moving",
        "leasing",
        "trailer"
    ],
    "sg:website":"http://www.ryder.com/",
    "wof:name":"Ryder",
    "wof:placetype":"venue"
},
  "geometry": {"coordinates":[-87.721583,41.739272],"type":"Point"}
}