{
  "type": "Feature",
  "properties": {
    "iso:country":"US",
    "sg:address":"702 E 750N Rd",
    "sg:city":"Gibson City",
    "sg:classifiers":[
        {
            "category":"Building & Trades",
            "subcategory":"Construction",
            "type":"Services"
        }
    ],
    "sg:phone":"+1 217 784 8424",
    "sg:postcode":"60936",
    "sg:province":"IL",
    "sg:tags":[
        "general",
        "contractor"
    ],
    "wof:name":"Guthrie Builders",
    "wof:placetype":"venue"
},
  "geometry": {"coordinates":[-88.32548,40.508106],"type":"Point"}
}