{
  "type": "Feature",
  "properties": {
    "iso:country":"US",
    "sg:address":"314 Lincoln Hwy",
    "sg:city":"Rochelle",
    "sg:classifiers":[
        {
            "category":"Shopping",
            "subcategory":"Pharmacy",
            "type":"Retail Goods"
        }
    ],
    "sg:phone":"+1   ",
    "sg:postcode":"61068",
    "sg:province":"IL",
    "wof:name":"Semar",
    "wof:placetype":"venue"
},
  "geometry": {"coordinates":[-89.066301,41.921645],"type":"Point"}
}