{
  "type": "Feature",
  "properties": {
    "iso:country":"US",
    "sg:address":"900 N. Michigan Avenue",
    "sg:city":"Chicago",
    "sg:classifiers":[
        {
            "category":"Shopping",
            "subcategory":"Clothing, Apparel, & Fashions",
            "type":"Retail Goods"
        }
    ],
    "sg:phone":"+1 312 337 8366",
    "sg:postcode":"60011",
    "sg:province":"IL",
    "sg:tags":[
        "lingerie"
    ],
    "sg:website":"www.myintimacy.com",
    "wof:name":"Intimacy",
    "wof:placetype":"venue"
},
  "geometry": {"coordinates":[-87.624582,41.899591],"type":"Point"}
}