{
  "type": "Feature",
  "properties": {
    "addr:full":"2322 W North Ave Chicago IL 60647",
    "addr:housenumber":"2322",
    "addr:postcode":"60647",
    "addr:street":"W North Ave",
    "iso:country":"US",
    "sg:address":"2322 W North Ave",
    "sg:city":"Chicago",
    "sg:classifiers":[
        {
            "category":"Restaurant",
            "type":"Food & Drink"
        }
    ],
    "sg:phone":"+1 773 489 5747",
    "sg:postcode":"60647",
    "sg:province":"IL",
    "sg:tags":[
        "thai",
        "eating"
    ],
    "sg:website":"thai-lagoon.com/",
    "wof:name":"Thai Lagoon",
    "wof:placetype":"venue"
},
  "geometry": {"coordinates":[-87.685632,41.910337],"type":"Point"}
}