{
  "type": "Feature",
  "properties": {
    "iso:country":"US",
    "sg:address":"311 S Main St",
    "sg:city":"Galena",
    "sg:classifiers":[
        {
            "category":"Shopping",
            "subcategory":"Hobbies, Toys, & Games",
            "type":"Retail Goods"
        }
    ],
    "sg:phone":"+1 815 777 8697",
    "sg:postcode":"61036",
    "sg:province":"IL",
    "wof:name":"Atomic Toy Co",
    "wof:placetype":"venue"
},
  "geometry": {"coordinates":[-90.429941,42.415093],"type":"Point"}
}