{
  "type": "Feature",
  "properties": {
    "iso:country":"US",
    "sg:address":"4738 N Austin Ave",
    "sg:city":"Chicago",
    "sg:classifiers":[
        {
            "category":"Fast Food",
            "type":"Food & Drink"
        },
        {
            "category":"Restaurant",
            "type":"Food & Drink"
        }
    ],
    "sg:phone":"+1 773 282 5595",
    "sg:postcode":"60630",
    "sg:province":"IL",
    "sg:tags":[
        "chicken",
        "take"
    ],
    "wof:name":"Broasted Chicken Royal",
    "wof:placetype":"venue"
},
  "geometry": {"coordinates":[-87.777,41.9674],"type":"Point"}
}