{
  "type": "Feature",
  "properties": {
    "addr:full":"5525 S Oakley Ave Chicago IL 60636",
    "addr:housenumber":"5525",
    "addr:postcode":"60636",
    "addr:street":"S Oakley Ave",
    "iso:country":"US",
    "sg:address":"5525 S Oakley Ave",
    "sg:city":"Chicago",
    "sg:classifiers":[
        {
            "category":"Social Services",
            "type":"Services"
        },
        {
            "category":"Community Center",
            "subcategory":"Senior",
            "type":"Public Place"
        }
    ],
    "sg:phone":"+1 773 808 3389",
    "sg:postcode":"60636",
    "sg:province":"IL",
    "sg:tags":[
        "citizen"
    ],
    "wof:name":"The Blessed Child",
    "wof:placetype":"venue"
},
  "geometry": {"coordinates":[-87.681259,41.793193],"type":"Point"}
}