{
  "type": "Feature",
  "properties": {
    "iso:country":"US",
    "sg:address":"205 N Center St",
    "sg:city":"Lexington",
    "sg:classifiers":[
        {
            "category":"Professional",
            "subcategory":"Lawyer & Legal Services",
            "type":"Services"
        }
    ],
    "sg:phone":"+1 309 365 8926",
    "sg:postcode":"61753",
    "sg:province":"IL",
    "wof:name":"Anne W Fiero Atty",
    "wof:placetype":"venue"
},
  "geometry": {"coordinates":[-88.780877,40.643426],"type":"Point"}
}