{
  "type": "Feature",
  "properties": {
    "addr:full":"12 E Wilson St Batavia IL 60510",
    "addr:housenumber":"12",
    "addr:postcode":"60510",
    "addr:street":"E Wilson St",
    "iso:country":"US",
    "sg:address":"12 E Wilson St",
    "sg:city":"Batavia",
    "sg:classifiers":[
        {
            "category":"Social Services",
            "type":"Services"
        }
    ],
    "sg:phone":"+1 630 406 1343",
    "sg:postcode":"60510",
    "sg:province":"IL",
    "sg:tags":[
        "counselor",
        "marriage",
        "family"
    ],
    "wof:name":"Counseling On The Fox",
    "wof:placetype":"venue"
},
  "geometry": {"coordinates":[-88.30601,41.849937],"type":"Point"}
}