{
  "type": "Feature",
  "properties": {
    "addr:full":"17932 Halsted St Homewood IL 60430",
    "addr:housenumber":"17932",
    "addr:postcode":"60430",
    "addr:street":"Halsted St",
    "iso:country":"US",
    "sg:address":"17932 Halsted St",
    "sg:city":"Homewood",
    "sg:classifiers":[
        {
            "category":"Fast Food",
            "type":"Food & Drink"
        },
        {
            "category":"Restaurant",
            "type":"Food & Drink"
        }
    ],
    "sg:phone":"+1 708 206 9926",
    "sg:postcode":"60430",
    "sg:province":"IL",
    "sg:tags":[
        "take",
        "chinese"
    ],
    "sg:website":"http://www.pandaexpress.com",
    "wof:name":"Panda Express",
    "wof:placetype":"venue"
},
  "geometry": {"coordinates":[-87.636261,41.564045],"type":"Point"}
}