{
  "type": "Feature",
  "properties": {
    "addr:full":"342 N Michigan Ave Chicago IL 60601",
    "addr:housenumber":"342",
    "addr:postcode":"60601",
    "addr:street":"N Michigan Ave",
    "iso:country":"US",
    "sg:address":"342 N Michigan Ave",
    "sg:city":"Chicago",
    "sg:classifiers":[
        {
            "category":"Shopping",
            "subcategory":"Jewelry",
            "type":"Retail Goods"
        }
    ],
    "sg:phone":"+1 312 870 0230",
    "sg:postcode":"60601",
    "sg:province":"IL",
    "sg:website":"www.nakamolchicago.com",
    "wof:name":"Nakamol",
    "wof:placetype":"venue"
},
  "geometry": {"coordinates":[-87.62460299999999,41.887988],"type":"Point"}
}