{
  "type": "Feature",
  "properties": {
    "iso:country":"US",
    "sg:address":"2000 W 59th St",
    "sg:city":"Chicago",
    "sg:classifiers":[
        {
            "category":"Sports & Exercise",
            "subcategory":"Sports Center",
            "type":"Entertainment"
        }
    ],
    "sg:phone":"+1 773 471 5280",
    "sg:postcode":"60636",
    "sg:province":"IL",
    "wof:name":"Natural Rhythm 40 & Over Club",
    "wof:placetype":"venue"
},
  "geometry": {"coordinates":[-87.67411,41.786629],"type":"Point"}
}