{
  "type": "Feature",
  "properties": {
    "iso:country":"US",
    "sg:address":"1528 Windsor Rd",
    "sg:city":"Champaign",
    "sg:classifiers":[
        {
            "category":"Building & Trades",
            "subcategory":"Plumbing",
            "type":"Services"
        }
    ],
    "sg:phone":"+1 217 352 5400",
    "sg:postcode":"61821",
    "sg:province":"IL",
    "sg:tags":[
        "conditioning",
        "air",
        "system",
        "contractor"
    ],
    "wof:name":"ABC Heating & Air Cond",
    "wof:placetype":"venue"
},
  "geometry": {"coordinates":[-88.27264599999999,40.08369],"type":"Point"}
}