{
  "type": "Feature",
  "properties": {
    "addr:full":"33 W Jackson Boulevard Chicago IL 60604",
    "addr:housenumber":"33",
    "addr:postcode":"60604",
    "addr:street":"W Jackson Boulevard",
    "iso:country":"US",
    "sg:address":"33 W Jackson Boulevard",
    "sg:city":"Chicago",
    "sg:classifiers":[
        {
            "category":"Professional",
            "subcategory":"Lawyer & Legal Services",
            "type":"Services"
        }
    ],
    "sg:phone":"+1 312 341 0900",
    "sg:postcode":"60604",
    "sg:province":"IL",
    "sg:tags":[
        "divorce",
        "law",
        "family"
    ],
    "wof:name":"Chicago Women At Law Ltd",
    "wof:placetype":"venue"
},
  "geometry": {"coordinates":[-87.628822,41.87817],"type":"Point"}
}