{
  "type": "Feature",
  "properties": {
    "iso:country":"US",
    "sg:address":"2017 W 75th St",
    "sg:city":"Woodridge",
    "sg:classifiers":[
        {
            "category":"Health Services",
            "subcategory":"Optometrist",
            "type":"Services"
        }
    ],
    "sg:phone":"+1 630 427 1000",
    "sg:postcode":"60517",
    "sg:province":"IL",
    "wof:name":"Professional Eye Care",
    "wof:placetype":"venue"
},
  "geometry": {"coordinates":[-88.031426,41.750655],"type":"Point"}
}