{
  "type": "Feature",
  "properties": {
    "addr:full":"3312 N 36th St Quincy IL 62305",
    "addr:housenumber":"3312",
    "addr:postcode":"62305",
    "addr:street":"N 36Th St",
    "iso:country":"US",
    "sg:address":"3312 N 36th St",
    "sg:city":"Quincy",
    "sg:classifiers":[
        {
            "category":"Sports & Exercise",
            "subcategory":"Golf",
            "type":"Entertainment"
        }
    ],
    "sg:phone":"+1 217 223 1210",
    "sg:postcode":"62305",
    "sg:province":"IL",
    "sg:tags":[
        "course"
    ],
    "wof:name":"Cedar Crest Country Club",
    "wof:placetype":"venue"
},
  "geometry": {"coordinates":[-91.35778999999999,39.97385],"type":"Point"}
}