{
  "type": "Feature",
  "properties": {
    "iso:country":"US",
    "sg:address":"390 N Clay Ave",
    "sg:city":"Jacksonville",
    "sg:classifiers":[
        {
            "category":"Retail",
            "subcategory":"Auto Repair",
            "type":"Services"
        }
    ],
    "sg:phone":"+1 217 243 9402",
    "sg:postcode":"62650",
    "sg:province":"IL",
    "sg:tags":[
        "general"
    ],
    "wof:name":"Stewart Brothers",
    "wof:placetype":"venue"
},
  "geometry": {"coordinates":[-90.224307,39.737124],"type":"Point"}
}