{
  "type": "Feature",
  "properties": {
    "addr:full":"509 W Briar Pl Chicago IL 60657",
    "addr:housenumber":"509",
    "addr:postcode":"60657",
    "addr:street":"W Briar Pl",
    "iso:country":"US",
    "sg:address":"509 W Briar Pl",
    "sg:city":"Chicago",
    "sg:classifiers":[
        {
            "category":"Wholesale",
            "subcategory":"Home Furnishings",
            "type":"Manufacturing & Wholesale Goods"
        }
    ],
    "sg:phone":"+1 773 327 0313",
    "sg:postcode":"60657",
    "sg:province":"IL",
    "wof:name":"Houseworks Sales & Market",
    "wof:placetype":"venue"
},
  "geometry": {"coordinates":[-87.644278,41.938616],"type":"Point"}
}