{
  "type": "Feature",
  "properties": {
    "iso:country":"US",
    "sg:address":"808 Barber Ln",
    "sg:city":"Joliet",
    "sg:classifiers":[
        {
            "category":"Professional",
            "subcategory":"Accounting & Tax Preparation",
            "type":"Services"
        }
    ],
    "sg:phone":"+1 815 725 5653",
    "sg:postcode":"60435",
    "sg:province":"IL",
    "sg:tags":[
        "accountant"
    ],
    "wof:name":"Lane & Lane Cpa's",
    "wof:placetype":"venue"
},
  "geometry": {"coordinates":[-88.153421,41.538935],"type":"Point"}
}