{
  "type": "Feature",
  "properties": {
    "iso:country":"US",
    "sg:address":"1003 N Springfield St",
    "sg:city":"Virden",
    "sg:classifiers":[
        {
            "category":"Ice Cream",
            "type":"Food & Drink"
        }
    ],
    "sg:menulink":"http://www.allmenus.com/il/virden/161773-dairy-queen/menu/",
    "sg:phone":"+1 217 965 4287",
    "sg:postcode":"62690",
    "sg:province":"IL",
    "sg:tags":[
        "burger",
        "american"
    ],
    "wof:name":"Dairy Queen",
    "wof:placetype":"venue"
},
  "geometry": {"coordinates":[-89.767332,39.510969],"type":"Point"}
}