{
  "type": "Feature",
  "properties": {
    "iso:country":"US",
    "sg:address":"960 S Oak Park Ave",
    "sg:city":"Oak Park",
    "sg:classifiers":[
        {
            "category":"Health Services",
            "subcategory":"Optometrist",
            "type":"Services"
        }
    ],
    "sg:phone":"+1 708 383 3150",
    "sg:postcode":"60304",
    "sg:province":"IL",
    "wof:name":"Bowker Michael J OD",
    "wof:placetype":"venue"
},
  "geometry": {"coordinates":[-87.79389999999999,41.870701],"type":"Point"}
}