{
  "type": "Feature",
  "properties": {
    "iso:country":"US",
    "sg:address":"10206 S Vincennes Ave",
    "sg:city":"Chicago",
    "sg:classifiers":[
        {
            "category":"Shopping",
            "type":"Retail Goods"
        }
    ],
    "sg:phone":"+1 773 941 5035",
    "sg:postcode":"60643",
    "sg:province":"IL",
    "sg:tags":[
        "item",
        "boutique"
    ],
    "wof:name":"Boutique Store",
    "wof:placetype":"venue"
},
  "geometry": {"coordinates":[-87.655348,41.708615],"type":"Point"}
}