{
  "type": "Feature",
  "properties": {
    "addr:full":"5612 State Rte 31 Crystal Lake IL 60014",
    "addr:housenumber":"5612",
    "addr:postcode":"60014",
    "addr:street":"State Rte 31",
    "iso:country":"US",
    "sg:address":"5612 State Rte 31",
    "sg:city":"Crystal Lake",
    "sg:classifiers":[
        {
            "category":"Banks & Credit Unions",
            "subcategory":"Bank",
            "type":"Services"
        }
    ],
    "sg:phone":"+1 815 356 9950",
    "sg:postcode":"60014",
    "sg:province":"IL",
    "sg:tags":[
        "currency",
        "exchange"
    ],
    "wof:name":"Currency Exchange",
    "wof:placetype":"venue"
},
  "geometry": {"coordinates":[-88.286743,42.247327],"type":"Point"}
}