{
  "type": "Feature",
  "properties": {
    "iso:country":"US",
    "sg:address":"517 Morse Ave",
    "sg:city":"Schaumburg",
    "sg:classifiers":[
        {
            "category":"Wholesale",
            "subcategory":"Auto Parts",
            "type":"Manufacturing & Wholesale Goods"
        }
    ],
    "sg:phone":"+1 847 895 1380",
    "sg:postcode":"60193",
    "sg:province":"IL",
    "sg:tags":[
        "beverage",
        "truck"
    ],
    "wof:name":"Fleet Parts Corp",
    "wof:placetype":"venue"
},
  "geometry": {"coordinates":[-88.099453,42.000139],"type":"Point"}
}