{
  "type": "Feature",
  "properties": {
    "iso:country":"US",
    "sg:address":"18W455 Roosevelt Rd",
    "sg:city":"Lombard",
    "sg:classifiers":[
        {
            "category":"Professional",
            "subcategory":"Advertising",
            "type":"Services"
        },
        {
            "category":"Retail",
            "subcategory":"Auto Repair",
            "type":"Services"
        }
    ],
    "sg:phone":"+1 630 629 6244",
    "sg:postcode":"60148",
    "sg:province":"IL",
    "sg:tags":[
        "coupon"
    ],
    "sg:website":"http://www.ajsautorepair1.com",
    "wof:name":"A J's Auto Repair",
    "wof:placetype":"venue"
},
  "geometry": {"coordinates":[-87.99346199999999,41.8606],"type":"Point"}
}