{
  "type": "Feature",
  "properties": {
    "addr:full":"1901 S Laramie Ave Cicero IL 60804",
    "addr:housenumber":"1901",
    "addr:postcode":"60804",
    "addr:street":"S Laramie Ave",
    "iso:country":"US",
    "sg:address":"1901 S Laramie Ave",
    "sg:city":"Cicero",
    "sg:classifiers":[
        {
            "category":"Building & Trades",
            "subcategory":"Plumbing",
            "type":"Services"
        }
    ],
    "sg:phone":"+1 773 843 7867",
    "sg:postcode":"60804",
    "sg:province":"IL",
    "sg:tags":[
        "plumber",
        "industrial",
        "contractors-commercial"
    ],
    "wof:name":"Pumping Jetting & Rodding Co",
    "wof:placetype":"venue"
},
  "geometry": {"coordinates":[-87.753799,41.854301],"type":"Point"}
}