{
  "type": "Feature",
  "properties": {
    "iso:country":"US",
    "sg:address":"235 E Council Trl",
    "sg:city":"Arlington Heights",
    "sg:classifiers":[
        {
            "category":"Building & Trades",
            "subcategory":"Construction",
            "type":"Services"
        }
    ],
    "sg:phone":"+1 847 439 4679",
    "sg:postcode":"60005",
    "sg:province":"IL",
    "sg:tags":[
        "house"
    ],
    "wof:name":"R Ponterelli",
    "wof:placetype":"venue"
},
  "geometry": {"coordinates":[-87.978118,42.054095],"type":"Point"}
}