{
  "type": "Feature",
  "properties": {
    "iso:country":"US",
    "sg:address":"3340 Dundee Rd",
    "sg:city":"Northbrook",
    "sg:classifiers":[
        {
            "category":"Professional",
            "type":"Services"
        }
    ],
    "sg:phone":"+1 847 656 8733",
    "sg:postcode":"60062",
    "sg:province":"IL",
    "sg:tags":[
        "establishment"
    ],
    "wof:name":"Center For Egg Optionsillinois",
    "wof:placetype":"venue"
},
  "geometry": {"coordinates":[-87.860976,42.138425],"type":"Point"}
}