{
  "type": "Feature",
  "properties": {
    "iso:country":"US",
    "sg:address":"326 Belle St",
    "sg:city":"Alton",
    "sg:classifiers":[
        {
            "category":"Education",
            "subcategory":"Library",
            "type":"Public Place"
        }
    ],
    "sg:phone":"+1 618 462 0651",
    "sg:postcode":"62002",
    "sg:province":"IL",
    "sg:website":"www.haynerlibrary.org",
    "wof:name":"Hayner Public Library",
    "wof:placetype":"venue"
},
  "geometry": {"coordinates":[-90.187583,38.891857],"type":"Point"}
}