{
  "type": "Feature",
  "properties": {
    "iso:country":"US",
    "sg:address":"321 N Clark St Fl 5",
    "sg:city":"Chicago",
    "sg:classifiers":[
        {
            "category":"Banks & Credit Unions",
            "subcategory":"Investment Brokerage",
            "type":"Services"
        },
        {
            "category":"Professional",
            "subcategory":"Business Services",
            "type":"Services"
        }
    ],
    "sg:phone":"+1 773 227 7060",
    "sg:postcode":"60654",
    "sg:province":"IL",
    "sg:tags":[
        "broker",
        "commodity"
    ],
    "wof:name":"Venditio",
    "wof:placetype":"venue"
},
  "geometry": {"coordinates":[-87.631027,41.888119],"type":"Point"}
}