{
  "type": "Feature",
  "properties": {
    "addr:full":"15189 Lead Line Rd Waverly IL 62692",
    "addr:postcode":"15189;62692",
    "addr:street":"Lead Line Rd",
    "iso:country":"US",
    "sg:address":"15189 Lead Line Rd",
    "sg:city":"Waverly",
    "sg:classifiers":[
        {
            "category":"Freight",
            "type":"Transportation"
        }
    ],
    "sg:phone":"+1 217 438 3060",
    "sg:postcode":"62692",
    "sg:province":"IL",
    "sg:tags":[
        "local",
        "trucking"
    ],
    "wof:name":"Beatty Trucking Inc",
    "wof:placetype":"venue"
},
  "geometry": {"coordinates":[-89.813616,39.578258],"type":"Point"}
}