{
  "type": "Feature",
  "properties": {
    "addr:full":"25620 W Long Beach Dr Ingleside IL 60041",
    "addr:housenumber":"25620",
    "addr:postcode":"60041",
    "addr:street":"W Long Beach Dr",
    "iso:country":"US",
    "sg:address":"25620 W Long Beach Dr",
    "sg:city":"Ingleside",
    "sg:classifiers":[
        {
            "category":"Professional",
            "subcategory":"Lawyer & Legal Services",
            "type":"Services"
        }
    ],
    "sg:phone":"+1 847 546 4430",
    "sg:postcode":"60041",
    "sg:province":"IL",
    "wof:name":"Reese Norman Atty At Law",
    "wof:placetype":"venue"
},
  "geometry": {"coordinates":[-88.131238,42.369567],"type":"Point"}
}