{
  "type": "Feature",
  "properties": {
    "iso:country":"US",
    "sg:address":"109 S Main St",
    "sg:city":"Milmine",
    "sg:classifiers":[
        {
            "category":"Personal",
            "subcategory":"Nail Salon",
            "type":"Services"
        }
    ],
    "sg:phone":"+1 217 763 6481",
    "sg:postcode":"61855",
    "sg:province":"IL",
    "wof:name":"Nails By Debbie",
    "wof:placetype":"venue"
},
  "geometry": {"coordinates":[-88.65004,39.907643],"type":"Point"}
}