{
  "type": "Feature",
  "properties": {
    "iso:country":"US",
    "sg:address":"1721 McNeal Rd",
    "sg:city":"Kirkland",
    "sg:classifiers":[
        {
            "category":"Building & Trades",
            "subcategory":"Construction",
            "type":"Services"
        }
    ],
    "sg:phone":"+1 815 522 6643",
    "sg:postcode":"60146",
    "sg:province":"IL",
    "sg:tags":[
        "house"
    ],
    "wof:name":"Brian Stevens Builders",
    "wof:placetype":"venue"
},
  "geometry": {"coordinates":[-88.917412,42.137958],"type":"Point"}
}