{
  "type": "Feature",
  "properties": {
    "addr:full":"1200 E Higgins Rd Elk Grove Vlg IL 60007",
    "addr:housenumber":"1200",
    "addr:postcode":"60007",
    "addr:street":"E Higgins Rd",
    "iso:country":"US",
    "sg:address":"1200 E Higgins Rd",
    "sg:city":"Elk Grove Vlg",
    "sg:classifiers":[
        {
            "category":"Retail",
            "subcategory":"Auto Repair",
            "type":"Services"
        }
    ],
    "sg:phone":"+1 847 427 8730",
    "sg:postcode":"60007",
    "sg:province":"IL",
    "sg:tags":[
        "body",
        "automobile",
        "painting"
    ],
    "wof:name":"Cosmetic Collision Ctr",
    "wof:placetype":"venue"
},
  "geometry": {"coordinates":[-87.968778,42.026303],"type":"Point"}
}