{
  "type": "Feature",
  "properties": {
    "iso:country":"US",
    "sg:address":"956 Hillcrest Rd",
    "sg:city":"Elgin",
    "sg:classifiers":[
        {
            "category":"Building & Trades",
            "subcategory":"Construction",
            "type":"Services"
        }
    ],
    "sg:phone":"+1 847 622 0901",
    "sg:postcode":"60123",
    "sg:province":"IL",
    "sg:tags":[
        "general",
        "contractor"
    ],
    "wof:name":"Mechanical Designs",
    "wof:placetype":"venue"
},
  "geometry": {"coordinates":[-88.3026,42.060455],"type":"Point"}
}