{
  "type": "Feature",
  "properties": {
    "iso:country":"US",
    "sg:address":"1307 Caseyville Ave",
    "sg:city":"Belleville",
    "sg:classifiers":[
        {
            "category":"Shopping",
            "subcategory":"Clothing, Apparel, & Fashions",
            "type":"Retail Goods"
        }
    ],
    "sg:phone":"+1 618 233 3963",
    "sg:postcode":"62226",
    "sg:province":"IL",
    "sg:tags":[
        "repair",
        "tailor"
    ],
    "wof:name":"Millie's Alteraton Shop",
    "wof:placetype":"venue"
},
  "geometry": {"coordinates":[-89.990103,38.526068],"type":"Point"}
}