{
  "type": "Feature",
  "properties": {
    "addr:full":"105 E Galena Blvd Aurora IL 60505",
    "addr:housenumber":"105",
    "addr:postcode":"60505",
    "addr:street":"E Galena Blvd",
    "iso:country":"US",
    "sg:address":"105 E Galena Blvd",
    "sg:city":"Aurora",
    "sg:classifiers":[
        {
            "category":"Insurance",
            "subcategory":"Insurance Agent",
            "type":"Services"
        }
    ],
    "sg:phone":"+1 630 801 0744",
    "sg:postcode":"60505",
    "sg:province":"IL",
    "wof:name":"Lutheran Brotherhood Insurance",
    "wof:placetype":"venue"
},
  "geometry": {"coordinates":[-88.312178,41.75656],"type":"Point"}
}