{
  "type": "Feature",
  "properties": {
    "addr:full":"11 Bellevue Park Plz Belleville IL 62226",
    "addr:housenumber":"11",
    "addr:postcode":"62226",
    "addr:street":"Bellevue Park Plz",
    "iso:country":"US",
    "sg:address":"11 Bellevue Park Plz",
    "sg:city":"Belleville",
    "sg:classifiers":[
        {
            "category":"Banks & Credit Unions",
            "subcategory":"Bank",
            "type":"Services"
        }
    ],
    "sg:phone":"+1 618 233 2100",
    "sg:postcode":"62226",
    "sg:province":"IL",
    "sg:tags":[
        "cashing",
        "check"
    ],
    "wof:name":"First Payday Loans",
    "wof:placetype":"venue"
},
  "geometry": {"coordinates":[-90.02283799999999,38.543282],"type":"Point"}
}