{
  "type": "Feature",
  "properties": {
    "addr:full":"1122 W Newport Ave Chicago IL 60657",
    "addr:housenumber":"1122",
    "addr:postcode":"60657",
    "addr:street":"W Newport Ave",
    "iso:country":"US",
    "sg:address":"1122 W Newport Ave",
    "sg:city":"Chicago",
    "sg:classifiers":[
        {
            "category":"Professional",
            "subcategory":"Lawyer & Legal Services",
            "type":"Services"
        }
    ],
    "sg:phone":"+1 312 269 8497",
    "sg:postcode":"60657",
    "sg:province":"IL",
    "wof:name":"Amy Zdravecky",
    "wof:placetype":"venue"
},
  "geometry": {"coordinates":[-87.657901,41.944498],"type":"Point"}
}