{
  "type": "Feature",
  "properties": {
    "iso:country":"US",
    "sg:address":"337 Evergreen Dr",
    "sg:city":"Bolingbrook",
    "sg:classifiers":[
        {
            "category":"Personal",
            "type":"Services"
        }
    ],
    "sg:phone":"+1 630 739 0907",
    "sg:postcode":"60440",
    "sg:province":"IL",
    "wof:name":"Lytis Sitting Inc",
    "wof:placetype":"venue"
},
  "geometry": {"coordinates":[-88.05482,41.697019],"type":"Point"}
}