{
  "type": "Feature",
  "properties": {
    "iso:country":"US",
    "sg:address":"1999 W Downer Pl",
    "sg:city":"Aurora",
    "sg:classifiers":[
        {
            "category":"Government",
            "subcategory":"Police Station",
            "type":"Public Place"
        },
        {
            "category":"Professional",
            "subcategory":"Lawyer & Legal Services",
            "type":"Services"
        }
    ],
    "sg:phone":"+1 630 897 8764",
    "sg:postcode":"60506",
    "sg:province":"IL",
    "sg:tags":[
        "criminal",
        "attorney",
        "accident",
        "family",
        "duo",
        "corporation",
        "wills",
        "partnership",
        "damage",
        "elder",
        "planning",
        "traffic",
        "real estate",
        "child",
        "trust",
        "property",
        "dwi",
        "custody",
        "law"
    ],
    "sg:website":"http://www.dreyerfoote.com",
    "wof:name":"Dreyer Foote Streit Furgason & Slocum",
    "wof:placetype":"venue"
},
  "geometry": {"coordinates":[-88.36528800000001,41.761532],"type":"Point"}
}