{
  "type": "Feature",
  "properties": {
    "addr:full":"3900 Maple Ave Mc Henry IL 60050",
    "addr:housenumber":"3900",
    "addr:postcode":"60050",
    "addr:street":"Maple Ave Mc Henry",
    "iso:country":"US",
    "sg:address":"3900 Maple Ave",
    "sg:city":"Mc Henry",
    "sg:classifiers":[
        {
            "category":"Shopping",
            "type":"Retail Goods"
        },
        {
            "category":"Shopping",
            "subcategory":"Computers & Home Electronics",
            "type":"Retail Goods"
        }
    ],
    "sg:phone":"+1 815 363 1300",
    "sg:postcode":"60050",
    "sg:province":"IL",
    "sg:tags":[
        "repair",
        "cellular"
    ],
    "wof:name":"Lee Communications",
    "wof:placetype":"venue"
},
  "geometry": {"coordinates":[-88.273223,42.349562],"type":"Point"}
}