{
  "type": "Feature",
  "properties": {
    "iso:country":"US",
    "sg:address":"945 W. Belmont Ave.",
    "sg:city":"Chicago",
    "sg:classifiers":[
        {
            "category":"Local Transit",
            "type":"Transportation"
        }
    ],
    "sg:postcode":"60657",
    "sg:province":"IL",
    "sg:tags":[
        "public"
    ],
    "sg:website":"www.yourcta.com",
    "wof:name":"Belmont Red/Brown/Purple Line CTA",
    "wof:placetype":"venue"
},
  "geometry": {"coordinates":[-87.65329699999999,41.9398],"type":"Point"}
}