{
  "type": "Feature",
  "properties": {
    "iso:country":"US",
    "sg:address":"938 W Perry St",
    "sg:city":"Pittsfield",
    "sg:classifiers":[
        {
            "category":"Real Estate",
            "subcategory":"Real Estate Agent",
            "type":"Services"
        }
    ],
    "sg:phone":"+1 217 285 6000",
    "sg:postcode":"62363",
    "sg:province":"IL",
    "wof:name":"Midwest Land Sales",
    "wof:placetype":"venue"
},
  "geometry": {"coordinates":[-90.820844,39.610168],"type":"Point"}
}