{
  "type": "Feature",
  "properties": {
    "addr:full":"103 N Heaton St Morrison IL 61270",
    "addr:housenumber":"103",
    "addr:postcode":"61270",
    "addr:street":"N Heaton St",
    "iso:country":"US",
    "sg:address":"103 N Heaton St",
    "sg:city":"Morrison",
    "sg:classifiers":[
        {
            "category":"Home & Garden",
            "subcategory":"Garden Supply",
            "type":"Retail Goods"
        },
        {
            "category":"Shopping",
            "subcategory":"Gifts & Souvenirs",
            "type":"Retail Goods"
        },
        {
            "category":"Shopping",
            "subcategory":"Crafts & Fabrics",
            "type":"Retail Goods"
        },
        {
            "category":"Shopping",
            "subcategory":"Florist",
            "type":"Retail Goods"
        }
    ],
    "sg:phone":"+1 815 772 2126",
    "sg:postcode":"61270",
    "sg:province":"IL",
    "sg:tags":[
        "plant",
        "etc-retail",
        "dried",
        "basket",
        "trees-silk",
        "flowers"
    ],
    "sg:website":"http://www.wilsonghseandflorists.com",
    "wof:name":"Wilson Greenhouses & Florist",
    "wof:placetype":"venue"
},
  "geometry": {"coordinates":[-89.974535,41.811269],"type":"Point"}
}