{
  "type": "Feature",
  "properties": {
    "addr:full":"1816 N Clark St Chicago IL 60614",
    "addr:housenumber":"1816",
    "addr:postcode":"60614",
    "addr:street":"N Clark St",
    "iso:country":"US",
    "sg:address":"1816 N Clark St",
    "sg:city":"Chicago",
    "sg:classifiers":[
        {
            "category":"Travel",
            "subcategory":"Hotels & Motels",
            "type":"Entertainment"
        }
    ],
    "sg:phone":"+1 312 664 3040",
    "sg:postcode":"60614",
    "sg:province":"IL",
    "sg:website":"www.parkviewhotelchicago.com",
    "wof:name":"The Park View Hotel",
    "wof:placetype":"venue"
},
  "geometry": {"coordinates":[-87.634124,41.915269],"type":"Point"}
}