{
  "type": "Feature",
  "properties": {
    "iso:country":"US",
    "sg:address":"2302 Barberry Dr",
    "sg:city":"Champaign",
    "sg:classifiers":[
        {
            "category":"Shopping",
            "subcategory":"Computers & Home Electronics",
            "type":"Retail Goods"
        }
    ],
    "sg:phone":"+1   ",
    "sg:postcode":"61821",
    "sg:province":"IL",
    "sg:tags":[
        "motion"
    ],
    "wof:name":"Video Store",
    "wof:placetype":"venue"
},
  "geometry": {"coordinates":[-88.283842,40.089949],"type":"Point"}
}