{
  "type": "Feature",
  "properties": {
    "addr:full":"555 W Bluff St Marseilles IL 61341",
    "addr:housenumber":"555",
    "addr:postcode":"61341",
    "addr:street":"W Bluff St",
    "iso:country":"US",
    "sg:address":"555 W Bluff St",
    "sg:city":"Marseilles",
    "sg:classifiers":[
        {
            "category":"Organizations",
            "subcategory":"Religious Organization",
            "type":"Services"
        }
    ],
    "sg:phone":"+1 815 795 5235",
    "sg:postcode":"61341",
    "sg:province":"IL",
    "wof:name":"First Baptist Church",
    "wof:placetype":"venue"
},
  "geometry": {"coordinates":[-88.72017700000001,41.334807],"type":"Point"}
}