{
  "type": "Feature",
  "properties": {
    "iso:country":"US",
    "sg:address":"2149 S Clark Street",
    "sg:city":"Chicago",
    "sg:classifiers":[
        {
            "category":"Education",
            "subcategory":"School",
            "type":"Public Place"
        }
    ],
    "sg:phone":"+1 773 534 9065",
    "sg:postcode":"60616",
    "sg:province":"IL",
    "sg:tags":[
        "high",
        "middle",
        "elementary"
    ],
    "wof:name":"Schools Public",
    "wof:placetype":"venue"
},
  "geometry": {"coordinates":[-87.63026000000001,41.85365],"type":"Point"}
}