{
  "type": "Feature",
  "properties": {
    "iso:country":"US",
    "sg:address":"2950 N Main St",
    "sg:city":"Princeton",
    "sg:classifiers":[
        {
            "category":"Banks & Credit Unions",
            "subcategory":"Bank",
            "type":"Services"
        }
    ],
    "sg:phone":"+1 815 872 3607",
    "sg:postcode":"61356",
    "sg:province":"IL",
    "wof:name":"Agri Bank Fcb",
    "wof:placetype":"venue"
},
  "geometry": {"coordinates":[-89.469332,41.399462],"type":"Point"}
}