{
  "type": "Feature",
  "properties": {
    "addr:full":"4732 N 2nd St Loves Park IL 61111",
    "addr:housenumber":"4732",
    "addr:postcode":"61111",
    "addr:street":"N 2Nd St",
    "iso:country":"US",
    "sg:address":"4732 N 2nd St",
    "sg:city":"Loves Park",
    "sg:classifiers":[
        {
            "category":"Autos & Motor Vehicles",
            "subcategory":"Automobile Sales",
            "type":"Retail Goods"
        }
    ],
    "sg:phone":"+1 815 637 1000",
    "sg:postcode":"61111",
    "sg:province":"IL",
    "sg:tags":[
        "van",
        "used",
        "truck"
    ],
    "wof:name":"Jim Orsinger Inc",
    "wof:placetype":"venue"
},
  "geometry": {"coordinates":[-89.057778,42.298707],"type":"Point"}
}