{
  "type": "Feature",
  "properties": {
    "addr:full":"209 Lincoln St Marseilles IL 61341",
    "addr:housenumber":"209",
    "addr:postcode":"61341",
    "addr:street":"Lincoln St",
    "iso:country":"US",
    "sg:address":"209 Lincoln St",
    "sg:city":"Marseilles",
    "sg:classifiers":[
        {
            "category":"Professional",
            "subcategory":"Management & Consulting",
            "type":"Services"
        }
    ],
    "sg:phone":"+1 815 795 4000",
    "sg:postcode":"61341",
    "sg:province":"IL",
    "sg:tags":[
        "public",
        "relations"
    ],
    "wof:name":"Marseille Supt-Streets",
    "wof:placetype":"venue"
},
  "geometry": {"coordinates":[-88.70860399999999,41.328249],"type":"Point"}
}