{
  "type": "Feature",
  "properties": {
    "iso:country":"US",
    "sg:address":"2520 W Armitage Ave",
    "sg:city":"Chicago",
    "sg:classifiers":[
        {
            "category":"Shopping",
            "subcategory":"Pets & Pet Supplies",
            "type":"Retail Goods"
        },
        {
            "category":"Retail",
            "subcategory":"Veterinary Services",
            "type":"Services"
        }
    ],
    "sg:phone":"+1 773 269 2964",
    "sg:postcode":"60647",
    "sg:province":"IL",
    "sg:tags":[
        "veterinarian",
        "store"
    ],
    "sg:website":"www.integrativepetcare.com",
    "wof:name":"Integrative Pet Care",
    "wof:placetype":"venue"
},
  "geometry": {"coordinates":[-87.690972,41.917629],"type":"Point"}
}