{
  "type": "Feature",
  "properties": {
    "iso:country":"US",
    "sg:address":"529 W Orchard St",
    "sg:city":"Vandalia",
    "sg:classifiers":[
        {
            "category":"Home & Garden",
            "subcategory":"Building Materials",
            "type":"Retail Goods"
        }
    ],
    "sg:phone":"+1 618 283 1837",
    "sg:postcode":"62471",
    "sg:province":"IL",
    "sg:tags":[
        "glass",
        "window",
        "plate"
    ],
    "wof:name":"Farmland Auto Glass",
    "wof:placetype":"venue"
},
  "geometry": {"coordinates":[-89.096373,38.972811],"type":"Point"}
}