{
  "type": "Feature",
  "properties": {
    "iso:country":"US",
    "sg:address":"911 S Main St",
    "sg:city":"Columbia",
    "sg:classifiers":[
        {
            "category":"Personal",
            "subcategory":"Beauty Salon",
            "type":"Services"
        }
    ],
    "sg:phone":"+1 618 281 4343",
    "sg:postcode":"62236",
    "sg:province":"IL",
    "wof:name":"Ultimate Dimensions Hair Salon",
    "wof:placetype":"venue"
},
  "geometry": {"coordinates":[-90.192546,38.439622],"type":"Point"}
}