{
  "type": "Feature",
  "properties": {
    "iso:country":"US",
    "sg:address":"611 N Milwaukee Ave",
    "sg:city":"Libertyville",
    "sg:classifiers":[
        {
            "category":"Autos & Motor Vehicles",
            "subcategory":"Motorcycle Sales",
            "type":"Retail Goods"
        }
    ],
    "sg:phone":"+1 847 362 7110",
    "sg:postcode":"60048",
    "sg:province":"IL",
    "sg:tags":[
        "scooter"
    ],
    "wof:name":"Banzai Motorsports Inc",
    "wof:placetype":"venue"
},
  "geometry": {"coordinates":[-87.954654,42.289068],"type":"Point"}
}