{
  "type": "Feature",
  "properties": {
    "iso:country":"US",
    "sg:address":"1262 Adirondack Dr",
    "sg:city":"Northbrook",
    "sg:classifiers":[
        {
            "category":"Professional",
            "subcategory":"Management & Consulting",
            "type":"Services"
        }
    ],
    "sg:phone":"+1 847 418 3240",
    "sg:postcode":"60062",
    "sg:province":"IL",
    "sg:tags":[
        "marketing",
        "consultant"
    ],
    "wof:name":"Deko Group",
    "wof:placetype":"venue"
},
  "geometry": {"coordinates":[-87.857302,42.130782],"type":"Point"}
}