{
  "type": "Feature",
  "properties": {
    "addr:full":"519 N Cedar Lake Rd Round Lake IL 60073",
    "addr:housenumber":"519",
    "addr:postcode":"60073",
    "addr:street":"N Cedar Lake Rd",
    "iso:country":"US",
    "sg:address":"519 N Cedar Lake Rd",
    "sg:city":"Round Lake",
    "sg:classifiers":[
        {
            "category":"Real Estate",
            "subcategory":"Surveying",
            "type":"Services"
        }
    ],
    "sg:phone":"+1 847 546 9411",
    "sg:postcode":"60073",
    "sg:province":"IL",
    "sg:tags":[
        "surveyor"
    ],
    "wof:name":"James R Dietz",
    "wof:placetype":"venue"
},
  "geometry": {"coordinates":[-88.093458,42.355722],"type":"Point"}
}