{
  "type": "Feature",
  "properties": {
    "addr:full":"350 S Greenleaf St Ste 403 Gurnee IL 60031",
    "addr:housenumber":"350",
    "addr:postcode":"60031",
    "addr:street":"S Greenleaf St Ste 403",
    "iso:country":"US",
    "sg:address":"350 S Greenleaf St Ste 403",
    "sg:city":"Gurnee",
    "sg:classifiers":[
        {
            "category":"Health Services",
            "subcategory":"Doctor",
            "type":"Services"
        }
    ],
    "sg:phone":"+1 847 855 8383",
    "sg:postcode":"60031",
    "sg:province":"IL",
    "sg:tags":[
        "physician",
        "surgeons",
        "neurology",
        "medicine",
        "surgeon",
        "internal"
    ],
    "wof:name":"Piergies, Antoni A, Md - Deerpath Physician Group Ltd",
    "wof:placetype":"venue"
},
  "geometry": {"coordinates":[-87.90216599999999,42.366905],"type":"Point"}
}