{
  "type": "Feature",
  "properties": {
    "iso:country":"US",
    "sg:address":"700 N 12th St",
    "sg:city":"Herrin",
    "sg:classifiers":[
        {
            "category":"Building & Trades",
            "subcategory":"Locksmith",
            "type":"Services"
        }
    ],
    "sg:phone":"+1 618 942 5576",
    "sg:postcode":"62948",
    "sg:province":"IL",
    "sg:tags":[
        "key"
    ],
    "sg:website":"parkavenueplayers.itgo.com",
    "wof:name":"Brooks Locksmith Shop",
    "wof:placetype":"venue"
},
  "geometry": {"coordinates":[-89.023804,37.8092],"type":"Point"}
}