{
  "type": "Feature",
  "properties": {
    "addr:full":"76 S La Grange Rd La Grange IL 60525",
    "addr:housenumber":"76",
    "addr:postcode":"60525",
    "addr:street":"S La Grange Rd",
    "iso:country":"US",
    "sg:address":"76 S La Grange Rd",
    "sg:city":"La Grange",
    "sg:classifiers":[
        {
            "category":"Ice Cream",
            "type":"Food & Drink"
        }
    ],
    "sg:menulink":"http://www.allmenus.com/il/lyons/184762-cold-stone-creamery/menu/",
    "sg:phone":"+1 708 354 2600",
    "sg:postcode":"60525",
    "sg:province":"IL",
    "sg:tags":[
        "smoothy",
        "juice",
        "american"
    ],
    "wof:name":"Cold Stone Creamery",
    "wof:placetype":"venue"
},
  "geometry": {"coordinates":[-87.869562,41.812984],"type":"Point"}
}