{
  "type": "Feature",
  "properties": {
    "iso:country":"US",
    "sg:address":"1111 Greenfield Cir",
    "sg:city":"Geneva",
    "sg:classifiers":[
        {
            "category":"Professional",
            "type":"Services"
        }
    ],
    "sg:phone":"+1 630 208 7843",
    "sg:postcode":"60134",
    "sg:province":"IL",
    "wof:name":"Documents Plus",
    "wof:placetype":"venue"
},
  "geometry": {"coordinates":[-88.283729,41.888923],"type":"Point"}
}