{
  "type": "Feature",
  "properties": {
    "addr:full":"1111 Greenfield Cir Geneva IL 60134",
    "addr:housenumber":"1111",
    "addr:postcode":"60134",
    "addr:street":"Greenfield Cir",
    "iso:country":"US",
    "sg:address":"1111 Greenfield Cir",
    "sg:city":"Geneva",
    "sg:classifiers":[
        {
            "category":"Professional",
            "type":"Services"
        }
    ],
    "sg:phone":"+1 630 208 7843",
    "sg:postcode":"60134",
    "sg:province":"IL",
    "wof:name":"Documents Plus",
    "wof:placetype":"venue"
},
  "geometry": {"coordinates":[-88.28372899999999,41.888923],"type":"Point"}
}