{
  "type": "Feature",
  "properties": {
    "addr:full":"4626 Court Rd Germantown IL 62245",
    "addr:housenumber":"4626",
    "addr:postcode":"62245",
    "addr:street":"Court Rd",
    "iso:country":"US",
    "sg:address":"4626 Court Rd",
    "sg:city":"Germantown",
    "sg:classifiers":[
        {
            "category":"Farming",
            "subcategory":"Livestock Farm",
            "type":"Manufacturing & Wholesale Goods"
        }
    ],
    "sg:phone":"+1 618 248 5448",
    "sg:postcode":"62245",
    "sg:province":"IL",
    "sg:tags":[
        "hog"
    ],
    "wof:name":"Heartland Pigs Inc",
    "wof:placetype":"venue"
},
  "geometry": {"coordinates":[-89.62114800000001,38.55405],"type":"Point"}
}