{
  "type": "Feature",
  "properties": {
    "iso:country":"US",
    "sg:address":"20 N Cass Ave",
    "sg:city":"Westmont",
    "sg:classifiers":[
        {
            "category":"Professional",
            "type":"Services"
        },
        {
            "category":"Coffee & Tea",
            "type":"Food & Drink"
        },
        {
            "category":"Restaurant",
            "type":"Food & Drink"
        },
        {
            "category":"Bakery",
            "type":"Food & Drink"
        }
    ],
    "sg:phone":"+1 630 971 2233",
    "sg:postcode":"60559",
    "sg:province":"IL",
    "sg:tags":[
        "dessert",
        "espresso",
        "caterer"
    ],
    "sg:website":"http://www.thetravelerscafe.com",
    "wof:name":"Travelers Cafe",
    "wof:placetype":"venue"
},
  "geometry": {"coordinates":[-87.975345,41.795929],"type":"Point"}
}