{
  "type": "Feature",
  "properties": {
    "addr:full":"616 Broadway St Lincoln IL 62656",
    "addr:housenumber":"616",
    "addr:postcode":"62656",
    "addr:street":"Broadway St",
    "iso:country":"US",
    "sg:address":"616 Broadway St",
    "sg:city":"Lincoln",
    "sg:classifiers":[
        {
            "category":"Shopping",
            "subcategory":"Used Merchandise",
            "type":"Retail Goods"
        }
    ],
    "sg:phone":"+1   ",
    "sg:postcode":"62656",
    "sg:province":"IL",
    "wof:name":"Mission Mart Of Lincoln",
    "wof:placetype":"venue"
},
  "geometry": {"coordinates":[-89.362376,40.146713],"type":"Point"}
}