{
  "type": "Feature",
  "properties": {
    "addr:full":"4245 N Elston Avenue Chicago IL 60618",
    "addr:housenumber":"4245",
    "addr:postcode":"60618",
    "addr:street":"N Elston Avenue",
    "iso:country":"US",
    "sg:address":"4245 N Elston Avenue",
    "sg:city":"Chicago",
    "sg:classifiers":[
        {
            "category":"Building & Trades",
            "subcategory":"Construction",
            "type":"Services"
        }
    ],
    "sg:phone":"+1 773 267 6483",
    "sg:postcode":"60618",
    "sg:province":"IL",
    "sg:tags":[
        "contractor"
    ],
    "wof:name":"Renner & Renner Construction Company",
    "wof:placetype":"venue"
},
  "geometry": {"coordinates":[-87.725577,41.957944],"type":"Point"}
}