{
  "type": "Feature",
  "properties": {
    "addr:full":"1702 Berkley St Elgin IL 60123",
    "addr:housenumber":"1702",
    "addr:postcode":"60123",
    "addr:street":"Berkley St",
    "iso:country":"US",
    "sg:address":"1702 Berkley St",
    "sg:city":"Elgin",
    "sg:classifiers":[
        {
            "category":"Wholesale",
            "subcategory":"Machinery & Supplies",
            "type":"Manufacturing & Wholesale Goods"
        }
    ],
    "sg:phone":"+1 847 697 5705",
    "sg:postcode":"60123",
    "sg:province":"IL",
    "sg:tags":[
        "screw",
        "assembly",
        "drilling",
        "automatic"
    ],
    "sg:website":"www.kinetictools.com",
    "wof:name":"Kinetic Tools Inc",
    "wof:placetype":"venue"
},
  "geometry": {"coordinates":[-88.320866,42.022715],"type":"Point"}
}