{
  "type": "Feature",
  "properties": {
    "iso:country":"US",
    "sg:address":"1307 N Court St",
    "sg:city":"Mc Henry",
    "sg:classifiers":[
        {
            "category":"Health Services",
            "subcategory":"Doctor",
            "type":"Services"
        }
    ],
    "sg:phone":"+1 815 385 0911",
    "sg:postcode":"60050",
    "sg:province":"IL",
    "wof:name":"Thomas S Kukla DDS",
    "wof:placetype":"venue"
},
  "geometry": {"coordinates":[-88.264403,42.346509],"type":"Point"}
}