{
  "type": "Feature",
  "properties": {
    "addr:full":"2538 W Devon Avenue Chicago IL 60659",
    "addr:housenumber":"2538",
    "addr:postcode":"60659",
    "addr:street":"W Devon Avenue",
    "iso:country":"US",
    "sg:address":"2538 W Devon Avenue",
    "sg:city":"Chicago",
    "sg:classifiers":[
        {
            "category":"Cinema",
            "subcategory":"Movie Rental",
            "type":"Entertainment"
        }
    ],
    "sg:phone":"+1 773 973 1223",
    "sg:postcode":"60659",
    "sg:province":"IL",
    "sg:tags":[
        "game",
        "video"
    ],
    "wof:name":"Star Video",
    "wof:placetype":"venue"
},
  "geometry": {"coordinates":[-87.69385,41.997651],"type":"Point"}
}