{
  "type": "Feature",
  "properties": {
    "addr:full":"1307 N Convent St Bourbonnais IL 60914",
    "addr:housenumber":"1307",
    "addr:postcode":"60914",
    "addr:street":"N Convent St",
    "iso:country":"US",
    "sg:address":"1307 N Convent St",
    "sg:city":"Bourbonnais",
    "sg:classifiers":[
        {
            "category":"Home & Garden",
            "subcategory":"Garden Supply",
            "type":"Retail Goods"
        }
    ],
    "sg:phone":"+1 815 935 9999",
    "sg:postcode":"60914",
    "sg:province":"IL",
    "sg:tags":[
        "sprinkler"
    ],
    "wof:name":"Blake's Irrigation Station",
    "wof:placetype":"venue"
},
  "geometry": {"coordinates":[-87.87559899999999,41.177154],"type":"Point"}
}