{
  "type": "Feature",
  "properties": {
    "iso:country":"US",
    "sg:address":"71 E 152nd St",
    "sg:city":"Harvey",
    "sg:classifiers":[
        {
            "category":"Education",
            "subcategory":"School",
            "type":"Public Place"
        }
    ],
    "sg:phone":"+1 708 331 1130",
    "sg:postcode":"60426",
    "sg:province":"IL",
    "sg:tags":[
        "high",
        "middle",
        "elementary"
    ],
    "wof:name":"Whittier School",
    "wof:placetype":"venue"
},
  "geometry": {"coordinates":[-87.651398,41.613602],"type":"Point"}
}