{
  "type": "Feature",
  "properties": {
    "iso:country":"US",
    "sg:address":"1525 E 168th St",
    "sg:city":"South Holland",
    "sg:classifiers":[
        {
            "category":"Building & Trades",
            "subcategory":"Construction",
            "type":"Services"
        }
    ],
    "sg:phone":"+1 708 225 5108",
    "sg:postcode":"60473",
    "sg:province":"IL",
    "sg:tags":[
        "contractor"
    ],
    "wof:name":"Top Notch Building & Maintenance",
    "wof:placetype":"venue"
},
  "geometry": {"coordinates":[-87.579926,41.589969],"type":"Point"}
}