{
  "type": "Feature",
  "properties": {
    "iso:country":"US",
    "sg:address":"4527 S Saint Lawrence Ave",
    "sg:city":"Chicago",
    "sg:classifiers":[
        {
            "category":"Building & Trades",
            "subcategory":"Construction",
            "type":"Services"
        }
    ],
    "sg:phone":"+1 773 268 3411",
    "sg:postcode":"60653",
    "sg:province":"IL",
    "sg:tags":[
        "work",
        "metal"
    ],
    "wof:name":"Infra Metals Inc",
    "wof:placetype":"venue"
},
  "geometry": {"coordinates":[-87.611435,41.811769],"type":"Point"}
}