{
  "type": "Feature",
  "properties": {
    "addr:full":"188 S Bolingbrook Dr Bolingbrook IL 60440",
    "addr:housenumber":"188",
    "addr:postcode":"60440",
    "addr:street":"S Bolingbrook Dr",
    "iso:country":"US",
    "sg:address":"188 S Bolingbrook Dr",
    "sg:city":"Bolingbrook",
    "sg:classifiers":[
        {
            "category":"Restaurant",
            "type":"Food & Drink"
        }
    ],
    "sg:phone":"+1   ",
    "sg:postcode":"60440",
    "sg:province":"IL",
    "sg:tags":[
        "eating"
    ],
    "wof:name":"Arbys",
    "wof:placetype":"venue"
},
  "geometry": {"coordinates":[-88.068151,41.696745],"type":"Point"}
}