{
  "type": "Feature",
  "properties": {
    "iso:country":"US",
    "sg:address":"1650 Waukegan Rd",
    "sg:city":"Glenview",
    "sg:classifiers":[
        {
            "category":"Restaurant",
            "type":"Food & Drink"
        }
    ],
    "sg:menulink":"http://www.allmenus.com/il/northfield/224218-dragon-inn-north/menu/",
    "sg:phone":"+1 847 729 8383",
    "sg:postcode":"60025",
    "sg:province":"IL",
    "sg:tags":[
        "asian",
        "chinese"
    ],
    "wof:name":"Dragon Inn North",
    "wof:placetype":"venue"
},
  "geometry": {"coordinates":[-87.79822900000001,42.085],"type":"Point"}
}