{
  "type": "Feature",
  "properties": {
    "addr:full":"1014 Cypress Dr Aurora IL 60506",
    "addr:housenumber":"1014",
    "addr:postcode":"60506",
    "addr:street":"Cypress Dr",
    "iso:country":"US",
    "sg:address":"1014 Cypress Dr",
    "sg:city":"Aurora",
    "sg:classifiers":[
        {
            "category":"Professional",
            "subcategory":"Accounting & Tax Preparation",
            "type":"Services"
        }
    ],
    "sg:phone":"+1 630 264 6086",
    "sg:postcode":"60506",
    "sg:province":"IL",
    "sg:tags":[
        "accountant"
    ],
    "wof:name":"Edwin S Harrison Accounting",
    "wof:placetype":"venue"
},
  "geometry": {"coordinates":[-88.360623,41.780318],"type":"Point"}
}