{
  "type": "Feature",
  "properties": {
    "addr:full":"13236 Shabbona Rd Shabbona IL 60550",
    "addr:housenumber":"13236",
    "addr:postcode":"60550",
    "addr:street":"Shabbona Rd",
    "iso:country":"US",
    "sg:address":"13236 Shabbona Rd",
    "sg:city":"Shabbona",
    "sg:classifiers":[
        {
            "category":"Manufacturing",
            "subcategory":"Food",
            "type":"Manufacturing & Wholesale Goods"
        },
        {
            "category":"Farming",
            "subcategory":"Livestock Farm",
            "type":"Manufacturing & Wholesale Goods"
        },
        {
            "category":"Farming",
            "subcategory":"Farm",
            "type":"Manufacturing & Wholesale Goods"
        }
    ],
    "sg:phone":"+1 815 824 2922",
    "sg:postcode":"60550",
    "sg:province":"IL",
    "sg:tags":[
        "product",
        "ranch",
        "corn"
    ],
    "wof:name":"Boehne Farms",
    "wof:placetype":"venue"
},
  "geometry": {"coordinates":[-88.886403,41.82164],"type":"Point"}
}