{
  "type": "Feature",
  "properties": {
    "addr:full":"6129 E Elbow Ln Calhoun IL 62419",
    "addr:housenumber":"6129",
    "addr:postcode":"62419",
    "addr:street":"E Elbow Ln",
    "iso:country":"US",
    "sg:address":"6129 E Elbow Ln",
    "sg:city":"Calhoun",
    "sg:phone":"+1 618 863 2237",
    "sg:postcode":"62419",
    "sg:province":"IL",
    "sg:tags":[
        "farm",
        "corn",
        "soybean"
    ],
    "wof:name":"Don Dunahee",
    "wof:placetype":"venue"
},
  "geometry": {"coordinates":[-88.01192399999999,38.643949],"type":"Point"}
}