{
  "type": "Feature",
  "properties": {
    "addr:full":"14302 S Burnham Avenue Chicago IL 60633",
    "addr:housenumber":"14302",
    "addr:postcode":"60633",
    "addr:street":"S Burnham Avenue",
    "iso:country":"US",
    "sg:address":"14302 S Burnham Avenue",
    "sg:city":"Chicago",
    "sg:classifiers":[
        {
            "category":"Retail",
            "subcategory":"Auto Repair",
            "type":"Services"
        }
    ],
    "sg:phone":"+1 708 868 6560",
    "sg:postcode":"60633",
    "sg:province":"IL",
    "sg:tags":[
        "body",
        "repairing",
        "painting",
        "automobile"
    ],
    "wof:name":"Cundiff's Body Shop",
    "wof:placetype":"venue"
},
  "geometry": {"coordinates":[-87.539675,41.63519],"type":"Point"}
}