{
  "type": "Feature",
  "properties": {
    "iso:country":"US",
    "sg:address":"339 E Chicago Avenue Rm 717",
    "sg:city":"Chicago",
    "sg:classifiers":[
        {
            "category":"Education",
            "subcategory":"University",
            "type":"Public Place"
        }
    ],
    "sg:phone":"+1 312 503 6950",
    "sg:postcode":"60611",
    "sg:province":"IL",
    "sg:tags":[
        "college"
    ],
    "sg:website":"www.northwestern.edu",
    "wof:name":"Northwestern University",
    "wof:placetype":"venue"
},
  "geometry": {"coordinates":[-87.619242,41.896898],"type":"Point"}
}