{
  "type": "Feature",
  "properties": {
    "addr:full":"424 Riverside Dr East Peoria IL 61611",
    "addr:housenumber":"424",
    "addr:postcode":"61611",
    "addr:street":"Riverside Dr",
    "iso:country":"US",
    "sg:address":"424 Riverside Dr",
    "sg:city":"East Peoria",
    "sg:classifiers":[
        {
            "category":"Restaurant",
            "type":"Food & Drink"
        }
    ],
    "sg:menulink":"http://www.allmenus.com/il/fondulac/136607-smoothie-king/menu/",
    "sg:phone":"+1 309 694 6100",
    "sg:postcode":"61611",
    "sg:province":"IL",
    "sg:tags":[
        "smoothy",
        "juice",
        "american"
    ],
    "wof:name":"Smoothie King",
    "wof:placetype":"venue"
},
  "geometry": {"coordinates":[-89.58398,40.679903],"type":"Point"}
}