{
  "type": "Feature",
  "properties": {
    "iso:country":"US",
    "sg:address":"200 W South St",
    "sg:city":"Durand",
    "sg:classifiers":[
        {
            "category":"Education",
            "subcategory":"School",
            "type":"Public Place"
        }
    ],
    "sg:phone":"+1 815 248 2171",
    "sg:postcode":"61024",
    "sg:province":"IL",
    "wof:name":"Durand JUNIOR High School",
    "wof:placetype":"venue"
},
  "geometry": {"coordinates":[-89.335028,42.433446],"type":"Point"}
}