{
  "type": "Feature",
  "properties": {
    "addr:full":"200 W South St Durand IL 61024",
    "addr:housenumber":"200",
    "addr:postcode":"61024",
    "addr:street":"W South St",
    "iso:country":"US",
    "sg:address":"200 W South St",
    "sg:city":"Durand",
    "sg:classifiers":[
        {
            "category":"Education",
            "subcategory":"School",
            "type":"Public Place"
        }
    ],
    "sg:phone":"+1 815 248 2171",
    "sg:postcode":"61024",
    "sg:province":"IL",
    "wof:name":"Durand JUNIOR High School",
    "wof:placetype":"venue"
},
  "geometry": {"coordinates":[-89.33502799999999,42.433446],"type":"Point"}
}