{
  "type": "Feature",
  "properties": {
    "addr:full":"15175 State St South Holland IL 60473",
    "addr:housenumber":"15175",
    "addr:postcode":"60473",
    "addr:street":"State St",
    "iso:country":"US",
    "sg:address":"15175 State St",
    "sg:city":"South Holland",
    "sg:classifiers":[
        {
            "category":"Health Services",
            "subcategory":"Nursing And Care Facility",
            "type":"Services"
        }
    ],
    "sg:phone":"+1 708 333 5019",
    "sg:postcode":"60473",
    "sg:province":"IL",
    "wof:name":"Holland Terrace",
    "wof:placetype":"venue"
},
  "geometry": {"coordinates":[-87.617029,41.6204],"type":"Point"}
}