{
  "type": "Feature",
  "properties": {
    "addr:full":"908 S Northwest Hwy Barrington IL 60010",
    "addr:housenumber":"908",
    "addr:postcode":"60010",
    "addr:street":"S Northwest Hwy",
    "iso:country":"US",
    "sg:address":"908 S Northwest Hwy",
    "sg:city":"Barrington",
    "sg:classifiers":[
        {
            "category":"Retail",
            "subcategory":"Auto Repair",
            "type":"Services"
        }
    ],
    "sg:phone":"+1 847 304 8822",
    "sg:postcode":"60010",
    "sg:province":"IL",
    "sg:tags":[
        "repairing",
        "automobile"
    ],
    "wof:name":"R Fischer Motors Inc",
    "wof:placetype":"venue"
},
  "geometry": {"coordinates":[-88.120074,42.147067],"type":"Point"}
}