{
  "type": "Feature",
  "properties": {
    "iso:country":"US",
    "sg:address":"3473 S Pecatonica Rd",
    "sg:city":"Pecatonica",
    "sg:phone":"+1 815 247 9020",
    "sg:postcode":"61063",
    "sg:province":"IL",
    "sg:tags":[
        "farm",
        "field",
        "crop"
    ],
    "wof:name":"Duane Lovett",
    "wof:placetype":"venue"
},
  "geometry": {"coordinates":[-89.358013,42.231879],"type":"Point"}
}