{
  "type": "Feature",
  "properties": {
    "addr:full":"106 N Metcalf Ave Amboy IL 61310",
    "addr:housenumber":"106",
    "addr:postcode":"61310",
    "addr:street":"N Metcalf Ave",
    "iso:country":"US",
    "sg:address":"106 N Metcalf Ave",
    "sg:city":"Amboy",
    "sg:classifiers":[
        {
            "category":"Personal",
            "subcategory":"Beauty Salon",
            "type":"Services"
        }
    ],
    "sg:phone":"+1 815 857 2024",
    "sg:postcode":"61310",
    "sg:province":"IL",
    "sg:tags":[
        "shop"
    ],
    "wof:name":"Alice S Beauty Shop",
    "wof:placetype":"venue"
},
  "geometry": {"coordinates":[-89.332306,41.718543],"type":"Point"}
}