{
  "type": "Feature",
  "properties": {
    "addr:full":"1212 N Prospect Ave Champaign IL 61820",
    "addr:housenumber":"1212",
    "addr:postcode":"61820",
    "addr:street":"N Prospect Ave",
    "iso:country":"US",
    "sg:address":"1212 N Prospect Ave",
    "sg:city":"Champaign",
    "sg:classifiers":[
        {
            "category":"Autos & Motor Vehicles",
            "subcategory":"Automobile Sales",
            "type":"Retail Goods"
        },
        {
            "category":"Retail",
            "subcategory":"Auto Rental",
            "type":"Services"
        }
    ],
    "sg:phone":"+1 217 355 1300",
    "sg:postcode":"61820",
    "sg:province":"IL",
    "sg:tags":[
        "truck",
        "leasing",
        "car"
    ],
    "sg:website":"http://www.enterprise.com/car_rental/deeplinkmap.do?gpbr=6201&bid=004&cnty=US&arc=YPTRL01&cm_mmc=Yellowpages.com-_-IYP-_-Tradelisting-_-branch",
    "wof:name":"Enterprise Rent-a-Car",
    "wof:placetype":"venue"
},
  "geometry": {"coordinates":[-88.257895,40.128286],"type":"Point"}
}