{
  "type": "Feature",
  "properties": {
    "iso:country":"US",
    "sg:address":"1004 Greenvalley St",
    "sg:city":"Bensenville",
    "sg:classifiers":[
        {
            "category":"Real Estate",
            "subcategory":"Real Estate Services",
            "type":"Services"
        },
        {
            "category":"Building & Trades",
            "subcategory":"Cleaning & Sanitation",
            "type":"Services"
        }
    ],
    "sg:phone":"+1 630 694 1772",
    "sg:postcode":"60106",
    "sg:province":"IL",
    "sg:tags":[
        "maintenance",
        "cleaners-interior"
    ],
    "wof:name":"Pm Maintenance",
    "wof:placetype":"venue"
},
  "geometry": {"coordinates":[-87.95559799999999,41.966301],"type":"Point"}
}