{
  "type": "Feature",
  "properties": {
    "addr:full":"201 E Huron St Ste 10-160 Chicago IL 60611",
    "addr:housenumber":"201",
    "addr:postcode":"10-160;60611",
    "addr:street":"E Huron St Ste",
    "iso:country":"US",
    "sg:address":"201 E Huron St Ste 10-160",
    "sg:city":"Chicago",
    "sg:classifiers":[
        {
            "category":"Health Services",
            "subcategory":"Doctor",
            "type":"Services"
        }
    ],
    "sg:phone":"+1 312 926 0055",
    "sg:postcode":"60611",
    "sg:province":"IL",
    "sg:tags":[
        "physician",
        "reproductive",
        "endocrinology",
        "surgeons",
        "surgeon",
        "metabolism",
        "diabetes"
    ],
    "wof:name":"Sanija Bajramovic Md",
    "wof:placetype":"venue"
},
  "geometry": {"coordinates":[-87.622772,41.89497],"type":"Point"}
}