{
  "type": "Feature",
  "properties": {
    "iso:country":"US",
    "sg:address":"12165 Golf Course Dr",
    "sg:city":"Whittington",
    "sg:classifiers":[
        {
            "category":"Recreation",
            "subcategory":"Picnic Area",
            "type":"Entertainment"
        }
    ],
    "sg:phone":"+1 618 629 1828",
    "sg:postcode":"62897",
    "sg:province":"IL",
    "sg:tags":[
        "place",
        "arcade",
        "amusement"
    ],
    "wof:name":"Recreation Information Ntwk",
    "wof:placetype":"venue"
},
  "geometry": {"coordinates":[-88.92028500000001,38.086725],"type":"Point"}
}