{
  "type": "Feature",
  "properties": {
    "addr:full":"2555 W Lawrence Ave Chicago IL 60625",
    "addr:housenumber":"2555",
    "addr:postcode":"60625",
    "addr:street":"W Lawrence Ave",
    "iso:country":"US",
    "sg:address":"2555 W Lawrence Ave",
    "sg:city":"Chicago",
    "sg:classifiers":[
        {
            "category":"Personal",
            "subcategory":"Day Spa",
            "type":"Services"
        },
        {
            "category":"Personal",
            "subcategory":"Nail Salon",
            "type":"Services"
        }
    ],
    "sg:phone":"+1 773 907 0654",
    "sg:postcode":"60625",
    "sg:province":"IL",
    "sg:website":"www.spahavananights.com",
    "wof:name":"Havana Nights Nails and Spa",
    "wof:placetype":"venue"
},
  "geometry": {"coordinates":[-87.69304700000001,41.968581],"type":"Point"}
}