{
  "type": "Feature",
  "properties": {
    "iso:country":"US",
    "sg:address":"387 North Ave",
    "sg:city":"Glendale Heights",
    "sg:classifiers":[
        {
            "category":"Retail",
            "subcategory":"Auto Repair",
            "type":"Services"
        }
    ],
    "sg:phone":"+1 630 668 1956",
    "sg:postcode":"60139",
    "sg:province":"IL",
    "sg:tags":[
        "body",
        "shop"
    ],
    "sg:website":"www.ednsonsautobody.com",
    "wof:name":"Ed-N-Sons Autobody",
    "wof:placetype":"venue"
},
  "geometry": {"coordinates":[-88.0784,41.899101],"type":"Point"}
}