{
  "type": "Feature",
  "properties": {
    "addr:full":"2859 W Montrose Avenue Chicago IL 60618",
    "addr:housenumber":"2859",
    "addr:postcode":"60618",
    "addr:street":"W Montrose Avenue",
    "iso:country":"US",
    "sg:address":"2859 W Montrose Avenue",
    "sg:city":"Chicago",
    "sg:classifiers":[
        {
            "category":"Retail",
            "subcategory":"Auto Repair",
            "type":"Services"
        }
    ],
    "sg:phone":"+1 773 588 8393",
    "sg:postcode":"60618",
    "sg:province":"IL",
    "wof:name":"Cool Heat Auto Radiator & Air Conditioning Service Centers",
    "wof:placetype":"venue"
},
  "geometry": {"coordinates":[-87.700682,41.961123],"type":"Point"}
}