{
  "type": "Feature",
  "properties": {
    "addr:full":"7 State Rte 59 Aurora IL 60504",
    "addr:housenumber":"7",
    "addr:postcode":"60504",
    "addr:street":"State Rte 59",
    "iso:country":"US",
    "sg:address":"7 State Rte 59",
    "sg:city":"Aurora",
    "sg:classifiers":[
        {
            "category":"Retail",
            "subcategory":"Auto Repair",
            "type":"Services"
        }
    ],
    "sg:phone":"+1 630 898 0190",
    "sg:postcode":"60504",
    "sg:province":"IL",
    "sg:tags":[
        "repairing",
        "automobile"
    ],
    "wof:name":"All Tune & Lube",
    "wof:placetype":"venue"
},
  "geometry": {"coordinates":[-88.205963,41.762464],"type":"Point"}
}