{
  "type": "Feature",
  "properties": {
    "iso:country":"US",
    "sg:address":"21680 Shawneetown Rd",
    "sg:city":"Thompsonville",
    "sg:classifiers":[
        {
            "category":"Autos & Motor Vehicles",
            "subcategory":"Automobile Sales",
            "type":"Retail Goods"
        }
    ],
    "sg:phone":"+1 618 627 2111",
    "sg:postcode":"62890",
    "sg:province":"IL",
    "sg:tags":[
        "new",
        "used",
        "car"
    ],
    "wof:name":"Shelton Motors",
    "wof:placetype":"venue"
},
  "geometry": {"coordinates":[-88.74741,37.913748],"type":"Point"}
}