{
  "type": "Feature",
  "properties": {
    "addr:full":"3010 King St Tilton IL 61833",
    "addr:housenumber":"3010",
    "addr:postcode":"61833",
    "addr:street":"King St",
    "iso:country":"US",
    "sg:address":"3010 King St",
    "sg:city":"Tilton",
    "sg:classifiers":[
        {
            "category":"Retail",
            "subcategory":"Auto Repair",
            "type":"Services"
        }
    ],
    "sg:phone":"+1 217 443 3368",
    "sg:postcode":"61833",
    "sg:province":"IL",
    "sg:tags":[
        "body",
        "automobile",
        "painting",
        "repairing"
    ],
    "sg:website":"http://truscellicollisionrepair.com",
    "wof:name":"Truscellis Collision & Repair",
    "wof:placetype":"venue"
},
  "geometry": {"coordinates":[-87.63764500000001,40.084985],"type":"Point"}
}