{
  "type": "Feature",
  "properties": {
    "addr:full":"175 W Jackson Blvd Chicago IL 60604",
    "addr:housenumber":"175",
    "addr:postcode":"60604",
    "addr:street":"W Jackson Blvd",
    "iso:country":"US",
    "sg:address":"175 W Jackson Blvd",
    "sg:city":"Chicago",
    "sg:classifiers":[
        {
            "category":"Professional",
            "type":"Services"
        }
    ],
    "sg:phone":"+1 312 602 4000",
    "sg:postcode":"60604",
    "sg:province":"IL",
    "sg:website":"www.westmonroepartners.com",
    "wof:name":"West Monroe Partners",
    "wof:placetype":"venue"
},
  "geometry": {"coordinates":[-87.633197,41.877997],"type":"Point"}
}