{
  "type": "Feature",
  "properties": {
    "iso:country":"US",
    "sg:address":"3452 N Southport Ste 1",
    "sg:city":"Chicago",
    "sg:classifiers":[
        {
            "category":"Travel",
            "subcategory":"Hotels & Motels",
            "type":"Entertainment"
        }
    ],
    "sg:phone":"+1 773 454 2116",
    "sg:postcode":"60657",
    "sg:province":"IL",
    "sg:tags":[
        "house",
        "guest"
    ],
    "sg:website":"www.chicagosouthportsuites.com",
    "wof:name":"Chicago Southport Suites",
    "wof:placetype":"venue"
},
  "geometry": {"coordinates":[-87.663955,41.944319],"type":"Point"}
}