{
  "type": "Feature",
  "properties": {
    "addr:full":"700 Lincoln Hwy Fairview Heights IL 62208",
    "addr:housenumber":"700",
    "addr:postcode":"62208",
    "addr:street":"Lincoln Hwy",
    "iso:country":"US",
    "sg:address":"700 Lincoln Hwy",
    "sg:city":"Fairview Heights",
    "sg:classifiers":[
        {
            "category":"Professional",
            "subcategory":"Business Services",
            "type":"Services"
        }
    ],
    "sg:phone":"+1 618 628 9020",
    "sg:postcode":"62208",
    "sg:province":"IL",
    "wof:name":"Signs By Tomorrow",
    "wof:placetype":"venue"
},
  "geometry": {"coordinates":[-89.97403,38.592693],"type":"Point"}
}