{
  "type": "Feature",
  "properties": {
    "iso:country":"US",
    "sg:address":"5768 W 2000N Rd",
    "sg:city":"Bonfield",
    "sg:classifiers":[
        {
            "category":"Professional",
            "subcategory":"Business Services",
            "type":"Services"
        }
    ],
    "sg:phone":"+1 815 933 3558",
    "sg:postcode":"60913",
    "sg:province":"IL",
    "wof:name":"National Prpts Inspections",
    "wof:placetype":"venue"
},
  "geometry": {"coordinates":[-87.984226,41.147201],"type":"Point"}
}