{
  "type": "Feature",
  "properties": {
    "iso:country":"US",
    "sg:address":"1311 Court St",
    "sg:city":"Mchenry",
    "sg:classifiers":[
        {
            "category":"Government",
            "subcategory":"Fire Station",
            "type":"Public Place"
        },
        {
            "category":"Professional",
            "subcategory":"Detective & Security Services",
            "type":"Services"
        },
        {
            "category":"Shopping",
            "subcategory":"Computers & Home Electronics",
            "type":"Retail Goods"
        }
    ],
    "sg:phone":"+1 877 519 9692",
    "sg:postcode":"60050",
    "sg:province":"IL",
    "sg:tags":[
        "control",
        "monitoring",
        "supply",
        "consultant",
        "system",
        "surveillance",
        "equipment",
        "protection"
    ],
    "sg:website":"http://www.homesecurityteam.com/?tfid=y",
    "wof:name":"Advanced Direct Security - ADT Authorized Company",
    "wof:placetype":"venue"
},
  "geometry": {"coordinates":[-88.26495799999999,42.345482],"type":"Point"}
}