{
  "type": "Feature",
  "properties": {
    "iso:country":"US",
    "sg:address":"218 S 7th St",
    "sg:city":"Wood River",
    "sg:classifiers":[
        {
            "category":"Arts & Performance",
            "subcategory":"Theater",
            "type":"Entertainment"
        }
    ],
    "sg:phone":"+1 618 254 4080",
    "sg:postcode":"62095",
    "sg:province":"IL",
    "sg:tags":[
        "sound",
        "lighting"
    ],
    "wof:name":"L B Music",
    "wof:placetype":"venue"
},
  "geometry": {"coordinates":[-90.085237,38.85679],"type":"Point"}
}