{
  "type": "Feature",
  "properties": {
    "addr:full":"180 Nottingham Dr Bolingbrook IL 60440",
    "addr:housenumber":"180",
    "addr:postcode":"60440",
    "addr:street":"Nottingham Dr",
    "iso:country":"US",
    "sg:address":"180 Nottingham Dr",
    "sg:city":"Bolingbrook",
    "sg:classifiers":[
        {
            "category":"Health Services",
            "subcategory":"Clinic",
            "type":"Services"
        }
    ],
    "sg:phone":"+1 630 759 2832",
    "sg:postcode":"60440",
    "sg:province":"IL",
    "wof:name":"Rich & Irene Morales",
    "wof:placetype":"venue"
},
  "geometry": {"coordinates":[-88.08542300000001,41.701104],"type":"Point"}
}