{
  "type": "Feature",
  "properties": {
    "addr:full":"723 S Cameron Ln Peoria IL 61607",
    "addr:housenumber":"723",
    "addr:postcode":"61607",
    "addr:street":"S Cameron Ln",
    "iso:country":"US",
    "sg:address":"723 S Cameron Ln",
    "sg:city":"Peoria",
    "sg:classifiers":[
        {
            "category":"Professional",
            "subcategory":"Business Services",
            "type":"Services"
        }
    ],
    "sg:phone":"+1 309 697 8613",
    "sg:postcode":"61607",
    "sg:province":"IL",
    "sg:tags":[
        "organizing",
        "services-household"
    ],
    "wof:name":"Stuart J Karl",
    "wof:placetype":"venue"
},
  "geometry": {"coordinates":[-89.727814,40.682342],"type":"Point"}
}