{
  "type": "Feature",
  "properties": {
    "addr:full":"782 N Broadway Aurora IL 60505",
    "addr:housenumber":"782",
    "addr:postcode":"60505",
    "addr:street":"N Broadway",
    "iso:country":"US",
    "sg:address":"782 N Broadway",
    "sg:city":"Aurora",
    "sg:classifiers":[
        {
            "category":"Building & Trades",
            "subcategory":"Construction",
            "type":"Services"
        }
    ],
    "sg:phone":"+1 630 896 9505",
    "sg:postcode":"60505",
    "sg:province":"IL",
    "sg:tags":[
        "hanging",
        "contractor"
    ],
    "wof:name":"Midwest Coatings & Sandblast",
    "wof:placetype":"venue"
},
  "geometry": {"coordinates":[-88.30624,41.770916],"type":"Point"}
}