{
  "type": "Feature",
  "properties": {
    "addr:full":"3142 E 1st Rd Peru IL 61354",
    "addr:housenumber":"3142",
    "addr:postcode":"61354",
    "addr:street":"E 1St Rd",
    "iso:country":"US",
    "sg:address":"3142 E 1st Rd",
    "sg:city":"Peru",
    "sg:phone":"+1 815 223 6356",
    "sg:postcode":"61354",
    "sg:province":"IL",
    "sg:tags":[
        "farm",
        "corn",
        "soybean"
    ],
    "wof:name":"Dean Sack",
    "wof:placetype":"venue"
},
  "geometry": {"coordinates":[-89.144835,41.386521],"type":"Point"}
}