{
  "type": "Feature",
  "properties": {
    "iso:country":"US",
    "sg:address":"12143 W 159th St",
    "sg:city":"Homer Glen",
    "sg:classifiers":[
        {
            "category":"Manufacturing",
            "subcategory":"Signs",
            "type":"Manufacturing & Wholesale Goods"
        }
    ],
    "sg:phone":"+1 708 301 5529",
    "sg:postcode":"60491",
    "sg:province":"IL",
    "wof:name":"F X Graphics",
    "wof:placetype":"venue"
},
  "geometry": {"coordinates":[-87.912928,41.600189],"type":"Point"}
}