{
  "type": "Feature",
  "properties": {
    "iso:country":"US",
    "sg:address":"212 W Main St",
    "sg:city":"Rockton",
    "sg:classifiers":[
        {
            "category":"Shopping",
            "subcategory":"Used Merchandise",
            "type":"Retail Goods"
        }
    ],
    "sg:phone":"+1   ",
    "sg:postcode":"61072",
    "sg:province":"IL",
    "wof:name":"Nichols Antiques",
    "wof:placetype":"venue"
},
  "geometry": {"coordinates":[-89.075224,42.452429],"type":"Point"}
}