{
  "type": "Feature",
  "properties": {
    "iso:country":"US",
    "sg:address":"212 N Fremont St",
    "sg:city":"Tampico",
    "sg:classifiers":[
        {
            "category":"Farming",
            "subcategory":"Farm",
            "type":"Manufacturing & Wholesale Goods"
        }
    ],
    "sg:phone":"+1 815 438 2341",
    "sg:postcode":"61283",
    "sg:province":"IL",
    "sg:tags":[
        "crop",
        "general"
    ],
    "wof:name":"Mike Cady",
    "wof:placetype":"venue"
},
  "geometry": {"coordinates":[-89.783155,41.632327],"type":"Point"}
}