{
  "type": "Feature",
  "properties": {
    "addr:full":"212 N Fremont St Tampico IL 61283",
    "addr:housenumber":"212",
    "addr:postcode":"61283",
    "addr:street":"N Fremont St",
    "iso:country":"US",
    "sg:address":"212 N Fremont St",
    "sg:city":"Tampico",
    "sg:classifiers":[
        {
            "category":"Farming",
            "subcategory":"Farm",
            "type":"Manufacturing & Wholesale Goods"
        }
    ],
    "sg:phone":"+1 815 438 2341",
    "sg:postcode":"61283",
    "sg:province":"IL",
    "sg:tags":[
        "crop",
        "general"
    ],
    "wof:name":"Mike Cady",
    "wof:placetype":"venue"
},
  "geometry": {"coordinates":[-89.78315499999999,41.632327],"type":"Point"}
}