{
  "type": "Feature",
  "properties": {
    "iso:country":"US",
    "sg:address":"1701 Larkin Ave",
    "sg:city":"Crest Hill",
    "sg:classifiers":[
        {
            "category":"Shopping",
            "subcategory":"Used Merchandise",
            "type":"Retail Goods"
        }
    ],
    "sg:phone":"+1 815 729 2222",
    "sg:postcode":"60435",
    "sg:province":"IL",
    "sg:tags":[
        "pawnbroker"
    ],
    "wof:name":"Crest Hill Pawn & Jewelry",
    "wof:placetype":"venue"
},
  "geometry": {"coordinates":[-88.126028,41.553769],"type":"Point"}
}