{
  "type": "Feature",
  "properties": {
    "iso:country":"US",
    "sg:address":"220 E 1st St",
    "sg:city":"Genoa",
    "sg:classifiers":[
        {
            "category":"Manufacturing",
            "subcategory":"Tools & Machinery",
            "type":"Manufacturing & Wholesale Goods"
        }
    ],
    "sg:phone":"+1 815 784 6471",
    "sg:postcode":"60135",
    "sg:province":"IL",
    "sg:tags":[
        "mfg"
    ],
    "wof:name":"Micro Master Tool & Die",
    "wof:placetype":"venue"
},
  "geometry": {"coordinates":[-88.690956,42.099442],"type":"Point"}
}