{
  "type": "Feature",
  "properties": {
    "iso:country":"US",
    "sg:address":"4065 183rd St",
    "sg:city":"Country Club Hills",
    "sg:classifiers":[
        {
            "category":"Insurance",
            "subcategory":"Insurance Agent",
            "type":"Services"
        }
    ],
    "sg:phone":"+1 708 798 7688",
    "sg:postcode":"60478",
    "sg:province":"IL",
    "wof:name":"State Farm Insurance",
    "wof:placetype":"venue"
},
  "geometry": {"coordinates":[-87.715063,41.557052],"type":"Point"}
}