{
  "type": "Feature",
  "properties": {
    "addr:full":"100 S Railroad St Patoka IL 62875",
    "addr:housenumber":"100",
    "addr:postcode":"62875",
    "addr:street":"S Railroad St",
    "iso:country":"US",
    "sg:address":"100 S Railroad St",
    "sg:city":"Patoka",
    "sg:classifiers":[
        {
            "category":"Wholesale",
            "subcategory":"Farm Supplies",
            "type":"Manufacturing & Wholesale Goods"
        },
        {
            "category":"Shopping",
            "subcategory":"Pets & Pet Supplies",
            "type":"Retail Goods"
        }
    ],
    "sg:phone":"+1 618 432 7194",
    "sg:postcode":"62875",
    "sg:province":"IL",
    "sg:tags":[
        "feed",
        "concentrate",
        "supplement",
        "grain",
        "elevator"
    ],
    "wof:name":"Adm Grain",
    "wof:placetype":"venue"
},
  "geometry": {"coordinates":[-89.09610000000001,38.753929],"type":"Point"}
}