{
  "type": "Feature",
  "properties": {
    "addr:full":"5909 N Kenmore Ave Chicago IL 60660",
    "addr:housenumber":"5909",
    "addr:postcode":"60660",
    "addr:street":"N Kenmore Ave",
    "iso:country":"US",
    "sg:address":"5909 N Kenmore Ave",
    "sg:city":"Chicago",
    "sg:classifiers":[
        {
            "category":"Education",
            "subcategory":"Music School",
            "type":"Public Place"
        }
    ],
    "sg:phone":"+1 312 401 5737",
    "sg:postcode":"60660",
    "sg:province":"IL",
    "sg:tags":[
        "instruction-vocal"
    ],
    "sg:website":"http://www.livewebvoicelessons.com/",
    "wof:name":"Live Web Voice Lessons",
    "wof:placetype":"venue"
},
  "geometry": {"coordinates":[-87.65670299999999,41.989617],"type":"Point"}
}