{
  "type": "Feature",
  "properties": {
    "addr:full":"2333 Randall Rd Carpentersville IL 60110",
    "addr:housenumber":"2333",
    "addr:postcode":"60110",
    "addr:street":"Randall Rd",
    "iso:country":"US",
    "sg:address":"2333 Randall Rd",
    "sg:city":"Carpentersville",
    "sg:classifiers":[
        {
            "category":"Cinema",
            "subcategory":"Movie Rental",
            "type":"Entertainment"
        }
    ],
    "sg:phone":"+1 847 428 7760",
    "sg:postcode":"60110",
    "sg:province":"IL",
    "sg:tags":[
        "game",
        "video"
    ],
    "sg:website":"www.blockbuster.com",
    "wof:name":"Blockbuster",
    "wof:placetype":"venue"
},
  "geometry": {"coordinates":[-88.335503,42.122898],"type":"Point"}
}