{
  "type": "Feature",
  "properties": {
    "addr:full":"7624 W Main St Belleville IL 62223",
    "addr:housenumber":"7624",
    "addr:postcode":"62223",
    "addr:street":"W Main St",
    "iso:country":"US",
    "sg:address":"7624 W Main St",
    "sg:city":"Belleville",
    "sg:classifiers":[
        {
            "category":"Professional",
            "subcategory":"Lawyer & Legal Services",
            "type":"Services"
        }
    ],
    "sg:phone":"+1 618 397 5778",
    "sg:postcode":"62223",
    "sg:province":"IL",
    "sg:tags":[
        "business"
    ],
    "wof:name":"Coffman Townslin",
    "wof:placetype":"venue"
},
  "geometry": {"coordinates":[-90.047299,38.562056],"type":"Point"}
}