{
  "type": "Feature",
  "properties": {
    "addr:full":"845 Indian Wells Cir Elgin IL 60123",
    "addr:housenumber":"845",
    "addr:postcode":"60123",
    "addr:street":"Indian Wells Cir",
    "iso:country":"US",
    "sg:address":"845 Indian Wells Cir",
    "sg:city":"Elgin",
    "sg:classifiers":[
        {
            "category":"Food & Beverages",
            "subcategory":"Specialty",
            "type":"Retail Goods"
        }
    ],
    "sg:phone":"+1   ",
    "sg:postcode":"60123",
    "sg:province":"IL",
    "wof:name":"Genesis Partners",
    "wof:placetype":"venue"
},
  "geometry": {"coordinates":[-88.321517,42.012343],"type":"Point"}
}