{
  "type": "Feature",
  "properties": {
    "iso:country":"US",
    "sg:address":"23608 S Harlem Ave",
    "sg:city":"Frankfort",
    "sg:classifiers":[
        {
            "category":"Retail",
            "subcategory":"Auto Repair",
            "type":"Services"
        }
    ],
    "sg:phone":"+1 815 464 5671",
    "sg:postcode":"60423",
    "sg:province":"IL",
    "sg:tags":[
        "general"
    ],
    "wof:name":"Solid Auto Service",
    "wof:placetype":"venue"
},
  "geometry": {"coordinates":[-87.787273,41.461726],"type":"Point"}
}