{
  "type": "Feature",
  "properties": {
    "iso:country":"US",
    "sg:address":"5416 W 25th St",
    "sg:city":"Cicero",
    "sg:classifiers":[
        {
            "category":"Communications",
            "subcategory":"Newspaper",
            "type":"Services"
        }
    ],
    "sg:phone":"+1 708 656 6400",
    "sg:postcode":"60804",
    "sg:province":"IL",
    "sg:tags":[
        "print",
        "medium"
    ],
    "wof:name":"Lawndale News Noticiero Bilingue",
    "wof:placetype":"venue"
},
  "geometry": {"coordinates":[-87.759697,41.845699],"type":"Point"}
}