{
  "type": "Feature",
  "properties": {
    "iso:country":"US",
    "sg:address":"9146 Broadway Ave",
    "sg:city":"Brookfield",
    "sg:classifiers":[
        {
            "category":"Health Services",
            "subcategory":"Chiropractor",
            "type":"Services"
        }
    ],
    "sg:phone":"+1 708 485 3260",
    "sg:postcode":"60513",
    "sg:province":"IL",
    "wof:name":"Physicians For Natural Health",
    "wof:placetype":"venue"
},
  "geometry": {"coordinates":[-87.850247,41.828842],"type":"Point"}
}