{
  "type": "Feature",
  "properties": {
    "addr:full":"5722 N Kimball Ave Chicago IL 60659",
    "addr:housenumber":"5722",
    "addr:postcode":"60659",
    "addr:street":"N Kimball Ave",
    "iso:country":"US",
    "sg:address":"5722 N Kimball Ave",
    "sg:city":"Chicago",
    "sg:classifiers":[
        {
            "category":"Food & Beverages",
            "subcategory":"Groceries & Convenience Stores",
            "type":"Retail Goods"
        }
    ],
    "sg:phone":"+1   ",
    "sg:postcode":"60659",
    "sg:province":"IL",
    "wof:name":"Makki Meat & Groceries",
    "wof:placetype":"venue"
},
  "geometry": {"coordinates":[-87.71393,41.986231],"type":"Point"}
}