{
  "type": "Feature",
  "properties": {
    "addr:full":"2486 W Schaumburg Rd Schaumburg IL 60194",
    "addr:housenumber":"2486",
    "addr:postcode":"60194",
    "addr:street":"W Schaumburg Rd",
    "iso:country":"US",
    "sg:address":"2486 W Schaumburg Rd",
    "sg:city":"Schaumburg",
    "sg:classifiers":[
        {
            "category":"Wholesale",
            "subcategory":"Home Furnishings",
            "type":"Manufacturing & Wholesale Goods"
        }
    ],
    "sg:phone":"+1 847 490 9580",
    "sg:postcode":"60194",
    "sg:province":"IL",
    "sg:tags":[
        "picture",
        "framing",
        "custom"
    ],
    "wof:name":"Framed Art",
    "wof:placetype":"venue"
},
  "geometry": {"coordinates":[-88.153847,42.029692],"type":"Point"}
}