{
  "type": "Feature",
  "properties": {
    "iso:country":"US",
    "sg:address":"514 N Delmar Ave",
    "sg:city":"Hartford",
    "sg:classifiers":[
        {
            "category":"Professional",
            "subcategory":"Engineering",
            "type":"Services"
        },
        {
            "category":"Building & Trades",
            "subcategory":"Cleaning & Sanitation",
            "type":"Services"
        },
        {
            "category":"Wholesale",
            "subcategory":"Machinery & Supplies",
            "type":"Manufacturing & Wholesale Goods"
        },
        {
            "category":"Building & Trades",
            "subcategory":"Construction",
            "type":"Services"
        }
    ],
    "sg:phone":"+1 618 254 2407",
    "sg:postcode":"62048",
    "sg:province":"IL",
    "sg:tags":[
        "equipment-commercial",
        "system",
        "specialty",
        "heating",
        "ice",
        "machine",
        "equipment",
        "furnaces-repairing",
        "refrigeration",
        "industrial",
        "making",
        "contractor",
        "air conditioning"
    ],
    "wof:name":"AaA Heating Cooling & Refrigeration",
    "wof:placetype":"venue"
},
  "geometry": {"coordinates":[-90.095686,38.838043],"type":"Point"}
}