{
  "type": "Feature",
  "properties": {
    "addr:full":"732 S Pulaski Road Chicago IL 60624",
    "addr:housenumber":"732",
    "addr:postcode":"60624",
    "addr:street":"S Pulaski Road",
    "iso:country":"US",
    "sg:address":"732 S Pulaski Road",
    "sg:city":"Chicago",
    "sg:classifiers":[
        {
            "category":"Health Services",
            "subcategory":"Doctor",
            "type":"Services"
        }
    ],
    "sg:phone":"+1 773 533 3553",
    "sg:postcode":"60624",
    "sg:province":"IL",
    "sg:tags":[
        "practice",
        "family"
    ],
    "wof:name":"A & D Medical",
    "wof:placetype":"venue"
},
  "geometry": {"coordinates":[-87.72537199999999,41.871549],"type":"Point"}
}