{
  "type": "Feature",
  "properties": {
    "iso:country":"US",
    "sg:address":"1411 W Hwy 50",
    "sg:city":"O'Fallon",
    "sg:classifiers":[
        {
            "category":"Restaurant",
            "type":"Food & Drink"
        }
    ],
    "sg:phone":"+1 618 622 3322",
    "sg:postcode":"62269",
    "sg:province":"IL",
    "sg:tags":[
        "chinese"
    ],
    "wof:name":"Liu's Buffet",
    "wof:placetype":"venue"
},
  "geometry": {"coordinates":[-89.952625,38.592163],"type":"Point"}
}