{
  "type": "Feature",
  "properties": {
    "addr:full":"760 N Entrance Ave Kankakee IL 60901",
    "addr:housenumber":"760",
    "addr:postcode":"60901",
    "addr:street":"N Entrance Ave",
    "iso:country":"US",
    "sg:address":"760 N Entrance Ave",
    "sg:city":"Kankakee",
    "sg:classifiers":[
        {
            "category":"Building & Trades",
            "subcategory":"Construction",
            "type":"Services"
        }
    ],
    "sg:phone":"+1 815 933 6045",
    "sg:postcode":"60901",
    "sg:province":"IL",
    "sg:tags":[
        "excavating",
        "contractor"
    ],
    "wof:name":"Oakwood Trucking & Excavating",
    "wof:placetype":"venue"
},
  "geometry": {"coordinates":[-87.86891,41.129163],"type":"Point"}
}