{
  "type": "Feature",
  "properties": {
    "iso:country":"US",
    "sg:address":"6755 Giant City Rd",
    "sg:city":"Carbondale",
    "sg:classifiers":[
        {
            "category":"Organizations",
            "subcategory":"Non-profit Organization",
            "type":"Services"
        }
    ],
    "sg:phone":"+1 618 549 4633",
    "sg:postcode":"62902",
    "sg:province":"IL",
    "sg:tags":[
        "information",
        "alcoholism",
        "treatment"
    ],
    "wof:name":"Alcoholics Anonymous",
    "wof:placetype":"venue"
},
  "geometry": {"coordinates":[-89.174087,37.68228],"type":"Point"}
}