{
  "type": "Feature",
  "properties": {
    "addr:full":"1870 E Voorhees St Danville IL 61834",
    "addr:housenumber":"1870",
    "addr:postcode":"61834",
    "addr:street":"E Voorhees St",
    "iso:country":"US",
    "sg:address":"1870 E Voorhees St",
    "sg:city":"Danville",
    "sg:classifiers":[
        {
            "category":"Building & Trades",
            "subcategory":"Equipment Rental",
            "type":"Services"
        }
    ],
    "sg:phone":"+1 217 442 6030",
    "sg:postcode":"61834",
    "sg:province":"IL",
    "sg:tags":[
        "leasing",
        "furniture"
    ],
    "sg:website":"www.instantfurniture.com",
    "wof:name":"Cort Furniture Rental",
    "wof:placetype":"venue"
},
  "geometry": {"coordinates":[-87.58911999999999,40.146805],"type":"Point"}
}