{
  "type": "Feature",
  "properties": {
    "addr:full":"1615 N Alpine Rd Rockford IL 61107",
    "addr:housenumber":"1615",
    "addr:postcode":"61107",
    "addr:street":"N Alpine Rd",
    "iso:country":"US",
    "sg:address":"1615 N Alpine Rd",
    "sg:city":"Rockford",
    "sg:classifiers":[
        {
            "category":"Shopping",
            "subcategory":"Clothing, Apparel, & Fashions",
            "type":"Retail Goods"
        }
    ],
    "sg:phone":"+1   ",
    "sg:postcode":"61107",
    "sg:province":"IL",
    "sg:tags":[
        "silk",
        "gift"
    ],
    "wof:name":"Sara Grace Company",
    "wof:placetype":"venue"
},
  "geometry": {"coordinates":[-89.02903000000001,42.287],"type":"Point"}
}