{
  "type": "Feature",
  "properties": {
    "addr:full":"2373 E 70th St Chicago IL 60649",
    "addr:housenumber":"2373",
    "addr:postcode":"60649",
    "addr:street":"E 70Th St",
    "iso:country":"US",
    "sg:address":"2373 E 70th St",
    "sg:city":"Chicago",
    "sg:classifiers":[
        {
            "category":"Real Estate",
            "subcategory":"Real Estate Operator",
            "type":"Services"
        }
    ],
    "sg:phone":"+1 773 752 3500",
    "sg:postcode":"60649",
    "sg:province":"IL",
    "sg:tags":[
        "apartment"
    ],
    "wof:name":"7000 S South Shore Drive Apts",
    "wof:placetype":"venue"
},
  "geometry": {"coordinates":[-87.56658299999999,41.768],"type":"Point"}
}