{
  "type": "Feature",
  "properties": {
    "addr:full":"343 Harrison St Oak Park IL 60304",
    "addr:housenumber":"343",
    "addr:postcode":"60304",
    "addr:street":"Harrison St",
    "iso:country":"US",
    "sg:address":"343 Harrison St",
    "sg:city":"Oak Park",
    "sg:classifiers":[
        {
            "category":"Recreation",
            "type":"Entertainment"
        }
    ],
    "sg:phone":"+1 708 386 0603",
    "sg:postcode":"60304",
    "sg:province":"IL",
    "sg:tags":[
        "mfg"
    ],
    "wof:name":"Prairie Woodworking",
    "wof:placetype":"venue"
},
  "geometry": {"coordinates":[-87.783942,41.872554],"type":"Point"}
}