{
  "type": "Feature",
  "properties": {
    "addr:full":"1034 Elm St Rockford IL 61102",
    "addr:housenumber":"1034",
    "addr:postcode":"61102",
    "addr:street":"Elm St",
    "iso:country":"US",
    "sg:address":"1034 Elm St",
    "sg:city":"Rockford",
    "sg:classifiers":[
        {
            "category":"Wholesale",
            "subcategory":"Vending Machines",
            "type":"Manufacturing & Wholesale Goods"
        }
    ],
    "sg:phone":"+1 815 963 7541",
    "sg:postcode":"61102",
    "sg:province":"IL",
    "wof:name":"Future Vending",
    "wof:placetype":"venue"
},
  "geometry": {"coordinates":[-89.10556,42.274622],"type":"Point"}
}