{
  "type": "Feature",
  "properties": {
    "iso:country":"US",
    "sg:address":"1312 Washington St",
    "sg:city":"Waukegan",
    "sg:classifiers":[
        {
            "category":"Organizations",
            "subcategory":"Professional Association",
            "type":"Services"
        }
    ],
    "sg:phone":"+1 847 623 2345",
    "sg:postcode":"60085",
    "sg:province":"IL",
    "sg:website":"www.lcca-il.org",
    "wof:name":"Lake County Contractors Assn",
    "wof:placetype":"venue"
},
  "geometry": {"coordinates":[-87.848201,42.359729],"type":"Point"}
}