{
  "type": "Feature",
  "properties": {
    "iso:country":"US",
    "sg:address":"3001 Chatham Rd",
    "sg:city":"Springfield",
    "sg:classifiers":[
        {
            "category":"Banks & Credit Unions",
            "subcategory":"Bank",
            "type":"Services"
        }
    ],
    "sg:phone":"+1 217 789 3500",
    "sg:postcode":"62704",
    "sg:province":"IL",
    "sg:website":"http://www.securitybk.com",
    "wof:name":"Security Federal Savings & Loan Association (Inc)",
    "wof:placetype":"venue"
},
  "geometry": {"coordinates":[-89.686913,39.766369],"type":"Point"}
}