{
  "type": "Feature",
  "properties": {
    "addr:full":"910 N Kinzie Ave Bradley IL 60915",
    "addr:housenumber":"910",
    "addr:postcode":"60915",
    "addr:street":"N Kinzie Ave",
    "iso:country":"US",
    "sg:address":"910 N Kinzie Ave",
    "sg:city":"Bradley",
    "sg:classifiers":[
        {
            "category":"Restaurant",
            "type":"Food & Drink"
        }
    ],
    "sg:phone":"+1 815 802 0947",
    "sg:postcode":"60915",
    "sg:province":"IL",
    "wof:name":"Ryan's Grill Buffet & Bakery",
    "wof:placetype":"venue"
},
  "geometry": {"coordinates":[-87.85107600000001,41.156239],"type":"Point"}
}