{
  "type": "Feature",
  "properties": {
    "addr:full":"1028 15th Ave Fulton IL 61252",
    "addr:housenumber":"1028",
    "addr:postcode":"61252",
    "addr:street":"15Th Ave",
    "iso:country":"US",
    "sg:address":"1028 15th Ave",
    "sg:city":"Fulton",
    "sg:classifiers":[
        {
            "category":"Professional",
            "subcategory":"Business Services",
            "type":"Services"
        }
    ],
    "sg:phone":"+1 815 589 4493",
    "sg:postcode":"61252",
    "sg:province":"IL",
    "sg:tags":[
        "industrial",
        "machinery",
        "mfg"
    ],
    "wof:name":"Hobby Machine",
    "wof:placetype":"venue"
},
  "geometry": {"coordinates":[-90.157465,41.862832],"type":"Point"}
}