{
  "type": "Feature",
  "properties": {
    "iso:country":"US",
    "sg:address":"3393 Whirlaway Dr",
    "sg:city":"Northbrook",
    "sg:classifiers":[
        {
            "category":"Manufacturing",
            "subcategory":"Paper Products",
            "type":"Manufacturing & Wholesale Goods"
        }
    ],
    "sg:phone":"+1 312 848 1602",
    "sg:postcode":"60062",
    "sg:province":"IL",
    "sg:tags":[
        "machine",
        "shredding"
    ],
    "wof:name":"Arebas Inc",
    "wof:placetype":"venue"
},
  "geometry": {"coordinates":[-87.865206,42.107949],"type":"Point"}
}