{
  "type": "Feature",
  "properties": {
    "addr:full":"5531 Belmont Rd Downers Grove IL 60515",
    "addr:housenumber":"5531",
    "addr:postcode":"60515",
    "addr:street":"Belmont Rd",
    "iso:country":"US",
    "sg:address":"5531 Belmont Rd",
    "sg:city":"Downers Grove",
    "sg:classifiers":[
        {
            "category":"Restaurant",
            "type":"Food & Drink"
        }
    ],
    "sg:menulink":"http://www.allmenus.com/il/lisle/76590-dominos-pizza/menu/",
    "sg:phone":"+1 630 515 1700",
    "sg:postcode":"60515",
    "sg:province":"IL",
    "sg:tags":[
        "american",
        "wing",
        "pizza"
    ],
    "wof:name":"Domino's Pizza",
    "wof:placetype":"venue"
},
  "geometry": {"coordinates":[-88.03750700000001,41.786409],"type":"Point"}
}