{
  "type": "Feature",
  "properties": {
    "iso:country":"US",
    "sg:address":"4340 S Archer Ave",
    "sg:city":"Chicago",
    "sg:classifiers":[
        {
            "category":"Restaurant",
            "type":"Food & Drink"
        }
    ],
    "sg:menulink":"http://www.allmenus.com/il/chicago/221597-wing-wah-lau/menu/",
    "sg:phone":"+1 773 247 1663",
    "sg:postcode":"60632",
    "sg:province":"IL",
    "sg:tags":[
        "asian",
        "chinese"
    ],
    "wof:name":"Wing Wah Lau",
    "wof:placetype":"venue"
},
  "geometry": {"coordinates":[-87.70349899999999,41.814437],"type":"Point"}
}