{
  "type": "Feature",
  "properties": {
    "addr:full":"1119 W Bryn Mawr Ave Chicago IL 60660",
    "addr:housenumber":"1119",
    "addr:postcode":"60660",
    "addr:street":"W Bryn Mawr Ave",
    "iso:country":"US",
    "sg:address":"1119 W Bryn Mawr Ave",
    "sg:city":"Chicago",
    "sg:classifiers":[
        {
            "category":"Shopping",
            "subcategory":"Tobacco",
            "type":"Retail Goods"
        }
    ],
    "sg:phone":"+1 773 989 4786",
    "sg:postcode":"60660",
    "sg:province":"IL",
    "sg:tags":[
        "shop"
    ],
    "wof:name":"T & J Concession",
    "wof:placetype":"venue"
},
  "geometry": {"coordinates":[-87.658699,41.983501],"type":"Point"}
}