{
  "type": "Feature",
  "properties": {
    "iso:country":"US",
    "sg:address":"398 W Army Trail Rd Ste 110",
    "sg:city":"Bloomingdale",
    "sg:classifiers":[
        {
            "category":"Home & Garden",
            "subcategory":"Furniture",
            "type":"Retail Goods"
        },
        {
            "category":"Home & Garden",
            "subcategory":"Carpets & Floor Coverings",
            "type":"Retail Goods"
        }
    ],
    "sg:phone":"+1 630 582 8500",
    "sg:postcode":"60108",
    "sg:province":"IL",
    "sg:tags":[
        "store",
        "mattress"
    ],
    "wof:name":"Amer Mattress",
    "wof:placetype":"venue"
},
  "geometry": {"coordinates":[-88.114799,41.939301],"type":"Point"}
}