{
  "type": "Feature",
  "properties": {
    "addr:full":"172 Waukegan Rd Deerfield IL 60015",
    "addr:housenumber":"172",
    "addr:postcode":"60015",
    "addr:street":"Waukegan Rd",
    "iso:country":"US",
    "sg:address":"172 Waukegan Rd",
    "sg:city":"Deerfield",
    "sg:classifiers":[
        {
            "category":"Personal",
            "subcategory":"Beauty Salon",
            "type":"Services"
        }
    ],
    "sg:phone":"+1 847 412 1488",
    "sg:postcode":"60015",
    "sg:province":"IL",
    "sg:tags":[
        "shop"
    ],
    "wof:name":"Pretty Nails",
    "wof:placetype":"venue"
},
  "geometry": {"coordinates":[-87.837334,42.155627],"type":"Point"}
}