{
  "type": "Feature",
  "properties": {
    "iso:country":"US",
    "sg:address":"1429 S Main St",
    "sg:city":"Jacksonville",
    "sg:classifiers":[
        {
            "category":"Retail",
            "subcategory":"Repair Shop",
            "type":"Services"
        },
        {
            "category":"Shopping",
            "subcategory":"Jewelry",
            "type":"Retail Goods"
        }
    ],
    "sg:phone":"+1 217 243 8042",
    "sg:postcode":"62650",
    "sg:province":"IL",
    "sg:tags":[
        "clocks",
        "parts"
    ],
    "wof:name":"Jacksonville Clock Shop",
    "wof:placetype":"venue"
},
  "geometry": {"coordinates":[-90.229301,39.715355],"type":"Point"}
}