{
  "type": "Feature",
  "properties": {
    "iso:country":"US",
    "sg:address":"1631 35th St",
    "sg:city":"Rock Island",
    "sg:classifiers":[
        {
            "category":"Wholesale",
            "subcategory":"Machinery & Supplies",
            "type":"Manufacturing & Wholesale Goods"
        }
    ],
    "sg:phone":"+1 309 786 6821",
    "sg:postcode":"61201",
    "sg:province":"IL",
    "sg:tags":[
        "equipment",
        "construction",
        "nonresidential"
    ],
    "wof:name":"Wick Buildings-Harold Bramlet",
    "wof:placetype":"venue"
},
  "geometry": {"coordinates":[-90.551149,41.493498],"type":"Point"}
}