{
  "type": "Feature",
  "properties": {
    "addr:full":"3917 W 95th St Evergreen Park IL 60805",
    "addr:housenumber":"3917",
    "addr:postcode":"60805",
    "addr:street":"W 95Th St",
    "iso:country":"US",
    "sg:address":"3917 W 95th St",
    "sg:city":"Evergreen Park",
    "sg:classifiers":[
        {
            "category":"Retail",
            "subcategory":"Animal Services",
            "type":"Services"
        }
    ],
    "sg:phone":"+1 708 499 9989",
    "sg:postcode":"60805",
    "sg:province":"IL",
    "sg:tags":[
        "pet",
        "grooming",
        "washing"
    ],
    "wof:name":"Barb's All-Breed Dog Grooming",
    "wof:placetype":"venue"
},
  "geometry": {"coordinates":[-87.719616,41.720416],"type":"Point"}
}