{
  "type": "Feature",
  "properties": {
    "addr:full":"4514 N Ashland Ave Chicago IL 60640",
    "addr:housenumber":"4514",
    "addr:postcode":"60640",
    "addr:street":"N Ashland Ave",
    "iso:country":"US",
    "sg:address":"4514 N Ashland Ave",
    "sg:city":"Chicago",
    "sg:classifiers":[
        {
            "category":"Sports & Exercise",
            "subcategory":"Sports Center",
            "type":"Entertainment"
        },
        {
            "category":"Community Center",
            "type":"Public Place"
        },
        {
            "category":"Sports & Exercise",
            "subcategory":"Golf",
            "type":"Entertainment"
        }
    ],
    "sg:phone":"+1 773 414 3459",
    "sg:postcode":"60640",
    "sg:province":"IL",
    "sg:tags":[
        "course",
        "recreation",
        "instruction"
    ],
    "wof:name":"The Swing Doctors",
    "wof:placetype":"venue"
},
  "geometry": {"coordinates":[-87.66930499999999,41.963687],"type":"Point"}
}