{
  "type": "Feature",
  "properties": {
    "iso:country":"US",
    "sg:address":"1081 N Co Rd 850",
    "sg:city":"Hamilton",
    "sg:classifiers":[
        {
            "category":"Farming",
            "subcategory":"Farm",
            "type":"Manufacturing & Wholesale Goods"
        }
    ],
    "sg:phone":"+1 217 847 3796",
    "sg:postcode":"62341",
    "sg:province":"IL",
    "sg:tags":[
        "crop",
        "general"
    ],
    "wof:name":"Larry Hufendick",
    "wof:placetype":"venue"
},
  "geometry": {"coordinates":[-91.342207,40.353258],"type":"Point"}
}