{
  "type": "Feature",
  "properties": {
    "addr:full":"2039 W Cullom Ave Chicago IL 60618",
    "addr:housenumber":"2039",
    "addr:postcode":"60618",
    "addr:street":"W Cullom Ave",
    "iso:country":"US",
    "sg:address":"2039 W Cullom Ave",
    "sg:city":"Chicago",
    "sg:classifiers":[
        {
            "category":"Professional",
            "subcategory":"Management & Consulting",
            "type":"Services"
        }
    ],
    "sg:phone":"+1 773 281 5767",
    "sg:postcode":"60618",
    "sg:province":"IL",
    "sg:tags":[
        "counselor",
        "relation",
        "public"
    ],
    "wof:name":"Stein, Phoebe Public Relations Ltd",
    "wof:placetype":"venue"
},
  "geometry": {"coordinates":[-87.679851,41.959614],"type":"Point"}
}