{
  "type": "Feature",
  "properties": {
    "addr:full":"375 E Cherry St Hoyleton IL 62803",
    "addr:housenumber":"375",
    "addr:postcode":"62803",
    "addr:street":"E Cherry St",
    "iso:country":"US",
    "sg:address":"375 E Cherry St",
    "sg:city":"Hoyleton",
    "sg:phone":"+1 618 493 6121",
    "sg:postcode":"62803",
    "sg:province":"IL",
    "sg:tags":[
        "farm",
        "corn"
    ],
    "wof:name":"Rodney Schnitker",
    "wof:placetype":"venue"
},
  "geometry": {"coordinates":[-89.268591,38.444548],"type":"Point"}
}