{
  "type": "Feature",
  "properties": {
    "iso:country":"US",
    "sg:address":"205 W Union St",
    "sg:city":"West Union",
    "sg:classifiers":[
        {
            "category":"Organizations",
            "subcategory":"Religious Organization",
            "type":"Services"
        }
    ],
    "sg:phone":"+1 217 279 3879",
    "sg:postcode":"62477",
    "sg:province":"IL",
    "sg:tags":[
        "church"
    ],
    "wof:name":"West Union Church-Nazarene",
    "wof:placetype":"venue"
},
  "geometry": {"coordinates":[-87.667565,39.215969],"type":"Point"}
}