{
  "type": "Feature",
  "properties": {
    "iso:country":"US",
    "sg:address":"228 Lydia St",
    "sg:city":"Graymont",
    "sg:classifiers":[
        {
            "category":"Education",
            "subcategory":"School",
            "type":"Public Place"
        }
    ],
    "sg:phone":"+1 815 743 5346",
    "sg:postcode":"61743",
    "sg:province":"IL",
    "wof:name":"Graymont Elementary SCHOOL",
    "wof:placetype":"venue"
},
  "geometry": {"coordinates":[-88.77646900000001,40.87866],"type":"Point"}
}