{
  "type": "Feature",
  "properties": {
    "iso:country":"US",
    "sg:address":"2362 Lehman Dr",
    "sg:city":"West Chicago",
    "sg:classifiers":[
        {
            "category":"Professional",
            "subcategory":"Testing Lab",
            "type":"Services"
        },
        {
            "category":"Health Services",
            "subcategory":"Medical Lab",
            "type":"Services"
        }
    ],
    "sg:phone":"+1 630 762 8861",
    "sg:postcode":"60185",
    "sg:province":"IL",
    "sg:tags":[
        "x",
        "laboratory"
    ],
    "wof:name":"Excel Portable X-Ray Service",
    "wof:placetype":"venue"
},
  "geometry": {"coordinates":[-88.25426,41.931751],"type":"Point"}
}