{
  "type": "Feature",
  "properties": {
    "addr:full":"1247 Milwaukee Ave Glenview IL 60025",
    "addr:housenumber":"1247",
    "addr:postcode":"60025",
    "addr:street":"Milwaukee Ave",
    "iso:country":"US",
    "sg:address":"1247 Milwaukee Ave",
    "sg:city":"Glenview",
    "sg:phone":"+1 847 827 3700",
    "sg:postcode":"60025",
    "sg:province":"IL",
    "wof:name":"Jguenti Milena Md",
    "wof:placetype":"venue"
},
  "geometry": {"coordinates":[-87.86084700000001,42.077677],"type":"Point"}
}