{
  "type": "Feature",
  "properties": {
    "addr:full":"31 S Prospect Ave Park Ridge IL 60068",
    "addr:housenumber":"31",
    "addr:postcode":"60068",
    "addr:street":"S Prospect Ave",
    "iso:country":"US",
    "sg:address":"31 S Prospect Ave",
    "sg:city":"Park Ridge",
    "sg:classifiers":[
        {
            "category":"Food & Beverages",
            "subcategory":"Candy",
            "type":"Retail Goods"
        }
    ],
    "sg:phone":"+1 847 635 0006",
    "sg:postcode":"60068",
    "sg:province":"IL",
    "sg:tags":[
        "confectionery"
    ],
    "wof:name":"Fannie May Confections Inc",
    "wof:placetype":"venue"
},
  "geometry": {"coordinates":[-87.83013699999999,42.010198],"type":"Point"}
}