{
  "type": "Feature",
  "properties": {
    "iso:country":"US",
    "sg:address":"1444 Hazel Ave",
    "sg:city":"Deerfield",
    "sg:classifiers":[
        {
            "category":"Building & Trades",
            "subcategory":"Cleaning & Sanitation",
            "type":"Services"
        }
    ],
    "sg:phone":"+1 847 267 9847",
    "sg:postcode":"60015",
    "sg:province":"IL",
    "sg:tags":[
        "maintenance"
    ],
    "wof:name":"Monica Cleaning Systems",
    "wof:placetype":"venue"
},
  "geometry": {"coordinates":[-87.863485,42.171034],"type":"Point"}
}