{
  "type": "Feature",
  "properties": {
    "addr:full":"519 N Main St Carrollton IL 62016",
    "addr:housenumber":"519",
    "addr:postcode":"62016",
    "addr:street":"N Main St",
    "iso:country":"US",
    "sg:address":"519 N Main St",
    "sg:city":"Carrollton",
    "sg:classifiers":[
        {
            "category":"Government",
            "subcategory":"Office",
            "type":"Public Place"
        }
    ],
    "sg:phone":"+1 217 942 5443",
    "sg:postcode":"62016",
    "sg:province":"IL",
    "sg:tags":[
        "county"
    ],
    "wof:name":"Greene County Circuit Clerk",
    "wof:placetype":"venue"
},
  "geometry": {"coordinates":[-90.40811600000001,39.302068],"type":"Point"}
}