{
  "type": "Feature",
  "properties": {
    "addr:full":"421 S County Farm Rd Wheaton IL 60187",
    "addr:housenumber":"421",
    "addr:postcode":"60187",
    "addr:street":"S County Farm Rd",
    "iso:country":"US",
    "sg:address":"421 S County Farm Rd",
    "sg:city":"Wheaton",
    "sg:classifiers":[
        {
            "category":"Government",
            "subcategory":"Office",
            "type":"Public Place"
        }
    ],
    "sg:phone":"+1   ",
    "sg:postcode":"60187",
    "sg:province":"IL",
    "sg:tags":[
        "policy"
    ],
    "wof:name":"Finance Department",
    "wof:placetype":"venue"
},
  "geometry": {"coordinates":[-88.14251,41.85985],"type":"Point"}
}