{
  "type": "Feature",
  "properties": {
    "addr:full":"7410 Duvan Dr Tinley Park IL 60477",
    "addr:housenumber":"7410",
    "addr:postcode":"60477",
    "addr:street":"Duvan Dr",
    "iso:country":"US",
    "sg:address":"7410 Duvan Dr",
    "sg:city":"Tinley Park",
    "sg:classifiers":[
        {
            "category":"Building & Trades",
            "subcategory":"Plumbing",
            "type":"Services"
        }
    ],
    "sg:phone":"+1 708 429 7700",
    "sg:postcode":"60477",
    "sg:province":"IL",
    "sg:tags":[
        "sheet",
        "metal",
        "heating",
        "air",
        "ventilation",
        "warm",
        "refrigeration"
    ],
    "wof:name":"Roberts Environmental Control",
    "wof:placetype":"venue"
},
  "geometry": {"coordinates":[-87.79893300000001,41.570585],"type":"Point"}
}