{
  "type": "Feature",
  "properties": {
    "iso:country":"US",
    "sg:address":"10605 Lincoln Trl",
    "sg:city":"Fairview Heights",
    "sg:classifiers":[
        {
            "category":"Personal",
            "subcategory":"Beauty Salon",
            "type":"Services"
        }
    ],
    "sg:phone":"+1 618 394 8760",
    "sg:postcode":"62208",
    "sg:province":"IL",
    "wof:name":"Nett's Hair Gallery",
    "wof:placetype":"venue"
},
  "geometry": {"coordinates":[-89.994309,38.59296],"type":"Point"}
}