{
  "type": "Feature",
  "properties": {
    "iso:country":"US",
    "sg:address":"7177 N Lincoln Ave",
    "sg:city":"Lincolnwood",
    "sg:classifiers":[
        {
            "category":"Health Services",
            "subcategory":"Doctor",
            "type":"Services"
        },
        {
            "category":"Community Center",
            "subcategory":"Senior",
            "type":"Public Place"
        },
        {
            "category":"Social Services",
            "subcategory":"Adult Care",
            "type":"Services"
        }
    ],
    "sg:phone":"+1 847 674 1888",
    "sg:postcode":"60712",
    "sg:province":"IL",
    "sg:tags":[
        "counseling",
        "physician",
        "surgeon",
        "citizen"
    ],
    "wof:name":"Omega Community Healthcare Organization",
    "wof:placetype":"venue"
},
  "geometry": {"coordinates":[-87.738207,42.010924],"type":"Point"}
}