{
  "type": "Feature",
  "properties": {
    "iso:country":"US",
    "sg:address":"123 S Vine St",
    "sg:city":"Arthur",
    "sg:classifiers":[
        {
            "category":"Shopping",
            "subcategory":"Clothing, Apparel, & Fashions",
            "type":"Retail Goods"
        }
    ],
    "sg:phone":"+1   ",
    "sg:postcode":"61928",
    "sg:province":"IL",
    "sg:tags":[
        "wear"
    ],
    "wof:name":"Delberts Big & Tall",
    "wof:placetype":"venue"
},
  "geometry": {"coordinates":[-88.472515,39.716694],"type":"Point"}
}