{
  "type": "Feature",
  "properties": {
    "iso:country":"US",
    "sg:address":"7 N Belleville St",
    "sg:city":"Freeburg",
    "sg:classifiers":[
        {
            "category":"Organizations",
            "subcategory":"Religious Organization",
            "type":"Services"
        }
    ],
    "sg:phone":"+1 618 539 3262",
    "sg:postcode":"62243",
    "sg:province":"IL",
    "sg:tags":[
        "church"
    ],
    "sg:website":"www.stpaulsfreeburg.org",
    "wof:name":"St Paul's United Church",
    "wof:placetype":"venue"
},
  "geometry": {"coordinates":[-89.911184,38.427388],"type":"Point"}
}