{
  "type": "Feature",
  "properties": {
    "iso:country":"US",
    "sg:address":"400 S 9th St",
    "sg:city":"Springfield",
    "sg:classifiers":[
        {
            "category":"Building & Trades",
            "subcategory":"Cleaning & Sanitation",
            "type":"Services"
        }
    ],
    "sg:phone":"+1 217 528 3674",
    "sg:postcode":"62701",
    "sg:province":"IL",
    "sg:tags":[
        "broom"
    ],
    "sg:website":"http://www.heplerbroom.com",
    "wof:name":"Hepler Broom",
    "wof:placetype":"venue"
},
  "geometry": {"coordinates":[-89.643646,39.79826],"type":"Point"}
}