{
  "type": "Feature",
  "properties": {
    "iso:country":"US",
    "sg:address":"2258 W Grand Ave",
    "sg:city":"Chicago",
    "sg:classifiers":[
        {
            "category":"Sports & Exercise",
            "subcategory":"Playing Field",
            "type":"Entertainment"
        }
    ],
    "sg:phone":"+1 312 405 4219",
    "sg:postcode":"60612",
    "sg:province":"IL",
    "sg:tags":[
        "instruction",
        "fitness"
    ],
    "wof:name":"Xuntas",
    "wof:placetype":"venue"
},
  "geometry": {"coordinates":[-87.68410799999999,41.890944],"type":"Point"}
}