{
  "type": "Feature",
  "properties": {
    "addr:full":"209 el Cerrito Dr Belleville IL 62221",
    "addr:housenumber":"209",
    "addr:postcode":"62221",
    "addr:street":"El Cerrito Dr",
    "iso:country":"US",
    "sg:address":"209 el Cerrito Dr",
    "sg:city":"Belleville",
    "sg:classifiers":[
        {
            "category":"Government",
            "subcategory":"Office",
            "type":"Public Place"
        }
    ],
    "sg:phone":"+1 618 277 3052",
    "sg:postcode":"62221",
    "sg:province":"IL",
    "sg:tags":[
        "village"
    ],
    "wof:name":"St Clair Twp Street Lighting",
    "wof:placetype":"venue"
},
  "geometry": {"coordinates":[-89.947664,38.537565],"type":"Point"}
}