{
  "type": "Feature",
  "properties": {
    "iso:country":"US",
    "sg:address":"325 Co Rd 300 N",
    "sg:city":"Sadorus",
    "sg:phone":"+1 217 598 2280",
    "sg:postcode":"61872",
    "sg:province":"IL",
    "sg:tags":[
        "farm",
        "corn",
        "soybean"
    ],
    "wof:name":"Bob Stierwalt",
    "wof:placetype":"venue"
},
  "geometry": {"coordinates":[-88.391575,39.923289],"type":"Point"}
}