{
  "type": "Feature",
  "properties": {
    "iso:country":"US",
    "sg:address":"7301 Duvan Dr",
    "sg:city":"Tinley Park",
    "sg:classifiers":[
        {
            "category":"Shopping",
            "type":"Retail Goods"
        }
    ],
    "sg:phone":"+1 708 560 0023",
    "sg:postcode":"60477",
    "sg:province":"IL",
    "sg:tags":[
        "water",
        "heater"
    ],
    "wof:name":"G R Stob Plumbing Svc",
    "wof:placetype":"venue"
},
  "geometry": {"coordinates":[-87.79518,41.571535],"type":"Point"}
}