{
  "type": "Feature",
  "properties": {
    "iso:country":"US",
    "sg:address":"712 4th Ave",
    "sg:city":"Rock Falls",
    "sg:classifiers":[
        {
            "category":"Organizations",
            "subcategory":"Community Association",
            "type":"Services"
        }
    ],
    "sg:phone":"+1 815 626 3862",
    "sg:postcode":"61071",
    "sg:province":"IL",
    "sg:tags":[
        "military"
    ],
    "wof:name":"American Legion",
    "wof:placetype":"venue"
},
  "geometry": {"coordinates":[-89.690387,41.775344],"type":"Point"}
}