{
  "type": "Feature",
  "properties": {
    "iso:country":"US",
    "sg:address":"1703 18th Ave",
    "sg:city":"East Moline",
    "sg:classifiers":[
        {
            "category":"Retail",
            "subcategory":"Auto Repair",
            "type":"Services"
        }
    ],
    "sg:phone":"+1   ",
    "sg:postcode":"61244",
    "sg:province":"IL",
    "sg:tags":[
        "station",
        "gasoline",
        "general"
    ],
    "wof:name":"Bills Service Center",
    "wof:placetype":"venue"
},
  "geometry": {"coordinates":[-90.42722999999999,41.515424],"type":"Point"}
}