{
  "type": "Feature",
  "properties": {
    "iso:country":"US",
    "sg:address":"4605 S State St",
    "sg:city":"Chicago",
    "sg:classifiers":[
        {
            "category":"Food & Beverages",
            "subcategory":"Meat & Fish",
            "type":"Retail Goods"
        }
    ],
    "sg:phone":"+1 773 538 1112",
    "sg:postcode":"60609",
    "sg:province":"IL",
    "sg:tags":[
        "shop",
        "sausage",
        "market"
    ],
    "wof:name":"Parker House Sausage Co",
    "wof:placetype":"venue"
},
  "geometry": {"coordinates":[-87.6259,41.810101],"type":"Point"}
}