{
  "type": "Feature",
  "properties": {
    "addr:full":"944 N Farnsworth Ave Aurora IL 60505",
    "addr:housenumber":"944",
    "addr:postcode":"60505",
    "addr:street":"N Farnsworth Ave",
    "iso:country":"US",
    "sg:address":"944 N Farnsworth Ave",
    "sg:city":"Aurora",
    "sg:classifiers":[
        {
            "category":"Restaurant",
            "type":"Food & Drink"
        }
    ],
    "sg:menulink":"http://www.allmenus.com/il/aurora/221495-taqueria-los-comales/menu/",
    "sg:phone":"+1 630 820 6988",
    "sg:postcode":"60505",
    "sg:province":"IL",
    "sg:tags":[
        "mexican"
    ],
    "wof:name":"Taqueria Los Comales",
    "wof:placetype":"venue"
},
  "geometry": {"coordinates":[-88.281727,41.776749],"type":"Point"}
}