{
  "type": "Feature",
  "properties": {
    "iso:country":"US",
    "sg:address":"7400 W Foster Ave",
    "sg:city":"Chicago",
    "sg:classifiers":[
        {
            "category":"Education",
            "subcategory":"Preschool",
            "type":"Public Place"
        },
        {
            "category":"Education",
            "subcategory":"School",
            "type":"Public Place"
        }
    ],
    "sg:phone":"+1 773 775 4207",
    "sg:postcode":"60656",
    "sg:province":"IL",
    "sg:tags":[
        "elementary"
    ],
    "wof:name":"Oriole Park Pre-K",
    "wof:placetype":"venue"
},
  "geometry": {"coordinates":[-87.812016,41.974517],"type":"Point"}
}