{
  "type": "Feature",
  "properties": {
    "iso:country":"US",
    "sg:address":"1334 Loretta Ave",
    "sg:city":"Joliet",
    "sg:classifiers":[
        {
            "category":"Retail",
            "subcategory":"Repair Shop",
            "type":"Services"
        },
        {
            "category":"Building & Trades",
            "subcategory":"Plumbing",
            "type":"Services"
        }
    ],
    "sg:phone":"+1 815 722 8806",
    "sg:postcode":"60436",
    "sg:province":"IL",
    "sg:tags":[
        "septic"
    ],
    "wof:name":"Kimble Septic Service & Repair",
    "wof:placetype":"venue"
},
  "geometry": {"coordinates":[-88.096407,41.496452],"type":"Point"}
}