{
  "type": "Feature",
  "properties": {
    "iso:country":"US",
    "sg:address":"7839 Nevois Ln",
    "sg:city":"East Carondelet",
    "sg:classifiers":[
        {
            "category":"Retail",
            "subcategory":"Auto Repair",
            "type":"Services"
        }
    ],
    "sg:phone":"+1 618 286 4777",
    "sg:postcode":"62240",
    "sg:province":"IL",
    "sg:tags":[
        "exchanging",
        "engine"
    ],
    "wof:name":"Diesel Services",
    "wof:placetype":"venue"
},
  "geometry": {"coordinates":[-90.18732,38.507905],"type":"Point"}
}