{
  "type": "Feature",
  "properties": {
    "addr:full":"19065 Hickory Creek Dr Mokena IL 60448",
    "addr:housenumber":"19065",
    "addr:postcode":"60448",
    "addr:street":"Hickory Creek Dr",
    "iso:country":"US",
    "sg:address":"19065 Hickory Creek Dr",
    "sg:city":"Mokena",
    "sg:classifiers":[
        {
            "category":"Health Services",
            "subcategory":"Clinic",
            "type":"Services"
        }
    ],
    "sg:phone":"+1 708 478 5304",
    "sg:postcode":"60448",
    "sg:province":"IL",
    "sg:tags":[
        "care"
    ],
    "wof:name":"Advanced Ancillary Services",
    "wof:placetype":"venue"
},
  "geometry": {"coordinates":[-87.84290300000001,41.545585],"type":"Point"}
}