{
  "type": "Feature",
  "properties": {
    "iso:country":"US",
    "sg:address":"1038 Lake St",
    "sg:city":"Oak Park",
    "sg:classifiers":[
        {
            "category":"Shopping",
            "subcategory":"Clothing, Apparel, & Fashions",
            "type":"Retail Goods"
        },
        {
            "category":"Shopping",
            "subcategory":"Party Supplies",
            "type":"Retail Goods"
        }
    ],
    "sg:phone":"+1 708 383 5962",
    "sg:postcode":"60301",
    "sg:province":"IL",
    "sg:tags":[
        "costume"
    ],
    "wof:name":"Razzle-Dazzle Costumes",
    "wof:placetype":"venue"
},
  "geometry": {"coordinates":[-87.79949999999999,41.888699],"type":"Point"}
}