{
  "type": "Feature",
  "properties": {
    "iso:country":"US",
    "sg:address":"311 E Main St",
    "sg:city":"Galesburg",
    "sg:phone":"+1 309 343 2396",
    "sg:postcode":"61401",
    "sg:province":"IL",
    "wof:name":"Consultants",
    "wof:placetype":"venue"
},
  "geometry": {"coordinates":[-90.366113,40.94745],"type":"Point"}
}