{
  "type": "Feature",
  "properties": {
    "iso:country":"US",
    "sg:address":"2809 N Ashland Ave",
    "sg:city":"Chicago",
    "sg:classifiers":[
        {
            "category":"Restaurant",
            "type":"Food & Drink"
        }
    ],
    "sg:phone":"+1 773 549 2484",
    "sg:postcode":"60657",
    "sg:province":"IL",
    "wof:name":"Subway Sandwich Shop",
    "wof:placetype":"venue"
},
  "geometry": {"coordinates":[-87.668503,41.933102],"type":"Point"}
}