{
  "type": "Feature",
  "properties": {
    "iso:country":"US",
    "sg:address":"2400 SE 3rd St",
    "sg:city":"Aledo",
    "sg:classifiers":[
        {
            "category":"Wholesale",
            "subcategory":"Machinery & Supplies",
            "type":"Manufacturing & Wholesale Goods"
        }
    ],
    "sg:phone":"+1 309 582 3676",
    "sg:postcode":"61231",
    "sg:province":"IL",
    "sg:tags":[
        "farm",
        "equipment"
    ],
    "wof:name":"Kleine Equipment",
    "wof:placetype":"venue"
},
  "geometry": {"coordinates":[-90.720615,41.19938],"type":"Point"}
}