{
  "type": "Feature",
  "properties": {
    "addr:full":"1435 N Randall Rd Suite 309 Elgin IL 60123",
    "addr:housenumber":"1435",
    "addr:postcode":"60123",
    "addr:street":"N Randall Rd Suite 309",
    "iso:country":"US",
    "sg:address":"1435 N Randall Rd Suite 309",
    "sg:city":"Elgin",
    "sg:classifiers":[
        {
            "category":"Health Services",
            "subcategory":"Doctor",
            "type":"Services"
        },
        {
            "category":"Personal",
            "subcategory":"Adult",
            "type":"Services"
        }
    ],
    "sg:phone":"+1 847 741 7990",
    "sg:postcode":"60123",
    "sg:province":"IL",
    "sg:tags":[
        "obstetrician",
        "midwife",
        "gynecologist"
    ],
    "sg:website":"fvwh.com",
    "wof:name":"Fox Valley Women's Healthcare Sc",
    "wof:placetype":"venue"
},
  "geometry": {"coordinates":[-88.335544,42.064834],"type":"Point"}
}