{
  "type": "Feature",
  "properties": {
    "addr:full":"5412 N Clark St Chicago IL 60640",
    "addr:housenumber":"5412",
    "addr:postcode":"60640",
    "addr:street":"N Clark St",
    "iso:country":"US",
    "sg:address":"5412 N Clark St",
    "sg:city":"Chicago",
    "sg:classifiers":[
        {
            "category":"Personal",
            "subcategory":"Massage",
            "type":"Services"
        }
    ],
    "sg:phone":"+1 773 213 9398",
    "sg:postcode":"60640",
    "sg:province":"IL",
    "sg:website":"www.shungobodywork.com",
    "wof:name":"Shungo - Bodywork for Women's Health",
    "wof:placetype":"venue"
},
  "geometry": {"coordinates":[-87.668351,41.980545],"type":"Point"}
}