{
  "type": "Feature",
  "properties": {
    "addr:full":"4924 S Indiana Ave Chicago IL 60615",
    "addr:housenumber":"4924",
    "addr:postcode":"60615",
    "addr:street":"S Indiana Ave",
    "iso:country":"US",
    "sg:address":"4924 S Indiana Ave",
    "sg:city":"Chicago",
    "sg:classifiers":[
        {
            "category":"Real Estate",
            "subcategory":"Architect",
            "type":"Services"
        }
    ],
    "sg:phone":"+1 773 536 5256",
    "sg:postcode":"60615",
    "sg:province":"IL",
    "wof:name":"Twin Arch Inc",
    "wof:placetype":"venue"
},
  "geometry": {"coordinates":[-87.621263,41.805162],"type":"Point"}
}