{
  "type": "Feature",
  "properties": {
    "iso:country":"US",
    "sg:address":"2700 S Belt W",
    "sg:city":"Belleville",
    "sg:classifiers":[
        {
            "category":"Home & Garden",
            "subcategory":"Building Materials",
            "type":"Retail Goods"
        },
        {
            "category":"Building & Trades",
            "subcategory":"Construction",
            "type":"Services"
        }
    ],
    "sg:phone":"+1 618 233 7286",
    "sg:postcode":"62226",
    "sg:province":"IL",
    "sg:tags":[
        "excavation",
        "concrete",
        "plastering",
        "contractor"
    ],
    "wof:name":"Fournie Contracting Co Inc",
    "wof:placetype":"venue"
},
  "geometry": {"coordinates":[-90.017915,38.524042],"type":"Point"}
}