{
  "type": "Feature",
  "properties": {
    "addr:full":"1062 N Milwaukee Ave Chicago IL 60642",
    "addr:housenumber":"1062",
    "addr:postcode":"60642",
    "addr:street":"N Milwaukee Ave",
    "iso:country":"US",
    "sg:address":"1062 N Milwaukee Ave",
    "sg:city":"Chicago",
    "sg:phone":"+1 773 342 4444",
    "sg:postcode":"60642",
    "sg:province":"IL",
    "wof:name":"Insight Studios",
    "wof:placetype":"venue"
},
  "geometry": {"coordinates":[-87.66291,41.901051],"type":"Point"}
}