{
  "type": "Feature",
  "properties": {
    "addr:full":"535 Tollgate Rd Elgin IL 60123",
    "addr:housenumber":"535",
    "addr:postcode":"60123",
    "addr:street":"Tollgate Rd",
    "iso:country":"US",
    "sg:address":"535 Tollgate Rd",
    "sg:city":"Elgin",
    "sg:classifiers":[
        {
            "category":"Banks & Credit Unions",
            "subcategory":"Bank",
            "type":"Services"
        }
    ],
    "sg:phone":"+1 847 608 0707",
    "sg:postcode":"60123",
    "sg:province":"IL",
    "sg:tags":[
        "loan",
        "mortgage",
        "real estate"
    ],
    "wof:name":"Anchor Mortgage Corporation",
    "wof:placetype":"venue"
},
  "geometry": {"coordinates":[-88.29085600000001,42.072395],"type":"Point"}
}