{
  "type": "Feature",
  "properties": {
    "iso:country":"US",
    "sg:address":"1225 E Forest Ave",
    "sg:city":"Des Plaines",
    "sg:classifiers":[
        {
            "category":"Manufacturing",
            "subcategory":"Tools & Machinery",
            "type":"Manufacturing & Wholesale Goods"
        }
    ],
    "sg:phone":"+1 847 297 1790",
    "sg:postcode":"60018",
    "sg:province":"IL",
    "sg:tags":[
        "packaging",
        "machine",
        "mfg"
    ],
    "wof:name":"H L Fisher Manufacturing Co",
    "wof:placetype":"venue"
},
  "geometry": {"coordinates":[-87.893595,42.027552],"type":"Point"}
}