{
  "type": "Feature",
  "properties": {
    "addr:full":"982 Co Rd 2550 N Champaign IL 61822",
    "addr:housenumber":"982",
    "addr:postcode":"61822",
    "addr:street":"Co Rd 2550 N",
    "iso:country":"US",
    "sg:address":"982 Co Rd 2550 N",
    "sg:city":"Champaign",
    "sg:classifiers":[
        {
            "category":"Retail",
            "subcategory":"Auto Repair",
            "type":"Services"
        }
    ],
    "sg:phone":"+1 217 643 2000",
    "sg:postcode":"61822",
    "sg:province":"IL",
    "sg:tags":[
        "repairing",
        "automobile",
        "general"
    ],
    "wof:name":"Frazier's Inc",
    "wof:placetype":"venue"
},
  "geometry": {"coordinates":[-88.27047399999999,40.245659],"type":"Point"}
}