{
  "type": "Feature",
  "properties": {
    "iso:country":"US",
    "sg:address":"3469 N Clark St",
    "sg:city":"Chicago",
    "sg:classifiers":[
        {
            "category":"Restaurant",
            "type":"Food & Drink"
        }
    ],
    "sg:phone":"+1 773 248 2677",
    "sg:postcode":"60657",
    "sg:province":"IL",
    "sg:tags":[
        "style",
        "bar",
        "family",
        "sushi",
        "japanese",
        "asian",
        "pan"
    ],
    "wof:name":"Matsuya Japanese Restaurant",
    "wof:placetype":"venue"
},
  "geometry": {"coordinates":[-87.654895,41.945318],"type":"Point"}
}