{
  "type": "Feature",
  "properties": {
    "addr:full":"418 Washington St Quincy IL 62301",
    "addr:housenumber":"418",
    "addr:postcode":"62301",
    "addr:street":"Washington St",
    "iso:country":"US",
    "sg:address":"418 Washington St",
    "sg:city":"Quincy",
    "sg:classifiers":[
        {
            "category":"Health Services",
            "subcategory":"Nursing And Care Facility",
            "type":"Services"
        }
    ],
    "sg:phone":"+1 217 223 2636",
    "sg:postcode":"62301",
    "sg:province":"IL",
    "sg:tags":[
        "home",
        "skilled",
        "convalescent"
    ],
    "sg:website":"http://www.sunsethome.org",
    "wof:name":"Sunset Home",
    "wof:placetype":"venue"
},
  "geometry": {"coordinates":[-91.40924699999999,39.922646],"type":"Point"}
}