{
  "type": "Feature",
  "properties": {
    "addr:full":"1751 S Galena Ave Freeport IL 61032",
    "addr:housenumber":"1751",
    "addr:postcode":"61032",
    "addr:street":"S Galena Ave",
    "iso:country":"US",
    "sg:address":"1751 S Galena Ave",
    "sg:city":"Freeport",
    "sg:classifiers":[
        {
            "category":"Building & Trades",
            "subcategory":"Landscaping Services",
            "type":"Services"
        }
    ],
    "sg:phone":"+1 815 232 0079",
    "sg:postcode":"61032",
    "sg:province":"IL",
    "sg:tags":[
        "lawn",
        "maintenance",
        "grounds"
    ],
    "wof:name":"Bill The Yard Barber",
    "wof:placetype":"venue"
},
  "geometry": {"coordinates":[-89.59851500000001,42.280819],"type":"Point"}
}