{
  "type": "Feature",
  "properties": {
    "iso:country":"US",
    "sg:address":"13126 Saunders Rd",
    "sg:city":"Pecatonica",
    "sg:classifiers":[
        {
            "category":"Building & Trades",
            "subcategory":"Construction",
            "type":"Services"
        }
    ],
    "sg:phone":"+1 815 335 2645",
    "sg:postcode":"61063",
    "sg:province":"IL",
    "sg:tags":[
        "utility",
        "contractor"
    ],
    "wof:name":"Westlake Utilities Inc",
    "wof:placetype":"venue"
},
  "geometry": {"coordinates":[-89.293126,42.318454],"type":"Point"}
}