{
  "type": "Feature",
  "properties": {
    "iso:country":"US",
    "sg:address":"715 S Bloomington St",
    "sg:city":"Streator",
    "sg:classifiers":[
        {
            "category":"Food & Beverages",
            "subcategory":"Bakery",
            "type":"Retail Goods"
        },
        {
            "category":"Bakery",
            "type":"Food & Drink"
        }
    ],
    "sg:phone":"+1 815 672 0442",
    "sg:postcode":"61364",
    "sg:province":"IL",
    "sg:tags":[
        "bakers-wholesale"
    ],
    "sg:website":"http://www.interstatebakeriescorp.com",
    "wof:name":"Butternut Bread",
    "wof:placetype":"venue"
},
  "geometry": {"coordinates":[-88.835438,41.112672],"type":"Point"}
}