{
  "type": "Feature",
  "properties": {
    "iso:country":"US",
    "sg:address":"936 Moen Ave",
    "sg:city":"Rockdale",
    "sg:classifiers":[
        {
            "category":"Wholesale",
            "subcategory":"Non-durable Goods",
            "type":"Manufacturing & Wholesale Goods"
        }
    ],
    "sg:phone":"+1 815 730 7602",
    "sg:postcode":"60436",
    "sg:province":"IL",
    "sg:tags":[
        "candle"
    ],
    "wof:name":"Dakar USA Corp",
    "wof:placetype":"venue"
},
  "geometry": {"coordinates":[-88.120915,41.504896],"type":"Point"}
}