{
  "type": "Feature",
  "properties": {
    "iso:country":"US",
    "sg:address":"350 W Erie St 1st Fl",
    "sg:city":"Chicago",
    "sg:classifiers":[
        {
            "category":"Home & Garden",
            "subcategory":"Home Furnishings",
            "type":"Retail Goods"
        },
        {
            "category":"Building & Trades",
            "subcategory":"Construction",
            "type":"Services"
        }
    ],
    "sg:phone":"+1 312 587 8150",
    "sg:postcode":"60654",
    "sg:province":"IL",
    "sg:tags":[
        "interior",
        "decor",
        "design"
    ],
    "sg:website":"www.susanfredman.com",
    "wof:name":"Susan Fredman At Home In the City",
    "wof:placetype":"venue"
},
  "geometry": {"coordinates":[-87.637722,41.89419],"type":"Point"}
}