{
  "type": "Feature",
  "properties": {
    "iso:country":"US",
    "sg:address":"1760 5th St",
    "sg:city":"Lincoln",
    "sg:classifiers":[
        {
            "category":"Retail",
            "subcategory":"Auto Repair",
            "type":"Services"
        }
    ],
    "sg:phone":"+1 217 735 3868",
    "sg:postcode":"62656",
    "sg:province":"IL",
    "sg:tags":[
        "truck"
    ],
    "wof:name":"T-N-T Truck & Trailer Svc",
    "wof:placetype":"venue"
},
  "geometry": {"coordinates":[-89.387569,40.146936],"type":"Point"}
}