{
  "type": "Feature",
  "properties": {
    "iso:country":"US",
    "sg:address":"3535 S Cottage Grove Avenue",
    "sg:city":"Chicago",
    "sg:classifiers":[
        {
            "category":"Real Estate",
            "subcategory":"Real Estate Services",
            "type":"Services"
        }
    ],
    "sg:phone":"+1 773 373 2178",
    "sg:postcode":"60653",
    "sg:province":"IL",
    "sg:tags":[
        "management",
        "property"
    ],
    "wof:name":"Lake Grove Village",
    "wof:placetype":"venue"
},
  "geometry": {"coordinates":[-87.610249,41.830517],"type":"Point"}
}