{
  "type": "Feature",
  "properties": {
    "addr:full":"7550 Janes Ave Woodridge IL 60517",
    "addr:housenumber":"7550",
    "addr:postcode":"60517",
    "addr:street":"Janes Ave",
    "iso:country":"US",
    "sg:address":"7550 Janes Ave",
    "sg:city":"Woodridge",
    "sg:classifiers":[
        {
            "category":"Building & Trades",
            "subcategory":"Construction",
            "type":"Services"
        }
    ],
    "sg:phone":"+1 630 985 3300",
    "sg:postcode":"60517",
    "sg:province":"IL",
    "sg:tags":[
        "house",
        "subdivide",
        "nonresidential"
    ],
    "wof:name":"Surety Builders Inc",
    "wof:placetype":"venue"
},
  "geometry": {"coordinates":[-88.04075400000001,41.749032],"type":"Point"}
}