{
  "type": "Feature",
  "properties": {
    "iso:country":"US",
    "sg:address":"939 W Grace St",
    "sg:city":"Chicago",
    "sg:classifiers":[
        {
            "category":"Professional",
            "subcategory":"Lawyer & Legal Services",
            "type":"Services"
        }
    ],
    "sg:phone":"+1 773 348 5375",
    "sg:postcode":"60613",
    "sg:province":"IL",
    "sg:tags":[
        "attorney",
        "federal",
        "practice",
        "governmental",
        "law",
        "administrative"
    ],
    "wof:name":"Edelstein, Simon",
    "wof:placetype":"venue"
},
  "geometry": {"coordinates":[-87.65349399999999,41.951104],"type":"Point"}
}