{
  "type": "Feature",
  "properties": {
    "iso:country":"US",
    "sg:address":"600 W Fulton Street Fl 2",
    "sg:city":"Chicago",
    "sg:classifiers":[
        {
            "category":"Shopping",
            "subcategory":"Stationery & Office Supplies",
            "type":"Retail Goods"
        }
    ],
    "sg:phone":"+1 312 334 3375",
    "sg:postcode":"60661",
    "sg:province":"IL",
    "sg:tags":[
        "equipment"
    ],
    "wof:name":"Desks",
    "wof:placetype":"venue"
},
  "geometry": {"coordinates":[-87.642816,41.88694],"type":"Point"}
}