{
  "type": "Feature",
  "properties": {
    "iso:country":"US",
    "sg:address":"2369 Malmaison Rd",
    "sg:city":"Belvidere",
    "sg:classifiers":[
        {
            "category":"Shopping",
            "subcategory":"Shoes",
            "type":"Retail Goods"
        }
    ],
    "sg:phone":"+1   ",
    "sg:postcode":"61008",
    "sg:province":"IL",
    "wof:name":"AR Orbison Inc",
    "wof:placetype":"venue"
},
  "geometry": {"coordinates":[-88.888763,42.313178],"type":"Point"}
}