{
  "type": "Feature",
  "properties": {
    "addr:full":"1305 S Michigan Ave Ste 1204 Chicago IL 60605",
    "addr:housenumber":"1305",
    "addr:postcode":"60605",
    "addr:street":"S Michigan Ave Ste 1204",
    "iso:country":"US",
    "sg:address":"1305 S Michigan Ave Ste 1204",
    "sg:city":"Chicago",
    "sg:classifiers":[
        {
            "category":"Shopping",
            "subcategory":"Clothing, Apparel, & Fashions",
            "type":"Retail Goods"
        }
    ],
    "sg:phone":"+1 800 511 8707",
    "sg:postcode":"60605",
    "sg:province":"IL",
    "sg:tags":[
        "men's",
        "clothing",
        "women's"
    ],
    "wof:name":"Lead Apparel",
    "wof:placetype":"venue"
},
  "geometry": {"coordinates":[-87.623783,41.86542],"type":"Point"}
}