{
  "type": "Feature",
  "properties": {
    "addr:full":"10 W 3rd St Sterling IL 61081",
    "addr:housenumber":"10",
    "addr:postcode":"61081",
    "addr:street":"W 3Rd St",
    "iso:country":"US",
    "sg:address":"10 W 3rd St",
    "sg:city":"Sterling",
    "sg:classifiers":[
        {
            "category":"Health Services",
            "subcategory":"Doctor",
            "type":"Services"
        },
        {
            "category":"Health Services",
            "subcategory":"Dentist",
            "type":"Services"
        }
    ],
    "sg:phone":"+1 815 632 5300",
    "sg:postcode":"61081",
    "sg:province":"IL",
    "sg:tags":[
        "dentists-oral",
        "physician",
        "maxillofacial",
        "surgeons",
        "surgery",
        "oral"
    ],
    "sg:website":"http://www.srfc.com",
    "wof:name":"Whittaker Robert A DMD MD",
    "wof:placetype":"venue"
},
  "geometry": {"coordinates":[-89.696186,41.787924],"type":"Point"}
}