{
  "type": "Feature",
  "properties": {
    "iso:country":"US",
    "sg:address":"1901 Flintshire Dr",
    "sg:city":"Schaumburg",
    "sg:classifiers":[
        {
            "category":"Personal",
            "type":"Services"
        }
    ],
    "sg:phone":"+1 847 324 3333",
    "sg:postcode":"60194",
    "sg:province":"IL",
    "sg:tags":[
        "electrolysis"
    ],
    "wof:name":"Electrology Assoc Of Illinois",
    "wof:placetype":"venue"
},
  "geometry": {"coordinates":[-88.126721,42.041185],"type":"Point"}
}