{
  "type": "Feature",
  "properties": {
    "addr:full":"2214 N 31st Rd Marseilles IL 61341",
    "addr:housenumber":"2214",
    "addr:postcode":"61341",
    "addr:street":"N 31St Rd",
    "iso:country":"US",
    "sg:address":"2214 N 31st Rd",
    "sg:city":"Marseilles",
    "sg:classifiers":[
        {
            "category":"Retail",
            "subcategory":"Repair Shop",
            "type":"Services"
        }
    ],
    "sg:phone":"+1 815 434 2590",
    "sg:postcode":"61341",
    "sg:province":"IL",
    "sg:tags":[
        "electrical"
    ],
    "wof:name":"KB Enterprises",
    "wof:placetype":"venue"
},
  "geometry": {"coordinates":[-88.743572,41.383025],"type":"Point"}
}