{
  "type": "Feature",
  "properties": {
    "iso:country":"US",
    "sg:address":"465 N Roselle Rd",
    "sg:city":"Roselle",
    "sg:classifiers":[
        {
            "category":"Health Services",
            "subcategory":"Clinic",
            "type":"Services"
        },
        {
            "category":"Health Services",
            "subcategory":"Health Practitioner",
            "type":"Services"
        },
        {
            "category":"Community Center",
            "type":"Public Place"
        }
    ],
    "sg:phone":"+1 630 893 4546",
    "sg:postcode":"60172",
    "sg:province":"IL",
    "sg:tags":[
        "medical",
        "therapist",
        "therapy",
        "physical"
    ],
    "wof:name":"Northwest Physical Therap",
    "wof:placetype":"venue"
},
  "geometry": {"coordinates":[-88.080243,41.991286],"type":"Point"}
}