{
  "type": "Feature",
  "properties": {
    "addr:full":"2118 Bristol Rd Champaign IL 61821",
    "addr:housenumber":"2118",
    "addr:postcode":"61821",
    "addr:street":"Bristol Rd",
    "iso:country":"US",
    "sg:address":"2118 Bristol Rd",
    "sg:city":"Champaign",
    "sg:classifiers":[
        {
            "category":"Professional",
            "subcategory":"Computer Services",
            "type":"Services"
        }
    ],
    "sg:phone":"+1 217 398 5771",
    "sg:postcode":"61821",
    "sg:province":"IL",
    "sg:tags":[
        "repair"
    ],
    "wof:name":"Computer Physician LLC",
    "wof:placetype":"venue"
},
  "geometry": {"coordinates":[-88.26049999999999,40.087574],"type":"Point"}
}