{
  "type": "Feature",
  "properties": {
    "iso:country":"US",
    "sg:address":"609 E 4th St",
    "sg:city":"Delavan",
    "sg:classifiers":[
        {
            "category":"Restaurant",
            "type":"Food & Drink"
        }
    ],
    "sg:menulink":"http://www.allmenus.com/il/delavan/226237-caseys-general-store/menu/",
    "sg:phone":"+1 309 244 8649",
    "sg:postcode":"61734",
    "sg:province":"IL",
    "sg:tags":[
        "american",
        "pizza"
    ],
    "wof:name":"Casey's General Store",
    "wof:placetype":"venue"
},
  "geometry": {"coordinates":[-89.54044,40.372541],"type":"Point"}
}