{
  "type": "Feature",
  "properties": {
    "iso:country":"US",
    "sg:address":"445 E Ohio Street Suite 400",
    "sg:city":"Chicago",
    "sg:classifiers":[
        {
            "category":"Education",
            "subcategory":"School",
            "type":"Public Place"
        }
    ],
    "sg:phone":"+1 312 645 8300",
    "sg:postcode":"60611",
    "sg:province":"IL",
    "sg:website":"www.wrightleadership.com",
    "wof:name":"The Wright Institute",
    "wof:placetype":"venue"
},
  "geometry": {"coordinates":[-87.616203,41.89263],"type":"Point"}
}