{
  "type": "Feature",
  "properties": {
    "iso:country":"US",
    "sg:address":"5103 Bunkum Rd",
    "sg:city":"East Saint Louis",
    "sg:classifiers":[
        {
            "category":"Education",
            "subcategory":"Library",
            "type":"Public Place"
        }
    ],
    "sg:phone":"+1 618 271 5103",
    "sg:postcode":"62204",
    "sg:province":"IL",
    "wof:name":"Washington Park Public Library",
    "wof:placetype":"venue"
},
  "geometry": {"coordinates":[-90.095221,38.623199],"type":"Point"}
}