{
  "type": "Feature",
  "properties": {
    "addr:full":"15293 W Oak Pond Ln Libertyville IL 60048",
    "addr:housenumber":"15293",
    "addr:postcode":"60048",
    "addr:street":"W Oak Pond Ln",
    "iso:country":"US",
    "sg:address":"15293 W Oak Pond Ln",
    "sg:city":"Libertyville",
    "sg:classifiers":[
        {
            "category":"Professional",
            "subcategory":"Business Services",
            "type":"Services"
        }
    ],
    "sg:phone":"+1 847 680 8031",
    "sg:postcode":"60048",
    "sg:province":"IL",
    "sg:tags":[
        "interior",
        "consultant",
        "design",
        "decorator"
    ],
    "wof:name":"Classic Design Interiors",
    "wof:placetype":"venue"
},
  "geometry": {"coordinates":[-87.930604,42.286726],"type":"Point"}
}