{
  "type": "Feature",
  "properties": {
    "iso:country":"US",
    "sg:address":"2219 Martin Luther King Jr Dr",
    "sg:city":"North Chicago",
    "sg:classifiers":[
        {
            "category":"Retail",
            "subcategory":"Laundry & Dry Cleaning",
            "type":"Services"
        }
    ],
    "sg:phone":"+1 847 688 0036",
    "sg:postcode":"60064",
    "sg:province":"IL",
    "sg:tags":[
        "cleaners"
    ],
    "wof:name":"Hanks Cleaners",
    "wof:placetype":"venue"
},
  "geometry": {"coordinates":[-87.859628,42.319346],"type":"Point"}
}