{
  "type": "Feature",
  "properties": {
    "addr:full":"2200 W Main St Marion IL 62959",
    "addr:housenumber":"2200",
    "addr:postcode":"62959",
    "addr:street":"W Main St",
    "iso:country":"US",
    "sg:address":"2200 W Main St",
    "sg:city":"Marion",
    "sg:classifiers":[
        {
            "category":"Ice Cream",
            "type":"Food & Drink"
        }
    ],
    "sg:menulink":"http://www.allmenus.com/il/west-marion/161880-dairy-queen/menu/",
    "sg:phone":"+1 618 997 5180",
    "sg:postcode":"62959",
    "sg:province":"IL",
    "sg:tags":[
        "burger",
        "american"
    ],
    "wof:name":"Dairy Queen",
    "wof:placetype":"venue"
},
  "geometry": {"coordinates":[-88.95137699999999,37.730626],"type":"Point"}
}