{
  "type": "Feature",
  "properties": {
    "iso:country":"US",
    "sg:address":"707 S 6th St",
    "sg:city":"Champaign",
    "sg:classifiers":[
        {
            "category":"Shopping",
            "subcategory":"Mobile Phones",
            "type":"Retail Goods"
        },
        {
            "category":"Utilities",
            "type":"Services"
        }
    ],
    "sg:phone":"+1 217 384 9300",
    "sg:postcode":"61820",
    "sg:province":"IL",
    "sg:tags":[
        "provider",
        "internet"
    ],
    "sg:website":"www.wirelessmikes.com",
    "wof:name":"Wireless Mike's",
    "wof:placetype":"venue"
},
  "geometry": {"coordinates":[-88.23056800000001,40.110234],"type":"Point"}
}