{
  "type": "Feature",
  "properties": {
    "iso:country":"US",
    "sg:address":"9401 S Cicero Ave",
    "sg:city":"Oak Lawn",
    "sg:classifiers":[
        {
            "category":"Banks & Credit Unions",
            "subcategory":"Bank",
            "type":"Services"
        }
    ],
    "sg:phone":"+1 708 423 0068",
    "sg:postcode":"60453",
    "sg:province":"IL",
    "wof:name":"Charter One Bank",
    "wof:placetype":"venue"
},
  "geometry": {"coordinates":[-87.740898,41.722],"type":"Point"}
}