{
  "type": "Feature",
  "properties": {
    "iso:country":"US",
    "sg:address":"1393 N Milwaukee Ave",
    "sg:city":"Chicago",
    "sg:classifiers":[
        {
            "category":"Bars & Pubs",
            "type":"Food & Drink"
        },
        {
            "category":"Restaurant",
            "type":"Food & Drink"
        }
    ],
    "sg:phone":"+1 773 276 7422",
    "sg:postcode":"60622",
    "sg:province":"IL",
    "sg:tags":[
        "mexican"
    ],
    "sg:website":"www.wolfsdenchicago.com",
    "wof:name":"The Wolf's Den",
    "wof:placetype":"venue"
},
  "geometry": {"coordinates":[-87.672326,41.907293],"type":"Point"}
}