{
  "type": "Feature",
  "properties": {
    "iso:country":"US",
    "sg:address":"711 W North Ave Ste 201",
    "sg:city":"Chicago",
    "sg:classifiers":[
        {
            "category":"Health Services",
            "subcategory":"Doctor",
            "type":"Services"
        }
    ],
    "sg:phone":"+1 312 787 9120",
    "sg:postcode":"60610",
    "sg:province":"IL",
    "sg:tags":[
        "medicine",
        "sport"
    ],
    "wof:name":"Natatajan Balu",
    "wof:placetype":"venue"
},
  "geometry": {"coordinates":[-87.64612700000001,41.910958],"type":"Point"}
}