{
  "type": "Feature",
  "properties": {
    "iso:country":"US",
    "sg:address":"4667 W Washington Blvd",
    "sg:city":"Chicago",
    "sg:classifiers":[
        {
            "category":"Retail",
            "subcategory":"Car Wash",
            "type":"Services"
        }
    ],
    "sg:phone":"+1 773 921 0610",
    "sg:postcode":"60644",
    "sg:province":"IL",
    "wof:name":"L & D Towing",
    "wof:placetype":"venue"
},
  "geometry": {"coordinates":[-87.74181900000001,41.881725],"type":"Point"}
}