{
  "type": "Feature",
  "properties": {
    "addr:full":"600 Spruce Ave Lake Forest IL 60045",
    "addr:housenumber":"600",
    "addr:postcode":"60045",
    "addr:street":"Spruce Ave",
    "iso:country":"US",
    "sg:address":"600 Spruce Ave",
    "sg:city":"Lake Forest",
    "sg:classifiers":[
        {
            "category":"Manufacturing",
            "subcategory":"Textiles",
            "type":"Manufacturing & Wholesale Goods"
        }
    ],
    "sg:phone":"+1 847 482 0927",
    "sg:postcode":"60045",
    "sg:province":"IL",
    "sg:tags":[
        "fabric"
    ],
    "wof:name":"Mc Grath & Marchesci",
    "wof:placetype":"venue"
},
  "geometry": {"coordinates":[-87.833882,42.264996],"type":"Point"}
}