{
  "type": "Feature",
  "properties": {
    "addr:full":"63 N Randall Rd Batavia IL 60510",
    "addr:housenumber":"63",
    "addr:postcode":"60510",
    "addr:street":"N Randall Rd",
    "iso:country":"US",
    "sg:address":"63 N Randall Rd",
    "sg:city":"Batavia",
    "sg:classifiers":[
        {
            "category":"Shopping",
            "type":"Retail Goods"
        }
    ],
    "sg:phone":"+1 630 761 0636",
    "sg:postcode":"60510",
    "sg:province":"IL",
    "sg:tags":[
        "cosmetic",
        "perfume"
    ],
    "wof:name":"Sally Beauty Supply",
    "wof:placetype":"venue"
},
  "geometry": {"coordinates":[-88.340554,41.852787],"type":"Point"}
}