{
  "type": "Feature",
  "properties": {
    "iso:country":"US",
    "sg:address":"5306 Rich Rd",
    "sg:city":"Clare",
    "sg:classifiers":[
        {
            "category":"Building & Trades",
            "subcategory":"Construction",
            "type":"Services"
        }
    ],
    "sg:phone":"+1 815 825 2255",
    "sg:postcode":"60111",
    "sg:province":"IL",
    "sg:tags":[
        "mason",
        "masonry",
        "industrial",
        "contractors-commercial",
        "contractor"
    ],
    "wof:name":"Greg Stephen",
    "wof:placetype":"venue"
},
  "geometry": {"coordinates":[-88.842468,41.972185],"type":"Point"}
}