{
  "type": "Feature",
  "properties": {
    "iso:country":"US",
    "sg:address":"1831 W Devon Ave",
    "sg:city":"Chicago",
    "sg:classifiers":[
        {
            "category":"Restaurant",
            "type":"Food & Drink"
        }
    ],
    "sg:phone":"+1 773 381 2252",
    "sg:postcode":"60660",
    "sg:province":"IL",
    "sg:website":"www.mcdonalds.com",
    "wof:name":"McDonald's",
    "wof:placetype":"venue"
},
  "geometry": {"coordinates":[-87.67590300000001,41.997799],"type":"Point"}
}