{
  "type": "Feature",
  "properties": {
    "iso:country":"US",
    "sg:address":"655 E Co Rd 650",
    "sg:city":"Warsaw",
    "sg:phone":"+1 217 658 3201",
    "sg:postcode":"62379",
    "sg:province":"IL",
    "sg:tags":[
        "farm",
        "corn",
        "soybean"
    ],
    "wof:name":"Tom Kraushaar",
    "wof:placetype":"venue"
},
  "geometry": {"coordinates":[-91.382673,40.295107],"type":"Point"}
}