{
  "type": "Feature",
  "properties": {
    "iso:country":"US",
    "sg:address":"20519 S Graceland Ln",
    "sg:city":"Frankfort",
    "sg:classifiers":[
        {
            "category":"Shopping",
            "subcategory":"Music",
            "type":"Retail Goods"
        }
    ],
    "sg:phone":"+1   ",
    "sg:postcode":"60423",
    "sg:province":"IL",
    "wof:name":"Record Spinners Inc",
    "wof:placetype":"venue"
},
  "geometry": {"coordinates":[-87.80407700000001,41.514774],"type":"Point"}
}