{
  "type": "Feature",
  "properties": {
    "iso:country":"US",
    "sg:address":"255 Mittel Dr",
    "sg:city":"Wood Dale",
    "sg:classifiers":[
        {
            "category":"Professional",
            "subcategory":"Detective & Security Services",
            "type":"Services"
        }
    ],
    "sg:phone":"+1 630 694 1600",
    "sg:postcode":"60191",
    "sg:province":"IL",
    "sg:tags":[
        "system"
    ],
    "wof:name":"Navarrete Industries Inc",
    "wof:placetype":"venue"
},
  "geometry": {"coordinates":[-87.984853,41.9763],"type":"Point"}
}