{
  "type": "Feature",
  "properties": {
    "iso:country":"US",
    "sg:address":"1848 E Broadway",
    "sg:city":"Alton",
    "sg:classifiers":[
        {
            "category":"Shopping",
            "subcategory":"Discount & Variety Stores",
            "type":"Retail Goods"
        }
    ],
    "sg:phone":"+1   ",
    "sg:postcode":"62002",
    "sg:province":"IL",
    "wof:name":"Dollar General",
    "wof:placetype":"venue"
},
  "geometry": {"coordinates":[-90.158311,38.888033],"type":"Point"}
}