{
  "type": "Feature",
  "properties": {
    "addr:full":"6300 N River Rd Rosemont IL 60018",
    "addr:housenumber":"6300",
    "addr:postcode":"60018",
    "addr:street":"N River Rd",
    "iso:country":"US",
    "sg:address":"6300 N River Rd",
    "sg:city":"Rosemont",
    "sg:classifiers":[
        {
            "category":"Organizations",
            "subcategory":"Professional Association",
            "type":"Services"
        }
    ],
    "sg:phone":"+1 847 698 1693",
    "sg:postcode":"60018",
    "sg:province":"IL",
    "wof:name":"Association For Arthritic Hip",
    "wof:placetype":"venue"
},
  "geometry": {"coordinates":[-87.860973,41.993599],"type":"Point"}
}