{
  "type": "Feature",
  "properties": {
    "addr:full":"421 Sherman St Joliet IL 60433",
    "addr:housenumber":"421",
    "addr:postcode":"60433",
    "addr:street":"Sherman St",
    "iso:country":"US",
    "sg:address":"421 Sherman St",
    "sg:city":"Joliet",
    "sg:classifiers":[
        {
            "category":"Building & Trades",
            "subcategory":"Construction",
            "type":"Services"
        }
    ],
    "sg:phone":"+1 815 726 0316",
    "sg:postcode":"60433",
    "sg:province":"IL",
    "sg:tags":[
        "contractor"
    ],
    "wof:name":"Stevens Siding & Home Imprv",
    "wof:placetype":"venue"
},
  "geometry": {"coordinates":[-88.07643899999999,41.515162],"type":"Point"}
}