{
  "type": "Feature",
  "properties": {
    "iso:country":"US",
    "sg:address":"1700 E Higgins Rd",
    "sg:city":"Des Plaines",
    "sg:classifiers":[
        {
            "category":"Utilities",
            "subcategory":"Mobile Phone",
            "type":"Services"
        }
    ],
    "sg:phone":"+1 847 321 6300",
    "sg:postcode":"60018",
    "sg:province":"IL",
    "sg:tags":[
        "carrier",
        "voice",
        "dialing",
        "cellular",
        "for"
    ],
    "wof:name":"Voicecue",
    "wof:placetype":"venue"
},
  "geometry": {"coordinates":[-87.881221,41.997447],"type":"Point"}
}