{
  "type": "Feature",
  "properties": {
    "addr:full":"294 W 5th Ave Woodhull IL 61490",
    "addr:housenumber":"294",
    "addr:postcode":"61490",
    "addr:street":"W 5Th Ave",
    "iso:country":"US",
    "sg:address":"294 W 5th Ave",
    "sg:city":"Woodhull",
    "sg:classifiers":[
        {
            "category":"Building & Trades",
            "subcategory":"Electrical",
            "type":"Services"
        }
    ],
    "sg:phone":"+1 309 334 2393",
    "sg:postcode":"61490",
    "sg:province":"IL",
    "sg:tags":[
        "electrical",
        "contractor"
    ],
    "wof:name":"Tusing Plumbing Heating & Elc",
    "wof:placetype":"venue"
},
  "geometry": {"coordinates":[-90.317584,41.181597],"type":"Point"}
}