{
  "type": "Feature",
  "properties": {
    "addr:full":"1713 W John St Champaign IL 61821",
    "addr:housenumber":"1713",
    "addr:postcode":"61821",
    "addr:street":"W John St",
    "iso:country":"US",
    "sg:address":"1713 W John St",
    "sg:city":"Champaign",
    "sg:classifiers":[
        {
            "category":"Food & Beverages",
            "subcategory":"Groceries & Convenience Stores",
            "type":"Retail Goods"
        }
    ],
    "sg:phone":"+1 217 359 4515",
    "sg:postcode":"61821",
    "sg:province":"IL",
    "sg:website":"www.circlek.com",
    "wof:name":"Circle K",
    "wof:placetype":"venue"
},
  "geometry": {"coordinates":[-88.275521,40.108853],"type":"Point"}
}