{
  "type": "Feature",
  "properties": {
    "addr:full":"270 N Schuyler Ave Kankakee IL 60901",
    "addr:housenumber":"270",
    "addr:postcode":"60901",
    "addr:street":"N Schuyler Ave",
    "iso:country":"US",
    "sg:address":"270 N Schuyler Ave",
    "sg:city":"Kankakee",
    "sg:classifiers":[
        {
            "category":"Social Services",
            "type":"Services"
        }
    ],
    "sg:phone":"+1 815 932 1921",
    "sg:postcode":"60901",
    "sg:province":"IL",
    "sg:tags":[
        "senior",
        "citizen"
    ],
    "wof:name":"Senior Services Info & Asst",
    "wof:placetype":"venue"
},
  "geometry": {"coordinates":[-87.863484,41.121999],"type":"Point"}
}