{
  "type": "Feature",
  "properties": {
    "addr:full":"2213 W Cermak Road Chicago IL 60608",
    "addr:housenumber":"2213",
    "addr:postcode":"60608",
    "addr:street":"W Cermak Road",
    "iso:country":"US",
    "sg:address":"2213 W Cermak Road",
    "sg:city":"Chicago",
    "sg:classifiers":[
        {
            "category":"Professional",
            "subcategory":"Lawyer & Legal Services",
            "type":"Services"
        }
    ],
    "sg:phone":"+1 773 247 5544",
    "sg:postcode":"60608",
    "sg:province":"IL",
    "wof:name":"Am & Associates of Chicago",
    "wof:placetype":"venue"
},
  "geometry": {"coordinates":[-87.681332,41.851986],"type":"Point"}
}