{
  "type": "Feature",
  "properties": {
    "addr:full":"747 Aurora Ave Aurora IL 60505",
    "addr:housenumber":"747",
    "addr:postcode":"60505",
    "addr:street":"Aurora Ave",
    "iso:country":"US",
    "sg:address":"747 Aurora Ave",
    "sg:city":"Aurora",
    "sg:classifiers":[
        {
            "category":"Structure",
            "subcategory":"Office Building",
            "type":"Public Place"
        }
    ],
    "sg:phone":"+1 630 897 8800",
    "sg:postcode":"60505",
    "sg:province":"IL",
    "sg:tags":[
        "park"
    ],
    "wof:name":"Palace Properties",
    "wof:placetype":"venue"
},
  "geometry": {"coordinates":[-88.30591099999999,41.772669],"type":"Point"}
}