{
  "type": "Feature",
  "properties": {
    "addr:full":"9801 W Higgins Rd Des Plaines IL 60018",
    "addr:housenumber":"9801",
    "addr:postcode":"60018",
    "addr:street":"W Higgins Rd Des",
    "iso:country":"US",
    "sg:address":"9801 W Higgins Rd",
    "sg:city":"Des Plaines",
    "sg:classifiers":[
        {
            "category":"Real Estate",
            "subcategory":"Real Estate Agent",
            "type":"Services"
        }
    ],
    "sg:phone":"+1 847 823 7676",
    "sg:postcode":"60018",
    "sg:province":"IL",
    "sg:tags":[
        "management"
    ],
    "wof:name":"Draper and Kramer Incorporated",
    "wof:placetype":"venue"
},
  "geometry": {"coordinates":[-87.872107,41.994911],"type":"Point"}
}