{
  "type": "Feature",
  "properties": {
    "iso:country":"US",
    "sg:address":"1538 W State Rte 102",
    "sg:city":"Bourbonnais",
    "sg:classifiers":[
        {
            "category":"Home & Garden",
            "subcategory":"Building Materials",
            "type":"Retail Goods"
        }
    ],
    "sg:phone":"+1 815 592 3200",
    "sg:postcode":"60914",
    "sg:province":"IL",
    "sg:tags":[
        "glass",
        "leaded"
    ],
    "wof:name":"Designer Glass",
    "wof:placetype":"venue"
},
  "geometry": {"coordinates":[-87.905866,41.167497],"type":"Point"}
}