{
  "type": "Feature",
  "properties": {
    "iso:country":"US",
    "sg:address":"380 N Fairway Dr",
    "sg:city":"Vernon Hills",
    "sg:classifiers":[
        {
            "category":"Wholesale",
            "subcategory":"Stationery",
            "type":"Manufacturing & Wholesale Goods"
        },
        {
            "category":"Manufacturing",
            "subcategory":"Retail Goods",
            "type":"Manufacturing & Wholesale Goods"
        }
    ],
    "sg:phone":"+1 847 573 8400",
    "sg:postcode":"60061",
    "sg:province":"IL",
    "sg:tags":[
        "educational",
        "mfg",
        "supply",
        "school",
        "item",
        "import"
    ],
    "sg:website":"www.learningresources.com",
    "wof:name":"Learning Resources Inc",
    "wof:placetype":"venue"
},
  "geometry": {"coordinates":[-87.95455200000001,42.232153],"type":"Point"}
}