{
  "type": "Feature",
  "properties": {
    "addr:full":"356 W Superior St Chicago IL 60654",
    "addr:housenumber":"356",
    "addr:postcode":"60654",
    "addr:street":"W Superior St",
    "iso:country":"US",
    "sg:address":"356 W Superior St",
    "sg:city":"Chicago",
    "sg:classifiers":[
        {
            "category":"Health Services",
            "subcategory":"Doctor",
            "type":"Services"
        },
        {
            "category":"Community Center",
            "type":"Public Place"
        }
    ],
    "sg:phone":"+1 312 932 0300",
    "sg:postcode":"60654",
    "sg:province":"IL",
    "sg:tags":[
        "medical",
        "cardiologist"
    ],
    "wof:name":"Preventive Cardiovascular Services",
    "wof:placetype":"venue"
},
  "geometry": {"coordinates":[-87.637697,41.895709],"type":"Point"}
}