{
  "type": "Feature",
  "properties": {
    "iso:country":"US",
    "sg:address":"3139 N Lincoln Avenue Suite 209",
    "sg:city":"Chicago",
    "sg:classifiers":[
        {
            "category":"Health Services",
            "subcategory":"Chiropractor",
            "type":"Services"
        }
    ],
    "sg:phone":"+1 773 348 6908",
    "sg:postcode":"60657",
    "sg:province":"IL",
    "wof:name":"Total Balance Chiropractic",
    "wof:placetype":"venue"
},
  "geometry": {"coordinates":[-87.667168,41.93859],"type":"Point"}
}