{
  "type": "Feature",
  "properties": {
    "addr:full":"34 E Oak St 2nd Fl Chicago IL 60611",
    "addr:housenumber":"34",
    "addr:postcode":"60611",
    "addr:street":"E Oak St",
    "iso:country":"US",
    "sg:address":"34 E Oak St 2nd Fl",
    "sg:city":"Chicago",
    "sg:classifiers":[
        {
            "category":"Shopping",
            "subcategory":"Clothing, Apparel, & Fashions",
            "type":"Retail Goods"
        },
        {
            "category":"Shopping",
            "subcategory":"Bridal",
            "type":"Retail Goods"
        }
    ],
    "sg:phone":"+1 312 751 2222",
    "sg:postcode":"60611",
    "sg:province":"IL",
    "sg:website":"www.verawangchicago.com",
    "wof:name":"Vera Wang Chicago",
    "wof:placetype":"venue"
},
  "geometry": {"coordinates":[-87.627213,41.900761],"type":"Point"}
}