{
  "type": "Feature",
  "properties": {
    "iso:country":"US",
    "sg:address":"511 E Illinois Hwy",
    "sg:city":"New Lenox",
    "sg:classifiers":[
        {
            "category":"Education",
            "subcategory":"School",
            "type":"Public Place"
        }
    ],
    "sg:phone":"+1 815 485 2398",
    "sg:postcode":"60154",
    "sg:province":"IL",
    "wof:name":"Arnold Tyler Elementary School",
    "wof:placetype":"venue"
},
  "geometry": {"coordinates":[-87.95561499999999,41.497731],"type":"Point"}
}