{
  "type": "Feature",
  "properties": {
    "iso:country":"US",
    "sg:address":"1544 Ogden Ave",
    "sg:city":"Downers Grove",
    "sg:classifiers":[
        {
            "category":"Shopping",
            "type":"Retail Goods"
        }
    ],
    "sg:phone":"+1 630 964 4035",
    "sg:postcode":"60515",
    "sg:province":"IL",
    "sg:tags":[
        "picture",
        "frame"
    ],
    "wof:name":"Framing Avenue & Gallery",
    "wof:placetype":"venue"
},
  "geometry": {"coordinates":[-88.024076,41.808282],"type":"Point"}
}