{
  "type": "Feature",
  "properties": {
    "addr:full":"1544 Ogden Ave Downers Grove IL 60515",
    "addr:housenumber":"1544",
    "addr:postcode":"60515",
    "addr:street":"Ogden Ave",
    "iso:country":"US",
    "sg:address":"1544 Ogden Ave",
    "sg:city":"Downers Grove",
    "sg:classifiers":[
        {
            "category":"Shopping",
            "type":"Retail Goods"
        }
    ],
    "sg:phone":"+1 630 964 4035",
    "sg:postcode":"60515",
    "sg:province":"IL",
    "sg:tags":[
        "picture",
        "frame"
    ],
    "wof:name":"Framing Avenue & Gallery",
    "wof:placetype":"venue"
},
  "geometry": {"coordinates":[-88.02407599999999,41.808282],"type":"Point"}
}