{
  "type": "Feature",
  "properties": {
    "iso:country":"US",
    "sg:address":"5131 N Lincoln Ave",
    "sg:city":"Chicago",
    "sg:classifiers":[
        {
            "category":"Health Services",
            "subcategory":"Dentist",
            "type":"Services"
        }
    ],
    "sg:phone":"+1 773 271 5596",
    "sg:postcode":"60625",
    "sg:province":"IL",
    "sg:website":"www.moskindentalassociates.com/",
    "wof:name":"Jeannie Moskin, DDS & Associates",
    "wof:placetype":"venue"
},
  "geometry": {"coordinates":[-87.691875,41.975005],"type":"Point"}
}