{
  "type": "Feature",
  "properties": {
    "iso:country":"US",
    "sg:address":"4214 Wyndwood Dr",
    "sg:city":"Crystal Lake",
    "sg:classifiers":[
        {
            "category":"Communications",
            "subcategory":"Film & Video Production",
            "type":"Services"
        }
    ],
    "sg:phone":"+1 815 356 0556",
    "sg:postcode":"60014",
    "sg:province":"IL",
    "sg:tags":[
        "taping"
    ],
    "wof:name":"Ace Videography",
    "wof:placetype":"venue"
},
  "geometry": {"coordinates":[-88.276629,42.234252],"type":"Point"}
}