{
  "type": "Feature",
  "properties": {
    "iso:country":"US",
    "sg:address":"602 W 65th St",
    "sg:city":"Downers Grove",
    "sg:classifiers":[
        {
            "category":"Education",
            "subcategory":"School",
            "type":"Public Place"
        }
    ],
    "sg:phone":"+1 630 963 2124",
    "sg:postcode":"60516",
    "sg:province":"IL",
    "wof:name":"Power Think",
    "wof:placetype":"venue"
},
  "geometry": {"coordinates":[-88.000814,41.769605],"type":"Point"}
}