{
  "type": "Feature",
  "properties": {
    "addr:full":"20155 Ranch Ln Marion IL 62959",
    "addr:housenumber":"20155",
    "addr:postcode":"62959",
    "addr:street":"Ranch Ln",
    "iso:country":"US",
    "sg:address":"20155 Ranch Ln",
    "sg:city":"Marion",
    "sg:classifiers":[
        {
            "category":"Transit Center",
            "subcategory":"Freight",
            "type":"Transportation"
        },
        {
            "category":"Freight",
            "type":"Transportation"
        }
    ],
    "sg:phone":"+1 618 982 9103",
    "sg:postcode":"62959",
    "sg:province":"IL",
    "sg:tags":[
        "local",
        "trucking-motor",
        "trucking"
    ],
    "wof:name":"Bradford Trucking",
    "wof:placetype":"venue"
},
  "geometry": {"coordinates":[-88.938344,37.717635],"type":"Point"}
}