{
  "type": "Feature",
  "properties": {
    "addr:full":"617 W Roosevelt Rd Chicago IL 60607",
    "addr:housenumber":"617",
    "addr:postcode":"60607",
    "addr:street":"W Roosevelt Rd",
    "iso:country":"US",
    "sg:address":"617 W Roosevelt Rd",
    "sg:city":"Chicago",
    "sg:classifiers":[
        {
            "category":"Shopping",
            "subcategory":"Shoes",
            "type":"Retail Goods"
        }
    ],
    "sg:phone":"+1 312 249 8887",
    "sg:postcode":"60607",
    "sg:province":"IL",
    "sg:tags":[
        "store"
    ],
    "wof:name":"Bucci For Big & Tall",
    "wof:placetype":"venue"
},
  "geometry": {"coordinates":[-87.645599,41.867001],"type":"Point"}
}