{
  "type": "Feature",
  "properties": {
    "iso:country":"US",
    "sg:address":"4700 Golf Rd",
    "sg:city":"Skokie",
    "sg:classifiers":[
        {
            "category":"Autos & Motor Vehicles",
            "subcategory":"Automobile Sales",
            "type":"Retail Goods"
        }
    ],
    "sg:phone":"+1   ",
    "sg:postcode":"60076",
    "sg:province":"IL",
    "sg:tags":[
        "new",
        "used"
    ],
    "wof:name":"Mauro Chevorlet Inc",
    "wof:placetype":"venue"
},
  "geometry": {"coordinates":[-87.746848,42.055285],"type":"Point"}
}