{
  "type": "Feature",
  "properties": {
    "iso:country":"US",
    "sg:address":"1114 1st Ave",
    "sg:city":"Rock Falls",
    "sg:classifiers":[
        {
            "category":"Banks & Credit Unions",
            "subcategory":"Bank",
            "type":"Services"
        }
    ],
    "sg:phone":"+1 815 626 8000",
    "sg:postcode":"61071",
    "sg:province":"IL",
    "sg:tags":[
        "loan"
    ],
    "wof:name":"Heights Finance Corp",
    "wof:placetype":"venue"
},
  "geometry": {"coordinates":[-89.689417,41.770858],"type":"Point"}
}