{
  "type": "Feature",
  "properties": {
    "addr:full":"948 W 18th St Chicago IL 60608",
    "addr:housenumber":"948",
    "addr:postcode":"60608",
    "addr:street":"W 18Th St",
    "iso:country":"US",
    "sg:address":"948 W 18th St",
    "sg:city":"Chicago",
    "sg:classifiers":[
        {
            "category":"Personal",
            "type":"Services"
        }
    ],
    "sg:phone":"+1 312 226 0013",
    "sg:postcode":"60608",
    "sg:province":"IL",
    "sg:tags":[
        "sewing",
        "alteration"
    ],
    "wof:name":"Tino's Tailor Shop",
    "wof:placetype":"venue"
},
  "geometry": {"coordinates":[-87.650497,41.8582],"type":"Point"}
}