{
  "type": "Feature",
  "properties": {
    "addr:full":"921 Main St Antioch IL 60002",
    "addr:housenumber":"921",
    "addr:postcode":"60002",
    "addr:street":"Main St",
    "iso:country":"US",
    "sg:address":"921 Main St",
    "sg:city":"Antioch",
    "sg:classifiers":[
        {
            "category":"Shopping",
            "subcategory":"Clothing, Apparel, & Fashions",
            "type":"Retail Goods"
        }
    ],
    "sg:phone":"+1 847 395 4570",
    "sg:postcode":"60002",
    "sg:province":"IL",
    "sg:tags":[
        "uniform"
    ],
    "sg:website":"www.accentuniforms.com",
    "wof:name":"Accent Uniforms",
    "wof:placetype":"venue"
},
  "geometry": {"coordinates":[-88.09616699999999,42.478714],"type":"Point"}
}