{
  "type": "Feature",
  "properties": {
    "iso:country":"US",
    "sg:address":"215 S Galena Ave",
    "sg:city":"Dixon",
    "sg:classifiers":[
        {
            "category":"Real Estate",
            "subcategory":"Real Estate Operator",
            "type":"Services"
        }
    ],
    "sg:phone":"+1 815 284 0190",
    "sg:postcode":"61021",
    "sg:province":"IL",
    "sg:tags":[
        "apartment"
    ],
    "wof:name":"Nachusa House Apartments",
    "wof:placetype":"venue"
},
  "geometry": {"coordinates":[-89.482302,41.8425],"type":"Point"}
}