{
  "type": "Feature",
  "properties": {
    "iso:country":"US",
    "sg:address":"287 Lakehurst Rd",
    "sg:city":"Waukegan",
    "sg:classifiers":[
        {
            "category":"Shopping",
            "subcategory":"Jewelry",
            "type":"Retail Goods"
        }
    ],
    "sg:phone":"+1   ",
    "sg:postcode":"60085",
    "sg:province":"IL",
    "wof:name":"Waldin Jewelers",
    "wof:placetype":"venue"
},
  "geometry": {"coordinates":[-87.899816,42.339861],"type":"Point"}
}