{
  "type": "Feature",
  "properties": {
    "addr:full":"501 W Yates St Newman IL 61942",
    "addr:housenumber":"501",
    "addr:postcode":"61942",
    "addr:street":"W Yates St",
    "iso:country":"US",
    "sg:address":"501 W Yates St",
    "sg:city":"Newman",
    "sg:classifiers":[
        {
            "category":"Utilities",
            "subcategory":"Water",
            "type":"Services"
        }
    ],
    "sg:phone":"+1 217 837 2943",
    "sg:postcode":"61942",
    "sg:province":"IL",
    "sg:tags":[
        "company-utility",
        "system",
        "supply"
    ],
    "wof:name":"Water Dept",
    "wof:placetype":"venue"
},
  "geometry": {"coordinates":[-87.98893,39.797871],"type":"Point"}
}