{
  "type": "Feature",
  "properties": {
    "addr:full":"314 Plaza Dr Carterville IL 62918",
    "addr:housenumber":"314",
    "addr:postcode":"62918",
    "addr:street":"Plaza Dr",
    "iso:country":"US",
    "sg:address":"314 Plaza Dr",
    "sg:city":"Carterville",
    "sg:classifiers":[
        {
            "category":"Shopping",
            "subcategory":"Department Store",
            "type":"Retail Goods"
        }
    ],
    "sg:phone":"+1 618 985 6281",
    "sg:postcode":"62918",
    "sg:province":"IL",
    "sg:tags":[
        "shop"
    ],
    "wof:name":"Dollar General",
    "wof:placetype":"venue"
},
  "geometry": {"coordinates":[-89.07737899999999,37.745681],"type":"Point"}
}