{
  "type": "Feature",
  "properties": {
    "iso:country":"US",
    "sg:address":"1714 Broadway St",
    "sg:city":"Mount Vernon",
    "sg:classifiers":[
        {
            "category":"Education",
            "subcategory":"School",
            "type":"Public Place"
        }
    ],
    "sg:phone":"+1 618 244 8040",
    "sg:postcode":"62864",
    "sg:province":"IL",
    "sg:tags":[
        "regional"
    ],
    "wof:name":"Regional Office Education 25",
    "wof:placetype":"venue"
},
  "geometry": {"coordinates":[-88.910506,38.316485],"type":"Point"}
}