{
  "type": "Feature",
  "properties": {
    "iso:country":"US",
    "sg:address":"17034 Oak Park Ave",
    "sg:city":"Tinley Park",
    "sg:classifiers":[
        {
            "category":"Shopping",
            "type":"Retail Goods"
        }
    ],
    "sg:phone":"+1 708 429 5160",
    "sg:postcode":"60477",
    "sg:province":"IL",
    "sg:tags":[
        "monument"
    ],
    "wof:name":"Graf Memorials Inc",
    "wof:placetype":"venue"
},
  "geometry": {"coordinates":[-87.784627,41.58118],"type":"Point"}
}