{
  "type": "Feature",
  "properties": {
    "iso:country":"US",
    "sg:address":"5 Main St",
    "sg:city":"Oswego",
    "sg:classifiers":[
        {
            "category":"Insurance",
            "subcategory":"Hazard Insurance",
            "type":"Services"
        }
    ],
    "sg:phone":"+1 630 554 8831",
    "sg:postcode":"60543",
    "sg:province":"IL",
    "sg:website":"http://trippinsuranceagency.com",
    "wof:name":"N. M. Tripp Insurance Agency",
    "wof:placetype":"venue"
},
  "geometry": {"coordinates":[-88.351342,41.685029],"type":"Point"}
}