{
  "type": "Feature",
  "properties": {
    "iso:country":"US",
    "sg:address":"10359 S Torrence Avenue",
    "sg:city":"Chicago",
    "sg:classifiers":[
        {
            "category":"Fast Food",
            "type":"Food & Drink"
        },
        {
            "category":"Restaurant",
            "type":"Food & Drink"
        }
    ],
    "sg:phone":"+1 773 734 8400",
    "sg:postcode":"60617",
    "sg:province":"IL",
    "sg:tags":[
        "seafood",
        "chicken",
        "wing"
    ],
    "wof:name":"Hienie's Shrimp House",
    "wof:placetype":"venue"
},
  "geometry": {"coordinates":[-87.559603,41.706515],"type":"Point"}
}