{
  "type": "Feature",
  "properties": {
    "addr:full":"5349 N Winthrop Ave Chicago IL 60640",
    "addr:housenumber":"5349",
    "addr:postcode":"60640",
    "addr:street":"N Winthrop Ave",
    "iso:country":"US",
    "sg:address":"5349 N Winthrop Ave",
    "sg:city":"Chicago",
    "sg:classifiers":[
        {
            "category":"Social Services",
            "type":"Services"
        },
        {
            "category":"Personal",
            "type":"Services"
        }
    ],
    "sg:phone":"+1 773 842 7364",
    "sg:postcode":"60640",
    "sg:province":"IL",
    "sg:tags":[
        "family",
        "individual",
        "marriage",
        "child",
        "counseling",
        "counselor"
    ],
    "sg:website":"http://www.healingfromtheinsideout.com",
    "wof:name":"Adler Karen S LCSW",
    "wof:placetype":"venue"
},
  "geometry": {"coordinates":[-87.657791,41.979071],"type":"Point"}
}