{
  "type": "Feature",
  "properties": {
    "iso:country":"US",
    "sg:address":"2429 Crystal Ln",
    "sg:city":"Arlington Hts",
    "sg:classifiers":[
        {
            "category":"Building & Trades",
            "subcategory":"Landscaping Services",
            "type":"Services"
        }
    ],
    "sg:phone":"+1 847 991 2312",
    "sg:postcode":"60004",
    "sg:province":"IL",
    "sg:tags":[
        "landscape",
        "contractor"
    ],
    "wof:name":"A Puga Landscaping Co",
    "wof:placetype":"venue"
},
  "geometry": {"coordinates":[-88.013329,42.152566],"type":"Point"}
}