{
  "type": "Feature",
  "properties": {
    "addr:full":"170 W 144th St Riverdale IL 60827",
    "addr:housenumber":"170",
    "addr:postcode":"60827",
    "addr:street":"W 144Th St",
    "iso:country":"US",
    "sg:address":"170 W 144th St",
    "sg:city":"Riverdale",
    "sg:classifiers":[
        {
            "category":"Personal",
            "subcategory":"Barber",
            "type":"Services"
        }
    ],
    "sg:phone":"+1 708 849 2994",
    "sg:postcode":"60827",
    "sg:province":"IL",
    "wof:name":"Brand New Man Barber Palace",
    "wof:placetype":"venue"
},
  "geometry": {"coordinates":[-87.62616300000001,41.633323],"type":"Point"}
}