{
  "type": "Feature",
  "properties": {
    "iso:country":"US",
    "sg:address":"4 Thunderbird Rd",
    "sg:city":"Oakwood",
    "sg:classifiers":[
        {
            "category":"Freight",
            "type":"Transportation"
        }
    ],
    "sg:phone":"+1 217 442 6593",
    "sg:postcode":"61858",
    "sg:province":"IL",
    "sg:tags":[
        "operator",
        "local",
        "trucking"
    ],
    "wof:name":"Red Dog Trucking Inc",
    "wof:placetype":"venue"
},
  "geometry": {"coordinates":[-87.714966,40.117574],"type":"Point"}
}