{
  "type": "Feature",
  "properties": {
    "addr:full":"2256 N Orchard St Chicago IL 60614",
    "addr:housenumber":"2256",
    "addr:postcode":"60614",
    "addr:street":"N Orchard St",
    "iso:country":"US",
    "sg:address":"2256 N Orchard St",
    "sg:city":"Chicago",
    "sg:classifiers":[
        {
            "category":"Restaurant",
            "type":"Food & Drink"
        }
    ],
    "sg:menulink":"http://www.allmenus.com/il/chicago/221796-chipotle/menu/",
    "sg:phone":"+1 773 935 6744",
    "sg:postcode":"60614",
    "sg:province":"IL",
    "sg:tags":[
        "mexican"
    ],
    "wof:name":"Chipotle",
    "wof:placetype":"venue"
},
  "geometry": {"coordinates":[-87.646235,41.923403],"type":"Point"}
}