{
  "type": "Feature",
  "properties": {
    "addr:full":"5642 W Diversey Ave Ste 101 Chicago IL 60639",
    "addr:housenumber":"5642",
    "addr:postcode":"60639",
    "addr:street":"W Diversey Ave Ste 101",
    "iso:country":"US",
    "sg:address":"5642 W Diversey Ave Ste 101",
    "sg:city":"Chicago",
    "sg:classifiers":[
        {
            "category":"Building & Trades",
            "subcategory":"Landscaping Services",
            "type":"Services"
        }
    ],
    "sg:phone":"+1 773 235 8004",
    "sg:postcode":"60639",
    "sg:province":"IL",
    "sg:tags":[
        "lawn",
        "tree",
        "arborist"
    ],
    "wof:name":"Jim's Tree Svc",
    "wof:placetype":"venue"
},
  "geometry": {"coordinates":[-87.767622,41.931266],"type":"Point"}
}