{
  "type": "Feature",
  "properties": {
    "addr:full":"2169 State Rte 26 Dixon IL 61021",
    "addr:housenumber":"2169",
    "addr:postcode":"61021",
    "addr:street":"State Rte 26",
    "iso:country":"US",
    "sg:address":"2169 State Rte 26",
    "sg:city":"Dixon",
    "sg:classifiers":[
        {
            "category":"Building & Trades",
            "subcategory":"Construction",
            "type":"Services"
        }
    ],
    "sg:phone":"+1 815 288 3811",
    "sg:postcode":"61021",
    "sg:province":"IL",
    "sg:tags":[
        "woodworker"
    ],
    "wof:name":"Frog Tool Co LTD",
    "wof:placetype":"venue"
},
  "geometry": {"coordinates":[-89.53044800000001,41.89509],"type":"Point"}
}