{
  "type": "Feature",
  "properties": {
    "iso:country":"US",
    "sg:address":"1929 N Charles St",
    "sg:city":"Belleville",
    "sg:classifiers":[
        {
            "category":"Social Services",
            "subcategory":"Child Care",
            "type":"Services"
        }
    ],
    "sg:phone":"+1 618 233 1605",
    "sg:postcode":"62221",
    "sg:province":"IL",
    "wof:name":"Marjorie Oliver",
    "wof:placetype":"venue"
},
  "geometry": {"coordinates":[-89.96341700000001,38.531857],"type":"Point"}
}