{
  "type": "Feature",
  "properties": {
    "iso:country":"US",
    "sg:address":"4525 Simpson Rd",
    "sg:city":"Rockford",
    "sg:classifiers":[
        {
            "category":"Building & Trades",
            "subcategory":"Construction",
            "type":"Services"
        }
    ],
    "sg:phone":"+1 815 963 6088",
    "sg:postcode":"61102",
    "sg:province":"IL",
    "sg:tags":[
        "house",
        "contractor",
        "concrete"
    ],
    "wof:name":"Illinois Construction Co",
    "wof:placetype":"venue"
},
  "geometry": {"coordinates":[-89.12680899999999,42.223264],"type":"Point"}
}