{
  "type": "Feature",
  "properties": {
    "addr:full":"6122 W Addison St Chicago IL 60634",
    "addr:housenumber":"6122",
    "addr:postcode":"60634",
    "addr:street":"W Addison St",
    "iso:country":"US",
    "sg:address":"6122 W Addison St",
    "sg:city":"Chicago",
    "sg:classifiers":[
        {
            "category":"Fast Food",
            "type":"Food & Drink"
        },
        {
            "category":"Restaurant",
            "type":"Food & Drink"
        }
    ],
    "sg:phone":"+1 773 777 7050",
    "sg:postcode":"60634",
    "sg:province":"IL",
    "sg:tags":[
        "take"
    ],
    "wof:name":"Ferridino Enterprises",
    "wof:placetype":"venue"
},
  "geometry": {"coordinates":[-87.779488,41.945746],"type":"Point"}
}