{
  "type": "Feature",
  "properties": {
    "iso:country":"US",
    "sg:address":"4034 W North Avenue",
    "sg:city":"Chicago",
    "sg:classifiers":[
        {
            "category":"Sports & Exercise",
            "subcategory":"Bicycle Rental",
            "type":"Entertainment"
        }
    ],
    "sg:phone":"+1 773 278 2620",
    "sg:postcode":"60639",
    "sg:province":"IL",
    "sg:tags":[
        "wear"
    ],
    "wof:name":"A-1 Fashion",
    "wof:placetype":"venue"
},
  "geometry": {"coordinates":[-87.72761300000001,41.909802],"type":"Point"}
}