{
  "type": "Feature",
  "properties": {
    "iso:country":"US",
    "sg:address":"407 E Center St Ste D",
    "sg:city":"Eureka",
    "sg:classifiers":[
        {
            "category":"Retail",
            "subcategory":"Photofinishing",
            "type":"Services"
        },
        {
            "category":"Professional",
            "subcategory":"Printing & Photocopies",
            "type":"Services"
        }
    ],
    "sg:phone":"+1 309 467 4686",
    "sg:postcode":"61530",
    "sg:province":"IL",
    "sg:tags":[
        "laboratory",
        "laboratories-commercial",
        "finishing-custom",
        "photo"
    ],
    "sg:website":"http://www.precisionphotoimaging.com",
    "wof:name":"Precision Photo Imaging",
    "wof:placetype":"venue"
},
  "geometry": {"coordinates":[-89.268823,40.721415],"type":"Point"}
}