{
  "type": "Feature",
  "properties": {
    "addr:full":"741 E Boughton Rd Bolingbrook IL 60440",
    "addr:housenumber":"741",
    "addr:postcode":"60440",
    "addr:street":"E Boughton Rd",
    "iso:country":"US",
    "sg:address":"741 E Boughton Rd",
    "sg:city":"Bolingbrook",
    "sg:classifiers":[
        {
            "category":"Banks & Credit Unions",
            "subcategory":"Bank",
            "type":"Services"
        }
    ],
    "sg:phone":"+1 630 783 8264",
    "sg:postcode":"60440",
    "sg:province":"IL",
    "sg:tags":[
        "federal",
        "savings",
        "institution"
    ],
    "wof:name":"Washington Mutual Bank",
    "wof:placetype":"venue"
},
  "geometry": {"coordinates":[-88.04157600000001,41.721444],"type":"Point"}
}