{
  "type": "Feature",
  "properties": {
    "iso:country":"US",
    "sg:address":"4101 N Western Ave",
    "sg:city":"Chicago",
    "sg:classifiers":[
        {
            "category":"Health Services",
            "subcategory":"Health Practitioner",
            "type":"Services"
        }
    ],
    "sg:phone":"+1 877 608 5500",
    "sg:postcode":"60618",
    "sg:province":"IL",
    "sg:tags":[
        "acupuncture"
    ],
    "sg:website":"www.midwestacupuncturegroup.com",
    "wof:name":"Midwest Acupuncture Group",
    "wof:placetype":"venue"
},
  "geometry": {"coordinates":[-87.688136,41.955984],"type":"Point"}
}