{
  "type": "Feature",
  "properties": {
    "addr:full":"1900 W Main St Shelbyville IL 62565",
    "addr:housenumber":"1900",
    "addr:postcode":"62565",
    "addr:street":"W Main St",
    "iso:country":"US",
    "sg:address":"1900 W Main St",
    "sg:city":"Shelbyville",
    "sg:classifiers":[
        {
            "category":"Restaurant",
            "type":"Food & Drink"
        }
    ],
    "sg:menulink":"http://www.allmenus.com/il/rose/88386-monicals-pizza/menu/",
    "sg:phone":"+1 217 774 4100",
    "sg:postcode":"62565",
    "sg:province":"IL",
    "sg:tags":[
        "american",
        "pizza"
    ],
    "wof:name":"Monicals Pizza",
    "wof:placetype":"venue"
},
  "geometry": {"coordinates":[-88.81151199999999,39.406456],"type":"Point"}
}