{
  "type": "Feature",
  "properties": {
    "iso:country":"US",
    "sg:address":"1416 S Butterfield Rd",
    "sg:city":"Mundelein",
    "sg:classifiers":[
        {
            "category":"Personal",
            "subcategory":"Tanning Parlor",
            "type":"Services"
        },
        {
            "category":"Professional",
            "subcategory":"Advertising",
            "type":"Services"
        },
        {
            "category":"Personal",
            "subcategory":"Nail Salon",
            "type":"Services"
        }
    ],
    "sg:phone":"+1 847 816 0101",
    "sg:postcode":"60060",
    "sg:province":"IL",
    "sg:tags":[
        "coupon"
    ],
    "wof:name":"Awesome Tan",
    "wof:placetype":"venue"
},
  "geometry": {"coordinates":[-87.977767,42.242417],"type":"Point"}
}