{
  "type": "Feature",
  "properties": {
    "addr:full":"109 Lamar Dr Salem IL 62881",
    "addr:housenumber":"109",
    "addr:postcode":"62881",
    "addr:street":"Lamar Dr",
    "iso:country":"US",
    "sg:address":"109 Lamar Dr",
    "sg:city":"Salem",
    "sg:classifiers":[
        {
            "category":"Social Services",
            "subcategory":"Child Care",
            "type":"Services"
        }
    ],
    "sg:phone":"+1 618 548 3302",
    "sg:postcode":"62881",
    "sg:province":"IL",
    "sg:tags":[
        "nursery",
        "day"
    ],
    "wof:name":"Bonnie George",
    "wof:placetype":"venue"
},
  "geometry": {"coordinates":[-88.96794300000001,38.631998],"type":"Point"}
}