{
  "type": "Feature",
  "properties": {
    "iso:country":"US",
    "sg:address":"1051 Groton Ct",
    "sg:city":"Schaumburg",
    "sg:classifiers":[
        {
            "category":"Building & Trades",
            "subcategory":"Cleaning & Sanitation",
            "type":"Services"
        }
    ],
    "sg:phone":"+1 847 729 6925",
    "sg:postcode":"60193",
    "sg:province":"IL",
    "sg:tags":[
        "maintenance"
    ],
    "wof:name":"Quest Service Group",
    "wof:placetype":"venue"
},
  "geometry": {"coordinates":[-88.105955,42.008175],"type":"Point"}
}