{
  "type": "Feature",
  "properties": {
    "addr:full":"3803 Sage Dr Rockford IL 61114",
    "addr:housenumber":"3803",
    "addr:postcode":"61114",
    "addr:street":"Sage Dr",
    "iso:country":"US",
    "sg:address":"3803 Sage Dr",
    "sg:city":"Rockford",
    "sg:classifiers":[
        {
            "category":"Real Estate",
            "subcategory":"Real Estate Operator",
            "type":"Services"
        }
    ],
    "sg:phone":"+1 815 282 3550",
    "sg:postcode":"61114",
    "sg:province":"IL",
    "sg:tags":[
        "building",
        "apartment"
    ],
    "wof:name":"Foxwood Village Apartments",
    "wof:placetype":"venue"
},
  "geometry": {"coordinates":[-89.021688,42.316095],"type":"Point"}
}