{
  "type": "Feature",
  "properties": {
    "iso:country":"US",
    "sg:address":"546 N Brewster Ave",
    "sg:city":"Freeport",
    "sg:phone":"+1 815 233 5736",
    "sg:postcode":"61032",
    "sg:province":"IL",
    "sg:tags":[
        "gas"
    ],
    "wof:name":"Martin's Propane Svc",
    "wof:placetype":"venue"
},
  "geometry": {"coordinates":[-89.644374,42.302544],"type":"Point"}
}