{
  "type": "Feature",
  "properties": {
    "iso:country":"US",
    "sg:address":"6012 Forest Hills Rd",
    "sg:city":"Loves Park",
    "sg:classifiers":[
        {
            "category":"Wholesale",
            "subcategory":"Hardware",
            "type":"Manufacturing & Wholesale Goods"
        }
    ],
    "sg:phone":"+1 815 654 7873",
    "sg:postcode":"61111",
    "sg:province":"IL",
    "sg:tags":[
        "purifying",
        "cleaning",
        "air"
    ],
    "wof:name":"Pure Air Products",
    "wof:placetype":"venue"
},
  "geometry": {"coordinates":[-89.04050100000001,42.311201],"type":"Point"}
}