{
  "type": "Feature",
  "properties": {
    "addr:full":"27848 N Bradley Rd Lake Forest IL 60048",
    "addr:housenumber":"27848",
    "addr:postcode":"60048",
    "addr:street":"N Bradley Rd",
    "iso:country":"US",
    "sg:address":"27848 N Bradley Rd",
    "sg:city":"Lake Forest",
    "sg:classifiers":[
        {
            "category":"Government",
            "subcategory":"Post Office",
            "type":"Public Place"
        }
    ],
    "sg:phone":"+1 847 680 5464",
    "sg:postcode":"60048",
    "sg:province":"IL",
    "sg:tags":[
        "postal",
        "us"
    ],
    "wof:name":"Lake Forest Post Office",
    "wof:placetype":"venue"
},
  "geometry": {"coordinates":[-87.905502,42.266411],"type":"Point"}
}