{
  "type": "Feature",
  "properties": {
    "addr:full":"2270 N Lincoln Avenue Chicago IL 60614",
    "addr:housenumber":"2270",
    "addr:postcode":"60614",
    "addr:street":"N Lincoln Avenue",
    "iso:country":"US",
    "sg:address":"2270 N Lincoln Avenue",
    "sg:city":"Chicago",
    "sg:classifiers":[
        {
            "category":"Bars & Pubs",
            "type":"Food & Drink"
        },
        {
            "category":"Restaurant",
            "type":"Food & Drink"
        }
    ],
    "sg:phone":"+1 773 929 1300",
    "sg:postcode":"60614",
    "sg:province":"IL",
    "sg:tags":[
        "tavern",
        "grill",
        "brew"
    ],
    "sg:website":"http://www.wisefoolpress.com",
    "wof:name":"Wise Fools Pub",
    "wof:placetype":"venue"
},
  "geometry": {"coordinates":[-87.646304,41.923655],"type":"Point"}
}