{
  "type": "Feature",
  "properties": {
    "addr:full":"1774 Old Rte 121 Lincoln IL 62656",
    "addr:housenumber":"1774",
    "addr:postcode":"62656",
    "addr:street":"Old Rte 121",
    "iso:country":"US",
    "sg:address":"1774 Old Rte 121",
    "sg:city":"Lincoln",
    "sg:phone":"+1 217 735 4602",
    "sg:postcode":"62656",
    "sg:province":"IL",
    "sg:tags":[
        "farm",
        "wheat",
        "soybean"
    ],
    "wof:name":"Larry Ingrim",
    "wof:placetype":"venue"
},
  "geometry": {"coordinates":[-89.38715000000001,40.180191],"type":"Point"}
}