{
  "type": "Feature",
  "properties": {
    "addr:full":"190 N Anderson Rd New Lenox IL 60451",
    "addr:housenumber":"190",
    "addr:postcode":"60451",
    "addr:street":"N Anderson Rd",
    "iso:country":"US",
    "sg:address":"190 N Anderson Rd",
    "sg:city":"New Lenox",
    "sg:classifiers":[
        {
            "category":"Shopping",
            "subcategory":"Clothing, Apparel, & Fashions",
            "type":"Retail Goods"
        }
    ],
    "sg:phone":"+1 815 462 1249",
    "sg:postcode":"60451",
    "sg:province":"IL",
    "sg:tags":[
        "t"
    ],
    "wof:name":"Z-Wear",
    "wof:placetype":"venue"
},
  "geometry": {"coordinates":[-87.936876,41.513794],"type":"Point"}
}