{
  "type": "Feature",
  "properties": {
    "iso:country":"US",
    "sg:address":"1304 Megan Ct",
    "sg:city":"Minooka",
    "sg:classifiers":[
        {
            "category":"Retail",
            "subcategory":"Auto Repair",
            "type":"Services"
        }
    ],
    "sg:phone":"+1 815 791 4416",
    "sg:postcode":"60447",
    "sg:province":"IL",
    "sg:tags":[
        "body"
    ],
    "wof:name":"Firepainting",
    "wof:placetype":"venue"
},
  "geometry": {"coordinates":[-88.27351299999999,41.431688],"type":"Point"}
}