{
  "type": "Feature",
  "properties": {
    "iso:country":"US",
    "sg:address":"2701 23rd St",
    "sg:city":"Broadview",
    "sg:classifiers":[
        {
            "category":"Wholesale",
            "subcategory":"Beer",
            "type":"Manufacturing & Wholesale Goods"
        }
    ],
    "sg:phone":"+1 708 345 2600",
    "sg:postcode":"60155",
    "sg:province":"IL",
    "sg:tags":[
        "ale",
        "ale-wholesale",
        "manufacturer"
    ],
    "wof:name":"Grant Import",
    "wof:placetype":"venue"
},
  "geometry": {"coordinates":[-87.863319,41.847321],"type":"Point"}
}