{
  "type": "Feature",
  "properties": {
    "iso:country":"US",
    "sg:address":"46 Lenora St",
    "sg:city":"Cottage Hills",
    "sg:classifiers":[
        {
            "category":"Professional",
            "subcategory":"Management & Consulting",
            "type":"Services"
        }
    ],
    "sg:phone":"+1 618 259 3020",
    "sg:postcode":"62018",
    "sg:province":"IL",
    "wof:name":"Charles E Mahoney",
    "wof:placetype":"venue"
},
  "geometry": {"coordinates":[-90.070521,38.90261],"type":"Point"}
}