{
  "type": "Feature",
  "properties": {
    "addr:full":"1030 E 162nd St South Holland IL 60473",
    "addr:housenumber":"1030",
    "addr:postcode":"60473",
    "addr:street":"E 162Nd St",
    "iso:country":"US",
    "sg:address":"1030 E 162nd St",
    "sg:city":"South Holland",
    "sg:classifiers":[
        {
            "category":"Food & Beverages",
            "subcategory":"Candy",
            "type":"Retail Goods"
        }
    ],
    "sg:phone":"+1 708 596 2440",
    "sg:postcode":"60473",
    "sg:province":"IL",
    "sg:tags":[
        "store"
    ],
    "wof:name":"Cunis Candies Inc",
    "wof:placetype":"venue"
},
  "geometry": {"coordinates":[-87.591499,41.6007],"type":"Point"}
}