{
  "type": "Feature",
  "properties": {
    "iso:country":"US",
    "sg:address":"1400 N Vermilion St",
    "sg:city":"Danville",
    "sg:classifiers":[
        {
            "category":"Organizations",
            "subcategory":"Religious Organization",
            "type":"Services"
        }
    ],
    "sg:phone":"+1 217 442 3668",
    "sg:postcode":"61832",
    "sg:province":"IL",
    "sg:tags":[
        "church"
    ],
    "wof:name":"Lincoln United Methodist Chr",
    "wof:placetype":"venue"
},
  "geometry": {"coordinates":[-87.630249,40.149399],"type":"Point"}
}