{
  "type": "Feature",
  "properties": {
    "addr:full":"2306 N Sawyer Ave Chicago IL 60647",
    "addr:housenumber":"2306",
    "addr:postcode":"60647",
    "addr:street":"N Sawyer Ave",
    "iso:country":"US",
    "sg:address":"2306 N Sawyer Ave",
    "sg:city":"Chicago",
    "sg:classifiers":[
        {
            "category":"Social Services",
            "subcategory":"Child Care",
            "type":"Services"
        }
    ],
    "sg:phone":"+1 773 235 1260",
    "sg:postcode":"60647",
    "sg:province":"IL",
    "sg:tags":[
        "day"
    ],
    "wof:name":"Future Generation Daycare",
    "wof:placetype":"venue"
},
  "geometry": {"coordinates":[-87.709214,41.924048],"type":"Point"}
}