{
  "type": "Feature",
  "properties": {
    "iso:country":"US",
    "sg:address":"4337 S Kildare Ave",
    "sg:city":"Chicago",
    "sg:classifiers":[
        {
            "category":"Personal",
            "type":"Services"
        }
    ],
    "sg:phone":"+1 773 890 4894",
    "sg:postcode":"60632",
    "sg:province":"IL",
    "sg:tags":[
        "towing"
    ],
    "wof:name":"Miller Towing",
    "wof:placetype":"venue"
},
  "geometry": {"coordinates":[-87.731201,41.814301],"type":"Point"}
}