{
  "type": "Feature",
  "properties": {
    "addr:full":"434 N. Main St. Glen Ellyn IL 60137",
    "addr:housenumber":"434",
    "addr:postcode":"60137",
    "addr:street":"N. Main St.",
    "iso:country":"US",
    "sg:address":"434 N. Main St.",
    "sg:city":"Glen Ellyn",
    "sg:classifiers":[
        {
            "category":"Winery",
            "type":"Food & Drink"
        },
        {
            "category":"Food & Beverages",
            "subcategory":"Liquor & Beverages",
            "type":"Retail Goods"
        }
    ],
    "sg:phone":"+1 630 469 2644",
    "sg:postcode":"60137",
    "sg:province":"IL",
    "sg:tags":[
        "beer",
        "spirit",
        "wine"
    ],
    "sg:website":"www.cabernetco.com",
    "wof:name":"Cabernet & Company",
    "wof:placetype":"venue"
},
  "geometry": {"coordinates":[-88.06672,41.875209],"type":"Point"}
}