{
  "type": "Feature",
  "properties": {
    "iso:country":"US",
    "sg:address":"839 8th St",
    "sg:city":"La Salle",
    "sg:classifiers":[
        {
            "category":"Wholesale",
            "subcategory":"Machinery & Supplies",
            "type":"Manufacturing & Wholesale Goods"
        }
    ],
    "sg:phone":"+1 815 223 2388",
    "sg:postcode":"61301",
    "sg:province":"IL",
    "sg:tags":[
        "janitor"
    ],
    "wof:name":"Midwest Service & Supply Co",
    "wof:placetype":"venue"
},
  "geometry": {"coordinates":[-89.094364,41.336056],"type":"Point"}
}