{
  "type": "Feature",
  "properties": {
    "addr:full":"1209 S Walnut Ave Freeport IL 61032",
    "addr:housenumber":"1209",
    "addr:postcode":"61032",
    "addr:street":"S Walnut Ave",
    "iso:country":"US",
    "sg:address":"1209 S Walnut Ave",
    "sg:city":"Freeport",
    "sg:classifiers":[
        {
            "category":"Place Of Worship",
            "subcategory":"Church",
            "type":"Public Place"
        },
        {
            "category":"Place Of Worship",
            "type":"Public Place"
        },
        {
            "category":"Organizations",
            "subcategory":"Religious Organization",
            "type":"Services"
        }
    ],
    "sg:phone":"+1 815 297 8287",
    "sg:postcode":"61032",
    "sg:province":"IL",
    "sg:tags":[
        "churches-salvation",
        "army"
    ],
    "wof:name":"Congregation Of Sisters Of Immaculate",
    "wof:placetype":"venue"
},
  "geometry": {"coordinates":[-89.621208,42.289141],"type":"Point"}
}