{
  "type": "Feature",
  "properties": {
    "iso:country":"US",
    "sg:address":"1400 W Northwest Hwy",
    "sg:city":"Arlington Heights",
    "sg:classifiers":[
        {
            "category":"Health Services",
            "subcategory":"Medical Lab",
            "type":"Services"
        }
    ],
    "sg:phone":"+1 847 259 7306",
    "sg:postcode":"60004",
    "sg:province":"IL",
    "sg:tags":[
        "laboratory",
        "dental"
    ],
    "wof:name":"Ijuin Dental Lab Inc",
    "wof:placetype":"venue"
},
  "geometry": {"coordinates":[-88.001525,42.09238],"type":"Point"}
}