{
  "type": "Feature",
  "properties": {
    "iso:country":"US",
    "sg:address":"7650 W Irving Park Rd",
    "sg:city":"Harwood Heights",
    "sg:classifiers":[
        {
            "category":"Restaurant",
            "type":"Food & Drink"
        }
    ],
    "sg:menulink":"http://www.allmenus.com/il/norwood-park/241346-edlweiss-/menu/",
    "sg:phone":"+1 708 452 6040",
    "sg:postcode":"60706",
    "sg:province":"IL",
    "sg:tags":[
        "german"
    ],
    "wof:name":"Edlweiss ",
    "wof:placetype":"venue"
},
  "geometry": {"coordinates":[-87.819216,41.952666],"type":"Point"}
}