{
  "type": "Feature",
  "properties": {
    "iso:country":"US",
    "sg:address":"1823 Wesley Ave",
    "sg:city":"Evanston",
    "sg:classifiers":[
        {
            "category":"Building & Trades",
            "subcategory":"Construction",
            "type":"Services"
        }
    ],
    "sg:phone":"+1 847 864 0665",
    "sg:postcode":"60201",
    "sg:province":"IL",
    "sg:tags":[
        "house"
    ],
    "wof:name":"Cornerstone Remodeling",
    "wof:placetype":"venue"
},
  "geometry": {"coordinates":[-87.691849,42.051779],"type":"Point"}
}