{
  "type": "Feature",
  "properties": {
    "iso:country":"US",
    "sg:address":"9222 S Stony Island Ave",
    "sg:city":"Chicago",
    "sg:classifiers":[
        {
            "category":"Personal",
            "subcategory":"Day Spa",
            "type":"Services"
        }
    ],
    "sg:phone":"+1 773 375 6014",
    "sg:postcode":"60617",
    "sg:province":"IL",
    "wof:name":"With These Hands",
    "wof:placetype":"venue"
},
  "geometry": {"coordinates":[-87.58562499999999,41.727385],"type":"Point"}
}