{
  "type": "Feature",
  "properties": {
    "iso:country":"US",
    "sg:address":"1030 N State St Apt 39H",
    "sg:city":"Chicago",
    "sg:classifiers":[
        {
            "category":"Professional",
            "subcategory":"Advertising",
            "type":"Services"
        }
    ],
    "sg:phone":"+1 312 642 6506",
    "sg:postcode":"60610",
    "sg:province":"IL",
    "sg:tags":[
        "advertising-promotional",
        "product",
        "specialty"
    ],
    "sg:website":"http://www.bkspecialties.com",
    "wof:name":"B & K Specialties",
    "wof:placetype":"venue"
},
  "geometry": {"coordinates":[-87.628343,41.901181],"type":"Point"}
}