{
  "type": "Feature",
  "properties": {
    "iso:country":"US",
    "sg:address":"1800 N Clybourn Ave",
    "sg:city":"Chicago",
    "sg:classifiers":[
        {
            "category":"Sports & Exercise",
            "subcategory":"Bicycle Rental",
            "type":"Entertainment"
        }
    ],
    "sg:phone":"+1 312 951 0518",
    "sg:postcode":"60614",
    "sg:province":"IL",
    "sg:tags":[
        "wear"
    ],
    "wof:name":"Patagonia",
    "wof:placetype":"venue"
},
  "geometry": {"coordinates":[-87.653397,41.9137],"type":"Point"}
}