{
  "type": "Feature",
  "properties": {
    "iso:country":"US",
    "sg:address":"4900 W Fullerton Avenue",
    "sg:city":"Chicago",
    "sg:classifiers":[
        {
            "category":"Autos & Motor Vehicles",
            "subcategory":"Fuel & Gas Station",
            "type":"Retail Goods"
        },
        {
            "category":"Manufacturing",
            "subcategory":"Petroleum Products",
            "type":"Manufacturing & Wholesale Goods"
        }
    ],
    "sg:phone":"+1 773 889 6562",
    "sg:postcode":"60639",
    "sg:province":"IL",
    "sg:tags":[
        "oil",
        "refiner"
    ],
    "wof:name":"Mgm Petroleum",
    "wof:placetype":"venue"
},
  "geometry": {"coordinates":[-87.749025,41.924235],"type":"Point"}
}