{
  "type": "Feature",
  "properties": {
    "iso:country":"US",
    "sg:address":"514 Dubois Cir",
    "sg:city":"Bolingbrook",
    "sg:classifiers":[
        {
            "category":"Banks & Credit Unions",
            "subcategory":"Financial Services",
            "type":"Services"
        }
    ],
    "sg:phone":"+1 630 972 2191",
    "sg:postcode":"60440",
    "sg:province":"IL",
    "sg:tags":[
        "trust",
        "management"
    ],
    "wof:name":"Sayani Dilshad & Zulfigar",
    "wof:placetype":"venue"
},
  "geometry": {"coordinates":[-88.061587,41.714243],"type":"Point"}
}