{
  "type": "Feature",
  "properties": {
    "addr:full":"23 W Rollins Rd Round Lake IL 60073",
    "addr:housenumber":"23",
    "addr:postcode":"60073",
    "addr:street":"W Rollins Rd",
    "iso:country":"US",
    "sg:address":"23 W Rollins Rd",
    "sg:city":"Round Lake",
    "sg:classifiers":[
        {
            "category":"Professional",
            "subcategory":"Accounting & Tax Preparation",
            "type":"Services"
        }
    ],
    "sg:phone":"+1 847 740 7500",
    "sg:postcode":"60073",
    "sg:province":"IL",
    "sg:tags":[
        "return"
    ],
    "wof:name":"Jackson Hewitt Tax Service",
    "wof:placetype":"venue"
},
  "geometry": {"coordinates":[-88.089933,42.378864],"type":"Point"}
}