{
  "type": "Feature",
  "properties": {
    "addr:full":"2925 W Diversey Ave Chicago IL 60647",
    "addr:housenumber":"2925",
    "addr:postcode":"60647",
    "addr:street":"W Diversey Ave",
    "iso:country":"US",
    "sg:address":"2925 W Diversey Ave",
    "sg:city":"Chicago",
    "sg:classifiers":[
        {
            "category":"Travel",
            "subcategory":"Travel Agent",
            "type":"Entertainment"
        }
    ],
    "sg:phone":"+1 773 342 5919",
    "sg:postcode":"60647",
    "sg:province":"IL",
    "sg:tags":[
        "agency"
    ],
    "wof:name":"Lg Travel",
    "wof:placetype":"venue"
},
  "geometry": {"coordinates":[-87.700264,41.932002],"type":"Point"}
}