{
  "type": "Feature",
  "properties": {
    "addr:full":"12770 W 4000N Rd Bonfield IL 60913",
    "addr:housenumber":"12770",
    "addr:postcode":"60913",
    "addr:street":"W 4000N Rd",
    "iso:country":"US",
    "sg:address":"12770 W 4000N Rd",
    "sg:city":"Bonfield",
    "sg:classifiers":[
        {
            "category":"Professional",
            "subcategory":"Accounting & Tax Preparation",
            "type":"Services"
        }
    ],
    "sg:phone":"+1 815 421 0361",
    "sg:postcode":"60913",
    "sg:province":"IL",
    "sg:tags":[
        "public",
        "accountants-certified"
    ],
    "wof:name":"Lavina Estell Cpa",
    "wof:placetype":"venue"
},
  "geometry": {"coordinates":[-88.126734,41.174974],"type":"Point"}
}