{
  "type": "Feature",
  "properties": {
    "addr:full":"6803 S Pulaski Road Chicago IL 60629",
    "addr:housenumber":"6803",
    "addr:postcode":"60629",
    "addr:street":"S Pulaski Road",
    "iso:country":"US",
    "sg:address":"6803 S Pulaski Road",
    "sg:city":"Chicago",
    "sg:classifiers":[
        {
            "category":"Insurance",
            "subcategory":"Hazard Insurance",
            "type":"Services"
        }
    ],
    "sg:phone":"+1 773 585 2100",
    "sg:postcode":"60629",
    "sg:province":"IL",
    "wof:name":"Allstate Insurance",
    "wof:placetype":"venue"
},
  "geometry": {"coordinates":[-87.722291,41.769162],"type":"Point"}
}