{
  "type": "Feature",
  "properties": {
    "iso:country":"US",
    "sg:address":"2303 W North Ave",
    "sg:city":"Chicago",
    "sg:classifiers":[
        {
            "category":"Professional",
            "subcategory":"Lawyer & Legal Services",
            "type":"Services"
        }
    ],
    "sg:phone":"+1 773 289 4700",
    "sg:postcode":"60647",
    "sg:province":"IL",
    "wof:name":"Mondero Rim D'souza & Gosrisirikul Ltd",
    "wof:placetype":"venue"
},
  "geometry": {"coordinates":[-87.685097,41.910198],"type":"Point"}
}