{
  "type": "Feature",
  "properties": {
    "iso:country":"US",
    "sg:address":"333 North Michigan Ave.",
    "sg:city":"Chicago",
    "sg:classifiers":[
        {
            "category":"Professional",
            "subcategory":"Computer Services",
            "type":"Services"
        }
    ],
    "sg:postcode":"60601",
    "sg:province":"IL",
    "sg:website":"http://www.GameCards.com",
    "wof:name":"GameCards.com",
    "wof:placetype":"venue"
},
  "geometry": {"coordinates":[-87.624466,41.886866],"type":"Point"}
}