{
  "type": "Feature",
  "properties": {
    "addr:full":"121 W Main St Genoa IL 60135",
    "addr:housenumber":"121",
    "addr:postcode":"60135",
    "addr:street":"W Main St",
    "iso:country":"US",
    "sg:address":"121 W Main St",
    "sg:city":"Genoa",
    "sg:classifiers":[
        {
            "category":"Shopping",
            "type":"Retail Goods"
        },
        {
            "category":"Shopping",
            "subcategory":"Gifts & Souvenirs",
            "type":"Retail Goods"
        }
    ],
    "sg:phone":"+1 815 784 2767",
    "sg:postcode":"60135",
    "sg:province":"IL",
    "sg:tags":[
        "candle"
    ],
    "wof:name":"Fame Partylite Regional Office",
    "wof:placetype":"venue"
},
  "geometry": {"coordinates":[-88.693235,42.097362],"type":"Point"}
}