{
  "type": "Feature",
  "properties": {
    "iso:country":"US",
    "sg:address":"1718 Lincoln Ave",
    "sg:city":"Charleston",
    "sg:classifiers":[
        {
            "category":"Retail",
            "subcategory":"Auto Repair",
            "type":"Services"
        }
    ],
    "sg:phone":"+1 217 345 2121",
    "sg:postcode":"61920",
    "sg:province":"IL",
    "sg:tags":[
        "repairing",
        "automobile"
    ],
    "wof:name":"Charleston Service Ctr",
    "wof:placetype":"venue"
},
  "geometry": {"coordinates":[-88.167081,39.48437],"type":"Point"}
}