{
  "type": "Feature",
  "properties": {
    "iso:country":"US",
    "sg:address":"410 E Green St",
    "sg:city":"Champaign",
    "sg:classifiers":[
        {
            "category":"Restaurant",
            "type":"Food & Drink"
        }
    ],
    "sg:menulink":"http://www.allmenus.com/il/champaign-city/17070-empire-chinese-restaurant/menu/",
    "sg:phone":"+1 217 328 0832",
    "sg:postcode":"61820",
    "sg:province":"IL",
    "sg:tags":[
        "asian",
        "chinese"
    ],
    "wof:name":"Empire Chinese Restaurant",
    "wof:placetype":"venue"
},
  "geometry": {"coordinates":[-88.233457,40.110281],"type":"Point"}
}