{
  "type": "Feature",
  "properties": {
    "iso:country":"US",
    "sg:address":"1550 Douglas St",
    "sg:city":"Charleston",
    "sg:classifiers":[
        {
            "category":"Banks & Credit Unions",
            "subcategory":"Investment Brokerage",
            "type":"Services"
        }
    ],
    "sg:phone":"+1 217 348 1271",
    "sg:postcode":"61920",
    "sg:province":"IL",
    "sg:tags":[
        "security"
    ],
    "wof:name":"Assoc Jim Invstment/Ins McNutt",
    "wof:placetype":"venue"
},
  "geometry": {"coordinates":[-88.195976,39.484526],"type":"Point"}
}