{
  "type": "Feature",
  "properties": {
    "addr:full":"420 Hammond Ave Elgin IL 60120",
    "addr:housenumber":"420",
    "addr:postcode":"60120",
    "addr:street":"Hammond Ave",
    "iso:country":"US",
    "sg:address":"420 Hammond Ave",
    "sg:city":"Elgin",
    "sg:classifiers":[
        {
            "category":"Professional",
            "subcategory":"Business Services",
            "type":"Services"
        }
    ],
    "sg:phone":"+1 847 888 3870",
    "sg:postcode":"60120",
    "sg:province":"IL",
    "sg:tags":[
        "auctioneer"
    ],
    "sg:website":"www.johnpriggeauctions.com",
    "wof:name":"John Prigge Auctions",
    "wof:placetype":"venue"
},
  "geometry": {"coordinates":[-88.26907300000001,42.015492],"type":"Point"}
}