{
  "type": "Feature",
  "properties": {
    "iso:country":"US",
    "sg:address":"1700 Estes Ave",
    "sg:city":"Elk Grove Village",
    "sg:classifiers":[
        {
            "category":"Wholesale",
            "subcategory":"Electrical",
            "type":"Manufacturing & Wholesale Goods"
        }
    ],
    "sg:phone":"+1 847 290 8899",
    "sg:postcode":"60007",
    "sg:province":"IL",
    "sg:tags":[
        "supply"
    ],
    "wof:name":"Crescent Electric Sup Co Del",
    "wof:placetype":"venue"
},
  "geometry": {"coordinates":[-87.949469,42.006168],"type":"Point"}
}