{
  "type": "Feature",
  "properties": {
    "iso:country":"US",
    "sg:address":"2531 N 550 East Rd",
    "sg:city":"De Land",
    "sg:phone":"+1 217 664 3567",
    "sg:postcode":"61839",
    "sg:province":"IL",
    "sg:tags":[
        "farm",
        "corn",
        "soybean"
    ],
    "wof:name":"Levelland Farms",
    "wof:placetype":"venue"
},
  "geometry": {"coordinates":[-88.639849,40.166458],"type":"Point"}
}