{
  "type": "Feature",
  "properties": {
    "addr:full":"908 E Roosevelt Rd Wheaton IL 60187",
    "addr:housenumber":"908",
    "addr:postcode":"60187",
    "addr:street":"E Roosevelt Rd",
    "iso:country":"US",
    "sg:address":"908 E Roosevelt Rd",
    "sg:city":"Wheaton",
    "sg:classifiers":[
        {
            "category":"Building & Trades",
            "subcategory":"Equipment Rental",
            "type":"Services"
        }
    ],
    "sg:phone":"+1 630 221 1133",
    "sg:postcode":"60187",
    "sg:province":"IL",
    "sg:tags":[
        "tool"
    ],
    "wof:name":"Rental Max LLC",
    "wof:placetype":"venue"
},
  "geometry": {"coordinates":[-88.094303,41.858864],"type":"Point"}
}