{
  "type": "Feature",
  "properties": {
    "addr:full":"311 W Center St Cambridge IL 61238",
    "addr:housenumber":"311",
    "addr:postcode":"61238",
    "addr:street":"W Center St",
    "iso:country":"US",
    "sg:address":"311 W Center St",
    "sg:city":"Cambridge",
    "sg:classifiers":[
        {
            "category":"Government",
            "subcategory":"Jail",
            "type":"Public Place"
        }
    ],
    "sg:phone":"+1   ",
    "sg:postcode":"61238",
    "sg:province":"IL",
    "sg:tags":[
        "correctional",
        "institution"
    ],
    "wof:name":"County Jail",
    "wof:placetype":"venue"
},
  "geometry": {"coordinates":[-90.19710600000001,41.302697],"type":"Point"}
}