{
  "type": "Feature",
  "properties": {
    "iso:country":"US",
    "sg:address":"101 N Jeffrey St",
    "sg:city":"Cooksville",
    "sg:classifiers":[
        {
            "category":"Government",
            "subcategory":"Fire Station",
            "type":"Public Place"
        }
    ],
    "sg:phone":"+1   ",
    "sg:postcode":"61730",
    "sg:province":"IL",
    "sg:tags":[
        "dept"
    ],
    "wof:name":"Cooksville Fire Dept",
    "wof:placetype":"venue"
},
  "geometry": {"coordinates":[-88.719241,40.543],"type":"Point"}
}