{
  "type": "Feature",
  "properties": {
    "addr:full":"1828 W Irving Park Rd Chicago IL 60613",
    "addr:housenumber":"1828",
    "addr:postcode":"60613",
    "addr:street":"W Irving Park Rd",
    "iso:country":"US",
    "sg:address":"1828 W Irving Park Rd",
    "sg:city":"Chicago",
    "sg:classifiers":[
        {
            "category":"Retail",
            "subcategory":"Auto Repair",
            "type":"Services"
        }
    ],
    "sg:phone":"+1 773 404 5483",
    "sg:postcode":"60613",
    "sg:province":"IL",
    "wof:name":"Ago's Auto Repair",
    "wof:placetype":"venue"
},
  "geometry": {"coordinates":[-87.675697,41.954399],"type":"Point"}
}