{
  "type": "Feature",
  "properties": {
    "addr:full":"1230 Parkview Dr Bartlett IL 60133",
    "addr:housenumber":"1230",
    "addr:postcode":"60133",
    "addr:street":"Parkview Dr",
    "iso:country":"US",
    "sg:address":"1230 Parkview Dr",
    "sg:city":"Bartlett",
    "sg:classifiers":[
        {
            "category":"Professional",
            "subcategory":"Business Services",
            "type":"Services"
        }
    ],
    "sg:phone":"+1 630 289 5640",
    "sg:postcode":"60133",
    "sg:province":"IL",
    "wof:name":"Nisha Bharti Enterprises Inc",
    "wof:placetype":"venue"
},
  "geometry": {"coordinates":[-88.13789800000001,42.009256],"type":"Point"}
}