{
  "type": "Feature",
  "properties": {
    "iso:country":"US",
    "sg:address":"1100 W Cermak Rd",
    "sg:city":"Chicago",
    "sg:classifiers":[
        {
            "category":"Arts & Performance",
            "subcategory":"Music",
            "type":"Entertainment"
        }
    ],
    "sg:phone":"+1 773 419 1738",
    "sg:postcode":"60608",
    "sg:province":"IL",
    "sg:tags":[
        "venue"
    ],
    "sg:website":"www.thelivingroomlounge.net/",
    "wof:name":"Living Room Lounge",
    "wof:placetype":"venue"
},
  "geometry": {"coordinates":[-87.653544,41.853203],"type":"Point"}
}