{
  "type": "Feature",
  "properties": {
    "addr:full":"8916 Ogden Ave Brookfield IL 60513",
    "addr:housenumber":"8916",
    "addr:postcode":"60513",
    "addr:street":"Ogden Ave",
    "iso:country":"US",
    "sg:address":"8916 Ogden Ave",
    "sg:city":"Brookfield",
    "sg:classifiers":[
        {
            "category":"Building & Trades",
            "subcategory":"Construction",
            "type":"Services"
        }
    ],
    "sg:phone":"+1 708 354 4404",
    "sg:postcode":"60513",
    "sg:province":"IL",
    "sg:tags":[
        "industrial",
        "contractor"
    ],
    "wof:name":"Garfield Ridge Contractors",
    "wof:placetype":"venue"
},
  "geometry": {"coordinates":[-87.84470399999999,41.8167],"type":"Point"}
}