{
  "type": "Feature",
  "properties": {
    "iso:country":"US",
    "sg:address":"259 Market Sq",
    "sg:city":"Lake Forest",
    "sg:classifiers":[
        {
            "category":"Health Services",
            "subcategory":"Hospital",
            "type":"Services"
        }
    ],
    "sg:phone":"+1 847 234 5970",
    "sg:postcode":"60045",
    "sg:province":"IL",
    "wof:name":"Lake Forest Hospital Trading",
    "wof:placetype":"venue"
},
  "geometry": {"coordinates":[-87.840828,42.25215],"type":"Point"}
}