{
  "type": "Feature",
  "properties": {
    "addr:full":"4337 N Lincoln Ave Chicago IL 60618",
    "addr:housenumber":"4337",
    "addr:postcode":"60618",
    "addr:street":"N Lincoln Ave",
    "iso:country":"US",
    "sg:address":"4337 N Lincoln Ave",
    "sg:city":"Chicago",
    "sg:classifiers":[
        {
            "category":"Restaurant",
            "type":"Food & Drink"
        }
    ],
    "sg:menulink":"http://www.allmenus.com/il/chicago/210017-jurys-food--drink/menu/",
    "sg:phone":"+1 773 935 2255",
    "sg:postcode":"60618",
    "sg:province":"IL",
    "sg:tags":[
        "american"
    ],
    "wof:name":"Jury's Food & Drink",
    "wof:placetype":"venue"
},
  "geometry": {"coordinates":[-87.683238,41.960509],"type":"Point"}
}