{
  "type": "Feature",
  "properties": {
    "iso:country":"US",
    "sg:address":"794 W Army Trail Rd",
    "sg:city":"Carol Stream",
    "sg:classifiers":[
        {
            "category":"Personal",
            "subcategory":"Tanning Parlor",
            "type":"Services"
        }
    ],
    "sg:phone":"+1 630 837 9400",
    "sg:postcode":"60188",
    "sg:province":"IL",
    "wof:name":"The Beach Tan Club",
    "wof:placetype":"venue"
},
  "geometry": {"coordinates":[-88.15450300000001,41.941002],"type":"Point"}
}