{
  "type": "Feature",
  "properties": {
    "addr:full":"4815 Crain St Skokie IL 60077",
    "addr:housenumber":"4815",
    "addr:postcode":"60077",
    "addr:street":"Crain St",
    "iso:country":"US",
    "sg:address":"4815 Crain St",
    "sg:city":"Skokie",
    "sg:classifiers":[
        {
            "category":"Banks & Credit Unions",
            "subcategory":"Financial Services",
            "type":"Services"
        }
    ],
    "sg:phone":"+1 847 763 8500",
    "sg:postcode":"60077",
    "sg:province":"IL",
    "sg:tags":[
        "trust",
        "investment",
        "real estate"
    ],
    "wof:name":"Ace Realty",
    "wof:placetype":"venue"
},
  "geometry": {"coordinates":[-87.74834199999999,42.038949],"type":"Point"}
}