{
  "type": "Feature",
  "properties": {
    "addr:full":"1835 Rohlwing Rd Rolling Meadows IL 60008",
    "addr:housenumber":"1835",
    "addr:postcode":"60008",
    "addr:street":"Rohlwing Rd",
    "iso:country":"US",
    "sg:address":"1835 Rohlwing Rd",
    "sg:city":"Rolling Meadows",
    "sg:classifiers":[
        {
            "category":"Real Estate",
            "subcategory":"Architect",
            "type":"Services"
        }
    ],
    "sg:phone":"+1 847 704 3200",
    "sg:postcode":"60008",
    "sg:province":"IL",
    "sg:tags":[
        "architectural"
    ],
    "wof:name":"Robert Flubacker Architect Ltd",
    "wof:placetype":"venue"
},
  "geometry": {"coordinates":[-88.026793,42.090598],"type":"Point"}
}