{
  "type": "Feature",
  "properties": {
    "addr:full":"1500 E New York St Aurora IL 60505",
    "addr:housenumber":"1500",
    "addr:postcode":"60505",
    "addr:street":"E New York St",
    "iso:country":"US",
    "sg:address":"1500 E New York St",
    "sg:city":"Aurora",
    "sg:classifiers":[
        {
            "category":"Restaurant",
            "type":"Food & Drink"
        }
    ],
    "sg:phone":"+1 630 499 8180",
    "sg:postcode":"60505",
    "sg:province":"IL",
    "wof:name":"Taco Mobile",
    "wof:placetype":"venue"
},
  "geometry": {"coordinates":[-88.28077500000001,41.756527],"type":"Point"}
}