{
  "type": "Feature",
  "properties": {
    "iso:country":"US",
    "sg:address":"497 Whispering Pines Rd",
    "sg:city":"Lindenhurst",
    "sg:classifiers":[
        {
            "category":"Professional",
            "subcategory":"Computer Services",
            "type":"Services"
        }
    ],
    "sg:phone":"+1 847 784 8270",
    "sg:postcode":"60046",
    "sg:province":"IL",
    "wof:name":"Balance Point Technologies Inc",
    "wof:placetype":"venue"
},
  "geometry": {"coordinates":[-88.023982,42.426679],"type":"Point"}
}