{
  "type": "Feature",
  "properties": {
    "addr:full":"3170 Macarthur Blvd Northbrook IL 60062",
    "addr:housenumber":"3170",
    "addr:postcode":"60062",
    "addr:street":"Macarthur Blvd",
    "iso:country":"US",
    "sg:address":"3170 Macarthur Blvd",
    "sg:city":"Northbrook",
    "sg:classifiers":[
        {
            "category":"Manufacturing",
            "subcategory":"Printing",
            "type":"Manufacturing & Wholesale Goods"
        }
    ],
    "sg:phone":"+1 847 562 9292",
    "sg:postcode":"60062",
    "sg:province":"IL",
    "sg:tags":[
        "publisher",
        "art",
        "fine"
    ],
    "wof:name":"Chesley LLC",
    "wof:placetype":"venue"
},
  "geometry": {"coordinates":[-87.854111,42.148362],"type":"Point"}
}