{
  "type": "Feature",
  "properties": {
    "iso:country":"US",
    "sg:address":"2401 Delta Ln",
    "sg:city":"Elk Grove Village",
    "sg:classifiers":[
        {
            "category":"Wholesale",
            "subcategory":"Electrical",
            "type":"Manufacturing & Wholesale Goods"
        }
    ],
    "sg:phone":"+1 847 350 1100",
    "sg:postcode":"60007",
    "sg:province":"IL",
    "sg:tags":[
        "video",
        "television",
        "r",
        "appliance",
        "cassette"
    ],
    "wof:name":"A & J Distributors Inc",
    "wof:placetype":"venue"
},
  "geometry": {"coordinates":[-87.941833,41.988674],"type":"Point"}
}