{
  "type": "Feature",
  "properties": {
    "iso:country":"US",
    "sg:address":"645 McKinney Hill Ln",
    "sg:city":"Carbondale",
    "sg:classifiers":[
        {
            "category":"Food & Beverages",
            "subcategory":"Specialty",
            "type":"Retail Goods"
        }
    ],
    "sg:phone":"+1 618 549 7844",
    "sg:postcode":"62901",
    "sg:province":"IL",
    "sg:tags":[
        "vitamin"
    ],
    "wof:name":"Mannatech Distributor",
    "wof:placetype":"venue"
},
  "geometry": {"coordinates":[-89.150489,37.75525],"type":"Point"}
}