{
  "type": "Feature",
  "properties": {
    "addr:full":"2249 S 24th Ave Broadview IL 60155",
    "addr:housenumber":"2249",
    "addr:postcode":"60155",
    "addr:street":"S 24Th Ave",
    "iso:country":"US",
    "sg:address":"2249 S 24th Ave",
    "sg:city":"Broadview",
    "sg:classifiers":[
        {
            "category":"Real Estate",
            "subcategory":"Real Estate Agent",
            "type":"Services"
        }
    ],
    "sg:phone":"+1 708 344 6605",
    "sg:postcode":"60155",
    "sg:province":"IL",
    "wof:name":"Teller Williams & Assoc R",
    "wof:placetype":"venue"
},
  "geometry": {"coordinates":[-87.861554,41.862955],"type":"Point"}
}