{
  "type": "Feature",
  "properties": {
    "addr:full":"2917 N Vermilion St Danville IL 61832",
    "addr:housenumber":"2917",
    "addr:postcode":"61832",
    "addr:street":"N Vermilion St",
    "iso:country":"US",
    "sg:address":"2917 N Vermilion St",
    "sg:city":"Danville",
    "sg:phone":"+1 217 442 6814",
    "sg:postcode":"61832",
    "sg:province":"IL",
    "sg:website":"http://www.fancythatbridalshop.com",
    "wof:name":"Fancy That",
    "wof:placetype":"venue"
},
  "geometry": {"coordinates":[-87.630696,40.172144],"type":"Point"}
}