{
  "type": "Feature",
  "properties": {
    "addr:full":"707 Center St Augusta IL 62311",
    "addr:housenumber":"707",
    "addr:postcode":"62311",
    "addr:street":"Center St",
    "iso:country":"US",
    "sg:address":"707 Center St",
    "sg:city":"Augusta",
    "sg:classifiers":[
        {
            "category":"Transit Center",
            "subcategory":"Freight",
            "type":"Transportation"
        },
        {
            "category":"Freight",
            "type":"Transportation"
        }
    ],
    "sg:phone":"+1 217 392 2500",
    "sg:postcode":"62311",
    "sg:province":"IL",
    "sg:tags":[
        "trucking-motor",
        "trucking"
    ],
    "wof:name":"Orris' Trucking Inc",
    "wof:placetype":"venue"
},
  "geometry": {"coordinates":[-90.94975100000001,40.236736],"type":"Point"}
}