{
  "type": "Feature",
  "properties": {
    "iso:country":"US",
    "sg:address":"850 Mark St",
    "sg:city":"Elk Grove Vlg",
    "sg:classifiers":[
        {
            "category":"Professional",
            "subcategory":"Art Services",
            "type":"Services"
        }
    ],
    "sg:phone":"+1 847 787 0340",
    "sg:postcode":"60007",
    "sg:province":"IL",
    "sg:tags":[
        "development",
        "package",
        "designing"
    ],
    "sg:website":"www.chickpackaging.com",
    "wof:name":"Chick Packaging Group",
    "wof:placetype":"venue"
},
  "geometry": {"coordinates":[-87.974007,41.988369],"type":"Point"}
}