{
  "type": "Feature",
  "properties": {
    "addr:full":"650 E Main St Lake Zurich IL 60047",
    "addr:housenumber":"650",
    "addr:postcode":"60047",
    "addr:street":"E Main St",
    "iso:country":"US",
    "sg:address":"650 E Main St",
    "sg:city":"Lake Zurich",
    "sg:classifiers":[
        {
            "category":"Restaurant",
            "type":"Food & Drink"
        }
    ],
    "sg:phone":"+1 847 438 4288",
    "sg:postcode":"60047",
    "sg:province":"IL",
    "wof:name":"Hunan Wing",
    "wof:placetype":"venue"
},
  "geometry": {"coordinates":[-88.083257,42.197551],"type":"Point"}
}