{
  "type": "Feature",
  "properties": {
    "addr:full":"8305 Bluff St East Saint Louis IL 62203",
    "addr:housenumber":"8305",
    "addr:postcode":"62203",
    "addr:street":"Bluff St",
    "iso:country":"US",
    "sg:address":"8305 Bluff St",
    "sg:city":"East Saint Louis",
    "sg:classifiers":[
        {
            "category":"Organizations",
            "subcategory":"Religious Organization",
            "type":"Services"
        }
    ],
    "sg:phone":"+1 618 398 5203",
    "sg:postcode":"62203",
    "sg:province":"IL",
    "wof:name":"Church of Grace",
    "wof:placetype":"venue"
},
  "geometry": {"coordinates":[-90.072304,38.586102],"type":"Point"}
}