{
  "type": "Feature",
  "properties": {
    "iso:country":"US",
    "sg:address":"406 N Beech St",
    "sg:city":"Normal",
    "sg:classifiers":[
        {
            "category":"Autos & Motor Vehicles",
            "subcategory":"Automobile Sales",
            "type":"Retail Goods"
        }
    ],
    "sg:phone":"+1 309 452 7398",
    "sg:postcode":"61761",
    "sg:province":"IL",
    "sg:tags":[
        "new",
        "car"
    ],
    "wof:name":"Exotic Autos",
    "wof:placetype":"venue"
},
  "geometry": {"coordinates":[-88.977722,40.513304],"type":"Point"}
}