{
  "type": "Feature",
  "properties": {
    "iso:country":"US",
    "sg:address":"1148 Saddle Ridge Trl",
    "sg:city":"Cary",
    "sg:classifiers":[
        {
            "category":"Retail",
            "subcategory":"Funeral Services",
            "type":"Services"
        }
    ],
    "sg:phone":"+1 847 639 9750",
    "sg:postcode":"60013",
    "sg:province":"IL",
    "sg:tags":[
        "crematory"
    ],
    "wof:name":"Jos J Ewald",
    "wof:placetype":"venue"
},
  "geometry": {"coordinates":[-88.268632,42.211932],"type":"Point"}
}