{
  "type": "Feature",
  "properties": {
    "iso:country":"US",
    "sg:address":"122 S River St",
    "sg:city":"Aurora",
    "sg:classifiers":[
        {
            "category":"Autos & Motor Vehicles",
            "subcategory":"Auto Supplies",
            "type":"Retail Goods"
        }
    ],
    "sg:phone":"+1 630 892 9606",
    "sg:postcode":"60506",
    "sg:province":"IL",
    "sg:tags":[
        "wheel",
        "part",
        "automobile"
    ],
    "wof:name":"P Q Custom Wheels",
    "wof:placetype":"venue"
},
  "geometry": {"coordinates":[-88.319835,41.756815],"type":"Point"}
}