{
  "type": "Feature",
  "properties": {
    "addr:full":"3989 Pearl Street Rd Belvidere IL 61008",
    "addr:housenumber":"3989",
    "addr:postcode":"61008",
    "addr:street":"Pearl Street Rd",
    "iso:country":"US",
    "sg:address":"3989 Pearl Street Rd",
    "sg:city":"Belvidere",
    "sg:classifiers":[
        {
            "category":"Food & Beverages",
            "subcategory":"Bakery",
            "type":"Retail Goods"
        }
    ],
    "sg:phone":"+1   ",
    "sg:postcode":"61008",
    "sg:province":"IL",
    "wof:name":"Happy Hound Bakery",
    "wof:placetype":"venue"
},
  "geometry": {"coordinates":[-88.84169199999999,42.208646],"type":"Point"}
}