{
  "type": "Feature",
  "properties": {
    "iso:country":"US",
    "sg:address":"592 N Schuyler Ave",
    "sg:city":"Kankakee",
    "sg:classifiers":[
        {
            "category":"Bars & Pubs",
            "type":"Food & Drink"
        }
    ],
    "sg:phone":"+1 815 935 2642",
    "sg:postcode":"60901",
    "sg:province":"IL",
    "sg:tags":[
        "drinking"
    ],
    "wof:name":"Coretta's Corner",
    "wof:placetype":"venue"
},
  "geometry": {"coordinates":[-87.862809,41.125678],"type":"Point"}
}