{
  "type": "Feature",
  "properties": {
    "addr:full":"425 Arlington Heights Rd Arlington Heights IL 60005",
    "addr:housenumber":"425",
    "addr:postcode":"60005",
    "addr:street":"Arlington Heights Rd",
    "iso:country":"US",
    "sg:address":"425 Arlington Heights Rd",
    "sg:city":"Arlington Heights",
    "sg:classifiers":[
        {
            "category":"Wholesale",
            "subcategory":"Machinery & Supplies",
            "type":"Manufacturing & Wholesale Goods"
        }
    ],
    "sg:phone":"+1 847 437 4195",
    "sg:postcode":"60005",
    "sg:province":"IL",
    "sg:tags":[
        "sales"
    ],
    "wof:name":"A M Multigraphics",
    "wof:placetype":"venue"
},
  "geometry": {"coordinates":[-87.980462,42.076007],"type":"Point"}
}