{
  "type": "Feature",
  "properties": {
    "iso:country":"US",
    "sg:address":"6 Whiteside Dr",
    "sg:city":"Belleville",
    "sg:classifiers":[
        {
            "category":"Organizations",
            "subcategory":"Community Association",
            "type":"Services"
        }
    ],
    "sg:phone":"+1 618 233 5884",
    "sg:postcode":"62221",
    "sg:province":"IL",
    "wof:name":"Military Order of World Wars",
    "wof:placetype":"venue"
},
  "geometry": {"coordinates":[-89.954012,38.543238],"type":"Point"}
}