{
  "type": "Feature",
  "properties": {
    "iso:country":"US",
    "sg:address":"11400 Lincoln Hwy",
    "sg:city":"Mokena",
    "sg:classifiers":[
        {
            "category":"Restaurant",
            "type":"Food & Drink"
        }
    ],
    "sg:phone":"+1 815 806 8282",
    "sg:postcode":"60448",
    "sg:province":"IL",
    "sg:tags":[
        "style",
        "italian",
        "family",
        "pizza"
    ],
    "wof:name":"Giordano's Of Mokena",
    "wof:placetype":"venue"
},
  "geometry": {"coordinates":[-87.89582799999999,41.504589],"type":"Point"}
}