{
  "type": "Feature",
  "properties": {
    "iso:country":"US",
    "sg:address":"3998 S Knoll Rd",
    "sg:city":"Rochelle",
    "sg:classifiers":[
        {
            "category":"Travel",
            "subcategory":"Campground",
            "type":"Entertainment"
        }
    ],
    "sg:phone":"+1 815 562 4990",
    "sg:postcode":"61068",
    "sg:province":"IL",
    "sg:tags":[
        "camp"
    ],
    "wof:name":"Boy Scouts Of America",
    "wof:placetype":"venue"
},
  "geometry": {"coordinates":[-89.166573,41.961937],"type":"Point"}
}