{
  "type": "Feature",
  "properties": {
    "addr:full":"1649 Heal Rd Malta IL 60150",
    "addr:housenumber":"1649",
    "addr:postcode":"60150",
    "addr:street":"Heal Rd",
    "iso:country":"US",
    "sg:address":"1649 Heal Rd",
    "sg:city":"Malta",
    "sg:classifiers":[
        {
            "category":"Manufacturing",
            "subcategory":"Food",
            "type":"Manufacturing & Wholesale Goods"
        },
        {
            "category":"Farming",
            "subcategory":"Farm",
            "type":"Manufacturing & Wholesale Goods"
        }
    ],
    "sg:phone":"+1 815 825 2277",
    "sg:postcode":"60150",
    "sg:province":"IL",
    "sg:tags":[
        "corn",
        "product"
    ],
    "wof:name":"Barry Montgomery",
    "wof:placetype":"venue"
},
  "geometry": {"coordinates":[-88.915783,41.964374],"type":"Point"}
}