{
  "type": "Feature",
  "properties": {
    "addr:full":"960 Winstead Rd Cobden IL 62920",
    "addr:housenumber":"960",
    "addr:postcode":"62920",
    "addr:street":"Winstead Rd",
    "iso:country":"US",
    "sg:address":"960 Winstead Rd",
    "sg:city":"Cobden",
    "sg:classifiers":[
        {
            "category":"Building & Trades",
            "subcategory":"Landscaping Services",
            "type":"Services"
        }
    ],
    "sg:phone":"+1 618 893 2828",
    "sg:postcode":"62920",
    "sg:province":"IL",
    "sg:tags":[
        "landscape",
        "contractor"
    ],
    "wof:name":"Greenridge Landscaping",
    "wof:placetype":"venue"
},
  "geometry": {"coordinates":[-89.283855,37.580281],"type":"Point"}
}