{
  "type": "Feature",
  "properties": {
    "addr:full":"12810 W Beach Rd Beach Park IL 60087",
    "addr:housenumber":"12810",
    "addr:postcode":"60087",
    "addr:street":"W Beach Rd",
    "iso:country":"US",
    "sg:address":"12810 W Beach Rd",
    "sg:city":"Beach Park",
    "sg:classifiers":[
        {
            "category":"Building & Trades",
            "subcategory":"Construction",
            "type":"Services"
        }
    ],
    "sg:phone":"+1 847 244 2542",
    "sg:postcode":"60087",
    "sg:province":"IL",
    "sg:tags":[
        "dry wall",
        "contractor"
    ],
    "wof:name":"Carl's Plastering",
    "wof:placetype":"venue"
},
  "geometry": {"coordinates":[-87.885678,42.421159],"type":"Point"}
}