{
  "type": "Feature",
  "properties": {
    "addr:full":"601 W 80th St Chicago IL 60620",
    "addr:housenumber":"601",
    "addr:postcode":"60620",
    "addr:street":"W 80Th St",
    "iso:country":"US",
    "sg:address":"601 W 80th St",
    "sg:city":"Chicago",
    "sg:classifiers":[
        {
            "category":"Food & Beverages",
            "subcategory":"Dairy",
            "type":"Retail Goods"
        }
    ],
    "sg:phone":"+1 773 846 7300",
    "sg:postcode":"60620",
    "sg:province":"IL",
    "sg:tags":[
        "products-wholesale"
    ],
    "wof:name":"National Casein Sales",
    "wof:placetype":"venue"
},
  "geometry": {"coordinates":[-87.63902299999999,41.748878],"type":"Point"}
}