{
  "type": "Feature",
  "properties": {
    "addr:full":"7222 S Richmond St Chicago IL 60629",
    "addr:housenumber":"7222",
    "addr:postcode":"60629",
    "addr:street":"S Richmond St",
    "iso:country":"US",
    "sg:address":"7222 S Richmond St",
    "sg:city":"Chicago",
    "sg:classifiers":[
        {
            "category":"Home & Garden",
            "subcategory":"Home Furnishings",
            "type":"Retail Goods"
        }
    ],
    "sg:phone":"+1 773 436 9344",
    "sg:postcode":"60629",
    "sg:province":"IL",
    "sg:tags":[
        "candle"
    ],
    "wof:name":"Noo Noo's House Of Scents",
    "wof:placetype":"venue"
},
  "geometry": {"coordinates":[-87.69662599999999,41.762235],"type":"Point"}
}