{
  "type": "Feature",
  "properties": {
    "iso:country":"US",
    "sg:address":"670 E Main St",
    "sg:city":"Lake Zurich",
    "sg:classifiers":[
        {
            "category":"Restaurant",
            "type":"Food & Drink"
        }
    ],
    "sg:phone":"+1 847 540 6836",
    "sg:postcode":"60047",
    "sg:province":"IL",
    "wof:name":"Ricci's Ult Dog",
    "wof:placetype":"venue"
},
  "geometry": {"coordinates":[-88.074062,42.197511],"type":"Point"}
}