{
  "type": "Feature",
  "properties": {
    "addr:full":"6600 W 127th St Palos Heights IL 60463",
    "addr:housenumber":"6600",
    "addr:postcode":"60463",
    "addr:street":"W 127Th St",
    "iso:country":"US",
    "sg:address":"6600 W 127th St",
    "sg:city":"Palos Heights",
    "sg:classifiers":[
        {
            "category":"Organizations",
            "subcategory":"Religious Organization",
            "type":"Services"
        }
    ],
    "sg:phone":"+1 708 388 5485",
    "sg:postcode":"60463",
    "sg:province":"IL",
    "wof:name":"Christ Community Church",
    "wof:placetype":"venue"
},
  "geometry": {"coordinates":[-87.782799,41.660999],"type":"Point"}
}