{
  "type": "Feature",
  "properties": {
    "addr:full":"4308 N Pulaski Rd Chicago IL 60641",
    "addr:housenumber":"4308",
    "addr:postcode":"60641",
    "addr:street":"N Pulaski Rd",
    "iso:country":"US",
    "sg:address":"4308 N Pulaski Rd",
    "sg:city":"Chicago",
    "sg:classifiers":[
        {
            "category":"Home & Garden",
            "subcategory":"Building Materials",
            "type":"Retail Goods"
        }
    ],
    "sg:phone":"+1 773 725 2218",
    "sg:postcode":"60641",
    "sg:province":"IL",
    "sg:tags":[
        "glass",
        "leaded"
    ],
    "wof:name":"Fredrick Stained Glass",
    "wof:placetype":"venue"
},
  "geometry": {"coordinates":[-87.727858,41.959393],"type":"Point"}
}