{
  "type": "Feature",
  "properties": {
    "addr:full":"1750 E 78th St Chicago IL 60649",
    "addr:housenumber":"1750",
    "addr:postcode":"60649",
    "addr:street":"E 78Th St",
    "iso:country":"US",
    "sg:address":"1750 E 78th St",
    "sg:city":"Chicago",
    "sg:classifiers":[
        {
            "category":"Organizations",
            "subcategory":"Religious Organization",
            "type":"Services"
        }
    ],
    "sg:phone":"+1 773 978 0947",
    "sg:postcode":"60649",
    "sg:province":"IL",
    "sg:tags":[
        "church"
    ],
    "wof:name":"New Original Church of God In Christ",
    "wof:placetype":"venue"
},
  "geometry": {"coordinates":[-87.581596,41.753502],"type":"Point"}
}