{
  "type": "Feature",
  "properties": {
    "iso:country":"US",
    "sg:address":"1922 W. Montrose Ave.",
    "sg:city":"Chicago",
    "sg:classifiers":[
        {
            "category":"Sports & Exercise",
            "subcategory":"Playing Field",
            "type":"Entertainment"
        }
    ],
    "sg:phone":"+1 773 275 5992",
    "sg:postcode":"60613",
    "sg:province":"IL",
    "sg:tags":[
        "chi",
        "tai"
    ],
    "sg:website":"illinois.usa.taoist.org",
    "wof:name":"Taoist Tai Chi Society - Chicago Center",
    "wof:placetype":"venue"
},
  "geometry": {"coordinates":[-87.676473,41.9615],"type":"Point"}
}