{
  "type": "Feature",
  "properties": {
    "iso:country":"US",
    "sg:address":"26507 W Countryside Ln",
    "sg:city":"Plainfield",
    "sg:classifiers":[
        {
            "category":"Real Estate",
            "subcategory":"Real Estate Operator",
            "type":"Services"
        }
    ],
    "sg:phone":"+1 815 267 8686",
    "sg:postcode":"60585",
    "sg:province":"IL",
    "sg:tags":[
        "apartment"
    ],
    "wof:name":"Chatham Square Townhomes",
    "wof:placetype":"venue"
},
  "geometry": {"coordinates":[-88.262085,41.655433],"type":"Point"}
}