{
  "type": "Feature",
  "properties": {
    "iso:country":"US",
    "sg:address":"622 E Golf Rd",
    "sg:city":"Schaumburg",
    "sg:classifiers":[
        {
            "category":"Bakery",
            "type":"Food & Drink"
        }
    ],
    "sg:menulink":"http://www.allmenus.com/il/schaumburg/103398-panera-bread/menu/",
    "sg:phone":"+1 847 781 1800",
    "sg:postcode":"60173",
    "sg:province":"IL",
    "sg:tags":[
        "american",
        "sandwich",
        "pastry"
    ],
    "wof:name":"Panera Bread",
    "wof:placetype":"venue"
},
  "geometry": {"coordinates":[-88.064831,42.049988],"type":"Point"}
}