{
  "type": "Feature",
  "properties": {
    "iso:country":"US",
    "sg:address":"6341 N Kedzie Ave",
    "sg:city":"Chicago",
    "sg:classifiers":[
        {
            "category":"Organizations",
            "subcategory":"Religious Organization",
            "type":"Services"
        }
    ],
    "sg:phone":"+1 773 764 8881",
    "sg:postcode":"60659",
    "sg:province":"IL",
    "wof:name":"Sam Raitzik Rev",
    "wof:placetype":"venue"
},
  "geometry": {"coordinates":[-87.709239,41.9962],"type":"Point"}
}