{
  "type": "Feature",
  "properties": {
    "addr:full":"1113 N Main St Normal IL 61761",
    "addr:housenumber":"1113",
    "addr:postcode":"61761",
    "addr:street":"N Main St",
    "iso:country":"US",
    "sg:address":"1113 N Main St",
    "sg:city":"Normal",
    "sg:classifiers":[
        {
            "category":"Restaurant",
            "type":"Food & Drink"
        }
    ],
    "sg:menulink":"http://www.allmenus.com/il/normal/151607-aw-restaurant/menu/",
    "sg:phone":"+1 309 452 4444",
    "sg:postcode":"61761",
    "sg:province":"IL",
    "sg:tags":[
        "burger",
        "american",
        "dog",
        "pub",
        "hot"
    ],
    "wof:name":"A&W Restaurant",
    "wof:placetype":"venue"
},
  "geometry": {"coordinates":[-88.995357,40.524824],"type":"Point"}
}