{
  "type": "Feature",
  "properties": {
    "addr:full":"1415 S Barrington Rd Barrington IL 60010",
    "addr:housenumber":"1415",
    "addr:postcode":"60010",
    "addr:street":"S Barrington Rd",
    "iso:country":"US",
    "sg:address":"1415 S Barrington Rd",
    "sg:city":"Barrington",
    "sg:classifiers":[
        {
            "category":"Real Estate",
            "subcategory":"Architect",
            "type":"Services"
        }
    ],
    "sg:phone":"+1 847 381 1190",
    "sg:postcode":"60010",
    "sg:province":"IL",
    "sg:tags":[
        "architectural"
    ],
    "wof:name":"Reed Architect LLC",
    "wof:placetype":"venue"
},
  "geometry": {"coordinates":[-88.144594,42.061644],"type":"Point"}
}