{
  "type": "Feature",
  "properties": {
    "iso:country":"US",
    "sg:address":"9412 W 143rd St",
    "sg:city":"Orland Park",
    "sg:classifiers":[
        {
            "category":"Professional",
            "subcategory":"Business Services",
            "type":"Services"
        }
    ],
    "sg:phone":"+1 708 349 7789",
    "sg:postcode":"60462",
    "sg:province":"IL",
    "wof:name":"Sir Speedy",
    "wof:placetype":"venue"
},
  "geometry": {"coordinates":[-87.851425,41.630597],"type":"Point"}
}