{
  "type": "Feature",
  "properties": {
    "iso:country":"US",
    "sg:address":"1100 E Roosevelt Rd",
    "sg:city":"Wheaton",
    "sg:classifiers":[
        {
            "category":"Autos & Motor Vehicles",
            "subcategory":"Automobile Sales",
            "type":"Retail Goods"
        }
    ],
    "sg:phone":"+1   ",
    "sg:postcode":"60187",
    "sg:province":"IL",
    "sg:tags":[
        "new",
        "used"
    ],
    "wof:name":"Suburban Buick Company",
    "wof:placetype":"venue"
},
  "geometry": {"coordinates":[-88.090491,41.858923],"type":"Point"}
}