{
  "type": "Feature",
  "properties": {
    "addr:full":"925 Fairway Park Dr Madison IL 62060",
    "addr:housenumber":"925",
    "addr:postcode":"62060",
    "addr:street":"Fairway Park Dr",
    "iso:country":"US",
    "sg:address":"925 Fairway Park Dr",
    "sg:city":"Madison",
    "sg:classifiers":[
        {
            "category":"Shopping",
            "subcategory":"Bicycles & Sporting Goods",
            "type":"Retail Goods"
        },
        {
            "category":"Wholesale",
            "subcategory":"Chemicals & Plastics",
            "type":"Manufacturing & Wholesale Goods"
        },
        {
            "category":"Government",
            "subcategory":"Post Office",
            "type":"Public Place"
        }
    ],
    "sg:phone":"+1 618 271 1850",
    "sg:postcode":"62060",
    "sg:province":"IL",
    "sg:tags":[
        "supply",
        "equipment",
        "distributor",
        "manufacturer",
        "supplies-wholesale",
        "pool",
        "swimming"
    ],
    "sg:website":"http://www.atyourservicepools.com",
    "wof:name":"South Central Pool 75",
    "wof:placetype":"venue"
},
  "geometry": {"coordinates":[-90.153859,38.658337],"type":"Point"}
}