{
  "type": "Feature",
  "properties": {
    "iso:country":"US",
    "sg:address":"2235 Hammond Dr",
    "sg:city":"Schaumburg",
    "sg:classifiers":[
        {
            "category":"Professional",
            "subcategory":"Printing & Photocopies",
            "type":"Services"
        }
    ],
    "sg:phone":"+1 847 925 0023",
    "sg:postcode":"60173",
    "sg:province":"IL",
    "sg:tags":[
        "photographers-commercial"
    ],
    "wof:name":"Gl Technology Inc",
    "wof:placetype":"venue"
},
  "geometry": {"coordinates":[-88.060017,42.068543],"type":"Point"}
}