{
  "type": "Feature",
  "properties": {
    "iso:country":"US",
    "sg:address":"4811 W State St",
    "sg:city":"Rockford",
    "sg:classifiers":[
        {
            "category":"Retail",
            "subcategory":"Auto Rental",
            "type":"Services"
        }
    ],
    "sg:phone":"+1 815 968 8988",
    "sg:postcode":"61102",
    "sg:province":"IL",
    "sg:tags":[
        "truck",
        "trailer",
        "utility"
    ],
    "wof:name":"U-Haul",
    "wof:placetype":"venue"
},
  "geometry": {"coordinates":[-89.162333,42.27879],"type":"Point"}
}