{
  "type": "Feature",
  "properties": {
    "addr:full":"516 Chester Ave Danville IL 61832",
    "addr:housenumber":"516",
    "addr:postcode":"61832",
    "addr:street":"Chester Ave",
    "iso:country":"US",
    "sg:address":"516 Chester Ave",
    "sg:city":"Danville",
    "sg:classifiers":[
        {
            "category":"Organizations",
            "subcategory":"Community Association",
            "type":"Services"
        }
    ],
    "sg:phone":"+1 217 446 3788",
    "sg:postcode":"61832",
    "sg:province":"IL",
    "sg:tags":[
        "membership"
    ],
    "wof:name":"National Society Daughters",
    "wof:placetype":"venue"
},
  "geometry": {"coordinates":[-87.624145,40.161819],"type":"Point"}
}