{
  "type": "Feature",
  "properties": {
    "iso:country":"US",
    "sg:address":"817 Lake St",
    "sg:city":"Oak Park",
    "sg:classifiers":[
        {
            "category":"Professional",
            "subcategory":"Computer Services",
            "type":"Services"
        }
    ],
    "sg:phone":"+1 708 386 8300",
    "sg:postcode":"60301",
    "sg:province":"IL",
    "sg:tags":[
        "related"
    ],
    "sg:website":"www.equitek.com",
    "wof:name":"Equitek Inc",
    "wof:placetype":"venue"
},
  "geometry": {"coordinates":[-87.795576,41.888587],"type":"Point"}
}