{
  "type": "Feature",
  "properties": {
    "iso:country":"US",
    "sg:address":"4045 W Lawrence Avenue",
    "sg:city":"Chicago",
    "sg:classifiers":[
        {
            "category":"Bakery",
            "type":"Food & Drink"
        }
    ],
    "sg:phone":"+1 773 427 9777",
    "sg:postcode":"60630",
    "sg:province":"IL",
    "wof:name":"Gul Foods",
    "wof:placetype":"venue"
},
  "geometry": {"coordinates":[-87.72999900000001,41.968005],"type":"Point"}
}