{
  "type": "Feature",
  "properties": {
    "iso:country":"US",
    "sg:address":"848 Geneva Ct",
    "sg:city":"Elmhurst",
    "sg:classifiers":[
        {
            "category":"Building & Trades",
            "subcategory":"Construction",
            "type":"Services"
        }
    ],
    "sg:phone":"+1 630 530 2825",
    "sg:postcode":"60126",
    "sg:province":"IL",
    "sg:tags":[
        "concrete",
        "contractor"
    ],
    "wof:name":"Salcon Concrete Construction",
    "wof:placetype":"venue"
},
  "geometry": {"coordinates":[-87.926438,41.923542],"type":"Point"}
}