{
  "type": "Feature",
  "properties": {
    "iso:country":"US",
    "sg:address":"10710 N Main St",
    "sg:city":"Richmond",
    "sg:classifiers":[
        {
            "category":"Restaurant",
            "type":"Food & Drink"
        }
    ],
    "sg:menulink":"http://www.allmenus.com/il/richmond/196305-taco-bell/menu/",
    "sg:postcode":"60071",
    "sg:province":"IL",
    "sg:tags":[
        "mexican"
    ],
    "wof:name":"Taco Bell",
    "wof:placetype":"venue"
},
  "geometry": {"coordinates":[-88.306089,42.481616],"type":"Point"}
}