{
  "type": "Feature",
  "properties": {
    "iso:country":"US",
    "sg:address":"702 S Washington St",
    "sg:city":"Bunker Hill",
    "sg:classifiers":[
        {
            "category":"Retail",
            "subcategory":"Storage",
            "type":"Services"
        },
        {
            "category":"Food & Beverages",
            "subcategory":"Groceries & Convenience Stores",
            "type":"Retail Goods"
        }
    ],
    "sg:phone":"+1 618 585 4514",
    "sg:postcode":"62014",
    "sg:province":"IL",
    "sg:tags":[
        "self"
    ],
    "wof:name":"Bunker Hill Self-Storage",
    "wof:placetype":"venue"
},
  "geometry": {"coordinates":[-89.951599,39.0368],"type":"Point"}
}