{
  "type": "Feature",
  "properties": {
    "iso:country":"US",
    "sg:address":"19816 N 700th St",
    "sg:city":"Annapolis",
    "sg:classifiers":[
        {
            "category":"Retail",
            "subcategory":"Auto Repair",
            "type":"Services"
        }
    ],
    "sg:phone":"+1 618 569 9275",
    "sg:postcode":"62413",
    "sg:province":"IL",
    "sg:tags":[
        "body",
        "automobile",
        "painting"
    ],
    "wof:name":"Rick's Auto Body & Paint",
    "wof:placetype":"venue"
},
  "geometry": {"coordinates":[-87.81627400000001,39.118007],"type":"Point"}
}