{
  "type": "Feature",
  "properties": {
    "iso:country":"US",
    "sg:address":"1137 W Bryn Mawr Ave",
    "sg:city":"Chicago",
    "sg:classifiers":[
        {
            "category":"Home & Garden",
            "subcategory":"Household Appliances",
            "type":"Retail Goods"
        }
    ],
    "sg:phone":"+1 773 340 2484",
    "sg:postcode":"60640",
    "sg:province":"IL",
    "sg:tags":[
        "repair"
    ],
    "sg:website":"www.affordableservicesclub.com",
    "wof:name":"Affordable Services Club",
    "wof:placetype":"venue"
},
  "geometry": {"coordinates":[-87.659178,41.98362],"type":"Point"}
}