{
  "type": "Feature",
  "properties": {
    "iso:country":"US",
    "sg:address":"1201 Park Ave",
    "sg:city":"River Forest",
    "sg:classifiers":[
        {
            "category":"Building & Trades",
            "subcategory":"Construction",
            "type":"Services"
        }
    ],
    "sg:phone":"+1 708 366 6733",
    "sg:postcode":"60305",
    "sg:province":"IL",
    "sg:tags":[
        "concrete",
        "contractor"
    ],
    "wof:name":"A-1 Concrete Leveling",
    "wof:placetype":"venue"
},
  "geometry": {"coordinates":[-87.820223,41.90433],"type":"Point"}
}