{
  "type": "Feature",
  "properties": {
    "addr:full":"200 South Wacker Drive Sutie 1500 Chicago IL 60606",
    "addr:housenumber":"200;1500",
    "addr:postcode":"60606",
    "addr:street":"South Wacker Drive",
    "iso:country":"US",
    "sg:address":"200 South Wacker Drive Sutie 1500",
    "sg:city":"Chicago",
    "sg:classifiers":[
        {
            "category":"Professional",
            "subcategory":"Computer Services",
            "type":"Services"
        }
    ],
    "sg:phone":"+1 312 857 5003",
    "sg:postcode":"60606",
    "sg:province":"IL",
    "sg:tags":[
        "business-intelligence",
        "business-analytics",
        "hosted-business-intelligence",
        "hosted-database",
        "hosted-analytics"
    ],
    "sg:website":"http://www.decisivebi.com",
    "wof:name":"Decisive BI",
    "wof:placetype":"venue"
},
  "geometry": {"coordinates":[-87.63667599999999,41.878752],"type":"Point"}
}