{
  "type": "Feature",
  "properties": {
    "addr:full":"5011 W Cermak Rd Cicero IL 60804",
    "addr:housenumber":"5011",
    "addr:postcode":"60804",
    "addr:street":"W Cermak Rd",
    "iso:country":"US",
    "sg:address":"5011 W Cermak Rd",
    "sg:city":"Cicero",
    "sg:classifiers":[
        {
            "category":"Real Estate",
            "subcategory":"Real Estate Agent",
            "type":"Services"
        }
    ],
    "sg:phone":"+1 708 652 9163",
    "sg:postcode":"60804",
    "sg:province":"IL",
    "sg:tags":[
        "manager"
    ],
    "wof:name":"Reno Mangemnet",
    "wof:placetype":"venue"
},
  "geometry": {"coordinates":[-87.751437,41.851159],"type":"Point"}
}