{
  "type": "Feature",
  "properties": {
    "iso:country":"US",
    "sg:address":"2416 Garden St",
    "sg:city":"Joliet",
    "sg:classifiers":[
        {
            "category":"Retail",
            "subcategory":"Repair Shop",
            "type":"Services"
        }
    ],
    "sg:phone":"+1 815 436 1325",
    "sg:postcode":"60435",
    "sg:province":"IL",
    "sg:tags":[
        "appliance",
        "electrical"
    ],
    "wof:name":"A-Dave's Appliance Repair",
    "wof:placetype":"venue"
},
  "geometry": {"coordinates":[-88.147332,41.572922],"type":"Point"}
}