{
  "type": "Feature",
  "properties": {
    "addr:full":"4100 N Long Avenue Chicago IL 60641",
    "addr:housenumber":"4100",
    "addr:postcode":"60641",
    "addr:street":"N Long Avenue",
    "iso:country":"US",
    "sg:address":"4100 N Long Avenue",
    "sg:city":"Chicago",
    "sg:classifiers":[
        {
            "category":"Sports & Exercise",
            "subcategory":"Sports Center",
            "type":"Entertainment"
        }
    ],
    "sg:phone":"+1 773 685 3389",
    "sg:postcode":"60641",
    "sg:province":"IL",
    "sg:tags":[
        "amateur",
        "team"
    ],
    "sg:website":"www.cpdgolf.com",
    "wof:name":"Chicago Park District",
    "wof:placetype":"venue"
},
  "geometry": {"coordinates":[-87.761927,41.955255],"type":"Point"}
}