{
  "type": "Feature",
  "properties": {
    "iso:country":"US",
    "sg:address":"100 E 3rd St",
    "sg:city":"Tampico",
    "sg:classifiers":[
        {
            "category":"Retail",
            "subcategory":"Auto Repair",
            "type":"Services"
        }
    ],
    "sg:phone":"+1 815 438 6055",
    "sg:postcode":"61283",
    "sg:province":"IL",
    "sg:tags":[
        "body",
        "automobile",
        "painting"
    ],
    "wof:name":"Chriest Garage",
    "wof:placetype":"venue"
},
  "geometry": {"coordinates":[-89.786018,41.633356],"type":"Point"}
}