{
  "type": "Feature",
  "properties": {
    "iso:country":"US",
    "sg:address":"2620 W Division St",
    "sg:city":"Chicago",
    "sg:classifiers":[
        {
            "category":"Home & Garden",
            "subcategory":"Furniture",
            "type":"Retail Goods"
        }
    ],
    "sg:phone":"+1 773 276 4339",
    "sg:postcode":"60622",
    "sg:province":"IL",
    "sg:tags":[
        "store"
    ],
    "wof:name":"Ama Furniture",
    "wof:placetype":"venue"
},
  "geometry": {"coordinates":[-87.692398,41.903],"type":"Point"}
}