{
  "type": "Feature",
  "properties": {
    "addr:full":"1007 N Western Ave Chicago IL 60622",
    "addr:housenumber":"1007",
    "addr:postcode":"60622",
    "addr:street":"N Western Ave",
    "iso:country":"US",
    "sg:address":"1007 N Western Ave",
    "sg:city":"Chicago",
    "sg:classifiers":[
        {
            "category":"Wholesale",
            "subcategory":"Painting Supplies",
            "type":"Manufacturing & Wholesale Goods"
        },
        {
            "category":"Home & Garden",
            "subcategory":"Hardware",
            "type":"Retail Goods"
        },
        {
            "category":"Home & Garden",
            "subcategory":"Building Materials",
            "type":"Retail Goods"
        }
    ],
    "sg:phone":"+1 773 276 6003",
    "sg:postcode":"60622",
    "sg:province":"IL",
    "sg:tags":[
        "paint",
        "wallpaper",
        "store",
        "wallcoverings"
    ],
    "wof:name":"Western Paint and Hardware",
    "wof:placetype":"venue"
},
  "geometry": {"coordinates":[-87.686881,41.899578],"type":"Point"}
}