{
  "type": "Feature",
  "properties": {
    "iso:country":"US",
    "sg:address":"3307 Brookview Rd",
    "sg:city":"Rockford",
    "sg:classifiers":[
        {
            "category":"Building & Trades",
            "subcategory":"Electrical",
            "type":"Services"
        }
    ],
    "sg:phone":"+1 815 399 1722",
    "sg:postcode":"61107",
    "sg:province":"IL",
    "sg:tags":[
        "electric",
        "contractor"
    ],
    "wof:name":"Zimmerman Electric Co",
    "wof:placetype":"venue"
},
  "geometry": {"coordinates":[-89.038728,42.293027],"type":"Point"}
}