{
  "type": "Feature",
  "properties": {
    "iso:country":"US",
    "sg:address":"120 S Riverside Plz",
    "sg:city":"Chicago",
    "sg:classifiers":[
        {
            "category":"Professional",
            "subcategory":"Lawyer & Legal Services",
            "type":"Services"
        }
    ],
    "sg:phone":"+1 312 655 1500",
    "sg:postcode":"60606",
    "sg:province":"IL",
    "wof:name":"Tambolas Teresa D Lwyr",
    "wof:placetype":"venue"
},
  "geometry": {"coordinates":[-87.63870199999999,41.880299],"type":"Point"}
}