{
  "type": "Feature",
  "properties": {
    "iso:country":"US",
    "sg:address":"212 W Main St",
    "sg:city":"Mount Sterling",
    "sg:classifiers":[
        {
            "category":"Retail",
            "subcategory":"Laundry & Dry Cleaning",
            "type":"Services"
        }
    ],
    "sg:phone":"+1 217 773 2721",
    "sg:postcode":"62353",
    "sg:province":"IL",
    "sg:tags":[
        "drycleaning",
        "plant",
        "coin",
        "power"
    ],
    "wof:name":"J&J Clean Wash",
    "wof:placetype":"venue"
},
  "geometry": {"coordinates":[-90.76796,39.986537],"type":"Point"}
}