{
  "type": "Feature",
  "properties": {
    "iso:country":"US",
    "sg:address":"1028 E Riverside Blvd",
    "sg:city":"Loves Park",
    "sg:classifiers":[
        {
            "category":"Professional",
            "subcategory":"Art Services",
            "type":"Services"
        }
    ],
    "sg:phone":"+1 815 637 8989",
    "sg:postcode":"61111",
    "sg:province":"IL",
    "sg:tags":[
        "marketing",
        "communications"
    ],
    "wof:name":"Powell Kw & Associates Inc",
    "wof:placetype":"venue"
},
  "geometry": {"coordinates":[-89.046846,42.3163],"type":"Point"}
}