{
  "type": "Feature",
  "properties": {
    "addr:full":"125 Clyde Ave Evanston IL 60202",
    "addr:housenumber":"125",
    "addr:postcode":"60202",
    "addr:street":"Clyde Ave",
    "iso:country":"US",
    "sg:address":"125 Clyde Ave",
    "sg:city":"Evanston",
    "sg:classifiers":[
        {
            "category":"Real Estate",
            "subcategory":"Real Estate Operator",
            "type":"Services"
        }
    ],
    "sg:phone":"+1 847 869 5815",
    "sg:postcode":"60202",
    "sg:province":"IL",
    "sg:tags":[
        "condominium"
    ],
    "wof:name":"Clyde Court Condominiums",
    "wof:placetype":"venue"
},
  "geometry": {"coordinates":[-87.677921,42.020535],"type":"Point"}
}