{
  "type": "Feature",
  "properties": {
    "addr:full":"502 SW 8th Ave Aledo IL 61231",
    "addr:housenumber":"502",
    "addr:postcode":"61231",
    "addr:street":"Sw 8Th Ave",
    "iso:country":"US",
    "sg:address":"502 SW 8th Ave",
    "sg:city":"Aledo",
    "sg:classifiers":[
        {
            "category":"Personal",
            "subcategory":"Beauty Salon",
            "type":"Services"
        }
    ],
    "sg:phone":"+1 309 582 5843",
    "sg:postcode":"61231",
    "sg:province":"IL",
    "wof:name":"Diane's Hair Port",
    "wof:placetype":"venue"
},
  "geometry": {"coordinates":[-90.75749999999999,41.198252],"type":"Point"}
}