{
  "type": "Feature",
  "properties": {
    "iso:country":"US",
    "sg:address":"2103 Crescent Dr",
    "sg:city":"Peru",
    "sg:classifiers":[
        {
            "category":"Professional",
            "type":"Services"
        },
        {
            "category":"Local Transit",
            "type":"Transportation"
        }
    ],
    "sg:phone":"+1 815 223 1769",
    "sg:postcode":"61354",
    "sg:province":"IL",
    "sg:tags":[
        "passenger",
        "establishment"
    ],
    "wof:name":"Art's Shuttle",
    "wof:placetype":"venue"
},
  "geometry": {"coordinates":[-89.126484,41.340046],"type":"Point"}
}