{
  "type": "Feature",
  "properties": {
    "addr:full":"4205 Broadway St Mount Vernon IL 62864",
    "addr:housenumber":"4205",
    "addr:postcode":"62864",
    "addr:street":"Broadway St",
    "iso:country":"US",
    "sg:address":"4205 Broadway St",
    "sg:city":"Mount Vernon",
    "sg:classifiers":[
        {
            "category":"Restaurant",
            "type":"Food & Drink"
        }
    ],
    "sg:menulink":"http://www.allmenus.com/il/shiloh/196273-taco-bell/menu/",
    "sg:postcode":"62864",
    "sg:province":"IL",
    "sg:tags":[
        "mexican"
    ],
    "wof:name":"Taco Bell",
    "wof:placetype":"venue"
},
  "geometry": {"coordinates":[-88.942245,38.314142],"type":"Point"}
}