{
  "type": "Feature",
  "properties": {
    "addr:full":"500 N Green Bay Rd Waukegan IL 60085",
    "addr:housenumber":"500",
    "addr:postcode":"60085",
    "addr:street":"N Green Bay Rd",
    "iso:country":"US",
    "sg:address":"500 N Green Bay Rd",
    "sg:city":"Waukegan",
    "sg:classifiers":[
        {
            "category":"Retail",
            "subcategory":"Auto Repair",
            "type":"Services"
        }
    ],
    "sg:phone":"+1 847 360 9330",
    "sg:postcode":"60085",
    "sg:province":"IL",
    "sg:tags":[
        "general"
    ],
    "wof:name":"Kinlan Enterprises Inc",
    "wof:placetype":"venue"
},
  "geometry": {"coordinates":[-87.879029,42.366547],"type":"Point"}
}