{
  "type": "Feature",
  "properties": {
    "iso:country":"US",
    "sg:address":"3739 N Tripp Ave",
    "sg:city":"Chicago",
    "sg:classifiers":[
        {
            "category":"Professional",
            "subcategory":"Management & Consulting",
            "type":"Services"
        }
    ],
    "sg:phone":"+1 773 282 0571",
    "sg:postcode":"60641",
    "sg:province":"IL",
    "sg:tags":[
        "business"
    ],
    "wof:name":"Rodgers Group Ltd",
    "wof:placetype":"venue"
},
  "geometry": {"coordinates":[-87.733765,41.949241],"type":"Point"}
}