{
  "type": "Feature",
  "properties": {
    "iso:country":"US",
    "sg:address":"35168 N Rand Hill Dr",
    "sg:city":"Ingleside",
    "sg:classifiers":[
        {
            "category":"Wholesale",
            "subcategory":"Furniture",
            "type":"Manufacturing & Wholesale Goods"
        }
    ],
    "sg:phone":"+1 847 973 0022",
    "sg:postcode":"60041",
    "sg:province":"IL",
    "wof:name":"National Business Furniture",
    "wof:placetype":"venue"
},
  "geometry": {"coordinates":[-88.171105,42.374773],"type":"Point"}
}