{
  "type": "Feature",
  "properties": {
    "iso:country":"US",
    "sg:address":"3434 Runge St",
    "sg:city":"Franklin Park",
    "sg:classifiers":[
        {
            "category":"Freight",
            "type":"Transportation"
        }
    ],
    "sg:phone":"+1 847 455 2770",
    "sg:postcode":"60131",
    "sg:province":"IL",
    "sg:tags":[
        "warehouse",
        "produce",
        "processing"
    ],
    "wof:name":"Ready Pac Produce Inc",
    "wof:placetype":"venue"
},
  "geometry": {"coordinates":[-87.91059,41.939625],"type":"Point"}
}