{
  "type": "Feature",
  "properties": {
    "addr:full":"6348 W Gunnison St Chicago IL 60630",
    "addr:housenumber":"6348",
    "addr:postcode":"60630",
    "addr:street":"W Gunnison St",
    "iso:country":"US",
    "sg:address":"6348 W Gunnison St",
    "sg:city":"Chicago",
    "sg:classifiers":[
        {
            "category":"Personal",
            "type":"Services"
        }
    ],
    "sg:phone":"+1 773 777 5884",
    "sg:postcode":"60630",
    "sg:province":"IL",
    "sg:tags":[
        "home"
    ],
    "wof:name":"Affordable Heating and Cooling",
    "wof:placetype":"venue"
},
  "geometry": {"coordinates":[-87.78714600000001,41.968423],"type":"Point"}
}