{
  "type": "Feature",
  "properties": {
    "addr:full":"2001 S Banker St Effingham IL 62401",
    "addr:housenumber":"2001",
    "addr:postcode":"62401",
    "addr:street":"S Banker St",
    "iso:country":"US",
    "sg:address":"2001 S Banker St",
    "sg:city":"Effingham",
    "sg:classifiers":[
        {
            "category":"Banks & Credit Unions",
            "subcategory":"Bank",
            "type":"Services"
        }
    ],
    "sg:phone":"+1 217 347 7000",
    "sg:postcode":"62401",
    "sg:province":"IL",
    "sg:tags":[
        "depository",
        "banking",
        "loan"
    ],
    "wof:name":"Cash Store The",
    "wof:placetype":"venue"
},
  "geometry": {"coordinates":[-88.547016,39.103929],"type":"Point"}
}