{
  "type": "Feature",
  "properties": {
    "iso:country":"US",
    "sg:address":"100 Rte 30",
    "sg:city":"Aurora",
    "sg:classifiers":[
        {
            "category":"Recreation",
            "type":"Entertainment"
        }
    ],
    "sg:phone":"+1 630 820 2085",
    "sg:postcode":"60504",
    "sg:province":"IL",
    "sg:tags":[
        "golf",
        "driving",
        "field",
        "range",
        "operator",
        "sport"
    ],
    "wof:name":"Ultimate Sports Dome",
    "wof:placetype":"venue"
},
  "geometry": {"coordinates":[-88.28478,41.724373],"type":"Point"}
}