{
  "type": "Feature",
  "properties": {
    "addr:full":"1489 Division St Morris IL 60450",
    "addr:housenumber":"1489",
    "addr:postcode":"60450",
    "addr:street":"Division St",
    "iso:country":"US",
    "sg:address":"1489 Division St",
    "sg:city":"Morris",
    "sg:classifiers":[
        {
            "category":"Shopping",
            "type":"Retail Goods"
        }
    ],
    "sg:phone":"+1   ",
    "sg:postcode":"60450",
    "sg:province":"IL",
    "sg:tags":[
        "phone",
        "cellular"
    ],
    "wof:name":"Air 1 Wireless-Morris",
    "wof:placetype":"venue"
},
  "geometry": {"coordinates":[-88.42210900000001,41.372142],"type":"Point"}
}