{
  "type": "Feature",
  "properties": {
    "addr:full":"260 N Ardmore Ave Villa Park IL 60181",
    "addr:housenumber":"260",
    "addr:postcode":"60181",
    "addr:street":"N Ardmore Ave",
    "iso:country":"US",
    "sg:address":"260 N Ardmore Ave",
    "sg:city":"Villa Park",
    "sg:classifiers":[
        {
            "category":"Building & Trades",
            "subcategory":"Pest Control",
            "type":"Services"
        }
    ],
    "sg:phone":"+1 630 782 9394",
    "sg:postcode":"60181",
    "sg:province":"IL",
    "wof:name":"Personal Touch Pest Control",
    "wof:placetype":"venue"
},
  "geometry": {"coordinates":[-87.97918300000001,41.893968],"type":"Point"}
}