{
  "type": "Feature",
  "properties": {
    "addr:full":"115 E Spring St Freeport IL 61032",
    "addr:housenumber":"115",
    "addr:postcode":"61032",
    "addr:street":"E Spring St",
    "iso:country":"US",
    "sg:address":"115 E Spring St",
    "sg:city":"Freeport",
    "sg:classifiers":[
        {
            "category":"Social Services",
            "subcategory":"Adult Care",
            "type":"Services"
        }
    ],
    "sg:phone":"+1 815 232 8896",
    "sg:postcode":"61032",
    "sg:province":"IL",
    "sg:tags":[
        "organization",
        "senior",
        "citizen"
    ],
    "wof:name":"Golden Meals NICAA Program",
    "wof:placetype":"venue"
},
  "geometry": {"coordinates":[-89.61657099999999,42.297711],"type":"Point"}
}