{
  "type": "Feature",
  "properties": {
    "iso:country":"US",
    "sg:address":"3822 S Michigan Ave # 408",
    "sg:city":"Chicago",
    "sg:classifiers":[
        {
            "category":"Real Estate",
            "subcategory":"Architect",
            "type":"Services"
        }
    ],
    "sg:phone":"+1 773 268 1575",
    "sg:postcode":"60653",
    "sg:province":"IL",
    "sg:tags":[
        "architects'",
        "specification",
        "construction",
        "builders'",
        "architectural"
    ],
    "wof:name":"Kelly George",
    "wof:placetype":"venue"
},
  "geometry": {"coordinates":[-87.623113,41.824417],"type":"Point"}
}