{
  "type": "Feature",
  "properties": {
    "addr:full":"101 E Saint Charles Rd Villa Park IL 60181",
    "addr:housenumber":"101",
    "addr:postcode":"60181",
    "addr:street":"E Saint Charles Rd",
    "iso:country":"US",
    "sg:address":"101 E Saint Charles Rd",
    "sg:city":"Villa Park",
    "sg:classifiers":[
        {
            "category":"Banks & Credit Unions",
            "subcategory":"Investment Brokerage",
            "type":"Services"
        }
    ],
    "sg:phone":"+1 630 833 2000",
    "sg:postcode":"60181",
    "sg:province":"IL",
    "wof:name":"Citicorp",
    "wof:placetype":"venue"
},
  "geometry": {"coordinates":[-87.975129,41.889851],"type":"Point"}
}