{
  "type": "Feature",
  "properties": {
    "addr:full":"900 N Union St Dwight IL 60420",
    "addr:housenumber":"900",
    "addr:postcode":"60420",
    "addr:street":"N Union St",
    "iso:country":"US",
    "sg:address":"900 N Union St",
    "sg:city":"Dwight",
    "sg:classifiers":[
        {
            "category":"Restaurant",
            "type":"Food & Drink"
        }
    ],
    "sg:phone":"+1   ",
    "sg:postcode":"60420",
    "sg:province":"IL",
    "sg:tags":[
        "eating"
    ],
    "wof:name":"Petes Restaurant & Pnck Hse",
    "wof:placetype":"venue"
},
  "geometry": {"coordinates":[-88.420159,41.10093],"type":"Point"}
}