{
  "type": "Feature",
  "properties": {
    "addr:full":"3013 W Warren Blvd Chicago IL 60612",
    "addr:housenumber":"3013",
    "addr:postcode":"60612",
    "addr:street":"W Warren Blvd",
    "iso:country":"US",
    "sg:address":"3013 W Warren Blvd",
    "sg:city":"Chicago",
    "sg:classifiers":[
        {
            "category":"Personal",
            "subcategory":"Beauty Salon",
            "type":"Services"
        }
    ],
    "sg:phone":"+1 773 826 3390",
    "sg:postcode":"60612",
    "sg:province":"IL",
    "sg:tags":[
        "hair"
    ],
    "wof:name":"Sister African Hair Brading",
    "wof:placetype":"venue"
},
  "geometry": {"coordinates":[-87.701776,41.881674],"type":"Point"}
}