{
  "type": "Feature",
  "properties": {
    "iso:country":"US",
    "sg:address":"4838 W 79th St",
    "sg:city":"Bedford Park",
    "sg:classifiers":[
        {
            "category":"Wholesale",
            "subcategory":"Tobacco Products",
            "type":"Manufacturing & Wholesale Goods"
        }
    ],
    "sg:phone":"+1 708 229 9421",
    "sg:postcode":"60459",
    "sg:province":"IL",
    "wof:name":"Suburbn Tobacco Inc",
    "wof:placetype":"venue"
},
  "geometry": {"coordinates":[-87.74368,41.749179],"type":"Point"}
}