{
  "type": "Feature",
  "properties": {
    "addr:full":"716 Bluecrest Dr Rockford IL 61107",
    "addr:housenumber":"716",
    "addr:postcode":"61107",
    "addr:street":"Bluecrest Dr",
    "iso:country":"US",
    "sg:address":"716 Bluecrest Dr",
    "sg:city":"Rockford",
    "sg:classifiers":[
        {
            "category":"Building & Trades",
            "subcategory":"Construction",
            "type":"Services"
        }
    ],
    "sg:phone":"+1 815 399 3616",
    "sg:postcode":"61107",
    "sg:province":"IL",
    "sg:tags":[
        "hanging",
        "contractor"
    ],
    "wof:name":"Paramount Paint Services",
    "wof:placetype":"venue"
},
  "geometry": {"coordinates":[-89.02459,42.276964],"type":"Point"}
}