{
  "type": "Feature",
  "properties": {
    "addr:full":"1500 Torrence Ave Calumet City IL 60409",
    "addr:housenumber":"1500",
    "addr:postcode":"60409",
    "addr:street":"Torrence Ave",
    "iso:country":"US",
    "sg:address":"1500 Torrence Ave",
    "sg:city":"Calumet City",
    "sg:classifiers":[
        {
            "category":"Sports & Exercise",
            "subcategory":"Gym",
            "type":"Entertainment"
        }
    ],
    "sg:phone":"+1 708 891 8800",
    "sg:postcode":"60409",
    "sg:province":"IL",
    "sg:tags":[
        "club",
        "health"
    ],
    "sg:website":"www.ballyfitness.com/",
    "wof:name":"Bally Total Fitness",
    "wof:placetype":"venue"
},
  "geometry": {"coordinates":[-87.558755,41.590989],"type":"Point"}
}