{
  "type": "Feature",
  "properties": {
    "addr:full":"10443 S Kedzie Ave Chicago IL 60655",
    "addr:housenumber":"10443",
    "addr:postcode":"60655",
    "addr:street":"S Kedzie Ave",
    "iso:country":"US",
    "sg:address":"10443 S Kedzie Ave",
    "sg:city":"Chicago",
    "sg:classifiers":[
        {
            "category":"Real Estate",
            "subcategory":"Real Estate Agent",
            "type":"Services"
        }
    ],
    "sg:phone":"+1 773 779 3457",
    "sg:postcode":"60655",
    "sg:province":"IL",
    "sg:tags":[
        "appraisers-business",
        "industrial",
        "commercial"
    ],
    "sg:website":"http://www.mpappraisals.com",
    "wof:name":"M P Appraisals Inc",
    "wof:placetype":"venue"
},
  "geometry": {"coordinates":[-87.701257,41.703565],"type":"Point"}
}