{
  "type": "Feature",
  "properties": {
    "addr:full":"1616 W Colonial Pkwy Palatine IL 60067",
    "addr:housenumber":"1616",
    "addr:postcode":"60067",
    "addr:street":"W Colonial Pkwy",
    "iso:country":"US",
    "sg:address":"1616 W Colonial Pkwy",
    "sg:city":"Palatine",
    "sg:classifiers":[
        {
            "category":"Health Services",
            "subcategory":"Doctor",
            "type":"Services"
        }
    ],
    "sg:phone":"+1 847 359 6979",
    "sg:postcode":"60067",
    "sg:province":"IL",
    "wof:name":"Joseph Baldassano DDS",
    "wof:placetype":"venue"
},
  "geometry": {"coordinates":[-88.078622,42.084992],"type":"Point"}
}