{
  "type": "Feature",
  "properties": {
    "addr:full":"375 Channing Ave Belvidere IL 61008",
    "addr:housenumber":"375",
    "addr:postcode":"61008",
    "addr:street":"Channing Ave",
    "iso:country":"US",
    "sg:address":"375 Channing Ave",
    "sg:city":"Belvidere",
    "sg:classifiers":[
        {
            "category":"Real Estate",
            "subcategory":"Real Estate Agent",
            "type":"Services"
        }
    ],
    "sg:phone":"+1 815 547 0848",
    "sg:postcode":"61008",
    "sg:province":"IL",
    "sg:tags":[
        "inspection"
    ],
    "wof:name":"Dun Rite Home Inspection",
    "wof:placetype":"venue"
},
  "geometry": {"coordinates":[-88.82311,42.25748],"type":"Point"}
}