{
  "type": "Feature",
  "properties": {
    "iso:country":"US",
    "sg:address":"125 Old Orchard Shopping Ctr",
    "sg:city":"Skokie",
    "sg:classifiers":[
        {
            "category":"Shopping",
            "subcategory":"Jewelry",
            "type":"Retail Goods"
        }
    ],
    "sg:phone":"+1 847 674 5140",
    "sg:postcode":"60077",
    "sg:province":"IL",
    "sg:tags":[
        "diamond",
        "jeweler"
    ],
    "sg:website":"http://www.helzberg.com",
    "wof:name":"Helzberg Diamonds",
    "wof:placetype":"venue"
},
  "geometry": {"coordinates":[-87.74901699999999,42.055744],"type":"Point"}
}