{
  "type": "Feature",
  "properties": {
    "iso:country":"US",
    "sg:address":"123 W Front St Ste 200",
    "sg:city":"Wheaton",
    "sg:classifiers":[
        {
            "category":"Professional",
            "subcategory":"Accounting & Tax Preparation",
            "type":"Services"
        }
    ],
    "sg:phone":"+1 630 681 8100",
    "sg:postcode":"60187",
    "sg:province":"IL",
    "sg:tags":[
        "accountant"
    ],
    "wof:name":"Alexander X Kuhn & Co",
    "wof:placetype":"venue"
},
  "geometry": {"coordinates":[-88.10770100000001,41.864848],"type":"Point"}
}