{
  "type": "Feature",
  "properties": {
    "iso:country":"US",
    "sg:address":"219 W North Ave",
    "sg:city":"Chicago",
    "sg:classifiers":[
        {
            "category":"Bars & Pubs",
            "type":"Food & Drink"
        },
        {
            "category":"Bars & Pubs",
            "subcategory":"Dive Bar",
            "type":"Food & Drink"
        }
    ],
    "sg:phone":"+1 312 944 7020",
    "sg:postcode":"60610",
    "sg:province":"IL",
    "sg:website":"www.oldtownalehousechicago.com/",
    "wof:name":"Old Town Ale House",
    "wof:placetype":"venue"
},
  "geometry": {"coordinates":[-87.635391,41.910917],"type":"Point"}
}