{
  "type": "Feature",
  "properties": {
    "iso:country":"US",
    "sg:address":"107 W Monroe St",
    "sg:city":"Villa Park",
    "sg:classifiers":[
        {
            "category":"Professional",
            "subcategory":"Business Services",
            "type":"Services"
        }
    ],
    "sg:phone":"+1 630 834 5037",
    "sg:postcode":"60181",
    "sg:province":"IL",
    "wof:name":"Milne Translation Svcs",
    "wof:placetype":"venue"
},
  "geometry": {"coordinates":[-87.978773,41.87369],"type":"Point"}
}