{
  "type": "Feature",
  "properties": {
    "iso:country":"US",
    "sg:address":"204 Country Commons Rd",
    "sg:city":"Trout Valley",
    "sg:classifiers":[
        {
            "category":"Manufacturing",
            "subcategory":"Printing",
            "type":"Manufacturing & Wholesale Goods"
        }
    ],
    "sg:phone":"+1 847 639 8040",
    "sg:postcode":"60013",
    "sg:province":"IL",
    "sg:tags":[
        "printer",
        "metal",
        "plastic"
    ],
    "sg:website":"www.carlgorrprinting.com",
    "wof:name":"Gorr Printing Co",
    "wof:placetype":"venue"
},
  "geometry": {"coordinates":[-88.253637,42.203639],"type":"Point"}
}