{
  "type": "Feature",
  "properties": {
    "addr:full":"418 W Blackhawk Dr Byron IL 61010",
    "addr:housenumber":"418",
    "addr:postcode":"61010",
    "addr:street":"W Blackhawk Dr",
    "iso:country":"US",
    "sg:address":"418 W Blackhawk Dr",
    "sg:city":"Byron",
    "sg:classifiers":[
        {
            "category":"Real Estate",
            "subcategory":"Real Estate Agent",
            "type":"Services"
        }
    ],
    "sg:phone":"+1 815 234 3100",
    "sg:postcode":"61010",
    "sg:province":"IL",
    "sg:website":"www.whiteheadweb.com",
    "wof:name":"Whitehead Inc",
    "wof:placetype":"venue"
},
  "geometry": {"coordinates":[-89.260391,42.125228],"type":"Point"}
}