{
  "type": "Feature",
  "properties": {
    "iso:country":"US",
    "sg:address":"6220 East Dr",
    "sg:city":"Loves Park",
    "sg:classifiers":[
        {
            "category":"Retail",
            "subcategory":"Repair Shop",
            "type":"Services"
        }
    ],
    "sg:phone":"+1 815 637 4840",
    "sg:postcode":"61111",
    "sg:province":"IL",
    "sg:tags":[
        "scooter",
        "motorcycle",
        "motor"
    ],
    "wof:name":"Voodoo Performance",
    "wof:placetype":"venue"
},
  "geometry": {"coordinates":[-89.06601999999999,42.321007],"type":"Point"}
}