{
  "type": "Feature",
  "properties": {
    "iso:country":"US",
    "sg:address":"2780 State Rte 142 N",
    "sg:city":"Eldorado",
    "sg:classifiers":[
        {
            "category":"Personal",
            "subcategory":"Beauty Salon",
            "type":"Services"
        }
    ],
    "sg:phone":"+1 618 273 5757",
    "sg:postcode":"62930",
    "sg:province":"IL",
    "sg:tags":[
        "shop"
    ],
    "wof:name":"Kountryside Klips",
    "wof:placetype":"venue"
},
  "geometry": {"coordinates":[-88.452682,37.842523],"type":"Point"}
}