{
  "type": "Feature",
  "properties": {
    "iso:country":"US",
    "sg:address":"22076 W Chestnut Ridge Rd",
    "sg:city":"Kildeer",
    "sg:classifiers":[
        {
            "category":"Professional",
            "subcategory":"Research",
            "type":"Services"
        },
        {
            "category":"Professional",
            "subcategory":"Management & Consulting",
            "type":"Services"
        }
    ],
    "sg:phone":"+1 847 438 4941",
    "sg:postcode":"60047",
    "sg:province":"IL",
    "sg:tags":[
        "nonphysical",
        "s",
        "commercial",
        "consultant",
        "marketing"
    ],
    "wof:name":"Macey Marketing Group",
    "wof:placetype":"venue"
},
  "geometry": {"coordinates":[-88.06379,42.17559],"type":"Point"}
}