{
  "type": "Feature",
  "properties": {
    "iso:country":"US",
    "sg:address":"1105 Edgar Ave",
    "sg:city":"Mattoon",
    "sg:classifiers":[
        {
            "category":"Social Services",
            "subcategory":"Child Care",
            "type":"Services"
        }
    ],
    "sg:phone":"+1 217 235 2485",
    "sg:postcode":"61938",
    "sg:province":"IL",
    "sg:tags":[
        "day"
    ],
    "wof:name":"Lori Bullock",
    "wof:placetype":"venue"
},
  "geometry": {"coordinates":[-88.368332,39.478286],"type":"Point"}
}