{
  "type": "Feature",
  "properties": {
    "addr:full":"4259 N Western Ave Chicago IL 60618",
    "addr:housenumber":"4259",
    "addr:postcode":"60618",
    "addr:street":"N Western Ave",
    "iso:country":"US",
    "sg:address":"4259 N Western Ave",
    "sg:city":"Chicago",
    "sg:classifiers":[
        {
            "category":"Travel",
            "subcategory":"Travel Agent",
            "type":"Entertainment"
        }
    ],
    "sg:phone":"+1 773 539 8085",
    "sg:postcode":"60618",
    "sg:province":"IL",
    "wof:name":"Magnum Travel Inc",
    "wof:placetype":"venue"
},
  "geometry": {"coordinates":[-87.688259,41.959277],"type":"Point"}
}