{
  "type": "Feature",
  "properties": {
    "iso:country":"US",
    "sg:address":"2860 S River Rd",
    "sg:city":"Des Plaines",
    "sg:classifiers":[
        {
            "category":"Professional",
            "subcategory":"Management & Consulting",
            "type":"Services"
        }
    ],
    "sg:phone":"+1 847 824 2525",
    "sg:postcode":"60018",
    "sg:province":"IL",
    "sg:tags":[
        "food"
    ],
    "wof:name":"Antler Management Corp",
    "wof:placetype":"venue"
},
  "geometry": {"coordinates":[-87.863409,41.999615],"type":"Point"}
}