{
  "type": "Feature",
  "properties": {
    "addr:full":"5594 Larkspur Rd Coulterville IL 62237",
    "addr:housenumber":"5594",
    "addr:postcode":"62237",
    "addr:street":"Larkspur Rd",
    "iso:country":"US",
    "sg:address":"5594 Larkspur Rd",
    "sg:city":"Coulterville",
    "sg:phone":"+1 618 758 3043",
    "sg:postcode":"62237",
    "sg:province":"IL",
    "sg:tags":[
        "farm",
        "soybean"
    ],
    "wof:name":"Leonard Lawless",
    "wof:placetype":"venue"
},
  "geometry": {"coordinates":[-89.517726,38.139839],"type":"Point"}
}