{
  "type": "Feature",
  "properties": {
    "iso:country":"US",
    "sg:address":"3125 Washington Ave",
    "sg:city":"Alton",
    "sg:classifiers":[
        {
            "category":"Restaurant",
            "type":"Food & Drink"
        }
    ],
    "sg:phone":"+1   ",
    "sg:postcode":"62002",
    "sg:province":"IL",
    "sg:tags":[
        "fast"
    ],
    "wof:name":"KFC",
    "wof:placetype":"venue"
},
  "geometry": {"coordinates":[-90.14942000000001,38.917932],"type":"Point"}
}