{
  "type": "Feature",
  "properties": {
    "addr:full":"1005 W Gregory Dr Urbana IL 61801",
    "addr:housenumber":"1005",
    "addr:postcode":"61801",
    "addr:street":"W Gregory Dr",
    "iso:country":"US",
    "sg:address":"1005 W Gregory Dr",
    "sg:city":"Urbana",
    "sg:classifiers":[
        {
            "category":"Education",
            "subcategory":"University",
            "type":"Public Place"
        }
    ],
    "sg:phone":"+1 217 333 1100",
    "sg:postcode":"61801",
    "sg:province":"IL",
    "sg:tags":[
        "college"
    ],
    "sg:website":"www.uillinois.edu",
    "wof:name":"University of Illinois",
    "wof:placetype":"venue"
},
  "geometry": {"coordinates":[-88.221175,40.103973],"type":"Point"}
}