{
  "type": "Feature",
  "properties": {
    "iso:country":"US",
    "sg:address":"111 N State St",
    "sg:city":"Chicago",
    "sg:classifiers":[
        {
            "category":"Wholesale",
            "subcategory":"Medical Equipment & Supplies",
            "type":"Manufacturing & Wholesale Goods"
        },
        {
            "category":"Personal",
            "type":"Services"
        }
    ],
    "sg:phone":"+1 800 332 4990",
    "sg:postcode":"60602",
    "sg:province":"IL",
    "sg:tags":[
        "alarm"
    ],
    "sg:website":"http://www.IllinoisLifeline.com",
    "wof:name":"Lifeline Systems",
    "wof:placetype":"venue"
},
  "geometry": {"coordinates":[-87.627883,41.883485],"type":"Point"}
}