{
  "type": "Feature",
  "properties": {
    "iso:country":"US",
    "sg:address":"416 Donelda Ln",
    "sg:city":"Rockford",
    "sg:classifiers":[
        {
            "category":"Building & Trades",
            "subcategory":"Construction",
            "type":"Services"
        }
    ],
    "sg:phone":"+1 815 965 0825",
    "sg:postcode":"61102",
    "sg:province":"IL",
    "sg:tags":[
        "house"
    ],
    "wof:name":"S&J Home Repair",
    "wof:placetype":"venue"
},
  "geometry": {"coordinates":[-89.170258,42.271639],"type":"Point"}
}