{
  "type": "Feature",
  "properties": {
    "iso:country":"US",
    "sg:address":"8410 Mansfield Ave",
    "sg:city":"Bedford Park",
    "sg:classifiers":[
        {
            "category":"Building & Trades",
            "subcategory":"Plumbing",
            "type":"Services"
        }
    ],
    "sg:phone":"+1 708 424 0417",
    "sg:postcode":"60459",
    "sg:province":"IL",
    "sg:tags":[
        "contractor"
    ],
    "wof:name":"Ricchiuto Plumbing",
    "wof:placetype":"venue"
},
  "geometry": {"coordinates":[-87.767011,41.73976],"type":"Point"}
}