{
  "type": "Feature",
  "properties": {
    "iso:country":"US",
    "sg:address":"20065 E 200th St",
    "sg:city":"Coal Valley",
    "sg:classifiers":[
        {
            "category":"Organizations",
            "subcategory":"Religious Organization",
            "type":"Services"
        }
    ],
    "sg:phone":"+1 309 234 5126",
    "sg:postcode":"61240",
    "sg:province":"IL",
    "wof:name":"Gary L Temple",
    "wof:placetype":"venue"
},
  "geometry": {"coordinates":[-90.396352,41.442693],"type":"Point"}
}