{
  "type": "Feature",
  "properties": {
    "iso:country":"US",
    "sg:address":"222 Merchandise Mart Plaza Ste 135",
    "sg:city":"Chicago",
    "sg:classifiers":[
        {
            "category":"Restaurant",
            "type":"Food & Drink"
        }
    ],
    "sg:phone":"+1 312 621 0200",
    "sg:postcode":"60654",
    "sg:province":"IL",
    "sg:tags":[
        "seafood"
    ],
    "sg:website":"www.nicks-fishmarket.com",
    "wof:name":"Nick's Fishmarket Grill & Bar",
    "wof:placetype":"venue"
},
  "geometry": {"coordinates":[-87.635311,41.888557],"type":"Point"}
}