{
  "type": "Feature",
  "properties": {
    "addr:full":"1203 10th St East Moline IL 61244",
    "addr:housenumber":"1203",
    "addr:postcode":"61244",
    "addr:street":"10Th St",
    "iso:country":"US",
    "sg:address":"1203 10th St",
    "sg:city":"East Moline",
    "sg:classifiers":[
        {
            "category":"Railroad",
            "type":"Transportation"
        }
    ],
    "sg:phone":"+1 309 755 2791",
    "sg:postcode":"61244",
    "sg:province":"IL",
    "sg:tags":[
        "operator",
        "line"
    ],
    "wof:name":"I & M Rail Link LLC",
    "wof:placetype":"venue"
},
  "geometry": {"coordinates":[-90.44002,41.519066],"type":"Point"}
}