{
  "type": "Feature",
  "properties": {
    "iso:country":"US",
    "sg:address":"3345 W 115th St",
    "sg:city":"Alsip",
    "sg:classifiers":[
        {
            "category":"Sports & Exercise",
            "subcategory":"Gym",
            "type":"Entertainment"
        }
    ],
    "sg:phone":"+1 708 293 0775",
    "sg:postcode":"60803",
    "sg:province":"IL",
    "sg:tags":[
        "fitness",
        "physical",
        "facility"
    ],
    "wof:name":"Southside Fitness",
    "wof:placetype":"venue"
},
  "geometry": {"coordinates":[-87.701851,41.684167],"type":"Point"}
}