{
  "type": "Feature",
  "properties": {
    "iso:country":"US",
    "sg:address":"1835 E Oakton St",
    "sg:city":"Des Plaines",
    "sg:classifiers":[
        {
            "category":"Building & Trades",
            "subcategory":"Cleaning & Sanitation",
            "type":"Services"
        }
    ],
    "sg:phone":"+1 847 795 9480",
    "sg:postcode":"60018",
    "sg:province":"IL",
    "sg:tags":[
        "maintenance"
    ],
    "wof:name":"Master Maid",
    "wof:placetype":"venue"
},
  "geometry": {"coordinates":[-87.879059,42.024287],"type":"Point"}
}