{
  "type": "Feature",
  "properties": {
    "iso:country":"US",
    "sg:address":"5347 N Clark St",
    "sg:city":"Chicago",
    "sg:classifiers":[
        {
            "category":"Restaurant",
            "type":"Food & Drink"
        }
    ],
    "sg:menulink":"http://www.allmenus.com/il/chicago/209828-augies-restaurant/menu/",
    "sg:phone":"+1 773 271 7868",
    "sg:postcode":"60640",
    "sg:province":"IL",
    "sg:tags":[
        "american",
        "diner"
    ],
    "wof:name":"Augie's Restaurant",
    "wof:placetype":"venue"
},
  "geometry": {"coordinates":[-87.66824099999999,41.979039],"type":"Point"}
}