{
  "type": "Feature",
  "properties": {
    "addr:full":"709 14th St Silvis IL 61282",
    "addr:housenumber":"709",
    "addr:postcode":"61282",
    "addr:street":"14Th St",
    "iso:country":"US",
    "sg:address":"709 14th St",
    "sg:city":"Silvis",
    "sg:classifiers":[
        {
            "category":"Manufacturing",
            "subcategory":"Retail Goods",
            "type":"Manufacturing & Wholesale Goods"
        }
    ],
    "sg:phone":"+1 309 796 2834",
    "sg:postcode":"61282",
    "sg:province":"IL",
    "sg:tags":[
        "product",
        "mfg"
    ],
    "wof:name":"Soy Lites Ltd",
    "wof:placetype":"venue"
},
  "geometry": {"coordinates":[-90.409785,41.500184],"type":"Point"}
}