{
  "type": "Feature",
  "properties": {
    "addr:full":"3242 Hopkins St Steger IL 60475",
    "addr:housenumber":"3242",
    "addr:postcode":"60475",
    "addr:street":"Hopkins St",
    "iso:country":"US",
    "sg:address":"3242 Hopkins St",
    "sg:city":"Steger",
    "sg:classifiers":[
        {
            "category":"Building & Trades",
            "subcategory":"Construction",
            "type":"Services"
        }
    ],
    "sg:phone":"+1 708 755 7474",
    "sg:postcode":"60475",
    "sg:province":"IL",
    "sg:tags":[
        "carpentry",
        "contractor"
    ],
    "wof:name":"Heft Construction",
    "wof:placetype":"venue"
},
  "geometry": {"coordinates":[-87.626976,41.472411],"type":"Point"}
}