{
  "type": "Feature",
  "properties": {
    "iso:country":"US",
    "sg:address":"16 E Pearson St",
    "sg:city":"Chicago",
    "sg:classifiers":[
        {
            "category":"Manufacturing",
            "subcategory":"Tools & Machinery",
            "type":"Manufacturing & Wholesale Goods"
        }
    ],
    "sg:phone":"+1 312 915 6481",
    "sg:postcode":"60611",
    "sg:province":"IL",
    "sg:tags":[
        "lead-wholesale",
        "manufacturer"
    ],
    "wof:name":"Lead Safe Illinois",
    "wof:placetype":"venue"
},
  "geometry": {"coordinates":[-87.62763,41.897535],"type":"Point"}
}