{
  "type": "Feature",
  "properties": {
    "iso:country":"US",
    "sg:address":"4400 N 24th St",
    "sg:city":"Quincy",
    "sg:classifiers":[
        {
            "category":"Freight",
            "type":"Transportation"
        }
    ],
    "sg:phone":"+1 217 222 3111",
    "sg:postcode":"62305",
    "sg:province":"IL",
    "sg:tags":[
        "inland",
        "terminal"
    ],
    "wof:name":"Mid America International",
    "wof:placetype":"venue"
},
  "geometry": {"coordinates":[-91.377071,39.984102],"type":"Point"}
}