{
  "type": "Feature",
  "properties": {
    "addr:full":"37 E 35th Pl Steger IL 60475",
    "addr:housenumber":"37",
    "addr:postcode":"60475",
    "addr:street":"E 35Th Pl",
    "iso:country":"US",
    "sg:address":"37 E 35th Pl",
    "sg:city":"Steger",
    "sg:classifiers":[
        {
            "category":"Retail",
            "subcategory":"Auto Repair",
            "type":"Services"
        }
    ],
    "sg:phone":"+1 708 754 8750",
    "sg:postcode":"60475",
    "sg:province":"IL",
    "sg:tags":[
        "body"
    ],
    "wof:name":"Nydam Auto Body Inc",
    "wof:placetype":"venue"
},
  "geometry": {"coordinates":[-87.632942,41.466964],"type":"Point"}
}