{
  "type": "Feature",
  "properties": {
    "addr:full":"400 N Ashland Ave Ste 1 Chicago IL 60622",
    "addr:housenumber":"400",
    "addr:postcode":"60622",
    "addr:street":"N Ashland Ave Ste 1",
    "iso:country":"US",
    "sg:address":"400 N Ashland Ave Ste 1",
    "sg:city":"Chicago",
    "sg:classifiers":[
        {
            "category":"Manufacturing",
            "subcategory":"Chemicals & Compounds",
            "type":"Manufacturing & Wholesale Goods"
        }
    ],
    "sg:phone":"+1 312 226 0400",
    "sg:postcode":"60622",
    "sg:province":"IL",
    "sg:tags":[
        "chemicals-wholesale",
        "manufacturer"
    ],
    "wof:name":"Portion Pac Chemical Corporation",
    "wof:placetype":"venue"
},
  "geometry": {"coordinates":[-87.667084,41.88887],"type":"Point"}
}