{
  "type": "Feature",
  "properties": {
    "addr:full":"85 W Congress Pkwy Chicago IL 60605",
    "addr:housenumber":"85",
    "addr:postcode":"60605",
    "addr:street":"W Congress Pkwy",
    "iso:country":"US",
    "sg:address":"85 W Congress Pkwy",
    "sg:city":"Chicago",
    "sg:classifiers":[
        {
            "category":"Communications",
            "type":"Services"
        },
        {
            "category":"Communications",
            "subcategory":"Television Station",
            "type":"Services"
        }
    ],
    "sg:phone":"+1 630 241 0143",
    "sg:postcode":"60605",
    "sg:province":"IL",
    "sg:tags":[
        "satellite",
        "cable",
        "tv",
        "system",
        "equipment",
        "carrier",
        "communications-common"
    ],
    "sg:website":"http://www.directv.com",
    "wof:name":"DIRECTV",
    "wof:placetype":"venue"
},
  "geometry": {"coordinates":[-87.63035600000001,41.875526],"type":"Point"}
}