{
  "type": "Feature",
  "properties": {
    "addr:full":"138 W Main St Aledo IL 61231",
    "addr:housenumber":"138",
    "addr:postcode":"61231",
    "addr:street":"W Main St",
    "iso:country":"US",
    "sg:address":"138 W Main St",
    "sg:city":"Aledo",
    "sg:classifiers":[
        {
            "category":"Manufacturing",
            "subcategory":"Signs",
            "type":"Manufacturing & Wholesale Goods"
        }
    ],
    "sg:phone":"+1 309 582 7446",
    "sg:postcode":"61231",
    "sg:province":"IL",
    "wof:name":"Clark Signs",
    "wof:placetype":"venue"
},
  "geometry": {"coordinates":[-90.750027,41.201609],"type":"Point"}
}