{
  "type": "Feature",
  "properties": {
    "iso:country":"US",
    "sg:address":"4400 44th Ave",
    "sg:city":"Moline",
    "sg:classifiers":[
        {
            "category":"Shopping",
            "type":"Retail Goods"
        }
    ],
    "sg:phone":"+1   ",
    "sg:postcode":"61265",
    "sg:province":"IL",
    "sg:tags":[
        "photocopying",
        "merchandise"
    ],
    "wof:name":"City Blueprint",
    "wof:placetype":"venue"
},
  "geometry": {"coordinates":[-90.475043,41.469197],"type":"Point"}
}