{
  "type": "Feature",
  "properties": {
    "iso:country":"US",
    "sg:address":"121 Southwood Trce",
    "sg:city":"Collinsville",
    "sg:classifiers":[
        {
            "category":"Shopping",
            "subcategory":"Crafts & Fabrics",
            "type":"Retail Goods"
        }
    ],
    "sg:phone":"+1   ",
    "sg:postcode":"62234",
    "sg:province":"IL",
    "sg:tags":[
        "sewing"
    ],
    "wof:name":"In Stitches By Beverly",
    "wof:placetype":"venue"
},
  "geometry": {"coordinates":[-89.991887,38.655094],"type":"Point"}
}