{
  "type": "Feature",
  "properties": {
    "iso:country":"US",
    "sg:address":"813 Essex St",
    "sg:city":"Prospect Heights",
    "sg:classifiers":[
        {
            "category":"Professional",
            "subcategory":"Management & Consulting",
            "type":"Services"
        }
    ],
    "sg:phone":"+1 847 215 6706",
    "sg:postcode":"60070",
    "sg:province":"IL",
    "sg:tags":[
        "resource",
        "human"
    ],
    "wof:name":"Hr By Design Inc",
    "wof:placetype":"venue"
},
  "geometry": {"coordinates":[-87.93907,42.110239],"type":"Point"}
}