{
  "type": "Feature",
  "properties": {
    "iso:country":"US",
    "sg:address":"3120 River Rd",
    "sg:city":"River Grove",
    "sg:classifiers":[
        {
            "category":"Retail",
            "subcategory":"Auto Repair",
            "type":"Services"
        }
    ],
    "sg:phone":"+1 708 453 0505",
    "sg:postcode":"60171",
    "sg:province":"IL",
    "sg:tags":[
        "body",
        "shop"
    ],
    "wof:name":"Twinn Frame & Body Repair",
    "wof:placetype":"venue"
},
  "geometry": {"coordinates":[-87.850098,41.9366],"type":"Point"}
}