{
  "type": "Feature",
  "properties": {
    "iso:country":"US",
    "sg:address":"3000 N Halsted St Ste 501",
    "sg:city":"Chicago",
    "sg:classifiers":[
        {
            "category":"Health Services",
            "subcategory":"Optometrist",
            "type":"Services"
        }
    ],
    "sg:phone":"+1 773 935 2800",
    "sg:postcode":"60657",
    "sg:province":"IL",
    "sg:tags":[
        "ophthalmologist"
    ],
    "wof:name":"Doren Gregory S MD",
    "wof:placetype":"venue"
},
  "geometry": {"coordinates":[-87.649162,41.936489],"type":"Point"}
}