{
  "type": "Feature",
  "properties": {
    "addr:full":"3025 N Kenmore Ave Chicago IL 60657",
    "addr:housenumber":"3025",
    "addr:postcode":"60657",
    "addr:street":"N Kenmore Ave",
    "iso:country":"US",
    "sg:address":"3025 N Kenmore Ave",
    "sg:city":"Chicago",
    "sg:classifiers":[
        {
            "category":"Real Estate",
            "subcategory":"Real Estate Agent",
            "type":"Services"
        }
    ],
    "sg:phone":"+1 773 525 0422",
    "sg:postcode":"60657",
    "sg:province":"IL",
    "wof:name":"Fremont Sheridan Prop",
    "wof:placetype":"venue"
},
  "geometry": {"coordinates":[-87.65519999999999,41.936251],"type":"Point"}
}