{
  "type": "Feature",
  "properties": {
    "iso:country":"US",
    "sg:address":"209 S Chestnut St",
    "sg:city":"Chebanse",
    "sg:classifiers":[
        {
            "category":"Government",
            "subcategory":"Post Office",
            "type":"Public Place"
        }
    ],
    "sg:phone":"+1 815 697 2221",
    "sg:postcode":"60922",
    "sg:province":"IL",
    "wof:name":"US Post Office",
    "wof:placetype":"venue"
},
  "geometry": {"coordinates":[-87.91008600000001,41.000796],"type":"Point"}
}