{
  "type": "Feature",
  "properties": {
    "iso:country":"US",
    "sg:address":"2305 Gardner Rd",
    "sg:city":"Broadview",
    "sg:classifiers":[
        {
            "category":"Manufacturing",
            "subcategory":"Tools & Machinery",
            "type":"Manufacturing & Wholesale Goods"
        }
    ],
    "sg:phone":"+1 708 344 3030",
    "sg:postcode":"60155",
    "sg:province":"IL",
    "sg:tags":[
        "machine",
        "manufacturer"
    ],
    "wof:name":"Hudson Precision Products",
    "wof:placetype":"venue"
},
  "geometry": {"coordinates":[-87.86766799999999,41.861679],"type":"Point"}
}