{
  "type": "Feature",
  "properties": {
    "addr:full":"2091 Shopiere Rd Beloit IL 53511",
    "addr:housenumber":"2091",
    "addr:postcode":"53511",
    "addr:street":"Shopiere Rd",
    "iso:country":"US",
    "sg:address":"2091 Shopiere Rd",
    "sg:city":"Beloit",
    "sg:classifiers":[
        {
            "category":"Health Services",
            "subcategory":"Medical Lab",
            "type":"Services"
        }
    ],
    "sg:phone":"+1 608 365 6625",
    "sg:postcode":"53511",
    "sg:province":"IL",
    "sg:tags":[
        "laboratory",
        "dental"
    ],
    "wof:name":"Stateline Dental Lab",
    "wof:placetype":"venue"
},
  "geometry": {"coordinates":[-89.00707800000001,42.528123],"type":"Point"}
}