{
  "type": "Feature",
  "properties": {
    "addr:full":"221 W Veterans Pkwy Yorkville IL 60560",
    "addr:housenumber":"221",
    "addr:postcode":"60560",
    "addr:street":"W Veterans Pkwy",
    "iso:country":"US",
    "sg:address":"221 W Veterans Pkwy",
    "sg:city":"Yorkville",
    "sg:classifiers":[
        {
            "category":"Fast Food",
            "type":"Food & Drink"
        },
        {
            "category":"Restaurant",
            "type":"Food & Drink"
        }
    ],
    "sg:phone":"+1 630 553 1954",
    "sg:postcode":"60560",
    "sg:province":"IL",
    "sg:tags":[
        "chicken"
    ],
    "sg:website":"http://www.kfc.com",
    "wof:name":"Kfc",
    "wof:placetype":"venue"
},
  "geometry": {"coordinates":[-88.446816,41.658069],"type":"Point"}
}