{
  "type": "Feature",
  "properties": {
    "iso:country":"US",
    "sg:address":"713 S Princeton Ave",
    "sg:city":"Villa Park",
    "sg:classifiers":[
        {
            "category":"Building & Trades",
            "subcategory":"Construction",
            "type":"Services"
        }
    ],
    "sg:phone":"+1 630 941 1893",
    "sg:postcode":"60181",
    "sg:province":"IL",
    "sg:tags":[
        "hanging",
        "contractor"
    ],
    "wof:name":"Thomas-Vil Painting Co",
    "wof:placetype":"venue"
},
  "geometry": {"coordinates":[-87.98029099999999,41.877043],"type":"Point"}
}