{
  "type": "Feature",
  "properties": {
    "iso:country":"US",
    "sg:address":"2348 W Devon Ave",
    "sg:city":"Chicago",
    "sg:classifiers":[
        {
            "category":"Shopping",
            "subcategory":"Computers & Home Electronics",
            "type":"Retail Goods"
        }
    ],
    "sg:phone":"+1   ",
    "sg:postcode":"60659",
    "sg:province":"IL",
    "wof:name":"Worldwide Electronics",
    "wof:placetype":"venue"
},
  "geometry": {"coordinates":[-87.689582,41.997809],"type":"Point"}
}