{
  "type": "Feature",
  "properties": {
    "addr:full":"535 S La Grange Rd La Grange IL 60525",
    "addr:housenumber":"535",
    "addr:postcode":"60525",
    "addr:street":"S La Grange Rd",
    "iso:country":"US",
    "sg:address":"535 S La Grange Rd",
    "sg:city":"La Grange",
    "sg:classifiers":[
        {
            "category":"Shopping",
            "subcategory":"Mobile Phones",
            "type":"Retail Goods"
        }
    ],
    "sg:phone":"+1 708 352 2360",
    "sg:postcode":"60525",
    "sg:province":"IL",
    "sg:website":"www.radioshack.com",
    "wof:name":"Radioshack",
    "wof:placetype":"venue"
},
  "geometry": {"coordinates":[-87.869102,41.804901],"type":"Point"}
}