{
  "type": "Feature",
  "properties": {
    "addr:full":"20332 S White Fence Ct Frankfort IL 60423",
    "addr:housenumber":"20332",
    "addr:postcode":"60423",
    "addr:street":"S White Fence Ct",
    "iso:country":"US",
    "sg:address":"20332 S White Fence Ct",
    "sg:city":"Frankfort",
    "sg:classifiers":[
        {
            "category":"Organizations",
            "subcategory":"Non-profit Organization",
            "type":"Services"
        }
    ],
    "sg:phone":"+1 815 469 5700",
    "sg:postcode":"60423",
    "sg:province":"IL",
    "sg:tags":[
        "disability"
    ],
    "wof:name":"Abovotek Inc",
    "wof:placetype":"venue"
},
  "geometry": {"coordinates":[-87.79707999999999,41.517471],"type":"Point"}
}