{
  "type": "Feature",
  "properties": {
    "iso:country":"US",
    "sg:address":"8734 S. Stony Island Ave.",
    "sg:city":"Chicago",
    "sg:classifiers":[
        {
            "category":"Restaurant",
            "type":"Food & Drink"
        }
    ],
    "sg:phone":"+1 773 374 4700",
    "sg:postcode":"60617",
    "sg:province":"IL",
    "sg:tags":[
        "southern"
    ],
    "wof:name":"B.J.'s Market and Bakery",
    "wof:placetype":"venue"
},
  "geometry": {"coordinates":[-87.58564,41.735912],"type":"Point"}
}