{
  "type": "Feature",
  "properties": {
    "iso:country":"US",
    "sg:address":"427 Des Plaines Ave",
    "sg:city":"Forest Park",
    "sg:classifiers":[
        {
            "category":"Food & Beverages",
            "subcategory":"Meat & Fish",
            "type":"Retail Goods"
        }
    ],
    "sg:phone":"+1 708 366 0321",
    "sg:postcode":"60130",
    "sg:province":"IL",
    "sg:tags":[
        "shop"
    ],
    "wof:name":"Rapid Foods Inc",
    "wof:placetype":"venue"
},
  "geometry": {"coordinates":[-87.814003,41.878502],"type":"Point"}
}