{
  "type": "Feature",
  "properties": {
    "iso:country":"US",
    "sg:address":"2000 Larkin Ave",
    "sg:city":"Elgin",
    "sg:classifiers":[
        {
            "category":"Professional",
            "subcategory":"Management & Consulting",
            "type":"Services"
        }
    ],
    "sg:phone":"+1 847 697 2088",
    "sg:postcode":"60123",
    "sg:province":"IL",
    "sg:tags":[
        "consultant"
    ],
    "wof:name":"Managed Care Consultants",
    "wof:placetype":"venue"
},
  "geometry": {"coordinates":[-88.32892699999999,42.032316],"type":"Point"}
}