{
  "type": "Feature",
  "properties": {
    "addr:full":"9800 S Francisco Ave Evergreen Park IL 60805",
    "addr:housenumber":"9800",
    "addr:postcode":"60805",
    "addr:street":"S Francisco Ave",
    "iso:country":"US",
    "sg:address":"9800 S Francisco Ave",
    "sg:city":"Evergreen Park",
    "sg:classifiers":[
        {
            "category":"Education",
            "subcategory":"School",
            "type":"Public Place"
        }
    ],
    "sg:phone":"+1 708 422 1021",
    "sg:postcode":"60805",
    "sg:province":"IL",
    "wof:name":"Southeast Elementary School",
    "wof:placetype":"venue"
},
  "geometry": {"coordinates":[-87.694237,41.714937],"type":"Point"}
}