{
  "type": "Feature",
  "properties": {
    "addr:full":"700 N Green St Ste 102 Chicago IL 60622",
    "addr:housenumber":"700",
    "addr:postcode":"60622",
    "addr:street":"N Green St Ste 102",
    "iso:country":"US",
    "sg:address":"700 N Green St Ste 102",
    "sg:city":"Chicago",
    "sg:classifiers":[
        {
            "category":"Professional",
            "subcategory":"Accounting & Tax Preparation",
            "type":"Services"
        }
    ],
    "sg:phone":"+1 312 455 1946",
    "sg:postcode":"60622",
    "sg:province":"IL",
    "sg:tags":[
        "accountant"
    ],
    "sg:website":"www.1040.com/cclcpa",
    "wof:name":"Lee Consuella, CPA",
    "wof:placetype":"venue"
},
  "geometry": {"coordinates":[-87.64886799999999,41.895125],"type":"Point"}
}