{
  "type": "Feature",
  "properties": {
    "addr:full":"1404 Joliet Rd Romeoville IL 60446",
    "addr:housenumber":"1404",
    "addr:postcode":"60446",
    "addr:street":"Joliet Rd",
    "iso:country":"US",
    "sg:address":"1404 Joliet Rd",
    "sg:city":"Romeoville",
    "sg:classifiers":[
        {
            "category":"Professional",
            "subcategory":"Engineering",
            "type":"Services"
        },
        {
            "category":"Wholesale",
            "subcategory":"Machinery & Supplies",
            "type":"Manufacturing & Wholesale Goods"
        }
    ],
    "sg:phone":"+1 630 783 2606",
    "sg:postcode":"60446",
    "sg:province":"IL",
    "sg:tags":[
        "equipment",
        "industrial",
        "engineer"
    ],
    "sg:website":"www.scrolllabs.com",
    "wof:name":"Scroll Labs",
    "wof:placetype":"venue"
},
  "geometry": {"coordinates":[-88.055306,41.677333],"type":"Point"}
}