{
  "type": "Feature",
  "properties": {
    "iso:country":"US",
    "sg:address":"14470 S La Grange Rd",
    "sg:city":"Orland Park",
    "sg:classifiers":[
        {
            "category":"Restaurant",
            "type":"Food & Drink"
        }
    ],
    "sg:menulink":"http://www.allmenus.com/il/orland/127193-subway/menu/",
    "sg:phone":"+1 708 364 0070",
    "sg:postcode":"60462",
    "sg:province":"IL",
    "sg:tags":[
        "american",
        "sandwich"
    ],
    "wof:name":"Subway",
    "wof:placetype":"venue"
},
  "geometry": {"coordinates":[-87.853983,41.626566],"type":"Point"}
}