{
  "type": "Feature",
  "properties": {
    "addr:full":"12 E 47th St Chicago IL 60653",
    "addr:housenumber":"12",
    "addr:postcode":"60653",
    "addr:street":"E 47Th St",
    "iso:country":"US",
    "sg:address":"12 E 47th St",
    "sg:city":"Chicago",
    "sg:classifiers":[
        {
            "category":"Restaurant",
            "type":"Food & Drink"
        }
    ],
    "sg:phone":"+1 773 268 2811",
    "sg:postcode":"60653",
    "sg:province":"IL",
    "sg:tags":[
        "chinese"
    ],
    "wof:name":"China 1 Chinese Restaurant",
    "wof:placetype":"venue"
},
  "geometry": {"coordinates":[-87.62420400000001,41.80948],"type":"Point"}
}