{
  "type": "Feature",
  "properties": {
    "addr:full":"16525 State St South Holland IL 60473",
    "addr:housenumber":"16525",
    "addr:postcode":"60473",
    "addr:street":"State St",
    "iso:country":"US",
    "sg:address":"16525 State St",
    "sg:city":"South Holland",
    "sg:classifiers":[
        {
            "category":"Retail",
            "subcategory":"Repair Shop",
            "type":"Services"
        }
    ],
    "sg:phone":"+1 708 339 3666",
    "sg:postcode":"60473",
    "sg:province":"IL",
    "sg:tags":[
        "lift",
        "truck"
    ],
    "wof:name":"Engine Shop",
    "wof:placetype":"venue"
},
  "geometry": {"coordinates":[-87.61693699999999,41.594133],"type":"Point"}
}