{
  "type": "Feature",
  "properties": {
    "iso:country":"US",
    "sg:address":"412 Elles Ave",
    "sg:city":"Carterville",
    "sg:classifiers":[
        {
            "category":"Wholesale",
            "subcategory":"Sporting Goods",
            "type":"Manufacturing & Wholesale Goods"
        }
    ],
    "sg:phone":"+1 618 985 8282",
    "sg:postcode":"62918",
    "sg:province":"IL",
    "wof:name":"Whiteys Plastic Lures",
    "wof:placetype":"venue"
},
  "geometry": {"coordinates":[-89.081651,37.754853],"type":"Point"}
}