{
  "type": "Feature",
  "properties": {
    "iso:country":"US",
    "sg:address":"1513 Fairoaks Dr",
    "sg:city":"Troy",
    "sg:classifiers":[
        {
            "category":"Professional",
            "subcategory":"Lawyer & Legal Services",
            "type":"Services"
        }
    ],
    "sg:phone":"+1 618 667 0535",
    "sg:postcode":"62294",
    "sg:province":"IL",
    "sg:tags":[
        "attorney",
        "plan"
    ],
    "wof:name":"Archway Legal Services",
    "wof:placetype":"venue"
},
  "geometry": {"coordinates":[-89.87772,38.714346],"type":"Point"}
}