{
  "type": "Feature",
  "properties": {
    "addr:full":"5459 W 64th St Chicago IL 60638",
    "addr:housenumber":"5459",
    "addr:postcode":"60638",
    "addr:street":"W 64Th St",
    "iso:country":"US",
    "sg:address":"5459 W 64th St",
    "sg:city":"Chicago",
    "sg:classifiers":[
        {
            "category":"Organizations",
            "subcategory":"Community Association",
            "type":"Services"
        }
    ],
    "sg:phone":"+1 708 323 9695",
    "sg:postcode":"60638",
    "sg:province":"IL",
    "sg:tags":[
        "opera"
    ],
    "wof:name":"Dulski Professional Rail Opera",
    "wof:placetype":"venue"
},
  "geometry": {"coordinates":[-87.758214,41.7763],"type":"Point"}
}