{
  "type": "Feature",
  "properties": {
    "iso:country":"US",
    "sg:address":"27607 W Brandenburg Rd",
    "sg:city":"Ingleside",
    "sg:classifiers":[
        {
            "category":"Shopping",
            "subcategory":"Pets & Pet Supplies",
            "type":"Retail Goods"
        },
        {
            "category":"Retail",
            "subcategory":"Pet Boarding",
            "type":"Services"
        },
        {
            "category":"Retail",
            "subcategory":"Animal Services",
            "type":"Services"
        }
    ],
    "sg:phone":"+1 815 322 7657",
    "sg:postcode":"60041",
    "sg:province":"IL",
    "sg:tags":[
        "grooming",
        "store",
        "exercising",
        "kennel",
        "sitting"
    ],
    "sg:website":"http://www.barkntown.com",
    "wof:name":"Bark 'N' Town",
    "wof:placetype":"venue"
},
  "geometry": {"coordinates":[-88.175729,42.357803],"type":"Point"}
}