{
  "type": "Feature",
  "properties": {
    "iso:country":"US",
    "sg:address":"3100 Madison Ave",
    "sg:city":"Granite City",
    "sg:classifiers":[
        {
            "category":"Food & Beverages",
            "subcategory":"Groceries & Convenience Stores",
            "type":"Retail Goods"
        }
    ],
    "sg:phone":"+1 618 451 0517",
    "sg:postcode":"62040",
    "sg:province":"IL",
    "wof:name":"Schnucks Supermarkets",
    "wof:placetype":"venue"
},
  "geometry": {"coordinates":[-90.123802,38.7174],"type":"Point"}
}