{
  "type": "Feature",
  "properties": {
    "iso:country":"US",
    "sg:address":"501 5th St",
    "sg:city":"Carrollton",
    "sg:classifiers":[
        {
            "category":"Food & Beverages",
            "subcategory":"Groceries & Convenience Stores",
            "type":"Retail Goods"
        }
    ],
    "sg:phone":"+1 217 942 3812",
    "sg:postcode":"62016",
    "sg:province":"IL",
    "wof:name":"Carrollton Moto Mart",
    "wof:placetype":"venue"
},
  "geometry": {"coordinates":[-90.407654,39.299755],"type":"Point"}
}