{
  "type": "Feature",
  "properties": {
    "iso:country":"US",
    "sg:address":"800 5th St",
    "sg:city":"Aurora",
    "sg:classifiers":[
        {
            "category":"Personal",
            "subcategory":"Beauty Salon",
            "type":"Services"
        }
    ],
    "sg:phone":"+1 630 851 6616",
    "sg:postcode":"60505",
    "sg:province":"IL",
    "wof:name":"K M Designs",
    "wof:placetype":"venue"
},
  "geometry": {"coordinates":[-88.312744,41.739267],"type":"Point"}
}