{
  "type": "Feature",
  "properties": {
    "addr:full":"2201 Center St Crest Hill IL 60435",
    "addr:housenumber":"2201",
    "addr:postcode":"60435",
    "addr:street":"Center St",
    "iso:country":"US",
    "sg:address":"2201 Center St",
    "sg:city":"Crest Hill",
    "sg:classifiers":[
        {
            "category":"Autos & Motor Vehicles",
            "subcategory":"Automobile Sales",
            "type":"Retail Goods"
        }
    ],
    "sg:phone":"+1 815 726 3966",
    "sg:postcode":"60435",
    "sg:province":"IL",
    "sg:tags":[
        "snowmobile"
    ],
    "wof:name":"Midwest Dyno",
    "wof:placetype":"venue"
},
  "geometry": {"coordinates":[-88.09255899999999,41.56353],"type":"Point"}
}