{
  "type": "Feature",
  "properties": {
    "iso:country":"US",
    "sg:address":"2201 Center St",
    "sg:city":"Crest Hill",
    "sg:classifiers":[
        {
            "category":"Autos & Motor Vehicles",
            "subcategory":"Automobile Sales",
            "type":"Retail Goods"
        }
    ],
    "sg:phone":"+1 815 726 3966",
    "sg:postcode":"60435",
    "sg:province":"IL",
    "sg:tags":[
        "snowmobile"
    ],
    "wof:name":"Midwest Dyno",
    "wof:placetype":"venue"
},
  "geometry": {"coordinates":[-88.092559,41.56353],"type":"Point"}
}