{
  "type": "Feature",
  "properties": {
    "addr:full":"15409 W Old School Rd Libertyville IL 60048",
    "addr:housenumber":"15409",
    "addr:postcode":"60048",
    "addr:street":"W Old School Rd",
    "iso:country":"US",
    "sg:address":"15409 W Old School Rd",
    "sg:city":"Libertyville",
    "sg:classifiers":[
        {
            "category":"Building & Trades",
            "subcategory":"Construction",
            "type":"Services"
        }
    ],
    "sg:phone":"+1 847 918 8626",
    "sg:postcode":"60048",
    "sg:province":"IL",
    "sg:tags":[
        "house"
    ],
    "wof:name":"T2 Builders Inc",
    "wof:placetype":"venue"
},
  "geometry": {"coordinates":[-87.93392900000001,42.261958],"type":"Point"}
}