{
  "type": "Feature",
  "properties": {
    "addr:full":"4211 Continental Dr Waukegan IL 60087",
    "addr:housenumber":"4211",
    "addr:postcode":"60087",
    "addr:street":"Continental Dr",
    "iso:country":"US",
    "sg:address":"4211 Continental Dr",
    "sg:city":"Waukegan",
    "sg:classifiers":[
        {
            "category":"Manufacturing",
            "subcategory":"Buildings",
            "type":"Manufacturing & Wholesale Goods"
        },
        {
            "category":"Building & Trades",
            "subcategory":"Construction",
            "type":"Services"
        }
    ],
    "sg:phone":"+1 847 672 9598",
    "sg:postcode":"60087",
    "sg:province":"IL",
    "sg:tags":[
        "home",
        "builder",
        "contractor"
    ],
    "wof:name":"Favored Home",
    "wof:placetype":"venue"
},
  "geometry": {"coordinates":[-87.90642699999999,42.396814],"type":"Point"}
}