{
  "type": "Feature",
  "properties": {
    "iso:country":"US",
    "sg:address":"6223 W 79th St",
    "sg:city":"Burbank",
    "sg:classifiers":[
        {
            "category":"Shopping",
            "subcategory":"Clothing, Apparel, & Fashions",
            "type":"Retail Goods"
        }
    ],
    "sg:phone":"+1 708 598 8008",
    "sg:postcode":"60459",
    "sg:province":"IL",
    "sg:tags":[
        "uniforms-accessories"
    ],
    "wof:name":"Schoolbelles",
    "wof:placetype":"venue"
},
  "geometry": {"coordinates":[-87.776295,41.748535],"type":"Point"}
}