{
  "type": "Feature",
  "properties": {
    "addr:full":"2228 S Wood St Chicago IL 60608",
    "addr:housenumber":"2228",
    "addr:postcode":"60608",
    "addr:street":"S Wood St",
    "iso:country":"US",
    "sg:address":"2228 S Wood St",
    "sg:city":"Chicago",
    "sg:classifiers":[
        {
            "category":"Building & Trades",
            "subcategory":"Plumbing",
            "type":"Services"
        },
        {
            "category":"Building & Trades",
            "subcategory":"Cleaning & Sanitation",
            "type":"Services"
        }
    ],
    "sg:phone":"+1 773 376 6666",
    "sg:postcode":"60608",
    "sg:province":"IL",
    "sg:tags":[
        "cleaner",
        "plumber",
        "industrial",
        "repairer",
        "sewer",
        "contractors-commercial",
        "plumbing-drain"
    ],
    "wof:name":"Action Plumbing & Sewers",
    "wof:placetype":"venue"
},
  "geometry": {"coordinates":[-87.670889,41.85142],"type":"Point"}
}