{
  "type": "Feature",
  "properties": {
    "iso:country":"US",
    "sg:address":"145 N Hale St",
    "sg:city":"Wheaton",
    "sg:classifiers":[
        {
            "category":"Restaurant",
            "type":"Food & Drink"
        }
    ],
    "sg:phone":"+1 630 690 9001",
    "sg:postcode":"60187",
    "sg:province":"IL",
    "sg:website":"www.egglecticcafe.net",
    "wof:name":"Egg'lectic Cafe",
    "wof:placetype":"venue"
},
  "geometry": {"coordinates":[-88.108232,41.865421],"type":"Point"}
}