{
  "type": "Feature",
  "properties": {
    "addr:full":"1051 Inlet Rd Amboy IL 61310",
    "addr:housenumber":"1051",
    "addr:postcode":"61310",
    "addr:street":"Inlet Rd",
    "iso:country":"US",
    "sg:address":"1051 Inlet Rd",
    "sg:city":"Amboy",
    "sg:classifiers":[
        {
            "category":"Mining & Drilling",
            "type":"Manufacturing & Wholesale Goods"
        }
    ],
    "sg:phone":"+1 815 857 3797",
    "sg:postcode":"61310",
    "sg:province":"IL",
    "sg:tags":[
        "quarry"
    ],
    "wof:name":"Frank N Butler Co",
    "wof:placetype":"venue"
},
  "geometry": {"coordinates":[-89.252185,41.742796],"type":"Point"}
}