{
  "type": "Feature",
  "properties": {
    "addr:full":"17729 Norris Rd Pecatonica IL 61063",
    "addr:housenumber":"17729",
    "addr:postcode":"61063",
    "addr:street":"Norris Rd",
    "iso:country":"US",
    "sg:address":"17729 Norris Rd",
    "sg:city":"Pecatonica",
    "sg:phone":"+1 815 239 2574",
    "sg:postcode":"61063",
    "sg:province":"IL",
    "sg:tags":[
        "farm",
        "corn",
        "dairy",
        "soybean"
    ],
    "wof:name":"Larson Brothers Farm",
    "wof:placetype":"venue"
},
  "geometry": {"coordinates":[-89.383123,42.339876],"type":"Point"}
}