{
  "type": "Feature",
  "properties": {
    "addr:full":"1351 Todd Farm Dr Elgin IL 60123",
    "addr:housenumber":"1351",
    "addr:postcode":"60123",
    "addr:street":"Todd Farm Dr",
    "iso:country":"US",
    "sg:address":"1351 Todd Farm Dr",
    "sg:city":"Elgin",
    "sg:classifiers":[
        {
            "category":"Personal",
            "type":"Services"
        }
    ],
    "sg:phone":"+1 847 289 8417",
    "sg:postcode":"60123",
    "sg:province":"IL",
    "sg:tags":[
        "hair",
        "replacement"
    ],
    "wof:name":"Braid-A-Style",
    "wof:placetype":"venue"
},
  "geometry": {"coordinates":[-88.31058899999999,42.061549],"type":"Point"}
}