{
  "type": "Feature",
  "properties": {
    "iso:country":"US",
    "sg:address":"341 Washington St",
    "sg:city":"Prophetstown",
    "sg:classifiers":[
        {
            "category":"Personal",
            "subcategory":"Beauty Salon",
            "type":"Services"
        }
    ],
    "sg:phone":"+1 815 537 2455",
    "sg:postcode":"61277",
    "sg:province":"IL",
    "wof:name":"Hearts Desire",
    "wof:placetype":"venue"
},
  "geometry": {"coordinates":[-89.936369,41.669927],"type":"Point"}
}