{
  "type": "Feature",
  "properties": {
    "iso:country":"US",
    "sg:address":"2001 Irving Park Rd",
    "sg:city":"Hanover Park",
    "sg:classifiers":[
        {
            "category":"Shopping",
            "subcategory":"Books",
            "type":"Retail Goods"
        }
    ],
    "sg:phone":"+1 630 837 5006",
    "sg:postcode":"60133",
    "sg:province":"IL",
    "sg:tags":[
        "comic"
    ],
    "sg:website":"www.gotham-city.org",
    "wof:name":"Gotham City LTD",
    "wof:placetype":"venue"
},
  "geometry": {"coordinates":[-88.153989,42.008156],"type":"Point"}
}