{
  "type": "Feature",
  "properties": {
    "iso:country":"US",
    "sg:address":"17162 S Osage Ct",
    "sg:city":"Lockport",
    "sg:classifiers":[
        {
            "category":"Building & Trades",
            "subcategory":"Construction",
            "type":"Services"
        }
    ],
    "sg:phone":"+1 630 759 0562",
    "sg:postcode":"60441",
    "sg:province":"IL",
    "sg:tags":[
        "house"
    ],
    "wof:name":"Even Par Construction",
    "wof:placetype":"venue"
},
  "geometry": {"coordinates":[-88.009659,41.574307],"type":"Point"}
}