{
  "type": "Feature",
  "properties": {
    "iso:country":"US",
    "sg:address":"28045 N Ashley Cir",
    "sg:city":"Libertyville",
    "sg:classifiers":[
        {
            "category":"Insurance",
            "subcategory":"Insurance Agent",
            "type":"Services"
        }
    ],
    "sg:phone":"+1 847 549 8411",
    "sg:postcode":"60048",
    "sg:province":"IL",
    "wof:name":"Primerica",
    "wof:placetype":"venue"
},
  "geometry": {"coordinates":[-87.909729,42.270772],"type":"Point"}
}