{
  "type": "Feature",
  "properties": {
    "iso:country":"US",
    "sg:address":"78 Front St",
    "sg:city":"Hume",
    "sg:classifiers":[
        {
            "category":"Government",
            "subcategory":"Office",
            "type":"Public Place"
        }
    ],
    "sg:phone":"+1 217 887 2432",
    "sg:postcode":"61932",
    "sg:province":"IL",
    "sg:tags":[
        "village"
    ],
    "wof:name":"Young America Twp Office",
    "wof:placetype":"venue"
},
  "geometry": {"coordinates":[-87.865932,39.798424],"type":"Point"}
}