{
  "type": "Feature",
  "properties": {
    "addr:full":"641 W Grand Avenue Chicago IL 60610",
    "addr:housenumber":"641",
    "addr:postcode":"60610",
    "addr:street":"W Grand Avenue",
    "iso:country":"US",
    "sg:address":"641 W Grand Avenue",
    "sg:city":"Chicago",
    "sg:classifiers":[
        {
            "category":"Building & Trades",
            "subcategory":"Construction",
            "type":"Services"
        }
    ],
    "sg:phone":"+1 312 421 4422",
    "sg:postcode":"60610",
    "sg:province":"IL",
    "sg:tags":[
        "interior",
        "design"
    ],
    "wof:name":"Jorje",
    "wof:placetype":"venue"
},
  "geometry": {"coordinates":[-87.644355,41.891204],"type":"Point"}
}