{
  "type": "Feature",
  "properties": {
    "addr:full":"1004 E Walnut St Watseka IL 60970",
    "addr:housenumber":"1004",
    "addr:postcode":"60970",
    "addr:street":"E Walnut St",
    "iso:country":"US",
    "sg:address":"1004 E Walnut St",
    "sg:city":"Watseka",
    "sg:classifiers":[
        {
            "category":"Restaurant",
            "type":"Food & Drink"
        }
    ],
    "sg:menulink":"http://www.allmenus.com/il/middleport/88395-monicals-pizza/menu/",
    "sg:phone":"+1 815 432 3714",
    "sg:postcode":"60970",
    "sg:province":"IL",
    "sg:tags":[
        "american",
        "pizza"
    ],
    "wof:name":"Monicals Pizza",
    "wof:placetype":"venue"
},
  "geometry": {"coordinates":[-87.713279,40.775709],"type":"Point"}
}