{
  "type": "Feature",
  "properties": {
    "iso:country":"US",
    "sg:address":"7901 167th St",
    "sg:city":"Tinley Park",
    "sg:classifiers":[
        {
            "category":"Social Services",
            "subcategory":"Child Care",
            "type":"Services"
        }
    ],
    "sg:phone":"+1 708 532 7676",
    "sg:postcode":"60477",
    "sg:province":"IL",
    "sg:tags":[
        "kindergarten",
        "academic",
        "school"
    ],
    "wof:name":"Bobbie Noonan's Child Care Inc",
    "wof:placetype":"venue"
},
  "geometry": {"coordinates":[-87.810543,41.587455],"type":"Point"}
}