{
  "type": "Feature",
  "properties": {
    "iso:country":"US",
    "sg:address":"1610 Luther Ln",
    "sg:city":"Park Ridge",
    "sg:classifiers":[
        {
            "category":"Organizations",
            "subcategory":"Religious Organization",
            "type":"Services"
        }
    ],
    "sg:phone":"+1 847 518 0773",
    "sg:postcode":"60068",
    "sg:province":"IL",
    "sg:tags":[
        "church"
    ],
    "wof:name":"Counseling Center-Luth Gen",
    "wof:placetype":"venue"
},
  "geometry": {"coordinates":[-87.849833,42.038043],"type":"Point"}
}