{
  "type": "Feature",
  "properties": {
    "addr:full":"1225 Tendick St Jacksonville IL 62650",
    "addr:housenumber":"1225",
    "addr:postcode":"62650",
    "addr:street":"Tendick St",
    "iso:country":"US",
    "sg:address":"1225 Tendick St",
    "sg:city":"Jacksonville",
    "sg:classifiers":[
        {
            "category":"Organizations",
            "subcategory":"Professional Association",
            "type":"Services"
        }
    ],
    "sg:phone":"+1 217 245 0707",
    "sg:postcode":"62650",
    "sg:province":"IL",
    "wof:name":"AFSCME",
    "wof:placetype":"venue"
},
  "geometry": {"coordinates":[-90.241027,39.71897],"type":"Point"}
}