{
  "type": "Feature",
  "properties": {
    "addr:full":"4340 Woodburn Rd Alton IL 62002",
    "addr:housenumber":"4340",
    "addr:postcode":"62002",
    "addr:street":"Woodburn Rd",
    "iso:country":"US",
    "sg:address":"4340 Woodburn Rd",
    "sg:city":"Alton",
    "sg:classifiers":[
        {
            "category":"Building & Trades",
            "subcategory":"Landscaping Services",
            "type":"Services"
        }
    ],
    "sg:phone":"+1 618 656 1385",
    "sg:postcode":"62002",
    "sg:province":"IL",
    "sg:tags":[
        "landscape",
        "contractor"
    ],
    "wof:name":"Professional Turf Mgmt Svc",
    "wof:placetype":"venue"
},
  "geometry": {"coordinates":[-90.063327,38.988635],"type":"Point"}
}