{
  "type": "Feature",
  "properties": {
    "addr:full":"7613 W Belmont Ave Elmwood Park IL 60707",
    "addr:housenumber":"7613",
    "addr:postcode":"60707",
    "addr:street":"W Belmont Ave",
    "iso:country":"US",
    "sg:address":"7613 W Belmont Ave",
    "sg:city":"Elmwood Park",
    "sg:classifiers":[
        {
            "category":"Professional",
            "subcategory":"Lawyer & Legal Services",
            "type":"Services"
        }
    ],
    "sg:phone":"+1 708 583 9788",
    "sg:postcode":"60707",
    "sg:province":"IL",
    "wof:name":"Alkhalafawi Amal",
    "wof:placetype":"venue"
},
  "geometry": {"coordinates":[-87.81710099999999,41.937698],"type":"Point"}
}