{
  "type": "Feature",
  "properties": {
    "iso:country":"US",
    "sg:address":"104 Walnut Cir",
    "sg:city":"Eureka",
    "sg:classifiers":[
        {
            "category":"Banks & Credit Unions",
            "subcategory":"Investment Brokerage",
            "type":"Services"
        }
    ],
    "sg:phone":"+1 309 467 4678",
    "sg:postcode":"61530",
    "sg:province":"IL",
    "sg:tags":[
        "advisory",
        "financial"
    ],
    "wof:name":"Fellner Financial Svc",
    "wof:placetype":"venue"
},
  "geometry": {"coordinates":[-89.274383,40.698775],"type":"Point"}
}