{
  "type": "Feature",
  "properties": {
    "addr:full":"8257 Express Dr Marion IL 62959",
    "addr:housenumber":"8257",
    "addr:postcode":"62959",
    "addr:street":"Express Dr",
    "iso:country":"US",
    "sg:address":"8257 Express Dr",
    "sg:city":"Marion",
    "sg:classifiers":[
        {
            "category":"Retail",
            "subcategory":"Veterinary Services",
            "type":"Services"
        }
    ],
    "sg:phone":"+1 618 993 2273",
    "sg:postcode":"62959",
    "sg:province":"IL",
    "sg:tags":[
        "veterinarian"
    ],
    "wof:name":"Pet Wellness Center PC",
    "wof:placetype":"venue"
},
  "geometry": {"coordinates":[-89.00990299999999,37.746601],"type":"Point"}
}