{
  "type": "Feature",
  "properties": {
    "iso:country":"US",
    "sg:address":"320 Melrose Ave",
    "sg:city":"Kenilworth",
    "sg:phone":"+1 847 853 8507",
    "sg:postcode":"60043",
    "sg:province":"IL",
    "sg:tags":[
        "farm",
        "corn",
        "soybean"
    ],
    "wof:name":"Heck Farms",
    "wof:placetype":"venue"
},
  "geometry": {"coordinates":[-87.71511099999999,42.09003],"type":"Point"}
}