{
  "type": "Feature",
  "properties": {
    "addr:full":"23558 N Echo Lake Rd Lake Zurich IL 60047",
    "addr:housenumber":"23558",
    "addr:postcode":"60047",
    "addr:street":"N Echo Lake Rd",
    "iso:country":"US",
    "sg:address":"23558 N Echo Lake Rd",
    "sg:city":"Lake Zurich",
    "sg:classifiers":[
        {
            "category":"Wholesale",
            "subcategory":"Non-durable Goods",
            "type":"Manufacturing & Wholesale Goods"
        }
    ],
    "sg:phone":"+1 847 550 1870",
    "sg:postcode":"60047",
    "sg:province":"IL",
    "wof:name":"SRK Enterprises Inc",
    "wof:placetype":"venue"
},
  "geometry": {"coordinates":[-88.085661,42.205282],"type":"Point"}
}