{
  "type": "Feature",
  "properties": {
    "addr:full":"8 Wesley St Henning IL 61848",
    "addr:housenumber":"8",
    "addr:postcode":"61848",
    "addr:street":"Wesley St",
    "iso:country":"US",
    "sg:address":"8 Wesley St",
    "sg:city":"Henning",
    "sg:classifiers":[
        {
            "category":"Government",
            "subcategory":"Fire Station",
            "type":"Public Place"
        }
    ],
    "sg:phone":"+1 217 759 7373",
    "sg:postcode":"61848",
    "sg:province":"IL",
    "sg:tags":[
        "department"
    ],
    "wof:name":"Henning Fire Dept",
    "wof:placetype":"venue"
},
  "geometry": {"coordinates":[-87.702116,40.306584],"type":"Point"}
}