{
  "type": "Feature",
  "properties": {
    "iso:country":"US",
    "sg:address":"3429 N. Harlem Ave.",
    "sg:city":"Chicago",
    "sg:classifiers":[
        {
            "category":"Arts & Performance",
            "subcategory":"Art Gallery",
            "type":"Entertainment"
        }
    ],
    "sg:phone":"+1 630 220 4916",
    "sg:postcode":"60634",
    "sg:province":"IL",
    "sg:website":"www.ArmaniSculpture.com",
    "wof:name":"Armani Sculptures and Figurines",
    "wof:placetype":"venue"
},
  "geometry": {"coordinates":[-87.806459,41.942446],"type":"Point"}
}