{
  "type": "Feature",
  "properties": {
    "addr:full":"5774 State Rte 26 S Freeport IL 61032",
    "addr:housenumber":"5774",
    "addr:postcode":"61032",
    "addr:street":"State Rte 26 S",
    "iso:country":"US",
    "sg:address":"5774 State Rte 26 S",
    "sg:city":"Freeport",
    "sg:classifiers":[
        {
            "category":"Real Estate",
            "subcategory":"Real Estate Operator",
            "type":"Services"
        }
    ],
    "sg:phone":"+1 815 232 1236",
    "sg:postcode":"61032",
    "sg:province":"IL",
    "sg:tags":[
        "lessor",
        "farm",
        "crop",
        "field",
        "soybean",
        "property"
    ],
    "wof:name":"Philip Meiners",
    "wof:placetype":"venue"
},
  "geometry": {"coordinates":[-89.63033799999999,42.218562],"type":"Point"}
}