{
  "type": "Feature",
  "properties": {
    "iso:country":"US",
    "sg:address":"1100 N East St",
    "sg:city":"Kewanee",
    "sg:classifiers":[
        {
            "category":"Organizations",
            "subcategory":"Non-profit Organization",
            "type":"Services"
        },
        {
            "category":"Social Services",
            "subcategory":"Job Training",
            "type":"Services"
        }
    ],
    "sg:phone":"+1 309 852 4626",
    "sg:postcode":"61443",
    "sg:province":"IL",
    "sg:tags":[
        "skilled",
        "disability",
        "center"
    ],
    "sg:website":"www.abilitiesplus.org",
    "wof:name":"Abilities Plus Inc",
    "wof:placetype":"venue"
},
  "geometry": {"coordinates":[-89.915181,41.256249],"type":"Point"}
}