{
  "type": "Feature",
  "properties": {
    "addr:full":"77 W Washington St Ste 1620 Chicago IL 60602",
    "addr:housenumber":"77",
    "addr:postcode":"60602",
    "addr:street":"W Washington St Ste 1620",
    "iso:country":"US",
    "sg:address":"77 W Washington St Ste 1620",
    "sg:city":"Chicago",
    "sg:classifiers":[
        {
            "category":"Health Services",
            "subcategory":"Clinic",
            "type":"Services"
        },
        {
            "category":"Health Services",
            "subcategory":"Health Practitioner",
            "type":"Services"
        }
    ],
    "sg:phone":"+1 847 721 8030",
    "sg:postcode":"60602",
    "sg:province":"IL",
    "sg:tags":[
        "nutritionist",
        "counseling",
        "mental"
    ],
    "sg:website":"www.eatingdisorderdietitian.com",
    "wof:name":"Allison B. Shudnow, MS, RD, LDN",
    "wof:placetype":"venue"
},
  "geometry": {"coordinates":[-87.63032699999999,41.88321],"type":"Point"}
}