{
  "type": "Feature",
  "properties": {
    "iso:country":"US",
    "sg:address":"17 Oak Park Dr W",
    "sg:city":"Centralia",
    "sg:classifiers":[
        {
            "category":"Personal",
            "subcategory":"Beauty Salon",
            "type":"Services"
        }
    ],
    "sg:phone":"+1 618 532 1739",
    "sg:postcode":"62801",
    "sg:province":"IL",
    "wof:name":"Ila's Hair Design",
    "wof:placetype":"venue"
},
  "geometry": {"coordinates":[-89.156516,38.529896],"type":"Point"}
}