{
  "type": "Feature",
  "properties": {
    "addr:full":"4121 Rutgers Ln Northbrook IL 60062",
    "addr:housenumber":"4121",
    "addr:postcode":"60062",
    "addr:street":"Rutgers Ln",
    "iso:country":"US",
    "sg:address":"4121 Rutgers Ln",
    "sg:city":"Northbrook",
    "sg:classifiers":[
        {
            "category":"Professional",
            "subcategory":"Secretarial Services",
            "type":"Services"
        }
    ],
    "sg:phone":"+1 847 564 5575",
    "sg:postcode":"60062",
    "sg:province":"IL",
    "sg:tags":[
        "convention",
        "court",
        "reporter"
    ],
    "wof:name":"Debra Hass & Assoc",
    "wof:placetype":"venue"
},
  "geometry": {"coordinates":[-87.88149900000001,42.134008],"type":"Point"}
}