{
  "type": "Feature",
  "properties": {
    "addr:full":"4805 N Pulaski Road Chicago IL 60630",
    "addr:housenumber":"4805",
    "addr:postcode":"60630",
    "addr:street":"N Pulaski Road",
    "iso:country":"US",
    "sg:address":"4805 N Pulaski Road",
    "sg:city":"Chicago",
    "sg:classifiers":[
        {
            "category":"Food & Beverages",
            "subcategory":"Groceries & Convenience Stores",
            "type":"Retail Goods"
        }
    ],
    "sg:phone":"+1 773 539 1779",
    "sg:postcode":"60630",
    "sg:province":"IL",
    "wof:name":"Eljeeb Grocery & Meat",
    "wof:placetype":"venue"
},
  "geometry": {"coordinates":[-87.72807299999999,41.968313],"type":"Point"}
}