{
  "type": "Feature",
  "properties": {
    "addr:full":"620 W Webster Ave Chicago IL 60614",
    "addr:housenumber":"620",
    "addr:postcode":"60614",
    "addr:street":"W Webster Ave",
    "iso:country":"US",
    "sg:address":"620 W Webster Ave",
    "sg:city":"Chicago",
    "sg:classifiers":[
        {
            "category":"Retail",
            "subcategory":"Veterinary Services",
            "type":"Services"
        }
    ],
    "sg:phone":"+1 773 327 5024",
    "sg:postcode":"60614",
    "sg:province":"IL",
    "sg:tags":[
        "veterinarian"
    ],
    "sg:website":"www.compassionatevet.com",
    "wof:name":"Compassionate Veterinary Care",
    "wof:placetype":"venue"
},
  "geometry": {"coordinates":[-87.644285,41.921879],"type":"Point"}
}