{
  "type": "Feature",
  "properties": {
    "iso:country":"US",
    "sg:address":"2507 Gael Ave",
    "sg:city":"Joliet",
    "sg:classifiers":[
        {
            "category":"Wholesale",
            "subcategory":"Painting Supplies",
            "type":"Manufacturing & Wholesale Goods"
        }
    ],
    "sg:phone":"+1 815 503 4122",
    "sg:postcode":"60435",
    "sg:province":"IL",
    "wof:name":"Team Revolution",
    "wof:placetype":"venue"
},
  "geometry": {"coordinates":[-88.15548800000001,41.569884],"type":"Point"}
}