{
  "type": "Feature",
  "properties": {
    "iso:country":"US",
    "sg:address":"624 W 61st Street",
    "sg:city":"Chicago",
    "sg:classifiers":[
        {
            "category":"Real Estate",
            "subcategory":"Real Estate Operator",
            "type":"Services"
        }
    ],
    "sg:phone":"+1 773 994 3690",
    "sg:postcode":"60621",
    "sg:province":"IL",
    "sg:tags":[
        "apartment"
    ],
    "wof:name":"Victoria Jennings Residences",
    "wof:placetype":"venue"
},
  "geometry": {"coordinates":[-87.640449,41.783333],"type":"Point"}
}