{
  "type": "Feature",
  "properties": {
    "iso:country":"US",
    "sg:address":"720 Calico Dr",
    "sg:city":"Aurora",
    "sg:classifiers":[
        {
            "category":"Building & Trades",
            "subcategory":"Construction",
            "type":"Services"
        }
    ],
    "sg:phone":"+1 630 892 9454",
    "sg:postcode":"60506",
    "sg:province":"IL",
    "sg:tags":[
        "system",
        "contractor",
        "air conditioning"
    ],
    "wof:name":"Williams & Sons Heating Cooling",
    "wof:placetype":"venue"
},
  "geometry": {"coordinates":[-88.33289499999999,41.791183],"type":"Point"}
}