{
  "type": "Feature",
  "properties": {
    "iso:country":"US",
    "sg:address":"501 N Mine St",
    "sg:city":"Sandoval",
    "sg:classifiers":[
        {
            "category":"Retail",
            "subcategory":"Laundry & Dry Cleaning",
            "type":"Services"
        }
    ],
    "sg:phone":"+1 618 247 3800",
    "sg:postcode":"62882",
    "sg:province":"IL",
    "wof:name":"Derricks Laundry",
    "wof:placetype":"venue"
},
  "geometry": {"coordinates":[-89.114322,38.616047],"type":"Point"}
}