{
  "type": "Feature",
  "properties": {
    "addr:full":"3492 Mississippi Ave East Saint Louis IL 62206",
    "addr:housenumber":"3492",
    "addr:postcode":"62206",
    "addr:street":"Mississippi Ave East",
    "iso:country":"US",
    "sg:address":"3492 Mississippi Ave",
    "sg:city":"East Saint Louis",
    "sg:classifiers":[
        {
            "category":"Personal",
            "type":"Services"
        }
    ],
    "sg:phone":"+1 618 337 6213",
    "sg:postcode":"62206",
    "sg:province":"IL",
    "sg:tags":[
        "towing"
    ],
    "wof:name":"MacKanson Automotive & Towing",
    "wof:placetype":"venue"
},
  "geometry": {"coordinates":[-90.1828,38.578899],"type":"Point"}
}