{
  "type": "Feature",
  "properties": {
    "iso:country":"US",
    "sg:address":"3715 N Vermilion St",
    "sg:city":"Danville",
    "sg:classifiers":[
        {
            "category":"Organizations",
            "subcategory":"Non-profit Organization",
            "type":"Services"
        },
        {
            "category":"Professional",
            "subcategory":"Employment Agencies",
            "type":"Services"
        }
    ],
    "sg:phone":"+1 217 446 1146",
    "sg:postcode":"61832",
    "sg:province":"IL",
    "sg:tags":[
        "job",
        "training",
        "vocational",
        "rehabilitation"
    ],
    "wof:name":"Rehab Products & Services Inc",
    "wof:placetype":"venue"
},
  "geometry": {"coordinates":[-87.630493,40.173253],"type":"Point"}
}