{
  "type": "Feature",
  "properties": {
    "addr:full":"230 W North Ave Chicago IL 60610",
    "addr:housenumber":"230",
    "addr:postcode":"60610",
    "addr:street":"W North Ave",
    "iso:country":"US",
    "sg:address":"230 W North Ave",
    "sg:city":"Chicago",
    "sg:classifiers":[
        {
            "category":"Food & Beverages",
            "subcategory":"Specialty",
            "type":"Retail Goods"
        },
        {
            "category":"Food & Beverages",
            "subcategory":"Fruits & Vegetables",
            "type":"Retail Goods"
        },
        {
            "category":"Shopping",
            "subcategory":"Pharmacy",
            "type":"Retail Goods"
        }
    ],
    "sg:phone":"+1 312 944 7085",
    "sg:postcode":"60610",
    "sg:province":"IL",
    "sg:tags":[
        "product",
        "wellness",
        "vitamin",
        "diet",
        "supplement",
        "health",
        "herb"
    ],
    "sg:website":"http://www.gnc.com",
    "wof:name":"GNC",
    "wof:placetype":"venue"
},
  "geometry": {"coordinates":[-87.63579,41.91114],"type":"Point"}
}