{
  "type": "Feature",
  "properties": {
    "addr:full":"1748 N Newcastle Ave Chicago IL 60707",
    "addr:housenumber":"1748",
    "addr:postcode":"60707",
    "addr:street":"N Newcastle Ave",
    "iso:country":"US",
    "sg:address":"1748 N Newcastle Ave",
    "sg:city":"Chicago",
    "sg:classifiers":[
        {
            "category":"Farming",
            "subcategory":"Orchard",
            "type":"Manufacturing & Wholesale Goods"
        },
        {
            "category":"Retail",
            "subcategory":"Animal Services",
            "type":"Services"
        }
    ],
    "sg:phone":"+1 773 637 7191",
    "sg:postcode":"60707",
    "sg:province":"IL",
    "sg:tags":[
        "transportation",
        "livestock",
        "hauling"
    ],
    "wof:name":"Cumberland Horse Vans Inc",
    "wof:placetype":"venue"
},
  "geometry": {"coordinates":[-87.796024,41.911723],"type":"Point"}
}