{
  "type": "Feature",
  "properties": {
    "iso:country":"US",
    "sg:address":"4918 N Clark St",
    "sg:city":"Chicago",
    "sg:classifiers":[
        {
            "category":"Taxi",
            "type":"Transportation"
        }
    ],
    "sg:phone":"+1 773 506 0000",
    "sg:postcode":"60640",
    "sg:province":"IL",
    "wof:name":"Avenue Transportion Inc",
    "wof:placetype":"venue"
},
  "geometry": {"coordinates":[-87.668043,41.971899],"type":"Point"}
}