{
  "type": "Feature",
  "properties": {
    "iso:country":"US",
    "sg:address":"1422 W Barry Ave",
    "sg:city":"Chicago",
    "sg:classifiers":[
        {
            "category":"Building & Trades",
            "subcategory":"Plumbing",
            "type":"Services"
        }
    ],
    "sg:phone":"+1 773 296 9196",
    "sg:postcode":"60657",
    "sg:province":"IL",
    "sg:tags":[
        "contractor"
    ],
    "wof:name":"Quality Plumbing & Cnstr",
    "wof:placetype":"venue"
},
  "geometry": {"coordinates":[-87.66392,41.938014],"type":"Point"}
}