{
  "type": "Feature",
  "properties": {
    "addr:full":"1645 Algonquin Rd Rolling Meadows IL 60008",
    "addr:housenumber":"1645",
    "addr:postcode":"60008",
    "addr:street":"Algonquin Rd",
    "iso:country":"US",
    "sg:address":"1645 Algonquin Rd",
    "sg:city":"Rolling Meadows",
    "sg:classifiers":[
        {
            "category":"Shopping",
            "subcategory":"Computers & Home Electronics",
            "type":"Retail Goods"
        }
    ],
    "sg:phone":"+1 847 956 9790",
    "sg:postcode":"60008",
    "sg:province":"IL",
    "sg:tags":[
        "game",
        "video"
    ],
    "wof:name":"EB Games",
    "wof:placetype":"venue"
},
  "geometry": {"coordinates":[-87.999121,42.055094],"type":"Point"}
}