{
  "type": "Feature",
  "properties": {
    "iso:country":"US",
    "sg:address":"1109 Huntleigh Dr",
    "sg:city":"Naperville",
    "sg:classifiers":[
        {
            "category":"Manufacturing",
            "subcategory":"Tools & Machinery",
            "type":"Manufacturing & Wholesale Goods"
        }
    ],
    "sg:phone":"+1 630 527 9906",
    "sg:postcode":"60540",
    "sg:province":"IL",
    "sg:tags":[
        "shades-wholesale",
        "lamp",
        "manufacturer"
    ],
    "wof:name":"Hand In Hand International Corporation",
    "wof:placetype":"venue"
},
  "geometry": {"coordinates":[-88.115984,41.75661],"type":"Point"}
}