{
  "type": "Feature",
  "properties": {
    "iso:country":"US",
    "sg:address":"2735 N Clark St",
    "sg:city":"Chicago",
    "sg:classifiers":[
        {
            "category":"Banks & Credit Unions",
            "subcategory":"Bureau De Change",
            "type":"Services"
        }
    ],
    "sg:phone":"+1 773 348 5474",
    "sg:postcode":"60614",
    "sg:province":"IL",
    "sg:tags":[
        "currency",
        "exchange",
        "broker",
        "foreign"
    ],
    "wof:name":"Clark & Diversey Currency Exchange",
    "wof:placetype":"venue"
},
  "geometry": {"coordinates":[-87.644594,41.931888],"type":"Point"}
}