{
  "type": "Feature",
  "properties": {
    "iso:country":"US",
    "sg:address":"151st & Central Ave",
    "sg:city":"Oak Forest",
    "sg:classifiers":[
        {
            "category":"Education",
            "subcategory":"Preschool",
            "type":"Public Place"
        },
        {
            "category":"Education",
            "subcategory":"School",
            "type":"Public Place"
        }
    ],
    "sg:phone":"+1 708 687 2196",
    "sg:postcode":"60452",
    "sg:province":"IL",
    "sg:tags":[
        "elementary"
    ],
    "wof:name":"Resurrection Preschool",
    "wof:placetype":"venue"
},
  "geometry": {"coordinates":[-87.756455,41.617583],"type":"Point"}
}