{
  "type": "Feature",
  "properties": {
    "iso:country":"US",
    "sg:address":"207 S Pershing St",
    "sg:city":"Energy",
    "sg:classifiers":[
        {
            "category":"Professional",
            "subcategory":"Computer Services",
            "type":"Services"
        }
    ],
    "sg:phone":"+1 618 942 7313",
    "sg:postcode":"62933",
    "sg:province":"IL",
    "sg:tags":[
        "repair"
    ],
    "wof:name":"Happy Tom's Discount Computers Inc",
    "wof:placetype":"venue"
},
  "geometry": {"coordinates":[-89.026134,37.770062],"type":"Point"}
}