{
  "type": "Feature",
  "properties": {
    "iso:country":"US",
    "sg:address":"306 42nd Ave",
    "sg:city":"East Moline",
    "sg:classifiers":[
        {
            "category":"Retail",
            "subcategory":"Car Wash",
            "type":"Services"
        }
    ],
    "sg:phone":"+1 309 792 2810",
    "sg:postcode":"61244",
    "sg:province":"IL",
    "sg:tags":[
        "carwash"
    ],
    "wof:name":"Waterworks Car Wash",
    "wof:placetype":"venue"
},
  "geometry": {"coordinates":[-90.453625,41.489885],"type":"Point"}
}