{
  "type": "Feature",
  "properties": {
    "iso:country":"US",
    "sg:address":"1467 McKinley Ave",
    "sg:city":"Belvidere",
    "sg:classifiers":[
        {
            "category":"Freight",
            "type":"Transportation"
        }
    ],
    "sg:phone":"+1 815 544 1169",
    "sg:postcode":"61008",
    "sg:province":"IL",
    "sg:tags":[
        "trucking"
    ],
    "wof:name":"Gallano Trucking Inc",
    "wof:placetype":"venue"
},
  "geometry": {"coordinates":[-88.841427,42.274689],"type":"Point"}
}