{
  "type": "Feature",
  "properties": {
    "iso:country":"US",
    "sg:address":"1116 Meriden St",
    "sg:city":"Mendota",
    "sg:classifiers":[
        {
            "category":"Shopping",
            "subcategory":"Pharmacy",
            "type":"Retail Goods"
        }
    ],
    "sg:phone":"+1   ",
    "sg:postcode":"61342",
    "sg:province":"IL",
    "sg:tags":[
        "photofinishing",
        "laboratory"
    ],
    "wof:name":"CVS",
    "wof:placetype":"venue"
},
  "geometry": {"coordinates":[-89.127582,41.555379],"type":"Point"}
}