{
  "type": "Feature",
  "properties": {
    "iso:country":"US",
    "sg:address":"441 Eagles Nest Dr",
    "sg:city":"Darien",
    "sg:classifiers":[
        {
            "category":"Health Services",
            "subcategory":"Doctor",
            "type":"Services"
        }
    ],
    "sg:phone":"+1 630 655 0731",
    "sg:postcode":"60561",
    "sg:province":"IL",
    "sg:tags":[
        "physician",
        "surgeon"
    ],
    "wof:name":"Physician Mgmt. Resources",
    "wof:placetype":"venue"
},
  "geometry": {"coordinates":[-87.956292,41.768162],"type":"Point"}
}