{
  "type": "Feature",
  "properties": {
    "addr:full":"5657 N Lincoln Ave Chicago IL 60659",
    "addr:housenumber":"5657",
    "addr:postcode":"60659",
    "addr:street":"N Lincoln Ave",
    "iso:country":"US",
    "sg:address":"5657 N Lincoln Ave",
    "sg:city":"Chicago",
    "sg:classifiers":[
        {
            "category":"Restaurant",
            "type":"Food & Drink"
        }
    ],
    "sg:menulink":"http://www.allmenus.com/il/chicago/203799-cedar-grill-restaurant--cage/menu/",
    "sg:phone":"+1 773 506 2050",
    "sg:postcode":"60659",
    "sg:province":"IL",
    "sg:tags":[
        "middle",
        "eastern"
    ],
    "wof:name":"Cedar Grill Restaurant & Cage",
    "wof:placetype":"venue"
},
  "geometry": {"coordinates":[-87.697029,41.984246],"type":"Point"}
}