{
  "type": "Feature",
  "properties": {
    "iso:country":"US",
    "sg:address":"2580 Northwest Pkwy",
    "sg:city":"Elgin",
    "sg:classifiers":[
        {
            "category":"Wholesale",
            "subcategory":"Auto Parts",
            "type":"Manufacturing & Wholesale Goods"
        }
    ],
    "sg:phone":"+1 847 844 7680",
    "sg:postcode":"60124",
    "sg:province":"IL",
    "wof:name":"Nova Prevost Bus Parts",
    "wof:placetype":"venue"
},
  "geometry": {"coordinates":[-88.25852399999999,42.062072],"type":"Point"}
}