{
  "type": "Feature",
  "properties": {
    "addr:full":"2214 Scottsdale Dr Champaign IL 61822",
    "addr:housenumber":"2214",
    "addr:postcode":"61822",
    "addr:street":"Scottsdale Dr",
    "iso:country":"US",
    "sg:address":"2214 Scottsdale Dr",
    "sg:city":"Champaign",
    "sg:classifiers":[
        {
            "category":"Organizations",
            "subcategory":"Religious Organization",
            "type":"Services"
        }
    ],
    "sg:phone":"+1 217 352 6244",
    "sg:postcode":"61822",
    "sg:province":"IL",
    "wof:name":"Hindu Temple & Cultural Soc",
    "wof:placetype":"venue"
},
  "geometry": {"coordinates":[-88.288291,40.086327],"type":"Point"}
}