{
  "type": "Feature",
  "properties": {
    "addr:full":"927 Britta Ln Batavia IL 60510",
    "addr:housenumber":"927",
    "addr:postcode":"60510",
    "addr:street":"Britta Ln",
    "iso:country":"US",
    "sg:address":"927 Britta Ln",
    "sg:city":"Batavia",
    "sg:classifiers":[
        {
            "category":"Shopping",
            "subcategory":"Clothing, Apparel, & Fashions",
            "type":"Retail Goods"
        }
    ],
    "sg:phone":"+1 630 406 1495",
    "sg:postcode":"60510",
    "sg:province":"IL",
    "sg:tags":[
        "clothing",
        "store"
    ],
    "sg:website":"http://www.lcweave.com",
    "wof:name":"Lynn Caldwell Ltd",
    "wof:placetype":"venue"
},
  "geometry": {"coordinates":[-88.32123199999999,41.863428],"type":"Point"}
}