{
  "type": "Feature",
  "properties": {
    "addr:full":"4703 W Arthington St Chicago IL 60644",
    "addr:housenumber":"4703",
    "addr:postcode":"60644",
    "addr:street":"W Arthington St",
    "iso:country":"US",
    "sg:address":"4703 W Arthington St",
    "sg:city":"Chicago",
    "sg:classifiers":[
        {
            "category":"Building & Trades",
            "subcategory":"Construction",
            "type":"Services"
        }
    ],
    "sg:phone":"+1 773 626 3366",
    "sg:postcode":"60644",
    "sg:province":"IL",
    "sg:tags":[
        "company",
        "moving"
    ],
    "wof:name":"Rameco Inc",
    "wof:placetype":"venue"
},
  "geometry": {"coordinates":[-87.74423899999999,41.869476],"type":"Point"}
}