{
  "type": "Feature",
  "properties": {
    "addr:full":"70 S Evergreen Ave Arlington Hts IL 60005",
    "addr:housenumber":"70",
    "addr:postcode":"60005",
    "addr:street":"S Evergreen Ave",
    "iso:country":"US",
    "sg:address":"70 S Evergreen Ave",
    "sg:city":"Arlington Hts",
    "sg:classifiers":[
        {
            "category":"Food & Beverages",
            "subcategory":"Liquor & Beverages",
            "type":"Retail Goods"
        }
    ],
    "sg:phone":"+1 847 590 8655",
    "sg:postcode":"60005",
    "sg:province":"IL",
    "sg:tags":[
        "wine"
    ],
    "wof:name":"Cabernet & Co",
    "wof:placetype":"venue"
},
  "geometry": {"coordinates":[-87.981775,42.082243],"type":"Point"}
}