{
  "type": "Feature",
  "properties": {
    "iso:country":"US",
    "sg:address":"4921 Hiawatha Dr",
    "sg:city":"Rockford",
    "sg:classifiers":[
        {
            "category":"Wholesale",
            "subcategory":"Construction Materials",
            "type":"Manufacturing & Wholesale Goods"
        }
    ],
    "sg:phone":"+1 815 877 1471",
    "sg:postcode":"61103",
    "sg:province":"IL",
    "sg:tags":[
        "plywood",
        "veneer"
    ],
    "wof:name":"Seigle's Millwork Ctr",
    "wof:placetype":"venue"
},
  "geometry": {"coordinates":[-89.06935300000001,42.327587],"type":"Point"}
}