{
  "type": "Feature",
  "properties": {
    "iso:country":"US",
    "sg:address":"1191 E 4000S Rd",
    "sg:city":"Kankakee",
    "sg:classifiers":[
        {
            "category":"Social Services",
            "type":"Services"
        }
    ],
    "sg:phone":"+1 815 937 6981",
    "sg:postcode":"60901",
    "sg:province":"IL",
    "wof:name":"Joint Armed Forces Reserve Ctr",
    "wof:placetype":"venue"
},
  "geometry": {"coordinates":[-87.847321,41.062526],"type":"Point"}
}