{
  "type": "Feature",
  "properties": {
    "addr:full":"4401 W Carroll Ave Chicago IL 60624",
    "addr:housenumber":"4401",
    "addr:postcode":"60624",
    "addr:street":"W Carroll Ave",
    "iso:country":"US",
    "sg:address":"4401 W Carroll Ave",
    "sg:city":"Chicago",
    "sg:classifiers":[
        {
            "category":"Place Of Worship",
            "subcategory":"Church",
            "type":"Public Place"
        },
        {
            "category":"Place Of Worship",
            "type":"Public Place"
        },
        {
            "category":"Organizations",
            "subcategory":"Religious Organization",
            "type":"Services"
        }
    ],
    "sg:phone":"+1 773 261 0655",
    "sg:postcode":"60624",
    "sg:province":"IL",
    "sg:tags":[
        "christ",
        "god",
        "denomination",
        "churches-church",
        "churches-pentecostal",
        "churches-interdenominational",
        "churches-various"
    ],
    "wof:name":"True Tabernacle Fellowship Church of God In Christ",
    "wof:placetype":"venue"
},
  "geometry": {"coordinates":[-87.735657,41.886879],"type":"Point"}
}