{
  "type": "Feature",
  "properties": {
    "iso:country":"US",
    "sg:address":"1750 N Natoma Ave",
    "sg:city":"Chicago",
    "sg:classifiers":[
        {
            "category":"Social Services",
            "subcategory":"Child Care",
            "type":"Services"
        }
    ],
    "sg:phone":"+1 773 237 7377",
    "sg:postcode":"60707",
    "sg:province":"IL",
    "sg:tags":[
        "nursery",
        "day"
    ],
    "sg:website":"www.grannyscorner.com",
    "wof:name":"Granny's Corner Child Care",
    "wof:placetype":"venue"
},
  "geometry": {"coordinates":[-87.791,41.912399],"type":"Point"}
}