{
  "type": "Feature",
  "properties": {
    "addr:full":"1315 Arlington Chase Sherman IL 62684",
    "addr:housenumber":"1315",
    "addr:postcode":"62684",
    "addr:street":"Arlington Chase",
    "iso:country":"US",
    "sg:address":"1315 Arlington Chase",
    "sg:city":"Sherman",
    "sg:classifiers":[
        {
            "category":"Building & Trades",
            "subcategory":"Construction",
            "type":"Services"
        }
    ],
    "sg:phone":"+1 217 496 3112",
    "sg:postcode":"62684",
    "sg:province":"IL",
    "sg:tags":[
        "house"
    ],
    "wof:name":"Zinn Construction LLC",
    "wof:placetype":"venue"
},
  "geometry": {"coordinates":[-89.602001,39.87664],"type":"Point"}
}