{
  "type": "Feature",
  "properties": {
    "iso:country":"US",
    "sg:address":"20446 Rand Rd",
    "sg:city":"Kildeer",
    "sg:classifiers":[
        {
            "category":"Shopping",
            "subcategory":"Computers & Home Electronics",
            "type":"Retail Goods"
        }
    ],
    "sg:phone":"+1 847 550 1500",
    "sg:postcode":"60074",
    "sg:province":"IL",
    "sg:tags":[
        "equipment",
        "electronic",
        "supply"
    ],
    "wof:name":"1 Stop Electronics Inc",
    "wof:placetype":"venue"
},
  "geometry": {"coordinates":[-88.049656,42.160551],"type":"Point"}
}