{
  "type": "Feature",
  "properties": {
    "iso:country":"US",
    "sg:address":"211 E Sherwood Dr",
    "sg:city":"Cary",
    "sg:classifiers":[
        {
            "category":"Building & Trades",
            "subcategory":"Cleaning & Sanitation",
            "type":"Services"
        }
    ],
    "sg:phone":"+1 847 639 7860",
    "sg:postcode":"60013",
    "sg:province":"IL",
    "sg:tags":[
        "janitor"
    ],
    "wof:name":"Cruz Janitorial Svc",
    "wof:placetype":"venue"
},
  "geometry": {"coordinates":[-88.23161899999999,42.212304],"type":"Point"}
}