{
  "type": "Feature",
  "properties": {
    "iso:country":"US",
    "sg:address":"316 Brady Mill Rd",
    "sg:city":"Anna",
    "sg:classifiers":[
        {
            "category":"Social Services",
            "subcategory":"Adult Care",
            "type":"Services"
        }
    ],
    "sg:phone":"+1 618 833 4774",
    "sg:postcode":"62906",
    "sg:province":"IL",
    "sg:tags":[
        "residential"
    ],
    "wof:name":"Village Inn Cobden Inc",
    "wof:placetype":"venue"
},
  "geometry": {"coordinates":[-89.232799,37.453204],"type":"Point"}
}