{
  "type": "Feature",
  "properties": {
    "iso:country":"US",
    "sg:address":"1001 N Old Rand Rd Unit 103A",
    "sg:city":"Wauconda",
    "sg:classifiers":[
        {
            "category":"Industrial Area",
            "type":"Public Place"
        }
    ],
    "sg:phone":"+1 847 528 0064",
    "sg:postcode":"60084",
    "sg:province":"IL",
    "sg:tags":[
        "consultant"
    ],
    "sg:website":"http://www.bonafidecorp.com",
    "wof:name":"Bona Fide",
    "wof:placetype":"venue"
},
  "geometry": {"coordinates":[-88.14728700000001,42.27514],"type":"Point"}
}