{
  "type": "Feature",
  "properties": {
    "addr:full":"6451 W. Diversey Avenue Brickyard Mall Chicago IL 60707",
    "addr:housenumber":"6451",
    "addr:postcode":"60707",
    "addr:street":"W. Diversey Avenue Brickyard Mall",
    "iso:country":"US",
    "sg:address":"6451 W. Diversey Avenue Brickyard Mall",
    "sg:city":"Chicago",
    "sg:classifiers":[
        {
            "category":"Shopping",
            "subcategory":"Department Store",
            "type":"Retail Goods"
        },
        {
            "category":"Shopping",
            "subcategory":"Shoes",
            "type":"Retail Goods"
        }
    ],
    "sg:phone":"+1 773 237 3459",
    "sg:postcode":"60707",
    "sg:province":"IL",
    "sg:website":"www.hotforshoes.com/",
    "wof:name":"Hot for Shoes",
    "wof:placetype":"venue"
},
  "geometry": {"coordinates":[-87.787346,41.930862],"type":"Point"}
}