{
  "type": "Feature",
  "properties": {
    "iso:country":"US",
    "sg:address":"21 N Wabash Ave Ste 15",
    "sg:city":"Chicago",
    "sg:phone":"+1 312 558 9200",
    "sg:postcode":"60602",
    "sg:province":"IL",
    "wof:name":"Porush Jewelers",
    "wof:placetype":"venue"
},
  "geometry": {"coordinates":[-87.626172,41.882304],"type":"Point"}
}