{
  "type": "Feature",
  "properties": {
    "addr:full":"31 N Broadway Aurora IL 60505",
    "addr:housenumber":"31",
    "addr:postcode":"60505",
    "addr:street":"N Broadway",
    "iso:country":"US",
    "sg:address":"31 N Broadway",
    "sg:city":"Aurora",
    "sg:classifiers":[
        {
            "category":"Restaurant",
            "type":"Food & Drink"
        }
    ],
    "sg:phone":"+1 630 844 9904",
    "sg:postcode":"60505",
    "sg:province":"IL",
    "wof:name":"Ciara's Place",
    "wof:placetype":"venue"
},
  "geometry": {"coordinates":[-88.31244700000001,41.757413],"type":"Point"}
}