{
  "type": "Feature",
  "properties": {
    "iso:country":"US",
    "sg:address":"31 N Broadway",
    "sg:city":"Aurora",
    "sg:classifiers":[
        {
            "category":"Restaurant",
            "type":"Food & Drink"
        }
    ],
    "sg:phone":"+1 630 844 9904",
    "sg:postcode":"60505",
    "sg:province":"IL",
    "wof:name":"Ciara's Place",
    "wof:placetype":"venue"
},
  "geometry": {"coordinates":[-88.312447,41.757413],"type":"Point"}
}