{
  "type": "Feature",
  "properties": {
    "addr:full":"1400 N Center St Joliet IL 60435",
    "addr:housenumber":"1400",
    "addr:postcode":"60435",
    "addr:street":"N Center St",
    "iso:country":"US",
    "sg:address":"1400 N Center St",
    "sg:city":"Joliet",
    "sg:classifiers":[
        {
            "category":"Bars & Pubs",
            "type":"Food & Drink"
        }
    ],
    "sg:phone":"+1 815 722 8701",
    "sg:postcode":"60435",
    "sg:province":"IL",
    "wof:name":"Crow's Nest Sports Bar & Grill",
    "wof:placetype":"venue"
},
  "geometry": {"coordinates":[-88.092085,41.550523],"type":"Point"}
}