{
  "type": "Feature",
  "properties": {
    "addr:full":"202 S Church St Belleville IL 62220",
    "addr:housenumber":"202",
    "addr:postcode":"62220",
    "addr:street":"S Church St",
    "iso:country":"US",
    "sg:address":"202 S Church St",
    "sg:city":"Belleville",
    "sg:classifiers":[
        {
            "category":"Personal",
            "subcategory":"Beauty Salon",
            "type":"Services"
        }
    ],
    "sg:phone":"+1 618 234 6547",
    "sg:postcode":"62220",
    "sg:province":"IL",
    "sg:tags":[
        "shop"
    ],
    "wof:name":"Hair Designers LTD",
    "wof:placetype":"venue"
},
  "geometry": {"coordinates":[-89.980165,38.509781],"type":"Point"}
}