{
  "type": "Feature",
  "properties": {
    "iso:country":"US",
    "sg:address":"1049 W Bryn Mawr Ave",
    "sg:city":"Chicago",
    "sg:classifiers":[
        {
            "category":"Food & Beverages",
            "subcategory":"Groceries & Convenience Stores",
            "type":"Retail Goods"
        }
    ],
    "sg:phone":"+1 773 728 3900",
    "sg:postcode":"60660",
    "sg:province":"IL",
    "wof:name":"Super Food Inc",
    "wof:placetype":"venue"
},
  "geometry": {"coordinates":[-87.6576,41.983501],"type":"Point"}
}