{
  "type": "Feature",
  "properties": {
    "addr:full":"1429 Thouvenot Ln O Fallon IL 62269",
    "addr:housenumber":"1429",
    "addr:postcode":"62269",
    "addr:street":"Thouvenot Ln O",
    "iso:country":"US",
    "sg:address":"1429 Thouvenot Ln",
    "sg:city":"O Fallon",
    "sg:classifiers":[
        {
            "category":"Building & Trades",
            "subcategory":"Plumbing",
            "type":"Services"
        }
    ],
    "sg:phone":"+1 618 656 9925",
    "sg:postcode":"62269",
    "sg:province":"IL",
    "wof:name":"AAA Aceco Plumbing & Heating",
    "wof:placetype":"venue"
},
  "geometry": {"coordinates":[-89.96199799999999,38.570702],"type":"Point"}
}