{
  "type": "Feature",
  "properties": {
    "addr:full":"4328 S Western Ave Chicago IL 60609",
    "addr:housenumber":"4328",
    "addr:postcode":"60609",
    "addr:street":"S Western Ave",
    "iso:country":"US",
    "sg:address":"4328 S Western Ave",
    "sg:city":"Chicago",
    "sg:classifiers":[
        {
            "category":"Manufacturing",
            "subcategory":"Tools & Machinery",
            "type":"Manufacturing & Wholesale Goods"
        },
        {
            "category":"Wholesale",
            "subcategory":"Electrical",
            "type":"Manufacturing & Wholesale Goods"
        },
        {
            "category":"Building & Trades",
            "subcategory":"Electrical",
            "type":"Services"
        }
    ],
    "sg:phone":"+1 773 843 9700",
    "sg:postcode":"60609",
    "sg:province":"IL",
    "sg:tags":[
        "electrician",
        "electric",
        "supply",
        "equipment",
        "supplies-wholesale",
        "manufacturer"
    ],
    "wof:name":"Parras Auto Electric",
    "wof:placetype":"venue"
},
  "geometry": {"coordinates":[-87.684622,41.815172],"type":"Point"}
}