{
  "type": "Feature",
  "properties": {
    "addr:full":"615 W Kemper Place Chicago IL 60614",
    "addr:housenumber":"615",
    "addr:postcode":"60614",
    "addr:street":"W Kemper Place",
    "iso:country":"US",
    "sg:address":"615 W Kemper Place",
    "sg:city":"Chicago",
    "sg:classifiers":[
        {
            "category":"Education",
            "subcategory":"School",
            "type":"Public Place"
        }
    ],
    "sg:phone":"+1 773 534 5720",
    "sg:postcode":"60614",
    "sg:province":"IL",
    "sg:tags":[
        "high",
        "middle",
        "elementary"
    ],
    "wof:name":"Schools Public",
    "wof:placetype":"venue"
},
  "geometry": {"coordinates":[-87.644203,41.924608],"type":"Point"}
}