{
  "type": "Feature",
  "properties": {
    "iso:country":"US",
    "sg:address":"307 Henry St",
    "sg:city":"Alton",
    "sg:classifiers":[
        {
            "category":"Health Services",
            "subcategory":"Doctor",
            "type":"Services"
        }
    ],
    "sg:phone":"+1 618 462 0818",
    "sg:postcode":"62002",
    "sg:province":"IL",
    "sg:tags":[
        "physician",
        "medical",
        "surgeon"
    ],
    "wof:name":"Bradley G Campbell MD",
    "wof:placetype":"venue"
},
  "geometry": {"coordinates":[-90.176902,38.891146],"type":"Point"}
}