{
  "type": "Feature",
  "properties": {
    "iso:country":"US",
    "sg:address":"2060 Pratt Blvd",
    "sg:city":"Elk Grove Village",
    "sg:classifiers":[
        {
            "category":"Professional",
            "subcategory":"Management & Consulting",
            "type":"Services"
        }
    ],
    "sg:phone":"+1 847 427 8527",
    "sg:postcode":"60007",
    "sg:province":"IL",
    "sg:tags":[
        "grocery",
        "general"
    ],
    "wof:name":"Gordon Food Service Inc",
    "wof:placetype":"venue"
},
  "geometry": {"coordinates":[-87.95818199999999,41.998312],"type":"Point"}
}