{
  "type": "Feature",
  "properties": {
    "iso:country":"US",
    "sg:address":"1607 W Fullerton Ave",
    "sg:city":"Chicago",
    "sg:classifiers":[
        {
            "category":"Autos & Motor Vehicles",
            "subcategory":"Fuel & Gas Station",
            "type":"Retail Goods"
        }
    ],
    "sg:phone":"+1 773 525 9697",
    "sg:postcode":"60614",
    "sg:province":"IL",
    "wof:name":"J F Service Inc",
    "wof:placetype":"venue"
},
  "geometry": {"coordinates":[-87.66837200000001,41.924993],"type":"Point"}
}