{
  "type": "Feature",
  "properties": {
    "addr:full":"1826 Parkdale Dr Champaign IL 61821",
    "addr:housenumber":"1826",
    "addr:postcode":"61821",
    "addr:street":"Parkdale Dr",
    "iso:country":"US",
    "sg:address":"1826 Parkdale Dr",
    "sg:city":"Champaign",
    "sg:classifiers":[
        {
            "category":"Personal",
            "type":"Services"
        }
    ],
    "sg:phone":"+1 217 352 8734",
    "sg:postcode":"61821",
    "sg:province":"IL",
    "sg:tags":[
        "sewing",
        "alteration"
    ],
    "wof:name":"Connie's Caring Hands",
    "wof:placetype":"venue"
},
  "geometry": {"coordinates":[-88.27950300000001,40.0975],"type":"Point"}
}