{
  "type": "Feature",
  "properties": {
    "addr:full":"507 4th Ave Rochelle IL 61068",
    "addr:housenumber":"507",
    "addr:postcode":"61068",
    "addr:street":"4Th Ave",
    "iso:country":"US",
    "sg:address":"507 4th Ave",
    "sg:city":"Rochelle",
    "sg:classifiers":[
        {
            "category":"Restaurant",
            "type":"Food & Drink"
        }
    ],
    "sg:phone":"+1 815 562 1851",
    "sg:postcode":"61068",
    "sg:province":"IL",
    "sg:tags":[
        "eating"
    ],
    "wof:name":"El Sol Restaurant",
    "wof:placetype":"venue"
},
  "geometry": {"coordinates":[-89.066383,41.922748],"type":"Point"}
}