{
  "type": "Feature",
  "properties": {
    "iso:country":"US",
    "sg:address":"1515 E 71st Street",
    "sg:city":"Chicago",
    "sg:classifiers":[
        {
            "category":"Professional",
            "subcategory":"Employment Agencies",
            "type":"Services"
        }
    ],
    "sg:phone":"+1 773 947 2500",
    "sg:postcode":"60619",
    "sg:province":"IL",
    "wof:name":"Illinois Department of Employment Security",
    "wof:placetype":"venue"
},
  "geometry": {"coordinates":[-87.58783699999999,41.76605],"type":"Point"}
}