{
  "type": "Feature",
  "properties": {
    "addr:full":"900 Ogden Ave Downers Grove IL 60515",
    "addr:housenumber":"900",
    "addr:postcode":"60515",
    "addr:street":"Ogden Ave",
    "iso:country":"US",
    "sg:address":"900 Ogden Ave",
    "sg:city":"Downers Grove",
    "sg:classifiers":[
        {
            "category":"Professional",
            "subcategory":"Computer Services",
            "type":"Services"
        }
    ],
    "sg:phone":"+1 630 221 9116",
    "sg:postcode":"60515",
    "sg:province":"IL",
    "sg:tags":[
        "insurance",
        "related"
    ],
    "wof:name":"Managerial Technologies Corp",
    "wof:placetype":"venue"
},
  "geometry": {"coordinates":[-88.00738200000001,41.809036],"type":"Point"}
}