{
  "type": "Feature",
  "properties": {
    "iso:country":"US",
    "sg:address":"3022 Tower Dr",
    "sg:city":"Mc Henry",
    "sg:classifiers":[
        {
            "category":"Building & Trades",
            "subcategory":"Cleaning & Sanitation",
            "type":"Services"
        }
    ],
    "sg:phone":"+1 815 578 0018",
    "sg:postcode":"60051",
    "sg:province":"IL",
    "sg:tags":[
        "maintenance"
    ],
    "wof:name":"Excellent Cleaning Service",
    "wof:placetype":"venue"
},
  "geometry": {"coordinates":[-88.226251,42.286427],"type":"Point"}
}