{
  "type": "Feature",
  "properties": {
    "addr:full":"1132 Avenue of the Cities East Moline IL 61244",
    "addr:housenumber":"1132",
    "addr:postcode":"61244",
    "addr:street":"Avenue Of The;East",
    "iso:country":"US",
    "sg:address":"1132 Avenue of the Cities",
    "sg:city":"East Moline",
    "sg:classifiers":[
        {
            "category":"Professional",
            "type":"Services"
        },
        {
            "category":"Restaurant",
            "type":"Food & Drink"
        }
    ],
    "sg:phone":"+1 309 792 9500",
    "sg:postcode":"61244",
    "sg:province":"IL",
    "sg:tags":[
        "pizza",
        "caterer"
    ],
    "sg:website":"www.fieldsofpizza.com",
    "wof:name":"Fields of Pizza",
    "wof:placetype":"venue"
},
  "geometry": {"coordinates":[-90.43526199999999,41.489618],"type":"Point"}
}