{
  "type": "Feature",
  "properties": {
    "iso:country":"US",
    "sg:address":"116 W Hubbard St",
    "sg:city":"Chicago",
    "sg:classifiers":[
        {
            "category":"Bars & Pubs",
            "type":"Food & Drink"
        },
        {
            "category":"Bars & Pubs",
            "subcategory":"Nightclub",
            "type":"Food & Drink"
        },
        {
            "category":"Bars & Pubs",
            "subcategory":"Lounge",
            "type":"Food & Drink"
        }
    ],
    "sg:phone":"+1 312 329 9960",
    "sg:postcode":"60654",
    "sg:province":"IL",
    "sg:tags":[
        "club",
        "cocktail",
        "night"
    ],
    "wof:name":"Nv Penthouse Lounge",
    "wof:placetype":"venue"
},
  "geometry": {"coordinates":[-87.63177,41.890016],"type":"Point"}
}