{
  "type": "Feature",
  "properties": {
    "addr:full":"2000 W Fulton St Chicago IL 60612",
    "addr:housenumber":"2000",
    "addr:postcode":"60612",
    "addr:street":"W Fulton St",
    "iso:country":"US",
    "sg:address":"2000 W Fulton St",
    "sg:city":"Chicago",
    "sg:classifiers":[
        {
            "category":"Professional",
            "subcategory":"Computer Services",
            "type":"Services"
        }
    ],
    "sg:phone":"+1 312 226 4063",
    "sg:postcode":"60612",
    "sg:province":"IL",
    "sg:tags":[
        "repair"
    ],
    "sg:website":"www.carltontechnologies.com",
    "wof:name":"Carlton Technologies",
    "wof:placetype":"venue"
},
  "geometry": {"coordinates":[-87.67679099999999,41.886768],"type":"Point"}
}