{
  "type": "Feature",
  "properties": {
    "iso:country":"US",
    "sg:address":"400 E 76th St",
    "sg:city":"Chicago",
    "sg:classifiers":[
        {
            "category":"Home & Garden",
            "subcategory":"Household Appliances",
            "type":"Retail Goods"
        }
    ],
    "sg:phone":"+1 773 924 1630",
    "sg:postcode":"60619",
    "sg:province":"IL",
    "sg:tags":[
        "equipment",
        "purifying",
        "cleaning",
        "air"
    ],
    "wof:name":"Enviroair Incorporated",
    "wof:placetype":"venue"
},
  "geometry": {"coordinates":[-87.615082,41.75658],"type":"Point"}
}