{
  "type": "Feature",
  "properties": {
    "addr:full":"1203 Aurora Way Wheaton IL 60187",
    "addr:housenumber":"1203",
    "addr:postcode":"60187",
    "addr:street":"Aurora Way",
    "iso:country":"US",
    "sg:address":"1203 Aurora Way",
    "sg:city":"Wheaton",
    "sg:classifiers":[
        {
            "category":"Building & Trades",
            "subcategory":"Construction",
            "type":"Services"
        }
    ],
    "sg:phone":"+1 630 462 8062",
    "sg:postcode":"60187",
    "sg:province":"IL",
    "sg:tags":[
        "house"
    ],
    "wof:name":"Armbrust Rj Inc",
    "wof:placetype":"venue"
},
  "geometry": {"coordinates":[-88.12469900000001,41.8517],"type":"Point"}
}