{
  "type": "Feature",
  "properties": {
    "addr:full":"1 Franklin Ct Bolingbrook IL 60440",
    "addr:housenumber":"1",
    "addr:postcode":"60440",
    "addr:street":"Franklin Ct",
    "iso:country":"US",
    "sg:address":"1 Franklin Ct",
    "sg:city":"Bolingbrook",
    "sg:classifiers":[
        {
            "category":"Professional",
            "subcategory":"Employment Agencies",
            "type":"Services"
        }
    ],
    "sg:phone":"+1 630 378 5219",
    "sg:postcode":"60440",
    "sg:province":"IL",
    "sg:tags":[
        "opportunity"
    ],
    "wof:name":"Corinthian Man Power Dev",
    "wof:placetype":"venue"
},
  "geometry": {"coordinates":[-88.09793500000001,41.699303],"type":"Point"}
}