{
  "type": "Feature",
  "properties": {
    "iso:country":"US",
    "sg:address":"839 E Rollins Rd",
    "sg:city":"Round Lake Beach",
    "sg:classifiers":[
        {
            "category":"Banks & Credit Unions",
            "subcategory":"Bank",
            "type":"Services"
        }
    ],
    "sg:phone":"+1 847 543 4904",
    "sg:postcode":"60073",
    "sg:province":"IL",
    "wof:name":"Washington Mutual",
    "wof:placetype":"venue"
},
  "geometry": {"coordinates":[-88.059556,42.380593],"type":"Point"}
}