{
  "type": "Feature",
  "properties": {
    "iso:country":"US",
    "sg:address":"1234 N Lake St",
    "sg:city":"Aurora",
    "sg:classifiers":[
        {
            "category":"Restaurant",
            "type":"Food & Drink"
        }
    ],
    "sg:phone":"+1   ",
    "sg:postcode":"60506",
    "sg:province":"IL",
    "sg:tags":[
        "eating"
    ],
    "wof:name":"Thai Spice Restaurant",
    "wof:placetype":"venue"
},
  "geometry": {"coordinates":[-88.320154,41.785985],"type":"Point"}
}