{
  "type": "Feature",
  "properties": {
    "addr:full":"561 Kilkenny Ct Gilberts IL 60136",
    "addr:housenumber":"561",
    "addr:postcode":"60136",
    "addr:street":"Kilkenny Ct",
    "iso:country":"US",
    "sg:address":"561 Kilkenny Ct",
    "sg:city":"Gilberts",
    "sg:classifiers":[
        {
            "category":"Wholesale",
            "subcategory":"Machinery & Supplies",
            "type":"Manufacturing & Wholesale Goods"
        }
    ],
    "sg:phone":"+1 847 741 4000",
    "sg:postcode":"60136",
    "sg:province":"IL",
    "sg:tags":[
        "equipment",
        "printing"
    ],
    "wof:name":"A Folding Machine Svc Inc",
    "wof:placetype":"venue"
},
  "geometry": {"coordinates":[-88.357941,42.08692],"type":"Point"}
}