{
  "type": "Feature",
  "properties": {
    "iso:country":"US",
    "sg:address":"1900 Hollister Dr",
    "sg:city":"Libertyville",
    "sg:classifiers":[
        {
            "category":"Health Services",
            "subcategory":"Doctor",
            "type":"Services"
        }
    ],
    "sg:phone":"+1 847 367 1760",
    "sg:postcode":"60048",
    "sg:province":"IL",
    "sg:tags":[
        "physician",
        "surgeon"
    ],
    "wof:name":"Lanoff Daddono Cavanaugh",
    "wof:placetype":"venue"
},
  "geometry": {"coordinates":[-87.944322,42.249866],"type":"Point"}
}