{
  "type": "Feature",
  "properties": {
    "iso:country":"US",
    "sg:address":"905 Gregory Ln",
    "sg:city":"Schaumburg",
    "sg:classifiers":[
        {
            "category":"Professional",
            "type":"Services"
        }
    ],
    "sg:phone":"+1 847 524 0584",
    "sg:postcode":"60193",
    "sg:province":"IL",
    "wof:name":"McKeown Home Services",
    "wof:placetype":"venue"
},
  "geometry": {"coordinates":[-88.08807299999999,42.00928],"type":"Point"}
}