{
  "type": "Feature",
  "properties": {
    "addr:full":"1614 Taft Ave Wheaton IL 60187",
    "addr:housenumber":"1614",
    "addr:postcode":"60187",
    "addr:street":"Taft Ave",
    "iso:country":"US",
    "sg:address":"1614 Taft Ave",
    "sg:city":"Wheaton",
    "sg:classifiers":[
        {
            "category":"Professional",
            "subcategory":"Computer Services",
            "type":"Services"
        }
    ],
    "sg:phone":"+1 630 682 0212",
    "sg:postcode":"60187",
    "sg:province":"IL",
    "sg:tags":[
        "related"
    ],
    "wof:name":"Isv",
    "wof:placetype":"venue"
},
  "geometry": {"coordinates":[-88.082356,41.858171],"type":"Point"}
}