{
  "type": "Feature",
  "properties": {
    "iso:country":"US",
    "sg:address":"26076 N Geraldine Ln",
    "sg:city":"Barrington",
    "sg:classifiers":[
        {
            "category":"Retail",
            "subcategory":"Laundry & Dry Cleaning",
            "type":"Services"
        }
    ],
    "sg:phone":"+1 847 382 0628",
    "sg:postcode":"60010",
    "sg:province":"IL",
    "sg:tags":[
        "cleaners",
        "rug",
        "carpet"
    ],
    "wof:name":"Fox Valley Steamway Inc",
    "wof:placetype":"venue"
},
  "geometry": {"coordinates":[-88.197355,42.243373],"type":"Point"}
}