{
  "type": "Feature",
  "properties": {
    "iso:country":"US",
    "sg:address":"3525 Merriott Dr",
    "sg:city":"Rockford",
    "sg:classifiers":[
        {
            "category":"Building & Trades",
            "subcategory":"Construction",
            "type":"Services"
        }
    ],
    "sg:phone":"+1 815 964 9861",
    "sg:postcode":"61101",
    "sg:province":"IL",
    "sg:tags":[
        "house"
    ],
    "wof:name":"Carbone Construction Inc",
    "wof:placetype":"venue"
},
  "geometry": {"coordinates":[-89.10703599999999,42.312624],"type":"Point"}
}