{
  "type": "Feature",
  "properties": {
    "iso:country":"US",
    "sg:address":"703 Main St",
    "sg:city":"Evanston",
    "sg:classifiers":[
        {
            "category":"Shopping",
            "subcategory":"Jewelry",
            "type":"Retail Goods"
        },
        {
            "category":"Manufacturing",
            "subcategory":"Jewelry",
            "type":"Manufacturing & Wholesale Goods"
        },
        {
            "category":"Retail",
            "subcategory":"Repair Shop",
            "type":"Services"
        }
    ],
    "sg:phone":"+1 847 864 9660",
    "sg:postcode":"60202",
    "sg:province":"IL",
    "sg:tags":[
        "repairing",
        "watch",
        "jeweler"
    ],
    "sg:website":"http://www.viragjewelers.com",
    "wof:name":"Virag Jewelers Inc",
    "wof:placetype":"venue"
},
  "geometry": {"coordinates":[-87.680519,42.033951],"type":"Point"}
}