{
  "type": "Feature",
  "properties": {
    "iso:country":"US",
    "sg:address":"4614 N Harlem Ave",
    "sg:city":"Harwood Heights",
    "sg:classifiers":[
        {
            "category":"Shopping",
            "subcategory":"Pets & Pet Supplies",
            "type":"Retail Goods"
        }
    ],
    "sg:phone":"+1 708 867 7700",
    "sg:postcode":"60706",
    "sg:province":"IL",
    "sg:tags":[
        "store",
        "groomers"
    ],
    "sg:website":"www.petco.com",
    "wof:name":"Petco",
    "wof:placetype":"venue"
},
  "geometry": {"coordinates":[-87.8069,41.964401],"type":"Point"}
}