{
  "type": "Feature",
  "properties": {
    "addr:full":"4012 Maple Ave East Saint Louis IL 62201",
    "addr:housenumber":"4012",
    "addr:postcode":"62201",
    "addr:street":"Maple Ave East",
    "iso:country":"US",
    "sg:address":"4012 Maple Ave",
    "sg:city":"East Saint Louis",
    "sg:classifiers":[
        {
            "category":"Restaurant",
            "type":"Food & Drink"
        }
    ],
    "sg:phone":"+1 618 875 8806",
    "sg:postcode":"62201",
    "sg:province":"IL",
    "wof:name":"Baby Ruth's Restaurant",
    "wof:placetype":"venue"
},
  "geometry": {"coordinates":[-90.108299,38.6441],"type":"Point"}
}