{
  "type": "Feature",
  "properties": {
    "addr:full":"5430 W Chicago Ave Chicago IL 60651",
    "addr:housenumber":"5430",
    "addr:postcode":"60651",
    "addr:street":"W Chicago Ave",
    "iso:country":"US",
    "sg:address":"5430 W Chicago Ave",
    "sg:city":"Chicago",
    "sg:classifiers":[
        {
            "category":"Personal",
            "subcategory":"Nail Salon",
            "type":"Services"
        }
    ],
    "sg:phone":"+1 773 626 6245",
    "sg:postcode":"60651",
    "sg:province":"IL",
    "wof:name":"Queen Nails",
    "wof:placetype":"venue"
},
  "geometry": {"coordinates":[-87.76159699999999,41.895],"type":"Point"}
}