{
  "type": "Feature",
  "properties": {
    "iso:country":"US",
    "sg:address":"100 N Island Ave",
    "sg:city":"Batavia",
    "sg:classifiers":[
        {
            "category":"Arts & Performance",
            "subcategory":"Theater",
            "type":"Entertainment"
        }
    ],
    "sg:phone":"+1 630 406 8838",
    "sg:postcode":"60510",
    "sg:province":"IL",
    "wof:name":"Albright Theatre Co",
    "wof:placetype":"venue"
},
  "geometry": {"coordinates":[-88.309246,41.853629],"type":"Point"}
}