{
  "type": "Feature",
  "properties": {
    "addr:full":"465 N Desplaines Chicago IL 60654",
    "addr:housenumber":"465",
    "addr:postcode":"60654",
    "addr:street":"N Desplaines",
    "iso:country":"US",
    "sg:address":"465 N Desplaines",
    "sg:city":"Chicago",
    "sg:classifiers":[
        {
            "category":"Retail",
            "subcategory":"Storage",
            "type":"Services"
        }
    ],
    "sg:phone":"+1 312 386 7685",
    "sg:postcode":"60654",
    "sg:province":"IL",
    "sg:tags":[
        "self"
    ],
    "sg:website":"www.metrostorage.com/",
    "wof:name":"Metro Self Storage",
    "wof:placetype":"venue"
},
  "geometry": {"coordinates":[-87.644333,41.890436],"type":"Point"}
}