{
  "type": "Feature",
  "properties": {
    "iso:country":"US",
    "sg:address":"4647 N Lincoln Ave",
    "sg:city":"Chicago",
    "sg:classifiers":[
        {
            "category":"Restaurant",
            "type":"Food & Drink"
        },
        {
            "category":"Deli",
            "type":"Food & Drink"
        },
        {
            "category":"Food & Beverages",
            "subcategory":"Bakery",
            "type":"Retail Goods"
        },
        {
            "category":"Fast Food",
            "type":"Food & Drink"
        }
    ],
    "sg:phone":"+1 773 989 7788",
    "sg:postcode":"60625",
    "sg:province":"IL",
    "sg:tags":[
        "style",
        "sandwich",
        "delicatessen",
        "family",
        "take"
    ],
    "sg:website":"www.costellosandwich.com/",
    "wof:name":"Costello Sandwich & Sides",
    "wof:placetype":"venue"
},
  "geometry": {"coordinates":[-87.68710299999999,41.966099],"type":"Point"}
}