{
  "type": "Feature",
  "properties": {
    "addr:full":"1003 E McCord St Centralia IL 62801",
    "addr:housenumber":"1003",
    "addr:postcode":"62801",
    "addr:street":"E Mccord St",
    "iso:country":"US",
    "sg:address":"1003 E McCord St",
    "sg:city":"Centralia",
    "sg:classifiers":[
        {
            "category":"Health Services",
            "subcategory":"Doctor",
            "type":"Services"
        }
    ],
    "sg:phone":"+1 618 532 1858",
    "sg:postcode":"62801",
    "sg:province":"IL",
    "sg:tags":[
        "physician",
        "surgeon"
    ],
    "wof:name":"P B Shah Inc",
    "wof:placetype":"venue"
},
  "geometry": {"coordinates":[-89.11948700000001,38.527464],"type":"Point"}
}