{
  "type": "Feature",
  "properties": {
    "iso:country":"US",
    "sg:address":"11302 Lincoln St",
    "sg:city":"Huntley",
    "sg:classifiers":[
        {
            "category":"Education",
            "subcategory":"School",
            "type":"Public Place"
        }
    ],
    "sg:phone":"+1 847 659 6158",
    "sg:postcode":"60142",
    "sg:province":"IL",
    "wof:name":"Huntley Consolidated School District 158",
    "wof:placetype":"venue"
},
  "geometry": {"coordinates":[-88.43144599999999,42.165613],"type":"Point"}
}