{
  "type": "Feature",
  "properties": {
    "iso:country":"US",
    "sg:address":"137 N. Oak Park Ave Ste 115",
    "sg:city":"Oak Park",
    "sg:classifiers":[
        {
            "category":"Home & Garden",
            "subcategory":"Building Materials",
            "type":"Retail Goods"
        },
        {
            "category":"Home & Garden",
            "subcategory":"Furniture",
            "type":"Retail Goods"
        }
    ],
    "sg:phone":"+1 708 445 3606",
    "sg:postcode":"60301",
    "sg:province":"IL",
    "sg:tags":[
        "equipment",
        "lighting",
        "fixture",
        "store"
    ],
    "sg:website":"www.OPHH.com",
    "wof:name":"Oak Park Home & Hardware",
    "wof:placetype":"venue"
},
  "geometry": {"coordinates":[-87.794533,41.888423],"type":"Point"}
}