{
  "type": "Feature",
  "properties": {
    "iso:country":"US",
    "sg:address":"91 Hunt Trl",
    "sg:city":"Barrington",
    "sg:classifiers":[
        {
            "category":"Professional",
            "subcategory":"Business Services",
            "type":"Services"
        }
    ],
    "sg:phone":"+1 847 381 9092",
    "sg:postcode":"60010",
    "sg:province":"IL",
    "wof:name":"Greenfield Associates Partnr",
    "wof:placetype":"venue"
},
  "geometry": {"coordinates":[-88.141899,42.220309],"type":"Point"}
}