{
  "type": "Feature",
  "properties": {
    "addr:full":"909 W Montrose Avenue Chicago IL 60613",
    "addr:housenumber":"909",
    "addr:postcode":"60613",
    "addr:street":"W Montrose Avenue",
    "iso:country":"US",
    "sg:address":"909 W Montrose Avenue",
    "sg:city":"Chicago",
    "sg:classifiers":[
        {
            "category":"Personal",
            "subcategory":"Day Spa",
            "type":"Services"
        }
    ],
    "sg:phone":"+1 773 244 2373",
    "sg:postcode":"60613",
    "sg:province":"IL",
    "wof:name":"Le Petite Spa",
    "wof:placetype":"venue"
},
  "geometry": {"coordinates":[-87.65312,41.961681],"type":"Point"}
}