{
  "type": "Feature",
  "properties": {
    "iso:country":"US",
    "sg:address":"6030 Garrett Ln",
    "sg:city":"Rockford",
    "sg:classifiers":[
        {
            "category":"Health Services",
            "subcategory":"Doctor",
            "type":"Services"
        }
    ],
    "sg:phone":"+1 815 226 1172",
    "sg:postcode":"61107",
    "sg:province":"IL",
    "sg:tags":[
        "gynecology",
        "physician",
        "surgeons",
        "obstetrics"
    ],
    "sg:website":"http://www.obgynrockford.com",
    "wof:name":"OB-GYN Associates Ltd",
    "wof:placetype":"venue"
},
  "geometry": {"coordinates":[-88.998688,42.273602],"type":"Point"}
}