{
  "type": "Feature",
  "properties": {
    "addr:full":"4807 W Harrison St Chicago IL 60644",
    "addr:housenumber":"4807",
    "addr:postcode":"60644",
    "addr:street":"W Harrison St",
    "iso:country":"US",
    "sg:address":"4807 W Harrison St",
    "sg:city":"Chicago",
    "sg:classifiers":[
        {
            "category":"Personal",
            "subcategory":"Beauty Salon",
            "type":"Services"
        }
    ],
    "sg:phone":"+1 773 378 0890",
    "sg:postcode":"60644",
    "sg:province":"IL",
    "wof:name":"Dgeleka Hair Braiding",
    "wof:placetype":"venue"
},
  "geometry": {"coordinates":[-87.745509,41.873047],"type":"Point"}
}