{
  "type": "Feature",
  "properties": {
    "addr:full":"2444 Pro Tour Dr Belleville IL 62220",
    "addr:housenumber":"2444",
    "addr:postcode":"62220",
    "addr:street":"Pro Tour Dr",
    "iso:country":"US",
    "sg:address":"2444 Pro Tour Dr",
    "sg:city":"Belleville",
    "sg:classifiers":[
        {
            "category":"Professional",
            "subcategory":"Business Services",
            "type":"Services"
        }
    ],
    "sg:phone":"+1 618 235 0343",
    "sg:postcode":"62220",
    "sg:province":"IL",
    "wof:name":"Connectivity Associates LLC",
    "wof:placetype":"venue"
},
  "geometry": {"coordinates":[-89.913482,38.490047],"type":"Point"}
}