{
  "type": "Feature",
  "properties": {
    "iso:country":"US",
    "sg:address":"2801 W State St",
    "sg:city":"Rockford",
    "sg:classifiers":[
        {
            "category":"Autos & Motor Vehicles",
            "subcategory":"Fuel & Gas Station",
            "type":"Retail Goods"
        }
    ],
    "sg:phone":"+1 815 962 8087",
    "sg:postcode":"61102",
    "sg:province":"IL",
    "sg:tags":[
        "oil"
    ],
    "wof:name":"Lee's Automotive",
    "wof:placetype":"venue"
},
  "geometry": {"coordinates":[-89.130851,42.276911],"type":"Point"}
}