{
  "type": "Feature",
  "properties": {
    "iso:country":"US",
    "sg:address":"2770 N Osage Dr",
    "sg:city":"Bourbonnais",
    "sg:classifiers":[
        {
            "category":"Professional",
            "subcategory":"Engineering",
            "type":"Services"
        }
    ],
    "sg:phone":"+1 815 939 1001",
    "sg:postcode":"60914",
    "sg:province":"IL",
    "wof:name":"Cornerstone Engineering",
    "wof:placetype":"venue"
},
  "geometry": {"coordinates":[-87.909439,41.159381],"type":"Point"}
}