{
  "type": "Feature",
  "properties": {
    "addr:full":"9150-58 W Grand Ave Franklin Park IL 60131",
    "addr:housenumber":"9150-58",
    "addr:postcode":"60131",
    "addr:street":"W Grand Ave",
    "iso:country":"US",
    "sg:address":"9150-58 W Grand Ave",
    "sg:city":"Franklin Park",
    "sg:classifiers":[
        {
            "category":"Shopping",
            "subcategory":"Pets & Pet Supplies",
            "type":"Retail Goods"
        },
        {
            "category":"Retail",
            "subcategory":"Pet Boarding",
            "type":"Services"
        }
    ],
    "sg:phone":"+1 847 455 5959",
    "sg:postcode":"60131",
    "sg:province":"IL",
    "sg:tags":[
        "training",
        "boarding/pet",
        "sitting"
    ],
    "sg:website":"www.kaninehabitat.com",
    "wof:name":"Kanine Habitat & Spa",
    "wof:placetype":"venue"
},
  "geometry": {"coordinates":[-87.85526299999999,41.929401],"type":"Point"}
}