{
  "type": "Feature",
  "properties": {
    "addr:full":"6119 W Addison Street Chicago IL 60634",
    "addr:housenumber":"6119",
    "addr:postcode":"60634",
    "addr:street":"W Addison Street",
    "iso:country":"US",
    "sg:address":"6119 W Addison Street",
    "sg:city":"Chicago",
    "sg:classifiers":[
        {
            "category":"Building & Trades",
            "subcategory":"Construction",
            "type":"Services"
        }
    ],
    "sg:phone":"+1 773 777 7677",
    "sg:postcode":"60634",
    "sg:province":"IL",
    "sg:tags":[
        "contractor"
    ],
    "sg:website":"www.mikeconstruction.com",
    "wof:name":"Mike's Construction",
    "wof:placetype":"venue"
},
  "geometry": {"coordinates":[-87.779826,41.945527],"type":"Point"}
}