{
  "type": "Feature",
  "properties": {
    "addr:full":"5750 W Superior St Chicago IL 60644",
    "addr:housenumber":"5750",
    "addr:postcode":"60644",
    "addr:street":"W Superior St",
    "iso:country":"US",
    "sg:address":"5750 W Superior St",
    "sg:city":"Chicago",
    "sg:classifiers":[
        {
            "category":"Retail",
            "subcategory":"Auto Rental",
            "type":"Services"
        }
    ],
    "sg:phone":"+1 773 287 5518",
    "sg:postcode":"60644",
    "sg:province":"IL",
    "sg:tags":[
        "car"
    ],
    "wof:name":"Defax",
    "wof:placetype":"venue"
},
  "geometry": {"coordinates":[-87.76916300000001,41.893938],"type":"Point"}
}