{
  "type": "Feature",
  "properties": {
    "addr:full":"764 W Northwest Hwy Barrington IL 60010",
    "addr:housenumber":"764",
    "addr:postcode":"60010",
    "addr:street":"W Northwest Hwy",
    "iso:country":"US",
    "sg:address":"764 W Northwest Hwy",
    "sg:city":"Barrington",
    "sg:classifiers":[
        {
            "category":"Personal",
            "subcategory":"Beauty Salon",
            "type":"Services"
        }
    ],
    "sg:phone":"+1 847 381 3552",
    "sg:postcode":"60010",
    "sg:province":"IL",
    "wof:name":"Ella's Room At Lauberge",
    "wof:placetype":"venue"
},
  "geometry": {"coordinates":[-88.157729,42.166678],"type":"Point"}
}