{
  "type": "Feature",
  "properties": {
    "addr:full":"501 E 47th St Chicago IL 60653",
    "addr:housenumber":"501",
    "addr:postcode":"60653",
    "addr:street":"E 47Th St",
    "iso:country":"US",
    "sg:address":"501 E 47th St",
    "sg:city":"Chicago",
    "sg:classifiers":[
        {
            "category":"Personal",
            "subcategory":"Beauty Salon",
            "type":"Services"
        }
    ],
    "sg:phone":"+1 773 285 7401",
    "sg:postcode":"60653",
    "sg:province":"IL",
    "wof:name":"Glamourama Curl Salon",
    "wof:placetype":"venue"
},
  "geometry": {"coordinates":[-87.61266999999999,41.809442],"type":"Point"}
}