{
  "type": "Feature",
  "properties": {
    "iso:country":"US",
    "sg:address":"7006 Catalpa Ct",
    "sg:city":"Spring Grove",
    "sg:classifiers":[
        {
            "category":"Banks & Credit Unions",
            "subcategory":"Bank",
            "type":"Services"
        }
    ],
    "sg:phone":"+1 815 675 6631",
    "sg:postcode":"60081",
    "sg:province":"IL",
    "sg:tags":[
        "federal",
        "agency"
    ],
    "wof:name":"Phenix International",
    "wof:placetype":"venue"
},
  "geometry": {"coordinates":[-88.224193,42.428381],"type":"Point"}
}