{
  "type": "Feature",
  "properties": {
    "iso:country":"US",
    "sg:address":"5500 Touhy Ave",
    "sg:city":"Skokie",
    "sg:classifiers":[
        {
            "category":"Building & Trades",
            "subcategory":"Plumbing",
            "type":"Services"
        }
    ],
    "sg:phone":"+1 847 679 0212",
    "sg:postcode":"60077",
    "sg:province":"IL",
    "sg:tags":[
        "heating",
        "contractor"
    ],
    "wof:name":"Assurance Heating & Air Cond",
    "wof:placetype":"venue"
},
  "geometry": {"coordinates":[-87.767342,42.011938],"type":"Point"}
}