{
  "type": "Feature",
  "properties": {
    "addr:full":"200 S Maple Ave Wauconda IL 60084",
    "addr:housenumber":"200",
    "addr:postcode":"60084",
    "addr:street":"S Maple Ave",
    "iso:country":"US",
    "sg:address":"200 S Maple Ave",
    "sg:city":"Wauconda",
    "sg:classifiers":[
        {
            "category":"Organizations",
            "subcategory":"Community Association",
            "type":"Services"
        }
    ],
    "sg:phone":"+1 847 526 8118",
    "sg:postcode":"60084",
    "sg:province":"IL",
    "wof:name":"Lodge 1969 - Wauconda",
    "wof:placetype":"venue"
},
  "geometry": {"coordinates":[-88.140209,42.258085],"type":"Point"}
}