{
  "type": "Feature",
  "properties": {
    "iso:country":"US",
    "sg:address":"55 E Washington St Ste 222",
    "sg:city":"Chicago",
    "sg:classifiers":[
        {
            "category":"Shopping",
            "subcategory":"Jewelry",
            "type":"Retail Goods"
        },
        {
            "category":"Manufacturing",
            "subcategory":"Jewelry",
            "type":"Manufacturing & Wholesale Goods"
        }
    ],
    "sg:phone":"+1 312 857 1990",
    "sg:postcode":"60602",
    "sg:province":"IL",
    "sg:tags":[
        "stone",
        "designer",
        "semi-precious",
        "precious",
        "jeweler"
    ],
    "wof:name":"Yungs Brother Jeweler",
    "wof:placetype":"venue"
},
  "geometry": {"coordinates":[-87.625801,41.883202],"type":"Point"}
}