{
  "type": "Feature",
  "properties": {
    "iso:country":"US",
    "sg:address":"1976 Round Barn Rd",
    "sg:city":"Champaign",
    "sg:classifiers":[
        {
            "category":"Shopping",
            "subcategory":"Gifts & Souvenirs",
            "type":"Retail Goods"
        }
    ],
    "sg:phone":"+1 217 356 7668",
    "sg:postcode":"61821",
    "sg:province":"IL",
    "sg:tags":[
        "shop"
    ],
    "wof:name":"E & E Oriental Gift Shop",
    "wof:placetype":"venue"
},
  "geometry": {"coordinates":[-88.282236,40.111194],"type":"Point"}
}