{
  "type": "Feature",
  "properties": {
    "addr:full":"1750 Techny Ct Northbrook IL 60062",
    "addr:housenumber":"1750",
    "addr:postcode":"60062",
    "addr:street":"Techny Ct",
    "iso:country":"US",
    "sg:address":"1750 Techny Ct",
    "sg:city":"Northbrook",
    "sg:classifiers":[
        {
            "category":"Sports & Exercise",
            "subcategory":"Golf",
            "type":"Entertainment"
        }
    ],
    "sg:phone":"+1 847 291 2971",
    "sg:postcode":"60062",
    "sg:province":"IL",
    "sg:tags":[
        "course",
        "instruction"
    ],
    "sg:website":"http://www.sportsmansgolf.com",
    "wof:name":"Anetsberger Golf Course",
    "wof:placetype":"venue"
},
  "geometry": {"coordinates":[-87.819971,42.116428],"type":"Point"}
}