{
  "type": "Feature",
  "properties": {
    "iso:country":"US",
    "sg:address":"333 Commerce Dr",
    "sg:city":"Crystal Lake",
    "sg:classifiers":[
        {
            "category":"Professional",
            "subcategory":"Computer Services",
            "type":"Services"
        }
    ],
    "sg:phone":"+1 815 477 0011",
    "sg:postcode":"60014",
    "sg:province":"IL",
    "sg:tags":[
        "information",
        "maintenance",
        "contract",
        "renewal"
    ],
    "wof:name":"Trident Contract MGT LLC",
    "wof:placetype":"venue"
},
  "geometry": {"coordinates":[-88.329459,42.249797],"type":"Point"}
}