{
  "type": "Feature",
  "properties": {
    "addr:full":"6100 S Keeler Ave Chicago IL 60629",
    "addr:housenumber":"6100",
    "addr:postcode":"60629",
    "addr:street":"S Keeler Ave",
    "iso:country":"US",
    "sg:address":"6100 S Keeler Ave",
    "sg:city":"Chicago",
    "sg:classifiers":[
        {
            "category":"Building & Trades",
            "subcategory":"Construction",
            "type":"Services"
        }
    ],
    "sg:phone":"+1 773 732 8210",
    "sg:postcode":"60629",
    "sg:province":"IL",
    "sg:tags":[
        "siding",
        "contractor"
    ],
    "wof:name":"J And D Siding",
    "wof:placetype":"venue"
},
  "geometry": {"coordinates":[-87.727737,41.78223],"type":"Point"}
}