{
  "type": "Feature",
  "properties": {
    "iso:country":"US",
    "sg:address":"640 Church Rd",
    "sg:city":"Elgin",
    "sg:classifiers":[
        {
            "category":"Manufacturing",
            "subcategory":"Tools & Machinery",
            "type":"Manufacturing & Wholesale Goods"
        }
    ],
    "sg:phone":"+1 847 741 3600",
    "sg:postcode":"60123",
    "sg:province":"IL",
    "wof:name":"Iden Co",
    "wof:placetype":"venue"
},
  "geometry": {"coordinates":[-88.293809,42.073429],"type":"Point"}
}