{
  "type": "Feature",
  "properties": {
    "iso:country":"US",
    "sg:address":"2115 W Arthur Ave",
    "sg:city":"Chicago",
    "sg:classifiers":[
        {
            "category":"Retail",
            "subcategory":"Repair Shop",
            "type":"Services"
        }
    ],
    "sg:phone":"+1 773 338 8077",
    "sg:postcode":"60645",
    "sg:province":"IL",
    "wof:name":"Star Belen Upholstery",
    "wof:placetype":"venue"
},
  "geometry": {"coordinates":[-87.683386,41.999578],"type":"Point"}
}