{
  "type": "Feature",
  "properties": {
    "addr:full":"200 N Gilbert St Danville IL 61832",
    "addr:housenumber":"200",
    "addr:postcode":"61832",
    "addr:street":"N Gilbert St",
    "iso:country":"US",
    "sg:address":"200 N Gilbert St",
    "sg:city":"Danville",
    "sg:classifiers":[
        {
            "category":"Professional",
            "subcategory":"Lawyer & Legal Services",
            "type":"Services"
        }
    ],
    "sg:phone":"+1 217 431 2503",
    "sg:postcode":"61832",
    "sg:province":"IL",
    "sg:tags":[
        "attorney"
    ],
    "wof:name":"Gary J Stokes Law Office",
    "wof:placetype":"venue"
},
  "geometry": {"coordinates":[-87.63542,40.128935],"type":"Point"}
}