{
  "type": "Feature",
  "properties": {
    "addr:full":"500 N Michigan Avenue Chicago IL 60611",
    "addr:housenumber":"500",
    "addr:postcode":"60611",
    "addr:street":"N Michigan Avenue",
    "iso:country":"US",
    "sg:address":"500 N Michigan Avenue",
    "sg:city":"Chicago",
    "sg:classifiers":[
        {
            "category":"Personal",
            "type":"Services"
        }
    ],
    "sg:phone":"+1 312 939 6490",
    "sg:postcode":"60611",
    "sg:province":"IL",
    "sg:tags":[
        "party",
        "planning",
        "event"
    ],
    "wof:name":"Maid To Order Party Staffing",
    "wof:placetype":"venue"
},
  "geometry": {"coordinates":[-87.62063000000001,41.894988],"type":"Point"}
}