{
  "type": "Feature",
  "properties": {
    "addr:full":"7404 W North Ave Elmwood Park IL 60707",
    "addr:housenumber":"7404",
    "addr:postcode":"60707",
    "addr:street":"W North Ave",
    "iso:country":"US",
    "sg:address":"7404 W North Ave",
    "sg:city":"Elmwood Park",
    "sg:classifiers":[
        {
            "category":"Shopping",
            "subcategory":"Mobile Phones",
            "type":"Retail Goods"
        }
    ],
    "sg:phone":"+1 708 452 2400",
    "sg:postcode":"60707",
    "sg:province":"IL",
    "sg:website":"www.sprint.com",
    "wof:name":"Sprint",
    "wof:placetype":"venue"
},
  "geometry": {"coordinates":[-87.810799,41.908798],"type":"Point"}
}