{
  "type": "Feature",
  "properties": {
    "addr:full":"3756 W Montrose Ave Chicago IL 60618",
    "addr:housenumber":"3756",
    "addr:postcode":"60618",
    "addr:street":"W Montrose Ave",
    "iso:country":"US",
    "sg:address":"3756 W Montrose Ave",
    "sg:city":"Chicago",
    "sg:classifiers":[
        {
            "category":"Food & Beverages",
            "subcategory":"Groceries & Convenience Stores",
            "type":"Retail Goods"
        }
    ],
    "sg:phone":"+1 773 588 3677",
    "sg:postcode":"60618",
    "sg:province":"IL",
    "wof:name":"Two Brothers Mart",
    "wof:placetype":"venue"
},
  "geometry": {"coordinates":[-87.72199999999999,41.960999],"type":"Point"}
}