{
  "type": "Feature",
  "properties": {
    "addr:full":"10603 Bencie Ln West Frankfort IL 62896",
    "addr:housenumber":"10603",
    "addr:postcode":"62896",
    "addr:street":"Bencie Ln West",
    "iso:country":"US",
    "sg:address":"10603 Bencie Ln",
    "sg:city":"West Frankfort",
    "sg:classifiers":[
        {
            "category":"Building & Trades",
            "subcategory":"Equipment Rental",
            "type":"Services"
        }
    ],
    "sg:phone":"+1 618 937 2271",
    "sg:postcode":"62896",
    "sg:province":"IL",
    "sg:tags":[
        "leasing"
    ],
    "wof:name":"AAA Cylinder Leasing & Refur",
    "wof:placetype":"venue"
},
  "geometry": {"coordinates":[-88.960812,37.890756],"type":"Point"}
}