{
  "type": "Feature",
  "properties": {
    "addr:full":"716 N Cicero Ave Chicago IL 60644",
    "addr:housenumber":"716",
    "addr:postcode":"60644",
    "addr:street":"N Cicero Ave",
    "iso:country":"US",
    "sg:address":"716 N Cicero Ave",
    "sg:city":"Chicago",
    "sg:classifiers":[
        {
            "category":"Organizations",
            "subcategory":"Religious Organization",
            "type":"Services"
        }
    ],
    "sg:phone":"+1 773 379 1728",
    "sg:postcode":"60644",
    "sg:province":"IL",
    "wof:name":"Gods Way Mssnary Bptst Church",
    "wof:placetype":"venue"
},
  "geometry": {"coordinates":[-87.74584400000001,41.893849],"type":"Point"}
}