{
  "type": "Feature",
  "properties": {
    "iso:country":"US",
    "sg:address":"221 E Locust St",
    "sg:city":"Sumner",
    "sg:classifiers":[
        {
            "category":"Building & Trades",
            "subcategory":"Plumbing",
            "type":"Services"
        }
    ],
    "sg:phone":"+1 618 936 9040",
    "sg:postcode":"62466",
    "sg:province":"IL",
    "sg:tags":[
        "septic"
    ],
    "wof:name":"Jerry's Septic Tank Svc",
    "wof:placetype":"venue"
},
  "geometry": {"coordinates":[-87.858671,38.714294],"type":"Point"}
}