{
  "type": "Feature",
  "properties": {
    "iso:country":"US",
    "sg:address":"77 W Washington St",
    "sg:city":"Chicago",
    "sg:classifiers":[
        {
            "category":"Professional",
            "subcategory":"Lawyer & Legal Services",
            "type":"Services"
        }
    ],
    "sg:phone":"+1 312 429 7328",
    "sg:postcode":"60602",
    "sg:province":"IL",
    "sg:tags":[
        "property",
        "attorney",
        "accident",
        "damage"
    ],
    "sg:website":"http://www.BestChicagoLawyer.com",
    "wof:name":"Kenneth Fleischer Accident and Personal Injury Attorney",
    "wof:placetype":"venue"
},
  "geometry": {"coordinates":[-87.630234,41.883228],"type":"Point"}
}