{
  "type": "Feature",
  "properties": {
    "addr:full":"401 N Randall Rd Batavia IL 60510",
    "addr:housenumber":"401",
    "addr:postcode":"60510",
    "addr:street":"N Randall Rd",
    "iso:country":"US",
    "sg:address":"401 N Randall Rd",
    "sg:city":"Batavia",
    "sg:classifiers":[
        {
            "category":"Shopping",
            "type":"Retail Goods"
        }
    ],
    "sg:phone":"+1 630 761 1047",
    "sg:postcode":"60510",
    "sg:province":"IL",
    "sg:tags":[
        "pet",
        "shop"
    ],
    "sg:website":"www.petland.com",
    "wof:name":"Petland",
    "wof:placetype":"venue"
},
  "geometry": {"coordinates":[-88.340542,41.857393],"type":"Point"}
}