{
  "type": "Feature",
  "properties": {
    "iso:country":"US",
    "sg:address":"201 E McMackin St",
    "sg:city":"Salem",
    "sg:classifiers":[
        {
            "category":"Organizations",
            "subcategory":"Religious Organization",
            "type":"Services"
        }
    ],
    "sg:phone":"+1 618 548 2754",
    "sg:postcode":"62881",
    "sg:province":"IL",
    "sg:tags":[
        "church"
    ],
    "wof:name":"Salem Presbyterian Church",
    "wof:placetype":"venue"
},
  "geometry": {"coordinates":[-88.94461,38.626251],"type":"Point"}
}