{
  "type": "Feature",
  "properties": {
    "addr:full":"1596 N Kingsbury St Chicago IL 60642",
    "addr:housenumber":"1596",
    "addr:postcode":"60642",
    "addr:street":"N Kingsbury St",
    "iso:country":"US",
    "sg:address":"1596 N Kingsbury St",
    "sg:city":"Chicago",
    "sg:classifiers":[
        {
            "category":"Shopping",
            "subcategory":"Clothing, Apparel, & Fashions",
            "type":"Retail Goods"
        },
        {
            "category":"Shopping",
            "subcategory":"Baby Store",
            "type":"Retail Goods"
        }
    ],
    "sg:phone":"+1 312 397 0485",
    "sg:postcode":"60642",
    "sg:province":"IL",
    "sg:tags":[
        "infant",
        "men's",
        "women's",
        "children's",
        "maternity",
        "wear",
        "apparel",
        "girls'",
        "clothing",
        "boys'",
        "clothes"
    ],
    "sg:website":"http://www.oldnavy.com",
    "wof:name":"Old Navy",
    "wof:placetype":"venue"
},
  "geometry": {"coordinates":[-87.654004,41.910759],"type":"Point"}
}