{
  "type": "Feature",
  "properties": {
    "iso:country":"US",
    "sg:address":"1800 Goshen Trail Rd",
    "sg:city":"Eldorado",
    "sg:classifiers":[
        {
            "category":"Social Services",
            "subcategory":"Child Care",
            "type":"Services"
        }
    ],
    "sg:phone":"+1 618 273 2200",
    "sg:postcode":"62930",
    "sg:province":"IL",
    "wof:name":"Gina's Babysitting",
    "wof:placetype":"venue"
},
  "geometry": {"coordinates":[-88.447835,37.843211],"type":"Point"}
}