{
  "type": "Feature",
  "properties": {
    "addr:full":"4817 W Main St Belleville IL 62226",
    "addr:housenumber":"4817",
    "addr:postcode":"62226",
    "addr:street":"W Main St",
    "iso:country":"US",
    "sg:address":"4817 W Main St",
    "sg:city":"Belleville",
    "sg:classifiers":[
        {
            "category":"Restaurant",
            "type":"Food & Drink"
        }
    ],
    "sg:menulink":"http://www.allmenus.com/il/belleville/79864-pizza-hut/menu/",
    "sg:phone":"+1 618 233 8504",
    "sg:postcode":"62226",
    "sg:province":"IL",
    "sg:tags":[
        "american",
        "pizza"
    ],
    "wof:name":"Pizza Hut",
    "wof:placetype":"venue"
},
  "geometry": {"coordinates":[-90.02708699999999,38.543482],"type":"Point"}
}