{
  "type": "Feature",
  "properties": {
    "addr:full":"1912 Lowell Park Rd Dixon IL 61021",
    "addr:housenumber":"1912",
    "addr:postcode":"61021",
    "addr:street":"Lowell Park Rd",
    "iso:country":"US",
    "sg:address":"1912 Lowell Park Rd",
    "sg:city":"Dixon",
    "sg:classifiers":[
        {
            "category":"Ice Cream",
            "type":"Food & Drink"
        }
    ],
    "sg:menulink":"http://www.allmenus.com/il/dixon/161861-dairy-queen/menu/",
    "sg:phone":"+1 815 288 6115",
    "sg:postcode":"61021",
    "sg:province":"IL",
    "sg:tags":[
        "burger",
        "american"
    ],
    "wof:name":"Dairy Queen",
    "wof:placetype":"venue"
},
  "geometry": {"coordinates":[-89.496334,41.863041],"type":"Point"}
}