{
  "type": "Feature",
  "properties": {
    "iso:country":"US",
    "sg:address":"915 S Center St",
    "sg:city":"Geneseo",
    "sg:classifiers":[
        {
            "category":"Organizations",
            "subcategory":"Religious Organization",
            "type":"Services"
        }
    ],
    "sg:phone":"+1 309 944 2772",
    "sg:postcode":"61254",
    "sg:province":"IL",
    "wof:name":"LDDS Missionaries",
    "wof:placetype":"venue"
},
  "geometry": {"coordinates":[-90.157672,41.441623],"type":"Point"}
}