{
  "type": "Feature",
  "properties": {
    "iso:country":"US",
    "sg:address":"6125 W 26th St",
    "sg:city":"Cicero",
    "sg:classifiers":[
        {
            "category":"Shopping",
            "subcategory":"Computers & Home Electronics",
            "type":"Retail Goods"
        }
    ],
    "sg:phone":"+1 708 853 0501",
    "sg:postcode":"60804",
    "sg:province":"IL",
    "wof:name":"Direct Sat Tv",
    "wof:placetype":"venue"
},
  "geometry": {"coordinates":[-87.776798,41.843359],"type":"Point"}
}