{
  "type": "Feature",
  "properties": {
    "iso:country":"US",
    "sg:address":"5511 S Sawyer Ave",
    "sg:city":"Chicago",
    "sg:classifiers":[
        {
            "category":"Organizations",
            "subcategory":"Religious Organization",
            "type":"Services"
        }
    ],
    "sg:phone":"+1 773 737 3113",
    "sg:postcode":"60629",
    "sg:province":"IL",
    "wof:name":"St Gall Church",
    "wof:placetype":"venue"
},
  "geometry": {"coordinates":[-87.70459700000001,41.793201],"type":"Point"}
}