{
  "type": "Feature",
  "properties": {
    "addr:full":"980 N Northwest Hwy Park Ridge IL 60068",
    "addr:housenumber":"980",
    "addr:postcode":"60068",
    "addr:street":"N Northwest Hwy",
    "iso:country":"US",
    "sg:address":"980 N Northwest Hwy",
    "sg:city":"Park Ridge",
    "sg:classifiers":[
        {
            "category":"Retail",
            "subcategory":"Laundry & Dry Cleaning",
            "type":"Services"
        }
    ],
    "sg:phone":"+1 847 825 0231",
    "sg:postcode":"60068",
    "sg:province":"IL",
    "sg:tags":[
        "drycleaning",
        "plant"
    ],
    "wof:name":"JP Cleaners",
    "wof:placetype":"venue"
},
  "geometry": {"coordinates":[-87.85154,42.024994],"type":"Point"}
}