{
  "type": "Feature",
  "properties": {
    "iso:country":"US",
    "sg:address":"5221 W Belmont Ave",
    "sg:city":"Chicago",
    "sg:classifiers":[
        {
            "category":"Arts & Performance",
            "subcategory":"Music",
            "type":"Entertainment"
        },
        {
            "category":"Manufacturing",
            "subcategory":"Musical Instruments",
            "type":"Manufacturing & Wholesale Goods"
        }
    ],
    "sg:phone":"+1 773 205 6167",
    "sg:postcode":"60641",
    "sg:province":"IL",
    "sg:tags":[
        "instruments-supplies",
        "sheet",
        "accessory"
    ],
    "wof:name":"Goldmart Co",
    "wof:placetype":"venue"
},
  "geometry": {"coordinates":[-87.757214,41.938704],"type":"Point"}
}