{
  "type": "Feature",
  "properties": {
    "iso:country":"US",
    "sg:address":"3452 N Southport Ave",
    "sg:city":"Chicago",
    "sg:classifiers":[
        {
            "category":"Building & Trades",
            "subcategory":"Electrical",
            "type":"Services"
        }
    ],
    "sg:phone":"+1 773 296 4400",
    "sg:postcode":"60657",
    "sg:province":"IL",
    "sg:tags":[
        "electric",
        "contractor"
    ],
    "wof:name":"CED Inc",
    "wof:placetype":"venue"
},
  "geometry": {"coordinates":[-87.664007,41.943911],"type":"Point"}
}