{
  "type": "Feature",
  "properties": {
    "addr:full":"255 Cortland Ave Lombard IL 60148",
    "addr:housenumber":"255",
    "addr:postcode":"60148",
    "addr:street":"Cortland Ave",
    "iso:country":"US",
    "sg:address":"255 Cortland Ave",
    "sg:city":"Lombard",
    "sg:classifiers":[
        {
            "category":"Manufacturing",
            "subcategory":"Textiles",
            "type":"Manufacturing & Wholesale Goods"
        }
    ],
    "sg:phone":"+1 630 424 8000",
    "sg:postcode":"60148",
    "sg:province":"IL",
    "wof:name":"R & R Textile",
    "wof:placetype":"venue"
},
  "geometry": {"coordinates":[-88.022975,41.911026],"type":"Point"}
}