{
  "type": "Feature",
  "properties": {
    "addr:full":"2508 N Frolic Ave Waukegan IL 60087",
    "addr:housenumber":"2508",
    "addr:postcode":"60087",
    "addr:street":"N Frolic Ave",
    "iso:country":"US",
    "sg:address":"2508 N Frolic Ave",
    "sg:city":"Waukegan",
    "sg:classifiers":[
        {
            "category":"Health Services",
            "subcategory":"Doctor",
            "type":"Services"
        }
    ],
    "sg:phone":"+1 847 623 1107",
    "sg:postcode":"60087",
    "sg:province":"IL",
    "sg:tags":[
        "dentist"
    ],
    "wof:name":"David G Anderson DDS",
    "wof:placetype":"venue"
},
  "geometry": {"coordinates":[-87.87210399999999,42.405321],"type":"Point"}
}