{
  "type": "Feature",
  "properties": {
    "iso:country":"US",
    "sg:address":"3512 W 159th St",
    "sg:city":"Markham",
    "sg:classifiers":[
        {
            "category":"Social Services",
            "subcategory":"Child Care",
            "type":"Services"
        }
    ],
    "sg:phone":"+1 708 225 1443",
    "sg:postcode":"60428",
    "sg:province":"IL",
    "sg:tags":[
        "day"
    ],
    "wof:name":"Academy of Early Learning the",
    "wof:placetype":"venue"
},
  "geometry": {"coordinates":[-87.702376,41.600757],"type":"Point"}
}