{
  "type": "Feature",
  "properties": {
    "iso:country":"US",
    "sg:address":"1000 E Harris Ave Ste 4",
    "sg:city":"Greenville",
    "sg:classifiers":[
        {
            "category":"Insurance",
            "subcategory":"Hazard Insurance",
            "type":"Services"
        }
    ],
    "sg:phone":"+1 618 664 3465",
    "sg:postcode":"62246",
    "sg:province":"IL",
    "sg:tags":[
        "commercial",
        "business"
    ],
    "wof:name":"Egisure Insurance",
    "wof:placetype":"venue"
},
  "geometry": {"coordinates":[-89.400356,38.887219],"type":"Point"}
}