{
  "type": "Feature",
  "properties": {
    "iso:country":"US",
    "sg:address":"132 S Northwest Hwy",
    "sg:city":"Barrington",
    "sg:classifiers":[
        {
            "category":"Personal",
            "subcategory":"Beauty Salon",
            "type":"Services"
        }
    ],
    "sg:phone":"+1 847 894 7977",
    "sg:postcode":"60010",
    "sg:province":"IL",
    "wof:name":"Salon 151",
    "wof:placetype":"venue"
},
  "geometry": {"coordinates":[-88.128311,42.153244],"type":"Point"}
}