{
  "type": "Feature",
  "properties": {
    "addr:full":"8607 W 95th St Hickory Hills IL 60457",
    "addr:housenumber":"8607",
    "addr:postcode":"60457",
    "addr:street":"W 95Th St",
    "iso:country":"US",
    "sg:address":"8607 W 95th St",
    "sg:city":"Hickory Hills",
    "sg:classifiers":[
        {
            "category":"Education",
            "subcategory":"Music School",
            "type":"Public Place"
        }
    ],
    "sg:phone":"+1 708 599 9050",
    "sg:postcode":"60457",
    "sg:province":"IL",
    "sg:tags":[
        "instrument",
        "teacher",
        "musical"
    ],
    "wof:name":"Guido's Conservatory of Music",
    "wof:placetype":"venue"
},
  "geometry": {"coordinates":[-87.831596,41.7183],"type":"Point"}
}