{
  "type": "Feature",
  "properties": {
    "addr:full":"6143 E State St Rockford IL 61108",
    "addr:housenumber":"6143",
    "addr:postcode":"61108",
    "addr:street":"E State St",
    "iso:country":"US",
    "sg:address":"6143 E State St",
    "sg:city":"Rockford",
    "sg:classifiers":[
        {
            "category":"Shopping",
            "subcategory":"Gifts & Souvenirs",
            "type":"Retail Goods"
        }
    ],
    "sg:phone":"+1 815 226 9111",
    "sg:postcode":"61108",
    "sg:province":"IL",
    "sg:tags":[
        "cards",
        "party",
        "supply"
    ],
    "wof:name":"Factory Card Outlet 118",
    "wof:placetype":"venue"
},
  "geometry": {"coordinates":[-88.99824,42.266893],"type":"Point"}
}