{
  "type": "Feature",
  "properties": {
    "addr:full":"3270 N Clark St Chicago IL 60657",
    "addr:housenumber":"3270",
    "addr:postcode":"60657",
    "addr:street":"N Clark St",
    "iso:country":"US",
    "sg:address":"3270 N Clark St",
    "sg:city":"Chicago",
    "sg:classifiers":[
        {
            "category":"Manufacturing",
            "subcategory":"Musical Instruments",
            "type":"Manufacturing & Wholesale Goods"
        },
        {
            "category":"Shopping",
            "subcategory":"Musical Instruments",
            "type":"Retail Goods"
        }
    ],
    "sg:phone":"+1 773 477 0830",
    "sg:postcode":"60657",
    "sg:province":"IL",
    "sg:website":"www.chicagomusicexchange.com",
    "wof:name":"Chicago Music Exchange Inc",
    "wof:placetype":"venue"
},
  "geometry": {"coordinates":[-87.65134,41.940439],"type":"Point"}
}