{
  "type": "Feature",
  "properties": {
    "iso:country":"US",
    "sg:address":"14934 Freeport Rd",
    "sg:city":"Durand",
    "sg:classifiers":[
        {
            "category":"Wholesale",
            "subcategory":"Machinery & Supplies",
            "type":"Manufacturing & Wholesale Goods"
        }
    ],
    "sg:phone":"+1 815 248 2161",
    "sg:postcode":"61024",
    "sg:province":"IL",
    "sg:tags":[
        "farm",
        "equipment"
    ],
    "wof:name":"A C Mc Cartney Farm Equipment",
    "wof:placetype":"venue"
},
  "geometry": {"coordinates":[-89.329852,42.418876],"type":"Point"}
}