{
  "type": "Feature",
  "properties": {
    "addr:full":"3112 W Lawrence Ave Chicago IL 60625",
    "addr:housenumber":"3112",
    "addr:postcode":"60625",
    "addr:street":"W Lawrence Ave",
    "iso:country":"US",
    "sg:address":"3112 W Lawrence Ave",
    "sg:city":"Chicago",
    "sg:classifiers":[
        {
            "category":"Bars & Pubs",
            "subcategory":"Sports Bar",
            "type":"Food & Drink"
        }
    ],
    "sg:phone":"+1 773 267 8166",
    "sg:postcode":"60625",
    "sg:province":"IL",
    "sg:tags":[
        "hall",
        "pool"
    ],
    "wof:name":"Uno Billiard",
    "wof:placetype":"venue"
},
  "geometry": {"coordinates":[-87.706902,41.968601],"type":"Point"}
}