{
  "type": "Feature",
  "properties": {
    "addr:full":"11522 W Barr Rd Peotone IL 60468",
    "addr:housenumber":"11522",
    "addr:postcode":"60468",
    "addr:street":"W Barr Rd",
    "iso:country":"US",
    "sg:address":"11522 W Barr Rd",
    "sg:city":"Peotone",
    "sg:classifiers":[
        {
            "category":"Professional",
            "subcategory":"Management & Consulting",
            "type":"Services"
        }
    ],
    "sg:phone":"+1 708 258 3181",
    "sg:postcode":"60468",
    "sg:province":"IL",
    "sg:tags":[
        "instrumentation",
        "indicating"
    ],
    "wof:name":"Technical Support Assoc",
    "wof:placetype":"venue"
},
  "geometry": {"coordinates":[-87.886978,41.33823],"type":"Point"}
}