{
  "type": "Feature",
  "properties": {
    "addr:full":"123 N Main St Galena IL 61036",
    "addr:housenumber":"123",
    "addr:postcode":"61036",
    "addr:street":"N Main St",
    "iso:country":"US",
    "sg:address":"123 N Main St",
    "sg:city":"Galena",
    "sg:classifiers":[
        {
            "category":"Organizations",
            "subcategory":"Community Association",
            "type":"Services"
        }
    ],
    "sg:phone":"+1 815 777 0011",
    "sg:postcode":"61036",
    "sg:province":"IL",
    "sg:tags":[
        "fraternal"
    ],
    "wof:name":"BPOE Club",
    "wof:placetype":"venue"
},
  "geometry": {"coordinates":[-90.427657,42.4166],"type":"Point"}
}