{
  "type": "Feature",
  "properties": {
    "addr:full":"4910 W Armitage Ave Chicago IL 60639",
    "addr:housenumber":"4910",
    "addr:postcode":"60639",
    "addr:street":"W Armitage Ave",
    "iso:country":"US",
    "sg:address":"4910 W Armitage Ave",
    "sg:city":"Chicago",
    "sg:classifiers":[
        {
            "category":"Food & Beverages",
            "subcategory":"Groceries & Convenience Stores",
            "type":"Retail Goods"
        }
    ],
    "sg:phone":"+1 773 622 5962",
    "sg:postcode":"60639",
    "sg:province":"IL",
    "wof:name":"Armitage Market",
    "wof:placetype":"venue"
},
  "geometry": {"coordinates":[-87.75,41.916901],"type":"Point"}
}