{
  "type": "Feature",
  "properties": {
    "addr:full":"6901 S Bell Ave Chicago IL 60636",
    "addr:housenumber":"6901",
    "addr:postcode":"60636",
    "addr:street":"S Bell Ave",
    "iso:country":"US",
    "sg:address":"6901 S Bell Ave",
    "sg:city":"Chicago",
    "sg:classifiers":[
        {
            "category":"Retail",
            "subcategory":"Auto Repair",
            "type":"Services"
        }
    ],
    "sg:phone":"+1 773 925 9547",
    "sg:postcode":"60636",
    "sg:province":"IL",
    "wof:name":"Chicago Auto Repair",
    "wof:placetype":"venue"
},
  "geometry": {"coordinates":[-87.67939800000001,41.768002],"type":"Point"}
}