{
  "type": "Feature",
  "properties": {
    "addr:full":"2743 N Albany Ave Chicago IL 60647",
    "addr:housenumber":"2743",
    "addr:postcode":"60647",
    "addr:street":"N Albany Ave",
    "iso:country":"US",
    "sg:address":"2743 N Albany Ave",
    "sg:city":"Chicago",
    "sg:classifiers":[
        {
            "category":"Professional",
            "subcategory":"Secretarial Services",
            "type":"Services"
        }
    ],
    "sg:phone":"+1 773 278 8476",
    "sg:postcode":"60647",
    "sg:province":"IL",
    "sg:tags":[
        "consulting",
        "management",
        "reporting"
    ],
    "wof:name":"Keyboard Connections",
    "wof:placetype":"venue"
},
  "geometry": {"coordinates":[-87.70487300000001,41.930851],"type":"Point"}
}