{
  "type": "Feature",
  "properties": {
    "iso:country":"US",
    "sg:address":"5518 W Gettysburg Street",
    "sg:city":"Chicago",
    "sg:classifiers":[
        {
            "category":"Place Of Worship",
            "subcategory":"Church",
            "type":"Public Place"
        },
        {
            "category":"Place Of Worship",
            "type":"Public Place"
        },
        {
            "category":"Organizations",
            "subcategory":"Religious Organization",
            "type":"Services"
        }
    ],
    "sg:phone":"+1 773 777 3360",
    "sg:postcode":"60630",
    "sg:province":"IL",
    "sg:tags":[
        "churches-evangelical",
        "churches-covenant",
        "covenant",
        "free"
    ],
    "wof:name":"Jefferson Park Evangelical Free Church",
    "wof:placetype":"venue"
},
  "geometry": {"coordinates":[-87.765897,41.975755],"type":"Point"}
}