{
  "type": "Feature",
  "properties": {
    "iso:country":"US",
    "sg:address":"345 N Salem Dr",
    "sg:city":"Schaumburg",
    "sg:classifiers":[
        {
            "category":"Education",
            "subcategory":"School",
            "type":"Public Place"
        }
    ],
    "sg:phone":"+1 847 357 6400",
    "sg:postcode":"60194",
    "sg:province":"IL",
    "sg:website":"http://www.sd54.k12.il.us",
    "wof:name":"Enders Salk Elementary School",
    "wof:placetype":"venue"
},
  "geometry": {"coordinates":[-88.101094,42.032963],"type":"Point"}
}