{
  "type": "Feature",
  "properties": {
    "iso:country":"US",
    "sg:address":"933 E Irving Park Rd",
    "sg:city":"Streamwood",
    "sg:classifiers":[
        {
            "category":"Real Estate",
            "subcategory":"Real Estate Services",
            "type":"Services"
        },
        {
            "category":"Real Estate",
            "subcategory":"Real Estate Agent",
            "type":"Services"
        }
    ],
    "sg:phone":"+1 630 540 2780",
    "sg:postcode":"60107",
    "sg:province":"IL",
    "sg:tags":[
        "buyer",
        "broker"
    ],
    "wof:name":"Su Casa",
    "wof:placetype":"venue"
},
  "geometry": {"coordinates":[-88.161213,42.00935],"type":"Point"}
}