{
  "type": "Feature",
  "properties": {
    "iso:country":"US",
    "sg:address":"400 N McClurg Court Apt 3104",
    "sg:city":"Chicago",
    "sg:classifiers":[
        {
            "category":"Health Services",
            "subcategory":"Doctor",
            "type":"Services"
        }
    ],
    "sg:phone":"+1 312 726 3165",
    "sg:postcode":"60611",
    "sg:province":"IL",
    "wof:name":"Gunther Meyer S MD Sc",
    "wof:placetype":"venue"
},
  "geometry": {"coordinates":[-87.62063000000001,41.894988],"type":"Point"}
}