{
  "type": "Feature",
  "properties": {
    "iso:country":"US",
    "sg:address":"19202 E Co Rd 1500 N",
    "sg:city":"Charleston",
    "sg:phone":"+1 217 345 1188",
    "sg:postcode":"61920",
    "sg:province":"IL",
    "sg:tags":[
        "hog",
        "farm",
        "corn",
        "soybean",
        "or",
        "feedlot"
    ],
    "wof:name":"Rick Winkler",
    "wof:placetype":"venue"
},
  "geometry": {"coordinates":[-88.102272,39.594826],"type":"Point"}
}