{
  "type": "Feature",
  "properties": {
    "iso:country":"US",
    "sg:address":"10918 S Bell Avenue",
    "sg:city":"Chicago",
    "sg:classifiers":[
        {
            "category":"Building & Trades",
            "subcategory":"Construction",
            "type":"Services"
        }
    ],
    "sg:phone":"+1 773 238 7166",
    "sg:postcode":"60643",
    "sg:province":"IL",
    "sg:tags":[
        "contractor"
    ],
    "wof:name":"Home Condominium Remodeling Center",
    "wof:placetype":"venue"
},
  "geometry": {"coordinates":[-87.676248,41.695034],"type":"Point"}
}