{
  "type": "Feature",
  "properties": {
    "iso:country":"US",
    "sg:address":"1001 Claim St",
    "sg:city":"Aurora",
    "sg:classifiers":[
        {
            "category":"Personal",
            "subcategory":"Beauty Salon",
            "type":"Services"
        }
    ],
    "sg:phone":"+1 630 499 8515",
    "sg:postcode":"60505",
    "sg:province":"IL",
    "wof:name":"Isabell's Unisex 2",
    "wof:placetype":"venue"
},
  "geometry": {"coordinates":[-88.28993199999999,41.760275],"type":"Point"}
}