{
  "type": "Feature",
  "properties": {
    "iso:country":"US",
    "sg:address":"1114 Olive St",
    "sg:city":"Collinsville",
    "sg:classifiers":[
        {
            "category":"Social Services",
            "subcategory":"Job Training",
            "type":"Services"
        }
    ],
    "sg:phone":"+1 618 346 0680",
    "sg:postcode":"62234",
    "sg:province":"IL",
    "sg:tags":[
        "rehabilitation"
    ],
    "wof:name":"Rehabilitation Institute",
    "wof:placetype":"venue"
},
  "geometry": {"coordinates":[-89.971538,38.680957],"type":"Point"}
}