{
  "type": "Feature",
  "properties": {
    "iso:country":"US",
    "sg:address":"515 E Fairview St",
    "sg:city":"Arlington Heights",
    "sg:classifiers":[
        {
            "category":"Freight",
            "type":"Transportation"
        }
    ],
    "sg:phone":"+1 847 392 0793",
    "sg:postcode":"60005",
    "sg:province":"IL",
    "sg:tags":[
        "operator",
        "local",
        "trucking"
    ],
    "wof:name":"Fmk",
    "wof:placetype":"venue"
},
  "geometry": {"coordinates":[-87.975853,42.073652],"type":"Point"}
}