{
  "type": "Feature",
  "properties": {
    "iso:country":"US",
    "sg:address":"19 W Scates St",
    "sg:city":"Caseyville",
    "sg:classifiers":[
        {
            "category":"Manufacturing",
            "subcategory":"Tools & Machinery",
            "type":"Manufacturing & Wholesale Goods"
        }
    ],
    "sg:phone":"+1 618 344 7683",
    "sg:postcode":"62232",
    "sg:province":"IL",
    "sg:tags":[
        "machine",
        "shop"
    ],
    "wof:name":"H & R Tool & Mach Co",
    "wof:placetype":"venue"
},
  "geometry": {"coordinates":[-90.025497,38.638468],"type":"Point"}
}