{
  "type": "Feature",
  "properties": {
    "iso:country":"US",
    "sg:address":"655 Oakview Dr",
    "sg:city":"Algonquin",
    "sg:classifiers":[
        {
            "category":"Health Services",
            "subcategory":"Clinic",
            "type":"Services"
        }
    ],
    "sg:phone":"+1 847 458 0398",
    "sg:postcode":"60102",
    "sg:province":"IL",
    "sg:tags":[
        "welfare"
    ],
    "wof:name":"Quick Claim Medical Billin",
    "wof:placetype":"venue"
},
  "geometry": {"coordinates":[-88.3075,42.162944],"type":"Point"}
}