{
  "type": "Feature",
  "properties": {
    "iso:country":"US",
    "sg:address":"940 W Adams St",
    "sg:city":"Chicago",
    "sg:classifiers":[
        {
            "category":"Real Estate",
            "subcategory":"Real Estate Services",
            "type":"Services"
        }
    ],
    "sg:phone":"+1 312 421 5260",
    "sg:postcode":"60607",
    "sg:province":"IL",
    "sg:tags":[
        "management",
        "property"
    ],
    "wof:name":"L J Sheridian",
    "wof:placetype":"venue"
},
  "geometry": {"coordinates":[-87.65100099999999,41.8792],"type":"Point"}
}