{
  "type": "Feature",
  "properties": {
    "addr:full":"3071 N Lincoln Ave Chicago IL 60657",
    "addr:housenumber":"3071",
    "addr:postcode":"60657",
    "addr:street":"N Lincoln Ave",
    "iso:country":"US",
    "sg:address":"3071 N Lincoln Ave",
    "sg:city":"Chicago",
    "sg:classifiers":[
        {
            "category":"Home & Garden",
            "subcategory":"Carpets & Floor Coverings",
            "type":"Retail Goods"
        }
    ],
    "sg:phone":"+1 773 528 3355",
    "sg:postcode":"60657",
    "sg:province":"IL",
    "sg:tags":[
        "carpeting"
    ],
    "wof:name":"Home Carpet & Linoleum Center",
    "wof:placetype":"venue"
},
  "geometry": {"coordinates":[-87.6661,41.937698],"type":"Point"}
}