{
  "type": "Feature",
  "properties": {
    "addr:full":"5835 W Roosevelt Rd Cicero IL 60804",
    "addr:housenumber":"5835",
    "addr:postcode":"60804",
    "addr:street":"W Roosevelt Rd",
    "iso:country":"US",
    "sg:address":"5835 W Roosevelt Rd",
    "sg:city":"Cicero",
    "sg:classifiers":[
        {
            "category":"Building & Trades",
            "subcategory":"Cleaning & Sanitation",
            "type":"Services"
        }
    ],
    "sg:phone":"+1 708 863 3774",
    "sg:postcode":"60804",
    "sg:province":"IL",
    "sg:tags":[
        "maintenance"
    ],
    "wof:name":"Dist 99 Service Center",
    "wof:placetype":"venue"
},
  "geometry": {"coordinates":[-87.770442,41.865511],"type":"Point"}
}