{
  "type": "Feature",
  "properties": {
    "addr:full":"1225 Blackhawk Dr Elgin IL 60120",
    "addr:housenumber":"1225",
    "addr:postcode":"60120",
    "addr:street":"Blackhawk Dr",
    "iso:country":"US",
    "sg:address":"1225 Blackhawk Dr",
    "sg:city":"Elgin",
    "sg:classifiers":[
        {
            "category":"Shopping",
            "subcategory":"Clothing, Apparel, & Fashions",
            "type":"Retail Goods"
        }
    ],
    "sg:phone":"+1   ",
    "sg:postcode":"60120",
    "sg:province":"IL",
    "wof:name":"Haggard Custom Bridal Designs",
    "wof:placetype":"venue"
},
  "geometry": {"coordinates":[-88.253839,42.05985],"type":"Point"}
}