{
  "type": "Feature",
  "properties": {
    "addr:full":"90 McMillen Rd Antioch IL 60002",
    "addr:housenumber":"90",
    "addr:postcode":"60002",
    "addr:street":"Mcmillen Rd",
    "iso:country":"US",
    "sg:address":"90 McMillen Rd",
    "sg:city":"Antioch",
    "sg:classifiers":[
        {
            "category":"Manufacturing",
            "subcategory":"Tools & Machinery",
            "type":"Manufacturing & Wholesale Goods"
        }
    ],
    "sg:phone":"+1 847 395 6200",
    "sg:postcode":"60002",
    "sg:province":"IL",
    "sg:tags":[
        "equipment",
        "lawn",
        "garden"
    ],
    "wof:name":"Kay Home Products",
    "wof:placetype":"venue"
},
  "geometry": {"coordinates":[-88.087142,42.472794],"type":"Point"}
}