{
  "type": "Feature",
  "properties": {
    "addr:full":"12255 Western Ave Ste 6 Blue Island IL 60406",
    "addr:housenumber":"12255",
    "addr:postcode":"60406",
    "addr:street":"Western Ave Ste 6",
    "iso:country":"US",
    "sg:address":"12255 Western Ave Ste 6",
    "sg:city":"Blue Island",
    "sg:classifiers":[
        {
            "category":"Food & Beverages",
            "subcategory":"Groceries & Convenience Stores",
            "type":"Retail Goods"
        }
    ],
    "sg:phone":"+1 708 385 3709",
    "sg:postcode":"60406",
    "sg:province":"IL",
    "wof:name":"Supermercado El Gallo",
    "wof:placetype":"venue"
},
  "geometry": {"coordinates":[-87.680397,41.670799],"type":"Point"}
}