{
  "type": "Feature",
  "properties": {
    "iso:country":"US",
    "sg:address":"2755 W Cermak Road",
    "sg:city":"Chicago",
    "sg:classifiers":[
        {
            "category":"Home & Garden",
            "subcategory":"Hardware",
            "type":"Retail Goods"
        }
    ],
    "sg:phone":"+1 773 247 6789",
    "sg:postcode":"60608",
    "sg:province":"IL",
    "sg:tags":[
        "store"
    ],
    "wof:name":"A-Z Hardware",
    "wof:placetype":"venue"
},
  "geometry": {"coordinates":[-87.695227,41.851797],"type":"Point"}
}