{
  "type": "Feature",
  "properties": {
    "iso:country":"US",
    "sg:address":"110 N State St",
    "sg:city":"Geneseo",
    "sg:classifiers":[
        {
            "category":"Insurance",
            "subcategory":"Insurance Agent",
            "type":"Services"
        }
    ],
    "sg:phone":"+1 309 944 1510",
    "sg:postcode":"61254",
    "sg:province":"IL",
    "wof:name":"Randy Augsburger Insurance",
    "wof:placetype":"venue"
},
  "geometry": {"coordinates":[-90.15563,41.4538],"type":"Point"}
}