{
  "type": "Feature",
  "properties": {
    "iso:country":"US",
    "sg:address":"5419 W 95th St",
    "sg:city":"Oak Lawn",
    "sg:classifiers":[
        {
            "category":"Wholesale",
            "subcategory":"Plants",
            "type":"Manufacturing & Wholesale Goods"
        }
    ],
    "sg:phone":"+1 708 424 8683",
    "sg:postcode":"60453",
    "sg:province":"IL",
    "sg:tags":[
        "florist"
    ],
    "wof:name":"Gallery of Flowers",
    "wof:placetype":"venue"
},
  "geometry": {"coordinates":[-87.75599699999999,41.719601],"type":"Point"}
}