{
  "type": "Feature",
  "properties": {
    "addr:full":"2260 Cornell Ave Aurora IL 60506",
    "addr:housenumber":"2260",
    "addr:postcode":"60506",
    "addr:street":"Cornell Ave",
    "iso:country":"US",
    "sg:address":"2260 Cornell Ave",
    "sg:city":"Aurora",
    "sg:classifiers":[
        {
            "category":"Manufacturing",
            "subcategory":"Chemicals & Compounds",
            "type":"Manufacturing & Wholesale Goods"
        },
        {
            "category":"Animal Shelter",
            "type":"Public Place"
        },
        {
            "category":"Building & Trades",
            "subcategory":"Pest Control",
            "type":"Services"
        }
    ],
    "sg:phone":"+1 866 574 1660",
    "sg:postcode":"60506",
    "sg:province":"IL",
    "sg:tags":[
        "industrial",
        "supply",
        "services-commercial",
        "termite",
        "bee",
        "equipment",
        "mothproofing",
        "removal"
    ],
    "sg:website":"http://orkin.com",
    "wof:name":"Orkin Pest & Termite Control",
    "wof:placetype":"venue"
},
  "geometry": {"coordinates":[-88.37394399999999,41.74248],"type":"Point"}
}