{
  "type": "Feature",
  "properties": {
    "addr:full":"2956 N Milwaukee Ave # 204 Chicago IL 60618",
    "addr:housenumber":"2956",
    "addr:postcode":"60618",
    "addr:street":"N Milwaukee Ave # 204",
    "iso:country":"US",
    "sg:address":"2956 N Milwaukee Ave # 204",
    "sg:city":"Chicago",
    "sg:classifiers":[
        {
            "category":"Place Of Worship",
            "subcategory":"Church",
            "type":"Public Place"
        },
        {
            "category":"Place Of Worship",
            "type":"Public Place"
        }
    ],
    "sg:phone":"+1 773 772 0400",
    "sg:postcode":"60618",
    "sg:province":"IL",
    "sg:tags":[
        "lutheran",
        "denomination",
        "churches-lutheran-evangelical",
        "churches-interdenominational",
        "america",
        "churches-various",
        "churches-lutheran"
    ],
    "wof:name":"Crossroads Christian Church",
    "wof:placetype":"venue"
},
  "geometry": {"coordinates":[-87.71727,41.935108],"type":"Point"}
}