{
  "type": "Feature",
  "properties": {
    "iso:country":"US",
    "sg:address":"2991 Co Rd 500 E",
    "sg:city":"Fisher",
    "sg:classifiers":[
        {
            "category":"Recreation",
            "type":"Entertainment"
        }
    ],
    "sg:phone":"+1 217 897 1907",
    "sg:postcode":"61843",
    "sg:province":"IL",
    "sg:tags":[
        "track",
        "operation",
        "racing",
        "or"
    ],
    "wof:name":"Eakers Stable",
    "wof:placetype":"venue"
},
  "geometry": {"coordinates":[-88.365432,40.309621],"type":"Point"}
}