{
  "type": "Feature",
  "properties": {
    "addr:full":"3817 W Pratt Ave Lincolnwood IL 60712",
    "addr:housenumber":"3817",
    "addr:postcode":"60712",
    "addr:street":"W Pratt Ave",
    "iso:country":"US",
    "sg:address":"3817 W Pratt Ave",
    "sg:city":"Lincolnwood",
    "sg:classifiers":[
        {
            "category":"Shopping",
            "subcategory":"Jewelry",
            "type":"Retail Goods"
        },
        {
            "category":"Manufacturing",
            "subcategory":"Jewelry",
            "type":"Manufacturing & Wholesale Goods"
        }
    ],
    "sg:phone":"+1 847 676 0318",
    "sg:postcode":"60712",
    "sg:province":"IL",
    "sg:tags":[
        "designer",
        "jeweler"
    ],
    "wof:name":"Edgar J Weisz Ofc",
    "wof:placetype":"venue"
},
  "geometry": {"coordinates":[-87.72413,42.004509],"type":"Point"}
}