{
  "type": "Feature",
  "properties": {
    "iso:country":"US",
    "sg:address":"1020 Madison Ave",
    "sg:city":"Madison",
    "sg:classifiers":[
        {
            "category":"Retail",
            "subcategory":"Auto Repair",
            "type":"Services"
        }
    ],
    "sg:phone":"+1 618 451 2886",
    "sg:postcode":"62060",
    "sg:province":"IL",
    "wof:name":"Madison Foreign & Domestic Auto Repair",
    "wof:placetype":"venue"
},
  "geometry": {"coordinates":[-90.155998,38.687199],"type":"Point"}
}