{
  "type": "Feature",
  "properties": {
    "iso:country":"US",
    "sg:address":"1101 Chestnut St",
    "sg:city":"Waukegan",
    "sg:classifiers":[
        {
            "category":"Professional",
            "subcategory":"Accounting & Tax Preparation",
            "type":"Services"
        }
    ],
    "sg:phone":"+1 847 263 0074",
    "sg:postcode":"60085",
    "sg:province":"IL",
    "wof:name":"January Accounting Service",
    "wof:placetype":"venue"
},
  "geometry": {"coordinates":[-87.840693,42.37645],"type":"Point"}
}