{
  "type": "Feature",
  "properties": {
    "iso:country":"US",
    "sg:address":"231 N 6th St",
    "sg:city":"Quincy",
    "sg:classifiers":[
        {
            "category":"Real Estate",
            "subcategory":"Real Estate Services",
            "type":"Services"
        }
    ],
    "sg:phone":"+1 217 222 2090",
    "sg:postcode":"62301",
    "sg:province":"IL",
    "sg:tags":[
        "company",
        "title"
    ],
    "wof:name":"Adams County Abstract & Title",
    "wof:placetype":"venue"
},
  "geometry": {"coordinates":[-91.406818,39.934101],"type":"Point"}
}