{
  "type": "Feature",
  "properties": {
    "addr:full":"2227 W Belmont Ave Chicago IL 60618",
    "addr:housenumber":"2227",
    "addr:postcode":"60618",
    "addr:street":"W Belmont Ave",
    "iso:country":"US",
    "sg:address":"2227 W Belmont Ave",
    "sg:city":"Chicago",
    "sg:classifiers":[
        {
            "category":"Shopping",
            "subcategory":"Pets & Pet Supplies",
            "type":"Retail Goods"
        }
    ],
    "sg:phone":"+1 773 661 0135",
    "sg:postcode":"60618",
    "sg:province":"IL",
    "sg:tags":[
        "training"
    ],
    "sg:website":"www.ilcanedolce.com",
    "wof:name":"Il Cane Dolce",
    "wof:placetype":"venue"
},
  "geometry": {"coordinates":[-87.683922,41.939503],"type":"Point"}
}