{
  "type": "Feature",
  "properties": {
    "addr:full":"1256 S Desplaines St Joliet IL 60436",
    "addr:housenumber":"1256",
    "addr:postcode":"60436",
    "addr:street":"S Desplaines St",
    "iso:country":"US",
    "sg:address":"1256 S Desplaines St",
    "sg:city":"Joliet",
    "sg:classifiers":[
        {
            "category":"Building & Trades",
            "subcategory":"Plumbing",
            "type":"Services"
        }
    ],
    "sg:phone":"+1 708 596 6122",
    "sg:postcode":"60436",
    "sg:province":"IL",
    "sg:tags":[
        "plumbing",
        "contractor"
    ],
    "wof:name":"Mr Rooter",
    "wof:placetype":"venue"
},
  "geometry": {"coordinates":[-88.08561899999999,41.51918],"type":"Point"}
}