{
  "type": "Feature",
  "properties": {
    "iso:country":"US",
    "sg:address":"2 W Talcott Rd Ste 30",
    "sg:city":"Park Ridge",
    "sg:classifiers":[
        {
            "category":"Health Services",
            "subcategory":"Optometrist",
            "type":"Services"
        }
    ],
    "sg:phone":"+1 847 696 2434",
    "sg:postcode":"60068",
    "sg:province":"IL",
    "wof:name":"Lossman Eye Care Associates",
    "wof:placetype":"venue"
},
  "geometry": {"coordinates":[-87.822098,41.993301],"type":"Point"}
}