{
  "type": "Feature",
  "properties": {
    "addr:full":"337 Ridge Ave Elmhurst IL 60126",
    "addr:housenumber":"337",
    "addr:postcode":"60126",
    "addr:street":"Ridge Ave",
    "iso:country":"US",
    "sg:address":"337 Ridge Ave",
    "sg:city":"Elmhurst",
    "sg:classifiers":[
        {
            "category":"Retail",
            "subcategory":"Repair Shop",
            "type":"Services"
        }
    ],
    "sg:phone":"+1 630 279 6244",
    "sg:postcode":"60126",
    "sg:province":"IL",
    "wof:name":"Martin Fako Piano Technician",
    "wof:placetype":"venue"
},
  "geometry": {"coordinates":[-87.927357,41.886386],"type":"Point"}
}