{
  "type": "Feature",
  "properties": {
    "iso:country":"US",
    "sg:address":"457 E Oxford Rd",
    "sg:city":"North Barrington",
    "sg:classifiers":[
        {
            "category":"Professional",
            "subcategory":"Advertising",
            "type":"Services"
        }
    ],
    "sg:phone":"+1 847 842 1441",
    "sg:postcode":"60010",
    "sg:province":"IL",
    "sg:tags":[
        "mail"
    ],
    "sg:website":"www.salesoverlays.com",
    "wof:name":"Sales Overlays",
    "wof:placetype":"venue"
},
  "geometry": {"coordinates":[-88.128209,42.20566],"type":"Point"}
}