{
  "type": "Feature",
  "properties": {
    "iso:country":"US",
    "sg:address":"570 Turner Ave",
    "sg:city":"Glen Ellyn",
    "sg:classifiers":[
        {
            "category":"Professional",
            "subcategory":"Business Services",
            "type":"Services"
        }
    ],
    "sg:phone":"+1 630 790 0284",
    "sg:postcode":"60137",
    "sg:province":"IL",
    "wof:name":"Paw Paw Partners",
    "wof:placetype":"venue"
},
  "geometry": {"coordinates":[-88.061691,41.870745],"type":"Point"}
}