{
  "type": "Feature",
  "properties": {
    "iso:country":"US",
    "sg:address":"2612 18th",
    "sg:city":"Silvis",
    "sg:classifiers":[
        {
            "category":"Building & Trades",
            "subcategory":"Locksmith",
            "type":"Services"
        }
    ],
    "sg:phone":"+1 309 792 0611",
    "sg:postcode":"61282",
    "sg:province":"IL",
    "sg:tags":[
        "key"
    ],
    "wof:name":"Johnston Marvin L",
    "wof:placetype":"venue"
},
  "geometry": {"coordinates":[-90.415604,41.499001],"type":"Point"}
}