{
  "type": "Feature",
  "properties": {
    "addr:full":"1613 E 55th St Chicago IL 60615",
    "addr:housenumber":"1613",
    "addr:postcode":"60615",
    "addr:street":"E 55Th St",
    "iso:country":"US",
    "sg:address":"1613 E 55th St",
    "sg:city":"Chicago",
    "sg:classifiers":[
        {
            "category":"Organizations",
            "subcategory":"Membership Organization",
            "type":"Services"
        }
    ],
    "sg:phone":"+1 800 649 7654",
    "sg:postcode":"60615",
    "sg:province":"IL",
    "sg:tags":[
        "club",
        "travel"
    ],
    "wof:name":"Rite Way Travel Greater Chicagoland Toll Free",
    "wof:placetype":"venue"
},
  "geometry": {"coordinates":[-87.5855,41.795211],"type":"Point"}
}