{
  "type": "Feature",
  "properties": {
    "iso:country":"US",
    "sg:address":"15503 S 70th Ct",
    "sg:city":"Orland Park",
    "sg:classifiers":[
        {
            "category":"Wholesale",
            "subcategory":"Machinery & Supplies",
            "type":"Manufacturing & Wholesale Goods"
        }
    ],
    "sg:phone":"+1 708 633 1400",
    "sg:postcode":"60462",
    "sg:province":"IL",
    "sg:tags":[
        "rubber",
        "product",
        "industrial"
    ],
    "wof:name":"Badger Rubber Co",
    "wof:placetype":"venue"
},
  "geometry": {"coordinates":[-87.790871,41.606085],"type":"Point"}
}