{
  "type": "Feature",
  "properties": {
    "iso:country":"US",
    "sg:address":"16705 Gentry Ln",
    "sg:city":"Tinley Park",
    "sg:classifiers":[
        {
            "category":"Real Estate",
            "subcategory":"Real Estate Operator",
            "type":"Services"
        }
    ],
    "sg:phone":"+1 708 429 7573",
    "sg:postcode":"60477",
    "sg:province":"IL",
    "sg:tags":[
        "apartment"
    ],
    "wof:name":"Edgewater Walk Apartments",
    "wof:placetype":"venue"
},
  "geometry": {"coordinates":[-87.761111,41.588153],"type":"Point"}
}