{
  "type": "Feature",
  "properties": {
    "iso:country":"US",
    "sg:address":"3106 Broadway St",
    "sg:city":"Mount Vernon",
    "sg:classifiers":[
        {
            "category":"Personal",
            "subcategory":"Tanning Parlor",
            "type":"Services"
        },
        {
            "category":"Personal",
            "type":"Services"
        }
    ],
    "sg:phone":"+1 618 244 0109",
    "sg:postcode":"62864",
    "sg:province":"IL",
    "sg:tags":[
        "salon"
    ],
    "wof:name":"Sun City Tanning Salon",
    "wof:placetype":"venue"
},
  "geometry": {"coordinates":[-88.929149,38.314828],"type":"Point"}
}