{
  "type": "Feature",
  "properties": {
    "iso:country":"US",
    "sg:address":"866 S Park Ter",
    "sg:city":"Chicago",
    "sg:classifiers":[
        {
            "category":"Food & Beverages",
            "subcategory":"Meat & Fish",
            "type":"Retail Goods"
        }
    ],
    "sg:phone":"+1 312 320 6928",
    "sg:postcode":"60605",
    "sg:province":"IL",
    "sg:tags":[
        "seafood-wholesale"
    ],
    "wof:name":"Ietc Corp.",
    "wof:placetype":"venue"
},
  "geometry": {"coordinates":[-87.629548,41.870881],"type":"Point"}
}