{
  "type": "Feature",
  "properties": {
    "iso:country":"US",
    "sg:address":"Park Place Shopping",
    "sg:city":"Carbondale",
    "sg:classifiers":[
        {
            "category":"Retail",
            "subcategory":"Laundry & Dry Cleaning",
            "type":"Services"
        }
    ],
    "sg:phone":"+1 618 457 6121",
    "sg:postcode":"62901",
    "sg:province":"IL",
    "wof:name":"University Cleaners & Shirt Laundry",
    "wof:placetype":"venue"
},
  "geometry": {"coordinates":[-89.215897,37.7253],"type":"Point"}
}