{
  "type": "Feature",
  "properties": {
    "addr:full":"1835 S Canal St Chicago IL 60616",
    "addr:housenumber":"1835",
    "addr:postcode":"60616",
    "addr:street":"S Canal St",
    "iso:country":"US",
    "sg:address":"1835 S Canal St",
    "sg:city":"Chicago",
    "sg:classifiers":[
        {
            "category":"Shopping",
            "subcategory":"Clothing, Apparel, & Fashions",
            "type":"Retail Goods"
        },
        {
            "category":"Manufacturing",
            "subcategory":"Apparel",
            "type":"Manufacturing & Wholesale Goods"
        }
    ],
    "sg:phone":"+1 312 733 9993",
    "sg:postcode":"60616",
    "sg:province":"IL",
    "sg:tags":[
        "apparel-wholesale",
        "manufacturer",
        "women's"
    ],
    "sg:website":"http://www.galaday.com",
    "wof:name":"Galaday",
    "wof:placetype":"venue"
},
  "geometry": {"coordinates":[-87.638929,41.857319],"type":"Point"}
}