{
  "type": "Feature",
  "properties": {
    "addr:full":"21534 N 1100th St Hidalgo IL 62432",
    "addr:housenumber":"21534",
    "addr:postcode":"62432",
    "addr:street":"N 1100Th St",
    "iso:country":"US",
    "sg:address":"21534 N 1100th St",
    "sg:city":"Hidalgo",
    "sg:phone":"+1 618 793 2514",
    "sg:postcode":"62432",
    "sg:province":"IL",
    "sg:tags":[
        "farm",
        "corn",
        "soybean"
    ],
    "wof:name":"Charles Carr",
    "wof:placetype":"venue"
},
  "geometry": {"coordinates":[-88.17277799999999,39.165558],"type":"Point"}
}