{
  "type": "Feature",
  "properties": {
    "addr:full":"706 Plaza Dr Carterville IL 62918",
    "addr:housenumber":"706",
    "addr:postcode":"62918",
    "addr:street":"Plaza Dr",
    "iso:country":"US",
    "sg:address":"706 Plaza Dr",
    "sg:city":"Carterville",
    "sg:classifiers":[
        {
            "category":"Restaurant",
            "type":"Food & Drink"
        }
    ],
    "sg:phone":"+1   ",
    "sg:postcode":"62918",
    "sg:province":"IL",
    "wof:name":"China City",
    "wof:placetype":"venue"
},
  "geometry": {"coordinates":[-89.07209899999999,37.745534],"type":"Point"}
}