{
  "type": "Feature",
  "properties": {
    "iso:country":"US",
    "sg:address":"1938 Shirland Ave",
    "sg:city":"South Beloit",
    "sg:classifiers":[
        {
            "category":"Wholesale",
            "subcategory":"Non-durable Goods",
            "type":"Manufacturing & Wholesale Goods"
        }
    ],
    "sg:phone":"+1 815 389 0230",
    "sg:postcode":"61080",
    "sg:province":"WI",
    "sg:tags":[
        "packaging",
        "material"
    ],
    "wof:name":"Soft Touch Packaging",
    "wof:placetype":"venue"
},
  "geometry": {"coordinates":[-89.062627,42.496168],"type":"Point"}
}