{
  "type": "Feature",
  "properties": {
    "iso:country":"US",
    "sg:address":"1201 Silo Hill Dr",
    "sg:city":"Grayslake",
    "sg:classifiers":[
        {
            "category":"Professional",
            "subcategory":"Detective & Security Services",
            "type":"Services"
        }
    ],
    "sg:phone":"+1 224 383 8000",
    "sg:postcode":"60030",
    "sg:province":"IL",
    "sg:tags":[
        "information",
        "bureau"
    ],
    "wof:name":"Eilis Construction",
    "wof:placetype":"venue"
},
  "geometry": {"coordinates":[-88.01561700000001,42.33696],"type":"Point"}
}