{
  "type": "Feature",
  "properties": {
    "addr:full":"915 Garfield Ave Aurora IL 60506",
    "addr:housenumber":"915",
    "addr:postcode":"60506",
    "addr:street":"Garfield Ave",
    "iso:country":"US",
    "sg:address":"915 Garfield Ave",
    "sg:city":"Aurora",
    "sg:classifiers":[
        {
            "category":"Building & Trades",
            "subcategory":"Electrical",
            "type":"Services"
        }
    ],
    "sg:phone":"+1 630 264 6822",
    "sg:postcode":"60506",
    "sg:province":"IL",
    "sg:tags":[
        "electrical",
        "contractor"
    ],
    "wof:name":"G & G Electric",
    "wof:placetype":"venue"
},
  "geometry": {"coordinates":[-88.33959400000001,41.75991],"type":"Point"}
}