{
  "type": "Feature",
  "properties": {
    "addr:full":"215 E New York St Aurora IL 60506",
    "addr:housenumber":"215",
    "addr:postcode":"60506",
    "addr:street":"E New York St",
    "iso:country":"US",
    "sg:address":"215 E New York St",
    "sg:city":"Aurora",
    "sg:classifiers":[
        {
            "category":"Shopping",
            "subcategory":"Used Merchandise",
            "type":"Retail Goods"
        }
    ],
    "sg:phone":"+1 630 892 4239",
    "sg:postcode":"60506",
    "sg:province":"IL",
    "sg:tags":[
        "shop",
        "thrift"
    ],
    "wof:name":"Hope Chest",
    "wof:placetype":"venue"
},
  "geometry": {"coordinates":[-88.309759,41.756892],"type":"Point"}
}