{
  "type": "Feature",
  "properties": {
    "iso:country":"US",
    "sg:address":"12800 106th Ave",
    "sg:city":"Coal Valley",
    "sg:classifiers":[
        {
            "category":"Wholesale",
            "subcategory":"Machinery & Supplies",
            "type":"Manufacturing & Wholesale Goods"
        },
        {
            "category":"Building & Trades",
            "subcategory":"Construction",
            "type":"Services"
        }
    ],
    "sg:phone":"+1 309 762 1773",
    "sg:postcode":"61240",
    "sg:province":"IL",
    "sg:tags":[
        "equipment",
        "general",
        "contractor"
    ],
    "wof:name":"Michael De Volder Construction",
    "wof:placetype":"venue"
},
  "geometry": {"coordinates":[-90.439176,41.414077],"type":"Point"}
}