{
  "type": "Feature",
  "properties": {
    "addr:full":"308 W Erie St Ste 300 Chicago IL 60654",
    "addr:housenumber":"308",
    "addr:postcode":"60654",
    "addr:street":"W Erie St Ste 300",
    "iso:country":"US",
    "sg:address":"308 W Erie St Ste 300",
    "sg:city":"Chicago",
    "sg:classifiers":[
        {
            "category":"Professional",
            "subcategory":"Employment Agencies",
            "type":"Services"
        }
    ],
    "sg:phone":"+1 312 957 0337",
    "sg:postcode":"60654",
    "sg:province":"IL",
    "wof:name":"R S M R Global Resources",
    "wof:placetype":"venue"
},
  "geometry": {"coordinates":[-87.63628300000001,41.894337],"type":"Point"}
}