{
  "type": "Feature",
  "properties": {
    "iso:country":"US",
    "sg:address":"190 S Prospect Ave",
    "sg:city":"Elmhurst",
    "sg:classifiers":[
        {
            "category":"Restaurant",
            "type":"Food & Drink"
        }
    ],
    "sg:phone":"+1 630 617 3183",
    "sg:postcode":"60126",
    "sg:province":"IL",
    "wof:name":"Blimpie Subs & Salads",
    "wof:placetype":"venue"
},
  "geometry": {"coordinates":[-87.944952,41.895262],"type":"Point"}
}