{
  "type": "Feature",
  "properties": {
    "addr:full":"6429 S Seeley Avenue Chicago IL 60636",
    "addr:housenumber":"6429",
    "addr:postcode":"60636",
    "addr:street":"S Seeley Avenue",
    "iso:country":"US",
    "sg:address":"6429 S Seeley Avenue",
    "sg:city":"Chicago",
    "sg:classifiers":[
        {
            "category":"Building & Trades",
            "subcategory":"Plumbing",
            "type":"Services"
        }
    ],
    "sg:phone":"+1 773 925 7504",
    "sg:postcode":"60636",
    "sg:province":"IL",
    "wof:name":"Modern Plumbing & Sewerage Company",
    "wof:placetype":"venue"
},
  "geometry": {"coordinates":[-87.67483,41.776013],"type":"Point"}
}