{
  "type": "Feature",
  "properties": {
    "addr:full":"400 N Clark St Chicago IL 60654",
    "addr:housenumber":"400",
    "addr:postcode":"60654",
    "addr:street":"N Clark St",
    "iso:country":"US",
    "sg:address":"400 N Clark St",
    "sg:city":"Chicago",
    "sg:classifiers":[
        {
            "category":"Banks & Credit Unions",
            "subcategory":"Investment Brokerage",
            "type":"Services"
        },
        {
            "category":"Banks & Credit Unions",
            "subcategory":"Bank",
            "type":"Services"
        },
        {
            "category":"Banks & Credit Unions",
            "subcategory":"Financial Services",
            "type":"Services"
        },
        {
            "category":"Professional",
            "subcategory":"Lawyer & Legal Services",
            "type":"Services"
        }
    ],
    "sg:phone":"+1 312 670 3310",
    "sg:postcode":"60654",
    "sg:province":"IL",
    "sg:tags":[
        "advisory",
        "attorney",
        "estate",
        "agent",
        "planning",
        "trust",
        "insurance",
        "mutual",
        "retirement",
        "profit",
        "transfer",
        "wills",
        "stock",
        "sharing",
        "broker",
        "fund",
        "management",
        "plan",
        "planner",
        "annuity",
        "pension",
        "consultant",
        "security",
        "bond"
    ],
    "sg:website":"https://www.smithbarney.com",
    "wof:name":"Smith Barney",
    "wof:placetype":"venue"
},
  "geometry": {"coordinates":[-87.63104199999999,41.88921],"type":"Point"}
}