{
  "type": "Feature",
  "properties": {
    "iso:country":"US",
    "sg:address":"173 S River St",
    "sg:city":"Aurora",
    "sg:classifiers":[
        {
            "category":"Home & Garden",
            "subcategory":"Carpets & Floor Coverings",
            "type":"Retail Goods"
        }
    ],
    "sg:phone":"+1 630 897 1168",
    "sg:postcode":"60506",
    "sg:province":"IL",
    "sg:tags":[
        "dealer",
        "rug"
    ],
    "wof:name":"Carpetville Flooring America",
    "wof:placetype":"venue"
},
  "geometry": {"coordinates":[-88.320393,41.756758],"type":"Point"}
}