{
  "type": "Feature",
  "properties": {
    "iso:country":"US",
    "sg:address":"118 Ballinger St",
    "sg:city":"Girard",
    "sg:classifiers":[
        {
            "category":"Education",
            "subcategory":"School",
            "type":"Public Place"
        }
    ],
    "sg:phone":"+1   ",
    "sg:postcode":"62640",
    "sg:province":"IL",
    "sg:tags":[
        "educational",
        "administrative"
    ],
    "wof:name":"Bus Garage",
    "wof:placetype":"venue"
},
  "geometry": {"coordinates":[-89.786918,39.446329],"type":"Point"}
}