{
  "type": "Feature",
  "properties": {
    "iso:country":"US",
    "sg:address":"500 St Lucy Ct",
    "sg:city":"East St Louis",
    "sg:classifiers":[
        {
            "category":"Building & Trades",
            "subcategory":"Construction",
            "type":"Services"
        }
    ],
    "sg:phone":"+1 618 271 1615",
    "sg:postcode":"62206",
    "sg:province":"IL",
    "sg:tags":[
        "railroad",
        "contractor"
    ],
    "wof:name":"Heartland Track Works",
    "wof:placetype":"venue"
},
  "geometry": {"coordinates":[-90.186638,38.563244],"type":"Point"}
}