{
  "type": "Feature",
  "properties": {
    "iso:country":"US",
    "sg:address":"1410 Lawrence Ave",
    "sg:city":"Joliet",
    "sg:classifiers":[
        {
            "category":"Restaurant",
            "type":"Food & Drink"
        }
    ],
    "sg:phone":"+1 815 722 4450",
    "sg:postcode":"60435",
    "sg:province":"IL",
    "wof:name":"Shortley's Corner",
    "wof:placetype":"venue"
},
  "geometry": {"coordinates":[-88.09804699999999,41.550505],"type":"Point"}
}