{
  "type": "Feature",
  "properties": {
    "addr:full":"4701 N. Clark Street Chicago IL 60640",
    "addr:housenumber":"4701",
    "addr:postcode":"60640",
    "addr:street":"N. Clark Street",
    "iso:country":"US",
    "sg:address":"4701 N. Clark Street",
    "sg:city":"Chicago",
    "sg:classifiers":[
        {
            "category":"Banks & Credit Unions",
            "subcategory":"Bank",
            "type":"Services"
        }
    ],
    "sg:phone":"+1 773 564 3480",
    "sg:postcode":"60640",
    "sg:province":"IL",
    "sg:website":"www.northcommunitybank.com",
    "wof:name":"North Community Bank",
    "wof:placetype":"venue"
},
  "geometry": {"coordinates":[-87.667063,41.968515],"type":"Point"}
}