{
  "type": "Feature",
  "properties": {
    "addr:full":"4405 N Sterling Ave Peoria IL 61615",
    "addr:housenumber":"4405",
    "addr:postcode":"61615",
    "addr:street":"N Sterling Ave",
    "iso:country":"US",
    "sg:address":"4405 N Sterling Ave",
    "sg:city":"Peoria",
    "sg:classifiers":[
        {
            "category":"Banks & Credit Unions",
            "subcategory":"Financial Services",
            "type":"Services"
        }
    ],
    "sg:phone":"+1 309 686 9777",
    "sg:postcode":"61615",
    "sg:province":"IL",
    "sg:tags":[
        "loan",
        "plan"
    ],
    "sg:website":"http://www.americashloans.net",
    "wof:name":"Americash Loans",
    "wof:placetype":"venue"
},
  "geometry": {"coordinates":[-89.63181299999999,40.740508],"type":"Point"}
}