{
  "type": "Feature",
  "properties": {
    "addr:full":"4647 W Augusta Blvd Chicago IL 60651",
    "addr:housenumber":"4647",
    "addr:postcode":"60651",
    "addr:street":"W Augusta Blvd",
    "iso:country":"US",
    "sg:address":"4647 W Augusta Blvd",
    "sg:city":"Chicago",
    "sg:classifiers":[
        {
            "category":"Manufacturing",
            "subcategory":"Rubber & Plastics",
            "type":"Manufacturing & Wholesale Goods"
        }
    ],
    "sg:phone":"+1 773 261 5200",
    "sg:postcode":"60651",
    "sg:province":"IL",
    "sg:tags":[
        "profile",
        "p",
        "shape",
        "film",
        "mfg"
    ],
    "wof:name":"Warp Bros",
    "wof:placetype":"venue"
},
  "geometry": {"coordinates":[-87.742763,41.898678],"type":"Point"}
}