{
  "type": "Feature",
  "properties": {
    "iso:country":"US",
    "sg:address":"2350 Dogwood Rd",
    "sg:city":"Carbondale",
    "sg:classifiers":[
        {
            "category":"Professional",
            "subcategory":"Management & Consulting",
            "type":"Services"
        }
    ],
    "sg:phone":"+1 618 457 7361",
    "sg:postcode":"62902",
    "sg:province":"IL",
    "sg:tags":[
        "consultant",
        "safety"
    ],
    "wof:name":"J M Davis & Assoc Inc",
    "wof:placetype":"venue"
},
  "geometry": {"coordinates":[-89.16180900000001,37.703485],"type":"Point"}
}