{
  "type": "Feature",
  "properties": {
    "iso:country":"US",
    "sg:address":"3420 W 26th St",
    "sg:city":"Chicago",
    "sg:classifiers":[
        {
            "category":"Shopping",
            "subcategory":"Clothing, Apparel, & Fashions",
            "type":"Retail Goods"
        }
    ],
    "sg:phone":"+1 773 542 4111",
    "sg:postcode":"60623",
    "sg:province":"IL",
    "sg:tags":[
        "children's",
        "clothing"
    ],
    "wof:name":"Vergil Raul",
    "wof:placetype":"venue"
},
  "geometry": {"coordinates":[-87.710877,41.844601],"type":"Point"}
}