{
  "type": "Feature",
  "properties": {
    "iso:country":"US",
    "sg:address":"3701 Algonquin Rd",
    "sg:city":"Rolling Meadows",
    "sg:classifiers":[
        {
            "category":"Organizations",
            "subcategory":"Professional Association",
            "type":"Services"
        }
    ],
    "sg:phone":"+1 847 590 1191",
    "sg:postcode":"60008",
    "sg:province":"IL",
    "sg:tags":[
        "trade"
    ],
    "wof:name":"I Car",
    "wof:placetype":"venue"
},
  "geometry": {"coordinates":[-88.02729100000001,42.062339],"type":"Point"}
}