{
  "type": "Feature",
  "properties": {
    "iso:country":"US",
    "sg:address":"4800 N Ashland Ave",
    "sg:city":"Chicago",
    "sg:classifiers":[
        {
            "category":"Retail",
            "subcategory":"Auto Repair",
            "type":"Services"
        }
    ],
    "sg:phone":"+1 773 878 5480",
    "sg:postcode":"60640",
    "sg:province":"IL",
    "wof:name":"Ashland Lawrence Shell Service",
    "wof:placetype":"venue"
},
  "geometry": {"coordinates":[-87.669296,41.969101],"type":"Point"}
}