{
  "type": "Feature",
  "properties": {
    "iso:country":"US",
    "sg:address":"445 E North Water St # 1504",
    "sg:city":"Chicago",
    "sg:classifiers":[
        {
            "category":"Professional",
            "subcategory":"Computer Services",
            "type":"Services"
        }
    ],
    "sg:phone":"+1 312 661 0102",
    "sg:postcode":"60611",
    "sg:province":"IL",
    "sg:tags":[
        "graphic"
    ],
    "wof:name":"Q E D Consulting",
    "wof:placetype":"venue"
},
  "geometry": {"coordinates":[-87.617097,41.889523],"type":"Point"}
}