{
  "type": "Feature",
  "properties": {
    "iso:country":"US",
    "sg:address":"434 Redwood Ln",
    "sg:city":"Schaumburg",
    "sg:classifiers":[
        {
            "category":"Bars & Pubs",
            "type":"Food & Drink"
        }
    ],
    "sg:phone":"+1   ",
    "sg:postcode":"60193",
    "sg:province":"IL",
    "sg:tags":[
        "drinking"
    ],
    "wof:name":"Angel Playpen",
    "wof:placetype":"venue"
},
  "geometry": {"coordinates":[-88.093407,42.017985],"type":"Point"}
}