{
  "type": "Feature",
  "properties": {
    "addr:full":"1300 Mercantile Dr Highland IL 62249",
    "addr:housenumber":"1300",
    "addr:postcode":"62249",
    "addr:street":"Mercantile Dr",
    "iso:country":"US",
    "sg:address":"1300 Mercantile Dr",
    "sg:city":"Highland",
    "sg:classifiers":[
        {
            "category":"Banks & Credit Unions",
            "subcategory":"Bank",
            "type":"Services"
        }
    ],
    "sg:phone":"+1 618 654 5632",
    "sg:postcode":"62249",
    "sg:province":"IL",
    "sg:tags":[
        "small",
        "loan",
        "company"
    ],
    "wof:name":"Security Finance Corp of Ill",
    "wof:placetype":"venue"
},
  "geometry": {"coordinates":[-89.675754,38.748982],"type":"Point"}
}