{
  "type": "Feature",
  "properties": {
    "iso:country":"US",
    "sg:address":"1153 W Belmont Avenue",
    "sg:city":"Chicago",
    "sg:classifiers":[
        {
            "category":"Food & Beverages",
            "subcategory":"Groceries & Convenience Stores",
            "type":"Retail Goods"
        }
    ],
    "sg:phone":"+1 773 528 7322",
    "sg:postcode":"60657",
    "sg:province":"IL",
    "sg:website":"www.7-eleven.com",
    "wof:name":"7-Eleven Food Stores",
    "wof:placetype":"venue"
},
  "geometry": {"coordinates":[-87.65854400000001,41.939732],"type":"Point"}
}