{
  "type": "Feature",
  "properties": {
    "iso:country":"US",
    "sg:address":"7300 W 71st St",
    "sg:city":"Bridgeview",
    "sg:classifiers":[
        {
            "category":"Autos & Motor Vehicles",
            "subcategory":"Automobile Sales",
            "type":"Retail Goods"
        }
    ],
    "sg:phone":"+1 708 594 7200",
    "sg:postcode":"60455",
    "sg:province":"IL",
    "sg:tags":[
        "new",
        "car"
    ],
    "wof:name":"Toyota Park",
    "wof:placetype":"venue"
},
  "geometry": {"coordinates":[-87.802673,41.76263],"type":"Point"}
}