{
  "type": "Feature",
  "properties": {
    "iso:country":"US",
    "sg:address":"3006 N Elston",
    "sg:city":"Chicago",
    "sg:classifiers":[
        {
            "category":"Restaurant",
            "type":"Food & Drink"
        }
    ],
    "sg:phone":"+1 773 539 1814",
    "sg:postcode":"60618",
    "sg:province":"IL",
    "sg:tags":[
        "mexican"
    ],
    "wof:name":"Best Taco Burrito",
    "wof:placetype":"venue"
},
  "geometry": {"coordinates":[-87.693414,41.936028],"type":"Point"}
}