{
  "type": "Feature",
  "properties": {
    "iso:country":"US",
    "sg:address":"220 W Mill St",
    "sg:city":"Kewanee",
    "sg:classifiers":[
        {
            "category":"Organizations",
            "subcategory":"Religious Organization",
            "type":"Services"
        }
    ],
    "sg:phone":"+1 309 852 2455",
    "sg:postcode":"61443",
    "sg:province":"IL",
    "wof:name":"Emmanuel Mssnary Baptst Church",
    "wof:placetype":"venue"
},
  "geometry": {"coordinates":[-89.932215,41.232602],"type":"Point"}
}