{
  "type": "Feature",
  "properties": {
    "addr:full":"101 W Grand Ave Chicago IL 60654",
    "addr:housenumber":"101",
    "addr:postcode":"60654",
    "addr:street":"W Grand Ave",
    "iso:country":"US",
    "sg:address":"101 W Grand Ave",
    "sg:city":"Chicago",
    "sg:classifiers":[
        {
            "category":"Professional",
            "subcategory":"Lawyer & Legal Services",
            "type":"Services"
        }
    ],
    "sg:phone":"+1 312 321 9448",
    "sg:postcode":"60654",
    "sg:province":"IL",
    "sg:website":"www.underadvisement.com",
    "wof:name":"Under Advisement Ltd",
    "wof:placetype":"venue"
},
  "geometry": {"coordinates":[-87.631125,41.891611],"type":"Point"}
}