{
  "type": "Feature",
  "properties": {
    "addr:full":"1225 Harlem Ave Forest Park IL 60130",
    "addr:housenumber":"1225",
    "addr:postcode":"60130",
    "addr:street":"Harlem Ave",
    "iso:country":"US",
    "sg:address":"1225 Harlem Ave",
    "sg:city":"Forest Park",
    "sg:classifiers":[
        {
            "category":"Health Services",
            "subcategory":"Clinic",
            "type":"Services"
        }
    ],
    "sg:phone":"+1 708 488 8701",
    "sg:postcode":"60130",
    "sg:province":"IL",
    "sg:tags":[
        "medical"
    ],
    "wof:name":"Asap Physicians Services, LTD",
    "wof:placetype":"venue"
},
  "geometry": {"coordinates":[-87.804508,41.86384],"type":"Point"}
}