{
  "type": "Feature",
  "properties": {
    "addr:full":"5512 W Devon Ave Chicago IL 60646",
    "addr:housenumber":"5512",
    "addr:postcode":"60646",
    "addr:street":"W Devon Ave",
    "iso:country":"US",
    "sg:address":"5512 W Devon Ave",
    "sg:city":"Chicago",
    "sg:classifiers":[
        {
            "category":"Shopping",
            "subcategory":"Florist",
            "type":"Retail Goods"
        }
    ],
    "sg:phone":"+1   ",
    "sg:postcode":"60646",
    "sg:province":"IL",
    "wof:name":"Floral Affairs LTD",
    "wof:placetype":"venue"
},
  "geometry": {"coordinates":[-87.76669200000001,41.997302],"type":"Point"}
}