{
  "type": "Feature",
  "properties": {
    "addr:full":"2685 New Milford School Rd Rockford IL 61109",
    "addr:housenumber":"2685",
    "addr:postcode":"61109",
    "addr:street":"New Milford School Rd",
    "iso:country":"US",
    "sg:address":"2685 New Milford School Rd",
    "sg:city":"Rockford",
    "sg:classifiers":[
        {
            "category":"Organizations",
            "subcategory":"Non-profit Organization",
            "type":"Services"
        }
    ],
    "sg:phone":"+1 815 874 7576",
    "sg:postcode":"61109",
    "sg:province":"IL",
    "sg:tags":[
        "fund",
        "support",
        "raising",
        "for",
        "environmental"
    ],
    "wof:name":"Friends of Atwood Inc",
    "wof:placetype":"venue"
},
  "geometry": {"coordinates":[-89.064161,42.187309],"type":"Point"}
}