{
  "type": "Feature",
  "properties": {
    "iso:country":"US",
    "sg:address":"214 S Hough St",
    "sg:city":"Barrington",
    "sg:classifiers":[
        {
            "category":"Restaurant",
            "type":"Food & Drink"
        }
    ],
    "sg:phone":"+1   ",
    "sg:postcode":"60010",
    "sg:province":"IL",
    "wof:name":"Canteen Restaurant",
    "wof:placetype":"venue"
},
  "geometry": {"coordinates":[-88.13612,42.152523],"type":"Point"}
}