{
  "type": "Feature",
  "properties": {
    "addr:full":"233 S Wacker Dr Chicago IL 60606",
    "addr:housenumber":"233",
    "addr:postcode":"60606",
    "addr:street":"S Wacker Dr",
    "iso:country":"US",
    "sg:address":"233 S Wacker Dr",
    "sg:city":"Chicago",
    "sg:classifiers":[
        {
            "category":"Professional",
            "subcategory":"Management & Consulting",
            "type":"Services"
        },
        {
            "category":"Professional",
            "subcategory":"Computer Services",
            "type":"Services"
        }
    ],
    "sg:phone":"+1 312 589 6210",
    "sg:postcode":"60606",
    "sg:province":"IL",
    "sg:tags":[
        "science",
        "consultant",
        "academic",
        "internet"
    ],
    "wof:name":"Signature Consultants, LLC",
    "wof:placetype":"venue"
},
  "geometry": {"coordinates":[-87.634496,41.886768],"type":"Point"}
}