{
  "type": "Feature",
  "properties": {
    "iso:country":"US",
    "sg:address":"1235 N Mulford Rd",
    "sg:city":"Rockford",
    "sg:classifiers":[
        {
            "category":"Health Services",
            "subcategory":"Doctor",
            "type":"Services"
        }
    ],
    "sg:phone":"+1 815 484 9900",
    "sg:postcode":"61107",
    "sg:province":"IL",
    "sg:tags":[
        "physician",
        "surgeons",
        "otorhinolaryngology",
        "throat",
        "nose",
        "dermatology",
        "surgeon",
        "ear"
    ],
    "wof:name":"Andrew Jun I MD",
    "wof:placetype":"venue"
},
  "geometry": {"coordinates":[-88.999621,42.280983],"type":"Point"}
}