{
  "type": "Feature",
  "properties": {
    "iso:country":"US",
    "sg:address":"180 E Rollins Rd",
    "sg:city":"Round Lake",
    "sg:classifiers":[
        {
            "category":"Autos & Motor Vehicles",
            "subcategory":"Fuel & Gas Station",
            "type":"Retail Goods"
        }
    ],
    "sg:phone":"+1   ",
    "sg:postcode":"60073",
    "sg:province":"IL",
    "sg:tags":[
        "food",
        "mart",
        "station"
    ],
    "wof:name":"Thorntons Gas & Foodmart 114",
    "wof:placetype":"venue"
},
  "geometry": {"coordinates":[-88.07724,42.37891],"type":"Point"}
}