{
  "type": "Feature",
  "properties": {
    "iso:country":"US",
    "sg:address":"603 Alida Dr",
    "sg:city":"Cary",
    "sg:classifiers":[
        {
            "category":"Building & Trades",
            "subcategory":"Construction",
            "type":"Services"
        }
    ],
    "sg:phone":"+1 847 344 9166",
    "sg:postcode":"60013",
    "sg:province":"IL",
    "sg:tags":[
        "house"
    ],
    "wof:name":"E & B General Contract",
    "wof:placetype":"venue"
},
  "geometry": {"coordinates":[-88.25196200000001,42.210112],"type":"Point"}
}