{
  "type": "Feature",
  "properties": {
    "iso:country":"US",
    "sg:address":"212 Center St",
    "sg:city":"Glenwood",
    "sg:classifiers":[
        {
            "category":"Building & Trades",
            "subcategory":"Plumbing",
            "type":"Services"
        }
    ],
    "sg:phone":"+1 773 581 5533",
    "sg:postcode":"60425",
    "sg:province":"IL",
    "sg:tags":[
        "repair",
        "contractor"
    ],
    "wof:name":"Sam Houstons Sewerage & Plbg",
    "wof:placetype":"venue"
},
  "geometry": {"coordinates":[-87.605607,41.546236],"type":"Point"}
}