{
  "type": "Feature",
  "properties": {
    "iso:country":"US",
    "sg:address":"Hoffman Plz",
    "sg:city":"Roselle",
    "sg:classifiers":[
        {
            "category":"Restaurant",
            "type":"Food & Drink"
        }
    ],
    "sg:phone":"+1 847 885 0888",
    "sg:postcode":"60172",
    "sg:province":"IL",
    "wof:name":"Jockey Wok'n'rolls Restaurant",
    "wof:placetype":"venue"
},
  "geometry": {"coordinates":[-88.086502,41.983299],"type":"Point"}
}