{
  "type": "Feature",
  "properties": {
    "addr:full":"22960 N Apple Hill Ln Lincolnshire IL 60069",
    "addr:housenumber":"22960",
    "addr:postcode":"60069",
    "addr:street":"N Apple Hill Ln",
    "iso:country":"US",
    "sg:address":"22960 N Apple Hill Ln",
    "sg:city":"Lincolnshire",
    "sg:classifiers":[
        {
            "category":"Real Estate",
            "subcategory":"Real Estate Operator",
            "type":"Services"
        }
    ],
    "sg:phone":"+1 847 793 0310",
    "sg:postcode":"60069",
    "sg:province":"IL",
    "sg:tags":[
        "building",
        "apartment"
    ],
    "wof:name":"Lincolnshire Chalet Condo",
    "wof:placetype":"venue"
},
  "geometry": {"coordinates":[-87.94929,42.200286],"type":"Point"}
}