{
  "type": "Feature",
  "properties": {
    "addr:full":"8368 Grand Ave River Grove IL 60171",
    "addr:housenumber":"8368",
    "addr:postcode":"60171",
    "addr:street":"Grand Ave",
    "iso:country":"US",
    "sg:address":"8368 Grand Ave",
    "sg:city":"River Grove",
    "sg:classifiers":[
        {
            "category":"Health Services",
            "subcategory":"Dentist",
            "type":"Services"
        }
    ],
    "sg:phone":"+1 708 453 0500",
    "sg:postcode":"60171",
    "sg:province":"IL",
    "wof:name":"One Grand Smile",
    "wof:placetype":"venue"
},
  "geometry": {"coordinates":[-87.835503,41.9286],"type":"Point"}
}