{
  "type": "Feature",
  "properties": {
    "iso:country":"US",
    "sg:address":"2030 W Illinois Ave",
    "sg:city":"Aurora",
    "sg:classifiers":[
        {
            "category":"Freight",
            "type":"Transportation"
        }
    ],
    "sg:phone":"+1 630 215 9420",
    "sg:postcode":"60506",
    "sg:province":"IL",
    "sg:tags":[
        "operator",
        "trucking"
    ],
    "wof:name":"USA Expediting",
    "wof:placetype":"venue"
},
  "geometry": {"coordinates":[-88.363068,41.769941],"type":"Point"}
}