{
  "type": "Feature",
  "properties": {
    "addr:full":"3154 183rd St Homewood IL 60430",
    "addr:housenumber":"3154",
    "addr:postcode":"60430",
    "addr:street":"183Rd St",
    "iso:country":"US",
    "sg:address":"3154 183rd St",
    "sg:city":"Homewood",
    "sg:classifiers":[
        {
            "category":"Food & Beverages",
            "subcategory":"Groceries & Convenience Stores",
            "type":"Retail Goods"
        }
    ],
    "sg:phone":"+1 708 957 3611",
    "sg:postcode":"60430",
    "sg:province":"IL",
    "wof:name":"7-Eleven",
    "wof:placetype":"venue"
},
  "geometry": {"coordinates":[-87.690969,41.557251],"type":"Point"}
}