{
  "type": "Feature",
  "properties": {
    "iso:country":"US",
    "sg:address":"300 W Lake St",
    "sg:city":"Elmhurst",
    "sg:classifiers":[
        {
            "category":"Social Services",
            "type":"Services"
        }
    ],
    "sg:phone":"+1 630 530 1100",
    "sg:postcode":"60126",
    "sg:province":"IL",
    "wof:name":"Eisner Michael Msw Lcsw",
    "wof:placetype":"venue"
},
  "geometry": {"coordinates":[-87.948849,41.917259],"type":"Point"}
}