{
  "type": "Feature",
  "properties": {
    "addr:full":"3511 N Harlem Ave Chicago IL 60634",
    "addr:housenumber":"3511",
    "addr:postcode":"60634",
    "addr:street":"N Harlem Ave",
    "iso:country":"US",
    "sg:address":"3511 N Harlem Ave",
    "sg:city":"Chicago",
    "sg:classifiers":[
        {
            "category":"Retail",
            "subcategory":"Auto Repair",
            "type":"Services"
        }
    ],
    "sg:phone":"+1 773 283 2292",
    "sg:postcode":"60634",
    "sg:province":"IL",
    "sg:tags":[
        "body",
        "shop",
        "classic",
        "automobile",
        "painting",
        "repairing",
        "restoration-antique"
    ],
    "wof:name":"Precision Auto Body",
    "wof:placetype":"venue"
},
  "geometry": {"coordinates":[-87.806999,41.944302],"type":"Point"}
}