{
  "type": "Feature",
  "properties": {
    "iso:country":"US",
    "sg:address":"510 W 5th St",
    "sg:city":"Tilton",
    "sg:classifiers":[
        {
            "category":"Freight",
            "type":"Transportation"
        }
    ],
    "sg:phone":"+1 217 446 0207",
    "sg:postcode":"61833",
    "sg:province":"IL",
    "sg:tags":[
        "trucking"
    ],
    "wof:name":"Daniel L Ribbe Trucking Inc",
    "wof:placetype":"venue"
},
  "geometry": {"coordinates":[-87.653593,40.101504],"type":"Point"}
}