{
  "type": "Feature",
  "properties": {
    "iso:country":"US",
    "sg:address":"1001 S Chicago St",
    "sg:city":"Geneseo",
    "sg:classifiers":[
        {
            "category":"Social Services",
            "type":"Services"
        }
    ],
    "sg:phone":"+1 309 944 2843",
    "sg:postcode":"61254",
    "sg:province":"IL",
    "sg:tags":[
        "youth",
        "organization",
        "center"
    ],
    "wof:name":"Bollen Field Concession",
    "wof:placetype":"venue"
},
  "geometry": {"coordinates":[-90.144141,41.439733],"type":"Point"}
}