{
  "type": "Feature",
  "properties": {
    "iso:country":"US",
    "sg:address":"6701 S Archer Rd",
    "sg:city":"Summit Argo",
    "sg:classifiers":[
        {
            "category":"Building & Trades",
            "subcategory":"Construction",
            "type":"Services"
        }
    ],
    "sg:phone":"+1 708 458 2158",
    "sg:postcode":"60501",
    "sg:province":"IL",
    "sg:tags":[
        "marking",
        "maintenance",
        "parking"
    ],
    "wof:name":"Bedford Park Public Works",
    "wof:placetype":"venue"
},
  "geometry": {"coordinates":[-87.815185,41.775192],"type":"Point"}
}