{
  "type": "Feature",
  "properties": {
    "iso:country":"US",
    "sg:address":"13477 N 400th St",
    "sg:city":"Wheeler",
    "sg:classifiers":[
        {
            "category":"Farming",
            "subcategory":"Dairy Farm",
            "type":"Manufacturing & Wholesale Goods"
        }
    ],
    "sg:phone":"+1 217 925 5626",
    "sg:postcode":"62479",
    "sg:province":"IL",
    "sg:tags":[
        "corn",
        "wheat",
        "soybean"
    ],
    "wof:name":"Lidy Dairy & Hogs",
    "wof:placetype":"venue"
},
  "geometry": {"coordinates":[-88.298093,39.043513],"type":"Point"}
}