{
  "type": "Feature",
  "properties": {
    "addr:full":"5711 S Western Ave Chicago IL 60636",
    "addr:housenumber":"5711",
    "addr:postcode":"60636",
    "addr:street":"S Western Ave",
    "iso:country":"US",
    "sg:address":"5711 S Western Ave",
    "sg:city":"Chicago",
    "sg:phone":"+1 773 476 3390",
    "sg:postcode":"60636",
    "sg:province":"IL",
    "wof:name":"Att Media Svc",
    "wof:placetype":"venue"
},
  "geometry": {"coordinates":[-87.683939,41.789896],"type":"Point"}
}