{
  "type": "Feature",
  "properties": {
    "iso:country":"US",
    "sg:address":"520 Burnt Ember Ln",
    "sg:city":"Buffalo Grove",
    "sg:classifiers":[
        {
            "category":"Professional",
            "subcategory":"Management & Consulting",
            "type":"Services"
        }
    ],
    "sg:phone":"+1 847 541 3594",
    "sg:postcode":"60089",
    "sg:province":"IL",
    "wof:name":"Myer Paul J & Assoc",
    "wof:placetype":"venue"
},
  "geometry": {"coordinates":[-87.98045500000001,42.161046],"type":"Point"}
}