{
  "type": "Feature",
  "properties": {
    "addr:full":"1851 S Main St Jacksonville IL 62650",
    "addr:housenumber":"1851",
    "addr:postcode":"62650",
    "addr:street":"S Main St",
    "iso:country":"US",
    "sg:address":"1851 S Main St",
    "sg:city":"Jacksonville",
    "sg:classifiers":[
        {
            "category":"Shopping",
            "subcategory":"Gifts & Souvenirs",
            "type":"Retail Goods"
        }
    ],
    "sg:phone":"+1 217 243 2005",
    "sg:postcode":"62650",
    "sg:province":"IL",
    "sg:tags":[
        "shop"
    ],
    "wof:name":"Family Gardens",
    "wof:placetype":"venue"
},
  "geometry": {"coordinates":[-90.229311,39.707703],"type":"Point"}
}