{
  "type": "Feature",
  "properties": {
    "iso:country":"US",
    "sg:address":"6060 Alessandra Dr",
    "sg:city":"Matteson",
    "sg:classifiers":[
        {
            "category":"Building & Trades",
            "subcategory":"Electrical",
            "type":"Services"
        }
    ],
    "sg:phone":"+1 708 720 1290",
    "sg:postcode":"60443",
    "sg:province":"IL",
    "sg:tags":[
        "electrician"
    ],
    "wof:name":"Val & Ced Enterprise",
    "wof:placetype":"venue"
},
  "geometry": {"coordinates":[-87.761314,41.500914],"type":"Point"}
}