{
  "type": "Feature",
  "properties": {
    "iso:country":"US",
    "sg:address":"1315 N Latrobe Ave",
    "sg:city":"Chicago",
    "sg:classifiers":[
        {
            "category":"Social Services",
            "subcategory":"Child Care",
            "type":"Services"
        }
    ],
    "sg:phone":"+1 773 287 8391",
    "sg:postcode":"60651",
    "sg:province":"IL",
    "sg:tags":[
        "day"
    ],
    "wof:name":"Djs Daycare",
    "wof:placetype":"venue"
},
  "geometry": {"coordinates":[-87.75703300000001,41.904954],"type":"Point"}
}