{
  "type": "Feature",
  "properties": {
    "addr:full":"1015 N Plum Grove Rd Palatine IL 60067",
    "addr:housenumber":"1015",
    "addr:postcode":"60067",
    "addr:street":"N Plum Grove Rd",
    "iso:country":"US",
    "sg:address":"1015 N Plum Grove Rd",
    "sg:city":"Palatine",
    "sg:classifiers":[
        {
            "category":"Education",
            "subcategory":"School",
            "type":"Public Place"
        }
    ],
    "sg:phone":"+1 847 705 9206",
    "sg:postcode":"60067",
    "sg:province":"IL",
    "wof:name":"Cila",
    "wof:placetype":"venue"
},
  "geometry": {"coordinates":[-88.043695,42.131716],"type":"Point"}
}