{
  "type": "Feature",
  "properties": {
    "iso:country":"US",
    "sg:address":"2727 S Poplar Avenue",
    "sg:city":"Chicago",
    "sg:classifiers":[
        {
            "category":"Food & Beverages",
            "subcategory":"Groceries & Convenience Stores",
            "type":"Retail Goods"
        }
    ],
    "sg:phone":"+1 312 808 0311",
    "sg:postcode":"60608",
    "sg:province":"IL",
    "wof:name":"Little Market",
    "wof:placetype":"venue"
},
  "geometry": {"coordinates":[-87.65118699999999,41.843204],"type":"Point"}
}