{
  "type": "Feature",
  "properties": {
    "iso:country":"US",
    "sg:address":"1255 Elder Rd",
    "sg:city":"Homewood",
    "sg:classifiers":[
        {
            "category":"Building & Trades",
            "subcategory":"Construction",
            "type":"Services"
        }
    ],
    "sg:phone":"+1 708 259 5177",
    "sg:postcode":"60430",
    "sg:province":"IL",
    "sg:tags":[
        "house"
    ],
    "wof:name":"Honeydo Home Repair Mntnc",
    "wof:placetype":"venue"
},
  "geometry": {"coordinates":[-87.647534,41.558223],"type":"Point"}
}