{
  "type": "Feature",
  "properties": {
    "iso:country":"US",
    "sg:address":"597 W Exchange St",
    "sg:city":"Crete",
    "sg:classifiers":[
        {
            "category":"Shopping",
            "subcategory":"Gifts & Souvenirs",
            "type":"Retail Goods"
        }
    ],
    "sg:phone":"+1   ",
    "sg:postcode":"60417",
    "sg:province":"IN",
    "wof:name":"Front Gate",
    "wof:placetype":"venue"
},
  "geometry": {"coordinates":[-87.636089,41.444349],"type":"Point"}
}