{
  "type": "Feature",
  "properties": {
    "addr:full":"6130 W Ardmore Ave Chicago IL 60646",
    "addr:housenumber":"6130",
    "addr:postcode":"60646",
    "addr:street":"W Ardmore Ave",
    "iso:country":"US",
    "sg:address":"6130 W Ardmore Ave",
    "sg:city":"Chicago",
    "sg:classifiers":[
        {
            "category":"Home & Garden",
            "subcategory":"Building Materials",
            "type":"Retail Goods"
        },
        {
            "category":"Building & Trades",
            "subcategory":"Construction",
            "type":"Services"
        },
        {
            "category":"Manufacturing",
            "subcategory":"Building Materials",
            "type":"Manufacturing & Wholesale Goods"
        }
    ],
    "sg:phone":"+1 312 226 4949",
    "sg:postcode":"60646",
    "sg:province":"IL",
    "sg:tags":[
        "door",
        "fence",
        "specialty",
        "contractor",
        "garage",
        "opener",
        "doors",
        "frames",
        "gate",
        "accessory",
        "fence-sales"
    ],
    "sg:website":"http://rpmgaragedoor.com/",
    "wof:name":"RPM Garage Door & Gate Service Inc",
    "wof:placetype":"venue"
},
  "geometry": {"coordinates":[-87.78148299999999,41.9865],"type":"Point"}
}