{
  "type": "Feature",
  "properties": {
    "iso:country":"US",
    "sg:address":"2723 N Clark St",
    "sg:city":"Chicago",
    "sg:classifiers":[
        {
            "category":"Restaurant",
            "type":"Food & Drink"
        }
    ],
    "sg:phone":"+1 773 868 4888",
    "sg:postcode":"60614",
    "sg:province":"IL",
    "sg:tags":[
        "vietnamese"
    ],
    "sg:website":"www.haiyenrestaurant.com",
    "wof:name":"Hai Yen Restaurant",
    "wof:placetype":"venue"
},
  "geometry": {"coordinates":[-87.644524,41.932148],"type":"Point"}
}