{
  "type": "Feature",
  "properties": {
    "iso:country":"US",
    "sg:address":"511 Chicago Ridge Mall",
    "sg:city":"Chicago Ridge",
    "sg:classifiers":[
        {
            "category":"Shopping",
            "subcategory":"Clothing, Apparel, & Fashions",
            "type":"Retail Goods"
        }
    ],
    "sg:phone":"+1 708 229 9763",
    "sg:postcode":"60415",
    "sg:province":"IL",
    "sg:tags":[
        "children's",
        "clothing"
    ],
    "sg:website":"www.gymboree.com",
    "wof:name":"Gymboree",
    "wof:placetype":"venue"
},
  "geometry": {"coordinates":[-87.784103,41.714699],"type":"Point"}
}