{
  "type": "Feature",
  "properties": {
    "addr:full":"3301 W 65th Pl Chicago IL 60629",
    "addr:housenumber":"3301",
    "addr:postcode":"60629",
    "addr:street":"W 65Th Pl",
    "iso:country":"US",
    "sg:address":"3301 W 65th Pl",
    "sg:city":"Chicago",
    "sg:classifiers":[
        {
            "category":"Building & Trades",
            "subcategory":"Landscaping Services",
            "type":"Services"
        }
    ],
    "sg:phone":"+1 773 776 9160",
    "sg:postcode":"60629",
    "sg:province":"IL",
    "sg:tags":[
        "lawn"
    ],
    "wof:name":"Divine Custom Landscape Co",
    "wof:placetype":"venue"
},
  "geometry": {"coordinates":[-87.705437,41.774361],"type":"Point"}
}