{
  "type": "Feature",
  "properties": {
    "addr:full":"4421 N Austin Chicago IL 60630",
    "addr:housenumber":"4421",
    "addr:postcode":"60630",
    "addr:street":"N",
    "iso:country":"US",
    "sg:address":"4421 N Austin",
    "sg:city":"Chicago",
    "sg:classifiers":[
        {
            "category":"Professional",
            "subcategory":"Art Services",
            "type":"Services"
        }
    ],
    "sg:phone":"+1 847 606 4187",
    "sg:postcode":"60630",
    "sg:province":"IL",
    "sg:tags":[
        "graphic",
        "design"
    ],
    "sg:website":"www.inadvertweb.com",
    "wof:name":"Inadvert",
    "wof:placetype":"venue"
},
  "geometry": {"coordinates":[-87.776595,41.960964],"type":"Point"}
}