{
  "type": "Feature",
  "properties": {
    "addr:full":"5336 W 124th St Alsip IL 60803",
    "addr:housenumber":"5336",
    "addr:postcode":"60803",
    "addr:street":"W 124Th St",
    "iso:country":"US",
    "sg:address":"5336 W 124th St",
    "sg:city":"Alsip",
    "sg:classifiers":[
        {
            "category":"Manufacturing",
            "subcategory":"Chemicals & Compounds",
            "type":"Manufacturing & Wholesale Goods"
        },
        {
            "category":"Animal Shelter",
            "type":"Public Place"
        },
        {
            "category":"Building & Trades",
            "subcategory":"Pest Control",
            "type":"Services"
        }
    ],
    "sg:phone":"+1 866 574 1660",
    "sg:postcode":"60803",
    "sg:province":"IL",
    "sg:tags":[
        "industrial",
        "supply",
        "services-commercial",
        "termite",
        "bee",
        "equipment",
        "mothproofing",
        "removal"
    ],
    "sg:website":"http://signup.orkin.com/orkin/res/fun-Standard-pph_pcb_tph_tsch.aspx?cm_mmc=yahoo-yellowpages-_-yahoo-local-_-WEBYL-_-_&utm_source=yahoo-yellowpages&utm_content=yahoo-local&utm_medium=internet-yellow-pages&utm_campaign=WEBYL",
    "wof:name":"Orkin Pest & Termite Control",
    "wof:placetype":"venue"
},
  "geometry": {"coordinates":[-87.751895,41.667271],"type":"Point"}
}