{
  "type": "Feature",
  "properties": {
    "addr:full":"10227 Lincoln Trl Fairview Heights IL 62208",
    "addr:housenumber":"10227",
    "addr:postcode":"62208",
    "addr:street":"Lincoln Trl",
    "iso:country":"US",
    "sg:address":"10227 Lincoln Trl",
    "sg:city":"Fairview Heights",
    "sg:classifiers":[
        {
            "category":"Personal",
            "subcategory":"Beauty Salon",
            "type":"Services"
        }
    ],
    "sg:phone":"+1 618 394 0710",
    "sg:postcode":"62208",
    "sg:province":"IL",
    "wof:name":"D-Styles Studio",
    "wof:placetype":"venue"
},
  "geometry": {"coordinates":[-90.009109,38.593185],"type":"Point"}
}