{
  "type": "Feature",
  "properties": {
    "addr:full":"4389 Venture Dr Peru IL 61354",
    "addr:housenumber":"4389",
    "addr:postcode":"61354",
    "addr:street":"Venture Dr",
    "iso:country":"US",
    "sg:address":"4389 Venture Dr",
    "sg:city":"Peru",
    "sg:classifiers":[
        {
            "category":"Travel",
            "subcategory":"Hotels & Motels",
            "type":"Entertainment"
        }
    ],
    "sg:phone":"+1 815 224 9000",
    "sg:postcode":"61354",
    "sg:province":"IL",
    "sg:tags":[
        "corporate",
        "lodging"
    ],
    "sg:website":"http://redirect.searchignite.com/si/cm/tracking/DGTrackingRedirect.aspx?siclientid=2537&siredirect=http%3A%2F%2Fwww%2Elq%2Ecom%2Flq%2Fproperties%2FpropertyProfile%2Edo%3Fident%3DLQ743%26IATA%3D99020726%26WT%2Esrch%3D1&sisearchengine=155&siproduct=LQ+Peru",
    "wof:name":"La Quinta Inn Peru",
    "wof:placetype":"venue"
},
  "geometry": {"coordinates":[-89.12911200000001,41.363237],"type":"Point"}
}