{
  "type": "Feature",
  "properties": {
    "addr:full":"4329 W Grand Ave Chicago IL 60651",
    "addr:housenumber":"4329",
    "addr:postcode":"60651",
    "addr:street":"W Grand Ave",
    "iso:country":"US",
    "sg:address":"4329 W Grand Ave",
    "sg:city":"Chicago",
    "sg:classifiers":[
        {
            "category":"Autos & Motor Vehicles",
            "subcategory":"Fuel & Gas Station",
            "type":"Retail Goods"
        }
    ],
    "sg:phone":"+1   ",
    "sg:postcode":"60651",
    "sg:province":"IL",
    "sg:tags":[
        "station",
        "gasoline"
    ],
    "wof:name":"Pavon Service Station",
    "wof:placetype":"venue"
},
  "geometry": {"coordinates":[-87.73324,41.908733],"type":"Point"}
}