{
  "type": "Feature",
  "properties": {
    "addr:full":"1588 Naperville Wheaton Rd Naperville IL 60563",
    "addr:housenumber":"1588",
    "addr:postcode":"60563",
    "addr:street":"Wheaton Rd",
    "iso:country":"US",
    "sg:address":"1588 Naperville Wheaton Rd",
    "sg:city":"Naperville",
    "sg:classifiers":[
        {
            "category":"Restaurant",
            "type":"Food & Drink"
        }
    ],
    "sg:phone":"+1 630 548 2333",
    "sg:postcode":"60563",
    "sg:province":"IL",
    "sg:tags":[
        "house",
        "steak",
        "italian"
    ],
    "wof:name":"Buona Beef Restaurant",
    "wof:placetype":"venue"
},
  "geometry": {"coordinates":[-88.121647,41.797069],"type":"Point"}
}