{
  "type": "Feature",
  "properties": {
    "addr:full":"5320 N Sheridan Road Ofc Chicago IL 60640",
    "addr:housenumber":"5320",
    "addr:postcode":"60640",
    "addr:street":"N Sheridan Road",
    "iso:country":"US",
    "sg:address":"5320 N Sheridan Road Ofc",
    "sg:city":"Chicago",
    "sg:classifiers":[
        {
            "category":"Real Estate",
            "subcategory":"Real Estate Services",
            "type":"Services"
        }
    ],
    "sg:phone":"+1 773 334 7005",
    "sg:postcode":"60640",
    "sg:province":"IL",
    "sg:tags":[
        "management",
        "property"
    ],
    "wof:name":"Briarwood Management",
    "wof:placetype":"venue"
},
  "geometry": {"coordinates":[-87.65507100000001,41.978741],"type":"Point"}
}