{
  "type": "Feature",
  "properties": {
    "addr:full":"2625 S 21st Ave Broadview IL 60155",
    "addr:housenumber":"2625",
    "addr:postcode":"60155",
    "addr:street":"S 21St Ave",
    "iso:country":"US",
    "sg:address":"2625 S 21st Ave",
    "sg:city":"Broadview",
    "sg:classifiers":[
        {
            "category":"Manufacturing",
            "subcategory":"Metals",
            "type":"Manufacturing & Wholesale Goods"
        }
    ],
    "sg:phone":"+1 708 681 1920",
    "sg:postcode":"60155",
    "sg:province":"IL",
    "sg:tags":[
        "concrete",
        "metalwork",
        "sheet",
        "mfg"
    ],
    "wof:name":"Pate Co",
    "wof:placetype":"venue"
},
  "geometry": {"coordinates":[-87.85754,41.85459],"type":"Point"}
}