{
  "type": "Feature",
  "properties": {
    "addr:full":"8911 Odell Ave Bridgeview IL 60455",
    "addr:housenumber":"8911",
    "addr:postcode":"60455",
    "addr:street":"Odell Ave",
    "iso:country":"US",
    "sg:address":"8911 Odell Ave",
    "sg:city":"Bridgeview",
    "sg:classifiers":[
        {
            "category":"Manufacturing",
            "subcategory":"Tools & Machinery",
            "type":"Manufacturing & Wholesale Goods"
        }
    ],
    "sg:phone":"+1 708 599 5745",
    "sg:postcode":"60455",
    "sg:province":"IL",
    "sg:tags":[
        "shop",
        "industrial",
        "mfg",
        "m",
        "accessory",
        "machine"
    ],
    "wof:name":"A R Tech & Tool Inc",
    "wof:placetype":"venue"
},
  "geometry": {"coordinates":[-87.802493,41.729128],"type":"Point"}
}