{
  "type": "Feature",
  "properties": {
    "addr:full":"4214 W 26th Street Chicago IL 60623",
    "addr:housenumber":"4214",
    "addr:postcode":"60623",
    "addr:street":"W 26Th Street",
    "iso:country":"US",
    "sg:address":"4214 W 26th Street",
    "sg:city":"Chicago",
    "sg:classifiers":[
        {
            "category":"Restaurant",
            "type":"Food & Drink"
        }
    ],
    "sg:phone":"+1 773 277 4908",
    "sg:postcode":"60623",
    "sg:province":"IL",
    "wof:name":"Villa Delmar",
    "wof:placetype":"venue"
},
  "geometry": {"coordinates":[-87.72988700000001,41.844183],"type":"Point"}
}