{
  "type": "Feature",
  "properties": {
    "addr:full":"414 S 2nd Ave Maywood IL 60153",
    "addr:housenumber":"414",
    "addr:postcode":"60153",
    "addr:street":"S 2Nd Ave",
    "iso:country":"US",
    "sg:address":"414 S 2nd Ave",
    "sg:city":"Maywood",
    "sg:classifiers":[
        {
            "category":"Social Services",
            "subcategory":"Child Care",
            "type":"Services"
        }
    ],
    "sg:phone":"+1 708 345 5335",
    "sg:postcode":"60153",
    "sg:province":"IL",
    "sg:tags":[
        "day"
    ],
    "wof:name":"Tweedy Home Day Care",
    "wof:placetype":"venue"
},
  "geometry": {"coordinates":[-87.835472,41.883683],"type":"Point"}
}