{
  "type": "Feature",
  "properties": {
    "iso:country":"US",
    "sg:address":"858 W 33rd St",
    "sg:city":"Chicago",
    "sg:classifiers":[
        {
            "category":"Food & Beverages",
            "subcategory":"Groceries & Convenience Stores",
            "type":"Retail Goods"
        }
    ],
    "sg:phone":"+1 773 247 6388",
    "sg:postcode":"60608",
    "sg:province":"IL",
    "wof:name":"MS Grocery",
    "wof:placetype":"venue"
},
  "geometry": {"coordinates":[-87.648415,41.834974],"type":"Point"}
}