{
  "type": "Feature",
  "properties": {
    "iso:country":"US",
    "sg:address":"Rush University Medical Center 1725 W Harrison St, Ste 264",
    "sg:city":"Chicago",
    "sg:classifiers":[
        {
            "category":"Health Services",
            "subcategory":"Doctor",
            "type":"Services"
        }
    ],
    "sg:phone":"+1 312 942 2195",
    "sg:postcode":"60612",
    "sg:province":"IL",
    "sg:tags":[
        "dermatologist"
    ],
    "wof:name":"Vassilios A. Dimitropoulos, MD",
    "wof:placetype":"venue"
},
  "geometry": {"coordinates":[-87.670045,41.87413],"type":"Point"}
}