{
  "type": "Feature",
  "properties": {
    "iso:country":"US",
    "sg:address":"1701 Crossroads Dr",
    "sg:city":"Joliet",
    "sg:classifiers":[
        {
            "category":"Wholesale",
            "subcategory":"Stationery",
            "type":"Manufacturing & Wholesale Goods"
        }
    ],
    "sg:phone":"+1 630 227 4600",
    "sg:postcode":"60431",
    "sg:province":"IL",
    "sg:tags":[
        "personal",
        "industrial",
        "paper"
    ],
    "wof:name":"Unisource Worldwide Inc",
    "wof:placetype":"venue"
},
  "geometry": {"coordinates":[-88.182457,41.492603],"type":"Point"}
}