{
  "type": "Feature",
  "properties": {
    "iso:country":"US",
    "sg:address":"1458 W Belmont Ave",
    "sg:city":"Chicago",
    "sg:classifiers":[
        {
            "category":"Retail",
            "subcategory":"Funeral Services",
            "type":"Services"
        }
    ],
    "sg:phone":"+1 773 883 0010",
    "sg:postcode":"60657",
    "sg:province":"IL",
    "sg:tags":[
        "cemetery"
    ],
    "wof:name":"Apollo Cremation Service",
    "wof:placetype":"venue"
},
  "geometry": {"coordinates":[-87.6661,41.9398],"type":"Point"}
}