{
  "type": "Feature",
  "properties": {
    "iso:country":"US",
    "sg:address":"9250 S Harlem Ave",
    "sg:city":"Bridgeview",
    "sg:classifiers":[
        {
            "category":"Food & Beverages",
            "subcategory":"Groceries & Convenience Stores",
            "type":"Retail Goods"
        }
    ],
    "sg:phone":"+1 708 233 0044",
    "sg:postcode":"60455",
    "sg:province":"IL",
    "wof:name":"Harlem Foods Incorporated",
    "wof:placetype":"venue"
},
  "geometry": {"coordinates":[-87.798698,41.7234],"type":"Point"}
}