{
  "type": "Feature",
  "properties": {
    "addr:full":"405 Randolph Dr Centralia IL 62801",
    "addr:housenumber":"405",
    "addr:postcode":"62801",
    "addr:street":"Randolph Dr",
    "iso:country":"US",
    "sg:address":"405 Randolph Dr",
    "sg:city":"Centralia",
    "sg:classifiers":[
        {
            "category":"Shopping",
            "subcategory":"Computers & Home Electronics",
            "type":"Retail Goods"
        }
    ],
    "sg:phone":"+1   ",
    "sg:postcode":"62801",
    "sg:province":"IL",
    "wof:name":"Cyber Byte Computing",
    "wof:placetype":"venue"
},
  "geometry": {"coordinates":[-89.160051,38.52575],"type":"Point"}
}