{
  "type": "Feature",
  "properties": {
    "iso:country":"US",
    "sg:address":"2200 Hicks Rd",
    "sg:city":"Rolling Meadows",
    "sg:classifiers":[
        {
            "category":"Professional",
            "subcategory":"Lawyer & Legal Services",
            "type":"Services"
        }
    ],
    "sg:phone":"+1 847 506 8932",
    "sg:postcode":"60008",
    "sg:province":"IL",
    "wof:name":"Sullivan & Sullivan",
    "wof:placetype":"venue"
},
  "geometry": {"coordinates":[-88.03404,42.088131],"type":"Point"}
}