{
  "type": "Feature",
  "properties": {
    "addr:full":"1845 E Rand Rd Arlington Hts IL 60004",
    "addr:housenumber":"1845",
    "addr:postcode":"60004",
    "addr:street":"E Rand Rd",
    "iso:country":"US",
    "sg:address":"1845 E Rand Rd",
    "sg:city":"Arlington Hts",
    "sg:classifiers":[
        {
            "category":"Building & Trades",
            "subcategory":"Construction",
            "type":"Services"
        }
    ],
    "sg:phone":"+1 847 342 9999",
    "sg:postcode":"60004",
    "sg:province":"IL",
    "sg:tags":[
        "concrete",
        "contractor"
    ],
    "wof:name":"All Shield Concrete Guard Inc",
    "wof:placetype":"venue"
},
  "geometry": {"coordinates":[-87.957391,42.097175],"type":"Point"}
}