{
  "type": "Feature",
  "properties": {
    "iso:country":"US",
    "sg:address":"158 N Edison Ave",
    "sg:city":"Elgin",
    "sg:classifiers":[
        {
            "category":"Health Services",
            "subcategory":"Chiropractor",
            "type":"Services"
        }
    ],
    "sg:phone":"+1 847 741 3650",
    "sg:postcode":"60123",
    "sg:province":"IL",
    "sg:tags":[
        "chiropractic"
    ],
    "wof:name":"Zenith Chiropratic Equip.",
    "wof:placetype":"venue"
},
  "geometry": {"coordinates":[-88.304498,42.037172],"type":"Point"}
}