{
  "type": "Feature",
  "properties": {
    "iso:country":"US",
    "sg:address":"2817 N Burling St",
    "sg:city":"Chicago",
    "sg:classifiers":[
        {
            "category":"Professional",
            "type":"Services"
        }
    ],
    "sg:phone":"+1 773 348 9554",
    "sg:postcode":"60657",
    "sg:province":"IL",
    "sg:tags":[
        "literary",
        "writer",
        "agent"
    ],
    "sg:website":"http://www.wordsofmouth.com",
    "wof:name":"Words Of Mouth",
    "wof:placetype":"venue"
},
  "geometry": {"coordinates":[-87.64764,41.932884],"type":"Point"}
}