{
  "type": "Feature",
  "properties": {
    "iso:country":"US",
    "sg:address":"121 Stablestone Dr",
    "sg:city":"Belleville",
    "sg:classifiers":[
        {
            "category":"Building & Trades",
            "subcategory":"Construction",
            "type":"Services"
        }
    ],
    "sg:phone":"+1 618 234 4778",
    "sg:postcode":"62221",
    "sg:province":"IL",
    "sg:tags":[
        "general",
        "contractor"
    ],
    "wof:name":"Country Crossing Clubhouse",
    "wof:placetype":"venue"
},
  "geometry": {"coordinates":[-89.946628,38.545026],"type":"Point"}
}