{
  "type": "Feature",
  "properties": {
    "addr:full":"845 N Lake St Ste 2 Aurora IL 60506",
    "addr:housenumber":"845",
    "addr:postcode":"60506",
    "addr:street":"N Lake St Ste 2",
    "iso:country":"US",
    "sg:address":"845 N Lake St Ste 2",
    "sg:city":"Aurora",
    "sg:classifiers":[
        {
            "category":"Autos & Motor Vehicles",
            "subcategory":"Auto Supplies",
            "type":"Retail Goods"
        }
    ],
    "sg:phone":"+1 630 264 4320",
    "sg:postcode":"60506",
    "sg:province":"IL",
    "sg:tags":[
        "automobile",
        "stereo",
        "radio",
        "system"
    ],
    "wof:name":"Gorilla Sound",
    "wof:placetype":"venue"
},
  "geometry": {"coordinates":[-88.314542,41.774786],"type":"Point"}
}