{
  "type": "Feature",
  "properties": {
    "addr:full":"375 E Locust St Columbia IL 62236",
    "addr:housenumber":"375",
    "addr:postcode":"62236",
    "addr:street":"E Locust St",
    "iso:country":"US",
    "sg:address":"375 E Locust St",
    "sg:city":"Columbia",
    "sg:classifiers":[
        {
            "category":"Organizations",
            "subcategory":"Community Association",
            "type":"Services"
        }
    ],
    "sg:phone":"+1 618 281 5556",
    "sg:postcode":"62236",
    "sg:province":"IL",
    "sg:tags":[
        "military"
    ],
    "wof:name":"American Legion",
    "wof:placetype":"venue"
},
  "geometry": {"coordinates":[-90.198696,38.445244],"type":"Point"}
}