{
  "type": "Feature",
  "properties": {
    "addr:full":"3105 W Jefferson St Joliet IL 60435",
    "addr:housenumber":"3105",
    "addr:postcode":"60435",
    "addr:street":"W Jefferson St",
    "iso:country":"US",
    "sg:address":"3105 W Jefferson St",
    "sg:city":"Joliet",
    "sg:classifiers":[
        {
            "category":"Shopping",
            "subcategory":"Books",
            "type":"Retail Goods"
        }
    ],
    "sg:phone":"+1 815 729 2400",
    "sg:postcode":"60435",
    "sg:province":"IL",
    "sg:tags":[
        "dealer"
    ],
    "sg:website":"www.familychristian.com",
    "wof:name":"Family Christian Book Store",
    "wof:placetype":"venue"
},
  "geometry": {"coordinates":[-88.156954,41.52191],"type":"Point"}
}