{
  "type": "Feature",
  "properties": {
    "addr:full":"239 S Greenwood Ave Kankakee IL 60901",
    "addr:housenumber":"239",
    "addr:postcode":"60901",
    "addr:street":"S Greenwood Ave",
    "iso:country":"US",
    "sg:address":"239 S Greenwood Ave",
    "sg:city":"Kankakee",
    "sg:classifiers":[
        {
            "category":"Education",
            "subcategory":"School",
            "type":"Public Place"
        }
    ],
    "sg:phone":"+1 815 933 4963",
    "sg:postcode":"60901",
    "sg:province":"IL",
    "wof:name":"National College Of Education",
    "wof:placetype":"venue"
},
  "geometry": {"coordinates":[-87.857393,41.117463],"type":"Point"}
}