{
  "type": "Feature",
  "properties": {
    "addr:full":"6046 Dempster St Morton Grove IL 60053",
    "addr:housenumber":"6046",
    "addr:postcode":"60053",
    "addr:street":"Dempster St",
    "iso:country":"US",
    "sg:address":"6046 Dempster St",
    "sg:city":"Morton Grove",
    "sg:classifiers":[
        {
            "category":"Health Services",
            "subcategory":"Doctor",
            "type":"Services"
        }
    ],
    "sg:phone":"+1 847 583 0250",
    "sg:postcode":"60053",
    "sg:province":"IL",
    "wof:name":"Antonio-Garcia Rowena",
    "wof:placetype":"venue"
},
  "geometry": {"coordinates":[-87.778683,42.040991],"type":"Point"}
}