{
  "type": "Feature",
  "properties": {
    "iso:country":"US",
    "sg:address":"555 Skokie Blvd",
    "sg:city":"Northbrook",
    "sg:classifiers":[
        {
            "category":"Farming",
            "subcategory":"Livestock Farm",
            "type":"Manufacturing & Wholesale Goods"
        },
        {
            "category":"Professional",
            "type":"Services"
        }
    ],
    "sg:phone":"+1 847 291 1431",
    "sg:postcode":"60062",
    "sg:province":"IL",
    "sg:tags":[
        "establishment",
        "equine"
    ],
    "wof:name":"H P Interests Inc",
    "wof:placetype":"venue"
},
  "geometry": {"coordinates":[-87.793386,42.14116],"type":"Point"}
}