{
  "type": "Feature",
  "properties": {
    "addr:full":"20180 Governors Hwy Olympia Fields IL 60461",
    "addr:housenumber":"20180",
    "addr:postcode":"60461",
    "addr:street":"Governors Hwy",
    "iso:country":"US",
    "sg:address":"20180 Governors Hwy",
    "sg:city":"Olympia Fields",
    "sg:classifiers":[
        {
            "category":"Wholesale",
            "subcategory":"Chemicals & Plastics",
            "type":"Manufacturing & Wholesale Goods"
        }
    ],
    "sg:phone":"+1 708 747 8664",
    "sg:postcode":"60461",
    "sg:province":"IL",
    "wof:name":"Millennium",
    "wof:placetype":"venue"
},
  "geometry": {"coordinates":[-87.70204099999999,41.523516],"type":"Point"}
}