{
  "type": "Feature",
  "properties": {
    "addr:full":"227 W Wilson St Batavia IL 60510",
    "addr:housenumber":"227",
    "addr:postcode":"60510",
    "addr:street":"W Wilson St",
    "iso:country":"US",
    "sg:address":"227 W Wilson St",
    "sg:city":"Batavia",
    "sg:classifiers":[
        {
            "category":"Building & Trades",
            "subcategory":"Construction",
            "type":"Services"
        }
    ],
    "sg:phone":"+1 630 879 5212",
    "sg:postcode":"60510",
    "sg:province":"IL",
    "sg:tags":[
        "system",
        "specialty",
        "heating",
        "contractor",
        "air conditioning"
    ],
    "wof:name":"Hogan's, Ray Heating & Air Conditioning Inc",
    "wof:placetype":"venue"
},
  "geometry": {"coordinates":[-88.31088800000001,41.849958],"type":"Point"}
}