{
  "type": "Feature",
  "properties": {
    "iso:country":"US",
    "sg:address":"1629 N Damen Ave",
    "sg:city":"Chicago",
    "sg:classifiers":[
        {
            "category":"Shopping",
            "subcategory":"Clothing, Apparel, & Fashions",
            "type":"Retail Goods"
        }
    ],
    "sg:phone":"+1 773 772 7357",
    "sg:postcode":"60647",
    "sg:province":"IL",
    "sg:website":"www.bebe.com",
    "wof:name":"bebe",
    "wof:placetype":"venue"
},
  "geometry": {"coordinates":[-87.677255,41.911403],"type":"Point"}
}