{
  "type": "Feature",
  "properties": {
    "iso:country":"US",
    "sg:address":"405 Lake Cook Rd",
    "sg:city":"Deerfield",
    "sg:classifiers":[
        {
            "category":"Health Services",
            "subcategory":"Optometrist",
            "type":"Services"
        }
    ],
    "sg:phone":"+1 847 498 3737",
    "sg:postcode":"60015",
    "sg:province":"IL",
    "wof:name":"Doyle Opticians Of Deerfield",
    "wof:placetype":"venue"
},
  "geometry": {"coordinates":[-87.837373,42.152686],"type":"Point"}
}