{
  "type": "Feature",
  "properties": {
    "iso:country":"US",
    "sg:address":"1222 Lee St",
    "sg:city":"Des Plaines",
    "sg:classifiers":[
        {
            "category":"Autos & Motor Vehicles",
            "subcategory":"Fuel & Gas Station",
            "type":"Retail Goods"
        }
    ],
    "sg:phone":"+1 847 298 7351",
    "sg:postcode":"60018",
    "sg:province":"IL",
    "sg:tags":[
        "oil"
    ],
    "wof:name":"Checker Oil Co",
    "wof:placetype":"venue"
},
  "geometry": {"coordinates":[-87.894464,42.030504],"type":"Point"}
}