{
  "type": "Feature",
  "properties": {
    "addr:full":"611 N 4th St Chillicothe IL 61523",
    "addr:housenumber":"611",
    "addr:postcode":"61523",
    "addr:street":"N 4Th St",
    "iso:country":"US",
    "sg:address":"611 N 4th St",
    "sg:city":"Chillicothe",
    "sg:classifiers":[
        {
            "category":"Shopping",
            "subcategory":"Gifts & Souvenirs",
            "type":"Retail Goods"
        }
    ],
    "sg:phone":"+1   ",
    "sg:postcode":"61523",
    "sg:province":"IL",
    "wof:name":"Traditions",
    "wof:placetype":"venue"
},
  "geometry": {"coordinates":[-89.489637,40.914686],"type":"Point"}
}