{
  "type": "Feature",
  "properties": {
    "iso:country":"US",
    "sg:address":"16712 Liken Rd",
    "sg:city":"Geneseo",
    "sg:phone":"+1 309 944 2226",
    "sg:postcode":"61254",
    "sg:province":"IL",
    "sg:tags":[
        "farm",
        "corn",
        "soybean"
    ],
    "wof:name":"Fredric Magerkurth",
    "wof:placetype":"venue"
},
  "geometry": {"coordinates":[-90.187256,41.395866],"type":"Point"}
}