{
  "type": "Feature",
  "properties": {
    "iso:country":"US",
    "sg:address":"114 Buchanan St",
    "sg:city":"Carthage",
    "sg:classifiers":[
        {
            "category":"Wholesale",
            "subcategory":"Scrap",
            "type":"Manufacturing & Wholesale Goods"
        }
    ],
    "sg:phone":"+1 217 357 3891",
    "sg:postcode":"62321",
    "sg:province":"IL",
    "sg:tags":[
        "recycling",
        "center"
    ],
    "wof:name":"Disposal Pro Inc",
    "wof:placetype":"venue"
},
  "geometry": {"coordinates":[-91.14501199999999,40.41621],"type":"Point"}
}