{
  "type": "Feature",
  "properties": {
    "iso:country":"US",
    "sg:address":"3017 E 78th St",
    "sg:city":"Chicago",
    "sg:classifiers":[
        {
            "category":"Professional",
            "subcategory":"Management & Consulting",
            "type":"Services"
        }
    ],
    "sg:phone":"+1 773 933 6715",
    "sg:postcode":"60649",
    "sg:province":"IL",
    "wof:name":"Primaca Financial Services",
    "wof:placetype":"venue"
},
  "geometry": {"coordinates":[-87.551576,41.755274],"type":"Point"}
}