{
  "type": "Feature",
  "properties": {
    "iso:country":"US",
    "sg:address":"1624 N Kilbourn Avenue",
    "sg:city":"Chicago",
    "sg:classifiers":[
        {
            "category":"Building & Trades",
            "subcategory":"Construction",
            "type":"Services"
        }
    ],
    "sg:phone":"+1 773 772 2887",
    "sg:postcode":"60639",
    "sg:province":"IL",
    "sg:tags":[
        "contractor"
    ],
    "wof:name":"K Dl Builders",
    "wof:placetype":"venue"
},
  "geometry": {"coordinates":[-87.738395,41.910532],"type":"Point"}
}