{
  "type": "Feature",
  "properties": {
    "iso:country":"US",
    "sg:address":"18450 Waller Rd",
    "sg:city":"Fulton",
    "sg:classifiers":[
        {
            "category":"Retail",
            "subcategory":"Auto Repair",
            "type":"Services"
        }
    ],
    "sg:phone":"+1 815 589 2207",
    "sg:postcode":"61252",
    "sg:province":"IL",
    "sg:tags":[
        "general"
    ],
    "wof:name":"Premier Motor Solutions",
    "wof:placetype":"venue"
},
  "geometry": {"coordinates":[-90.15096,41.860664],"type":"Point"}
}