{
  "type": "Feature",
  "properties": {
    "iso:country":"US",
    "sg:address":"2263 N Main St",
    "sg:city":"Decatur",
    "sg:classifiers":[
        {
            "category":"Retail",
            "subcategory":"Car Wash",
            "type":"Services"
        }
    ],
    "sg:phone":"+1 217 433 9997",
    "sg:postcode":"62526",
    "sg:province":"IL",
    "wof:name":"Show Shop Pressure Wash",
    "wof:placetype":"venue"
},
  "geometry": {"coordinates":[-88.956376,39.866831],"type":"Point"}
}