{
  "type": "Feature",
  "properties": {
    "addr:full":"24635 S Walnut St Crete IN 60417",
    "addr:housenumber":"24635",
    "addr:postcode":"60417",
    "addr:street":"S Walnut St",
    "iso:country":"US",
    "sg:address":"24635 S Walnut St",
    "sg:city":"Crete",
    "sg:classifiers":[
        {
            "category":"Recreation",
            "type":"Entertainment"
        }
    ],
    "sg:phone":"+1 708 672 7874",
    "sg:postcode":"60417",
    "sg:province":"IN",
    "sg:tags":[
        "riding",
        "academy"
    ],
    "wof:name":"Alpha Royale Stable",
    "wof:placetype":"venue"
},
  "geometry": {"coordinates":[-87.56222200000001,41.442378],"type":"Point"}
}