{
  "type": "Feature",
  "properties": {
    "iso:country":"US",
    "sg:address":"130 W Fremont St",
    "sg:city":"West Chicago",
    "sg:classifiers":[
        {
            "category":"Fast Food",
            "type":"Food & Drink"
        },
        {
            "category":"Ice Cream",
            "type":"Food & Drink"
        }
    ],
    "sg:phone":"+1 630 231 3242",
    "sg:postcode":"60185",
    "sg:province":"IL",
    "sg:tags":[
        "frozen",
        "yogurt"
    ],
    "sg:website":"www.tastee-freez.com/",
    "wof:name":"Tastee Freez",
    "wof:placetype":"venue"
},
  "geometry": {"coordinates":[-88.205056,41.885108],"type":"Point"}
}