{
  "type": "Feature",
  "properties": {
    "addr:full":"2105 S China Pl Chicago IL 60616",
    "addr:housenumber":"2105",
    "addr:postcode":"60616",
    "addr:street":"S China Pl",
    "iso:country":"US",
    "sg:address":"2105 S China Pl",
    "sg:city":"Chicago",
    "sg:classifiers":[
        {
            "category":"Food & Beverages",
            "subcategory":"Liquor & Beverages",
            "type":"Retail Goods"
        }
    ],
    "sg:phone":"+1 312 225 8118",
    "sg:postcode":"60616",
    "sg:province":"IL",
    "sg:tags":[
        "beer",
        "spirit",
        "wine"
    ],
    "wof:name":"China Place Liquor City",
    "wof:placetype":"venue"
},
  "geometry": {"coordinates":[-87.632757,41.854669],"type":"Point"}
}