{
  "type": "Feature",
  "properties": {
    "addr:full":"3033 W Fletcher St Chicago IL 60618",
    "addr:housenumber":"3033",
    "addr:postcode":"60618",
    "addr:street":"W Fletcher St",
    "iso:country":"US",
    "sg:address":"3033 W Fletcher St",
    "sg:city":"Chicago",
    "sg:classifiers":[
        {
            "category":"Building & Trades",
            "subcategory":"Construction",
            "type":"Services"
        }
    ],
    "sg:phone":"+1 773 588 0001",
    "sg:postcode":"60618",
    "sg:province":"IL",
    "sg:tags":[
        "painter"
    ],
    "wof:name":"Ascher Brothers",
    "wof:placetype":"venue"
},
  "geometry": {"coordinates":[-87.70369700000001,41.938301],"type":"Point"}
}