{
  "type": "Feature",
  "properties": {
    "addr:full":"1144 N Main St Glendale Heights IL 60139",
    "addr:housenumber":"1144",
    "addr:postcode":"60139",
    "addr:street":"N Main St",
    "iso:country":"US",
    "sg:address":"1144 N Main St",
    "sg:city":"Glendale Heights",
    "sg:classifiers":[
        {
            "category":"Shopping",
            "subcategory":"Pets & Pet Supplies",
            "type":"Retail Goods"
        }
    ],
    "sg:phone":"+1 630 858 6900",
    "sg:postcode":"60139",
    "sg:province":"IL",
    "sg:tags":[
        "groomers"
    ],
    "wof:name":"Glendale Grooming Salon",
    "wof:placetype":"venue"
},
  "geometry": {"coordinates":[-88.106764,41.87661],"type":"Point"}
}