{
  "type": "Feature",
  "properties": {
    "addr:full":"12101 S Doty Ave Chicago IL 60633",
    "addr:housenumber":"12101",
    "addr:postcode":"60633",
    "addr:street":"S Doty Ave",
    "iso:country":"US",
    "sg:address":"12101 S Doty Ave",
    "sg:city":"Chicago",
    "sg:classifiers":[
        {
            "category":"Manufacturing",
            "subcategory":"Building Materials",
            "type":"Manufacturing & Wholesale Goods"
        }
    ],
    "sg:phone":"+1 773 995 5100",
    "sg:postcode":"60633",
    "sg:province":"IL",
    "sg:tags":[
        "cement"
    ],
    "wof:name":"Cemex Cement, Inc.",
    "wof:placetype":"venue"
},
  "geometry": {"coordinates":[-87.600723,41.674858],"type":"Point"}
}