{
  "type": "Feature",
  "properties": {
    "addr:full":"929 Maple Ave Downers Grove IL 60515",
    "addr:housenumber":"929",
    "addr:postcode":"60515",
    "addr:street":"Maple Ave",
    "iso:country":"US",
    "sg:address":"929 Maple Ave",
    "sg:city":"Downers Grove",
    "sg:classifiers":[
        {
            "category":"Education",
            "subcategory":"School",
            "type":"Public Place"
        }
    ],
    "sg:phone":"+1 630 852 0832",
    "sg:postcode":"60515",
    "sg:province":"IL",
    "sg:website":"www.dgchristian.org",
    "wof:name":"Downers Grove Christian School",
    "wof:placetype":"venue"
},
  "geometry": {"coordinates":[-88.00975200000001,41.791407],"type":"Point"}
}