{
  "type": "Feature",
  "properties": {
    "addr:full":"328 Williams St New Lenox IL 60476",
    "addr:housenumber":"328",
    "addr:postcode":"60476",
    "addr:street":"Williams St",
    "iso:country":"US",
    "sg:address":"328 Williams St",
    "sg:city":"New Lenox",
    "sg:classifiers":[
        {
            "category":"Professional",
            "type":"Services"
        }
    ],
    "sg:phone":"+1 815 462 0371",
    "sg:postcode":"60476",
    "sg:province":"IL",
    "sg:tags":[
        "establishment"
    ],
    "wof:name":"Hojnacki & Hojnacki",
    "wof:placetype":"venue"
},
  "geometry": {"coordinates":[-87.613569,41.571541],"type":"Point"}
}