{
  "type": "Feature",
  "properties": {
    "addr:full":"189 S Randall Rd Algonquin IL 60102",
    "addr:housenumber":"189",
    "addr:postcode":"60102",
    "addr:street":"S Randall Rd",
    "iso:country":"US",
    "sg:address":"189 S Randall Rd",
    "sg:city":"Algonquin",
    "sg:classifiers":[
        {
            "category":"Sports & Exercise",
            "subcategory":"Gym",
            "type":"Entertainment"
        },
        {
            "category":"Health Services",
            "subcategory":"Health Practitioner",
            "type":"Services"
        },
        {
            "category":"Arena",
            "subcategory":"Sports Club",
            "type":"Entertainment"
        }
    ],
    "sg:phone":"+1 847 658 1919",
    "sg:postcode":"60102",
    "sg:province":"IL",
    "sg:tags":[
        "nutritionist",
        "gymnasium"
    ],
    "wof:name":"Fitness 19",
    "wof:placetype":"venue"
},
  "geometry": {"coordinates":[-88.335309,42.173358],"type":"Point"}
}