{
  "type": "Feature",
  "properties": {
    "addr:full":"1250 N Dearborn St Chicago IL 60610",
    "addr:housenumber":"1250",
    "addr:postcode":"60610",
    "addr:street":"N Dearborn St",
    "iso:country":"US",
    "sg:address":"1250 N Dearborn St",
    "sg:city":"Chicago",
    "sg:classifiers":[
        {
            "category":"Health Services",
            "subcategory":"Doctor",
            "type":"Services"
        },
        {
            "category":"Health Services",
            "subcategory":"Hospital",
            "type":"Services"
        }
    ],
    "sg:phone":"+1 312 751 9978",
    "sg:postcode":"60610",
    "sg:province":"IL",
    "sg:tags":[
        "nursing",
        "consultant",
        "medical",
        "practice",
        "home"
    ],
    "wof:name":"Baron Enterprises Inc",
    "wof:placetype":"venue"
},
  "geometry": {"coordinates":[-87.630017,41.904888],"type":"Point"}
}