{
  "type": "Feature",
  "properties": {
    "iso:country":"US",
    "sg:address":"227 E Westminster Ave",
    "sg:city":"Lake Forest",
    "sg:classifiers":[
        {
            "category":"Shopping",
            "subcategory":"Beauty & Cosmetics",
            "type":"Retail Goods"
        }
    ],
    "sg:phone":"+1   ",
    "sg:postcode":"60045",
    "sg:province":"IL",
    "sg:tags":[
        "mail",
        "product",
        "perfume",
        "order",
        "bath"
    ],
    "wof:name":"Dans Un Jardin",
    "wof:placetype":"venue"
},
  "geometry": {"coordinates":[-87.841803,42.252938],"type":"Point"}
}