{
  "type": "Feature",
  "properties": {
    "iso:country":"US",
    "sg:address":"1321 Felten Rd",
    "sg:city":"Aurora",
    "sg:classifiers":[
        {
            "category":"Building & Trades",
            "subcategory":"Construction",
            "type":"Services"
        }
    ],
    "sg:phone":"+1 630 375 9357",
    "sg:postcode":"60504",
    "sg:province":"IL",
    "sg:tags":[
        "general",
        "contractor"
    ],
    "wof:name":"Porky Villa Construction Inc",
    "wof:placetype":"venue"
},
  "geometry": {"coordinates":[-88.27046300000001,41.783295],"type":"Point"}
}