{
  "type": "Feature",
  "properties": {
    "iso:country":"US",
    "sg:address":"1240 E Empire St",
    "sg:city":"Bloomington",
    "sg:classifiers":[
        {
            "category":"Restaurant",
            "type":"Food & Drink"
        }
    ],
    "sg:menulink":"http://www.allmenus.com/il/bloomington-city/159466-arbys/menu/",
    "sg:phone":"+1 309 829 2041",
    "sg:postcode":"61701",
    "sg:province":"IL",
    "sg:tags":[
        "burger",
        "american"
    ],
    "wof:name":"Arby's",
    "wof:placetype":"venue"
},
  "geometry": {"coordinates":[-88.973758,40.488376],"type":"Point"}
}