{
  "type": "Feature",
  "properties": {
    "iso:country":"US",
    "sg:address":"3222 Keeney Ave",
    "sg:city":"Steger",
    "sg:classifiers":[
        {
            "category":"Building & Trades",
            "subcategory":"Equipment Rental",
            "type":"Services"
        }
    ],
    "sg:phone":"+1 708 754 7900",
    "sg:postcode":"60475",
    "sg:province":"IL",
    "wof:name":"John Tidy Inc",
    "wof:placetype":"venue"
},
  "geometry": {"coordinates":[-87.622406,41.475173],"type":"Point"}
}