{
  "type": "Feature",
  "properties": {
    "addr:full":"1236 63rd St Downers Grove IL 60516",
    "addr:housenumber":"1236",
    "addr:postcode":"60516",
    "addr:street":"63Rd St",
    "iso:country":"US",
    "sg:address":"1236 63rd St",
    "sg:city":"Downers Grove",
    "sg:classifiers":[
        {
            "category":"Organizations",
            "subcategory":"Religious Organization",
            "type":"Services"
        }
    ],
    "sg:phone":"+1 630 968 0760",
    "sg:postcode":"60516",
    "sg:province":"IL",
    "wof:name":"Church of Christ Inc",
    "wof:placetype":"venue"
},
  "geometry": {"coordinates":[-88.015666,41.772964],"type":"Point"}
}