{
  "type": "Feature",
  "properties": {
    "addr:full":"11125 Branding Iron Ln Roscoe IL 61073",
    "addr:housenumber":"11125",
    "addr:postcode":"61073",
    "addr:street":"Branding Iron Ln",
    "iso:country":"US",
    "sg:address":"11125 Branding Iron Ln",
    "sg:city":"Roscoe",
    "sg:classifiers":[
        {
            "category":"Wholesale",
            "subcategory":"Machinery & Supplies",
            "type":"Manufacturing & Wholesale Goods"
        }
    ],
    "sg:phone":"+1 815 623 6916",
    "sg:postcode":"61073",
    "sg:province":"IL",
    "sg:tags":[
        "equipment",
        "welding"
    ],
    "wof:name":"Entron Controls Inc",
    "wof:placetype":"venue"
},
  "geometry": {"coordinates":[-88.980952,42.422685],"type":"Point"}
}