{
  "type": "Feature",
  "properties": {
    "iso:country":"US",
    "sg:address":"551 Edens Ln",
    "sg:city":"Northfield",
    "sg:classifiers":[
        {
            "category":"Real Estate",
            "subcategory":"Real Estate Services",
            "type":"Services"
        },
        {
            "category":"Real Estate",
            "subcategory":"Real Estate Agent",
            "type":"Services"
        }
    ],
    "sg:phone":"+1 847 501 3823",
    "sg:postcode":"60093",
    "sg:province":"IL",
    "sg:tags":[
        "management"
    ],
    "wof:name":"Soler Systems Search Inc",
    "wof:placetype":"venue"
},
  "geometry": {"coordinates":[-87.775368,42.106812],"type":"Point"}
}