{
  "type": "Feature",
  "properties": {
    "addr:full":"335 N River St Batavia IL 60510",
    "addr:housenumber":"335",
    "addr:postcode":"60510",
    "addr:street":"N River St",
    "iso:country":"US",
    "sg:address":"335 N River St",
    "sg:city":"Batavia",
    "sg:classifiers":[
        {
            "category":"Professional",
            "subcategory":"Management & Consulting",
            "type":"Services"
        }
    ],
    "sg:phone":"+1 630 482 2030",
    "sg:postcode":"60510",
    "sg:province":"IL",
    "sg:tags":[
        "business"
    ],
    "wof:name":"O Connor Mary & Company",
    "wof:placetype":"venue"
},
  "geometry": {"coordinates":[-88.306468,41.853601],"type":"Point"}
}