{
  "type": "Feature",
  "properties": {
    "addr:full":"6540 N Waukesha Avenue Chicago IL 60646",
    "addr:housenumber":"6540",
    "addr:postcode":"60646",
    "addr:street":"N Waukesha Avenue",
    "iso:country":"US",
    "sg:address":"6540 N Waukesha Avenue",
    "sg:city":"Chicago",
    "sg:classifiers":[
        {
            "category":"Building & Trades",
            "subcategory":"Construction",
            "type":"Services"
        }
    ],
    "sg:phone":"+1 773 774 5383",
    "sg:postcode":"60646",
    "sg:province":"IL",
    "sg:tags":[
        "interior",
        "design"
    ],
    "wof:name":"Abramovitz Associates",
    "wof:placetype":"venue"
},
  "geometry": {"coordinates":[-87.76843599999999,41.9998],"type":"Point"}
}