{
  "type": "Feature",
  "properties": {
    "iso:country":"US",
    "sg:address":"1903 S Shore Dr",
    "sg:city":"Springfield",
    "sg:classifiers":[
        {
            "category":"Organizations",
            "subcategory":"Religious Organization",
            "type":"Services"
        }
    ],
    "sg:phone":"+1 217 529 2213",
    "sg:postcode":"61265",
    "sg:province":"IL",
    "sg:tags":[
        "house",
        "retreat"
    ],
    "wof:name":"Villa Maria Retreat Ctr",
    "wof:placetype":"venue"
},
  "geometry": {"coordinates":[-90.502259,41.458763],"type":"Point"}
}