{
  "type": "Feature",
  "properties": {
    "iso:country":"US",
    "sg:address":"4954 W Irving Park Rd",
    "sg:city":"Chicago",
    "sg:classifiers":[
        {
            "category":"Health Services",
            "subcategory":"Doctor",
            "type":"Services"
        }
    ],
    "sg:phone":"+1 773 286 7900",
    "sg:postcode":"60641",
    "sg:province":"IL",
    "wof:name":"Wanda Sygieda DDS",
    "wof:placetype":"venue"
},
  "geometry": {"coordinates":[-87.751864,41.953444],"type":"Point"}
}