{
  "type": "Feature",
  "properties": {
    "addr:full":"5724 W. Lake Street Corporate Office Chicago IL 60644",
    "addr:housenumber":"5724",
    "addr:postcode":"60644",
    "addr:street":"W. Lake Street",
    "iso:country":"US",
    "sg:address":"5724 W. Lake Street Corporate Office",
    "sg:city":"Chicago",
    "sg:classifiers":[
        {
            "category":"Professional",
            "type":"Services"
        },
        {
            "category":"Food & Beverages",
            "subcategory":"Chocolate",
            "type":"Retail Goods"
        }
    ],
    "sg:phone":"+1 888 773 7870",
    "sg:postcode":"60644",
    "sg:province":"IL",
    "sg:tags":[
        "shop",
        "chocolatiers",
        "caterer"
    ],
    "sg:website":"www.laparisianneduchocolat.com",
    "wof:name":"La Parisianne du Chocolat Company",
    "wof:placetype":"venue"
},
  "geometry": {"coordinates":[-87.768731,41.888193],"type":"Point"}
}