{
  "type": "Feature",
  "properties": {
    "iso:country":"US",
    "sg:address":"675 Deerfield Rd",
    "sg:city":"Deerfield",
    "sg:classifiers":[
        {
            "category":"Restaurant",
            "type":"Food & Drink"
        }
    ],
    "sg:menulink":"http://www.allmenus.com/il/west-deerfield/221775-chipotle/menu/",
    "sg:phone":"+1 847 948 7902",
    "sg:postcode":"60015",
    "sg:province":"IL",
    "sg:tags":[
        "mexican"
    ],
    "wof:name":"Chipotle",
    "wof:placetype":"venue"
},
  "geometry": {"coordinates":[-87.84475,42.167303],"type":"Point"}
}