{
  "type": "Feature",
  "properties": {
    "iso:country":"US",
    "sg:address":"11960 Oak Creek Pkwy",
    "sg:city":"Huntley",
    "sg:classifiers":[
        {
            "category":"Wholesale",
            "subcategory":"Office Equipment",
            "type":"Manufacturing & Wholesale Goods"
        },
        {
            "category":"Professional",
            "subcategory":"Printing & Photocopies",
            "type":"Services"
        },
        {
            "category":"Shopping",
            "subcategory":"Computers & Home Electronics",
            "type":"Retail Goods"
        }
    ],
    "sg:phone":"+1 847 669 9620",
    "sg:postcode":"60142",
    "sg:province":"IL",
    "sg:tags":[
        "scanning",
        "printer",
        "services-commercial",
        "plotting",
        "supply"
    ],
    "sg:website":"http://www.serviceprintingcorp.com",
    "wof:name":"Service Printing Corporation",
    "wof:placetype":"venue"
},
  "geometry": {"coordinates":[-88.43167800000001,42.137443],"type":"Point"}
}