{
  "type": "Feature",
  "properties": {
    "iso:country":"US",
    "sg:address":"1430 Ogden Ave",
    "sg:city":"Downers Grove",
    "sg:classifiers":[
        {
            "category":"Retail",
            "subcategory":"Auto Repair",
            "type":"Services"
        }
    ],
    "sg:phone":"+1 630 963 1340",
    "sg:postcode":"60515",
    "sg:province":"IL",
    "sg:tags":[
        "general"
    ],
    "wof:name":"Helmut & Vitos Auto Service",
    "wof:placetype":"venue"
},
  "geometry": {"coordinates":[-88.021818,41.808261],"type":"Point"}
}