{
  "type": "Feature",
  "properties": {
    "addr:full":"44 S Mill St Naperville IL 60540",
    "addr:housenumber":"44",
    "addr:postcode":"60540",
    "addr:street":"S Mill St",
    "iso:country":"US",
    "sg:address":"44 S Mill St",
    "sg:city":"Naperville",
    "sg:classifiers":[
        {
            "category":"Cemetery",
            "type":"Public Place"
        },
        {
            "category":"Landmark",
            "subcategory":"Monument",
            "type":"Public Place"
        },
        {
            "category":"Retail",
            "subcategory":"Funeral Services",
            "type":"Services"
        }
    ],
    "sg:phone":"+1 630 355 0213",
    "sg:postcode":"60540",
    "sg:province":"IL",
    "sg:tags":[
        "director",
        "crematory",
        "plans-pre-arranged"
    ],
    "sg:website":"http://www.friedrich-jones.com/",
    "wof:name":"Friedrich-Jones Funeral Home",
    "wof:placetype":"venue"
},
  "geometry": {"coordinates":[-88.15451,41.774922],"type":"Point"}
}