{
  "type": "Feature",
  "properties": {
    "iso:country":"US",
    "sg:address":"220 E 2nd St",
    "sg:city":"Centralia",
    "sg:classifiers":[
        {
            "category":"Insurance",
            "subcategory":"Insurance Agent",
            "type":"Services"
        }
    ],
    "sg:phone":"+1 618 532 4724",
    "sg:postcode":"62801",
    "sg:province":"IL",
    "wof:name":"Hudson-Gray Insurance",
    "wof:placetype":"venue"
},
  "geometry": {"coordinates":[-89.13437,38.52641],"type":"Point"}
}