{
  "type": "Feature",
  "properties": {
    "addr:full":"500 Central Ave University Park IL 60466",
    "addr:housenumber":"500",
    "addr:postcode":"60466",
    "addr:street":"Central Ave",
    "iso:country":"US",
    "sg:address":"500 Central Ave",
    "sg:city":"University Park",
    "sg:classifiers":[
        {
            "category":"Wholesale",
            "subcategory":"Chemicals & Plastics",
            "type":"Manufacturing & Wholesale Goods"
        }
    ],
    "sg:phone":"+1 708 534 5511",
    "sg:postcode":"60466",
    "sg:province":"IL",
    "sg:website":"www.avatarcorp.com",
    "wof:name":"Avatar Corp",
    "wof:placetype":"venue"
},
  "geometry": {"coordinates":[-87.748035,41.453174],"type":"Point"}
}