{
  "type": "Feature",
  "properties": {
    "iso:country":"US",
    "sg:address":"8707 Skokie Blvd",
    "sg:city":"Skokie",
    "sg:classifiers":[
        {
            "category":"Banks & Credit Unions",
            "subcategory":"Bank",
            "type":"Services"
        }
    ],
    "sg:phone":"+1 847 675 9008",
    "sg:postcode":"60077",
    "sg:province":"IL",
    "sg:tags":[
        "short",
        "institution",
        "business"
    ],
    "wof:name":"Universal Funding Corporation",
    "wof:placetype":"venue"
},
  "geometry": {"coordinates":[-87.747041,42.039621],"type":"Point"}
}