{
  "type": "Feature",
  "properties": {
    "iso:country":"US",
    "sg:address":"1251 E 3300 North Rd",
    "sg:city":"Mansfield",
    "sg:classifiers":[
        {
            "category":"Manufacturing",
            "subcategory":"Food",
            "type":"Manufacturing & Wholesale Goods"
        },
        {
            "category":"Farming",
            "subcategory":"Farm",
            "type":"Manufacturing & Wholesale Goods"
        }
    ],
    "sg:phone":"+1 217 489 3501",
    "sg:postcode":"61854",
    "sg:province":"IL",
    "sg:tags":[
        "corn",
        "product"
    ],
    "wof:name":"K&M Bradd Inc",
    "wof:placetype":"venue"
},
  "geometry": {"coordinates":[-88.50306999999999,40.266796],"type":"Point"}
}