{
  "type": "Feature",
  "properties": {
    "iso:country":"US",
    "sg:address":"118 S Illinois Ave",
    "sg:city":"Carbondale",
    "sg:classifiers":[
        {
            "category":"Shopping",
            "subcategory":"Used Merchandise",
            "type":"Retail Goods"
        }
    ],
    "sg:phone":"+1 618 549 0157",
    "sg:postcode":"62901",
    "sg:province":"IL",
    "sg:tags":[
        "shop",
        "thrift"
    ],
    "wof:name":"Salvation Army Thrift Store",
    "wof:placetype":"venue"
},
  "geometry": {"coordinates":[-89.217,37.727089],"type":"Point"}
}