{
  "type": "Feature",
  "properties": {
    "iso:country":"US",
    "sg:address":"126 S Main St",
    "sg:city":"Morton",
    "sg:classifiers":[
        {
            "category":"Banks & Credit Unions",
            "subcategory":"Investment Brokerage",
            "type":"Services"
        },
        {
            "category":"Banks & Credit Unions",
            "subcategory":"Financial Services",
            "type":"Services"
        }
    ],
    "sg:phone":"+1 309 266 7171",
    "sg:postcode":"61550",
    "sg:province":"IL",
    "sg:tags":[
        "advisory",
        "planner"
    ],
    "sg:website":"http://www.concordfinancialadvisors.com",
    "wof:name":"Ameriprise Financial Services Inc.",
    "wof:placetype":"venue"
},
  "geometry": {"coordinates":[-89.46198800000001,40.610114],"type":"Point"}
}