{
  "type": "Feature",
  "properties": {
    "addr:full":"33 Deer Ct Geneseo IL 61254",
    "addr:housenumber":"33",
    "addr:postcode":"61254",
    "addr:street":"Deer Ct",
    "iso:country":"US",
    "sg:address":"33 Deer Ct",
    "sg:city":"Geneseo",
    "sg:classifiers":[
        {
            "category":"Professional",
            "subcategory":"Computer Services",
            "type":"Services"
        }
    ],
    "sg:phone":"+1 309 441 6323",
    "sg:postcode":"61254",
    "sg:province":"IL",
    "sg:tags":[
        "related"
    ],
    "wof:name":"Advanced Technologies",
    "wof:placetype":"venue"
},
  "geometry": {"coordinates":[-90.19864,41.529607],"type":"Point"}
}