{
  "type": "Feature",
  "properties": {
    "addr:full":"8834 Gross Point Rd Skokie IL 60077",
    "addr:housenumber":"8834",
    "addr:postcode":"60077",
    "addr:street":"Gross Point Rd",
    "iso:country":"US",
    "sg:address":"8834 Gross Point Rd",
    "sg:city":"Skokie",
    "sg:classifiers":[
        {
            "category":"Communications",
            "subcategory":"Film & Video Production",
            "type":"Services"
        }
    ],
    "sg:phone":"+1 847 965 6173",
    "sg:postcode":"60077",
    "sg:province":"IL",
    "sg:tags":[
        "tv",
        "picture",
        "radio",
        "motion",
        "companies-film"
    ],
    "wof:name":"Michael Toth Productions",
    "wof:placetype":"venue"
},
  "geometry": {"coordinates":[-87.755771,42.041517],"type":"Point"}
}