{
  "type": "Feature",
  "properties": {
    "iso:country":"US",
    "sg:address":"2604 E Goodrich Ave",
    "sg:city":"Chicago",
    "sg:classifiers":[
        {
            "category":"Transit Center",
            "subcategory":"Freight",
            "type":"Transportation"
        },
        {
            "category":"Freight",
            "type":"Transportation"
        },
        {
            "category":"Retail",
            "subcategory":"Pet Boarding",
            "type":"Services"
        }
    ],
    "sg:phone":"+1 708 868 4225",
    "sg:postcode":"60633",
    "sg:province":"IL",
    "sg:tags":[
        "crating",
        "trucking-motor",
        "trucking",
        "packing",
        "local"
    ],
    "wof:name":"Emj Transportation Service, Inc.",
    "wof:placetype":"venue"
},
  "geometry": {"coordinates":[-87.55416,41.63086],"type":"Point"}
}