{
  "type": "Feature",
  "properties": {
    "iso:country":"US",
    "sg:address":"112 W Washington St",
    "sg:city":"Pittsfield",
    "sg:classifiers":[
        {
            "category":"Professional",
            "subcategory":"Lawyer & Legal Services",
            "type":"Services"
        }
    ],
    "sg:phone":"+1 217 285 6460",
    "sg:postcode":"62363",
    "sg:province":"IL",
    "wof:name":"Myers & Filbert PC",
    "wof:placetype":"venue"
},
  "geometry": {"coordinates":[-90.806676,39.606857],"type":"Point"}
}