{
  "type": "Feature",
  "properties": {
    "iso:country":"US",
    "sg:address":"648 S Roselle Rd",
    "sg:city":"Schaumburg",
    "sg:classifiers":[
        {
            "category":"Personal",
            "subcategory":"Beauty Salon",
            "type":"Services"
        },
        {
            "category":"Personal",
            "subcategory":"Barber",
            "type":"Services"
        }
    ],
    "sg:phone":"+1 847 895 0104",
    "sg:postcode":"60193",
    "sg:province":"IL",
    "sg:tags":[
        "hair",
        "stylist"
    ],
    "wof:name":"Hair Spot",
    "wof:placetype":"venue"
},
  "geometry": {"coordinates":[-88.08000199999999,42.015294],"type":"Point"}
}