{
  "type": "Feature",
  "properties": {
    "iso:country":"US",
    "sg:address":"117 Woodward Ave",
    "sg:city":"Geneva",
    "sg:classifiers":[
        {
            "category":"Wholesale",
            "subcategory":"Machinery & Supplies",
            "type":"Manufacturing & Wholesale Goods"
        }
    ],
    "sg:phone":"+1 630 208 9116",
    "sg:postcode":"60134",
    "sg:province":"IL",
    "sg:tags":[
        "equipment",
        "industrial"
    ],
    "wof:name":"McDonald Do Val International",
    "wof:placetype":"venue"
},
  "geometry": {"coordinates":[-88.29555,41.891977],"type":"Point"}
}