{
  "type": "Feature",
  "properties": {
    "addr:full":"1153 E Co Rd 2300 Niota IL 62358",
    "addr:housenumber":"1153",
    "addr:postcode":"2300;62358",
    "addr:street":"E Co Rd",
    "iso:country":"US",
    "sg:address":"1153 E Co Rd 2300",
    "sg:city":"Niota",
    "sg:classifiers":[
        {
            "category":"Real Estate",
            "subcategory":"Real Estate Operator",
            "type":"Services"
        }
    ],
    "sg:phone":"+1 217 453 2506",
    "sg:postcode":"62358",
    "sg:province":"IL",
    "sg:tags":[
        "property",
        "lessor"
    ],
    "wof:name":"Morgan Lewis",
    "wof:placetype":"venue"
},
  "geometry": {"coordinates":[-91.27712,40.536049],"type":"Point"}
}