{
  "type": "Feature",
  "properties": {
    "iso:country":"US",
    "sg:address":"3522 214th St N",
    "sg:city":"Port Byron",
    "sg:classifiers":[
        {
            "category":"Retail",
            "subcategory":"Animal Services",
            "type":"Services"
        }
    ],
    "sg:phone":"+1 309 523 2787",
    "sg:postcode":"61275",
    "sg:province":"IL",
    "wof:name":"Almasta Racing Stables",
    "wof:placetype":"venue"
},
  "geometry": {"coordinates":[-90.327654,41.560757],"type":"Point"}
}