{
  "type": "Feature",
  "properties": {
    "iso:country":"US",
    "sg:address":"3515 Auburn St",
    "sg:city":"Rockford",
    "sg:classifiers":[
        {
            "category":"Autos & Motor Vehicles",
            "subcategory":"Motorcycle Sales",
            "type":"Retail Goods"
        }
    ],
    "sg:phone":"+1   ",
    "sg:postcode":"61101",
    "sg:province":"IL",
    "sg:tags":[
        "repair"
    ],
    "wof:name":"Precision Cycle Inc",
    "wof:placetype":"venue"
},
  "geometry": {"coordinates":[-89.113452,42.288422],"type":"Point"}
}