{
  "type": "Feature",
  "properties": {
    "addr:full":"4112 N Pulaski Rd Chicago IL 60641",
    "addr:housenumber":"4112",
    "addr:postcode":"60641",
    "addr:street":"N Pulaski Rd",
    "iso:country":"US",
    "sg:address":"4112 N Pulaski Rd",
    "sg:city":"Chicago",
    "sg:classifiers":[
        {
            "category":"Health Services",
            "subcategory":"Health Practitioner",
            "type":"Services"
        }
    ],
    "sg:phone":"+1 773 481 9881",
    "sg:postcode":"60641",
    "sg:province":"IL",
    "sg:tags":[
        "acupuncture"
    ],
    "wof:name":"Acupuncture & Nutrition Center",
    "wof:placetype":"venue"
},
  "geometry": {"coordinates":[-87.72784,41.955709],"type":"Point"}
}