{
  "type": "Feature",
  "properties": {
    "iso:country":"US",
    "sg:address":"9195 Gross Point Rd",
    "sg:city":"Skokie",
    "sg:classifiers":[
        {
            "category":"Health Services",
            "subcategory":"Health Practitioner",
            "type":"Services"
        }
    ],
    "sg:phone":"+1 847 329 8226",
    "sg:postcode":"60077",
    "sg:province":"IL",
    "wof:name":"Wee Speech PC",
    "wof:placetype":"venue"
},
  "geometry": {"coordinates":[-87.74955,42.0472],"type":"Point"}
}