{
  "type": "Feature",
  "properties": {
    "iso:country":"US",
    "sg:address":"1410 S Alpine Rd",
    "sg:city":"Rockford",
    "sg:classifiers":[
        {
            "category":"Restaurant",
            "type":"Food & Drink"
        }
    ],
    "sg:phone":"+1 815 227 9851",
    "sg:postcode":"61108",
    "sg:province":"IL",
    "wof:name":"Swedish Pancake House",
    "wof:placetype":"venue"
},
  "geometry": {"coordinates":[-89.02901,42.25354],"type":"Point"}
}