{
  "type": "Feature",
  "properties": {
    "iso:country":"US",
    "sg:address":"2917 W Irving Park Rd",
    "sg:city":"Chicago",
    "sg:classifiers":[
        {
            "category":"Autos & Motor Vehicles",
            "subcategory":"Automobile Sales",
            "type":"Retail Goods"
        }
    ],
    "sg:phone":"+1 888 287 1572",
    "sg:postcode":"60618",
    "sg:province":"IL",
    "sg:tags":[
        "car"
    ],
    "wof:name":"Car Outlet",
    "wof:placetype":"venue"
},
  "geometry": {"coordinates":[-87.701261,41.953651],"type":"Point"}
}