{
  "type": "Feature",
  "properties": {
    "addr:full":"2840 N Lincoln Ave Chicago IL 60657",
    "addr:housenumber":"2840",
    "addr:postcode":"60657",
    "addr:street":"N Lincoln Ave",
    "iso:country":"US",
    "sg:address":"2840 N Lincoln Ave",
    "sg:city":"Chicago",
    "sg:classifiers":[
        {
            "category":"Education",
            "subcategory":"Preschool",
            "type":"Public Place"
        },
        {
            "category":"Education",
            "subcategory":"School",
            "type":"Public Place"
        }
    ],
    "sg:phone":"+1 773 935 7300",
    "sg:postcode":"60657",
    "sg:province":"IL",
    "sg:tags":[
        "elementary"
    ],
    "sg:website":"www.chalkpreschool.com",
    "wof:name":"Chalk Preschool",
    "wof:placetype":"venue"
},
  "geometry": {"coordinates":[-87.659818,41.933204],"type":"Point"}
}