{
  "type": "Feature",
  "properties": {
    "iso:country":"US",
    "sg:address":"744 Sheridan Rd",
    "sg:city":"Evanston",
    "sg:classifiers":[
        {
            "category":"Travel",
            "subcategory":"Travel Agent",
            "type":"Entertainment"
        }
    ],
    "sg:phone":"+1 847 475 0585",
    "sg:postcode":"60202",
    "sg:province":"IL",
    "sg:tags":[
        "agency"
    ],
    "wof:name":"Geeta Tours & Travels",
    "wof:placetype":"venue"
},
  "geometry": {"coordinates":[-87.67067400000001,42.03022],"type":"Point"}
}