{
  "type": "Feature",
  "properties": {
    "iso:country":"US",
    "sg:address":"3917 W 95th St",
    "sg:city":"Evergreen Park",
    "sg:classifiers":[
        {
            "category":"Personal",
            "subcategory":"Barber",
            "type":"Services"
        }
    ],
    "sg:phone":"+1 708 424 0775",
    "sg:postcode":"60805",
    "sg:province":"IL",
    "sg:website":"ChucksBarberShop.com",
    "wof:name":"Chucks Barber Salon",
    "wof:placetype":"venue"
},
  "geometry": {"coordinates":[-87.719289,41.720318],"type":"Point"}
}