{
  "type": "Feature",
  "properties": {
    "addr:full":"4515 N Elston Ave Chicago IL 60630",
    "addr:housenumber":"4515",
    "addr:postcode":"60630",
    "addr:street":"N Elston Ave",
    "iso:country":"US",
    "sg:address":"4515 N Elston Ave",
    "sg:city":"Chicago",
    "sg:classifiers":[
        {
            "category":"Retail",
            "subcategory":"Auto Repair",
            "type":"Services"
        }
    ],
    "sg:phone":"+1 773 283 2181",
    "sg:postcode":"60630",
    "sg:province":"IL",
    "wof:name":"Rs Repair",
    "wof:placetype":"venue"
},
  "geometry": {"coordinates":[-87.73222,41.962884],"type":"Point"}
}