{
  "type": "Feature",
  "properties": {
    "iso:country":"US",
    "sg:address":"22 E Chicago Ave",
    "sg:city":"Naperville",
    "sg:classifiers":[
        {
            "category":"Personal",
            "subcategory":"Beauty Salon",
            "type":"Services"
        },
        {
            "category":"Utilities",
            "subcategory":"Mobile Phone",
            "type":"Services"
        }
    ],
    "sg:phone":"+1 630 848 1003",
    "sg:postcode":"60540",
    "sg:province":"IL",
    "sg:tags":[
        "wi-fi",
        "hotspot"
    ],
    "wof:name":"E'lon By Laura Anderson",
    "wof:placetype":"venue"
},
  "geometry": {"coordinates":[-88.147694,41.771506],"type":"Point"}
}