{
  "type": "Feature",
  "properties": {
    "iso:country":"US",
    "sg:address":"913 Millcreek Cir",
    "sg:city":"Elgin",
    "sg:classifiers":[
        {
            "category":"Retail",
            "subcategory":"Repair Shop",
            "type":"Services"
        }
    ],
    "sg:phone":"+1 847 697 7783",
    "sg:postcode":"60123",
    "sg:province":"IL",
    "wof:name":"CA Iversen Inc",
    "wof:placetype":"venue"
},
  "geometry": {"coordinates":[-88.334811,42.055838],"type":"Point"}
}