{
  "type": "Feature",
  "properties": {
    "iso:country":"US",
    "sg:address":"6250 Northwest Hwy",
    "sg:city":"Crystal Lake",
    "sg:classifiers":[
        {
            "category":"Shopping",
            "subcategory":"Hobbies, Toys, & Games",
            "type":"Retail Goods"
        }
    ],
    "sg:phone":"+1   ",
    "sg:postcode":"60014",
    "sg:province":"IL",
    "wof:name":"Hobby Lobby 186",
    "wof:placetype":"venue"
},
  "geometry": {"coordinates":[-88.31948800000001,42.226223],"type":"Point"}
}