{
  "type": "Feature",
  "properties": {
    "addr:full":"4249 Elm Ave Brookfield IL 60513",
    "addr:housenumber":"4249",
    "addr:postcode":"60513",
    "addr:street":"Elm Ave",
    "iso:country":"US",
    "sg:address":"4249 Elm Ave",
    "sg:city":"Brookfield",
    "sg:classifiers":[
        {
            "category":"Professional",
            "subcategory":"Engineering",
            "type":"Services"
        }
    ],
    "sg:phone":"+1 708 387 0177",
    "sg:postcode":"60513",
    "sg:province":"IL",
    "wof:name":"Richard Roleck & Associates",
    "wof:placetype":"venue"
},
  "geometry": {"coordinates":[-87.850114,41.813652],"type":"Point"}
}