{
  "type": "Feature",
  "properties": {
    "addr:full":"1175 McCabe Ave Elk Grove Village IL 60007",
    "addr:housenumber":"1175",
    "addr:postcode":"60007",
    "addr:street":"Mccabe Ave",
    "iso:country":"US",
    "sg:address":"1175 McCabe Ave",
    "sg:city":"Elk Grove Village",
    "sg:classifiers":[
        {
            "category":"Freight",
            "type":"Transportation"
        }
    ],
    "sg:phone":"+1 847 734 0500",
    "sg:postcode":"60007",
    "sg:province":"IL",
    "sg:tags":[
        "forwarder"
    ],
    "wof:name":"G & B International Inc",
    "wof:placetype":"venue"
},
  "geometry": {"coordinates":[-87.95497899999999,42.010536],"type":"Point"}
}