{
  "type": "Feature",
  "properties": {
    "iso:country":"US",
    "sg:address":"1175 McCabe Ave",
    "sg:city":"Elk Grove Village",
    "sg:classifiers":[
        {
            "category":"Freight",
            "type":"Transportation"
        }
    ],
    "sg:phone":"+1 847 734 0500",
    "sg:postcode":"60007",
    "sg:province":"IL",
    "sg:tags":[
        "forwarder"
    ],
    "wof:name":"G & B International Inc",
    "wof:placetype":"venue"
},
  "geometry": {"coordinates":[-87.954979,42.010536],"type":"Point"}
}