{
  "type": "Feature",
  "properties": {
    "iso:country":"US",
    "sg:address":"1702 Washington St",
    "sg:city":"Waukegan",
    "sg:classifiers":[
        {
            "category":"Professional",
            "type":"Services"
        }
    ],
    "sg:phone":"+1 847 249 5060",
    "sg:postcode":"60085",
    "sg:province":"IL",
    "sg:tags":[
        "establishment"
    ],
    "wof:name":"Brilliant Technologies",
    "wof:placetype":"venue"
},
  "geometry": {"coordinates":[-87.85351799999999,42.359759],"type":"Point"}
}