{
  "type": "Feature",
  "properties": {
    "iso:country":"US",
    "sg:address":"935 W Elmscourt Ln",
    "sg:city":"Crete",
    "sg:classifiers":[
        {
            "category":"Building & Trades",
            "subcategory":"Construction",
            "type":"Services"
        }
    ],
    "sg:phone":"+1 708 672 3802",
    "sg:postcode":"60417",
    "sg:province":"IL",
    "sg:tags":[
        "roofing",
        "industrial",
        "contractors-commercial",
        "contractor"
    ],
    "wof:name":"Century Roofing & Constru",
    "wof:placetype":"venue"
},
  "geometry": {"coordinates":[-87.636921,41.406028],"type":"Point"}
}