{
  "type": "Feature",
  "properties": {
    "iso:country":"US",
    "sg:address":"3623 S Giles Ave",
    "sg:city":"Chicago",
    "sg:classifiers":[
        {
            "category":"Banks & Credit Unions",
            "subcategory":"Investment Brokerage",
            "type":"Services"
        }
    ],
    "sg:phone":"+1 773 373 5100",
    "sg:postcode":"60653",
    "sg:province":"IL",
    "sg:tags":[
        "consultant",
        "planning",
        "financial"
    ],
    "wof:name":"AFA Financial Consultants",
    "wof:placetype":"venue"
},
  "geometry": {"coordinates":[-87.619183,41.827629],"type":"Point"}
}