{
  "type": "Feature",
  "properties": {
    "addr:full":"2590 N Lincoln Lake Dr Coal City IL 60416",
    "addr:housenumber":"2590",
    "addr:postcode":"60416",
    "addr:street":"N Lincoln Lake Dr",
    "iso:country":"US",
    "sg:address":"2590 N Lincoln Lake Dr",
    "sg:city":"Coal City",
    "sg:classifiers":[
        {
            "category":"Building & Trades",
            "subcategory":"Plumbing",
            "type":"Services"
        }
    ],
    "sg:phone":"+1 815 634 4681",
    "sg:postcode":"60416",
    "sg:province":"IL",
    "sg:tags":[
        "plumbing",
        "contractor"
    ],
    "wof:name":"Lavezzi Plumbing Inc",
    "wof:placetype":"venue"
},
  "geometry": {"coordinates":[-88.29893199999999,41.326778],"type":"Point"}
}