{
  "type": "Feature",
  "properties": {
    "iso:country":"US",
    "sg:address":"1121 E Woodfield Dr",
    "sg:city":"Alton",
    "sg:classifiers":[
        {
            "category":"Recreation",
            "type":"Entertainment"
        }
    ],
    "sg:phone":"+1 618 467 8860",
    "sg:postcode":"62002",
    "sg:province":"IL",
    "sg:tags":[
        "carnival"
    ],
    "wof:name":"Olde Alton Arts & Crafts Fair",
    "wof:placetype":"venue"
},
  "geometry": {"coordinates":[-90.141944,38.964984],"type":"Point"}
}