{
  "type": "Feature",
  "properties": {
    "iso:country":"US",
    "sg:address":"200 Dearborn Ave",
    "sg:city":"South Beloit",
    "sg:classifiers":[
        {
            "category":"Restaurant",
            "type":"Food & Drink"
        }
    ],
    "sg:phone":"+1 815 389 1400",
    "sg:postcode":"61080",
    "sg:province":"WI",
    "wof:name":"Cattails Restaurant",
    "wof:placetype":"venue"
},
  "geometry": {"coordinates":[-89.020199,42.494728],"type":"Point"}
}