{
  "type": "Feature",
  "properties": {
    "iso:country":"US",
    "sg:address":"10402 S Cicero Ave",
    "sg:city":"Oak Lawn",
    "sg:classifiers":[
        {
            "category":"Banks & Credit Unions",
            "subcategory":"Bank",
            "type":"Services"
        }
    ],
    "sg:phone":"+1 708 229 9742",
    "sg:postcode":"60453",
    "sg:province":"IL",
    "sg:tags":[
        "loan",
        "broker"
    ],
    "wof:name":"Advance Til Payday",
    "wof:placetype":"venue"
},
  "geometry": {"coordinates":[-87.74020899999999,41.701938],"type":"Point"}
}