{
  "type": "Feature",
  "properties": {
    "iso:country":"US",
    "sg:address":"108 E Superior Ave",
    "sg:city":"Alexander",
    "sg:classifiers":[
        {
            "category":"Government",
            "subcategory":"Post Office",
            "type":"Public Place"
        }
    ],
    "sg:phone":"+1 217 478 2161",
    "sg:postcode":"62650",
    "sg:province":"IL",
    "wof:name":"US Post Office",
    "wof:placetype":"venue"
},
  "geometry": {"coordinates":[-90.229116,39.719581],"type":"Point"}
}