{
  "type": "Feature",
  "properties": {
    "iso:country":"US",
    "sg:address":"16444 Craig Dr",
    "sg:city":"Oak Forest",
    "sg:classifiers":[
        {
            "category":"Real Estate",
            "subcategory":"Real Estate Agent",
            "type":"Services"
        }
    ],
    "sg:phone":"+1 708 535 1136",
    "sg:postcode":"60452",
    "sg:province":"IL",
    "wof:name":"I and E Properties LLC",
    "wof:placetype":"venue"
},
  "geometry": {"coordinates":[-87.727096,41.594002],"type":"Point"}
}