{
  "type": "Feature",
  "properties": {
    "iso:country":"US",
    "sg:address":"50 Deerfield Trailer Ct",
    "sg:city":"Freeburg",
    "sg:classifiers":[
        {
            "category":"Building & Trades",
            "subcategory":"Construction",
            "type":"Services"
        }
    ],
    "sg:phone":"+1 618 539 5108",
    "sg:postcode":"62243",
    "sg:province":"IL",
    "sg:tags":[
        "system",
        "specialty",
        "heating",
        "contractor",
        "air conditioning"
    ],
    "wof:name":"Dow Heating & Air Conditioning",
    "wof:placetype":"venue"
},
  "geometry": {"coordinates":[-89.91619799999999,38.438983],"type":"Point"}
}