{
  "type": "Feature",
  "properties": {
    "addr:full":"2147 N Rockwell St Chicago IL 60647",
    "addr:housenumber":"2147",
    "addr:postcode":"60647",
    "addr:street":"N Rockwell St",
    "iso:country":"US",
    "sg:address":"2147 N Rockwell St",
    "sg:city":"Chicago",
    "sg:classifiers":[
        {
            "category":"Food & Beverages",
            "subcategory":"Meat & Fish",
            "type":"Retail Goods"
        }
    ],
    "sg:phone":"+1   ",
    "sg:postcode":"60647",
    "sg:province":"IL",
    "wof:name":"Siam Meats Inc",
    "wof:placetype":"venue"
},
  "geometry": {"coordinates":[-87.69273,41.920695],"type":"Point"}
}