{
  "type": "Feature",
  "properties": {
    "addr:full":"7726 Monroe St Forest Park IL 60130",
    "addr:housenumber":"7726",
    "addr:postcode":"60130",
    "addr:street":"Monroe St",
    "iso:country":"US",
    "sg:address":"7726 Monroe St",
    "sg:city":"Forest Park",
    "sg:classifiers":[
        {
            "category":"Food & Beverages",
            "subcategory":"Specialty",
            "type":"Retail Goods"
        }
    ],
    "sg:phone":"+1   ",
    "sg:postcode":"60130",
    "sg:province":"IL",
    "wof:name":"Garapolo Group",
    "wof:placetype":"venue"
},
  "geometry": {"coordinates":[-87.81852600000001,41.878372],"type":"Point"}
}