{
  "type": "Feature",
  "properties": {
    "iso:country":"US",
    "sg:address":"7726 Monroe St",
    "sg:city":"Forest Park",
    "sg:classifiers":[
        {
            "category":"Food & Beverages",
            "subcategory":"Specialty",
            "type":"Retail Goods"
        }
    ],
    "sg:phone":"+1   ",
    "sg:postcode":"60130",
    "sg:province":"IL",
    "wof:name":"Garapolo Group",
    "wof:placetype":"venue"
},
  "geometry": {"coordinates":[-87.818526,41.878372],"type":"Point"}
}