{
  "type": "Feature",
  "properties": {
    "iso:country":"US",
    "sg:address":"1123 Elm St",
    "sg:city":"Jacksonville",
    "sg:classifiers":[
        {
            "category":"Organizations",
            "subcategory":"Religious Organization",
            "type":"Services"
        }
    ],
    "sg:phone":"+1 217 245 6006",
    "sg:postcode":"62650",
    "sg:province":"IL",
    "wof:name":"Corporation of President of Th",
    "wof:placetype":"venue"
},
  "geometry": {"coordinates":[-90.25021,39.740067],"type":"Point"}
}