{
  "type": "Feature",
  "properties": {
    "iso:country":"US",
    "sg:address":"5 Crestmont Dr",
    "sg:city":"Collinsville",
    "sg:classifiers":[
        {
            "category":"Social Services",
            "subcategory":"Child Care",
            "type":"Services"
        },
        {
            "category":"Education",
            "subcategory":"Preschool",
            "type":"Public Place"
        },
        {
            "category":"Education",
            "subcategory":"School",
            "type":"Public Place"
        }
    ],
    "sg:phone":"+1 618 345 9588",
    "sg:postcode":"62234",
    "sg:province":"IL",
    "sg:tags":[
        "elementary",
        "day"
    ],
    "sg:website":"www.riverbendfamilies.org",
    "wof:name":"Riverbend Head Start & Family Services",
    "wof:placetype":"venue"
},
  "geometry": {"coordinates":[-89.98870100000001,38.690399],"type":"Point"}
}