{
  "type": "Feature",
  "properties": {
    "iso:country":"US",
    "sg:address":"12 E Green St",
    "sg:city":"Champaign",
    "sg:classifiers":[
        {
            "category":"Restaurant",
            "type":"Food & Drink"
        }
    ],
    "sg:phone":"+1 217 356 4700",
    "sg:postcode":"61820",
    "sg:province":"IL",
    "wof:name":"Number One Wok",
    "wof:placetype":"venue"
},
  "geometry": {"coordinates":[-88.242897,40.1101],"type":"Point"}
}