{
  "type": "Feature",
  "properties": {
    "iso:country":"US",
    "sg:address":"4034 N. Nashville Ave.",
    "sg:city":"Chicago",
    "sg:classifiers":[
        {
            "category":"Personal",
            "type":"Services"
        }
    ],
    "sg:phone":"+1 312 593 7225",
    "sg:postcode":"60634",
    "sg:province":"IL",
    "sg:tags":[
        "planning",
        "wedding"
    ],
    "sg:website":"www.bbweddingrentals.com",
    "wof:name":"BB Event Rentals",
    "wof:placetype":"venue"
},
  "geometry": {"coordinates":[-87.793959,41.95299],"type":"Point"}
}