{
  "type": "Feature",
  "properties": {
    "iso:country":"US",
    "sg:address":"1503 Ogden Ave",
    "sg:city":"Downers Grove",
    "sg:classifiers":[
        {
            "category":"Home & Garden",
            "subcategory":"Carpets & Floor Coverings",
            "type":"Retail Goods"
        }
    ],
    "sg:phone":"+1   ",
    "sg:postcode":"60515",
    "sg:province":"IL",
    "wof:name":"Central Tile Inc",
    "wof:placetype":"venue"
},
  "geometry": {"coordinates":[-88.023138,41.808124],"type":"Point"}
}