{
  "type": "Feature",
  "properties": {
    "addr:full":"6692 N Sioux Ave Chicago IL 60646",
    "addr:housenumber":"6692",
    "addr:postcode":"60646",
    "addr:street":"N Sioux Ave",
    "iso:country":"US",
    "sg:address":"6692 N Sioux Ave",
    "sg:city":"Chicago",
    "sg:classifiers":[
        {
            "category":"Manufacturing",
            "subcategory":"Printing",
            "type":"Manufacturing & Wholesale Goods"
        }
    ],
    "sg:phone":"+1 773 775 8801",
    "sg:postcode":"60646",
    "sg:province":"IL",
    "sg:tags":[
        "newspaper",
        "publishing"
    ],
    "wof:name":"Bureau Of National Affairs Inc",
    "wof:placetype":"venue"
},
  "geometry": {"coordinates":[-87.76469400000001,42.001655],"type":"Point"}
}