{
  "type": "Feature",
  "properties": {
    "iso:country":"US",
    "sg:address":"27750 W Il Route 22",
    "sg:city":"Barrington",
    "sg:classifiers":[
        {
            "category":"Health Services",
            "subcategory":"Doctor",
            "type":"Services"
        }
    ],
    "sg:phone":"+1 847 382 1505",
    "sg:postcode":"60010",
    "sg:province":"IL",
    "sg:tags":[
        "throat",
        "surgeon",
        "ear",
        "cosmetic",
        "nose"
    ],
    "wof:name":"Mercy Regional Plastic Surgery Center",
    "wof:placetype":"venue"
},
  "geometry": {"coordinates":[-88.15529600000001,42.190701],"type":"Point"}
}