{
  "type": "Feature",
  "properties": {
    "iso:country":"US",
    "sg:address":"847 S Randall Rd",
    "sg:city":"Elgin",
    "sg:phone":"+1 847 697 9900",
    "sg:postcode":"60123",
    "sg:province":"IL",
    "wof:name":"Landscape Innovations",
    "wof:placetype":"venue"
},
  "geometry": {"coordinates":[-88.33620000000001,42.012436],"type":"Point"}
}