{
  "type": "Feature",
  "properties": {
    "iso:country":"US",
    "sg:address":"506 S Main St",
    "sg:city":"Anna",
    "sg:classifiers":[
        {
            "category":"Building & Trades",
            "subcategory":"Construction",
            "type":"Services"
        }
    ],
    "sg:phone":"+1 618 833 8309",
    "sg:postcode":"62906",
    "sg:province":"IL",
    "sg:tags":[
        "house"
    ],
    "wof:name":"Waller Construction",
    "wof:placetype":"venue"
},
  "geometry": {"coordinates":[-89.252133,37.457961],"type":"Point"}
}