{
  "type": "Feature",
  "properties": {
    "addr:full":"2220 W Homer St Chicago IL 60647",
    "addr:housenumber":"2220",
    "addr:postcode":"60647",
    "addr:street":"W Homer St",
    "iso:country":"US",
    "sg:address":"2220 W Homer St",
    "sg:city":"Chicago",
    "sg:classifiers":[
        {
            "category":"Professional",
            "type":"Services"
        }
    ],
    "sg:phone":"+1 312 399 8719",
    "sg:postcode":"60647",
    "sg:province":"IL",
    "sg:tags":[
        "establishment"
    ],
    "wof:name":"Bacchus Inc",
    "wof:placetype":"venue"
},
  "geometry": {"coordinates":[-87.682502,41.916895],"type":"Point"}
}