{
  "type": "Feature",
  "properties": {
    "iso:country":"US",
    "sg:address":"5419 Kenosha St",
    "sg:city":"Richmond",
    "sg:classifiers":[
        {
            "category":"Sports & Exercise",
            "subcategory":"Golf",
            "type":"Entertainment"
        }
    ],
    "sg:phone":"+1 815 678 3000",
    "sg:postcode":"60071",
    "sg:province":"IL",
    "sg:tags":[
        "course"
    ],
    "wof:name":"Hunter Country Club Inc",
    "wof:placetype":"venue"
},
  "geometry": {"coordinates":[-88.302854,42.479708],"type":"Point"}
}