{
  "type": "Feature",
  "properties": {
    "iso:country":"US",
    "sg:address":"2511 State St",
    "sg:city":"Alton",
    "sg:classifiers":[
        {
            "category":"Recreation",
            "type":"Entertainment"
        }
    ],
    "sg:phone":"+1 618 467 2477",
    "sg:postcode":"62002",
    "sg:province":"IL",
    "sg:tags":[
        "martial",
        "arts",
        "instruction"
    ],
    "wof:name":"Citong Shaolin Wushu Kung Fu",
    "wof:placetype":"venue"
},
  "geometry": {"coordinates":[-90.192432,38.919944],"type":"Point"}
}