{
  "type": "Feature",
  "properties": {
    "iso:country":"US",
    "sg:address":"9613 S. Western Ave",
    "sg:city":"Chicago",
    "sg:classifiers":[
        {
            "category":"Restaurant",
            "type":"Food & Drink"
        }
    ],
    "sg:phone":"+1 773 445 6255",
    "sg:postcode":"60643",
    "sg:province":"IL",
    "sg:tags":[
        "pizza"
    ],
    "wof:name":"Gianna's Pizza",
    "wof:placetype":"venue"
},
  "geometry": {"coordinates":[-87.681924,41.718742],"type":"Point"}
}