{
  "type": "Feature",
  "properties": {
    "iso:country":"US",
    "sg:address":"1529 Locust St",
    "sg:city":"Quincy",
    "sg:classifiers":[
        {
            "category":"Professional",
            "type":"Services"
        },
        {
            "category":"Government",
            "subcategory":"Office",
            "type":"Public Place"
        }
    ],
    "sg:phone":"+1 217 224 7438",
    "sg:postcode":"62301",
    "sg:province":"IL",
    "sg:tags":[
        "housing",
        "specialty",
        "outpatient",
        "clinic",
        "program",
        "establishment"
    ],
    "wof:name":"Community Village",
    "wof:placetype":"venue"
},
  "geometry": {"coordinates":[-91.39169,39.950484],"type":"Point"}
}