{
  "type": "Feature",
  "properties": {
    "iso:country":"US",
    "sg:address":"11529 Five Points St",
    "sg:city":"Tallula",
    "sg:classifiers":[
        {
            "category":"Manufacturing",
            "subcategory":"Food",
            "type":"Manufacturing & Wholesale Goods"
        },
        {
            "category":"Farming",
            "subcategory":"Farm",
            "type":"Manufacturing & Wholesale Goods"
        }
    ],
    "sg:phone":"+1 217 632 3567",
    "sg:postcode":"62688",
    "sg:province":"IL",
    "sg:tags":[
        "corn",
        "product"
    ],
    "wof:name":"Gerald Miller",
    "wof:placetype":"venue"
},
  "geometry": {"coordinates":[-89.882759,39.923322],"type":"Point"}
}