{
  "type": "Feature",
  "properties": {
    "iso:country":"US",
    "sg:address":"301 S 3rd St",
    "sg:city":"Vandalia",
    "sg:classifiers":[
        {
            "category":"Government",
            "subcategory":"Office",
            "type":"Public Place"
        }
    ],
    "sg:phone":"+1   ",
    "sg:postcode":"62471",
    "sg:province":"IL",
    "sg:tags":[
        "use",
        "land",
        "commodity",
        "related",
        "program",
        "administers"
    ],
    "wof:name":"Farm Service Agency",
    "wof:placetype":"venue"
},
  "geometry": {"coordinates":[-89.093284,38.959595],"type":"Point"}
}