{
  "type": "Feature",
  "properties": {
    "addr:full":"745 S Oakley Boulevard Chicago IL 60612",
    "addr:housenumber":"745",
    "addr:postcode":"60612",
    "addr:street":"S Oakley Boulevard",
    "iso:country":"US",
    "sg:address":"745 S Oakley Boulevard",
    "sg:city":"Chicago",
    "sg:classifiers":[
        {
            "category":"Education",
            "subcategory":"School",
            "type":"Public Place"
        }
    ],
    "sg:phone":"+1 773 534 7295",
    "sg:postcode":"60612",
    "sg:province":"IL",
    "sg:tags":[
        "high",
        "middle",
        "elementary"
    ],
    "wof:name":"Schools Public",
    "wof:placetype":"venue"
},
  "geometry": {"coordinates":[-87.683567,41.871956],"type":"Point"}
}