{
  "type": "Feature",
  "properties": {
    "iso:country":"US",
    "sg:address":"3707 Sauk Trl",
    "sg:city":"Richton Park",
    "sg:classifiers":[
        {
            "category":"Shopping",
            "subcategory":"Computers & Home Electronics",
            "type":"Retail Goods"
        }
    ],
    "sg:phone":"+1   ",
    "sg:postcode":"60471",
    "sg:province":"IL",
    "wof:name":"Systems Beyond Computers Inc",
    "wof:placetype":"venue"
},
  "geometry": {"coordinates":[-87.70620599999999,41.484271],"type":"Point"}
}