{
  "type": "Feature",
  "properties": {
    "iso:country":"US",
    "sg:address":"523 Cowles Ave",
    "sg:city":"Joliet",
    "sg:classifiers":[
        {
            "category":"Shopping",
            "subcategory":"Computers & Home Electronics",
            "type":"Retail Goods"
        }
    ],
    "sg:phone":"+1 815 723 5711",
    "sg:postcode":"60435",
    "sg:province":"IL",
    "sg:tags":[
        "equipment",
        "dealer"
    ],
    "wof:name":"Aztron Computer Svc",
    "wof:placetype":"venue"
},
  "geometry": {"coordinates":[-88.106112,41.533615],"type":"Point"}
}