{
  "type": "Feature",
  "properties": {
    "iso:country":"US",
    "sg:address":"5664 N Lincoln Ave",
    "sg:city":"Chicago",
    "sg:classifiers":[
        {
            "category":"Restaurant",
            "type":"Food & Drink"
        }
    ],
    "sg:phone":"+1 773 784 0566",
    "sg:postcode":"60659",
    "sg:province":"IL",
    "sg:tags":[
        "chinese"
    ],
    "wof:name":"How Lee Chop Suey",
    "wof:placetype":"venue"
},
  "geometry": {"coordinates":[-87.69699900000001,41.9842],"type":"Point"}
}