{
  "type": "Feature",
  "properties": {
    "iso:country":"US",
    "sg:address":"604 W Johnson St",
    "sg:city":"Collinsville",
    "sg:classifiers":[
        {
            "category":"Social Services",
            "subcategory":"Child Care",
            "type":"Services"
        }
    ],
    "sg:phone":"+1 618 345 9915",
    "sg:postcode":"62234",
    "sg:province":"IL",
    "sg:tags":[
        "day"
    ],
    "wof:name":"Priscilla's Daycare",
    "wof:placetype":"venue"
},
  "geometry": {"coordinates":[-89.993452,38.672544],"type":"Point"}
}