{
  "type": "Feature",
  "properties": {
    "addr:full":"4118 Harrison Ave Rockford IL 61108",
    "addr:housenumber":"4118",
    "addr:postcode":"61108",
    "addr:street":"Harrison Ave",
    "iso:country":"US",
    "sg:address":"4118 Harrison Ave",
    "sg:city":"Rockford",
    "sg:classifiers":[
        {
            "category":"Retail",
            "subcategory":"Car Wash",
            "type":"Services"
        }
    ],
    "sg:phone":"+1 815 395 8155",
    "sg:postcode":"61108",
    "sg:province":"IL",
    "sg:tags":[
        "carwash"
    ],
    "wof:name":"Super Wash of Harrison",
    "wof:placetype":"venue"
},
  "geometry": {"coordinates":[-89.03152,42.238321],"type":"Point"}
}