{
  "type": "Feature",
  "properties": {
    "iso:country":"US",
    "sg:address":"1234 S Michigan Ave 2nd Fl",
    "sg:city":"Chicago",
    "sg:classifiers":[
        {
            "category":"Education",
            "subcategory":"Dance Studio",
            "type":"Public Place"
        },
        {
            "category":"Arts & Performance",
            "subcategory":"Dance",
            "type":"Entertainment"
        }
    ],
    "sg:phone":"+1 312 765 6755",
    "sg:postcode":"60605",
    "sg:province":"IL",
    "sg:tags":[
        "school"
    ],
    "sg:website":"www.intriguedance.com",
    "wof:name":"Intrigue Dance",
    "wof:placetype":"venue"
},
  "geometry": {"coordinates":[-87.624619,41.866854],"type":"Point"}
}