{
  "type": "Feature",
  "properties": {
    "addr:full":"1123 W Webster Ave Chicago IL 60614",
    "addr:housenumber":"1123",
    "addr:postcode":"60614",
    "addr:street":"W Webster Ave",
    "iso:country":"US",
    "sg:address":"1123 W Webster Ave",
    "sg:city":"Chicago",
    "sg:classifiers":[
        {
            "category":"Personal",
            "subcategory":"Beauty Salon",
            "type":"Services"
        }
    ],
    "sg:phone":"+1 773 327 1130",
    "sg:postcode":"60614",
    "sg:province":"IL",
    "sg:tags":[
        "hair"
    ],
    "wof:name":"Strand",
    "wof:placetype":"venue"
},
  "geometry": {"coordinates":[-87.656862,41.921425],"type":"Point"}
}