{
  "type": "Feature",
  "properties": {
    "iso:country":"US",
    "sg:address":"3510 Harrison Ave",
    "sg:city":"Rockford",
    "sg:classifiers":[
        {
            "category":"Professional",
            "subcategory":"Computer Services",
            "type":"Services"
        }
    ],
    "sg:phone":"+1 815 298 1597",
    "sg:postcode":"61108",
    "sg:province":"IL",
    "sg:tags":[
        "preparation",
        "processing",
        "datum"
    ],
    "wof:name":"Patterson Luanda L",
    "wof:placetype":"venue"
},
  "geometry": {"coordinates":[-89.039475,42.238151],"type":"Point"}
}