{
  "type": "Feature",
  "properties": {
    "iso:country":"US",
    "sg:address":"339 N Milwaukee Ave",
    "sg:city":"Libertyville",
    "sg:classifiers":[
        {
            "category":"Professional",
            "subcategory":"Secretarial Services",
            "type":"Services"
        }
    ],
    "sg:phone":"+1 847 680 7794",
    "sg:postcode":"60048",
    "sg:province":"IL",
    "sg:tags":[
        "reporting",
        "word",
        "processing"
    ],
    "wof:name":"Bytewackers",
    "wof:placetype":"venue"
},
  "geometry": {"coordinates":[-87.95402,42.286026],"type":"Point"}
}