{
  "type": "Feature",
  "properties": {
    "iso:country":"US",
    "sg:address":"6464 W Main St Ste 1B",
    "sg:city":"Belleville",
    "sg:classifiers":[
        {
            "category":"Professional",
            "subcategory":"Lawyer & Legal Services",
            "type":"Services"
        }
    ],
    "sg:phone":"+1 618 398 7027",
    "sg:postcode":"62223",
    "sg:province":"IL",
    "sg:tags":[
        "attorney",
        "law",
        "personal",
        "labor",
        "plan",
        "injury",
        "employment",
        "insurance"
    ],
    "wof:name":"A Law Office For Accidents",
    "wof:placetype":"venue"
},
  "geometry": {"coordinates":[-90.039742,38.553754],"type":"Point"}
}