{
  "type": "Feature",
  "properties": {
    "addr:full":"5793 State Rte 78 Virginia IL 62691",
    "addr:housenumber":"5793",
    "addr:postcode":"62691",
    "addr:street":"State Rte 78",
    "iso:country":"US",
    "sg:address":"5793 State Rte 78",
    "sg:city":"Virginia",
    "sg:classifiers":[
        {
            "category":"Retail",
            "subcategory":"Veterinary Services",
            "type":"Services"
        }
    ],
    "sg:phone":"+1 217 452 7292",
    "sg:postcode":"62691",
    "sg:province":"IL",
    "wof:name":"Cass Veterinary Services Inc",
    "wof:placetype":"venue"
},
  "geometry": {"coordinates":[-90.207352,39.953434],"type":"Point"}
}