{
  "type": "Feature",
  "properties": {
    "iso:country":"US",
    "sg:address":"2102 E B St",
    "sg:city":"Belleville",
    "sg:classifiers":[
        {
            "category":"Home & Garden",
            "subcategory":"Building Materials",
            "type":"Retail Goods"
        },
        {
            "category":"Professional",
            "subcategory":"Business Services",
            "type":"Services"
        }
    ],
    "sg:phone":"+1 618 277 7080",
    "sg:postcode":"62221",
    "sg:province":"IL",
    "sg:tags":[
        "door"
    ],
    "wof:name":"Cox Interior Supply Inc",
    "wof:placetype":"venue"
},
  "geometry": {"coordinates":[-89.957347,38.526932],"type":"Point"}
}