{
  "type": "Feature",
  "properties": {
    "addr:full":"413 Columbine Ln Bolingbrook IL 60440",
    "addr:housenumber":"413",
    "addr:postcode":"60440",
    "addr:street":"Columbine Ln",
    "iso:country":"US",
    "sg:address":"413 Columbine Ln",
    "sg:city":"Bolingbrook",
    "sg:classifiers":[
        {
            "category":"Professional",
            "subcategory":"Business Services",
            "type":"Services"
        }
    ],
    "sg:phone":"+1 630 378 9219",
    "sg:postcode":"60440",
    "sg:province":"IL",
    "sg:tags":[
        "drafting"
    ],
    "wof:name":"Aircad Inc",
    "wof:placetype":"venue"
},
  "geometry": {"coordinates":[-88.08298600000001,41.688031],"type":"Point"}
}