{
  "type": "Feature",
  "properties": {
    "addr:full":"1102 E Dundee Rd Palatine IL 60074",
    "addr:housenumber":"1102",
    "addr:postcode":"60074",
    "addr:street":"E Dundee Rd",
    "iso:country":"US",
    "sg:address":"1102 E Dundee Rd",
    "sg:city":"Palatine",
    "sg:classifiers":[
        {
            "category":"Retail",
            "subcategory":"Auto Rental",
            "type":"Services"
        }
    ],
    "sg:phone":"+1 847 202 6410",
    "sg:postcode":"60074",
    "sg:province":"IL",
    "sg:tags":[
        "passenger",
        "car"
    ],
    "wof:name":"Enterprise Rent-A-Car",
    "wof:placetype":"venue"
},
  "geometry": {"coordinates":[-88.014146,42.139141],"type":"Point"}
}