{
  "type": "Feature",
  "properties": {
    "iso:country":"US",
    "sg:address":"600 Valley View Dr",
    "sg:city":"Moline",
    "sg:classifiers":[
        {
            "category":"Health Services",
            "subcategory":"Doctor",
            "type":"Services"
        }
    ],
    "sg:phone":"+1 309 762 2106",
    "sg:postcode":"61265",
    "sg:province":"IL",
    "sg:tags":[
        "medical"
    ],
    "wof:name":"Joc Doc",
    "wof:placetype":"venue"
},
  "geometry": {"coordinates":[-90.395384,41.49892],"type":"Point"}
}