{
  "type": "Feature",
  "properties": {
    "iso:country":"US",
    "sg:address":"1595 Weld Rd",
    "sg:city":"Elgin",
    "sg:classifiers":[
        {
            "category":"Banks & Credit Unions",
            "subcategory":"Bank",
            "type":"Services"
        }
    ],
    "sg:phone":"+1 847 888 9300",
    "sg:postcode":"60123",
    "sg:province":"IL",
    "sg:tags":[
        "loan",
        "real estate"
    ],
    "sg:website":"www.casementmortgage.com",
    "wof:name":"Casement Group",
    "wof:placetype":"venue"
},
  "geometry": {"coordinates":[-88.32,42.025631],"type":"Point"}
}