{
  "type": "Feature",
  "properties": {
    "iso:country":"US",
    "sg:address":"4201 Columbus St",
    "sg:city":"Ottawa",
    "sg:classifiers":[
        {
            "category":"Professional",
            "subcategory":"Management & Consulting",
            "type":"Services"
        },
        {
            "category":"Farming",
            "subcategory":"Farm",
            "type":"Manufacturing & Wholesale Goods"
        }
    ],
    "sg:phone":"+1 815 433 1635",
    "sg:postcode":"61350",
    "sg:province":"IL",
    "wof:name":"Lasalle County Farm Bureau",
    "wof:placetype":"venue"
},
  "geometry": {"coordinates":[-88.835899,41.382453],"type":"Point"}
}