{
  "type": "Feature",
  "properties": {
    "addr:full":"3035 W George St Chicago IL 60618",
    "addr:housenumber":"3035",
    "addr:postcode":"60618",
    "addr:street":"W George St",
    "iso:country":"US",
    "sg:address":"3035 W George St",
    "sg:city":"Chicago",
    "sg:classifiers":[
        {
            "category":"Food & Beverages",
            "subcategory":"Groceries & Convenience Stores",
            "type":"Retail Goods"
        }
    ],
    "sg:postcode":"60618",
    "sg:province":"IL",
    "wof:name":"Bread & Butter",
    "wof:placetype":"venue"
},
  "geometry": {"coordinates":[-87.703965,41.93363],"type":"Point"}
}