{
  "type": "Feature",
  "properties": {
    "addr:full":"301 Wille Rd Des Plaines IL 60018",
    "addr:housenumber":"301",
    "addr:postcode":"60018",
    "addr:street":"Wille Rd Des",
    "iso:country":"US",
    "sg:address":"301 Wille Rd",
    "sg:city":"Des Plaines",
    "sg:classifiers":[
        {
            "category":"Retail",
            "subcategory":"Auto Rental",
            "type":"Services"
        }
    ],
    "sg:phone":"+1 847 298 1747",
    "sg:postcode":"60018",
    "sg:province":"IL",
    "sg:tags":[
        "semi",
        "trailer",
        "lease"
    ],
    "wof:name":"Tip Trailer Leasing",
    "wof:placetype":"venue"
},
  "geometry": {"coordinates":[-87.93034400000001,42.01907],"type":"Point"}
}