{
  "type": "Feature",
  "properties": {
    "addr:full":"1415 E Algonquin Rd Arlington Hts IL 60005",
    "addr:housenumber":"1415",
    "addr:postcode":"60005",
    "addr:street":"E Algonquin Rd",
    "iso:country":"US",
    "sg:address":"1415 E Algonquin Rd",
    "sg:city":"Arlington Hts",
    "sg:classifiers":[
        {
            "category":"Government",
            "subcategory":"Fire Station",
            "type":"Public Place"
        }
    ],
    "sg:phone":"+1 847 364 4236",
    "sg:postcode":"60005",
    "sg:province":"IL",
    "sg:tags":[
        "department"
    ],
    "wof:name":"Elk Grove Rural Fire Prtctn",
    "wof:placetype":"venue"
},
  "geometry": {"coordinates":[-87.951143,42.032179],"type":"Point"}
}