{
  "type": "Feature",
  "properties": {
    "iso:country":"US",
    "sg:address":"19 Main St",
    "sg:city":"Oswego",
    "sg:phone":"+1 630 554 6678",
    "sg:postcode":"60543",
    "sg:province":"IL",
    "wof:name":"Village Grind",
    "wof:placetype":"venue"
},
  "geometry": {"coordinates":[-88.351788,41.684523],"type":"Point"}
}