{
  "type": "Feature",
  "properties": {
    "iso:country":"US",
    "sg:address":"645 Trail 264A",
    "sg:city":"Jonesboro",
    "sg:classifiers":[
        {
            "category":"Manufacturing",
            "subcategory":"Buildings",
            "type":"Manufacturing & Wholesale Goods"
        },
        {
            "category":"Building & Trades",
            "subcategory":"Construction",
            "type":"Services"
        }
    ],
    "sg:phone":"+1 618 833 3383",
    "sg:postcode":"62952",
    "sg:province":"IL",
    "sg:tags":[
        "home",
        "builder",
        "contractor"
    ],
    "wof:name":"Randal Charles",
    "wof:placetype":"venue"
},
  "geometry": {"coordinates":[-89.334029,37.395868],"type":"Point"}
}