{
  "type": "Feature",
  "properties": {
    "addr:full":"8706 Harvest View Ln Tinley Park IL 60487",
    "addr:housenumber":"8706",
    "addr:postcode":"60487",
    "addr:street":"Harvest View Ln",
    "iso:country":"US",
    "sg:address":"8706 Harvest View Ln",
    "sg:city":"Tinley Park",
    "sg:classifiers":[
        {
            "category":"Professional",
            "subcategory":"Business Services",
            "type":"Services"
        }
    ],
    "sg:phone":"+1 815 464 6530",
    "sg:postcode":"60487",
    "sg:province":"IL",
    "wof:name":"Ramirez & Assoc",
    "wof:placetype":"venue"
},
  "geometry": {"coordinates":[-87.827792,41.536423],"type":"Point"}
}