{
  "type": "Feature",
  "properties": {
    "iso:country":"US",
    "sg:address":"1050 N Dodge St",
    "sg:city":"Galena",
    "sg:classifiers":[
        {
            "category":"Manufacturing",
            "subcategory":"Tools & Machinery",
            "type":"Manufacturing & Wholesale Goods"
        }
    ],
    "sg:phone":"+1 815 777 1366",
    "sg:postcode":"61036",
    "sg:province":"IL",
    "sg:tags":[
        "farm",
        "mfg"
    ],
    "wof:name":"Clinton White",
    "wof:placetype":"venue"
},
  "geometry": {"coordinates":[-90.416972,42.4227],"type":"Point"}
}