{
  "type": "Feature",
  "properties": {
    "iso:country":"US",
    "sg:address":"6239 Ogden Ave",
    "sg:city":"Berwyn",
    "sg:classifiers":[
        {
            "category":"Autos & Motor Vehicles",
            "subcategory":"Auto Supplies",
            "type":"Retail Goods"
        }
    ],
    "sg:phone":"+1 708 442 5045",
    "sg:postcode":"60402",
    "sg:province":"IL",
    "sg:tags":[
        "automobile",
        "parts"
    ],
    "wof:name":"Family Auto Parts",
    "wof:placetype":"venue"
},
  "geometry": {"coordinates":[-87.780417,41.831591],"type":"Point"}
}