{
  "type": "Feature",
  "properties": {
    "addr:full":"501 Belt Line Rd Collinsville IL 62234",
    "addr:housenumber":"501",
    "addr:postcode":"62234",
    "addr:street":"Belt Line Rd",
    "iso:country":"US",
    "sg:address":"501 Belt Line Rd",
    "sg:city":"Collinsville",
    "sg:classifiers":[
        {
            "category":"Insurance",
            "subcategory":"Health Insurance",
            "type":"Services"
        }
    ],
    "sg:phone":"+1 618 346 8845",
    "sg:postcode":"62234",
    "sg:province":"IL",
    "sg:tags":[
        "market"
    ],
    "sg:website":"www.gnc.com",
    "wof:name":"General Nutrition Center",
    "wof:placetype":"venue"
},
  "geometry": {"coordinates":[-89.97580000000001,38.691002],"type":"Point"}
}