{
  "type": "Feature",
  "properties": {
    "addr:full":"950 Lee St Des Plaines IL 60016",
    "addr:housenumber":"950",
    "addr:postcode":"60016",
    "addr:street":"Lee St",
    "iso:country":"US",
    "sg:address":"950 Lee St",
    "sg:city":"Des Plaines",
    "sg:classifiers":[
        {
            "category":"Manufacturing",
            "subcategory":"Tools & Machinery",
            "type":"Manufacturing & Wholesale Goods"
        }
    ],
    "sg:phone":"+1 847 297 8419",
    "sg:postcode":"60016",
    "sg:province":"IL",
    "sg:tags":[
        "physician",
        "surgeon"
    ],
    "wof:name":"Addition Technology",
    "wof:placetype":"venue"
},
  "geometry": {"coordinates":[-87.892791,42.035239],"type":"Point"}
}