{
  "type": "Feature",
  "properties": {
    "addr:full":"14855 West Ave Orland Park IL 60462",
    "addr:housenumber":"14855",
    "addr:postcode":"60462",
    "addr:street":"West Ave",
    "iso:country":"US",
    "sg:address":"14855 West Ave",
    "sg:city":"Orland Park",
    "sg:classifiers":[
        {
            "category":"Education",
            "subcategory":"School",
            "type":"Public Place"
        }
    ],
    "sg:phone":"+1 708 349 5319",
    "sg:postcode":"60462",
    "sg:province":"IL",
    "sg:tags":[
        "secondary"
    ],
    "wof:name":"Orland Junior High",
    "wof:placetype":"venue"
},
  "geometry": {"coordinates":[-87.863102,41.622495],"type":"Point"}
}