{
  "type": "Feature",
  "properties": {
    "addr:full":"6319 S King Drive Chicago IL 60637",
    "addr:housenumber":"6319",
    "addr:postcode":"60637",
    "addr:street":"S King Drive",
    "iso:country":"US",
    "sg:address":"6319 S King Drive",
    "sg:city":"Chicago",
    "sg:classifiers":[
        {
            "category":"Restaurant",
            "type":"Food & Drink"
        }
    ],
    "sg:phone":"+1 773 493 8928",
    "sg:postcode":"60637",
    "sg:province":"IL",
    "sg:tags":[
        "chinese"
    ],
    "wof:name":"Danies Chinese Food",
    "wof:placetype":"venue"
},
  "geometry": {"coordinates":[-87.615432,41.779619],"type":"Point"}
}