{
  "type": "Feature",
  "properties": {
    "addr:full":"2600 Central Park Ave Evanston IL 60201",
    "addr:housenumber":"2600",
    "addr:postcode":"60201",
    "addr:street":"Central Park Ave",
    "iso:country":"US",
    "sg:address":"2600 Central Park Ave",
    "sg:city":"Evanston",
    "sg:classifiers":[
        {
            "category":"Arts & Performance",
            "subcategory":"Art Gallery",
            "type":"Entertainment"
        },
        {
            "category":"Museum",
            "type":"Entertainment"
        }
    ],
    "sg:phone":"+1 847 475 1030",
    "sg:postcode":"60201",
    "sg:province":"IL",
    "sg:tags":[
        "consultant",
        "galleries"
    ],
    "wof:name":"Michell Museum of The American Indian",
    "wof:placetype":"venue"
},
  "geometry": {"coordinates":[-87.71779600000001,42.06451],"type":"Point"}
}