{
  "type": "Feature",
  "properties": {
    "iso:country":"US",
    "sg:address":"4302 W Crystal Lake Rd",
    "sg:city":"Mc Henry",
    "sg:classifiers":[
        {
            "category":"Professional",
            "subcategory":"Engineering",
            "type":"Services"
        },
        {
            "category":"Professional",
            "subcategory":"Management & Consulting",
            "type":"Services"
        }
    ],
    "sg:phone":"+1 815 385 6560",
    "sg:postcode":"60050",
    "sg:province":"IL",
    "sg:tags":[
        "business"
    ],
    "wof:name":"Illinois Roof Consulting Assoc",
    "wof:placetype":"venue"
},
  "geometry": {"coordinates":[-88.285645,42.338824],"type":"Point"}
}