{
  "type": "Feature",
  "properties": {
    "iso:country":"US",
    "sg:address":"7214 W Belmont Avenue",
    "sg:city":"Chicago",
    "sg:classifiers":[
        {
            "category":"Personal",
            "subcategory":"Beauty Salon",
            "type":"Services"
        }
    ],
    "sg:phone":"+1 773 637 8583",
    "sg:postcode":"60634",
    "sg:province":"IL",
    "sg:tags":[
        "hair"
    ],
    "wof:name":"Iza's Beauty Salon",
    "wof:placetype":"venue"
},
  "geometry": {"coordinates":[-87.80744,41.938011],"type":"Point"}
}