{
  "type": "Feature",
  "properties": {
    "iso:country":"US",
    "sg:address":"16006 875 East St",
    "sg:city":"Sheffield",
    "sg:classifiers":[
        {
            "category":"Shopping",
            "subcategory":"Bicycles & Sporting Goods",
            "type":"Retail Goods"
        }
    ],
    "sg:phone":"+1 815 454 2328",
    "sg:postcode":"61361",
    "sg:province":"IL",
    "sg:tags":[
        "equipment",
        "camping"
    ],
    "wof:name":"Department Of Natural Res",
    "wof:placetype":"venue"
},
  "geometry": {"coordinates":[-89.69171900000001,41.381836],"type":"Point"}
}