{
  "type": "Feature",
  "properties": {
    "addr:full":"1960 N Clybourn Ave Chicago IL 60614",
    "addr:housenumber":"1960",
    "addr:postcode":"60614",
    "addr:street":"N Clybourn Ave",
    "iso:country":"US",
    "sg:address":"1960 N Clybourn Ave",
    "sg:city":"Chicago",
    "sg:classifiers":[
        {
            "category":"Restaurant",
            "type":"Food & Drink"
        }
    ],
    "sg:phone":"+1 773 880 5256",
    "sg:postcode":"60614",
    "sg:province":"IL",
    "sg:tags":[
        "mexican"
    ],
    "sg:website":"www.lalos.com",
    "wof:name":"Lalo's",
    "wof:placetype":"venue"
},
  "geometry": {"coordinates":[-87.657613,41.916701],"type":"Point"}
}