{
  "type": "Feature",
  "properties": {
    "iso:country":"US",
    "sg:address":"41005 N Elime Rd",
    "sg:city":"Antioch",
    "sg:classifiers":[
        {
            "category":"Professional",
            "subcategory":"Research",
            "type":"Services"
        }
    ],
    "sg:phone":"+1 847 395 0227",
    "sg:postcode":"60002",
    "sg:province":"IL",
    "sg:tags":[
        "environmental",
        "ecological"
    ],
    "wof:name":"Midwest Power Vac Inc",
    "wof:placetype":"venue"
},
  "geometry": {"coordinates":[-88.138356,42.456077],"type":"Point"}
}