{
  "type": "Feature",
  "properties": {
    "iso:country":"US",
    "sg:address":"222 W Hubbard St. Suite 400",
    "sg:city":"Chicago",
    "sg:classifiers":[
        {
            "category":"Professional",
            "subcategory":"Advertising",
            "type":"Services"
        }
    ],
    "sg:phone":"+1 312 397 3330",
    "sg:postcode":"60654",
    "sg:province":"IL",
    "sg:tags":[
        "advertising",
        "marketing",
        "media",
        "online-advertising"
    ],
    "sg:website":"http://www.centro.net",
    "wof:name":"Centro",
    "wof:placetype":"venue"
},
  "geometry": {"coordinates":[-87.634274,41.890054],"type":"Point"}
}