{
  "type": "Feature",
  "properties": {
    "addr:full":"1823 N 40th St East St Louis IL 62204",
    "addr:housenumber":"1823",
    "addr:postcode":"62204",
    "addr:street":"N 40Th St",
    "iso:country":"US",
    "sg:address":"1823 N 40th St",
    "sg:city":"East St Louis",
    "sg:classifiers":[
        {
            "category":"Food & Beverages",
            "subcategory":"Groceries & Convenience Stores",
            "type":"Retail Goods"
        }
    ],
    "sg:phone":"+1 618 482 3007",
    "sg:postcode":"62204",
    "sg:province":"IL",
    "sg:tags":[
        "grocer"
    ],
    "wof:name":"Forty Street Market",
    "wof:placetype":"venue"
},
  "geometry": {"coordinates":[-90.10866799999999,38.634588],"type":"Point"}
}