{
  "type": "Feature",
  "properties": {
    "addr:full":"8623 W Bryn Mawr Ave Ste 502 Chicago IL 60631",
    "addr:housenumber":"8623",
    "addr:postcode":"60631",
    "addr:street":"W Bryn Mawr Ave Ste 502",
    "iso:country":"US",
    "sg:address":"8623 W Bryn Mawr Ave Ste 502",
    "sg:city":"Chicago",
    "sg:classifiers":[
        {
            "category":"Shopping",
            "subcategory":"Optician",
            "type":"Retail Goods"
        }
    ],
    "sg:phone":"+1 773 867 0380",
    "sg:postcode":"60631",
    "sg:province":"IL",
    "sg:tags":[
        "eyewear"
    ],
    "sg:website":"www.functionalvisionanalyzer.com",
    "wof:name":"Stereo Optical",
    "wof:placetype":"venue"
},
  "geometry": {"coordinates":[-87.842069,41.980897],"type":"Point"}
}