{
  "type": "Feature",
  "properties": {
    "iso:country":"US",
    "sg:address":"1721 S Belt W",
    "sg:city":"Belleville",
    "sg:classifiers":[
        {
            "category":"Food & Beverages",
            "subcategory":"Groceries & Convenience Stores",
            "type":"Retail Goods"
        }
    ],
    "sg:phone":"+1 618 233 1988",
    "sg:postcode":"62226",
    "sg:province":"IL",
    "wof:name":"Beltline Mart",
    "wof:placetype":"venue"
},
  "geometry": {"coordinates":[-90.007812,38.515672],"type":"Point"}
}