{
  "type": "Feature",
  "properties": {
    "addr:full":"7520 N Albany Ave Chicago IL 60645",
    "addr:housenumber":"7520",
    "addr:postcode":"60645",
    "addr:street":"N Albany Ave",
    "iso:country":"US",
    "sg:address":"7520 N Albany Ave",
    "sg:city":"Chicago",
    "sg:classifiers":[
        {
            "category":"Health Services",
            "subcategory":"Doctor",
            "type":"Services"
        }
    ],
    "sg:phone":"+1 773 764 7079",
    "sg:postcode":"60645",
    "sg:province":"IL",
    "sg:tags":[
        "medical"
    ],
    "wof:name":"Leonard Pomper MD",
    "wof:placetype":"venue"
},
  "geometry": {"coordinates":[-87.706756,42.01814],"type":"Point"}
}