{
  "type": "Feature",
  "properties": {
    "iso:country":"US",
    "sg:address":"406 N 74th St",
    "sg:city":"East St Louis",
    "sg:classifiers":[
        {
            "category":"Freight",
            "type":"Transportation"
        }
    ],
    "sg:phone":"+1 618 398 9820",
    "sg:postcode":"62203",
    "sg:province":"IL",
    "sg:tags":[
        "delivery"
    ],
    "wof:name":"C & R Delivery",
    "wof:placetype":"venue"
},
  "geometry": {"coordinates":[-90.08024,38.590046],"type":"Point"}
}