{
  "type": "Feature",
  "properties": {
    "iso:country":"US",
    "sg:address":"2526 W Armitage Ave",
    "sg:city":"Chicago",
    "sg:classifiers":[
        {
            "category":"Shopping",
            "subcategory":"Pets & Pet Supplies",
            "type":"Retail Goods"
        }
    ],
    "sg:phone":"+1 312 564 4570",
    "sg:postcode":"60647",
    "sg:province":"IL",
    "sg:tags":[
        "training"
    ],
    "sg:website":"www.animalsense.com",
    "wof:name":"AnimalSense Canine Training and Behavior",
    "wof:placetype":"venue"
},
  "geometry": {"coordinates":[-87.69108,41.917557],"type":"Point"}
}