{
  "type": "Feature",
  "properties": {
    "iso:country":"US",
    "sg:address":"560 Crescent Blvd",
    "sg:city":"Glen Ellyn",
    "sg:classifiers":[
        {
            "category":"Shopping",
            "subcategory":"Bicycles & Sporting Goods",
            "type":"Retail Goods"
        }
    ],
    "sg:phone":"+1 630 858 7844",
    "sg:postcode":"60137",
    "sg:province":"IL",
    "sg:tags":[
        "tackle",
        "fishing"
    ],
    "sg:website":"www.flyfield.com",
    "wof:name":"Fly-N-Field",
    "wof:placetype":"venue"
},
  "geometry": {"coordinates":[-88.063367,41.877152],"type":"Point"}
}