{
  "type": "Feature",
  "properties": {
    "iso:country":"US",
    "sg:address":"12225 S Emerald Ave",
    "sg:city":"Chicago",
    "sg:classifiers":[
        {
            "category":"Organizations",
            "subcategory":"Religious Organization",
            "type":"Services"
        }
    ],
    "sg:phone":"+1 773 660 9266",
    "sg:postcode":"60628",
    "sg:province":"IL",
    "wof:name":"Christ the Rock Full Gospel Holiness Church",
    "wof:placetype":"venue"
},
  "geometry": {"coordinates":[-87.640297,41.671299],"type":"Point"}
}