{
  "type": "Feature",
  "properties": {
    "addr:full":"378 E Tanner St Waverly IL 62692",
    "addr:housenumber":"378",
    "addr:postcode":"62692",
    "addr:street":"E Tanner St",
    "iso:country":"US",
    "sg:address":"378 E Tanner St",
    "sg:city":"Waverly",
    "sg:classifiers":[
        {
            "category":"Shopping",
            "type":"Retail Goods"
        }
    ],
    "sg:phone":"+1 217 435 3801",
    "sg:postcode":"62692",
    "sg:province":"IL",
    "sg:tags":[
        "monument"
    ],
    "wof:name":"Waverly Monument Co",
    "wof:placetype":"venue"
},
  "geometry": {"coordinates":[-89.947427,39.589656],"type":"Point"}
}