{
  "type": "Feature",
  "properties": {
    "addr:full":"6255 S Archer Rd Summit Argo IL 60501",
    "addr:housenumber":"6255",
    "addr:postcode":"60501",
    "addr:street":"S Archer Rd",
    "iso:country":"US",
    "sg:address":"6255 S Archer Rd",
    "sg:city":"Summit Argo",
    "sg:classifiers":[
        {
            "category":"Restaurant",
            "type":"Food & Drink"
        }
    ],
    "sg:phone":"+1 708 458 1117",
    "sg:postcode":"60501",
    "sg:province":"IL",
    "sg:tags":[
        "pizza"
    ],
    "wof:name":"Orsi's Pizza",
    "wof:placetype":"venue"
},
  "geometry": {"coordinates":[-87.813822,41.777479],"type":"Point"}
}