{
  "type": "Feature",
  "properties": {
    "addr:full":"1317 W Concord Pl Chicago IL 60642",
    "addr:housenumber":"1317",
    "addr:postcode":"60642",
    "addr:street":"W Concord Pl",
    "iso:country":"US",
    "sg:address":"1317 W Concord Pl",
    "sg:city":"Chicago",
    "sg:classifiers":[
        {
            "category":"Building & Trades",
            "subcategory":"Construction",
            "type":"Services"
        }
    ],
    "sg:phone":"+1 773 227 6323",
    "sg:postcode":"60642",
    "sg:province":"IL",
    "sg:tags":[
        "management"
    ],
    "wof:name":"Concord Construction & Management Inc",
    "wof:placetype":"venue"
},
  "geometry": {"coordinates":[-87.66116700000001,41.912415],"type":"Point"}
}