{
  "type": "Feature",
  "properties": {
    "addr:full":"619 N Midlothian Rd Mundelein IL 60060",
    "addr:housenumber":"619",
    "addr:postcode":"60060",
    "addr:street":"N Midlothian Rd",
    "iso:country":"US",
    "sg:address":"619 N Midlothian Rd",
    "sg:city":"Mundelein",
    "sg:classifiers":[
        {
            "category":"Retail",
            "subcategory":"Laundry & Dry Cleaning",
            "type":"Services"
        }
    ],
    "sg:phone":"+1 847 949 7277",
    "sg:postcode":"60060",
    "sg:province":"IL",
    "sg:tags":[
        "drycleaning",
        "plant",
        "coin"
    ],
    "wof:name":"Millers Dry Cleaning & Laundry",
    "wof:placetype":"venue"
},
  "geometry": {"coordinates":[-88.018754,42.274219],"type":"Point"}
}