{
  "type": "Feature",
  "properties": {
    "addr:full":"595 Paxton Ave Calumet City IL 60409",
    "addr:housenumber":"595",
    "addr:postcode":"60409",
    "addr:street":"Paxton Ave",
    "iso:country":"US",
    "sg:address":"595 Paxton Ave",
    "sg:city":"Calumet City",
    "sg:classifiers":[
        {
            "category":"Organizations",
            "subcategory":"Labor Organization",
            "type":"Services"
        }
    ],
    "sg:phone":"+1 708 868 2043",
    "sg:postcode":"60409",
    "sg:province":"IL",
    "wof:name":"Sutton Sonja L Rn Lc",
    "wof:placetype":"venue"
},
  "geometry": {"coordinates":[-87.56872799999999,41.619128],"type":"Point"}
}