{
  "type": "Feature",
  "properties": {
    "iso:country":"US",
    "sg:address":"211 S Bowman Ave",
    "sg:city":"Danville",
    "sg:classifiers":[
        {
            "category":"Wholesale",
            "subcategory":"Groceries",
            "type":"Manufacturing & Wholesale Goods"
        }
    ],
    "sg:phone":"+1 217 446 0123",
    "sg:postcode":"61832",
    "sg:province":"IL",
    "sg:tags":[
        "beverage"
    ],
    "wof:name":"Pepsi Cola Gen Bottlers Inc",
    "wof:placetype":"venue"
},
  "geometry": {"coordinates":[-87.611581,40.122808],"type":"Point"}
}