{
  "type": "Feature",
  "properties": {
    "addr:full":"3429 W Diversey Ave Ste 208 Chicago IL 60647",
    "addr:housenumber":"3429",
    "addr:postcode":"60647",
    "addr:street":"W Diversey Ave Ste 208",
    "iso:country":"US",
    "sg:address":"3429 W Diversey Ave Ste 208",
    "sg:city":"Chicago",
    "sg:classifiers":[
        {
            "category":"Arts & Performance",
            "subcategory":"Arts Center",
            "type":"Entertainment"
        },
        {
            "category":"Education",
            "subcategory":"School",
            "type":"Public Place"
        },
        {
            "category":"Cinema",
            "subcategory":"Movie Theater",
            "type":"Entertainment"
        }
    ],
    "sg:phone":"+1 773 782 9471",
    "sg:postcode":"60647",
    "sg:province":"IL",
    "sg:tags":[
        "theatrical",
        "consultant"
    ],
    "sg:website":"www.voiceofthecity.org",
    "wof:name":"Voice of the City",
    "wof:placetype":"venue"
},
  "geometry": {"coordinates":[-87.712959,41.931957],"type":"Point"}
}