{
  "type": "Feature",
  "properties": {
    "addr:full":"6100 W. Belmont Ave Chicago IL 60634",
    "addr:housenumber":"6100",
    "addr:postcode":"60634",
    "addr:street":"W. Belmont Ave",
    "iso:country":"US",
    "sg:address":"6100 W. Belmont Ave",
    "sg:city":"Chicago",
    "sg:classifiers":[
        {
            "category":"Fast Food",
            "type":"Food & Drink"
        }
    ],
    "sg:phone":"+1 773 283 8722",
    "sg:postcode":"60634",
    "sg:province":"IL",
    "wof:name":"The Dog Stop",
    "wof:placetype":"venue"
},
  "geometry": {"coordinates":[-87.778764,41.938411],"type":"Point"}
}