{
  "type": "Feature",
  "properties": {
    "addr:full":"6007 Chestnut Ct Crystal Lake IL 60014",
    "addr:housenumber":"6007",
    "addr:postcode":"60014",
    "addr:street":"Chestnut Ct",
    "iso:country":"US",
    "sg:address":"6007 Chestnut Ct",
    "sg:city":"Crystal Lake",
    "sg:classifiers":[
        {
            "category":"Wholesale",
            "subcategory":"Construction Materials",
            "type":"Manufacturing & Wholesale Goods"
        }
    ],
    "sg:phone":"+1 815 459 8387",
    "sg:postcode":"60014",
    "sg:province":"IL",
    "sg:tags":[
        "fence"
    ],
    "wof:name":"Wilson's Fencing Svc Inc",
    "wof:placetype":"venue"
},
  "geometry": {"coordinates":[-88.379953,42.241327],"type":"Point"}
}