{
  "type": "Feature",
  "properties": {
    "addr:full":"1012 N Rohlwing Rd Addison IL 60101",
    "addr:housenumber":"1012",
    "addr:postcode":"60101",
    "addr:street":"N Rohlwing Rd",
    "iso:country":"US",
    "sg:address":"1012 N Rohlwing Rd",
    "sg:city":"Addison",
    "sg:classifiers":[
        {
            "category":"Fast Food",
            "type":"Food & Drink"
        },
        {
            "category":"Food & Beverages",
            "subcategory":"Meat & Fish",
            "type":"Retail Goods"
        }
    ],
    "sg:phone":"+1 630 705 9078",
    "sg:postcode":"60101",
    "sg:province":"IL",
    "sg:tags":[
        "burger",
        "hot",
        "dog"
    ],
    "sg:website":"www.burgerking.com",
    "wof:name":"Burger King",
    "wof:placetype":"venue"
},
  "geometry": {"coordinates":[-88.032084,41.94767],"type":"Point"}
}