{
  "type": "Feature",
  "properties": {
    "addr:full":"566 Collins St Joliet IL 60432",
    "addr:housenumber":"566",
    "addr:postcode":"60432",
    "addr:street":"Collins St",
    "iso:country":"US",
    "sg:address":"566 Collins St",
    "sg:city":"Joliet",
    "sg:classifiers":[
        {
            "category":"Freight",
            "type":"Transportation"
        }
    ],
    "sg:phone":"+1 815 723 9526",
    "sg:postcode":"60432",
    "sg:province":"IL",
    "sg:tags":[
        "delivery"
    ],
    "wof:name":"Order Express",
    "wof:placetype":"venue"
},
  "geometry": {"coordinates":[-88.072604,41.534942],"type":"Point"}
}