{
  "type": "Feature",
  "properties": {
    "iso:country":"US",
    "sg:address":"24393 Litwiller Rd",
    "sg:city":"Delavan",
    "sg:classifiers":[
        {
            "category":"Building & Trades",
            "subcategory":"Construction",
            "type":"Services"
        }
    ],
    "sg:phone":"+1 309 244 7853",
    "sg:postcode":"61734",
    "sg:province":"IL",
    "sg:tags":[
        "general",
        "contractor"
    ],
    "wof:name":"Hodges Construction",
    "wof:placetype":"venue"
},
  "geometry": {"coordinates":[-89.45710800000001,40.366263],"type":"Point"}
}