{
  "type": "Feature",
  "properties": {
    "iso:country":"US",
    "sg:address":"1764 N Clark St",
    "sg:city":"Chicago",
    "sg:classifiers":[
        {
            "category":"Real Estate",
            "subcategory":"Real Estate Services",
            "type":"Services"
        }
    ],
    "sg:phone":"+1 312 337 5142",
    "sg:postcode":"60614",
    "sg:province":"IL",
    "sg:tags":[
        "management",
        "property"
    ],
    "wof:name":"Triangle Management Co",
    "wof:placetype":"venue"
},
  "geometry": {"coordinates":[-87.63359800000001,41.9146],"type":"Point"}
}