{
  "type": "Feature",
  "properties": {
    "iso:country":"US",
    "sg:address":"105 N College St",
    "sg:city":"Assumption",
    "sg:classifiers":[
        {
            "category":"Education",
            "subcategory":"School",
            "type":"Public Place"
        }
    ],
    "sg:phone":"+1 217 226 4022",
    "sg:postcode":"62510",
    "sg:province":"IL",
    "sg:website":"www.cam.k12.il.us",
    "wof:name":"Bond ELEMENTARY School",
    "wof:placetype":"venue"
},
  "geometry": {"coordinates":[-89.055519,39.521257],"type":"Point"}
}