{
  "type": "Feature",
  "properties": {
    "iso:country":"US",
    "sg:address":"479 E 300N Rd",
    "sg:city":"Gibson City",
    "sg:classifiers":[
        {
            "category":"Professional",
            "subcategory":"Accounting & Tax Preparation",
            "type":"Services"
        }
    ],
    "sg:phone":"+1 217 784 8811",
    "sg:postcode":"60936",
    "sg:province":"IL",
    "sg:tags":[
        "return",
        "filing"
    ],
    "wof:name":"Marti Consulting",
    "wof:placetype":"venue"
},
  "geometry": {"coordinates":[-88.37121500000001,40.442173],"type":"Point"}
}