{
  "type": "Feature",
  "properties": {
    "iso:country":"US",
    "sg:address":"30 N La Salle St Lbby 1",
    "sg:city":"Chicago",
    "sg:classifiers":[
        {
            "category":"Coffee & Tea",
            "type":"Food & Drink"
        },
        {
            "category":"Restaurant",
            "type":"Food & Drink"
        }
    ],
    "sg:phone":"+1 312 920 9024",
    "sg:postcode":"60602",
    "sg:province":"IL",
    "sg:tags":[
        "espresso"
    ],
    "wof:name":"Torrefazione Italia",
    "wof:placetype":"venue"
},
  "geometry": {"coordinates":[-87.632401,41.882599],"type":"Point"}
}