{
  "type": "Feature",
  "properties": {
    "addr:full":"1905 Patrick Henry Cir Urbana IL 61802",
    "addr:housenumber":"1905",
    "addr:postcode":"61802",
    "addr:street":"Patrick Henry Cir",
    "iso:country":"US",
    "sg:address":"1905 Patrick Henry Cir",
    "sg:city":"Urbana",
    "sg:classifiers":[
        {
            "category":"Social Services",
            "subcategory":"Child Care",
            "type":"Services"
        }
    ],
    "sg:phone":"+1 217 384 6483",
    "sg:postcode":"61802",
    "sg:province":"IL",
    "sg:tags":[
        "day"
    ],
    "wof:name":"Day Care",
    "wof:placetype":"venue"
},
  "geometry": {"coordinates":[-88.186673,40.135827],"type":"Point"}
}