{
  "type": "Feature",
  "properties": {
    "iso:country":"US",
    "sg:address":"37 E Market St",
    "sg:city":"Shannon",
    "sg:classifiers":[
        {
            "category":"Retail",
            "subcategory":"Funeral Services",
            "type":"Services"
        }
    ],
    "sg:phone":"+1 815 864 2441",
    "sg:postcode":"61078",
    "sg:province":"IL",
    "sg:tags":[
        "director"
    ],
    "wof:name":"Hermann Funeral Home",
    "wof:placetype":"venue"
},
  "geometry": {"coordinates":[-89.73930799999999,42.154557],"type":"Point"}
}