{
  "type": "Feature",
  "properties": {
    "iso:country":"US",
    "sg:address":"6930 N Kenneth Ave",
    "sg:city":"Lincolnwood",
    "sg:classifiers":[
        {
            "category":"Professional",
            "subcategory":"Advertising",
            "type":"Services"
        }
    ],
    "sg:phone":"+1 847 674 6500",
    "sg:postcode":"60712",
    "sg:province":"IL",
    "sg:tags":[
        "outdoor"
    ],
    "wof:name":"Outdoor Impact Inc",
    "wof:placetype":"venue"
},
  "geometry": {"coordinates":[-87.73935299999999,42.006521],"type":"Point"}
}