{
  "type": "Feature",
  "properties": {
    "iso:country":"US",
    "sg:address":"1749 Paul Ave",
    "sg:city":"Glendale Heights",
    "sg:classifiers":[
        {
            "category":"Shopping",
            "subcategory":"Beauty & Cosmetics",
            "type":"Retail Goods"
        }
    ],
    "sg:phone":"+1 630 790 1373",
    "sg:postcode":"60139",
    "sg:province":"IL",
    "sg:tags":[
        "supply"
    ],
    "wof:name":"Mid City Beauty Supply Co",
    "wof:placetype":"venue"
},
  "geometry": {"coordinates":[-88.073303,41.924801],"type":"Point"}
}