{
  "type": "Feature",
  "properties": {
    "iso:country":"US",
    "sg:address":"413 W 1st Ave",
    "sg:city":"Colona",
    "sg:classifiers":[
        {
            "category":"Retail",
            "subcategory":"Auto Repair",
            "type":"Services"
        }
    ],
    "sg:phone":"+1 309 792 6160",
    "sg:postcode":"61241",
    "sg:province":"IL",
    "wof:name":"Last Chance Garage",
    "wof:placetype":"venue"
},
  "geometry": {"coordinates":[-90.29540299999999,41.501202],"type":"Point"}
}