{
  "type": "Feature",
  "properties": {
    "iso:country":"US",
    "sg:address":"421 Checker Dr",
    "sg:city":"Buffalo Grove",
    "sg:classifiers":[
        {
            "category":"Wholesale",
            "subcategory":"Non-durable Goods",
            "type":"Manufacturing & Wholesale Goods"
        }
    ],
    "sg:phone":"+1 847 459 1191",
    "sg:postcode":"60089",
    "sg:province":"IL",
    "wof:name":"Gifts Of Distinction",
    "wof:placetype":"venue"
},
  "geometry": {"coordinates":[-87.977159,42.161205],"type":"Point"}
}