{
  "type": "Feature",
  "properties": {
    "addr:full":"209 W Cermak Road Chicago IL 60616",
    "addr:housenumber":"209",
    "addr:postcode":"60616",
    "addr:street":"W Cermak Road",
    "iso:country":"US",
    "sg:address":"209 W Cermak Road",
    "sg:city":"Chicago",
    "sg:classifiers":[
        {
            "category":"Professional",
            "subcategory":"Accounting & Tax Preparation",
            "type":"Services"
        },
        {
            "category":"Real Estate",
            "subcategory":"Real Estate Services",
            "type":"Services"
        },
        {
            "category":"Real Estate",
            "subcategory":"Real Estate Agent",
            "type":"Services"
        }
    ],
    "sg:phone":"+1 312 842 5555",
    "sg:postcode":"60616",
    "sg:province":"IL",
    "sg:tags":[
        "buyer",
        "accountant",
        "broker"
    ],
    "wof:name":"Realty Pacific Chicago",
    "wof:placetype":"venue"
},
  "geometry": {"coordinates":[-87.632159,41.85267],"type":"Point"}
}