{
  "type": "Feature",
  "properties": {
    "addr:full":"1891 Summit Ave Kankakee IL 60901",
    "addr:housenumber":"1891",
    "addr:postcode":"60901",
    "addr:street":"Summit Ave",
    "iso:country":"US",
    "sg:address":"1891 Summit Ave",
    "sg:city":"Kankakee",
    "sg:classifiers":[
        {
            "category":"Building & Trades",
            "subcategory":"Construction",
            "type":"Services"
        }
    ],
    "sg:phone":"+1 815 939 4019",
    "sg:postcode":"60901",
    "sg:province":"IL",
    "sg:tags":[
        "painter"
    ],
    "wof:name":"Savoie's Construction",
    "wof:placetype":"venue"
},
  "geometry": {"coordinates":[-87.84026,41.108412],"type":"Point"}
}