{
  "type": "Feature",
  "properties": {
    "iso:country":"US",
    "sg:address":"5225 Old Orchard Rd",
    "sg:city":"Skokie",
    "sg:classifiers":[
        {
            "category":"Social Services",
            "type":"Services"
        }
    ],
    "sg:phone":"+1 847 470 0717",
    "sg:postcode":"60077",
    "sg:province":"IL",
    "sg:tags":[
        "counselor",
        "marriage",
        "family"
    ],
    "wof:name":"Randy Kanter",
    "wof:placetype":"venue"
},
  "geometry": {"coordinates":[-87.756151,42.062442],"type":"Point"}
}