{
  "type": "Feature",
  "properties": {
    "addr:full":"5100 W Chicago Ave Chicago IL 60651",
    "addr:housenumber":"5100",
    "addr:postcode":"60651",
    "addr:street":"W Chicago Ave",
    "iso:country":"US",
    "sg:address":"5100 W Chicago Ave",
    "sg:city":"Chicago",
    "sg:classifiers":[
        {
            "category":"Organizations",
            "subcategory":"Religious Organization",
            "type":"Services"
        }
    ],
    "sg:phone":"+1 773 921 8674",
    "sg:postcode":"60651",
    "sg:province":"IL",
    "sg:tags":[
        "church"
    ],
    "wof:name":"Christ Outreach Deliverance",
    "wof:placetype":"venue"
},
  "geometry": {"coordinates":[-87.753766,41.894957],"type":"Point"}
}