{
  "type": "Feature",
  "properties": {
    "iso:country":"US",
    "sg:address":"4753 N Broadway St",
    "sg:city":"Chicago",
    "sg:classifiers":[
        {
            "category":"Organizations",
            "subcategory":"Professional Association",
            "type":"Services"
        }
    ],
    "sg:phone":"+1 773 878 1184",
    "sg:postcode":"60640",
    "sg:province":"IL",
    "sg:tags":[
        "business"
    ],
    "wof:name":"Uptown Chamber Commerce Upcorp",
    "wof:placetype":"venue"
},
  "geometry": {"coordinates":[-87.659374,41.968491],"type":"Point"}
}