{
  "type": "Feature",
  "properties": {
    "iso:country":"US",
    "sg:address":"101 N Memorial St",
    "sg:city":"Pittsfield",
    "sg:classifiers":[
        {
            "category":"Food & Beverages",
            "subcategory":"Groceries & Convenience Stores",
            "type":"Retail Goods"
        }
    ],
    "sg:phone":"+1   ",
    "sg:postcode":"62363",
    "sg:province":"IL",
    "sg:tags":[
        "station",
        "gasoline"
    ],
    "wof:name":"Ayerco Convenience Center",
    "wof:placetype":"venue"
},
  "geometry": {"coordinates":[-90.80756,39.60734],"type":"Point"}
}