{
  "type": "Feature",
  "properties": {
    "iso:country":"US",
    "sg:address":"9300 W Main St",
    "sg:city":"East Saint Louis",
    "sg:classifiers":[
        {
            "category":"Building & Trades",
            "subcategory":"Construction",
            "type":"Services"
        }
    ],
    "sg:phone":"+1 618 398 0873",
    "sg:postcode":"62203",
    "sg:province":"IL",
    "sg:tags":[
        "contractor"
    ],
    "wof:name":"Weinland Refrigeration Service",
    "wof:placetype":"venue"
},
  "geometry": {"coordinates":[-90.077003,38.601501],"type":"Point"}
}