{
  "type": "Feature",
  "properties": {
    "addr:full":"1977 E Fremont St Galesburg IL 61401",
    "addr:housenumber":"1977",
    "addr:postcode":"61401",
    "addr:street":"E Fremont St",
    "iso:country":"US",
    "sg:address":"1977 E Fremont St",
    "sg:city":"Galesburg",
    "sg:classifiers":[
        {
            "category":"Place Of Worship",
            "subcategory":"Church",
            "type":"Public Place"
        },
        {
            "category":"Place Of Worship",
            "type":"Public Place"
        }
    ],
    "sg:phone":"+1 309 342 9025",
    "sg:postcode":"61401",
    "sg:province":"IL",
    "sg:tags":[
        "jesus",
        "churches-church",
        "christ",
        "saint",
        "latter-day"
    ],
    "sg:website":"http://www.lds.org",
    "wof:name":"The Corp Of Church Of Christ Latter-Day St",
    "wof:placetype":"venue"
},
  "geometry": {"coordinates":[-90.339658,40.962004],"type":"Point"}
}