{
  "type": "Feature",
  "properties": {
    "addr:full":"306 N Rebecca St Crystal Lake IL 60014",
    "addr:housenumber":"306",
    "addr:postcode":"60014",
    "addr:street":"N Rebecca St",
    "iso:country":"US",
    "sg:address":"306 N Rebecca St",
    "sg:city":"Crystal Lake",
    "sg:classifiers":[
        {
            "category":"Building & Trades",
            "subcategory":"Construction",
            "type":"Services"
        }
    ],
    "sg:phone":"+1 815 459 0292",
    "sg:postcode":"60014",
    "sg:province":"IL",
    "sg:tags":[
        "general",
        "contractor"
    ],
    "wof:name":"Joseph J Henderson & Sons",
    "wof:placetype":"venue"
},
  "geometry": {"coordinates":[-88.31467000000001,42.249832],"type":"Point"}
}