{
  "type": "Feature",
  "properties": {
    "iso:country":"US",
    "sg:address":"425 E Locust St",
    "sg:city":"Canton",
    "sg:classifiers":[
        {
            "category":"Retail",
            "subcategory":"Auto Repair",
            "type":"Services"
        }
    ],
    "sg:phone":"+1 309 647 1633",
    "sg:postcode":"61520",
    "sg:province":"IL",
    "sg:tags":[
        "automotive",
        "wrecker"
    ],
    "wof:name":"Bob's & Swise Towing & Repair",
    "wof:placetype":"venue"
},
  "geometry": {"coordinates":[-90.028443,40.558386],"type":"Point"}
}