{
  "type": "Feature",
  "properties": {
    "addr:full":"300 S Fairview Ave Park Ridge IL 60068",
    "addr:housenumber":"300",
    "addr:postcode":"60068",
    "addr:street":"S Fairview Ave",
    "iso:country":"US",
    "sg:address":"300 S Fairview Ave",
    "sg:city":"Park Ridge",
    "sg:classifiers":[
        {
            "category":"Manufacturing",
            "subcategory":"Tools & Machinery",
            "type":"Manufacturing & Wholesale Goods"
        }
    ],
    "sg:phone":"+1 847 698 0546",
    "sg:postcode":"60068",
    "sg:province":"IL",
    "sg:tags":[
        "equipment",
        "photographic",
        "mfg"
    ],
    "wof:name":"Polaroid",
    "wof:placetype":"venue"
},
  "geometry": {"coordinates":[-87.83433599999999,42.005632],"type":"Point"}
}