{
  "type": "Feature",
  "properties": {
    "addr:full":"2018 Southbrooke Rd Jacksonville IL 62650",
    "addr:housenumber":"2018",
    "addr:postcode":"62650",
    "addr:street":"Southbrooke Rd",
    "iso:country":"US",
    "sg:address":"2018 Southbrooke Rd",
    "sg:city":"Jacksonville",
    "sg:classifiers":[
        {
            "category":"Real Estate",
            "subcategory":"Real Estate Services",
            "type":"Services"
        },
        {
            "category":"Building & Trades",
            "subcategory":"Construction",
            "type":"Services"
        }
    ],
    "sg:phone":"+1 217 245 7508",
    "sg:postcode":"62650",
    "sg:province":"IL",
    "sg:tags":[
        "roofing",
        "industrial",
        "consultant",
        "contractor",
        "contractors-commercial",
        "maintenance",
        "insulation"
    ],
    "sg:website":"http://www.jicroofing.com",
    "wof:name":"JIC Professional Roofing",
    "wof:placetype":"venue"
},
  "geometry": {"coordinates":[-90.22648599999999,39.694038],"type":"Point"}
}