{
  "type": "Feature",
  "properties": {
    "addr:full":"7520 W Ute Ln Palos Heights IL 60463",
    "addr:housenumber":"7520",
    "addr:postcode":"60463",
    "addr:street":"W Ute Ln",
    "iso:country":"US",
    "sg:address":"7520 W Ute Ln",
    "sg:city":"Palos Heights",
    "sg:classifiers":[
        {
            "category":"Banks & Credit Unions",
            "subcategory":"Financial Services",
            "type":"Services"
        }
    ],
    "sg:phone":"+1 708 361 4803",
    "sg:postcode":"60463",
    "sg:province":"IL",
    "sg:tags":[
        "fund",
        "investment"
    ],
    "wof:name":"Amitaf LLC",
    "wof:placetype":"venue"
},
  "geometry": {"coordinates":[-87.80480300000001,41.653981],"type":"Point"}
}