{
  "type": "Feature",
  "properties": {
    "addr:full":"7601 S Cicero Ave Chicago IL 60652",
    "addr:housenumber":"7601",
    "addr:postcode":"60652",
    "addr:street":"S Cicero Ave",
    "iso:country":"US",
    "sg:address":"7601 S Cicero Ave",
    "sg:city":"Chicago",
    "sg:classifiers":[
        {
            "category":"Shopping",
            "subcategory":"Jewelry",
            "type":"Retail Goods"
        }
    ],
    "sg:phone":"+1 773 585 8774",
    "sg:postcode":"60652",
    "sg:province":"IL",
    "sg:website":"www.treasuresofchicago.com",
    "wof:name":"Treasures Jewelry",
    "wof:placetype":"venue"
},
  "geometry": {"coordinates":[-87.741399,41.75428],"type":"Point"}
}