{
  "type": "Feature",
  "properties": {
    "addr:full":"1905 N State St Belvidere IL 61008",
    "addr:housenumber":"1905",
    "addr:postcode":"61008",
    "addr:street":"N State St",
    "iso:country":"US",
    "sg:address":"1905 N State St",
    "sg:city":"Belvidere",
    "sg:classifiers":[
        {
            "category":"Restaurant",
            "type":"Food & Drink"
        }
    ],
    "sg:phone":"+1   ",
    "sg:postcode":"61008",
    "sg:province":"IL",
    "sg:tags":[
        "eating"
    ],
    "wof:name":"Pizza Hut",
    "wof:placetype":"venue"
},
  "geometry": {"coordinates":[-88.86116199999999,42.272283],"type":"Point"}
}