{
  "type": "Feature",
  "properties": {
    "iso:country":"US",
    "sg:address":"1501 S Neil St",
    "sg:city":"Champaign",
    "sg:classifiers":[
        {
            "category":"Travel",
            "subcategory":"Hotels & Motels",
            "type":"Entertainment"
        }
    ],
    "sg:phone":"+1 217 352 9970",
    "sg:postcode":"61820",
    "sg:province":"IL",
    "sg:tags":[
        "lodging"
    ],
    "sg:website":"hiltongardeninn.hilton.com/en/gi...",
    "wof:name":"Hilton Garden Inn Champaign/Urbana",
    "wof:placetype":"venue"
},
  "geometry": {"coordinates":[-88.244629,40.09901],"type":"Point"}
}