{
  "type": "Feature",
  "properties": {
    "iso:country":"US",
    "sg:address":"3464 N Pulaski Rd",
    "sg:city":"Chicago",
    "sg:classifiers":[
        {
            "category":"Shopping",
            "subcategory":"Pets & Pet Supplies",
            "type":"Retail Goods"
        }
    ],
    "sg:postcode":"60641",
    "sg:province":"IL",
    "sg:tags":[
        "groomers"
    ],
    "sg:website":"www.luvyourpupspa.com",
    "wof:name":"Luv Your Pup Dog Grooming & Spa",
    "wof:placetype":"venue"
},
  "geometry": {"coordinates":[-87.727203,41.944472],"type":"Point"}
}