{
  "type": "Feature",
  "properties": {
    "addr:full":"1500 E 53rd St Chicago IL 60615",
    "addr:housenumber":"1500",
    "addr:postcode":"60615",
    "addr:street":"E 53Rd St",
    "iso:country":"US",
    "sg:address":"1500 E 53rd St",
    "sg:city":"Chicago",
    "sg:classifiers":[
        {
            "category":"Coffee & Tea",
            "type":"Food & Drink"
        }
    ],
    "sg:phone":"+1 773 324 1241",
    "sg:postcode":"60615",
    "sg:province":"IL",
    "wof:name":"Starbucks",
    "wof:placetype":"venue"
},
  "geometry": {"coordinates":[-87.58904800000001,41.799561],"type":"Point"}
}