{
  "type": "Feature",
  "properties": {
    "addr:full":"8050 New Castle Ave Burbank IL 60459",
    "addr:housenumber":"8050",
    "addr:postcode":"60459",
    "addr:street":"New Castle Ave",
    "iso:country":"US",
    "sg:address":"8050 New Castle Ave",
    "sg:city":"Burbank",
    "sg:classifiers":[
        {
            "category":"Park",
            "type":"Public Place"
        }
    ],
    "sg:phone":"+1 708 599 2070",
    "sg:postcode":"60459",
    "sg:province":"IL",
    "wof:name":"Burbank Park District",
    "wof:placetype":"venue"
},
  "geometry": {"coordinates":[-87.79119900000001,41.745998],"type":"Point"}
}