{
  "type": "Feature",
  "properties": {
    "iso:country":"US",
    "sg:address":"1411 6th Ave",
    "sg:city":"Moline",
    "sg:classifiers":[
        {
            "category":"Personal",
            "subcategory":"Massage",
            "type":"Services"
        },
        {
            "category":"Health Services",
            "subcategory":"Clinic",
            "type":"Services"
        },
        {
            "category":"Health Services",
            "subcategory":"Health Practitioner",
            "type":"Services"
        }
    ],
    "sg:phone":"+1 309 797 3529",
    "sg:postcode":"61265",
    "sg:province":"IL",
    "sg:tags":[
        "therapist",
        "therapy",
        "physical"
    ],
    "wof:name":"Two Rivers Massage",
    "wof:placetype":"venue"
},
  "geometry": {"coordinates":[-90.516954,41.504802],"type":"Point"}
}