{
  "type": "Feature",
  "properties": {
    "addr:full":"4347 E 1490 North Rd Fithian IL 61844",
    "addr:housenumber":"4347",
    "addr:postcode":"61844",
    "addr:street":"E 1490 North Rd",
    "iso:country":"US",
    "sg:address":"4347 E 1490 North Rd",
    "sg:city":"Fithian",
    "sg:phone":"+1 217 548 2362",
    "sg:postcode":"61844",
    "sg:province":"IL",
    "sg:tags":[
        "beef",
        "farm",
        "cash",
        "grain",
        "cattle",
        "feedlot"
    ],
    "wof:name":"Dana Jolley",
    "wof:placetype":"venue"
},
  "geometry": {"coordinates":[-87.862493,40.08335],"type":"Point"}
}