{
  "type": "Feature",
  "properties": {
    "addr:full":"12404 Archer Ave Lemont IL 60439",
    "addr:housenumber":"12404",
    "addr:postcode":"60439",
    "addr:street":"Archer Ave",
    "iso:country":"US",
    "sg:address":"12404 Archer Ave",
    "sg:city":"Lemont",
    "sg:classifiers":[
        {
            "category":"Social Services",
            "subcategory":"Child Care",
            "type":"Services"
        }
    ],
    "sg:phone":"+1 630 257 1142",
    "sg:postcode":"60439",
    "sg:province":"IL",
    "sg:tags":[
        "day"
    ],
    "wof:name":"Kindercare Child Care Network",
    "wof:placetype":"venue"
},
  "geometry": {"coordinates":[-87.964388,41.662753],"type":"Point"}
}