{
  "type": "Feature",
  "properties": {
    "addr:full":"1686 Wright Blvd Schaumburg IL 60193",
    "addr:housenumber":"1686",
    "addr:postcode":"60193",
    "addr:street":"Wright Blvd",
    "iso:country":"US",
    "sg:address":"1686 Wright Blvd",
    "sg:city":"Schaumburg",
    "sg:classifiers":[
        {
            "category":"Home & Garden",
            "subcategory":"Kitchen Supply",
            "type":"Retail Goods"
        }
    ],
    "sg:phone":"+1 800 307 8060",
    "sg:postcode":"60193",
    "sg:province":"IL",
    "sg:tags":[
        "food",
        "equipment",
        "processing"
    ],
    "wof:name":"Die Roll'rs Inc",
    "wof:placetype":"venue"
},
  "geometry": {"coordinates":[-88.101778,41.994797],"type":"Point"}
}