{
  "type": "Feature",
  "properties": {
    "addr:full":"Chicago Marriott O'Hare 8535 West Higgins Rd Chicago IL 60631",
    "addr:housenumber":"8535",
    "addr:postcode":"60631",
    "addr:street":"West Higgins Rd",
    "iso:country":"US",
    "sg:address":"Chicago Marriott O'Hare 8535 West Higgins Rd",
    "sg:city":"Chicago",
    "sg:classifiers":[
        {
            "category":"Restaurant",
            "type":"Food & Drink"
        }
    ],
    "sg:phone":"+1 773 693 4444",
    "sg:postcode":"60631",
    "sg:province":"IL",
    "sg:tags":[
        "new",
        "american"
    ],
    "sg:website":"www.marriott.com/hotels/hotel-in...",
    "wof:name":"Champions Sports Bar",
    "wof:placetype":"venue"
},
  "geometry": {"coordinates":[-87.83906899999999,41.986694],"type":"Point"}
}