{
  "type": "Feature",
  "properties": {
    "iso:country":"US",
    "sg:address":"1190 W 18th St",
    "sg:city":"Chicago",
    "sg:classifiers":[
        {
            "category":"Banks & Credit Unions",
            "subcategory":"Bank",
            "type":"Services"
        }
    ],
    "sg:phone":"+1 773 299 8891",
    "sg:postcode":"60608",
    "sg:province":"IL",
    "wof:name":"Payday Loans Chicago",
    "wof:placetype":"venue"
},
  "geometry": {"coordinates":[-87.656273,41.857979],"type":"Point"}
}