{
  "type": "Feature",
  "properties": {
    "addr:full":"1300 Dover St Centralia IL 62801",
    "addr:housenumber":"1300",
    "addr:postcode":"62801",
    "addr:street":"Dover St",
    "iso:country":"US",
    "sg:address":"1300 Dover St",
    "sg:city":"Centralia",
    "sg:classifiers":[
        {
            "category":"Personal",
            "subcategory":"Beauty Salon",
            "type":"Services"
        }
    ],
    "sg:phone":"+1 618 533 2344",
    "sg:postcode":"62801",
    "sg:province":"IL",
    "sg:tags":[
        "shop"
    ],
    "wof:name":"Pams Beauty Salon",
    "wof:placetype":"venue"
},
  "geometry": {"coordinates":[-89.147031,38.513183],"type":"Point"}
}