{
  "type": "Feature",
  "properties": {
    "addr:full":"1740 E Riverside Blvd Loves Park IL 61111",
    "addr:housenumber":"1740",
    "addr:postcode":"61111",
    "addr:street":"E Riverside Blvd",
    "iso:country":"US",
    "sg:address":"1740 E Riverside Blvd",
    "sg:city":"Loves Park",
    "sg:classifiers":[
        {
            "category":"Retail",
            "subcategory":"Veterinary Services",
            "type":"Services"
        }
    ],
    "sg:phone":"+1 815 654 2012",
    "sg:postcode":"61111",
    "sg:province":"IL",
    "sg:tags":[
        "specialty"
    ],
    "wof:name":"Brookside Veterinary Clinic",
    "wof:placetype":"venue"
},
  "geometry": {"coordinates":[-89.02723899999999,42.318356],"type":"Point"}
}