{
  "type": "Feature",
  "properties": {
    "iso:country":"US",
    "sg:address":"3019 W 111th St",
    "sg:city":"Chicago",
    "sg:classifiers":[
        {
            "category":"Restaurant",
            "type":"Food & Drink"
        }
    ],
    "sg:phone":"+1 773 881 1313",
    "sg:postcode":"60655",
    "sg:province":"IL",
    "sg:tags":[
        "pizza"
    ],
    "wof:name":"Tata's Chicago Pizzeria",
    "wof:placetype":"venue"
},
  "geometry": {"coordinates":[-87.69686299999999,41.691317],"type":"Point"}
}