{
  "type": "Feature",
  "properties": {
    "addr:full":"610 S Canal St Chicago IL 60607",
    "addr:housenumber":"610",
    "addr:postcode":"60607",
    "addr:street":"S Canal St",
    "iso:country":"US",
    "sg:address":"610 S Canal St",
    "sg:city":"Chicago",
    "sg:classifiers":[
        {
            "category":"Science Facility",
            "type":"Public Place"
        }
    ],
    "sg:phone":"+1 312 983 9300",
    "sg:postcode":"60607",
    "sg:province":"IL",
    "sg:tags":[
        "development",
        "laboratories-research"
    ],
    "wof:name":"Customs Laboratory",
    "wof:placetype":"venue"
},
  "geometry": {"coordinates":[-87.63946,41.874273],"type":"Point"}
}