{
  "type": "Feature",
  "properties": {
    "iso:country":"US",
    "sg:address":"702 N Logan Ave",
    "sg:city":"Danville",
    "sg:classifiers":[
        {
            "category":"Health Services",
            "subcategory":"Clinic",
            "type":"Services"
        }
    ],
    "sg:phone":"+1 217 431 7021",
    "sg:postcode":"61832",
    "sg:province":"IL",
    "sg:tags":[
        "medical"
    ],
    "wof:name":"Vermilion Hlth Care Foundation",
    "wof:placetype":"venue"
},
  "geometry": {"coordinates":[-87.644964,40.134762],"type":"Point"}
}