{
  "type": "Feature",
  "properties": {
    "addr:full":"1454 N Milwaukee Ave Chicago IL 60622",
    "addr:housenumber":"1454",
    "addr:postcode":"60622",
    "addr:street":"N Milwaukee Ave",
    "iso:country":"US",
    "sg:address":"1454 N Milwaukee Ave",
    "sg:city":"Chicago",
    "sg:classifiers":[
        {
            "category":"Shopping",
            "subcategory":"Music",
            "type":"Retail Goods"
        }
    ],
    "sg:phone":"+1 773 235 6900",
    "sg:postcode":"60622",
    "sg:province":"IL",
    "sg:tags":[
        "dvd's"
    ],
    "wof:name":"Adelqui Enterprises Inc",
    "wof:placetype":"venue"
},
  "geometry": {"coordinates":[-87.674103,41.908298],"type":"Point"}
}