{
  "type": "Feature",
  "properties": {
    "iso:country":"US",
    "sg:address":"106 E North Ave",
    "sg:city":"Carol Stream",
    "sg:classifiers":[
        {
            "category":"Autos & Motor Vehicles",
            "subcategory":"Fuel & Gas Station",
            "type":"Retail Goods"
        }
    ],
    "sg:phone":"+1 630 462 1863",
    "sg:postcode":"60188",
    "sg:province":"IL",
    "wof:name":"Rmart",
    "wof:placetype":"venue"
},
  "geometry": {"coordinates":[-88.119991,41.903915],"type":"Point"}
}