{
  "type": "Feature",
  "properties": {
    "iso:country":"US",
    "sg:address":"506 S Grant St",
    "sg:city":"Clinton",
    "sg:classifiers":[
        {
            "category":"Restaurant",
            "type":"Food & Drink"
        }
    ],
    "sg:phone":"+1 217 935 4646",
    "sg:postcode":"61727",
    "sg:province":"IL",
    "sg:tags":[
        "italian"
    ],
    "wof:name":"The Shack",
    "wof:placetype":"venue"
},
  "geometry": {"coordinates":[-88.963978,40.148904],"type":"Point"}
}