{
  "type": "Feature",
  "properties": {
    "iso:country":"US",
    "sg:address":"1233 W Carmen Ave",
    "sg:city":"Chicago",
    "sg:classifiers":[
        {
            "category":"Organizations",
            "subcategory":"Membership Organization",
            "type":"Services"
        }
    ],
    "sg:phone":"+1 773 728 6510",
    "sg:postcode":"60640",
    "sg:province":"IL",
    "wof:name":"1233 W Carmen Ave Assn",
    "wof:placetype":"venue"
},
  "geometry": {"coordinates":[-87.664666,41.974467],"type":"Point"}
}