{
  "type": "Feature",
  "properties": {
    "addr:full":"340 Lila's Ct New Lenox IL 60451",
    "addr:housenumber":"340",
    "addr:postcode":"60451",
    "addr:street":"Lila'S Ct",
    "iso:country":"US",
    "sg:address":"340 Lila's Ct",
    "sg:city":"New Lenox",
    "sg:classifiers":[
        {
            "category":"Wholesale",
            "subcategory":"Machinery & Supplies",
            "type":"Manufacturing & Wholesale Goods"
        }
    ],
    "sg:phone":"+1 815 485 5557",
    "sg:postcode":"60451",
    "sg:province":"IL",
    "sg:tags":[
        "construction",
        "used"
    ],
    "wof:name":"Goffinet Equipment Sales",
    "wof:placetype":"venue"
},
  "geometry": {"coordinates":[-87.957312,41.532786],"type":"Point"}
}