{
  "type": "Feature",
  "properties": {
    "iso:country":"US",
    "sg:address":"460 N Main St",
    "sg:city":"Glen Ellyn",
    "sg:classifiers":[
        {
            "category":"Professional",
            "subcategory":"Accounting & Tax Preparation",
            "type":"Services"
        }
    ],
    "sg:phone":"+1 630 790 3455",
    "sg:postcode":"60137",
    "sg:province":"IL",
    "wof:name":"Olinger & Associates PC",
    "wof:placetype":"venue"
},
  "geometry": {"coordinates":[-88.066785,41.876251],"type":"Point"}
}