{
  "type": "Feature",
  "properties": {
    "addr:full":"3850 W Devon Ave Lincolnwood IL 60712",
    "addr:housenumber":"3850",
    "addr:postcode":"60712",
    "addr:street":"W Devon Ave",
    "iso:country":"US",
    "sg:address":"3850 W Devon Ave",
    "sg:city":"Lincolnwood",
    "sg:classifiers":[
        {
            "category":"Retail",
            "subcategory":"Storage",
            "type":"Services"
        }
    ],
    "sg:phone":"+1 847 673 3850",
    "sg:postcode":"60712",
    "sg:province":"IL",
    "sg:tags":[
        "self"
    ],
    "sg:website":"www.thelockup.com",
    "wof:name":"The Lock Up Self Storage",
    "wof:placetype":"venue"
},
  "geometry": {"coordinates":[-87.72592899999999,41.997763],"type":"Point"}
}