{
  "type": "Feature",
  "properties": {
    "addr:full":"1134 Leicester Ct Wheaton IL 60187",
    "addr:housenumber":"1134",
    "addr:postcode":"60187",
    "addr:street":"Leicester Ct",
    "iso:country":"US",
    "sg:address":"1134 Leicester Ct",
    "sg:city":"Wheaton",
    "sg:classifiers":[
        {
            "category":"Professional",
            "subcategory":"Employment Agencies",
            "type":"Services"
        }
    ],
    "sg:phone":"+1 630 871 8050",
    "sg:postcode":"60187",
    "sg:province":"IL",
    "sg:tags":[
        "recruiter",
        "executive"
    ],
    "wof:name":"Executive Recruiters",
    "wof:placetype":"venue"
},
  "geometry": {"coordinates":[-88.089156,41.845442],"type":"Point"}
}