{
  "type": "Feature",
  "properties": {
    "addr:full":"16138 Cicero Ave Oak Forest IL 60452",
    "addr:housenumber":"16138",
    "addr:postcode":"60452",
    "addr:street":"Cicero Ave",
    "iso:country":"US",
    "sg:address":"16138 Cicero Ave",
    "sg:city":"Oak Forest",
    "sg:classifiers":[
        {
            "category":"Real Estate",
            "subcategory":"Real Estate Operator",
            "type":"Services"
        }
    ],
    "sg:phone":"+1 708 687 0163",
    "sg:postcode":"60452",
    "sg:province":"IL",
    "sg:tags":[
        "building",
        "residential",
        "apartment",
        "care"
    ],
    "wof:name":"Twin Pines Senior Living",
    "wof:placetype":"venue"
},
  "geometry": {"coordinates":[-87.736391,41.598882],"type":"Point"}
}