{
  "type": "Feature",
  "properties": {
    "iso:country":"US",
    "sg:address":"1805 Philo Rd",
    "sg:city":"Urbana",
    "sg:classifiers":[
        {
            "category":"Restaurant",
            "type":"Food & Drink"
        }
    ],
    "sg:phone":"+1 217 344 4500",
    "sg:postcode":"61802",
    "sg:province":"IL",
    "sg:tags":[
        "chinese"
    ],
    "wof:name":"First Wok",
    "wof:placetype":"venue"
},
  "geometry": {"coordinates":[-88.19059799999999,40.095699],"type":"Point"}
}