{
  "type": "Feature",
  "properties": {
    "iso:country":"US",
    "sg:address":"2918 W Grand Ave",
    "sg:city":"Chicago",
    "sg:classifiers":[
        {
            "category":"Manufacturing",
            "subcategory":"Motor Vehicles & Parts",
            "type":"Manufacturing & Wholesale Goods"
        },
        {
            "category":"Utilities",
            "subcategory":"Electric",
            "type":"Services"
        },
        {
            "category":"Autos & Motor Vehicles",
            "subcategory":"Auto Supplies",
            "type":"Retail Goods"
        }
    ],
    "sg:phone":"+1 773 276 8686",
    "sg:postcode":"60622",
    "sg:province":"IL",
    "sg:tags":[
        "distributor",
        "equipment-repair",
        "motors-manufacturers",
        "motors-used"
    ],
    "wof:name":"Palm Electric Motor",
    "wof:placetype":"venue"
},
  "geometry": {"coordinates":[-87.700267,41.895796],"type":"Point"}
}