{
  "type": "Feature",
  "properties": {
    "iso:country":"US",
    "sg:address":"305 E Northwest Hwy",
    "sg:city":"Palatine",
    "sg:classifiers":[
        {
            "category":"Health Services",
            "subcategory":"Health Practitioner",
            "type":"Services"
        }
    ],
    "sg:phone":"+1 847 359 1068",
    "sg:postcode":"60067",
    "sg:province":"IL",
    "wof:name":"Regina Dzlewlor MA",
    "wof:placetype":"venue"
},
  "geometry": {"coordinates":[-88.036062,42.119199],"type":"Point"}
}