{
  "type": "Feature",
  "properties": {
    "iso:country":"US",
    "sg:address":"1221 9th Ave",
    "sg:city":"Rock Island",
    "sg:classifiers":[
        {
            "category":"Personal",
            "subcategory":"Beauty Salon",
            "type":"Services"
        }
    ],
    "sg:phone":"+1 309 786 6111",
    "sg:postcode":"61201",
    "sg:province":"IL",
    "sg:tags":[
        "shop"
    ],
    "wof:name":"Shirley P Richardson",
    "wof:placetype":"venue"
},
  "geometry": {"coordinates":[-90.579286,41.502345],"type":"Point"}
}