{
  "type": "Feature",
  "properties": {
    "addr:full":"10135 S 80th Ct Palos Hills IL 60465",
    "addr:housenumber":"10135",
    "addr:postcode":"60465",
    "addr:street":"S 80Th Ct",
    "iso:country":"US",
    "sg:address":"10135 S 80th Ct",
    "sg:city":"Palos Hills",
    "sg:classifiers":[
        {
            "category":"Building & Trades",
            "subcategory":"Plumbing",
            "type":"Services"
        }
    ],
    "sg:phone":"+1 708 599 5229",
    "sg:postcode":"60465",
    "sg:province":"IL",
    "sg:tags":[
        "contractor"
    ],
    "wof:name":"Speedway Heating & Cooling",
    "wof:placetype":"venue"
},
  "geometry": {"coordinates":[-87.818713,41.707587],"type":"Point"}
}