{
  "type": "Feature",
  "properties": {
    "addr:full":"2160 Apple Hill Ln Buffalo Grove IL 60089",
    "addr:housenumber":"2160",
    "addr:postcode":"60089",
    "addr:street":"Apple Hill Ln",
    "iso:country":"US",
    "sg:address":"2160 Apple Hill Ln",
    "sg:city":"Buffalo Grove",
    "sg:classifiers":[
        {
            "category":"Insurance",
            "subcategory":"Insurance Agent",
            "type":"Services"
        }
    ],
    "sg:phone":"+1 847 821 7771",
    "sg:postcode":"60089",
    "sg:province":"IL",
    "wof:name":"Financial Plans",
    "wof:placetype":"venue"
},
  "geometry": {"coordinates":[-87.94767299999999,42.190613],"type":"Point"}
}