{
  "type": "Feature",
  "properties": {
    "iso:country":"US",
    "sg:address":"725 Eastland St",
    "sg:city":"Elmhurst",
    "sg:classifiers":[
        {
            "category":"Wholesale",
            "subcategory":"Stationery",
            "type":"Manufacturing & Wholesale Goods"
        }
    ],
    "sg:phone":"+1 630 834 6223",
    "sg:postcode":"60126",
    "sg:province":"IL",
    "sg:tags":[
        "paper"
    ],
    "wof:name":"Solo Cup",
    "wof:placetype":"venue"
},
  "geometry": {"coordinates":[-87.9275,41.920707],"type":"Point"}
}