{
  "type": "Feature",
  "properties": {
    "iso:country":"US",
    "sg:address":"431 21st St",
    "sg:city":"Carlyle",
    "sg:classifiers":[
        {
            "category":"Building & Trades",
            "subcategory":"Construction",
            "type":"Services"
        }
    ],
    "sg:phone":"+1 618 594 2224",
    "sg:postcode":"62231",
    "sg:province":"IL",
    "sg:tags":[
        "grading",
        "contractor"
    ],
    "wof:name":"Clinton County Highway Dept",
    "wof:placetype":"venue"
},
  "geometry": {"coordinates":[-89.385195,38.609837],"type":"Point"}
}