{
  "type": "Feature",
  "properties": {
    "iso:country":"US",
    "sg:address":"2128 Sherman Ave",
    "sg:city":"North Chicago",
    "sg:classifiers":[
        {
            "category":"Health Services",
            "subcategory":"Health Practitioner",
            "type":"Services"
        }
    ],
    "sg:phone":"+1 847 785 1504",
    "sg:postcode":"60064",
    "sg:province":"IL",
    "sg:tags":[
        "dental"
    ],
    "wof:name":"C&T Dental Supply and Clg Co",
    "wof:placetype":"venue"
},
  "geometry": {"coordinates":[-87.862271,42.321831],"type":"Point"}
}