{
  "type": "Feature",
  "properties": {
    "addr:full":"2423 W Lawrence Ave Springfield IL 62704",
    "addr:housenumber":"2423",
    "addr:postcode":"62704",
    "addr:street":"W Lawrence Ave",
    "iso:country":"US",
    "sg:address":"2423 W Lawrence Ave",
    "sg:city":"Springfield",
    "sg:classifiers":[
        {
            "category":"Restaurant",
            "type":"Food & Drink"
        }
    ],
    "sg:phone":"+1 217 726 5331",
    "sg:postcode":"62704",
    "sg:province":"IL",
    "wof:name":"Exceptional Pleasures Catering",
    "wof:placetype":"venue"
},
  "geometry": {"coordinates":[-89.697113,39.79583],"type":"Point"}
}