{
  "type": "Feature",
  "properties": {
    "iso:country":"US",
    "sg:address":"4485 N State Hwy 251",
    "sg:city":"Mendota",
    "sg:classifiers":[
        {
            "category":"Real Estate",
            "subcategory":"Real Estate Operator",
            "type":"Services"
        }
    ],
    "sg:phone":"+1 815 539 6133",
    "sg:postcode":"61342",
    "sg:province":"IL",
    "sg:tags":[
        "property",
        "lessor"
    ],
    "wof:name":"Carl Wieman",
    "wof:placetype":"venue"
},
  "geometry": {"coordinates":[-89.128196,41.575587],"type":"Point"}
}