{
  "type": "Feature",
  "properties": {
    "addr:full":"3847 W Fullerton Avenue Chicago IL 60647",
    "addr:housenumber":"3847",
    "addr:postcode":"60647",
    "addr:street":"W Fullerton Avenue",
    "iso:country":"US",
    "sg:address":"3847 W Fullerton Avenue",
    "sg:city":"Chicago",
    "sg:classifiers":[
        {
            "category":"Bakery",
            "type":"Food & Drink"
        }
    ],
    "sg:phone":"+1 773 772 5147",
    "sg:postcode":"60647",
    "sg:province":"IL",
    "wof:name":"Marie's Bakery",
    "wof:placetype":"venue"
},
  "geometry": {"coordinates":[-87.723411,41.924336],"type":"Point"}
}