{
  "type": "Feature",
  "properties": {
    "addr:full":"1425 Spring Lake Rd Quincy IL 62305",
    "addr:housenumber":"1425",
    "addr:postcode":"62305",
    "addr:street":"Spring Lake Rd",
    "iso:country":"US",
    "sg:address":"1425 Spring Lake Rd",
    "sg:city":"Quincy",
    "sg:phone":"+1 217 223 1779",
    "sg:postcode":"62305",
    "sg:province":"IL",
    "sg:tags":[
        "farm",
        "corn",
        "cash",
        "crop",
        "field",
        "grain"
    ],
    "wof:name":"Hilgenbrinck Alvera",
    "wof:placetype":"venue"
},
  "geometry": {"coordinates":[-91.39441100000001,39.994513],"type":"Point"}
}