{
  "type": "Feature",
  "properties": {
    "iso:country":"US",
    "sg:address":"310 Crest Dr",
    "sg:city":"Cary",
    "sg:classifiers":[
        {
            "category":"Home & Garden",
            "subcategory":"Building Materials",
            "type":"Retail Goods"
        },
        {
            "category":"Building & Trades",
            "subcategory":"Construction",
            "type":"Services"
        }
    ],
    "sg:phone":"+1 847 516 0777",
    "sg:postcode":"60013",
    "sg:province":"IL",
    "sg:tags":[
        "insulation",
        "contractor"
    ],
    "wof:name":"Division 7 Insulation Contractors",
    "wof:placetype":"venue"
},
  "geometry": {"coordinates":[-88.23462600000001,42.213301],"type":"Point"}
}