{
  "type": "Feature",
  "properties": {
    "iso:country":"US",
    "sg:address":"16923 Coles Creek Rd",
    "sg:city":"Carlyle",
    "sg:phone":"+1 618 226 3464",
    "sg:postcode":"62231",
    "sg:province":"IL",
    "sg:tags":[
        "wheat",
        "farm",
        "corn",
        "cash",
        "grain",
        "soybean"
    ],
    "wof:name":"Brad & Henry Nolte Farms",
    "wof:placetype":"venue"
},
  "geometry": {"coordinates":[-89.25350899999999,38.665454],"type":"Point"}
}