{
  "type": "Feature",
  "properties": {
    "iso:country":"US",
    "sg:address":"14801 Schumacher Rd",
    "sg:city":"Aviston",
    "sg:classifiers":[
        {
            "category":"Shopping",
            "subcategory":"Beauty & Cosmetics",
            "type":"Retail Goods"
        }
    ],
    "sg:phone":"+1   ",
    "sg:postcode":"62216",
    "sg:province":"IL",
    "sg:tags":[
        "merchandise"
    ],
    "wof:name":"Mary Kay Cosemetics",
    "wof:placetype":"venue"
},
  "geometry": {"coordinates":[-89.59432700000001,38.623405],"type":"Point"}
}