{
  "type": "Feature",
  "properties": {
    "iso:country":"US",
    "sg:address":"900 Oakton St",
    "sg:city":"Evanston",
    "sg:classifiers":[
        {
            "category":"Arts & Performance",
            "subcategory":"Theater",
            "type":"Entertainment"
        }
    ],
    "sg:phone":"+1 847 491 9714",
    "sg:postcode":"60202",
    "sg:province":"IL",
    "sg:tags":[
        "group"
    ],
    "wof:name":"Great Midwestern Music Inc",
    "wof:placetype":"venue"
},
  "geometry": {"coordinates":[-87.685454,42.026655],"type":"Point"}
}