{
  "type": "Feature",
  "properties": {
    "iso:country":"US",
    "sg:address":"6180 E State St",
    "sg:city":"Rockford",
    "sg:classifiers":[
        {
            "category":"Professional",
            "subcategory":"Advertising",
            "type":"Services"
        }
    ],
    "sg:phone":"+1 815 395 9730",
    "sg:postcode":"61108",
    "sg:province":"IL",
    "wof:name":"Trader Publishing",
    "wof:placetype":"venue"
},
  "geometry": {"coordinates":[-88.999079,42.267036],"type":"Point"}
}