{
  "type": "Feature",
  "properties": {
    "iso:country":"US",
    "sg:address":"605 Fulton Ave",
    "sg:city":"Rockford",
    "sg:classifiers":[
        {
            "category":"Professional",
            "subcategory":"Research",
            "type":"Services"
        }
    ],
    "sg:phone":"+1 815 965 3522",
    "sg:postcode":"61103",
    "sg:province":"IL",
    "sg:tags":[
        "development",
        "laboratory"
    ],
    "wof:name":"Eigerlab",
    "wof:placetype":"venue"
},
  "geometry": {"coordinates":[-89.070437,42.297964],"type":"Point"}
}