{
  "type": "Feature",
  "properties": {
    "addr:full":"630 N Church St Rockford IL 61103",
    "addr:housenumber":"630",
    "addr:postcode":"61103",
    "addr:street":"N Church St",
    "iso:country":"US",
    "sg:address":"630 N Church St",
    "sg:city":"Rockford",
    "sg:classifiers":[
        {
            "category":"Insurance",
            "subcategory":"Insurance Agent",
            "type":"Services"
        }
    ],
    "sg:phone":"+1 815 966 2380",
    "sg:postcode":"61103",
    "sg:province":"IL",
    "wof:name":"Ken Conti",
    "wof:placetype":"venue"
},
  "geometry": {"coordinates":[-89.09034,42.278215],"type":"Point"}
}