{
  "type": "Feature",
  "properties": {
    "iso:country":"US",
    "sg:address":"200 E Bethalto Dr",
    "sg:city":"Bethalto",
    "sg:classifiers":[
        {
            "category":"Retail",
            "subcategory":"Car Wash",
            "type":"Services"
        }
    ],
    "sg:phone":"+1 618 377 6264",
    "sg:postcode":"62010",
    "sg:province":"IL",
    "sg:tags":[
        "carwash"
    ],
    "wof:name":"Wash-N-Go",
    "wof:placetype":"venue"
},
  "geometry": {"coordinates":[-90.038264,38.90085],"type":"Point"}
}