{
  "type": "Feature",
  "properties": {
    "iso:country":"US",
    "sg:address":"7044 Cermak Rd",
    "sg:city":"Berwyn",
    "sg:classifiers":[
        {
            "category":"Banks & Credit Unions",
            "subcategory":"Bank",
            "type":"Services"
        }
    ],
    "sg:phone":"+1 708 788 2308",
    "sg:postcode":"60402",
    "sg:province":"IL",
    "sg:tags":[
        "personal",
        "institution"
    ],
    "wof:name":"Title Loans Express",
    "wof:placetype":"venue"
},
  "geometry": {"coordinates":[-87.800827,41.850549],"type":"Point"}
}