{
  "type": "Feature",
  "properties": {
    "addr:full":"2823 N Dryden Pl Arlington Heights IL 60004",
    "addr:housenumber":"2823",
    "addr:postcode":"60004",
    "addr:street":"N Dryden Pl",
    "iso:country":"US",
    "sg:address":"2823 N Dryden Pl",
    "sg:city":"Arlington Heights",
    "sg:classifiers":[
        {
            "category":"Building & Trades",
            "subcategory":"Construction",
            "type":"Services"
        }
    ],
    "sg:phone":"+1 312 835 8527",
    "sg:postcode":"60004",
    "sg:province":"IL",
    "sg:tags":[
        "house"
    ],
    "wof:name":"WA Builders Inc",
    "wof:placetype":"venue"
},
  "geometry": {"coordinates":[-87.968811,42.127557],"type":"Point"}
}