{
  "type": "Feature",
  "properties": {
    "iso:country":"US",
    "sg:address":"26005 Highline Rd",
    "sg:city":"Ashley",
    "sg:phone":"+1 618 485 2750",
    "sg:postcode":"62808",
    "sg:province":"IL",
    "sg:tags":[
        "farm",
        "corn",
        "wheat",
        "soybean"
    ],
    "wof:name":"Alan Czajkowski",
    "wof:placetype":"venue"
},
  "geometry": {"coordinates":[-89.220857,38.345921],"type":"Point"}
}