{
  "type": "Feature",
  "properties": {
    "addr:full":"680 N Lake Shore Drive Fl 19 Chicago IL 60611",
    "addr:housenumber":"680;19",
    "addr:postcode":"60611",
    "addr:street":"N Lake Shore Drive Fl",
    "iso:country":"US",
    "sg:address":"680 N Lake Shore Drive Fl 19",
    "sg:city":"Chicago",
    "sg:classifiers":[
        {
            "category":"Real Estate",
            "subcategory":"Real Estate Services",
            "type":"Services"
        },
        {
            "category":"Real Estate",
            "subcategory":"Real Estate Operator",
            "type":"Services"
        }
    ],
    "sg:phone":"+1 312 943 7000",
    "sg:postcode":"60611",
    "sg:province":"IL",
    "sg:tags":[
        "apartment",
        "property",
        "management"
    ],
    "wof:name":"Forman Realty Corporation",
    "wof:placetype":"venue"
},
  "geometry": {"coordinates":[-87.615611,41.894691],"type":"Point"}
}