{
  "type": "Feature",
  "properties": {
    "iso:country":"US",
    "sg:address":"2004 Fox Dr",
    "sg:city":"Champaign",
    "sg:classifiers":[
        {
            "category":"Health Services",
            "subcategory":"Dentist",
            "type":"Services"
        }
    ],
    "sg:phone":"+1 877 577 1590",
    "sg:postcode":"61820",
    "sg:province":"IL",
    "sg:tags":[
        "dentists-orthodontists"
    ],
    "sg:website":"http://www.robertjfleming.com",
    "wof:name":"Fleming J Robert DDS",
    "wof:placetype":"venue"
},
  "geometry": {"coordinates":[-88.250705,40.091001],"type":"Point"}
}