{
  "type": "Feature",
  "properties": {
    "addr:full":"1327 Acorn St Lemont IL 60439",
    "addr:housenumber":"1327",
    "addr:postcode":"60439",
    "addr:street":"Acorn St",
    "iso:country":"US",
    "sg:address":"1327 Acorn St",
    "sg:city":"Lemont",
    "sg:classifiers":[
        {
            "category":"Building & Trades",
            "subcategory":"Construction",
            "type":"Services"
        }
    ],
    "sg:phone":"+1 630 243 0483",
    "sg:postcode":"60439",
    "sg:province":"IL",
    "sg:tags":[
        "excavation",
        "contractor"
    ],
    "wof:name":"Onsite Excavating  Inc",
    "wof:placetype":"venue"
},
  "geometry": {"coordinates":[-88.007413,41.649582],"type":"Point"}
}