{
  "type": "Feature",
  "properties": {
    "iso:country":"US",
    "sg:address":"312 Springfield Ave",
    "sg:city":"Urbana",
    "sg:classifiers":[
        {
            "category":"Health Services",
            "subcategory":"Doctor",
            "type":"Services"
        }
    ],
    "sg:phone":"+1 217 337 2430",
    "sg:postcode":"61801",
    "sg:province":"IL",
    "sg:tags":[
        "medical"
    ],
    "wof:name":"Reynaldo E Tirona",
    "wof:placetype":"venue"
},
  "geometry": {"coordinates":[-88.211668,40.112416],"type":"Point"}
}