{
  "type": "Feature",
  "properties": {
    "addr:full":"205 Potomac Blvd Mount Vernon IL 62864",
    "addr:housenumber":"205",
    "addr:postcode":"62864",
    "addr:street":"Potomac Blvd",
    "iso:country":"US",
    "sg:address":"205 Potomac Blvd",
    "sg:city":"Mount Vernon",
    "sg:classifiers":[
        {
            "category":"Travel",
            "subcategory":"Hotels & Motels",
            "type":"Entertainment"
        }
    ],
    "sg:phone":"+1 618 244 9700",
    "sg:postcode":"62864",
    "sg:province":"IL",
    "wof:name":"Days Inn",
    "wof:placetype":"venue"
},
  "geometry": {"coordinates":[-88.95618,38.317968],"type":"Point"}
}