{
  "type": "Feature",
  "properties": {
    "iso:country":"US",
    "sg:address":"508 Cary Algonquin Rd",
    "sg:city":"Cary",
    "sg:classifiers":[
        {
            "category":"Manufacturing",
            "subcategory":"Signs",
            "type":"Manufacturing & Wholesale Goods"
        }
    ],
    "sg:phone":"+1 847 639 7917",
    "sg:postcode":"60013",
    "sg:province":"IL",
    "sg:website":"www.signx.com",
    "wof:name":"Sign-X Co",
    "wof:placetype":"venue"
},
  "geometry": {"coordinates":[-88.25142099999999,42.214454],"type":"Point"}
}