{
  "type": "Feature",
  "properties": {
    "addr:full":"4000 W Montrose Ave Chicago IL 60641",
    "addr:housenumber":"4000",
    "addr:postcode":"60641",
    "addr:street":"W Montrose Ave",
    "iso:country":"US",
    "sg:address":"4000 W Montrose Ave",
    "sg:city":"Chicago",
    "sg:classifiers":[
        {
            "category":"Shopping",
            "subcategory":"Mobile Phones",
            "type":"Retail Goods"
        }
    ],
    "sg:phone":"+1 773 685 1840",
    "sg:postcode":"60641",
    "sg:province":"IL",
    "sg:website":"www.uscellular.com",
    "wof:name":"U S Cellular",
    "wof:placetype":"venue"
},
  "geometry": {"coordinates":[-87.72779300000001,41.961097],"type":"Point"}
}