{
  "type": "Feature",
  "properties": {
    "addr:full":"RR 14 Fox River Grove IL 60021",
    "addr:housenumber":"14",
    "addr:postcode":"60021",
    "addr:street":"Rr",
    "iso:country":"US",
    "sg:address":"RR 14",
    "sg:city":"Fox River Grove",
    "sg:classifiers":[
        {
            "category":"Autos & Motor Vehicles",
            "subcategory":"Fuel & Gas Station",
            "type":"Retail Goods"
        }
    ],
    "sg:phone":"+1 847 639 1188",
    "sg:postcode":"60021",
    "sg:province":"IL",
    "sg:website":"www.shell.com",
    "wof:name":"Fox River Grove Shell",
    "wof:placetype":"venue"
},
  "geometry": {"coordinates":[-88.2146,42.194],"type":"Point"}
}