{
  "type": "Feature",
  "properties": {
    "iso:country":"US",
    "sg:address":"1501 W Randolph St",
    "sg:city":"Chicago",
    "sg:classifiers":[
        {
            "category":"Arts & Performance",
            "subcategory":"Arts Center",
            "type":"Entertainment"
        },
        {
            "category":"Restaurant",
            "type":"Food & Drink"
        }
    ],
    "sg:postcode":"60607",
    "sg:province":"IL",
    "sg:tags":[
        "flavor",
        "performing",
        "local"
    ],
    "sg:website":"pitchforkmusicfestival.com/",
    "wof:name":"Pitchfork Festival",
    "wof:placetype":"venue"
},
  "geometry": {"coordinates":[-87.66422300000001,41.884693],"type":"Point"}
}