{
  "type": "Feature",
  "properties": {
    "iso:country":"US",
    "sg:address":"204 E 7th St",
    "sg:city":"Delavan",
    "sg:classifiers":[
        {
            "category":"Communications",
            "subcategory":"Radio Station",
            "type":"Services"
        },
        {
            "category":"Recreation",
            "type":"Entertainment"
        }
    ],
    "sg:phone":"+1 309 244 8443",
    "sg:postcode":"61734",
    "sg:province":"IL",
    "sg:tags":[
        "band",
        "radios-citizens",
        "system",
        "equipment"
    ],
    "wof:name":"Bluhm Engineering",
    "wof:placetype":"venue"
},
  "geometry": {"coordinates":[-89.54579,40.369427],"type":"Point"}
}