{
  "type": "Feature",
  "properties": {
    "iso:country":"US",
    "sg:address":"333 Washington Ave",
    "sg:city":"Saint Louis",
    "sg:classifiers":[
        {
            "category":"Bars & Pubs",
            "type":"Food & Drink"
        },
        {
            "category":"Restaurant",
            "type":"Food & Drink"
        }
    ],
    "sg:phone":"+1 314 241 8666",
    "sg:postcode":"63103",
    "sg:province":"MO",
    "sg:tags":[
        "irish"
    ],
    "sg:website":"www.tiginirishpub.com/stl",
    "wof:name":"Tigin Irish Pub and Restaurant",
    "wof:placetype":"venue"
},
  "geometry": {"coordinates":[-90.187359,38.627117],"type":"Point"}
}