{
  "type": "Feature",
  "properties": {
    "iso:country":"US",
    "sg:address":"284 Market Sq",
    "sg:city":"Lake Forest",
    "sg:classifiers":[
        {
            "category":"Shopping",
            "subcategory":"Shoes",
            "type":"Retail Goods"
        }
    ],
    "sg:phone":"+1   ",
    "sg:postcode":"60045",
    "sg:province":"IL",
    "sg:tags":[
        "family"
    ],
    "wof:name":"Forest Bootery Ltd I",
    "wof:placetype":"venue"
},
  "geometry": {"coordinates":[-87.840409,42.252557],"type":"Point"}
}