{
  "type": "Feature",
  "properties": {
    "iso:country":"US",
    "sg:address":"1550 W North Ave",
    "sg:city":"Melrose Park",
    "sg:classifiers":[
        {
            "category":"Fast Food",
            "type":"Food & Drink"
        }
    ],
    "sg:phone":"+1 708 681 1895",
    "sg:postcode":"60160",
    "sg:province":"IL",
    "wof:name":"Burger King",
    "wof:placetype":"venue"
},
  "geometry": {"coordinates":[-87.853071,41.907482],"type":"Point"}
}