{
  "type": "Feature",
  "properties": {
    "addr:full":"415 W Belmont Ave Chicago IL 60657",
    "addr:housenumber":"415",
    "addr:postcode":"60657",
    "addr:street":"W Belmont Ave",
    "iso:country":"US",
    "sg:address":"415 W Belmont Ave",
    "sg:city":"Chicago",
    "sg:classifiers":[
        {
            "category":"Personal",
            "subcategory":"Beauty Salon",
            "type":"Services"
        }
    ],
    "sg:phone":"+1 773 296 6264",
    "sg:postcode":"60657",
    "sg:province":"IL",
    "sg:tags":[
        "shop"
    ],
    "wof:name":"Nails Aurora",
    "wof:placetype":"venue"
},
  "geometry": {"coordinates":[-87.639656,41.940058],"type":"Point"}
}