{
  "type": "Feature",
  "properties": {
    "iso:country":"US",
    "sg:address":"1011 Olympic Dr",
    "sg:city":"Batavia",
    "sg:classifiers":[
        {
            "category":"Manufacturing",
            "subcategory":"Rubber & Plastics",
            "type":"Manufacturing & Wholesale Goods"
        },
        {
            "category":"Wholesale",
            "subcategory":"Home Furnishings",
            "type":"Manufacturing & Wholesale Goods"
        }
    ],
    "sg:phone":"+1 630 879 7776",
    "sg:postcode":"60510",
    "sg:province":"IL",
    "sg:tags":[
        "plastics-vacuum",
        "plastics-finished-wholesale",
        "pressure",
        "forming-manufacturers",
        "thermoforming",
        "manufacturer"
    ],
    "sg:website":"http://www.proexinc.com",
    "wof:name":"Proex Inc",
    "wof:placetype":"venue"
},
  "geometry": {"coordinates":[-88.288004,41.865855],"type":"Point"}
}