{
  "type": "Feature",
  "properties": {
    "addr:full":"1440 W Devon Ave Chicago IL 60660",
    "addr:housenumber":"1440",
    "addr:postcode":"60660",
    "addr:street":"W Devon Ave",
    "iso:country":"US",
    "sg:address":"1440 W Devon Ave",
    "sg:city":"Chicago",
    "sg:classifiers":[
        {
            "category":"Food & Beverages",
            "subcategory":"Groceries & Convenience Stores",
            "type":"Retail Goods"
        }
    ],
    "sg:phone":"+1 773 338 2572",
    "sg:postcode":"60660",
    "sg:province":"IL",
    "sg:tags":[
        "grocer"
    ],
    "wof:name":"Devon Market",
    "wof:placetype":"venue"
},
  "geometry": {"coordinates":[-87.667,41.9981],"type":"Point"}
}