{
  "type": "Feature",
  "properties": {
    "iso:country":"US",
    "sg:address":"5658 S Loomis Blvd",
    "sg:city":"Chicago",
    "sg:classifiers":[
        {
            "category":"Food & Beverages",
            "subcategory":"Groceries & Convenience Stores",
            "type":"Retail Goods"
        }
    ],
    "sg:phone":"+1 773 434 8700",
    "sg:postcode":"60636",
    "sg:province":"IL",
    "wof:name":"R&b Food & Clothing Store",
    "wof:placetype":"venue"
},
  "geometry": {"coordinates":[-87.65981600000001,41.791231],"type":"Point"}
}