{
  "type": "Feature",
  "properties": {
    "addr:full":"4630 W 55th St Chicago IL 60632",
    "addr:housenumber":"4630",
    "addr:postcode":"60632",
    "addr:street":"W 55Th St",
    "iso:country":"US",
    "sg:address":"4630 W 55th St",
    "sg:city":"Chicago",
    "sg:classifiers":[
        {
            "category":"Manufacturing",
            "subcategory":"Tools & Machinery",
            "type":"Manufacturing & Wholesale Goods"
        },
        {
            "category":"Building & Trades",
            "subcategory":"Plumbing",
            "type":"Services"
        }
    ],
    "sg:phone":"+1 773 767 2500",
    "sg:postcode":"60632",
    "sg:province":"IL",
    "sg:tags":[
        "jig",
        "fixture",
        "maker",
        "die"
    ],
    "sg:website":"http://www.oandkamerican.com",
    "wof:name":"O & K American",
    "wof:placetype":"venue"
},
  "geometry": {"coordinates":[-87.738827,41.793054],"type":"Point"}
}