{
  "type": "Feature",
  "properties": {
    "addr:full":"5027 S 1400W Rd Chebanse IL 60922",
    "addr:housenumber":"5027",
    "addr:postcode":"60922",
    "addr:street":"S 1400W Rd",
    "iso:country":"US",
    "sg:address":"5027 S 1400W Rd",
    "sg:city":"Chebanse",
    "sg:classifiers":[
        {
            "category":"Railroad",
            "type":"Transportation"
        }
    ],
    "sg:phone":"+1 815 932 9470",
    "sg:postcode":"60922",
    "sg:province":"IL",
    "wof:name":"Illinois Central Railroad",
    "wof:placetype":"venue"
},
  "geometry": {"coordinates":[-87.894452,41.046545],"type":"Point"}
}