{
  "type": "Feature",
  "properties": {
    "iso:country":"US",
    "sg:address":"17589 E Adams Rd",
    "sg:city":"Bonnie",
    "sg:phone":"+1 618 244 2791",
    "sg:postcode":"62816",
    "sg:province":"IL",
    "sg:tags":[
        "farm",
        "corn",
        "soybean"
    ],
    "wof:name":"Howard Adams Farm",
    "wof:placetype":"venue"
},
  "geometry": {"coordinates":[-88.822649,38.185028],"type":"Point"}
}