{
  "type": "Feature",
  "properties": {
    "addr:full":"901 Clock Tower Dr Springfield IL 62704",
    "addr:housenumber":"901",
    "addr:postcode":"62704",
    "addr:street":"Clock Tower Dr",
    "iso:country":"US",
    "sg:address":"901 Clock Tower Dr",
    "sg:city":"Springfield",
    "sg:classifiers":[
        {
            "category":"Personal",
            "subcategory":"Massage",
            "type":"Services"
        }
    ],
    "sg:phone":"+1 217 726 0067",
    "sg:postcode":"62704",
    "sg:province":"IL",
    "wof:name":"A Touch Of Healing Massage",
    "wof:placetype":"venue"
},
  "geometry": {"coordinates":[-89.70493399999999,39.79075],"type":"Point"}
}