{
  "type": "Feature",
  "properties": {
    "iso:country":"US",
    "sg:address":"901 Clock Tower Dr",
    "sg:city":"Springfield",
    "sg:classifiers":[
        {
            "category":"Personal",
            "subcategory":"Massage",
            "type":"Services"
        }
    ],
    "sg:phone":"+1 217 726 0067",
    "sg:postcode":"62704",
    "sg:province":"IL",
    "wof:name":"A Touch Of Healing Massage",
    "wof:placetype":"venue"
},
  "geometry": {"coordinates":[-89.704934,39.79075],"type":"Point"}
}