{
  "type": "Feature",
  "properties": {
    "addr:full":"4649 Yorktown Rd Prophetstown IL 61277",
    "addr:housenumber":"4649",
    "addr:postcode":"61277",
    "addr:street":"Yorktown Rd",
    "iso:country":"US",
    "sg:address":"4649 Yorktown Rd",
    "sg:city":"Prophetstown",
    "sg:classifiers":[
        {
            "category":"Professional",
            "subcategory":"Business Services",
            "type":"Services"
        }
    ],
    "sg:phone":"+1 815 537 5542",
    "sg:postcode":"61277",
    "sg:province":"IL",
    "wof:name":"Koehler Farm",
    "wof:placetype":"venue"
},
  "geometry": {"coordinates":[-89.862443,41.649409],"type":"Point"}
}