{
  "type": "Feature",
  "properties": {
    "addr:full":"3408 N Harlem Avenue Chicago IL 60634",
    "addr:housenumber":"3408",
    "addr:postcode":"60634",
    "addr:street":"N Harlem Avenue",
    "iso:country":"US",
    "sg:address":"3408 N Harlem Avenue",
    "sg:city":"Chicago",
    "sg:classifiers":[
        {
            "category":"Cinema",
            "subcategory":"Movie Rental",
            "type":"Entertainment"
        },
        {
            "category":"Shopping",
            "subcategory":"Music",
            "type":"Retail Goods"
        }
    ],
    "sg:phone":"+1 773 889 8003",
    "sg:postcode":"60634",
    "sg:province":"IL",
    "sg:tags":[
        "game",
        "video",
        "dvd's"
    ],
    "wof:name":"Polish-American Video",
    "wof:placetype":"venue"
},
  "geometry": {"coordinates":[-87.80663300000001,41.942052],"type":"Point"}
}