{
  "type": "Feature",
  "properties": {
    "iso:country":"US",
    "sg:address":"5600 W Addison Street",
    "sg:city":"Chicago",
    "sg:classifiers":[
        {
            "category":"Health Services",
            "subcategory":"Doctor",
            "type":"Services"
        }
    ],
    "sg:phone":"+1 773 736 6999",
    "sg:postcode":"60634",
    "sg:province":"IL",
    "wof:name":"Firoozi Taraneh S MD",
    "wof:placetype":"venue"
},
  "geometry": {"coordinates":[-87.76667399999999,41.945905],"type":"Point"}
}