{
  "type": "Feature",
  "properties": {
    "addr:full":"4452 S. Archer Avenue Chicago IL 60632",
    "addr:housenumber":"4452",
    "addr:postcode":"60632",
    "addr:street":"S. Archer Avenue",
    "iso:country":"US",
    "sg:address":"4452 S. Archer Avenue",
    "sg:city":"Chicago",
    "sg:classifiers":[
        {
            "category":"Building & Trades",
            "subcategory":"Landscaping Services",
            "type":"Services"
        }
    ],
    "sg:phone":"+1 773 376 2500",
    "sg:postcode":"60632",
    "sg:province":"IL",
    "sg:tags":[
        "landscape",
        "contractor"
    ],
    "sg:website":"www.greencitylandscapes.com/",
    "wof:name":"Green City Landscapes",
    "wof:placetype":"venue"
},
  "geometry": {"coordinates":[-87.706913,41.81264],"type":"Point"}
}