{
  "type": "Feature",
  "properties": {
    "iso:country":"US",
    "sg:address":"1008 1/2 W Irving Park Rd",
    "sg:city":"Chicago",
    "sg:classifiers":[
        {
            "category":"Restaurant",
            "type":"Food & Drink"
        }
    ],
    "sg:phone":"+1 773 404 5969",
    "sg:postcode":"60613",
    "sg:province":"IL",
    "sg:tags":[
        "mexican"
    ],
    "wof:name":"El Palmar",
    "wof:placetype":"venue"
},
  "geometry": {"coordinates":[-87.654934,41.955005],"type":"Point"}
}