{
  "type": "Feature",
  "properties": {
    "iso:country":"US",
    "sg:address":"3148 W Montrose Ave",
    "sg:city":"Chicago",
    "sg:classifiers":[
        {
            "category":"Personal",
            "subcategory":"Nail Salon",
            "type":"Services"
        }
    ],
    "sg:phone":"+1 773 866 2404",
    "sg:postcode":"60618",
    "sg:province":"IL",
    "wof:name":"Nail Care",
    "wof:placetype":"venue"
},
  "geometry": {"coordinates":[-87.707802,41.9613],"type":"Point"}
}