{
  "type": "Feature",
  "properties": {
    "iso:country":"US",
    "sg:address":"300 W Hill Street",
    "sg:city":"Chicago",
    "sg:classifiers":[
        {
            "category":"Education",
            "subcategory":"School",
            "type":"Public Place"
        }
    ],
    "sg:phone":"+1 312 266 0801",
    "sg:postcode":"60610",
    "sg:province":"IL",
    "sg:tags":[
        "high",
        "middle",
        "elementary"
    ],
    "wof:name":"Lakeshore Preparatory",
    "wof:placetype":"venue"
},
  "geometry": {"coordinates":[-87.636169,41.902096],"type":"Point"}
}