{
  "type": "Feature",
  "properties": {
    "addr:full":"213 Peterson Rd Libertyville IL 60048",
    "addr:housenumber":"213",
    "addr:postcode":"60048",
    "addr:street":"Peterson Rd",
    "iso:country":"US",
    "sg:address":"213 Peterson Rd",
    "sg:city":"Libertyville",
    "sg:classifiers":[
        {
            "category":"Building & Trades",
            "subcategory":"Pest Control",
            "type":"Services"
        }
    ],
    "sg:phone":"+1 847 336 8400",
    "sg:postcode":"60048",
    "sg:province":"IL",
    "wof:name":"Andex",
    "wof:placetype":"venue"
},
  "geometry": {"coordinates":[-87.965226,42.305908],"type":"Point"}
}