{
  "type": "Feature",
  "properties": {
    "addr:full":"1051 E Main St Ste 213 East Dundee IL 60118",
    "addr:housenumber":"1051",
    "addr:postcode":"60118",
    "addr:street":"E Main St Ste 213",
    "iso:country":"US",
    "sg:address":"1051 E Main St Ste 213",
    "sg:city":"East Dundee",
    "sg:classifiers":[
        {
            "category":"Banks & Credit Unions",
            "subcategory":"Financial Services",
            "type":"Services"
        }
    ],
    "sg:phone":"+1 847 551 1766",
    "sg:postcode":"60118",
    "sg:province":"IL",
    "sg:tags":[
        "broker",
        "mortgage"
    ],
    "wof:name":"Barclay's Financial Inc",
    "wof:placetype":"venue"
},
  "geometry": {"coordinates":[-88.24749799999999,42.089298],"type":"Point"}
}