{
  "type": "Feature",
  "properties": {
    "iso:country":"US",
    "sg:address":"14160 Cicero Ave",
    "sg:city":"Crestwood",
    "sg:classifiers":[
        {
            "category":"Personal",
            "subcategory":"Beauty Salon",
            "type":"Services"
        }
    ],
    "sg:phone":"+1 708 385 5544",
    "sg:postcode":"60445",
    "sg:province":"IL",
    "wof:name":"Russo Of Italy Hairstylists",
    "wof:placetype":"venue"
},
  "geometry": {"coordinates":[-87.73763599999999,41.635055],"type":"Point"}
}