{
  "type": "Feature",
  "properties": {
    "addr:full":"1045 W. Belmont Ave. Chicago IL 60657",
    "addr:housenumber":"1045",
    "addr:postcode":"60657",
    "addr:street":"W. Belmont Ave.",
    "iso:country":"US",
    "sg:address":"1045 W. Belmont Ave.",
    "sg:city":"Chicago",
    "sg:classifiers":[
        {
            "category":"Health Services",
            "subcategory":"Doctor",
            "type":"Services"
        }
    ],
    "sg:phone":"+1 630 238 1111",
    "sg:postcode":"60657",
    "sg:province":"IL",
    "sg:tags":[
        "podiatrist"
    ],
    "sg:website":"www.drjamesdvelarde.com",
    "wof:name":"James D. Velarde, DPM",
    "wof:placetype":"venue"
},
  "geometry": {"coordinates":[-87.655846,41.939638],"type":"Point"}
}