{
  "type": "Feature",
  "properties": {
    "addr:full":"1315 N Main St Princeton IL 61356",
    "addr:housenumber":"1315",
    "addr:postcode":"61356",
    "addr:street":"N Main St",
    "iso:country":"US",
    "sg:address":"1315 N Main St",
    "sg:city":"Princeton",
    "sg:classifiers":[
        {
            "category":"Home & Garden",
            "subcategory":"Building Materials",
            "type":"Retail Goods"
        }
    ],
    "sg:phone":"+1 815 875 1141",
    "sg:postcode":"61356",
    "sg:province":"IL",
    "sg:tags":[
        "lumber"
    ],
    "wof:name":"Allen Lumber Co",
    "wof:placetype":"venue"
},
  "geometry": {"coordinates":[-89.465097,41.388429],"type":"Point"}
}