{
  "type": "Feature",
  "properties": {
    "iso:country":"US",
    "sg:address":"24020 W Riverwalk Ct",
    "sg:city":"Plainfield",
    "sg:classifiers":[
        {
            "category":"Personal",
            "subcategory":"Massage",
            "type":"Services"
        },
        {
            "category":"Health Services",
            "subcategory":"Health Practitioner",
            "type":"Services"
        },
        {
            "category":"Health Services",
            "subcategory":"Chiropractor",
            "type":"Services"
        }
    ],
    "sg:phone":"+1 815 230 1013",
    "sg:postcode":"60544",
    "sg:province":"IL",
    "sg:tags":[
        "information",
        "sport",
        "chiropractic",
        "nutritionist",
        "therapist",
        "treatment",
        "medicine",
        "injury",
        "referral"
    ],
    "sg:website":"http://www.yext.com/p/superpages/health-source-of-plainfield-plainfield-illinois.html",
    "wof:name":"HealthSource of Plainfield",
    "wof:placetype":"venue"
},
  "geometry": {"coordinates":[-88.202938,41.619302],"type":"Point"}
}