{
  "type": "Feature",
  "properties": {
    "addr:full":"1008 W 63rd St Chicago IL 60621",
    "addr:housenumber":"1008",
    "addr:postcode":"60621",
    "addr:street":"W 63Rd St",
    "iso:country":"US",
    "sg:address":"1008 W 63rd St",
    "sg:city":"Chicago",
    "sg:classifiers":[
        {
            "category":"Shopping",
            "subcategory":"Beauty & Cosmetics",
            "type":"Retail Goods"
        }
    ],
    "sg:phone":"+1 773 918 0733",
    "sg:postcode":"60621",
    "sg:province":"IL",
    "sg:tags":[
        "supply"
    ],
    "wof:name":"Beauty Mart Inc",
    "wof:placetype":"venue"
},
  "geometry": {"coordinates":[-87.64998,41.779816],"type":"Point"}
}