{
  "type": "Feature",
  "properties": {
    "iso:country":"US",
    "sg:address":"1712 Hampshire Dr",
    "sg:city":"Elk Grove Village",
    "sg:classifiers":[
        {
            "category":"Manufacturing",
            "subcategory":"Metals",
            "type":"Manufacturing & Wholesale Goods"
        }
    ],
    "sg:phone":"+1 847 524 6909",
    "sg:postcode":"60007",
    "sg:province":"IL",
    "sg:tags":[
        "tool",
        "mfg"
    ],
    "wof:name":"Art Terlecki",
    "wof:placetype":"venue"
},
  "geometry": {"coordinates":[-88.051208,42.013537],"type":"Point"}
}