{
  "type": "Feature",
  "properties": {
    "addr:full":"1733 Gay Ave East Saint Louis IL 62207",
    "addr:housenumber":"1733",
    "addr:postcode":"62207",
    "addr:street":"Gay Ave East",
    "iso:country":"US",
    "sg:address":"1733 Gay Ave",
    "sg:city":"East Saint Louis",
    "sg:classifiers":[
        {
            "category":"Social Services",
            "subcategory":"Child Care",
            "type":"Services"
        }
    ],
    "sg:phone":"+1 618 271 0865",
    "sg:postcode":"62207",
    "sg:province":"IL",
    "sg:tags":[
        "day"
    ],
    "wof:name":"Dorothy A Radford",
    "wof:placetype":"venue"
},
  "geometry": {"coordinates":[-90.155901,38.602698],"type":"Point"}
}