{
  "type": "Feature",
  "properties": {
    "iso:country":"US",
    "sg:address":"1122 Gilbert Ave",
    "sg:city":"Downers Grove",
    "sg:classifiers":[
        {
            "category":"Social Services",
            "type":"Services"
        }
    ],
    "sg:phone":"+1 630 968 6569",
    "sg:postcode":"60515",
    "sg:province":"IL",
    "sg:tags":[
        "senior",
        "citizen"
    ],
    "wof:name":"Dupage Council Nutrition",
    "wof:placetype":"venue"
},
  "geometry": {"coordinates":[-88.014572,41.794623],"type":"Point"}
}