{
  "type": "Feature",
  "properties": {
    "iso:country":"US",
    "sg:address":"7106 Exner Rd",
    "sg:city":"Darien",
    "sg:classifiers":[
        {
            "category":"Autos & Motor Vehicles",
            "subcategory":"Automobile Sales",
            "type":"Retail Goods"
        }
    ],
    "sg:phone":"+1 630 460 5994",
    "sg:postcode":"60561",
    "sg:province":"IL",
    "sg:tags":[
        "new",
        "car"
    ],
    "wof:name":"Oakbrook Toyota",
    "wof:placetype":"venue"
},
  "geometry": {"coordinates":[-87.986828,41.758275],"type":"Point"}
}