{
  "type": "Feature",
  "properties": {
    "iso:country":"US",
    "sg:address":"205 N Washington St",
    "sg:city":"Wheaton",
    "sg:classifiers":[
        {
            "category":"Building & Trades",
            "subcategory":"Construction",
            "type":"Services"
        }
    ],
    "sg:phone":"+1 630 871 1220",
    "sg:postcode":"60187",
    "sg:province":"IL",
    "sg:tags":[
        "residential",
        "real estate"
    ],
    "wof:name":"Bechtold Development Company",
    "wof:placetype":"venue"
},
  "geometry": {"coordinates":[-88.101108,41.867248],"type":"Point"}
}