{
  "type": "Feature",
  "properties": {
    "addr:full":"933 S Lincoln Ave Waukegan IL 60085",
    "addr:housenumber":"933",
    "addr:postcode":"60085",
    "addr:street":"S Lincoln Ave",
    "iso:country":"US",
    "sg:address":"933 S Lincoln Ave",
    "sg:city":"Waukegan",
    "sg:classifiers":[
        {
            "category":"Retail",
            "subcategory":"Auto Repair",
            "type":"Services"
        }
    ],
    "sg:phone":"+1 847 249 0136",
    "sg:postcode":"60085",
    "sg:province":"IL",
    "sg:tags":[
        "general"
    ],
    "wof:name":"Acuna & Rodas Auto Repair",
    "wof:placetype":"venue"
},
  "geometry": {"coordinates":[-87.842026,42.341856],"type":"Point"}
}