{
  "type": "Feature",
  "properties": {
    "iso:country":"US",
    "sg:address":"520 S Maple Ave",
    "sg:city":"Oak Park",
    "sg:classifiers":[
        {
            "category":"Health Services",
            "subcategory":"Doctor",
            "type":"Services"
        }
    ],
    "sg:phone":"+1 708 660 6266",
    "sg:postcode":"60304",
    "sg:province":"IL",
    "sg:tags":[
        "physician",
        "surgeon"
    ],
    "wof:name":"Comprehensive Breast Ctr",
    "wof:placetype":"venue"
},
  "geometry": {"coordinates":[-87.803778,41.879436],"type":"Point"}
}