{
  "type": "Feature",
  "properties": {
    "addr:full":"185 Peterson Rd Libertyville IL 60048",
    "addr:housenumber":"185",
    "addr:postcode":"60048",
    "addr:street":"Peterson Rd",
    "iso:country":"US",
    "sg:address":"185 Peterson Rd",
    "sg:city":"Libertyville",
    "sg:classifiers":[
        {
            "category":"Building & Trades",
            "subcategory":"Equipment Rental",
            "type":"Services"
        }
    ],
    "sg:phone":"+1 847 362 7610",
    "sg:postcode":"60048",
    "sg:province":"IL",
    "wof:name":"Libertyville Rent-Alls",
    "wof:placetype":"venue"
},
  "geometry": {"coordinates":[-87.96407000000001,42.305898],"type":"Point"}
}