{
  "type": "Feature",
  "properties": {
    "iso:country":"US",
    "sg:address":"1315 Vandalia St",
    "sg:city":"Collinsville",
    "sg:classifiers":[
        {
            "category":"Shopping",
            "subcategory":"Musical Instruments",
            "type":"Retail Goods"
        },
        {
            "category":"Education",
            "subcategory":"Music School",
            "type":"Public Place"
        },
        {
            "category":"Manufacturing",
            "subcategory":"Musical Instruments",
            "type":"Manufacturing & Wholesale Goods"
        }
    ],
    "sg:phone":"+1 618 343 6900",
    "sg:postcode":"62234",
    "sg:province":"IL",
    "sg:tags":[
        "guitar",
        "instruments-rental",
        "amplifier",
        "teacher"
    ],
    "wof:name":"Guitars of the Stars",
    "wof:placetype":"venue"
},
  "geometry": {"coordinates":[-89.975841,38.68529],"type":"Point"}
}