{
  "type": "Feature",
  "properties": {
    "addr:full":"602 W University Ave Urbana IL 61801",
    "addr:housenumber":"602",
    "addr:postcode":"61801",
    "addr:street":"W University Ave",
    "iso:country":"US",
    "sg:address":"602 W University Ave",
    "sg:city":"Urbana",
    "sg:classifiers":[
        {
            "category":"Health Services",
            "subcategory":"Doctor",
            "type":"Services"
        }
    ],
    "sg:phone":"+1 217 383 3260",
    "sg:postcode":"61801",
    "sg:province":"IL",
    "sg:tags":[
        "podiatrist",
        "orthopedist"
    ],
    "wof:name":"Logsdon Phillip DPM",
    "wof:placetype":"venue"
},
  "geometry": {"coordinates":[-88.214699,40.116199],"type":"Point"}
}