{
  "type": "Feature",
  "properties": {
    "addr:full":"38628 N Hilltop Ave Antioch IL 60002",
    "addr:housenumber":"38628",
    "addr:postcode":"60002",
    "addr:street":"N Hilltop Ave",
    "iso:country":"US",
    "sg:address":"38628 N Hilltop Ave",
    "sg:city":"Antioch",
    "sg:classifiers":[
        {
            "category":"Building & Trades",
            "subcategory":"Construction",
            "type":"Services"
        }
    ],
    "sg:phone":"+1 847 356 3766",
    "sg:postcode":"60002",
    "sg:province":"IL",
    "sg:tags":[
        "paving",
        "contractor"
    ],
    "wof:name":"Eslinger Seal Coating",
    "wof:placetype":"venue"
},
  "geometry": {"coordinates":[-88.15015099999999,42.423276],"type":"Point"}
}