{
  "type": "Feature",
  "properties": {
    "iso:country":"US",
    "sg:address":"501 N Vermilion St",
    "sg:city":"Lexington",
    "sg:classifiers":[
        {
            "category":"Real Estate",
            "subcategory":"Real Estate Agent",
            "type":"Services"
        }
    ],
    "sg:phone":"+1 309 365 3551",
    "sg:postcode":"61753",
    "sg:province":"IL",
    "sg:tags":[
        "inspection"
    ],
    "wof:name":"Pillar To Post",
    "wof:placetype":"venue"
},
  "geometry": {"coordinates":[-88.775082,40.646083],"type":"Point"}
}