{
  "type": "Feature",
  "properties": {
    "addr:full":"1860 E Lincoln Hwy New Lenox IL 60451",
    "addr:housenumber":"1860",
    "addr:postcode":"60451",
    "addr:street":"E Lincoln Hwy",
    "iso:country":"US",
    "sg:address":"1860 E Lincoln Hwy",
    "sg:city":"New Lenox",
    "sg:classifiers":[
        {
            "category":"Cinema",
            "subcategory":"Movie Rental",
            "type":"Entertainment"
        }
    ],
    "sg:phone":"+1 815 463 1393",
    "sg:postcode":"60451",
    "sg:province":"IL",
    "sg:tags":[
        "leasing",
        "video",
        "disc",
        "tape"
    ],
    "wof:name":"Movie Gallery",
    "wof:placetype":"venue"
},
  "geometry": {"coordinates":[-87.93034400000001,41.511238],"type":"Point"}
}