{
  "type": "Feature",
  "properties": {
    "addr:full":"1300 Harvey St Beloit IL 53511",
    "addr:housenumber":"1300",
    "addr:postcode":"53511",
    "addr:street":"Harvey St",
    "iso:country":"US",
    "sg:address":"1300 Harvey St",
    "sg:city":"Beloit",
    "sg:classifiers":[
        {
            "category":"Manufacturing",
            "subcategory":"Chemicals & Compounds",
            "type":"Manufacturing & Wholesale Goods"
        }
    ],
    "sg:phone":"+1 608 362 1900",
    "sg:postcode":"53511",
    "sg:province":"IL",
    "sg:tags":[
        "paint",
        "product",
        "mfg"
    ],
    "wof:name":"Murmac Paint Mfg Inc",
    "wof:placetype":"venue"
},
  "geometry": {"coordinates":[-89.022428,42.516254],"type":"Point"}
}