{
  "type": "Feature",
  "properties": {
    "iso:country":"US",
    "sg:address":"905 Spring St",
    "sg:city":"Galena",
    "sg:classifiers":[
        {
            "category":"Autos & Motor Vehicles",
            "subcategory":"Auto Supplies",
            "type":"Retail Goods"
        }
    ],
    "sg:phone":"+1   ",
    "sg:postcode":"61036",
    "sg:province":"IL",
    "wof:name":"Moliters Shell Service Station",
    "wof:placetype":"venue"
},
  "geometry": {"coordinates":[-90.438035,42.416128],"type":"Point"}
}