{
  "type": "Feature",
  "properties": {
    "addr:full":"5622 N Jersey Ave Chicago IL 60659",
    "addr:housenumber":"5622",
    "addr:postcode":"60659",
    "addr:street":"N Jersey Ave",
    "iso:country":"US",
    "sg:address":"5622 N Jersey Ave",
    "sg:city":"Chicago",
    "sg:classifiers":[
        {
            "category":"Social Services",
            "subcategory":"Job Training",
            "type":"Services"
        }
    ],
    "sg:phone":"+1 773 478 0361",
    "sg:postcode":"60659",
    "sg:province":"IL",
    "sg:tags":[
        "consultant"
    ],
    "wof:name":"Training Paths Inc",
    "wof:placetype":"venue"
},
  "geometry": {"coordinates":[-87.709023,41.983719],"type":"Point"}
}