{
  "type": "Feature",
  "properties": {
    "iso:country":"US",
    "sg:address":"5117 S Cornell Ave",
    "sg:city":"Chicago",
    "sg:classifiers":[
        {
            "category":"Professional",
            "subcategory":"Lawyer & Legal Services",
            "type":"Services"
        }
    ],
    "sg:phone":"+1 773 288 6938",
    "sg:postcode":"60615",
    "sg:province":"IL",
    "wof:name":"Robinson Edward Ltd",
    "wof:placetype":"venue"
},
  "geometry": {"coordinates":[-87.586403,41.802399],"type":"Point"}
}