{
  "type": "Feature",
  "properties": {
    "iso:country":"US",
    "sg:address":"846 E 87th Pl",
    "sg:city":"Chicago",
    "sg:classifiers":[
        {
            "category":"Wholesale",
            "subcategory":"Computers",
            "type":"Manufacturing & Wholesale Goods"
        }
    ],
    "sg:phone":"+1 773 994 1972",
    "sg:postcode":"60619",
    "sg:province":"IL",
    "sg:tags":[
        "equipment"
    ],
    "wof:name":"Merchanized Solutions Group Inc",
    "wof:placetype":"venue"
},
  "geometry": {"coordinates":[-87.603216,41.735748],"type":"Point"}
}