{
  "type": "Feature",
  "properties": {
    "addr:full":"1550 S State St Chicago IL 60605",
    "addr:housenumber":"1550",
    "addr:postcode":"60605",
    "addr:street":"S State St",
    "iso:country":"US",
    "sg:address":"1550 S State St",
    "sg:city":"Chicago",
    "sg:classifiers":[
        {
            "category":"Building & Trades",
            "subcategory":"Construction",
            "type":"Services"
        }
    ],
    "sg:phone":"+1 312 949 9599",
    "sg:postcode":"60605",
    "sg:province":"IL",
    "sg:tags":[
        "contractor"
    ],
    "wof:name":"We O'neil Construction",
    "wof:placetype":"venue"
},
  "geometry": {"coordinates":[-87.62751400000001,41.860748],"type":"Point"}
}