{
  "type": "Feature",
  "properties": {
    "addr:full":"529 W Roosevelt Rd Wheaton IL 60187",
    "addr:housenumber":"529",
    "addr:postcode":"60187",
    "addr:street":"W Roosevelt Rd",
    "iso:country":"US",
    "sg:address":"529 W Roosevelt Rd",
    "sg:city":"Wheaton",
    "sg:classifiers":[
        {
            "category":"Building & Trades",
            "subcategory":"Construction",
            "type":"Services"
        }
    ],
    "sg:phone":"+1 630 293 9586",
    "sg:postcode":"60187",
    "sg:province":"IL",
    "sg:tags":[
        "industrial",
        "painting",
        "contractors-commercial",
        "contractor"
    ],
    "sg:website":"http://www.aaapaintco.com",
    "wof:name":"Aaa Painting Contractors, Inc.",
    "wof:placetype":"venue"
},
  "geometry": {"coordinates":[-88.11415599999999,41.858639],"type":"Point"}
}