{
  "type": "Feature",
  "properties": {
    "addr:full":"1640 Lebanon Ave Belleville IL 62221",
    "addr:housenumber":"1640",
    "addr:postcode":"62221",
    "addr:street":"Lebanon Ave",
    "iso:country":"US",
    "sg:address":"1640 Lebanon Ave",
    "sg:city":"Belleville",
    "sg:classifiers":[
        {
            "category":"Personal",
            "subcategory":"Beauty Salon",
            "type":"Services"
        }
    ],
    "sg:phone":"+1 618 277 0097",
    "sg:postcode":"62221",
    "sg:province":"IL",
    "sg:tags":[
        "manicuring"
    ],
    "wof:name":"Custom Nail Design",
    "wof:placetype":"venue"
},
  "geometry": {"coordinates":[-89.96405799999999,38.53373],"type":"Point"}
}