{
  "type": "Feature",
  "properties": {
    "iso:country":"US",
    "sg:address":"606 Shepherd Ln",
    "sg:city":"Geneva",
    "sg:classifiers":[
        {
            "category":"Building & Trades",
            "subcategory":"Landscaping Services",
            "type":"Services"
        }
    ],
    "sg:phone":"+1 630 620 0707",
    "sg:postcode":"60134",
    "sg:province":"IL",
    "sg:tags":[
        "tree"
    ],
    "wof:name":"Little Termite Inc",
    "wof:placetype":"venue"
},
  "geometry": {"coordinates":[-88.354178,41.895828],"type":"Point"}
}