{
  "type": "Feature",
  "properties": {
    "addr:full":"4129 W Lawrence Ave Chicago IL 60630",
    "addr:housenumber":"4129",
    "addr:postcode":"60630",
    "addr:street":"W Lawrence Ave",
    "iso:country":"US",
    "sg:address":"4129 W Lawrence Ave",
    "sg:city":"Chicago",
    "sg:classifiers":[
        {
            "category":"Restaurant",
            "type":"Food & Drink"
        }
    ],
    "sg:phone":"+1 773 725 1812",
    "sg:postcode":"60630",
    "sg:province":"IL",
    "sg:tags":[
        "pizza"
    ],
    "sg:website":"mariespizzachicago.com/",
    "wof:name":"Marie's Pizzeria & Lounge",
    "wof:placetype":"venue"
},
  "geometry": {"coordinates":[-87.731577,41.968205],"type":"Point"}
}