{
  "type": "Feature",
  "properties": {
    "addr:full":"1129 Beloit Ave Forest Park IL 60130",
    "addr:housenumber":"1129",
    "addr:postcode":"60130",
    "addr:street":"Beloit Ave",
    "iso:country":"US",
    "sg:address":"1129 Beloit Ave",
    "sg:city":"Forest Park",
    "sg:classifiers":[
        {
            "category":"Health Services",
            "subcategory":"Doctor",
            "type":"Services"
        }
    ],
    "sg:phone":"+1 708 771 3743",
    "sg:postcode":"60130",
    "sg:province":"IL",
    "sg:tags":[
        "medical"
    ],
    "wof:name":"Martin G Fortier Dr",
    "wof:placetype":"venue"
},
  "geometry": {"coordinates":[-87.81159599999999,41.86587],"type":"Point"}
}