{
  "type": "Feature",
  "properties": {
    "iso:country":"US",
    "sg:address":"10331 Linus Ln",
    "sg:city":"Oak Lawn",
    "sg:classifiers":[
        {
            "category":"Manufacturing",
            "subcategory":"Glass & Minerals",
            "type":"Manufacturing & Wholesale Goods"
        }
    ],
    "sg:phone":"+1 708 425 1657",
    "sg:postcode":"60453",
    "sg:province":"IL",
    "sg:tags":[
        "concrete",
        "product",
        "mfg"
    ],
    "wof:name":"Felician Sisters",
    "wof:placetype":"venue"
},
  "geometry": {"coordinates":[-87.747461,41.704177],"type":"Point"}
}