{
  "type": "Feature",
  "properties": {
    "iso:country":"US",
    "sg:address":"3710 Riverside Dr",
    "sg:city":"Crystal Lake",
    "sg:classifiers":[
        {
            "category":"Autos & Motor Vehicles",
            "subcategory":"Auto Supplies",
            "type":"Retail Goods"
        },
        {
            "category":"Wholesale",
            "subcategory":"Auto Parts",
            "type":"Manufacturing & Wholesale Goods"
        }
    ],
    "sg:phone":"+1 815 459 0355",
    "sg:postcode":"60014",
    "sg:province":"IL",
    "sg:tags":[
        "mfg",
        "automotive",
        "after",
        "electrical",
        "t",
        "automobile",
        "representative"
    ],
    "sg:website":"www.venselenterprises.com",
    "wof:name":"Vensel Enterprises Inc",
    "wof:placetype":"venue"
},
  "geometry": {"coordinates":[-88.22577200000001,42.275221],"type":"Point"}
}