{
  "type": "Feature",
  "properties": {
    "iso:country":"US",
    "sg:address":"148 N Mayfield Ave",
    "sg:city":"Chicago",
    "sg:classifiers":[
        {
            "category":"Travel",
            "subcategory":"Hotels & Motels",
            "type":"Entertainment"
        }
    ],
    "sg:phone":"+1 773 378 1035",
    "sg:postcode":"60644",
    "sg:province":"IL",
    "wof:name":"Tia-Cc Mae Suites",
    "wof:placetype":"venue"
},
  "geometry": {"coordinates":[-87.77179700000001,41.882999],"type":"Point"}
}