{
  "type": "Feature",
  "properties": {
    "iso:country":"US",
    "sg:address":"720 Industrial Dr",
    "sg:city":"Cary",
    "sg:classifiers":[
        {
            "category":"Professional",
            "type":"Services"
        }
    ],
    "sg:phone":"+1 847 462 1062",
    "sg:postcode":"60013",
    "sg:province":"IL",
    "sg:tags":[
        "establishment"
    ],
    "wof:name":"Dalveco",
    "wof:placetype":"venue"
},
  "geometry": {"coordinates":[-88.255591,42.214829],"type":"Point"}
}