{
  "type": "Feature",
  "properties": {
    "addr:full":"67 Academy St Eldorado IL 62930",
    "addr:housenumber":"67",
    "addr:postcode":"62930",
    "addr:street":"Academy St",
    "iso:country":"US",
    "sg:address":"67 Academy St",
    "sg:city":"Eldorado",
    "sg:classifiers":[
        {
            "category":"Organizations",
            "subcategory":"Religious Organization",
            "type":"Services"
        }
    ],
    "sg:phone":"+1 618 273 7536",
    "sg:postcode":"62930",
    "sg:province":"IL",
    "wof:name":"Charles Phelps Rev",
    "wof:placetype":"venue"
},
  "geometry": {"coordinates":[-88.45048199999999,37.810063],"type":"Point"}
}