{
  "type": "Feature",
  "properties": {
    "addr:full":"8624 W 95th St Hickory Hills IL 60457",
    "addr:housenumber":"8624",
    "addr:postcode":"60457",
    "addr:street":"W 95Th St",
    "iso:country":"US",
    "sg:address":"8624 W 95th St",
    "sg:city":"Hickory Hills",
    "sg:classifiers":[
        {
            "category":"Restaurant",
            "type":"Food & Drink"
        }
    ],
    "sg:phone":"+1 708 598 6680",
    "sg:postcode":"60457",
    "sg:province":"IL",
    "sg:tags":[
        "banquet",
        "rooms"
    ],
    "wof:name":"Camelot Restaurant",
    "wof:placetype":"venue"
},
  "geometry": {"coordinates":[-87.833685,41.718253],"type":"Point"}
}