{
  "type": "Feature",
  "properties": {
    "addr:full":"60 E. Van Buren St. Suite 1502 Chicago IL 60605",
    "addr:housenumber":"60",
    "addr:postcode":"60605",
    "addr:street":"E. Van Buren St. Suite 1502",
    "iso:country":"US",
    "sg:address":"60 E. Van Buren St. Suite 1502",
    "sg:city":"Chicago",
    "sg:classifiers":[
        {
            "category":"Professional",
            "type":"Services"
        },
        {
            "category":"Professional",
            "subcategory":"Printing & Photocopies",
            "type":"Services"
        }
    ],
    "sg:phone":"+1 312 542 1300",
    "sg:postcode":"60605",
    "sg:province":"IL",
    "sg:website":"www.alohadocs.com",
    "wof:name":"Aloha Document Services",
    "wof:placetype":"venue"
},
  "geometry": {"coordinates":[-87.625253,41.877003],"type":"Point"}
}