{
  "type": "Feature",
  "properties": {
    "addr:full":"1020 N Kolmar Ave Chicago IL 60651",
    "addr:housenumber":"1020",
    "addr:postcode":"60651",
    "addr:street":"N Kolmar Ave",
    "iso:country":"US",
    "sg:address":"1020 N Kolmar Ave",
    "sg:city":"Chicago",
    "sg:classifiers":[
        {
            "category":"Manufacturing",
            "subcategory":"Metals",
            "type":"Manufacturing & Wholesale Goods"
        }
    ],
    "sg:phone":"+1 773 384 3700",
    "sg:postcode":"60651",
    "sg:province":"IL",
    "sg:tags":[
        "steel",
        "detailers",
        "product",
        "mfg",
        "fabricated",
        "stampings",
        "structural"
    ],
    "sg:website":"http://www.tritonindustries.com",
    "wof:name":"Triton Industries, Inc.",
    "wof:placetype":"venue"
},
  "geometry": {"coordinates":[-87.739812,41.899183],"type":"Point"}
}