{
  "type": "Feature",
  "properties": {
    "iso:country":"US",
    "sg:address":"950 W North Ave",
    "sg:city":"Melrose Park",
    "sg:classifiers":[
        {
            "category":"Food & Beverages",
            "subcategory":"Groceries & Convenience Stores",
            "type":"Retail Goods"
        }
    ],
    "sg:phone":"+1 708 410 1700",
    "sg:postcode":"60160",
    "sg:province":"IL",
    "wof:name":"Grand Mart",
    "wof:placetype":"venue"
},
  "geometry": {"coordinates":[-87.84552600000001,41.907986],"type":"Point"}
}