{
  "type": "Feature",
  "properties": {
    "addr:full":"81 S River St Aurora IL 60506",
    "addr:housenumber":"81",
    "addr:postcode":"60506",
    "addr:street":"S River St",
    "iso:country":"US",
    "sg:address":"81 S River St",
    "sg:city":"Aurora",
    "sg:classifiers":[
        {
            "category":"Restaurant",
            "type":"Food & Drink"
        }
    ],
    "sg:phone":"+1 630 844 6603",
    "sg:postcode":"60506",
    "sg:province":"IL",
    "sg:tags":[
        "mexican"
    ],
    "wof:name":"Taqueria El Cio",
    "wof:placetype":"venue"
},
  "geometry": {"coordinates":[-88.31888499999999,41.757545],"type":"Point"}
}