{
  "type": "Feature",
  "properties": {
    "addr:full":"1234 W Sunset Ter Arlington Heights IL 60005",
    "addr:housenumber":"1234",
    "addr:postcode":"60005",
    "addr:street":"W Sunset Ter",
    "iso:country":"US",
    "sg:address":"1234 W Sunset Ter",
    "sg:city":"Arlington Heights",
    "sg:classifiers":[
        {
            "category":"Building & Trades",
            "subcategory":"Construction",
            "type":"Services"
        }
    ],
    "sg:phone":"+1 847 398 2068",
    "sg:postcode":"60005",
    "sg:province":"IL",
    "sg:tags":[
        "house"
    ],
    "wof:name":"Holfeld Construction",
    "wof:placetype":"venue"
},
  "geometry": {"coordinates":[-87.998994,42.083483],"type":"Point"}
}