{
  "type": "Feature",
  "properties": {
    "addr:full":"621 W Roosevelt Rd Chicago IL 60607",
    "addr:housenumber":"621",
    "addr:postcode":"60607",
    "addr:street":"W Roosevelt Rd",
    "iso:country":"US",
    "sg:address":"621 W Roosevelt Rd",
    "sg:city":"Chicago",
    "sg:classifiers":[
        {
            "category":"Shopping",
            "subcategory":"Department Store",
            "type":"Retail Goods"
        },
        {
            "category":"Wholesale",
            "subcategory":"Non-durable Goods",
            "type":"Manufacturing & Wholesale Goods"
        },
        {
            "category":"Professional",
            "subcategory":"Business Services",
            "type":"Services"
        }
    ],
    "sg:phone":"+1 312 733 0991",
    "sg:postcode":"60607",
    "sg:province":"IL",
    "sg:tags":[
        "merchandise-wholesale",
        "broker",
        "merchandise",
        "variety"
    ],
    "wof:name":"Roosevelt Sales",
    "wof:placetype":"venue"
},
  "geometry": {"coordinates":[-87.64312200000001,41.867204],"type":"Point"}
}