{
  "type": "Feature",
  "properties": {
    "addr:full":"7108 W Belmont Ave Chicago IL 60634",
    "addr:housenumber":"7108",
    "addr:postcode":"60634",
    "addr:street":"W Belmont Ave",
    "iso:country":"US",
    "sg:address":"7108 W Belmont Ave",
    "sg:city":"Chicago",
    "sg:classifiers":[
        {
            "category":"Autos & Motor Vehicles",
            "subcategory":"Auto Supplies",
            "type":"Retail Goods"
        }
    ],
    "sg:phone":"+1 773 736 4848",
    "sg:postcode":"60634",
    "sg:province":"IL",
    "sg:tags":[
        "part"
    ],
    "wof:name":"Premier Auto Supply Inc",
    "wof:placetype":"venue"
},
  "geometry": {"coordinates":[-87.804901,41.938],"type":"Point"}
}