{
  "type": "Feature",
  "properties": {
    "addr:full":"401 E Illinois Street Suite 330 Chicago IL 60611",
    "addr:housenumber":"401",
    "addr:postcode":"60611",
    "addr:street":"E Illinois Street Suite 330",
    "iso:country":"US",
    "sg:address":"401 E Illinois Street Suite 330",
    "sg:city":"Chicago",
    "sg:classifiers":[
        {
            "category":"Shopping",
            "subcategory":"Computers & Home Electronics",
            "type":"Retail Goods"
        }
    ],
    "sg:phone":"+1 312 645 0303",
    "sg:postcode":"60611",
    "sg:province":"IL",
    "wof:name":"I Cubed",
    "wof:placetype":"venue"
},
  "geometry": {"coordinates":[-87.617671,41.891032],"type":"Point"}
}