{
  "type": "Feature",
  "properties": {
    "iso:country":"US",
    "sg:address":"300 S Broadway Ave",
    "sg:city":"Urbana",
    "sg:classifiers":[
        {
            "category":"Education",
            "subcategory":"Vocational School",
            "type":"Public Place"
        },
        {
            "category":"Education",
            "subcategory":"School",
            "type":"Public Place"
        }
    ],
    "sg:phone":"+1 217 328 2590",
    "sg:postcode":"61801",
    "sg:province":"IL",
    "sg:tags":[
        "high",
        "middle",
        "cosmetology",
        "elementary"
    ],
    "wof:name":"Mr John's School of Cosmetology Esthetics & Nails",
    "wof:placetype":"venue"
},
  "geometry": {"coordinates":[-88.207497,40.1115],"type":"Point"}
}