{
  "type": "Feature",
  "properties": {
    "addr:full":"77 W Jackson Blvd Fl 20 Chicago IL 60604",
    "addr:housenumber":"77;20",
    "addr:postcode":"60604",
    "addr:street":"W Jackson Blvd Fl",
    "iso:country":"US",
    "sg:address":"77 W Jackson Blvd Fl 20",
    "sg:city":"Chicago",
    "sg:classifiers":[
        {
            "category":"Farming",
            "subcategory":"Livestock Farm",
            "type":"Manufacturing & Wholesale Goods"
        }
    ],
    "sg:phone":"+1 312 353 6664",
    "sg:postcode":"60604",
    "sg:province":"IL",
    "sg:tags":[
        "livestock-commission"
    ],
    "wof:name":"Midwest Regional Office",
    "wof:placetype":"venue"
},
  "geometry": {"coordinates":[-87.630189,41.878172],"type":"Point"}
}