{
  "type": "Feature",
  "properties": {
    "iso:country":"US",
    "sg:address":"119 W Gilmer Rd",
    "sg:city":"Lake Zurich",
    "sg:classifiers":[
        {
            "category":"Restaurant",
            "type":"Food & Drink"
        }
    ],
    "sg:phone":"+1   ",
    "sg:postcode":"60047",
    "sg:province":"IL",
    "sg:tags":[
        "eating"
    ],
    "wof:name":"Oreganos Corner Cafe",
    "wof:placetype":"venue"
},
  "geometry": {"coordinates":[-88.052624,42.239872],"type":"Point"}
}