{
  "type": "Feature",
  "properties": {
    "iso:country":"US",
    "sg:address":"900 S. Wabash Ave",
    "sg:city":"Chicago",
    "sg:classifiers":[
        {
            "category":"Professional",
            "subcategory":"Art Services",
            "type":"Services"
        },
        {
            "category":"Professional",
            "subcategory":"Printing & Photocopies",
            "type":"Services"
        }
    ],
    "sg:phone":"+1 312 753 3025",
    "sg:postcode":"60605",
    "sg:province":"IL",
    "sg:tags":[
        "lithographer",
        "graphic",
        "design"
    ],
    "sg:website":"www.indigodigitalprinting.com",
    "wof:name":"Indigo Digital Printing",
    "wof:placetype":"venue"
},
  "geometry": {"coordinates":[-87.626079,41.870389],"type":"Point"}
}