{
  "type": "Feature",
  "properties": {
    "addr:full":"895 S State St Ste 201 Hampshire IL 60140",
    "addr:housenumber":"895",
    "addr:postcode":"60140",
    "addr:street":"S State St Ste 201",
    "iso:country":"US",
    "sg:address":"895 S State St Ste 201",
    "sg:city":"Hampshire",
    "sg:classifiers":[
        {
            "category":"Personal",
            "subcategory":"Massage",
            "type":"Services"
        },
        {
            "category":"Health Services",
            "subcategory":"Doctor",
            "type":"Services"
        }
    ],
    "sg:phone":"+1 847 683 4358",
    "sg:postcode":"60140",
    "sg:province":"IL",
    "sg:website":"www.unlimitedperformance.org",
    "wof:name":"Kishwaukee Health Care",
    "wof:placetype":"venue"
},
  "geometry": {"coordinates":[-88.528856,42.08924],"type":"Point"}
}