{
  "type": "Feature",
  "properties": {
    "addr:full":"275 Saint Clair Sq Fairview Heights IL 62208",
    "addr:housenumber":"275",
    "addr:postcode":"62208",
    "addr:street":"Saint Clair Sq",
    "iso:country":"US",
    "sg:address":"275 Saint Clair Sq",
    "sg:city":"Fairview Heights",
    "sg:classifiers":[
        {
            "category":"Shopping",
            "subcategory":"Department Store",
            "type":"Retail Goods"
        }
    ],
    "sg:phone":"+1 618 632 5000",
    "sg:postcode":"62208",
    "sg:province":"IL",
    "wof:name":"Dillard's",
    "wof:placetype":"venue"
},
  "geometry": {"coordinates":[-89.982697,38.594398],"type":"Point"}
}