{
  "type": "Feature",
  "properties": {
    "addr:full":"1896 Deer Run Dr Montgomery IL 60538",
    "addr:housenumber":"1896",
    "addr:postcode":"60538",
    "addr:street":"Deer Run Dr",
    "iso:country":"US",
    "sg:address":"1896 Deer Run Dr",
    "sg:city":"Montgomery",
    "sg:classifiers":[
        {
            "category":"Arts & Performance",
            "subcategory":"Theater",
            "type":"Entertainment"
        }
    ],
    "sg:phone":"+1 630 896 2455",
    "sg:postcode":"60538",
    "sg:province":"IL",
    "sg:tags":[
        "group"
    ],
    "wof:name":"Innovative Entertainment",
    "wof:placetype":"venue"
},
  "geometry": {"coordinates":[-88.329746,41.719805],"type":"Point"}
}