{
  "type": "Feature",
  "properties": {
    "addr:full":"123 N Main St Altamont IL 62411",
    "addr:housenumber":"123",
    "addr:postcode":"62411",
    "addr:street":"N Main St",
    "iso:country":"US",
    "sg:address":"123 N Main St",
    "sg:city":"Altamont",
    "sg:classifiers":[
        {
            "category":"Building & Trades",
            "subcategory":"Plumbing",
            "type":"Services"
        }
    ],
    "sg:phone":"+1 618 483 6159",
    "sg:postcode":"62411",
    "sg:province":"IL",
    "sg:tags":[
        "heating",
        "air",
        "re",
        "conditioning",
        "plumbing",
        "contractor"
    ],
    "wof:name":"R & H Plumbing & Heating Inc",
    "wof:placetype":"venue"
},
  "geometry": {"coordinates":[-88.747839,39.061526],"type":"Point"}
}