{
  "type": "Feature",
  "properties": {
    "iso:country":"US",
    "sg:address":"426 S Milwaukee Ave",
    "sg:city":"Libertyville",
    "sg:classifiers":[
        {
            "category":"Real Estate",
            "subcategory":"Real Estate Agent",
            "type":"Services"
        }
    ],
    "sg:phone":"+1 847 367 0078",
    "sg:postcode":"60048",
    "sg:province":"IL",
    "sg:tags":[
        "inspection"
    ],
    "wof:name":"Dunsing Inspectech",
    "wof:placetype":"venue"
},
  "geometry": {"coordinates":[-87.952348,42.278519],"type":"Point"}
}