{
  "type": "Feature",
  "properties": {
    "iso:country":"US",
    "sg:address":"233 E Wacker Dr",
    "sg:city":"Chicago",
    "sg:classifiers":[
        {
            "category":"Personal",
            "subcategory":"Beauty Salon",
            "type":"Services"
        }
    ],
    "sg:phone":"+1 312 565 0505",
    "sg:postcode":"60601",
    "sg:province":"IL",
    "sg:tags":[
        "hair"
    ],
    "wof:name":"Spa Di La Fronza Salon",
    "wof:placetype":"venue"
},
  "geometry": {"coordinates":[-87.62116,41.887674],"type":"Point"}
}