{
  "type": "Feature",
  "properties": {
    "addr:full":"1400 N Larkin Ave Joliet IL 60435",
    "addr:housenumber":"1400",
    "addr:postcode":"60435",
    "addr:street":"N Larkin Ave",
    "iso:country":"US",
    "sg:address":"1400 N Larkin Ave",
    "sg:city":"Joliet",
    "sg:classifiers":[
        {
            "category":"Shopping",
            "subcategory":"Hobbies, Toys, & Games",
            "type":"Retail Goods"
        },
        {
            "category":"Shopping",
            "subcategory":"Crafts & Fabrics",
            "type":"Retail Goods"
        }
    ],
    "sg:phone":"+1 815 725 4792",
    "sg:postcode":"60435",
    "sg:province":"IL",
    "sg:tags":[
        "shop",
        "toy",
        "art",
        "supply",
        "hobby",
        "model",
        "store"
    ],
    "sg:website":"http://www.hobbylobby.com",
    "wof:name":"Hobby Lobby",
    "wof:placetype":"venue"
},
  "geometry": {"coordinates":[-88.125702,41.548038],"type":"Point"}
}