{
  "type": "Feature",
  "properties": {
    "iso:country":"US",
    "sg:address":"544 Congress St",
    "sg:city":"Ottawa",
    "sg:classifiers":[
        {
            "category":"Wholesale",
            "subcategory":"Machinery & Supplies",
            "type":"Manufacturing & Wholesale Goods"
        }
    ],
    "sg:phone":"+1 815 434 0874",
    "sg:postcode":"61350",
    "sg:province":"IL",
    "sg:tags":[
        "packaging"
    ],
    "wof:name":"Orga Pack Inc",
    "wof:placetype":"venue"
},
  "geometry": {"coordinates":[-88.833973,41.346783],"type":"Point"}
}