{
  "type": "Feature",
  "properties": {
    "addr:full":"6847 N 2200th Ave Geneseo IL 61254",
    "addr:housenumber":"6847",
    "addr:postcode":"61254",
    "addr:street":"N 2200Th Ave",
    "iso:country":"US",
    "sg:address":"6847 N 2200th Ave",
    "sg:city":"Geneseo",
    "sg:phone":"+1 309 949 2433",
    "sg:postcode":"61254",
    "sg:province":"IL",
    "sg:tags":[
        "farm",
        "corn",
        "soybean"
    ],
    "wof:name":"Tom Housenga",
    "wof:placetype":"venue"
},
  "geometry": {"coordinates":[-90.299267,41.46906],"type":"Point"}
}