{
  "type": "Feature",
  "properties": {
    "iso:country":"US",
    "sg:address":"6000 W Ogden Ave",
    "sg:city":"Cicero",
    "sg:classifiers":[
        {
            "category":"Railroad",
            "type":"Transportation"
        }
    ],
    "sg:phone":"+1 708 652 1111",
    "sg:postcode":"60804",
    "sg:province":"IL",
    "sg:tags":[
        "repair",
        "semi"
    ],
    "wof:name":"Bozovic Brothers Entps Inc",
    "wof:placetype":"venue"
},
  "geometry": {"coordinates":[-87.77447600000001,41.833563],"type":"Point"}
}