{
  "type": "Feature",
  "properties": {
    "addr:full":"127 US Hwy 50 Carlyle IL 62231",
    "addr:housenumber":"127",
    "addr:postcode":"62231",
    "addr:street":"Us Hwy 50 Carlyle",
    "iso:country":"US",
    "sg:address":"127 US Hwy 50",
    "sg:city":"Carlyle",
    "sg:classifiers":[
        {
            "category":"Restaurant",
            "type":"Food & Drink"
        }
    ],
    "sg:phone":"+1   ",
    "sg:postcode":"62231",
    "sg:province":"IL",
    "sg:tags":[
        "eating"
    ],
    "wof:name":"Dairy Queen",
    "wof:placetype":"venue"
},
  "geometry": {"coordinates":[-89.359911,38.6103],"type":"Point"}
}