{
  "type": "Feature",
  "properties": {
    "addr:full":"15817 West Ave Harvey IL 60426",
    "addr:housenumber":"15817",
    "addr:postcode":"60426",
    "addr:street":"West Ave",
    "iso:country":"US",
    "sg:address":"15817 West Ave",
    "sg:city":"Harvey",
    "sg:classifiers":[
        {
            "category":"Building & Trades",
            "subcategory":"Locksmith",
            "type":"Services"
        }
    ],
    "sg:phone":"+1 708 566 9075",
    "sg:postcode":"60426",
    "sg:province":"IL",
    "sg:tags":[
        "key"
    ],
    "wof:name":"Always Available 24 Hour Emergency Locksmi",
    "wof:placetype":"venue"
},
  "geometry": {"coordinates":[-87.644783,41.602403],"type":"Point"}
}