{
  "type": "Feature",
  "properties": {
    "iso:country":"US",
    "sg:address":"9409 Holy Cross Ln",
    "sg:city":"Breese",
    "sg:classifiers":[
        {
            "category":"Health Services",
            "subcategory":"Doctor",
            "type":"Services"
        }
    ],
    "sg:phone":"+1 618 526 7399",
    "sg:postcode":"62230",
    "sg:province":"IL",
    "sg:tags":[
        "physician",
        "surgeon"
    ],
    "sg:website":"www.gatewaygeriatrics.com",
    "wof:name":"Southern Illinois Geriatrics",
    "wof:placetype":"venue"
},
  "geometry": {"coordinates":[-89.528189,38.625392],"type":"Point"}
}