{
  "type": "Feature",
  "properties": {
    "iso:country":"US",
    "sg:address":"885 Main St",
    "sg:city":"Antioch",
    "sg:classifiers":[
        {
            "category":"Organizations",
            "subcategory":"Community Association",
            "type":"Services"
        }
    ],
    "sg:phone":"+1 847 395 3381",
    "sg:postcode":"60002",
    "sg:province":"IL",
    "sg:tags":[
        "club"
    ],
    "wof:name":"Club 885 Civic",
    "wof:placetype":"venue"
},
  "geometry": {"coordinates":[-88.096053,42.478231],"type":"Point"}
}