{
  "type": "Feature",
  "properties": {
    "iso:country":"US",
    "sg:address":"16142 Cicero Ave",
    "sg:city":"Oak Forest",
    "sg:classifiers":[
        {
            "category":"Personal",
            "subcategory":"Beauty Salon",
            "type":"Services"
        }
    ],
    "sg:phone":"+1 708 687 1242",
    "sg:postcode":"60452",
    "sg:province":"IL",
    "sg:tags":[
        "shop"
    ],
    "wof:name":"Hair Loft Beauty Salon",
    "wof:placetype":"venue"
},
  "geometry": {"coordinates":[-87.73639300000001,41.598956],"type":"Point"}
}