{
  "type": "Feature",
  "properties": {
    "addr:full":"8510 S Harlem Ave Bridgeview IL 60455",
    "addr:housenumber":"8510",
    "addr:postcode":"60455",
    "addr:street":"S Harlem Ave",
    "iso:country":"US",
    "sg:address":"8510 S Harlem Ave",
    "sg:city":"Bridgeview",
    "sg:classifiers":[
        {
            "category":"Real Estate",
            "subcategory":"Real Estate Services",
            "type":"Services"
        },
        {
            "category":"Real Estate",
            "subcategory":"Real Estate Agent",
            "type":"Services"
        }
    ],
    "sg:phone":"+1 708 430 6666",
    "sg:postcode":"60455",
    "sg:province":"IL",
    "sg:tags":[
        "buyer",
        "broker"
    ],
    "wof:name":"Re/Max Express Real Estate, Inc.",
    "wof:placetype":"venue"
},
  "geometry": {"coordinates":[-87.799211,41.736335],"type":"Point"}
}