{
  "type": "Feature",
  "properties": {
    "iso:country":"US",
    "sg:address":"1202 Nelson Rd",
    "sg:city":"Rock Falls",
    "sg:classifiers":[
        {
            "category":"Real Estate",
            "subcategory":"Real Estate Operator",
            "type":"Services"
        }
    ],
    "sg:phone":"+1 815 625 2849",
    "sg:postcode":"61071",
    "sg:province":"IL",
    "sg:tags":[
        "property",
        "lessor"
    ],
    "wof:name":"Coleman Glen and Ruth",
    "wof:placetype":"venue"
},
  "geometry": {"coordinates":[-89.601677,41.7643],"type":"Point"}
}