{
  "type": "Feature",
  "properties": {
    "addr:full":"632 N 1st Bank Dr Palatine IL 60067",
    "addr:housenumber":"632",
    "addr:postcode":"60067",
    "addr:street":"N 1St Bank Dr",
    "iso:country":"US",
    "sg:address":"632 N 1st Bank Dr",
    "sg:city":"Palatine",
    "sg:classifiers":[
        {
            "category":"Real Estate",
            "subcategory":"Real Estate Agent",
            "type":"Services"
        }
    ],
    "sg:phone":"+1 847 991 7744",
    "sg:postcode":"60067",
    "sg:province":"IL",
    "sg:tags":[
        "multiple",
        "listing"
    ],
    "wof:name":"Multiple Listing",
    "wof:placetype":"venue"
},
  "geometry": {"coordinates":[-88.03641,42.120438],"type":"Point"}
}