{
  "type": "Feature",
  "properties": {
    "iso:country":"US",
    "sg:address":"2411 W Schaumburg Rd",
    "sg:city":"Schaumburg",
    "sg:classifiers":[
        {
            "category":"Sports & Exercise",
            "subcategory":"Gym",
            "type":"Entertainment"
        }
    ],
    "sg:phone":"+1 847 923 0564",
    "sg:postcode":"60194",
    "sg:province":"IL",
    "sg:tags":[
        "woman",
        "for",
        "club",
        "gymnasium",
        "health",
        "studio",
        "man"
    ],
    "sg:website":"www.ballyfitness.com",
    "wof:name":"Bally Total Fitness",
    "wof:placetype":"venue"
},
  "geometry": {"coordinates":[-88.154335,42.029862],"type":"Point"}
}