{
  "type": "Feature",
  "properties": {
    "iso:country":"US",
    "sg:address":"55 Powder Creek Dr",
    "sg:city":"Belleville",
    "sg:classifiers":[
        {
            "category":"Restaurant",
            "type":"Food & Drink"
        }
    ],
    "sg:phone":"+1   ",
    "sg:postcode":"62223",
    "sg:province":"IL",
    "sg:tags":[
        "eating"
    ],
    "wof:name":"Lori Powell Catering",
    "wof:placetype":"venue"
},
  "geometry": {"coordinates":[-90.064529,38.568203],"type":"Point"}
}