{
  "type": "Feature",
  "properties": {
    "iso:country":"US",
    "sg:address":"2408 Timber Trl Dr",
    "sg:city":"Crystal Lake",
    "sg:classifiers":[
        {
            "category":"Restaurant",
            "type":"Food & Drink"
        }
    ],
    "sg:phone":"+1 847 392 8802",
    "sg:postcode":"60012",
    "sg:province":"IL",
    "sg:tags":[
        "pizza"
    ],
    "wof:name":"Rosati's Pizza",
    "wof:placetype":"venue"
},
  "geometry": {"coordinates":[-88.245169,42.277057],"type":"Point"}
}