{
  "type": "Feature",
  "properties": {
    "addr:full":"3151 Harrison St Evanston IL 60201",
    "addr:housenumber":"3151",
    "addr:postcode":"60201",
    "addr:street":"Harrison St",
    "iso:country":"US",
    "sg:address":"3151 Harrison St",
    "sg:city":"Evanston",
    "sg:classifiers":[
        {
            "category":"Shopping",
            "subcategory":"Music",
            "type":"Retail Goods"
        }
    ],
    "sg:phone":"+1 847 864 3981",
    "sg:postcode":"60201",
    "sg:province":"IL",
    "sg:tags":[
        "compact",
        "record",
        "disc",
        "tape"
    ],
    "sg:website":"www.classicalcollector.com",
    "wof:name":"Classical Collector",
    "wof:placetype":"venue"
},
  "geometry": {"coordinates":[-87.72275,42.062614],"type":"Point"}
}