{
  "type": "Feature",
  "properties": {
    "addr:full":"1448 Fargo Blvd Geneva IL 60134",
    "addr:housenumber":"1448",
    "addr:postcode":"60134",
    "addr:street":"Fargo Blvd",
    "iso:country":"US",
    "sg:address":"1448 Fargo Blvd",
    "sg:city":"Geneva",
    "sg:classifiers":[
        {
            "category":"Shopping",
            "type":"Retail Goods"
        }
    ],
    "sg:phone":"+1   ",
    "sg:postcode":"60134",
    "sg:province":"IL",
    "sg:tags":[
        "personal",
        "medical",
        "pump"
    ],
    "wof:name":"Intra Pump Infusion Systems",
    "wof:placetype":"venue"
},
  "geometry": {"coordinates":[-88.326894,41.874971],"type":"Point"}
}