{
  "type": "Feature",
  "properties": {
    "iso:country":"US",
    "sg:address":"23W240 Geneva Rd",
    "sg:city":"Glen Ellyn",
    "sg:classifiers":[
        {
            "category":"Education",
            "subcategory":"School",
            "type":"Public Place"
        }
    ],
    "sg:phone":"+1 630 790 6485",
    "sg:postcode":"60137",
    "sg:province":"IL",
    "sg:tags":[
        "high",
        "middle",
        "elementary"
    ],
    "wof:name":"Schools Public",
    "wof:placetype":"venue"
},
  "geometry": {"coordinates":[-88.073233,41.889741],"type":"Point"}
}