{
  "type": "Feature",
  "properties": {
    "addr:full":"6032 Roosevelt Rd Oak Park IL 60304",
    "addr:housenumber":"6032",
    "addr:postcode":"60304",
    "addr:street":"Roosevelt Rd",
    "iso:country":"US",
    "sg:address":"6032 Roosevelt Rd",
    "sg:city":"Oak Park",
    "sg:classifiers":[
        {
            "category":"Shopping",
            "subcategory":"Jewelry",
            "type":"Retail Goods"
        }
    ],
    "sg:phone":"+1 708 383 4363",
    "sg:postcode":"60304",
    "sg:province":"IL",
    "sg:website":"www.Harrisonjewelers.com",
    "wof:name":"Harrison Jewelers Inc",
    "wof:placetype":"venue"
},
  "geometry": {"coordinates":[-87.78220399999999,41.865299],"type":"Point"}
}