{
  "type": "Feature",
  "properties": {
    "addr:full":"205 Snow Ave Loves Park IL 61111",
    "addr:housenumber":"205",
    "addr:postcode":"61111",
    "addr:street":"Snow Ave",
    "iso:country":"US",
    "sg:address":"205 Snow Ave",
    "sg:city":"Loves Park",
    "sg:classifiers":[
        {
            "category":"Real Estate",
            "subcategory":"Real Estate Agent",
            "type":"Services"
        }
    ],
    "sg:phone":"+1 815 633 0524",
    "sg:postcode":"61111",
    "sg:province":"IL",
    "wof:name":"Pauley Real Estate",
    "wof:placetype":"venue"
},
  "geometry": {"coordinates":[-89.06186099999999,42.299028],"type":"Point"}
}