{
  "type": "Feature",
  "properties": {
    "addr:full":"518 Shagbark Dr Elgin IL 60123",
    "addr:housenumber":"518",
    "addr:postcode":"60123",
    "addr:street":"Shagbark Dr",
    "iso:country":"US",
    "sg:address":"518 Shagbark Dr",
    "sg:city":"Elgin",
    "sg:classifiers":[
        {
            "category":"Professional",
            "type":"Services"
        }
    ],
    "sg:phone":"+1 847 488 1483",
    "sg:postcode":"60123",
    "sg:province":"IL",
    "sg:tags":[
        "establishment"
    ],
    "wof:name":"JAF Enterprises Inc",
    "wof:placetype":"venue"
},
  "geometry": {"coordinates":[-88.34,42.047664],"type":"Point"}
}