{
  "type": "Feature",
  "properties": {
    "addr:full":"319 E Elm St Gillespie IL 62033",
    "addr:housenumber":"319",
    "addr:postcode":"62033",
    "addr:street":"E Elm St",
    "iso:country":"US",
    "sg:address":"319 E Elm St",
    "sg:city":"Gillespie",
    "sg:classifiers":[
        {
            "category":"Retail",
            "subcategory":"Auto Repair",
            "type":"Services"
        }
    ],
    "sg:phone":"+1 217 839 4542",
    "sg:postcode":"62033",
    "sg:province":"IL",
    "sg:tags":[
        "body",
        "painting",
        "repairing",
        "automobile"
    ],
    "wof:name":"Body Care Plus",
    "wof:placetype":"venue"
},
  "geometry": {"coordinates":[-89.822835,39.128612],"type":"Point"}
}