{
  "type": "Feature",
  "properties": {
    "iso:country":"US",
    "sg:address":"610 8th Ave",
    "sg:city":"Fulton",
    "sg:classifiers":[
        {
            "category":"Personal",
            "subcategory":"Beauty Salon",
            "type":"Services"
        }
    ],
    "sg:phone":"+1 815 589 2314",
    "sg:postcode":"61252",
    "sg:province":"IL",
    "sg:tags":[
        "shop"
    ],
    "wof:name":"Kay's Beauty Shop",
    "wof:placetype":"venue"
},
  "geometry": {"coordinates":[-90.16240500000001,41.86878],"type":"Point"}
}