{
  "type": "Feature",
  "properties": {
    "addr:full":"6374 N Lincoln Ave Ste 301 Chicago IL 60659",
    "addr:housenumber":"6374",
    "addr:postcode":"60659",
    "addr:street":"N Lincoln Ave Ste 301",
    "iso:country":"US",
    "sg:address":"6374 N Lincoln Ave Ste 301",
    "sg:city":"Chicago",
    "sg:classifiers":[
        {
            "category":"Health Services",
            "subcategory":"Doctor",
            "type":"Services"
        }
    ],
    "sg:phone":"+1 773 463 2377",
    "sg:postcode":"60659",
    "sg:province":"IL",
    "sg:tags":[
        "medicine",
        "sport",
        "orthopedist"
    ],
    "sg:website":"gtortho.com",
    "wof:name":"Dr. Christos Giannoulias, MD",
    "wof:placetype":"venue"
},
  "geometry": {"coordinates":[-87.71848799999999,41.997055],"type":"Point"}
}