{
  "type": "Feature",
  "properties": {
    "addr:full":"202 N Dunton Ave Arlington Heights IL 60004",
    "addr:housenumber":"202",
    "addr:postcode":"60004",
    "addr:street":"N Dunton Ave",
    "iso:country":"US",
    "sg:address":"202 N Dunton Ave",
    "sg:city":"Arlington Heights",
    "sg:classifiers":[
        {
            "category":"Restaurant",
            "type":"Food & Drink"
        }
    ],
    "sg:phone":"+1   ",
    "sg:postcode":"60004",
    "sg:province":"IL",
    "sg:tags":[
        "eating"
    ],
    "wof:name":"La Chicanita Mexican Rest",
    "wof:placetype":"venue"
},
  "geometry": {"coordinates":[-87.98297100000001,42.085549],"type":"Point"}
}