{
  "type": "Feature",
  "properties": {
    "iso:country":"US",
    "sg:address":"910 Skokie Blvd",
    "sg:city":"Northbrook",
    "sg:classifiers":[
        {
            "category":"Banks & Credit Unions",
            "subcategory":"Investment Brokerage",
            "type":"Services"
        }
    ],
    "sg:phone":"+1 847 272 3300",
    "sg:postcode":"60062",
    "sg:province":"IL",
    "sg:tags":[
        "advisory"
    ],
    "wof:name":"Cloverleaf Fund II LLC",
    "wof:placetype":"venue"
},
  "geometry": {"coordinates":[-87.790863,42.136639],"type":"Point"}
}