{
  "type": "Feature",
  "properties": {
    "addr:full":"1300 W Maple St New Lenox IL 60451",
    "addr:housenumber":"1300",
    "addr:postcode":"60451",
    "addr:street":"W Maple St",
    "iso:country":"US",
    "sg:address":"1300 W Maple St",
    "sg:city":"New Lenox",
    "sg:classifiers":[
        {
            "category":"Home & Garden",
            "subcategory":"Building Materials",
            "type":"Retail Goods"
        }
    ],
    "sg:phone":"+1   ",
    "sg:postcode":"60451",
    "sg:province":"IL",
    "sg:tags":[
        "brick",
        "related"
    ],
    "wof:name":"Illinois Brick Co",
    "wof:placetype":"venue"
},
  "geometry": {"coordinates":[-87.989302,41.519555],"type":"Point"}
}