{
  "type": "Feature",
  "properties": {
    "iso:country":"US",
    "sg:address":"501 W Golf Rd",
    "sg:city":"Des Plaines",
    "sg:classifiers":[
        {
            "category":"Organizations",
            "subcategory":"Religious Organization",
            "type":"Services"
        }
    ],
    "sg:phone":"+1 847 364 0530",
    "sg:postcode":"60016",
    "sg:province":"IL",
    "sg:tags":[
        "church"
    ],
    "sg:website":"www.golfroadbaptistchurch.lifewaylink.or",
    "wof:name":"Golf Road Baptist Church Inc",
    "wof:placetype":"venue"
},
  "geometry": {"coordinates":[-87.936019,42.047715],"type":"Point"}
}