{
  "type": "Feature",
  "properties": {
    "addr:full":"2210 W North Ave Chicago IL 60647",
    "addr:housenumber":"2210",
    "addr:postcode":"60647",
    "addr:street":"W North Ave",
    "iso:country":"US",
    "sg:address":"2210 W North Ave",
    "sg:city":"Chicago",
    "sg:classifiers":[
        {
            "category":"Professional",
            "subcategory":"Art Services",
            "type":"Services"
        }
    ],
    "sg:phone":"+1 773 489 1400",
    "sg:postcode":"60647",
    "sg:province":"IL",
    "sg:tags":[
        "graphic",
        "designer"
    ],
    "sg:website":"www.sx2.com",
    "wof:name":"Essex Two",
    "wof:placetype":"venue"
},
  "geometry": {"coordinates":[-87.683179,41.910456],"type":"Point"}
}