{
  "type": "Feature",
  "properties": {
    "iso:country":"US",
    "sg:address":"2930 Twin Oaks Dr",
    "sg:city":"Joliet",
    "sg:classifiers":[
        {
            "category":"Shopping",
            "subcategory":"Crafts & Fabrics",
            "type":"Retail Goods"
        }
    ],
    "sg:phone":"+1 815 725 9725",
    "sg:postcode":"60435",
    "sg:province":"IL",
    "sg:tags":[
        "sewing",
        "costume",
        "accessory",
        "trimmings"
    ],
    "wof:name":"Needler's Niche",
    "wof:placetype":"venue"
},
  "geometry": {"coordinates":[-88.159988,41.52408],"type":"Point"}
}