{
  "type": "Feature",
  "properties": {
    "iso:country":"US",
    "sg:address":"2009 N Bluff Rd",
    "sg:city":"Collinsville",
    "sg:classifiers":[
        {
            "category":"Farming",
            "subcategory":"Farm",
            "type":"Manufacturing & Wholesale Goods"
        }
    ],
    "sg:phone":"+1 618 344 7450",
    "sg:postcode":"62234",
    "sg:province":"IL",
    "sg:tags":[
        "crop",
        "general"
    ],
    "wof:name":"Springvalley Farms",
    "wof:placetype":"venue"
},
  "geometry": {"coordinates":[-90.00277,38.733697],"type":"Point"}
}