{
  "type": "Feature",
  "properties": {
    "addr:full":"2762 Knox Highway 6 Oneida IL 61467",
    "addr:housenumber":"2762",
    "addr:postcode":"61467",
    "addr:street":"Knox Highway 6",
    "iso:country":"US",
    "sg:address":"2762 Knox Highway 6",
    "sg:city":"Oneida",
    "sg:classifiers":[
        {
            "category":"Real Estate",
            "subcategory":"Real Estate Services",
            "type":"Services"
        },
        {
            "category":"Real Estate",
            "subcategory":"Real Estate Agent",
            "type":"Services"
        }
    ],
    "sg:phone":"+1 309 483 6367",
    "sg:postcode":"61467",
    "sg:province":"IL",
    "sg:tags":[
        "buyer",
        "broker"
    ],
    "wof:name":"Holt Inc",
    "wof:placetype":"venue"
},
  "geometry": {"coordinates":[-90.30695299999999,41.137646],"type":"Point"}
}