{
  "type": "Feature",
  "properties": {
    "addr:full":"63 Douglas Ave Elgin IL 60120",
    "addr:housenumber":"63",
    "addr:postcode":"60120",
    "addr:street":"Douglas Ave",
    "iso:country":"US",
    "sg:address":"63 Douglas Ave",
    "sg:city":"Elgin",
    "sg:classifiers":[
        {
            "category":"Wholesale",
            "subcategory":"Stationery",
            "type":"Manufacturing & Wholesale Goods"
        }
    ],
    "sg:phone":"+1 847 622 1313",
    "sg:postcode":"60120",
    "sg:province":"IL",
    "sg:tags":[
        "business",
        "form",
        "system"
    ],
    "sg:website":"www.docuprintforms.com",
    "wof:name":"Docuprint Business Forms",
    "wof:placetype":"venue"
},
  "geometry": {"coordinates":[-88.283946,42.038439],"type":"Point"}
}