{
  "type": "Feature",
  "properties": {
    "addr:full":"6561 N Seeley Ave Chicago IL 60645",
    "addr:housenumber":"6561",
    "addr:postcode":"60645",
    "addr:street":"N Seeley Ave",
    "iso:country":"US",
    "sg:address":"6561 N Seeley Ave",
    "sg:city":"Chicago",
    "sg:classifiers":[
        {
            "category":"Professional",
            "subcategory":"Management & Consulting",
            "type":"Services"
        }
    ],
    "sg:phone":"+1 773 973 4850",
    "sg:postcode":"60645",
    "sg:province":"IL",
    "sg:tags":[
        "control",
        "noise",
        "vibration",
        "consultant",
        "environmental",
        "remediation",
        "services-site"
    ],
    "wof:name":"Midwest Envmtl Assistance Ctr",
    "wof:placetype":"venue"
},
  "geometry": {"coordinates":[-87.681422,42.000623],"type":"Point"}
}