{
  "type": "Feature",
  "properties": {
    "iso:country":"US",
    "sg:address":"4256 W Walton St",
    "sg:city":"Chicago",
    "sg:classifiers":[
        {
            "category":"Education",
            "subcategory":"School",
            "type":"Public Place"
        }
    ],
    "sg:phone":"+1 773 227 7572",
    "sg:postcode":"60651",
    "sg:province":"IL",
    "wof:name":"Holy Family Lutheran School",
    "wof:placetype":"venue"
},
  "geometry": {"coordinates":[-87.732381,41.898076],"type":"Point"}
}