{
  "type": "Feature",
  "properties": {
    "iso:country":"US",
    "sg:address":"308 Cary Point Dr",
    "sg:city":"Cary",
    "sg:classifiers":[
        {
            "category":"Wholesale",
            "subcategory":"Computers",
            "type":"Manufacturing & Wholesale Goods"
        }
    ],
    "sg:phone":"+1 847 516 0191",
    "sg:postcode":"60013",
    "sg:province":"IL",
    "sg:tags":[
        "equipment",
        "peripheral"
    ],
    "wof:name":"Micro Parts & Supplies Inc",
    "wof:placetype":"venue"
},
  "geometry": {"coordinates":[-88.231718,42.202111],"type":"Point"}
}