{
  "type": "Feature",
  "properties": {
    "iso:country":"US",
    "sg:address":"6003 N Wakefield Rd",
    "sg:city":"Noble",
    "sg:classifiers":[
        {
            "category":"Building & Trades",
            "subcategory":"Construction",
            "type":"Services"
        }
    ],
    "sg:phone":"+1 618 752 7421",
    "sg:postcode":"62868",
    "sg:province":"IL",
    "sg:tags":[
        "carpenter"
    ],
    "wof:name":"Bill Herdes",
    "wof:placetype":"venue"
},
  "geometry": {"coordinates":[-88.243767,38.789349],"type":"Point"}
}