{
  "type": "Feature",
  "properties": {
    "addr:full":"4043 N Ravenswood Ste 220 Chicago IL 60613",
    "addr:housenumber":"4043",
    "addr:postcode":"60613",
    "addr:street":"N Ravenswood Ste 220",
    "iso:country":"US",
    "sg:address":"4043 N Ravenswood Ste 220",
    "sg:city":"Chicago",
    "sg:classifiers":[
        {
            "category":"Communications",
            "subcategory":"Newspaper",
            "type":"Services"
        }
    ],
    "sg:phone":"+1 773 404 1497",
    "sg:postcode":"60613",
    "sg:province":"IL",
    "sg:tags":[
        "print",
        "medium"
    ],
    "sg:website":"www.urchicago.com",
    "wof:name":"UR Chicago Magazine",
    "wof:placetype":"venue"
},
  "geometry": {"coordinates":[-87.67383100000001,41.955058],"type":"Point"}
}