{
  "type": "Feature",
  "properties": {
    "addr:full":"735 Marquette St La Salle IL 61301",
    "addr:housenumber":"735",
    "addr:postcode":"61301",
    "addr:street":"Marquette St",
    "iso:country":"US",
    "sg:address":"735 Marquette St",
    "sg:city":"La Salle",
    "sg:classifiers":[
        {
            "category":"Building & Trades",
            "subcategory":"Construction",
            "type":"Services"
        }
    ],
    "sg:phone":"+1 815 220 8233",
    "sg:postcode":"61301",
    "sg:province":"IL",
    "sg:tags":[
        "house"
    ],
    "wof:name":"Emmanuel Limberg Limberg Bldrs",
    "wof:placetype":"venue"
},
  "geometry": {"coordinates":[-89.096559,41.33474],"type":"Point"}
}