{
  "type": "Feature",
  "properties": {
    "addr:full":"2501 Huffman Blvd Rockford IL 61103",
    "addr:housenumber":"2501",
    "addr:postcode":"61103",
    "addr:street":"Huffman Blvd",
    "iso:country":"US",
    "sg:address":"2501 Huffman Blvd",
    "sg:city":"Rockford",
    "sg:classifiers":[
        {
            "category":"Food & Beverages",
            "subcategory":"Groceries & Convenience Stores",
            "type":"Retail Goods"
        }
    ],
    "sg:phone":"+1 815 962 5640",
    "sg:postcode":"61103",
    "sg:province":"IL",
    "wof:name":"Stop N Shop",
    "wof:placetype":"venue"
},
  "geometry": {"coordinates":[-89.086851,42.298431],"type":"Point"}
}