{
  "type": "Feature",
  "properties": {
    "iso:country":"US",
    "sg:address":"1905 S Mulford Rd",
    "sg:city":"Rockford",
    "sg:classifiers":[
        {
            "category":"Organizations",
            "subcategory":"Religious Organization",
            "type":"Services"
        }
    ],
    "sg:phone":"+1 815 398 6164",
    "sg:postcode":"61108",
    "sg:province":"IL",
    "wof:name":"Jehovah S Witnesses East",
    "wof:placetype":"venue"
},
  "geometry": {"coordinates":[-88.999751,42.249328],"type":"Point"}
}