{
  "type": "Feature",
  "properties": {
    "addr:full":"12118 Ellis Rd Highland IL 62249",
    "addr:housenumber":"12118",
    "addr:postcode":"62249",
    "addr:street":"Ellis Rd",
    "iso:country":"US",
    "sg:address":"12118 Ellis Rd",
    "sg:city":"Highland",
    "sg:classifiers":[
        {
            "category":"Retail",
            "subcategory":"Animal Services",
            "type":"Services"
        }
    ],
    "sg:phone":"+1 618 654 3401",
    "sg:postcode":"62249",
    "sg:province":"IL",
    "wof:name":"Highland Horse Stable",
    "wof:placetype":"venue"
},
  "geometry": {"coordinates":[-89.707064,38.713243],"type":"Point"}
}