{
  "type": "Feature",
  "properties": {
    "iso:country":"US",
    "sg:address":"203 N Crest Ave",
    "sg:city":"Bartlett",
    "sg:classifiers":[
        {
            "category":"Professional",
            "subcategory":"Detective & Security Services",
            "type":"Services"
        }
    ],
    "sg:phone":"+1 630 837 8671",
    "sg:postcode":"60103",
    "sg:province":"IL",
    "sg:tags":[
        "information",
        "bureau"
    ],
    "wof:name":"Jim S Service",
    "wof:placetype":"venue"
},
  "geometry": {"coordinates":[-88.17897000000001,41.996867],"type":"Point"}
}