{
  "type": "Feature",
  "properties": {
    "iso:country":"US",
    "sg:address":"8358 E 1025th Ave",
    "sg:city":"Effingham",
    "sg:classifiers":[
        {
            "category":"Education",
            "subcategory":"School",
            "type":"Public Place"
        }
    ],
    "sg:phone":"+1 217 536 9306",
    "sg:postcode":"62401",
    "sg:province":"IL",
    "wof:name":"ASK Christian Academy",
    "wof:placetype":"venue"
},
  "geometry": {"coordinates":[-88.644983,39.065338],"type":"Point"}
}