{
  "type": "Feature",
  "properties": {
    "iso:country":"US",
    "sg:address":"125 S Galena St",
    "sg:city":"Tiskilwa",
    "sg:classifiers":[
        {
            "category":"Home & Garden",
            "subcategory":"Building Materials",
            "type":"Retail Goods"
        },
        {
            "category":"Building & Trades",
            "subcategory":"Construction",
            "type":"Services"
        }
    ],
    "sg:phone":"+1 815 646 4606",
    "sg:postcode":"61368",
    "sg:province":"IL",
    "sg:tags":[
        "concrete",
        "staining",
        "contractor"
    ],
    "wof:name":"Forristall Concrete Inc",
    "wof:placetype":"venue"
},
  "geometry": {"coordinates":[-89.51000999999999,41.291541],"type":"Point"}
}