{
  "type": "Feature",
  "properties": {
    "iso:country":"US",
    "sg:address":"432 E. State Pkwy #128",
    "sg:city":"Schaumburg",
    "sg:classifiers":[
        {
            "category":"Internet Cafe",
            "subcategory":"None",
            "type":"Food & Drink"
        },
        {
            "category":"Professional",
            "subcategory":"Computer Services",
            "type":"Services"
        }
    ],
    "sg:phone":"+1 847 524 3900",
    "sg:postcode":"60173",
    "sg:province":"IL",
    "sg:tags":[
        "web",
        "product",
        "network",
        "hosting",
        "isp",
        "site",
        "system",
        "design",
        "provider",
        "software"
    ],
    "sg:website":"http://www.ync.net",
    "wof:name":"YourNet Connection",
    "wof:placetype":"venue"
},
  "geometry": {"coordinates":[-88.06898200000001,42.055327],"type":"Point"}
}