{
  "type": "Feature",
  "properties": {
    "addr:full":"420 Elmwood Ave Evanston IL 60202",
    "addr:housenumber":"420",
    "addr:postcode":"60202",
    "addr:street":"Elmwood Ave",
    "iso:country":"US",
    "sg:address":"420 Elmwood Ave",
    "sg:city":"Evanston",
    "sg:classifiers":[
        {
            "category":"Building & Trades",
            "subcategory":"Construction",
            "type":"Services"
        }
    ],
    "sg:phone":"+1 847 867 7428",
    "sg:postcode":"60202",
    "sg:province":"IL",
    "sg:tags":[
        "house"
    ],
    "wof:name":"Zk Roofing & Construction",
    "wof:placetype":"venue"
},
  "geometry": {"coordinates":[-87.684271,42.025794],"type":"Point"}
}