{
  "type": "Feature",
  "properties": {
    "addr:full":"566 W Adams St Chicago IL 60661",
    "addr:housenumber":"566",
    "addr:postcode":"60661",
    "addr:street":"W Adams St",
    "iso:country":"US",
    "sg:address":"566 W Adams St",
    "sg:city":"Chicago",
    "sg:classifiers":[
        {
            "category":"Professional",
            "subcategory":"Computer Services",
            "type":"Services"
        }
    ],
    "sg:phone":"+1 312 669 9500",
    "sg:postcode":"60661",
    "sg:province":"IL",
    "sg:tags":[
        "specializing",
        "consultant",
        "as",
        "software",
        "operates"
    ],
    "wof:name":"Paragon Consulting Group Inc",
    "wof:placetype":"venue"
},
  "geometry": {"coordinates":[-87.642467,41.879348],"type":"Point"}
}