{
  "type": "Feature",
  "properties": {
    "addr:full":"1200 Shermer Rd Northbrook IL 60062",
    "addr:housenumber":"1200",
    "addr:postcode":"60062",
    "addr:street":"Shermer Rd",
    "iso:country":"US",
    "sg:address":"1200 Shermer Rd",
    "sg:city":"Northbrook",
    "sg:classifiers":[
        {
            "category":"Banks & Credit Unions",
            "subcategory":"Financial Services",
            "type":"Services"
        }
    ],
    "sg:phone":"+1 847 480 7721",
    "sg:postcode":"60062",
    "sg:province":"IL",
    "sg:tags":[
        "mortgage"
    ],
    "wof:name":"Hiton Financial Services",
    "wof:placetype":"venue"
},
  "geometry": {"coordinates":[-87.823204,42.131675],"type":"Point"}
}