{
  "type": "Feature",
  "properties": {
    "addr:full":"820 W Jackson Blvd Ste 850 Chicago IL 60607",
    "addr:housenumber":"820",
    "addr:postcode":"60607",
    "addr:street":"W Jackson Blvd Ste 850",
    "iso:country":"US",
    "sg:address":"820 W Jackson Blvd Ste 850",
    "sg:city":"Chicago",
    "sg:classifiers":[
        {
            "category":"Professional",
            "subcategory":"Employment Agencies",
            "type":"Services"
        }
    ],
    "sg:phone":"+1 312 422 0036",
    "sg:postcode":"60607",
    "sg:province":"IL",
    "wof:name":"Amr Pronurse",
    "wof:placetype":"venue"
},
  "geometry": {"coordinates":[-87.64815400000001,41.877962],"type":"Point"}
}