{
  "type": "Feature",
  "properties": {
    "addr:full":"5286 Yorktown Rd Prophetstown IL 61277",
    "addr:housenumber":"5286",
    "addr:postcode":"61277",
    "addr:street":"Yorktown Rd",
    "iso:country":"US",
    "sg:address":"5286 Yorktown Rd",
    "sg:city":"Prophetstown",
    "sg:phone":"+1 815 537 2414",
    "sg:postcode":"61277",
    "sg:province":"IL",
    "sg:tags":[
        "a",
        "farm",
        "cash",
        "raw",
        "grain",
        "real estate"
    ],
    "wof:name":"Plautz Realty Inc",
    "wof:placetype":"venue"
},
  "geometry": {"coordinates":[-89.862405,41.662798],"type":"Point"}
}