{
  "type": "Feature",
  "properties": {
    "iso:country":"US",
    "sg:address":"114 N Vine St",
    "sg:city":"Urbana",
    "sg:classifiers":[
        {
            "category":"Banks & Credit Unions",
            "subcategory":"Investment Brokerage",
            "type":"Services"
        }
    ],
    "sg:phone":"+1 217 344 7806",
    "sg:postcode":"61802",
    "sg:province":"IL",
    "sg:tags":[
        "security"
    ],
    "wof:name":"Edward Jones 17640",
    "wof:placetype":"venue"
},
  "geometry": {"coordinates":[-88.204918,40.113382],"type":"Point"}
}