{
  "type": "Feature",
  "properties": {
    "iso:country":"US",
    "sg:address":"6810 Gardner Expy",
    "sg:city":"Quincy",
    "sg:classifiers":[
        {
            "category":"Building & Trades",
            "subcategory":"Construction",
            "type":"Services"
        }
    ],
    "sg:phone":"+1 217 222 6831",
    "sg:postcode":"62305",
    "sg:province":"IL",
    "sg:tags":[
        "general",
        "contractor"
    ],
    "wof:name":"Diamond Construction Co",
    "wof:placetype":"venue"
},
  "geometry": {"coordinates":[-91.379178,39.849928],"type":"Point"}
}