{
  "type": "Feature",
  "properties": {
    "iso:country":"US",
    "sg:address":"6560 W Fullerton Ave Ste S",
    "sg:city":"Chicago",
    "sg:classifiers":[
        {
            "category":"Shopping",
            "subcategory":"Department Store",
            "type":"Retail Goods"
        }
    ],
    "sg:phone":"+1 773 385 5608",
    "sg:postcode":"60707",
    "sg:province":"IL",
    "wof:name":"Max 10",
    "wof:placetype":"venue"
},
  "geometry": {"coordinates":[-87.791967,41.923787],"type":"Point"}
}