{
  "type": "Feature",
  "properties": {
    "iso:country":"US",
    "sg:address":"436 N Lake St",
    "sg:city":"Aurora",
    "sg:classifiers":[
        {
            "category":"Banks & Credit Unions",
            "subcategory":"Bank",
            "type":"Services"
        }
    ],
    "sg:phone":"+1 630 897 9200",
    "sg:postcode":"60506",
    "sg:province":"IL",
    "sg:tags":[
        "loan",
        "real estate"
    ],
    "wof:name":"First Centennial Mortgage",
    "wof:placetype":"venue"
},
  "geometry": {"coordinates":[-88.313698,41.764921],"type":"Point"}
}