{
  "type": "Feature",
  "properties": {
    "iso:country":"US",
    "sg:address":"2800 S River Rd",
    "sg:city":"Des Plaines",
    "sg:classifiers":[
        {
            "category":"Health Services",
            "subcategory":"Clinic",
            "type":"Services"
        },
        {
            "category":"Professional",
            "subcategory":"Advertising",
            "type":"Services"
        }
    ],
    "sg:phone":"+1 847 298 9900",
    "sg:postcode":"60018",
    "sg:province":"IL",
    "sg:tags":[
        "organization",
        "medical",
        "agency",
        "surgical"
    ],
    "wof:name":"Peters Fergus Group Inc",
    "wof:placetype":"venue"
},
  "geometry": {"coordinates":[-87.864783,42.002755],"type":"Point"}
}