{
  "type": "Feature",
  "properties": {
    "iso:country":"US",
    "sg:address":"2331 Grove Ave",
    "sg:city":"Berwyn",
    "sg:classifiers":[
        {
            "category":"Home & Garden",
            "subcategory":"Home Furnishings",
            "type":"Retail Goods"
        }
    ],
    "sg:phone":"+1   ",
    "sg:postcode":"60402",
    "sg:province":"IL",
    "wof:name":"Atomic Mama",
    "wof:placetype":"venue"
},
  "geometry": {"coordinates":[-87.794415,41.847679],"type":"Point"}
}