{
  "type": "Feature",
  "properties": {
    "iso:country":"US",
    "sg:address":"420 S Illinois St",
    "sg:city":"Belleville",
    "sg:classifiers":[
        {
            "category":"Manufacturing",
            "subcategory":"Rubber & Plastics",
            "type":"Manufacturing & Wholesale Goods"
        },
        {
            "category":"Autos & Motor Vehicles",
            "subcategory":"Auto Supplies",
            "type":"Retail Goods"
        }
    ],
    "sg:phone":"+1 618 233 0177",
    "sg:postcode":"62220",
    "sg:province":"IL",
    "sg:tags":[
        "tires-wholesale",
        "tire",
        "manufacturer"
    ],
    "wof:name":"Froesel Tire (formerly Centreads)",
    "wof:placetype":"venue"
},
  "geometry": {"coordinates":[-89.984261,38.509609],"type":"Point"}
}