{
  "type": "Feature",
  "properties": {
    "iso:country":"US",
    "sg:address":"1751 W Division St",
    "sg:city":"Chicago",
    "sg:classifiers":[
        {
            "category":"Shopping",
            "subcategory":"Clothing, Apparel, & Fashions",
            "type":"Retail Goods"
        }
    ],
    "sg:phone":"+1 312 421 2799",
    "sg:postcode":"60622",
    "sg:province":"IL",
    "sg:tags":[
        "clothing",
        "women's"
    ],
    "sg:website":"www.shopouest.com",
    "wof:name":"Ouest",
    "wof:placetype":"venue"
},
  "geometry": {"coordinates":[-87.671898,41.903032],"type":"Point"}
}