{
  "type": "Feature",
  "properties": {
    "iso:country":"US",
    "sg:address":"200 Botanical Dr",
    "sg:city":"Belleville",
    "sg:classifiers":[
        {
            "category":"Shopping",
            "subcategory":"Clothing, Apparel, & Fashions",
            "type":"Retail Goods"
        }
    ],
    "sg:phone":"+1 618 234 3250",
    "sg:postcode":"62226",
    "sg:province":"IL",
    "sg:tags":[
        "salvage",
        "surplus",
        "merchandise"
    ],
    "wof:name":"Government Liquidations",
    "wof:placetype":"venue"
},
  "geometry": {"coordinates":[-89.990173,38.566338],"type":"Point"}
}