{
  "type": "Feature",
  "properties": {
    "addr:full":"7229 W 103rd St Palos Hills IL 60465",
    "addr:housenumber":"7229",
    "addr:postcode":"60465",
    "addr:street":"W 103Rd St",
    "iso:country":"US",
    "sg:address":"7229 W 103rd St",
    "sg:city":"Palos Hills",
    "sg:classifiers":[
        {
            "category":"Health Services",
            "subcategory":"Chiropractor",
            "type":"Services"
        }
    ],
    "sg:phone":"+1 708 430 2444",
    "sg:postcode":"60465",
    "sg:province":"IL",
    "wof:name":"Mulhall Chiropractic Center",
    "wof:placetype":"venue"
},
  "geometry": {"coordinates":[-87.799301,41.704201],"type":"Point"}
}