{
  "type": "Feature",
  "properties": {
    "addr:full":"2970 Maria Ave Northbrook IL 60062",
    "addr:postcode":"2970;60062",
    "addr:street":"Maria Ave",
    "iso:country":"US",
    "sg:address":"2970 Maria Ave",
    "sg:city":"Northbrook",
    "sg:classifiers":[
        {
            "category":"Wholesale",
            "subcategory":"Chemicals & Plastics",
            "type":"Manufacturing & Wholesale Goods"
        },
        {
            "category":"Wholesale",
            "subcategory":"Scrap",
            "type":"Manufacturing & Wholesale Goods"
        }
    ],
    "sg:phone":"+1 847 564 8595",
    "sg:postcode":"60062",
    "sg:province":"IL",
    "sg:tags":[
        "resin"
    ],
    "wof:name":"Empire Plastics Inc",
    "wof:placetype":"venue"
},
  "geometry": {"coordinates":[-87.852053,42.14566],"type":"Point"}
}