{
  "type": "Feature",
  "properties": {
    "addr:full":"567 S Arthur Ave Arlington Heights IL 60005",
    "addr:housenumber":"567",
    "addr:postcode":"60005",
    "addr:street":"S Arthur Ave",
    "iso:country":"US",
    "sg:address":"567 S Arthur Ave",
    "sg:city":"Arlington Heights",
    "sg:classifiers":[
        {
            "category":"Shopping",
            "subcategory":"Bicycles & Sporting Goods",
            "type":"Retail Goods"
        }
    ],
    "sg:phone":"+1   ",
    "sg:postcode":"60005",
    "sg:province":"IL",
    "sg:tags":[
        "equipment",
        "sport"
    ],
    "wof:name":"F Askates & Snowboards",
    "wof:placetype":"venue"
},
  "geometry": {"coordinates":[-87.965974,42.075678],"type":"Point"}
}