{
  "type": "Feature",
  "properties": {
    "iso:country":"US",
    "sg:address":"663 Elder Ln",
    "sg:city":"Deerfield",
    "sg:classifiers":[
        {
            "category":"Professional",
            "subcategory":"Management & Consulting",
            "type":"Services"
        }
    ],
    "sg:phone":"+1 847 267 0772",
    "sg:postcode":"60015",
    "sg:province":"IL",
    "sg:tags":[
        "business"
    ],
    "wof:name":"G M Fankhauser and Associ",
    "wof:placetype":"venue"
},
  "geometry": {"coordinates":[-87.846225,42.170771],"type":"Point"}
}