{
  "type": "Feature",
  "properties": {
    "addr:full":"19134 Revere Rd Mokena IL 60448",
    "addr:housenumber":"19134",
    "addr:postcode":"60448",
    "addr:street":"Revere Rd",
    "iso:country":"US",
    "sg:address":"19134 Revere Rd",
    "sg:city":"Mokena",
    "sg:classifiers":[
        {
            "category":"Retail",
            "subcategory":"Laundry & Dry Cleaning",
            "type":"Services"
        }
    ],
    "sg:phone":"+1 708 479 6938",
    "sg:postcode":"60448",
    "sg:province":"IL",
    "sg:tags":[
        "drycleaning",
        "plant"
    ],
    "wof:name":"Perfectionist Cleaners",
    "wof:placetype":"venue"
},
  "geometry": {"coordinates":[-87.876097,41.541482],"type":"Point"}
}