{
  "type": "Feature",
  "properties": {
    "addr:full":"4622 N Hermitage Chicago IL 60640",
    "addr:housenumber":"4622",
    "addr:postcode":"60640",
    "addr:street":"N Hermitage",
    "iso:country":"US",
    "sg:address":"4622 N Hermitage",
    "sg:city":"Chicago",
    "sg:classifiers":[
        {
            "category":"Professional",
            "subcategory":"Art Services",
            "type":"Services"
        },
        {
            "category":"Communications",
            "type":"Services"
        }
    ],
    "sg:phone":"+1 773 989 9203",
    "sg:postcode":"60640",
    "sg:province":"IL",
    "sg:tags":[
        "web",
        "graphic",
        "design"
    ],
    "sg:website":"graphicalchemy.com/",
    "wof:name":"Graphic Alchemy",
    "wof:placetype":"venue"
},
  "geometry": {"coordinates":[-87.67296,41.965939],"type":"Point"}
}