{
  "type": "Feature",
  "properties": {
    "iso:country":"US",
    "sg:address":"4901 Sheridan Rd",
    "sg:city":"Groveland",
    "sg:classifiers":[
        {
            "category":"Retail",
            "subcategory":"Animal Services",
            "type":"Services"
        }
    ],
    "sg:phone":"+1 309 387 2045",
    "sg:postcode":"61535",
    "sg:province":"IL",
    "wof:name":"Haushahn",
    "wof:placetype":"venue"
},
  "geometry": {"coordinates":[-89.540115,40.586689],"type":"Point"}
}