{
  "type": "Feature",
  "properties": {
    "iso:country":"US",
    "sg:address":"14755 131st St",
    "sg:city":"Lemont",
    "sg:classifiers":[
        {
            "category":"Building & Trades",
            "subcategory":"Construction",
            "type":"Services"
        }
    ],
    "sg:phone":"+1 630 243 0220",
    "sg:postcode":"60439",
    "sg:province":"IL",
    "sg:tags":[
        "house"
    ],
    "wof:name":"Savvy Construction",
    "wof:placetype":"venue"
},
  "geometry": {"coordinates":[-87.97642399999999,41.64985],"type":"Point"}
}