{
  "type": "Feature",
  "properties": {
    "addr:full":"1486 E Oakton St Des Plaines IL 60018",
    "addr:housenumber":"1486",
    "addr:postcode":"60018",
    "addr:street":"E Oakton St",
    "iso:country":"US",
    "sg:address":"1486 E Oakton St",
    "sg:city":"Des Plaines",
    "sg:classifiers":[
        {
            "category":"Retail",
            "subcategory":"Auto Repair",
            "type":"Services"
        }
    ],
    "sg:phone":"+1 847 390 9945",
    "sg:postcode":"60018",
    "sg:province":"IL",
    "sg:tags":[
        "general"
    ],
    "wof:name":"Aranda Transmission",
    "wof:placetype":"venue"
},
  "geometry": {"coordinates":[-87.88656,42.024253],"type":"Point"}
}