{
  "type": "Feature",
  "properties": {
    "addr:full":"125 55th St Clarendon Hills IL 60514",
    "addr:housenumber":"125",
    "addr:postcode":"60514",
    "addr:street":"55Th St",
    "iso:country":"US",
    "sg:address":"125 55th St",
    "sg:city":"Clarendon Hills",
    "sg:classifiers":[
        {
            "category":"Real Estate",
            "subcategory":"Real Estate Agent",
            "type":"Services"
        }
    ],
    "sg:phone":"+1 630 887 1991",
    "sg:postcode":"60514",
    "sg:province":"IL",
    "wof:name":"Thomas & Kuiken Inc",
    "wof:placetype":"venue"
},
  "geometry": {"coordinates":[-87.952671,41.788575],"type":"Point"}
}