{
  "type": "Feature",
  "properties": {
    "addr:full":"1932 S Main St Eureka IL 61530",
    "addr:housenumber":"1932",
    "addr:postcode":"61530",
    "addr:street":"S Main St",
    "iso:country":"US",
    "sg:address":"1932 S Main St",
    "sg:city":"Eureka",
    "sg:classifiers":[
        {
            "category":"Professional",
            "subcategory":"Accounting & Tax Preparation",
            "type":"Services"
        }
    ],
    "sg:phone":"+1 309 467 4641",
    "sg:postcode":"61530",
    "sg:province":"IL",
    "sg:tags":[
        "accountant"
    ],
    "wof:name":"Donald M Heinold CPA",
    "wof:placetype":"venue"
},
  "geometry": {"coordinates":[-89.272648,40.70128],"type":"Point"}
}