{
  "type": "Feature",
  "properties": {
    "addr:full":"2267 Co Rd 1000 E Champaign IL 61822",
    "addr:housenumber":"2267;1000 e",
    "addr:postcode":"61822",
    "addr:street":"Co Rd",
    "iso:country":"US",
    "sg:address":"2267 Co Rd 1000 E",
    "sg:city":"Champaign",
    "sg:phone":"+1 217 356 4514",
    "sg:postcode":"61822",
    "sg:province":"IL",
    "sg:tags":[
        "farm",
        "corn",
        "soybean"
    ],
    "wof:name":"Hansens Farm Acc Lou",
    "wof:placetype":"venue"
},
  "geometry": {"coordinates":[-88.277906,40.210024],"type":"Point"}
}