{
  "type": "Feature",
  "properties": {
    "iso:country":"US",
    "sg:address":"320 Water Stone Way",
    "sg:city":"Joliet",
    "sg:classifiers":[
        {
            "category":"Banks & Credit Unions",
            "subcategory":"Investment Brokerage",
            "type":"Services"
        },
        {
            "category":"Banks & Credit Unions",
            "subcategory":"Financial Services",
            "type":"Services"
        }
    ],
    "sg:phone":"+1 815 744 9500",
    "sg:postcode":"60431",
    "sg:province":"IL",
    "sg:tags":[
        "advisory",
        "planner"
    ],
    "wof:name":"Mike Hansen Co",
    "wof:placetype":"venue"
},
  "geometry": {"coordinates":[-88.18356199999999,41.515561],"type":"Point"}
}