{
  "type": "Feature",
  "properties": {
    "addr:full":"1226 S Canal Street Chicago IL 60607",
    "addr:housenumber":"1226",
    "addr:postcode":"60607",
    "addr:street":"S Canal Street",
    "iso:country":"US",
    "sg:address":"1226 S Canal Street",
    "sg:city":"Chicago",
    "sg:classifiers":[
        {
            "category":"Banks & Credit Unions",
            "subcategory":"Bank",
            "type":"Services"
        },
        {
            "category":"Banks & Credit Unions",
            "subcategory":"Financial Services",
            "type":"Services"
        }
    ],
    "sg:phone":"+1 312 421 3283",
    "sg:postcode":"60607",
    "sg:province":"IL",
    "sg:tags":[
        "broker",
        "mortgage"
    ],
    "sg:website":"www.wamu.com",
    "wof:name":"Washington Mutual",
    "wof:placetype":"venue"
},
  "geometry": {"coordinates":[-87.639349,41.867123],"type":"Point"}
}