{
  "type": "Feature",
  "properties": {
    "iso:country":"US",
    "sg:address":"515 N Turner St",
    "sg:city":"Davis",
    "sg:classifiers":[
        {
            "category":"Autos & Motor Vehicles",
            "subcategory":"Automobile Sales",
            "type":"Retail Goods"
        }
    ],
    "sg:phone":"+1 815 865 5292",
    "sg:postcode":"61019",
    "sg:province":"IL",
    "sg:tags":[
        "car",
        "dealer"
    ],
    "wof:name":"Cars R Us Svc Ctr",
    "wof:placetype":"venue"
},
  "geometry": {"coordinates":[-89.415042,42.422761],"type":"Point"}
}