{
  "type": "Feature",
  "properties": {
    "addr:full":"209 E Center St Le Roy IL 61752",
    "addr:housenumber":"209",
    "addr:postcode":"61752",
    "addr:street":"E Center St",
    "iso:country":"US",
    "sg:address":"209 E Center St",
    "sg:city":"Le Roy",
    "sg:classifiers":[
        {
            "category":"Retail",
            "subcategory":"Repair Shop",
            "type":"Services"
        }
    ],
    "sg:phone":"+1 309 962 8208",
    "sg:postcode":"61752",
    "sg:province":"IL",
    "sg:tags":[
        "repairing",
        "piano",
        "refinishing"
    ],
    "wof:name":"Ron Scott Piano Svc",
    "wof:placetype":"venue"
},
  "geometry": {"coordinates":[-88.76045499999999,40.34706],"type":"Point"}
}