{
  "type": "Feature",
  "properties": {
    "addr:full":"152 N Myrtle Ave Villa Park IL 60181",
    "addr:housenumber":"152",
    "addr:postcode":"60181",
    "addr:street":"N Myrtle Ave",
    "iso:country":"US",
    "sg:address":"152 N Myrtle Ave",
    "sg:city":"Villa Park",
    "sg:classifiers":[
        {
            "category":"Professional",
            "type":"Services"
        }
    ],
    "sg:phone":"+1 630 834 3039",
    "sg:postcode":"60181",
    "sg:province":"IL",
    "wof:name":"Edward T Corkery",
    "wof:placetype":"venue"
},
  "geometry": {"coordinates":[-87.970702,41.892947],"type":"Point"}
}