{
  "type": "Feature",
  "properties": {
    "addr:full":"35 Ct of Cobblestone Northbrook IL 60062",
    "addr:postcode":"60062",
    "addr:street":"35 Ct",
    "iso:country":"US",
    "sg:address":"35 Ct of Cobblestone",
    "sg:city":"Northbrook",
    "sg:classifiers":[
        {
            "category":"Wholesale",
            "subcategory":"Machinery & Supplies",
            "type":"Manufacturing & Wholesale Goods"
        }
    ],
    "sg:phone":"+1 847 412 9725",
    "sg:postcode":"60062",
    "sg:province":"IL",
    "sg:tags":[
        "agent"
    ],
    "wof:name":"Dl Sales Associates",
    "wof:placetype":"venue"
},
  "geometry": {"coordinates":[-87.862684,42.129419],"type":"Point"}
}