{
  "type": "Feature",
  "properties": {
    "addr:full":"203 W Walnut St Oglesby IL 61348",
    "addr:housenumber":"203",
    "addr:postcode":"61348",
    "addr:street":"W Walnut St",
    "iso:country":"US",
    "sg:address":"203 W Walnut St",
    "sg:city":"Oglesby",
    "sg:classifiers":[
        {
            "category":"Government",
            "subcategory":"Post Office",
            "type":"Public Place"
        }
    ],
    "sg:phone":"+1 815 883 8541",
    "sg:postcode":"61348",
    "sg:province":"IL",
    "wof:name":"US Post Office",
    "wof:placetype":"venue"
},
  "geometry": {"coordinates":[-89.063965,41.294994],"type":"Point"}
}