{
  "type": "Feature",
  "properties": {
    "iso:country":"US",
    "sg:address":"5015 N Paulina St",
    "sg:city":"Chicago",
    "sg:classifiers":[
        {
            "category":"Health Services",
            "subcategory":"Doctor",
            "type":"Services"
        }
    ],
    "sg:phone":"+1 773 275 4225",
    "sg:postcode":"60640",
    "sg:province":"IL",
    "sg:tags":[
        "medical"
    ],
    "wof:name":"Ernest D Gutman MD",
    "wof:placetype":"venue"
},
  "geometry": {"coordinates":[-87.671051,41.972687],"type":"Point"}
}