{
  "type": "Feature",
  "properties": {
    "addr:full":"1680 Irving Park Rd Bartlett IL 60133",
    "addr:housenumber":"1680",
    "addr:postcode":"60133",
    "addr:street":"Irving Park Rd",
    "iso:country":"US",
    "sg:address":"1680 Irving Park Rd",
    "sg:city":"Bartlett",
    "sg:classifiers":[
        {
            "category":"Retail",
            "subcategory":"Auto Repair",
            "type":"Services"
        }
    ],
    "sg:phone":"+1 630 289 5656",
    "sg:postcode":"60133",
    "sg:province":"IL",
    "sg:tags":[
        "automotive",
        "brake",
        "system",
        "exhaust"
    ],
    "wof:name":"Merlins Muffler & Brake",
    "wof:placetype":"venue"
},
  "geometry": {"coordinates":[-88.14645400000001,42.006218],"type":"Point"}
}