{
  "type": "Feature",
  "properties": {
    "iso:country":"US",
    "sg:address":"304 N Draper Ave",
    "sg:city":"Champaign",
    "sg:classifiers":[
        {
            "category":"Organizations",
            "subcategory":"Community Association",
            "type":"Services"
        }
    ],
    "sg:phone":"+1 217 352 2684",
    "sg:postcode":"61821",
    "sg:province":"IL",
    "wof:name":"Notre Dame Club Eastern Ill",
    "wof:placetype":"venue"
},
  "geometry": {"coordinates":[-88.27025999999999,40.120113],"type":"Point"}
}