{
  "type": "Feature",
  "properties": {
    "addr:full":"654 Park Ave E Princeton IL 61356",
    "addr:housenumber":"654",
    "addr:postcode":"61356",
    "addr:street":"Park Ave E",
    "iso:country":"US",
    "sg:address":"654 Park Ave E",
    "sg:city":"Princeton",
    "sg:classifiers":[
        {
            "category":"Organizations",
            "subcategory":"Community Association",
            "type":"Services"
        }
    ],
    "sg:phone":"+1 815 875 1501",
    "sg:postcode":"61356",
    "sg:province":"IL",
    "wof:name":"Princeton Rotary Club",
    "wof:placetype":"venue"
},
  "geometry": {"coordinates":[-89.453779,41.36792],"type":"Point"}
}