{
  "type": "Feature",
  "properties": {
    "iso:country":"US",
    "sg:address":"5840 N Lincoln Ave",
    "sg:city":"Chicago",
    "sg:classifiers":[
        {
            "category":"Manufacturing",
            "subcategory":"Chemicals & Compounds",
            "type":"Manufacturing & Wholesale Goods"
        },
        {
            "category":"Animal Shelter",
            "type":"Public Place"
        },
        {
            "category":"Building & Trades",
            "subcategory":"Pest Control",
            "type":"Services"
        }
    ],
    "sg:phone":"+1 866 574 1660",
    "sg:postcode":"60659",
    "sg:province":"IL",
    "sg:tags":[
        "industrial",
        "supply",
        "services-commercial",
        "termite",
        "bee",
        "equipment",
        "mothproofing",
        "removal"
    ],
    "sg:website":"http://orkin.com",
    "wof:name":"Orkin Pest & Termite Control",
    "wof:placetype":"venue"
},
  "geometry": {"coordinates":[-87.70259900000001,41.987549],"type":"Point"}
}