{
  "type": "Feature",
  "properties": {
    "addr:full":"10301 S Kolmar Ave Oak Lawn IL 60453",
    "addr:housenumber":"10301",
    "addr:postcode":"60453",
    "addr:street":"S Kolmar Ave",
    "iso:country":"US",
    "sg:address":"10301 S Kolmar Ave",
    "sg:city":"Oak Lawn",
    "sg:classifiers":[
        {
            "category":"Place Of Worship",
            "subcategory":"Church",
            "type":"Public Place"
        }
    ],
    "sg:phone":"+1 708 636 5460",
    "sg:postcode":"60453",
    "sg:province":"IL",
    "sg:website":"www.stnicholasil.org",
    "wof:name":"St Nicholas Greek Orthodox Church",
    "wof:placetype":"venue"
},
  "geometry": {"coordinates":[-87.73400100000001,41.705601],"type":"Point"}
}