{
  "type": "Feature",
  "properties": {
    "addr:full":"37274 N Stanton Point Rd Ingleside IL 60041",
    "addr:housenumber":"37274",
    "addr:postcode":"60041",
    "addr:street":"N Stanton Point Rd",
    "iso:country":"US",
    "sg:address":"37274 N Stanton Point Rd",
    "sg:city":"Ingleside",
    "sg:classifiers":[
        {
            "category":"Building & Trades",
            "subcategory":"Plumbing",
            "type":"Services"
        }
    ],
    "sg:phone":"+1 847 973 2428",
    "sg:postcode":"60041",
    "sg:province":"IL",
    "sg:tags":[
        "plumbing",
        "contractor"
    ],
    "wof:name":"A A Supreme Plumbing Inc",
    "wof:placetype":"venue"
},
  "geometry": {"coordinates":[-88.147131,42.395881],"type":"Point"}
}