{
  "type": "Feature",
  "properties": {
    "iso:country":"US",
    "sg:address":"1666 Independence Ave",
    "sg:city":"Glenview",
    "sg:classifiers":[
        {
            "category":"Health Services",
            "subcategory":"Doctor",
            "type":"Services"
        }
    ],
    "sg:phone":"+1 847 729 9266",
    "sg:postcode":"60026",
    "sg:province":"IL",
    "sg:tags":[
        "medicine",
        "physician",
        "practice",
        "surgeons",
        "family"
    ],
    "wof:name":"M B Noone Md Sc",
    "wof:placetype":"venue"
},
  "geometry": {"coordinates":[-87.816464,42.084409],"type":"Point"}
}