{
  "type": "Feature",
  "properties": {
    "iso:country":"US",
    "sg:address":"655 17th Ave",
    "sg:city":"East Moline",
    "sg:classifiers":[
        {
            "category":"Restaurant",
            "type":"Food & Drink"
        }
    ],
    "sg:phone":"+1   ",
    "sg:postcode":"61244",
    "sg:province":"IL",
    "sg:tags":[
        "eating"
    ],
    "wof:name":"Cristnas Mexican Casual Dining",
    "wof:placetype":"venue"
},
  "geometry": {"coordinates":[-90.445942,41.514026],"type":"Point"}
}