{
  "type": "Feature",
  "properties": {
    "iso:country":"US",
    "sg:address":"5903 S Halsted St",
    "sg:city":"Chicago",
    "sg:classifiers":[
        {
            "category":"Building & Trades",
            "subcategory":"Locksmith",
            "type":"Services"
        }
    ],
    "sg:phone":"+1 773 922 7991",
    "sg:postcode":"60621",
    "sg:province":"IL",
    "sg:tags":[
        "key"
    ],
    "wof:name":"24 Hour Locks and Locksmith",
    "wof:placetype":"venue"
},
  "geometry": {"coordinates":[-87.644836,41.786983],"type":"Point"}
}