{
  "type": "Feature",
  "properties": {
    "iso:country":"US",
    "sg:address":"213 W Institute Place",
    "sg:city":"Chicago",
    "sg:classifiers":[
        {
            "category":"Sports & Exercise",
            "subcategory":"Gym",
            "type":"Entertainment"
        }
    ],
    "sg:phone":"+1 312 266 8030",
    "sg:postcode":"60610",
    "sg:province":"IL",
    "sg:tags":[
        "trainer"
    ],
    "wof:name":"Chicago River North Pilate",
    "wof:placetype":"venue"
},
  "geometry": {"coordinates":[-87.634451,41.897295],"type":"Point"}
}