{
  "type": "Feature",
  "properties": {
    "addr:full":"128 Sycamore St Sumner IL 62466",
    "addr:housenumber":"128",
    "addr:postcode":"62466",
    "addr:street":"Sycamore St",
    "iso:country":"US",
    "sg:address":"128 Sycamore St",
    "sg:city":"Sumner",
    "sg:classifiers":[
        {
            "category":"Community Center",
            "subcategory":"Senior",
            "type":"Public Place"
        },
        {
            "category":"Social Services",
            "subcategory":"Adult Care",
            "type":"Services"
        }
    ],
    "sg:phone":"+1 618 936 2023",
    "sg:postcode":"62466",
    "sg:province":"IL",
    "sg:tags":[
        "counseling",
        "citizen"
    ],
    "wof:name":"Lawrence County Senior Citizen Center, The Office",
    "wof:placetype":"venue"
},
  "geometry": {"coordinates":[-87.86077899999999,38.718288],"type":"Point"}
}