{
  "type": "Feature",
  "properties": {
    "addr:full":"404 Roosevelt Rd Glen Ellyn IL 60137",
    "addr:housenumber":"404",
    "addr:postcode":"60137",
    "addr:street":"Roosevelt Rd",
    "iso:country":"US",
    "sg:address":"404 Roosevelt Rd",
    "sg:city":"Glen Ellyn",
    "sg:classifiers":[
        {
            "category":"Restaurant",
            "type":"Food & Drink"
        }
    ],
    "sg:phone":"+1 630 469 1535",
    "sg:postcode":"60137",
    "sg:province":"IL",
    "sg:tags":[
        "chinese"
    ],
    "wof:name":"Beijing Chinese Catering",
    "wof:placetype":"venue"
},
  "geometry": {"coordinates":[-88.073196,41.859402],"type":"Point"}
}