{
  "type": "Feature",
  "properties": {
    "iso:country":"US",
    "sg:address":"2242 S Princeton Avenue Ofc",
    "sg:city":"Chicago",
    "sg:classifiers":[
        {
            "category":"Real Estate",
            "subcategory":"Real Estate Operator",
            "type":"Services"
        }
    ],
    "sg:phone":"+1 312 674 9490",
    "sg:postcode":"60616",
    "sg:province":"IL",
    "sg:tags":[
        "apartment"
    ],
    "wof:name":"Archer Courts Apartments-Service Coordinator",
    "wof:placetype":"venue"
},
  "geometry": {"coordinates":[-87.63476300000001,41.851458],"type":"Point"}
}