{
  "type": "Feature",
  "properties": {
    "iso:country":"US",
    "sg:address":"1651 N Charles St",
    "sg:city":"Belleville",
    "sg:classifiers":[
        {
            "category":"Manufacturing",
            "subcategory":"Metals",
            "type":"Manufacturing & Wholesale Goods"
        }
    ],
    "sg:phone":"+1 618 233 4808",
    "sg:postcode":"62221",
    "sg:province":"IL",
    "sg:tags":[
        "steel",
        "plating"
    ],
    "wof:name":"Quality Plating Works",
    "wof:placetype":"venue"
},
  "geometry": {"coordinates":[-89.96828499999999,38.528507],"type":"Point"}
}