{
  "type": "Feature",
  "properties": {
    "iso:country":"US",
    "sg:address":"2822 N Harvard Ave",
    "sg:city":"Arlington Hts",
    "sg:classifiers":[
        {
            "category":"Professional",
            "subcategory":"Advertising",
            "type":"Services"
        }
    ],
    "sg:phone":"+1 847 506 9381",
    "sg:postcode":"60004",
    "sg:province":"IL",
    "sg:tags":[
        "distributing",
        "sample"
    ],
    "wof:name":"Asco Artglass",
    "wof:placetype":"venue"
},
  "geometry": {"coordinates":[-87.99693,42.126015],"type":"Point"}
}