{
  "type": "Feature",
  "properties": {
    "iso:country":"US",
    "sg:address":"980 N Michigan Ave # 1700",
    "sg:city":"Chicago",
    "sg:classifiers":[
        {
            "category":"Banks & Credit Unions",
            "subcategory":"Financial Services",
            "type":"Services"
        }
    ],
    "sg:phone":"+1 312 587 7000",
    "sg:postcode":"60611",
    "sg:province":"IL",
    "sg:tags":[
        "money",
        "transfer"
    ],
    "sg:website":"http://www.geneva-trading.com",
    "wof:name":"Geneva Trading Usa",
    "wof:placetype":"venue"
},
  "geometry": {"coordinates":[-87.62417499999999,41.900657],"type":"Point"}
}