{
  "type": "Feature",
  "properties": {
    "addr:full":"1711 E Main St Salem IL 62881",
    "addr:housenumber":"1711",
    "addr:postcode":"62881",
    "addr:street":"E Main St",
    "iso:country":"US",
    "sg:address":"1711 E Main St",
    "sg:city":"Salem",
    "sg:phone":"+1 618 548 4685",
    "sg:postcode":"62881",
    "sg:province":"IL",
    "sg:website":"http://www.dairymart.com",
    "wof:name":"Dairy Mart Convenience Store",
    "wof:placetype":"venue"
},
  "geometry": {"coordinates":[-88.92629100000001,38.627671],"type":"Point"}
}