{
  "type": "Feature",
  "properties": {
    "addr:full":"3704 W Fullerton Ave Chicago IL 60647",
    "addr:housenumber":"3704",
    "addr:postcode":"60647",
    "addr:street":"W Fullerton Ave",
    "iso:country":"US",
    "sg:address":"3704 W Fullerton Ave",
    "sg:city":"Chicago",
    "sg:classifiers":[
        {
            "category":"Personal",
            "subcategory":"Beauty Salon",
            "type":"Services"
        },
        {
            "category":"Personal",
            "subcategory":"Barber",
            "type":"Services"
        },
        {
            "category":"Personal",
            "subcategory":"Nail Salon",
            "type":"Services"
        }
    ],
    "sg:phone":"+1 773 227 9088",
    "sg:postcode":"60647",
    "sg:province":"IL",
    "sg:tags":[
        "hair"
    ],
    "wof:name":"Tania's Unisex Beauty Salon",
    "wof:placetype":"venue"
},
  "geometry": {"coordinates":[-87.71968200000001,41.924879],"type":"Point"}
}