{
  "type": "Feature",
  "properties": {
    "addr:full":"2226 Chestnut St Northbrook IL 60062",
    "addr:housenumber":"2226",
    "addr:postcode":"60062",
    "addr:street":"Chestnut St",
    "iso:country":"US",
    "sg:address":"2226 Chestnut St",
    "sg:city":"Northbrook",
    "sg:classifiers":[
        {
            "category":"Shopping",
            "subcategory":"Computers & Home Electronics",
            "type":"Retail Goods"
        }
    ],
    "sg:phone":"+1 847 291 7684",
    "sg:postcode":"60062",
    "sg:province":"IL",
    "sg:tags":[
        "renting",
        "equipment",
        "leasing"
    ],
    "wof:name":"Barry Kessler",
    "wof:placetype":"venue"
},
  "geometry": {"coordinates":[-87.834548,42.130086],"type":"Point"}
}