{
  "type": "Feature",
  "properties": {
    "addr:full":"825 W Brookline St Bunker Hill IL 62014",
    "addr:housenumber":"825",
    "addr:postcode":"62014",
    "addr:street":"W Brookline St",
    "iso:country":"US",
    "sg:address":"825 W Brookline St",
    "sg:city":"Bunker Hill",
    "sg:classifiers":[
        {
            "category":"Personal",
            "subcategory":"Beauty Salon",
            "type":"Services"
        }
    ],
    "sg:phone":"+1 618 585 4825",
    "sg:postcode":"62014",
    "sg:province":"IL",
    "sg:tags":[
        "shop"
    ],
    "wof:name":"Rodgers Wm",
    "wof:placetype":"venue"
},
  "geometry": {"coordinates":[-89.956603,39.040112],"type":"Point"}
}