{
  "type": "Feature",
  "properties": {
    "iso:country":"US",
    "sg:address":"2145 W Irving Park Rd",
    "sg:city":"Chicago",
    "sg:classifiers":[
        {
            "category":"Health Services",
            "subcategory":"Chiropractor",
            "type":"Services"
        }
    ],
    "sg:phone":"+1 773 539 7216",
    "sg:postcode":"60618",
    "sg:province":"IL",
    "wof:name":"Lazarowich Max DC",
    "wof:placetype":"venue"
},
  "geometry": {"coordinates":[-87.68256599999999,41.95393],"type":"Point"}
}