{
  "type": "Feature",
  "properties": {
    "iso:country":"US",
    "sg:address":"7080 McCormick Blvd",
    "sg:city":"Lincolnwood",
    "sg:classifiers":[
        {
            "category":"Retail",
            "subcategory":"Auto Rental",
            "type":"Services"
        }
    ],
    "sg:phone":"+1 847 675 5176",
    "sg:postcode":"60712",
    "sg:province":"IL",
    "sg:tags":[
        "renting",
        "automobile"
    ],
    "wof:name":"Enterprise Rent-A-Car",
    "wof:placetype":"venue"
},
  "geometry": {"coordinates":[-87.711643,42.00851],"type":"Point"}
}