{
  "type": "Feature",
  "properties": {
    "iso:country":"US",
    "sg:address":"5901 Material Ave",
    "sg:city":"Loves Park",
    "sg:classifiers":[
        {
            "category":"Wholesale",
            "subcategory":"Construction Materials",
            "type":"Manufacturing & Wholesale Goods"
        }
    ],
    "sg:phone":"+1 815 877 5788",
    "sg:postcode":"61111",
    "sg:province":"IL",
    "sg:tags":[
        "brick",
        "common",
        "face"
    ],
    "sg:website":"www.rockvalleybrick.com",
    "wof:name":"Rock-Valley Brick & Supply Co",
    "wof:placetype":"venue"
},
  "geometry": {"coordinates":[-89.038152,42.325354],"type":"Point"}
}