{
  "type": "Feature",
  "properties": {
    "iso:country":"US",
    "sg:address":"117 Uncle Leo Dr",
    "sg:city":"Bradley",
    "sg:classifiers":[
        {
            "category":"Professional",
            "subcategory":"Management & Consulting",
            "type":"Services"
        }
    ],
    "sg:phone":"+1 815 929 9733",
    "sg:postcode":"60915",
    "sg:province":"IL",
    "sg:tags":[
        "consultant",
        "business"
    ],
    "wof:name":"IMC Property Management",
    "wof:placetype":"venue"
},
  "geometry": {"coordinates":[-87.84460799999999,41.159963],"type":"Point"}
}