{
  "type": "Feature",
  "properties": {
    "iso:country":"US",
    "sg:address":"105 E 51st St",
    "sg:city":"Chicago",
    "sg:classifiers":[
        {
            "category":"Health Services",
            "subcategory":"Chiropractor",
            "type":"Services"
        }
    ],
    "sg:phone":"+1 773 536 2300",
    "sg:postcode":"60615",
    "sg:province":"IL",
    "sg:website":"www.gordonfamilychiropractic.com",
    "wof:name":"Gordon Family Chiropractic",
    "wof:placetype":"venue"
},
  "geometry": {"coordinates":[-87.622552,41.801904],"type":"Point"}
}