{
  "type": "Feature",
  "properties": {
    "iso:country":"US",
    "sg:address":"8 Cour Montreal",
    "sg:city":"Palos Hills",
    "sg:classifiers":[
        {
            "category":"Professional",
            "subcategory":"Secretarial Services",
            "type":"Services"
        }
    ],
    "sg:phone":"+1 708 974 1331",
    "sg:postcode":"60465",
    "sg:province":"IL",
    "sg:tags":[
        "reporting"
    ],
    "wof:name":"Bink Burke Word Processing",
    "wof:placetype":"venue"
},
  "geometry": {"coordinates":[-87.825628,41.685751],"type":"Point"}
}