{
  "type": "Feature",
  "properties": {
    "iso:country":"US",
    "sg:address":"4845 Dempster St",
    "sg:city":"Skokie",
    "sg:classifiers":[
        {
            "category":"Health Services",
            "subcategory":"Clinic",
            "type":"Services"
        }
    ],
    "sg:phone":"+1 847 679 6065",
    "sg:postcode":"60077",
    "sg:province":"IL",
    "sg:tags":[
        "home",
        "care"
    ],
    "wof:name":"Relief Medical Services Inc",
    "wof:placetype":"venue"
},
  "geometry": {"coordinates":[-87.750409,42.040707],"type":"Point"}
}