{
  "type": "Feature",
  "properties": {
    "addr:full":"3 E Northwest Hwy Palatine IL 60067",
    "addr:housenumber":"3",
    "addr:postcode":"60067",
    "addr:street":"E Northwest Hwy",
    "iso:country":"US",
    "sg:address":"3 E Northwest Hwy",
    "sg:city":"Palatine",
    "sg:classifiers":[
        {
            "category":"Manufacturing",
            "subcategory":"Jewelry",
            "type":"Manufacturing & Wholesale Goods"
        }
    ],
    "sg:phone":"+1 847 991 3990",
    "sg:postcode":"60067",
    "sg:province":"IL",
    "sg:tags":[
        "precious",
        "metal",
        "mfg"
    ],
    "wof:name":"M Cohen Inc",
    "wof:placetype":"venue"
},
  "geometry": {"coordinates":[-88.043018,42.120909],"type":"Point"}
}