{
  "type": "Feature",
  "properties": {
    "iso:country":"US",
    "sg:address":"205 W Walnut St",
    "sg:city":"Carbondale",
    "sg:classifiers":[
        {
            "category":"Personal",
            "subcategory":"Tattoo Parlor",
            "type":"Services"
        }
    ],
    "sg:phone":"+1 618 549 1112",
    "sg:postcode":"62901",
    "sg:province":"IL",
    "sg:tags":[
        "tattooing"
    ],
    "wof:name":"Hard Times Tattoos",
    "wof:placetype":"venue"
},
  "geometry": {"coordinates":[-89.216763,37.725138],"type":"Point"}
}