{
  "type": "Feature",
  "properties": {
    "iso:country":"US",
    "sg:address":"1133 Harms Ave",
    "sg:city":"Libertyville",
    "sg:classifiers":[
        {
            "category":"Building & Trades",
            "subcategory":"Cleaning & Sanitation",
            "type":"Services"
        }
    ],
    "sg:phone":"+1 847 362 5994",
    "sg:postcode":"60048",
    "sg:province":"IL",
    "sg:tags":[
        "janitor"
    ],
    "wof:name":"S M Cleaning & Remodeling Inc",
    "wof:placetype":"venue"
},
  "geometry": {"coordinates":[-87.972548,42.278074],"type":"Point"}
}