{
  "type": "Feature",
  "properties": {
    "iso:country":"US",
    "sg:address":"5541 S Everett Ave",
    "sg:city":"Chicago",
    "sg:classifiers":[
        {
            "category":"Retail",
            "subcategory":"Laundry & Dry Cleaning",
            "type":"Services"
        }
    ],
    "sg:phone":"+1 773 363 1588",
    "sg:postcode":"60637",
    "sg:province":"IL",
    "sg:tags":[
        "laundries-self"
    ],
    "wof:name":"Macke Laundry Service",
    "wof:placetype":"venue"
},
  "geometry": {"coordinates":[-87.58249499999999,41.794496],"type":"Point"}
}