{
  "type": "Feature",
  "properties": {
    "addr:full":"1027 Lantern Ct Dixon IL 61021",
    "addr:housenumber":"1027",
    "addr:postcode":"61021",
    "addr:street":"Lantern Ct",
    "iso:country":"US",
    "sg:address":"1027 Lantern Ct",
    "sg:city":"Dixon",
    "sg:classifiers":[
        {
            "category":"Education",
            "subcategory":"Dance Studio",
            "type":"Public Place"
        }
    ],
    "sg:phone":"+1 815 284 7852",
    "sg:postcode":"61021",
    "sg:province":"IL",
    "wof:name":"Eastman School Of Dance",
    "wof:placetype":"venue"
},
  "geometry": {"coordinates":[-89.466114,41.840905],"type":"Point"}
}