{
  "type": "Feature",
  "properties": {
    "iso:country":"US",
    "sg:address":"23 Douglas Ave",
    "sg:city":"Elgin",
    "sg:classifiers":[
        {
            "category":"Professional",
            "subcategory":"Lawyer & Legal Services",
            "type":"Services"
        }
    ],
    "sg:phone":"+1 847 742 9555",
    "sg:postcode":"60120",
    "sg:province":"IL",
    "sg:tags":[
        "attorney"
    ],
    "wof:name":"Rodney D Cavitt Law Offices",
    "wof:placetype":"venue"
},
  "geometry": {"coordinates":[-88.283952,42.037729],"type":"Point"}
}