{
  "type": "Feature",
  "properties": {
    "iso:country":"US",
    "sg:address":"4 Burr Oak Trl",
    "sg:city":"Riverwoods",
    "sg:classifiers":[
        {
            "category":"Banks & Credit Unions",
            "subcategory":"Financial Services",
            "type":"Services"
        }
    ],
    "sg:phone":"+1 847 945 0266",
    "sg:postcode":"60015",
    "sg:province":"IL",
    "sg:tags":[
        "trust",
        "management"
    ],
    "wof:name":"Lynn Butler",
    "wof:placetype":"venue"
},
  "geometry": {"coordinates":[-87.901235,42.174689],"type":"Point"}
}