{
  "type": "Feature",
  "properties": {
    "iso:country":"US",
    "sg:address":"427 W Marion St",
    "sg:city":"Monticello",
    "sg:classifiers":[
        {
            "category":"Insurance",
            "subcategory":"Hazard Insurance",
            "type":"Services"
        },
        {
            "category":"Banks & Credit Unions",
            "subcategory":"Investment Brokerage",
            "type":"Services"
        },
        {
            "category":"Insurance",
            "subcategory":"Life Insurance",
            "type":"Services"
        },
        {
            "category":"Banks & Credit Unions",
            "subcategory":"Financial Services",
            "type":"Services"
        }
    ],
    "sg:phone":"+1 217 762 2174",
    "sg:postcode":"61856",
    "sg:province":"IL",
    "sg:website":"http://champaign.citysearch.com/profile/external/3830756/monticello_il/country_financial_harold_vogelzang.html?publisher=yellowpages&reference_id=1&placement=ypwebsitemip",
    "wof:name":"COUNTRY Financial - Harold Vogelzang",
    "wof:placetype":"venue"
},
  "geometry": {"coordinates":[-88.575447,40.023624],"type":"Point"}
}