{
  "type": "Feature",
  "properties": {
    "iso:country":"US",
    "sg:address":"210 S Milwaukee Ave",
    "sg:city":"Libertyville",
    "sg:classifiers":[
        {
            "category":"Banks & Credit Unions",
            "subcategory":"Investment Brokerage",
            "type":"Services"
        }
    ],
    "sg:phone":"+1 847 573 2960",
    "sg:postcode":"60048",
    "sg:province":"IL",
    "sg:tags":[
        "security"
    ],
    "sg:website":"www.msdw.com",
    "wof:name":"Morgan Stanley",
    "wof:placetype":"venue"
},
  "geometry": {"coordinates":[-87.952853,42.280971],"type":"Point"}
}