{
  "type": "Feature",
  "properties": {
    "iso:country":"US",
    "sg:address":"2075 W Hopkins Pl",
    "sg:city":"Chicago",
    "sg:classifiers":[
        {
            "category":"Building & Trades",
            "subcategory":"Construction",
            "type":"Services"
        }
    ],
    "sg:phone":"+1 773 238 8930",
    "sg:postcode":"60620",
    "sg:province":"IL",
    "sg:tags":[
        "interior",
        "design"
    ],
    "wof:name":"Mwm Design",
    "wof:placetype":"venue"
},
  "geometry": {"coordinates":[-87.675301,41.731201],"type":"Point"}
}