{
  "type": "Feature",
  "properties": {
    "iso:country":"US",
    "sg:address":"18535 Meridian Rd",
    "sg:city":"Peru",
    "sg:phone":"+1 815 223 6309",
    "sg:postcode":"61312",
    "sg:province":"IL",
    "sg:tags":[
        "farm",
        "corn",
        "soybean"
    ],
    "wof:name":"Peter Debernardi",
    "wof:placetype":"venue"
},
  "geometry": {"coordinates":[-89.165364,41.410469],"type":"Point"}
}