{
  "type": "Feature",
  "properties": {
    "iso:country":"US",
    "sg:address":"812 W Randolph Street",
    "sg:city":"Chicago",
    "sg:classifiers":[
        {
            "category":"Restaurant",
            "type":"Food & Drink"
        }
    ],
    "sg:phone":"+1 312 455 1710",
    "sg:postcode":"60607",
    "sg:province":"IL",
    "wof:name":"Today's Taco Corporation",
    "wof:placetype":"venue"
},
  "geometry": {"coordinates":[-87.648022,41.884689],"type":"Point"}
}