{
  "type": "Feature",
  "properties": {
    "iso:country":"US",
    "sg:address":"27500 W Grass Lake Rd",
    "sg:city":"Antioch",
    "sg:classifiers":[
        {
            "category":"Recreation",
            "subcategory":"Marina",
            "type":"Entertainment"
        }
    ],
    "sg:phone":"+1 847 395 3093",
    "sg:postcode":"60002",
    "sg:province":"IL",
    "wof:name":"Mutiny Boat Club",
    "wof:placetype":"venue"
},
  "geometry": {"coordinates":[-88.154027,42.430127],"type":"Point"}
}