{
  "type": "Feature",
  "properties": {
    "addr:full":"1441 55th Ave Seaton IL 61476",
    "addr:housenumber":"1441",
    "addr:postcode":"61476",
    "addr:street":"55Th Ave",
    "iso:country":"US",
    "sg:address":"1441 55th Ave",
    "sg:city":"Seaton",
    "sg:classifiers":[
        {
            "category":"Real Estate",
            "subcategory":"Real Estate Operator",
            "type":"Services"
        }
    ],
    "sg:phone":"+1 309 586 6888",
    "sg:postcode":"61476",
    "sg:province":"IL",
    "sg:tags":[
        "apartment"
    ],
    "wof:name":"Eagle Management Apartments",
    "wof:placetype":"venue"
},
  "geometry": {"coordinates":[-90.812984,41.151041],"type":"Point"}
}