{
  "type": "Feature",
  "properties": {
    "addr:full":"5614 Fox Ct Crystal Lake IL 60012",
    "addr:housenumber":"5614",
    "addr:postcode":"60012",
    "addr:street":"Fox Ct",
    "iso:country":"US",
    "sg:address":"5614 Fox Ct",
    "sg:city":"Crystal Lake",
    "sg:classifiers":[
        {
            "category":"Professional",
            "subcategory":"Engineering",
            "type":"Services"
        }
    ],
    "sg:phone":"+1 815 455 6405",
    "sg:postcode":"60012",
    "sg:province":"IL",
    "sg:tags":[
        "engineer"
    ],
    "wof:name":"Strata Consulting",
    "wof:placetype":"venue"
},
  "geometry": {"coordinates":[-88.30698,42.265634],"type":"Point"}
}