{
  "type": "Feature",
  "properties": {
    "addr:full":"558 Main St Antioch IL 60002",
    "addr:housenumber":"558",
    "addr:postcode":"60002",
    "addr:street":"Main St",
    "iso:country":"US",
    "sg:address":"558 Main St",
    "sg:city":"Antioch",
    "sg:classifiers":[
        {
            "category":"Personal",
            "subcategory":"Beauty Salon",
            "type":"Services"
        }
    ],
    "sg:phone":"+1 847 838 2288",
    "sg:postcode":"60002",
    "sg:province":"IL",
    "sg:tags":[
        "shop"
    ],
    "wof:name":"Perfect Ten Nails & Tanning",
    "wof:placetype":"venue"
},
  "geometry": {"coordinates":[-88.095603,42.48805],"type":"Point"}
}