{
  "type": "Feature",
  "properties": {
    "addr:full":"2829 Central St Evanston IL 60201",
    "addr:housenumber":"2829",
    "addr:postcode":"60201",
    "addr:street":"Central St",
    "iso:country":"US",
    "sg:address":"2829 Central St",
    "sg:city":"Evanston",
    "sg:classifiers":[
        {
            "category":"Retail",
            "subcategory":"Auto Repair",
            "type":"Services"
        }
    ],
    "sg:phone":"+1 847 492 0755",
    "sg:postcode":"60201",
    "sg:province":"IL",
    "sg:tags":[
        "repairing",
        "automobile"
    ],
    "wof:name":"Bryan's Garage",
    "wof:placetype":"venue"
},
  "geometry": {"coordinates":[-87.71471,42.064539],"type":"Point"}
}