{
  "type": "Feature",
  "properties": {
    "addr:full":"975 S Durkin Dr Springfield IL 62704",
    "addr:housenumber":"975",
    "addr:postcode":"62704",
    "addr:street":"S Durkin Dr",
    "iso:country":"US",
    "sg:address":"975 S Durkin Dr",
    "sg:city":"Springfield",
    "sg:classifiers":[
        {
            "category":"Professional",
            "subcategory":"Management & Consulting",
            "type":"Services"
        }
    ],
    "sg:phone":"+1 217 698 0577",
    "sg:postcode":"62704",
    "sg:province":"IL",
    "sg:tags":[
        "consultant"
    ],
    "wof:name":"Walsh & Assoc",
    "wof:placetype":"venue"
},
  "geometry": {"coordinates":[-89.703011,39.790771],"type":"Point"}
}