{
  "type": "Feature",
  "properties": {
    "addr:full":"1 E Wacker Chicago IL 60601",
    "addr:housenumber":"1",
    "addr:postcode":"60601",
    "addr:street":"E",
    "iso:country":"US",
    "sg:address":"1 E Wacker",
    "sg:city":"Chicago",
    "sg:classifiers":[
        {
            "category":"Professional",
            "type":"Services"
        },
        {
            "category":"Coffee & Tea",
            "type":"Food & Drink"
        },
        {
            "category":"Restaurant",
            "type":"Food & Drink"
        }
    ],
    "sg:phone":"+1 312 644 2233",
    "sg:postcode":"60601",
    "sg:province":"IL",
    "sg:tags":[
        "espresso",
        "mediterranean",
        "caterer"
    ],
    "sg:website":"caffecafechicago.com",
    "wof:name":"Caffecafe",
    "wof:placetype":"venue"
},
  "geometry": {"coordinates":[-87.627246,41.886541],"type":"Point"}
}