{
  "type": "Feature",
  "properties": {
    "iso:country":"US",
    "sg:address":"7239 S Harlem Ave",
    "sg:city":"Bridgeview",
    "sg:classifiers":[
        {
            "category":"Retail",
            "subcategory":"Auto Repair",
            "type":"Services"
        }
    ],
    "sg:phone":"+1 708 594 1177",
    "sg:postcode":"60455",
    "sg:province":"IL",
    "sg:tags":[
        "transmission"
    ],
    "wof:name":"Continental Transmission",
    "wof:placetype":"venue"
},
  "geometry": {"coordinates":[-87.800209,41.760871],"type":"Point"}
}