{
  "type": "Feature",
  "properties": {
    "addr:full":"1350 W Wilson Ave Chicago IL 60640",
    "addr:housenumber":"1350",
    "addr:postcode":"60640",
    "addr:street":"W Wilson Ave",
    "iso:country":"US",
    "sg:address":"1350 W Wilson Ave",
    "sg:city":"Chicago",
    "sg:classifiers":[
        {
            "category":"Personal",
            "subcategory":"Beauty Salon",
            "type":"Services"
        }
    ],
    "sg:phone":"+1 773 907 8602",
    "sg:postcode":"60640",
    "sg:province":"IL",
    "sg:tags":[
        "treatment",
        "skin"
    ],
    "wof:name":"Dynamic Skin",
    "wof:placetype":"venue"
},
  "geometry": {"coordinates":[-87.664356,41.965377],"type":"Point"}
}