{
  "type": "Feature",
  "properties": {
    "addr:full":"1315 N Lewis Ave Waukegan IL 60085",
    "addr:housenumber":"1315",
    "addr:postcode":"60085",
    "addr:street":"N Lewis Ave",
    "iso:country":"US",
    "sg:address":"1315 N Lewis Ave",
    "sg:city":"Waukegan",
    "sg:classifiers":[
        {
            "category":"Banks & Credit Unions",
            "subcategory":"Investment Brokerage",
            "type":"Services"
        }
    ],
    "sg:phone":"+1 847 662 0667",
    "sg:postcode":"60085",
    "sg:province":"IL",
    "sg:tags":[
        "currency",
        "exchange"
    ],
    "wof:name":"Leon Berg",
    "wof:placetype":"venue"
},
  "geometry": {"coordinates":[-87.855369,42.381756],"type":"Point"}
}