{
  "type": "Feature",
  "properties": {
    "addr:full":"1111 S Homan Avenue Chicago IL 60624",
    "addr:housenumber":"1111",
    "addr:postcode":"60624",
    "addr:street":"S Homan Avenue",
    "iso:country":"US",
    "sg:address":"1111 S Homan Avenue",
    "sg:city":"Chicago",
    "sg:classifiers":[
        {
            "category":"Banks & Credit Unions",
            "subcategory":"Bank",
            "type":"Services"
        }
    ],
    "sg:phone":"+1 773 533 2265",
    "sg:postcode":"60624",
    "sg:province":"IL",
    "wof:name":"International Bank of Chicago",
    "wof:placetype":"venue"
},
  "geometry": {"coordinates":[-87.710542,41.867422],"type":"Point"}
}