{
  "type": "Feature",
  "properties": {
    "addr:full":"3708 Grove Ave Berwyn IL 60402",
    "addr:housenumber":"3708",
    "addr:postcode":"60402",
    "addr:street":"Grove Ave",
    "iso:country":"US",
    "sg:address":"3708 Grove Ave",
    "sg:city":"Berwyn",
    "sg:classifiers":[
        {
            "category":"Personal",
            "subcategory":"Beauty Salon",
            "type":"Services"
        }
    ],
    "sg:phone":"+1 708 484 0027",
    "sg:postcode":"60402",
    "sg:province":"IL",
    "sg:tags":[
        "shop"
    ],
    "wof:name":"Hair Rx",
    "wof:placetype":"venue"
},
  "geometry": {"coordinates":[-87.79379,41.823299],"type":"Point"}
}