{
  "type": "Feature",
  "properties": {
    "iso:country":"US",
    "sg:address":"2754 US Hwy 24",
    "sg:city":"Clayton",
    "sg:classifiers":[
        {
            "category":"Building & Trades",
            "subcategory":"Construction",
            "type":"Services"
        }
    ],
    "sg:phone":"+1 217 894 7705",
    "sg:postcode":"62324",
    "sg:province":"IL",
    "sg:tags":[
        "general",
        "contractor"
    ],
    "wof:name":"Energy Efficient Builders",
    "wof:placetype":"venue"
},
  "geometry": {"coordinates":[-90.98573,40.033018],"type":"Point"}
}