{
  "type": "Feature",
  "properties": {
    "iso:country":"US",
    "sg:address":"1308 Wolff Ave",
    "sg:city":"Elgin",
    "sg:classifiers":[
        {
            "category":"Wholesale",
            "subcategory":"Non-durable Goods",
            "type":"Manufacturing & Wholesale Goods"
        }
    ],
    "sg:phone":"+1 847 888 4880",
    "sg:postcode":"60123",
    "sg:province":"IL",
    "sg:tags":[
        "shop",
        "item",
        "representative",
        "gift",
        "manufacturer"
    ],
    "wof:name":"Franzen Enterprises Inc",
    "wof:placetype":"venue"
},
  "geometry": {"coordinates":[-88.311725,42.037521],"type":"Point"}
}