{
  "type": "Feature",
  "properties": {
    "addr:full":"18707 W Kelly Rd Wadsworth IL 60083",
    "addr:housenumber":"18707",
    "addr:postcode":"60083",
    "addr:street":"W Kelly Rd",
    "iso:country":"US",
    "sg:address":"18707 W Kelly Rd",
    "sg:city":"Wadsworth",
    "sg:classifiers":[
        {
            "category":"Government",
            "subcategory":"Office",
            "type":"Public Place"
        }
    ],
    "sg:phone":"+1 847 395 2763",
    "sg:postcode":"60083",
    "sg:province":"IL",
    "sg:tags":[
        "government-united",
        "state"
    ],
    "wof:name":"Usgs",
    "wof:placetype":"venue"
},
  "geometry": {"coordinates":[-87.93937699999999,42.44348],"type":"Point"}
}