{
  "type": "Feature",
  "properties": {
    "addr:full":"713 Wayne Dr Crete IL 60417",
    "addr:housenumber":"713",
    "addr:postcode":"60417",
    "addr:street":"Wayne Dr",
    "iso:country":"US",
    "sg:address":"713 Wayne Dr",
    "sg:city":"Crete",
    "sg:classifiers":[
        {
            "category":"Building & Trades",
            "subcategory":"Construction",
            "type":"Services"
        }
    ],
    "sg:phone":"+1 708 672 9572",
    "sg:postcode":"60417",
    "sg:province":"IL",
    "sg:tags":[
        "concrete",
        "contractor"
    ],
    "wof:name":"Burnham Concrete Co",
    "wof:placetype":"venue"
},
  "geometry": {"coordinates":[-87.639872,41.43724],"type":"Point"}
}