{
  "type": "Feature",
  "properties": {
    "addr:full":"2100 Manchester Rd Wheaton IL 60187",
    "addr:housenumber":"2100",
    "addr:postcode":"60187",
    "addr:street":"Manchester Rd",
    "iso:country":"US",
    "sg:address":"2100 Manchester Rd",
    "sg:city":"Wheaton",
    "sg:classifiers":[
        {
            "category":"Professional",
            "subcategory":"Employment Agencies",
            "type":"Services"
        }
    ],
    "sg:phone":"+1 630 653 3200",
    "sg:postcode":"60187",
    "sg:province":"IL",
    "sg:tags":[
        "computer",
        "help",
        "related",
        "supply"
    ],
    "wof:name":"Tekmark Global Solutions LLC",
    "wof:placetype":"venue"
},
  "geometry": {"coordinates":[-88.13596200000001,41.865567],"type":"Point"}
}