{
  "type": "Feature",
  "properties": {
    "addr:full":"1608 W Healey St Champaign IL 61821",
    "addr:housenumber":"1608",
    "addr:postcode":"61821",
    "addr:street":"W Healey St",
    "iso:country":"US",
    "sg:address":"1608 W Healey St",
    "sg:city":"Champaign",
    "sg:classifiers":[
        {
            "category":"Building & Trades",
            "subcategory":"Construction",
            "type":"Services"
        }
    ],
    "sg:phone":"+1 217 359 8628",
    "sg:postcode":"61821",
    "sg:province":"IL",
    "sg:tags":[
        "carpentry",
        "contractor"
    ],
    "wof:name":"Pomattos Carpentry Services",
    "wof:placetype":"venue"
},
  "geometry": {"coordinates":[-88.2723,40.111916],"type":"Point"}
}