{
  "type": "Feature",
  "properties": {
    "iso:country":"US",
    "sg:address":"2035 63rd St",
    "sg:city":"Downers Grove",
    "sg:classifiers":[
        {
            "category":"Shopping",
            "subcategory":"Used Merchandise",
            "type":"Retail Goods"
        }
    ],
    "sg:phone":"+1 630 271 0835",
    "sg:postcode":"60516",
    "sg:province":"IL",
    "sg:tags":[
        "shop",
        "consignment"
    ],
    "wof:name":"Family Tree Thrift Store Inc",
    "wof:placetype":"venue"
},
  "geometry": {"coordinates":[-88.032741,41.772405],"type":"Point"}
}