{
  "type": "Feature",
  "properties": {
    "iso:country":"US",
    "sg:address":"200 Carver Ln",
    "sg:city":"Schaumburg",
    "sg:classifiers":[
        {
            "category":"Building & Trades",
            "subcategory":"Cleaning & Sanitation",
            "type":"Services"
        }
    ],
    "sg:phone":"+1 847 352 0784",
    "sg:postcode":"60193",
    "sg:province":"IL",
    "sg:tags":[
        "maintenance"
    ],
    "wof:name":"Engine Maintenance Specialists",
    "wof:placetype":"venue"
},
  "geometry": {"coordinates":[-88.114843,42.023292],"type":"Point"}
}