{
  "type": "Feature",
  "properties": {
    "iso:country":"US",
    "sg:address":"17712 East St",
    "sg:city":"Breese",
    "sg:classifiers":[
        {
            "category":"Home & Garden",
            "subcategory":"Carpets & Floor Coverings",
            "type":"Retail Goods"
        }
    ],
    "sg:phone":"+1   ",
    "sg:postcode":"62230",
    "sg:province":"IL",
    "wof:name":"Rehkemper Tile & Floor Cvg",
    "wof:placetype":"venue"
},
  "geometry": {"coordinates":[-89.5534,38.681225],"type":"Point"}
}