{
  "type": "Feature",
  "properties": {
    "iso:country":"US",
    "sg:address":"7855 Gross Point Rd",
    "sg:city":"Skokie",
    "sg:classifiers":[
        {
            "category":"Building & Trades",
            "subcategory":"Pest Control",
            "type":"Services"
        }
    ],
    "sg:phone":"+1 847 676 0099",
    "sg:postcode":"60077",
    "sg:province":"IL",
    "wof:name":"Orkin Pest Control 508",
    "wof:placetype":"venue"
},
  "geometry": {"coordinates":[-87.769267,42.023365],"type":"Point"}
}