{
  "type": "Feature",
  "properties": {
    "addr:full":"6001 N Legett Ave Chicago IL 60646",
    "addr:housenumber":"6001",
    "addr:postcode":"60646",
    "addr:street":"N Legett Ave",
    "iso:country":"US",
    "sg:address":"6001 N Legett Ave",
    "sg:city":"Chicago",
    "sg:classifiers":[
        {
            "category":"Building & Trades",
            "subcategory":"Landscaping Services",
            "type":"Services"
        }
    ],
    "sg:phone":"+1 773 725 4798",
    "sg:postcode":"60646",
    "sg:province":"IL",
    "sg:tags":[
        "consultant",
        "designer",
        "landscape"
    ],
    "wof:name":"Williams Landscaping Inc",
    "wof:placetype":"venue"
},
  "geometry": {"coordinates":[-87.75649300000001,41.99041],"type":"Point"}
}