{
  "type": "Feature",
  "properties": {
    "iso:country":"US",
    "sg:address":"520 Lake Cook Rd",
    "sg:city":"Deerfield",
    "sg:classifiers":[
        {
            "category":"Banks & Credit Unions",
            "subcategory":"Bank",
            "type":"Services"
        }
    ],
    "sg:phone":"+1 847 267 0600",
    "sg:postcode":"60015",
    "sg:province":"IL",
    "sg:tags":[
        "equipment",
        "purchase",
        "defaulted",
        "lease"
    ],
    "wof:name":"Tbf Financial",
    "wof:placetype":"venue"
},
  "geometry": {"coordinates":[-87.838626,42.15284],"type":"Point"}
}