{
  "type": "Feature",
  "properties": {
    "iso:country":"US",
    "sg:address":"201 Field Ave",
    "sg:city":"Mount Sterling",
    "sg:classifiers":[
        {
            "category":"Organizations",
            "subcategory":"Community Association",
            "type":"Services"
        }
    ],
    "sg:phone":"+1 217 773 4889",
    "sg:postcode":"62353",
    "sg:province":"IL",
    "wof:name":"Delta Kappa Gamma Society",
    "wof:placetype":"venue"
},
  "geometry": {"coordinates":[-90.76487299999999,39.993005],"type":"Point"}
}