{
  "type": "Feature",
  "properties": {
    "addr:full":"1719 N Ridgeway Ave Chicago IL 60647",
    "addr:housenumber":"1719",
    "addr:postcode":"60647",
    "addr:street":"N Ridgeway Ave",
    "iso:country":"US",
    "sg:address":"1719 N Ridgeway Ave",
    "sg:city":"Chicago",
    "sg:classifiers":[
        {
            "category":"Building & Trades",
            "subcategory":"Cleaning & Sanitation",
            "type":"Services"
        }
    ],
    "sg:phone":"+1 773 478 6584",
    "sg:postcode":"60647",
    "sg:province":"IL",
    "sg:tags":[
        "window"
    ],
    "wof:name":"Als Professional Window Cleani",
    "wof:placetype":"venue"
},
  "geometry": {"coordinates":[-87.720268,41.912],"type":"Point"}
}