{
  "type": "Feature",
  "properties": {
    "iso:country":"US",
    "sg:address":"308 S Mclean Blvd",
    "sg:city":"Elgin",
    "sg:classifiers":[
        {
            "category":"Personal",
            "subcategory":"Beauty Salon",
            "type":"Services"
        }
    ],
    "sg:phone":"+1 847 429 9698",
    "sg:postcode":"60123",
    "sg:province":"IL",
    "wof:name":"Elizabeth Beauty Salon",
    "wof:placetype":"venue"
},
  "geometry": {"coordinates":[-88.31197400000001,42.025749],"type":"Point"}
}