{
  "type": "Feature",
  "properties": {
    "addr:full":"6042 Roosevelt Rd Oak Park IL 60304",
    "addr:housenumber":"6042",
    "addr:postcode":"60304",
    "addr:street":"Roosevelt Rd",
    "iso:country":"US",
    "sg:address":"6042 Roosevelt Rd",
    "sg:city":"Oak Park",
    "sg:classifiers":[
        {
            "category":"Retail",
            "subcategory":"Veterinary Services",
            "type":"Services"
        }
    ],
    "sg:phone":"+1 708 386 6205",
    "sg:postcode":"60304",
    "sg:province":"IL",
    "sg:tags":[
        "animal",
        "sitting",
        "pet",
        "hospital",
        "veterinarian",
        "boarding/pet"
    ],
    "wof:name":"Aamerican Veterinary Hospital",
    "wof:placetype":"venue"
},
  "geometry": {"coordinates":[-87.776205,41.865684],"type":"Point"}
}