{
  "type": "Feature",
  "properties": {
    "addr:full":"623 N Adams St Kewanee IL 61443",
    "addr:housenumber":"623",
    "addr:postcode":"61443",
    "addr:street":"N Adams St",
    "iso:country":"US",
    "sg:address":"623 N Adams St",
    "sg:city":"Kewanee",
    "sg:classifiers":[
        {
            "category":"Retail",
            "subcategory":"Animal Services",
            "type":"Services"
        }
    ],
    "sg:phone":"+1 309 852 2868",
    "sg:postcode":"61443",
    "sg:province":"IL",
    "sg:tags":[
        "pet",
        "grooming",
        "washing"
    ],
    "wof:name":"Country Pines Grooming & Brdng",
    "wof:placetype":"venue"
},
  "geometry": {"coordinates":[-89.941603,41.250646],"type":"Point"}
}