{
  "type": "Feature",
  "properties": {
    "addr:full":"7162 S Exchange Ave Chicago IL 60649",
    "addr:housenumber":"7162",
    "addr:postcode":"60649",
    "addr:street":"S Exchange Ave",
    "iso:country":"US",
    "sg:address":"7162 S Exchange Ave",
    "sg:city":"Chicago",
    "sg:classifiers":[
        {
            "category":"Food & Beverages",
            "subcategory":"Groceries & Convenience Stores",
            "type":"Retail Goods"
        }
    ],
    "sg:phone":"+1   ",
    "sg:postcode":"60649",
    "sg:province":"IL",
    "sg:tags":[
        "independent"
    ],
    "wof:name":"Food Exchange The",
    "wof:placetype":"venue"
},
  "geometry": {"coordinates":[-87.56507499999999,41.764612],"type":"Point"}
}