{
  "type": "Feature",
  "properties": {
    "addr:full":"875 N Michigan Ave # 2600 Chicago IL 60611",
    "addr:housenumber":"875",
    "addr:postcode":"60611",
    "addr:street":"N Michigan Ave # 2600",
    "iso:country":"US",
    "sg:address":"875 N Michigan Ave # 2600",
    "sg:city":"Chicago",
    "sg:classifiers":[
        {
            "category":"Real Estate",
            "subcategory":"Real Estate Services",
            "type":"Services"
        }
    ],
    "sg:phone":"+1 312 706 2462",
    "sg:postcode":"60611",
    "sg:province":"IL",
    "sg:tags":[
        "management",
        "condominium"
    ],
    "wof:name":"220 East Walton Condominium Association",
    "wof:placetype":"venue"
},
  "geometry": {"coordinates":[-87.624101,41.898827],"type":"Point"}
}