{
  "type": "Feature",
  "properties": {
    "iso:country":"US",
    "sg:address":"202 S Main St",
    "sg:city":"Columbia",
    "sg:classifiers":[
        {
            "category":"Home & Garden",
            "subcategory":"Building Materials",
            "type":"Retail Goods"
        }
    ],
    "sg:phone":"+1 618 281 8666",
    "sg:postcode":"62236",
    "sg:province":"IL",
    "sg:tags":[
        "mixed",
        "concrete"
    ],
    "wof:name":"Roessler Ready Mix Inc",
    "wof:placetype":"venue"
},
  "geometry": {"coordinates":[-90.197796,38.442121],"type":"Point"}
}