{
  "type": "Feature",
  "properties": {
    "addr:full":"537 N Central Ave Chicago IL 60644",
    "addr:housenumber":"537",
    "addr:postcode":"60644",
    "addr:street":"N Central Ave",
    "iso:country":"US",
    "sg:address":"537 N Central Ave",
    "sg:city":"Chicago",
    "sg:classifiers":[
        {
            "category":"Social Services",
            "subcategory":"Child Care",
            "type":"Services"
        }
    ],
    "sg:phone":"+1 773 626 0574",
    "sg:postcode":"60644",
    "sg:province":"IL",
    "wof:name":"Sadie Jefferson",
    "wof:placetype":"venue"
},
  "geometry": {"coordinates":[-87.76514299999999,41.890264],"type":"Point"}
}