{
  "type": "Feature",
  "properties": {
    "addr:full":"315 W Oak St Greenville IL 62246",
    "addr:housenumber":"315",
    "addr:postcode":"62246",
    "addr:street":"W Oak St",
    "iso:country":"US",
    "sg:address":"315 W Oak St",
    "sg:city":"Greenville",
    "sg:classifiers":[
        {
            "category":"Health Services",
            "subcategory":"Optometrist",
            "type":"Services"
        }
    ],
    "sg:phone":"+1 618 664 9101",
    "sg:postcode":"62246",
    "sg:province":"IL",
    "wof:name":"Greenville Eyeglass Ctr",
    "wof:placetype":"venue"
},
  "geometry": {"coordinates":[-89.413566,38.893697],"type":"Point"}
}