{
  "type": "Feature",
  "properties": {
    "iso:country":"US",
    "sg:address":"313 Morrison St",
    "sg:city":"Green Valley",
    "sg:classifiers":[
        {
            "category":"Social Services",
            "subcategory":"Adult Care",
            "type":"Services"
        }
    ],
    "sg:phone":"+1 309 352 3064",
    "sg:postcode":"61534",
    "sg:province":"IL",
    "sg:tags":[
        "residential"
    ],
    "wof:name":"Mardell Manor",
    "wof:placetype":"venue"
},
  "geometry": {"coordinates":[-89.63941800000001,40.405637],"type":"Point"}
}