{
  "type": "Feature",
  "properties": {
    "iso:country":"US",
    "sg:address":"1072 Lanark Ln",
    "sg:city":"Palatine",
    "sg:classifiers":[
        {
            "category":"Food & Beverages",
            "subcategory":"Groceries & Convenience Stores",
            "type":"Retail Goods"
        }
    ],
    "sg:phone":"+1   ",
    "sg:postcode":"60067",
    "sg:province":"IL",
    "wof:name":"International Machinery Market",
    "wof:placetype":"venue"
},
  "geometry": {"coordinates":[-88.100785,42.129383],"type":"Point"}
}