{
  "type": "Feature",
  "properties": {
    "iso:country":"US",
    "sg:address":"4700 W 95th St Ste 204",
    "sg:city":"Oak Lawn",
    "sg:classifiers":[
        {
            "category":"Professional",
            "subcategory":"Accounting & Tax Preparation",
            "type":"Services"
        }
    ],
    "sg:phone":"+1 708 422 2600",
    "sg:postcode":"60453",
    "sg:province":"IL",
    "sg:tags":[
        "accountant"
    ],
    "wof:name":"Geissler & Associates",
    "wof:placetype":"venue"
},
  "geometry": {"coordinates":[-87.738297,41.7201],"type":"Point"}
}