{
  "type": "Feature",
  "properties": {
    "iso:country":"US",
    "sg:address":"151 N Seminary St",
    "sg:city":"Galesburg",
    "sg:classifiers":[
        {
            "category":"Professional",
            "subcategory":"Lawyer & Legal Services",
            "type":"Services"
        }
    ],
    "sg:phone":"+1 309 341 2889",
    "sg:postcode":"61401",
    "sg:province":"IL",
    "sg:tags":[
        "information",
        "attorney",
        "practice",
        "referral"
    ],
    "wof:name":"Watts Steve Attorney",
    "wof:placetype":"venue"
},
  "geometry": {"coordinates":[-90.364609,40.949182],"type":"Point"}
}