{
  "type": "Feature",
  "properties": {
    "addr:full":"6039 N Kenmore Ave Chicago IL 60660",
    "addr:housenumber":"6039",
    "addr:postcode":"60660",
    "addr:street":"N Kenmore Ave",
    "iso:country":"US",
    "sg:address":"6039 N Kenmore Ave",
    "sg:city":"Chicago",
    "sg:classifiers":[
        {
            "category":"Real Estate",
            "subcategory":"Real Estate Operator",
            "type":"Services"
        }
    ],
    "sg:phone":"+1 773 989 8295",
    "sg:postcode":"60660",
    "sg:province":"IL",
    "sg:tags":[
        "condominium"
    ],
    "wof:name":"Glenlake Court Condo Assoc",
    "wof:placetype":"venue"
},
  "geometry": {"coordinates":[-87.656802,41.992071],"type":"Point"}
}