{
  "type": "Feature",
  "properties": {
    "addr:full":"9352 W Ballard Rd Des Plaines IL 60016",
    "addr:housenumber":"9352",
    "addr:postcode":"60016",
    "addr:street":"W Ballard Rd Des",
    "iso:country":"US",
    "sg:address":"9352 W Ballard Rd",
    "sg:city":"Des Plaines",
    "sg:classifiers":[
        {
            "category":"Personal",
            "subcategory":"Beauty Salon",
            "type":"Services"
        }
    ],
    "sg:phone":"+1 847 635 7820",
    "sg:postcode":"60016",
    "sg:province":"IL",
    "sg:tags":[
        "shop"
    ],
    "wof:name":"European Touch Inc",
    "wof:placetype":"venue"
},
  "geometry": {"coordinates":[-87.859323,42.043339],"type":"Point"}
}