{
  "type": "Feature",
  "properties": {
    "iso:country":"US",
    "sg:address":"1613 Hedge Rd",
    "sg:city":"Champaign",
    "sg:classifiers":[
        {
            "category":"Personal",
            "subcategory":"Tattoo Parlor",
            "type":"Services"
        }
    ],
    "sg:phone":"+1 217 352 8466",
    "sg:postcode":"61821",
    "sg:province":"IL",
    "sg:tags":[
        "tattooing"
    ],
    "wof:name":"Corey's Tattoo Piercing",
    "wof:placetype":"venue"
},
  "geometry": {"coordinates":[-88.275938,40.1336],"type":"Point"}
}