{
  "type": "Feature",
  "properties": {
    "iso:country":"US",
    "sg:address":"3236 N Pulaski Rd",
    "sg:city":"Chicago",
    "sg:classifiers":[
        {
            "category":"Retail",
            "subcategory":"Laundry & Dry Cleaning",
            "type":"Services"
        }
    ],
    "sg:phone":"+1 773 685 6266",
    "sg:postcode":"60641",
    "sg:province":"IL",
    "wof:name":"Spotsgard Cleaners",
    "wof:placetype":"venue"
},
  "geometry": {"coordinates":[-87.727203,41.939999],"type":"Point"}
}