{
  "type": "Feature",
  "properties": {
    "iso:country":"US",
    "sg:address":"213 N 30th St",
    "sg:city":"Herrin",
    "sg:classifiers":[
        {
            "category":"Place Of Worship",
            "type":"Public Place"
        },
        {
            "category":"Organizations",
            "subcategory":"Religious Organization",
            "type":"Services"
        }
    ],
    "sg:phone":"+1 618 942 7918",
    "sg:postcode":"62948",
    "sg:province":"IL",
    "sg:tags":[
        "clergy",
        "church"
    ],
    "wof:name":"Griffith Terry Rev",
    "wof:placetype":"venue"
},
  "geometry": {"coordinates":[-89.04399100000001,37.804581],"type":"Point"}
}