{
  "type": "Feature",
  "properties": {
    "iso:country":"US",
    "sg:address":"4526 N Clark St",
    "sg:city":"Chicago",
    "sg:classifiers":[
        {
            "category":"Wholesale",
            "subcategory":"Apparel",
            "type":"Manufacturing & Wholesale Goods"
        },
        {
            "category":"Wholesale",
            "subcategory":"Durable Goods & Equipment",
            "type":"Manufacturing & Wholesale Goods"
        }
    ],
    "sg:phone":"+1 773 784 2424",
    "sg:postcode":"60640",
    "sg:province":"IL",
    "sg:tags":[
        "importer",
        "clothing"
    ],
    "wof:name":"The Fashion House",
    "wof:placetype":"venue"
},
  "geometry": {"coordinates":[-87.666715,41.964776],"type":"Point"}
}