{
  "type": "Feature",
  "properties": {
    "addr:full":"1 Executive Ct South Barrington IL 60010",
    "addr:housenumber":"1",
    "addr:postcode":"60010",
    "addr:street":"Executive Ct",
    "iso:country":"US",
    "sg:address":"1 Executive Ct",
    "sg:city":"South Barrington",
    "sg:classifiers":[
        {
            "category":"Banks & Credit Unions",
            "subcategory":"Investment Brokerage",
            "type":"Services"
        }
    ],
    "sg:phone":"+1 847 382 2600",
    "sg:postcode":"60010",
    "sg:province":"IL",
    "sg:tags":[
        "consultant",
        "planning",
        "financial"
    ],
    "wof:name":"Keith Mooney & Assoc",
    "wof:placetype":"venue"
},
  "geometry": {"coordinates":[-88.14204100000001,42.079806],"type":"Point"}
}