{
  "type": "Feature",
  "properties": {
    "addr:full":"2410 Caton Farm Rd Joliet IL 60403",
    "addr:housenumber":"2410",
    "addr:postcode":"60403",
    "addr:street":"Caton Farm Rd",
    "iso:country":"US",
    "sg:address":"2410 Caton Farm Rd",
    "sg:city":"Joliet",
    "sg:classifiers":[
        {
            "category":"Communications",
            "subcategory":"Radio Station",
            "type":"Services"
        }
    ],
    "sg:phone":"+1 815 556 0100",
    "sg:postcode":"60403",
    "sg:province":"IL",
    "sg:tags":[
        "broadcast"
    ],
    "wof:name":"Next Media Inc",
    "wof:placetype":"venue"
},
  "geometry": {"coordinates":[-89.562146,39.126394],"type":"Point"}
}