{
  "type": "Feature",
  "properties": {
    "addr:full":"425 W Talcott Rd Park Ridge IL 60068",
    "addr:housenumber":"425",
    "addr:postcode":"60068",
    "addr:street":"W Talcott Rd Park Ridge",
    "iso:country":"US",
    "sg:address":"425 W Talcott Rd",
    "sg:city":"Park Ridge",
    "sg:classifiers":[
        {
            "category":"Shopping",
            "subcategory":"Clothing, Apparel, & Fashions",
            "type":"Retail Goods"
        }
    ],
    "sg:phone":"+1 847 384 9033",
    "sg:postcode":"60068",
    "sg:province":"IL",
    "sg:tags":[
        "children's",
        "clothing"
    ],
    "wof:name":"Earth Angel Childrens Boutique",
    "wof:placetype":"venue"
},
  "geometry": {"coordinates":[-87.8283,41.995399],"type":"Point"}
}