{
  "type": "Feature",
  "properties": {
    "iso:country":"US",
    "sg:address":"550 E Roosevelt Rd",
    "sg:city":"Glen Ellyn",
    "sg:classifiers":[
        {
            "category":"Autos & Motor Vehicles",
            "subcategory":"Automobile Sales",
            "type":"Retail Goods"
        }
    ],
    "sg:phone":"+1 630 545 1000",
    "sg:postcode":"60137",
    "sg:province":"IL",
    "wof:name":"Motor World Inc",
    "wof:placetype":"venue"
},
  "geometry": {"coordinates":[-88.064904,41.859418],"type":"Point"}
}