{
  "type": "Feature",
  "properties": {
    "addr:full":"3329 Crestview Dr Quincy IL 62301",
    "addr:housenumber":"3329",
    "addr:postcode":"62301",
    "addr:street":"Crestview Dr",
    "iso:country":"US",
    "sg:address":"3329 Crestview Dr",
    "sg:city":"Quincy",
    "sg:classifiers":[
        {
            "category":"Social Services",
            "subcategory":"Child Care",
            "type":"Services"
        }
    ],
    "sg:phone":"+1 217 228 1544",
    "sg:postcode":"62301",
    "sg:province":"IL",
    "sg:tags":[
        "day"
    ],
    "wof:name":"Tamara Hoschar",
    "wof:placetype":"venue"
},
  "geometry": {"coordinates":[-91.363381,39.942339],"type":"Point"}
}