{
  "type": "Feature",
  "properties": {
    "iso:country":"US",
    "sg:address":"1733 30th St",
    "sg:city":"Rock Island",
    "sg:classifiers":[
        {
            "category":"Home & Garden",
            "subcategory":"Carpets & Floor Coverings",
            "type":"Retail Goods"
        }
    ],
    "sg:phone":"+1 309 796 6131",
    "sg:postcode":"61201",
    "sg:province":"IL",
    "sg:tags":[
        "dealer",
        "rug"
    ],
    "wof:name":"Town & Country Carpets Carpet",
    "wof:placetype":"venue"
},
  "geometry": {"coordinates":[-90.557185,41.493685],"type":"Point"}
}