{
  "type": "Feature",
  "properties": {
    "iso:country":"US",
    "sg:address":"210 N Mulford Rd",
    "sg:city":"Rockford",
    "sg:classifiers":[
        {
            "category":"Banks & Credit Unions",
            "subcategory":"Investment Brokerage",
            "type":"Services"
        }
    ],
    "sg:phone":"+1 815 398 9092",
    "sg:postcode":"61107",
    "sg:province":"IL",
    "sg:tags":[
        "security"
    ],
    "wof:name":"Edward Jones 13966",
    "wof:placetype":"venue"
},
  "geometry": {"coordinates":[-88.99967,42.271014],"type":"Point"}
}