{
  "type": "Feature",
  "properties": {
    "addr:full":"901 Union St Alton IL 62002",
    "addr:housenumber":"901",
    "addr:postcode":"62002",
    "addr:street":"Union St",
    "iso:country":"US",
    "sg:address":"901 Union St",
    "sg:city":"Alton",
    "sg:classifiers":[
        {
            "category":"Home & Garden",
            "subcategory":"Household Appliances",
            "type":"Retail Goods"
        }
    ],
    "sg:phone":"+1 618 462 4537",
    "sg:postcode":"62002",
    "sg:province":"IL",
    "sg:tags":[
        "cleaners",
        "vacuum"
    ],
    "wof:name":"Colman Distributing Co",
    "wof:placetype":"venue"
},
  "geometry": {"coordinates":[-90.171224,38.895227],"type":"Point"}
}