{
  "type": "Feature",
  "properties": {
    "iso:country":"US",
    "sg:address":"259 E Baltusrol Dr",
    "sg:city":"Vernon Hills",
    "sg:classifiers":[
        {
            "category":"Manufacturing",
            "subcategory":"Retail Goods",
            "type":"Manufacturing & Wholesale Goods"
        }
    ],
    "sg:phone":"+1 847 816 0138",
    "sg:postcode":"60061",
    "sg:province":"IL",
    "sg:tags":[
        "manufacturer"
    ],
    "wof:name":"Burlington Industries",
    "wof:placetype":"venue"
},
  "geometry": {"coordinates":[-87.958439,42.254065],"type":"Point"}
}