{
  "type": "Feature",
  "properties": {
    "addr:full":"28W250 Saint Chas Road W Chicago IL 60607",
    "addr:housenumber":"28w250",
    "addr:postcode":"60607",
    "addr:street":"Saint Chas Road W",
    "iso:country":"US",
    "sg:address":"28W250 Saint Chas Road W",
    "sg:city":"Chicago",
    "sg:classifiers":[
        {
            "category":"Education",
            "subcategory":"School",
            "type":"Public Place"
        }
    ],
    "sg:phone":"+1 630 293 5080",
    "sg:postcode":"60607",
    "sg:province":"IL",
    "sg:tags":[
        "high",
        "middle",
        "elementary"
    ],
    "wof:name":"Benjamin Middle School",
    "wof:placetype":"venue"
},
  "geometry": {"coordinates":[-87.656932,41.873792],"type":"Point"}
}