{
  "type": "Feature",
  "properties": {
    "iso:country":"US",
    "sg:address":"3416 N Southport Ave",
    "sg:city":"Chicago",
    "sg:classifiers":[
        {
            "category":"Cafe",
            "type":"Food & Drink"
        }
    ],
    "sg:menulink":"http://www.allmenus.com/il/chicago/20946-ann-sather-cafe/menu/",
    "sg:phone":"+1 773 404 4475",
    "sg:postcode":"60657",
    "sg:province":"IL",
    "sg:tags":[
        "american"
    ],
    "wof:name":"Ann Sather Cafe",
    "wof:placetype":"venue"
},
  "geometry": {"coordinates":[-87.663928,41.943626],"type":"Point"}
}