{
  "type": "Feature",
  "properties": {
    "addr:full":"547 W Jackson Blvd Chicago IL 60661",
    "addr:housenumber":"547",
    "addr:postcode":"60661",
    "addr:street":"W Jackson Blvd",
    "iso:country":"US",
    "sg:address":"547 W Jackson Blvd",
    "sg:city":"Chicago",
    "sg:classifiers":[
        {
            "category":"Professional",
            "subcategory":"Accounting & Tax Preparation",
            "type":"Services"
        }
    ],
    "sg:phone":"+1 312 224 2000",
    "sg:postcode":"60661",
    "sg:province":"IL",
    "sg:tags":[
        "billing"
    ],
    "wof:name":"Physician Support Systems",
    "wof:placetype":"venue"
},
  "geometry": {"coordinates":[-87.641037,41.87804],"type":"Point"}
}