{
  "type": "Feature",
  "properties": {
    "addr:full":"2528 N Racine Ave Chicago IL 60614",
    "addr:housenumber":"2528",
    "addr:postcode":"60614",
    "addr:street":"N Racine Ave",
    "iso:country":"US",
    "sg:address":"2528 N Racine Ave",
    "sg:city":"Chicago",
    "sg:classifiers":[
        {
            "category":"Park",
            "type":"Public Place"
        }
    ],
    "sg:postcode":"60614",
    "sg:province":"IL",
    "sg:website":"www.chicagoparkdistrict.com/inde...",
    "wof:name":"Supera Playlot Park",
    "wof:placetype":"venue"
},
  "geometry": {"coordinates":[-87.65858,41.927988],"type":"Point"}
}