{
  "type": "Feature",
  "properties": {
    "iso:country":"US",
    "sg:address":"5044 W Madison St",
    "sg:city":"Chicago",
    "sg:classifiers":[
        {
            "category":"Personal",
            "subcategory":"Beauty Salon",
            "type":"Services"
        }
    ],
    "sg:phone":"+1 773 287 8711",
    "sg:postcode":"60644",
    "sg:province":"IL",
    "sg:tags":[
        "shop"
    ],
    "wof:name":"Two Nishas Salon of Beauty",
    "wof:placetype":"venue"
},
  "geometry": {"coordinates":[-87.751677,41.880491],"type":"Point"}
}