{
  "type": "Feature",
  "properties": {
    "iso:country":"US",
    "sg:address":"120 S State St",
    "sg:city":"Geneseo",
    "sg:classifiers":[
        {
            "category":"Shopping",
            "subcategory":"Clothing, Apparel, & Fashions",
            "type":"Retail Goods"
        }
    ],
    "sg:phone":"+1   ",
    "sg:postcode":"61254",
    "sg:province":"IL",
    "sg:tags":[
        "wear"
    ],
    "wof:name":"Four Seasons The",
    "wof:placetype":"venue"
},
  "geometry": {"coordinates":[-90.155641,41.452904],"type":"Point"}
}