{
  "type": "Feature",
  "properties": {
    "iso:country":"US",
    "sg:address":"820 E Sibley Blvd",
    "sg:city":"Dolton",
    "sg:classifiers":[
        {
            "category":"Retail",
            "subcategory":"Auto Repair",
            "type":"Services"
        }
    ],
    "sg:phone":"+1 708 849 6600",
    "sg:postcode":"60419",
    "sg:province":"IL",
    "sg:website":"www.merlins.com",
    "wof:name":"Merlin 200 000 Mile Shops",
    "wof:placetype":"venue"
},
  "geometry": {"coordinates":[-87.597469,41.622751],"type":"Point"}
}