{
  "type": "Feature",
  "properties": {
    "addr:full":"401 N Wabash Ave Ste 636 Chicago IL 60611",
    "addr:housenumber":"401",
    "addr:postcode":"60611",
    "addr:street":"N Wabash Ave Ste 636",
    "iso:country":"US",
    "sg:address":"401 N Wabash Ave Ste 636",
    "sg:city":"Chicago",
    "sg:classifiers":[
        {
            "category":"Communications",
            "type":"Services"
        }
    ],
    "sg:phone":"+1 312 410 7307",
    "sg:postcode":"60611",
    "sg:province":"IL",
    "sg:tags":[
        "medium",
        "mass"
    ],
    "wof:name":"Fox News Channel",
    "wof:placetype":"venue"
},
  "geometry": {"coordinates":[-87.626701,41.889301],"type":"Point"}
}