{
  "type": "Feature",
  "properties": {
    "iso:country":"US",
    "sg:address":"725 Morton Ave",
    "sg:city":"Aurora",
    "sg:classifiers":[
        {
            "category":"Real Estate",
            "subcategory":"Real Estate Services",
            "type":"Services"
        }
    ],
    "sg:phone":"+1 630 897 0500",
    "sg:postcode":"60506",
    "sg:province":"IL",
    "sg:tags":[
        "management",
        "condominium"
    ],
    "sg:website":"http://www.baumprop.com",
    "wof:name":"Baum Property Services Ltd.",
    "wof:placetype":"venue"
},
  "geometry": {"coordinates":[-88.33566999999999,41.770883],"type":"Point"}
}