{
  "type": "Feature",
  "properties": {
    "addr:full":"887 E Wilmette Rd Palatine IL 60074",
    "addr:housenumber":"887",
    "addr:postcode":"60074",
    "addr:street":"E Wilmette Rd",
    "iso:country":"US",
    "sg:address":"887 E Wilmette Rd",
    "sg:city":"Palatine",
    "sg:classifiers":[
        {
            "category":"Manufacturing",
            "subcategory":"Chemicals & Compounds",
            "type":"Manufacturing & Wholesale Goods"
        }
    ],
    "sg:phone":"+1 847 202 8890",
    "sg:postcode":"60074",
    "sg:province":"IL",
    "sg:tags":[
        "mfg",
        "plastic"
    ],
    "wof:name":"M B H Cad Design",
    "wof:placetype":"venue"
},
  "geometry": {"coordinates":[-88.02401399999999,42.104658],"type":"Point"}
}