{
  "type": "Feature",
  "properties": {
    "iso:country":"US",
    "sg:address":"87 S Galena Ave",
    "sg:city":"Dixon",
    "sg:classifiers":[
        {
            "category":"Bars & Pubs",
            "type":"Food & Drink"
        }
    ],
    "sg:phone":"+1   ",
    "sg:postcode":"61021",
    "sg:province":"IL",
    "sg:tags":[
        "drinking"
    ],
    "wof:name":"Stables",
    "wof:placetype":"venue"
},
  "geometry": {"coordinates":[-89.482845,41.843722],"type":"Point"}
}