{
  "type": "Feature",
  "properties": {
    "iso:country":"US",
    "sg:address":"23577 N Overhill Dr",
    "sg:city":"Lake Zurich",
    "sg:classifiers":[
        {
            "category":"Home & Garden",
            "subcategory":"Furniture",
            "type":"Retail Goods"
        }
    ],
    "sg:phone":"+1   ",
    "sg:postcode":"60047",
    "sg:province":"IL",
    "sg:tags":[
        "cabinet"
    ],
    "wof:name":"Custom Cabinetry",
    "wof:placetype":"venue"
},
  "geometry": {"coordinates":[-88.05181,42.204589],"type":"Point"}
}