{
  "type": "Feature",
  "properties": {
    "addr:full":"819 N Milwaukee Avenue Chicago IL 60622",
    "addr:housenumber":"819",
    "addr:postcode":"60622",
    "addr:street":"N Milwaukee Avenue",
    "iso:country":"US",
    "sg:address":"819 N Milwaukee Avenue",
    "sg:city":"Chicago",
    "sg:classifiers":[
        {
            "category":"Shopping",
            "subcategory":"Mobile Phones",
            "type":"Retail Goods"
        }
    ],
    "sg:phone":"+1 312 432 9590",
    "sg:postcode":"60622",
    "sg:province":"IL",
    "wof:name":"Multiple Wireless Solutions",
    "wof:placetype":"venue"
},
  "geometry": {"coordinates":[-87.656029,41.89666],"type":"Point"}
}