{
  "type": "Feature",
  "properties": {
    "iso:country":"US",
    "sg:address":"103 Seminole St",
    "sg:city":"Edwardsville",
    "sg:classifiers":[
        {
            "category":"Autos & Motor Vehicles",
            "subcategory":"Auto Supplies",
            "type":"Retail Goods"
        },
        {
            "category":"Retail",
            "subcategory":"Auto Repair",
            "type":"Services"
        }
    ],
    "sg:phone":"+1 618 656 4640",
    "sg:postcode":"62025",
    "sg:province":"IL",
    "sg:tags":[
        "automobile",
        "part",
        "truck"
    ],
    "sg:website":"http://clickserve.dartsearch.net/link/click?lid=43000000313871274&ds_s_kwgid=58000000006820725&ds_e_matchtype={MatchType}&ds_e_kwdid={OrderItemId}&ds_e_adid={AdId}&ds_url_v=2",
    "wof:name":"LRE Automotive",
    "wof:placetype":"venue"
},
  "geometry": {"coordinates":[-89.941704,38.813032],"type":"Point"}
}