{
  "type": "Feature",
  "properties": {
    "addr:full":"3550 W Pratt Ave Lincolnwood IL 60646",
    "addr:housenumber":"3550",
    "addr:postcode":"60646",
    "addr:street":"W Pratt Ave",
    "iso:country":"US",
    "sg:address":"3550 W Pratt Ave",
    "sg:city":"Lincolnwood",
    "sg:classifiers":[
        {
            "category":"Wholesale",
            "subcategory":"Machinery & Supplies",
            "type":"Manufacturing & Wholesale Goods"
        }
    ],
    "sg:phone":"+1 847 677 1300",
    "sg:postcode":"60646",
    "sg:province":"IL",
    "sg:tags":[
        "fastener",
        "who"
    ],
    "wof:name":"Rifast Systems LLC",
    "wof:placetype":"venue"
},
  "geometry": {"coordinates":[-87.71877600000001,42.004641],"type":"Point"}
}