{
  "type": "Feature",
  "properties": {
    "iso:country":"US",
    "sg:address":"1821 Lincoln St",
    "sg:city":"North Chicago",
    "sg:classifiers":[
        {
            "category":"Professional",
            "subcategory":"Business Services",
            "type":"Services"
        }
    ],
    "sg:phone":"+1 847 473 5646",
    "sg:postcode":"60064",
    "sg:province":"IL",
    "wof:name":"Pedro Castillo",
    "wof:placetype":"venue"
},
  "geometry": {"coordinates":[-87.842502,42.325346],"type":"Point"}
}