{
  "type": "Feature",
  "properties": {
    "iso:country":"US",
    "sg:address":"8 Executive Dr",
    "sg:city":"Fairview Heights",
    "sg:classifiers":[
        {
            "category":"Banks & Credit Unions",
            "subcategory":"Bank",
            "type":"Services"
        }
    ],
    "sg:phone":"+1 618 624 5390",
    "sg:postcode":"62208",
    "sg:province":"IL",
    "sg:tags":[
        "escrow"
    ],
    "wof:name":"Professional Escrow Svc LLC",
    "wof:placetype":"venue"
},
  "geometry": {"coordinates":[-89.976426,38.599417],"type":"Point"}
}