{
  "type": "Feature",
  "properties": {
    "iso:country":"US",
    "sg:address":"17336 Torrence Ave",
    "sg:city":"Lansing",
    "sg:classifiers":[
        {
            "category":"Personal",
            "subcategory":"Nail Salon",
            "type":"Services"
        }
    ],
    "sg:phone":"+1 708 895 4292",
    "sg:postcode":"60438",
    "sg:province":"IL",
    "wof:name":"Nail Expo",
    "wof:placetype":"venue"
},
  "geometry": {"coordinates":[-87.55909699999999,41.5807],"type":"Point"}
}