{
  "type": "Feature",
  "properties": {
    "iso:country":"US",
    "sg:address":"255 Niagara Ave",
    "sg:city":"Elmhurst",
    "sg:classifiers":[
        {
            "category":"Professional",
            "subcategory":"Art Services",
            "type":"Services"
        }
    ],
    "sg:phone":"+1 630 530 8343",
    "sg:postcode":"60126",
    "sg:province":"IL",
    "sg:tags":[
        "graphic",
        "design"
    ],
    "sg:website":"www.blevinsdesign.com",
    "wof:name":"Blevins Design",
    "wof:placetype":"venue"
},
  "geometry": {"coordinates":[-87.931626,41.882199],"type":"Point"}
}