{
  "type": "Feature",
  "properties": {
    "iso:country":"US",
    "sg:address":"3661 Gatewood Ln",
    "sg:city":"Aurora",
    "sg:classifiers":[
        {
            "category":"Manufacturing",
            "subcategory":"Glass & Minerals",
            "type":"Manufacturing & Wholesale Goods"
        }
    ],
    "sg:phone":"+1 630 585 8951",
    "sg:postcode":"60504",
    "sg:province":"IL",
    "sg:tags":[
        "product",
        "mfg"
    ],
    "wof:name":"Class On Glass Inc",
    "wof:placetype":"venue"
},
  "geometry": {"coordinates":[-88.225967,41.752437],"type":"Point"}
}