{
  "type": "Feature",
  "properties": {
    "addr:full":"7511 Lawrenceville Rd Garden Prairie IL 61038",
    "addr:housenumber":"7511",
    "addr:postcode":"61038",
    "addr:street":"Lawrenceville Rd",
    "iso:country":"US",
    "sg:address":"7511 Lawrenceville Rd",
    "sg:city":"Garden Prairie",
    "sg:classifiers":[
        {
            "category":"Wholesale",
            "subcategory":"Construction Materials",
            "type":"Manufacturing & Wholesale Goods"
        }
    ],
    "sg:phone":"+1 815 544 2810",
    "sg:postcode":"61038",
    "sg:province":"IL",
    "wof:name":"Pyramid Material Service Inc",
    "wof:placetype":"venue"
},
  "geometry": {"coordinates":[-88.792768,42.262289],"type":"Point"}
}