{
  "type": "Feature",
  "properties": {
    "addr:full":"4904 W Elm St Mc Henry IL 60050",
    "addr:housenumber":"4904",
    "addr:postcode":"60050",
    "addr:street":"W Elm St Mc Henry",
    "iso:country":"US",
    "sg:address":"4904 W Elm St",
    "sg:city":"Mc Henry",
    "sg:classifiers":[
        {
            "category":"Autos & Motor Vehicles",
            "subcategory":"Fuel & Gas Station",
            "type":"Retail Goods"
        }
    ],
    "sg:phone":"+1 815 344 5840",
    "sg:postcode":"60050",
    "sg:province":"IL",
    "sg:tags":[
        "automotive",
        "station",
        "gasoline",
        "oil"
    ],
    "wof:name":"Mc Henry Quick Oil Change",
    "wof:placetype":"venue"
},
  "geometry": {"coordinates":[-88.29338,42.349142],"type":"Point"}
}