{
  "type": "Feature",
  "properties": {
    "iso:country":"US",
    "sg:address":"4022 Harvard Ter",
    "sg:city":"Skokie",
    "sg:classifiers":[
        {
            "category":"Organizations",
            "subcategory":"Non-profit Organization",
            "type":"Services"
        }
    ],
    "sg:phone":"+1 847 677 2109",
    "sg:postcode":"60076",
    "sg:province":"IL",
    "wof:name":"Deen Intensive Inc",
    "wof:placetype":"venue"
},
  "geometry": {"coordinates":[-87.728478,42.021785],"type":"Point"}
}