{
  "type": "Feature",
  "properties": {
    "iso:country":"US",
    "sg:address":"1330 Holmes Rd",
    "sg:city":"Elgin",
    "sg:classifiers":[
        {
            "category":"Manufacturing",
            "subcategory":"Rubber & Plastics",
            "type":"Manufacturing & Wholesale Goods"
        }
    ],
    "sg:phone":"+1 630 883 0239",
    "sg:postcode":"60123",
    "sg:province":"IL",
    "sg:tags":[
        "plastics-vacuum",
        "coloring",
        "molding",
        "custom",
        "pressure",
        "forming-manufacturers",
        "injection",
        "finishing"
    ],
    "sg:website":"www.pd-inc.com",
    "wof:name":"Plastic Decorators",
    "wof:placetype":"venue"
},
  "geometry": {"coordinates":[-88.309853,42.068291],"type":"Point"}
}