{
  "type": "Feature",
  "properties": {
    "iso:country":"US",
    "sg:address":"1860 N Co Rd 760",
    "sg:city":"Nauvoo",
    "sg:classifiers":[
        {
            "category":"Shopping",
            "subcategory":"Florist",
            "type":"Retail Goods"
        }
    ],
    "sg:phone":"+1   ",
    "sg:postcode":"62354",
    "sg:province":"IL",
    "wof:name":"Hilltop Floral",
    "wof:placetype":"venue"
},
  "geometry": {"coordinates":[-91.357497,40.472192],"type":"Point"}
}