{
  "type": "Feature",
  "properties": {
    "addr:full":"245 Hidden Pond Ln Barrington IL 60010",
    "addr:housenumber":"245",
    "addr:postcode":"60010",
    "addr:street":"Hidden Pond Ln",
    "iso:country":"US",
    "sg:address":"245 Hidden Pond Ln",
    "sg:city":"Barrington",
    "sg:classifiers":[
        {
            "category":"Professional",
            "subcategory":"Management & Consulting",
            "type":"Services"
        }
    ],
    "sg:phone":"+1 847 571 1004",
    "sg:postcode":"60010",
    "sg:province":"IL",
    "wof:name":"New Paradigm Group",
    "wof:placetype":"venue"
},
  "geometry": {"coordinates":[-88.122321,42.211617],"type":"Point"}
}