{
  "type": "Feature",
  "properties": {
    "addr:full":"605 Washington St Prophetstown IL 61277",
    "addr:housenumber":"605",
    "addr:postcode":"61277",
    "addr:street":"Washington St",
    "iso:country":"US",
    "sg:address":"605 Washington St",
    "sg:city":"Prophetstown",
    "sg:classifiers":[
        {
            "category":"Professional",
            "subcategory":"Accounting & Tax Preparation",
            "type":"Services"
        }
    ],
    "sg:phone":"+1 815 537 2903",
    "sg:postcode":"61277",
    "sg:province":"IL",
    "wof:name":"Roman Bookkeeping",
    "wof:placetype":"venue"
},
  "geometry": {"coordinates":[-89.938756,41.667483],"type":"Point"}
}