{
  "type": "Feature",
  "properties": {
    "iso:country":"US",
    "sg:address":"563 Forest Ave",
    "sg:city":"River Forest",
    "sg:classifiers":[
        {
            "category":"Professional",
            "subcategory":"Management & Consulting",
            "type":"Services"
        }
    ],
    "sg:phone":"+1 708 415 0729",
    "sg:postcode":"60305",
    "sg:province":"IL",
    "sg:tags":[
        "employee",
        "consultant",
        "benefit"
    ],
    "wof:name":"Annese Piazza & Assoc",
    "wof:placetype":"venue"
},
  "geometry": {"coordinates":[-87.821695,41.890683],"type":"Point"}
}