{
  "type": "Feature",
  "properties": {
    "iso:country":"US",
    "sg:address":"1490 E Oakton St",
    "sg:city":"Des Plaines",
    "sg:classifiers":[
        {
            "category":"Autos & Motor Vehicles",
            "subcategory":"Fuel & Gas Station",
            "type":"Retail Goods"
        }
    ],
    "sg:phone":"+1   ",
    "sg:postcode":"60018",
    "sg:province":"IL",
    "sg:tags":[
        "station",
        "gasoline"
    ],
    "wof:name":"Citgo",
    "wof:placetype":"venue"
},
  "geometry": {"coordinates":[-87.88675499999999,42.024251],"type":"Point"}
}