{
  "type": "Feature",
  "properties": {
    "addr:full":"505 Arlington Heights Rd Arlington Heights IL 60005",
    "addr:housenumber":"505",
    "addr:postcode":"60005",
    "addr:street":"Arlington Heights Rd",
    "iso:country":"US",
    "sg:address":"505 Arlington Heights Rd",
    "sg:city":"Arlington Heights",
    "sg:classifiers":[
        {
            "category":"Professional",
            "subcategory":"Lawyer & Legal Services",
            "type":"Services"
        }
    ],
    "sg:phone":"+1 847 593 7200",
    "sg:postcode":"60005",
    "sg:province":"IL",
    "wof:name":"Terrence D Kane Attorney",
    "wof:placetype":"venue"
},
  "geometry": {"coordinates":[-87.98047200000001,42.073821],"type":"Point"}
}