{
  "type": "Feature",
  "properties": {
    "addr:full":"9126 N Lindbergh Dr Peoria IL 61615",
    "addr:housenumber":"9126",
    "addr:postcode":"61615",
    "addr:street":"N Lindbergh Dr",
    "iso:country":"US",
    "sg:address":"9126 N Lindbergh Dr",
    "sg:city":"Peoria",
    "sg:classifiers":[
        {
            "category":"Deli",
            "type":"Food & Drink"
        }
    ],
    "sg:menulink":"http://www.allmenus.com/il/peoria-city/99665-schlotzskys/menu/",
    "sg:phone":"+1 309 692 6544",
    "sg:postcode":"61615",
    "sg:province":"IL",
    "sg:tags":[
        "wrap",
        "american",
        "sandwich",
        "pizza"
    ],
    "wof:name":"Schlotzsky's",
    "wof:placetype":"venue"
},
  "geometry": {"coordinates":[-89.610311,40.798781],"type":"Point"}
}