{
  "type": "Feature",
  "properties": {
    "addr:full":"3927 N Central Park Ave Chicago IL 60618",
    "addr:housenumber":"3927",
    "addr:postcode":"60618",
    "addr:street":"N Central Park Ave",
    "iso:country":"US",
    "sg:address":"3927 N Central Park Ave",
    "sg:city":"Chicago",
    "sg:classifiers":[
        {
            "category":"Professional",
            "type":"Services"
        },
        {
            "category":"Professional",
            "subcategory":"Business Services",
            "type":"Services"
        }
    ],
    "sg:phone":"+1 773 313 1640",
    "sg:postcode":"60618",
    "sg:province":"IL",
    "sg:tags":[
        "packaging",
        "labeling"
    ],
    "wof:name":"Navis Logistics Network Inc.",
    "wof:placetype":"venue"
},
  "geometry": {"coordinates":[-87.717782,41.952803],"type":"Point"}
}