{
  "type": "Feature",
  "properties": {
    "addr:full":"840 W Sunnyside Ave Chicago IL 60640",
    "addr:housenumber":"840",
    "addr:postcode":"60640",
    "addr:street":"W Sunnyside Ave",
    "iso:country":"US",
    "sg:address":"840 W Sunnyside Ave",
    "sg:city":"Chicago",
    "sg:classifiers":[
        {
            "category":"Real Estate",
            "subcategory":"Real Estate Agent",
            "type":"Services"
        }
    ],
    "sg:phone":"+1 773 334 8155",
    "sg:postcode":"60640",
    "sg:province":"IL",
    "sg:tags":[
        "residential",
        "apartment"
    ],
    "wof:name":"840 West Sunnyside Apartment",
    "wof:placetype":"venue"
},
  "geometry": {"coordinates":[-87.652186,41.963565],"type":"Point"}
}