{
  "type": "Feature",
  "properties": {
    "iso:country":"US",
    "sg:address":"2400 W Diversey Ave",
    "sg:city":"Chicago",
    "sg:classifiers":[
        {
            "category":"Retail",
            "subcategory":"Repair Shop",
            "type":"Services"
        }
    ],
    "sg:phone":"+1 773 227 3337",
    "sg:postcode":"60647",
    "sg:province":"IL",
    "sg:tags":[
        "lock",
        "locksmith"
    ],
    "wof:name":"Always Available",
    "wof:placetype":"venue"
},
  "geometry": {"coordinates":[-87.689127,41.932157],"type":"Point"}
}