{
  "type": "Feature",
  "properties": {
    "iso:country":"US",
    "sg:address":"750 Almar Pkwy Ste 202",
    "sg:city":"Bourbonnais",
    "sg:classifiers":[
        {
            "category":"Professional",
            "subcategory":"Detective & Security Services",
            "type":"Services"
        }
    ],
    "sg:phone":"+1 815 933 5808",
    "sg:postcode":"60914",
    "sg:province":"IL",
    "sg:tags":[
        "information",
        "bureau"
    ],
    "wof:name":"Horizon Conseling Services",
    "wof:placetype":"venue"
},
  "geometry": {"coordinates":[-87.889105,41.163038],"type":"Point"}
}