{
  "type": "Feature",
  "properties": {
    "addr:full":"1806 E Northwest Hwy Arlington Heights IL 60004",
    "addr:housenumber":"1806",
    "addr:postcode":"60004",
    "addr:street":"E Northwest Hwy",
    "iso:country":"US",
    "sg:address":"1806 E Northwest Hwy",
    "sg:city":"Arlington Heights",
    "sg:classifiers":[
        {
            "category":"Insurance",
            "subcategory":"Insurance Agent",
            "type":"Services"
        }
    ],
    "sg:phone":"+1 847 394 3220",
    "sg:postcode":"60004",
    "sg:province":"IL",
    "wof:name":"AFLAC",
    "wof:placetype":"venue"
},
  "geometry": {"coordinates":[-87.960217,42.074047],"type":"Point"}
}