{
  "type": "Feature",
  "properties": {
    "addr:full":"36 S Wabash Avenue Suite 604 Chicago IL 60603",
    "addr:housenumber":"36",
    "addr:postcode":"60603",
    "addr:street":"S Wabash Avenue Suite 604",
    "iso:country":"US",
    "sg:address":"36 S Wabash Avenue Suite 604",
    "sg:city":"Chicago",
    "sg:classifiers":[
        {
            "category":"Shopping",
            "subcategory":"Florist",
            "type":"Retail Goods"
        }
    ],
    "sg:phone":"+1 312 855 0944",
    "sg:postcode":"60603",
    "sg:province":"IL",
    "wof:name":"Arts & Artisans Ltd",
    "wof:placetype":"venue"
},
  "geometry": {"coordinates":[-87.626167,41.881627],"type":"Point"}
}