{
  "type": "Feature",
  "properties": {
    "iso:country":"US",
    "sg:address":"8286 Kiowa Xing",
    "sg:city":"Roscoe",
    "sg:classifiers":[
        {
            "category":"Professional",
            "subcategory":"Management & Consulting",
            "type":"Services"
        }
    ],
    "sg:phone":"+1 815 389 9766",
    "sg:postcode":"61073",
    "sg:province":"IL",
    "sg:tags":[
        "business"
    ],
    "wof:name":"Celebrtons By Marshall Vicki L",
    "wof:placetype":"venue"
},
  "geometry": {"coordinates":[-88.95492400000001,42.446185],"type":"Point"}
}