{
  "type": "Feature",
  "properties": {
    "iso:country":"US",
    "sg:address":"140 E Vienna St",
    "sg:city":"Anna",
    "sg:classifiers":[
        {
            "category":"Restaurant",
            "type":"Food & Drink"
        }
    ],
    "sg:menulink":"http://www.allmenus.com/il/anna-district-5/154540-hardees/menu/",
    "sg:phone":"+1 618 833 3980",
    "sg:postcode":"62906",
    "sg:province":"IL",
    "sg:tags":[
        "burger",
        "american"
    ],
    "wof:name":"Hardee's",
    "wof:placetype":"venue"
},
  "geometry": {"coordinates":[-89.245351,37.459786],"type":"Point"}
}