{
  "type": "Feature",
  "properties": {
    "iso:country":"US",
    "sg:address":"361 W Chestnut Street",
    "sg:city":"Chicago",
    "sg:classifiers":[
        {
            "category":"Education",
            "subcategory":"Vocational School",
            "type":"Public Place"
        },
        {
            "category":"Education",
            "subcategory":"School",
            "type":"Public Place"
        }
    ],
    "sg:phone":"+1 312 944 0882",
    "sg:postcode":"60610",
    "sg:province":"IL",
    "sg:tags":[
        "cooking"
    ],
    "wof:name":"Cooking Hospitality Institute of Chgo",
    "wof:placetype":"venue"
},
  "geometry": {"coordinates":[-87.637486,41.898152],"type":"Point"}
}