{
  "type": "Feature",
  "properties": {
    "iso:country":"US",
    "sg:address":"200 Berteau Ave",
    "sg:city":"Elmhurst",
    "sg:classifiers":[
        {
            "category":"Health Services",
            "subcategory":"Doctor",
            "type":"Services"
        }
    ],
    "sg:phone":"+1 630 941 4564",
    "sg:postcode":"60126",
    "sg:province":"IL",
    "sg:tags":[
        "medical"
    ],
    "wof:name":"Associated Pathology Cons SC",
    "wof:placetype":"venue"
},
  "geometry": {"coordinates":[-87.929416,41.902134],"type":"Point"}
}