{
  "type": "Feature",
  "properties": {
    "iso:country":"US",
    "sg:address":"1027 Western Ave",
    "sg:city":"Henry",
    "sg:classifiers":[
        {
            "category":"Real Estate",
            "subcategory":"Real Estate Operator",
            "type":"Services"
        }
    ],
    "sg:phone":"+1 309 364 3478",
    "sg:postcode":"61537",
    "sg:province":"IL",
    "sg:tags":[
        "farm",
        "management",
        "property",
        "lessor"
    ],
    "wof:name":"Bogner Farm",
    "wof:placetype":"venue"
},
  "geometry": {"coordinates":[-89.367172,41.111462],"type":"Point"}
}