{
  "type": "Feature",
  "properties": {
    "iso:country":"US",
    "sg:address":"11 Pembrooke Rd",
    "sg:city":"Montgomery",
    "sg:classifiers":[
        {
            "category":"Organizations",
            "subcategory":"Religious Organization",
            "type":"Services"
        }
    ],
    "sg:phone":"+1 630 892 9309",
    "sg:postcode":"60538",
    "sg:province":"IL",
    "sg:tags":[
        "church",
        "day",
        "care",
        "child"
    ],
    "wof:name":"St Luke's Lutheran Church",
    "wof:placetype":"venue"
},
  "geometry": {"coordinates":[-88.335878,41.715728],"type":"Point"}
}