{
  "type": "Feature",
  "properties": {
    "iso:country":"US",
    "sg:address":"1712 Roosevelt Rd",
    "sg:city":"Machesney Park",
    "sg:classifiers":[
        {
            "category":"Social Services",
            "subcategory":"Child Care",
            "type":"Services"
        }
    ],
    "sg:phone":"+1 815 282 5091",
    "sg:postcode":"61115",
    "sg:province":"IL",
    "sg:tags":[
        "day"
    ],
    "wof:name":"Kathy Rush",
    "wof:placetype":"venue"
},
  "geometry": {"coordinates":[-89.029296,42.347402],"type":"Point"}
}