{
  "type": "Feature",
  "properties": {
    "iso:country":"US",
    "sg:address":"4930 Oakton St",
    "sg:city":"Skokie",
    "sg:classifiers":[
        {
            "category":"Banks & Credit Unions",
            "subcategory":"Investment Brokerage",
            "type":"Services"
        }
    ],
    "sg:phone":"+1 847 674 8565",
    "sg:postcode":"60077",
    "sg:province":"IL",
    "sg:tags":[
        "stock",
        "bond"
    ],
    "wof:name":"Edward Jones Co",
    "wof:placetype":"venue"
},
  "geometry": {"coordinates":[-87.7517,42.026364],"type":"Point"}
}