{
  "type": "Feature",
  "properties": {
    "iso:country":"US",
    "sg:address":"41380 N State Rte 83",
    "sg:city":"Antioch",
    "sg:classifiers":[
        {
            "category":"Building & Trades",
            "subcategory":"Construction",
            "type":"Services"
        }
    ],
    "sg:phone":"+1 847 395 5345",
    "sg:postcode":"60002",
    "sg:province":"IL",
    "sg:tags":[
        "balancing"
    ],
    "wof:name":"Industrial Diagnostics Spec",
    "wof:placetype":"venue"
},
  "geometry": {"coordinates":[-88.092184,42.464337],"type":"Point"}
}