{
  "type": "Feature",
  "properties": {
    "addr:full":"201 S College Ave Aledo IL 61231",
    "addr:housenumber":"201",
    "addr:postcode":"61231",
    "addr:street":"S College Ave",
    "iso:country":"US",
    "sg:address":"201 S College Ave",
    "sg:city":"Aledo",
    "sg:classifiers":[
        {
            "category":"Banks & Credit Unions",
            "subcategory":"Bank",
            "type":"Services"
        }
    ],
    "sg:phone":"+1 309 582 3150",
    "sg:postcode":"61231",
    "sg:province":"IL",
    "sg:website":"www.fsbwil.com",
    "wof:name":"Farmers State Bank",
    "wof:placetype":"venue"
},
  "geometry": {"coordinates":[-90.749239,41.20083],"type":"Point"}
}