{
  "type": "Feature",
  "properties": {
    "addr:full":"3483 S 6000W Rd Kankakee IL 60901",
    "addr:housenumber":"3483",
    "addr:postcode":"60901",
    "addr:street":"S 6000W Rd",
    "iso:country":"US",
    "sg:address":"3483 S 6000W Rd",
    "sg:city":"Kankakee",
    "sg:classifiers":[
        {
            "category":"Retail",
            "subcategory":"Auto Repair",
            "type":"Services"
        }
    ],
    "sg:phone":"+1 815 922 3480",
    "sg:postcode":"60901",
    "sg:province":"IL",
    "sg:tags":[
        "glass",
        "coating",
        "tinting"
    ],
    "wof:name":"A Shade Above",
    "wof:placetype":"venue"
},
  "geometry": {"coordinates":[-87.984111,41.067093],"type":"Point"}
}