{
  "type": "Feature",
  "properties": {
    "iso:country":"US",
    "sg:address":"1751 W Belmont Ave",
    "sg:city":"Chicago",
    "sg:classifiers":[
        {
            "category":"Manufacturing",
            "subcategory":"Printing",
            "type":"Manufacturing & Wholesale Goods"
        }
    ],
    "sg:phone":"+1 773 525 4126",
    "sg:postcode":"60657",
    "sg:province":"IL",
    "sg:tags":[
        "leather",
        "item",
        "bindery",
        "hotel",
        "co"
    ],
    "wof:name":"Monastery Hill Bindery",
    "wof:placetype":"venue"
},
  "geometry": {"coordinates":[-87.672036,41.93958],"type":"Point"}
}