{
  "type": "Feature",
  "properties": {
    "iso:country":"US",
    "sg:address":"109 W Pennsylvania Ave",
    "sg:city":"Urbana",
    "sg:phone":"+1 217 367 9663",
    "sg:postcode":"61801",
    "sg:province":"IL",
    "sg:tags":[
        "farm",
        "corn",
        "soybean"
    ],
    "wof:name":"Gordon Martin",
    "wof:placetype":"venue"
},
  "geometry": {"coordinates":[-88.209484,40.100631],"type":"Point"}
}