{
  "type": "Feature",
  "properties": {
    "iso:country":"US",
    "sg:address":"110 S Park St",
    "sg:city":"Wilmington",
    "sg:classifiers":[
        {
            "category":"Restaurant",
            "type":"Food & Drink"
        }
    ],
    "sg:phone":"+1 815 476 5417",
    "sg:postcode":"60481",
    "sg:province":"IL",
    "sg:tags":[
        "pizza"
    ],
    "wof:name":"Mama's Pizzeria",
    "wof:placetype":"venue"
},
  "geometry": {"coordinates":[-88.149872,41.304729],"type":"Point"}
}