{
  "type": "Feature",
  "properties": {
    "addr:full":"4315 Auburn St Rockford IL 61101",
    "addr:housenumber":"4315",
    "addr:postcode":"61101",
    "addr:street":"Auburn St",
    "iso:country":"US",
    "sg:address":"4315 Auburn St",
    "sg:city":"Rockford",
    "sg:classifiers":[
        {
            "category":"Food & Beverages",
            "subcategory":"Groceries & Convenience Stores",
            "type":"Retail Goods"
        }
    ],
    "sg:phone":"+1 815 965 3556",
    "sg:postcode":"61101",
    "sg:province":"IL",
    "wof:name":"Clark Gas",
    "wof:placetype":"venue"
},
  "geometry": {"coordinates":[-89.12679300000001,42.28832],"type":"Point"}
}