{
  "type": "Feature",
  "properties": {
    "iso:country":"US",
    "sg:address":"10714 S Roberts Rd",
    "sg:city":"Palos Hills",
    "sg:classifiers":[
        {
            "category":"Shopping",
            "subcategory":"Antiques",
            "type":"Retail Goods"
        }
    ],
    "sg:phone":"+1 708 974 2743",
    "sg:postcode":"60465",
    "sg:province":"IL",
    "wof:name":"Now and Again Resale",
    "wof:placetype":"venue"
},
  "geometry": {"coordinates":[-87.81710099999999,41.696499],"type":"Point"}
}