{
  "type": "Feature",
  "properties": {
    "iso:country":"US",
    "sg:address":"70 E 21st St",
    "sg:city":"Chicago",
    "sg:classifiers":[
        {
            "category":"Government",
            "subcategory":"Office",
            "type":"Public Place"
        }
    ],
    "sg:phone":"+1 312 793 7500",
    "sg:postcode":"60616",
    "sg:province":"IL",
    "sg:tags":[
        "government-state"
    ],
    "wof:name":"Public Aid Dept",
    "wof:placetype":"venue"
},
  "geometry": {"coordinates":[-87.62481099999999,41.85426],"type":"Point"}
}