{
  "type": "Feature",
  "properties": {
    "addr:full":"6420 N California Ave Chicago IL 60645",
    "addr:housenumber":"6420",
    "addr:postcode":"60645",
    "addr:street":"N California Ave",
    "iso:country":"US",
    "sg:address":"6420 N California Ave",
    "sg:city":"Chicago",
    "sg:classifiers":[
        {
            "category":"Health Services",
            "subcategory":"Doctor",
            "type":"Services"
        }
    ],
    "sg:phone":"+1 773 973 6100",
    "sg:postcode":"60645",
    "sg:province":"IL",
    "sg:tags":[
        "hospital",
        "medical"
    ],
    "wof:name":"California Devon Medical",
    "wof:placetype":"venue"
},
  "geometry": {"coordinates":[-87.6996,41.997799],"type":"Point"}
}