{
  "type": "Feature",
  "properties": {
    "iso:country":"US",
    "sg:address":"408 W 2nd St",
    "sg:city":"Centralia",
    "sg:classifiers":[
        {
            "category":"Health Services",
            "subcategory":"Doctor",
            "type":"Services"
        }
    ],
    "sg:phone":"+1 618 532 5531",
    "sg:postcode":"62801",
    "sg:province":"IL",
    "sg:tags":[
        "physician",
        "surgeon"
    ],
    "wof:name":"Klingele Terence G MD",
    "wof:placetype":"venue"
},
  "geometry": {"coordinates":[-89.141431,38.527641],"type":"Point"}
}