{
  "type": "Feature",
  "properties": {
    "iso:country":"US",
    "sg:address":"1001 E Main St",
    "sg:city":"Carbondale",
    "sg:classifiers":[
        {
            "category":"Insurance",
            "subcategory":"Insurance Agent",
            "type":"Services"
        }
    ],
    "sg:phone":"+1 618 549 2168",
    "sg:postcode":"62901",
    "sg:province":"IL",
    "wof:name":"Northwestern Mutual Financial",
    "wof:placetype":"venue"
},
  "geometry": {"coordinates":[-89.199483,37.728623],"type":"Point"}
}