{
  "type": "Feature",
  "properties": {
    "iso:country":"US",
    "sg:address":"348 W Smith Ave",
    "sg:city":"Bonfield",
    "sg:classifiers":[
        {
            "category":"Organizations",
            "subcategory":"Religious Organization",
            "type":"Services"
        }
    ],
    "sg:phone":"+1 815 932 7619",
    "sg:postcode":"60913",
    "sg:province":"IL",
    "sg:tags":[
        "church"
    ],
    "wof:name":"Bonfield Evangelical Methodist",
    "wof:placetype":"venue"
},
  "geometry": {"coordinates":[-88.06458499999999,41.146642],"type":"Point"}
}