{
  "type": "Feature",
  "properties": {
    "iso:country":"US",
    "sg:address":"640 Pearson St",
    "sg:city":"Des Plaines",
    "sg:classifiers":[
        {
            "category":"Health Services",
            "subcategory":"Health Practitioner",
            "type":"Services"
        }
    ],
    "sg:phone":"+1 847 803 6166",
    "sg:postcode":"60016",
    "sg:province":"IL",
    "sg:tags":[
        "psychologist"
    ],
    "wof:name":"Dunkelblau Ed & Assoc",
    "wof:placetype":"venue"
},
  "geometry": {"coordinates":[-87.884708,42.041868],"type":"Point"}
}