{
  "type": "Feature",
  "properties": {
    "addr:full":"1139 W Broadway Centralia IL 62801",
    "addr:housenumber":"1139",
    "addr:postcode":"62801",
    "addr:street":"W Broadway",
    "iso:country":"US",
    "sg:address":"1139 W Broadway",
    "sg:city":"Centralia",
    "sg:classifiers":[
        {
            "category":"Shopping",
            "subcategory":"Department Store",
            "type":"Retail Goods"
        },
        {
            "category":"Shopping",
            "subcategory":"Clothing, Apparel, & Fashions",
            "type":"Retail Goods"
        }
    ],
    "sg:phone":"+1 618 545 0148",
    "sg:postcode":"62801",
    "sg:province":"IL",
    "sg:tags":[
        "family"
    ],
    "wof:name":"Goodys Family Clothing Inc",
    "wof:placetype":"venue"
},
  "geometry": {"coordinates":[-89.148713,38.529595],"type":"Point"}
}