{
  "type": "Feature",
  "properties": {
    "iso:country":"US",
    "sg:address":"334 N Independence Blvd",
    "sg:city":"Romeoville",
    "sg:classifiers":[
        {
            "category":"Restaurant",
            "type":"Food & Drink"
        }
    ],
    "sg:phone":"+1 815 886 5200",
    "sg:postcode":"60446",
    "sg:province":"IL",
    "wof:name":"Ats-A-Nice Pizza",
    "wof:placetype":"venue"
},
  "geometry": {"coordinates":[-88.080552,41.645668],"type":"Point"}
}