{
  "type": "Feature",
  "properties": {
    "iso:country":"US",
    "sg:address":"1701 E College Ave",
    "sg:city":"Bloomington",
    "sg:classifiers":[
        {
            "category":"Insurance",
            "subcategory":"Hazard Insurance",
            "type":"Services"
        }
    ],
    "sg:phone":"+1 309 664 3038",
    "sg:postcode":"61704",
    "sg:province":"IL",
    "sg:tags":[
        "group"
    ],
    "wof:name":"Robert K Seidl Md",
    "wof:placetype":"venue"
},
  "geometry": {"coordinates":[-88.92783,40.510391],"type":"Point"}
}