{
  "type": "Feature",
  "properties": {
    "addr:full":"11220 S Eggleston Ave Chicago IL 60628",
    "addr:housenumber":"11220",
    "addr:postcode":"60628",
    "addr:street":"S Eggleston Ave",
    "iso:country":"US",
    "sg:address":"11220 S Eggleston Ave",
    "sg:city":"Chicago",
    "sg:classifiers":[
        {
            "category":"Manufacturing",
            "subcategory":"Chemicals & Compounds",
            "type":"Manufacturing & Wholesale Goods"
        }
    ],
    "sg:phone":"+1 773 821 5451",
    "sg:postcode":"60628",
    "sg:province":"IL",
    "wof:name":"Vidwan",
    "wof:placetype":"venue"
},
  "geometry": {"coordinates":[-87.633838,41.690266],"type":"Point"}
}