{
  "type": "Feature",
  "properties": {
    "iso:country":"US",
    "sg:address":"207 E Main St",
    "sg:city":"Salem",
    "sg:classifiers":[
        {
            "category":"Real Estate",
            "subcategory":"Real Estate Agent",
            "type":"Services"
        }
    ],
    "sg:phone":"+1 618 548 3300",
    "sg:postcode":"62881",
    "sg:province":"IL",
    "wof:name":"Neighbor 2 Neighbor Real Est",
    "wof:placetype":"venue"
},
  "geometry": {"coordinates":[-88.944579,38.627017],"type":"Point"}
}