{
  "type": "Feature",
  "properties": {
    "iso:country":"US",
    "sg:address":"733 W Madison St",
    "sg:city":"Chicago",
    "sg:classifiers":[
        {
            "category":"Restaurant",
            "type":"Food & Drink"
        }
    ],
    "sg:menulink":"http://www.allmenus.com/il/chicago/22443-dine/menu/",
    "sg:phone":"+1 312 602 2100",
    "sg:postcode":"60661",
    "sg:province":"IL",
    "sg:tags":[
        "american"
    ],
    "wof:name":"Dine",
    "wof:placetype":"venue"
},
  "geometry": {"coordinates":[-87.64490000000001,41.88181],"type":"Point"}
}