{
  "type": "Feature",
  "properties": {
    "iso:country":"US",
    "sg:address":"2020 N. Randall Rd",
    "sg:city":"Elgin",
    "sg:classifiers":[
        {
            "category":"Autos & Motor Vehicles",
            "subcategory":"Automobile Sales",
            "type":"Retail Goods"
        },
        {
            "category":"Autos & Motor Vehicles",
            "subcategory":"Auto Supplies",
            "type":"Retail Goods"
        },
        {
            "category":"Retail",
            "subcategory":"Auto Repair",
            "type":"Services"
        }
    ],
    "sg:phone":"+1 847 695 8000",
    "sg:postcode":"60124",
    "sg:province":"IL",
    "sg:tags":[
        "car",
        "part"
    ],
    "sg:website":"www.mcgrathhonda.com",
    "wof:name":"McGrath Honda",
    "wof:placetype":"venue"
},
  "geometry": {"coordinates":[-88.335668,42.075918],"type":"Point"}
}