{
  "type": "Feature",
  "properties": {
    "iso:country":"US",
    "sg:address":"1810 Garden St",
    "sg:city":"Belleville",
    "sg:classifiers":[
        {
            "category":"Health Services",
            "subcategory":"Health Practitioner",
            "type":"Services"
        }
    ],
    "sg:phone":"+1 618 236 2100",
    "sg:postcode":"62226",
    "sg:province":"IL",
    "wof:name":"Cermonies of Love",
    "wof:placetype":"venue"
},
  "geometry": {"coordinates":[-89.984536,38.535372],"type":"Point"}
}