{
  "type": "Feature",
  "properties": {
    "iso:country":"US",
    "sg:address":"2380 5th St",
    "sg:city":"Lincoln",
    "sg:classifiers":[
        {
            "category":"Retail",
            "subcategory":"Portrait Studio",
            "type":"Services"
        }
    ],
    "sg:phone":"+1 217 735 5332",
    "sg:postcode":"62656",
    "sg:province":"IL",
    "sg:tags":[
        "photo"
    ],
    "wof:name":"Picture Photography Inc",
    "wof:placetype":"venue"
},
  "geometry": {"coordinates":[-89.401505,40.146941],"type":"Point"}
}