{
  "type": "Feature",
  "properties": {
    "iso:country":"US",
    "sg:address":"102 W Rte 30",
    "sg:city":"Rock Falls",
    "sg:classifiers":[
        {
            "category":"Government",
            "subcategory":"Office",
            "type":"Public Place"
        }
    ],
    "sg:phone":"+1 815 625 3854",
    "sg:postcode":"61071",
    "sg:province":"IL",
    "wof:name":"Blackhawk Hills RC & D",
    "wof:placetype":"venue"
},
  "geometry": {"coordinates":[-89.689854,41.765644],"type":"Point"}
}