{
  "type": "Feature",
  "properties": {
    "addr:full":"415 N State Street Chicago IL 60610",
    "addr:housenumber":"415",
    "addr:postcode":"60610",
    "addr:street":"N State Street",
    "iso:country":"US",
    "sg:address":"415 N State Street",
    "sg:city":"Chicago",
    "sg:classifiers":[
        {
            "category":"Communications",
            "subcategory":"Newspaper",
            "type":"Services"
        }
    ],
    "sg:phone":"+1 312 644 7800",
    "sg:postcode":"60610",
    "sg:province":"IL",
    "sg:tags":[
        "print",
        "medium"
    ],
    "wof:name":"Chicago Banks",
    "wof:placetype":"venue"
},
  "geometry": {"coordinates":[-87.627972,41.889773],"type":"Point"}
}