{
  "type": "Feature",
  "properties": {
    "addr:full":"429 N Marion St Oak Park IL 60302",
    "addr:housenumber":"429",
    "addr:postcode":"60302",
    "addr:street":"N Marion St",
    "iso:country":"US",
    "sg:address":"429 N Marion St",
    "sg:city":"Oak Park",
    "sg:classifiers":[
        {
            "category":"Health Services",
            "subcategory":"Health Practitioner",
            "type":"Services"
        }
    ],
    "sg:phone":"+1 708 386 8822",
    "sg:postcode":"60302",
    "sg:province":"IL",
    "wof:name":"Synergy Health Systems",
    "wof:placetype":"venue"
},
  "geometry": {"coordinates":[-87.802887,41.893914],"type":"Point"}
}