{
  "type": "Feature",
  "properties": {
    "iso:country":"US",
    "sg:address":"2198 Gladstone Ct",
    "sg:city":"Glendale Heights",
    "sg:classifiers":[
        {
            "category":"Health Services",
            "subcategory":"Doctor",
            "type":"Services"
        }
    ],
    "sg:phone":"+1 630 980 5480",
    "sg:postcode":"60139",
    "sg:province":"IL",
    "wof:name":"Hines Dorothy DO",
    "wof:placetype":"venue"
},
  "geometry": {"coordinates":[-88.08509100000001,41.937678],"type":"Point"}
}