{
  "type": "Feature",
  "properties": {
    "iso:country":"US",
    "sg:address":"2603 N Rodgers Ave",
    "sg:city":"Alton",
    "sg:classifiers":[
        {
            "category":"Social Services",
            "type":"Services"
        }
    ],
    "sg:phone":"+1 618 465 6230",
    "sg:postcode":"62002",
    "sg:province":"IL",
    "wof:name":"Senior Services Plus Inc",
    "wof:placetype":"venue"
},
  "geometry": {"coordinates":[-90.137224,38.915728],"type":"Point"}
}