{
  "type": "Feature",
  "properties": {
    "iso:country":"US",
    "sg:address":"687 E Court St",
    "sg:city":"Kankakee",
    "sg:classifiers":[
        {
            "category":"Retail",
            "subcategory":"Laundry & Dry Cleaning",
            "type":"Services"
        }
    ],
    "sg:phone":"+1 815 939 4806",
    "sg:postcode":"60901",
    "sg:province":"IL",
    "sg:tags":[
        "cleaners"
    ],
    "wof:name":"Economy Cleaners",
    "wof:placetype":"venue"
},
  "geometry": {"coordinates":[-87.858109,41.119757],"type":"Point"}
}