{
  "type": "Feature",
  "properties": {
    "iso:country":"US",
    "sg:address":"6820 S Stony Island Ave",
    "sg:city":"Chicago",
    "sg:classifiers":[
        {
            "category":"Shopping",
            "subcategory":"Beauty & Cosmetics",
            "type":"Retail Goods"
        }
    ],
    "sg:phone":"+1 773 363 7890",
    "sg:postcode":"60649",
    "sg:province":"IL",
    "sg:tags":[
        "supply"
    ],
    "wof:name":"Cosmo Discount",
    "wof:placetype":"venue"
},
  "geometry": {"coordinates":[-87.586446,41.771126],"type":"Point"}
}