{
  "type": "Feature",
  "properties": {
    "iso:country":"US",
    "sg:address":"103 Diagonal St",
    "sg:city":"Elizabeth",
    "sg:classifiers":[
        {
            "category":"Autos & Motor Vehicles",
            "subcategory":"Fuel & Gas Station",
            "type":"Retail Goods"
        }
    ],
    "sg:phone":"+1 815 858 2536",
    "sg:postcode":"61028",
    "sg:province":"IL",
    "sg:tags":[
        "oil"
    ],
    "wof:name":"Little Keg",
    "wof:placetype":"venue"
},
  "geometry": {"coordinates":[-90.223524,42.318678],"type":"Point"}
}