{
  "type": "Feature",
  "properties": {
    "addr:full":"7334 S Racine Ave Chicago IL 60636",
    "addr:housenumber":"7334",
    "addr:postcode":"60636",
    "addr:street":"S Racine Ave",
    "iso:country":"US",
    "sg:address":"7334 S Racine Ave",
    "sg:city":"Chicago",
    "sg:classifiers":[
        {
            "category":"Place Of Worship",
            "subcategory":"Church",
            "type":"Public Place"
        },
        {
            "category":"Place Of Worship",
            "type":"Public Place"
        }
    ],
    "sg:phone":"+1 773 874 5817",
    "sg:postcode":"60636",
    "sg:province":"IL",
    "sg:tags":[
        "churches-apostolic",
        "churches-pentecostal-apostolic"
    ],
    "wof:name":"Holy Miracle House Of Prayer",
    "wof:placetype":"venue"
},
  "geometry": {"coordinates":[-87.653969,41.760355],"type":"Point"}
}