{
  "type": "Feature",
  "properties": {
    "addr:full":"5205 S Wood St Chicago IL 60609",
    "addr:housenumber":"5205",
    "addr:postcode":"60609",
    "addr:street":"S Wood St",
    "iso:country":"US",
    "sg:address":"5205 S Wood St",
    "sg:city":"Chicago",
    "sg:classifiers":[
        {
            "category":"Social Services",
            "subcategory":"Child Care",
            "type":"Services"
        }
    ],
    "sg:phone":"+1 773 778 3745",
    "sg:postcode":"60609",
    "sg:province":"IL",
    "sg:tags":[
        "nursery",
        "day"
    ],
    "wof:name":"Helper Mothers",
    "wof:placetype":"venue"
},
  "geometry": {"coordinates":[-87.669577,41.799376],"type":"Point"}
}