{
  "type": "Feature",
  "properties": {
    "iso:country":"US",
    "sg:address":"7000 Barrington Rd",
    "sg:city":"Hanover Park",
    "sg:classifiers":[
        {
            "category":"Retail",
            "subcategory":"Auto Repair",
            "type":"Services"
        }
    ],
    "sg:phone":"+1 630 837 3051",
    "sg:postcode":"60133",
    "sg:province":"IL",
    "sg:tags":[
        "glass",
        "coating",
        "tinting"
    ],
    "wof:name":"Carsmart",
    "wof:placetype":"venue"
},
  "geometry": {"coordinates":[-88.144932,41.995729],"type":"Point"}
}