{
  "type": "Feature",
  "properties": {
    "iso:country":"US",
    "sg:address":"2638 W Brooklyn Rd",
    "sg:city":"Compton",
    "sg:phone":"+1 815 497 3881",
    "sg:postcode":"61318",
    "sg:province":"IL",
    "sg:tags":[
        "farm",
        "grain",
        "cash"
    ],
    "wof:name":"Kent Carnahan",
    "wof:placetype":"venue"
},
  "geometry": {"coordinates":[-89.132971,41.693565],"type":"Point"}
}