{
  "type": "Feature",
  "properties": {
    "addr:full":"5 S Van Buren St East Dundee IL 60118",
    "addr:housenumber":"5",
    "addr:postcode":"60118",
    "addr:street":"S Van Buren St",
    "iso:country":"US",
    "sg:address":"5 S Van Buren St",
    "sg:city":"East Dundee",
    "sg:classifiers":[
        {
            "category":"Education",
            "subcategory":"School",
            "type":"Public Place"
        }
    ],
    "sg:phone":"+1 847 428 1010",
    "sg:postcode":"60118",
    "sg:province":"IL",
    "wof:name":"Immanuel Lutheran School",
    "wof:placetype":"venue"
},
  "geometry": {"coordinates":[-88.27302400000001,42.098647],"type":"Point"}
}