{
  "type": "Feature",
  "properties": {
    "addr:full":"807 Portsmouth Ave Westchester IL 60154",
    "addr:housenumber":"807",
    "addr:postcode":"60154",
    "addr:street":"Portsmouth Ave",
    "iso:country":"US",
    "sg:address":"807 Portsmouth Ave",
    "sg:city":"Westchester",
    "sg:classifiers":[
        {
            "category":"Travel",
            "subcategory":"Travel Agent",
            "type":"Entertainment"
        }
    ],
    "sg:phone":"+1 708 615 0843",
    "sg:postcode":"60154",
    "sg:province":"IL",
    "sg:tags":[
        "agency",
        "services-commercial"
    ],
    "wof:name":"Mimi Travels",
    "wof:placetype":"venue"
},
  "geometry": {"coordinates":[-87.87408499999999,41.868145],"type":"Point"}
}