{
  "type": "Feature",
  "properties": {
    "addr:full":"7515 Hoffman Rd Centralia IL 62801",
    "addr:housenumber":"7515",
    "addr:postcode":"62801",
    "addr:street":"Hoffman Rd",
    "iso:country":"US",
    "sg:address":"7515 Hoffman Rd",
    "sg:city":"Centralia",
    "sg:classifiers":[
        {
            "category":"Government",
            "subcategory":"Office",
            "type":"Public Place"
        }
    ],
    "sg:phone":"+1   ",
    "sg:postcode":"62801",
    "sg:province":"IL",
    "sg:tags":[
        "executive"
    ],
    "wof:name":"Lake Township",
    "wof:placetype":"venue"
},
  "geometry": {"coordinates":[-89.273449,38.52695],"type":"Point"}
}