{
  "type": "Feature",
  "properties": {
    "iso:country":"US",
    "sg:address":"5716 N. Kenmore Ave Ste 1005",
    "sg:city":"Chicago",
    "sg:classifiers":[
        {
            "category":"Professional",
            "subcategory":"Management & Consulting",
            "type":"Services"
        },
        {
            "category":"Social Services",
            "subcategory":"Job Training",
            "type":"Services"
        }
    ],
    "sg:phone":"+1 773 368 3575",
    "sg:postcode":"60660",
    "sg:province":"IL",
    "sg:tags":[
        "career",
        "counseling",
        "life",
        "coach"
    ],
    "sg:website":"www.niquenyafulbright.com/",
    "wof:name":"Niquenya D. Fulbright, Executive Life Coach",
    "wof:placetype":"venue"
},
  "geometry": {"coordinates":[-87.656676,41.986033],"type":"Point"}
}