{
  "type": "Feature",
  "properties": {
    "iso:country":"US",
    "sg:address":"3434 W Peterson Ave",
    "sg:city":"Chicago",
    "sg:classifiers":[
        {
            "category":"Health Services",
            "subcategory":"Doctor",
            "type":"Services"
        }
    ],
    "sg:phone":"+1 773 604 4619",
    "sg:postcode":"60659",
    "sg:province":"IL",
    "wof:name":"Shapiro Dr Morton A DDS",
    "wof:placetype":"venue"
},
  "geometry": {"coordinates":[-87.716346,41.99037],"type":"Point"}
}