{
  "type": "Feature",
  "properties": {
    "addr:full":"1214 Plainfield Rd Joliet IL 60435",
    "addr:housenumber":"1214",
    "addr:postcode":"60435",
    "addr:street":"Plainfield Rd",
    "iso:country":"US",
    "sg:address":"1214 Plainfield Rd",
    "sg:city":"Joliet",
    "sg:classifiers":[
        {
            "category":"Shopping",
            "type":"Retail Goods"
        }
    ],
    "sg:phone":"+1 815 744 2822",
    "sg:postcode":"60435",
    "sg:province":"IL",
    "sg:tags":[
        "monument"
    ],
    "wof:name":"Novielli Memorials",
    "wof:placetype":"venue"
},
  "geometry": {"coordinates":[-88.11296400000001,41.545926],"type":"Point"}
}