{
  "type": "Feature",
  "properties": {
    "addr:full":"423 S Dearborn St Chicago IL 60605",
    "addr:housenumber":"423",
    "addr:postcode":"60605",
    "addr:street":"S Dearborn St",
    "iso:country":"US",
    "sg:address":"423 S Dearborn St",
    "sg:city":"Chicago",
    "sg:classifiers":[
        {
            "category":"Insurance",
            "subcategory":"Hazard Insurance",
            "type":"Services"
        }
    ],
    "sg:phone":"+1 312 341 0123",
    "sg:postcode":"60605",
    "sg:province":"IL",
    "sg:website":"kimberlydanlow.com",
    "wof:name":"Kimberly Danlow - State Farm",
    "wof:placetype":"venue"
},
  "geometry": {"coordinates":[-87.629204,41.876161],"type":"Point"}
}