{
  "type": "Feature",
  "properties": {
    "iso:country":"US",
    "sg:address":"9049 Jefferson Rd",
    "sg:city":"Freeburg",
    "sg:classifiers":[
        {
            "category":"Farming",
            "subcategory":"Livestock Farm",
            "type":"Manufacturing & Wholesale Goods"
        }
    ],
    "sg:phone":"+1 618 566 4868",
    "sg:postcode":"62243",
    "sg:province":"IL",
    "sg:tags":[
        "beef",
        "feedlot",
        "cattle"
    ],
    "wof:name":"Dale Kinzel",
    "wof:placetype":"venue"
},
  "geometry": {"coordinates":[-89.842826,38.44623],"type":"Point"}
}