{
  "type": "Feature",
  "properties": {
    "iso:country":"US",
    "sg:address":"134 S Stough St",
    "sg:city":"Hinsdale",
    "sg:classifiers":[
        {
            "category":"Shopping",
            "subcategory":"Catalog Store",
            "type":"Retail Goods"
        }
    ],
    "sg:phone":"+1 630 654 0626",
    "sg:postcode":"60521",
    "sg:province":"IL",
    "sg:tags":[
        "mail",
        "order",
        "online"
    ],
    "wof:name":"Kowalczyk Sales Associaties Inc",
    "wof:placetype":"venue"
},
  "geometry": {"coordinates":[-87.945182,41.800105],"type":"Point"}
}