{
  "type": "Feature",
  "properties": {
    "addr:full":"8122 S Grant Hwy Marengo IL 60152",
    "addr:housenumber":"8122",
    "addr:postcode":"60152",
    "addr:street":"S Grant Hwy",
    "iso:country":"US",
    "sg:address":"8122 S Grant Hwy",
    "sg:city":"Marengo",
    "sg:classifiers":[
        {
            "category":"Retail",
            "subcategory":"Auto Repair",
            "type":"Services"
        }
    ],
    "sg:phone":"+1 815 923 4182",
    "sg:postcode":"60152",
    "sg:province":"IL",
    "sg:tags":[
        "transmission",
        "automotive",
        "general"
    ],
    "wof:name":"Remkes Garage LLC",
    "wof:placetype":"venue"
},
  "geometry": {"coordinates":[-88.55860300000001,42.21105],"type":"Point"}
}