{
  "type": "Feature",
  "properties": {
    "iso:country":"US",
    "sg:address":"2053 W Lawrence Ave",
    "sg:city":"Chicago",
    "sg:classifiers":[
        {
            "category":"Fast Food",
            "type":"Food & Drink"
        },
        {
            "category":"Restaurant",
            "type":"Food & Drink"
        }
    ],
    "sg:phone":"+1 773 275 1090",
    "sg:postcode":"60625",
    "sg:province":"IL",
    "sg:tags":[
        "burger",
        "hot",
        "american",
        "hamburger",
        "dog"
    ],
    "sg:website":"http://www.wendys.com",
    "wof:name":"Wendy's",
    "wof:placetype":"venue"
},
  "geometry": {"coordinates":[-87.68128400000001,41.96845],"type":"Point"}
}