{
  "type": "Feature",
  "properties": {
    "iso:country":"US",
    "sg:address":"613 E Green St",
    "sg:city":"Champaign",
    "sg:classifiers":[
        {
            "category":"Bars & Pubs",
            "type":"Food & Drink"
        }
    ],
    "sg:phone":"+1 217 328 5531",
    "sg:postcode":"61820",
    "sg:province":"IL",
    "sg:tags":[
        "drinking"
    ],
    "wof:name":"It's Brothers Bar & Grill",
    "wof:placetype":"venue"
},
  "geometry": {"coordinates":[-88.229797,40.1105],"type":"Point"}
}