{
  "type": "Feature",
  "properties": {
    "iso:country":"US",
    "sg:address":"411 Roxana Ave",
    "sg:city":"South Roxana",
    "sg:classifiers":[
        {
            "category":"Retail",
            "subcategory":"Car Wash",
            "type":"Services"
        }
    ],
    "sg:phone":"+1 618 254 2515",
    "sg:postcode":"62087",
    "sg:province":"IL",
    "sg:tags":[
        "automobile",
        "detail",
        "clean"
    ],
    "wof:name":"Auto Plus",
    "wof:placetype":"venue"
},
  "geometry": {"coordinates":[-90.064318,38.828216],"type":"Point"}
}