{
  "type": "Feature",
  "properties": {
    "iso:country":"US",
    "sg:address":"5815 W Madison St",
    "sg:city":"Chicago",
    "sg:classifiers":[
        {
            "category":"Fast Food",
            "type":"Food & Drink"
        },
        {
            "category":"Restaurant",
            "type":"Food & Drink"
        }
    ],
    "sg:phone":"+1 773 287 3663",
    "sg:postcode":"60644",
    "sg:province":"IL",
    "sg:tags":[
        "vegetarian"
    ],
    "sg:website":"www.ilovefoodgroup.com",
    "wof:name":"Quench",
    "wof:placetype":"venue"
},
  "geometry": {"coordinates":[-87.770391,41.879808],"type":"Point"}
}