{
  "type": "Feature",
  "properties": {
    "iso:country":"US",
    "sg:address":"730 Waukegan Rd",
    "sg:city":"Deerfield",
    "sg:classifiers":[
        {
            "category":"Home & Garden",
            "subcategory":"Building Materials",
            "type":"Retail Goods"
        }
    ],
    "sg:phone":"+1 847 945 9240",
    "sg:postcode":"60015",
    "sg:province":"IL",
    "sg:tags":[
        "door"
    ],
    "wof:name":"Deerfield Garage Door Svc Co",
    "wof:placetype":"venue"
},
  "geometry": {"coordinates":[-87.844158,42.164688],"type":"Point"}
}