{
  "type": "Feature",
  "properties": {
    "addr:full":"228 Foster Ave Rockford IL 61102",
    "addr:housenumber":"228",
    "addr:postcode":"61102",
    "addr:street":"Foster Ave",
    "iso:country":"US",
    "sg:address":"228 Foster Ave",
    "sg:city":"Rockford",
    "sg:classifiers":[
        {
            "category":"Professional",
            "subcategory":"Accounting & Tax Preparation",
            "type":"Services"
        }
    ],
    "sg:phone":"+1 815 964 8760",
    "sg:postcode":"61102",
    "sg:province":"IL",
    "sg:tags":[
        "return",
        "provides"
    ],
    "wof:name":"Acd Taxes & Services",
    "wof:placetype":"venue"
},
  "geometry": {"coordinates":[-89.12388799999999,42.275409],"type":"Point"}
}