{
  "type": "Feature",
  "properties": {
    "iso:country":"US",
    "sg:address":"403 E Morgan St",
    "sg:city":"Bunker Hill",
    "sg:classifiers":[
        {
            "category":"Organizations",
            "subcategory":"Religious Organization",
            "type":"Services"
        }
    ],
    "sg:phone":"+1 618 585 6601",
    "sg:postcode":"62014",
    "sg:province":"IL",
    "wof:name":"Saint Chads Anglican Church",
    "wof:placetype":"venue"
},
  "geometry": {"coordinates":[-89.949226,39.045767],"type":"Point"}
}