{
  "type": "Feature",
  "properties": {
    "addr:full":"10543 E Flagg Rd Rochelle IL 61068",
    "addr:housenumber":"10543",
    "addr:postcode":"61068",
    "addr:street":"E Flagg Rd",
    "iso:country":"US",
    "sg:address":"10543 E Flagg Rd",
    "sg:city":"Rochelle",
    "sg:classifiers":[
        {
            "category":"Professional",
            "subcategory":"Computer Services",
            "type":"Services"
        }
    ],
    "sg:phone":"+1 815 562 5300",
    "sg:postcode":"61068",
    "sg:province":"IL",
    "sg:tags":[
        "reseller"
    ],
    "wof:name":"Windcrest Corporation",
    "wof:placetype":"venue"
},
  "geometry": {"coordinates":[-89.133543,41.940337],"type":"Point"}
}