{
  "type": "Feature",
  "properties": {
    "iso:country":"US",
    "sg:address":"336 W Maple St",
    "sg:city":"New Lenox",
    "sg:classifiers":[
        {
            "category":"Food & Beverages",
            "subcategory":"Candy",
            "type":"Retail Goods"
        }
    ],
    "sg:phone":"+1 815 485 8633",
    "sg:postcode":"60451",
    "sg:province":"IL",
    "sg:tags":[
        "confectionery"
    ],
    "wof:name":"Simply Sweets",
    "wof:placetype":"venue"
},
  "geometry": {"coordinates":[-87.97343499999999,41.515462],"type":"Point"}
}