{
  "type": "Feature",
  "properties": {
    "iso:country":"US",
    "sg:address":"815 Monroe Ave",
    "sg:city":"Charleston",
    "sg:classifiers":[
        {
            "category":"Insurance",
            "subcategory":"Insurance Agent",
            "type":"Services"
        }
    ],
    "sg:phone":"+1 217 348 1102",
    "sg:postcode":"61920",
    "sg:province":"IL",
    "wof:name":"Terwilliger Insurance Agency",
    "wof:placetype":"venue"
},
  "geometry": {"coordinates":[-88.172858,39.495633],"type":"Point"}
}