{
  "type": "Feature",
  "properties": {
    "iso:country":"US",
    "sg:address":"2006 Round Barn Rd",
    "sg:city":"Champaign",
    "sg:classifiers":[
        {
            "category":"Sports & Exercise",
            "subcategory":"Gym",
            "type":"Entertainment"
        },
        {
            "category":"Health Services",
            "subcategory":"Health Practitioner",
            "type":"Services"
        }
    ],
    "sg:phone":"+1 217 378 4560",
    "sg:postcode":"61821",
    "sg:province":"IL",
    "sg:tags":[
        "therapy",
        "physical"
    ],
    "sg:website":"www.champfitness.com",
    "wof:name":"Champion Fitness & Physical Therapy",
    "wof:placetype":"venue"
},
  "geometry": {"coordinates":[-88.282115,40.11113],"type":"Point"}
}