{
  "type": "Feature",
  "properties": {
    "iso:country":"US",
    "sg:address":"1815 Victoria Ave",
    "sg:city":"Rockford",
    "sg:classifiers":[
        {
            "category":"Building & Trades",
            "subcategory":"Cleaning & Sanitation",
            "type":"Services"
        }
    ],
    "sg:phone":"+1 815 961 8815",
    "sg:postcode":"61102",
    "sg:province":"IL",
    "sg:tags":[
        "janitorial"
    ],
    "wof:name":"B & B Services",
    "wof:placetype":"venue"
},
  "geometry": {"coordinates":[-89.11731,42.253551],"type":"Point"}
}