{
  "type": "Feature",
  "properties": {
    "iso:country":"US",
    "sg:address":"230 W Monroe St Ste 1125",
    "sg:city":"Chicago",
    "sg:classifiers":[
        {
            "category":"Professional",
            "subcategory":"Lawyer & Legal Services",
            "type":"Services"
        }
    ],
    "sg:phone":"+1 312 541 9710",
    "sg:postcode":"60606",
    "sg:province":"IL",
    "wof:name":"Johnson Blumberg & Associates Llc",
    "wof:placetype":"venue"
},
  "geometry": {"coordinates":[-87.63425100000001,41.880781],"type":"Point"}
}