{
  "type": "Feature",
  "properties": {
    "iso:country":"US",
    "sg:address":"854 S Il Route 59",
    "sg:city":"Bartlett",
    "sg:classifiers":[
        {
            "category":"Restaurant",
            "type":"Food & Drink"
        }
    ],
    "sg:phone":"+1 630 830 7861",
    "sg:postcode":"60103",
    "sg:province":"IL",
    "sg:website":"www.wendys.com",
    "wof:name":"Wendy's Old Fashioned Hamburgers",
    "wof:placetype":"venue"
},
  "geometry": {"coordinates":[-88.20700100000001,41.971298],"type":"Point"}
}