{
  "type": "Feature",
  "properties": {
    "addr:full":"602 Hillview Ct West Chicago IL 60185",
    "addr:housenumber":"602",
    "addr:postcode":"60185",
    "addr:street":"Hillview Ct West",
    "iso:country":"US",
    "sg:address":"602 Hillview Ct",
    "sg:city":"West Chicago",
    "sg:classifiers":[
        {
            "category":"Building & Trades",
            "subcategory":"Cleaning & Sanitation",
            "type":"Services"
        },
        {
            "category":"Building & Trades",
            "subcategory":"Construction",
            "type":"Services"
        }
    ],
    "sg:phone":"+1 888 930 2532",
    "sg:postcode":"60185",
    "sg:province":"IL",
    "sg:tags":[
        "home",
        "window",
        "washing",
        "handyman"
    ],
    "sg:website":"www.paramounthomeservices.com/",
    "wof:name":"Paramount Home Services",
    "wof:placetype":"venue"
},
  "geometry": {"coordinates":[-88.19408300000001,41.880564],"type":"Point"}
}