{
  "type": "Feature",
  "properties": {
    "iso:country":"US",
    "sg:address":"3518 W Montrose Ave",
    "sg:city":"Chicago",
    "sg:classifiers":[
        {
            "category":"Food & Beverages",
            "subcategory":"Groceries & Convenience Stores",
            "type":"Retail Goods"
        }
    ],
    "sg:phone":"+1 773 588 0848",
    "sg:postcode":"60618",
    "sg:province":"IL",
    "wof:name":"Dona Mari's 2",
    "wof:placetype":"venue"
},
  "geometry": {"coordinates":[-87.716103,41.961102],"type":"Point"}
}