{
  "type": "Feature",
  "properties": {
    "addr:full":"1950 Somerset Ct Romeoville IL 60446",
    "addr:housenumber":"1950",
    "addr:postcode":"60446",
    "addr:street":"Somerset Ct",
    "iso:country":"US",
    "sg:address":"1950 Somerset Ct",
    "sg:city":"Romeoville",
    "sg:classifiers":[
        {
            "category":"Professional",
            "subcategory":"Management & Consulting",
            "type":"Services"
        }
    ],
    "sg:phone":"+1 312 890 3311",
    "sg:postcode":"60446",
    "sg:province":"IL",
    "sg:tags":[
        "benefit",
        "health"
    ],
    "wof:name":"Homebase Health Corporation",
    "wof:placetype":"venue"
},
  "geometry": {"coordinates":[-88.15569000000001,41.622442],"type":"Point"}
}