{
  "type": "Feature",
  "properties": {
    "addr:full":"22421 E 2nd St Dennison IL 62423",
    "addr:housenumber":"22421",
    "addr:postcode":"62423",
    "addr:street":"E 2Nd St",
    "iso:country":"US",
    "sg:address":"22421 E 2nd St",
    "sg:city":"Dennison",
    "sg:classifiers":[
        {
            "category":"Building & Trades",
            "subcategory":"Landscaping Services",
            "type":"Services"
        }
    ],
    "sg:phone":"+1 217 826 2193",
    "sg:postcode":"62423",
    "sg:province":"IL",
    "sg:tags":[
        "lawn"
    ],
    "wof:name":"Davis Landscaping",
    "wof:placetype":"venue"
},
  "geometry": {"coordinates":[-87.597703,39.459848],"type":"Point"}
}