{
  "type": "Feature",
  "properties": {
    "iso:country":"US",
    "sg:address":"5332 Williams Dr",
    "sg:city":"Roscoe",
    "sg:classifiers":[
        {
            "category":"Education",
            "subcategory":"Special Training",
            "type":"Public Place"
        }
    ],
    "sg:phone":"+1 815 623 9199",
    "sg:postcode":"61073",
    "sg:province":"IL",
    "sg:tags":[
        "tutoring"
    ],
    "wof:name":"Sylvan Learning Ctr",
    "wof:placetype":"venue"
},
  "geometry": {"coordinates":[-89.01333099999999,42.421097],"type":"Point"}
}