{
  "type": "Feature",
  "properties": {
    "iso:country":"US",
    "sg:address":"3111 Ron Dr",
    "sg:city":"Godfrey",
    "sg:classifiers":[
        {
            "category":"Personal",
            "subcategory":"Beauty Salon",
            "type":"Services"
        }
    ],
    "sg:phone":"+1 618 466 2104",
    "sg:postcode":"62035",
    "sg:province":"IL",
    "wof:name":"Bohart's Beauty Salon",
    "wof:placetype":"venue"
},
  "geometry": {"coordinates":[-90.252934,38.938484],"type":"Point"}
}