{
  "type": "Feature",
  "properties": {
    "addr:full":"840 N 11th Ave Canton IL 61520",
    "addr:housenumber":"840",
    "addr:postcode":"61520",
    "addr:street":"N 11Th Ave",
    "iso:country":"US",
    "sg:address":"840 N 11th Ave",
    "sg:city":"Canton",
    "sg:classifiers":[
        {
            "category":"Professional",
            "subcategory":"Accounting & Tax Preparation",
            "type":"Services"
        }
    ],
    "sg:phone":"+1 309 649 1708",
    "sg:postcode":"61520",
    "sg:province":"IL",
    "wof:name":"Pierce Tax Service",
    "wof:placetype":"venue"
},
  "geometry": {"coordinates":[-90.01901599999999,40.566238],"type":"Point"}
}