{
  "type": "Feature",
  "properties": {
    "addr:full":"13311 S Brandon Avenue Chicago IL 60633",
    "addr:housenumber":"13311",
    "addr:postcode":"60633",
    "addr:street":"S Brandon Avenue",
    "iso:country":"US",
    "sg:address":"13311 S Brandon Avenue",
    "sg:city":"Chicago",
    "sg:classifiers":[
        {
            "category":"Shopping",
            "subcategory":"Pets & Pet Supplies",
            "type":"Retail Goods"
        },
        {
            "category":"Retail",
            "subcategory":"Pet Boarding",
            "type":"Services"
        },
        {
            "category":"Retail",
            "subcategory":"Animal Services",
            "type":"Services"
        }
    ],
    "sg:phone":"+1 773 646 3774",
    "sg:postcode":"60633",
    "sg:province":"IL",
    "sg:tags":[
        "sitting",
        "boarding/pet",
        "grooming",
        "kennel",
        "store"
    ],
    "sg:website":"http://www.7seaspets.com",
    "wof:name":"7 Seas Pet Care Center",
    "wof:placetype":"venue"
},
  "geometry": {"coordinates":[-87.545762,41.653218],"type":"Point"}
}