{
  "type": "Feature",
  "properties": {
    "iso:country":"US",
    "sg:address":"7777 159th St",
    "sg:city":"Tinley Park",
    "sg:classifiers":[
        {
            "category":"Professional",
            "subcategory":"Lawyer & Legal Services",
            "type":"Services"
        }
    ],
    "sg:phone":"+1 708 226 1600",
    "sg:postcode":"60477",
    "sg:province":"IL",
    "sg:tags":[
        "attorney"
    ],
    "wof:name":"Cossidente & Salus LTD",
    "wof:placetype":"venue"
},
  "geometry": {"coordinates":[-87.807497,41.60199],"type":"Point"}
}