{
  "type": "Feature",
  "properties": {
    "iso:country":"US",
    "sg:address":"20502 N 1400th St",
    "sg:city":"Hidalgo",
    "sg:classifiers":[
        {
            "category":"Shopping",
            "type":"Retail Goods"
        }
    ],
    "sg:phone":"+1 618 793 2500",
    "sg:postcode":"62432",
    "sg:province":"IL",
    "sg:tags":[
        "art",
        "gallery",
        "dealer"
    ],
    "wof:name":"Crooked Creek Antler Art",
    "wof:placetype":"venue"
},
  "geometry": {"coordinates":[-88.11536099999999,39.15487],"type":"Point"}
}