{
  "type": "Feature",
  "properties": {
    "addr:full":"1185 E Main St Carbondale IL 62901",
    "addr:housenumber":"1185",
    "addr:postcode":"62901",
    "addr:street":"E Main St",
    "iso:country":"US",
    "sg:address":"1185 E Main St",
    "sg:city":"Carbondale",
    "sg:classifiers":[
        {
            "category":"Shopping",
            "subcategory":"Clothing, Apparel, & Fashions",
            "type":"Retail Goods"
        }
    ],
    "sg:phone":"+1   ",
    "sg:postcode":"62901",
    "sg:province":"IL",
    "sg:tags":[
        "athletic"
    ],
    "wof:name":"Hibbett Sports",
    "wof:placetype":"venue"
},
  "geometry": {"coordinates":[-89.193572,37.730324],"type":"Point"}
}