{
  "type": "Feature",
  "properties": {
    "iso:country":"US",
    "sg:address":"7011 Nathan Ln",
    "sg:city":"Carpentersville",
    "sg:classifiers":[
        {
            "category":"Utilities",
            "subcategory":"Telephone",
            "type":"Services"
        }
    ],
    "sg:phone":"+1 847 836 8695",
    "sg:postcode":"60110",
    "sg:province":"IL",
    "sg:tags":[
        "systems-wholesale",
        "equipment",
        "manufacturer"
    ],
    "wof:name":"Telco Systems",
    "wof:placetype":"venue"
},
  "geometry": {"coordinates":[-88.329641,42.121249],"type":"Point"}
}