{
  "type": "Feature",
  "properties": {
    "iso:country":"US",
    "sg:address":"303 E Fayette St",
    "sg:city":"Bunker Hill",
    "sg:classifiers":[
        {
            "category":"Organizations",
            "subcategory":"Professional Association",
            "type":"Services"
        }
    ],
    "sg:phone":"+1 618 585 4836",
    "sg:postcode":"62014",
    "sg:province":"IL",
    "wof:name":"Bunker Hill Lodge",
    "wof:placetype":"venue"
},
  "geometry": {"coordinates":[-89.949956,39.043927],"type":"Point"}
}