{
  "type": "Feature",
  "properties": {
    "addr:full":"6 N State St Freeburg IL 62243",
    "addr:housenumber":"6",
    "addr:postcode":"62243",
    "addr:street":"N State St",
    "iso:country":"US",
    "sg:address":"6 N State St",
    "sg:city":"Freeburg",
    "sg:classifiers":[
        {
            "category":"Transit Center",
            "subcategory":"Freight",
            "type":"Transportation"
        },
        {
            "category":"Freight",
            "type":"Transportation"
        }
    ],
    "sg:phone":"+1 618 539 9818",
    "sg:postcode":"62243",
    "sg:province":"IL",
    "sg:tags":[
        "local",
        "trucking-motor",
        "trucking"
    ],
    "wof:name":"Tony Bonn",
    "wof:placetype":"venue"
},
  "geometry": {"coordinates":[-89.90898199999999,38.42653],"type":"Point"}
}