{
  "type": "Feature",
  "properties": {
    "iso:country":"US",
    "sg:address":"15 Stites Ave",
    "sg:city":"Fairview Heights",
    "sg:classifiers":[
        {
            "category":"Professional",
            "subcategory":"Secretarial Services",
            "type":"Services"
        }
    ],
    "sg:phone":"+1 618 355 5719",
    "sg:postcode":"62208",
    "sg:province":"IL",
    "sg:tags":[
        "clerical"
    ],
    "wof:name":"Express Clerical Services",
    "wof:placetype":"venue"
},
  "geometry": {"coordinates":[-89.986189,38.582485],"type":"Point"}
}