{
  "type": "Feature",
  "properties": {
    "iso:country":"US",
    "sg:address":"111 W 1st St",
    "sg:city":"Kewanee",
    "sg:classifiers":[
        {
            "category":"Recreation",
            "type":"Entertainment"
        }
    ],
    "sg:phone":"+1 309 856 7100",
    "sg:postcode":"61443",
    "sg:province":"IL",
    "sg:tags":[
        "martial",
        "arts",
        "instruction"
    ],
    "wof:name":"Stoner's Martial Arts Academy",
    "wof:placetype":"venue"
},
  "geometry": {"coordinates":[-89.926263,41.243347],"type":"Point"}
}