{
  "type": "Feature",
  "properties": {
    "addr:full":"10915 Franklin Ave Franklin Park IL 60131",
    "addr:housenumber":"10915",
    "addr:postcode":"60131",
    "addr:street":"Franklin Ave",
    "iso:country":"US",
    "sg:address":"10915 Franklin Ave",
    "sg:city":"Franklin Park",
    "sg:classifiers":[
        {
            "category":"Manufacturing",
            "subcategory":"Paper Products",
            "type":"Manufacturing & Wholesale Goods"
        }
    ],
    "sg:phone":"+1 847 451 6390",
    "sg:postcode":"60131",
    "sg:province":"IL",
    "sg:tags":[
        "label"
    ],
    "wof:name":"Arcadia Press",
    "wof:placetype":"venue"
},
  "geometry": {"coordinates":[-87.902235,41.944096],"type":"Point"}
}