{
  "type": "Feature",
  "properties": {
    "addr:full":"764 Grandview Dr Crystal Lake IL 60014",
    "addr:housenumber":"764",
    "addr:postcode":"60014",
    "addr:street":"Grandview Dr",
    "iso:country":"US",
    "sg:address":"764 Grandview Dr",
    "sg:city":"Crystal Lake",
    "sg:classifiers":[
        {
            "category":"Personal",
            "subcategory":"Barber",
            "type":"Services"
        }
    ],
    "sg:phone":"+1 815 788 9419",
    "sg:postcode":"60014",
    "sg:province":"IL",
    "sg:tags":[
        "shop"
    ],
    "wof:name":"Cutting Edge Communications",
    "wof:placetype":"venue"
},
  "geometry": {"coordinates":[-88.29196899999999,42.234967],"type":"Point"}
}