{
  "type": "Feature",
  "properties": {
    "addr:full":"14499 Catlin Tilton Rd Danville IL 61834",
    "addr:housenumber":"14499",
    "addr:postcode":"61834",
    "addr:street":"Catlin Tilton Rd",
    "iso:country":"US",
    "sg:address":"14499 Catlin Tilton Rd",
    "sg:city":"Danville",
    "sg:classifiers":[
        {
            "category":"Building & Trades",
            "subcategory":"Construction",
            "type":"Services"
        }
    ],
    "sg:phone":"+1 217 446 2442",
    "sg:postcode":"61834",
    "sg:province":"IL",
    "sg:tags":[
        "general",
        "contractor"
    ],
    "wof:name":"Smoot Construction Co",
    "wof:placetype":"venue"
},
  "geometry": {"coordinates":[-87.667688,40.095093],"type":"Point"}
}