{
  "type": "Feature",
  "properties": {
    "addr:full":"2112 W Jefferson St Joliet IL 60435",
    "addr:housenumber":"2112",
    "addr:postcode":"60435",
    "addr:street":"W Jefferson St",
    "iso:country":"US",
    "sg:address":"2112 W Jefferson St",
    "sg:city":"Joliet",
    "sg:classifiers":[
        {
            "category":"Health Services",
            "subcategory":"Doctor",
            "type":"Services"
        }
    ],
    "sg:phone":"+1 815 725 4566",
    "sg:postcode":"60435",
    "sg:province":"IL",
    "sg:tags":[
        "physician",
        "surgeon"
    ],
    "wof:name":"George T Jones MD",
    "wof:placetype":"venue"
},
  "geometry": {"coordinates":[-88.135462,41.522279],"type":"Point"}
}