{
  "type": "Feature",
  "properties": {
    "addr:full":"413 River Grove Ln Vernon Hills IL 60061",
    "addr:housenumber":"413",
    "addr:postcode":"60061",
    "addr:street":"River Grove Ln",
    "iso:country":"US",
    "sg:address":"413 River Grove Ln",
    "sg:city":"Vernon Hills",
    "sg:classifiers":[
        {
            "category":"Professional",
            "subcategory":"Management & Consulting",
            "type":"Services"
        }
    ],
    "sg:phone":"+1 847 478 0975",
    "sg:postcode":"60061",
    "sg:province":"IL",
    "sg:tags":[
        "marketing",
        "consultant"
    ],
    "wof:name":"LLW Group",
    "wof:placetype":"venue"
},
  "geometry": {"coordinates":[-87.95476499999999,42.210586],"type":"Point"}
}