{
  "type": "Feature",
  "properties": {
    "iso:country":"US",
    "sg:address":"414 Leafland Ave",
    "sg:city":"Centralia",
    "sg:classifiers":[
        {
            "category":"Building & Trades",
            "subcategory":"Landscaping Services",
            "type":"Services"
        }
    ],
    "sg:phone":"+1 618 532 5447",
    "sg:postcode":"62801",
    "sg:province":"IL",
    "sg:tags":[
        "equipment",
        "removal",
        "snow",
        "supply"
    ],
    "wof:name":"Holthaus Tree Stump Removal",
    "wof:placetype":"venue"
},
  "geometry": {"coordinates":[-89.124431,38.522533],"type":"Point"}
}