{
  "type": "Feature",
  "properties": {
    "addr:full":"240 Saint Clair Sq Fairview Heights IL 62208",
    "addr:housenumber":"240",
    "addr:postcode":"62208",
    "addr:street":"Saint Clair Sq",
    "iso:country":"US",
    "sg:address":"240 Saint Clair Sq",
    "sg:city":"Fairview Heights",
    "sg:classifiers":[
        {
            "category":"Shopping",
            "subcategory":"Clothing, Apparel, & Fashions",
            "type":"Retail Goods"
        }
    ],
    "sg:phone":"+1 618 632 6653",
    "sg:postcode":"62208",
    "sg:province":"IL",
    "sg:tags":[
        "accessory",
        "clothing",
        "women's"
    ],
    "sg:website":"www.fredericks.com",
    "wof:name":"Frederick's of Hollywood",
    "wof:placetype":"venue"
},
  "geometry": {"coordinates":[-89.982399,38.593899],"type":"Point"}
}