{
  "type": "Feature",
  "properties": {
    "iso:country":"US",
    "sg:address":"5722 W Higgins Ave",
    "sg:city":"Chicago",
    "sg:classifiers":[
        {
            "category":"Bars & Pubs",
            "type":"Food & Drink"
        }
    ],
    "sg:phone":"+1 773 427 6635",
    "sg:postcode":"60630",
    "sg:province":"IL",
    "sg:website":"www.facebook.com/pages/Chicago-I...",
    "wof:name":"Bar 57 West",
    "wof:placetype":"venue"
},
  "geometry": {"coordinates":[-87.771433,41.971647],"type":"Point"}
}