{
  "type": "Feature",
  "properties": {
    "addr:full":"4017 W Lawrence Ave Chicago IL 60630",
    "addr:housenumber":"4017",
    "addr:postcode":"60630",
    "addr:street":"W Lawrence Ave",
    "iso:country":"US",
    "sg:address":"4017 W Lawrence Ave",
    "sg:city":"Chicago",
    "sg:classifiers":[
        {
            "category":"Banks & Credit Unions",
            "subcategory":"Bank",
            "type":"Services"
        }
    ],
    "sg:phone":"+1 773 685 6940",
    "sg:postcode":"60630",
    "sg:province":"IL",
    "sg:website":"www.53.com",
    "wof:name":"Fifth Third Bank",
    "wof:placetype":"venue"
},
  "geometry": {"coordinates":[-87.728781,41.968134],"type":"Point"}
}