{
  "type": "Feature",
  "properties": {
    "iso:country":"US",
    "sg:address":"2400 Big Timber Rd",
    "sg:city":"Elgin",
    "sg:classifiers":[
        {
            "category":"Professional",
            "subcategory":"Accounting & Tax Preparation",
            "type":"Services"
        }
    ],
    "sg:phone":"+1 630 264 3843",
    "sg:postcode":"60124",
    "sg:province":"IL",
    "sg:tags":[
        "bookkeeping"
    ],
    "wof:name":"Gleeson Sklar Sawyers & Cumpata LLP",
    "wof:placetype":"venue"
},
  "geometry": {"coordinates":[-88.33564,42.065029],"type":"Point"}
}