{
  "type": "Feature",
  "properties": {
    "addr:full":"125 Old Orchard Shopping Center Skokie IL 60077",
    "addr:housenumber":"125",
    "addr:postcode":"60077",
    "addr:street":"Old Orchard",
    "iso:country":"US",
    "sg:address":"125 Old Orchard Shopping Center",
    "sg:city":"Skokie",
    "sg:classifiers":[
        {
            "category":"Shopping",
            "subcategory":"Gifts & Souvenirs",
            "type":"Retail Goods"
        }
    ],
    "sg:phone":"+1 847 675 1120",
    "sg:postcode":"60077",
    "sg:province":"IL",
    "sg:tags":[
        "shop"
    ],
    "wof:name":"Crabtree & Evelyn",
    "wof:placetype":"venue"
},
  "geometry": {"coordinates":[-87.74803,42.061556],"type":"Point"}
}