{
  "type": "Feature",
  "properties": {
    "iso:country":"US",
    "sg:address":"914 Front St",
    "sg:city":"Mchenry",
    "sg:classifiers":[
        {
            "category":"Sports & Exercise",
            "subcategory":"Ice Rink",
            "type":"Entertainment"
        }
    ],
    "sg:phone":"+1 815 363 4386",
    "sg:postcode":"60050",
    "sg:province":"IL",
    "sg:tags":[
        "skating"
    ],
    "wof:name":"Just For Fun Again Roller Rink",
    "wof:placetype":"venue"
},
  "geometry": {"coordinates":[-88.27450899999999,42.341213],"type":"Point"}
}