{
  "type": "Feature",
  "properties": {
    "addr:full":"5316 George St Skokie IL 60077",
    "addr:housenumber":"5316",
    "addr:postcode":"60077",
    "addr:street":"George St",
    "iso:country":"US",
    "sg:address":"5316 George St",
    "sg:city":"Skokie",
    "sg:classifiers":[
        {
            "category":"Wholesale",
            "subcategory":"Sporting Goods",
            "type":"Manufacturing & Wholesale Goods"
        }
    ],
    "sg:phone":"+1 847 677 4653",
    "sg:postcode":"60077",
    "sg:province":"IL",
    "wof:name":"M JS Wholesale Golf Inc",
    "wof:placetype":"venue"
},
  "geometry": {"coordinates":[-87.76176,42.024043],"type":"Point"}
}