{
  "type": "Feature",
  "properties": {
    "iso:country":"US",
    "sg:address":"520 Bellarmine Dr W",
    "sg:city":"Joliet",
    "sg:classifiers":[
        {
            "category":"Real Estate",
            "subcategory":"Real Estate Agent",
            "type":"Services"
        }
    ],
    "sg:phone":"+1 815 729 2694",
    "sg:postcode":"60436",
    "sg:province":"IL",
    "wof:name":"Sansbrook Properties",
    "wof:placetype":"venue"
},
  "geometry": {"coordinates":[-88.128553,41.514119],"type":"Point"}
}