{
  "type": "Feature",
  "properties": {
    "iso:country":"US",
    "sg:address":"340 W 83rd St",
    "sg:city":"Chicago",
    "sg:classifiers":[
        {
            "category":"Building & Trades",
            "subcategory":"Locksmith",
            "type":"Services"
        }
    ],
    "sg:phone":"+1 773 896 9530",
    "sg:postcode":"60620",
    "sg:province":"IL",
    "sg:tags":[
        "key"
    ],
    "wof:name":"Always Available 24 Hour Emergency Locksmi",
    "wof:placetype":"venue"
},
  "geometry": {"coordinates":[-87.633002,41.743649],"type":"Point"}
}