{
  "type": "Feature",
  "properties": {
    "iso:country":"US",
    "sg:address":"20925 N Pheasant Trl",
    "sg:city":"Barrington",
    "sg:classifiers":[
        {
            "category":"Professional",
            "subcategory":"Business Services",
            "type":"Services"
        }
    ],
    "sg:phone":"+1 847 304 4069",
    "sg:postcode":"60010",
    "sg:province":"IL",
    "sg:tags":[
        "consulting",
        "management"
    ],
    "wof:name":"Barrington Group",
    "wof:placetype":"venue"
},
  "geometry": {"coordinates":[-88.089022,42.167812],"type":"Point"}
}