{
  "type": "Feature",
  "properties": {
    "iso:country":"US",
    "sg:address":"6718 S Ridgeland Avenue",
    "sg:city":"Chicago",
    "sg:classifiers":[
        {
            "category":"Building & Trades",
            "subcategory":"Pest Control",
            "type":"Services"
        }
    ],
    "sg:phone":"+1 773 255 4812",
    "sg:postcode":"60649",
    "sg:province":"IL",
    "wof:name":"R & B Pest Control",
    "wof:placetype":"venue"
},
  "geometry": {"coordinates":[-87.582763,41.772563],"type":"Point"}
}