{
  "type": "Feature",
  "properties": {
    "iso:country":"US",
    "sg:address":"326 E Walnut St",
    "sg:city":"Albion",
    "sg:classifiers":[
        {
            "category":"Autos & Motor Vehicles",
            "subcategory":"Automobile Sales",
            "type":"Retail Goods"
        }
    ],
    "sg:phone":"+1   ",
    "sg:postcode":"62806",
    "sg:province":"IL",
    "sg:tags":[
        "used"
    ],
    "wof:name":"Grimes Auto Sales",
    "wof:placetype":"venue"
},
  "geometry": {"coordinates":[-88.05194299999999,38.374074],"type":"Point"}
}