{
  "type": "Feature",
  "properties": {
    "iso:country":"US",
    "sg:address":"9314 Lawndale Ave",
    "sg:city":"Evanston",
    "sg:classifiers":[
        {
            "category":"Insurance",
            "subcategory":"Hazard Insurance",
            "type":"Services"
        }
    ],
    "sg:phone":"+1 847 983 4099",
    "sg:postcode":"60203",
    "sg:province":"IL",
    "sg:tags":[
        "commercial",
        "business"
    ],
    "wof:name":"Cagney Insurance Network Inc",
    "wof:placetype":"venue"
},
  "geometry": {"coordinates":[-87.720319,42.050145],"type":"Point"}
}