{
  "type": "Feature",
  "properties": {
    "iso:country":"US",
    "sg:address":"24735 W Eames St",
    "sg:city":"Channahon",
    "sg:classifiers":[
        {
            "category":"Social Services",
            "subcategory":"Child Care",
            "type":"Services"
        }
    ],
    "sg:phone":"+1 815 467 9890",
    "sg:postcode":"60410",
    "sg:province":"IL",
    "sg:tags":[
        "day"
    ],
    "wof:name":"Kiddie Kampus Learning Center",
    "wof:placetype":"venue"
},
  "geometry": {"coordinates":[-88.238139,41.420999],"type":"Point"}
}