{
  "type": "Feature",
  "properties": {
    "addr:full":"6647 N Greenview Chicago IL 60626",
    "addr:housenumber":"6647",
    "addr:postcode":"60626",
    "addr:street":"N",
    "iso:country":"US",
    "sg:address":"6647 N Greenview",
    "sg:city":"Chicago",
    "sg:classifiers":[
        {
            "category":"Professional",
            "subcategory":"Computer Services",
            "type":"Services"
        }
    ],
    "sg:phone":"+1 773 455 3338",
    "sg:postcode":"60626",
    "sg:province":"IL",
    "sg:tags":[
        "repair"
    ],
    "sg:website":"my-pcrepairman.com",
    "wof:name":"My-PC Repaiman",
    "wof:placetype":"venue"
},
  "geometry": {"coordinates":[-87.66758799999999,42.003041],"type":"Point"}
}