{
  "type": "Feature",
  "properties": {
    "iso:country":"US",
    "sg:address":"1539 Nelson Rd",
    "sg:city":"Dixon",
    "sg:phone":"+1 815 251 4726",
    "sg:postcode":"61021",
    "sg:province":"IL",
    "sg:tags":[
        "farm",
        "corn"
    ],
    "wof:name":"Richard Fluck",
    "wof:placetype":"venue"
},
  "geometry": {"coordinates":[-89.590011,41.808754],"type":"Point"}
}