{
  "type": "Feature",
  "properties": {
    "addr:full":"753 Metropolitan Ave Bolingbrook IL 60490",
    "addr:housenumber":"753",
    "addr:postcode":"60490",
    "addr:street":"Metropolitan Ave",
    "iso:country":"US",
    "sg:address":"753 Metropolitan Ave",
    "sg:city":"Bolingbrook",
    "sg:classifiers":[
        {
            "category":"Professional",
            "subcategory":"Management & Consulting",
            "type":"Services"
        }
    ],
    "sg:phone":"+1 630 378 5910",
    "sg:postcode":"60490",
    "sg:province":"IL",
    "sg:tags":[
        "construction"
    ],
    "wof:name":"Jen-One Co",
    "wof:placetype":"venue"
},
  "geometry": {"coordinates":[-88.144141,41.671967],"type":"Point"}
}