{
  "type": "Feature",
  "properties": {
    "iso:country":"US",
    "sg:address":"500 Rushing Dr",
    "sg:city":"Carterville",
    "sg:classifiers":[
        {
            "category":"Health Services",
            "subcategory":"Doctor",
            "type":"Services"
        }
    ],
    "sg:phone":"+1 618 998 8808",
    "sg:postcode":"62918",
    "sg:province":"IL",
    "sg:tags":[
        "physician",
        "surgeon"
    ],
    "wof:name":"Southern Illinois Ob-Gyn Assoc",
    "wof:placetype":"venue"
},
  "geometry": {"coordinates":[-89.02278699999999,37.747302],"type":"Point"}
}