{
  "type": "Feature",
  "properties": {
    "addr:full":"305 W Jackson St Ste 400 Carbondale IL 62901",
    "addr:housenumber":"305",
    "addr:postcode":"62901",
    "addr:street":"W Jackson St Ste 400",
    "iso:country":"US",
    "sg:address":"305 W Jackson St Ste 400",
    "sg:city":"Carbondale",
    "sg:classifiers":[
        {
            "category":"Health Services",
            "subcategory":"Doctor",
            "type":"Services"
        }
    ],
    "sg:phone":"+1 618 351 9300",
    "sg:postcode":"62901",
    "sg:province":"IL",
    "wof:name":"Stokes Institute of Urology",
    "wof:placetype":"venue"
},
  "geometry": {"coordinates":[-89.218768,37.727938],"type":"Point"}
}