{
  "type": "Feature",
  "properties": {
    "addr:full":"2722 Green Bay Rd Evanston IL 60201",
    "addr:housenumber":"2722",
    "addr:postcode":"60201",
    "addr:street":"Green Bay Rd",
    "iso:country":"US",
    "sg:address":"2722 Green Bay Rd",
    "sg:city":"Evanston",
    "sg:phone":"+1 847 475 2571",
    "sg:postcode":"60201",
    "sg:province":"IL",
    "sg:website":"http://www.officedepot.com",
    "wof:name":"Office Depot",
    "wof:placetype":"venue"
},
  "geometry": {"coordinates":[-87.701375,42.067424],"type":"Point"}
}