{
  "type": "Feature",
  "properties": {
    "addr:full":"980 N Michigan Avenue Chicago IL 60611",
    "addr:housenumber":"980",
    "addr:postcode":"60611",
    "addr:street":"N Michigan Avenue",
    "iso:country":"US",
    "sg:address":"980 N Michigan Avenue",
    "sg:city":"Chicago",
    "sg:classifiers":[
        {
            "category":"Arts & Performance",
            "subcategory":"Art Gallery",
            "type":"Entertainment"
        }
    ],
    "sg:phone":"+1 312 664 4860",
    "sg:postcode":"60611",
    "sg:province":"IL",
    "wof:name":"Solovy Stephen Fine Art",
    "wof:placetype":"venue"
},
  "geometry": {"coordinates":[-87.624269,41.900694],"type":"Point"}
}