{
  "type": "Feature",
  "properties": {
    "addr:full":"1130 Mount Vernon Ave Lake Forest IL 60045",
    "addr:housenumber":"1130",
    "addr:postcode":"60045",
    "addr:street":"Mount Vernon Ave",
    "iso:country":"US",
    "sg:address":"1130 Mount Vernon Ave",
    "sg:city":"Lake Forest",
    "sg:classifiers":[
        {
            "category":"Professional",
            "subcategory":"Management & Consulting",
            "type":"Services"
        }
    ],
    "sg:phone":"+1 847 234 6688",
    "sg:postcode":"60045",
    "sg:province":"IL",
    "sg:tags":[
        "public",
        "relations"
    ],
    "wof:name":"Stratco Inc",
    "wof:placetype":"venue"
},
  "geometry": {"coordinates":[-87.858136,42.218717],"type":"Point"}
}