{
  "type": "Feature",
  "properties": {
    "iso:country":"US",
    "sg:address":"2414 Brown Ave",
    "sg:city":"Evanston",
    "sg:classifiers":[
        {
            "category":"Professional",
            "type":"Services"
        }
    ],
    "sg:phone":"+1 847 475 7756",
    "sg:postcode":"60201",
    "sg:province":"IL",
    "sg:tags":[
        "publication",
        "editorial"
    ],
    "wof:name":"Downing Publishing",
    "wof:placetype":"venue"
},
  "geometry": {"coordinates":[-87.700374,42.061046],"type":"Point"}
}