{
  "type": "Feature",
  "properties": {
    "iso:country":"US",
    "sg:address":"5 Revere Dr",
    "sg:city":"Northbrook",
    "sg:classifiers":[
        {
            "category":"Insurance",
            "subcategory":"Hazard Insurance",
            "type":"Services"
        }
    ],
    "sg:phone":"+1 877 291 9549",
    "sg:postcode":"60062",
    "sg:province":"IL",
    "sg:website":"http://www.libsco.com/",
    "wof:name":"Lubin Bergman Organization Inc.",
    "wof:placetype":"venue"
},
  "geometry": {"coordinates":[-87.806378,42.152215],"type":"Point"}
}