{
  "type": "Feature",
  "properties": {
    "iso:country":"US",
    "sg:address":"1335 S Lowell Ave",
    "sg:city":"Springfield",
    "sg:classifiers":[
        {
            "category":"Personal",
            "subcategory":"Barber",
            "type":"Services"
        }
    ],
    "sg:phone":"+1 217 725 7647",
    "sg:postcode":"62704",
    "sg:province":"IL",
    "wof:name":"Lawn Barber Ltd",
    "wof:placetype":"venue"
},
  "geometry": {"coordinates":[-89.661384,39.786615],"type":"Point"}
}