{
  "type": "Feature",
  "properties": {
    "iso:country":"US",
    "sg:address":"5011 Fosterburg Rd",
    "sg:city":"Alton",
    "sg:phone":"+1 618 258 0362",
    "sg:postcode":"62002",
    "sg:province":"IL",
    "sg:tags":[
        "farm",
        "corn",
        "soybean"
    ],
    "wof:name":"Watsek John",
    "wof:placetype":"venue"
},
  "geometry": {"coordinates":[-90.074444,38.977237],"type":"Point"}
}