{
  "type": "Feature",
  "properties": {
    "iso:country":"US",
    "sg:address":"3200 Godfrey Rd",
    "sg:city":"Godfrey",
    "sg:classifiers":[
        {
            "category":"Building & Trades",
            "subcategory":"Pest Control",
            "type":"Services"
        }
    ],
    "sg:phone":"+1 618 466 4960",
    "sg:postcode":"62035",
    "sg:province":"IL",
    "sg:website":"http://www.bushtermiteandpestcontrol.com",
    "wof:name":"A1 Bush Termite & Pest Control",
    "wof:placetype":"venue"
},
  "geometry": {"coordinates":[-90.192268,38.93491],"type":"Point"}
}