{
  "type": "Feature",
  "properties": {
    "addr:full":"361 E Roosevelt Rd Glen Ellyn IL 60137",
    "addr:housenumber":"361",
    "addr:postcode":"60137",
    "addr:street":"E Roosevelt Rd",
    "iso:country":"US",
    "sg:address":"361 E Roosevelt Rd",
    "sg:city":"Glen Ellyn",
    "sg:classifiers":[
        {
            "category":"Recreation",
            "type":"Entertainment"
        }
    ],
    "sg:phone":"+1 630 858 4130",
    "sg:postcode":"60137",
    "sg:province":"IL",
    "wof:name":"Community Art Partners",
    "wof:placetype":"venue"
},
  "geometry": {"coordinates":[-88.074653,41.859201],"type":"Point"}
}