{
  "type": "Feature",
  "properties": {
    "iso:country":"US",
    "sg:address":"25041 W Pauline Dr",
    "sg:city":"Plainfield",
    "sg:classifiers":[
        {
            "category":"Real Estate",
            "subcategory":"Real Estate Services",
            "type":"Services"
        }
    ],
    "sg:phone":"+1 815 436 2129",
    "sg:postcode":"60586",
    "sg:province":"IL",
    "sg:tags":[
        "management"
    ],
    "wof:name":"Douglas Sandstrom",
    "wof:placetype":"venue"
},
  "geometry": {"coordinates":[-88.22542300000001,41.56551],"type":"Point"}
}