{
  "type": "Feature",
  "properties": {
    "iso:country":"US",
    "sg:address":"10275 W Higgins Rd",
    "sg:city":"Des Plaines",
    "sg:classifiers":[
        {
            "category":"Manufacturing",
            "subcategory":"Electronics",
            "type":"Manufacturing & Wholesale Goods"
        },
        {
            "category":"Manufacturing",
            "subcategory":"Tools & Machinery",
            "type":"Manufacturing & Wholesale Goods"
        }
    ],
    "sg:phone":"+1 847 390 5000",
    "sg:postcode":"60018",
    "sg:province":"IL",
    "sg:tags":[
        "transformer",
        "electric",
        "power",
        "mfg",
        "lamp",
        "electronic"
    ],
    "wof:name":"Advance Transformer Co",
    "wof:placetype":"venue"
},
  "geometry": {"coordinates":[-87.88408699999999,41.998028],"type":"Point"}
}