{
  "type": "Feature",
  "properties": {
    "iso:country":"US",
    "sg:address":"831 Maple Ave",
    "sg:city":"Homewood",
    "sg:classifiers":[
        {
            "category":"Professional",
            "subcategory":"Computer Services",
            "type":"Services"
        }
    ],
    "sg:phone":"+1 708 335 0944",
    "sg:postcode":"60430",
    "sg:province":"IL",
    "sg:tags":[
        "internet"
    ],
    "wof:name":"Aemser Computers",
    "wof:placetype":"venue"
},
  "geometry": {"coordinates":[-87.636471,41.567229],"type":"Point"}
}