{
  "type": "Feature",
  "properties": {
    "iso:country":"US",
    "sg:address":"4301 W 47th St",
    "sg:city":"Chicago",
    "sg:classifiers":[
        {
            "category":"Museum",
            "subcategory":"Zoo",
            "type":"Entertainment"
        }
    ],
    "sg:phone":"+1 773 376 0812",
    "sg:postcode":"60632",
    "sg:province":"IL",
    "sg:tags":[
        "preserve",
        "animals-circus"
    ],
    "wof:name":"Ed & Annette's Monkeys & More-Animal Shows",
    "wof:placetype":"venue"
},
  "geometry": {"coordinates":[-87.731109,41.807547],"type":"Point"}
}