{
  "type": "Feature",
  "properties": {
    "iso:country":"US",
    "sg:address":"5000 S Halsted St",
    "sg:city":"Chicago",
    "sg:classifiers":[
        {
            "category":"Health Services",
            "subcategory":"Dentist",
            "type":"Services"
        }
    ],
    "sg:phone":"+1 773 624 4330",
    "sg:postcode":"60609",
    "sg:province":"IL",
    "sg:tags":[
        "equipment",
        "dental",
        "supply"
    ],
    "wof:name":"Nevin Labs",
    "wof:placetype":"venue"
},
  "geometry": {"coordinates":[-87.645393,41.80341],"type":"Point"}
}