{
  "type": "Feature",
  "properties": {
    "iso:country":"US",
    "sg:address":"410 E Northwest Hwy",
    "sg:city":"Mount Prospect",
    "sg:classifiers":[
        {
            "category":"Insurance",
            "subcategory":"Insurance Agent",
            "type":"Services"
        }
    ],
    "sg:phone":"+1 847 394 0020",
    "sg:postcode":"60056",
    "sg:province":"IL",
    "sg:tags":[
        "agency"
    ],
    "wof:name":"Gierman and Associates Inc",
    "wof:placetype":"venue"
},
  "geometry": {"coordinates":[-87.92995999999999,42.06057],"type":"Point"}
}