{
  "type": "Feature",
  "properties": {
    "iso:country":"US",
    "sg:address":"4852 Arenzville Rd",
    "sg:city":"Beardstown",
    "sg:classifiers":[
        {
            "category":"Professional",
            "subcategory":"Management & Consulting",
            "type":"Services"
        }
    ],
    "sg:phone":"+1 217 997 2131",
    "sg:postcode":"62618",
    "sg:province":"IL",
    "sg:tags":[
        "farm"
    ],
    "wof:name":"Meyer, Wilburl",
    "wof:placetype":"venue"
},
  "geometry": {"coordinates":[-90.390335,39.946899],"type":"Point"}
}