{
  "type": "Feature",
  "properties": {
    "iso:country":"US",
    "sg:address":"10652 S Harlem",
    "sg:city":"Worth",
    "sg:classifiers":[
        {
            "category":"Fast Food",
            "type":"Food & Drink"
        }
    ],
    "sg:phone":"+1 708 361 6036",
    "sg:postcode":"60482",
    "sg:province":"IL",
    "wof:name":"Dabs",
    "wof:placetype":"venue"
},
  "geometry": {"coordinates":[-87.797848,41.697714],"type":"Point"}
}