{
  "type": "Feature",
  "properties": {
    "addr:full":"3708 Keith View Dr Rockford IL 61107",
    "addr:housenumber":"3708",
    "addr:postcode":"61107",
    "addr:street":"Keith View Dr",
    "iso:country":"US",
    "sg:address":"3708 Keith View Dr",
    "sg:city":"Rockford",
    "sg:classifiers":[
        {
            "category":"Building & Trades",
            "subcategory":"Equipment Rental",
            "type":"Services"
        }
    ],
    "sg:phone":"+1 815 227 9360",
    "sg:postcode":"61107",
    "sg:province":"IL",
    "sg:tags":[
        "television"
    ],
    "wof:name":"Telerent Leasing Corporation",
    "wof:placetype":"venue"
},
  "geometry": {"coordinates":[-89.03814199999999,42.268668],"type":"Point"}
}