{
  "type": "Feature",
  "properties": {
    "addr:full":"518 S Wille St Mount Prospect IL 60056",
    "addr:housenumber":"518",
    "addr:postcode":"60056",
    "addr:street":"S Wille St",
    "iso:country":"US",
    "sg:address":"518 S Wille St",
    "sg:city":"Mount Prospect",
    "sg:classifiers":[
        {
            "category":"Professional",
            "type":"Services"
        }
    ],
    "sg:phone":"+1 847 797 1380",
    "sg:postcode":"60056",
    "sg:province":"IL",
    "sg:tags":[
        "calligraphy"
    ],
    "wof:name":"Classic Calligraphy",
    "wof:placetype":"venue"
},
  "geometry": {"coordinates":[-87.938159,42.055968],"type":"Point"}
}