{
  "type": "Feature",
  "properties": {
    "addr:full":"1001 E Main St Carbondale IL 62901",
    "addr:housenumber":"1001",
    "addr:postcode":"62901",
    "addr:street":"E Main St",
    "iso:country":"US",
    "sg:address":"1001 E Main St",
    "sg:city":"Carbondale",
    "sg:classifiers":[
        {
            "category":"Insurance",
            "subcategory":"Insurance Agent",
            "type":"Services"
        }
    ],
    "sg:phone":"+1 618 529 1888",
    "sg:postcode":"62901",
    "sg:province":"IL",
    "wof:name":"Clemens & Assoc Insurance",
    "wof:placetype":"venue"
},
  "geometry": {"coordinates":[-89.199483,37.728623],"type":"Point"}
}