{
  "type": "Feature",
  "properties": {
    "addr:full":"8633 Summerset Dr Belvidere IL 61008",
    "addr:housenumber":"8633",
    "addr:postcode":"61008",
    "addr:street":"Summerset Dr",
    "iso:country":"US",
    "sg:address":"8633 Summerset Dr",
    "sg:city":"Belvidere",
    "sg:classifiers":[
        {
            "category":"Personal",
            "subcategory":"Beauty Salon",
            "type":"Services"
        }
    ],
    "sg:phone":"+1   ",
    "sg:postcode":"61008",
    "sg:province":"IL",
    "sg:tags":[
        "shop"
    ],
    "wof:name":"Illusions Hair Design",
    "wof:placetype":"venue"
},
  "geometry": {"coordinates":[-88.807367,42.279267],"type":"Point"}
}