{
  "type": "Feature",
  "properties": {
    "addr:full":"4908 Farwell Ave Skokie IL 60077",
    "addr:housenumber":"4908",
    "addr:postcode":"60077",
    "addr:street":"Farwell Ave",
    "iso:country":"US",
    "sg:address":"4908 Farwell Ave",
    "sg:city":"Skokie",
    "sg:classifiers":[
        {
            "category":"Building & Trades",
            "subcategory":"Construction",
            "type":"Services"
        }
    ],
    "sg:phone":"+1 847 674 3467",
    "sg:postcode":"60077",
    "sg:province":"IL",
    "sg:tags":[
        "resurfacing",
        "refinishing",
        "floor"
    ],
    "wof:name":"Artistic Remodeling Inc",
    "wof:placetype":"venue"
},
  "geometry": {"coordinates":[-87.75282900000001,42.005555],"type":"Point"}
}