{
  "type": "Feature",
  "properties": {
    "addr:full":"208 E Corning Ave Peotone IL 60468",
    "addr:housenumber":"208",
    "addr:postcode":"60468",
    "addr:street":"E Corning Ave",
    "iso:country":"US",
    "sg:address":"208 E Corning Ave",
    "sg:city":"Peotone",
    "sg:classifiers":[
        {
            "category":"Building & Trades",
            "subcategory":"Construction",
            "type":"Services"
        }
    ],
    "sg:phone":"+1 708 258 6858",
    "sg:postcode":"60468",
    "sg:province":"IL",
    "sg:tags":[
        "system",
        "specialty",
        "heating",
        "contractor",
        "air conditioning"
    ],
    "wof:name":"Peotone Hting-Plumbing-Cooling",
    "wof:placetype":"venue"
},
  "geometry": {"coordinates":[-87.790623,41.332091],"type":"Point"}
}