{
  "type": "Feature",
  "properties": {
    "iso:country":"US",
    "sg:address":"507 N Raddant Rd",
    "sg:city":"Batavia",
    "sg:classifiers":[
        {
            "category":"Manufacturing",
            "subcategory":"Furniture",
            "type":"Manufacturing & Wholesale Goods"
        }
    ],
    "sg:phone":"+1 630 761 0400",
    "sg:postcode":"60510",
    "sg:province":"IL",
    "sg:tags":[
        "mfg",
        "fixture",
        "rack",
        "store",
        "display"
    ],
    "sg:website":"www.randaldisplays.com",
    "wof:name":"Randal Wood Displays",
    "wof:placetype":"venue"
},
  "geometry": {"coordinates":[-88.29300499999999,41.860726],"type":"Point"}
}