{
  "type": "Feature",
  "properties": {
    "addr:full":"5948 N Sheridan Rd Chicago IL 60660",
    "addr:housenumber":"5948",
    "addr:postcode":"60660",
    "addr:street":"N Sheridan Rd",
    "iso:country":"US",
    "sg:address":"5948 N Sheridan Rd",
    "sg:city":"Chicago",
    "sg:classifiers":[
        {
            "category":"Organizations",
            "subcategory":"Religious Organization",
            "type":"Services"
        }
    ],
    "sg:phone":"+1 773 649 9892",
    "sg:postcode":"60660",
    "sg:province":"IL",
    "sg:tags":[
        "church"
    ],
    "wof:name":"Dharmadhatu Buddhist Ctr",
    "wof:placetype":"venue"
},
  "geometry": {"coordinates":[-87.655473,41.990501],"type":"Point"}
}