{
  "type": "Feature",
  "properties": {
    "addr:full":"230 W Broadway Centralia IL 62801",
    "addr:housenumber":"230",
    "addr:postcode":"62801",
    "addr:street":"W Broadway",
    "iso:country":"US",
    "sg:address":"230 W Broadway",
    "sg:city":"Centralia",
    "sg:classifiers":[
        {
            "category":"Retail",
            "subcategory":"Self-service Laundry",
            "type":"Services"
        }
    ],
    "sg:phone":"+1 618 532 5111",
    "sg:postcode":"62801",
    "sg:province":"IL",
    "sg:tags":[
        "coin"
    ],
    "wof:name":"Happy Hour Laundry",
    "wof:placetype":"venue"
},
  "geometry": {"coordinates":[-89.138341,38.528466],"type":"Point"}
}