{
  "type": "Feature",
  "properties": {
    "iso:country":"US",
    "sg:address":"2308 Main St",
    "sg:city":"Evanston",
    "sg:classifiers":[
        {
            "category":"Home & Garden",
            "subcategory":"Building Materials",
            "type":"Retail Goods"
        }
    ],
    "sg:phone":"+1 847 869 2111",
    "sg:postcode":"60202",
    "sg:province":"IL",
    "sg:tags":[
        "decorative",
        "plumbing",
        "hardware",
        "luxury",
        "ba"
    ],
    "wof:name":"Aquaworks",
    "wof:placetype":"venue"
},
  "geometry": {"coordinates":[-87.705657,42.033669],"type":"Point"}
}