{
  "type": "Feature",
  "properties": {
    "iso:country":"US",
    "sg:address":"975 N McLean Blvd",
    "sg:city":"Elgin",
    "sg:classifiers":[
        {
            "category":"Bars & Pubs",
            "type":"Food & Drink"
        },
        {
            "category":"Restaurant",
            "type":"Food & Drink"
        }
    ],
    "sg:phone":"+1 847 888 0094",
    "sg:postcode":"60123",
    "sg:province":"IL",
    "sg:tags":[
        "grill",
        "bar"
    ],
    "wof:name":"Hoopers Sports Bar & Grill Inc",
    "wof:placetype":"venue"
},
  "geometry": {"coordinates":[-88.314887,42.009462],"type":"Point"}
}