{
  "type": "Feature",
  "properties": {
    "addr:full":"3520 W Armitage Ave Chicago IL 60647",
    "addr:housenumber":"3520",
    "addr:postcode":"60647",
    "addr:street":"W Armitage Ave",
    "iso:country":"US",
    "sg:address":"3520 W Armitage Ave",
    "sg:city":"Chicago",
    "sg:classifiers":[
        {
            "category":"Personal",
            "subcategory":"Beauty Salon",
            "type":"Services"
        }
    ],
    "sg:phone":"+1 773 278 7619",
    "sg:postcode":"60647",
    "sg:province":"IL",
    "sg:tags":[
        "shop"
    ],
    "wof:name":"Ella Y El Hair Style Unisex",
    "wof:placetype":"venue"
},
  "geometry": {"coordinates":[-87.71442999999999,41.917387],"type":"Point"}
}