{
  "type": "Feature",
  "properties": {
    "addr:full":"505 S Quentin Rd Palatine IL 60067",
    "addr:housenumber":"505",
    "addr:postcode":"60067",
    "addr:street":"S Quentin Rd",
    "iso:country":"US",
    "sg:address":"505 S Quentin Rd",
    "sg:city":"Palatine",
    "sg:classifiers":[
        {
            "category":"Professional",
            "subcategory":"Engineering",
            "type":"Services"
        },
        {
            "category":"Wholesale",
            "subcategory":"Construction Materials",
            "type":"Manufacturing & Wholesale Goods"
        }
    ],
    "sg:phone":"+1 847 991 7360",
    "sg:postcode":"60067",
    "sg:province":"IL",
    "sg:tags":[
        "passenger-commercial",
        "industrial",
        "elevators-freight",
        "elevator"
    ],
    "wof:name":"Ptsc Elevator Line",
    "wof:placetype":"venue"
},
  "geometry": {"coordinates":[-88.063087,42.101398],"type":"Point"}
}