{
  "type": "Feature",
  "properties": {
    "iso:country":"US",
    "sg:address":"116 Wedgewood Dr",
    "sg:city":"Barrington",
    "sg:classifiers":[
        {
            "category":"Banks & Credit Unions",
            "subcategory":"Financial Services",
            "type":"Services"
        }
    ],
    "sg:phone":"+1 847 381 6947",
    "sg:postcode":"60010",
    "sg:province":"IL",
    "sg:tags":[
        "card-merchant",
        "card"
    ],
    "wof:name":"Las Merchant Services",
    "wof:placetype":"venue"
},
  "geometry": {"coordinates":[-88.084327,42.152022],"type":"Point"}
}