{
  "type": "Feature",
  "properties": {
    "addr:full":"2626 Flossmoor Rd Flossmoor IL 60422",
    "addr:housenumber":"2626",
    "addr:postcode":"60422",
    "addr:street":"Flossmoor Rd",
    "iso:country":"US",
    "sg:address":"2626 Flossmoor Rd",
    "sg:city":"Flossmoor",
    "sg:classifiers":[
        {
            "category":"Real Estate",
            "subcategory":"Real Estate Agent",
            "type":"Services"
        }
    ],
    "sg:phone":"+1 708 922 0120",
    "sg:postcode":"60422",
    "sg:province":"IL",
    "wof:name":"Gordon E Grober & Associates",
    "wof:placetype":"venue"
},
  "geometry": {"coordinates":[-87.68128900000001,41.542521],"type":"Point"}
}