{
  "type": "Feature",
  "properties": {
    "iso:country":"US",
    "sg:address":"22462 Henning Rd",
    "sg:city":"Danville",
    "sg:classifiers":[
        {
            "category":"Education",
            "subcategory":"Dance Studio",
            "type":"Public Place"
        }
    ],
    "sg:phone":"+1 217 443 8373",
    "sg:postcode":"61834",
    "sg:province":"IL",
    "wof:name":"Laurel School Of Dance",
    "wof:placetype":"venue"
},
  "geometry": {"coordinates":[-87.69747,40.19376],"type":"Point"}
}