{
  "type": "Feature",
  "properties": {
    "addr:full":"1734 W. 119th Street Chicago IL 60643",
    "addr:housenumber":"1734",
    "addr:postcode":"60643",
    "addr:street":"W. 119Th Street",
    "iso:country":"US",
    "sg:address":"1734 W. 119th Street",
    "sg:city":"Chicago",
    "sg:classifiers":[
        {
            "category":"Fast Food",
            "type":"Food & Drink"
        },
        {
            "category":"Food & Beverages",
            "subcategory":"Specialty",
            "type":"Retail Goods"
        }
    ],
    "sg:phone":"+1 773 821 1100",
    "sg:postcode":"60643",
    "sg:province":"IL",
    "sg:tags":[
        "chicken",
        "wing"
    ],
    "wof:name":"Harold's Chicken",
    "wof:placetype":"venue"
},
  "geometry": {"coordinates":[-87.664559,41.677482],"type":"Point"}
}