{
  "type": "Feature",
  "properties": {
    "addr:full":"110 Villa St Elgin IL 60120",
    "addr:housenumber":"110",
    "addr:postcode":"60120",
    "addr:street":"Villa St",
    "iso:country":"US",
    "sg:address":"110 Villa St",
    "sg:city":"Elgin",
    "sg:classifiers":[
        {
            "category":"Retail",
            "subcategory":"Auto Repair",
            "type":"Services"
        }
    ],
    "sg:phone":"+1 847 697 1950",
    "sg:postcode":"60120",
    "sg:province":"IL",
    "sg:tags":[
        "repairing",
        "automobile",
        "general"
    ],
    "wof:name":"Alfredo's Auto Repair",
    "wof:placetype":"venue"
},
  "geometry": {"coordinates":[-88.27980599999999,42.034973],"type":"Point"}
}