{
  "type": "Feature",
  "properties": {
    "addr:full":"15026 Prairie Ave Rockton IL 61072",
    "addr:housenumber":"15026",
    "addr:postcode":"61072",
    "addr:street":"Prairie Ave",
    "iso:country":"US",
    "sg:address":"15026 Prairie Ave",
    "sg:city":"Rockton",
    "sg:classifiers":[
        {
            "category":"Retail",
            "subcategory":"Repair Shop",
            "type":"Services"
        }
    ],
    "sg:phone":"+1 815 624 6604",
    "sg:postcode":"61072",
    "sg:province":"IL",
    "wof:name":"Kkk Industries",
    "wof:placetype":"venue"
},
  "geometry": {"coordinates":[-89.098934,42.48607],"type":"Point"}
}