{
  "type": "Feature",
  "properties": {
    "addr:full":"9110 N State Route 159 Bunker Hill IL 62014",
    "addr:housenumber":"9110",
    "addr:postcode":"62014",
    "addr:street":"N State Route 159",
    "iso:country":"US",
    "sg:address":"9110 N State Route 159",
    "sg:city":"Bunker Hill",
    "sg:classifiers":[
        {
            "category":"Home & Garden",
            "subcategory":"Garden Supply",
            "type":"Retail Goods"
        }
    ],
    "sg:phone":"+1 618 585 3414",
    "sg:postcode":"62014",
    "sg:province":"IL",
    "sg:tags":[
        "nursery",
        "gardening"
    ],
    "wof:name":"Waldbart & Sons Nursery",
    "wof:placetype":"venue"
},
  "geometry": {"coordinates":[-89.95230100000001,39.0429],"type":"Point"}
}