{
  "type": "Feature",
  "properties": {
    "addr:full":"214 S Hickory St Shannon IL 61078",
    "addr:housenumber":"214",
    "addr:postcode":"61078",
    "addr:street":"S Hickory St",
    "iso:country":"US",
    "sg:address":"214 S Hickory St",
    "sg:city":"Shannon",
    "sg:classifiers":[
        {
            "category":"Wholesale",
            "subcategory":"Machinery & Supplies",
            "type":"Manufacturing & Wholesale Goods"
        }
    ],
    "sg:phone":"+1 815 864 2826",
    "sg:postcode":"61078",
    "sg:province":"IL",
    "sg:tags":[
        "equipment"
    ],
    "wof:name":"Cherry Grove Shannon Township",
    "wof:placetype":"venue"
},
  "geometry": {"coordinates":[-89.73956200000001,42.152475],"type":"Point"}
}