{
  "type": "Feature",
  "properties": {
    "iso:country":"US",
    "sg:address":"10904 S Natchez Ave",
    "sg:city":"Worth",
    "sg:classifiers":[
        {
            "category":"Real Estate",
            "subcategory":"Real Estate Agent",
            "type":"Services"
        }
    ],
    "sg:phone":"+1 708 361 3821",
    "sg:postcode":"60482",
    "sg:province":"IL",
    "wof:name":"E&B Certified Appraisals",
    "wof:placetype":"venue"
},
  "geometry": {"coordinates":[-87.781313,41.690408],"type":"Point"}
}