{
  "type": "Feature",
  "properties": {
    "iso:country":"US",
    "sg:address":"1369 S 3000E Rd",
    "sg:city":"Kankakee",
    "sg:phone":"+1 815 937 1808",
    "sg:postcode":"60901",
    "sg:province":"IL",
    "sg:tags":[
        "farm",
        "corn",
        "soybean"
    ],
    "wof:name":"Charles Yohnka",
    "wof:placetype":"venue"
},
  "geometry": {"coordinates":[-87.811576,41.101054],"type":"Point"}
}