{
  "type": "Feature",
  "properties": {
    "iso:country":"US",
    "sg:address":"420 Crossing Dr",
    "sg:city":"Sherman",
    "sg:classifiers":[
        {
            "category":"Fast Food",
            "type":"Food & Drink"
        },
        {
            "category":"Restaurant",
            "type":"Food & Drink"
        },
        {
            "category":"Food & Beverages",
            "subcategory":"Groceries & Convenience Stores",
            "type":"Retail Goods"
        }
    ],
    "sg:phone":"+1 217 496 2929",
    "sg:postcode":"62684",
    "sg:province":"IL",
    "sg:tags":[
        "shop",
        "american",
        "sandwich",
        "take"
    ],
    "sg:website":"http://www.subway.com",
    "wof:name":"Subway",
    "wof:placetype":"venue"
},
  "geometry": {"coordinates":[-89.60525699999999,39.892093],"type":"Point"}
}