{
  "type": "Feature",
  "properties": {
    "addr:full":"1190 S Wolf Rd Des Plaines IL 60016",
    "addr:housenumber":"1190",
    "addr:postcode":"60016",
    "addr:street":"S Wolf Rd Des",
    "iso:country":"US",
    "sg:address":"1190 S Wolf Rd",
    "sg:city":"Des Plaines",
    "sg:classifiers":[
        {
            "category":"Retail",
            "subcategory":"Auto Repair",
            "type":"Services"
        }
    ],
    "sg:phone":"+1 847 824 1190",
    "sg:postcode":"60016",
    "sg:province":"IL",
    "sg:tags":[
        "general"
    ],
    "wof:name":"M & B Automotive Inc",
    "wof:placetype":"venue"
},
  "geometry": {"coordinates":[-87.909086,42.030934],"type":"Point"}
}