{
  "type": "Feature",
  "properties": {
    "addr:full":"102 Wilmot Rd Deerfield IL 60015",
    "addr:housenumber":"102",
    "addr:postcode":"60015",
    "addr:street":"Wilmot Rd",
    "iso:country":"US",
    "sg:address":"102 Wilmot Rd",
    "sg:city":"Deerfield",
    "sg:classifiers":[
        {
            "category":"Professional",
            "subcategory":"Management & Consulting",
            "type":"Services"
        }
    ],
    "sg:phone":"+1 847 405 9600",
    "sg:postcode":"60015",
    "sg:province":"IL",
    "sg:tags":[
        "engineering",
        "business"
    ],
    "wof:name":"Cape Environmental Management",
    "wof:placetype":"venue"
},
  "geometry": {"coordinates":[-87.86744400000001,42.15653],"type":"Point"}
}