{
  "type": "Feature",
  "properties": {
    "iso:country":"US",
    "sg:address":"8509 E Prairie Rd",
    "sg:city":"Skokie",
    "sg:classifiers":[
        {
            "category":"Professional",
            "subcategory":"Business Services",
            "type":"Services"
        }
    ],
    "sg:phone":"+1 847 675 5112",
    "sg:postcode":"60076",
    "sg:province":"IL",
    "sg:tags":[
        "machine",
        "tool",
        "mfg"
    ],
    "wof:name":"A J Carbide Grinding",
    "wof:placetype":"venue"
},
  "geometry": {"coordinates":[-87.72257500000001,42.035972],"type":"Point"}
}