{
  "type": "Feature",
  "properties": {
    "iso:country":"US",
    "sg:address":"15748 Page Ave",
    "sg:city":"Harvey",
    "sg:classifiers":[
        {
            "category":"Education",
            "subcategory":"School",
            "type":"Public Place"
        }
    ],
    "sg:phone":"+1 708 333 0740",
    "sg:postcode":"60426",
    "sg:province":"IL",
    "sg:tags":[
        "high",
        "middle",
        "elementary"
    ],
    "wof:name":"Maya Angelou School",
    "wof:placetype":"venue"
},
  "geometry": {"coordinates":[-87.659599,41.604],"type":"Point"}
}