{
  "type": "Feature",
  "properties": {
    "iso:country":"US",
    "sg:address":"4708 N Kedzie Ave",
    "sg:city":"Chicago",
    "sg:classifiers":[
        {
            "category":"Health Services",
            "subcategory":"Doctor",
            "type":"Services"
        },
        {
            "category":"Community Center",
            "type":"Public Place"
        }
    ],
    "sg:phone":"+1 773 583 7420",
    "sg:postcode":"60625",
    "sg:province":"IL",
    "sg:tags":[
        "medical"
    ],
    "wof:name":"Maitar Michael MD",
    "wof:placetype":"venue"
},
  "geometry": {"coordinates":[-87.708298,41.9669],"type":"Point"}
}