{
  "type": "Feature",
  "properties": {
    "iso:country":"US",
    "sg:address":"774 W Army Trail Rd",
    "sg:city":"Carol Stream",
    "sg:classifiers":[
        {
            "category":"Personal",
            "subcategory":"Nail Salon",
            "type":"Services"
        }
    ],
    "sg:phone":"+1 630 213 3888",
    "sg:postcode":"60188",
    "sg:province":"IL",
    "wof:name":"Hair Friends Z",
    "wof:placetype":"venue"
},
  "geometry": {"coordinates":[-88.14646500000001,41.940293],"type":"Point"}
}