{
  "type": "Feature",
  "properties": {
    "addr:full":"212 W State St Sycamore IL 60178",
    "addr:housenumber":"212",
    "addr:postcode":"60178",
    "addr:street":"W State St",
    "iso:country":"US",
    "sg:address":"212 W State St",
    "sg:city":"Sycamore",
    "sg:classifiers":[
        {
            "category":"Manufacturing",
            "subcategory":"Buildings",
            "type":"Manufacturing & Wholesale Goods"
        },
        {
            "category":"Building & Trades",
            "subcategory":"Construction",
            "type":"Services"
        },
        {
            "category":"Building & Trades",
            "subcategory":"Electrical",
            "type":"Services"
        }
    ],
    "sg:phone":"+1 815 895 7654",
    "sg:postcode":"60178",
    "sg:province":"IL",
    "sg:tags":[
        "system",
        "industrial",
        "electrician",
        "electric",
        "builder",
        "specialty",
        "heating",
        "contractors-commercial",
        "home",
        "contractor",
        "air conditioning"
    ],
    "wof:name":"Insights Electrical Service",
    "wof:placetype":"venue"
},
  "geometry": {"coordinates":[-88.68606,41.988696],"type":"Point"}
}