{
  "type": "Feature",
  "properties": {
    "iso:country":"US",
    "sg:address":"66 Montclair Dr",
    "sg:city":"Fairview Heights",
    "sg:classifiers":[
        {
            "category":"Communications",
            "subcategory":"Radio Station",
            "type":"Services"
        }
    ],
    "sg:phone":"+1 618 271 6890",
    "sg:postcode":"62208",
    "sg:province":"IL",
    "sg:tags":[
        "provide",
        "religious"
    ],
    "wof:name":"Ralph Muhammad",
    "wof:placetype":"venue"
},
  "geometry": {"coordinates":[-90.040034,38.59337],"type":"Point"}
}