{
  "type": "Feature",
  "properties": {
    "iso:country":"US",
    "sg:address":"1528 Leabrook Cv",
    "sg:city":"Wheaton",
    "sg:classifiers":[
        {
            "category":"Home & Garden",
            "subcategory":"Carpets & Floor Coverings",
            "type":"Retail Goods"
        }
    ],
    "sg:phone":"+1 630 690 1548",
    "sg:postcode":"60187",
    "sg:province":"IL",
    "sg:tags":[
        "carpeting"
    ],
    "wof:name":"Savo Carpets",
    "wof:placetype":"venue"
},
  "geometry": {"coordinates":[-88.132797,41.848],"type":"Point"}
}