{
  "type": "Feature",
  "properties": {
    "iso:country":"US",
    "sg:address":"8120 Central Park Ave",
    "sg:city":"Skokie",
    "sg:classifiers":[
        {
            "category":"Wholesale",
            "subcategory":"Home Furnishings",
            "type":"Manufacturing & Wholesale Goods"
        }
    ],
    "sg:phone":"+1 847 982 2280",
    "sg:postcode":"60076",
    "sg:province":"IL",
    "wof:name":"Superior Knife Inc",
    "wof:placetype":"venue"
},
  "geometry": {"coordinates":[-87.718507,42.0296],"type":"Point"}
}