{
  "type": "Feature",
  "properties": {
    "addr:full":"1858 W Wabansia Ave Chicago IL 60622",
    "addr:housenumber":"1858",
    "addr:postcode":"60622",
    "addr:street":"W Wabansia Ave",
    "iso:country":"US",
    "sg:address":"1858 W Wabansia Ave",
    "sg:city":"Chicago",
    "sg:classifiers":[
        {
            "category":"Bars & Pubs",
            "type":"Food & Drink"
        },
        {
            "category":"Restaurant",
            "type":"Food & Drink"
        }
    ],
    "sg:phone":"+1 773 342 7778",
    "sg:postcode":"60622",
    "sg:province":"IL",
    "sg:tags":[
        "traditional",
        "american"
    ],
    "sg:website":"lincolntavern.com/",
    "wof:name":"Lincoln Tavern & Restaurant",
    "wof:placetype":"venue"
},
  "geometry": {"coordinates":[-87.674896,41.912498],"type":"Point"}
}