{
  "type": "Feature",
  "properties": {
    "iso:country":"US",
    "sg:address":"810 W Anthony Dr",
    "sg:city":"Champaign",
    "sg:classifiers":[
        {
            "category":"Health Services",
            "subcategory":"Doctor",
            "type":"Services"
        }
    ],
    "sg:phone":"+1 217 326 2255",
    "sg:postcode":"61822",
    "sg:province":"IL",
    "sg:website":"www.carle.com",
    "wof:name":"Carle Clinic Association",
    "wof:placetype":"venue"
},
  "geometry": {"coordinates":[-88.25626099999999,40.136064],"type":"Point"}
}