{
  "type": "Feature",
  "properties": {
    "iso:country":"US",
    "sg:address":"34094 W Bluestem Rd",
    "sg:city":"Round Lake",
    "sg:classifiers":[
        {
            "category":"Real Estate",
            "subcategory":"Architect",
            "type":"Services"
        }
    ],
    "sg:phone":"+1 847 546 6207",
    "sg:postcode":"60073",
    "sg:province":"IL",
    "sg:tags":[
        "architectural"
    ],
    "wof:name":"Joels Installation",
    "wof:placetype":"venue"
},
  "geometry": {"coordinates":[-88.131999,42.359007],"type":"Point"}
}