{
  "type": "Feature",
  "properties": {
    "addr:full":"1404 S Banker St Effingham IL 62401",
    "addr:housenumber":"1404",
    "addr:postcode":"62401",
    "addr:street":"S Banker St",
    "iso:country":"US",
    "sg:address":"1404 S Banker St",
    "sg:city":"Effingham",
    "sg:classifiers":[
        {
            "category":"Food & Beverages",
            "subcategory":"Liquor & Beverages",
            "type":"Retail Goods"
        }
    ],
    "sg:phone":"+1   ",
    "sg:postcode":"62401",
    "sg:province":"IL",
    "sg:tags":[
        "alcoholic"
    ],
    "wof:name":"D JS Party Supply",
    "wof:placetype":"venue"
},
  "geometry": {"coordinates":[-88.546862,39.110096],"type":"Point"}
}