{
  "type": "Feature",
  "properties": {
    "iso:country":"US",
    "sg:address":"128 Orlando Ct",
    "sg:city":"Fairview Heights",
    "sg:classifiers":[
        {
            "category":"Building & Trades",
            "subcategory":"Construction",
            "type":"Services"
        }
    ],
    "sg:phone":"+1 618 628 0051",
    "sg:postcode":"62208",
    "sg:province":"IL",
    "sg:tags":[
        "house"
    ],
    "wof:name":"Erlinger Remodeling & Construc",
    "wof:placetype":"venue"
},
  "geometry": {"coordinates":[-89.98086,38.587501],"type":"Point"}
}