{
  "type": "Feature",
  "properties": {
    "iso:country":"US",
    "sg:address":"3811 Mississippi Ave",
    "sg:city":"East Saint Louis",
    "sg:classifiers":[
        {
            "category":"Professional",
            "subcategory":"Employment Agencies",
            "type":"Services"
        }
    ],
    "sg:phone":"+1 618 337 2168",
    "sg:postcode":"62206",
    "sg:province":"IL",
    "wof:name":"Partners Personnel Services",
    "wof:placetype":"venue"
},
  "geometry": {"coordinates":[-90.182489,38.578256],"type":"Point"}
}