{
  "type": "Feature",
  "properties": {
    "iso:country":"US",
    "sg:address":"448 E Spruce St",
    "sg:city":"Paxton",
    "sg:classifiers":[
        {
            "category":"Manufacturing",
            "subcategory":"Food",
            "type":"Manufacturing & Wholesale Goods"
        },
        {
            "category":"Farming",
            "subcategory":"Farm",
            "type":"Manufacturing & Wholesale Goods"
        }
    ],
    "sg:phone":"+1 217 379 3540",
    "sg:postcode":"60957",
    "sg:province":"IL",
    "sg:tags":[
        "corn",
        "product"
    ],
    "wof:name":"Lloyd Bluhm",
    "wof:placetype":"venue"
},
  "geometry": {"coordinates":[-88.089724,40.463994],"type":"Point"}
}