{
  "type": "Feature",
  "properties": {
    "iso:country":"US",
    "sg:address":"1110 Mulliken St",
    "sg:city":"Carlyle",
    "sg:classifiers":[
        {
            "category":"Health Services",
            "subcategory":"Doctor",
            "type":"Services"
        }
    ],
    "sg:phone":"+1 618 594 3613",
    "sg:postcode":"62231",
    "sg:province":"IL",
    "sg:tags":[
        "physician",
        "surgeon"
    ],
    "wof:name":"Renato B Rivera LTD",
    "wof:placetype":"venue"
},
  "geometry": {"coordinates":[-89.372857,38.615014],"type":"Point"}
}