{
  "type": "Feature",
  "properties": {
    "addr:full":"621 Chatfield Rd New Lenox IL 60451",
    "addr:housenumber":"621",
    "addr:postcode":"60451",
    "addr:street":"Chatfield Rd",
    "iso:country":"US",
    "sg:address":"621 Chatfield Rd",
    "sg:city":"New Lenox",
    "sg:classifiers":[
        {
            "category":"Professional",
            "subcategory":"Lawyer & Legal Services",
            "type":"Services"
        }
    ],
    "sg:phone":"+1 815 462 0777",
    "sg:postcode":"60451",
    "sg:province":"IL",
    "sg:tags":[
        "attorney"
    ],
    "wof:name":"Sidney M Sigel",
    "wof:placetype":"venue"
},
  "geometry": {"coordinates":[-87.929062,41.520196],"type":"Point"}
}