{
  "type": "Feature",
  "properties": {
    "addr:full":"325 W Prospect Ave Mount Prospect IL 60056",
    "addr:housenumber":"325",
    "addr:postcode":"60056",
    "addr:street":"W Prospect Ave",
    "iso:country":"US",
    "sg:address":"325 W Prospect Ave",
    "sg:city":"Mount Prospect",
    "sg:classifiers":[
        {
            "category":"Organizations",
            "subcategory":"Religious Organization",
            "type":"Services"
        }
    ],
    "sg:phone":"+1 847 368 0918",
    "sg:postcode":"60056",
    "sg:province":"IL",
    "sg:tags":[
        "medical"
    ],
    "wof:name":"Reeb Center For Wound MGT",
    "wof:placetype":"venue"
},
  "geometry": {"coordinates":[-87.942116,42.065286],"type":"Point"}
}