{
  "type": "Feature",
  "properties": {
    "addr:full":"6503 39th Ave Kenosha IL 53142",
    "addr:housenumber":"6503",
    "addr:postcode":"53142",
    "addr:street":"39Th Ave",
    "iso:country":"US",
    "sg:address":"6503 39th Ave",
    "sg:city":"Kenosha",
    "sg:classifiers":[
        {
            "category":"Retail",
            "subcategory":"Auto Rental",
            "type":"Services"
        }
    ],
    "sg:phone":"+1 262 652 4399",
    "sg:postcode":"53142",
    "sg:province":"IL",
    "sg:tags":[
        "truck",
        "trailer"
    ],
    "wof:name":"U-Haul",
    "wof:placetype":"venue"
},
  "geometry": {"coordinates":[-87.855206,42.573615],"type":"Point"}
}