{
  "type": "Feature",
  "properties": {
    "iso:country":"US",
    "sg:address":"5270 Gingeridge Ln",
    "sg:city":"Rockford",
    "sg:classifiers":[
        {
            "category":"Professional",
            "subcategory":"Research",
            "type":"Services"
        }
    ],
    "sg:phone":"+1 815 637 6653",
    "sg:postcode":"61114",
    "sg:province":"IL",
    "sg:tags":[
        "environmental",
        "ecological"
    ],
    "wof:name":"All Mold Environmental",
    "wof:placetype":"venue"
},
  "geometry": {"coordinates":[-89.015168,42.31084],"type":"Point"}
}