{
  "type": "Feature",
  "properties": {
    "addr:full":"201 Ohio St Brookport IL 62910",
    "addr:housenumber":"201",
    "addr:postcode":"62910",
    "addr:street":"Ohio St",
    "iso:country":"US",
    "sg:address":"201 Ohio St",
    "sg:city":"Brookport",
    "sg:classifiers":[
        {
            "category":"Wholesale",
            "subcategory":"Medical Equipment & Supplies",
            "type":"Manufacturing & Wholesale Goods"
        }
    ],
    "sg:phone":"+1 618 564 2026",
    "sg:postcode":"62910",
    "sg:province":"IL",
    "sg:tags":[
        "assistive",
        "aid",
        "device",
        "hearing"
    ],
    "wof:name":"Rhodes Hearing Aids",
    "wof:placetype":"venue"
},
  "geometry": {"coordinates":[-88.627869,37.12286],"type":"Point"}
}