{
  "type": "Feature",
  "properties": {
    "iso:country":"US",
    "sg:address":"3621 Ridge Rd",
    "sg:city":"Lansing",
    "sg:classifiers":[
        {
            "category":"Organizations",
            "subcategory":"Religious Organization",
            "type":"Services"
        }
    ],
    "sg:phone":"+1 708 474 8660",
    "sg:postcode":"60438",
    "sg:province":"IL",
    "sg:tags":[
        "church"
    ],
    "wof:name":"Christian Science Reading Rms",
    "wof:placetype":"venue"
},
  "geometry": {"coordinates":[-87.529241,41.563891],"type":"Point"}
}