{
  "type": "Feature",
  "properties": {
    "iso:country":"US",
    "sg:address":"2277 W Howard St",
    "sg:city":"Chicago",
    "sg:classifiers":[
        {
            "category":"Health Services",
            "subcategory":"Doctor",
            "type":"Services"
        }
    ],
    "sg:phone":"+1 773 508 0110",
    "sg:postcode":"60645",
    "sg:province":"IL",
    "sg:tags":[
        "physician",
        "surgeons",
        "nephrology",
        "surgeon",
        "kidneys"
    ],
    "wof:name":"Lakeside Nephrology, Ltd.",
    "wof:placetype":"venue"
},
  "geometry": {"coordinates":[-87.68286500000001,42.019459],"type":"Point"}
}