{
  "type": "Feature",
  "properties": {
    "iso:country":"US",
    "sg:address":"940 18th St",
    "sg:city":"Charleston",
    "sg:classifiers":[
        {
            "category":"Shopping",
            "subcategory":"Crafts & Fabrics",
            "type":"Retail Goods"
        }
    ],
    "sg:phone":"+1   ",
    "sg:postcode":"61920",
    "sg:province":"IL",
    "sg:tags":[
        "sewing"
    ],
    "wof:name":"Golden Thimble",
    "wof:placetype":"venue"
},
  "geometry": {"coordinates":[-88.163281,39.488914],"type":"Point"}
}