{
  "type": "Feature",
  "properties": {
    "iso:country":"US",
    "sg:address":"7414 N Illinois St",
    "sg:city":"Caseyville",
    "sg:classifiers":[
        {
            "category":"Food & Beverages",
            "subcategory":"Specialty",
            "type":"Retail Goods"
        }
    ],
    "sg:phone":"+1   ",
    "sg:postcode":"62232",
    "sg:province":"IL",
    "wof:name":"Mannatech",
    "wof:placetype":"venue"
},
  "geometry": {"coordinates":[-89.985268,38.635226],"type":"Point"}
}