{
  "type": "Feature",
  "properties": {
    "addr:full":"15019 Ivy Ct Homer Glen IL 60491",
    "addr:housenumber":"15019",
    "addr:postcode":"60491",
    "addr:street":"Ivy Ct",
    "iso:country":"US",
    "sg:address":"15019 Ivy Ct",
    "sg:city":"Homer Glen",
    "sg:classifiers":[
        {
            "category":"Real Estate",
            "subcategory":"Real Estate Agent",
            "type":"Services"
        }
    ],
    "sg:phone":"+1 708 301 1999",
    "sg:postcode":"60491",
    "sg:province":"IL",
    "wof:name":"Kingston Hills Subdivision",
    "wof:placetype":"venue"
},
  "geometry": {"coordinates":[-87.92294,41.615754],"type":"Point"}
}