{
  "type": "Feature",
  "properties": {
    "addr:full":"2140 W Division St Chicago IL 60622",
    "addr:housenumber":"2140",
    "addr:postcode":"60622",
    "addr:street":"W Division St",
    "iso:country":"US",
    "sg:address":"2140 W Division St",
    "sg:city":"Chicago",
    "sg:classifiers":[
        {
            "category":"Health Services",
            "subcategory":"Clinic",
            "type":"Services"
        },
        {
            "category":"Health Services",
            "subcategory":"Medical Lab",
            "type":"Services"
        }
    ],
    "sg:phone":"+1 800 639 6773",
    "sg:postcode":"60622",
    "sg:province":"IL",
    "sg:tags":[
        "information",
        "aid"
    ],
    "wof:name":"Local STD Testing",
    "wof:placetype":"venue"
},
  "geometry": {"coordinates":[-87.680696,41.903116],"type":"Point"}
}