{
  "type": "Feature",
  "properties": {
    "iso:country":"US",
    "sg:address":"2435 Glenwood Ave",
    "sg:city":"Joliet",
    "sg:classifiers":[
        {
            "category":"Health Services",
            "subcategory":"Doctor",
            "type":"Services"
        }
    ],
    "sg:phone":"+1 815 725 0260",
    "sg:postcode":"60435",
    "sg:province":"IL",
    "sg:tags":[
        "dentist"
    ],
    "wof:name":"Glenwood Dental Center",
    "wof:placetype":"venue"
},
  "geometry": {"coordinates":[-88.14274500000001,41.529532],"type":"Point"}
}