{
  "type": "Feature",
  "properties": {
    "addr:full":"1825 Glenview Rd Glenview IL 60025",
    "addr:housenumber":"1825",
    "addr:postcode":"60025",
    "addr:street":"Glenview Rd",
    "iso:country":"US",
    "sg:address":"1825 Glenview Rd",
    "sg:city":"Glenview",
    "sg:classifiers":[
        {
            "category":"Place Of Worship",
            "type":"Public Place"
        }
    ],
    "sg:phone":"+1 847 681 2872",
    "sg:postcode":"60025",
    "sg:province":"IL",
    "sg:tags":[
        "church"
    ],
    "wof:name":"Church of The Redeemer",
    "wof:placetype":"venue"
},
  "geometry": {"coordinates":[-87.80354199999999,42.072797],"type":"Point"}
}