{
  "type": "Feature",
  "properties": {
    "iso:country":"US",
    "sg:address":"2010 Dewey Ave",
    "sg:city":"Evanston",
    "sg:classifiers":[
        {
            "category":"Sports & Exercise",
            "subcategory":"Playing Field",
            "type":"Entertainment"
        }
    ],
    "sg:phone":"+1 847 328 2635",
    "sg:postcode":"60201",
    "sg:province":"IL",
    "sg:tags":[
        "boxing",
        "instruction"
    ],
    "wof:name":"Blackkats Wrestling",
    "wof:placetype":"venue"
},
  "geometry": {"coordinates":[-87.695739,42.054783],"type":"Point"}
}