{
  "type": "Feature",
  "properties": {
    "addr:full":"1040 Carlyle Ave Belleville IL 62221",
    "addr:housenumber":"1040",
    "addr:postcode":"62221",
    "addr:street":"Carlyle Ave",
    "iso:country":"US",
    "sg:address":"1040 Carlyle Ave",
    "sg:city":"Belleville",
    "sg:classifiers":[
        {
            "category":"Retail",
            "subcategory":"Laundry & Dry Cleaning",
            "type":"Services"
        }
    ],
    "sg:phone":"+1 618 222 2858",
    "sg:postcode":"62221",
    "sg:province":"IL",
    "wof:name":"Perfect Fit Alterations",
    "wof:placetype":"venue"
},
  "geometry": {"coordinates":[-89.946099,38.518354],"type":"Point"}
}