{
  "type": "Feature",
  "properties": {
    "addr:full":"2695 N Illinois St Swansea IL 62226",
    "addr:housenumber":"2695",
    "addr:postcode":"62226",
    "addr:street":"N Illinois St",
    "iso:country":"US",
    "sg:address":"2695 N Illinois St",
    "sg:city":"Swansea",
    "sg:classifiers":[
        {
            "category":"Banks & Credit Unions",
            "subcategory":"Investment Brokerage",
            "type":"Services"
        }
    ],
    "sg:phone":"+1 618 236 7789",
    "sg:postcode":"62226",
    "sg:province":"IL",
    "sg:tags":[
        "security"
    ],
    "sg:website":"www.edwardjones.com",
    "wof:name":"Edward Jones Co",
    "wof:placetype":"venue"
},
  "geometry": {"coordinates":[-89.983932,38.542372],"type":"Point"}
}