{
  "type": "Feature",
  "properties": {
    "iso:country":"US",
    "sg:address":"515 St Louis Ave",
    "sg:city":"East St Louis",
    "sg:classifiers":[
        {
            "category":"Restaurant",
            "type":"Food & Drink"
        }
    ],
    "sg:phone":"+1 618 271 0536",
    "sg:postcode":"62201",
    "sg:province":"IL",
    "wof:name":"Javons Restaurant",
    "wof:placetype":"venue"
},
  "geometry": {"coordinates":[-90.15587600000001,38.626461],"type":"Point"}
}