{
  "type": "Feature",
  "properties": {
    "iso:country":"US",
    "sg:address":"3 E Hawthorn Pkwy",
    "sg:city":"Vernon Hills",
    "sg:classifiers":[
        {
            "category":"Home & Garden",
            "subcategory":"Hardware",
            "type":"Retail Goods"
        }
    ],
    "sg:phone":"+1   ",
    "sg:postcode":"60061",
    "sg:province":"IL",
    "wof:name":"Bill True",
    "wof:placetype":"venue"
},
  "geometry": {"coordinates":[-87.962433,42.241621],"type":"Point"}
}