{
  "type": "Feature",
  "properties": {
    "iso:country":"US",
    "sg:address":"562 N Logan Ave",
    "sg:city":"Danville",
    "sg:classifiers":[
        {
            "category":"Freight",
            "type":"Transportation"
        }
    ],
    "sg:phone":"+1 217 431 4266",
    "sg:postcode":"61832",
    "sg:province":"IL",
    "sg:tags":[
        "commercial",
        "storage"
    ],
    "wof:name":"Danville Storage",
    "wof:placetype":"venue"
},
  "geometry": {"coordinates":[-87.644281,40.131762],"type":"Point"}
}