{
  "type": "Feature",
  "properties": {
    "addr:full":"21235 Deerpath Rd Frankfort IL 60423",
    "addr:housenumber":"21235",
    "addr:postcode":"60423",
    "addr:street":"Deerpath Rd",
    "iso:country":"US",
    "sg:address":"21235 Deerpath Rd",
    "sg:city":"Frankfort",
    "sg:classifiers":[
        {
            "category":"Organizations",
            "subcategory":"Religious Organization",
            "type":"Services"
        }
    ],
    "sg:phone":"+1 815 464 6983",
    "sg:postcode":"60423",
    "sg:province":"IL",
    "wof:name":"Holy Family Assoc",
    "wof:placetype":"venue"
},
  "geometry": {"coordinates":[-87.800613,41.504108],"type":"Point"}
}