{
  "type": "Feature",
  "properties": {
    "iso:country":"US",
    "sg:address":"724 W Rollins Rd",
    "sg:city":"Round Lake Beach",
    "sg:classifiers":[
        {
            "category":"Cinema",
            "subcategory":"Movie Rental",
            "type":"Entertainment"
        }
    ],
    "sg:phone":"+1 847 740 3616",
    "sg:postcode":"60073",
    "sg:province":"IL",
    "sg:tags":[
        "leasing",
        "video",
        "disc",
        "tape"
    ],
    "sg:website":"www.famvid.com",
    "wof:name":"Family Video",
    "wof:placetype":"venue"
},
  "geometry": {"coordinates":[-88.10091,42.379055],"type":"Point"}
}