{
  "type": "Feature",
  "properties": {
    "addr:full":"521 W Jackson St Macomb IL 61455",
    "addr:housenumber":"521",
    "addr:postcode":"61455",
    "addr:street":"W Jackson St",
    "iso:country":"US",
    "sg:address":"521 W Jackson St",
    "sg:city":"Macomb",
    "sg:classifiers":[
        {
            "category":"Restaurant",
            "type":"Food & Drink"
        }
    ],
    "sg:menulink":"http://www.allmenus.com/il/macomb-city/83868-papa-johns-pizza/menu/",
    "sg:phone":"+1 309 837 7272",
    "sg:postcode":"61455",
    "sg:province":"IL",
    "sg:tags":[
        "american",
        "pizza"
    ],
    "wof:name":"Papa John's Pizza",
    "wof:placetype":"venue"
},
  "geometry": {"coordinates":[-90.679114,40.458845],"type":"Point"}
}