{
  "type": "Feature",
  "properties": {
    "iso:country":"US",
    "sg:address":"5693 N Northwest Hwy",
    "sg:city":"Chicago",
    "sg:classifiers":[
        {
            "category":"Retail",
            "subcategory":"Auto Repair",
            "type":"Services"
        }
    ],
    "sg:phone":"+1 773 631 2828",
    "sg:postcode":"60646",
    "sg:province":"IL",
    "sg:tags":[
        "general"
    ],
    "wof:name":"Grand Touring",
    "wof:placetype":"venue"
},
  "geometry": {"coordinates":[-87.785715,41.984842],"type":"Point"}
}