{
  "type": "Feature",
  "properties": {
    "iso:country":"US",
    "sg:address":"419 S 2nd St",
    "sg:city":"Caseyville",
    "sg:classifiers":[
        {
            "category":"Education",
            "subcategory":"Library",
            "type":"Public Place"
        }
    ],
    "sg:phone":"+1 618 345 5848",
    "sg:postcode":"62232",
    "sg:province":"IL",
    "wof:name":"Caseyville Public Library",
    "wof:placetype":"venue"
},
  "geometry": {"coordinates":[-90.030434,38.635386],"type":"Point"}
}