{
  "type": "Feature",
  "properties": {
    "addr:full":"536 Orland Square Dr Orland Park IL 60462",
    "addr:housenumber":"536",
    "addr:postcode":"60462",
    "addr:street":"Orland Square Dr",
    "iso:country":"US",
    "sg:address":"536 Orland Square Dr",
    "sg:city":"Orland Park",
    "sg:classifiers":[
        {
            "category":"Building & Trades",
            "subcategory":"Construction",
            "type":"Services"
        }
    ],
    "sg:phone":"+1 708 226 0264",
    "sg:postcode":"60462",
    "sg:province":"IL",
    "sg:tags":[
        "contractor"
    ],
    "wof:name":"H & H Contracting Co Inc",
    "wof:placetype":"venue"
},
  "geometry": {"coordinates":[-87.852377,41.620255],"type":"Point"}
}