{
  "type": "Feature",
  "properties": {
    "iso:country":"US",
    "sg:address":"849 W 87th St",
    "sg:city":"Chicago",
    "sg:classifiers":[
        {
            "category":"Food & Beverages",
            "subcategory":"Liquor & Beverages",
            "type":"Retail Goods"
        }
    ],
    "sg:phone":"+1 773 874 4624",
    "sg:postcode":"60620",
    "sg:province":"IL",
    "sg:tags":[
        "beer",
        "spirit",
        "wine"
    ],
    "wof:name":"Buy Low Food & Liquors",
    "wof:placetype":"venue"
},
  "geometry": {"coordinates":[-87.64540100000001,41.735901],"type":"Point"}
}