{
  "type": "Feature",
  "properties": {
    "addr:full":"1348 W Concord Place Chicago IL 60622",
    "addr:housenumber":"1348",
    "addr:postcode":"60622",
    "addr:street":"W Concord Place",
    "iso:country":"US",
    "sg:address":"1348 W Concord Place",
    "sg:city":"Chicago",
    "sg:classifiers":[
        {
            "category":"Home & Garden",
            "subcategory":"Furniture",
            "type":"Retail Goods"
        }
    ],
    "sg:phone":"+1 773 489 9200",
    "sg:postcode":"60622",
    "sg:province":"IL",
    "sg:tags":[
        "store"
    ],
    "wof:name":"Galleria Concord",
    "wof:placetype":"venue"
},
  "geometry": {"coordinates":[-87.66218000000001,41.912134],"type":"Point"}
}