{
  "type": "Feature",
  "properties": {
    "addr:full":"213 Main St Chadwick IL 61014",
    "addr:housenumber":"213",
    "addr:postcode":"61014",
    "addr:street":"Main St",
    "iso:country":"US",
    "sg:address":"213 Main St",
    "sg:city":"Chadwick",
    "sg:classifiers":[
        {
            "category":"Food & Beverages",
            "subcategory":"Groceries & Convenience Stores",
            "type":"Retail Goods"
        }
    ],
    "sg:phone":"+1 815 684 5154",
    "sg:postcode":"61014",
    "sg:province":"IL",
    "sg:tags":[
        "grocer"
    ],
    "wof:name":"Hometown Food Ctr",
    "wof:placetype":"venue"
},
  "geometry": {"coordinates":[-89.890928,42.014428],"type":"Point"}
}