{
  "type": "Feature",
  "properties": {
    "addr:full":"115 W North Ave Chicago IL 60610",
    "addr:housenumber":"115",
    "addr:postcode":"60610",
    "addr:street":"W North Ave",
    "iso:country":"US",
    "sg:address":"115 W North Ave",
    "sg:city":"Chicago",
    "sg:classifiers":[
        {
            "category":"Personal",
            "subcategory":"Shoe Repair & Shine",
            "type":"Services"
        }
    ],
    "sg:phone":"+1 312 266 8966",
    "sg:postcode":"60610",
    "sg:province":"IL",
    "wof:name":"Sandburg Shoe Repair",
    "wof:placetype":"venue"
},
  "geometry": {"coordinates":[-87.63339999999999,41.910999],"type":"Point"}
}