{
  "type": "Feature",
  "properties": {
    "iso:country":"US",
    "sg:address":"1956 Knox Road 2150 E",
    "sg:city":"Williamsfield",
    "sg:phone":"+1 309 879 2486",
    "sg:postcode":"61489",
    "sg:province":"IL",
    "sg:tags":[
        "farm",
        "corn",
        "soybean"
    ],
    "wof:name":"Pat Strom",
    "wof:placetype":"venue"
},
  "geometry": {"coordinates":[-90.033085,41.002647],"type":"Point"}
}