{
  "type": "Feature",
  "properties": {
    "iso:country":"US",
    "sg:address":"600 S County Farm Rd",
    "sg:city":"Wheaton",
    "sg:classifiers":[
        {
            "category":"Personal",
            "subcategory":"Nail Salon",
            "type":"Services"
        }
    ],
    "sg:phone":"+1 630 260 8744",
    "sg:postcode":"60187",
    "sg:province":"IL",
    "wof:name":"Lexi Nails",
    "wof:placetype":"venue"
},
  "geometry": {"coordinates":[-88.14263699999999,41.857902],"type":"Point"}
}