{
  "type": "Feature",
  "properties": {
    "iso:country":"US",
    "sg:address":"3459 Yale Bridge Rd",
    "sg:city":"Rockton",
    "sg:classifiers":[
        {
            "category":"Home & Garden",
            "subcategory":"Garden Supply",
            "type":"Retail Goods"
        }
    ],
    "sg:phone":"+1 815 624 2098",
    "sg:postcode":"61072",
    "sg:province":"IL",
    "sg:tags":[
        "tree",
        "christmas"
    ],
    "wof:name":"Blackhawk Tree Farms",
    "wof:placetype":"venue"
},
  "geometry": {"coordinates":[-89.106753,42.477063],"type":"Point"}
}