{
  "type": "Feature",
  "properties": {
    "addr:full":"1960 S Mount Prospect Rd Des Plaines IL 60018",
    "addr:housenumber":"1960",
    "addr:postcode":"60018",
    "addr:street":"S Mount Prospect Rd Des",
    "iso:country":"US",
    "sg:address":"1960 S Mount Prospect Rd",
    "sg:city":"Des Plaines",
    "sg:classifiers":[
        {
            "category":"Restaurant",
            "type":"Food & Drink"
        }
    ],
    "sg:menulink":"http://www.allmenus.com/il/elk-grove/212315-mcdonalds/menu/",
    "sg:postcode":"60018",
    "sg:province":"IL",
    "sg:tags":[
        "burger",
        "american"
    ],
    "wof:name":"McDonald's",
    "wof:placetype":"venue"
},
  "geometry": {"coordinates":[-87.92081399999999,42.015972],"type":"Point"}
}