{
  "type": "Feature",
  "properties": {
    "addr:full":"2721 Sperry Ct Batavia IL 60510",
    "addr:housenumber":"2721",
    "addr:postcode":"60510",
    "addr:street":"Sperry Ct",
    "iso:country":"US",
    "sg:address":"2721 Sperry Ct",
    "sg:city":"Batavia",
    "sg:classifiers":[
        {
            "category":"Structure",
            "subcategory":"Office Building",
            "type":"Public Place"
        }
    ],
    "sg:phone":"+1 630 879 0836",
    "sg:postcode":"60510",
    "sg:province":"IL",
    "sg:tags":[
        "park"
    ],
    "wof:name":"Vance Properties",
    "wof:placetype":"venue"
},
  "geometry": {"coordinates":[-88.350949,41.853132],"type":"Point"}
}