{
  "type": "Feature",
  "properties": {
    "addr:full":"306 River Oaks Center Dr Calumet City IL 60409",
    "addr:housenumber":"306",
    "addr:postcode":"60409",
    "addr:street":"River Oaks Center Dr",
    "iso:country":"US",
    "sg:address":"306 River Oaks Center Dr",
    "sg:city":"Calumet City",
    "sg:classifiers":[
        {
            "category":"Restaurant",
            "type":"Food & Drink"
        }
    ],
    "sg:phone":"+1   ",
    "sg:postcode":"60409",
    "sg:province":"IL",
    "sg:tags":[
        "cajun"
    ],
    "wof:name":"Cajun Cafe",
    "wof:placetype":"venue"
},
  "geometry": {"coordinates":[-87.531739,41.595608],"type":"Point"}
}