{
  "type": "Feature",
  "properties": {
    "iso:country":"US",
    "sg:address":"203 S East St",
    "sg:city":"Dakota",
    "sg:classifiers":[
        {
            "category":"Autos & Motor Vehicles",
            "subcategory":"Fuel & Gas Station",
            "type":"Retail Goods"
        }
    ],
    "sg:phone":"+1 815 449 2412",
    "sg:postcode":"61018",
    "sg:province":"IL",
    "sg:tags":[
        "oil"
    ],
    "wof:name":"Dakota Garage",
    "wof:placetype":"venue"
},
  "geometry": {"coordinates":[-89.522691,42.385902],"type":"Point"}
}