{
  "type": "Feature",
  "properties": {
    "iso:country":"US",
    "sg:address":"351 E Cherry Cove Ln",
    "sg:city":"Round Lake Beach",
    "sg:classifiers":[
        {
            "category":"Professional",
            "subcategory":"Business Services",
            "type":"Services"
        }
    ],
    "sg:phone":"+1 847 265 6574",
    "sg:postcode":"60073",
    "sg:province":"IL",
    "wof:name":"Underground Electronics",
    "wof:placetype":"venue"
},
  "geometry": {"coordinates":[-88.07578700000001,42.3938],"type":"Point"}
}