{
  "type": "Feature",
  "properties": {
    "iso:country":"US",
    "sg:address":"3501 W Belmont Avenue",
    "sg:city":"Chicago",
    "sg:classifiers":[
        {
            "category":"Autos & Motor Vehicles",
            "subcategory":"Automobile Sales",
            "type":"Retail Goods"
        }
    ],
    "sg:phone":"+1 773 267 6800",
    "sg:postcode":"60618",
    "sg:province":"IL",
    "sg:tags":[
        "car"
    ],
    "wof:name":"Olympia Auto Sales & Service",
    "wof:placetype":"venue"
},
  "geometry": {"coordinates":[-87.71568000000001,41.939087],"type":"Point"}
}