{
  "type": "Feature",
  "properties": {
    "iso:country":"US",
    "sg:address":"9206 Grand Ave",
    "sg:city":"Franklin Park",
    "sg:classifiers":[
        {
            "category":"Manufacturing",
            "subcategory":"Tools & Machinery",
            "type":"Manufacturing & Wholesale Goods"
        }
    ],
    "sg:phone":"+1 847 455 0646",
    "sg:postcode":"60131",
    "sg:province":"IL",
    "sg:tags":[
        "mfg",
        "forging"
    ],
    "wof:name":"Central Forging Die Works Inc",
    "wof:placetype":"venue"
},
  "geometry": {"coordinates":[-87.85695699999999,41.929267],"type":"Point"}
}