{
  "type": "Feature",
  "properties": {
    "addr:full":"560 S River St Batavia IL 60510",
    "addr:housenumber":"560",
    "addr:postcode":"60510",
    "addr:street":"S River St",
    "iso:country":"US",
    "sg:address":"560 S River St",
    "sg:city":"Batavia",
    "sg:classifiers":[
        {
            "category":"Retail",
            "subcategory":"Laundry & Dry Cleaning",
            "type":"Services"
        }
    ],
    "sg:phone":"+1 630 879 3364",
    "sg:postcode":"60510",
    "sg:province":"IL",
    "sg:tags":[
        "cleaner",
        "rug",
        "carpet"
    ],
    "sg:website":"http://www.trueservice.net",
    "wof:name":"Strode Enterprises",
    "wof:placetype":"venue"
},
  "geometry": {"coordinates":[-88.305362,41.841124],"type":"Point"}
}