{
  "type": "Feature",
  "properties": {
    "addr:full":"4874 N Lincoln Ave Chicago IL 60625",
    "addr:housenumber":"4874",
    "addr:postcode":"60625",
    "addr:street":"N Lincoln Ave",
    "iso:country":"US",
    "sg:address":"4874 N Lincoln Ave",
    "sg:city":"Chicago",
    "sg:classifiers":[
        {
            "category":"Bars & Pubs",
            "subcategory":"Lounge",
            "type":"Food & Drink"
        },
        {
            "category":"Bars & Pubs",
            "subcategory":"Nightclub",
            "type":"Food & Drink"
        },
        {
            "category":"Sports & Exercise",
            "subcategory":"Bowling",
            "type":"Entertainment"
        }
    ],
    "sg:phone":"+1 773 561 8191",
    "sg:postcode":"60625",
    "sg:province":"IL",
    "sg:tags":[
        "nightlife",
        "cocktail"
    ],
    "wof:name":"Lincoln Square Lanes",
    "wof:placetype":"venue"
},
  "geometry": {"coordinates":[-87.689697,41.970699],"type":"Point"}
}