{
  "type": "Feature",
  "properties": {
    "addr:full":"323 N Central Ave Roxana IL 62084",
    "addr:housenumber":"323",
    "addr:postcode":"62084",
    "addr:street":"N Central Ave",
    "iso:country":"US",
    "sg:address":"323 N Central Ave",
    "sg:city":"Roxana",
    "sg:classifiers":[
        {
            "category":"Restaurant",
            "type":"Food & Drink"
        }
    ],
    "sg:phone":"+1 618 254 5601",
    "sg:postcode":"62084",
    "sg:province":"IL",
    "sg:tags":[
        "parlor",
        "eating",
        "ice",
        "cream"
    ],
    "wof:name":"Cone Barn",
    "wof:placetype":"venue"
},
  "geometry": {"coordinates":[-90.07887700000001,38.849521],"type":"Point"}
}