{
  "type": "Feature",
  "properties": {
    "addr:full":"27866 W Lakeview Dr N Wauconda IL 60084",
    "addr:housenumber":"27866",
    "addr:postcode":"60084",
    "addr:street":"W Lakeview Dr N",
    "iso:country":"US",
    "sg:address":"27866 W Lakeview Dr N",
    "sg:city":"Wauconda",
    "sg:classifiers":[
        {
            "category":"Retail",
            "subcategory":"Repair Shop",
            "type":"Services"
        },
        {
            "category":"Wholesale",
            "subcategory":"Chemicals & Plastics",
            "type":"Manufacturing & Wholesale Goods"
        }
    ],
    "sg:phone":"+1 847 526 8820",
    "sg:postcode":"60084",
    "sg:province":"IL",
    "wof:name":"Air Test Inc",
    "wof:placetype":"venue"
},
  "geometry": {"coordinates":[-88.156856,42.246333],"type":"Point"}
}