{
  "type": "Feature",
  "properties": {
    "addr:full":"3034 N Ashland Ave Chicago IL 60657",
    "addr:housenumber":"3034",
    "addr:postcode":"60657",
    "addr:street":"N Ashland Ave",
    "iso:country":"US",
    "sg:address":"3034 N Ashland Ave",
    "sg:city":"Chicago",
    "sg:classifiers":[
        {
            "category":"Real Estate",
            "subcategory":"Real Estate Operator",
            "type":"Services"
        }
    ],
    "sg:phone":"+1 773 248 1226",
    "sg:postcode":"60657",
    "sg:province":"IL",
    "sg:tags":[
        "apartment"
    ],
    "wof:name":"John Duffin",
    "wof:placetype":"venue"
},
  "geometry": {"coordinates":[-87.66866899999999,41.937784],"type":"Point"}
}