{
  "type": "Feature",
  "properties": {
    "iso:country":"US",
    "sg:address":"37 N Hale St",
    "sg:city":"Palatine",
    "sg:classifiers":[
        {
            "category":"Personal",
            "subcategory":"Beauty Salon",
            "type":"Services"
        }
    ],
    "sg:phone":"+1 847 991 6466",
    "sg:postcode":"60067",
    "sg:province":"IL",
    "wof:name":"Antoinette's Coiffures",
    "wof:placetype":"venue"
},
  "geometry": {"coordinates":[-88.042546,42.111331],"type":"Point"}
}