{
  "type": "Feature",
  "properties": {
    "iso:country":"US",
    "sg:address":"475 N Western Ave",
    "sg:city":"Chicago",
    "sg:phone":"+1 312 563 0606",
    "sg:postcode":"60612",
    "sg:province":"IL",
    "wof:name":"Hardcastle Auto Sales",
    "wof:placetype":"venue"
},
  "geometry": {"coordinates":[-87.686671,41.890372],"type":"Point"}
}