{
  "type": "Feature",
  "properties": {
    "iso:country":"US",
    "sg:address":"222 N Church St",
    "sg:city":"Virden",
    "sg:classifiers":[
        {
            "category":"Government",
            "subcategory":"Office",
            "type":"Public Place"
        }
    ],
    "sg:phone":"+1   ",
    "sg:postcode":"62690",
    "sg:province":"IL",
    "sg:tags":[
        "utility"
    ],
    "wof:name":"Ameren Cips",
    "wof:placetype":"venue"
},
  "geometry": {"coordinates":[-89.76901599999999,39.502834],"type":"Point"}
}