{
  "type": "Feature",
  "properties": {
    "addr:full":"203 N La Salle Street Chicago IL 60601",
    "addr:housenumber":"203",
    "addr:postcode":"60601",
    "addr:street":"N La Salle Street",
    "iso:country":"US",
    "sg:address":"203 N La Salle Street",
    "sg:city":"Chicago",
    "sg:classifiers":[
        {
            "category":"Building & Trades",
            "subcategory":"Construction",
            "type":"Services"
        }
    ],
    "sg:phone":"+1 312 332 0025",
    "sg:postcode":"60601",
    "sg:province":"IL",
    "sg:tags":[
        "contractor"
    ],
    "wof:name":"Lakeside Building Maintenence",
    "wof:placetype":"venue"
},
  "geometry": {"coordinates":[-87.632509,41.885807],"type":"Point"}
}