{
  "type": "Feature",
  "properties": {
    "addr:full":"337 Liberty St Walnut IL 61376",
    "addr:housenumber":"337",
    "addr:postcode":"61376",
    "addr:street":"Liberty St",
    "iso:country":"US",
    "sg:address":"337 Liberty St",
    "sg:city":"Walnut",
    "sg:classifiers":[
        {
            "category":"Autos & Motor Vehicles",
            "subcategory":"Auto Supplies",
            "type":"Retail Goods"
        },
        {
            "category":"Manufacturing",
            "subcategory":"Motor Vehicles & Parts",
            "type":"Manufacturing & Wholesale Goods"
        },
        {
            "category":"Retail",
            "subcategory":"Auto Repair",
            "type":"Services"
        }
    ],
    "sg:phone":"+1 815 379 2023",
    "sg:postcode":"61376",
    "sg:province":"IL",
    "sg:tags":[
        "body",
        "buses-distributors",
        "shop",
        "automobile",
        "buses-parts",
        "equipment",
        "parts",
        "truck",
        "accessories-wholesale",
        "painting",
        "repairing",
        "manufacturer"
    ],
    "wof:name":"Peterson Body Shop",
    "wof:placetype":"venue"
},
  "geometry": {"coordinates":[-89.585494,41.551563],"type":"Point"}
}