{
  "type": "Feature",
  "properties": {
    "addr:full":"6347 W Grand Ave Chicago IL 60639",
    "addr:housenumber":"6347",
    "addr:postcode":"60639",
    "addr:street":"W Grand Ave",
    "iso:country":"US",
    "sg:address":"6347 W Grand Ave",
    "sg:city":"Chicago",
    "sg:classifiers":[
        {
            "category":"Restaurant",
            "type":"Food & Drink"
        }
    ],
    "sg:phone":"+1 773 637 2221",
    "sg:postcode":"60639",
    "sg:province":"IL",
    "sg:tags":[
        "chinese"
    ],
    "wof:name":"Tony's Chinese & American Restaurant",
    "wof:placetype":"venue"
},
  "geometry": {"coordinates":[-87.78469800000001,41.922298],"type":"Point"}
}