{
  "type": "Feature",
  "properties": {
    "addr:full":"3359 S Leavitt Street Chicago IL 60608",
    "addr:housenumber":"3359",
    "addr:postcode":"60608",
    "addr:street":"S Leavitt Street",
    "iso:country":"US",
    "sg:address":"3359 S Leavitt Street",
    "sg:city":"Chicago",
    "sg:classifiers":[
        {
            "category":"Food & Beverages",
            "subcategory":"Candy",
            "type":"Retail Goods"
        }
    ],
    "sg:phone":"+1 773 847 2241",
    "sg:postcode":"60608",
    "sg:province":"IL",
    "sg:tags":[
        "store"
    ],
    "wof:name":"Leavitt Candy Store",
    "wof:placetype":"venue"
},
  "geometry": {"coordinates":[-87.680048,41.832255],"type":"Point"}
}