{
  "type": "Feature",
  "properties": {
    "addr:full":"1454 Miner St Des Plaines IL 60016",
    "addr:housenumber":"1454",
    "addr:postcode":"60016",
    "addr:street":"Miner St",
    "iso:country":"US",
    "sg:address":"1454 Miner St",
    "sg:city":"Des Plaines",
    "sg:classifiers":[
        {
            "category":"Professional",
            "subcategory":"Lawyer & Legal Services",
            "type":"Services"
        }
    ],
    "sg:phone":"+1 847 827 2700",
    "sg:postcode":"60016",
    "sg:province":"IL",
    "wof:name":"Law Office of Jory Ives Chelin",
    "wof:placetype":"venue"
},
  "geometry": {"coordinates":[-87.889033,42.042336],"type":"Point"}
}