{
  "type": "Feature",
  "properties": {
    "iso:country":"US",
    "sg:address":"802 Busse Hwy",
    "sg:city":"Park Ridge",
    "sg:classifiers":[
        {
            "category":"Retail",
            "subcategory":"Portrait Studio",
            "type":"Services"
        }
    ],
    "sg:phone":"+1 847 698 1212",
    "sg:postcode":"60068",
    "sg:province":"IL",
    "sg:tags":[
        "photo"
    ],
    "wof:name":"Lifetouch",
    "wof:placetype":"venue"
},
  "geometry": {"coordinates":[-87.85075000000001,42.021559],"type":"Point"}
}