{
  "type": "Feature",
  "properties": {
    "iso:country":"US",
    "sg:address":"8249 Aster Ln",
    "sg:city":"Tinley Park",
    "sg:classifiers":[
        {
            "category":"Travel",
            "subcategory":"Travel Agent",
            "type":"Entertainment"
        }
    ],
    "sg:phone":"+1 708 532 4500",
    "sg:postcode":"60477",
    "sg:province":"IL",
    "sg:tags":[
        "agency",
        "bureau"
    ],
    "sg:website":"www.angeltravel.com",
    "wof:name":"Angel Travel",
    "wof:placetype":"venue"
},
  "geometry": {"coordinates":[-87.819714,41.572052],"type":"Point"}
}