{
  "type": "Feature",
  "properties": {
    "addr:full":"4404 W Berteau Ave Chicago IL 60641",
    "addr:housenumber":"4404",
    "addr:postcode":"60641",
    "addr:street":"W Berteau Ave",
    "iso:country":"US",
    "sg:address":"4404 W Berteau Ave",
    "sg:city":"Chicago",
    "sg:classifiers":[
        {
            "category":"Freight",
            "type":"Transportation"
        }
    ],
    "sg:phone":"+1 773 685 5835",
    "sg:postcode":"60641",
    "sg:province":"IL",
    "sg:tags":[
        "trucking"
    ],
    "wof:name":"Europe Truck Line",
    "wof:placetype":"venue"
},
  "geometry": {"coordinates":[-87.738708,41.957211],"type":"Point"}
}