{
  "type": "Feature",
  "properties": {
    "iso:country":"US",
    "sg:address":"1509 E 53rd St",
    "sg:city":"Chicago",
    "sg:classifiers":[
        {
            "category":"Professional",
            "type":"Services"
        },
        {
            "category":"Restaurant",
            "type":"Food & Drink"
        },
        {
            "category":"Fast Food",
            "type":"Food & Drink"
        }
    ],
    "sg:phone":"+1 773 955 2200",
    "sg:postcode":"60615",
    "sg:province":"IL",
    "sg:tags":[
        "style",
        "family",
        "fusion",
        "asian",
        "caterer",
        "mongolian",
        "pan",
        "take"
    ],
    "sg:website":"www.chantchicago.com",
    "wof:name":"Chant",
    "wof:placetype":"venue"
},
  "geometry": {"coordinates":[-87.588908,41.799477],"type":"Point"}
}