{
  "type": "Feature",
  "properties": {
    "addr:full":"29538 N Birch Ave Lake Bluff IL 60044",
    "addr:housenumber":"29538",
    "addr:postcode":"60044",
    "addr:street":"N Birch Ave",
    "iso:country":"US",
    "sg:address":"29538 N Birch Ave",
    "sg:city":"Lake Bluff",
    "sg:classifiers":[
        {
            "category":"Banks & Credit Unions",
            "subcategory":"Bank",
            "type":"Services"
        }
    ],
    "sg:phone":"+1 847 283 0755",
    "sg:postcode":"60044",
    "sg:province":"IL",
    "sg:tags":[
        "mortgage"
    ],
    "wof:name":"Choice Best Mortgage",
    "wof:placetype":"venue"
},
  "geometry": {"coordinates":[-87.878573,42.291899],"type":"Point"}
}