{
  "type": "Feature",
  "properties": {
    "iso:country":"US",
    "sg:address":"2323 Mc Daniel Ave",
    "sg:city":"Evanston",
    "sg:classifiers":[
        {
            "category":"Professional",
            "subcategory":"Testing Lab",
            "type":"Services"
        }
    ],
    "sg:phone":"+1 847 869 3221",
    "sg:postcode":"60201",
    "sg:province":"IL",
    "sg:tags":[
        "laboratory"
    ],
    "wof:name":"Norsom Laboratory",
    "wof:placetype":"venue"
},
  "geometry": {"coordinates":[-87.70801899999999,42.060422],"type":"Point"}
}