{
  "type": "Feature",
  "properties": {
    "iso:country":"US",
    "sg:address":"800 W Superior St",
    "sg:city":"Chicago",
    "sg:classifiers":[
        {
            "category":"Retail",
            "subcategory":"Event Space",
            "type":"Services"
        }
    ],
    "sg:phone":"+1 800 799 3463",
    "sg:postcode":"60607",
    "sg:province":"IL",
    "sg:tags":[
        "venue"
    ],
    "sg:website":"www.kaleidoscopeevents.net",
    "wof:name":"Kaleidoscope",
    "wof:placetype":"venue"
},
  "geometry": {"coordinates":[-87.647847,41.895552],"type":"Point"}
}