{
  "type": "Feature",
  "properties": {
    "addr:full":"14101 S Halsted St Riverdale IL 60827",
    "addr:housenumber":"14101",
    "addr:postcode":"60827",
    "addr:street":"S Halsted St",
    "iso:country":"US",
    "sg:address":"14101 S Halsted St",
    "sg:city":"Riverdale",
    "sg:classifiers":[
        {
            "category":"Government",
            "subcategory":"Office",
            "type":"Public Place"
        }
    ],
    "sg:phone":"+1   ",
    "sg:postcode":"60827",
    "sg:province":"IL",
    "sg:tags":[
        "management"
    ],
    "wof:name":"Public Works Department",
    "wof:placetype":"venue"
},
  "geometry": {"coordinates":[-87.641429,41.639364],"type":"Point"}
}