{
  "type": "Feature",
  "properties": {
    "addr:full":"7000 S Cicero Ave Chicago IL 60638",
    "addr:housenumber":"7000",
    "addr:postcode":"60638",
    "addr:street":"S Cicero Ave",
    "iso:country":"US",
    "sg:address":"7000 S Cicero Ave",
    "sg:city":"Chicago",
    "sg:classifiers":[
        {
            "category":"Personal",
            "type":"Services"
        },
        {
            "category":"Retail",
            "subcategory":"Storage",
            "type":"Services"
        }
    ],
    "sg:phone":"+1 877 258 8230",
    "sg:postcode":"60638",
    "sg:province":"IL",
    "sg:tags":[
        "full",
        "self",
        "commercial",
        "mover",
        "household"
    ],
    "sg:website":"http://www.publicstorage.com/?pid=ypcomCPCingenio",
    "wof:name":"Public Storage",
    "wof:placetype":"venue"
},
  "geometry": {"coordinates":[-87.742323,41.764315],"type":"Point"}
}