{
  "type": "Feature",
  "properties": {
    "iso:country":"US",
    "sg:address":"1311 Oak Ridge Rd",
    "sg:city":"Barrington",
    "sg:classifiers":[
        {
            "category":"Professional",
            "subcategory":"Business Services",
            "type":"Services"
        }
    ],
    "sg:phone":"+1 224 848 4086",
    "sg:postcode":"60010",
    "sg:province":"IL",
    "sg:tags":[
        "organizing",
        "services-household"
    ],
    "wof:name":"S.D. Russell Management",
    "wof:placetype":"venue"
},
  "geometry": {"coordinates":[-88.11468499999999,42.150648],"type":"Point"}
}