{
  "type": "Feature",
  "properties": {
    "iso:country":"US",
    "sg:address":"475 W Boughton Rd",
    "sg:city":"Bolingbrook",
    "sg:classifiers":[
        {
            "category":"Professional",
            "type":"Services"
        },
        {
            "category":"Food & Beverages",
            "subcategory":"Groceries & Convenience Stores",
            "type":"Retail Goods"
        },
        {
            "category":"Professional",
            "subcategory":"Business Services",
            "type":"Services"
        },
        {
            "category":"Food & Beverages",
            "subcategory":"Meat & Fish",
            "type":"Retail Goods"
        }
    ],
    "sg:phone":"+1 630 759 4429",
    "sg:postcode":"60440",
    "sg:province":"IL",
    "sg:tags":[
        "butchering",
        "market",
        "caterer"
    ],
    "wof:name":"Bismillah Meat Market",
    "wof:placetype":"venue"
},
  "geometry": {"coordinates":[-88.08637299999999,41.707758],"type":"Point"}
}