{
  "type": "Feature",
  "properties": {
    "iso:country":"US",
    "sg:address":"4316 Squires Green Ct",
    "sg:city":"Richmond",
    "sg:classifiers":[
        {
            "category":"Professional",
            "subcategory":"Art Services",
            "type":"Services"
        }
    ],
    "sg:phone":"+1 815 678 0038",
    "sg:postcode":"60071",
    "sg:province":"IL",
    "sg:tags":[
        "commercial",
        "design"
    ],
    "wof:name":"Extrodianary Art",
    "wof:placetype":"venue"
},
  "geometry": {"coordinates":[-88.282532,42.468351],"type":"Point"}
}