{
  "type": "Feature",
  "properties": {
    "iso:country":"US",
    "sg:address":"18911 Pau Hana Ct",
    "sg:city":"Edelstein",
    "sg:classifiers":[
        {
            "category":"Food & Beverages",
            "subcategory":"Bakery",
            "type":"Retail Goods"
        }
    ],
    "sg:phone":"+1   ",
    "sg:postcode":"61526",
    "sg:province":"IL",
    "wof:name":"Cake Connection",
    "wof:placetype":"venue"
},
  "geometry": {"coordinates":[-89.580536,40.917219],"type":"Point"}
}