{
  "type": "Feature",
  "properties": {
    "addr:full":"5257 S Ashland Ave Chicago IL 60609",
    "addr:housenumber":"5257",
    "addr:postcode":"60609",
    "addr:street":"S Ashland Ave",
    "iso:country":"US",
    "sg:address":"5257 S Ashland Ave",
    "sg:city":"Chicago",
    "sg:classifiers":[
        {
            "category":"Restaurant",
            "type":"Food & Drink"
        }
    ],
    "sg:phone":"+1 773 776 6262",
    "sg:postcode":"60609",
    "sg:province":"IL",
    "sg:tags":[
        "house",
        "steak"
    ],
    "wof:name":"Chicago Steak House",
    "wof:placetype":"venue"
},
  "geometry": {"coordinates":[-87.664697,41.798426],"type":"Point"}
}