{
  "type": "Feature",
  "properties": {
    "iso:country":"US",
    "sg:address":"11801 W Pauling Rd",
    "sg:city":"Manhattan",
    "sg:classifiers":[
        {
            "category":"Shopping",
            "type":"Retail Goods"
        }
    ],
    "sg:phone":"+1   ",
    "sg:postcode":"60442",
    "sg:province":"IL",
    "sg:tags":[
        "merchandise"
    ],
    "wof:name":"Country Pettery",
    "wof:placetype":"venue"
},
  "geometry": {"coordinates":[-87.897717,41.396096],"type":"Point"}
}