{
  "type": "Feature",
  "properties": {
    "iso:country":"US",
    "sg:address":"235 W 61st St",
    "sg:city":"Westmont",
    "sg:classifiers":[
        {
            "category":"Real Estate",
            "subcategory":"Real Estate Services",
            "type":"Services"
        },
        {
            "category":"Real Estate",
            "subcategory":"Real Estate Agent",
            "type":"Services"
        }
    ],
    "sg:phone":"+1 630 963 8073",
    "sg:postcode":"60559",
    "sg:province":"IL",
    "sg:tags":[
        "buyer",
        "management",
        "broker"
    ],
    "wof:name":"Zygmunt Realty 3",
    "wof:placetype":"venue"
},
  "geometry": {"coordinates":[-87.982354,41.777192],"type":"Point"}
}