{
  "type": "Feature",
  "properties": {
    "addr:full":"800 W Washington St Pittsfield IL 62363",
    "addr:housenumber":"800",
    "addr:postcode":"62363",
    "addr:street":"W Washington St",
    "iso:country":"US",
    "sg:address":"800 W Washington St",
    "sg:city":"Pittsfield",
    "sg:classifiers":[
        {
            "category":"Manufacturing",
            "subcategory":"Building Materials",
            "type":"Manufacturing & Wholesale Goods"
        },
        {
            "category":"Home & Garden",
            "subcategory":"Home Furnishings",
            "type":"Retail Goods"
        },
        {
            "category":"Building & Trades",
            "subcategory":"Construction",
            "type":"Services"
        },
        {
            "category":"Retail",
            "subcategory":"Auto Repair",
            "type":"Services"
        },
        {
            "category":"Manufacturing",
            "subcategory":"Glass & Minerals",
            "type":"Manufacturing & Wholesale Goods"
        }
    ],
    "sg:phone":"+1 217 285 2886",
    "sg:postcode":"62363",
    "sg:province":"IL",
    "sg:tags":[
        "plate",
        "installation",
        "windows-repair",
        "window",
        "shower",
        "glass-auto",
        "mirror",
        "door",
        "windshield",
        "enclosure",
        "replacement"
    ],
    "sg:website":"http://www.glassdoctor.com/YPland.htm",
    "wof:name":"Glass Doctor Of West Central Illinois",
    "wof:placetype":"venue"
},
  "geometry": {"coordinates":[-90.817204,39.606794],"type":"Point"}
}