{
  "type": "Feature",
  "properties": {
    "iso:country":"US",
    "sg:address":"786 Centennial Dr",
    "sg:city":"Ottawa",
    "sg:phone":"+1 815 434 0353",
    "sg:postcode":"61350",
    "sg:province":"IL",
    "sg:tags":[
        "oil",
        "gasoline"
    ],
    "wof:name":"Etna Oil Co",
    "wof:placetype":"venue"
},
  "geometry": {"coordinates":[-88.823877,41.374023],"type":"Point"}
}