{
  "type": "Feature",
  "properties": {
    "addr:full":"3007 S Kostner Ave Chicago IL 60623",
    "addr:housenumber":"3007",
    "addr:postcode":"60623",
    "addr:street":"S Kostner Ave",
    "iso:country":"US",
    "sg:address":"3007 S Kostner Ave",
    "sg:city":"Chicago",
    "sg:classifiers":[
        {
            "category":"Professional",
            "subcategory":"Lawyer & Legal Services",
            "type":"Services"
        }
    ],
    "sg:phone":"+1 773 254 3348",
    "sg:postcode":"60623",
    "sg:province":"IL",
    "sg:tags":[
        "living",
        "estate",
        "planning",
        "trust",
        "probate"
    ],
    "wof:name":"Preservation Commitee",
    "wof:placetype":"venue"
},
  "geometry": {"coordinates":[-87.73409599999999,41.83843],"type":"Point"}
}