{
  "type": "Feature",
  "properties": {
    "addr:full":"1211 S Mattis Champaign IL 61821",
    "addr:housenumber":"1211",
    "addr:postcode":"61821",
    "addr:street":"S Mattis",
    "iso:country":"US",
    "sg:address":"1211 S Mattis",
    "sg:city":"Champaign",
    "sg:classifiers":[
        {
            "category":"Restaurant",
            "type":"Food & Drink"
        }
    ],
    "sg:phone":"+1 217 352 5544",
    "sg:postcode":"61821",
    "sg:province":"IL",
    "sg:tags":[
        "pizza"
    ],
    "sg:website":"www.littlecaesars.com",
    "wof:name":"Little Caesars Pizza",
    "wof:placetype":"venue"
},
  "geometry": {"coordinates":[-88.276554,40.103585],"type":"Point"}
}