{
  "type": "Feature",
  "properties": {
    "addr:full":"1115 Morse Ave Schaumburg IL 60193",
    "addr:housenumber":"1115",
    "addr:postcode":"60193",
    "addr:street":"Morse Ave",
    "iso:country":"US",
    "sg:address":"1115 Morse Ave",
    "sg:city":"Schaumburg",
    "sg:classifiers":[
        {
            "category":"Wholesale",
            "subcategory":"Machinery & Supplies",
            "type":"Manufacturing & Wholesale Goods"
        },
        {
            "category":"Manufacturing",
            "subcategory":"Tools & Machinery",
            "type":"Manufacturing & Wholesale Goods"
        }
    ],
    "sg:phone":"+1 847 891 7500",
    "sg:postcode":"60193",
    "sg:province":"IL",
    "sg:tags":[
        "control",
        "environmental",
        "fitting",
        "valve",
        "mfg"
    ],
    "sg:website":"www.cedampers.com",
    "wof:name":"Control Equipment Company Inc",
    "wof:placetype":"venue"
},
  "geometry": {"coordinates":[-88.104924,41.999981],"type":"Point"}
}