{
  "type": "Feature",
  "properties": {
    "addr:full":"2718 Broadway St Blue Island IL 60406",
    "addr:housenumber":"2718",
    "addr:postcode":"60406",
    "addr:street":"Broadway St",
    "iso:country":"US",
    "sg:address":"2718 Broadway St",
    "sg:city":"Blue Island",
    "sg:classifiers":[
        {
            "category":"Building & Trades",
            "subcategory":"Construction",
            "type":"Services"
        }
    ],
    "sg:phone":"+1 708 597 6713",
    "sg:postcode":"60406",
    "sg:province":"IL",
    "sg:tags":[
        "house"
    ],
    "wof:name":"Jac Home Remodeling",
    "wof:placetype":"venue"
},
  "geometry": {"coordinates":[-87.687101,41.650148],"type":"Point"}
}