{
  "type": "Feature",
  "properties": {
    "iso:country":"US",
    "sg:address":"1179 W Kennedy Rd",
    "sg:city":"Braidwood",
    "sg:classifiers":[
        {
            "category":"Travel",
            "subcategory":"Hotels & Motels",
            "type":"Entertainment"
        }
    ],
    "sg:phone":"+1 815 458 3401",
    "sg:postcode":"60408",
    "sg:province":"IL",
    "sg:tags":[
        "operation"
    ],
    "wof:name":"Sands Motel",
    "wof:placetype":"venue"
},
  "geometry": {"coordinates":[-88.24296,41.259507],"type":"Point"}
}