{
  "type": "Feature",
  "properties": {
    "iso:country":"US",
    "sg:address":"2101 S Illinois Ave",
    "sg:city":"Carbondale",
    "sg:classifiers":[
        {
            "category":"Food & Beverages",
            "subcategory":"Groceries & Convenience Stores",
            "type":"Retail Goods"
        }
    ],
    "sg:phone":"+1 618 351 1074",
    "sg:postcode":"62903",
    "sg:province":"IL",
    "wof:name":"Banga Petro",
    "wof:placetype":"venue"
},
  "geometry": {"coordinates":[-89.21892,37.70014],"type":"Point"}
}