{
  "type": "Feature",
  "properties": {
    "addr:full":"415 N Sangamon St Chicago IL 60642",
    "addr:housenumber":"415",
    "addr:postcode":"60642",
    "addr:street":"N Sangamon St",
    "iso:country":"US",
    "sg:address":"415 N Sangamon St",
    "sg:city":"Chicago",
    "sg:classifiers":[
        {
            "category":"Food & Beverages",
            "subcategory":"Liquor & Beverages",
            "type":"Retail Goods"
        },
        {
            "category":"Organizations",
            "subcategory":"Professional Association",
            "type":"Services"
        }
    ],
    "sg:phone":"+1 312 455 0893",
    "sg:postcode":"60642",
    "sg:province":"IL",
    "sg:tags":[
        "sale"
    ],
    "wof:name":"Falcon Equipment Supplies",
    "wof:placetype":"venue"
},
  "geometry": {"coordinates":[-87.65107500000001,41.889462],"type":"Point"}
}