{
  "type": "Feature",
  "properties": {
    "addr:full":"7777 Winn Rd Spring Grove IL 60081",
    "addr:housenumber":"7777",
    "addr:postcode":"60081",
    "addr:street":"Winn Rd",
    "iso:country":"US",
    "sg:address":"7777 Winn Rd",
    "sg:city":"Spring Grove",
    "sg:classifiers":[
        {
            "category":"Manufacturing",
            "subcategory":"Tools & Machinery",
            "type":"Manufacturing & Wholesale Goods"
        }
    ],
    "sg:phone":"+1 815 675 2321",
    "sg:postcode":"60081",
    "sg:province":"IL",
    "sg:tags":[
        "lighting",
        "fixture"
    ],
    "sg:website":"www.intermatic.org",
    "wof:name":"Intermatic Inc",
    "wof:placetype":"venue"
},
  "geometry": {"coordinates":[-88.247533,42.44018],"type":"Point"}
}