{
  "type": "Feature",
  "properties": {
    "iso:country":"US",
    "sg:address":"9717 S Western Avenue",
    "sg:city":"Chicago",
    "sg:classifiers":[
        {
            "category":"Health Services",
            "subcategory":"Doctor",
            "type":"Services"
        }
    ],
    "sg:phone":"+1 773 239 5495",
    "sg:postcode":"60643",
    "sg:province":"IL",
    "wof:name":"Midland Orthopedics Assoc",
    "wof:placetype":"venue"
},
  "geometry": {"coordinates":[-87.68168300000001,41.716423],"type":"Point"}
}