{
  "type": "Feature",
  "properties": {
    "addr:full":"309 N Seymour Ave Mundelein IL 60060",
    "addr:housenumber":"309",
    "addr:postcode":"60060",
    "addr:street":"N Seymour Ave",
    "iso:country":"US",
    "sg:address":"309 N Seymour Ave",
    "sg:city":"Mundelein",
    "sg:classifiers":[
        {
            "category":"Banks & Credit Unions",
            "subcategory":"Financial Services",
            "type":"Services"
        }
    ],
    "sg:phone":"+1 847 970 4261",
    "sg:postcode":"60060",
    "sg:province":"IL",
    "sg:tags":[
        "landlord"
    ],
    "wof:name":"945 Lakeview Partnership",
    "wof:placetype":"venue"
},
  "geometry": {"coordinates":[-88.00245700000001,42.269501],"type":"Point"}
}