{
  "type": "Feature",
  "properties": {
    "addr:full":"7824 Madison St Forest Park IL 60130",
    "addr:housenumber":"7824",
    "addr:postcode":"60130",
    "addr:street":"Madison St",
    "iso:country":"US",
    "sg:address":"7824 Madison St",
    "sg:city":"Forest Park",
    "sg:classifiers":[
        {
            "category":"Health Services",
            "subcategory":"Nursing And Care Facility",
            "type":"Services"
        }
    ],
    "sg:phone":"+1 708 366 2206",
    "sg:postcode":"60130",
    "sg:province":"IL",
    "sg:tags":[
        "home",
        "retirement",
        "community"
    ],
    "wof:name":"Altenheim",
    "wof:placetype":"venue"
},
  "geometry": {"coordinates":[-87.819543,41.879268],"type":"Point"}
}