{
  "type": "Feature",
  "properties": {
    "iso:country":"US",
    "sg:address":"103 S Commercial St",
    "sg:city":"Centralia",
    "sg:classifiers":[
        {
            "category":"Insurance",
            "subcategory":"Insurance Agent",
            "type":"Services"
        }
    ],
    "sg:phone":"+1 618 532 7307",
    "sg:postcode":"62801",
    "sg:province":"IL",
    "wof:name":"Alcorn Insurance",
    "wof:placetype":"venue"
},
  "geometry": {"coordinates":[-89.13055,38.547267],"type":"Point"}
}