{
  "type": "Feature",
  "properties": {
    "iso:country":"US",
    "sg:address":"1525 Windy Hill Dr",
    "sg:city":"Northbrook",
    "sg:classifiers":[
        {
            "category":"Professional",
            "subcategory":"Management & Consulting",
            "type":"Services"
        },
        {
            "category":"Banks & Credit Unions",
            "subcategory":"Financial Services",
            "type":"Services"
        }
    ],
    "sg:phone":"+1 847 412 4660",
    "sg:postcode":"60062",
    "sg:province":"IL",
    "sg:tags":[
        "consultant",
        "financing",
        "mortgage"
    ],
    "wof:name":"Premier Lending Group, Inc.",
    "wof:placetype":"venue"
},
  "geometry": {"coordinates":[-87.81629700000001,42.12228],"type":"Point"}
}