{
  "type": "Feature",
  "properties": {
    "addr:full":"760 W Holbrook Rd Glenwood IL 60425",
    "addr:housenumber":"760",
    "addr:postcode":"60425",
    "addr:street":"W Holbrook Rd",
    "iso:country":"US",
    "sg:address":"760 W Holbrook Rd",
    "sg:city":"Glenwood",
    "sg:classifiers":[
        {
            "category":"Building & Trades",
            "subcategory":"Construction",
            "type":"Services"
        }
    ],
    "sg:phone":"+1 708 756 7800",
    "sg:postcode":"60425",
    "sg:province":"IL",
    "sg:tags":[
        "roofing",
        "contractor"
    ],
    "wof:name":"M & M Windows & Siding",
    "wof:placetype":"venue"
},
  "geometry": {"coordinates":[-87.629447,41.538709],"type":"Point"}
}