{
  "type": "Feature",
  "properties": {
    "iso:country":"US",
    "sg:address":"824 W Oakdale Ave",
    "sg:city":"Chicago",
    "sg:classifiers":[
        {
            "category":"Travel",
            "subcategory":"Travel Agent",
            "type":"Entertainment"
        }
    ],
    "sg:phone":"+1 773 929 9300",
    "sg:postcode":"60657",
    "sg:province":"IL",
    "sg:tags":[
        "agency"
    ],
    "wof:name":"Big Tomato Travel Consultants",
    "wof:placetype":"venue"
},
  "geometry": {"coordinates":[-87.649108,41.935458],"type":"Point"}
}