{
  "type": "Feature",
  "properties": {
    "addr:full":"805 7th St Charleston IL 61920",
    "addr:housenumber":"805",
    "addr:postcode":"61920",
    "addr:street":"7Th St",
    "iso:country":"US",
    "sg:address":"805 7th St",
    "sg:city":"Charleston",
    "sg:classifiers":[
        {
            "category":"Retail",
            "subcategory":"Repair Shop",
            "type":"Services"
        }
    ],
    "sg:phone":"+1 217 345 9244",
    "sg:postcode":"61920",
    "sg:province":"IL",
    "sg:tags":[
        "cleaners",
        "parts",
        "vacuum"
    ],
    "wof:name":"Electrolux",
    "wof:placetype":"venue"
},
  "geometry": {"coordinates":[-88.17395999999999,39.491627],"type":"Point"}
}