{
  "type": "Feature",
  "properties": {
    "addr:full":"4101 W 95th St Oak Lawn IL 60453",
    "addr:housenumber":"4101",
    "addr:postcode":"60453",
    "addr:street":"W 95Th St",
    "iso:country":"US",
    "sg:address":"4101 W 95th St",
    "sg:city":"Oak Lawn",
    "sg:classifiers":[
        {
            "category":"Shopping",
            "subcategory":"Shoes",
            "type":"Retail Goods"
        }
    ],
    "sg:phone":"+1 708 422 7630",
    "sg:postcode":"60453",
    "sg:province":"IL",
    "sg:tags":[
        "store"
    ],
    "sg:website":"www.payless.com",
    "wof:name":"Payless Shoesource",
    "wof:placetype":"venue"
},
  "geometry": {"coordinates":[-87.726196,41.720299],"type":"Point"}
}