{
  "type": "Feature",
  "properties": {
    "iso:country":"US",
    "sg:address":"13907 Kostner Ave",
    "sg:city":"Midlothian",
    "sg:classifiers":[
        {
            "category":"Autos & Motor Vehicles",
            "subcategory":"Auto Supplies",
            "type":"Retail Goods"
        },
        {
            "category":"Military Area",
            "subcategory":"Naval Base",
            "type":"Public Place"
        }
    ],
    "sg:phone":"+1 708 385 2030",
    "sg:postcode":"60445",
    "sg:province":"IL",
    "sg:tags":[
        "equipment",
        "part",
        "trailer",
        "hitch"
    ],
    "sg:website":"http://www.brettequipment.com",
    "wof:name":"Brett Equipment Corp",
    "wof:placetype":"venue"
},
  "geometry": {"coordinates":[-87.72804600000001,41.639857],"type":"Point"}
}