{
  "type": "Feature",
  "properties": {
    "iso:country":"US",
    "sg:address":"2900 Macarthur Blvd",
    "sg:city":"Northbrook",
    "sg:classifiers":[
        {
            "category":"Manufacturing",
            "subcategory":"Tools & Machinery",
            "type":"Manufacturing & Wholesale Goods"
        }
    ],
    "sg:phone":"+1 847 559 1777",
    "sg:postcode":"60062",
    "sg:province":"IL",
    "sg:tags":[
        "industrial",
        "molding",
        "mfg",
        "plastic",
        "pump",
        "injection",
        "custom"
    ],
    "wof:name":"Pacer Pumps",
    "wof:placetype":"venue"
},
  "geometry": {"coordinates":[-87.853149,42.148286],"type":"Point"}
}