{
  "type": "Feature",
  "properties": {
    "addr:full":"200 W Monroe St Chicago IL 60606",
    "addr:housenumber":"200",
    "addr:postcode":"60606",
    "addr:street":"W Monroe St",
    "iso:country":"US",
    "sg:address":"200 W Monroe St",
    "sg:city":"Chicago",
    "sg:classifiers":[
        {
            "category":"Professional",
            "subcategory":"Computer Services",
            "type":"Services"
        }
    ],
    "sg:phone":"+1 312 706 3600",
    "sg:postcode":"60606",
    "sg:province":"IL",
    "sg:tags":[
        "web",
        "design",
        "hosting",
        "site"
    ],
    "sg:website":"http://www.gnxj.com",
    "wof:name":"Global Exchange",
    "wof:placetype":"venue"
},
  "geometry": {"coordinates":[-87.633781,41.88068],"type":"Point"}
}