{
  "type": "Feature",
  "properties": {
    "iso:country":"US",
    "sg:address":"4043 N Kenmore Ave 2",
    "sg:city":"Chicago",
    "sg:classifiers":[
        {
            "category":"Banks & Credit Unions",
            "subcategory":"Investment Brokerage",
            "type":"Services"
        },
        {
            "category":"Insurance",
            "subcategory":"Hazard Insurance",
            "type":"Services"
        }
    ],
    "sg:phone":"+1 312 656 9543",
    "sg:postcode":"60613",
    "sg:province":"IL",
    "sg:tags":[
        "agent",
        "resume"
    ],
    "wof:name":"Theodore Carpenter",
    "wof:placetype":"venue"
},
  "geometry": {"coordinates":[-87.656029,41.954642],"type":"Point"}
}