{
  "type": "Feature",
  "properties": {
    "addr:full":"152 W Old Higgins Rd Des Plaines IL 60018",
    "addr:housenumber":"152",
    "addr:postcode":"60018",
    "addr:street":"W Old Higgins Rd Des",
    "iso:country":"US",
    "sg:address":"152 W Old Higgins Rd",
    "sg:city":"Des Plaines",
    "sg:classifiers":[
        {
            "category":"Freight",
            "type":"Transportation"
        }
    ],
    "sg:phone":"+1 847 299 4750",
    "sg:postcode":"60018",
    "sg:province":"IL",
    "sg:tags":[
        "terminal"
    ],
    "wof:name":"Tax Airfreight Inc",
    "wof:placetype":"venue"
},
  "geometry": {"coordinates":[-87.923434,42.004185],"type":"Point"}
}