{
  "type": "Feature",
  "properties": {
    "iso:country":"US",
    "sg:address":"720 W McAllister St",
    "sg:city":"Lebanon",
    "sg:classifiers":[
        {
            "category":"Wholesale",
            "subcategory":"Groceries",
            "type":"Manufacturing & Wholesale Goods"
        }
    ],
    "sg:phone":"+1 618 537 6121",
    "sg:postcode":"62254",
    "sg:province":"IL",
    "sg:tags":[
        "food",
        "product"
    ],
    "wof:name":"PFD Supply",
    "wof:placetype":"venue"
},
  "geometry": {"coordinates":[-89.81715699999999,38.594074],"type":"Point"}
}