{
  "type": "Feature",
  "properties": {
    "iso:country":"US",
    "sg:address":"5145 N Lincoln Avenue Bsmt",
    "sg:city":"Chicago",
    "sg:classifiers":[
        {
            "category":"Building & Trades",
            "subcategory":"Locksmith",
            "type":"Services"
        }
    ],
    "sg:phone":"+1 773 728 6171",
    "sg:postcode":"60625",
    "sg:province":"IL",
    "sg:tags":[
        "key"
    ],
    "wof:name":"Ace Door Check & Locksmith",
    "wof:placetype":"venue"
},
  "geometry": {"coordinates":[-87.69226999999999,41.975057],"type":"Point"}
}