{
  "type": "Feature",
  "properties": {
    "iso:country":"US",
    "sg:address":"1115 North Blvd",
    "sg:city":"Oak Park",
    "sg:classifiers":[
        {
            "category":"Railroad",
            "type":"Transportation"
        }
    ],
    "sg:phone":"+1 708 386 0424",
    "sg:postcode":"60301",
    "sg:province":"IL",
    "sg:tags":[
        "rail"
    ],
    "wof:name":"Oakpark Station",
    "wof:placetype":"venue"
},
  "geometry": {"coordinates":[-87.804717,41.887044],"type":"Point"}
}