{
  "type": "Feature",
  "properties": {
    "addr:full":"1308 W 7th St Dixon IL 61021",
    "addr:housenumber":"1308",
    "addr:postcode":"61021",
    "addr:street":"W 7Th St",
    "iso:country":"US",
    "sg:address":"1308 W 7th St",
    "sg:city":"Dixon",
    "sg:classifiers":[
        {
            "category":"Building & Trades",
            "subcategory":"Electrical",
            "type":"Services"
        }
    ],
    "sg:phone":"+1 815 288 1405",
    "sg:postcode":"61021",
    "sg:province":"IL",
    "sg:tags":[
        "electrical",
        "electric",
        "contractor"
    ],
    "wof:name":"Dixon Commercial Electric Inc",
    "wof:placetype":"venue"
},
  "geometry": {"coordinates":[-89.49512199999999,41.8343],"type":"Point"}
}