{
  "type": "Feature",
  "properties": {
    "iso:country":"US",
    "sg:address":"121 N Main St",
    "sg:city":"Georgetown",
    "sg:classifiers":[
        {
            "category":"Cinema",
            "subcategory":"Movie Rental",
            "type":"Entertainment"
        }
    ],
    "sg:phone":"+1 217 662 6600",
    "sg:postcode":"61846",
    "sg:province":"IL",
    "sg:tags":[
        "leasing",
        "video",
        "disc",
        "tape"
    ],
    "wof:name":"Hollywood Video",
    "wof:placetype":"venue"
},
  "geometry": {"coordinates":[-87.63554999999999,39.9754],"type":"Point"}
}