{
  "type": "Feature",
  "properties": {
    "iso:country":"US",
    "sg:address":"1812 Fenwick Ct",
    "sg:city":"Schaumburg",
    "sg:classifiers":[
        {
            "category":"Health Services",
            "subcategory":"Nursing And Care Facility",
            "type":"Services"
        }
    ],
    "sg:phone":"+1 847 310 9929",
    "sg:postcode":"60194",
    "sg:province":"IL",
    "sg:tags":[
        "clinic",
        "mental"
    ],
    "wof:name":"Integrated Behavorial Mgt",
    "wof:placetype":"venue"
},
  "geometry": {"coordinates":[-88.124901,42.04224],"type":"Point"}
}