{
  "type": "Feature",
  "properties": {
    "addr:full":"217 E Norris Dr Ottawa IL 61350",
    "addr:housenumber":"217",
    "addr:postcode":"61350",
    "addr:street":"E Norris Dr",
    "iso:country":"US",
    "sg:address":"217 E Norris Dr",
    "sg:city":"Ottawa",
    "sg:classifiers":[
        {
            "category":"Restaurant",
            "type":"Food & Drink"
        }
    ],
    "sg:phone":"+1 815 434 6887",
    "sg:postcode":"61350",
    "sg:province":"IL",
    "wof:name":"Bianchi's Pizza",
    "wof:placetype":"venue"
},
  "geometry": {"coordinates":[-88.838492,41.356124],"type":"Point"}
}