{
  "type": "Feature",
  "properties": {
    "iso:country":"US",
    "sg:address":"600 Lakeview Pkwy",
    "sg:city":"Vernon Hills",
    "sg:classifiers":[
        {
            "category":"Retail",
            "subcategory":"Auto Repair",
            "type":"Services"
        }
    ],
    "sg:phone":"+1 847 816 0011",
    "sg:postcode":"60061",
    "sg:province":"IL",
    "sg:tags":[
        "repairing",
        "automobile"
    ],
    "sg:website":"www.cmauto.com",
    "wof:name":"C & M Auto Svc",
    "wof:placetype":"venue"
},
  "geometry": {"coordinates":[-87.947552,42.236082],"type":"Point"}
}