{
  "type": "Feature",
  "properties": {
    "iso:country":"US",
    "sg:address":"312 Chestnut St",
    "sg:city":"Barrington",
    "sg:classifiers":[
        {
            "category":"Education",
            "subcategory":"School",
            "type":"Public Place"
        }
    ],
    "sg:phone":"+1 847 381 0311",
    "sg:postcode":"60010",
    "sg:province":"IL",
    "wof:name":"St Anne's Catholic School",
    "wof:placetype":"venue"
},
  "geometry": {"coordinates":[-88.131352,42.154989],"type":"Point"}
}