{
  "type": "Feature",
  "properties": {
    "addr:full":"3401 N Ridge Ave Arlington Hts IL 60004",
    "addr:housenumber":"3401",
    "addr:postcode":"60004",
    "addr:street":"N Ridge Ave",
    "iso:country":"US",
    "sg:address":"3401 N Ridge Ave",
    "sg:city":"Arlington Hts",
    "sg:classifiers":[
        {
            "category":"Manufacturing",
            "subcategory":"Rubber & Plastics",
            "type":"Manufacturing & Wholesale Goods"
        }
    ],
    "sg:phone":"+1 847 394 2843",
    "sg:postcode":"60004",
    "sg:province":"IL",
    "wof:name":"C & J Molding Corp",
    "wof:placetype":"venue"
},
  "geometry": {"coordinates":[-87.99134100000001,42.136129],"type":"Point"}
}