{
  "type": "Feature",
  "properties": {
    "iso:country":"US",
    "sg:address":"320 S Ardmore Ave",
    "sg:city":"Villa Park",
    "sg:classifiers":[
        {
            "category":"Shopping",
            "type":"Retail Goods"
        }
    ],
    "sg:phone":"+1   ",
    "sg:postcode":"60181",
    "sg:province":"IL",
    "sg:tags":[
        "merchandise"
    ],
    "wof:name":"Ecale Studio",
    "wof:placetype":"venue"
},
  "geometry": {"coordinates":[-87.979064,41.884658],"type":"Point"}
}