{
  "type": "Feature",
  "properties": {
    "addr:full":"Corner of Montrose and Keeler Chicago IL 60641",
    "addr:postcode":"60641",
    "addr:street":"Corner",
    "iso:country":"US",
    "sg:address":"Corner of Montrose and Keeler",
    "sg:city":"Chicago",
    "sg:classifiers":[
        {
            "category":"Personal",
            "subcategory":"Barber",
            "type":"Services"
        }
    ],
    "sg:postcode":"60641",
    "sg:province":"IL",
    "wof:name":"Ray Fade Inc.",
    "wof:placetype":"venue"
},
  "geometry": {"coordinates":[-87.73258800000001,41.96079],"type":"Point"}
}