{
  "type": "Feature",
  "properties": {
    "iso:country":"US",
    "sg:address":"36771 N Kerwin Dr",
    "sg:city":"Ingleside",
    "sg:classifiers":[
        {
            "category":"Professional",
            "subcategory":"Business Services",
            "type":"Services"
        }
    ],
    "sg:phone":"+1 847 973 2106",
    "sg:postcode":"60041",
    "sg:province":"IL",
    "sg:tags":[
        "auctioneer"
    ],
    "wof:name":"Lee O Neuroth",
    "wof:placetype":"venue"
},
  "geometry": {"coordinates":[-88.133252,42.396732],"type":"Point"}
}