{
  "type": "Feature",
  "properties": {
    "iso:country":"US",
    "sg:address":"690 Revere St",
    "sg:city":"Bourbonnais",
    "sg:classifiers":[
        {
            "category":"Real Estate",
            "subcategory":"Real Estate Operator",
            "type":"Services"
        }
    ],
    "sg:phone":"+1 815 935 2439",
    "sg:postcode":"60914",
    "sg:province":"IL",
    "sg:tags":[
        "apartment"
    ],
    "wof:name":"Stratford Apartments",
    "wof:placetype":"venue"
},
  "geometry": {"coordinates":[-87.893135,41.175943],"type":"Point"}
}