{
  "type": "Feature",
  "properties": {
    "iso:country":"US",
    "sg:address":"2660 Raleigh Rd",
    "sg:city":"Eldorado",
    "sg:classifiers":[
        {
            "category":"Building & Trades",
            "subcategory":"Construction",
            "type":"Services"
        },
        {
            "category":"Home & Garden",
            "subcategory":"Household Appliances",
            "type":"Retail Goods"
        },
        {
            "category":"Retail",
            "subcategory":"Laundry & Dry Cleaning",
            "type":"Services"
        },
        {
            "category":"Home & Garden",
            "subcategory":"Carpets & Floor Coverings",
            "type":"Retail Goods"
        },
        {
            "category":"Manufacturing",
            "subcategory":"Tools & Machinery",
            "type":"Manufacturing & Wholesale Goods"
        },
        {
            "category":"Utilities",
            "subcategory":"Water",
            "type":"Services"
        },
        {
            "category":"Personal",
            "type":"Services"
        },
        {
            "category":"Building & Trades",
            "subcategory":"Cleaning & Sanitation",
            "type":"Services"
        }
    ],
    "sg:phone":"+1 618 273 2859",
    "sg:postcode":"62930",
    "sg:province":"IL",
    "sg:tags":[
        "control",
        "cleaner",
        "duct",
        "house",
        "mold",
        "janitorial",
        "site-clean-up",
        "equipment",
        "damage",
        "contractor",
        "extraction",
        "window",
        "cleaning-industrial",
        "curtain",
        "drapery",
        "counteracting",
        "emergency",
        "fire",
        "cleaners-water",
        "odor",
        "rug",
        "restoration",
        "vacuum",
        "remediation",
        "upholstery",
        "flood",
        "air",
        "waxing",
        "ventilation",
        "smoke",
        "polishing"
    ],
    "sg:website":"https://smclean.custhelp.com/cgi-bin/smclean.cfg/php/enduser/doc_serve.php?2=BSYellowPages09",
    "wof:name":"ServiceMaster Clean",
    "wof:placetype":"venue"
},
  "geometry": {"coordinates":[-88.486717,37.82107],"type":"Point"}
}