{
  "type": "Feature",
  "properties": {
    "addr:full":"7334 W Pershing Rd Lyons IL 60534",
    "addr:housenumber":"7334",
    "addr:postcode":"60534",
    "addr:street":"W Pershing Rd",
    "iso:country":"US",
    "sg:address":"7334 W Pershing Rd",
    "sg:city":"Lyons",
    "sg:classifiers":[
        {
            "category":"Bars & Pubs",
            "type":"Food & Drink"
        }
    ],
    "sg:phone":"+1   ",
    "sg:postcode":"60534",
    "sg:province":"IL",
    "sg:tags":[
        "bar"
    ],
    "wof:name":"J & R Amusement",
    "wof:placetype":"venue"
},
  "geometry": {"coordinates":[-87.806133,41.821199],"type":"Point"}
}