{
  "type": "Feature",
  "properties": {
    "addr:full":"2510 W Irving Park Road Chicago IL 60618",
    "addr:housenumber":"2510",
    "addr:postcode":"60618",
    "addr:street":"W Irving Park Road",
    "iso:country":"US",
    "sg:address":"2510 W Irving Park Road",
    "sg:city":"Chicago",
    "sg:classifiers":[
        {
            "category":"Health Services",
            "subcategory":"Doctor",
            "type":"Services"
        }
    ],
    "sg:phone":"+1 773 583 6955",
    "sg:postcode":"60618",
    "sg:province":"IL",
    "wof:name":"Badilla Marjerie MD",
    "wof:placetype":"venue"
},
  "geometry": {"coordinates":[-87.69130199999999,41.954064],"type":"Point"}
}