{
  "type": "Feature",
  "properties": {
    "iso:country":"US",
    "sg:address":"740 Maple Ave",
    "sg:city":"Rushville",
    "sg:classifiers":[
        {
            "category":"Education",
            "subcategory":"School",
            "type":"Public Place"
        }
    ],
    "sg:phone":"+1 217 322 4311",
    "sg:postcode":"62681",
    "sg:province":"IL",
    "sg:tags":[
        "secondary"
    ],
    "wof:name":"School Board Office",
    "wof:placetype":"venue"
},
  "geometry": {"coordinates":[-90.565619,40.127082],"type":"Point"}
}