{
  "type": "Feature",
  "properties": {
    "iso:country":"US",
    "sg:address":"11 W Ferguson Ave",
    "sg:city":"Wood River",
    "sg:classifiers":[
        {
            "category":"Professional",
            "subcategory":"Lawyer & Legal Services",
            "type":"Services"
        }
    ],
    "sg:phone":"+1 618 254 5446",
    "sg:postcode":"62095",
    "sg:province":"IL",
    "sg:tags":[
        "attorney"
    ],
    "wof:name":"Thornberry Law",
    "wof:placetype":"venue"
},
  "geometry": {"coordinates":[-90.0998,38.861002],"type":"Point"}
}