{
  "type": "Feature",
  "properties": {
    "addr:full":"299 Fleetwood Ln Elk Grove Village IL 60007",
    "addr:housenumber":"299",
    "addr:postcode":"60007",
    "addr:street":"Fleetwood Ln",
    "iso:country":"US",
    "sg:address":"299 Fleetwood Ln",
    "sg:city":"Elk Grove Village",
    "sg:classifiers":[
        {
            "category":"Building & Trades",
            "subcategory":"Cleaning & Sanitation",
            "type":"Services"
        }
    ],
    "sg:phone":"+1 847 640 0939",
    "sg:postcode":"60007",
    "sg:province":"IL",
    "sg:tags":[
        "maintenance"
    ],
    "wof:name":"Kr Cleaning Crew Inc",
    "wof:placetype":"venue"
},
  "geometry": {"coordinates":[-87.97560300000001,42.015111],"type":"Point"}
}