{
  "type": "Feature",
  "properties": {
    "addr:full":"540 S Rand Rd Wauconda IL 60084",
    "addr:housenumber":"540",
    "addr:postcode":"60084",
    "addr:street":"S Rand Rd",
    "iso:country":"US",
    "sg:address":"540 S Rand Rd",
    "sg:city":"Wauconda",
    "sg:classifiers":[
        {
            "category":"Professional",
            "subcategory":"Advertising",
            "type":"Services"
        },
        {
            "category":"Autos & Motor Vehicles",
            "subcategory":"Auto Supplies",
            "type":"Retail Goods"
        }
    ],
    "sg:phone":"+1 847 526 5151",
    "sg:postcode":"60084",
    "sg:province":"IL",
    "sg:tags":[
        "shell",
        "hitch",
        "liner",
        "caps",
        "truck",
        "accessory",
        "trailer"
    ],
    "sg:website":"http://www.nwtruckworld.com",
    "wof:name":"Northwest Truck World",
    "wof:placetype":"venue"
},
  "geometry": {"coordinates":[-88.138474,42.249249],"type":"Point"}
}