{
  "type": "Feature",
  "properties": {
    "iso:country":"US",
    "sg:address":"1580 S Milwaukee Ave",
    "sg:city":"Libertyville",
    "sg:classifiers":[
        {
            "category":"Wholesale",
            "subcategory":"Non-durable Goods",
            "type":"Manufacturing & Wholesale Goods"
        },
        {
            "category":"Professional",
            "subcategory":"Advertising",
            "type":"Services"
        }
    ],
    "sg:phone":"+1 847 522 7562",
    "sg:postcode":"60048",
    "sg:province":"IL",
    "sg:tags":[
        "counselor"
    ],
    "wof:name":"R J Greco Inc",
    "wof:placetype":"venue"
},
  "geometry": {"coordinates":[-87.947748,42.25817],"type":"Point"}
}