{
  "type": "Feature",
  "properties": {
    "addr:full":"140 Tyler Creek Plz Elgin IL 60123",
    "addr:housenumber":"140",
    "addr:postcode":"60123",
    "addr:street":"Tyler Creek Plz",
    "iso:country":"US",
    "sg:address":"140 Tyler Creek Plz",
    "sg:city":"Elgin",
    "sg:classifiers":[
        {
            "category":"Retail",
            "subcategory":"Pet Boarding",
            "type":"Services"
        }
    ],
    "sg:phone":"+1 847 931 0556",
    "sg:postcode":"60123",
    "sg:province":"IL",
    "sg:tags":[
        "boarding/pet",
        "sitting"
    ],
    "wof:name":"Jenny the Groomer",
    "wof:placetype":"venue"
},
  "geometry": {"coordinates":[-88.314903,42.059601],"type":"Point"}
}