{
  "type": "Feature",
  "properties": {
    "addr:full":"1549 W Division St Chicago IL 60622",
    "addr:housenumber":"1549",
    "addr:postcode":"60622",
    "addr:street":"W Division St",
    "iso:country":"US",
    "sg:address":"1549 W Division St",
    "sg:city":"Chicago",
    "sg:classifiers":[
        {
            "category":"Restaurant",
            "type":"Food & Drink"
        }
    ],
    "sg:phone":"+1 773 486 6655",
    "sg:postcode":"60622",
    "sg:province":"IL",
    "sg:tags":[
        "polish"
    ],
    "wof:name":"Podhalanka",
    "wof:placetype":"venue"
},
  "geometry": {"coordinates":[-87.666472,41.903356],"type":"Point"}
}