{
  "type": "Feature",
  "properties": {
    "addr:full":"218 Bruce Dr White Hall IL 62092",
    "addr:housenumber":"218",
    "addr:postcode":"62092",
    "addr:street":"Bruce Dr",
    "iso:country":"US",
    "sg:address":"218 Bruce Dr",
    "sg:city":"White Hall",
    "sg:classifiers":[
        {
            "category":"Professional",
            "type":"Services"
        }
    ],
    "sg:phone":"+1 217 374 2709",
    "sg:postcode":"62092",
    "sg:province":"IL",
    "wof:name":"Pathway Services Unlimited",
    "wof:placetype":"venue"
},
  "geometry": {"coordinates":[-90.414063,39.440602],"type":"Point"}
}