{
  "type": "Feature",
  "properties": {
    "iso:country":"US",
    "sg:address":"128 Berkshire Dr",
    "sg:city":"Belleville",
    "sg:classifiers":[
        {
            "category":"Building & Trades",
            "subcategory":"Construction",
            "type":"Services"
        }
    ],
    "sg:phone":"+1 618 234 9624",
    "sg:postcode":"62223",
    "sg:province":"IL",
    "sg:tags":[
        "commercial",
        "contractor"
    ],
    "wof:name":"Custom Design Inc",
    "wof:placetype":"venue"
},
  "geometry": {"coordinates":[-90.047299,38.534552],"type":"Point"}
}