{
  "type": "Feature",
  "properties": {
    "iso:country":"US",
    "sg:address":"912 Trakk Ln",
    "sg:city":"Woodstock",
    "sg:classifiers":[
        {
            "category":"Building & Trades",
            "subcategory":"Electrical",
            "type":"Services"
        }
    ],
    "sg:phone":"+1 815 338 6317",
    "sg:postcode":"60098",
    "sg:province":"IL",
    "sg:tags":[
        "electrician"
    ],
    "wof:name":"B & Z Electrical",
    "wof:placetype":"venue"
},
  "geometry": {"coordinates":[-88.4838,42.339133],"type":"Point"}
}