{
  "type": "Feature",
  "properties": {
    "iso:country":"US",
    "sg:address":"110 W Court St",
    "sg:city":"Eureka",
    "sg:classifiers":[
        {
            "category":"Building & Trades",
            "subcategory":"Plumbing",
            "type":"Services"
        }
    ],
    "sg:phone":"+1 309 467 3450",
    "sg:postcode":"61530",
    "sg:province":"IL",
    "sg:tags":[
        "contractor"
    ],
    "wof:name":"Klaus & Sons Plumbing & Htg",
    "wof:placetype":"venue"
},
  "geometry": {"coordinates":[-89.272966,40.722331],"type":"Point"}
}