{
  "type": "Feature",
  "properties": {
    "addr:full":"25305 W Eames St Channahon IL 60410",
    "addr:housenumber":"25305",
    "addr:postcode":"60410",
    "addr:street":"W Eames St",
    "iso:country":"US",
    "sg:address":"25305 W Eames St",
    "sg:city":"Channahon",
    "sg:classifiers":[
        {
            "category":"Home & Garden",
            "subcategory":"Hardware",
            "type":"Retail Goods"
        }
    ],
    "sg:phone":"+1 815 467 5991",
    "sg:postcode":"60410",
    "sg:province":"IL",
    "sg:tags":[
        "store"
    ],
    "wof:name":"Channahon True Value Hardware",
    "wof:placetype":"venue"
},
  "geometry": {"coordinates":[-88.24009700000001,41.420101],"type":"Point"}
}