{
  "type": "Feature",
  "properties": {
    "iso:country":"US",
    "sg:address":"15704 N Von Achen Dr",
    "sg:city":"Chillicothe",
    "sg:classifiers":[
        {
            "category":"Retail",
            "subcategory":"Auto Repair",
            "type":"Services"
        }
    ],
    "sg:phone":"+1 309 274 9550",
    "sg:postcode":"61523",
    "sg:province":"IL",
    "sg:tags":[
        "body",
        "automobile",
        "painting"
    ],
    "wof:name":"Precision Collision",
    "wof:placetype":"venue"
},
  "geometry": {"coordinates":[-89.506022,40.878065],"type":"Point"}
}