{
  "type": "Feature",
  "properties": {
    "addr:full":"8102 Lemont Rd Woodridge IL 60517",
    "addr:housenumber":"8102",
    "addr:postcode":"60517",
    "addr:street":"Lemont Rd",
    "iso:country":"US",
    "sg:address":"8102 Lemont Rd",
    "sg:city":"Woodridge",
    "sg:classifiers":[
        {
            "category":"Shopping",
            "type":"Retail Goods"
        }
    ],
    "sg:phone":"+1 630 427 1036",
    "sg:postcode":"60517",
    "sg:province":"IL",
    "sg:tags":[
        "equipment",
        "mining",
        "supply"
    ],
    "wof:name":"Dry Systems Technologies",
    "wof:placetype":"venue"
},
  "geometry": {"coordinates":[-88.012519,41.74282],"type":"Point"}
}