{
  "type": "Feature",
  "properties": {
    "iso:country":"US",
    "sg:address":"7300 N Western Ave Ste A",
    "sg:city":"Chicago",
    "sg:classifiers":[
        {
            "category":"Wholesale",
            "subcategory":"Wine & Distilled Alcoholic Beverages",
            "type":"Manufacturing & Wholesale Goods"
        }
    ],
    "sg:phone":"+1 773 764 2933",
    "sg:postcode":"60645",
    "sg:province":"IL",
    "sg:tags":[
        "liquors-wholesale"
    ],
    "wof:name":"Extra Value Co",
    "wof:placetype":"venue"
},
  "geometry": {"coordinates":[-87.690231,42.014099],"type":"Point"}
}