{
  "type": "Feature",
  "properties": {
    "iso:country":"US",
    "sg:address":"130 S Chicago St",
    "sg:city":"Lincoln",
    "sg:classifiers":[
        {
            "category":"Banks & Credit Unions",
            "subcategory":"Bank",
            "type":"Services"
        }
    ],
    "sg:phone":"+1 217 732 2033",
    "sg:postcode":"62656",
    "sg:province":"IL",
    "sg:tags":[
        "financing"
    ],
    "wof:name":"Sun Loan Co",
    "wof:placetype":"venue"
},
  "geometry": {"coordinates":[-89.363723,40.147181],"type":"Point"}
}