{
  "type": "Feature",
  "properties": {
    "iso:country":"US",
    "sg:address":"2160 E 71st St",
    "sg:city":"Chicago",
    "sg:classifiers":[
        {
            "category":"Food & Beverages",
            "subcategory":"Groceries & Convenience Stores",
            "type":"Retail Goods"
        }
    ],
    "sg:phone":"+1 773 363 5360",
    "sg:postcode":"60649",
    "sg:province":"IL",
    "wof:name":"Southshore Pantry",
    "wof:placetype":"venue"
},
  "geometry": {"coordinates":[-87.571701,41.766102],"type":"Point"}
}