{
  "type": "Feature",
  "properties": {
    "addr:full":"921 W 87th St Chicago IL 60620",
    "addr:housenumber":"921",
    "addr:postcode":"60620",
    "addr:street":"W 87Th St",
    "iso:country":"US",
    "sg:address":"921 W 87th St",
    "sg:city":"Chicago",
    "sg:classifiers":[
        {
            "category":"Building & Trades",
            "subcategory":"Locksmith",
            "type":"Services"
        }
    ],
    "sg:phone":"+1 773 896 9550",
    "sg:postcode":"60620",
    "sg:province":"IL",
    "sg:tags":[
        "key"
    ],
    "wof:name":"Always Available 24 Hour Emergency Locksmi",
    "wof:placetype":"venue"
},
  "geometry": {"coordinates":[-87.646936,41.735836],"type":"Point"}
}