{
  "type": "Feature",
  "properties": {
    "iso:country":"US",
    "sg:address":"2153 75th St",
    "sg:city":"Darien",
    "sg:classifiers":[
        {
            "category":"Retail",
            "subcategory":"Veterinary Services",
            "type":"Services"
        }
    ],
    "sg:phone":"+1 630 271 1233",
    "sg:postcode":"60561",
    "sg:province":"IL",
    "sg:tags":[
        "veterinarian"
    ],
    "sg:website":"http://www.banfield.net/ypoffer/?source=yp",
    "wof:name":"Banfield the Pet Hospital",
    "wof:placetype":"venue"
},
  "geometry": {"coordinates":[-87.965084,41.752111],"type":"Point"}
}