{
  "type": "Feature",
  "properties": {
    "addr:full":"3528 Summit Ave Belleville IL 62226",
    "addr:housenumber":"3528",
    "addr:postcode":"62226",
    "addr:street":"Summit Ave",
    "iso:country":"US",
    "sg:address":"3528 Summit Ave",
    "sg:city":"Belleville",
    "sg:classifiers":[
        {
            "category":"Building & Trades",
            "subcategory":"Construction",
            "type":"Services"
        }
    ],
    "sg:phone":"+1 618 277 8781",
    "sg:postcode":"62226",
    "sg:province":"IL",
    "sg:tags":[
        "hanging",
        "contractor"
    ],
    "wof:name":"Magic Painting Inc",
    "wof:placetype":"venue"
},
  "geometry": {"coordinates":[-90.013046,38.534951],"type":"Point"}
}