{
  "type": "Feature",
  "properties": {
    "iso:country":"US",
    "sg:address":"109 Oakdale Rd",
    "sg:city":"Washington",
    "sg:classifiers":[
        {
            "category":"Health Services",
            "subcategory":"Doctor",
            "type":"Services"
        }
    ],
    "sg:phone":"+1 309 252 1000",
    "sg:postcode":"61571",
    "sg:province":"IL",
    "sg:tags":[
        "physician",
        "surgeon"
    ],
    "wof:name":"Mark Canty Md Ltd",
    "wof:placetype":"venue"
},
  "geometry": {"coordinates":[-89.487994,40.692386],"type":"Point"}
}