{
  "type": "Feature",
  "properties": {
    "addr:full":"9650 S Kedzie Ave Evergreen Park IL 60805",
    "addr:housenumber":"9650",
    "addr:postcode":"60805",
    "addr:street":"S Kedzie Ave",
    "iso:country":"US",
    "sg:address":"9650 S Kedzie Ave",
    "sg:city":"Evergreen Park",
    "sg:classifiers":[
        {
            "category":"Restaurant",
            "type":"Food & Drink"
        }
    ],
    "sg:phone":"+1 708 636 8180",
    "sg:postcode":"60805",
    "sg:province":"IL",
    "sg:tags":[
        "thai",
        "japanese",
        "chinese"
    ],
    "sg:website":"www.chitung.com",
    "wof:name":"Chi Tung",
    "wof:placetype":"venue"
},
  "geometry": {"coordinates":[-87.701739,41.717643],"type":"Point"}
}