{
  "type": "Feature",
  "properties": {
    "iso:country":"US",
    "sg:address":"1022 4th St",
    "sg:city":"Orion",
    "sg:classifiers":[
        {
            "category":"Home & Garden",
            "subcategory":"Carpets & Floor Coverings",
            "type":"Retail Goods"
        }
    ],
    "sg:phone":"+1 309 526 3131",
    "sg:postcode":"61273",
    "sg:province":"IL",
    "sg:tags":[
        "dealer",
        "rug"
    ],
    "wof:name":"Carpet Time",
    "wof:placetype":"venue"
},
  "geometry": {"coordinates":[-90.38153200000001,41.35457],"type":"Point"}
}