{
  "type": "Feature",
  "properties": {
    "iso:country":"US",
    "sg:address":"9137 Belden Ave",
    "sg:city":"Franklin Park",
    "sg:classifiers":[
        {
            "category":"Retail",
            "subcategory":"Repair Shop",
            "type":"Services"
        }
    ],
    "sg:phone":"+1 847 455 7777",
    "sg:postcode":"60131",
    "sg:province":"IL",
    "sg:tags":[
        "welding"
    ],
    "wof:name":"Northwestern Welding Inc",
    "wof:placetype":"venue"
},
  "geometry": {"coordinates":[-87.855467,41.919398],"type":"Point"}
}