{
  "type": "Feature",
  "properties": {
    "addr:full":"6015 W 31st St Cicero IL 60804",
    "addr:housenumber":"6015",
    "addr:postcode":"60804",
    "addr:street":"W 31St St",
    "iso:country":"US",
    "sg:address":"6015 W 31st St",
    "sg:city":"Cicero",
    "sg:classifiers":[
        {
            "category":"Retail",
            "subcategory":"Auto Repair",
            "type":"Services"
        }
    ],
    "sg:phone":"+1 708 652 3988",
    "sg:postcode":"60804",
    "sg:province":"IL",
    "sg:tags":[
        "body",
        "shop"
    ],
    "wof:name":"Gto Body & Mechanical Shop",
    "wof:placetype":"venue"
},
  "geometry": {"coordinates":[-87.77330000000001,41.836102],"type":"Point"}
}