{
  "type": "Feature",
  "properties": {
    "iso:country":"US",
    "sg:address":"912 Sherman Ave",
    "sg:city":"Evanston",
    "sg:classifiers":[
        {
            "category":"Personal",
            "subcategory":"Beauty Salon",
            "type":"Services"
        }
    ],
    "sg:phone":"+1 847 475 4771",
    "sg:postcode":"60202",
    "sg:province":"IL",
    "sg:tags":[
        "shop"
    ],
    "wof:name":"Cocos Hair Studio",
    "wof:placetype":"venue"
},
  "geometry": {"coordinates":[-87.682228,42.035566],"type":"Point"}
}