{
  "type": "Feature",
  "properties": {
    "iso:country":"US",
    "sg:address":"3130 N Lincoln Ave",
    "sg:city":"Chicago",
    "sg:classifiers":[
        {
            "category":"Health Services",
            "subcategory":"Health Practitioner",
            "type":"Services"
        }
    ],
    "sg:phone":"+1 773 525 5200",
    "sg:postcode":"60657",
    "sg:province":"IL",
    "sg:tags":[
        "therapy",
        "physical"
    ],
    "sg:website":"www.balancechicago.com",
    "wof:name":"Lifestyle Physical Therapy",
    "wof:placetype":"venue"
},
  "geometry": {"coordinates":[-87.667348,41.938589],"type":"Point"}
}