{
  "type": "Feature",
  "properties": {
    "iso:country":"US",
    "sg:address":"104 W Madison St",
    "sg:city":"Mackinaw",
    "sg:classifiers":[
        {
            "category":"Government",
            "subcategory":"Fire Station",
            "type":"Public Place"
        },
        {
            "category":"Government",
            "subcategory":"Office",
            "type":"Public Place"
        }
    ],
    "sg:phone":"+1 309 359 3571",
    "sg:postcode":"61755",
    "sg:province":"IL",
    "sg:tags":[
        "department",
        "township",
        "protection",
        "government-city",
        "village"
    ],
    "wof:name":"Mackinaw Fire Protection Dst",
    "wof:placetype":"venue"
},
  "geometry": {"coordinates":[-89.360596,40.53579],"type":"Point"}
}