{
  "type": "Feature",
  "properties": {
    "iso:country":"US",
    "sg:address":"3832 Dobson St",
    "sg:city":"Skokie",
    "sg:classifiers":[
        {
            "category":"Wholesale",
            "subcategory":"Chemicals & Plastics",
            "type":"Manufacturing & Wholesale Goods"
        }
    ],
    "sg:phone":"+1 847 568 1047",
    "sg:postcode":"60076",
    "sg:province":"IL",
    "wof:name":"Chem Trade Global",
    "wof:placetype":"venue"
},
  "geometry": {"coordinates":[-87.725217,42.019998],"type":"Point"}
}