{
  "type": "Feature",
  "properties": {
    "addr:full":"8200 S South Shore Dr Chicago IL 60617",
    "addr:housenumber":"8200",
    "addr:postcode":"60617",
    "addr:street":"S South Shore Dr",
    "iso:country":"US",
    "sg:address":"8200 S South Shore Dr",
    "sg:city":"Chicago",
    "sg:classifiers":[
        {
            "category":"Place Of Worship",
            "subcategory":"Church",
            "type":"Public Place"
        },
        {
            "category":"Place Of Worship",
            "type":"Public Place"
        }
    ],
    "sg:phone":"+1 773 221 8999",
    "sg:postcode":"60617",
    "sg:province":"IL",
    "sg:tags":[
        "churches-baptist-general",
        "churches-non-denominational",
        "churches-baptist"
    ],
    "wof:name":"Grace Haitienne Alliance Ch",
    "wof:placetype":"venue"
},
  "geometry": {"coordinates":[-87.54789700000001,41.746521],"type":"Point"}
}