{
  "type": "Feature",
  "properties": {
    "iso:country":"US",
    "sg:address":"906 SW 3rd St",
    "sg:city":"Aledo",
    "sg:classifiers":[
        {
            "category":"Government",
            "subcategory":"Police Station",
            "type":"Public Place"
        }
    ],
    "sg:phone":"+1 309 582 3500",
    "sg:postcode":"61231",
    "sg:province":"IL",
    "sg:tags":[
        "department"
    ],
    "wof:name":"Crime Stoppers Of Mercer Cnty",
    "wof:placetype":"venue"
},
  "geometry": {"coordinates":[-90.759753,41.199959],"type":"Point"}
}