{
  "type": "Feature",
  "properties": {
    "iso:country":"US",
    "sg:address":"14189 Route 138",
    "sg:city":"Gillespie",
    "sg:classifiers":[
        {
            "category":"Manufacturing",
            "subcategory":"Food",
            "type":"Manufacturing & Wholesale Goods"
        },
        {
            "category":"Farming",
            "subcategory":"Farm",
            "type":"Manufacturing & Wholesale Goods"
        }
    ],
    "sg:phone":"+1 618 362 6467",
    "sg:postcode":"62033",
    "sg:province":"IL",
    "sg:tags":[
        "corn",
        "product"
    ],
    "wof:name":"Paul Alexander",
    "wof:placetype":"venue"
},
  "geometry": {"coordinates":[-89.878946,39.070959],"type":"Point"}
}