{
  "type": "Feature",
  "properties": {
    "iso:country":"US",
    "sg:address":"6 Bridlewood Trl",
    "sg:city":"Barrington",
    "sg:classifiers":[
        {
            "category":"Wholesale",
            "subcategory":"Medical Equipment & Supplies",
            "type":"Manufacturing & Wholesale Goods"
        }
    ],
    "sg:phone":"+1 847 381 0504",
    "sg:postcode":"60010",
    "sg:province":"IL",
    "sg:tags":[
        "hospital"
    ],
    "wof:name":"S & H Medical Limited",
    "wof:placetype":"venue"
},
  "geometry": {"coordinates":[-88.146272,42.096512],"type":"Point"}
}