{
  "type": "Feature",
  "properties": {
    "iso:country":"US",
    "sg:address":"210 1st Ave",
    "sg:city":"Forreston",
    "sg:classifiers":[
        {
            "category":"Insurance",
            "subcategory":"Insurance Agent",
            "type":"Services"
        }
    ],
    "sg:phone":"+1 815 938 2219",
    "sg:postcode":"61030",
    "sg:province":"IL",
    "wof:name":"Robert L Sandell Agency",
    "wof:placetype":"venue"
},
  "geometry": {"coordinates":[-89.579249,42.126235],"type":"Point"}
}