{
  "type": "Feature",
  "properties": {
    "addr:full":"PO Box 47863 Chicago IL 60647",
    "addr:housenumber":"po box",
    "addr:postcode":"47863;60647",
    "iso:country":"US",
    "sg:address":"PO Box 47863",
    "sg:city":"Chicago",
    "sg:classifiers":[
        {
            "category":"Sports & Exercise",
            "subcategory":"Sports Center",
            "type":"Entertainment"
        }
    ],
    "sg:postcode":"60647",
    "sg:province":"IL",
    "sg:tags":[
        "amateur",
        "team"
    ],
    "sg:website":"www.windycityrollers.com",
    "wof:name":"Windy City Rollers",
    "wof:placetype":"venue"
},
  "geometry": {"coordinates":[-87.701655,41.921482],"type":"Point"}
}