{
  "type": "Feature",
  "properties": {
    "addr:full":"6714 N Northwest Hwy Chicago IL 60631",
    "addr:housenumber":"6714",
    "addr:postcode":"60631",
    "addr:street":"N Northwest Hwy",
    "iso:country":"US",
    "sg:address":"6714 N Northwest Hwy",
    "sg:city":"Chicago",
    "sg:classifiers":[
        {
            "category":"Retail",
            "subcategory":"Auto Repair",
            "type":"Services"
        }
    ],
    "sg:phone":"+1 773 775 2277",
    "sg:postcode":"60631",
    "sg:province":"IL",
    "wof:name":"Northwest Car Care",
    "wof:placetype":"venue"
},
  "geometry": {"coordinates":[-87.816498,42.002998],"type":"Point"}
}