{
  "type": "Feature",
  "properties": {
    "iso:country":"US",
    "sg:address":"1874 Co Rd 1600 N",
    "sg:city":"Urbana",
    "sg:classifiers":[
        {
            "category":"Building & Trades",
            "subcategory":"Electrical",
            "type":"Services"
        }
    ],
    "sg:phone":"+1 217 344 8803",
    "sg:postcode":"61802",
    "sg:province":"IL",
    "sg:tags":[
        "electrical",
        "contractor"
    ],
    "wof:name":"Able Aire Services",
    "wof:placetype":"venue"
},
  "geometry": {"coordinates":[-88.109943,40.113444],"type":"Point"}
}