{
  "type": "Feature",
  "properties": {
    "addr:full":"1 American Way Elgin IL 60120",
    "addr:housenumber":"1",
    "addr:postcode":"60120",
    "addr:street":"American Way",
    "iso:country":"US",
    "sg:address":"1 American Way",
    "sg:city":"Elgin",
    "sg:classifiers":[
        {
            "category":"Health Services",
            "subcategory":"Doctor",
            "type":"Services"
        }
    ],
    "sg:phone":"+1 847 742 8211",
    "sg:postcode":"60120",
    "sg:province":"IL",
    "sg:tags":[
        "surgeon",
        "oral"
    ],
    "wof:name":"Sula Daniel DDS",
    "wof:placetype":"venue"
},
  "geometry": {"coordinates":[-88.257103,42.045799],"type":"Point"}
}