{
  "type": "Feature",
  "properties": {
    "addr:full":"3109 Twin Oaks Dr Joliet IL 60435",
    "addr:housenumber":"3109",
    "addr:postcode":"60435",
    "addr:street":"Twin Oaks Dr",
    "iso:country":"US",
    "sg:address":"3109 Twin Oaks Dr",
    "sg:city":"Joliet",
    "sg:classifiers":[
        {
            "category":"Health Services",
            "subcategory":"Doctor",
            "type":"Services"
        }
    ],
    "sg:phone":"+1 815 725 3109",
    "sg:postcode":"60435",
    "sg:province":"IL",
    "sg:tags":[
        "medical"
    ],
    "wof:name":"Richard A Tarizzo MD",
    "wof:placetype":"venue"
},
  "geometry": {"coordinates":[-88.15786900000001,41.524361],"type":"Point"}
}