{
  "type": "Feature",
  "properties": {
    "iso:country":"US",
    "sg:address":"956 N Neltnor Blvd",
    "sg:city":"West Chicago",
    "sg:classifiers":[
        {
            "category":"Food & Beverages",
            "subcategory":"Meat & Fish",
            "type":"Retail Goods"
        }
    ],
    "sg:phone":"+1 630 293 3294",
    "sg:postcode":"60185",
    "sg:province":"IL",
    "sg:tags":[
        "hot",
        "dog"
    ],
    "sg:website":"www.mrhotdog.net",
    "wof:name":"The Mr. Hot Dog",
    "wof:placetype":"venue"
},
  "geometry": {"coordinates":[-88.19487700000001,41.869952],"type":"Point"}
}