{
  "type": "Feature",
  "properties": {
    "iso:country":"US",
    "sg:address":"2013 N 17th St",
    "sg:city":"Swansea",
    "sg:classifiers":[
        {
            "category":"Restaurant",
            "type":"Food & Drink"
        }
    ],
    "sg:phone":"+1 618 233 9465",
    "sg:postcode":"62226",
    "sg:province":"IL",
    "sg:tags":[
        "delivery"
    ],
    "sg:website":"www.steakout.com",
    "wof:name":"Right Way Steaks",
    "wof:placetype":"venue"
},
  "geometry": {"coordinates":[-90.001913,38.541137],"type":"Point"}
}