{
  "type": "Feature",
  "properties": {
    "addr:full":"8129 S Francisco Ave Chicago IL 60652",
    "addr:housenumber":"8129",
    "addr:postcode":"60652",
    "addr:street":"S Francisco Ave",
    "iso:country":"US",
    "sg:address":"8129 S Francisco Ave",
    "sg:city":"Chicago",
    "sg:classifiers":[
        {
            "category":"Home & Garden",
            "subcategory":"Building Materials",
            "type":"Retail Goods"
        }
    ],
    "sg:phone":"+1 773 255 9491",
    "sg:postcode":"60652",
    "sg:province":"IL",
    "sg:tags":[
        "bathroom",
        "cabinet",
        "fixtures",
        "accessory"
    ],
    "wof:name":"Closet, The",
    "wof:placetype":"venue"
},
  "geometry": {"coordinates":[-87.69494400000001,41.745744],"type":"Point"}
}