{
  "type": "Feature",
  "properties": {
    "iso:country":"US",
    "sg:address":"105 W Adams St Ste 1400",
    "sg:city":"Chicago",
    "sg:classifiers":[
        {
            "category":"Professional",
            "subcategory":"Lawyer & Legal Services",
            "type":"Services"
        }
    ],
    "sg:phone":"+1 312 205 1010",
    "sg:postcode":"60603",
    "sg:province":"IL",
    "wof:name":"Coston and Rademacher",
    "wof:placetype":"venue"
},
  "geometry": {"coordinates":[-87.630912,41.879302],"type":"Point"}
}