{
  "type": "Feature",
  "properties": {
    "iso:country":"US",
    "sg:address":"3003 Corporate West Dr",
    "sg:city":"Lisle",
    "sg:classifiers":[
        {
            "category":"Restaurant",
            "type":"Food & Drink"
        }
    ],
    "sg:phone":"+1 630 848 9597",
    "sg:postcode":"60532",
    "sg:province":"IL",
    "sg:tags":[
        "house",
        "seafood",
        "buffet",
        "lunch",
        "american",
        "brunch",
        "steak",
        "breakfast"
    ],
    "sg:website":"http://chicago.citysearch.com/profile/external/3616829/lisle_il/allgauer_s.html?publisher=yellowpages&reference_id=1&placement=ypwebsitemip",
    "wof:name":"Allgauer's",
    "wof:placetype":"venue"
},
  "geometry": {"coordinates":[-88.110472,41.808263],"type":"Point"}
}