{
  "type": "Feature",
  "properties": {
    "iso:country":"US",
    "sg:address":"31 W Downer Pl",
    "sg:city":"Aurora",
    "sg:classifiers":[
        {
            "category":"Real Estate",
            "subcategory":"Real Estate Agent",
            "type":"Services"
        },
        {
            "category":"Insurance",
            "subcategory":"Insurance Agent",
            "type":"Services"
        }
    ],
    "sg:phone":"+1 630 892 6060",
    "sg:postcode":"60506",
    "sg:province":"IL",
    "sg:tags":[
        "property",
        "manager",
        "agency",
        "appraiser",
        "es"
    ],
    "wof:name":"Fox Valley Appraisals",
    "wof:placetype":"venue"
},
  "geometry": {"coordinates":[-88.317408,41.75779],"type":"Point"}
}