{
  "type": "Feature",
  "properties": {
    "iso:country":"US",
    "sg:address":"1815 E Riverside Blvd",
    "sg:city":"Rockford",
    "sg:classifiers":[
        {
            "category":"Professional",
            "subcategory":"Secretarial Services",
            "type":"Services"
        }
    ],
    "sg:phone":"+1 815 877 6578",
    "sg:postcode":"61114",
    "sg:province":"IL",
    "sg:tags":[
        "hearing",
        "reporter"
    ],
    "wof:name":"Marguerite J Smith",
    "wof:placetype":"venue"
},
  "geometry": {"coordinates":[-89.028109,42.318183],"type":"Point"}
}