{
  "type": "Feature",
  "properties": {
    "addr:full":"7361 Prescott Ln Countryside IL 60525",
    "addr:housenumber":"7361",
    "addr:postcode":"60525",
    "addr:street":"Prescott Ln",
    "iso:country":"US",
    "sg:address":"7361 Prescott Ln",
    "sg:city":"Countryside",
    "sg:classifiers":[
        {
            "category":"Professional",
            "subcategory":"Management & Consulting",
            "type":"Services"
        }
    ],
    "sg:phone":"+1 708 354 0664",
    "sg:postcode":"60525",
    "sg:province":"IL",
    "sg:tags":[
        "consultant",
        "educational"
    ],
    "wof:name":"Educational Consultants",
    "wof:placetype":"venue"
},
  "geometry": {"coordinates":[-87.883976,41.756166],"type":"Point"}
}