{
  "type": "Feature",
  "properties": {
    "addr:full":"706 Crystal Ct Shorewood IL 60404",
    "addr:housenumber":"706",
    "addr:postcode":"60404",
    "addr:street":"Crystal Ct",
    "iso:country":"US",
    "sg:address":"706 Crystal Ct",
    "sg:city":"Shorewood",
    "sg:classifiers":[
        {
            "category":"Building & Trades",
            "subcategory":"Construction",
            "type":"Services"
        }
    ],
    "sg:phone":"+1 815 919 2493",
    "sg:postcode":"60404",
    "sg:province":"IL",
    "sg:tags":[
        "repairing",
        "remodeling",
        "contractor"
    ],
    "wof:name":"Archers Custom Builders",
    "wof:placetype":"venue"
},
  "geometry": {"coordinates":[-88.20827,41.540655],"type":"Point"}
}