{
  "type": "Feature",
  "properties": {
    "iso:country":"US",
    "sg:address":"8990 Old River Rd",
    "sg:city":"Rockford",
    "sg:classifiers":[
        {
            "category":"Shopping",
            "subcategory":"Bicycles & Sporting Goods",
            "type":"Retail Goods"
        }
    ],
    "sg:phone":"+1   ",
    "sg:postcode":"61103",
    "sg:province":"IL",
    "sg:tags":[
        "eating",
        "sport",
        "golf",
        "public"
    ],
    "wof:name":"Atwood Homestead Golf Course",
    "wof:placetype":"venue"
},
  "geometry": {"coordinates":[-89.059393,42.393081],"type":"Point"}
}