{
  "type": "Feature",
  "properties": {
    "addr:full":"1415 W Irving Park Rd Chicago IL 60613",
    "addr:housenumber":"1415",
    "addr:postcode":"60613",
    "addr:street":"W Irving Park Rd",
    "iso:country":"US",
    "sg:address":"1415 W Irving Park Rd",
    "sg:city":"Chicago",
    "sg:classifiers":[
        {
            "category":"Retail",
            "subcategory":"Laundry & Dry Cleaning",
            "type":"Services"
        }
    ],
    "sg:phone":"+1 773 404 1210",
    "sg:postcode":"60613",
    "sg:province":"IL",
    "wof:name":"Sun Cleaners",
    "wof:placetype":"venue"
},
  "geometry": {"coordinates":[-87.66480300000001,41.954201],"type":"Point"}
}