{
  "type": "Feature",
  "properties": {
    "addr:full":"701 W South St Havana IL 62644",
    "addr:housenumber":"701",
    "addr:postcode":"62644",
    "addr:street":"W South St",
    "iso:country":"US",
    "sg:address":"701 W South St",
    "sg:city":"Havana",
    "sg:classifiers":[
        {
            "category":"Manufacturing",
            "subcategory":"Motor Vehicles & Parts",
            "type":"Manufacturing & Wholesale Goods"
        }
    ],
    "sg:phone":"+1 309 543 3306",
    "sg:postcode":"62644",
    "sg:province":"IL",
    "sg:tags":[
        "recreational"
    ],
    "wof:name":"Tracer Industries Inc",
    "wof:placetype":"venue"
},
  "geometry": {"coordinates":[-90.069165,40.286052],"type":"Point"}
}