{
  "type": "Feature",
  "properties": {
    "addr:full":"1528 20th Ave Rockford IL 61104",
    "addr:housenumber":"1528",
    "addr:postcode":"61104",
    "addr:street":"20Th Ave",
    "iso:country":"US",
    "sg:address":"1528 20th Ave",
    "sg:city":"Rockford",
    "sg:classifiers":[
        {
            "category":"Retail",
            "subcategory":"Auto Repair",
            "type":"Services"
        }
    ],
    "sg:phone":"+1 815 962 8085",
    "sg:postcode":"61104",
    "sg:province":"IL",
    "sg:tags":[
        "electric",
        "generator",
        "automobile",
        "electrical",
        "rebuilds",
        "starter"
    ],
    "wof:name":"Rockford Automotive Ltd",
    "wof:placetype":"venue"
},
  "geometry": {"coordinates":[-89.07265599999999,42.245783],"type":"Point"}
}