{
  "type": "Feature",
  "properties": {
    "addr:full":"304 Main St Waltonville IL 62894",
    "addr:housenumber":"304",
    "addr:postcode":"62894",
    "addr:street":"Main St",
    "iso:country":"US",
    "sg:address":"304 Main St",
    "sg:city":"Waltonville",
    "sg:classifiers":[
        {
            "category":"Government",
            "subcategory":"Fire Station",
            "type":"Public Place"
        }
    ],
    "sg:phone":"+1 618 279 3402",
    "sg:postcode":"62894",
    "sg:province":"IL",
    "sg:tags":[
        "department"
    ],
    "wof:name":"Waltonville Fire Dept",
    "wof:placetype":"venue"
},
  "geometry": {"coordinates":[-89.037814,38.20895],"type":"Point"}
}