{
  "type": "Feature",
  "properties": {
    "addr:full":"6950 Central Park Ave Lincolnwood IL 60712",
    "addr:housenumber":"6950",
    "addr:postcode":"60712",
    "addr:street":"Central Park Ave",
    "iso:country":"US",
    "sg:address":"6950 Central Park Ave",
    "sg:city":"Lincolnwood",
    "sg:classifiers":[
        {
            "category":"Manufacturing",
            "subcategory":"Tools & Machinery",
            "type":"Manufacturing & Wholesale Goods"
        }
    ],
    "sg:phone":"+1 847 674 2170",
    "sg:postcode":"60712",
    "sg:province":"IL",
    "sg:tags":[
        "equipment",
        "commercial",
        "laundry",
        "mfg"
    ],
    "wof:name":"Resillo Press Pad Co",
    "wof:placetype":"venue"
},
  "geometry": {"coordinates":[-87.719092,42.005363],"type":"Point"}
}