{
  "type": "Feature",
  "properties": {
    "iso:country":"US",
    "sg:address":"111 S Halsted St",
    "sg:city":"Chicago",
    "sg:classifiers":[
        {
            "category":"Shopping",
            "subcategory":"Pharmacy",
            "type":"Retail Goods"
        }
    ],
    "sg:phone":"+1 312 463 9142",
    "sg:postcode":"60661",
    "sg:province":"IL",
    "sg:tags":[
        "drugstore"
    ],
    "sg:website":"www.walgreens.com/",
    "wof:name":"Walgreens",
    "wof:placetype":"venue"
},
  "geometry": {"coordinates":[-87.647262,41.880152],"type":"Point"}
}