{
  "type": "Feature",
  "properties": {
    "iso:country":"US",
    "sg:address":"200 Eiler Rd",
    "sg:city":"Belleville",
    "sg:classifiers":[
        {
            "category":"Organizations",
            "subcategory":"Religious Organization",
            "type":"Services"
        }
    ],
    "sg:phone":"+1 618 538 7195",
    "sg:postcode":"62223",
    "sg:province":"IL",
    "wof:name":"Villa Hills Assembly of God",
    "wof:placetype":"venue"
},
  "geometry": {"coordinates":[-90.076622,38.544868],"type":"Point"}
}