{
  "type": "Feature",
  "properties": {
    "iso:country":"US",
    "sg:address":"85 S Airlite St",
    "sg:city":"Elgin",
    "sg:classifiers":[
        {
            "category":"Manufacturing",
            "subcategory":"Tools & Machinery",
            "type":"Manufacturing & Wholesale Goods"
        }
    ],
    "sg:phone":"+1 847 622 0457",
    "sg:postcode":"60123",
    "sg:province":"IL",
    "sg:tags":[
        "die",
        "maker"
    ],
    "wof:name":"Custom Cutting Edge Tool",
    "wof:placetype":"venue"
},
  "geometry": {"coordinates":[-88.328853,42.032192],"type":"Point"}
}