{
  "type": "Feature",
  "properties": {
    "addr:full":"137 Fillmore St 216 Worden IL 62097",
    "addr:housenumber":"137;216",
    "addr:postcode":"62097",
    "addr:street":"Fillmore St",
    "iso:country":"US",
    "sg:address":"137 Fillmore St 216",
    "sg:city":"Worden",
    "sg:classifiers":[
        {
            "category":"Wholesale",
            "subcategory":"Non-durable Goods",
            "type":"Manufacturing & Wholesale Goods"
        }
    ],
    "sg:phone":"+1 312 226 8073",
    "sg:postcode":"62097",
    "sg:province":"IL",
    "sg:tags":[
        "dry",
        "goods-wholesale"
    ],
    "wof:name":"Quality Produce Suppliers",
    "wof:placetype":"venue"
},
  "geometry": {"coordinates":[-89.84581,38.932603],"type":"Point"}
}