{
  "type": "Feature",
  "properties": {
    "addr:full":"1539 S Lake St Mundelein IL 60060",
    "addr:housenumber":"1539",
    "addr:postcode":"60060",
    "addr:street":"S Lake St",
    "iso:country":"US",
    "sg:address":"1539 S Lake St",
    "sg:city":"Mundelein",
    "sg:classifiers":[
        {
            "category":"Banks & Credit Unions",
            "subcategory":"Bank",
            "type":"Services"
        }
    ],
    "sg:phone":"+1 847 949 1341",
    "sg:postcode":"60060",
    "sg:province":"IL",
    "sg:tags":[
        "federal",
        "savings",
        "institution"
    ],
    "wof:name":"Washington Mutual Bank",
    "wof:placetype":"venue"
},
  "geometry": {"coordinates":[-87.994185,42.241894],"type":"Point"}
}