{
  "type": "Feature",
  "properties": {
    "addr:full":"1501 E 96th St Chicago IL 60628",
    "addr:housenumber":"1501",
    "addr:postcode":"60628",
    "addr:street":"E 96Th St",
    "iso:country":"US",
    "sg:address":"1501 E 96th St",
    "sg:city":"Chicago",
    "sg:classifiers":[
        {
            "category":"Transit Center",
            "subcategory":"Freight",
            "type":"Transportation"
        },
        {
            "category":"Freight",
            "type":"Transportation"
        }
    ],
    "sg:phone":"+1 773 374 3135",
    "sg:postcode":"60628",
    "sg:province":"IL",
    "sg:tags":[
        "forwarding",
        "local",
        "trucking-motor",
        "trucking"
    ],
    "wof:name":"Dsc Logistics, Inc.",
    "wof:placetype":"venue"
},
  "geometry": {"coordinates":[-87.588511,41.720946],"type":"Point"}
}