{
  "type": "Feature",
  "properties": {
    "addr:full":"617 W 43rd Chicago IL 60607",
    "addr:housenumber":"617",
    "addr:postcode":"60607",
    "addr:street":"W 43Rd",
    "iso:country":"US",
    "sg:address":"617 W 43rd",
    "sg:city":"Chicago",
    "sg:classifiers":[
        {
            "category":"Food & Beverages",
            "subcategory":"Liquor & Beverages",
            "type":"Retail Goods"
        }
    ],
    "sg:phone":"+1 773 624 5270",
    "sg:postcode":"60607",
    "sg:province":"IL",
    "sg:tags":[
        "beer",
        "spirit",
        "wine"
    ],
    "wof:name":"Bravo Food & Liquor",
    "wof:placetype":"venue"
},
  "geometry": {"coordinates":[-87.64158399999999,41.815983],"type":"Point"}
}