{
  "type": "Feature",
  "properties": {
    "addr:full":"411 Craig Ct Mount Prospect IL 60056",
    "addr:housenumber":"411",
    "addr:postcode":"60056",
    "addr:street":"Craig Ct",
    "iso:country":"US",
    "sg:address":"411 Craig Ct",
    "sg:city":"Mount Prospect",
    "sg:classifiers":[
        {
            "category":"Real Estate",
            "subcategory":"Real Estate Operator",
            "type":"Services"
        }
    ],
    "sg:phone":"+1 847 364 7616",
    "sg:postcode":"60056",
    "sg:province":"IL",
    "sg:tags":[
        "property",
        "commercial"
    ],
    "wof:name":"Stonington Partnership",
    "wof:placetype":"venue"
},
  "geometry": {"coordinates":[-87.971822,42.058597],"type":"Point"}
}