{
  "type": "Feature",
  "properties": {
    "iso:country":"US",
    "sg:address":"1609 S 8th St",
    "sg:city":"Marshall",
    "sg:classifiers":[
        {
            "category":"Place Of Worship",
            "subcategory":"Church",
            "type":"Public Place"
        },
        {
            "category":"Place Of Worship",
            "type":"Public Place"
        },
        {
            "category":"Organizations",
            "subcategory":"Religious Organization",
            "type":"Services"
        }
    ],
    "sg:phone":"+1 217 826 5433",
    "sg:postcode":"62441",
    "sg:province":"IL",
    "sg:tags":[
        "god",
        "god-independent",
        "churches-assemblies"
    ],
    "wof:name":"New Life Church",
    "wof:placetype":"venue"
},
  "geometry": {"coordinates":[-87.692697,39.376707],"type":"Point"}
}