{
  "type": "Feature",
  "properties": {
    "iso:country":"US",
    "sg:address":"1603 Hickory Hill Ln",
    "sg:city":"Freeport",
    "sg:classifiers":[
        {
            "category":"Organizations",
            "subcategory":"Religious Organization",
            "type":"Services"
        }
    ],
    "sg:phone":"+1 815 232 1090",
    "sg:postcode":"61032",
    "sg:province":"IL",
    "wof:name":"Hart of God",
    "wof:placetype":"venue"
},
  "geometry": {"coordinates":[-89.645866,42.281598],"type":"Point"}
}