{
  "type": "Feature",
  "properties": {
    "iso:country":"US",
    "sg:address":"735 S Elm Ave",
    "sg:city":"Kankakee",
    "sg:classifiers":[
        {
            "category":"Professional",
            "subcategory":"Management & Consulting",
            "type":"Services"
        }
    ],
    "sg:phone":"+1 815 933 3410",
    "sg:postcode":"60901",
    "sg:province":"IL",
    "sg:tags":[
        "business"
    ],
    "wof:name":"Bel Consulting",
    "wof:placetype":"venue"
},
  "geometry": {"coordinates":[-87.851695,41.110326],"type":"Point"}
}