{
  "type": "Feature",
  "properties": {
    "iso:country":"US",
    "sg:address":"7300 W Belmont Ave",
    "sg:city":"Chicago",
    "sg:classifiers":[
        {
            "category":"Autos & Motor Vehicles",
            "subcategory":"Auto Supplies",
            "type":"Retail Goods"
        },
        {
            "category":"Retail",
            "subcategory":"Auto Repair",
            "type":"Services"
        }
    ],
    "sg:phone":"+1 773 237 0011",
    "sg:postcode":"60634",
    "sg:province":"IL",
    "sg:tags":[
        "transmission",
        "part"
    ],
    "wof:name":"Austin Auto Repair",
    "wof:placetype":"venue"
},
  "geometry": {"coordinates":[-87.80940200000001,41.938185],"type":"Point"}
}