{
  "type": "Feature",
  "properties": {
    "iso:country":"US",
    "sg:address":"1023 Belton Dr",
    "sg:city":"Danville",
    "sg:classifiers":[
        {
            "category":"Social Services",
            "type":"Services"
        }
    ],
    "sg:phone":"+1 217 446 7739",
    "sg:postcode":"61832",
    "sg:province":"IL",
    "sg:tags":[
        "organization",
        "welfare"
    ],
    "wof:name":"Fair Oak Head Start Ctr",
    "wof:placetype":"venue"
},
  "geometry": {"coordinates":[-87.589787,40.139846],"type":"Point"}
}