{
  "type": "Feature",
  "properties": {
    "iso:country":"US",
    "sg:address":"1491 Littlefield Ct",
    "sg:city":"Lake Forest",
    "sg:classifiers":[
        {
            "category":"Wholesale",
            "subcategory":"Groceries",
            "type":"Manufacturing & Wholesale Goods"
        }
    ],
    "sg:phone":"+1 847 604 9745",
    "sg:postcode":"60045",
    "sg:province":"IL",
    "sg:tags":[
        "confectionery"
    ],
    "wof:name":"A Sweet Bgnning A Happy Ending",
    "wof:placetype":"venue"
},
  "geometry": {"coordinates":[-87.889926,42.212639],"type":"Point"}
}