{
  "type": "Feature",
  "properties": {
    "iso:country":"US",
    "sg:address":"1995 S Schuyler Ave",
    "sg:city":"Kankakee",
    "sg:classifiers":[
        {
            "category":"Professional",
            "subcategory":"Business Services",
            "type":"Services"
        }
    ],
    "sg:phone":"+1 815 929 0081",
    "sg:postcode":"60901",
    "sg:province":"IL",
    "sg:tags":[
        "lecture",
        "bureau",
        "seminar"
    ],
    "wof:name":"Michael Smith",
    "wof:placetype":"venue"
},
  "geometry": {"coordinates":[-87.86907,41.091767],"type":"Point"}
}