{
  "type": "Feature",
  "properties": {
    "iso:country":"US",
    "sg:address":"6630 Springside Ave",
    "sg:city":"Downers Grove",
    "sg:classifiers":[
        {
            "category":"Restaurant",
            "type":"Food & Drink"
        }
    ],
    "sg:phone":"+1   ",
    "sg:postcode":"60516",
    "sg:province":"IL",
    "sg:tags":[
        "eating"
    ],
    "wof:name":"Elliots Off Broadway Deli",
    "wof:placetype":"venue"
},
  "geometry": {"coordinates":[-88.023263,41.766534],"type":"Point"}
}