{
  "type": "Feature",
  "properties": {
    "addr:full":"2738 W Cermak Road Chicago IL 60608",
    "addr:housenumber":"2738",
    "addr:postcode":"60608",
    "addr:street":"W Cermak Road",
    "iso:country":"US",
    "sg:address":"2738 W Cermak Road",
    "sg:city":"Chicago",
    "sg:classifiers":[
        {
            "category":"Health Services",
            "subcategory":"Doctor",
            "type":"Services"
        }
    ],
    "sg:phone":"+1 773 376 1906",
    "sg:postcode":"60608",
    "sg:province":"IL",
    "sg:tags":[
        "practice",
        "family"
    ],
    "wof:name":"Asebey Edgar M MD",
    "wof:placetype":"venue"
},
  "geometry": {"coordinates":[-87.69463500000001,41.85202],"type":"Point"}
}