{
  "type": "Feature",
  "properties": {
    "addr:full":"4903 Kings Ct Richton Park IL 60471",
    "addr:housenumber":"4903",
    "addr:postcode":"60471",
    "addr:street":"Kings Ct",
    "iso:country":"US",
    "sg:address":"4903 Kings Ct",
    "sg:city":"Richton Park",
    "sg:classifiers":[
        {
            "category":"Organizations",
            "subcategory":"Religious Organization",
            "type":"Services"
        }
    ],
    "sg:phone":"+1 708 503 8971",
    "sg:postcode":"60471",
    "sg:province":"IL",
    "sg:tags":[
        "clergy"
    ],
    "sg:website":"www.blestgifts.com",
    "wof:name":"Charlie Coleman Jr",
    "wof:placetype":"venue"
},
  "geometry": {"coordinates":[-87.73448,41.479615],"type":"Point"}
}