{
  "type": "Feature",
  "properties": {
    "addr:full":"1811 N State Rte 50 Bourbonnais IL 60914",
    "addr:housenumber":"1811",
    "addr:postcode":"60914",
    "addr:street":"N State Rte 50 Bourbonnais",
    "iso:country":"US",
    "sg:address":"1811 N State Rte 50",
    "sg:city":"Bourbonnais",
    "sg:classifiers":[
        {
            "category":"Home & Garden",
            "subcategory":"Hardware",
            "type":"Retail Goods"
        }
    ],
    "sg:phone":"+1 815 933 3244",
    "sg:postcode":"60914",
    "sg:province":"IL",
    "sg:website":"www.farmandfleet.com",
    "wof:name":"Farm & Fleet Co",
    "wof:placetype":"venue"
},
  "geometry": {"coordinates":[-87.85097500000001,41.164076],"type":"Point"}
}