{
  "type": "Feature",
  "properties": {
    "addr:full":"16545 Halsted St Harvey IL 60426",
    "addr:housenumber":"16545",
    "addr:postcode":"60426",
    "addr:street":"Halsted St",
    "iso:country":"US",
    "sg:address":"16545 Halsted St",
    "sg:city":"Harvey",
    "sg:classifiers":[
        {
            "category":"Health Services",
            "subcategory":"Chiropractor",
            "type":"Services"
        }
    ],
    "sg:phone":"+1 708 331 3329",
    "sg:postcode":"60426",
    "sg:province":"IL",
    "wof:name":"Morantz Jerold I DC",
    "wof:placetype":"venue"
},
  "geometry": {"coordinates":[-87.6362,41.588699],"type":"Point"}
}