{
  "type": "Feature",
  "properties": {
    "addr:full":"3150 Tonti Dr Joliet IL 60431",
    "addr:postcode":"3150;60431",
    "addr:street":"Tonti Dr",
    "iso:country":"US",
    "sg:address":"3150 Tonti Dr",
    "sg:city":"Joliet",
    "sg:classifiers":[
        {
            "category":"Shopping",
            "subcategory":"Computers & Home Electronics",
            "type":"Retail Goods"
        }
    ],
    "sg:phone":"+1   ",
    "sg:postcode":"60431",
    "sg:province":"IL",
    "sg:website":"www.circuitcity.com",
    "wof:name":"Circuit City",
    "wof:placetype":"venue"
},
  "geometry": {"coordinates":[-88.162132,41.577566],"type":"Point"}
}