{
  "type": "Feature",
  "properties": {
    "iso:country":"US",
    "sg:address":"250 E 111th St",
    "sg:city":"Chicago",
    "sg:classifiers":[
        {
            "category":"Education",
            "subcategory":"School",
            "type":"Public Place"
        }
    ],
    "sg:phone":"+1 773 535 9941",
    "sg:postcode":"60628",
    "sg:province":"IL",
    "wof:name":"Gwendolyn Brooks Prep School",
    "wof:placetype":"venue"
},
  "geometry": {"coordinates":[-87.616996,41.692683],"type":"Point"}
}