{
  "type": "Feature",
  "properties": {
    "iso:country":"US",
    "sg:address":"1448 Wesley Ave",
    "sg:city":"Berwyn",
    "sg:classifiers":[
        {
            "category":"Food & Beverages",
            "subcategory":"Specialty",
            "type":"Retail Goods"
        }
    ],
    "sg:phone":"+1   ",
    "sg:postcode":"60402",
    "sg:province":"IL",
    "wof:name":"Food Pantry",
    "wof:placetype":"venue"
},
  "geometry": {"coordinates":[-87.79124,41.86062],"type":"Point"}
}