{
  "type": "Feature",
  "properties": {
    "addr:full":"1953 Airway Ct New Lenox IL 60451",
    "addr:housenumber":"1953",
    "addr:postcode":"60451",
    "addr:street":"Airway Ct",
    "iso:country":"US",
    "sg:address":"1953 Airway Ct",
    "sg:city":"New Lenox",
    "sg:classifiers":[
        {
            "category":"Wholesale",
            "subcategory":"Construction Materials",
            "type":"Manufacturing & Wholesale Goods"
        }
    ],
    "sg:phone":"+1 815 485 9200",
    "sg:postcode":"60451",
    "sg:province":"IL",
    "wof:name":"Mel Kel Supply Co",
    "wof:placetype":"venue"
},
  "geometry": {"coordinates":[-87.927127,41.484811],"type":"Point"}
}