{
  "type": "Feature",
  "properties": {
    "addr:full":"8927 Porter Oaks Dr Roscoe IL 61073",
    "addr:housenumber":"8927",
    "addr:postcode":"61073",
    "addr:street":"Porter Oaks Dr",
    "iso:country":"US",
    "sg:address":"8927 Porter Oaks Dr",
    "sg:city":"Roscoe",
    "sg:classifiers":[
        {
            "category":"Food & Beverages",
            "subcategory":"Specialty",
            "type":"Retail Goods"
        }
    ],
    "sg:phone":"+1 815 623 8832",
    "sg:postcode":"61073",
    "sg:province":"IL",
    "sg:tags":[
        "vitamin"
    ],
    "wof:name":"Shaklee Distributor",
    "wof:placetype":"venue"
},
  "geometry": {"coordinates":[-88.940569,42.416136],"type":"Point"}
}