{
  "type": "Feature",
  "properties": {
    "addr:full":"2350 N 2879th Rd Marseilles IL 61341",
    "addr:housenumber":"2350",
    "addr:postcode":"61341",
    "addr:street":"N 2879Th Rd",
    "iso:country":"US",
    "sg:address":"2350 N 2879th Rd",
    "sg:city":"Marseilles",
    "sg:classifiers":[
        {
            "category":"Professional",
            "subcategory":"Business Services",
            "type":"Services"
        }
    ],
    "sg:phone":"+1 815 795 6741",
    "sg:postcode":"61341",
    "sg:province":"IL",
    "sg:tags":[
        "company",
        "holding"
    ],
    "wof:name":"Wti",
    "wof:placetype":"venue"
},
  "geometry": {"coordinates":[-88.715057,41.351964],"type":"Point"}
}