{
  "type": "Feature",
  "properties": {
    "iso:country":"US",
    "sg:address":"1023 Gunderson Ave",
    "sg:city":"Berwyn",
    "sg:classifiers":[
        {
            "category":"Building & Trades",
            "subcategory":"Locksmith",
            "type":"Services"
        }
    ],
    "sg:phone":"+1 708 801 3360",
    "sg:postcode":"60402",
    "sg:province":"IL",
    "sg:tags":[
        "key"
    ],
    "wof:name":"A A Clancey Locksmith",
    "wof:placetype":"venue"
},
  "geometry": {"coordinates":[-87.786919,41.8699],"type":"Point"}
}