{
  "type": "Feature",
  "properties": {
    "addr:full":"1869 Techny Rd Northbrook IL 60062",
    "addr:housenumber":"1869",
    "addr:postcode":"60062",
    "addr:street":"Techny Rd",
    "iso:country":"US",
    "sg:address":"1869 Techny Rd",
    "sg:city":"Northbrook",
    "sg:classifiers":[
        {
            "category":"Building & Trades",
            "subcategory":"Landscaping Services",
            "type":"Services"
        }
    ],
    "sg:phone":"+1 847 564 9393",
    "sg:postcode":"60062",
    "sg:province":"IL",
    "sg:tags":[
        "landscape",
        "contractor"
    ],
    "wof:name":"Moore Landscapes Inc",
    "wof:placetype":"venue"
},
  "geometry": {"coordinates":[-87.823014,42.116369],"type":"Point"}
}