{
  "type": "Feature",
  "properties": {
    "iso:country":"US",
    "sg:address":"1905 100th St",
    "sg:city":"Monmouth",
    "sg:classifiers":[
        {
            "category":"Education",
            "subcategory":"School",
            "type":"Public Place"
        }
    ],
    "sg:phone":"+1   ",
    "sg:postcode":"61462",
    "sg:province":"IL",
    "sg:tags":[
        "educational",
        "administrative"
    ],
    "wof:name":"Warren High School",
    "wof:placetype":"venue"
},
  "geometry": {"coordinates":[-90.593117,40.899295],"type":"Point"}
}