{
  "type": "Feature",
  "properties": {
    "addr:full":"512 Twin Rail Dr Minooka IL 60447",
    "addr:housenumber":"512",
    "addr:postcode":"60447",
    "addr:street":"Twin Rail",
    "iso:country":"US",
    "sg:address":"512 Twin Rail Dr",
    "sg:city":"Minooka",
    "sg:classifiers":[
        {
            "category":"Shopping",
            "subcategory":"Gifts & Souvenirs",
            "type":"Retail Goods"
        }
    ],
    "sg:phone":"+1 815 467 4146",
    "sg:postcode":"60447",
    "sg:province":"IL",
    "sg:tags":[
        "shop"
    ],
    "wof:name":"Supply House",
    "wof:placetype":"venue"
},
  "geometry": {"coordinates":[-88.272204,41.453208],"type":"Point"}
}