{
  "type": "Feature",
  "properties": {
    "iso:country":"US",
    "sg:address":"1708 Philo Rd",
    "sg:city":"Urbana",
    "sg:classifiers":[
        {
            "category":"Restaurant",
            "type":"Food & Drink"
        }
    ],
    "sg:phone":"+1 217 344 2855",
    "sg:postcode":"61802",
    "sg:province":"IL",
    "sg:website":"www.bk.com/en/us/index.html",
    "wof:name":"Burger King",
    "wof:placetype":"venue"
},
  "geometry": {"coordinates":[-88.19070499999999,40.098027],"type":"Point"}
}