{
  "type": "Feature",
  "properties": {
    "iso:country":"US",
    "sg:address":"1997 Co Rd 3000 N",
    "sg:city":"Rantoul",
    "sg:phone":"+1 217 892 8278",
    "sg:postcode":"61866",
    "sg:province":"IL",
    "sg:tags":[
        "farm",
        "corn",
        "soybean"
    ],
    "wof:name":"Dennis Bergman",
    "wof:placetype":"venue"
},
  "geometry": {"coordinates":[-88.089479,40.312363],"type":"Point"}
}