{
  "type": "Feature",
  "properties": {
    "addr:full":"1381 Branden Ln Bartlett IL 60103",
    "addr:housenumber":"1381",
    "addr:postcode":"60103",
    "addr:street":"Branden Ln",
    "iso:country":"US",
    "sg:address":"1381 Branden Ln",
    "sg:city":"Bartlett",
    "sg:classifiers":[
        {
            "category":"Real Estate",
            "subcategory":"Real Estate Services",
            "type":"Services"
        },
        {
            "category":"Real Estate",
            "subcategory":"Real Estate Agent",
            "type":"Services"
        }
    ],
    "sg:phone":"+1 630 483 9942",
    "sg:postcode":"60103",
    "sg:province":"IL",
    "sg:tags":[
        "management"
    ],
    "wof:name":"Vita & Associates Inc",
    "wof:placetype":"venue"
},
  "geometry": {"coordinates":[-88.166827,41.959785],"type":"Point"}
}