{
  "type": "Feature",
  "properties": {
    "iso:country":"US",
    "sg:address":"600 W Chicago Ave",
    "sg:city":"Chicago",
    "sg:classifiers":[
        {
            "category":"Professional",
            "subcategory":"Advertising",
            "type":"Services"
        }
    ],
    "sg:phone":"+1 312 202 0604",
    "sg:postcode":"60654",
    "sg:province":"IL",
    "sg:tags":[
        "advertising-promotional",
        "product",
        "specialty"
    ],
    "wof:name":"Maxwell Lisa P",
    "wof:placetype":"venue"
},
  "geometry": {"coordinates":[-87.64299800000001,41.896469],"type":"Point"}
}