{
  "type": "Feature",
  "properties": {
    "iso:country":"US",
    "sg:address":"265 Chicago St",
    "sg:city":"West Chicago",
    "sg:classifiers":[
        {
            "category":"Restaurant",
            "type":"Food & Drink"
        }
    ],
    "sg:phone":"+1 630 231 3700",
    "sg:postcode":"60185",
    "sg:province":"IL",
    "wof:name":"Fraise Bakery & Cafe",
    "wof:placetype":"venue"
},
  "geometry": {"coordinates":[-88.199622,41.883591],"type":"Point"}
}