{
  "type": "Feature",
  "properties": {
    "addr:full":"939 State St Chester IL 62233",
    "addr:housenumber":"939",
    "addr:postcode":"62233",
    "addr:street":"State St",
    "iso:country":"US",
    "sg:address":"939 State St",
    "sg:city":"Chester",
    "sg:classifiers":[
        {
            "category":"Organizations",
            "subcategory":"Community Association",
            "type":"Services"
        }
    ],
    "sg:phone":"+1 618 826 3411",
    "sg:postcode":"62233",
    "sg:province":"IL",
    "wof:name":"Veterans Of Foreign Wars",
    "wof:placetype":"venue"
},
  "geometry": {"coordinates":[-89.824372,37.911426],"type":"Point"}
}