{
  "type": "Feature",
  "properties": {
    "addr:full":"1510 S Michigan Ave Chicago IL 60605",
    "addr:housenumber":"1510",
    "addr:postcode":"60605",
    "addr:street":"S Michigan Ave",
    "iso:country":"US",
    "sg:address":"1510 S Michigan Ave",
    "sg:city":"Chicago",
    "sg:classifiers":[
        {
            "category":"Home & Garden",
            "subcategory":"Furniture",
            "type":"Retail Goods"
        }
    ],
    "sg:phone":"+1 312 922 7200",
    "sg:postcode":"60605",
    "sg:province":"IL",
    "sg:tags":[
        "store"
    ],
    "wof:name":"Home Furnishings Consultants Ltd",
    "wof:placetype":"venue"
},
  "geometry": {"coordinates":[-87.624199,41.861301],"type":"Point"}
}