{
  "type": "Feature",
  "properties": {
    "iso:country":"US",
    "sg:address":"311 E Main St",
    "sg:city":"Knoxville",
    "sg:classifiers":[
        {
            "category":"Personal",
            "subcategory":"Barber",
            "type":"Services"
        }
    ],
    "sg:phone":"+1 309 289 2951",
    "sg:postcode":"61448",
    "sg:province":"IL",
    "sg:tags":[
        "shop"
    ],
    "wof:name":"Gary's Barber Shop",
    "wof:placetype":"venue"
},
  "geometry": {"coordinates":[-90.281707,40.908082],"type":"Point"}
}