{
  "type": "Feature",
  "properties": {
    "iso:country":"US",
    "sg:address":"15342 N 300th St",
    "sg:city":"Wheeler",
    "sg:classifiers":[
        {
            "category":"Personal",
            "subcategory":"Beauty Salon",
            "type":"Services"
        }
    ],
    "sg:phone":"+1 217 925 5484",
    "sg:postcode":"62479",
    "sg:province":"IL",
    "wof:name":"Sandy's Beauty Shop",
    "wof:placetype":"venue"
},
  "geometry": {"coordinates":[-88.316484,39.08471],"type":"Point"}
}