{
  "type": "Feature",
  "properties": {
    "iso:country":"US",
    "sg:address":"132 E Church St",
    "sg:city":"Sandwich",
    "sg:classifiers":[
        {
            "category":"Restaurant",
            "type":"Food & Drink"
        }
    ],
    "sg:phone":"+1 815 786 6737",
    "sg:postcode":"60548",
    "sg:province":"IL",
    "sg:tags":[
        "style",
        "family"
    ],
    "wof:name":"Santa Fe Restaurant",
    "wof:placetype":"venue"
},
  "geometry": {"coordinates":[-88.61998800000001,41.644307],"type":"Point"}
}