{
  "type": "Feature",
  "properties": {
    "iso:country":"US",
    "sg:address":"1811 S 17th Ave",
    "sg:city":"Broadview",
    "sg:classifiers":[
        {
            "category":"Autos & Motor Vehicles",
            "subcategory":"Fuel & Gas Station",
            "type":"Retail Goods"
        }
    ],
    "sg:phone":"+1   ",
    "sg:postcode":"60155",
    "sg:province":"IL",
    "sg:tags":[
        "grocery",
        "station",
        "gasoline"
    ],
    "wof:name":"Pit Stop",
    "wof:placetype":"venue"
},
  "geometry": {"coordinates":[-87.85324799999999,41.869514],"type":"Point"}
}