{
  "type": "Feature",
  "properties": {
    "iso:country":"US",
    "sg:address":"764 W Belvidere Rd",
    "sg:city":"Round Lake",
    "sg:classifiers":[
        {
            "category":"Autos & Motor Vehicles",
            "subcategory":"Recreational Vehicle Sales",
            "type":"Retail Goods"
        }
    ],
    "sg:phone":"+1 847 546 0026",
    "sg:postcode":"60073",
    "sg:province":"IL",
    "sg:tags":[
        "camper",
        "pick"
    ],
    "wof:name":"120 Rv",
    "wof:placetype":"venue"
},
  "geometry": {"coordinates":[-88.099662,42.338115],"type":"Point"}
}