{
  "type": "Feature",
  "properties": {
    "iso:country":"US",
    "sg:address":"10800 Central Ave",
    "sg:city":"Chicago Ridge",
    "sg:classifiers":[
        {
            "category":"Food & Beverages",
            "subcategory":"Meat & Fish",
            "type":"Retail Goods"
        }
    ],
    "sg:phone":"+1 708 425 5100",
    "sg:postcode":"60415",
    "sg:province":"IL",
    "sg:tags":[
        "shop"
    ],
    "wof:name":"Sherwood Foods",
    "wof:placetype":"venue"
},
  "geometry": {"coordinates":[-87.759704,41.696111],"type":"Point"}
}