{
  "type": "Feature",
  "properties": {
    "iso:country":"US",
    "sg:address":"78 S Broadway",
    "sg:city":"Aurora",
    "sg:classifiers":[
        {
            "category":"Shopping",
            "subcategory":"Florist",
            "type":"Retail Goods"
        }
    ],
    "sg:phone":"+1 630 264 9455",
    "sg:postcode":"60505",
    "sg:province":"IL",
    "wof:name":"Toss Salad Decor",
    "wof:placetype":"venue"
},
  "geometry": {"coordinates":[-88.314486,41.755665],"type":"Point"}
}