{
  "type": "Feature",
  "properties": {
    "addr:full":"5520 W Roscoe St Chicago IL 60641",
    "addr:housenumber":"5520",
    "addr:postcode":"60641",
    "addr:street":"W Roscoe St",
    "iso:country":"US",
    "sg:address":"5520 W Roscoe St",
    "sg:city":"Chicago",
    "sg:classifiers":[
        {
            "category":"Communications",
            "subcategory":"Film & Video Production",
            "type":"Services"
        }
    ],
    "sg:phone":"+1 773 685 1742",
    "sg:postcode":"60641",
    "sg:province":"IL",
    "sg:tags":[
        "taping"
    ],
    "wof:name":"Action Pro Video",
    "wof:placetype":"venue"
},
  "geometry": {"coordinates":[-87.764293,41.942332],"type":"Point"}
}