{
  "type": "Feature",
  "properties": {
    "iso:country":"US",
    "sg:address":"11235 N Trimble Rd",
    "sg:city":"Robinson",
    "sg:classifiers":[
        {
            "category":"Place Of Worship",
            "subcategory":"Church",
            "type":"Public Place"
        },
        {
            "category":"Place Of Worship",
            "type":"Public Place"
        }
    ],
    "sg:phone":"+1 618 544 2328",
    "sg:postcode":"62454",
    "sg:province":"IL",
    "sg:tags":[
        "churches-interdenominational",
        "churches-various",
        "denomination"
    ],
    "wof:name":"Disciples Of Christ",
    "wof:placetype":"venue"
},
  "geometry": {"coordinates":[-87.728362,39.017076],"type":"Point"}
}