{
  "type": "Feature",
  "properties": {
    "iso:country":"US",
    "sg:address":"3351 Mall Loop Dr",
    "sg:city":"Joliet",
    "sg:classifiers":[
        {
            "category":"Home & Garden",
            "subcategory":"Furniture",
            "type":"Retail Goods"
        }
    ],
    "sg:phone":"+1 815 609 3418",
    "sg:postcode":"60431",
    "sg:province":"IL",
    "wof:name":"Homemakers Furniture Inc",
    "wof:placetype":"venue"
},
  "geometry": {"coordinates":[-88.164351,41.579551],"type":"Point"}
}