{
  "type": "Feature",
  "properties": {
    "addr:full":"205 W Randolph St Ste 1340 Chicago IL 60606",
    "addr:housenumber":"205",
    "addr:postcode":"60606",
    "addr:street":"W Randolph St Ste 1340",
    "iso:country":"US",
    "sg:address":"205 W Randolph St Ste 1340",
    "sg:city":"Chicago",
    "sg:classifiers":[
        {
            "category":"Education",
            "subcategory":"School",
            "type":"Public Place"
        }
    ],
    "sg:phone":"+1 312 235 0798",
    "sg:postcode":"60606",
    "sg:province":"IL",
    "sg:tags":[
        "high",
        "middle",
        "elementary"
    ],
    "wof:name":"Illinois Network of Charter Schools",
    "wof:placetype":"venue"
},
  "geometry": {"coordinates":[-87.633972,41.884456],"type":"Point"}
}