{
  "type": "Feature",
  "properties": {
    "addr:full":"2350 Waterbury Cir Aurora IL 60504",
    "addr:housenumber":"2350",
    "addr:postcode":"60504",
    "addr:street":"Waterbury Cir",
    "iso:country":"US",
    "sg:address":"2350 Waterbury Cir",
    "sg:city":"Aurora",
    "sg:classifiers":[
        {
            "category":"Social Services",
            "subcategory":"Job Training",
            "type":"Services"
        }
    ],
    "sg:phone":"+1 630 375 9908",
    "sg:postcode":"60504",
    "sg:province":"IL",
    "sg:tags":[
        "consulting",
        "management"
    ],
    "wof:name":"Municipal Training Services",
    "wof:placetype":"venue"
},
  "geometry": {"coordinates":[-88.258887,41.744077],"type":"Point"}
}