{
  "type": "Feature",
  "properties": {
    "iso:country":"US",
    "sg:address":"2200 E Devon Ave",
    "sg:city":"Des Plaines",
    "sg:classifiers":[
        {
            "category":"Organizations",
            "subcategory":"Religious Organization",
            "type":"Services"
        }
    ],
    "sg:phone":"+1 847 297 2080",
    "sg:postcode":"60018",
    "sg:province":"IL",
    "wof:name":"Parish Evaluation Project",
    "wof:placetype":"venue"
},
  "geometry": {"coordinates":[-87.870676,41.995532],"type":"Point"}
}