{
  "type": "Feature",
  "properties": {
    "addr:full":"1717 Dodge Ave Evanston IL 60201",
    "addr:housenumber":"1717",
    "addr:postcode":"60201",
    "addr:street":"Dodge Ave",
    "iso:country":"US",
    "sg:address":"1717 Dodge Ave",
    "sg:city":"Evanston",
    "sg:classifiers":[
        {
            "category":"Restaurant",
            "type":"Food & Drink"
        }
    ],
    "sg:phone":"+1 847 332 2355",
    "sg:postcode":"60201",
    "sg:province":"IL",
    "wof:name":"Chicagoland Barbeque",
    "wof:placetype":"venue"
},
  "geometry": {"coordinates":[-87.698913,42.04852],"type":"Point"}
}