{
  "type": "Feature",
  "properties": {
    "iso:country":"US",
    "sg:address":"748 Campus Ave",
    "sg:city":"Matteson",
    "sg:classifiers":[
        {
            "category":"Professional",
            "subcategory":"Business Services",
            "type":"Services"
        }
    ],
    "sg:phone":"+1 708 748 2648",
    "sg:postcode":"60443",
    "sg:province":"IL",
    "wof:name":"Tiny Tots Consultant Service P",
    "wof:placetype":"venue"
},
  "geometry": {"coordinates":[-87.727048,41.512518],"type":"Point"}
}