{
  "type": "Feature",
  "properties": {
    "iso:country":"US",
    "sg:address":"140 Woodcrest Dr",
    "sg:city":"Highland",
    "sg:classifiers":[
        {
            "category":"Recreation",
            "type":"Entertainment"
        }
    ],
    "sg:phone":"+1 618 654 6024",
    "sg:postcode":"62249",
    "sg:province":"IL",
    "wof:name":"Fun Land Of Highland",
    "wof:placetype":"venue"
},
  "geometry": {"coordinates":[-89.67191,38.747653],"type":"Point"}
}