{
  "type": "Feature",
  "properties": {
    "iso:country":"US",
    "sg:address":"11638 S Pulaski Rd",
    "sg:city":"Alsip",
    "sg:classifiers":[
        {
            "category":"Building & Trades",
            "subcategory":"Locksmith",
            "type":"Services"
        }
    ],
    "sg:phone":"+1 708 389 1515",
    "sg:postcode":"60803",
    "sg:province":"IL",
    "sg:tags":[
        "key"
    ],
    "wof:name":"Johnson Locksmith",
    "wof:placetype":"venue"
},
  "geometry": {"coordinates":[-87.720001,41.6805],"type":"Point"}
}