{
  "type": "Feature",
  "properties": {
    "iso:country":"US",
    "sg:address":"3162 S Ashland Ave",
    "sg:city":"Chicago",
    "sg:classifiers":[
        {
            "category":"Food & Beverages",
            "subcategory":"Liquor & Beverages",
            "type":"Retail Goods"
        }
    ],
    "sg:phone":"+1 773 927 9697",
    "sg:postcode":"60608",
    "sg:province":"IL",
    "sg:tags":[
        "beer",
        "spirit",
        "wine"
    ],
    "wof:name":"Ashland S Inc",
    "wof:placetype":"venue"
},
  "geometry": {"coordinates":[-87.665802,41.836201],"type":"Point"}
}