{
  "type": "Feature",
  "properties": {
    "iso:country":"US",
    "sg:address":"230 E Ohio St",
    "sg:city":"Chicago",
    "sg:classifiers":[
        {
            "category":"Professional",
            "type":"Services"
        }
    ],
    "sg:phone":"+1 312 440 1200",
    "sg:postcode":"60611",
    "sg:province":"IL",
    "sg:tags":[
        "motion",
        "technician",
        "picture"
    ],
    "wof:name":"Am Films",
    "wof:placetype":"venue"
},
  "geometry": {"coordinates":[-87.62195199999999,41.89258],"type":"Point"}
}