{
  "type": "Feature",
  "properties": {
    "iso:country":"US",
    "sg:address":"73 S Grove Ave",
    "sg:city":"Elgin",
    "sg:classifiers":[
        {
            "category":"Wholesale",
            "subcategory":"Meat",
            "type":"Manufacturing & Wholesale Goods"
        }
    ],
    "sg:phone":"+1 847 741 8750",
    "sg:postcode":"60120",
    "sg:province":"IL",
    "wof:name":"Schaltz Enterprise LTD",
    "wof:placetype":"venue"
},
  "geometry": {"coordinates":[-88.283273,42.036259],"type":"Point"}
}