{
  "type": "Feature",
  "properties": {
    "iso:country":"US",
    "sg:address":"550 S Mulford Rd",
    "sg:city":"Rockford",
    "sg:classifiers":[
        {
            "category":"Health Services",
            "subcategory":"Nursing And Care Facility",
            "type":"Services"
        }
    ],
    "sg:phone":"+1 815 399 4914",
    "sg:postcode":"61108",
    "sg:province":"IL",
    "sg:tags":[
        "skilled"
    ],
    "wof:name":"Alden Alma Nelson Manor Inc",
    "wof:placetype":"venue"
},
  "geometry": {"coordinates":[-88.999595,42.261909],"type":"Point"}
}