{
  "type": "Feature",
  "properties": {
    "addr:full":"138 N State St Belvidere IL 61008",
    "addr:housenumber":"138",
    "addr:postcode":"61008",
    "addr:street":"N State St",
    "iso:country":"US",
    "sg:address":"138 N State St",
    "sg:city":"Belvidere",
    "sg:classifiers":[
        {
            "category":"Restaurant",
            "type":"Food & Drink"
        }
    ],
    "sg:phone":"+1   ",
    "sg:postcode":"61008",
    "sg:province":"IL",
    "sg:tags":[
        "eating"
    ],
    "wof:name":"Sams Pizza",
    "wof:placetype":"venue"
},
  "geometry": {"coordinates":[-88.843538,42.259696],"type":"Point"}
}