{
  "type": "Feature",
  "properties": {
    "iso:country":"US",
    "sg:address":"1154 N Bradfordton Rd",
    "sg:city":"Springfield",
    "sg:classifiers":[
        {
            "category":"Professional",
            "subcategory":"Engineering",
            "type":"Services"
        },
        {
            "category":"Professional",
            "subcategory":"Management & Consulting",
            "type":"Services"
        }
    ],
    "sg:phone":"+1 217 726 9468",
    "sg:postcode":"62711",
    "sg:province":"IL",
    "sg:tags":[
        "environmental",
        "ecological",
        "consultant",
        "engineer"
    ],
    "wof:name":"Environmental Management Inc",
    "wof:placetype":"venue"
},
  "geometry": {"coordinates":[-89.739574,39.817062],"type":"Point"}
}