{
  "type": "Feature",
  "properties": {
    "iso:country":"US",
    "sg:address":"2122 Sheridan Rd",
    "sg:city":"Evanston",
    "sg:classifiers":[
        {
            "category":"Shopping",
            "subcategory":"Books",
            "type":"Retail Goods"
        }
    ],
    "sg:phone":"+1   ",
    "sg:postcode":"60201",
    "sg:province":"IL",
    "sg:tags":[
        "store"
    ],
    "wof:name":"Book Shelf",
    "wof:placetype":"venue"
},
  "geometry": {"coordinates":[-87.67715,42.057295],"type":"Point"}
}