{
  "type": "Feature",
  "properties": {
    "addr:full":"790 Burnham Ave Calumet City IL 60409",
    "addr:housenumber":"790",
    "addr:postcode":"60409",
    "addr:street":"Burnham Ave",
    "iso:country":"US",
    "sg:address":"790 Burnham Ave",
    "sg:city":"Calumet City",
    "sg:classifiers":[
        {
            "category":"Professional",
            "subcategory":"Business Services",
            "type":"Services"
        }
    ],
    "sg:phone":"+1 708 891 1669",
    "sg:postcode":"60409",
    "sg:province":"IL",
    "wof:name":"Tammy Wisowaty",
    "wof:placetype":"venue"
},
  "geometry": {"coordinates":[-87.53961200000001,41.610396],"type":"Point"}
}