{
  "type": "Feature",
  "properties": {
    "iso:country":"US",
    "sg:address":"2407 W Devon Ave",
    "sg:city":"Chicago",
    "sg:classifiers":[
        {
            "category":"Shopping",
            "subcategory":"Clothing, Apparel, & Fashions",
            "type":"Retail Goods"
        }
    ],
    "sg:phone":"+1 773 973 3492",
    "sg:postcode":"60659",
    "sg:province":"IL",
    "sg:tags":[
        "clothing",
        "women's"
    ],
    "wof:name":"Fiza Palace",
    "wof:placetype":"venue"
},
  "geometry": {"coordinates":[-87.69036,41.997724],"type":"Point"}
}