{
  "type": "Feature",
  "properties": {
    "iso:country":"US",
    "sg:address":"701 W Myrtle St",
    "sg:city":"Baldwin",
    "sg:classifiers":[
        {
            "category":"Organizations",
            "subcategory":"Community Association",
            "type":"Services"
        }
    ],
    "sg:phone":"+1 618 785 9904",
    "sg:postcode":"62217",
    "sg:province":"IL",
    "wof:name":"American Legion Dept of PA",
    "wof:placetype":"venue"
},
  "geometry": {"coordinates":[-89.86094799999999,38.184491],"type":"Point"}
}