{
  "type": "Feature",
  "properties": {
    "iso:country":"US",
    "sg:address":"285 E Helen Rd",
    "sg:city":"Palatine",
    "sg:classifiers":[
        {
            "category":"Professional",
            "subcategory":"Accounting & Tax Preparation",
            "type":"Services"
        }
    ],
    "sg:phone":"+1 847 359 4820",
    "sg:postcode":"60067",
    "sg:province":"IL",
    "sg:tags":[
        "firm"
    ],
    "wof:name":"J Harris & Company Ltd",
    "wof:placetype":"venue"
},
  "geometry": {"coordinates":[-88.036653,42.103995],"type":"Point"}
}