{
  "type": "Feature",
  "properties": {
    "addr:full":"1918 Western Ave Mattoon IL 61938",
    "addr:housenumber":"1918",
    "addr:postcode":"61938",
    "addr:street":"Western Ave",
    "iso:country":"US",
    "sg:address":"1918 Western Ave",
    "sg:city":"Mattoon",
    "sg:classifiers":[
        {
            "category":"Personal",
            "subcategory":"Beauty Salon",
            "type":"Services"
        }
    ],
    "sg:phone":"+1 217 234 3393",
    "sg:postcode":"61938",
    "sg:province":"IL",
    "sg:tags":[
        "shop"
    ],
    "wof:name":"Hair Force 1",
    "wof:placetype":"venue"
},
  "geometry": {"coordinates":[-88.378676,39.483166],"type":"Point"}
}