{
  "type": "Feature",
  "properties": {
    "addr:full":"1925 13th St East Moline IL 61244",
    "addr:housenumber":"1925",
    "addr:postcode":"61244",
    "addr:street":"13Th St",
    "iso:country":"US",
    "sg:address":"1925 13th St",
    "sg:city":"East Moline",
    "sg:classifiers":[
        {
            "category":"Education",
            "subcategory":"School",
            "type":"Public Place"
        }
    ],
    "sg:phone":"+1 309 755 4352",
    "sg:postcode":"61244",
    "sg:province":"IL",
    "wof:name":"St Marys School",
    "wof:placetype":"venue"
},
  "geometry": {"coordinates":[-90.433083,41.514817],"type":"Point"}
}