{
  "type": "Feature",
  "properties": {
    "addr:full":"400 Park Ave Calumet City IL 60409",
    "addr:housenumber":"400",
    "addr:postcode":"60409",
    "addr:street":"Park Ave",
    "iso:country":"US",
    "sg:address":"400 Park Ave",
    "sg:city":"Calumet City",
    "sg:classifiers":[
        {
            "category":"Professional",
            "subcategory":"Business Services",
            "type":"Services"
        }
    ],
    "sg:phone":"+1 312 371 4637",
    "sg:postcode":"60409",
    "sg:province":"IL",
    "wof:name":"Baity Group",
    "wof:placetype":"venue"
},
  "geometry": {"coordinates":[-87.57335999999999,41.597749],"type":"Point"}
}