{
  "type": "Feature",
  "properties": {
    "addr:full":"319 Blaine St Batavia IL 60510",
    "addr:housenumber":"319",
    "addr:postcode":"60510",
    "addr:street":"Blaine St",
    "iso:country":"US",
    "sg:address":"319 Blaine St",
    "sg:city":"Batavia",
    "sg:classifiers":[
        {
            "category":"Banks & Credit Unions",
            "subcategory":"Investment Brokerage",
            "type":"Services"
        }
    ],
    "sg:phone":"+1 630 761 9961",
    "sg:postcode":"60510",
    "sg:province":"IL",
    "sg:tags":[
        "consultant",
        "planning",
        "financial"
    ],
    "wof:name":"Williams Consulting",
    "wof:placetype":"venue"
},
  "geometry": {"coordinates":[-88.31541199999999,41.842732],"type":"Point"}
}