{
  "type": "Feature",
  "properties": {
    "iso:country":"US",
    "sg:address":"103 Dickson St",
    "sg:city":"Sidell",
    "sg:classifiers":[
        {
            "category":"Bars & Pubs",
            "type":"Food & Drink"
        }
    ],
    "sg:phone":"+1 217 288 9629",
    "sg:postcode":"61876",
    "sg:province":"IL",
    "wof:name":"Pumps Corner",
    "wof:placetype":"venue"
},
  "geometry": {"coordinates":[-87.82198200000001,39.909814],"type":"Point"}
}