{
  "type": "Feature",
  "properties": {
    "iso:country":"US",
    "sg:address":"3143 S Austin Blvd",
    "sg:city":"Cicero",
    "sg:classifiers":[
        {
            "category":"Retail",
            "subcategory":"Auto Repair",
            "type":"Services"
        }
    ],
    "sg:phone":"+1 708 652 4601",
    "sg:postcode":"60804",
    "sg:province":"IL",
    "sg:tags":[
        "body",
        "shop"
    ],
    "wof:name":"Suburban Auto Service",
    "wof:placetype":"venue"
},
  "geometry": {"coordinates":[-87.77310199999999,41.8344],"type":"Point"}
}