{
  "type": "Feature",
  "properties": {
    "iso:country":"US",
    "sg:address":"109 W Main St",
    "sg:city":"San Jose",
    "sg:classifiers":[
        {
            "category":"Autos & Motor Vehicles",
            "subcategory":"Automobile Sales",
            "type":"Retail Goods"
        }
    ],
    "sg:phone":"+1 309 247 1239",
    "sg:postcode":"62682",
    "sg:province":"IL",
    "sg:tags":[
        "car",
        "dealer"
    ],
    "wof:name":"Trp Auto Sales Rs Svc",
    "wof:placetype":"venue"
},
  "geometry": {"coordinates":[-89.60325400000001,40.305499],"type":"Point"}
}