{
  "type": "Feature",
  "properties": {
    "addr:full":"305 W 138th St Riverdale IL 60827",
    "addr:housenumber":"305",
    "addr:postcode":"60827",
    "addr:street":"W 138Th St",
    "iso:country":"US",
    "sg:address":"305 W 138th St",
    "sg:city":"Riverdale",
    "sg:classifiers":[
        {
            "category":"Professional",
            "type":"Services"
        }
    ],
    "sg:phone":"+1 708 201 9070",
    "sg:postcode":"60827",
    "sg:province":"IL",
    "sg:tags":[
        "caterer"
    ],
    "wof:name":"Pearlz",
    "wof:placetype":"venue"
},
  "geometry": {"coordinates":[-87.628165,41.644707],"type":"Point"}
}