{
  "type": "Feature",
  "properties": {
    "iso:country":"US",
    "sg:address":"2658 Windfall Dr",
    "sg:city":"Sherman",
    "sg:classifiers":[
        {
            "category":"Organizations",
            "subcategory":"Religious Organization",
            "type":"Services"
        }
    ],
    "sg:phone":"+1 217 496 2771",
    "sg:postcode":"62684",
    "sg:province":"IL",
    "wof:name":"JAS Stuenkel Rev",
    "wof:placetype":"venue"
},
  "geometry": {"coordinates":[-89.604187,39.911736],"type":"Point"}
}