{
  "type": "Feature",
  "properties": {
    "iso:country":"US",
    "sg:address":"445 N Wells St",
    "sg:city":"Chicago",
    "sg:classifiers":[
        {
            "category":"Place Of Worship",
            "type":"Public Place"
        }
    ],
    "sg:phone":"+1 312 670 7000",
    "sg:postcode":"60654",
    "sg:province":"IL",
    "sg:tags":[
        "church"
    ],
    "wof:name":"New Site Designs",
    "wof:placetype":"venue"
},
  "geometry": {"coordinates":[-87.634018,41.890191],"type":"Point"}
}