{
  "type": "Feature",
  "properties": {
    "iso:country":"US",
    "sg:address":"319 Washington St",
    "sg:city":"Prophetstown",
    "sg:classifiers":[
        {
            "category":"Real Estate",
            "subcategory":"Real Estate Operator",
            "type":"Services"
        }
    ],
    "sg:phone":"+1 815 537 2242",
    "sg:postcode":"61277",
    "sg:province":"IL",
    "sg:tags":[
        "property",
        "lessor"
    ],
    "wof:name":"Century 21 Eagle Realty",
    "wof:placetype":"venue"
},
  "geometry": {"coordinates":[-89.936128,41.670405],"type":"Point"}
}