{
  "type": "Feature",
  "properties": {
    "iso:country":"US",
    "sg:address":"3235 Lightning Ct",
    "sg:city":"New Lenox",
    "sg:classifiers":[
        {
            "category":"Professional",
            "subcategory":"Management & Consulting",
            "type":"Services"
        },
        {
            "category":"Wholesale",
            "subcategory":"Durable Goods & Equipment",
            "type":"Manufacturing & Wholesale Goods"
        }
    ],
    "sg:phone":"+1 815 462 3595",
    "sg:postcode":"60451",
    "sg:province":"IL",
    "sg:tags":[
        "representative",
        "public",
        "relations",
        "manufacturer"
    ],
    "wof:name":"Bob Shurilla & Associates",
    "wof:placetype":"venue"
},
  "geometry": {"coordinates":[-88.004857,41.532893],"type":"Point"}
}