{
  "type": "Feature",
  "properties": {
    "iso:country":"US",
    "sg:address":"612 N 11th St Ste B",
    "sg:city":"Quincy",
    "sg:classifiers":[
        {
            "category":"Education",
            "subcategory":"University",
            "type":"Public Place"
        }
    ],
    "sg:phone":"+1 217 224 9484",
    "sg:postcode":"62301",
    "sg:province":"IL",
    "sg:tags":[
        "college"
    ],
    "sg:website":"http://www.siumed.edu",
    "wof:name":"Southern Illinois University",
    "wof:placetype":"venue"
},
  "geometry": {"coordinates":[-91.39837799999999,39.938306],"type":"Point"}
}