{
  "type": "Feature",
  "properties": {
    "addr:full":"3624 W 81st Pl Chicago IL 60652",
    "addr:housenumber":"3624",
    "addr:postcode":"60652",
    "addr:street":"W 81St Pl",
    "iso:country":"US",
    "sg:address":"3624 W 81st Pl",
    "sg:city":"Chicago",
    "sg:classifiers":[
        {
            "category":"Building & Trades",
            "subcategory":"Construction",
            "type":"Services"
        }
    ],
    "sg:phone":"+1 773 581 1687",
    "sg:postcode":"60652",
    "sg:province":"IL",
    "wof:name":"My Daddys Masonry",
    "wof:placetype":"venue"
},
  "geometry": {"coordinates":[-87.713921,41.745128],"type":"Point"}
}