{
  "type": "Feature",
  "properties": {
    "addr:full":"712 S Main St Lombard IL 60148",
    "addr:housenumber":"712",
    "addr:postcode":"60148",
    "addr:street":"S Main St",
    "iso:country":"US",
    "sg:address":"712 S Main St",
    "sg:city":"Lombard",
    "sg:classifiers":[
        {
            "category":"Personal",
            "subcategory":"Nail Salon",
            "type":"Services"
        }
    ],
    "sg:phone":"+1 630 627 2601",
    "sg:postcode":"60148",
    "sg:province":"IL",
    "wof:name":"Lexi Nail Spa",
    "wof:placetype":"venue"
},
  "geometry": {"coordinates":[-88.01795,41.872395],"type":"Point"}
}