{
  "type": "Feature",
  "properties": {
    "iso:country":"US",
    "sg:address":"4721 S Main St",
    "sg:city":"Rockford",
    "sg:classifiers":[
        {
            "category":"Shopping",
            "subcategory":"Books",
            "type":"Retail Goods"
        },
        {
            "category":"Shopping",
            "type":"Retail Goods"
        }
    ],
    "sg:phone":"+1 815 964 8000",
    "sg:postcode":"61102",
    "sg:province":"IL",
    "sg:tags":[
        "bible",
        "religious",
        "store"
    ],
    "sg:website":"http://www.rockfordfaithcenter.com",
    "wof:name":"Faith Eductl Netwrk - Wfen-Fm",
    "wof:placetype":"venue"
},
  "geometry": {"coordinates":[-89.10875900000001,42.212455],"type":"Point"}
}