{
  "type": "Feature",
  "properties": {
    "iso:country":"US",
    "sg:address":"7312 Ogden Ave",
    "sg:city":"Riverside",
    "sg:classifiers":[
        {
            "category":"Sports & Exercise",
            "subcategory":"Bowling",
            "type":"Entertainment"
        }
    ],
    "sg:phone":"+1 708 447 4000",
    "sg:postcode":"60546",
    "sg:province":"IL",
    "wof:name":"Victory Bowling Lanes",
    "wof:placetype":"venue"
},
  "geometry": {"coordinates":[-87.806999,41.822201],"type":"Point"}
}