{
  "type": "Feature",
  "properties": {
    "iso:country":"US",
    "sg:address":"511 W 8th St",
    "sg:city":"Gibson City",
    "sg:classifiers":[
        {
            "category":"Manufacturing",
            "subcategory":"Tools & Machinery",
            "type":"Manufacturing & Wholesale Goods"
        }
    ],
    "sg:phone":"+1 217 784 5480",
    "sg:postcode":"60936",
    "sg:province":"IL",
    "sg:tags":[
        "actuator",
        "cylinder",
        "fluid",
        "power"
    ],
    "wof:name":"Davis Welding & Mfg Co",
    "wof:placetype":"venue"
},
  "geometry": {"coordinates":[-88.382969,40.464939],"type":"Point"}
}