{
  "type": "Feature",
  "properties": {
    "addr:full":"5041 Lee St Skokie IL 60077",
    "addr:housenumber":"5041",
    "addr:postcode":"60077",
    "addr:street":"Lee St",
    "iso:country":"US",
    "sg:address":"5041 Lee St",
    "sg:city":"Skokie",
    "sg:classifiers":[
        {
            "category":"Manufacturing",
            "subcategory":"Jewelry",
            "type":"Manufacturing & Wholesale Goods"
        }
    ],
    "sg:phone":"+1 847 679 0995",
    "sg:postcode":"60077",
    "sg:province":"IL",
    "sg:tags":[
        "costume",
        "mfg"
    ],
    "wof:name":"Ron Levey Assocs",
    "wof:placetype":"venue"
},
  "geometry": {"coordinates":[-87.752712,42.035289],"type":"Point"}
}