{
  "type": "Feature",
  "properties": {
    "iso:country":"US",
    "sg:address":"10 Ponderosa Dr",
    "sg:city":"Romeoville",
    "sg:classifiers":[
        {
            "category":"Insurance",
            "subcategory":"Insurance Agent",
            "type":"Services"
        }
    ],
    "sg:phone":"+1 815 886 5849",
    "sg:postcode":"60446",
    "sg:province":"IL",
    "wof:name":"Lopez Insurance Agency Inc",
    "wof:placetype":"venue"
},
  "geometry": {"coordinates":[-88.078373,41.660644],"type":"Point"}
}