{
  "type": "Feature",
  "properties": {
    "iso:country":"US",
    "sg:address":"7245 Wishop Rd",
    "sg:city":"Rockton",
    "sg:classifiers":[
        {
            "category":"Manufacturing",
            "subcategory":"Metals",
            "type":"Manufacturing & Wholesale Goods"
        }
    ],
    "sg:phone":"+1 815 629 9608",
    "sg:postcode":"61072",
    "sg:province":"IL",
    "sg:tags":[
        "metalwork",
        "sheet",
        "mfg"
    ],
    "wof:name":"Metal Dimensions Inc",
    "wof:placetype":"venue"
},
  "geometry": {"coordinates":[-89.178892,42.406736],"type":"Point"}
}