{
  "type": "Feature",
  "properties": {
    "addr:full":"35 Berkshire Dr Crystal Lake IL 60014",
    "addr:housenumber":"35",
    "addr:postcode":"60014",
    "addr:street":"Berkshire Dr",
    "iso:country":"US",
    "sg:address":"35 Berkshire Dr",
    "sg:city":"Crystal Lake",
    "sg:classifiers":[
        {
            "category":"Restaurant",
            "type":"Food & Drink"
        },
        {
            "category":"Ice Cream",
            "type":"Food & Drink"
        }
    ],
    "sg:menulink":"http://www.allmenus.com/il/algonquin/161917-dairy-queen/menu/",
    "sg:phone":"+1 815 479 9818",
    "sg:postcode":"60014",
    "sg:province":"IL",
    "sg:tags":[
        "burger",
        "american",
        "ice",
        "cream"
    ],
    "wof:name":"Dairy Queen",
    "wof:placetype":"venue"
},
  "geometry": {"coordinates":[-88.32153700000001,42.219596],"type":"Point"}
}