{
  "type": "Feature",
  "properties": {
    "addr:full":"4371 16th St Moline IL 61265",
    "addr:housenumber":"4371",
    "addr:postcode":"61265",
    "addr:street":"16Th St",
    "iso:country":"US",
    "sg:address":"4371 16th St",
    "sg:city":"Moline",
    "sg:classifiers":[
        {
            "category":"Shopping",
            "subcategory":"Gifts & Souvenirs",
            "type":"Retail Goods"
        }
    ],
    "sg:phone":"+1 309 797 2096",
    "sg:postcode":"61265",
    "sg:province":"IL",
    "sg:tags":[
        "party",
        "novelty",
        "supply"
    ],
    "wof:name":"Factory Card Outlet 139",
    "wof:placetype":"venue"
},
  "geometry": {"coordinates":[-90.50713,41.467171],"type":"Point"}
}