{
  "type": "Feature",
  "properties": {
    "addr:full":"684 W North Ave Elmhurst IL 60126",
    "addr:housenumber":"684",
    "addr:postcode":"60126",
    "addr:street":"W North Ave",
    "iso:country":"US",
    "sg:address":"684 W North Ave",
    "sg:city":"Elmhurst",
    "sg:classifiers":[
        {
            "category":"Coffee & Tea",
            "type":"Food & Drink"
        }
    ],
    "sg:menulink":"http://www.allmenus.com/il/york/112470-starbucks-coffee/menu/",
    "sg:phone":"+1 630 993 0028",
    "sg:postcode":"60126",
    "sg:province":"IL",
    "sg:tags":[
        "american"
    ],
    "wof:name":"Starbucks Coffee",
    "wof:placetype":"venue"
},
  "geometry": {"coordinates":[-87.967186,41.905649],"type":"Point"}
}