{
  "type": "Feature",
  "properties": {
    "addr:full":"181 Co Rd 1900E Greenup IL 62428",
    "addr:housenumber":"181",
    "addr:postcode":"62428",
    "addr:street":"Co Rd",
    "iso:country":"US",
    "sg:address":"181 Co Rd 1900E",
    "sg:city":"Greenup",
    "sg:classifiers":[
        {
            "category":"Freight",
            "type":"Transportation"
        }
    ],
    "sg:phone":"+1 217 923 3495",
    "sg:postcode":"62428",
    "sg:province":"IL",
    "sg:tags":[
        "operator",
        "local",
        "trucking"
    ],
    "wof:name":"Ault Trucking",
    "wof:placetype":"venue"
},
  "geometry": {"coordinates":[-88.117541,39.196491],"type":"Point"}
}