{
  "type": "Feature",
  "properties": {
    "iso:country":"US",
    "sg:address":"3105 Tollview Dr",
    "sg:city":"Rolling Meadows",
    "sg:classifiers":[
        {
            "category":"Manufacturing",
            "subcategory":"Printing",
            "type":"Manufacturing & Wholesale Goods"
        }
    ],
    "sg:phone":"+1 847 398 2500",
    "sg:postcode":"60008",
    "sg:province":"IL",
    "sg:tags":[
        "lithographic",
        "commercial",
        "business",
        "type"
    ],
    "wof:name":"Allegra Print & Imaging",
    "wof:placetype":"venue"
},
  "geometry": {"coordinates":[-88.017619,42.056906],"type":"Point"}
}