{
  "type": "Feature",
  "properties": {
    "iso:country":"US",
    "sg:address":"406 N Chestnut St",
    "sg:city":"Le Roy",
    "sg:classifiers":[
        {
            "category":"Recreation",
            "type":"Entertainment"
        }
    ],
    "sg:phone":"+1 309 962 2311",
    "sg:postcode":"61752",
    "sg:province":"IL",
    "sg:tags":[
        "attraction",
        "tourist"
    ],
    "wof:name":"Rike House",
    "wof:placetype":"venue"
},
  "geometry": {"coordinates":[-88.760661,40.350701],"type":"Point"}
}