{
  "type": "Feature",
  "properties": {
    "addr:full":"35 N Brockway St Palatine IL 60067",
    "addr:housenumber":"35",
    "addr:postcode":"60067",
    "addr:street":"N Brockway St",
    "iso:country":"US",
    "sg:address":"35 N Brockway St",
    "sg:city":"Palatine",
    "sg:classifiers":[
        {
            "category":"Professional",
            "subcategory":"Lawyer & Legal Services",
            "type":"Services"
        }
    ],
    "sg:phone":"+1 847 991 4397",
    "sg:postcode":"60067",
    "sg:province":"IL",
    "wof:name":"Herbert Schnitzer",
    "wof:placetype":"venue"
},
  "geometry": {"coordinates":[-88.046201,42.111692],"type":"Point"}
}