{
  "type": "Feature",
  "properties": {
    "iso:country":"US",
    "sg:address":"118 W 1st St",
    "sg:city":"Oglesby",
    "sg:classifiers":[
        {
            "category":"Building & Trades",
            "subcategory":"Construction",
            "type":"Services"
        }
    ],
    "sg:phone":"+1 815 883 9515",
    "sg:postcode":"61348",
    "sg:province":"IL",
    "sg:tags":[
        "nonresidential"
    ],
    "wof:name":"Mj S Construction",
    "wof:placetype":"venue"
},
  "geometry": {"coordinates":[-89.06225499999999,41.294037],"type":"Point"}
}