{
  "type": "Feature",
  "properties": {
    "iso:country":"US",
    "sg:address":"7824 Nagle Ave",
    "sg:city":"Burbank",
    "sg:classifiers":[
        {
            "category":"Building & Trades",
            "subcategory":"Construction",
            "type":"Services"
        }
    ],
    "sg:phone":"+1 708 598 0945",
    "sg:postcode":"60459",
    "sg:province":"IL",
    "sg:tags":[
        "contractor"
    ],
    "wof:name":"Kesek Construction",
    "wof:placetype":"venue"
},
  "geometry": {"coordinates":[-87.781679,41.749827],"type":"Point"}
}