{
  "type": "Feature",
  "properties": {
    "iso:country":"US",
    "sg:address":"810 Plainfield Rd",
    "sg:city":"Joliet",
    "sg:classifiers":[
        {
            "category":"Restaurant",
            "type":"Food & Drink"
        }
    ],
    "sg:phone":"+1 815 723 6375",
    "sg:postcode":"60435",
    "sg:province":"IL",
    "sg:tags":[
        "eating"
    ],
    "wof:name":"Joe's Hot Dog Plainfield Rd",
    "wof:placetype":"venue"
},
  "geometry": {"coordinates":[-88.10258399999999,41.538483],"type":"Point"}
}