{
  "type": "Feature",
  "properties": {
    "addr:full":"1623 Magnolia St Rockford IL 61104",
    "addr:housenumber":"1623",
    "addr:postcode":"61104",
    "addr:street":"Magnolia St",
    "iso:country":"US",
    "sg:address":"1623 Magnolia St",
    "sg:city":"Rockford",
    "sg:classifiers":[
        {
            "category":"Manufacturing",
            "subcategory":"Tools & Machinery",
            "type":"Manufacturing & Wholesale Goods"
        }
    ],
    "sg:phone":"+1 815 963 5770",
    "sg:postcode":"61104",
    "sg:province":"IL",
    "sg:tags":[
        "die"
    ],
    "wof:name":"Shorts Steel Co",
    "wof:placetype":"venue"
},
  "geometry": {"coordinates":[-89.096802,42.248461],"type":"Point"}
}