{
  "type": "Feature",
  "properties": {
    "iso:country":"US",
    "sg:address":"444 W Crystal Lake Ave",
    "sg:city":"Crystal Lake",
    "sg:classifiers":[
        {
            "category":"Food & Beverages",
            "subcategory":"Specialty",
            "type":"Retail Goods"
        }
    ],
    "sg:phone":"+1   ",
    "sg:postcode":"60014",
    "sg:province":"IL",
    "sg:tags":[
        "gourmet",
        "kitchenware"
    ],
    "wof:name":"Now Youre Cookin",
    "wof:placetype":"venue"
},
  "geometry": {"coordinates":[-88.337836,42.240946],"type":"Point"}
}