{
  "type": "Feature",
  "properties": {
    "addr:full":"215 N Desplaines St Chicago IL 60661",
    "addr:housenumber":"215",
    "addr:postcode":"60661",
    "addr:street":"N Desplaines St",
    "iso:country":"US",
    "sg:address":"215 N Desplaines St",
    "sg:city":"Chicago",
    "sg:classifiers":[
        {
            "category":"Professional",
            "subcategory":"Employment Agencies",
            "type":"Services"
        }
    ],
    "sg:phone":"+1 312 575 8503",
    "sg:postcode":"60661",
    "sg:province":"IL",
    "sg:tags":[
        "employer"
    ],
    "wof:name":"Black Data Processing Associates-Chicago Chapter",
    "wof:placetype":"venue"
},
  "geometry": {"coordinates":[-87.64423600000001,41.885856],"type":"Point"}
}