{
  "type": "Feature",
  "properties": {
    "iso:country":"US",
    "sg:address":"5237 W Gladys Ave",
    "sg:city":"Chicago",
    "sg:classifiers":[
        {
            "category":"Professional",
            "subcategory":"Business Services",
            "type":"Services"
        }
    ],
    "sg:phone":"+1 773 287 2069",
    "sg:postcode":"60644",
    "sg:province":"IL",
    "sg:tags":[
        "consultant",
        "coach"
    ],
    "wof:name":"Redmond & Edwards Consulting",
    "wof:placetype":"venue"
},
  "geometry": {"coordinates":[-87.755849,41.875733],"type":"Point"}
}