{
  "type": "Feature",
  "properties": {
    "addr:full":"4849 W Irving Park Rd Chicago IL 60641",
    "addr:housenumber":"4849",
    "addr:postcode":"60641",
    "addr:street":"W Irving Park Rd",
    "iso:country":"US",
    "sg:address":"4849 W Irving Park Rd",
    "sg:city":"Chicago",
    "sg:classifiers":[
        {
            "category":"Travel",
            "subcategory":"Hotels & Motels",
            "type":"Entertainment"
        }
    ],
    "sg:phone":"+1 773 283 2300",
    "sg:postcode":"60641",
    "sg:province":"IL",
    "wof:name":"Irving Hotel",
    "wof:placetype":"venue"
},
  "geometry": {"coordinates":[-87.748802,41.953201],"type":"Point"}
}