{
  "type": "Feature",
  "properties": {
    "iso:country":"US",
    "sg:address":"2588 N Limekiln Rd",
    "sg:city":"Oregon",
    "sg:classifiers":[
        {
            "category":"Building & Trades",
            "subcategory":"Construction",
            "type":"Services"
        }
    ],
    "sg:phone":"+1 815 734 4091",
    "sg:postcode":"61061",
    "sg:province":"IL",
    "sg:tags":[
        "excavation",
        "contractor"
    ],
    "wof:name":"RE Wolber & Sons Excavating In",
    "wof:placetype":"venue"
},
  "geometry": {"coordinates":[-89.36551900000001,42.046805],"type":"Point"}
}