{
  "type": "Feature",
  "properties": {
    "iso:country":"US",
    "sg:address":"101 S Main St",
    "sg:city":"Orangeville",
    "sg:classifiers":[
        {
            "category":"Health Services",
            "subcategory":"Doctor",
            "type":"Services"
        }
    ],
    "sg:phone":"+1 815 789 3100",
    "sg:postcode":"61060",
    "sg:province":"IL",
    "sg:tags":[
        "medicine",
        "physician",
        "practice",
        "surgeons",
        "family"
    ],
    "wof:name":"Freeport Regional Hlth Care",
    "wof:placetype":"venue"
},
  "geometry": {"coordinates":[-89.646568,42.468639],"type":"Point"}
}