{
  "type": "Feature",
  "properties": {
    "iso:country":"US",
    "sg:address":"233 E Oriole Trl",
    "sg:city":"Cary",
    "sg:classifiers":[
        {
            "category":"Recreation",
            "type":"Entertainment"
        }
    ],
    "sg:phone":"+1 847 462 5801",
    "sg:postcode":"60013",
    "sg:province":"IL",
    "sg:tags":[
        "parks"
    ],
    "wof:name":"Cary Park District",
    "wof:placetype":"venue"
},
  "geometry": {"coordinates":[-88.232953,42.215969],"type":"Point"}
}