{
  "type": "Feature",
  "properties": {
    "addr:full":"8123 S Saint Lawrence Ave Chicago IL 60619",
    "addr:housenumber":"8123",
    "addr:postcode":"60619",
    "addr:street":"S Saint Lawrence Ave",
    "iso:country":"US",
    "sg:address":"8123 S Saint Lawrence Ave",
    "sg:city":"Chicago",
    "sg:classifiers":[
        {
            "category":"Professional",
            "subcategory":"Art Services",
            "type":"Services"
        },
        {
            "category":"Real Estate",
            "subcategory":"Architect",
            "type":"Services"
        }
    ],
    "sg:phone":"+1 773 651 8107",
    "sg:postcode":"60619",
    "sg:province":"IL",
    "sg:tags":[
        "architects'",
        "designer",
        "specification",
        "builders'",
        "construction",
        "architectural",
        "interior",
        "decorator"
    ],
    "wof:name":"Interior Achitectures",
    "wof:placetype":"venue"
},
  "geometry": {"coordinates":[-87.60992899999999,41.747065],"type":"Point"}
}