{
  "type": "Feature",
  "properties": {
    "iso:country":"US",
    "sg:address":"1110 N Green St",
    "sg:city":"Mc Henry",
    "sg:classifiers":[
        {
            "category":"Health Services",
            "subcategory":"Doctor",
            "type":"Services"
        }
    ],
    "sg:phone":"+1 815 344 3050",
    "sg:postcode":"60050",
    "sg:province":"IL",
    "sg:tags":[
        "medical"
    ],
    "wof:name":"John Elstrom Dr",
    "wof:placetype":"venue"
},
  "geometry": {"coordinates":[-88.267311,42.343626],"type":"Point"}
}