{
  "type": "Feature",
  "properties": {
    "addr:full":"201 Frazier Georgetown IL 61846",
    "addr:housenumber":"201",
    "addr:postcode":"61846",
    "addr:street":"Frazier",
    "iso:country":"US",
    "sg:address":"201 Frazier",
    "sg:city":"Georgetown",
    "sg:classifiers":[
        {
            "category":"Organizations",
            "subcategory":"Religious Organization",
            "type":"Services"
        }
    ],
    "sg:phone":"+1 217 662 2467",
    "sg:postcode":"61846",
    "sg:province":"IL",
    "sg:tags":[
        "church"
    ],
    "wof:name":"Cumberland Presbyterian Church",
    "wof:placetype":"venue"
},
  "geometry": {"coordinates":[-87.63427900000001,39.97925],"type":"Point"}
}