{
  "type": "Feature",
  "properties": {
    "addr:full":"16941 Mohican Dr Lockport IL 60441",
    "addr:postcode":"16941;60441",
    "addr:street":"Mohican Dr",
    "iso:country":"US",
    "sg:address":"16941 Mohican Dr",
    "sg:city":"Lockport",
    "sg:classifiers":[
        {
            "category":"Building & Trades",
            "subcategory":"Electrical",
            "type":"Services"
        }
    ],
    "sg:phone":"+1 815 834 9099",
    "sg:postcode":"60441",
    "sg:province":"IL",
    "sg:tags":[
        "electrical",
        "contractor"
    ],
    "wof:name":"C W Current Inc",
    "wof:placetype":"venue"
},
  "geometry": {"coordinates":[-88.01871,41.578869],"type":"Point"}
}