{
  "type": "Feature",
  "properties": {
    "addr:full":"6641 Grand Ave Ste A Gurnee IL 60031",
    "addr:housenumber":"6641",
    "addr:postcode":"60031",
    "addr:street":"Grand Ave Ste A",
    "iso:country":"US",
    "sg:address":"6641 Grand Ave Ste A",
    "sg:city":"Gurnee",
    "sg:classifiers":[
        {
            "category":"Deli",
            "type":"Food & Drink"
        },
        {
            "category":"Restaurant",
            "type":"Food & Drink"
        },
        {
            "category":"Bakery",
            "type":"Food & Drink"
        },
        {
            "category":"Bagels",
            "subcategory":"None",
            "type":"Food & Drink"
        }
    ],
    "sg:phone":"+1 847 855 0130",
    "sg:postcode":"60031",
    "sg:province":"IL",
    "sg:tags":[
        "lunch",
        "delicatessen",
        "brunch",
        "breakfast"
    ],
    "wof:name":"Einstein Bros",
    "wof:placetype":"venue"
},
  "geometry": {"coordinates":[-87.966489,42.385491],"type":"Point"}
}