{
  "type": "Feature",
  "properties": {
    "addr:full":"558 W de Koven St Chicago IL 60607",
    "addr:housenumber":"558",
    "addr:postcode":"60607",
    "addr:street":"W De Koven St",
    "iso:country":"US",
    "sg:address":"558 W de Koven St",
    "sg:city":"Chicago",
    "sg:classifiers":[
        {
            "category":"Education",
            "subcategory":"Special Training",
            "type":"Public Place"
        },
        {
            "category":"Education",
            "subcategory":"Vocational School",
            "type":"Public Place"
        }
    ],
    "sg:phone":"+1 312 747 7238",
    "sg:postcode":"60607",
    "sg:province":"IL",
    "sg:tags":[
        "adult",
        "business"
    ],
    "wof:name":"Chicago Fire Academy",
    "wof:placetype":"venue"
},
  "geometry": {"coordinates":[-87.641637,41.869035],"type":"Point"}
}