{
  "type": "Feature",
  "properties": {
    "addr:full":"18344 Poplar Ave Homewood IL 60430",
    "addr:housenumber":"18344",
    "addr:postcode":"60430",
    "addr:street":"Poplar Ave",
    "iso:country":"US",
    "sg:address":"18344 Poplar Ave",
    "sg:city":"Homewood",
    "sg:classifiers":[
        {
            "category":"Professional",
            "subcategory":"Management & Consulting",
            "type":"Services"
        }
    ],
    "sg:phone":"+1 708 957 5204",
    "sg:postcode":"60430",
    "sg:province":"IL",
    "sg:tags":[
        "business"
    ],
    "wof:name":"Red Door Inc",
    "wof:placetype":"venue"
},
  "geometry": {"coordinates":[-87.652484,41.555732],"type":"Point"}
}