{
  "type": "Feature",
  "properties": {
    "addr:full":"5600 N River Rd Des Plaines IL 60018",
    "addr:housenumber":"5600",
    "addr:postcode":"60018",
    "addr:street":"N River Rd Des",
    "iso:country":"US",
    "sg:address":"5600 N River Rd",
    "sg:city":"Des Plaines",
    "sg:classifiers":[
        {
            "category":"Professional",
            "subcategory":"Management & Consulting",
            "type":"Services"
        }
    ],
    "sg:phone":"+1 773 878 8493",
    "sg:postcode":"60018",
    "sg:province":"IL",
    "sg:tags":[
        "business"
    ],
    "wof:name":"Interpath Communications Inc",
    "wof:placetype":"venue"
},
  "geometry": {"coordinates":[-87.861983,41.980578],"type":"Point"}
}