{
  "type": "Feature",
  "properties": {
    "iso:country":"US",
    "sg:address":"1002 N California Ave",
    "sg:city":"Chicago",
    "sg:classifiers":[
        {
            "category":"Bars & Pubs",
            "type":"Food & Drink"
        },
        {
            "category":"Arts & Performance",
            "subcategory":"Music",
            "type":"Entertainment"
        },
        {
            "category":"Bars & Pubs",
            "subcategory":"Nightclub",
            "type":"Food & Drink"
        },
        {
            "category":"Bars & Pubs",
            "subcategory":"Lounge",
            "type":"Food & Drink"
        }
    ],
    "sg:phone":"+1 773 384 2547",
    "sg:postcode":"60622",
    "sg:province":"IL",
    "sg:tags":[
        "club",
        "venue",
        "cocktail",
        "night"
    ],
    "sg:website":"www.californiaclipper.com/",
    "wof:name":"The California Clipper",
    "wof:placetype":"venue"
},
  "geometry": {"coordinates":[-87.696602,41.899601],"type":"Point"}
}