{
  "type": "Feature",
  "properties": {
    "addr:full":"2630 N Halsted St Chicago IL 60614",
    "addr:housenumber":"2630",
    "addr:postcode":"60614",
    "addr:street":"N Halsted St",
    "iso:country":"US",
    "sg:address":"2630 N Halsted St",
    "sg:city":"Chicago",
    "sg:classifiers":[
        {
            "category":"Personal",
            "subcategory":"Beauty Salon",
            "type":"Services"
        }
    ],
    "sg:phone":"+1 773 868 9340",
    "sg:postcode":"60614",
    "sg:province":"IL",
    "wof:name":"Bombshell Salon Ltd",
    "wof:placetype":"venue"
},
  "geometry": {"coordinates":[-87.648933,41.929812],"type":"Point"}
}