{
  "type": "Feature",
  "properties": {
    "iso:country":"US",
    "sg:address":"580 US Hwy 45",
    "sg:city":"Norris City",
    "sg:classifiers":[
        {
            "category":"Education",
            "subcategory":"School",
            "type":"Public Place"
        }
    ],
    "sg:phone":"+1 618 378 3212",
    "sg:postcode":"62869",
    "sg:province":"IL",
    "wof:name":"Norris City-Omaha Elem School",
    "wof:placetype":"venue"
},
  "geometry": {"coordinates":[-88.328638,37.985324],"type":"Point"}
}