{
  "type": "Feature",
  "properties": {
    "iso:country":"US",
    "sg:address":"2501 N Elston Ave",
    "sg:city":"Chicago",
    "sg:classifiers":[
        {
            "category":"Shopping",
            "subcategory":"Gifts & Souvenirs",
            "type":"Retail Goods"
        },
        {
            "category":"Manufacturing",
            "subcategory":"Retail Goods",
            "type":"Manufacturing & Wholesale Goods"
        }
    ],
    "sg:phone":"+1 773 227 1115",
    "sg:postcode":"60647",
    "sg:province":"IL",
    "sg:tags":[
        "shop",
        "giftware's-wholesale",
        "manufacturer"
    ],
    "sg:website":"http://www.msrf.com",
    "wof:name":"Msrf, Inc.",
    "wof:placetype":"venue"
},
  "geometry": {"coordinates":[-87.680194,41.926945],"type":"Point"}
}