{
  "type": "Feature",
  "properties": {
    "addr:full":"100 W Roosevelt Rd Wheaton IL 60187",
    "addr:housenumber":"100",
    "addr:postcode":"60187",
    "addr:street":"W Roosevelt Rd",
    "iso:country":"US",
    "sg:address":"100 W Roosevelt Rd",
    "sg:city":"Wheaton",
    "sg:classifiers":[
        {
            "category":"Professional",
            "subcategory":"Management & Consulting",
            "type":"Services"
        }
    ],
    "sg:phone":"+1 630 407 0871",
    "sg:postcode":"60187",
    "sg:province":"IL",
    "sg:tags":[
        "consultant",
        "business"
    ],
    "wof:name":"Ed Knowledge",
    "wof:placetype":"venue"
},
  "geometry": {"coordinates":[-88.10811699999999,41.858754],"type":"Point"}
}