{
  "type": "Feature",
  "properties": {
    "addr:full":"53 W Jackson Blvd Ste 1403 Chicago IL 60604",
    "addr:housenumber":"53",
    "addr:postcode":"60604",
    "addr:street":"W Jackson Blvd Ste 1403",
    "iso:country":"US",
    "sg:address":"53 W Jackson Blvd Ste 1403",
    "sg:city":"Chicago",
    "sg:classifiers":[
        {
            "category":"Professional",
            "subcategory":"Lawyer & Legal Services",
            "type":"Services"
        }
    ],
    "sg:phone":"+1 312 939 1616",
    "sg:postcode":"60604",
    "sg:province":"IL",
    "wof:name":"Pissetzky Berliner & Zhitnitsky",
    "wof:placetype":"venue"
},
  "geometry": {"coordinates":[-87.62949500000001,41.878028],"type":"Point"}
}