{
  "type": "Feature",
  "properties": {
    "addr:full":"460 Coventry Ln Crystal Lake IL 60014",
    "addr:housenumber":"460",
    "addr:postcode":"60014",
    "addr:street":"Coventry Ln",
    "iso:country":"US",
    "sg:address":"460 Coventry Ln",
    "sg:city":"Crystal Lake",
    "sg:classifiers":[
        {
            "category":"Real Estate",
            "subcategory":"Real Estate Agent",
            "type":"Services"
        }
    ],
    "sg:phone":"+1 815 444 0400",
    "sg:postcode":"60014",
    "sg:province":"IL",
    "wof:name":"Scanlan Realty & Investments",
    "wof:placetype":"venue"
},
  "geometry": {"coordinates":[-88.330927,42.227719],"type":"Point"}
}