{
  "type": "Feature",
  "properties": {
    "iso:country":"US",
    "sg:address":"6315 North Ave",
    "sg:city":"Oak Park",
    "sg:classifiers":[
        {
            "category":"Shopping",
            "subcategory":"Beauty & Cosmetics",
            "type":"Retail Goods"
        }
    ],
    "sg:phone":"+1 708 660 0845",
    "sg:postcode":"60302",
    "sg:province":"IL",
    "sg:tags":[
        "supply"
    ],
    "wof:name":"Top Beauty Supply",
    "wof:placetype":"venue"
},
  "geometry": {"coordinates":[-87.783699,41.909],"type":"Point"}
}