{
  "type": "Feature",
  "properties": {
    "addr:full":"3900 N Claremont Ave Chicago IL 60618",
    "addr:housenumber":"3900",
    "addr:postcode":"60618",
    "addr:street":"N Claremont Ave",
    "iso:country":"US",
    "sg:address":"3900 N Claremont Ave",
    "sg:city":"Chicago",
    "sg:classifiers":[
        {
            "category":"Wholesale",
            "subcategory":"Computers",
            "type":"Manufacturing & Wholesale Goods"
        }
    ],
    "sg:phone":"+1 773 267 6806",
    "sg:postcode":"60618",
    "sg:province":"IL",
    "sg:tags":[
        "equipment"
    ],
    "wof:name":"Rush Media",
    "wof:placetype":"venue"
},
  "geometry": {"coordinates":[-87.687202,41.952221],"type":"Point"}
}