{
  "type": "Feature",
  "properties": {
    "iso:country":"US",
    "sg:address":"3000 N Halsted Street Suite 509",
    "sg:city":"Chicago",
    "sg:classifiers":[
        {
            "category":"Farming",
            "subcategory":"Crops",
            "type":"Manufacturing & Wholesale Goods"
        }
    ],
    "sg:phone":"+1 773 472 3891",
    "sg:postcode":"60657",
    "sg:province":"IL",
    "sg:tags":[
        "fertility"
    ],
    "wof:name":"Midwest Fertility Center Illinois Masonic",
    "wof:placetype":"venue"
},
  "geometry": {"coordinates":[-87.649151,41.936924],"type":"Point"}
}