{
  "type": "Feature",
  "properties": {
    "iso:country":"US",
    "sg:address":"227 56th St",
    "sg:city":"Downers Grove",
    "sg:classifiers":[
        {
            "category":"Social Services",
            "type":"Services"
        }
    ],
    "sg:phone":"+1 630 852 1028",
    "sg:postcode":"60516",
    "sg:province":"IL",
    "wof:name":"Kulma Medical Service Co",
    "wof:placetype":"venue"
},
  "geometry": {"coordinates":[-87.988705,41.786048],"type":"Point"}
}