{
  "type": "Feature",
  "properties": {
    "addr:full":"746 S Oak Park Ave Oak Park IL 60304",
    "addr:housenumber":"746",
    "addr:postcode":"60304",
    "addr:street":"S Oak Park Ave",
    "iso:country":"US",
    "sg:address":"746 S Oak Park Ave",
    "sg:city":"Oak Park",
    "sg:classifiers":[
        {
            "category":"Professional",
            "subcategory":"Lawyer & Legal Services",
            "type":"Services"
        }
    ],
    "sg:phone":"+1 708 763 0999",
    "sg:postcode":"60304",
    "sg:province":"IL",
    "sg:website":"www.connifflaw.com",
    "wof:name":"Lyn C. Conniff Law Offices",
    "wof:placetype":"venue"
},
  "geometry": {"coordinates":[-87.793724,41.874414],"type":"Point"}
}