{
  "type": "Feature",
  "properties": {
    "iso:country":"US",
    "sg:address":"104 N Old Edwardsville Rd",
    "sg:city":"Roxana",
    "sg:classifiers":[
        {
            "category":"Professional",
            "subcategory":"Testing Lab",
            "type":"Services"
        }
    ],
    "sg:phone":"+1 618 251 9830",
    "sg:postcode":"62084",
    "sg:province":"IL",
    "sg:tags":[
        "laboratory"
    ],
    "sg:website":"www.conaminsp.com",
    "wof:name":"Conam INSPECTION",
    "wof:placetype":"venue"
},
  "geometry": {"coordinates":[-90.084215,38.848813],"type":"Point"}
}