{
  "type": "Feature",
  "properties": {
    "addr:full":"927 S Busse Rd Mount Prospect IL 60056",
    "addr:housenumber":"927",
    "addr:postcode":"60056",
    "addr:street":"S Busse Rd",
    "iso:country":"US",
    "sg:address":"927 S Busse Rd",
    "sg:city":"Mount Prospect",
    "sg:classifiers":[
        {
            "category":"Autos & Motor Vehicles",
            "subcategory":"Fuel & Gas Station",
            "type":"Retail Goods"
        }
    ],
    "sg:phone":"+1   ",
    "sg:postcode":"60056",
    "sg:province":"IL",
    "sg:tags":[
        "station",
        "full"
    ],
    "wof:name":"Shell",
    "wof:placetype":"venue"
},
  "geometry": {"coordinates":[-87.960219,42.050412],"type":"Point"}
}