{
  "type": "Feature",
  "properties": {
    "addr:full":"750 W Lake Cook Rd Buffalo Grove IL 60089",
    "addr:housenumber":"750",
    "addr:postcode":"60089",
    "addr:street":"W Lake Cook Rd",
    "iso:country":"US",
    "sg:address":"750 W Lake Cook Rd",
    "sg:city":"Buffalo Grove",
    "sg:classifiers":[
        {
            "category":"Professional",
            "subcategory":"Employment Agencies",
            "type":"Services"
        }
    ],
    "sg:phone":"+1 847 465 1020",
    "sg:postcode":"60089",
    "sg:province":"IL",
    "sg:tags":[
        "opportunity"
    ],
    "sg:website":"www.erecruitusa.com",
    "wof:name":"Executive Recruiting Assn",
    "wof:placetype":"venue"
},
  "geometry": {"coordinates":[-87.98082100000001,42.153697],"type":"Point"}
}