{
  "type": "Feature",
  "properties": {
    "addr:full":"1111 N Carbon St Marion IL 62959",
    "addr:housenumber":"1111",
    "addr:postcode":"62959",
    "addr:street":"N Carbon St",
    "iso:country":"US",
    "sg:address":"1111 N Carbon St",
    "sg:city":"Marion",
    "sg:classifiers":[
        {
            "category":"Restaurant",
            "type":"Food & Drink"
        }
    ],
    "sg:menulink":"http://www.allmenus.com/il/west-marion/126751-subway/menu/",
    "sg:phone":"+1 618 993 2766",
    "sg:postcode":"62959",
    "sg:province":"IL",
    "sg:tags":[
        "american",
        "sandwich"
    ],
    "wof:name":"Subway",
    "wof:placetype":"venue"
},
  "geometry": {"coordinates":[-88.94802199999999,37.737028],"type":"Point"}
}