{
  "type": "Feature",
  "properties": {
    "addr:full":"5912 Blackhawk Rd Rockford IL 61109",
    "addr:housenumber":"5912",
    "addr:postcode":"61109",
    "addr:street":"Blackhawk Rd",
    "iso:country":"US",
    "sg:address":"5912 Blackhawk Rd",
    "sg:city":"Rockford",
    "sg:classifiers":[
        {
            "category":"Shopping",
            "type":"Retail Goods"
        }
    ],
    "sg:phone":"+1 815 222 9223",
    "sg:postcode":"61109",
    "sg:province":"IL",
    "sg:tags":[
        "candle"
    ],
    "wof:name":"Gold Canyon Of Rockford",
    "wof:placetype":"venue"
},
  "geometry": {"coordinates":[-89.013588,42.195136],"type":"Point"}
}