{
  "type": "Feature",
  "properties": {
    "addr:full":"101 S 1st St Oregon IL 61061",
    "addr:housenumber":"101",
    "addr:postcode":"61061",
    "addr:street":"S 1St St",
    "iso:country":"US",
    "sg:address":"101 S 1st St",
    "sg:city":"Oregon",
    "sg:classifiers":[
        {
            "category":"Retail",
            "subcategory":"Laundry & Dry Cleaning",
            "type":"Services"
        }
    ],
    "sg:phone":"+1 815 732 3265",
    "sg:postcode":"61061",
    "sg:province":"IL",
    "sg:tags":[
        "cleaners"
    ],
    "wof:name":"Arrow Cleaners",
    "wof:placetype":"venue"
},
  "geometry": {"coordinates":[-89.32872500000001,42.014521],"type":"Point"}
}