{
  "type": "Feature",
  "properties": {
    "addr:full":"2501 Broadway St Quincy IL 62301",
    "addr:housenumber":"2501",
    "addr:postcode":"62301",
    "addr:street":"Broadway St",
    "iso:country":"US",
    "sg:address":"2501 Broadway St",
    "sg:city":"Quincy",
    "sg:classifiers":[
        {
            "category":"Restaurant",
            "type":"Food & Drink"
        }
    ],
    "sg:menulink":"http://www.allmenus.com/il/quincy/76664-dominos-pizza/menu/",
    "sg:phone":"+1 217 223 4040",
    "sg:postcode":"62301",
    "sg:province":"IL",
    "sg:tags":[
        "american",
        "wing",
        "pizza"
    ],
    "wof:name":"Domino's Pizza",
    "wof:placetype":"venue"
},
  "geometry": {"coordinates":[-91.375354,39.9353],"type":"Point"}
}