{
  "type": "Feature",
  "properties": {
    "iso:country":"US",
    "sg:address":"1030 Willoby Ln",
    "sg:city":"Elgin",
    "sg:classifiers":[
        {
            "category":"Wholesale",
            "subcategory":"Painting Supplies",
            "type":"Manufacturing & Wholesale Goods"
        }
    ],
    "sg:phone":"+1 847 813 5501",
    "sg:postcode":"60120",
    "sg:province":"IL",
    "sg:tags":[
        "paint-wholesale",
        "manufacturer"
    ],
    "wof:name":"The Paint Boss Inc",
    "wof:placetype":"venue"
},
  "geometry": {"coordinates":[-88.24778999999999,42.055365],"type":"Point"}
}