{
  "type": "Feature",
  "properties": {
    "addr:full":"2306 W Bloomingdale Ave Chicago IL 60647",
    "addr:housenumber":"2306",
    "addr:postcode":"60647",
    "addr:street":"W Bloomingdale Ave",
    "iso:country":"US",
    "sg:address":"2306 W Bloomingdale Ave",
    "sg:city":"Chicago",
    "sg:classifiers":[
        {
            "category":"Professional",
            "subcategory":"Accounting & Tax Preparation",
            "type":"Services"
        }
    ],
    "sg:phone":"+1 773 772 2663",
    "sg:postcode":"60647",
    "sg:province":"IL",
    "wof:name":"Westell Technologies Inc",
    "wof:placetype":"venue"
},
  "geometry": {"coordinates":[-87.687198,41.914071],"type":"Point"}
}