{
  "type": "Feature",
  "properties": {
    "iso:country":"US",
    "sg:address":"1675 Sibley Blvd",
    "sg:city":"Calumet City",
    "sg:classifiers":[
        {
            "category":"Shopping",
            "subcategory":"Clothing, Apparel, & Fashions",
            "type":"Retail Goods"
        }
    ],
    "sg:phone":"+1 708 832 1430",
    "sg:postcode":"60409",
    "sg:province":"IL",
    "sg:tags":[
        "accessory",
        "clothing",
        "women's"
    ],
    "wof:name":"Girlfriend's Boutique",
    "wof:placetype":"venue"
},
  "geometry": {"coordinates":[-87.565933,41.622603],"type":"Point"}
}