{
  "type": "Feature",
  "properties": {
    "addr:full":"1N450 Main St Glen Ellyn IL 60137",
    "addr:housenumber":"1n450",
    "addr:postcode":"60137",
    "addr:street":"Main St",
    "iso:country":"US",
    "sg:address":"1N450 Main St",
    "sg:city":"Glen Ellyn",
    "sg:classifiers":[
        {
            "category":"Education",
            "subcategory":"School",
            "type":"Public Place"
        }
    ],
    "sg:phone":"+1 630 858 4225",
    "sg:postcode":"60137",
    "sg:province":"IL",
    "wof:name":"Seventh Day Adventist School of Glen Ellyn",
    "wof:placetype":"venue"
},
  "geometry": {"coordinates":[-88.063301,41.8951],"type":"Point"}
}