{
  "type": "Feature",
  "properties": {
    "iso:country":"US",
    "sg:address":"307 Henderson Rd",
    "sg:city":"Knoxville",
    "sg:classifiers":[
        {
            "category":"Health Services",
            "subcategory":"Chiropractor",
            "type":"Services"
        }
    ],
    "sg:phone":"+1 309 289 4000",
    "sg:postcode":"61448",
    "sg:province":"IL",
    "sg:tags":[
        "chiropractic"
    ],
    "wof:name":"White's Chiropractor",
    "wof:placetype":"venue"
},
  "geometry": {"coordinates":[-90.290543,40.911512],"type":"Point"}
}