{
  "type": "Feature",
  "properties": {
    "iso:country":"US",
    "sg:address":"311 Brighton Ln",
    "sg:city":"Crete",
    "sg:classifiers":[
        {
            "category":"Building & Trades",
            "subcategory":"Construction",
            "type":"Services"
        }
    ],
    "sg:phone":"+1 708 672 3665",
    "sg:postcode":"60417",
    "sg:province":"IL",
    "sg:tags":[
        "paving",
        "contractor"
    ],
    "sg:website":"www.pavementmaintenancesolutions.com",
    "wof:name":"Pavement Maintenance Solutions",
    "wof:placetype":"venue"
},
  "geometry": {"coordinates":[-87.623662,41.452131],"type":"Point"}
}