{
  "type": "Feature",
  "properties": {
    "addr:full":"3647 S Washtenaw Ave Chicago IL 60632",
    "addr:housenumber":"3647",
    "addr:postcode":"60632",
    "addr:street":"S Washtenaw Ave",
    "iso:country":"US",
    "sg:address":"3647 S Washtenaw Ave",
    "sg:city":"Chicago",
    "sg:classifiers":[
        {
            "category":"Shopping",
            "subcategory":"Party Supplies",
            "type":"Retail Goods"
        }
    ],
    "sg:phone":"+1 773 650 9010",
    "sg:postcode":"60632",
    "sg:province":"IL",
    "wof:name":"Roosevelt Chair & Party Rental",
    "wof:placetype":"venue"
},
  "geometry": {"coordinates":[-87.69226500000001,41.826982],"type":"Point"}
}