{
  "type": "Feature",
  "properties": {
    "iso:country":"US",
    "sg:address":"1277 Boa Trl",
    "sg:city":"Carol Stream",
    "sg:classifiers":[
        {
            "category":"Freight",
            "type":"Transportation"
        }
    ],
    "sg:phone":"+1 630 372 7416",
    "sg:postcode":"60188",
    "sg:province":"IL",
    "sg:tags":[
        "operator",
        "local",
        "trucking"
    ],
    "wof:name":"Ana & Frank Inc",
    "wof:placetype":"venue"
},
  "geometry": {"coordinates":[-88.165572,41.938215],"type":"Point"}
}