{
  "type": "Feature",
  "properties": {
    "addr:full":"513 Pulaski St Lincoln IL 62656",
    "addr:housenumber":"513",
    "addr:postcode":"62656",
    "addr:street":"Pulaski St",
    "iso:country":"US",
    "sg:address":"513 Pulaski St",
    "sg:city":"Lincoln",
    "sg:classifiers":[
        {
            "category":"Shopping",
            "subcategory":"Gifts & Souvenirs",
            "type":"Retail Goods"
        }
    ],
    "sg:phone":"+1 217 735 1093",
    "sg:postcode":"62656",
    "sg:province":"IL",
    "sg:tags":[
        "shop"
    ],
    "wof:name":"Mustard Moon",
    "wof:placetype":"venue"
},
  "geometry": {"coordinates":[-89.36339599999999,40.14586],"type":"Point"}
}