{
  "type": "Feature",
  "properties": {
    "iso:country":"US",
    "sg:address":"330 N 8th St",
    "sg:city":"Quincy",
    "sg:classifiers":[
        {
            "category":"Health Services",
            "subcategory":"Doctor",
            "type":"Services"
        }
    ],
    "sg:phone":"+1 217 223 5527",
    "sg:postcode":"62301",
    "sg:province":"IL",
    "sg:tags":[
        "dentist"
    ],
    "wof:name":"Cavity",
    "wof:placetype":"venue"
},
  "geometry": {"coordinates":[-91.40334799999999,39.935635],"type":"Point"}
}