{
  "type": "Feature",
  "properties": {
    "iso:country":"US",
    "sg:address":"3601 S Iron St",
    "sg:city":"Chicago",
    "sg:classifiers":[
        {
            "category":"Personal",
            "type":"Services"
        }
    ],
    "sg:phone":"+1 773 927 8888",
    "sg:postcode":"60609",
    "sg:province":"IL",
    "sg:tags":[
        "towing"
    ],
    "wof:name":"Rendered Services Inc",
    "wof:placetype":"venue"
},
  "geometry": {"coordinates":[-87.65920300000001,41.826698],"type":"Point"}
}