{
  "type": "Feature",
  "properties": {
    "iso:country":"US",
    "sg:address":"4800 148th St",
    "sg:city":"Midlothian",
    "sg:classifiers":[
        {
            "category":"Shopping",
            "subcategory":"Pharmacy",
            "type":"Retail Goods"
        }
    ],
    "sg:phone":"+1 708 535 9184",
    "sg:postcode":"60445",
    "sg:province":"IL",
    "sg:tags":[
        "drugstore"
    ],
    "sg:website":"walgreens.com|walgreens.com/Take...",
    "wof:name":"Walgreen Drug Stores",
    "wof:placetype":"venue"
},
  "geometry": {"coordinates":[-87.74335499999999,41.623337],"type":"Point"}
}