{
  "type": "Feature",
  "properties": {
    "iso:country":"US",
    "sg:address":"306 W Church St",
    "sg:city":"Champaign",
    "sg:classifiers":[
        {
            "category":"Professional",
            "subcategory":"Lawyer & Legal Services",
            "type":"Services"
        }
    ],
    "sg:phone":"+1 217 352 1800",
    "sg:postcode":"61820",
    "sg:province":"IL",
    "wof:name":"Nugent Tracy J Atty",
    "wof:placetype":"venue"
},
  "geometry": {"coordinates":[-88.247902,40.118301],"type":"Point"}
}