{
  "type": "Feature",
  "properties": {
    "iso:country":"US",
    "sg:address":"511 S Poplar St",
    "sg:city":"Carbondale",
    "sg:classifiers":[
        {
            "category":"Organizations",
            "subcategory":"Religious Organization",
            "type":"Services"
        }
    ],
    "sg:phone":"+1 618 549 3868",
    "sg:postcode":"62901",
    "sg:province":"IL",
    "wof:name":"Islamic Center of Carbondale",
    "wof:placetype":"venue"
},
  "geometry": {"coordinates":[-89.221298,37.721901],"type":"Point"}
}