{
  "type": "Feature",
  "properties": {
    "iso:country":"US",
    "sg:address":"135 Dover Dr",
    "sg:city":"Des Plaines",
    "sg:classifiers":[
        {
            "category":"Travel",
            "subcategory":"Travel Agent",
            "type":"Entertainment"
        }
    ],
    "sg:phone":"+1 847 827 8680",
    "sg:postcode":"60018",
    "sg:province":"IL",
    "sg:tags":[
        "agency",
        "bureau"
    ],
    "wof:name":"Catt Assistants Inc",
    "wof:placetype":"venue"
},
  "geometry": {"coordinates":[-87.92506299999999,42.024037],"type":"Point"}
}