{
  "type": "Feature",
  "properties": {
    "addr:full":"301 Shenstone Rd Riverside IL 60546",
    "addr:housenumber":"301",
    "addr:postcode":"60546",
    "addr:street":"Shenstone Rd",
    "iso:country":"US",
    "sg:address":"301 Shenstone Rd",
    "sg:city":"Riverside",
    "sg:classifiers":[
        {
            "category":"Autos & Motor Vehicles",
            "subcategory":"Fuel & Gas Station",
            "type":"Retail Goods"
        },
        {
            "category":"Autos & Motor Vehicles",
            "subcategory":"Auto Supplies",
            "type":"Retail Goods"
        }
    ],
    "sg:phone":"+1 708 853 9571",
    "sg:postcode":"60546",
    "sg:province":"IL",
    "sg:tags":[
        "dry",
        "tank",
        "trucking-liquid",
        "bulk",
        "truck",
        "transportation"
    ],
    "wof:name":"R & M Transport Company Inc",
    "wof:placetype":"venue"
},
  "geometry": {"coordinates":[-87.81043200000001,41.833305],"type":"Point"}
}