{
  "type": "Feature",
  "properties": {
    "addr:full":"2300 S 59th Ave Cicero IL 60804",
    "addr:housenumber":"2300",
    "addr:postcode":"60804",
    "addr:street":"S 59Th Ave",
    "iso:country":"US",
    "sg:address":"2300 S 59th Ave",
    "sg:city":"Cicero",
    "sg:classifiers":[
        {
            "category":"Professional",
            "subcategory":"Accounting & Tax Preparation",
            "type":"Services"
        }
    ],
    "sg:phone":"+1 708 652 7244",
    "sg:postcode":"60804",
    "sg:province":"IL",
    "wof:name":"Lahey Thomas P",
    "wof:placetype":"venue"
},
  "geometry": {"coordinates":[-87.77117200000001,41.847235],"type":"Point"}
}