{
  "type": "Feature",
  "properties": {
    "iso:country":"US",
    "sg:address":"8105 State Rte 2",
    "sg:city":"Dixon",
    "sg:classifiers":[
        {
            "category":"Professional",
            "subcategory":"Management & Consulting",
            "type":"Services"
        }
    ],
    "sg:phone":"+1 815 652 6755",
    "sg:postcode":"61021",
    "sg:province":"IL",
    "sg:tags":[
        "consultant"
    ],
    "wof:name":"Landmark Consulting",
    "wof:placetype":"venue"
},
  "geometry": {"coordinates":[-89.411759,41.898232],"type":"Point"}
}