{
  "type": "Feature",
  "properties": {
    "iso:country":"US",
    "sg:address":"73 S Riverside Dr",
    "sg:city":"Elgin",
    "sg:classifiers":[
        {
            "category":"Shopping",
            "subcategory":"Computers & Home Electronics",
            "type":"Retail Goods"
        }
    ],
    "sg:phone":"+1   ",
    "sg:postcode":"60120",
    "sg:province":"IL",
    "wof:name":"Langrafix",
    "wof:placetype":"venue"
},
  "geometry": {"coordinates":[-88.283019,42.034495],"type":"Point"}
}