{
  "type": "Feature",
  "properties": {
    "addr:full":"201 W Main St Glasford IL 61533",
    "addr:housenumber":"201",
    "addr:postcode":"61533",
    "addr:street":"W Main St",
    "iso:country":"US",
    "sg:address":"201 W Main St",
    "sg:city":"Glasford",
    "sg:classifiers":[
        {
            "category":"Health Services",
            "subcategory":"Doctor",
            "type":"Services"
        }
    ],
    "sg:phone":"+1 309 389 4999",
    "sg:postcode":"61533",
    "sg:province":"IL",
    "sg:tags":[
        "physician",
        "surgeon"
    ],
    "wof:name":"OSF Medical Group-Glasford",
    "wof:placetype":"venue"
},
  "geometry": {"coordinates":[-89.81602599999999,40.572856],"type":"Point"}
}