{
  "type": "Feature",
  "properties": {
    "addr:full":"418 W 31st St Chicago IL 60616",
    "addr:housenumber":"418",
    "addr:postcode":"60616",
    "addr:street":"W 31St St",
    "iso:country":"US",
    "sg:address":"418 W 31st St",
    "sg:city":"Chicago",
    "sg:classifiers":[
        {
            "category":"Personal",
            "subcategory":"Tanning Parlor",
            "type":"Services"
        }
    ],
    "sg:phone":"+1 312 791 9500",
    "sg:postcode":"60616",
    "sg:province":"IL",
    "wof:name":"Cabana Tan",
    "wof:placetype":"venue"
},
  "geometry": {"coordinates":[-87.637199,41.838299],"type":"Point"}
}