{
  "type": "Feature",
  "properties": {
    "iso:country":"US",
    "sg:address":"3052 Elm St",
    "sg:city":"Franklin Park",
    "sg:classifiers":[
        {
            "category":"Retail",
            "subcategory":"Animal Services",
            "type":"Services"
        }
    ],
    "sg:phone":"+1 847 671 4828",
    "sg:postcode":"60131",
    "sg:province":"IL",
    "sg:tags":[
        "pet",
        "training"
    ],
    "wof:name":"Forest Dog Training",
    "wof:placetype":"venue"
},
  "geometry": {"coordinates":[-87.851529,41.934678],"type":"Point"}
}