{
  "type": "Feature",
  "properties": {
    "addr:full":"PO Box 3097 Carbondale IL 62902",
    "addr:housenumber":"po",
    "addr:postcode":"3097;62902",
    "addr:street":"Box",
    "iso:country":"US",
    "sg:address":"PO Box 3097",
    "sg:city":"Carbondale",
    "sg:classifiers":[
        {
            "category":"Real Estate",
            "subcategory":"Real Estate Services",
            "type":"Services"
        },
        {
            "category":"Real Estate",
            "subcategory":"Real Estate Operator",
            "type":"Services"
        }
    ],
    "sg:phone":"+1 618 529 2954",
    "sg:postcode":"62902",
    "sg:province":"IL",
    "sg:tags":[
        "apartment",
        "property",
        "management"
    ],
    "wof:name":"Schilling Property Management",
    "wof:placetype":"venue"
},
  "geometry": {"coordinates":[-89.153099,37.676498],"type":"Point"}
}