{
  "type": "Feature",
  "properties": {
    "iso:country":"US",
    "sg:address":"500 W Madison St",
    "sg:city":"Chicago",
    "sg:classifiers":[
        {
            "category":"Ice Cream",
            "type":"Food & Drink"
        }
    ],
    "sg:phone":"+1 312 993 9644",
    "sg:postcode":"60686",
    "sg:province":"IL",
    "sg:tags":[
        "frozen",
        "yogurt"
    ],
    "sg:website":"www.berrychill.com",
    "wof:name":"Berry Chill",
    "wof:placetype":"venue"
},
  "geometry": {"coordinates":[-87.640451,41.88187],"type":"Point"}
}