{
  "type": "Feature",
  "properties": {
    "addr:full":"1365 Mulberry Ln Cary IL 60005",
    "addr:housenumber":"1365",
    "addr:postcode":"60005",
    "addr:street":"Mulberry Ln",
    "iso:country":"US",
    "sg:address":"1365 Mulberry Ln",
    "sg:city":"Cary",
    "sg:classifiers":[
        {
            "category":"Freight",
            "type":"Transportation"
        }
    ],
    "sg:phone":"+1 847 639 2552",
    "sg:postcode":"60005",
    "sg:province":"IL",
    "sg:tags":[
        "trucking"
    ],
    "wof:name":"Dart Transit Co",
    "wof:placetype":"venue"
},
  "geometry": {"coordinates":[-87.999014,42.086914],"type":"Point"}
}