{
  "type": "Feature",
  "properties": {
    "addr:full":"214 E Main St Robinson IL 62454",
    "addr:housenumber":"214",
    "addr:postcode":"62454",
    "addr:street":"E Main St",
    "iso:country":"US",
    "sg:address":"214 E Main St",
    "sg:city":"Robinson",
    "sg:classifiers":[
        {
            "category":"Shopping",
            "subcategory":"Clothing, Apparel, & Fashions",
            "type":"Retail Goods"
        },
        {
            "category":"Retail",
            "subcategory":"Laundry & Dry Cleaning",
            "type":"Services"
        }
    ],
    "sg:phone":"+1 618 544 5484",
    "sg:postcode":"62454",
    "sg:province":"IL",
    "sg:tags":[
        "cleaner",
        "tailor",
        "alterations-clothing",
        "operated",
        "dryer",
        "laundries-self",
        "washer",
        "coin"
    ],
    "wof:name":"Fields Cleaner",
    "wof:placetype":"venue"
},
  "geometry": {"coordinates":[-87.742154,39.00579],"type":"Point"}
}