{
  "type": "Feature",
  "properties": {
    "iso:country":"US",
    "sg:address":"315 Main St",
    "sg:city":"Batavia",
    "sg:classifiers":[
        {
            "category":"Wholesale",
            "subcategory":"Durable Goods & Equipment",
            "type":"Manufacturing & Wholesale Goods"
        }
    ],
    "sg:phone":"+1 630 406 9100",
    "sg:postcode":"60510",
    "sg:province":"IL",
    "sg:tags":[
        "compact",
        "record",
        "disc",
        "tape"
    ],
    "wof:name":"Jonescore Inc",
    "wof:placetype":"venue"
},
  "geometry": {"coordinates":[-88.314018,41.847012],"type":"Point"}
}