{
  "type": "Feature",
  "properties": {
    "iso:country":"US",
    "sg:address":"3318 N Illinois St",
    "sg:city":"Belleville",
    "sg:classifiers":[
        {
            "category":"Building & Trades",
            "subcategory":"Construction",
            "type":"Services"
        }
    ],
    "sg:phone":"+1 618 235 4300",
    "sg:postcode":"62226",
    "sg:province":"IL",
    "sg:tags":[
        "home",
        "improvement"
    ],
    "wof:name":"Fulford Home Remodeling",
    "wof:placetype":"venue"
},
  "geometry": {"coordinates":[-89.984397,38.553409],"type":"Point"}
}