{
  "type": "Feature",
  "properties": {
    "iso:country":"US",
    "sg:address":"4878 N Ashland Ave Ste 3E",
    "sg:city":"Chicago",
    "sg:classifiers":[
        {
            "category":"Building & Trades",
            "subcategory":"Cleaning & Sanitation",
            "type":"Services"
        }
    ],
    "sg:phone":"+1 215 704 7796",
    "sg:postcode":"60640",
    "sg:province":"IL",
    "sg:tags":[
        "home"
    ],
    "sg:website":"www.ocdcleaninginc.com",
    "wof:name":"OCD Cleaning Inc",
    "wof:placetype":"venue"
},
  "geometry": {"coordinates":[-87.669602,41.971225],"type":"Point"}
}