{
  "type": "Feature",
  "properties": {
    "iso:country":"US",
    "sg:address":"4170E N Harlem Ave",
    "sg:city":"Norridge",
    "sg:classifiers":[
        {
            "category":"Utilities",
            "subcategory":"Mobile Phone",
            "type":"Services"
        },
        {
            "category":"Shopping",
            "subcategory":"Mobile Phones",
            "type":"Retail Goods"
        }
    ],
    "sg:phone":"+1 708 453 1538",
    "sg:postcode":"60706",
    "sg:province":"IL",
    "sg:tags":[
        "supply",
        "communication",
        "telephone",
        "wireless",
        "equipment",
        "cellular"
    ],
    "sg:website":"http://www.sprint.com",
    "wof:name":"Sprint Store",
    "wof:placetype":"venue"
},
  "geometry": {"coordinates":[-87.80728999999999,41.95595],"type":"Point"}
}