{
  "type": "Feature",
  "properties": {
    "iso:country":"US",
    "sg:address":"4300 Oak Park Ave",
    "sg:city":"Berwyn",
    "sg:classifiers":[
        {
            "category":"Education",
            "subcategory":"School",
            "type":"Public Place"
        },
        {
            "category":"Organizations",
            "subcategory":"Community Association",
            "type":"Services"
        },
        {
            "category":"Organizations",
            "subcategory":"Religious Organization",
            "type":"Services"
        }
    ],
    "sg:phone":"+1 708 788 6090",
    "sg:postcode":"60402",
    "sg:province":"IL",
    "sg:tags":[
        "consultant",
        "spiritual",
        "interest"
    ],
    "wof:name":"Saint Plus X Church Religious Education & Youth Ministry",
    "wof:placetype":"venue"
},
  "geometry": {"coordinates":[-87.792367,41.814204],"type":"Point"}
}