{
  "type": "Feature",
  "properties": {
    "iso:country":"US",
    "sg:address":"77 W Wacker Drive Lbby",
    "sg:city":"Chicago",
    "sg:classifiers":[
        {
            "category":"Personal",
            "type":"Services"
        },
        {
            "category":"Sports & Exercise",
            "subcategory":"Gym",
            "type":"Entertainment"
        },
        {
            "category":"Arena",
            "subcategory":"Sports Club",
            "type":"Entertainment"
        }
    ],
    "sg:phone":"+1 312 849 2322",
    "sg:postcode":"60601",
    "sg:province":"IL",
    "sg:tags":[
        "trainer",
        "consultant",
        "physical",
        "health",
        "fitness"
    ],
    "wof:name":"Executive Sports & Fitness Center",
    "wof:placetype":"venue"
},
  "geometry": {"coordinates":[-87.62998,41.886755],"type":"Point"}
}