{
  "type": "Feature",
  "properties": {
    "iso:country":"US",
    "sg:address":"812 W Van Buren St Apt 3B",
    "sg:city":"Chicago",
    "sg:classifiers":[
        {
            "category":"Professional",
            "subcategory":"Employment Agencies",
            "type":"Services"
        }
    ],
    "sg:phone":"+1 312 573 4829",
    "sg:postcode":"60607",
    "sg:province":"IL",
    "sg:tags":[
        "employer"
    ],
    "wof:name":"Chicago Women In Architecture",
    "wof:placetype":"venue"
},
  "geometry": {"coordinates":[-87.647668,41.876656],"type":"Point"}
}