{
  "type": "Feature",
  "properties": {
    "addr:full":"1458 W Birchwood St Morton IL 61550",
    "addr:housenumber":"1458",
    "addr:postcode":"61550",
    "addr:street":"W Birchwood St",
    "iso:country":"US",
    "sg:address":"1458 W Birchwood St",
    "sg:city":"Morton",
    "sg:classifiers":[
        {
            "category":"Wholesale",
            "subcategory":"Farm Supplies",
            "type":"Manufacturing & Wholesale Goods"
        },
        {
            "category":"Autos & Motor Vehicles",
            "subcategory":"Automobile Sales",
            "type":"Retail Goods"
        },
        {
            "category":"Retail",
            "subcategory":"Auto Repair",
            "type":"Services"
        }
    ],
    "sg:phone":"+1 309 263 1303",
    "sg:postcode":"61550",
    "sg:province":"IL",
    "sg:tags":[
        "trailer",
        "truck",
        "trailers-repair",
        "tractor",
        "transport"
    ],
    "wof:name":"Morton Truck & Trailer",
    "wof:placetype":"venue"
},
  "geometry": {"coordinates":[-89.508419,40.603949],"type":"Point"}
}