{
  "type": "Feature",
  "properties": {
    "addr:full":"2295 Valley Creek Dr Elgin IL 60123",
    "addr:housenumber":"2295",
    "addr:postcode":"60123",
    "addr:street":"Valley Creek Dr",
    "iso:country":"US",
    "sg:address":"2295 Valley Creek Dr",
    "sg:city":"Elgin",
    "sg:classifiers":[
        {
            "category":"Professional",
            "subcategory":"Employment Agencies",
            "type":"Services"
        }
    ],
    "sg:phone":"+1 847 289 1270",
    "sg:postcode":"60123",
    "sg:province":"IL",
    "wof:name":"G-Tech Professional Staffing",
    "wof:placetype":"venue"
},
  "geometry": {"coordinates":[-88.335897,42.051245],"type":"Point"}
}