{
  "type": "Feature",
  "properties": {
    "iso:country":"US",
    "sg:address":"30 E Main St",
    "sg:city":"Round Lake Park",
    "sg:classifiers":[
        {
            "category":"Bars & Pubs",
            "type":"Food & Drink"
        }
    ],
    "sg:phone":"+1 847 546 2520",
    "sg:postcode":"60073",
    "sg:province":"IL",
    "sg:tags":[
        "drinking"
    ],
    "wof:name":"P J s Park Inn",
    "wof:placetype":"venue"
},
  "geometry": {"coordinates":[-88.082691,42.349733],"type":"Point"}
}