{
  "type": "Feature",
  "properties": {
    "addr:full":"18631 Willow Ave Country Club Hills IL 60478",
    "addr:housenumber":"18631",
    "addr:postcode":"60478",
    "addr:street":"Willow Ave",
    "iso:country":"US",
    "sg:address":"18631 Willow Ave",
    "sg:city":"Country Club Hills",
    "sg:classifiers":[
        {
            "category":"Professional",
            "subcategory":"Management & Consulting",
            "type":"Services"
        }
    ],
    "sg:phone":"+1 708 957 0952",
    "sg:postcode":"60478",
    "sg:province":"IL",
    "sg:tags":[
        "marketing"
    ],
    "wof:name":"Heuristics Marketing",
    "wof:placetype":"venue"
},
  "geometry": {"coordinates":[-87.71871899999999,41.550734],"type":"Point"}
}