{
  "type": "Feature",
  "properties": {
    "addr:full":"450 S East St Jacksonville IL 62650",
    "addr:housenumber":"450",
    "addr:postcode":"62650",
    "addr:street":"S East St",
    "iso:country":"US",
    "sg:address":"450 S East St",
    "sg:city":"Jacksonville",
    "sg:classifiers":[
        {
            "category":"Organizations",
            "subcategory":"Religious Organization",
            "type":"Services"
        }
    ],
    "sg:phone":"+1 217 243 3986",
    "sg:postcode":"62650",
    "sg:province":"IL",
    "sg:tags":[
        "church"
    ],
    "wof:name":"Mt Moriah Chr Of God In Christ",
    "wof:placetype":"venue"
},
  "geometry": {"coordinates":[-90.226736,39.729379],"type":"Point"}
}