{
  "type": "Feature",
  "properties": {
    "iso:country":"US",
    "sg:address":"2950 N Main St",
    "sg:city":"Decatur",
    "sg:classifiers":[
        {
            "category":"Insurance",
            "subcategory":"Hazard Insurance",
            "type":"Services"
        }
    ],
    "sg:phone":"+1 217 877 2834",
    "sg:postcode":"62526",
    "sg:province":"IL",
    "sg:tags":[
        "commercial",
        "business"
    ],
    "sg:website":"http://www.countryfinancial.com/",
    "wof:name":"Country Companies Insurance",
    "wof:placetype":"venue"
},
  "geometry": {"coordinates":[-88.956553,39.874171],"type":"Point"}
}