{
  "type": "Feature",
  "properties": {
    "iso:country":"US",
    "sg:address":"996 State Rte 94",
    "sg:city":"Carthage",
    "sg:phone":"+1 217 743 5350",
    "sg:postcode":"62321",
    "sg:province":"IL",
    "sg:tags":[
        "farm",
        "corn",
        "soybean"
    ],
    "wof:name":"Fred Klover",
    "wof:placetype":"venue"
},
  "geometry": {"coordinates":[-91.13692,40.42414],"type":"Point"}
}