{
  "type": "Feature",
  "properties": {
    "iso:country":"US",
    "sg:address":"525 E 162nd St",
    "sg:city":"South Holland",
    "sg:classifiers":[
        {
            "category":"Education",
            "subcategory":"School",
            "type":"Public Place"
        }
    ],
    "sg:phone":"+1 708 331 7600",
    "sg:postcode":"60473",
    "sg:province":"IL",
    "wof:name":"Schools Public",
    "wof:placetype":"venue"
},
  "geometry": {"coordinates":[-87.603308,41.600678],"type":"Point"}
}