{
  "type": "Feature",
  "properties": {
    "addr:full":"1689 Elk Blvd Des Plaines IL 60016",
    "addr:housenumber":"1689",
    "addr:postcode":"60016",
    "addr:street":"Elk Blvd",
    "iso:country":"US",
    "sg:address":"1689 Elk Blvd",
    "sg:city":"Des Plaines",
    "sg:classifiers":[
        {
            "category":"Professional",
            "subcategory":"Computer Services",
            "type":"Services"
        }
    ],
    "sg:phone":"+1 847 803 0044",
    "sg:postcode":"60016",
    "sg:province":"IL",
    "wof:name":"Jensen It Inc",
    "wof:placetype":"venue"
},
  "geometry": {"coordinates":[-87.88445400000001,42.045059],"type":"Point"}
}