{
  "type": "Feature",
  "properties": {
    "addr:full":"950 Milwaukee Ave Glenview IL 60025",
    "addr:housenumber":"950",
    "addr:postcode":"60025",
    "addr:street":"Milwaukee Ave",
    "iso:country":"US",
    "sg:address":"950 Milwaukee Ave",
    "sg:city":"Glenview",
    "sg:classifiers":[
        {
            "category":"Real Estate",
            "subcategory":"Real Estate Agent",
            "type":"Services"
        }
    ],
    "sg:phone":"+1 847 699 1500",
    "sg:postcode":"60025",
    "sg:province":"IL",
    "wof:name":"Portland Reality",
    "wof:placetype":"venue"
},
  "geometry": {"coordinates":[-87.85481299999999,42.071812],"type":"Point"}
}