{
  "type": "Feature",
  "properties": {
    "iso:country":"US",
    "sg:address":"13515 78th Ave W",
    "sg:city":"Taylor Ridge",
    "sg:classifiers":[
        {
            "category":"Restaurant",
            "type":"Food & Drink"
        }
    ],
    "sg:phone":"+1 309 798 2423",
    "sg:postcode":"61284",
    "sg:province":"IL",
    "wof:name":"Ducky's Lagoon",
    "wof:placetype":"venue"
},
  "geometry": {"coordinates":[-90.756082,41.437663],"type":"Point"}
}