{
  "type": "Feature",
  "properties": {
    "iso:country":"US",
    "sg:address":"45 N Wells St",
    "sg:city":"Chicago",
    "sg:classifiers":[
        {
            "category":"Restaurant",
            "type":"Food & Drink"
        }
    ],
    "sg:phone":"+1 312 346 1638",
    "sg:postcode":"60606",
    "sg:province":"IL",
    "sg:tags":[
        "mexican"
    ],
    "wof:name":"La Cocina",
    "wof:placetype":"venue"
},
  "geometry": {"coordinates":[-87.63400300000001,41.8825],"type":"Point"}
}