{
  "type": "Feature",
  "properties": {
    "addr:full":"1245 Larkin Ave Elgin IL 60123",
    "addr:housenumber":"1245",
    "addr:postcode":"60123",
    "addr:street":"Larkin Ave",
    "iso:country":"US",
    "sg:address":"1245 Larkin Ave",
    "sg:city":"Elgin",
    "sg:classifiers":[
        {
            "category":"Real Estate",
            "subcategory":"Real Estate Agent",
            "type":"Services"
        }
    ],
    "sg:phone":"+1 847 931 7447",
    "sg:postcode":"60123",
    "sg:province":"IL",
    "sg:tags":[
        "appraiser"
    ],
    "wof:name":"Steffens & Assoc LTD",
    "wof:placetype":"venue"
},
  "geometry": {"coordinates":[-88.310374,42.035359],"type":"Point"}
}