{
  "type": "Feature",
  "properties": {
    "iso:country":"US",
    "sg:address":"6143 W Touhy Ave",
    "sg:city":"Chicago",
    "sg:classifiers":[
        {
            "category":"Real Estate",
            "subcategory":"Real Estate Agent",
            "type":"Services"
        }
    ],
    "sg:phone":"+1 773 467 4444",
    "sg:postcode":"60646",
    "sg:province":"IL",
    "wof:name":"Metron Group",
    "wof:placetype":"venue"
},
  "geometry": {"coordinates":[-87.781698,42.011929],"type":"Point"}
}