{
  "type": "Feature",
  "properties": {
    "iso:country":"US",
    "sg:address":"524 N Miller Rd",
    "sg:city":"Lake Villa",
    "sg:classifiers":[
        {
            "category":"Professional",
            "subcategory":"Computer Services",
            "type":"Services"
        }
    ],
    "sg:phone":"+1 847 356 1460",
    "sg:postcode":"60046",
    "sg:province":"IL",
    "sg:tags":[
        "processing",
        "datum"
    ],
    "wof:name":"Larson's Keypunch Svc",
    "wof:placetype":"venue"
},
  "geometry": {"coordinates":[-88.046955,42.422689],"type":"Point"}
}