{
  "type": "Feature",
  "properties": {
    "addr:full":"215 W Grand Ave Bensenville IL 60106",
    "addr:housenumber":"215",
    "addr:postcode":"60106",
    "addr:street":"W Grand Ave",
    "iso:country":"US",
    "sg:address":"215 W Grand Ave",
    "sg:city":"Bensenville",
    "sg:classifiers":[
        {
            "category":"Insurance",
            "subcategory":"Hazard Insurance",
            "type":"Services"
        }
    ],
    "sg:phone":"+1 630 694 1185",
    "sg:postcode":"60106",
    "sg:province":"IL",
    "sg:tags":[
        "commercial",
        "business"
    ],
    "wof:name":"Magnum Insurance",
    "wof:placetype":"venue"
},
  "geometry": {"coordinates":[-87.94687500000001,41.931066],"type":"Point"}
}