{
  "type": "Feature",
  "properties": {
    "iso:country":"US",
    "sg:address":"320 S Green Bay Rd",
    "sg:city":"Waukegan",
    "sg:classifiers":[
        {
            "category":"Real Estate",
            "subcategory":"Real Estate Agent",
            "type":"Services"
        }
    ],
    "sg:phone":"+1 847 249 1880",
    "sg:postcode":"60085",
    "sg:province":"IL",
    "sg:tags":[
        "residential",
        "broker"
    ],
    "wof:name":"Century 21",
    "wof:placetype":"venue"
},
  "geometry": {"coordinates":[-87.87386600000001,42.353974],"type":"Point"}
}