{
  "type": "Feature",
  "properties": {
    "iso:country":"US",
    "sg:address":"201 N Kankakee St",
    "sg:city":"Wilmington",
    "sg:classifiers":[
        {
            "category":"Education",
            "subcategory":"School",
            "type":"Public Place"
        }
    ],
    "sg:phone":"+1 815 476 7424",
    "sg:postcode":"60481",
    "sg:province":"IL",
    "wof:name":"Booth Central Elementary Schl",
    "wof:placetype":"venue"
},
  "geometry": {"coordinates":[-88.145547,41.310166],"type":"Point"}
}