{
  "type": "Feature",
  "properties": {
    "iso:country":"US",
    "sg:address":"775 N Green Mount Rd",
    "sg:city":"Belleville",
    "sg:classifiers":[
        {
            "category":"Organizations",
            "subcategory":"Religious Organization",
            "type":"Services"
        }
    ],
    "sg:phone":"+1 618 239 9710",
    "sg:postcode":"62221",
    "sg:province":"IL",
    "sg:website":"www.cornerstone-ch.org",
    "wof:name":"Cornerstone Christian Church",
    "wof:placetype":"venue"
},
  "geometry": {"coordinates":[-89.92926900000001,38.560504],"type":"Point"}
}