{
  "type": "Feature",
  "properties": {
    "iso:country":"US",
    "sg:address":"104 E Locust St",
    "sg:city":"Geneseo",
    "sg:classifiers":[
        {
            "category":"Communications",
            "type":"Services"
        }
    ],
    "sg:phone":"+1 309 944 6883",
    "sg:postcode":"61254",
    "sg:province":"IL",
    "wof:name":"Riney Marketing Communications",
    "wof:placetype":"venue"
},
  "geometry": {"coordinates":[-90.155458,41.445438],"type":"Point"}
}