{
  "type": "Feature",
  "properties": {
    "iso:country":"US",
    "sg:address":"61 Newcastle Ct",
    "sg:city":"Crystal Lake",
    "sg:classifiers":[
        {
            "category":"Food & Beverages",
            "subcategory":"Groceries & Convenience Stores",
            "type":"Retail Goods"
        }
    ],
    "sg:phone":"+1   ",
    "sg:postcode":"60014",
    "sg:province":"IL",
    "wof:name":"Jose L Reyes",
    "wof:placetype":"venue"
},
  "geometry": {"coordinates":[-88.322282,42.212047],"type":"Point"}
}