{
  "type": "Feature",
  "properties": {
    "iso:country":"US",
    "sg:address":"325 W Main St",
    "sg:city":"Belleville",
    "sg:classifiers":[
        {
            "category":"Professional",
            "subcategory":"Accounting & Tax Preparation",
            "type":"Services"
        }
    ],
    "sg:phone":"+1 618 234 4530",
    "sg:postcode":"62220",
    "sg:province":"IL",
    "sg:tags":[
        "accountant",
        "return",
        "public",
        "certified",
        "filing"
    ],
    "wof:name":"R C Fietsam and Co",
    "wof:placetype":"venue"
},
  "geometry": {"coordinates":[-89.989604,38.513699],"type":"Point"}
}