{
  "type": "Feature",
  "properties": {
    "addr:full":"920 Brown Section Rd Cobden IL 62920",
    "addr:housenumber":"920",
    "addr:postcode":"62920",
    "addr:street":"Brown Section Rd",
    "iso:country":"US",
    "sg:address":"920 Brown Section Rd",
    "sg:city":"Cobden",
    "sg:classifiers":[
        {
            "category":"Professional",
            "subcategory":"Management & Consulting",
            "type":"Services"
        },
        {
            "category":"Farming",
            "subcategory":"Farm",
            "type":"Manufacturing & Wholesale Goods"
        }
    ],
    "sg:phone":"+1 618 893 2911",
    "sg:postcode":"62920",
    "sg:province":"IL",
    "wof:name":"Roma Kay Ranch",
    "wof:placetype":"venue"
},
  "geometry": {"coordinates":[-89.310585,37.525751],"type":"Point"}
}