{
  "type": "Feature",
  "properties": {
    "addr:full":"914 Timberline Ct East Dubuque IL 61025",
    "addr:housenumber":"914",
    "addr:postcode":"61025",
    "addr:street":"Timberline Ct",
    "iso:country":"US",
    "sg:address":"914 Timberline Ct",
    "sg:city":"East Dubuque",
    "sg:classifiers":[
        {
            "category":"Professional",
            "type":"Services"
        }
    ],
    "sg:phone":"+1 815 747 6960",
    "sg:postcode":"61025",
    "sg:province":"IL",
    "wof:name":"Mad Hatters Inc",
    "wof:placetype":"venue"
},
  "geometry": {"coordinates":[-90.631103,42.498207],"type":"Point"}
}