{
  "type": "Feature",
  "properties": {
    "addr:full":"25135 Crabtree Ln Ingleside IL 60041",
    "addr:housenumber":"25135",
    "addr:postcode":"60041",
    "addr:street":"Crabtree Ln",
    "iso:country":"US",
    "sg:address":"25135 Crabtree Ln",
    "sg:city":"Ingleside",
    "sg:classifiers":[
        {
            "category":"Banks & Credit Unions",
            "subcategory":"Investment Brokerage",
            "type":"Services"
        }
    ],
    "sg:phone":"+1 847 546 1031",
    "sg:postcode":"60041",
    "sg:province":"IL",
    "sg:tags":[
        "advisory"
    ],
    "wof:name":"Schuttlefield Financial Servic",
    "wof:placetype":"venue"
},
  "geometry": {"coordinates":[-88.122862,42.390199],"type":"Point"}
}