{
  "type": "Feature",
  "properties": {
    "iso:country":"US",
    "sg:address":"2708 N Illinois St",
    "sg:city":"Belleville",
    "sg:classifiers":[
        {
            "category":"Banks & Credit Unions",
            "subcategory":"Bank",
            "type":"Services"
        }
    ],
    "sg:phone":"+1 618 235 3636",
    "sg:postcode":"62226",
    "sg:province":"IL",
    "sg:tags":[
        "cashing",
        "loan",
        "agency",
        "check"
    ],
    "wof:name":"Swansea Quick Cash Inc",
    "wof:placetype":"venue"
},
  "geometry": {"coordinates":[-89.983773,38.542156],"type":"Point"}
}