{
  "type": "Feature",
  "properties": {
    "addr:full":"2740 Springdale Dr Rockford IL 61114",
    "addr:housenumber":"2740",
    "addr:postcode":"61114",
    "addr:street":"Springdale Dr",
    "iso:country":"US",
    "sg:address":"2740 Springdale Dr",
    "sg:city":"Rockford",
    "sg:classifiers":[
        {
            "category":"Building & Trades",
            "subcategory":"Electrical",
            "type":"Services"
        }
    ],
    "sg:phone":"+1 815 316 9398",
    "sg:postcode":"61114",
    "sg:province":"IL",
    "sg:tags":[
        "electrical",
        "contractor"
    ],
    "wof:name":"Precision Electric Co",
    "wof:placetype":"venue"
},
  "geometry": {"coordinates":[-89.013786,42.300243],"type":"Point"}
}