{
  "type": "Feature",
  "properties": {
    "iso:country":"US",
    "sg:address":"555 E Townline Rd",
    "sg:city":"Vernon Hills",
    "sg:classifiers":[
        {
            "category":"Personal",
            "subcategory":"Beauty Salon",
            "type":"Services"
        }
    ],
    "sg:phone":"+1 847 367 7135",
    "sg:postcode":"60061",
    "sg:province":"IL",
    "wof:name":"Supercuts",
    "wof:placetype":"venue"
},
  "geometry": {"coordinates":[-87.94830399999999,42.240381],"type":"Point"}
}