{
  "type": "Feature",
  "properties": {
    "iso:country":"US",
    "sg:address":"547 W Jackson Blvd",
    "sg:city":"Chicago",
    "sg:classifiers":[
        {
            "category":"Real Estate",
            "subcategory":"Real Estate Agent",
            "type":"Services"
        }
    ],
    "sg:phone":"+1 312 360 0800",
    "sg:postcode":"60661",
    "sg:province":"IL",
    "sg:tags":[
        "authorities",
        "housing"
    ],
    "wof:name":"Corp For Spprtve Hsng",
    "wof:placetype":"venue"
},
  "geometry": {"coordinates":[-87.641661,41.877947],"type":"Point"}
}