{
  "type": "Feature",
  "properties": {
    "addr:full":"47 E Chicago Ave Naperville IL 60540",
    "addr:housenumber":"47",
    "addr:postcode":"60540",
    "addr:street":"E Chicago Ave",
    "iso:country":"US",
    "sg:address":"47 E Chicago Ave",
    "sg:city":"Naperville",
    "sg:classifiers":[
        {
            "category":"Home & Garden",
            "subcategory":"Furniture",
            "type":"Retail Goods"
        }
    ],
    "sg:phone":"+1 630 579 6579",
    "sg:postcode":"60540",
    "sg:province":"IL",
    "sg:tags":[
        "store"
    ],
    "wof:name":"Restoration Hardware",
    "wof:placetype":"venue"
},
  "geometry": {"coordinates":[-88.14703799999999,41.771565],"type":"Point"}
}