{
  "type": "Feature",
  "properties": {
    "addr:full":"1855 W 47th Street Chicago IL 60609",
    "addr:housenumber":"1855",
    "addr:postcode":"60609",
    "addr:street":"W 47Th Street",
    "iso:country":"US",
    "sg:address":"1855 W 47th Street",
    "sg:city":"Chicago",
    "sg:classifiers":[
        {
            "category":"Restaurant",
            "type":"Food & Drink"
        }
    ],
    "sg:phone":"+1 773 927 0945",
    "sg:postcode":"60609",
    "sg:province":"IL",
    "sg:tags":[
        "mexican"
    ],
    "wof:name":"Mexico Express",
    "wof:placetype":"venue"
},
  "geometry": {"coordinates":[-87.671948,41.808269],"type":"Point"}
}