{
  "type": "Feature",
  "properties": {
    "iso:country":"US",
    "sg:address":"8602 US Hwy 50",
    "sg:city":"Lebanon",
    "sg:classifiers":[
        {
            "category":"Building & Trades",
            "subcategory":"Construction",
            "type":"Services"
        }
    ],
    "sg:phone":"+1 618 632 2386",
    "sg:postcode":"62254",
    "sg:province":"IL",
    "sg:tags":[
        "designer",
        "dealer",
        "pool",
        "swimming"
    ],
    "wof:name":"Wilson Siding Pools & Spas Inc",
    "wof:placetype":"venue"
},
  "geometry": {"coordinates":[-89.86626,38.586319],"type":"Point"}
}