{
  "type": "Feature",
  "properties": {
    "addr:full":"8458 S Green St Chicago IL 60620",
    "addr:housenumber":"8458",
    "addr:postcode":"60620",
    "addr:street":"S Green St",
    "iso:country":"US",
    "sg:address":"8458 S Green St",
    "sg:city":"Chicago",
    "sg:classifiers":[
        {
            "category":"Food & Beverages",
            "subcategory":"Bakery",
            "type":"Retail Goods"
        }
    ],
    "sg:phone":"+1 773 483 8690",
    "sg:postcode":"60620",
    "sg:province":"IL",
    "sg:tags":[
        "sandwich"
    ],
    "sg:website":"www.cornercafe.vpweb.com",
    "wof:name":"Corner Cafe",
    "wof:placetype":"venue"
},
  "geometry": {"coordinates":[-87.645293,41.739807],"type":"Point"}
}