{
  "type": "Feature",
  "properties": {
    "addr:full":"2417 Ridge Ave East Saint Louis IL 62205",
    "addr:housenumber":"2417",
    "addr:postcode":"62205",
    "addr:street":"Ridge Ave East",
    "iso:country":"US",
    "sg:address":"2417 Ridge Ave",
    "sg:city":"East Saint Louis",
    "sg:classifiers":[
        {
            "category":"Organizations",
            "subcategory":"Religious Organization",
            "type":"Services"
        }
    ],
    "sg:phone":"+1 618 875 1447",
    "sg:postcode":"62205",
    "sg:province":"IL",
    "sg:tags":[
        "monastery",
        "convent"
    ],
    "wof:name":"Cordi Marian Sisters",
    "wof:placetype":"venue"
},
  "geometry": {"coordinates":[-90.13009599999999,38.61326],"type":"Point"}
}