{
  "type": "Feature",
  "properties": {
    "iso:country":"US",
    "sg:address":"406 W Sigwalt St",
    "sg:city":"Arlington Heights",
    "sg:classifiers":[
        {
            "category":"Banks & Credit Unions",
            "subcategory":"Financial Services",
            "type":"Services"
        }
    ],
    "sg:phone":"+1 847 253 7224",
    "sg:postcode":"60005",
    "sg:province":"IL",
    "sg:tags":[
        "investor"
    ],
    "wof:name":"Msl Investors",
    "wof:placetype":"venue"
},
  "geometry": {"coordinates":[-87.988976,42.081131],"type":"Point"}
}