{
  "type": "Feature",
  "properties": {
    "addr:full":"9502 Trigger Rd Edwards IL 61528",
    "addr:housenumber":"9502",
    "addr:postcode":"61528",
    "addr:street":"Trigger Rd",
    "iso:country":"US",
    "sg:address":"9502 Trigger Rd",
    "sg:city":"Edwards",
    "sg:classifiers":[
        {
            "category":"Freight",
            "type":"Transportation"
        }
    ],
    "sg:phone":"+1 309 243 7655",
    "sg:postcode":"61528",
    "sg:province":"IL",
    "sg:tags":[
        "operator",
        "local",
        "storage",
        "trucking"
    ],
    "wof:name":"Jeff Donahoo Trucking",
    "wof:placetype":"venue"
},
  "geometry": {"coordinates":[-89.688615,40.803191],"type":"Point"}
}