{
  "type": "Feature",
  "properties": {
    "iso:country":"US",
    "sg:address":"3451 W 51st St",
    "sg:city":"Chicago",
    "sg:classifiers":[
        {
            "category":"Retail",
            "subcategory":"Auto Repair",
            "type":"Services"
        }
    ],
    "sg:phone":"+1 773 434 9062",
    "sg:postcode":"60632",
    "sg:province":"IL",
    "sg:tags":[
        "body",
        "shop"
    ],
    "wof:name":"The Custom Paint Parlor",
    "wof:placetype":"venue"
},
  "geometry": {"coordinates":[-87.710701,41.800499],"type":"Point"}
}