{
  "type": "Feature",
  "properties": {
    "iso:country":"US",
    "sg:address":"2575 W Algonquin Rd Ste D",
    "sg:city":"Algonquin",
    "sg:classifiers":[
        {
            "category":"Health Services",
            "subcategory":"Doctor",
            "type":"Services"
        },
        {
            "category":"Health Services",
            "subcategory":"Clinic",
            "type":"Services"
        },
        {
            "category":"Personal",
            "subcategory":"Day Spa",
            "type":"Services"
        }
    ],
    "sg:phone":"+1 847 458 1001",
    "sg:postcode":"60102",
    "sg:province":"IL",
    "sg:tags":[
        "medical"
    ],
    "sg:website":"www.aleyramedispa.com",
    "wof:name":"Aleyra Medispa",
    "wof:placetype":"venue"
},
  "geometry": {"coordinates":[-88.339777,42.17549],"type":"Point"}
}