{
  "type": "Feature",
  "properties": {
    "iso:country":"US",
    "sg:address":"2429 Burr Oak Ave",
    "sg:city":"Blue Island",
    "sg:classifiers":[
        {
            "category":"Retail",
            "subcategory":"Funeral Services",
            "type":"Services"
        }
    ],
    "sg:phone":"+1 708 388 1636",
    "sg:postcode":"60406",
    "sg:province":"IL",
    "sg:tags":[
        "cemetery"
    ],
    "wof:name":"Hickey Memorial Chapel",
    "wof:placetype":"venue"
},
  "geometry": {"coordinates":[-87.681297,41.662601],"type":"Point"}
}