{
  "type": "Feature",
  "properties": {
    "addr:full":"524 Center Rd Frankfort IL 60423",
    "addr:housenumber":"524",
    "addr:postcode":"60423",
    "addr:street":"Center Rd",
    "iso:country":"US",
    "sg:address":"524 Center Rd",
    "sg:city":"Frankfort",
    "sg:classifiers":[
        {
            "category":"Manufacturing",
            "subcategory":"Retail Goods",
            "type":"Manufacturing & Wholesale Goods"
        },
        {
            "category":"Manufacturing",
            "subcategory":"Printing",
            "type":"Manufacturing & Wholesale Goods"
        }
    ],
    "sg:phone":"+1 815 469 2314",
    "sg:postcode":"60423",
    "sg:province":"IL",
    "sg:tags":[
        "product",
        "typesetting",
        "commercial",
        "mfg"
    ],
    "sg:website":"www.matchbooks.com",
    "wof:name":"Atlantis Match Company",
    "wof:placetype":"venue"
},
  "geometry": {"coordinates":[-87.84845799999999,41.490495],"type":"Point"}
}