{
  "type": "Feature",
  "properties": {
    "addr:full":"496 W Boughton Rd Bolingbrook IL 60440",
    "addr:housenumber":"496",
    "addr:postcode":"60440",
    "addr:street":"W Boughton Rd",
    "iso:country":"US",
    "sg:address":"496 W Boughton Rd",
    "sg:city":"Bolingbrook",
    "sg:classifiers":[
        {
            "category":"Professional",
            "subcategory":"Accounting & Tax Preparation",
            "type":"Services"
        }
    ],
    "sg:phone":"+1 630 759 5070",
    "sg:postcode":"60440",
    "sg:province":"IL",
    "sg:tags":[
        "accountant"
    ],
    "wof:name":"Eberhart Accounting Svcs PC",
    "wof:placetype":"venue"
},
  "geometry": {"coordinates":[-88.08766900000001,41.707639],"type":"Point"}
}