{
  "type": "Feature",
  "properties": {
    "addr:full":"560 Darlington Ln Crystal Lake IL 60014",
    "addr:housenumber":"560",
    "addr:postcode":"60014",
    "addr:street":"Darlington Ln",
    "iso:country":"US",
    "sg:address":"560 Darlington Ln",
    "sg:city":"Crystal Lake",
    "sg:classifiers":[
        {
            "category":"Real Estate",
            "subcategory":"Real Estate Operator",
            "type":"Services"
        }
    ],
    "sg:phone":"+1 815 455 0540",
    "sg:postcode":"60014",
    "sg:province":"IL",
    "sg:tags":[
        "apartment",
        "complex",
        "apt"
    ],
    "wof:name":"Darlington Court Apartments",
    "wof:placetype":"venue"
},
  "geometry": {"coordinates":[-88.325722,42.223635],"type":"Point"}
}