{
  "type": "Feature",
  "properties": {
    "iso:country":"US",
    "sg:address":"656 N Broadway",
    "sg:city":"Aurora",
    "sg:classifiers":[
        {
            "category":"Retail",
            "subcategory":"Auto Repair",
            "type":"Services"
        }
    ],
    "sg:phone":"+1 630 801 4801",
    "sg:postcode":"60505",
    "sg:province":"IL",
    "sg:tags":[
        "body",
        "automobile",
        "painting"
    ],
    "wof:name":"Broadway Collision Ctr",
    "wof:placetype":"venue"
},
  "geometry": {"coordinates":[-88.306322,41.77055],"type":"Point"}
}