{
  "type": "Feature",
  "properties": {
    "iso:country":"US",
    "sg:address":"1902 Gladstone Dr",
    "sg:city":"Wheaton",
    "sg:classifiers":[
        {
            "category":"Social Services",
            "subcategory":"Child Care",
            "type":"Services"
        }
    ],
    "sg:phone":"+1 630 682 4219",
    "sg:postcode":"60187",
    "sg:province":"IL",
    "sg:tags":[
        "day"
    ],
    "wof:name":"Carolyn Rebman",
    "wof:placetype":"venue"
},
  "geometry": {"coordinates":[-88.115582,41.83345],"type":"Point"}
}