{
  "type": "Feature",
  "properties": {
    "iso:country":"US",
    "sg:address":"1425 N Cole Ct",
    "sg:city":"Peoria",
    "sg:classifiers":[
        {
            "category":"Farming",
            "subcategory":"Nursery",
            "type":"Manufacturing & Wholesale Goods"
        }
    ],
    "sg:phone":"+1 309 682 6716",
    "sg:postcode":"61606",
    "sg:province":"IL",
    "sg:tags":[
        "tree",
        "grower",
        "nursery-wholesale",
        "nurseries-plants"
    ],
    "wof:name":"Salnee",
    "wof:placetype":"venue"
},
  "geometry": {"coordinates":[-89.61264,40.705023],"type":"Point"}
}