{
  "type": "Feature",
  "properties": {
    "iso:country":"US",
    "sg:address":"921 Front St",
    "sg:city":"Mc Henry",
    "sg:classifiers":[
        {
            "category":"Retail",
            "subcategory":"Auto Repair",
            "type":"Services"
        }
    ],
    "sg:phone":"+1 815 385 0020",
    "sg:postcode":"60050",
    "sg:province":"IL",
    "sg:tags":[
        "glass",
        "replacement"
    ],
    "wof:name":"Cardinal Glass Company",
    "wof:placetype":"venue"
},
  "geometry": {"coordinates":[-88.274265,42.342336],"type":"Point"}
}