{
  "type": "Feature",
  "properties": {
    "iso:country":"US",
    "sg:address":"345 W Woodland Rdg",
    "sg:city":"Valmeyer",
    "sg:classifiers":[
        {
            "category":"Building & Trades",
            "subcategory":"Cleaning & Sanitation",
            "type":"Services"
        }
    ],
    "sg:phone":"+1 800 222 6815",
    "sg:postcode":"62295",
    "sg:province":"IL",
    "sg:tags":[
        "house"
    ],
    "wof:name":"Rapid Restoration- Emergency Sewage Damage Clean-up, Water Damage Restoration",
    "wof:placetype":"venue"
},
  "geometry": {"coordinates":[-90.28663299999999,38.313646],"type":"Point"}
}