{
  "type": "Feature",
  "properties": {
    "iso:country":"US",
    "sg:address":"2917 N Vermilion St",
    "sg:city":"Danville",
    "sg:classifiers":[
        {
            "category":"Autos & Motor Vehicles",
            "subcategory":"Automobile Sales",
            "type":"Retail Goods"
        }
    ],
    "sg:phone":"+1 217 431 2069",
    "sg:postcode":"61832",
    "sg:province":"IL",
    "sg:tags":[
        "car",
        "dealer"
    ],
    "wof:name":"American Chevrolet Cadillac",
    "wof:placetype":"venue"
},
  "geometry": {"coordinates":[-87.630587,40.16947],"type":"Point"}
}