{
  "type": "Feature",
  "properties": {
    "iso:country":"US",
    "sg:address":"1316 W Eddy St",
    "sg:city":"Chicago",
    "sg:classifiers":[
        {
            "category":"Shopping",
            "subcategory":"Computers & Home Electronics",
            "type":"Retail Goods"
        }
    ],
    "sg:phone":"+1 312 735 5890",
    "sg:postcode":"60657",
    "sg:province":"IL",
    "sg:tags":[
        "publishing"
    ],
    "wof:name":"Asparagus Design",
    "wof:placetype":"venue"
},
  "geometry": {"coordinates":[-87.663077,41.946235],"type":"Point"}
}