{
  "type": "Feature",
  "properties": {
    "addr:full":"1512 S Batavia Ave Geneva IL 60134",
    "addr:housenumber":"1512",
    "addr:postcode":"60134",
    "addr:street":"S Batavia Ave",
    "iso:country":"US",
    "sg:address":"1512 S Batavia Ave",
    "sg:city":"Geneva",
    "sg:classifiers":[
        {
            "category":"Professional",
            "subcategory":"Testing Lab",
            "type":"Services"
        }
    ],
    "sg:phone":"+1 630 232 0104",
    "sg:postcode":"60134",
    "sg:province":"IL",
    "sg:tags":[
        "laboratory"
    ],
    "wof:name":"Riverbank Acoustical Labs",
    "wof:placetype":"venue"
},
  "geometry": {"coordinates":[-88.313692,41.866806],"type":"Point"}
}