{
  "type": "Feature",
  "properties": {
    "iso:country":"US",
    "sg:address":"302 S Main St",
    "sg:city":"Benton",
    "sg:classifiers":[
        {
            "category":"Organizations",
            "subcategory":"Religious Organization",
            "type":"Services"
        }
    ],
    "sg:phone":"+1 618 927 6270",
    "sg:postcode":"62812",
    "sg:province":"IL",
    "wof:name":"Benton/West City Ministerial Alliance",
    "wof:placetype":"venue"
},
  "geometry": {"coordinates":[-88.920543,37.999505],"type":"Point"}
}