{
  "type": "Feature",
  "properties": {
    "iso:country":"US",
    "sg:address":"348 Wiltshire Ln",
    "sg:city":"Crystal Lake",
    "sg:classifiers":[
        {
            "category":"Wholesale",
            "subcategory":"Chemicals & Plastics",
            "type":"Manufacturing & Wholesale Goods"
        }
    ],
    "sg:phone":"+1 815 444 9592",
    "sg:postcode":"60014",
    "sg:province":"IL",
    "sg:tags":[
        "film"
    ],
    "wof:name":"Film Solutions Inc",
    "wof:placetype":"venue"
},
  "geometry": {"coordinates":[-88.356385,42.230408],"type":"Point"}
}