{
  "type": "Feature",
  "properties": {
    "addr:full":"108 E College Ave Eureka IL 61530",
    "addr:housenumber":"108",
    "addr:postcode":"61530",
    "addr:street":"E College Ave",
    "iso:country":"US",
    "sg:address":"108 E College Ave",
    "sg:city":"Eureka",
    "sg:classifiers":[
        {
            "category":"Organizations",
            "subcategory":"Religious Organization",
            "type":"Services"
        }
    ],
    "sg:phone":"+1 309 467 2646",
    "sg:postcode":"61530",
    "sg:province":"IL",
    "sg:tags":[
        "church"
    ],
    "wof:name":"Newman Foundation",
    "wof:placetype":"venue"
},
  "geometry": {"coordinates":[-89.271367,40.714358],"type":"Point"}
}