{
  "type": "Feature",
  "properties": {
    "iso:country":"US",
    "sg:address":"2523 Lexington St",
    "sg:city":"Broadview",
    "sg:classifiers":[
        {
            "category":"Education",
            "subcategory":"Vocational School",
            "type":"Public Place"
        }
    ],
    "sg:phone":"+1 708 345 6067",
    "sg:postcode":"60155",
    "sg:province":"IL",
    "sg:tags":[
        "organization",
        "labor"
    ],
    "wof:name":"For Lcal Un 63 Ir Leag Chcago",
    "wof:placetype":"venue"
},
  "geometry": {"coordinates":[-87.863761,41.869244],"type":"Point"}
}