{
  "type": "Feature",
  "properties": {
    "iso:country":"US",
    "sg:address":"3512 Lebanon Ave",
    "sg:city":"Belleville",
    "sg:classifiers":[
        {
            "category":"Home & Garden",
            "subcategory":"Household Appliances",
            "type":"Retail Goods"
        }
    ],
    "sg:phone":"+1 618 632 0500",
    "sg:postcode":"62221",
    "sg:province":"IL",
    "wof:name":"Lloyd's Appliance",
    "wof:placetype":"venue"
},
  "geometry": {"coordinates":[-89.924949,38.547617],"type":"Point"}
}