{
  "type": "Feature",
  "properties": {
    "iso:country":"US",
    "sg:address":"320 W 1st St",
    "sg:city":"Kewanee",
    "sg:classifiers":[
        {
            "category":"Sports & Exercise",
            "subcategory":"Bowling",
            "type":"Entertainment"
        }
    ],
    "sg:phone":"+1 309 853 1741",
    "sg:postcode":"61443",
    "sg:province":"IL",
    "sg:tags":[
        "center"
    ],
    "wof:name":"Dura Bowl",
    "wof:placetype":"venue"
},
  "geometry": {"coordinates":[-89.928992,41.243496],"type":"Point"}
}