{
  "type": "Feature",
  "properties": {
    "iso:country":"US",
    "sg:address":"326 W Army Trail Rd Ste 130",
    "sg:city":"Bloomingdale",
    "sg:classifiers":[
        {
            "category":"Shopping",
            "subcategory":"Shoes",
            "type":"Retail Goods"
        }
    ],
    "sg:phone":"+1 630 307 9910",
    "sg:postcode":"60108",
    "sg:province":"IL",
    "sg:tags":[
        "store"
    ],
    "wof:name":"Sas Comfort Shoes",
    "wof:placetype":"venue"
},
  "geometry": {"coordinates":[-88.105684,41.93889],"type":"Point"}
}