{
  "type": "Feature",
  "properties": {
    "iso:country":"US",
    "sg:address":"200 W Grove Ave",
    "sg:city":"Rantoul",
    "sg:classifiers":[
        {
            "category":"Government",
            "subcategory":"Office",
            "type":"Public Place"
        }
    ],
    "sg:phone":"+1 217 892 2178",
    "sg:postcode":"61866",
    "sg:province":"IL",
    "sg:tags":[
        "township",
        "government-city",
        "village"
    ],
    "wof:name":"Village Rantoul Elc Utility",
    "wof:placetype":"venue"
},
  "geometry": {"coordinates":[-88.16046900000001,40.311932],"type":"Point"}
}