{
  "type": "Feature",
  "properties": {
    "iso:country":"US",
    "sg:address":"106 E Wilson St",
    "sg:city":"Elmhurst",
    "sg:classifiers":[
        {
            "category":"Professional",
            "subcategory":"Computer Services",
            "type":"Services"
        }
    ],
    "sg:phone":"+1 630 993 1060",
    "sg:postcode":"60126",
    "sg:province":"IL",
    "sg:tags":[
        "consultant",
        "designer"
    ],
    "wof:name":"Acwan Enterprises Inc",
    "wof:placetype":"venue"
},
  "geometry": {"coordinates":[-87.938277,41.878149],"type":"Point"}
}