{
  "type": "Feature",
  "properties": {
    "iso:country":"US",
    "sg:address":"2022 South Archer Ave",
    "sg:city":"Chicago",
    "sg:classifiers":[
        {
            "category":"Banks & Credit Unions",
            "subcategory":"Bank",
            "type":"Services"
        }
    ],
    "sg:phone":"+1 800 627 3999",
    "sg:postcode":"60616",
    "sg:province":"IL",
    "sg:website":"citibank.com",
    "wof:name":"Citibank",
    "wof:placetype":"venue"
},
  "geometry": {"coordinates":[-87.63064199999999,41.854881],"type":"Point"}
}