{
  "type": "Feature",
  "properties": {
    "addr:full":"3000 80th St Kenosha IL 53142",
    "addr:housenumber":"3000",
    "addr:postcode":"53142",
    "addr:street":"80Th St",
    "iso:country":"US",
    "sg:address":"3000 80th St",
    "sg:city":"Kenosha",
    "sg:classifiers":[
        {
            "category":"Banks & Credit Unions",
            "subcategory":"Bank",
            "type":"Services"
        }
    ],
    "sg:phone":"+1 262 694 1600",
    "sg:postcode":"53142",
    "sg:province":"IL",
    "wof:name":"Southern Lakes Credit Union",
    "wof:placetype":"venue"
},
  "geometry": {"coordinates":[-87.84620099999999,42.558817],"type":"Point"}
}