{
  "type": "Feature",
  "properties": {
    "addr:full":"10 Marriott Dr Lincolnshire IL 60069",
    "addr:housenumber":"10",
    "addr:postcode":"60069",
    "addr:street":"Marriott Dr",
    "iso:country":"US",
    "sg:address":"10 Marriott Dr",
    "sg:city":"Lincolnshire",
    "sg:classifiers":[
        {
            "category":"Fast Food",
            "type":"Food & Drink"
        },
        {
            "category":"Restaurant",
            "type":"Food & Drink"
        }
    ],
    "sg:phone":"+1 847 634 0100",
    "sg:postcode":"60069",
    "sg:province":"IL",
    "sg:tags":[
        "seafood",
        "take"
    ],
    "wof:name":"King's Wharf Restaurant",
    "wof:placetype":"venue"
},
  "geometry": {"coordinates":[-87.930335,42.194727],"type":"Point"}
}