{
  "type": "Feature",
  "properties": {
    "addr:full":"2000 N Market St Champaign IL 61822",
    "addr:housenumber":"2000",
    "addr:postcode":"61822",
    "addr:street":"N Market St",
    "iso:country":"US",
    "sg:address":"2000 N Market St",
    "sg:city":"Champaign",
    "sg:classifiers":[
        {
            "category":"Building & Trades",
            "subcategory":"Construction",
            "type":"Services"
        }
    ],
    "sg:phone":"+1 217 355 5054",
    "sg:postcode":"61822",
    "sg:province":"IL",
    "sg:tags":[
        "excavation",
        "contractor"
    ],
    "wof:name":"Stark Excavating Inc",
    "wof:placetype":"venue"
},
  "geometry": {"coordinates":[-88.238969,40.139707],"type":"Point"}
}