{
  "type": "Feature",
  "properties": {
    "iso:country":"US",
    "sg:address":"235 41st St",
    "sg:city":"Moline",
    "sg:classifiers":[
        {
            "category":"Building & Trades",
            "subcategory":"Plumbing",
            "type":"Services"
        }
    ],
    "sg:phone":"+1 309 797 7938",
    "sg:postcode":"61265",
    "sg:province":"IL",
    "wof:name":"Eagle Plumbing",
    "wof:placetype":"venue"
},
  "geometry": {"coordinates":[-90.48005000000001,41.513329],"type":"Point"}
}