{
  "type": "Feature",
  "properties": {
    "addr:full":"3319 W Montrose Chicago IL 60618",
    "addr:housenumber":"3319",
    "addr:postcode":"60618",
    "addr:street":"W Montrose",
    "iso:country":"US",
    "sg:address":"3319 W Montrose",
    "sg:city":"Chicago",
    "sg:classifiers":[
        {
            "category":"Personal",
            "type":"Services"
        }
    ],
    "sg:phone":"+1 773 463 7021",
    "sg:postcode":"60618",
    "sg:province":"IL",
    "sg:tags":[
        "local"
    ],
    "wof:name":"American Arts Antiques Appraisals & Associates",
    "wof:placetype":"venue"
},
  "geometry": {"coordinates":[-87.71165999999999,41.961143],"type":"Point"}
}