{
  "type": "Feature",
  "properties": {
    "iso:country":"US",
    "sg:address":"3100 W 25th St",
    "sg:city":"Chicago",
    "sg:classifiers":[
        {
            "category":"Place Of Worship",
            "type":"Public Place"
        }
    ],
    "sg:phone":"+1 773 542 4540",
    "sg:postcode":"60623",
    "sg:province":"IL",
    "sg:tags":[
        "church"
    ],
    "wof:name":"Abc Nueva Vida",
    "wof:placetype":"venue"
},
  "geometry": {"coordinates":[-87.70262099999999,41.846378],"type":"Point"}
}