{
  "type": "Feature",
  "properties": {
    "iso:country":"US",
    "sg:address":"2174 Blackberry Dr Unit 100",
    "sg:city":"Geneva",
    "sg:classifiers":[
        {
            "category":"Insurance",
            "subcategory":"Insurance Agent",
            "type":"Services"
        },
        {
            "category":"Insurance",
            "subcategory":"Hazard Insurance",
            "type":"Services"
        },
        {
            "category":"Insurance",
            "subcategory":"Title Insurance",
            "type":"Services"
        },
        {
            "category":"Insurance",
            "subcategory":"Life Insurance",
            "type":"Services"
        }
    ],
    "sg:phone":"+1 630 262 1059",
    "sg:postcode":"60134",
    "sg:province":"IL",
    "sg:tags":[
        "auto",
        "commercial",
        "business",
        "homeowner"
    ],
    "sg:website":"http://www.countryfinancial.com/orazio.difruscolo",
    "wof:name":"COUNTRY Financial Orazio Difruscolo",
    "wof:placetype":"venue"
},
  "geometry": {"coordinates":[-88.336035,41.895221],"type":"Point"}
}