{
  "type": "Feature",
  "properties": {
    "iso:country":"US",
    "sg:address":"644 W Belmont Ave",
    "sg:city":"Chicago",
    "sg:classifiers":[
        {
            "category":"Education",
            "subcategory":"Library",
            "type":"Public Place"
        }
    ],
    "sg:phone":"+1 312 744 1139",
    "sg:postcode":"60657",
    "sg:province":"IL",
    "sg:website":"www.chipublib.org/branch/details...",
    "wof:name":"Chicago Public Library - John Merlo Branch",
    "wof:placetype":"venue"
},
  "geometry": {"coordinates":[-87.646146,41.940027],"type":"Point"}
}