{
  "type": "Feature",
  "properties": {
    "iso:country":"US",
    "sg:address":"425 Main St",
    "sg:city":"Warsaw",
    "sg:classifiers":[
        {
            "category":"Shopping",
            "subcategory":"Bicycles & Sporting Goods",
            "type":"Retail Goods"
        }
    ],
    "sg:phone":"+1 217 256 4867",
    "sg:postcode":"62379",
    "sg:province":"IL",
    "sg:tags":[
        "gun",
        "gunsmith"
    ],
    "wof:name":"Woolson Firearms",
    "wof:placetype":"venue"
},
  "geometry": {"coordinates":[-91.436626,40.359982],"type":"Point"}
}