{
  "type": "Feature",
  "properties": {
    "addr:full":"6950 Windsor Ave Berwyn IL 60402",
    "addr:housenumber":"6950",
    "addr:postcode":"60402",
    "addr:street":"Windsor Ave",
    "iso:country":"US",
    "sg:address":"6950 Windsor Ave",
    "sg:city":"Berwyn",
    "sg:classifiers":[
        {
            "category":"Shopping",
            "subcategory":"Clothing, Apparel, & Fashions",
            "type":"Retail Goods"
        }
    ],
    "sg:phone":"+1 708 749 2960",
    "sg:postcode":"60402",
    "sg:province":"IL",
    "sg:tags":[
        "theatrical",
        "costume"
    ],
    "wof:name":"Creative Costumes",
    "wof:placetype":"venue"
},
  "geometry": {"coordinates":[-87.797251,41.832169],"type":"Point"}
}