{
  "type": "Feature",
  "properties": {
    "iso:country":"US",
    "sg:address":"440 N Division St",
    "sg:city":"Woodhull",
    "sg:classifiers":[
        {
            "category":"Education",
            "subcategory":"Library",
            "type":"Public Place"
        }
    ],
    "sg:phone":"+1 309 334 2680",
    "sg:postcode":"61490",
    "sg:province":"IL",
    "wof:name":"Woodhull Library",
    "wof:placetype":"venue"
},
  "geometry": {"coordinates":[-90.315612,41.180568],"type":"Point"}
}