{
  "type": "Feature",
  "properties": {
    "iso:country":"US",
    "sg:address":"1634 Todd Farm Dr",
    "sg:city":"Elgin",
    "sg:classifiers":[
        {
            "category":"Manufacturing",
            "subcategory":"Soap",
            "type":"Manufacturing & Wholesale Goods"
        }
    ],
    "sg:phone":"+1 847 741 4300",
    "sg:postcode":"60123",
    "sg:province":"IL",
    "sg:tags":[
        "cleaners",
        "inhibitor",
        "blend",
        "rust",
        "mfg"
    ],
    "wof:name":"Blendtech Industries Inc",
    "wof:placetype":"venue"
},
  "geometry": {"coordinates":[-88.320316,42.061118],"type":"Point"}
}