{
  "type": "Feature",
  "properties": {
    "addr:full":"501 S College Ave Aledo IL 61231",
    "addr:housenumber":"501",
    "addr:postcode":"61231",
    "addr:street":"S College Ave",
    "iso:country":"US",
    "sg:address":"501 S College Ave",
    "sg:city":"Aledo",
    "sg:classifiers":[
        {
            "category":"Organizations",
            "subcategory":"Religious Organization",
            "type":"Services"
        }
    ],
    "sg:phone":"+1 309 582 2182",
    "sg:postcode":"61231",
    "sg:province":"IL",
    "sg:tags":[
        "church"
    ],
    "sg:website":"www.capchurch.org",
    "wof:name":"College Avenue Presbyterian",
    "wof:placetype":"venue"
},
  "geometry": {"coordinates":[-90.74930500000001,41.198164],"type":"Point"}
}