{
  "type": "Feature",
  "properties": {
    "iso:country":"US",
    "sg:address":"5201 S Harper Ave",
    "sg:city":"Chicago",
    "sg:classifiers":[
        {
            "category":"Restaurant",
            "type":"Food & Drink"
        }
    ],
    "sg:phone":"+1 773 241 5200",
    "sg:postcode":"60615",
    "sg:province":"IL",
    "sg:tags":[
        "new",
        "american"
    ],
    "sg:website":"park52chicago.com",
    "wof:name":"Park 52",
    "wof:placetype":"venue"
},
  "geometry": {"coordinates":[-87.58910299999999,41.800909],"type":"Point"}
}