{
  "type": "Feature",
  "properties": {
    "iso:country":"US",
    "sg:address":"382 Fawn Trail Ln",
    "sg:city":"Carbondale",
    "sg:classifiers":[
        {
            "category":"Travel",
            "subcategory":"Hotels & Motels",
            "type":"Entertainment"
        }
    ],
    "sg:phone":"+1 618 529 5261",
    "sg:postcode":"62903",
    "sg:province":"IL",
    "sg:tags":[
        "breakfast",
        "accommodation",
        "bed"
    ],
    "sg:website":"www.sassafrasbb.com",
    "wof:name":"Sassafras Ridge B & B",
    "wof:placetype":"venue"
},
  "geometry": {"coordinates":[-89.251622,37.670306],"type":"Point"}
}