{
  "type": "Feature",
  "properties": {
    "iso:country":"US",
    "sg:address":"67 Algonquin Rd",
    "sg:city":"South Barrington",
    "sg:classifiers":[
        {
            "category":"Place Of Worship",
            "subcategory":"Church",
            "type":"Public Place"
        }
    ],
    "sg:phone":"+1 847 765 5000",
    "sg:postcode":"60010",
    "sg:province":"IL",
    "sg:website":"www.willowcreek.org",
    "wof:name":"Willow Creek Community Church",
    "wof:placetype":"venue"
},
  "geometry": {"coordinates":[-88.25353,42.148897],"type":"Point"}
}