{
  "type": "Feature",
  "properties": {
    "addr:full":"7742 S Cregier Ave Chicago IL 60649",
    "addr:housenumber":"7742",
    "addr:postcode":"60649",
    "addr:street":"S Cregier Ave",
    "iso:country":"US",
    "sg:address":"7742 S Cregier Ave",
    "sg:city":"Chicago",
    "sg:classifiers":[
        {
            "category":"Wholesale",
            "subcategory":"Non-durable Goods",
            "type":"Manufacturing & Wholesale Goods"
        }
    ],
    "sg:phone":"+1 773 721 2342",
    "sg:postcode":"60649",
    "sg:province":"IL",
    "wof:name":"Distributing In Rapid Response",
    "wof:placetype":"venue"
},
  "geometry": {"coordinates":[-87.581,41.754141],"type":"Point"}
}