{
  "type": "Feature",
  "properties": {
    "iso:country":"US",
    "sg:address":"501 Ridge Rd",
    "sg:city":"Homewood",
    "sg:classifiers":[
        {
            "category":"Home & Garden",
            "subcategory":"Household Appliances",
            "type":"Retail Goods"
        },
        {
            "category":"Building & Trades",
            "subcategory":"Plumbing",
            "type":"Services"
        },
        {
            "category":"Building & Trades",
            "subcategory":"Construction",
            "type":"Services"
        }
    ],
    "sg:phone":"+1 708 799 0090",
    "sg:postcode":"60430",
    "sg:province":"IL",
    "sg:tags":[
        "repair",
        "major",
        "specialty",
        "system",
        "appliances-small",
        "heating",
        "clean",
        "contractor",
        "air conditioning",
        "boilers-repair"
    ],
    "wof:name":"Floyd's Heating & Air Conditioning Inc",
    "wof:placetype":"venue"
},
  "geometry": {"coordinates":[-87.63043999999999,41.564548],"type":"Point"}
}