{
  "type": "Feature",
  "properties": {
    "iso:country":"US",
    "sg:address":"208 Camelot Dr",
    "sg:city":"Collinsville",
    "sg:classifiers":[
        {
            "category":"Building & Trades",
            "subcategory":"Plumbing",
            "type":"Services"
        }
    ],
    "sg:phone":"+1 618 343 1002",
    "sg:postcode":"62234",
    "sg:province":"IL",
    "sg:tags":[
        "conditioning",
        "air",
        "system",
        "contractor"
    ],
    "wof:name":"Air Doctor",
    "wof:placetype":"venue"
},
  "geometry": {"coordinates":[-89.973237,38.696088],"type":"Point"}
}