{
  "type": "Feature",
  "properties": {
    "addr:full":"2835 N Sheffield Ave Chicago IL 60657",
    "addr:housenumber":"2835",
    "addr:postcode":"60657",
    "addr:street":"N Sheffield Ave",
    "iso:country":"US",
    "sg:address":"2835 N Sheffield Ave",
    "sg:city":"Chicago",
    "sg:classifiers":[
        {
            "category":"Banks & Credit Unions",
            "subcategory":"Investment Brokerage",
            "type":"Services"
        }
    ],
    "sg:phone":"+1 800 493 4444",
    "sg:postcode":"60657",
    "sg:province":"IL",
    "sg:tags":[
        "commodity",
        "contract"
    ],
    "wof:name":"Cleartrade Commodities",
    "wof:placetype":"venue"
},
  "geometry": {"coordinates":[-87.653829,41.933944],"type":"Point"}
}