{
  "type": "Feature",
  "properties": {
    "iso:country":"US",
    "sg:address":"75 W Elm St",
    "sg:city":"Chicago",
    "sg:classifiers":[
        {
            "category":"Food & Beverages",
            "subcategory":"Groceries & Convenience Stores",
            "type":"Retail Goods"
        }
    ],
    "sg:phone":"+1 312 440 1144",
    "sg:postcode":"60610",
    "sg:province":"IL",
    "wof:name":"Treasure Island Food Mart",
    "wof:placetype":"venue"
},
  "geometry": {"coordinates":[-87.631061,41.903002],"type":"Point"}
}