{
  "type": "Feature",
  "properties": {
    "iso:country":"US",
    "sg:address":"1017 Oakland Dr",
    "sg:city":"Barrington",
    "sg:classifiers":[
        {
            "category":"Wholesale",
            "subcategory":"Machinery & Supplies",
            "type":"Manufacturing & Wholesale Goods"
        }
    ],
    "sg:phone":"+1 847 842 1609",
    "sg:postcode":"60010",
    "sg:province":"IL",
    "wof:name":"Village Lawn Sprinklers",
    "wof:placetype":"venue"
},
  "geometry": {"coordinates":[-88.118336,42.148039],"type":"Point"}
}