{
  "type": "Feature",
  "properties": {
    "addr:full":"2631 Kirchoff Rd Rolling Meadows IL 60008",
    "addr:housenumber":"2631",
    "addr:postcode":"60008",
    "addr:street":"Kirchoff Rd",
    "iso:country":"US",
    "sg:address":"2631 Kirchoff Rd",
    "sg:city":"Rolling Meadows",
    "sg:classifiers":[
        {
            "category":"Retail",
            "subcategory":"Laundry & Dry Cleaning",
            "type":"Services"
        }
    ],
    "sg:phone":"+1 847 577 8101",
    "sg:postcode":"60008",
    "sg:province":"IL",
    "sg:tags":[
        "garment",
        "agent"
    ],
    "wof:name":"A Classic Dry Cleaning",
    "wof:placetype":"venue"
},
  "geometry": {"coordinates":[-88.014972,42.077379],"type":"Point"}
}