{
  "type": "Feature",
  "properties": {
    "iso:country":"US",
    "sg:address":"1650 N Wells St",
    "sg:city":"Chicago",
    "sg:classifiers":[
        {
            "category":"Real Estate",
            "subcategory":"Real Estate Services",
            "type":"Services"
        },
        {
            "category":"Real Estate",
            "subcategory":"Real Estate Agent",
            "type":"Services"
        }
    ],
    "sg:phone":"+1 773 809 3090",
    "sg:postcode":"60614",
    "sg:province":"IL",
    "sg:website":"hotpropertychicago.com/",
    "wof:name":"Andrea Geller - Sudler Sotheby's International Realty",
    "wof:placetype":"venue"
},
  "geometry": {"coordinates":[-87.635099,41.91273],"type":"Point"}
}