{
  "type": "Feature",
  "properties": {
    "addr:full":"5879 N Medina Ave Chicago IL 60646",
    "addr:housenumber":"5879",
    "addr:postcode":"60646",
    "addr:street":"N Medina Ave",
    "iso:country":"US",
    "sg:address":"5879 N Medina Ave",
    "sg:city":"Chicago",
    "sg:classifiers":[
        {
            "category":"Building & Trades",
            "subcategory":"Electrical",
            "type":"Services"
        }
    ],
    "sg:phone":"+1 773 792 1562",
    "sg:postcode":"60646",
    "sg:province":"IL",
    "sg:tags":[
        "electrical",
        "contractor"
    ],
    "wof:name":"Dld Electric Co",
    "wof:placetype":"venue"
},
  "geometry": {"coordinates":[-87.780174,41.988232],"type":"Point"}
}