{
  "type": "Feature",
  "properties": {
    "iso:country":"US",
    "sg:address":"120 Oak Creek Plz",
    "sg:city":"Mundelein",
    "sg:classifiers":[
        {
            "category":"Home & Garden",
            "subcategory":"Building Materials",
            "type":"Retail Goods"
        }
    ],
    "sg:phone":"+1   ",
    "sg:postcode":"60060",
    "sg:province":"IL",
    "sg:tags":[
        "hardware"
    ],
    "wof:name":"Menards 3514",
    "wof:placetype":"venue"
},
  "geometry": {"coordinates":[-87.992721,42.240074],"type":"Point"}
}