{
  "type": "Feature",
  "properties": {
    "iso:country":"US",
    "sg:address":"4418 Shabbona Ln",
    "sg:city":"Lisle",
    "sg:classifiers":[
        {
            "category":"Wholesale",
            "subcategory":"Metals & Minerals",
            "type":"Manufacturing & Wholesale Goods"
        }
    ],
    "sg:phone":"+1 630 420 9069",
    "sg:postcode":"60532",
    "sg:province":"IL",
    "sg:tags":[
        "center"
    ],
    "wof:name":"Jay Marquard & Assoc",
    "wof:placetype":"venue"
},
  "geometry": {"coordinates":[-88.10209500000001,41.801032],"type":"Point"}
}