{
  "type": "Feature",
  "properties": {
    "iso:country":"US",
    "sg:address":"654 E 1400 N Rd",
    "sg:city":"Flanagan",
    "sg:phone":"+1 815 796 4198",
    "sg:postcode":"61740",
    "sg:province":"IL",
    "sg:tags":[
        "farm",
        "corn",
        "soybean"
    ],
    "wof:name":"Greg Zimmerman",
    "wof:placetype":"venue"
},
  "geometry": {"coordinates":[-88.911773,40.826241],"type":"Point"}
}