{
  "type": "Feature",
  "properties": {
    "addr:full":"595 Main St Alto Pass IL 62905",
    "addr:housenumber":"595",
    "addr:postcode":"62905",
    "addr:street":"Main St Alto Pass",
    "iso:country":"US",
    "sg:address":"595 Main St",
    "sg:city":"Alto Pass",
    "sg:classifiers":[
        {
            "category":"Shopping",
            "subcategory":"Used Merchandise",
            "type":"Retail Goods"
        }
    ],
    "sg:phone":"+1 618 893 2206",
    "sg:postcode":"62905",
    "sg:province":"IL",
    "sg:tags":[
        "antique"
    ],
    "wof:name":"Austin's Of Alto Pass",
    "wof:placetype":"venue"
},
  "geometry": {"coordinates":[-89.32031600000001,37.574151],"type":"Point"}
}