{
  "type": "Feature",
  "properties": {
    "iso:country":"US",
    "sg:address":"595 Main St",
    "sg:city":"Alto Pass",
    "sg:classifiers":[
        {
            "category":"Shopping",
            "subcategory":"Used Merchandise",
            "type":"Retail Goods"
        }
    ],
    "sg:phone":"+1 618 893 2206",
    "sg:postcode":"62905",
    "sg:province":"IL",
    "sg:tags":[
        "antique"
    ],
    "wof:name":"Austin's Of Alto Pass",
    "wof:placetype":"venue"
},
  "geometry": {"coordinates":[-89.320316,37.574151],"type":"Point"}
}