{
  "type": "Feature",
  "properties": {
    "addr:full":"305 Main St West Chicago IL 60185",
    "addr:housenumber":"305",
    "addr:postcode":"60185",
    "addr:street":"Main St",
    "iso:country":"US",
    "sg:address":"305 Main St",
    "sg:city":"West Chicago",
    "sg:classifiers":[
        {
            "category":"Personal",
            "type":"Services"
        }
    ],
    "sg:phone":"+1 630 293 1200",
    "sg:postcode":"60185",
    "sg:province":"IL",
    "sg:tags":[
        "towing"
    ],
    "wof:name":"Area DuPage Towing",
    "wof:placetype":"venue"
},
  "geometry": {"coordinates":[-88.202544,41.882909],"type":"Point"}
}