{
  "type": "Feature",
  "properties": {
    "iso:country":"US",
    "sg:address":"9610 S Bell Ave",
    "sg:city":"Chicago",
    "sg:classifiers":[
        {
            "category":"Manufacturing",
            "subcategory":"Printing",
            "type":"Manufacturing & Wholesale Goods"
        }
    ],
    "sg:phone":"+1 773 445 5164",
    "sg:postcode":"60643",
    "sg:province":"IL",
    "sg:tags":[
        "label"
    ],
    "wof:name":"Badger Tag Label",
    "wof:placetype":"venue"
},
  "geometry": {"coordinates":[-87.67839600000001,41.717533],"type":"Point"}
}