{
  "type": "Feature",
  "properties": {
    "iso:country":"US",
    "sg:address":"1537 E Alison Dr",
    "sg:city":"Palatine",
    "sg:classifiers":[
        {
            "category":"Professional",
            "subcategory":"Computer Services",
            "type":"Services"
        }
    ],
    "sg:phone":"+1 847 934 6234",
    "sg:postcode":"60074",
    "sg:province":"IL",
    "sg:tags":[
        "related"
    ],
    "wof:name":"Nets To You Inc",
    "wof:placetype":"venue"
},
  "geometry": {"coordinates":[-88.005748,42.111104],"type":"Point"}
}