{
  "type": "Feature",
  "properties": {
    "addr:full":"640 Pond Dr Wood Dale IL 60191",
    "addr:housenumber":"640",
    "addr:postcode":"60191",
    "addr:street":"Pond Dr",
    "iso:country":"US",
    "sg:address":"640 Pond Dr",
    "sg:city":"Wood Dale",
    "sg:classifiers":[
        {
            "category":"Wholesale",
            "subcategory":"Machinery & Supplies",
            "type":"Manufacturing & Wholesale Goods"
        }
    ],
    "sg:phone":"+1 630 595 3323",
    "sg:postcode":"60191",
    "sg:province":"IL",
    "sg:tags":[
        "industrial"
    ],
    "wof:name":"Ochiai Seisakusho",
    "wof:placetype":"venue"
},
  "geometry": {"coordinates":[-87.982179,41.974537],"type":"Point"}
}