{
  "type": "Feature",
  "properties": {
    "addr:full":"409 Massey Ln Jacksonville IL 62650",
    "addr:housenumber":"409",
    "addr:postcode":"62650",
    "addr:street":"Massey Ln",
    "iso:country":"US",
    "sg:address":"409 Massey Ln",
    "sg:city":"Jacksonville",
    "sg:classifiers":[
        {
            "category":"Wholesale",
            "subcategory":"Non-durable Goods",
            "type":"Manufacturing & Wholesale Goods"
        }
    ],
    "sg:phone":"+1 217 245 9924",
    "sg:postcode":"62650",
    "sg:province":"IL",
    "wof:name":"Insight Media",
    "wof:placetype":"venue"
},
  "geometry": {"coordinates":[-90.266825,39.724855],"type":"Point"}
}