{
  "type": "Feature",
  "properties": {
    "addr:full":"144 N Dean Dr Palatine IL 60074",
    "addr:housenumber":"144",
    "addr:postcode":"60074",
    "addr:street":"N Dean Dr",
    "iso:country":"US",
    "sg:address":"144 N Dean Dr",
    "sg:city":"Palatine",
    "sg:classifiers":[
        {
            "category":"Manufacturing",
            "subcategory":"Retail Goods",
            "type":"Manufacturing & Wholesale Goods"
        }
    ],
    "sg:phone":"+1 847 202 8223",
    "sg:postcode":"60074",
    "sg:province":"IL",
    "sg:tags":[
        "marking",
        "devices"
    ],
    "wof:name":"Barkal Machine & Tool Sales",
    "wof:placetype":"venue"
},
  "geometry": {"coordinates":[-88.018317,42.115542],"type":"Point"}
}