{
  "type": "Feature",
  "properties": {
    "iso:country":"US",
    "sg:address":"1334 E State St",
    "sg:city":"Rockford",
    "sg:classifiers":[
        {
            "category":"Health Services",
            "subcategory":"Doctor",
            "type":"Services"
        }
    ],
    "sg:phone":"+1 815 962 1400",
    "sg:postcode":"61104",
    "sg:province":"IL",
    "sg:tags":[
        "dentist"
    ],
    "wof:name":"Milos Jamie L DDS PC",
    "wof:placetype":"venue"
},
  "geometry": {"coordinates":[-89.076892,42.266996],"type":"Point"}
}