{
  "type": "Feature",
  "properties": {
    "addr:full":"2190 Gladstone Ct Glendale Heights IL 60139",
    "addr:housenumber":"2190",
    "addr:postcode":"60139",
    "addr:street":"Gladstone Ct",
    "iso:country":"US",
    "sg:address":"2190 Gladstone Ct",
    "sg:city":"Glendale Heights",
    "sg:classifiers":[
        {
            "category":"Professional",
            "subcategory":"Advertising",
            "type":"Services"
        }
    ],
    "sg:phone":"+1 630 351 9003",
    "sg:postcode":"60139",
    "sg:province":"IL",
    "sg:tags":[
        "counselor"
    ],
    "sg:website":"www.balash.com",
    "wof:name":"Balash & Assoc",
    "wof:placetype":"venue"
},
  "geometry": {"coordinates":[-88.084947,41.937683],"type":"Point"}
}