{
  "type": "Feature",
  "properties": {
    "addr:full":"2545 E 79th St Chicago IL 60649",
    "addr:housenumber":"2545",
    "addr:postcode":"60649",
    "addr:street":"E 79Th St",
    "iso:country":"US",
    "sg:address":"2545 E 79th St",
    "sg:city":"Chicago",
    "sg:classifiers":[
        {
            "category":"Shopping",
            "subcategory":"Clothing, Apparel, & Fashions",
            "type":"Retail Goods"
        }
    ],
    "sg:phone":"+1 773 221 2940",
    "sg:postcode":"60649",
    "sg:province":"IL",
    "sg:tags":[
        "accessory",
        "clothing",
        "women's"
    ],
    "wof:name":"Rainbow Shop",
    "wof:placetype":"venue"
},
  "geometry": {"coordinates":[-87.561699,41.7519],"type":"Point"}
}