{
  "type": "Feature",
  "properties": {
    "iso:country":"US",
    "sg:address":"320 Leicester Rd",
    "sg:city":"Kenilworth",
    "sg:classifiers":[
        {
            "category":"Professional",
            "subcategory":"Business Services",
            "type":"Services"
        }
    ],
    "sg:phone":"+1 847 251 0200",
    "sg:postcode":"60043",
    "sg:province":"IL",
    "wof:name":"Preferred Financial",
    "wof:placetype":"venue"
},
  "geometry": {"coordinates":[-87.711022,42.090517],"type":"Point"}
}