{
  "type": "Feature",
  "properties": {
    "iso:country":"US",
    "sg:address":"2754 W Washington Blvd",
    "sg:city":"Chicago",
    "sg:classifiers":[
        {
            "category":"Place Of Worship",
            "type":"Public Place"
        }
    ],
    "sg:phone":"+1 773 619 0135",
    "sg:postcode":"60612",
    "sg:province":"IL",
    "sg:tags":[
        "church"
    ],
    "wof:name":"Palms Of Faith 1",
    "wof:placetype":"venue"
},
  "geometry": {"coordinates":[-87.694138,41.882918],"type":"Point"}
}