{
  "type": "Feature",
  "properties": {
    "iso:country":"US",
    "sg:address":"2000 Hwy 17",
    "sg:city":"Aledo",
    "sg:classifiers":[
        {
            "category":"Retail",
            "subcategory":"Funeral Services",
            "type":"Services"
        }
    ],
    "sg:phone":"+1 309 582 5145",
    "sg:postcode":"61231",
    "sg:province":"IL",
    "wof:name":"Reiser-Trimble Funeral Home",
    "wof:placetype":"venue"
},
  "geometry": {"coordinates":[-90.703808,41.199108],"type":"Point"}
}