{
  "type": "Feature",
  "properties": {
    "addr:full":"4422 Bayview Dr Crystal Lake IL 60014",
    "addr:housenumber":"4422",
    "addr:postcode":"60014",
    "addr:street":"Bayview Dr",
    "iso:country":"US",
    "sg:address":"4422 Bayview Dr",
    "sg:city":"Crystal Lake",
    "sg:classifiers":[
        {
            "category":"Professional",
            "subcategory":"Business Services",
            "type":"Services"
        }
    ],
    "sg:phone":"+1 815 477 7974",
    "sg:postcode":"60014",
    "sg:province":"IL",
    "sg:tags":[
        "embroidery"
    ],
    "wof:name":"Affordable Embroidery Mngrmmng",
    "wof:placetype":"venue"
},
  "geometry": {"coordinates":[-88.22565,42.264377],"type":"Point"}
}