{
  "type": "Feature",
  "properties": {
    "iso:country":"US",
    "sg:address":"1414 N Main St",
    "sg:city":"Rockford",
    "sg:classifiers":[
        {
            "category":"Shopping",
            "subcategory":"Music",
            "type":"Retail Goods"
        }
    ],
    "sg:phone":"+1   ",
    "sg:postcode":"61103",
    "sg:province":"IL",
    "wof:name":"Tin Whistle",
    "wof:placetype":"venue"
},
  "geometry": {"coordinates":[-89.080392,42.288472],"type":"Point"}
}