{
  "type": "Feature",
  "properties": {
    "iso:country":"US",
    "sg:address":"201 E Poplar St",
    "sg:city":"Odin",
    "sg:classifiers":[
        {
            "category":"Shopping",
            "subcategory":"Used Merchandise",
            "type":"Retail Goods"
        }
    ],
    "sg:phone":"+1 618 775 8817",
    "sg:postcode":"62870",
    "sg:province":"IL",
    "sg:tags":[
        "antique"
    ],
    "wof:name":"Carolyn's Corners",
    "wof:placetype":"venue"
},
  "geometry": {"coordinates":[-89.051211,38.619477],"type":"Point"}
}