{
  "type": "Feature",
  "properties": {
    "addr:full":"1304 Crispus Dr Champaign IL 61820",
    "addr:housenumber":"1304",
    "addr:postcode":"61820",
    "addr:street":"Crispus Dr",
    "iso:country":"US",
    "sg:address":"1304 Crispus Dr",
    "sg:city":"Champaign",
    "sg:classifiers":[
        {
            "category":"Professional",
            "subcategory":"Accounting & Tax Preparation",
            "type":"Services"
        }
    ],
    "sg:phone":"+1 217 359 3528",
    "sg:postcode":"61820",
    "sg:province":"IL",
    "sg:tags":[
        "return"
    ],
    "wof:name":"Greens Accounting & Tax Svc",
    "wof:placetype":"venue"
},
  "geometry": {"coordinates":[-88.229448,40.128273],"type":"Point"}
}