{
  "type": "Feature",
  "properties": {
    "addr:full":"3857 W Washington Blvd Chicago IL 60624",
    "addr:housenumber":"3857",
    "addr:postcode":"60624",
    "addr:street":"W Washington Blvd",
    "iso:country":"US",
    "sg:address":"3857 W Washington Blvd",
    "sg:city":"Chicago",
    "sg:classifiers":[
        {
            "category":"Health Services",
            "subcategory":"Doctor",
            "type":"Services"
        }
    ],
    "sg:phone":"+1 773 826 5350",
    "sg:postcode":"60624",
    "sg:province":"IL",
    "wof:name":"Butler David N MD",
    "wof:placetype":"venue"
},
  "geometry": {"coordinates":[-87.722054,41.881754],"type":"Point"}
}