{
  "type": "Feature",
  "properties": {
    "iso:country":"US",
    "sg:address":"6241 W Belmont Ave",
    "sg:city":"Chicago",
    "sg:classifiers":[
        {
            "category":"Professional",
            "subcategory":"Lawyer & Legal Services",
            "type":"Services"
        }
    ],
    "sg:phone":"+1 773 622 6713",
    "sg:postcode":"60634",
    "sg:province":"IL",
    "sg:tags":[
        "attorney",
        "law",
        "immigration"
    ],
    "wof:name":"Horizon Immigration",
    "wof:placetype":"venue"
},
  "geometry": {"coordinates":[-87.78206,41.938364],"type":"Point"}
}