{
  "type": "Feature",
  "properties": {
    "iso:country":"US",
    "sg:address":"407 N State St",
    "sg:city":"Geneseo",
    "sg:phone":"+1 309 944 3737",
    "sg:postcode":"61254",
    "sg:province":"IL",
    "sg:tags":[
        "farm",
        "corn"
    ],
    "wof:name":"James Dahl",
    "wof:placetype":"venue"
},
  "geometry": {"coordinates":[-90.155818,41.458259],"type":"Point"}
}