{
  "type": "Feature",
  "properties": {
    "addr:full":"10275 W Higgins Rd Des Plaines IL 60018",
    "addr:housenumber":"10275",
    "addr:postcode":"60018",
    "addr:street":"W Higgins Rd Des",
    "iso:country":"US",
    "sg:address":"10275 W Higgins Rd",
    "sg:city":"Des Plaines",
    "sg:classifiers":[
        {
            "category":"Insurance",
            "subcategory":"Insurance Agent",
            "type":"Services"
        }
    ],
    "sg:phone":"+1 847 338 4300",
    "sg:postcode":"60018",
    "sg:province":"IL",
    "wof:name":"Joshua A Hermann",
    "wof:placetype":"venue"
},
  "geometry": {"coordinates":[-87.88408699999999,41.998028],"type":"Point"}
}