{
  "type": "Feature",
  "properties": {
    "iso:country":"US",
    "sg:address":"1206 N 4th St",
    "sg:city":"Chillicothe",
    "sg:classifiers":[
        {
            "category":"Restaurant",
            "type":"Food & Drink"
        },
        {
            "category":"Ice Cream",
            "type":"Food & Drink"
        }
    ],
    "sg:menulink":"http://www.allmenus.com/il/chillicothe/161803-dairy-queen/menu/",
    "sg:phone":"+1 309 274 2070",
    "sg:postcode":"61523",
    "sg:province":"IL",
    "sg:tags":[
        "burger",
        "american",
        "ice",
        "cream"
    ],
    "wof:name":"Dairy Queen",
    "wof:placetype":"venue"
},
  "geometry": {"coordinates":[-89.487084,40.920198],"type":"Point"}
}