{
  "type": "Feature",
  "properties": {
    "addr:full":"640 Rockland Ave Lake Bluff IL 60044",
    "addr:housenumber":"640",
    "addr:postcode":"60044",
    "addr:street":"Rockland Ave",
    "iso:country":"US",
    "sg:address":"640 Rockland Ave",
    "sg:city":"Lake Bluff",
    "sg:classifiers":[
        {
            "category":"Recreation",
            "type":"Entertainment"
        }
    ],
    "sg:phone":"+1 847 295 6449",
    "sg:postcode":"60044",
    "sg:province":"IL",
    "sg:tags":[
        "parks"
    ],
    "wof:name":"Park Maintenance Garage",
    "wof:placetype":"venue"
},
  "geometry": {"coordinates":[-87.84963,42.280769],"type":"Point"}
}