{
  "type": "Feature",
  "properties": {
    "addr:full":"465 N Des Plaines River Rd Des Plaines IL 60016",
    "addr:housenumber":"465",
    "addr:postcode":"60016",
    "addr:street":"N Des Plaines River Rd Des",
    "iso:country":"US",
    "sg:address":"465 N Des Plaines River Rd",
    "sg:city":"Des Plaines",
    "sg:classifiers":[
        {
            "category":"Restaurant",
            "type":"Food & Drink"
        }
    ],
    "sg:menulink":"http://www.allmenus.com/il/maine/240857-white-castle/menu/",
    "sg:postcode":"60016",
    "sg:province":"IL",
    "sg:tags":[
        "burger",
        "american"
    ],
    "wof:name":"White Castle",
    "wof:placetype":"venue"
},
  "geometry": {"coordinates":[-87.88956399999999,42.059076],"type":"Point"}
}