{
  "type": "Feature",
  "properties": {
    "iso:country":"US",
    "sg:address":"1630 W 18th Street",
    "sg:city":"Chicago",
    "sg:classifiers":[
        {
            "category":"Health Services",
            "subcategory":"Doctor",
            "type":"Services"
        }
    ],
    "sg:phone":"+1 312 243 3131",
    "sg:postcode":"60608",
    "sg:province":"IL",
    "wof:name":"Glick Robert S",
    "wof:placetype":"venue"
},
  "geometry": {"coordinates":[-87.673343,41.850756],"type":"Point"}
}