{
  "type": "Feature",
  "properties": {
    "iso:country":"US",
    "sg:address":"4628 River rd",
    "sg:city":"Chicago",
    "sg:classifiers":[
        {
            "category":"Autos & Motor Vehicles",
            "subcategory":"Automobile Sales",
            "type":"Retail Goods"
        }
    ],
    "sg:phone":"+1 773 981 5896",
    "sg:postcode":"60686",
    "sg:province":"IL",
    "sg:tags":[
        "limo"
    ],
    "sg:website":"www.limousine-chicago-illinois.c...",
    "wof:name":"Chicago Limo Service",
    "wof:placetype":"venue"
},
  "geometry": {"coordinates":[-87.846625,41.962187],"type":"Point"}
}