{
  "type": "Feature",
  "properties": {
    "iso:country":"US",
    "sg:address":"15618 Co Hwy 5",
    "sg:city":"Atkinson",
    "sg:classifiers":[
        {
            "category":"Professional",
            "subcategory":"Management & Consulting",
            "type":"Services"
        }
    ],
    "sg:phone":"+1 309 936 7130",
    "sg:postcode":"61235",
    "sg:province":"IL",
    "sg:tags":[
        "fuel"
    ],
    "wof:name":"Diehl's Management Support",
    "wof:placetype":"venue"
},
  "geometry": {"coordinates":[-90.020527,41.379235],"type":"Point"}
}