{
  "type": "Feature",
  "properties": {
    "iso:country":"US",
    "sg:address":"1515 W Peru St",
    "sg:city":"Princeton",
    "sg:classifiers":[
        {
            "category":"Retail",
            "subcategory":"Auto Repair",
            "type":"Services"
        }
    ],
    "sg:phone":"+1 815 879 7767",
    "sg:postcode":"61356",
    "sg:province":"IL",
    "sg:tags":[
        "body",
        "shop",
        "painting",
        "automobile"
    ],
    "wof:name":"Heartland Autobody Inc",
    "wof:placetype":"venue"
},
  "geometry": {"coordinates":[-89.484196,41.371653],"type":"Point"}
}