{
  "type": "Feature",
  "properties": {
    "addr:full":"303 N 2nd St Geneva IL 60134",
    "addr:housenumber":"303",
    "addr:postcode":"60134",
    "addr:street":"N 2Nd St",
    "iso:country":"US",
    "sg:address":"303 N 2nd St",
    "sg:city":"Geneva",
    "sg:classifiers":[
        {
            "category":"Arts & Performance",
            "subcategory":"Theater",
            "type":"Entertainment"
        }
    ],
    "sg:phone":"+1 630 262 0392",
    "sg:postcode":"60134",
    "sg:province":"IL",
    "sg:tags":[
        "group"
    ],
    "wof:name":"A Better Sound",
    "wof:placetype":"venue"
},
  "geometry": {"coordinates":[-88.30544399999999,41.891849],"type":"Point"}
}