{
  "type": "Feature",
  "properties": {
    "addr:full":"805 Summit Ave Wauconda IL 60084",
    "addr:housenumber":"805",
    "addr:postcode":"60084",
    "addr:street":"Summit Ave",
    "iso:country":"US",
    "sg:address":"805 Summit Ave",
    "sg:city":"Wauconda",
    "sg:classifiers":[
        {
            "category":"Wholesale",
            "subcategory":"Electrical",
            "type":"Manufacturing & Wholesale Goods"
        }
    ],
    "sg:phone":"+1 847 526 6506",
    "sg:postcode":"60084",
    "sg:province":"IL",
    "sg:tags":[
        "alarm",
        "burglar",
        "system"
    ],
    "wof:name":"HAWC Security Systems",
    "wof:placetype":"venue"
},
  "geometry": {"coordinates":[-88.119551,42.272437],"type":"Point"}
}