{
  "type": "Feature",
  "properties": {
    "iso:country":"US",
    "sg:address":"520 W Boughton Rd",
    "sg:city":"Bolingbrook",
    "sg:classifiers":[
        {
            "category":"Recreation",
            "type":"Entertainment"
        }
    ],
    "sg:phone":"+1 630 378 5800",
    "sg:postcode":"60440",
    "sg:province":"IL",
    "sg:tags":[
        "riding",
        "academy"
    ],
    "wof:name":"Artes Infantiles",
    "wof:placetype":"venue"
},
  "geometry": {"coordinates":[-88.090981,41.70715],"type":"Point"}
}