{
  "type": "Feature",
  "properties": {
    "iso:country":"US",
    "sg:address":"801 SW 9th St",
    "sg:city":"Aledo",
    "sg:classifiers":[
        {
            "category":"Education",
            "subcategory":"School",
            "type":"Public Place"
        }
    ],
    "sg:phone":"+1 309 582 5350",
    "sg:postcode":"61231",
    "sg:province":"IL",
    "wof:name":"Apollo Elementary School",
    "wof:placetype":"venue"
},
  "geometry": {"coordinates":[-90.757588,41.194587],"type":"Point"}
}