{
  "type": "Feature",
  "properties": {
    "iso:country":"US",
    "sg:address":"715 Lake St",
    "sg:city":"Oak Park",
    "sg:classifiers":[
        {
            "category":"Shopping",
            "subcategory":"Optical Goods",
            "type":"Retail Goods"
        }
    ],
    "sg:phone":"+1 708 848 6640",
    "sg:postcode":"60301",
    "sg:province":"IL",
    "sg:tags":[
        "optician"
    ],
    "wof:name":"Eye Glass Shop Inc",
    "wof:placetype":"venue"
},
  "geometry": {"coordinates":[-87.793402,41.888522],"type":"Point"}
}