{
  "type": "Feature",
  "properties": {
    "iso:country":"US",
    "sg:address":"1010 Lake St Ste 109",
    "sg:city":"Oak Park",
    "sg:classifiers":[
        {
            "category":"Health Services",
            "subcategory":"Clinic",
            "type":"Services"
        }
    ],
    "sg:phone":"+1 708 445 8620",
    "sg:postcode":"60301",
    "sg:province":"IL",
    "sg:tags":[
        "counseling",
        "mental"
    ],
    "wof:name":"Davis Charles E PHD PC",
    "wof:placetype":"venue"
},
  "geometry": {"coordinates":[-87.80076099999999,41.888685],"type":"Point"}
}