{
  "type": "Feature",
  "properties": {
    "iso:country":"US",
    "sg:address":"444 Gramercy Dr",
    "sg:city":"Rockford",
    "sg:classifiers":[
        {
            "category":"Real Estate",
            "subcategory":"Real Estate Operator",
            "type":"Services"
        }
    ],
    "sg:phone":"+1 815 398 8553",
    "sg:postcode":"61107",
    "sg:province":"IL",
    "sg:tags":[
        "apartment",
        "complex"
    ],
    "wof:name":"Mulford Park Apartments Inc",
    "wof:placetype":"venue"
},
  "geometry": {"coordinates":[-89.002872,42.272167],"type":"Point"}
}