{
  "type": "Feature",
  "properties": {
    "addr:full":"7 Crestwood Ln Rockford IL 61107",
    "addr:housenumber":"7",
    "addr:postcode":"61107",
    "addr:street":"Crestwood Ln",
    "iso:country":"US",
    "sg:address":"7 Crestwood Ln",
    "sg:city":"Rockford",
    "sg:classifiers":[
        {
            "category":"Health Services",
            "subcategory":"Doctor",
            "type":"Services"
        }
    ],
    "sg:phone":"+1 815 397 1217",
    "sg:postcode":"61107",
    "sg:province":"IL",
    "sg:tags":[
        "physician",
        "surgeon"
    ],
    "wof:name":"Albert W Hudson MD",
    "wof:placetype":"venue"
},
  "geometry": {"coordinates":[-89.05014799999999,42.296182],"type":"Point"}
}