{
  "type": "Feature",
  "properties": {
    "addr:full":"4620 27th St Moline IL 61265",
    "addr:housenumber":"4620",
    "addr:postcode":"61265",
    "addr:street":"27Th St",
    "iso:country":"US",
    "sg:address":"4620 27th St",
    "sg:city":"Moline",
    "sg:classifiers":[
        {
            "category":"Autos & Motor Vehicles",
            "subcategory":"Automobile Sales",
            "type":"Retail Goods"
        }
    ],
    "sg:phone":"+1 309 764 7777",
    "sg:postcode":"61265",
    "sg:province":"IL",
    "sg:tags":[
        "car",
        "used"
    ],
    "wof:name":"South Park Auto Sales",
    "wof:placetype":"venue"
},
  "geometry": {"coordinates":[-90.49903500000001,41.466041],"type":"Point"}
}