{
  "type": "Feature",
  "properties": {
    "iso:country":"US",
    "sg:address":"4620 27th St",
    "sg:city":"Moline",
    "sg:classifiers":[
        {
            "category":"Autos & Motor Vehicles",
            "subcategory":"Automobile Sales",
            "type":"Retail Goods"
        }
    ],
    "sg:phone":"+1 309 764 7777",
    "sg:postcode":"61265",
    "sg:province":"IL",
    "sg:tags":[
        "car",
        "used"
    ],
    "wof:name":"South Park Auto Sales",
    "wof:placetype":"venue"
},
  "geometry": {"coordinates":[-90.499035,41.466041],"type":"Point"}
}