{
  "type": "Feature",
  "properties": {
    "iso:country":"US",
    "sg:address":"480 Arlington Ave",
    "sg:city":"Elgin",
    "sg:classifiers":[
        {
            "category":"Shopping",
            "subcategory":"Florist",
            "type":"Retail Goods"
        }
    ],
    "sg:phone":"+1 847 488 1443",
    "sg:postcode":"60120",
    "sg:province":"IL",
    "wof:name":"Blue Delphinium",
    "wof:placetype":"venue"
},
  "geometry": {"coordinates":[-88.269291,42.027452],"type":"Point"}
}