{
  "type": "Feature",
  "properties": {
    "addr:full":"6215 W 79th St Burbank IL 60459",
    "addr:housenumber":"6215",
    "addr:postcode":"60459",
    "addr:street":"W 79Th St",
    "iso:country":"US",
    "sg:address":"6215 W 79th St",
    "sg:city":"Burbank",
    "sg:classifiers":[
        {
            "category":"Banks & Credit Unions",
            "subcategory":"Financial Services",
            "type":"Services"
        }
    ],
    "sg:phone":"+1 708 741 5170",
    "sg:postcode":"60459",
    "sg:province":"IL",
    "sg:tags":[
        "broker",
        "mortgage"
    ],
    "wof:name":"Sterling Financial Mortgage Corp",
    "wof:placetype":"venue"
},
  "geometry": {"coordinates":[-87.77619900000001,41.748501],"type":"Point"}
}