{
  "type": "Feature",
  "properties": {
    "addr:full":"12131 S Harlem Ave Palos Heights IL 60463",
    "addr:housenumber":"12131",
    "addr:postcode":"60463",
    "addr:street":"S Harlem Ave",
    "iso:country":"US",
    "sg:address":"12131 S Harlem Ave",
    "sg:city":"Palos Heights",
    "sg:classifiers":[
        {
            "category":"Professional",
            "subcategory":"Accounting & Tax Preparation",
            "type":"Services"
        },
        {
            "category":"Banks & Credit Unions",
            "subcategory":"Financial Services",
            "type":"Services"
        }
    ],
    "sg:phone":"+1 708 448 5633",
    "sg:postcode":"60463",
    "sg:province":"IL",
    "sg:tags":[
        "accountant"
    ],
    "wof:name":"Richard J Jakes & Associates Ltd",
    "wof:placetype":"venue"
},
  "geometry": {"coordinates":[-87.796605,41.671076],"type":"Point"}
}