{
  "type": "Feature",
  "properties": {
    "iso:country":"US",
    "sg:address":"4257 W 167th St",
    "sg:city":"Country Club Hills",
    "sg:classifiers":[
        {
            "category":"Restaurant",
            "type":"Food & Drink"
        }
    ],
    "sg:phone":"+1 708 647 6666",
    "sg:postcode":"60478",
    "sg:province":"IL",
    "sg:tags":[
        "traditional",
        "american"
    ],
    "wof:name":"Baby Steak & Lemonade",
    "wof:placetype":"venue"
},
  "geometry": {"coordinates":[-87.72195600000001,41.586111],"type":"Point"}
}