{
  "type": "Feature",
  "properties": {
    "addr:full":"18505 W Creek Dr Tinley Park IL 60477",
    "addr:housenumber":"18505",
    "addr:postcode":"60477",
    "addr:street":"W Creek Dr",
    "iso:country":"US",
    "sg:address":"18505 W Creek Dr",
    "sg:city":"Tinley Park",
    "sg:classifiers":[
        {
            "category":"Building & Trades",
            "subcategory":"Construction",
            "type":"Services"
        }
    ],
    "sg:phone":"+1 708 802 8100",
    "sg:postcode":"60477",
    "sg:province":"IL",
    "sg:tags":[
        "contractor"
    ],
    "wof:name":"Pepper Construction",
    "wof:placetype":"venue"
},
  "geometry": {"coordinates":[-87.80045,41.555204],"type":"Point"}
}