{
  "type": "Feature",
  "properties": {
    "addr:full":"1530 N Grebner Rd Elizabeth IL 61028",
    "addr:housenumber":"1530",
    "addr:postcode":"61028",
    "addr:street":"N Grebner Rd",
    "iso:country":"US",
    "sg:address":"1530 N Grebner Rd",
    "sg:city":"Elizabeth",
    "sg:phone":"+1 815 845 2326",
    "sg:postcode":"61028",
    "sg:province":"IL",
    "sg:tags":[
        "farm",
        "field",
        "corn",
        "crop"
    ],
    "wof:name":"Wurm Farms",
    "wof:placetype":"venue"
},
  "geometry": {"coordinates":[-90.185242,42.372899],"type":"Point"}
}