{
  "type": "Feature",
  "properties": {
    "addr:full":"1721 Sherman Ave Evanston IL 60201",
    "addr:housenumber":"1721",
    "addr:postcode":"60201",
    "addr:street":"Sherman Ave",
    "iso:country":"US",
    "sg:address":"1721 Sherman Ave",
    "sg:city":"Evanston",
    "sg:classifiers":[
        {
            "category":"Personal",
            "subcategory":"Beauty Salon",
            "type":"Services"
        }
    ],
    "sg:phone":"+1 847 864 2655",
    "sg:postcode":"60201",
    "sg:province":"IL",
    "sg:tags":[
        "shop"
    ],
    "wof:name":"Steven Papageorge Hair Salon",
    "wof:placetype":"venue"
},
  "geometry": {"coordinates":[-87.681754,42.048703],"type":"Point"}
}