{
  "type": "Feature",
  "properties": {
    "iso:country":"US",
    "sg:address":"1149 E Golf Rd",
    "sg:city":"Schaumburg",
    "sg:classifiers":[
        {
            "category":"Restaurant",
            "type":"Food & Drink"
        }
    ],
    "sg:menulink":"http://www.allmenus.com/il/schaumburg/21203-dover-straits/menu/",
    "sg:phone":"+1 847 884 3900",
    "sg:postcode":"60173",
    "sg:province":"IL",
    "sg:tags":[
        "american"
    ],
    "wof:name":"Dover Straits",
    "wof:placetype":"venue"
},
  "geometry": {"coordinates":[-88.051743,42.050138],"type":"Point"}
}