{
  "type": "Feature",
  "properties": {
    "addr:full":"7230 W Benton Dr Frankfort IL 60423",
    "addr:housenumber":"7230",
    "addr:postcode":"60423",
    "addr:street":"W Benton Dr",
    "iso:country":"US",
    "sg:address":"7230 W Benton Dr",
    "sg:city":"Frankfort",
    "sg:classifiers":[
        {
            "category":"Shopping",
            "subcategory":"Tobacco",
            "type":"Retail Goods"
        }
    ],
    "sg:phone":"+1 815 469 4646",
    "sg:postcode":"60423",
    "sg:province":"IL",
    "sg:tags":[
        "cigarette",
        "cigar",
        "dealer"
    ],
    "wof:name":"Frankfort Tobacco & Liquor Inc",
    "wof:placetype":"venue"
},
  "geometry": {"coordinates":[-87.79461000000001,41.531433],"type":"Point"}
}