{
  "type": "Feature",
  "properties": {
    "iso:country":"US",
    "sg:address":"305 N Van Nortwick Ave",
    "sg:city":"Batavia",
    "sg:classifiers":[
        {
            "category":"Education",
            "subcategory":"School",
            "type":"Public Place"
        }
    ],
    "sg:phone":"+1 630 879 4637",
    "sg:postcode":"60510",
    "sg:province":"IL",
    "sg:website":"www.bps101.net",
    "wof:name":"H C Storm Elementary School",
    "wof:placetype":"venue"
},
  "geometry": {"coordinates":[-88.321557,41.856172],"type":"Point"}
}