{
  "type": "Feature",
  "properties": {
    "iso:country":"US",
    "sg:address":"5912 Castlewood Trl",
    "sg:city":"Mchenry",
    "sg:classifiers":[
        {
            "category":"Home & Garden",
            "subcategory":"Home Furnishings",
            "type":"Retail Goods"
        }
    ],
    "sg:phone":"+1 815 759 6900",
    "sg:postcode":"60050",
    "sg:province":"IL",
    "sg:tags":[
        "draperies",
        "vertical",
        "blinds-venetian",
        "window",
        "treatment",
        "curtain"
    ],
    "wof:name":"Blind Ambition",
    "wof:placetype":"venue"
},
  "geometry": {"coordinates":[-88.31161400000001,42.332556],"type":"Point"}
}