{
  "type": "Feature",
  "properties": {
    "iso:country":"US",
    "sg:address":"1753 W Chicago Ave",
    "sg:city":"Chicago",
    "sg:classifiers":[
        {
            "category":"Health Services",
            "subcategory":"Dentist",
            "type":"Services"
        }
    ],
    "sg:phone":"+1 312 491 0033",
    "sg:postcode":"60622",
    "sg:province":"IL",
    "wof:name":"Irina Bolotnikov, DDS",
    "wof:placetype":"venue"
},
  "geometry": {"coordinates":[-87.67181100000001,41.895693],"type":"Point"}
}