{
  "type": "Feature",
  "properties": {
    "addr:full":"10921 W Cowser Rd Glasford IL 61533",
    "addr:housenumber":"10921",
    "addr:postcode":"61533",
    "addr:street":"W Cowser Rd",
    "iso:country":"US",
    "sg:address":"10921 W Cowser Rd",
    "sg:city":"Glasford",
    "sg:classifiers":[
        {
            "category":"Farming",
            "subcategory":"Dairy Farm",
            "type":"Manufacturing & Wholesale Goods"
        }
    ],
    "sg:phone":"+1 309 389 4591",
    "sg:postcode":"61533",
    "sg:province":"IL",
    "wof:name":"Borland's Dairy",
    "wof:placetype":"venue"
},
  "geometry": {"coordinates":[-89.75822700000001,40.602208],"type":"Point"}
}