{
  "type": "Feature",
  "properties": {
    "iso:country":"US",
    "sg:address":"221 North LaSalle Ste 1763",
    "sg:city":"Chicago",
    "sg:classifiers":[
        {
            "category":"Professional",
            "subcategory":"Lawyer & Legal Services",
            "type":"Services"
        }
    ],
    "sg:phone":"+1 312 372 6058",
    "sg:postcode":"60601",
    "sg:province":"IL",
    "sg:tags":[
        "divorce",
        "law",
        "family"
    ],
    "wof:name":"Andrew Harger",
    "wof:placetype":"venue"
},
  "geometry": {"coordinates":[-87.632139,41.886438],"type":"Point"}
}