{
  "type": "Feature",
  "properties": {
    "addr:full":"14636 Kedzie Ave Midlothian IL 60445",
    "addr:housenumber":"14636",
    "addr:postcode":"60445",
    "addr:street":"Kedzie Ave",
    "iso:country":"US",
    "sg:address":"14636 Kedzie Ave",
    "sg:city":"Midlothian",
    "sg:classifiers":[
        {
            "category":"Professional",
            "subcategory":"Business Services",
            "type":"Services"
        }
    ],
    "sg:phone":"+1 708 824 1224",
    "sg:postcode":"60445",
    "sg:province":"IL",
    "wof:name":"Tomczak Enterprises",
    "wof:placetype":"venue"
},
  "geometry": {"coordinates":[-87.698441,41.627054],"type":"Point"}
}