{
  "type": "Feature",
  "properties": {
    "addr:full":"3200 Flossmoor Rd Flossmoor IL 60422",
    "addr:housenumber":"3200",
    "addr:postcode":"60422",
    "addr:street":"Flossmoor Rd",
    "iso:country":"US",
    "sg:address":"3200 Flossmoor Rd",
    "sg:city":"Flossmoor",
    "sg:classifiers":[
        {
            "category":"Organizations",
            "subcategory":"Religious Organization",
            "type":"Services"
        }
    ],
    "sg:phone":"+1 708 957 9555",
    "sg:postcode":"60422",
    "sg:province":"IL",
    "sg:tags":[
        "church"
    ],
    "sg:website":"www.thecathedralofjoy.com",
    "wof:name":"Cathedral Of Joy",
    "wof:placetype":"venue"
},
  "geometry": {"coordinates":[-87.695077,41.542518],"type":"Point"}
}