{
  "type": "Feature",
  "properties": {
    "addr:full":"1025 Woodbridge Dr Cary IL 60013",
    "addr:housenumber":"1025",
    "addr:postcode":"60013",
    "addr:street":"Woodbridge Dr",
    "iso:country":"US",
    "sg:address":"1025 Woodbridge Dr",
    "sg:city":"Cary",
    "sg:classifiers":[
        {
            "category":"Professional",
            "subcategory":"Management & Consulting",
            "type":"Services"
        }
    ],
    "sg:phone":"+1 847 639 6907",
    "sg:postcode":"60013",
    "sg:province":"IL",
    "sg:tags":[
        "planning",
        "consultant",
        "space",
        "facility"
    ],
    "wof:name":"Spring Hill Maintainance, Inc",
    "wof:placetype":"venue"
},
  "geometry": {"coordinates":[-88.27407100000001,42.196161],"type":"Point"}
}