{
  "type": "Feature",
  "properties": {
    "iso:country":"US",
    "sg:address":"6309 Woodward Ave",
    "sg:city":"Downers Grove",
    "sg:classifiers":[
        {
            "category":"Retail",
            "subcategory":"Animal Services",
            "type":"Services"
        }
    ],
    "sg:phone":"+1 630 971 0143",
    "sg:postcode":"60516",
    "sg:province":"IL",
    "wof:name":"Artistic Dog & Cat Grooming",
    "wof:placetype":"venue"
},
  "geometry": {"coordinates":[-88.031661,41.771051],"type":"Point"}
}