{
  "type": "Feature",
  "properties": {
    "iso:country":"US",
    "sg:address":"28379 Davis Pkwy",
    "sg:city":"Warrenville",
    "sg:classifiers":[
        {
            "category":"Health Services",
            "subcategory":"Chiropractor",
            "type":"Services"
        }
    ],
    "sg:phone":"+1 630 836 9900",
    "sg:postcode":"60555",
    "sg:province":"IL",
    "sg:tags":[
        "chiropractic"
    ],
    "wof:name":"Getting Healthy Now",
    "wof:placetype":"venue"
},
  "geometry": {"coordinates":[-88.176855,41.800975],"type":"Point"}
}