{
  "type": "Feature",
  "properties": {
    "iso:country":"US",
    "sg:address":"1790 Chris Ct",
    "sg:city":"Deerfield",
    "sg:classifiers":[
        {
            "category":"Professional",
            "subcategory":"Computer Services",
            "type":"Services"
        }
    ],
    "sg:phone":"+1 847 948 7767",
    "sg:postcode":"60015",
    "sg:province":"IL",
    "sg:tags":[
        "design",
        "system"
    ],
    "wof:name":"Decision Technologies Inc",
    "wof:placetype":"venue"
},
  "geometry": {"coordinates":[-87.871898,42.178963],"type":"Point"}
}