{
  "type": "Feature",
  "properties": {
    "iso:country":"US",
    "sg:address":"409 Roxana Ave",
    "sg:city":"South Roxana",
    "sg:classifiers":[
        {
            "category":"Local Transit",
            "type":"Transportation"
        }
    ],
    "sg:phone":"+1 618 462 3313",
    "sg:postcode":"62087",
    "sg:province":"IL",
    "sg:tags":[
        "airport"
    ],
    "wof:name":"Tranzlinx Inc",
    "wof:placetype":"venue"
},
  "geometry": {"coordinates":[-90.064321,38.828179],"type":"Point"}
}