{
  "type": "Feature",
  "properties": {
    "addr:full":"9901 S Saint Louis Ave Evergreen Park IL 60805",
    "addr:housenumber":"9901",
    "addr:postcode":"60805",
    "addr:street":"S Saint Louis Ave",
    "iso:country":"US",
    "sg:address":"9901 S Saint Louis Ave",
    "sg:city":"Evergreen Park",
    "sg:classifiers":[
        {
            "category":"Communications",
            "subcategory":"Film & Video Production",
            "type":"Services"
        }
    ],
    "sg:phone":"+1 708 422 2774",
    "sg:postcode":"60805",
    "sg:province":"IL",
    "sg:tags":[
        "motion",
        "business"
    ],
    "wof:name":"Carroll Productions Inc",
    "wof:placetype":"venue"
},
  "geometry": {"coordinates":[-87.708855,41.711527],"type":"Point"}
}