{
  "type": "Feature",
  "properties": {
    "iso:country":"US",
    "sg:address":"3453 Kirchoff Rd",
    "sg:city":"Rolling Meadows",
    "sg:classifiers":[
        {
            "category":"Personal",
            "subcategory":"Shoe Repair & Shine",
            "type":"Services"
        }
    ],
    "sg:phone":"+1 847 870 7839",
    "sg:postcode":"60008",
    "sg:province":"IL",
    "wof:name":"Rolling Meadows Shoe Repair",
    "wof:placetype":"venue"
},
  "geometry": {"coordinates":[-88.024027,42.0795],"type":"Point"}
}