{
  "type": "Feature",
  "properties": {
    "addr:full":"1421 Division St Morris IL 60450",
    "addr:housenumber":"1421",
    "addr:postcode":"60450",
    "addr:street":"Division St",
    "iso:country":"US",
    "sg:address":"1421 Division St",
    "sg:city":"Morris",
    "sg:classifiers":[
        {
            "category":"Professional",
            "subcategory":"Engineering",
            "type":"Services"
        },
        {
            "category":"Professional",
            "subcategory":"Computer Services",
            "type":"Services"
        }
    ],
    "sg:phone":"+1 815 942 6454",
    "sg:postcode":"60450",
    "sg:province":"IL",
    "sg:tags":[
        "designer",
        "rooms-installation",
        "consultant",
        "integration",
        "system",
        "equipment",
        "engineer"
    ],
    "wof:name":"L & L Larsen Electric Inc",
    "wof:placetype":"venue"
},
  "geometry": {"coordinates":[-88.421989,41.372082],"type":"Point"}
}