{
  "type": "Feature",
  "properties": {
    "addr:full":"3430 N Lake Shore Dr Chicago IL 60657",
    "addr:housenumber":"3430",
    "addr:postcode":"60657",
    "addr:street":"N Lake Shore Dr",
    "iso:country":"US",
    "sg:address":"3430 N Lake Shore Dr",
    "sg:city":"Chicago",
    "sg:classifiers":[
        {
            "category":"Professional",
            "subcategory":"Computer Services",
            "type":"Services"
        }
    ],
    "sg:phone":"+1 773 665 4241",
    "sg:postcode":"60657",
    "sg:province":"IL",
    "sg:tags":[
        "datum"
    ],
    "wof:name":"Dmitriy Sklyar",
    "wof:placetype":"venue"
},
  "geometry": {"coordinates":[-87.64032,41.943669],"type":"Point"}
}