{
  "type": "Feature",
  "properties": {
    "iso:country":"US",
    "sg:address":"9033 Tripp Ave",
    "sg:city":"Skokie",
    "sg:classifiers":[
        {
            "category":"Retail",
            "subcategory":"Portrait Studio",
            "type":"Services"
        }
    ],
    "sg:phone":"+1 847 729 2780",
    "sg:postcode":"60076",
    "sg:province":"IL",
    "sg:tags":[
        "photo"
    ],
    "wof:name":"David Blachman Photography",
    "wof:placetype":"venue"
},
  "geometry": {"coordinates":[-87.733634,42.045606],"type":"Point"}
}