{
  "type": "Feature",
  "properties": {
    "iso:country":"US",
    "sg:address":"263 W Valley View Dr",
    "sg:city":"Banner",
    "sg:classifiers":[
        {
            "category":"Bars & Pubs",
            "type":"Food & Drink"
        }
    ],
    "sg:phone":"+1 309 647 7758",
    "sg:postcode":"61520",
    "sg:province":"IL",
    "wof:name":"Goose Pit",
    "wof:placetype":"venue"
},
  "geometry": {"coordinates":[-89.910523,40.517008],"type":"Point"}
}