{
  "type": "Feature",
  "properties": {
    "iso:country":"US",
    "sg:address":"189 W Northwest Hwy",
    "sg:city":"Palatine",
    "sg:classifiers":[
        {
            "category":"Restaurant",
            "type":"Food & Drink"
        }
    ],
    "sg:phone":"+1   ",
    "sg:postcode":"60067",
    "sg:province":"IL",
    "sg:tags":[
        "eating"
    ],
    "wof:name":"Normas Coffee Corner",
    "wof:placetype":"venue"
},
  "geometry": {"coordinates":[-88.048186,42.122282],"type":"Point"}
}