{
  "type": "Feature",
  "properties": {
    "iso:country":"US",
    "sg:address":"18833 Keeler Ave",
    "sg:city":"Country Club Hls",
    "sg:classifiers":[
        {
            "category":"Insurance",
            "subcategory":"Insurance Agent",
            "type":"Services"
        }
    ],
    "sg:phone":"+1 708 957 8144",
    "sg:postcode":"60478",
    "sg:province":"IL",
    "wof:name":"Bradford & Assoc Insurance",
    "wof:placetype":"venue"
},
  "geometry": {"coordinates":[-87.718033,41.545968],"type":"Point"}
}