{
  "type": "Feature",
  "properties": {
    "iso:country":"US",
    "sg:address":"27W460 Beecher Ave",
    "sg:city":"Winfield",
    "sg:classifiers":[
        {
            "category":"Real Estate",
            "subcategory":"Real Estate Services",
            "type":"Services"
        },
        {
            "category":"Real Estate",
            "subcategory":"Real Estate Agent",
            "type":"Services"
        }
    ],
    "sg:phone":"+1 630 653 8200",
    "sg:postcode":"60190",
    "sg:province":"IL",
    "sg:tags":[
        "buyer",
        "broker"
    ],
    "wof:name":"Cantwell Realty",
    "wof:placetype":"venue"
},
  "geometry": {"coordinates":[-88.159023,41.86911],"type":"Point"}
}