{
  "type": "Feature",
  "properties": {
    "iso:country":"US",
    "sg:address":"179 E Lake Shore Drive",
    "sg:city":"Chicago",
    "sg:classifiers":[
        {
            "category":"Health Services",
            "subcategory":"Health Practitioner",
            "type":"Services"
        }
    ],
    "sg:phone":"+1 312 944 1781",
    "sg:postcode":"60611",
    "sg:province":"IL",
    "sg:tags":[
        "therapy",
        "physical"
    ],
    "wof:name":"Morrison Helen L MD",
    "wof:placetype":"venue"
},
  "geometry": {"coordinates":[-87.623099,41.900937],"type":"Point"}
}