{
  "type": "Feature",
  "properties": {
    "addr:full":"102 S Galena Ave Dixon IL 61021",
    "addr:housenumber":"102",
    "addr:postcode":"61021",
    "addr:street":"S Galena Ave",
    "iso:country":"US",
    "sg:address":"102 S Galena Ave",
    "sg:city":"Dixon",
    "sg:classifiers":[
        {
            "category":"Banks & Credit Unions",
            "subcategory":"Bank",
            "type":"Services"
        }
    ],
    "sg:phone":"+1 815 284 3333",
    "sg:postcode":"61021",
    "sg:province":"IL",
    "wof:name":"Fifth Third Bank",
    "wof:placetype":"venue"
},
  "geometry": {"coordinates":[-89.48260500000001,41.843597],"type":"Point"}
}