{
  "type": "Feature",
  "properties": {
    "iso:country":"US",
    "sg:address":"1325 N Central Avenue",
    "sg:city":"Chicago",
    "sg:classifiers":[
        {
            "category":"Restaurant",
            "type":"Food & Drink"
        }
    ],
    "sg:phone":"+1 773 261 0602",
    "sg:postcode":"60651",
    "sg:province":"IL",
    "wof:name":"Swan's Food & Deli",
    "wof:placetype":"venue"
},
  "geometry": {"coordinates":[-87.765794,41.904755],"type":"Point"}
}