{
  "type": "Feature",
  "properties": {
    "iso:country":"US",
    "sg:address":"904 Glenwood Dr",
    "sg:city":"Morrison",
    "sg:classifiers":[
        {
            "category":"Professional",
            "subcategory":"Business Services",
            "type":"Services"
        }
    ],
    "sg:phone":"+1 815 772 7877",
    "sg:postcode":"61270",
    "sg:province":"IL",
    "wof:name":"Stichter Enterprises Inc",
    "wof:placetype":"venue"
},
  "geometry": {"coordinates":[-89.956271,41.814757],"type":"Point"}
}