{
  "type": "Feature",
  "properties": {
    "addr:full":"1804 Guiles Ave Mendota IL 61342",
    "addr:housenumber":"1804",
    "addr:postcode":"61342",
    "addr:street":"Guiles Ave",
    "iso:country":"US",
    "sg:address":"1804 Guiles Ave",
    "sg:city":"Mendota",
    "sg:classifiers":[
        {
            "category":"Social Services",
            "type":"Services"
        }
    ],
    "sg:phone":"+1 815 539 9548",
    "sg:postcode":"61342",
    "sg:province":"IL",
    "wof:name":"Wic Lasalle County Health Department",
    "wof:placetype":"venue"
},
  "geometry": {"coordinates":[-89.118253,41.559293],"type":"Point"}
}