{
  "type": "Feature",
  "properties": {
    "iso:country":"US",
    "sg:address":"1701 W Monterey Ave",
    "sg:city":"Chicago",
    "sg:classifiers":[
        {
            "category":"Health Services",
            "subcategory":"Doctor",
            "type":"Services"
        }
    ],
    "sg:phone":"+1 773 445 9880",
    "sg:postcode":"60643",
    "sg:province":"IL",
    "sg:tags":[
        "dentist"
    ],
    "wof:name":"Dental Pullman Lab",
    "wof:placetype":"venue"
},
  "geometry": {"coordinates":[-87.665948,41.690491],"type":"Point"}
}