{
  "type": "Feature",
  "properties": {
    "iso:country":"US",
    "sg:address":"22870 E 1800th St",
    "sg:city":"Prairie City",
    "sg:phone":"+1 309 772 2014",
    "sg:postcode":"61470",
    "sg:province":"IL",
    "sg:tags":[
        "farm",
        "corn",
        "soybean"
    ],
    "wof:name":"Chase Farms",
    "wof:placetype":"venue"
},
  "geometry": {"coordinates":[-90.560103,40.602175],"type":"Point"}
}