{
  "type": "Feature",
  "properties": {
    "iso:country":"US",
    "sg:address":"3 E Huron St 3rd Floor",
    "sg:city":"Chicago",
    "sg:classifiers":[
        {
            "category":"Shopping",
            "subcategory":"Antiques",
            "type":"Retail Goods"
        }
    ],
    "sg:phone":"+1 312 981 7000",
    "sg:postcode":"60611",
    "sg:province":"IL",
    "sg:website":"www.oldplankonhuron.com",
    "wof:name":"Old Plank Antiques on Huron",
    "wof:placetype":"venue"
},
  "geometry": {"coordinates":[-87.628015,41.894858],"type":"Point"}
}