{
  "type": "Feature",
  "properties": {
    "iso:country":"US",
    "sg:address":"15514 Dobson Ave",
    "sg:city":"Dolton",
    "sg:classifiers":[
        {
            "category":"Personal",
            "subcategory":"Beauty Salon",
            "type":"Services"
        }
    ],
    "sg:phone":"+1 708 201 0980",
    "sg:postcode":"60419",
    "sg:province":"IL",
    "wof:name":"Glorias Glamour Girl",
    "wof:placetype":"venue"
},
  "geometry": {"coordinates":[-87.59168,41.613313],"type":"Point"}
}