{
  "type": "Feature",
  "properties": {
    "iso:country":"US",
    "sg:address":"8297 Main St",
    "sg:city":"Dixon",
    "sg:classifiers":[
        {
            "category":"Insurance",
            "subcategory":"Insurance Agent",
            "type":"Services"
        }
    ],
    "sg:phone":"+1 815 652 4133",
    "sg:postcode":"61021",
    "sg:province":"IL",
    "wof:name":"Hey Ice Cream",
    "wof:placetype":"venue"
},
  "geometry": {"coordinates":[-89.41557299999999,41.897082],"type":"Point"}
}