{
  "type": "Feature",
  "properties": {
    "iso:country":"US",
    "sg:address":"1647 S Blue Island Ave",
    "sg:city":"Chicago",
    "sg:classifiers":[
        {
            "category":"Professional",
            "subcategory":"Lawyer & Legal Services",
            "type":"Services"
        }
    ],
    "sg:phone":"+1 312 666 2700",
    "sg:postcode":"60608",
    "sg:province":"IL",
    "wof:name":"Quiroz M Dolores Attorney At Law",
    "wof:placetype":"venue"
},
  "geometry": {"coordinates":[-87.660308,41.858386],"type":"Point"}
}