{
  "type": "Feature",
  "properties": {
    "iso:country":"US",
    "sg:address":"7500 S Pulaski Rd",
    "sg:city":"Chicago",
    "sg:classifiers":[
        {
            "category":"Education",
            "subcategory":"Junior College",
            "type":"Public Place"
        }
    ],
    "sg:phone":"+1 773 838 7500",
    "sg:postcode":"60652",
    "sg:province":"IL",
    "sg:tags":[
        "business",
        "association"
    ],
    "wof:name":"Richard J Daley College",
    "wof:placetype":"venue"
},
  "geometry": {"coordinates":[-87.722186,41.755662],"type":"Point"}
}