{
  "type": "Feature",
  "properties": {
    "iso:country":"US",
    "sg:address":"1410 Lawrence Ave",
    "sg:city":"Lockport",
    "sg:classifiers":[
        {
            "category":"Building & Trades",
            "subcategory":"Electrical",
            "type":"Services"
        }
    ],
    "sg:phone":"+1 815 838 6255",
    "sg:postcode":"60441",
    "sg:province":"IL",
    "sg:tags":[
        "electrician",
        "contractor"
    ],
    "wof:name":"Dnm Electric Inc",
    "wof:placetype":"venue"
},
  "geometry": {"coordinates":[-88.05445899999999,41.582431],"type":"Point"}
}