{
  "type": "Feature",
  "properties": {
    "iso:country":"US",
    "sg:address":"124 Ludwig St",
    "sg:city":"Bushnell",
    "sg:classifiers":[
        {
            "category":"Farming",
            "subcategory":"Livestock Farm",
            "type":"Manufacturing & Wholesale Goods"
        }
    ],
    "sg:phone":"+1 309 772 3170",
    "sg:postcode":"61422",
    "sg:province":"IL",
    "sg:website":"http://www.excelmeats.com",
    "wof:name":"Cargill Meat Solutions Corp",
    "wof:placetype":"venue"
},
  "geometry": {"coordinates":[-90.511719,40.547407],"type":"Point"}
}