{
  "type": "Feature",
  "properties": {
    "iso:country":"US",
    "sg:address":"516 W Boughton Rd",
    "sg:city":"Bolingbrook",
    "sg:classifiers":[
        {
            "category":"Insurance",
            "subcategory":"Hazard Insurance",
            "type":"Services"
        },
        {
            "category":"Insurance",
            "subcategory":"Insurance Agent",
            "type":"Services"
        },
        {
            "category":"Insurance",
            "subcategory":"Life Insurance",
            "type":"Services"
        }
    ],
    "sg:phone":"+1 610 692 4425",
    "sg:postcode":"60440",
    "sg:province":"IL",
    "sg:tags":[
        "auto"
    ],
    "sg:website":"http://statefarm.mqgroup.com/url.asp?usr=133512",
    "wof:name":"McCadd, Gerald - State Farm Insurance Agent",
    "wof:placetype":"venue"
},
  "geometry": {"coordinates":[-88.088572,41.70748],"type":"Point"}
}