{
  "type": "Feature",
  "properties": {
    "iso:country":"US",
    "sg:address":"2023 Irving Park Rd",
    "sg:city":"Bartlett",
    "sg:classifiers":[
        {
            "category":"Shopping",
            "subcategory":"Shoes",
            "type":"Retail Goods"
        }
    ],
    "sg:phone":"+1 630 736 2120",
    "sg:postcode":"60133",
    "sg:province":"IL",
    "sg:tags":[
        "wear"
    ],
    "wof:name":"Christian Fashion",
    "wof:placetype":"venue"
},
  "geometry": {"coordinates":[-88.154442,42.00825],"type":"Point"}
}