{
  "type": "Feature",
  "properties": {
    "addr:full":"408 N Lake St Aurora IL 60506",
    "addr:housenumber":"408",
    "addr:postcode":"60506",
    "addr:street":"N Lake St",
    "iso:country":"US",
    "sg:address":"408 N Lake St",
    "sg:city":"Aurora",
    "sg:classifiers":[
        {
            "category":"Insurance",
            "subcategory":"Insurance Agent",
            "type":"Services"
        }
    ],
    "sg:phone":"+1 630 906 6500",
    "sg:postcode":"60506",
    "sg:province":"IL",
    "wof:name":"State Farm Insurance",
    "wof:placetype":"venue"
},
  "geometry": {"coordinates":[-88.31320100000001,41.76581],"type":"Point"}
}