{
  "type": "Feature",
  "properties": {
    "addr:full":"114 W Washington St Pittsfield IL 62363",
    "addr:housenumber":"114",
    "addr:postcode":"62363",
    "addr:street":"W Washington St",
    "iso:country":"US",
    "sg:address":"114 W Washington St",
    "sg:city":"Pittsfield",
    "sg:classifiers":[
        {
            "category":"Personal",
            "subcategory":"Beauty Salon",
            "type":"Services"
        }
    ],
    "sg:phone":"+1 217 285 9777",
    "sg:postcode":"62363",
    "sg:province":"IL",
    "wof:name":"Lox",
    "wof:placetype":"venue"
},
  "geometry": {"coordinates":[-90.806652,39.606857],"type":"Point"}
}