{
  "type": "Feature",
  "properties": {
    "iso:country":"US",
    "sg:address":"843 Co Rd 100 N",
    "sg:city":"Pesotum",
    "sg:phone":"+1 217 867 2552",
    "sg:postcode":"61863",
    "sg:province":"IL",
    "sg:tags":[
        "farm",
        "corn",
        "soybean"
    ],
    "wof:name":"Frank Hartman",
    "wof:placetype":"venue"
},
  "geometry": {"coordinates":[-88.30404,39.893693],"type":"Point"}
}