{
  "type": "Feature",
  "properties": {
    "iso:country":"US",
    "sg:address":"4084 N 1000W Rd",
    "sg:city":"Bourbonnais",
    "sg:classifiers":[
        {
            "category":"Sports & Exercise",
            "subcategory":"Golf",
            "type":"Entertainment"
        }
    ],
    "sg:phone":"+1 815 935 0400",
    "sg:postcode":"60914",
    "sg:province":"IL",
    "sg:tags":[
        "course"
    ],
    "sg:website":"www.bonvivant.com",
    "wof:name":"Bon Vivant Country Club",
    "wof:placetype":"venue"
},
  "geometry": {"coordinates":[-87.894919,41.176555],"type":"Point"}
}