{
  "type": "Feature",
  "properties": {
    "iso:country":"US",
    "sg:address":"1208 Nashua Ln",
    "sg:city":"Bartlett",
    "sg:classifiers":[
        {
            "category":"Professional",
            "type":"Services"
        }
    ],
    "sg:phone":"+1 630 289 7018",
    "sg:postcode":"60133",
    "sg:province":"IL",
    "wof:name":"Hell Creek Creations",
    "wof:placetype":"venue"
},
  "geometry": {"coordinates":[-88.134016,41.969337],"type":"Point"}
}