{
  "type": "Feature",
  "properties": {
    "iso:country":"US",
    "sg:address":"558 3rd St",
    "sg:city":"La Salle",
    "sg:classifiers":[
        {
            "category":"Professional",
            "type":"Services"
        }
    ],
    "sg:phone":"+1 815 223 1708",
    "sg:postcode":"61301",
    "sg:province":"IL",
    "wof:name":"Bill E Mecum",
    "wof:placetype":"venue"
},
  "geometry": {"coordinates":[-89.097818,41.330044],"type":"Point"}
}