{
  "type": "Feature",
  "properties": {
    "iso:country":"US",
    "sg:address":"9291 Bryn Mawr Ave",
    "sg:city":"Rosemont",
    "sg:classifiers":[
        {
            "category":"Manufacturing",
            "subcategory":"Printing",
            "type":"Manufacturing & Wholesale Goods"
        }
    ],
    "sg:phone":"+1 847 696 0123",
    "sg:postcode":"60018",
    "sg:province":"IL",
    "sg:tags":[
        "hot",
        "stamping",
        "gold"
    ],
    "wof:name":"Comet Labels",
    "wof:placetype":"venue"
},
  "geometry": {"coordinates":[-87.860673,41.980544],"type":"Point"}
}