{
  "type": "Feature",
  "properties": {
    "iso:country":"US",
    "sg:address":"5710 Shattuck Rd",
    "sg:city":"Belvidere",
    "sg:classifiers":[
        {
            "category":"Travel",
            "subcategory":"Hotels & Motels",
            "type":"Entertainment"
        }
    ],
    "sg:phone":"+1 815 547 5517",
    "sg:postcode":"61008",
    "sg:province":"IL",
    "sg:tags":[
        "operation"
    ],
    "wof:name":"Outworld World Pine Country",
    "wof:placetype":"venue"
},
  "geometry": {"coordinates":[-88.778603,42.238443],"type":"Point"}
}