{
  "type": "Feature",
  "properties": {
    "iso:country":"US",
    "sg:address":"7525 N Oak Park Ave",
    "sg:city":"Niles",
    "sg:classifiers":[
        {
            "category":"Manufacturing",
            "subcategory":"Tools & Machinery",
            "type":"Manufacturing & Wholesale Goods"
        },
        {
            "category":"Wholesale",
            "subcategory":"Machinery & Supplies",
            "type":"Manufacturing & Wholesale Goods"
        }
    ],
    "sg:phone":"+1 800 447 4248",
    "sg:postcode":"60714",
    "sg:province":"IL",
    "sg:tags":[
        "abrasives-wholesale",
        "abrasive",
        "industrial",
        "manufacturer",
        "equipment"
    ],
    "sg:website":"http://www.cgwcamel.com",
    "wof:name":"Camel Grinding Wheels",
    "wof:placetype":"venue"
},
  "geometry": {"coordinates":[-87.794113,42.015571],"type":"Point"}
}