{
  "type": "Feature",
  "properties": {
    "addr:full":"560 W 144th St Riverdale IL 60827",
    "addr:housenumber":"560",
    "addr:postcode":"60827",
    "addr:street":"W 144Th St",
    "iso:country":"US",
    "sg:address":"560 W 144th St",
    "sg:city":"Riverdale",
    "sg:classifiers":[
        {
            "category":"Education",
            "subcategory":"School",
            "type":"Public Place"
        }
    ],
    "sg:phone":"+1 708 849 7153",
    "sg:postcode":"60827",
    "sg:province":"IL",
    "wof:name":"Dolton Riverdal S D 148-Jefferson School",
    "wof:placetype":"venue"
},
  "geometry": {"coordinates":[-87.635902,41.6334],"type":"Point"}
}