{
  "type": "Feature",
  "properties": {
    "iso:country":"US",
    "sg:address":"1017 W Webster Ave",
    "sg:city":"Chicago",
    "sg:classifiers":[
        {
            "category":"Real Estate",
            "subcategory":"Architect",
            "type":"Services"
        }
    ],
    "sg:phone":"+1 773 935 3011",
    "sg:postcode":"60614",
    "sg:province":"IL",
    "wof:name":"Mayer Jeffers Gillespie Architects",
    "wof:placetype":"venue"
},
  "geometry": {"coordinates":[-87.65419799999999,41.9216],"type":"Point"}
}