{
  "type": "Feature",
  "properties": {
    "iso:country":"US",
    "sg:address":"1216 N Sheridan Rd",
    "sg:city":"Lake Forest",
    "sg:classifiers":[
        {
            "category":"Banks & Credit Unions",
            "subcategory":"Financial Services",
            "type":"Services"
        }
    ],
    "sg:phone":"+1 847 234 4520",
    "sg:postcode":"60045",
    "sg:province":"IL",
    "sg:tags":[
        "trust",
        "nonprofit",
        "management"
    ],
    "wof:name":"John C Bjork Family Foundation",
    "wof:placetype":"venue"
},
  "geometry": {"coordinates":[-87.835053,42.262553],"type":"Point"}
}