{
  "type": "Feature",
  "properties": {
    "iso:country":"US",
    "sg:address":"2170 Pearl St",
    "sg:city":"Belvidere",
    "sg:phone":"+1 815 547 5461",
    "sg:postcode":"61008",
    "sg:province":"IL",
    "wof:name":"Pocock, David G, Md - F W Shappert Primary Care Clnc",
    "wof:placetype":"venue"
},
  "geometry": {"coordinates":[-88.841722,42.23739],"type":"Point"}
}