{
  "type": "Feature",
  "properties": {
    "iso:country":"US",
    "sg:address":"1823 N Wilmot Ave",
    "sg:city":"Chicago",
    "sg:classifiers":[
        {
            "category":"Professional",
            "type":"Services"
        },
        {
            "category":"Shopping",
            "subcategory":"Clothing, Apparel, & Fashions",
            "type":"Retail Goods"
        }
    ],
    "sg:phone":"+1 773 489 1600",
    "sg:postcode":"60647",
    "sg:province":"IL",
    "sg:tags":[
        "establishment"
    ],
    "wof:name":"Frank Luizza & Associates",
    "wof:placetype":"venue"
},
  "geometry": {"coordinates":[-87.68248800000001,41.914739],"type":"Point"}
}