{
  "type": "Feature",
  "properties": {
    "addr:full":"11229 W 143rd St Orland Park IL 60467",
    "addr:housenumber":"11229",
    "addr:postcode":"60467",
    "addr:street":"W 143Rd St",
    "iso:country":"US",
    "sg:address":"11229 W 143rd St",
    "sg:city":"Orland Park",
    "sg:classifiers":[
        {
            "category":"Cinema",
            "subcategory":"Movie Rental",
            "type":"Entertainment"
        }
    ],
    "sg:phone":"+1 708 349 0178",
    "sg:postcode":"60467",
    "sg:province":"IL",
    "sg:tags":[
        "leasing",
        "video",
        "disc",
        "tape"
    ],
    "wof:name":"Blockbuster Video",
    "wof:placetype":"venue"
},
  "geometry": {"coordinates":[-87.89537199999999,41.629715],"type":"Point"}
}