{
  "type": "Feature",
  "properties": {
    "addr:full":"6105 Byron St Des Plaines IL 60018",
    "addr:housenumber":"6105",
    "addr:postcode":"60018",
    "addr:street":"Byron St",
    "iso:country":"US",
    "sg:address":"6105 Byron St",
    "sg:city":"Des Plaines",
    "sg:classifiers":[
        {
            "category":"Organizations",
            "subcategory":"Political Organization",
            "type":"Services"
        }
    ],
    "sg:phone":"+1 847 698 0347",
    "sg:postcode":"60018",
    "sg:province":"IL",
    "sg:tags":[
        "public",
        "relations"
    ],
    "wof:name":"Leyden Register The",
    "wof:placetype":"venue"
},
  "geometry": {"coordinates":[-87.873324,41.991512],"type":"Point"}
}