{
  "type": "Feature",
  "properties": {
    "iso:country":"US",
    "sg:address":"3 S Wabash Ave",
    "sg:city":"Chicago",
    "sg:classifiers":[
        {
            "category":"Shopping",
            "subcategory":"Jewelry",
            "type":"Retail Goods"
        }
    ],
    "sg:phone":"+1 312 609 1111",
    "sg:postcode":"60603",
    "sg:province":"IL",
    "sg:website":"mygoldendream.com",
    "wof:name":"Golden Dream Jewelers",
    "wof:placetype":"venue"
},
  "geometry": {"coordinates":[-87.62609500000001,41.881863],"type":"Point"}
}