{
  "type": "Feature",
  "properties": {
    "addr:full":"15833 S La Grange Rd Orland Park IL 60462",
    "addr:housenumber":"15833",
    "addr:postcode":"60462",
    "addr:street":"S La Grange Rd",
    "iso:country":"US",
    "sg:address":"15833 S La Grange Rd",
    "sg:city":"Orland Park",
    "sg:classifiers":[
        {
            "category":"Coffee & Tea",
            "type":"Food & Drink"
        }
    ],
    "sg:menulink":"http://www.allmenus.com/il/orland/112579-starbucks-coffee/menu/",
    "sg:phone":"+1 708 873 7960",
    "sg:postcode":"60462",
    "sg:province":"IL",
    "sg:tags":[
        "american"
    ],
    "wof:name":"Starbucks Coffee",
    "wof:placetype":"venue"
},
  "geometry": {"coordinates":[-87.85286000000001,41.603531],"type":"Point"}
}