{
  "type": "Feature",
  "properties": {
    "addr:full":"711 Ogden Ave Lisle IL 60532",
    "addr:housenumber":"711",
    "addr:postcode":"60532",
    "addr:street":"Ogden Ave",
    "iso:country":"US",
    "sg:address":"711 Ogden Ave",
    "sg:city":"Lisle",
    "sg:classifiers":[
        {
            "category":"Manufacturing",
            "subcategory":"Paper Products",
            "type":"Manufacturing & Wholesale Goods"
        }
    ],
    "sg:phone":"+1 630 285 1500",
    "sg:postcode":"60532",
    "sg:province":"IL",
    "sg:tags":[
        "machine",
        "cutting",
        "drilling"
    ],
    "sg:website":"http://www.formtekinc.com",
    "wof:name":"Formtek Inc",
    "wof:placetype":"venue"
},
  "geometry": {"coordinates":[-88.064319,41.802315],"type":"Point"}
}