{
  "type": "Feature",
  "properties": {
    "addr:full":"5120 Spooner Dr Rockford IL 61103",
    "addr:housenumber":"5120",
    "addr:postcode":"61103",
    "addr:street":"Spooner Dr",
    "iso:country":"US",
    "sg:address":"5120 Spooner Dr",
    "sg:city":"Rockford",
    "sg:classifiers":[
        {
            "category":"Restaurant",
            "type":"Food & Drink"
        }
    ],
    "sg:phone":"+1 815 636 0311",
    "sg:postcode":"61103",
    "sg:province":"IL",
    "wof:name":"Roy's North Shore Inn",
    "wof:placetype":"venue"
},
  "geometry": {"coordinates":[-89.07647,42.332867],"type":"Point"}
}