{
  "type": "Feature",
  "properties": {
    "iso:country":"US",
    "sg:address":"3333 W Deyoung St",
    "sg:city":"Marion",
    "sg:classifiers":[
        {
            "category":"Shopping",
            "subcategory":"Gifts & Souvenirs",
            "type":"Retail Goods"
        }
    ],
    "sg:phone":"+1 618 998 7481",
    "sg:postcode":"62959",
    "sg:province":"IL",
    "sg:tags":[
        "shop"
    ],
    "wof:name":"Hrmc Gift Shop",
    "wof:placetype":"venue"
},
  "geometry": {"coordinates":[-88.99338899999999,37.744911],"type":"Point"}
}