{
  "type": "Feature",
  "properties": {
    "addr:full":"2148 N Halsted Street Chicago IL 60614",
    "addr:housenumber":"2148",
    "addr:postcode":"60614",
    "addr:street":"N Halsted Street",
    "iso:country":"US",
    "sg:address":"2148 N Halsted Street",
    "sg:city":"Chicago",
    "sg:classifiers":[
        {
            "category":"Shopping",
            "subcategory":"Clothing, Apparel, & Fashions",
            "type":"Retail Goods"
        },
        {
            "category":"Sports & Exercise",
            "subcategory":"Bicycle Rental",
            "type":"Entertainment"
        }
    ],
    "sg:phone":"+1 773 404 1593",
    "sg:postcode":"60614",
    "sg:province":"IL",
    "sg:tags":[
        "accessory",
        "clothing",
        "wear",
        "women's"
    ],
    "sg:website":"www.londomondo.com",
    "wof:name":"Mondo Mondo",
    "wof:placetype":"venue"
},
  "geometry": {"coordinates":[-87.648629,41.921534],"type":"Point"}
}