{
  "type": "Feature",
  "properties": {
    "addr:full":"75 Old Farm Ct Lindenhurst IL 60046",
    "addr:housenumber":"75",
    "addr:postcode":"60046",
    "addr:street":"Old Farm Ct",
    "iso:country":"US",
    "sg:address":"75 Old Farm Ct",
    "sg:city":"Lindenhurst",
    "sg:classifiers":[
        {
            "category":"Shopping",
            "subcategory":"Bicycles & Sporting Goods",
            "type":"Retail Goods"
        }
    ],
    "sg:phone":"+1 847 356 2341",
    "sg:postcode":"60046",
    "sg:province":"IL",
    "sg:tags":[
        "equipment",
        "exercise"
    ],
    "wof:name":"Free Motion Fitness",
    "wof:placetype":"venue"
},
  "geometry": {"coordinates":[-88.007339,42.416417],"type":"Point"}
}