{
  "type": "Feature",
  "properties": {
    "iso:country":"US",
    "sg:address":"875 N Michigan Ave",
    "sg:city":"Chicago",
    "sg:classifiers":[
        {
            "category":"Professional",
            "type":"Services"
        }
    ],
    "sg:phone":"+1 312 944 2555",
    "sg:postcode":"60611",
    "sg:province":"IL",
    "sg:website":"www.awres.com",
    "wof:name":"Adler-Weiner Research Co",
    "wof:placetype":"venue"
},
  "geometry": {"coordinates":[-87.62400100000001,41.898499],"type":"Point"}
}