{
  "type": "Feature",
  "properties": {
    "iso:country":"US",
    "sg:address":"2513 Park Pl",
    "sg:city":"Evanston",
    "sg:classifiers":[
        {
            "category":"Health Services",
            "subcategory":"Doctor",
            "type":"Services"
        }
    ],
    "sg:phone":"+1 847 328 8480",
    "sg:postcode":"60201",
    "sg:province":"IL",
    "sg:tags":[
        "medical",
        "osteopathic"
    ],
    "wof:name":"Daniel Yamshom Do SC",
    "wof:placetype":"venue"
},
  "geometry": {"coordinates":[-87.710537,42.066782],"type":"Point"}
}