{
  "type": "Feature",
  "properties": {
    "addr:full":"833 Midway Rd Northbrook IL 60062",
    "addr:housenumber":"833",
    "addr:postcode":"60062",
    "addr:street":"Midway Rd",
    "iso:country":"US",
    "sg:address":"833 Midway Rd",
    "sg:city":"Northbrook",
    "sg:classifiers":[
        {
            "category":"Mining & Drilling",
            "type":"Manufacturing & Wholesale Goods"
        }
    ],
    "sg:phone":"+1 847 272 4412",
    "sg:postcode":"60062",
    "sg:province":"IL",
    "sg:tags":[
        "field"
    ],
    "wof:name":"Miris Inc",
    "wof:placetype":"venue"
},
  "geometry": {"coordinates":[-87.796496,42.136624],"type":"Point"}
}