{
  "type": "Feature",
  "properties": {
    "iso:country":"US",
    "sg:address":"940 Lee St",
    "sg:city":"Des Plaines",
    "sg:classifiers":[
        {
            "category":"Health Services",
            "subcategory":"Optometrist",
            "type":"Services"
        }
    ],
    "sg:phone":"+1 847 824 3417",
    "sg:postcode":"60016",
    "sg:province":"IL",
    "wof:name":"Vision Center",
    "wof:placetype":"venue"
},
  "geometry": {"coordinates":[-87.89149399999999,42.036973],"type":"Point"}
}