{
  "type": "Feature",
  "properties": {
    "addr:full":"2620 Lake Lucerne Dr Belleville IL 62221",
    "addr:housenumber":"2620",
    "addr:postcode":"62221",
    "addr:street":"Lake Lucerne Dr",
    "iso:country":"US",
    "sg:address":"2620 Lake Lucerne Dr",
    "sg:city":"Belleville",
    "sg:classifiers":[
        {
            "category":"Wholesale",
            "subcategory":"Vending Machines",
            "type":"Manufacturing & Wholesale Goods"
        }
    ],
    "sg:phone":"+1 618 624 5688",
    "sg:postcode":"62221",
    "sg:province":"IL",
    "wof:name":"Jz Vending Co",
    "wof:placetype":"venue"
},
  "geometry": {"coordinates":[-89.93598900000001,38.563412],"type":"Point"}
}