{
  "type": "Feature",
  "properties": {
    "addr:full":"209 W Pointe Dr Ste A Swansea IL 62226",
    "addr:housenumber":"209",
    "addr:postcode":"62226",
    "addr:street":"W Pointe Dr Ste A",
    "iso:country":"US",
    "sg:address":"209 W Pointe Dr Ste A",
    "sg:city":"Swansea",
    "sg:classifiers":[
        {
            "category":"Building & Trades",
            "subcategory":"Plumbing",
            "type":"Services"
        }
    ],
    "sg:phone":"+1 618 236 9100",
    "sg:postcode":"62226",
    "sg:province":"IL",
    "wof:name":"Great Southwestern Illinois Association of Phcc",
    "wof:placetype":"venue"
},
  "geometry": {"coordinates":[-89.985694,38.565171],"type":"Point"}
}