{
  "type": "Feature",
  "properties": {
    "addr:full":"6415 N Hamilton Ave Chicago IL 60645",
    "addr:housenumber":"6415",
    "addr:postcode":"60645",
    "addr:street":"N Hamilton Ave",
    "iso:country":"US",
    "sg:address":"6415 N Hamilton Ave",
    "sg:city":"Chicago",
    "sg:classifiers":[
        {
            "category":"Local Transit",
            "type":"Transportation"
        }
    ],
    "sg:phone":"+1 773 761 7881",
    "sg:postcode":"60645",
    "sg:province":"IL",
    "sg:tags":[
        "limousine"
    ],
    "wof:name":"First Chicago Limousine Svc",
    "wof:placetype":"venue"
},
  "geometry": {"coordinates":[-87.683723,41.997954],"type":"Point"}
}