{
  "type": "Feature",
  "properties": {
    "iso:country":"US",
    "sg:address":"1312 9th St",
    "sg:city":"Beloit",
    "sg:classifiers":[
        {
            "category":"Building & Trades",
            "subcategory":"Cleaning & Sanitation",
            "type":"Services"
        }
    ],
    "sg:phone":"+1 608 363 9603",
    "sg:postcode":"53511",
    "sg:province":"IL",
    "sg:tags":[
        "maintenance"
    ],
    "wof:name":"Service Cleaning Vics",
    "wof:placetype":"venue"
},
  "geometry": {"coordinates":[-89.048269,42.515762],"type":"Point"}
}