{
  "type": "Feature",
  "properties": {
    "iso:country":"US",
    "sg:address":"4562 E Golike Ln",
    "sg:city":"Bethalto",
    "sg:classifiers":[
        {
            "category":"Wholesale",
            "subcategory":"Construction Materials",
            "type":"Manufacturing & Wholesale Goods"
        }
    ],
    "sg:phone":"+1 618 377 5485",
    "sg:postcode":"62010",
    "sg:province":"IL",
    "sg:tags":[
        "fence"
    ],
    "wof:name":"Williams Fence & Deck",
    "wof:placetype":"venue"
},
  "geometry": {"coordinates":[-90.044361,38.953087],"type":"Point"}
}