{
  "type": "Feature",
  "properties": {
    "iso:country":"US",
    "sg:address":"701 E Walnut St",
    "sg:city":"Carrier Mills",
    "sg:classifiers":[
        {
            "category":"Building & Trades",
            "subcategory":"Construction",
            "type":"Services"
        }
    ],
    "sg:phone":"+1 618 994 2682",
    "sg:postcode":"62917",
    "sg:province":"IL",
    "sg:tags":[
        "residential"
    ],
    "wof:name":"C & H Construction",
    "wof:placetype":"venue"
},
  "geometry": {"coordinates":[-88.61904199999999,37.684922],"type":"Point"}
}