{
  "type": "Feature",
  "properties": {
    "addr:full":"10201 Belle Plaine Ave Schiller Park IL 60176",
    "addr:housenumber":"10201",
    "addr:postcode":"60176",
    "addr:street":"Belle Plaine Ave",
    "iso:country":"US",
    "sg:address":"10201 Belle Plaine Ave",
    "sg:city":"Schiller Park",
    "sg:classifiers":[
        {
            "category":"Bakery",
            "type":"Food & Drink"
        }
    ],
    "sg:menulink":"http://www.allmenus.com/il/leyden/219904-auntie-annes-pretzels/menu/",
    "sg:phone":"+1 847 671 6550",
    "sg:postcode":"60176",
    "sg:province":"IL",
    "sg:tags":[
        "american",
        "pastry"
    ],
    "wof:name":"Auntie Anne's Pretzels",
    "wof:placetype":"venue"
},
  "geometry": {"coordinates":[-87.883173,41.952724],"type":"Point"}
}