{
  "type": "Feature",
  "properties": {
    "iso:country":"US",
    "sg:address":"3306 Vfw Ln",
    "sg:city":"Collinsville",
    "sg:classifiers":[
        {
            "category":"Wholesale",
            "subcategory":"Scrap",
            "type":"Manufacturing & Wholesale Goods"
        }
    ],
    "sg:phone":"+1 618 344 4088",
    "sg:postcode":"62234",
    "sg:province":"IL",
    "sg:tags":[
        "metal",
        "iron"
    ],
    "wof:name":"Temple Metals",
    "wof:placetype":"venue"
},
  "geometry": {"coordinates":[-90.045976,38.664137],"type":"Point"}
}