{
  "type": "Feature",
  "properties": {
    "iso:country":"US",
    "sg:address":"456 N Oakley Blvd",
    "sg:city":"Chicago",
    "sg:classifiers":[
        {
            "category":"Building & Trades",
            "subcategory":"Cleaning & Sanitation",
            "type":"Services"
        }
    ],
    "sg:phone":"+1 847 860 2800",
    "sg:postcode":"60612",
    "sg:province":"IL",
    "sg:tags":[
        "janitorial"
    ],
    "sg:website":"http://www.midwaybuildingservices.com",
    "wof:name":"Midway Building Services Ltd",
    "wof:placetype":"venue"
},
  "geometry": {"coordinates":[-87.68424,41.890227],"type":"Point"}
}