{
  "type": "Feature",
  "properties": {
    "iso:country":"US",
    "sg:address":"4596 Coulters Mill Rd",
    "sg:city":"Oakley",
    "sg:classifiers":[
        {
            "category":"Building & Trades",
            "subcategory":"Landscaping Services",
            "type":"Services"
        }
    ],
    "sg:phone":"+1 217 763 6678",
    "sg:postcode":"62501",
    "sg:province":"IL",
    "sg:tags":[
        "tree"
    ],
    "wof:name":"Tree Works Co Inc",
    "wof:placetype":"venue"
},
  "geometry": {"coordinates":[-88.831864,39.909309],"type":"Point"}
}