{
  "type": "Feature",
  "properties": {
    "iso:country":"US",
    "sg:address":"1642 W 47th St",
    "sg:city":"Chicago",
    "sg:classifiers":[
        {
            "category":"Travel",
            "subcategory":"Travel Agent",
            "type":"Entertainment"
        }
    ],
    "sg:phone":"+1 773 376 7440",
    "sg:postcode":"60609",
    "sg:province":"IL",
    "sg:tags":[
        "agency",
        "services-commercial"
    ],
    "wof:name":"Cadena Mexicana De Viajes",
    "wof:placetype":"venue"
},
  "geometry": {"coordinates":[-87.66640599999999,41.808586],"type":"Point"}
}