{
  "type": "Feature",
  "properties": {
    "iso:country":"US",
    "sg:address":"1103 Co Rd 1450 E",
    "sg:city":"Toledo",
    "sg:classifiers":[
        {
            "category":"Real Estate",
            "subcategory":"Real Estate Operator",
            "type":"Services"
        }
    ],
    "sg:phone":"+1 217 849 2791",
    "sg:postcode":"62468",
    "sg:province":"IL",
    "sg:tags":[
        "property",
        "lessor"
    ],
    "wof:name":"Greeson Golden & Mary",
    "wof:placetype":"venue"
},
  "geometry": {"coordinates":[-88.204915,39.343191],"type":"Point"}
}