{
  "type": "Feature",
  "properties": {
    "addr:full":"1037 S Prospect Ave Park Ridge IL 60068",
    "addr:housenumber":"1037",
    "addr:postcode":"60068",
    "addr:street":"S Prospect Ave",
    "iso:country":"US",
    "sg:address":"1037 S Prospect Ave",
    "sg:city":"Park Ridge",
    "sg:classifiers":[
        {
            "category":"Shopping",
            "subcategory":"Gifts & Souvenirs",
            "type":"Retail Goods"
        }
    ],
    "sg:phone":"+1 847 698 3273",
    "sg:postcode":"60068",
    "sg:province":"IL",
    "sg:tags":[
        "basket",
        "parcel"
    ],
    "wof:name":"Basket Tree Inc",
    "wof:placetype":"venue"
},
  "geometry": {"coordinates":[-87.832735,41.998805],"type":"Point"}
}