{
  "type": "Feature",
  "properties": {
    "addr:full":"313 W Chestnut St Chicago IL 60610",
    "addr:housenumber":"313",
    "addr:postcode":"60610",
    "addr:street":"W Chestnut St",
    "iso:country":"US",
    "sg:address":"313 W Chestnut St",
    "sg:city":"Chicago",
    "sg:classifiers":[
        {
            "category":"Manufacturing",
            "subcategory":"Tools & Machinery",
            "type":"Manufacturing & Wholesale Goods"
        },
        {
            "category":"Manufacturing",
            "subcategory":"Metals",
            "type":"Manufacturing & Wholesale Goods"
        }
    ],
    "sg:phone":"+1 312 337 2177",
    "sg:postcode":"60610",
    "sg:province":"IL",
    "sg:tags":[
        "die",
        "stamping",
        "maker"
    ],
    "wof:name":"General Machine & Tool Works Inc",
    "wof:placetype":"venue"
},
  "geometry": {"coordinates":[-87.636438,41.898175],"type":"Point"}
}