{
  "type": "Feature",
  "properties": {
    "iso:country":"US",
    "sg:address":"701 W Industrial Park Rd",
    "sg:city":"Carbondale",
    "sg:classifiers":[
        {
            "category":"Building & Trades",
            "subcategory":"Cleaning & Sanitation",
            "type":"Services"
        }
    ],
    "sg:phone":"+1 618 529 3020",
    "sg:postcode":"62901",
    "sg:province":"IL",
    "sg:tags":[
        "janitor"
    ],
    "wof:name":"Bionic Broom Svc",
    "wof:placetype":"venue"
},
  "geometry": {"coordinates":[-89.22367800000001,37.747375],"type":"Point"}
}