{
  "type": "Feature",
  "properties": {
    "addr:full":"2400 W Dayfield Dr Minooka IL 60447",
    "addr:housenumber":"2400",
    "addr:postcode":"60447",
    "addr:street":"W Dayfield",
    "iso:country":"US",
    "sg:address":"2400 W Dayfield Dr",
    "sg:city":"Minooka",
    "sg:classifiers":[
        {
            "category":"Banks & Credit Unions",
            "subcategory":"Bank",
            "type":"Services"
        }
    ],
    "sg:phone":"+1 815 467 5321",
    "sg:postcode":"60447",
    "sg:province":"IL",
    "wof:name":"Founders Bank",
    "wof:placetype":"venue"
},
  "geometry": {"coordinates":[-88.265198,41.4552],"type":"Point"}
}