{
  "type": "Feature",
  "properties": {
    "iso:country":"US",
    "sg:address":"1n340 Prairie Ave",
    "sg:city":"Glen Ellyn",
    "sg:classifiers":[
        {
            "category":"Building & Trades",
            "subcategory":"Plumbing",
            "type":"Services"
        }
    ],
    "sg:phone":"+1 630 698 0777",
    "sg:postcode":"60137",
    "sg:province":"IL",
    "sg:website":"www.johnoconnellplumbing.com/",
    "wof:name":"John O Connell Plumbing Inc.",
    "wof:placetype":"venue"
},
  "geometry": {"coordinates":[-88.071144,41.894531],"type":"Point"}
}