{
  "type": "Feature",
  "properties": {
    "iso:country":"US",
    "sg:address":"500 S Madison St",
    "sg:city":"Carthage",
    "sg:classifiers":[
        {
            "category":"Building & Trades",
            "subcategory":"Construction",
            "type":"Services"
        }
    ],
    "sg:phone":"+1 217 357 2042",
    "sg:postcode":"62321",
    "sg:province":"IL",
    "sg:tags":[
        "house",
        "general",
        "contractor"
    ],
    "wof:name":"Wear Construction & Electrical",
    "wof:placetype":"venue"
},
  "geometry": {"coordinates":[-91.136425,40.406735],"type":"Point"}
}