{
  "type": "Feature",
  "properties": {
    "addr:full":"416 W Clinton St Rushville IL 62681",
    "addr:housenumber":"416",
    "addr:postcode":"62681",
    "addr:street":"W Clinton St",
    "iso:country":"US",
    "sg:address":"416 W Clinton St",
    "sg:city":"Rushville",
    "sg:classifiers":[
        {
            "category":"Restaurant",
            "type":"Food & Drink"
        }
    ],
    "sg:phone":"+1 217 322 6297",
    "sg:postcode":"62681",
    "sg:province":"IL",
    "sg:tags":[
        "pizza"
    ],
    "sg:website":"www.pizzaunlimited.com",
    "wof:name":"Pizza Unlimited",
    "wof:placetype":"venue"
},
  "geometry": {"coordinates":[-90.56585200000001,40.117565],"type":"Point"}
}