{
  "type": "Feature",
  "properties": {
    "addr:full":"6901 North Ave Oak Park IL 60302",
    "addr:housenumber":"6901",
    "addr:postcode":"60302",
    "addr:street":"North Ave",
    "iso:country":"US",
    "sg:address":"6901 North Ave",
    "sg:city":"Oak Park",
    "sg:classifiers":[
        {
            "category":"Insurance",
            "subcategory":"Insurance Agent",
            "type":"Services"
        }
    ],
    "sg:phone":"+1 708 848 0200",
    "sg:postcode":"60302",
    "sg:province":"IL",
    "wof:name":"Allstate Insurance",
    "wof:placetype":"venue"
},
  "geometry": {"coordinates":[-87.79845,41.908977],"type":"Point"}
}