{
  "type": "Feature",
  "properties": {
    "addr:full":"215 Lincoln Mall Dr Matteson IL 60443",
    "addr:housenumber":"215",
    "addr:postcode":"60443",
    "addr:street":"Lincoln Mall Dr",
    "iso:country":"US",
    "sg:address":"215 Lincoln Mall Dr",
    "sg:city":"Matteson",
    "sg:classifiers":[
        {
            "category":"Shopping",
            "subcategory":"Clothing, Apparel, & Fashions",
            "type":"Retail Goods"
        }
    ],
    "sg:phone":"+1   ",
    "sg:postcode":"60443",
    "sg:province":"IL",
    "wof:name":"Vanity 144",
    "wof:placetype":"venue"
},
  "geometry": {"coordinates":[-87.72659299999999,41.504564],"type":"Point"}
}