{
  "type": "Feature",
  "properties": {
    "addr:full":"3524 S Hoyne Ave Chicago IL 60609",
    "addr:housenumber":"3524",
    "addr:postcode":"60609",
    "addr:street":"S Hoyne Ave",
    "iso:country":"US",
    "sg:address":"3524 S Hoyne Ave",
    "sg:city":"Chicago",
    "sg:classifiers":[
        {
            "category":"Place Of Worship",
            "subcategory":"Church",
            "type":"Public Place"
        },
        {
            "category":"Place Of Worship",
            "type":"Public Place"
        },
        {
            "category":"Organizations",
            "subcategory":"Religious Organization",
            "type":"Services"
        }
    ],
    "sg:phone":"+1 773 523 7911",
    "sg:postcode":"60609",
    "sg:province":"IL",
    "sg:tags":[
        "churches-baptist-general",
        "churches-baptist"
    ],
    "wof:name":"Bethany Baptist Church",
    "wof:placetype":"venue"
},
  "geometry": {"coordinates":[-87.67769800000001,41.829921],"type":"Point"}
}