{
  "type": "Feature",
  "properties": {
    "iso:country":"US",
    "sg:address":"1 E Wilson St",
    "sg:city":"Batavia",
    "sg:classifiers":[
        {
            "category":"Recreation",
            "type":"Entertainment"
        }
    ],
    "sg:phone":"+1 630 406 6883",
    "sg:postcode":"60510",
    "sg:province":"IL",
    "sg:tags":[
        "martial",
        "arts",
        "instruction"
    ],
    "wof:name":"ATA Black Belt Academy",
    "wof:placetype":"venue"
},
  "geometry": {"coordinates":[-88.305946,41.850013],"type":"Point"}
}