{
  "type": "Feature",
  "properties": {
    "addr:full":"201 N Miller St Waverly IL 62692",
    "addr:housenumber":"201",
    "addr:postcode":"62692",
    "addr:street":"N Miller St",
    "iso:country":"US",
    "sg:address":"201 N Miller St",
    "sg:city":"Waverly",
    "sg:classifiers":[
        {
            "category":"Education",
            "subcategory":"School",
            "type":"Public Place"
        }
    ],
    "sg:phone":"+1 217 435 8121",
    "sg:postcode":"62692",
    "sg:province":"IL",
    "sg:website":"www.waverlyscotties.com",
    "wof:name":"Waverly Community Unit School",
    "wof:placetype":"venue"
},
  "geometry": {"coordinates":[-89.959704,39.59354],"type":"Point"}
}