{
  "type": "Feature",
  "properties": {
    "iso:country":"US",
    "sg:address":"7555 Walton St",
    "sg:city":"Rockford",
    "sg:classifiers":[
        {
            "category":"Travel",
            "subcategory":"Hotels & Motels",
            "type":"Entertainment"
        }
    ],
    "sg:phone":"+1 815 229 6192",
    "sg:postcode":"61108",
    "sg:province":"IL",
    "sg:tags":[
        "operation"
    ],
    "wof:name":"Candlewood Suites",
    "wof:placetype":"venue"
},
  "geometry": {"coordinates":[-88.96961,42.268806],"type":"Point"}
}