{
  "type": "Feature",
  "properties": {
    "iso:country":"US",
    "sg:address":"189 S Oak Park Ave",
    "sg:city":"Oak Park",
    "sg:classifiers":[
        {
            "category":"Banks & Credit Unions",
            "subcategory":"Bank",
            "type":"Services"
        }
    ],
    "sg:phone":"+1 708 386 1400",
    "sg:postcode":"60302",
    "sg:province":"IL",
    "sg:tags":[
        "loan",
        "broker"
    ],
    "wof:name":"Re/Max",
    "wof:placetype":"venue"
},
  "geometry": {"coordinates":[-87.79451299999999,41.886108],"type":"Point"}
}