{
  "type": "Feature",
  "properties": {
    "iso:country":"US",
    "sg:address":"1000 W Lincoln Ave",
    "sg:city":"Caseyville",
    "sg:classifiers":[
        {
            "category":"Retail",
            "subcategory":"Auto Repair",
            "type":"Services"
        }
    ],
    "sg:phone":"+1 618 394 0960",
    "sg:postcode":"62232",
    "sg:province":"IL",
    "sg:tags":[
        "body",
        "automobile",
        "painting"
    ],
    "wof:name":"Toms Custom Upholstery & Auto",
    "wof:placetype":"venue"
},
  "geometry": {"coordinates":[-90.044174,38.635867],"type":"Point"}
}