{
  "type": "Feature",
  "properties": {
    "iso:country":"US",
    "sg:address":"3330 N Milwaukee Ave",
    "sg:city":"Chicago",
    "sg:classifiers":[
        {
            "category":"Health Services",
            "subcategory":"Health Practitioner",
            "type":"Services"
        },
        {
            "category":"Education",
            "subcategory":"University",
            "type":"Public Place"
        }
    ],
    "sg:phone":"+1 773 282 2686",
    "sg:postcode":"60641",
    "sg:province":"IL",
    "sg:tags":[
        "naturopathic/holistic",
        "college"
    ],
    "sg:website":"www.naprapathicmedicine.edu/",
    "wof:name":"National College of Naprapathic Medicine",
    "wof:placetype":"venue"
},
  "geometry": {"coordinates":[-87.72813600000001,41.941387],"type":"Point"}
}