{
  "type": "Feature",
  "properties": {
    "iso:country":"US",
    "sg:address":"244 N Main St",
    "sg:city":"Elizabeth",
    "sg:classifiers":[
        {
            "category":"Restaurant",
            "type":"Food & Drink"
        }
    ],
    "sg:phone":"+1   ",
    "sg:postcode":"61028",
    "sg:province":"IL",
    "sg:tags":[
        "eating"
    ],
    "wof:name":"J& JS Restaurant",
    "wof:placetype":"venue"
},
  "geometry": {"coordinates":[-90.222054,42.318552],"type":"Point"}
}