{
  "type": "Feature",
  "properties": {
    "iso:country":"US",
    "sg:address":"18602 154th St W",
    "sg:city":"Reynolds",
    "sg:classifiers":[
        {
            "category":"Building & Trades",
            "subcategory":"Construction",
            "type":"Services"
        }
    ],
    "sg:phone":"+1 309 373 1041",
    "sg:postcode":"61279",
    "sg:province":"IL",
    "sg:tags":[
        "mason",
        "masonry",
        "industrial",
        "contractors-commercial",
        "contractor"
    ],
    "sg:website":"http://www.rivercityrestorationinc.com",
    "wof:name":"River City Restoration Of The Quad Cities, Inc.",
    "wof:placetype":"venue"
},
  "geometry": {"coordinates":[-90.782409,41.33367],"type":"Point"}
}