{
  "type": "Feature",
  "properties": {
    "addr:full":"5401 W 65th St Chicago IL 60638",
    "addr:housenumber":"5401",
    "addr:postcode":"60638",
    "addr:street":"W 65Th St",
    "iso:country":"US",
    "sg:address":"5401 W 65th St",
    "sg:city":"Chicago",
    "sg:classifiers":[
        {
            "category":"Building & Trades",
            "subcategory":"Electrical",
            "type":"Services"
        }
    ],
    "sg:phone":"+1 708 458 6210",
    "sg:postcode":"60638",
    "sg:province":"IL",
    "sg:tags":[
        "transmission",
        "power",
        "equipment"
    ],
    "wof:name":"Smith Power Transmission",
    "wof:placetype":"venue"
},
  "geometry": {"coordinates":[-87.756699,41.774479],"type":"Point"}
}