{
  "type": "Feature",
  "properties": {
    "addr:full":"18140 Springfield Ave Homewood IL 60430",
    "addr:housenumber":"18140",
    "addr:postcode":"60430",
    "addr:street":"Springfield Ave",
    "iso:country":"US",
    "sg:address":"18140 Springfield Ave",
    "sg:city":"Homewood",
    "sg:classifiers":[
        {
            "category":"Building & Trades",
            "subcategory":"Landscaping Services",
            "type":"Services"
        }
    ],
    "sg:phone":"+1 708 957 3281",
    "sg:postcode":"60430",
    "sg:province":"IL",
    "wof:name":"Aneston",
    "wof:placetype":"venue"
},
  "geometry": {"coordinates":[-87.711286,41.557643],"type":"Point"}
}