{
  "type": "Feature",
  "properties": {
    "iso:country":"US",
    "sg:address":"2515 Cleveland Blvd",
    "sg:city":"Granite City",
    "sg:classifiers":[
        {
            "category":"Building & Trades",
            "subcategory":"Plumbing",
            "type":"Services"
        }
    ],
    "sg:phone":"+1 618 451 8094",
    "sg:postcode":"62040",
    "sg:province":"IL",
    "wof:name":"Anchor Plumbing",
    "wof:placetype":"venue"
},
  "geometry": {"coordinates":[-90.14009900000001,38.711201],"type":"Point"}
}