{
  "type": "Feature",
  "properties": {
    "iso:country":"US",
    "sg:address":"6144 S Pulaski Road",
    "sg:city":"Chicago",
    "sg:classifiers":[
        {
            "category":"Health Services",
            "subcategory":"Dentist",
            "type":"Services"
        }
    ],
    "sg:phone":"+1 773 585 8000",
    "sg:postcode":"60629",
    "sg:province":"IL",
    "wof:name":"Brandenburg R C DDS",
    "wof:placetype":"venue"
},
  "geometry": {"coordinates":[-87.722882,41.780751],"type":"Point"}
}