{
  "type": "Feature",
  "properties": {
    "addr:full":"430 Lake Cook Rd Deerfield IL 60015",
    "addr:housenumber":"430",
    "addr:postcode":"60015",
    "addr:street":"Lake Cook Rd",
    "iso:country":"US",
    "sg:address":"430 Lake Cook Rd",
    "sg:city":"Deerfield",
    "sg:classifiers":[
        {
            "category":"Home & Garden",
            "subcategory":"Building Materials",
            "type":"Retail Goods"
        },
        {
            "category":"Building & Trades",
            "subcategory":"Construction",
            "type":"Services"
        }
    ],
    "sg:phone":"+1 847 945 9200",
    "sg:postcode":"60015",
    "sg:province":"IL",
    "sg:tags":[
        "windows",
        "contractor",
        "glass",
        "window",
        "curtain",
        "wall"
    ],
    "sg:website":"www.buildersarch.com",
    "wof:name":"Builders Architectural Prods",
    "wof:placetype":"venue"
},
  "geometry": {"coordinates":[-87.83850700000001,42.15269],"type":"Point"}
}