{
  "type": "Feature",
  "properties": {
    "iso:country":"US",
    "sg:address":"7N082 Medinah Rd",
    "sg:city":"Medinah",
    "sg:classifiers":[
        {
            "category":"Personal",
            "subcategory":"Barber",
            "type":"Services"
        }
    ],
    "sg:phone":"+1 630 529 2755",
    "sg:postcode":"60157",
    "sg:province":"IL",
    "wof:name":"Headhunters",
    "wof:placetype":"venue"
},
  "geometry": {"coordinates":[-88.0513,41.9785],"type":"Point"}
}