{
  "type": "Feature",
  "properties": {
    "iso:country":"US",
    "sg:address":"31 N Washington St",
    "sg:city":"Carthage",
    "sg:classifiers":[
        {
            "category":"Manufacturing",
            "subcategory":"Printing",
            "type":"Manufacturing & Wholesale Goods"
        }
    ],
    "sg:phone":"+1 217 357 2149",
    "sg:postcode":"62321",
    "sg:province":"IL",
    "sg:tags":[
        "newspaper"
    ],
    "sg:website":"www.journalpilot.com",
    "wof:name":"Hancock County Journal-Pilot",
    "wof:placetype":"venue"
},
  "geometry": {"coordinates":[-91.132853,40.414288],"type":"Point"}
}