{
  "type": "Feature",
  "properties": {
    "iso:country":"US",
    "sg:address":"210 McHenry Ave",
    "sg:city":"Crystal Lake",
    "sg:classifiers":[
        {
            "category":"Social Services",
            "type":"Services"
        }
    ],
    "sg:phone":"+1 815 787 2591",
    "sg:postcode":"60014",
    "sg:province":"IL",
    "sg:tags":[
        "organization",
        "welfare"
    ],
    "wof:name":"St Mary's Svc",
    "wof:placetype":"venue"
},
  "geometry": {"coordinates":[-88.330346,42.235035],"type":"Point"}
}