{
  "type": "Feature",
  "properties": {
    "addr:full":"407 Virginia Ave Westville IL 61883",
    "addr:housenumber":"407",
    "addr:postcode":"61883",
    "addr:street":"Virginia Ave",
    "iso:country":"US",
    "sg:address":"407 Virginia Ave",
    "sg:city":"Westville",
    "sg:classifiers":[
        {
            "category":"Wholesale",
            "subcategory":"Hardware",
            "type":"Manufacturing & Wholesale Goods"
        }
    ],
    "sg:phone":"+1 217 267 7016",
    "sg:postcode":"61883",
    "sg:province":"IL",
    "sg:tags":[
        "hardware-wholesale",
        "manufacturer"
    ],
    "wof:name":"Miller John",
    "wof:placetype":"venue"
},
  "geometry": {"coordinates":[-87.634074,40.033341],"type":"Point"}
}