{
  "type": "Feature",
  "properties": {
    "addr:full":"333 W Austin Ave Libertyville IL 60048",
    "addr:housenumber":"333",
    "addr:postcode":"60048",
    "addr:street":"W Austin Ave",
    "iso:country":"US",
    "sg:address":"333 W Austin Ave",
    "sg:city":"Libertyville",
    "sg:classifiers":[
        {
            "category":"Building & Trades",
            "subcategory":"Landscaping Services",
            "type":"Services"
        }
    ],
    "sg:phone":"+1 847 816 7440",
    "sg:postcode":"60048",
    "sg:province":"IL",
    "sg:tags":[
        "topsoil"
    ],
    "wof:name":"Keith's Top Soil",
    "wof:placetype":"venue"
},
  "geometry": {"coordinates":[-87.95756,42.277237],"type":"Point"}
}