{
  "type": "Feature",
  "properties": {
    "addr:full":"384 Northridge Rd Columbia IL 62236",
    "addr:housenumber":"384",
    "addr:postcode":"62236",
    "addr:street":"Northridge Rd",
    "iso:country":"US",
    "sg:address":"384 Northridge Rd",
    "sg:city":"Columbia",
    "sg:classifiers":[
        {
            "category":"Real Estate",
            "subcategory":"Real Estate Agent",
            "type":"Services"
        }
    ],
    "sg:phone":"+1 618 281 2657",
    "sg:postcode":"62236",
    "sg:province":"IL",
    "wof:name":"CMJP Properties",
    "wof:placetype":"venue"
},
  "geometry": {"coordinates":[-90.195695,38.433551],"type":"Point"}
}