{
  "type": "Feature",
  "properties": {
    "iso:country":"US",
    "sg:address":"450 W Menomonee St",
    "sg:city":"Chicago",
    "sg:classifiers":[
        {
            "category":"Social Services",
            "subcategory":"Child Care",
            "type":"Services"
        }
    ],
    "sg:phone":"+1 312 266 2573",
    "sg:postcode":"60614",
    "sg:province":"IL",
    "sg:tags":[
        "day"
    ],
    "wof:name":"Chalkboard the",
    "wof:placetype":"venue"
},
  "geometry": {"coordinates":[-87.64009900000001,41.914799],"type":"Point"}
}