{
  "type": "Feature",
  "properties": {
    "addr:full":"608 Carlyle Rd Bartelso IL 62218",
    "addr:housenumber":"608",
    "addr:postcode":"62218",
    "addr:street":"Carlyle Rd",
    "iso:country":"US",
    "sg:address":"608 Carlyle Rd",
    "sg:city":"Bartelso",
    "sg:classifiers":[
        {
            "category":"Retail",
            "subcategory":"Auto Repair",
            "type":"Services"
        }
    ],
    "sg:phone":"+1 618 765 2115",
    "sg:postcode":"62218",
    "sg:province":"IL",
    "sg:tags":[
        "body",
        "automobile",
        "painting"
    ],
    "wof:name":"Mickelson's Auto Body",
    "wof:placetype":"venue"
},
  "geometry": {"coordinates":[-89.47026,38.536486],"type":"Point"}
}