{
  "type": "Feature",
  "properties": {
    "iso:country":"US",
    "sg:address":"3211 Belvidere Rd",
    "sg:city":"Waukegan",
    "sg:classifiers":[
        {
            "category":"Real Estate",
            "subcategory":"Real Estate Agent",
            "type":"Services"
        }
    ],
    "sg:phone":"+1 847 244 1515",
    "sg:postcode":"60085",
    "sg:province":"IL",
    "sg:tags":[
        "agency"
    ],
    "wof:name":"Re/Max",
    "wof:placetype":"venue"
},
  "geometry": {"coordinates":[-87.88211699999999,42.348608],"type":"Point"}
}