{
  "type": "Feature",
  "properties": {
    "iso:country":"US",
    "sg:address":"524 E Gillespie St",
    "sg:city":"Bridgeport",
    "sg:classifiers":[
        {
            "category":"Organizations",
            "subcategory":"Religious Organization",
            "type":"Services"
        }
    ],
    "sg:phone":"+1 618 945 5941",
    "sg:postcode":"62417",
    "sg:province":"IL",
    "wof:name":"Bridgeport Wesleyan Church",
    "wof:placetype":"venue"
},
  "geometry": {"coordinates":[-87.756011,38.711945],"type":"Point"}
}