{
  "type": "Feature",
  "properties": {
    "addr:full":"910 Holly Stone Ln Buffalo Grove IL 60089",
    "addr:housenumber":"910",
    "addr:postcode":"60089",
    "addr:street":"Holly Stone Ln",
    "iso:country":"US",
    "sg:address":"910 Holly Stone Ln",
    "sg:city":"Buffalo Grove",
    "sg:classifiers":[
        {
            "category":"Shopping",
            "subcategory":"Clothing, Apparel, & Fashions",
            "type":"Retail Goods"
        }
    ],
    "sg:phone":"+1 847 459 4717",
    "sg:postcode":"60089",
    "sg:province":"IL",
    "sg:tags":[
        "c",
        "suit",
        "everyday",
        "outerwear"
    ],
    "wof:name":"Sandys Clothing Mens & Boys",
    "wof:placetype":"venue"
},
  "geometry": {"coordinates":[-87.97896799999999,42.164318],"type":"Point"}
}