{
  "type": "Feature",
  "properties": {
    "iso:country":"US",
    "sg:address":"8700 Coon Trail Rd",
    "sg:city":"Capron",
    "sg:classifiers":[
        {
            "category":"Farming",
            "subcategory":"Dairy Farm",
            "type":"Manufacturing & Wholesale Goods"
        }
    ],
    "sg:phone":"+1 815 737 8749",
    "sg:postcode":"61012",
    "sg:province":"IL",
    "wof:name":"Paul Donley",
    "wof:placetype":"venue"
},
  "geometry": {"coordinates":[-88.769781,42.472876],"type":"Point"}
}