{
  "type": "Feature",
  "properties": {
    "addr:full":"965 W Highland Ave Elgin IL 60123",
    "addr:housenumber":"965",
    "addr:postcode":"60123",
    "addr:street":"W Highland Ave",
    "iso:country":"US",
    "sg:address":"965 W Highland Ave",
    "sg:city":"Elgin",
    "sg:classifiers":[
        {
            "category":"Professional",
            "subcategory":"Business Services",
            "type":"Services"
        }
    ],
    "sg:phone":"+1 847 741 2015",
    "sg:postcode":"60123",
    "sg:province":"IL",
    "wof:name":"Pierce Inspections Inc",
    "wof:placetype":"venue"
},
  "geometry": {"coordinates":[-88.302865,42.038337],"type":"Point"}
}