{
  "type": "Feature",
  "properties": {
    "addr:full":"705 S Mitchell Ave Elmhurst IL 60126",
    "addr:housenumber":"705",
    "addr:postcode":"60126",
    "addr:street":"S Mitchell Ave",
    "iso:country":"US",
    "sg:address":"705 S Mitchell Ave",
    "sg:city":"Elmhurst",
    "sg:classifiers":[
        {
            "category":"Retail",
            "subcategory":"Repair Shop",
            "type":"Services"
        }
    ],
    "sg:phone":"+1 630 833 2183",
    "sg:postcode":"60126",
    "sg:province":"IL",
    "sg:tags":[
        "freezers-repair",
        "refrigerator"
    ],
    "wof:name":"John's Truck Refrigeration",
    "wof:placetype":"venue"
},
  "geometry": {"coordinates":[-87.945756,41.878375],"type":"Point"}
}