{
  "type": "Feature",
  "properties": {
    "addr:full":"3045 Chicago Rd Steger IL 60475",
    "addr:housenumber":"3045",
    "addr:postcode":"60475",
    "addr:street":"Chicago Rd",
    "iso:country":"US",
    "sg:address":"3045 Chicago Rd",
    "sg:city":"Steger",
    "sg:classifiers":[
        {
            "category":"Retail",
            "subcategory":"Funeral Services",
            "type":"Services"
        }
    ],
    "sg:phone":"+1 708 755 6100",
    "sg:postcode":"60475",
    "sg:province":"IL",
    "wof:name":"Smits General Home Limited",
    "wof:placetype":"venue"
},
  "geometry": {"coordinates":[-87.636833,41.475525],"type":"Point"}
}