{
  "type": "Feature",
  "properties": {
    "addr:full":"6981 Redansa Dr Rockford IL 61108",
    "addr:housenumber":"6981",
    "addr:postcode":"61108",
    "addr:street":"Redansa Dr",
    "iso:country":"US",
    "sg:address":"6981 Redansa Dr",
    "sg:city":"Rockford",
    "sg:classifiers":[
        {
            "category":"Professional",
            "subcategory":"Management & Consulting",
            "type":"Services"
        },
        {
            "category":"Banks & Credit Unions",
            "subcategory":"Investment Brokerage",
            "type":"Services"
        },
        {
            "category":"Banks & Credit Unions",
            "subcategory":"Financial Services",
            "type":"Services"
        }
    ],
    "sg:phone":"+1 815 399 9806",
    "sg:postcode":"61108",
    "sg:province":"IL",
    "sg:tags":[
        "planning",
        "advisory",
        "financing",
        "planner",
        "consultant"
    ],
    "wof:name":"Pathfinder Management",
    "wof:placetype":"venue"
},
  "geometry": {"coordinates":[-88.981291,42.254557],"type":"Point"}
}