{
  "type": "Feature",
  "properties": {
    "addr:full":"949 N Western Ave Chicago IL 60622",
    "addr:housenumber":"949",
    "addr:postcode":"60622",
    "addr:street":"N Western Ave",
    "iso:country":"US",
    "sg:address":"949 N Western Ave",
    "sg:city":"Chicago",
    "sg:classifiers":[
        {
            "category":"Restaurant",
            "type":"Food & Drink"
        }
    ],
    "sg:phone":"+1 773 486 4695",
    "sg:postcode":"60622",
    "sg:province":"IL",
    "sg:tags":[
        "diner"
    ],
    "wof:name":"Ricky's Deli",
    "wof:placetype":"venue"
},
  "geometry": {"coordinates":[-87.68672100000001,41.898985],"type":"Point"}
}