{
  "type": "Feature",
  "properties": {
    "iso:country":"US",
    "sg:address":"601 Co Rd 10",
    "sg:city":"Harrisburg",
    "sg:classifiers":[
        {
            "category":"Home & Garden",
            "subcategory":"Household Appliances",
            "type":"Retail Goods"
        }
    ],
    "sg:phone":"+1   ",
    "sg:postcode":"62918",
    "sg:province":"IL",
    "wof:name":"Lightnor Inc Sears",
    "wof:placetype":"venue"
},
  "geometry": {"coordinates":[-89.077163,37.757097],"type":"Point"}
}