{
  "type": "Feature",
  "properties": {
    "iso:country":"US",
    "sg:address":"1590 Cherry Valley Rd",
    "sg:city":"Bull Valley",
    "sg:classifiers":[
        {
            "category":"Building & Trades",
            "subcategory":"Landscaping Services",
            "type":"Services"
        }
    ],
    "sg:phone":"+1 815 356 6575",
    "sg:postcode":"60050",
    "sg:province":"IL",
    "sg:tags":[
        "landscape",
        "contractor"
    ],
    "wof:name":"Weber Tree Transplanters",
    "wof:placetype":"venue"
},
  "geometry": {"coordinates":[-88.350244,42.310551],"type":"Point"}
}