{
  "type": "Feature",
  "properties": {
    "iso:country":"US",
    "sg:address":"13400 S Corliss Ave",
    "sg:city":"Chicago",
    "sg:classifiers":[
        {
            "category":"Place Of Worship",
            "subcategory":"Church",
            "type":"Public Place"
        },
        {
            "category":"Place Of Worship",
            "type":"Public Place"
        },
        {
            "category":"Organizations",
            "subcategory":"Religious Organization",
            "type":"Services"
        }
    ],
    "sg:phone":"+1 773 468 3857",
    "sg:postcode":"60827",
    "sg:province":"IL",
    "sg:tags":[
        "god",
        "denomination",
        "churches-church",
        "churches-pentecostal",
        "churches-interdenominational",
        "churches-various"
    ],
    "wof:name":"Peter's Rock Church Of God In Christ",
    "wof:placetype":"venue"
},
  "geometry": {"coordinates":[-87.602203,41.651829],"type":"Point"}
}