{
  "type": "Feature",
  "properties": {
    "iso:country":"US",
    "sg:address":"3910 Wyndwood Dr",
    "sg:city":"Crystal Lake",
    "sg:classifiers":[
        {
            "category":"Professional",
            "subcategory":"Business Services",
            "type":"Services"
        }
    ],
    "sg:phone":"+1 815 477 5137",
    "sg:postcode":"60014",
    "sg:province":"IL",
    "wof:name":"Illinois Motor Sales Inc",
    "wof:placetype":"venue"
},
  "geometry": {"coordinates":[-88.270585,42.237889],"type":"Point"}
}