{
  "type": "Feature",
  "properties": {
    "addr:full":"210 W 79th St Chicago IL 60620",
    "addr:housenumber":"210",
    "addr:postcode":"60620",
    "addr:street":"W 79Th St",
    "iso:country":"US",
    "sg:address":"210 W 79th St",
    "sg:city":"Chicago",
    "sg:classifiers":[
        {
            "category":"Transit Center",
            "subcategory":"Passenger",
            "type":"Transportation"
        },
        {
            "category":"Local Transit",
            "type":"Transportation"
        }
    ],
    "sg:phone":"+1 773 874 7100",
    "sg:postcode":"60620",
    "sg:province":"IL",
    "sg:tags":[
        "bus",
        "line"
    ],
    "sg:website":"http://www.transitchicago.com",
    "wof:name":"Cta Garage & Warehouse",
    "wof:placetype":"venue"
},
  "geometry": {"coordinates":[-87.629741,41.750848],"type":"Point"}
}