{
  "type": "Feature",
  "properties": {
    "iso:country":"US",
    "sg:address":"500 W Main St",
    "sg:city":"Decatur",
    "sg:classifiers":[
        {
            "category":"Travel",
            "subcategory":"Hotels & Motels",
            "type":"Entertainment"
        },
        {
            "category":"Travel",
            "subcategory":"Bed & Breakfast",
            "type":"Entertainment"
        }
    ],
    "sg:phone":"+1 217 422 9707",
    "sg:postcode":"62522",
    "sg:province":"IL",
    "sg:tags":[
        "inn",
        "lodging"
    ],
    "wof:name":"The Younker House",
    "wof:placetype":"venue"
},
  "geometry": {"coordinates":[-88.961929,39.841301],"type":"Point"}
}