{
  "type": "Feature",
  "properties": {
    "addr:full":"25673 Marion Ave Ingleside IL 60041",
    "addr:housenumber":"25673",
    "addr:postcode":"60041",
    "addr:street":"Marion Ave",
    "iso:country":"US",
    "sg:address":"25673 Marion Ave",
    "sg:city":"Ingleside",
    "sg:classifiers":[
        {
            "category":"Professional",
            "subcategory":"Engineering",
            "type":"Services"
        }
    ],
    "sg:phone":"+1 847 587 9790",
    "sg:postcode":"60041",
    "sg:province":"IL",
    "sg:tags":[
        "engineer"
    ],
    "wof:name":"G & D Consulting Svc",
    "wof:placetype":"venue"
},
  "geometry": {"coordinates":[-88.13331599999999,42.379036],"type":"Point"}
}