{
  "type": "Feature",
  "properties": {
    "addr:full":"1 Erie Ct Ste 6140 Oak Park IL 60302",
    "addr:housenumber":"1",
    "addr:postcode":"60302",
    "addr:street":"Erie Ct Ste 6140",
    "iso:country":"US",
    "sg:address":"1 Erie Ct Ste 6140",
    "sg:city":"Oak Park",
    "sg:classifiers":[
        {
            "category":"Health Services",
            "subcategory":"Optometrist",
            "type":"Services"
        },
        {
            "category":"Banks & Credit Unions",
            "subcategory":"Financial Services",
            "type":"Services"
        }
    ],
    "sg:phone":"+1 708 848 2400",
    "sg:postcode":"60302",
    "sg:province":"IL",
    "sg:tags":[
        "ophthalmologist",
        "broker",
        "mortgage"
    ],
    "wof:name":"Springer David MD",
    "wof:placetype":"venue"
},
  "geometry": {"coordinates":[-87.774902,41.892799],"type":"Point"}
}