{
  "type": "Feature",
  "properties": {
    "iso:country":"US",
    "sg:address":"440 N Oakley Boulevard",
    "sg:city":"Chicago",
    "sg:classifiers":[
        {
            "category":"Professional",
            "type":"Services"
        }
    ],
    "sg:phone":"+1 312 666 2900",
    "sg:postcode":"60612",
    "sg:province":"IL",
    "sg:tags":[
        "caterer"
    ],
    "wof:name":"Kasia's Deli",
    "wof:placetype":"venue"
},
  "geometry": {"coordinates":[-87.684054,41.889827],"type":"Point"}
}