{
  "type": "Feature",
  "properties": {
    "addr:full":"5118 Hickory Ln Mc Henry IL 60051",
    "addr:housenumber":"5118",
    "addr:postcode":"60051",
    "addr:street":"Hickory Ln Mc Henry",
    "iso:country":"US",
    "sg:address":"5118 Hickory Ln",
    "sg:city":"Mc Henry",
    "sg:classifiers":[
        {
            "category":"Professional",
            "type":"Services"
        }
    ],
    "sg:phone":"+1 815 675 1168",
    "sg:postcode":"60051",
    "sg:province":"IL",
    "wof:name":"Dennis Stoner",
    "wof:placetype":"venue"
},
  "geometry": {"coordinates":[-88.258324,42.399976],"type":"Point"}
}