{
  "type": "Feature",
  "properties": {
    "iso:country":"US",
    "sg:address":"2251 State Rte 9",
    "sg:city":"Dallas City",
    "sg:phone":"+1 217 659 7854",
    "sg:postcode":"62330",
    "sg:province":"IL",
    "sg:tags":[
        "hog",
        "beef",
        "farm",
        "corn",
        "soybean",
        "cattle",
        "or",
        "feedlot"
    ],
    "wof:name":"Paul Corzatt",
    "wof:placetype":"venue"
},
  "geometry": {"coordinates":[-91.069732,40.591566],"type":"Point"}
}