{
  "type": "Feature",
  "properties": {
    "iso:country":"US",
    "sg:address":"2640 Co Rd 2500 E",
    "sg:city":"Penfield",
    "sg:phone":"+1 217 694 4775",
    "sg:postcode":"61862",
    "sg:province":"IL",
    "sg:tags":[
        "farm",
        "corn"
    ],
    "wof:name":"G & E Farm Inc",
    "wof:placetype":"venue"
},
  "geometry": {"coordinates":[-87.98677000000001,40.254669],"type":"Point"}
}