{
  "type": "Feature",
  "properties": {
    "iso:country":"US",
    "sg:address":"4730 Main St",
    "sg:city":"Downers Grove",
    "sg:classifiers":[
        {
            "category":"Professional",
            "subcategory":"Advertising",
            "type":"Services"
        }
    ],
    "sg:phone":"+1 630 960 0821",
    "sg:postcode":"60515",
    "sg:province":"IL",
    "sg:tags":[
        "agency"
    ],
    "wof:name":"William Makely Associates",
    "wof:placetype":"venue"
},
  "geometry": {"coordinates":[-88.01083,41.800637],"type":"Point"}
}