{
  "type": "Feature",
  "properties": {
    "addr:full":"1666 N Randall Rd Aurora IL 60506",
    "addr:housenumber":"1666",
    "addr:postcode":"60506",
    "addr:street":"N Randall Rd",
    "iso:country":"US",
    "sg:address":"1666 N Randall Rd",
    "sg:city":"Aurora",
    "sg:classifiers":[
        {
            "category":"Retail",
            "subcategory":"Laundry & Dry Cleaning",
            "type":"Services"
        }
    ],
    "sg:phone":"+1 630 907 0034",
    "sg:postcode":"60506",
    "sg:province":"IL",
    "sg:tags":[
        "cleaners"
    ],
    "wof:name":"Randall Cleaners",
    "wof:placetype":"venue"
},
  "geometry": {"coordinates":[-88.34980299999999,41.788821],"type":"Point"}
}