{
  "type": "Feature",
  "properties": {
    "iso:country":"US",
    "sg:address":"1449 Church St",
    "sg:city":"Northbrook",
    "sg:classifiers":[
        {
            "category":"Professional",
            "subcategory":"Business Services",
            "type":"Services"
        }
    ],
    "sg:phone":"+1 847 509 3066",
    "sg:postcode":"60062",
    "sg:province":"IL",
    "wof:name":"Blue Canyon Enterprises",
    "wof:placetype":"venue"
},
  "geometry": {"coordinates":[-87.821865,42.127425],"type":"Point"}
}