{
  "type": "Feature",
  "properties": {
    "addr:full":"1947 Quincy Ct Glendale Heights IL 60139",
    "addr:housenumber":"1947",
    "addr:postcode":"60139",
    "addr:street":"Quincy Ct",
    "iso:country":"US",
    "sg:address":"1947 Quincy Ct",
    "sg:city":"Glendale Heights",
    "sg:classifiers":[
        {
            "category":"Wholesale",
            "subcategory":"Durable Goods & Equipment",
            "type":"Manufacturing & Wholesale Goods"
        },
        {
            "category":"Wholesale",
            "subcategory":"Metals & Minerals",
            "type":"Manufacturing & Wholesale Goods"
        }
    ],
    "sg:phone":"+1 630 893 3888",
    "sg:postcode":"60139",
    "sg:province":"IL",
    "sg:tags":[
        "rope",
        "import",
        "importer",
        "wire",
        "cable"
    ],
    "wof:name":"Alps Wire Rope Corporation",
    "wof:placetype":"venue"
},
  "geometry": {"coordinates":[-88.086055,41.930931],"type":"Point"}
}