{
  "type": "Feature",
  "properties": {
    "addr:full":"900 Upper Cahokia Rd Cahokia IL 62206",
    "addr:housenumber":"900",
    "addr:postcode":"62206",
    "addr:street":"Upper Cahokia Rd",
    "iso:country":"US",
    "sg:address":"900 Upper Cahokia Rd",
    "sg:city":"Cahokia",
    "sg:classifiers":[
        {
            "category":"Banks & Credit Unions",
            "subcategory":"Bank",
            "type":"Services"
        }
    ],
    "sg:phone":"+1 618 332 3100",
    "sg:postcode":"62206",
    "sg:province":"IL",
    "wof:name":"Union Planters Bank",
    "wof:placetype":"venue"
},
  "geometry": {"coordinates":[-90.17526100000001,38.576008],"type":"Point"}
}