{
  "type": "Feature",
  "properties": {
    "iso:country":"US",
    "sg:address":"110 N Blake Dr",
    "sg:city":"Godley",
    "sg:classifiers":[
        {
            "category":"Building & Trades",
            "subcategory":"Construction",
            "type":"Services"
        }
    ],
    "sg:phone":"+1 815 458 9886",
    "sg:postcode":"60407",
    "sg:province":"IL",
    "sg:tags":[
        "general",
        "contractor"
    ],
    "wof:name":"Keith Construction Inc",
    "wof:placetype":"venue"
},
  "geometry": {"coordinates":[-88.239217,41.239356],"type":"Point"}
}