{
  "type": "Feature",
  "properties": {
    "addr:full":"565 Chestnut St Winnetka IL 60093",
    "addr:housenumber":"565",
    "addr:postcode":"60093",
    "addr:street":"Chestnut St",
    "iso:country":"US",
    "sg:address":"565 Chestnut St",
    "sg:city":"Winnetka",
    "sg:classifiers":[
        {
            "category":"Shopping",
            "subcategory":"Optical Goods",
            "type":"Retail Goods"
        },
        {
            "category":"Shopping",
            "subcategory":"Optician",
            "type":"Retail Goods"
        },
        {
            "category":"Health Services",
            "subcategory":"Optometrist",
            "type":"Services"
        }
    ],
    "sg:phone":"+1 847 446 6264",
    "sg:postcode":"60093",
    "sg:province":"IL",
    "sg:tags":[
        "lens",
        "contact"
    ],
    "sg:website":"http://www.doyleopt.com",
    "wof:name":"Doyle Opticians",
    "wof:placetype":"venue"
},
  "geometry": {"coordinates":[-87.73518300000001,42.106474],"type":"Point"}
}