{
  "type": "Feature",
  "properties": {
    "addr:full":"220 N Fisher Ave Kewanee IL 61443",
    "addr:housenumber":"220",
    "addr:postcode":"61443",
    "addr:street":"N Fisher Ave",
    "iso:country":"US",
    "sg:address":"220 N Fisher Ave",
    "sg:city":"Kewanee",
    "sg:classifiers":[
        {
            "category":"Farming",
            "subcategory":"Livestock Farm",
            "type":"Manufacturing & Wholesale Goods"
        }
    ],
    "sg:phone":"+1 309 854 5431",
    "sg:postcode":"61443",
    "sg:province":"IL",
    "sg:tags":[
        "hog",
        "corn",
        "or",
        "feedlot"
    ],
    "wof:name":"Ronald Schiltz",
    "wof:placetype":"venue"
},
  "geometry": {"coordinates":[-89.903305,41.244771],"type":"Point"}
}