{
  "type": "Feature",
  "properties": {
    "iso:country":"US",
    "sg:address":"599 State Aid Rd",
    "sg:city":"Wood River",
    "sg:classifiers":[
        {
            "category":"Freight",
            "type":"Transportation"
        }
    ],
    "sg:phone":"+1 618 254 8974",
    "sg:postcode":"62095",
    "sg:province":"IL",
    "sg:tags":[
        "trucking"
    ],
    "wof:name":"Mc Daniel Transportation Inc",
    "wof:placetype":"venue"
},
  "geometry": {"coordinates":[-90.100697,38.850351],"type":"Point"}
}