{
  "type": "Feature",
  "properties": {
    "iso:country":"US",
    "sg:address":"9326 Corsair Rd",
    "sg:city":"Frankfort",
    "sg:classifiers":[
        {
            "category":"Wholesale",
            "subcategory":"Groceries",
            "type":"Manufacturing & Wholesale Goods"
        }
    ],
    "sg:phone":"+1 815 464 5710",
    "sg:postcode":"60423",
    "sg:province":"IL",
    "sg:tags":[
        "food",
        "fresh",
        "fruit",
        "including",
        "vegetable"
    ],
    "wof:name":"Wilkens Produce",
    "wof:placetype":"venue"
},
  "geometry": {"coordinates":[-87.84497,41.476408],"type":"Point"}
}