{
  "type": "Feature",
  "properties": {
    "addr:full":"860 Moran St Joliet IL 60435",
    "addr:housenumber":"860",
    "addr:postcode":"60435",
    "addr:street":"Moran St",
    "iso:country":"US",
    "sg:address":"860 Moran St",
    "sg:city":"Joliet",
    "sg:classifiers":[
        {
            "category":"Building & Trades",
            "subcategory":"Construction",
            "type":"Services"
        }
    ],
    "sg:phone":"+1 630 330 6895",
    "sg:postcode":"60435",
    "sg:province":"IL",
    "sg:tags":[
        "residential",
        "painting"
    ],
    "wof:name":"Townsend Painting",
    "wof:placetype":"venue"
},
  "geometry": {"coordinates":[-88.10373199999999,41.541246],"type":"Point"}
}