{
  "type": "Feature",
  "properties": {
    "addr:full":"UPS Store 2506 North Clark St Chicago IL 60614",
    "addr:housenumber":"2506",
    "addr:postcode":"60614",
    "addr:street":"North Clark St",
    "iso:country":"US",
    "sg:address":"UPS Store 2506 North Clark St",
    "sg:city":"Chicago",
    "sg:classifiers":[
        {
            "category":"Freight",
            "type":"Transportation"
        },
        {
            "category":"Professional",
            "subcategory":"Business Services",
            "type":"Services"
        }
    ],
    "sg:phone":"+1 877 269 3789",
    "sg:postcode":"60614",
    "sg:province":"IL",
    "sg:tags":[
        "delivery",
        "courier",
        "shipping"
    ],
    "sg:website":"www.movingdayboxes.com/moving-bo...",
    "wof:name":"Moving Day Boxes",
    "wof:placetype":"venue"
},
  "geometry": {"coordinates":[-87.642004,41.92815],"type":"Point"}
}