{
  "type": "Feature",
  "properties": {
    "addr:full":"360 W Schick Rd Bloomingdale IL 60108",
    "addr:housenumber":"360",
    "addr:postcode":"60108",
    "addr:street":"W Schick Rd",
    "iso:country":"US",
    "sg:address":"360 W Schick Rd",
    "sg:city":"Bloomingdale",
    "sg:classifiers":[
        {
            "category":"Professional",
            "subcategory":"Detective & Security Services",
            "type":"Services"
        }
    ],
    "sg:phone":"+1 630 980 7000",
    "sg:postcode":"60108",
    "sg:province":"IL",
    "sg:tags":[
        "information",
        "bureau"
    ],
    "sg:website":"http://www.premierinfosource.com",
    "wof:name":"Cc Services Incorporated",
    "wof:placetype":"venue"
},
  "geometry": {"coordinates":[-88.109385,41.95337],"type":"Point"}
}