{
  "type": "Feature",
  "properties": {
    "iso:country":"US",
    "sg:address":"7401 Bunkum Rd",
    "sg:city":"East St Louis",
    "sg:classifiers":[
        {
            "category":"Wholesale",
            "subcategory":"Construction Materials",
            "type":"Manufacturing & Wholesale Goods"
        }
    ],
    "sg:phone":"+1 618 398 3838",
    "sg:postcode":"62204",
    "sg:province":"IL",
    "sg:tags":[
        "sand",
        "gravel"
    ],
    "wof:name":"Metro East Sand Inc",
    "wof:placetype":"venue"
},
  "geometry": {"coordinates":[-90.067982,38.62271],"type":"Point"}
}