{
  "type": "Feature",
  "properties": {
    "iso:country":"US",
    "sg:address":"9577 Henninger Dr",
    "sg:city":"Belvidere",
    "sg:classifiers":[
        {
            "category":"Manufacturing",
            "subcategory":"Tools & Machinery",
            "type":"Manufacturing & Wholesale Goods"
        }
    ],
    "sg:phone":"+1 815 544 4098",
    "sg:postcode":"61008",
    "sg:province":"IL",
    "sg:tags":[
        "mfg"
    ],
    "wof:name":"First Header Die",
    "wof:placetype":"venue"
},
  "geometry": {"coordinates":[-88.815308,42.294344],"type":"Point"}
}