{
  "type": "Feature",
  "properties": {
    "iso:country":"US",
    "sg:address":"372 W Ontario St Ste 400",
    "sg:city":"Chicago",
    "sg:classifiers":[
        {
            "category":"Professional",
            "type":"Services"
        }
    ],
    "sg:phone":"+1 312 589 6101",
    "sg:postcode":"60610",
    "sg:province":"IL",
    "wof:name":"Liquidus",
    "wof:placetype":"venue"
},
  "geometry": {"coordinates":[-87.638957,41.893127],"type":"Point"}
}