{
  "type": "Feature",
  "properties": {
    "iso:country":"US",
    "sg:address":"28 W Schaumburg Rd",
    "sg:city":"Schaumburg",
    "sg:classifiers":[
        {
            "category":"Organizations",
            "subcategory":"Professional Association",
            "type":"Services"
        }
    ],
    "sg:phone":"+1 847 885 8800",
    "sg:postcode":"60194",
    "sg:province":"IL",
    "sg:tags":[
        "business"
    ],
    "wof:name":"Schaumburg Business Assn",
    "wof:placetype":"venue"
},
  "geometry": {"coordinates":[-88.081959,42.027301],"type":"Point"}
}