{
  "type": "Feature",
  "properties": {
    "iso:country":"US",
    "sg:address":"1197 Narragansett Dr",
    "sg:city":"Carol Stream",
    "sg:classifiers":[
        {
            "category":"Professional",
            "subcategory":"Management & Consulting",
            "type":"Services"
        }
    ],
    "sg:phone":"+1 630 837 6774",
    "sg:postcode":"60188",
    "sg:province":"IL",
    "sg:tags":[
        "business"
    ],
    "wof:name":"K T Consulting Services",
    "wof:placetype":"venue"
},
  "geometry": {"coordinates":[-88.163669,41.934312],"type":"Point"}
}