{
  "type": "Feature",
  "properties": {
    "addr:full":"8621 Kedvale Ave Skokie IL 60076",
    "addr:postcode":"8621;60076",
    "addr:street":"Kedvale Ave",
    "iso:country":"US",
    "sg:address":"8621 Kedvale Ave",
    "sg:city":"Skokie",
    "sg:classifiers":[
        {
            "category":"Professional",
            "type":"Services"
        }
    ],
    "sg:phone":"+1 847 675 7310",
    "sg:postcode":"60076",
    "sg:province":"IL",
    "wof:name":"Nick Ftikas",
    "wof:placetype":"venue"
},
  "geometry": {"coordinates":[-87.73139,42.038576],"type":"Point"}
}