{
  "type": "Feature",
  "properties": {
    "addr:full":"130 Hillcrest Blvd Schaumburg IL 60195",
    "addr:housenumber":"130",
    "addr:postcode":"60195",
    "addr:street":"Hillcrest Blvd",
    "iso:country":"US",
    "sg:address":"130 Hillcrest Blvd",
    "sg:city":"Schaumburg",
    "sg:classifiers":[
        {
            "category":"Personal",
            "type":"Services"
        },
        {
            "category":"Structure",
            "subcategory":"Warehouse",
            "type":"Public Place"
        },
        {
            "category":"Retail",
            "subcategory":"Storage",
            "type":"Services"
        }
    ],
    "sg:phone":"+1 888 772 2293",
    "sg:postcode":"60195",
    "sg:province":"IL",
    "sg:tags":[
        "moving-self",
        "full",
        "warehouses-public-commercial",
        "automobile",
        "household",
        "recreational",
        "commercial",
        "campers-storage",
        "vehicle",
        "mover",
        "self",
        "boat"
    ],
    "sg:website":"http://www.shurgard.com",
    "wof:name":"Public Storage - Schaumburg",
    "wof:placetype":"venue"
},
  "geometry": {"coordinates":[-88.082694,42.060611],"type":"Point"}
}