{
  "type": "Feature",
  "properties": {
    "iso:country":"US",
    "sg:address":"107 N Main St",
    "sg:city":"Rockford",
    "sg:classifiers":[
        {
            "category":"Coffee & Tea",
            "type":"Food & Drink"
        },
        {
            "category":"Restaurant",
            "type":"Food & Drink"
        }
    ],
    "sg:phone":"+1 815 968 0123",
    "sg:postcode":"61101",
    "sg:province":"IL",
    "sg:tags":[
        "espresso"
    ],
    "wof:name":"Cafe Esperanto",
    "wof:placetype":"venue"
},
  "geometry": {"coordinates":[-89.093857,42.272201],"type":"Point"}
}