{
  "type": "Feature",
  "properties": {
    "iso:country":"US",
    "sg:address":"1750 Bradford Ln",
    "sg:city":"Normal",
    "sg:classifiers":[
        {
            "category":"Shopping",
            "subcategory":"Florist",
            "type":"Retail Goods"
        },
        {
            "category":"Shopping",
            "subcategory":"Pharmacy",
            "type":"Retail Goods"
        },
        {
            "category":"Food & Beverages",
            "subcategory":"Groceries & Convenience Stores",
            "type":"Retail Goods"
        }
    ],
    "sg:phone":"+1 309 451 7100",
    "sg:postcode":"61761",
    "sg:province":"IL",
    "sg:website":"http://www.schnucks.com",
    "wof:name":"Schnucks Normal",
    "wof:placetype":"venue"
},
  "geometry": {"coordinates":[-88.99323800000001,40.531395],"type":"Point"}
}