{
  "type": "Feature",
  "properties": {
    "iso:country":"US",
    "sg:address":"2365 Wood Dr",
    "sg:city":"Beloit",
    "sg:classifiers":[
        {
            "category":"Professional",
            "type":"Services"
        }
    ],
    "sg:phone":"+1 608 365 6518",
    "sg:postcode":"53511",
    "sg:province":"IL",
    "sg:tags":[
        "establishment"
    ],
    "wof:name":"Dungarvin Wisconsin Inc",
    "wof:placetype":"venue"
},
  "geometry": {"coordinates":[-89.015959,42.535981],"type":"Point"}
}