{
  "type": "Feature",
  "properties": {
    "iso:country":"US",
    "sg:address":"4440 W 83rd St",
    "sg:city":"Chicago",
    "sg:classifiers":[
        {
            "category":"Education",
            "subcategory":"School",
            "type":"Public Place"
        }
    ],
    "sg:phone":"+1 773 582 8800",
    "sg:postcode":"60652",
    "sg:province":"IL",
    "wof:name":"St Bede Venerable School",
    "wof:placetype":"venue"
},
  "geometry": {"coordinates":[-87.732147,41.742071],"type":"Point"}
}