{
  "type": "Feature",
  "properties": {
    "iso:country":"US",
    "sg:address":"5355 W Devon Avenue",
    "sg:city":"Chicago",
    "sg:classifiers":[
        {
            "category":"Education",
            "subcategory":"Special Training",
            "type":"Public Place"
        }
    ],
    "sg:phone":"+1 773 775 7355",
    "sg:postcode":"60646",
    "sg:province":"IL",
    "sg:tags":[
        "school",
        "specialty"
    ],
    "wof:name":"Miranda Real Estate School",
    "wof:placetype":"venue"
},
  "geometry": {"coordinates":[-87.762992,41.997188],"type":"Point"}
}