{
  "type": "Feature",
  "properties": {
    "iso:country":"US",
    "sg:address":"1355 Holmes Rd",
    "sg:city":"Elgin",
    "sg:classifiers":[
        {
            "category":"Manufacturing",
            "subcategory":"Metals",
            "type":"Manufacturing & Wholesale Goods"
        }
    ],
    "sg:phone":"+1 847 695 8030",
    "sg:postcode":"60123",
    "sg:province":"IL",
    "sg:tags":[
        "machine",
        "screw",
        "product"
    ],
    "wof:name":"AMTEC Precision Products Inc",
    "wof:placetype":"venue"
},
  "geometry": {"coordinates":[-88.31029,42.069143],"type":"Point"}
}