{
  "type": "Feature",
  "properties": {
    "iso:country":"US",
    "sg:address":"904 S Cook St",
    "sg:city":"Barrington",
    "sg:classifiers":[
        {
            "category":"Building & Trades",
            "subcategory":"Plumbing",
            "type":"Services"
        }
    ],
    "sg:phone":"+1 847 304 4241",
    "sg:postcode":"60010",
    "sg:province":"IL",
    "wof:name":"Halan & Co Plumbing & Heating",
    "wof:placetype":"venue"
},
  "geometry": {"coordinates":[-88.13459400000001,42.14189],"type":"Point"}
}