{
  "type": "Feature",
  "properties": {
    "iso:country":"US",
    "sg:address":"601 W North Ave",
    "sg:city":"Flora",
    "sg:classifiers":[
        {
            "category":"Restaurant",
            "type":"Food & Drink"
        }
    ],
    "sg:phone":"+1 618 662 8185",
    "sg:postcode":"62839",
    "sg:province":"IL",
    "sg:tags":[
        "pizza"
    ],
    "wof:name":"Pizza Pit",
    "wof:placetype":"venue"
},
  "geometry": {"coordinates":[-88.47837800000001,38.670879],"type":"Point"}
}