{
  "type": "Feature",
  "properties": {
    "iso:country":"US",
    "sg:address":"704 Florsheim Dr Ste 10",
    "sg:city":"Libertyville",
    "sg:classifiers":[
        {
            "category":"Home & Garden",
            "subcategory":"Home Furnishings",
            "type":"Retail Goods"
        },
        {
            "category":"Real Estate",
            "subcategory":"Architect",
            "type":"Services"
        }
    ],
    "sg:phone":"+1 847 362 9373",
    "sg:postcode":"60048",
    "sg:province":"IL",
    "sg:tags":[
        "architects'",
        "designer",
        "residential",
        "specification",
        "builders'",
        "planning",
        "design",
        "architectural",
        "construction"
    ],
    "sg:website":"http://www.prevesassociates.com",
    "wof:name":"Richard Preves & Associates Pc",
    "wof:placetype":"venue"
},
  "geometry": {"coordinates":[-87.94580499999999,42.258203],"type":"Point"}
}