{
  "type": "Feature",
  "properties": {
    "iso:country":"US",
    "sg:address":"820 Lincoln Ave",
    "sg:city":"Charleston",
    "sg:classifiers":[
        {
            "category":"Real Estate",
            "subcategory":"Real Estate Operator",
            "type":"Services"
        }
    ],
    "sg:phone":"+1 217 348 7746",
    "sg:postcode":"61920",
    "sg:province":"IL",
    "sg:tags":[
        "apartment"
    ],
    "wof:name":"Carlyle Apartments",
    "wof:placetype":"venue"
},
  "geometry": {"coordinates":[-88.173155,39.484304],"type":"Point"}
}