{
  "type": "Feature",
  "properties": {
    "iso:country":"US",
    "sg:address":"108 W Germania Place",
    "sg:city":"Chicago",
    "sg:classifiers":[
        {
            "category":"Personal",
            "type":"Services"
        },
        {
            "category":"Retail",
            "subcategory":"Event Space",
            "type":"Services"
        }
    ],
    "sg:phone":"+1 312 573 1968",
    "sg:postcode":"60610",
    "sg:province":"IL",
    "sg:tags":[
        "party",
        "planning",
        "venue"
    ],
    "sg:website":"www.germaniaplace.com/",
    "wof:name":"Germania Place",
    "wof:placetype":"venue"
},
  "geometry": {"coordinates":[-87.631708,41.910491],"type":"Point"}
}