{
  "type": "Feature",
  "properties": {
    "addr:full":"1336 Hoffman Rd Murphysboro IL 62966",
    "addr:housenumber":"1336",
    "addr:postcode":"62966",
    "addr:street":"Hoffman Rd",
    "iso:country":"US",
    "sg:address":"1336 Hoffman Rd",
    "sg:city":"Murphysboro",
    "sg:classifiers":[
        {
            "category":"Home & Garden",
            "subcategory":"Building Materials",
            "type":"Retail Goods"
        },
        {
            "category":"Building & Trades",
            "subcategory":"Construction",
            "type":"Services"
        },
        {
            "category":"Manufacturing",
            "subcategory":"Building Materials",
            "type":"Manufacturing & Wholesale Goods"
        }
    ],
    "sg:phone":"+1 618 687 4824",
    "sg:postcode":"62966",
    "sg:province":"IL",
    "sg:tags":[
        "roofing",
        "supply",
        "shingle",
        "contractor",
        "equipment",
        "consultant",
        "improvement"
    ],
    "wof:name":"Gary D Clover's Roofing",
    "wof:placetype":"venue"
},
  "geometry": {"coordinates":[-89.348523,37.735629],"type":"Point"}
}