{
  "type": "Feature",
  "properties": {
    "iso:country":"US",
    "sg:address":"1312 Arthur St",
    "sg:city":"Calumet City",
    "sg:classifiers":[
        {
            "category":"Building & Trades",
            "subcategory":"Construction",
            "type":"Services"
        }
    ],
    "sg:phone":"+1 708 891 1764",
    "sg:postcode":"60409",
    "sg:province":"IL",
    "sg:tags":[
        "siding",
        "carpentry",
        "contractor"
    ],
    "wof:name":"Bills Carpentry and Siding",
    "wof:placetype":"venue"
},
  "geometry": {"coordinates":[-87.547595,41.594498],"type":"Point"}
}