{
  "type": "Feature",
  "properties": {
    "iso:country":"US",
    "sg:address":"5234 N Wayne Ave",
    "sg:city":"Chicago",
    "sg:classifiers":[
        {
            "category":"Professional",
            "subcategory":"Computer Services",
            "type":"Services"
        }
    ],
    "sg:phone":"+1 773 275 5039",
    "sg:postcode":"60640",
    "sg:province":"IL",
    "sg:tags":[
        "datum"
    ],
    "wof:name":"Interactive Visuals Inc",
    "wof:placetype":"venue"
},
  "geometry": {"coordinates":[-87.663662,41.977455],"type":"Point"}
}