{
  "type": "Feature",
  "properties": {
    "addr:full":"6264 Oakton St Morton Grove IL 60053",
    "addr:housenumber":"6264",
    "addr:postcode":"60053",
    "addr:street":"Oakton St",
    "iso:country":"US",
    "sg:address":"6264 Oakton St",
    "sg:city":"Morton Grove",
    "sg:classifiers":[
        {
            "category":"Autos & Motor Vehicles",
            "subcategory":"Automobile Sales",
            "type":"Retail Goods"
        }
    ],
    "sg:phone":"+1   ",
    "sg:postcode":"60053",
    "sg:province":"IL",
    "wof:name":"Prime Air Parts Inc",
    "wof:placetype":"venue"
},
  "geometry": {"coordinates":[-87.782546,42.026519],"type":"Point"}
}