{
  "type": "Feature",
  "properties": {
    "iso:country":"US",
    "sg:address":"421 Ridge Rd",
    "sg:city":"Wilmette",
    "sg:classifiers":[
        {
            "category":"Deli",
            "type":"Food & Drink"
        },
        {
            "category":"Food & Beverages",
            "subcategory":"Meat & Fish",
            "type":"Retail Goods"
        }
    ],
    "sg:phone":"+1 847 251 3601",
    "sg:postcode":"60091",
    "sg:province":"IL",
    "sg:tags":[
        "delicatessen",
        "market"
    ],
    "wof:name":"Norshore Meats & Deli",
    "wof:placetype":"venue"
},
  "geometry": {"coordinates":[-87.72259,42.072694],"type":"Point"}
}