{
  "type": "Feature",
  "properties": {
    "addr:full":"572 N Melrose Ave Elgin IL 60123",
    "addr:housenumber":"572",
    "addr:postcode":"60123",
    "addr:street":"N Melrose Ave",
    "iso:country":"US",
    "sg:address":"572 N Melrose Ave",
    "sg:city":"Elgin",
    "sg:classifiers":[
        {
            "category":"Professional",
            "type":"Services"
        }
    ],
    "sg:phone":"+1 847 697 6025",
    "sg:postcode":"60123",
    "sg:province":"IL",
    "sg:tags":[
        "establishment"
    ],
    "wof:name":"Gladwin A Read Co",
    "wof:placetype":"venue"
},
  "geometry": {"coordinates":[-88.307946,42.045834],"type":"Point"}
}