{
  "type": "Feature",
  "properties": {
    "iso:country":"US",
    "sg:address":"800 Ravinia Pl",
    "sg:city":"Orland Park",
    "sg:classifiers":[
        {
            "category":"Professional",
            "subcategory":"Lawyer & Legal Services",
            "type":"Services"
        }
    ],
    "sg:phone":"+1 708 226 2700",
    "sg:postcode":"60462",
    "sg:province":"IL",
    "sg:tags":[
        "law"
    ],
    "wof:name":"Grochcinski Grochocinski Lloyd",
    "wof:placetype":"venue"
},
  "geometry": {"coordinates":[-87.853472,41.615341],"type":"Point"}
}