{
  "type": "Feature",
  "properties": {
    "addr:full":"606 W Grove St Arlington Heights IL 60005",
    "addr:housenumber":"606",
    "addr:postcode":"60005",
    "addr:street":"W Grove St",
    "iso:country":"US",
    "sg:address":"606 W Grove St",
    "sg:city":"Arlington Heights",
    "sg:classifiers":[
        {
            "category":"Utilities",
            "type":"Services"
        }
    ],
    "sg:phone":"+1 847 818 8546",
    "sg:postcode":"60005",
    "sg:province":"IL",
    "sg:tags":[
        "sanitary"
    ],
    "wof:name":"Northwest Clean Sweep",
    "wof:placetype":"venue"
},
  "geometry": {"coordinates":[-87.991822,42.077515],"type":"Point"}
}