{
  "type": "Feature",
  "properties": {
    "addr:full":"211 E Ontario St Ste 1800 Chicago IL 60611",
    "addr:housenumber":"211",
    "addr:postcode":"60611",
    "addr:street":"E Ontario St Ste 1800",
    "iso:country":"US",
    "sg:address":"211 E Ontario St Ste 1800",
    "sg:city":"Chicago",
    "sg:phone":"+1 312 730 8110",
    "sg:postcode":"60611",
    "sg:province":"IL",
    "wof:name":"Pechenik, Alexander - Law Office of Alexander Pechenik",
    "wof:placetype":"venue"
},
  "geometry": {"coordinates":[-87.622469,41.893365],"type":"Point"}
}