{
  "type": "Feature",
  "properties": {
    "iso:country":"US",
    "sg:address":"465 Golf Rd",
    "sg:city":"Crystal Lake",
    "sg:classifiers":[
        {
            "category":"Building & Trades",
            "subcategory":"Construction",
            "type":"Services"
        }
    ],
    "sg:phone":"+1 815 459 8245",
    "sg:postcode":"60014",
    "sg:province":"IL",
    "sg:tags":[
        "motion",
        "p",
        "industrial"
    ],
    "wof:name":"Fraser SM Inc",
    "wof:placetype":"venue"
},
  "geometry": {"coordinates":[-88.337681,42.227542],"type":"Point"}
}