{
  "type": "Feature",
  "properties": {
    "iso:country":"US",
    "sg:address":"1620 Ranch Dr",
    "sg:city":"Mc Henry",
    "sg:classifiers":[
        {
            "category":"Personal",
            "subcategory":"Beauty Salon",
            "type":"Services"
        }
    ],
    "sg:phone":"+1 815 385 0687",
    "sg:postcode":"60051",
    "sg:province":"IL",
    "sg:tags":[
        "shop"
    ],
    "wof:name":"Saunders Scissors & Supply",
    "wof:placetype":"venue"
},
  "geometry": {"coordinates":[-88.224687,42.352255],"type":"Point"}
}