{
  "type": "Feature",
  "properties": {
    "addr:full":"636 S Wabash Ave Chicago IL 60605",
    "addr:housenumber":"636",
    "addr:postcode":"60605",
    "addr:street":"S Wabash Ave",
    "iso:country":"US",
    "sg:address":"636 S Wabash Ave",
    "sg:city":"Chicago",
    "sg:classifiers":[
        {
            "category":"Fast Food",
            "type":"Food & Drink"
        }
    ],
    "sg:phone":"+1 312 362 0442",
    "sg:postcode":"60605",
    "sg:province":"IL",
    "sg:tags":[
        "chicken",
        "wing"
    ],
    "sg:website":"haroldschicken.com",
    "wof:name":"Harold's Chicken Shack",
    "wof:placetype":"venue"
},
  "geometry": {"coordinates":[-87.626099,41.8736],"type":"Point"}
}