{
  "type": "Feature",
  "properties": {
    "addr:full":"505 N Kinzie Ave Bradley IL 60915",
    "addr:housenumber":"505",
    "addr:postcode":"60915",
    "addr:street":"N Kinzie Ave",
    "iso:country":"US",
    "sg:address":"505 N Kinzie Ave",
    "sg:city":"Bradley",
    "sg:classifiers":[
        {
            "category":"Restaurant",
            "type":"Food & Drink"
        }
    ],
    "sg:phone":"+1   ",
    "sg:postcode":"60915",
    "sg:province":"IL",
    "sg:tags":[
        "eating"
    ],
    "wof:name":"Bibs Restaurant",
    "wof:placetype":"venue"
},
  "geometry": {"coordinates":[-87.85099700000001,41.151409],"type":"Point"}
}