{
  "type": "Feature",
  "properties": {
    "addr:full":"7080 Carpenter Rd Skokie IL 60077",
    "addr:housenumber":"7080",
    "addr:postcode":"60077",
    "addr:street":"Carpenter Rd",
    "iso:country":"US",
    "sg:address":"7080 Carpenter Rd",
    "sg:city":"Skokie",
    "sg:classifiers":[
        {
            "category":"Banks & Credit Unions",
            "subcategory":"Bank",
            "type":"Services"
        },
        {
            "category":"Banks & Credit Unions",
            "subcategory":"Financial Services",
            "type":"Services"
        }
    ],
    "sg:phone":"+1 847 677 1250",
    "sg:postcode":"60077",
    "sg:province":"IL",
    "sg:tags":[
        "commercial",
        "loan",
        "internet",
        "saving",
        "banking"
    ],
    "sg:website":"http://www.computer-plus.com",
    "wof:name":"Bank Of America",
    "wof:placetype":"venue"
},
  "geometry": {"coordinates":[-87.761628,42.010221],"type":"Point"}
}