{
  "type": "Feature",
  "properties": {
    "addr:full":"1485 W Broadway Centralia IL 62801",
    "addr:housenumber":"1485",
    "addr:postcode":"62801",
    "addr:street":"W Broadway",
    "iso:country":"US",
    "sg:address":"1485 W Broadway",
    "sg:city":"Centralia",
    "sg:classifiers":[
        {
            "category":"Restaurant",
            "type":"Food & Drink"
        }
    ],
    "sg:menulink":"http://www.allmenus.com/il/brookside/212189-mcdonalds/menu/",
    "sg:postcode":"62801",
    "sg:province":"IL",
    "sg:tags":[
        "burger",
        "american"
    ],
    "wof:name":"McDonald's",
    "wof:placetype":"venue"
},
  "geometry": {"coordinates":[-89.158911,38.532935],"type":"Point"}
}