{
  "type": "Feature",
  "properties": {
    "iso:country":"US",
    "sg:address":"205 Sycamore St",
    "sg:city":"Gladstone",
    "sg:classifiers":[
        {
            "category":"Freight",
            "type":"Transportation"
        }
    ],
    "sg:phone":"+1 309 627 2098",
    "sg:postcode":"61465",
    "sg:province":"IL",
    "sg:tags":[
        "commercial",
        "storage"
    ],
    "wof:name":"Gordon's Storage",
    "wof:placetype":"venue"
},
  "geometry": {"coordinates":[-90.439578,41.200054],"type":"Point"}
}