{
  "type": "Feature",
  "properties": {
    "iso:country":"US",
    "sg:address":"2915 W Palmer St",
    "sg:city":"Chicago",
    "sg:classifiers":[
        {
            "category":"Organizations",
            "subcategory":"Religious Organization",
            "type":"Services"
        }
    ],
    "sg:phone":"+1 773 278 8253",
    "sg:postcode":"60647",
    "sg:province":"IL",
    "sg:tags":[
        "monastery",
        "convent"
    ],
    "wof:name":"Convent St Sylvesters",
    "wof:placetype":"venue"
},
  "geometry": {"coordinates":[-87.701774,41.921445],"type":"Point"}
}