{
  "type": "Feature",
  "properties": {
    "addr:full":"129 W Main St Aledo IL 61231",
    "addr:housenumber":"129",
    "addr:postcode":"61231",
    "addr:street":"W Main St",
    "iso:country":"US",
    "sg:address":"129 W Main St",
    "sg:city":"Aledo",
    "sg:classifiers":[
        {
            "category":"Shopping",
            "type":"Retail Goods"
        }
    ],
    "sg:phone":"+1 309 582 3440",
    "sg:postcode":"61231",
    "sg:province":"IL",
    "sg:tags":[
        "monument"
    ],
    "wof:name":"Mc Fall Monument",
    "wof:placetype":"venue"
},
  "geometry": {"coordinates":[-90.750117,41.20176],"type":"Point"}
}