{
  "type": "Feature",
  "properties": {
    "addr:full":"2868 W Dickens Ave Chicago IL 60647",
    "addr:housenumber":"2868",
    "addr:postcode":"60647",
    "addr:street":"W Dickens Ave",
    "iso:country":"US",
    "sg:address":"2868 W Dickens Ave",
    "sg:city":"Chicago",
    "sg:classifiers":[
        {
            "category":"Autos & Motor Vehicles",
            "subcategory":"Auto Supplies",
            "type":"Retail Goods"
        }
    ],
    "sg:phone":"+1 312 342 7491",
    "sg:postcode":"60647",
    "sg:province":"IL",
    "sg:tags":[
        "wheel"
    ],
    "wof:name":"Wonder Wheel",
    "wof:placetype":"venue"
},
  "geometry": {"coordinates":[-87.69939599999999,41.91958],"type":"Point"}
}