{
  "type": "Feature",
  "properties": {
    "iso:country":"US",
    "sg:address":"861 Co Rd 2500 E",
    "sg:city":"Homer",
    "sg:phone":"+1 217 896 2596",
    "sg:postcode":"61849",
    "sg:province":"IL",
    "sg:tags":[
        "farm",
        "corn",
        "soybean"
    ],
    "wof:name":"Craddock Farms",
    "wof:placetype":"venue"
},
  "geometry": {"coordinates":[-87.994416,40.005876],"type":"Point"}
}