{
  "type": "Feature",
  "properties": {
    "iso:country":"US",
    "sg:address":"1306 Wabash Ave",
    "sg:city":"Belleville",
    "sg:classifiers":[
        {
            "category":"Health Services",
            "subcategory":"Health Practitioner",
            "type":"Services"
        }
    ],
    "sg:phone":"+1 618 234 8146",
    "sg:postcode":"62220",
    "sg:province":"IL",
    "sg:tags":[
        "therapist",
        "physical"
    ],
    "sg:website":"www.specialchildren.net",
    "wof:name":"Prime Care Pediatric Therapy",
    "wof:placetype":"venue"
},
  "geometry": {"coordinates":[-89.96664,38.499946],"type":"Point"}
}