{
  "type": "Feature",
  "properties": {
    "iso:country":"US",
    "sg:address":"5135 W Addison St",
    "sg:city":"Chicago",
    "sg:classifiers":[
        {
            "category":"Building & Trades",
            "subcategory":"Construction",
            "type":"Services"
        }
    ],
    "sg:phone":"+1 773 685 3590",
    "sg:postcode":"60641",
    "sg:province":"IL",
    "sg:tags":[
        "house"
    ],
    "wof:name":"Sylmark Construction Inc",
    "wof:placetype":"venue"
},
  "geometry": {"coordinates":[-87.756191,41.945935],"type":"Point"}
}