{
  "type": "Feature",
  "properties": {
    "iso:country":"US",
    "sg:address":"832 Deer Path Ln",
    "sg:city":"Elwood",
    "sg:classifiers":[
        {
            "category":"Building & Trades",
            "subcategory":"Construction",
            "type":"Services"
        }
    ],
    "sg:phone":"+1 815 424 0225",
    "sg:postcode":"60421",
    "sg:province":"IL",
    "sg:tags":[
        "wallcoverings-installation",
        "wallpaper",
        "painting",
        "contractor"
    ],
    "wof:name":"Elaine Neese Painter",
    "wof:placetype":"venue"
},
  "geometry": {"coordinates":[-88.109326,41.412737],"type":"Point"}
}