{
  "type": "Feature",
  "properties": {
    "addr:full":"1438 W 103rd St Chicago IL 60643",
    "addr:housenumber":"1438",
    "addr:postcode":"60643",
    "addr:street":"W 103Rd St",
    "iso:country":"US",
    "sg:address":"1438 W 103rd St",
    "sg:city":"Chicago",
    "sg:classifiers":[
        {
            "category":"Food & Beverages",
            "subcategory":"Groceries & Convenience Stores",
            "type":"Retail Goods"
        }
    ],
    "sg:phone":"+1 773 429 8951",
    "sg:postcode":"60643",
    "sg:province":"IL",
    "wof:name":"Sam's Food Mart",
    "wof:placetype":"venue"
},
  "geometry": {"coordinates":[-87.658632,41.706877],"type":"Point"}
}