{
  "type": "Feature",
  "properties": {
    "addr:full":"739 W Belmont Avenue Chicago IL 60657",
    "addr:housenumber":"739",
    "addr:postcode":"60657",
    "addr:street":"W Belmont Avenue",
    "iso:country":"US",
    "sg:address":"739 W Belmont Avenue",
    "sg:city":"Chicago",
    "sg:classifiers":[
        {
            "category":"Health Services",
            "subcategory":"Dentist",
            "type":"Services"
        }
    ],
    "sg:phone":"+1 773 248 8813",
    "sg:postcode":"60657",
    "sg:province":"IL",
    "wof:name":"Drake David B",
    "wof:placetype":"venue"
},
  "geometry": {"coordinates":[-87.64840599999999,41.939976],"type":"Point"}
}