{
  "type": "Feature",
  "properties": {
    "iso:country":"US",
    "sg:address":"634 N Austin Blvd",
    "sg:city":"Oak Park",
    "sg:classifiers":[
        {
            "category":"Organizations",
            "subcategory":"Religious Organization",
            "type":"Services"
        }
    ],
    "sg:phone":"+1 708 386 5664",
    "sg:postcode":"60302",
    "sg:province":"IL",
    "wof:name":"Austin Blvd Church",
    "wof:placetype":"venue"
},
  "geometry": {"coordinates":[-87.775063,41.892704],"type":"Point"}
}