{
  "type": "Feature",
  "properties": {
    "addr:full":"74 Ogden Ave Downers Grove IL 60515",
    "addr:housenumber":"74",
    "addr:postcode":"60515",
    "addr:street":"Ogden Ave",
    "iso:country":"US",
    "sg:address":"74 Ogden Ave",
    "sg:city":"Downers Grove",
    "sg:classifiers":[
        {
            "category":"Restaurant",
            "type":"Food & Drink"
        }
    ],
    "sg:menulink":"http://www.allmenus.com/il/downers-grove/240225-panda-express/menu/",
    "sg:phone":"+1 630 663 1260",
    "sg:postcode":"60515",
    "sg:province":"IL",
    "sg:tags":[
        "asian",
        "chinese"
    ],
    "wof:name":"Panda Express",
    "wof:placetype":"venue"
},
  "geometry": {"coordinates":[-87.986722,41.809904],"type":"Point"}
}