{
  "type": "Feature",
  "properties": {
    "iso:country":"US",
    "sg:address":"11275 W 143rd St",
    "sg:city":"Orland Park",
    "sg:classifiers":[
        {
            "category":"Banks & Credit Unions",
            "subcategory":"Bank",
            "type":"Services"
        }
    ],
    "sg:phone":"+1 708 364 7400",
    "sg:postcode":"60467",
    "sg:province":"IL",
    "wof:name":"A J Smith Federal Savings Bank",
    "wof:placetype":"venue"
},
  "geometry": {"coordinates":[-87.89537199999999,41.629715],"type":"Point"}
}