{
  "type": "Feature",
  "properties": {
    "iso:country":"US",
    "sg:address":"17310 Odell Ave",
    "sg:city":"Tinley Park",
    "sg:classifiers":[
        {
            "category":"Travel",
            "subcategory":"Travel Agent",
            "type":"Entertainment"
        }
    ],
    "sg:phone":"+1 708 532 9440",
    "sg:postcode":"60477",
    "sg:province":"IL",
    "sg:tags":[
        "agency"
    ],
    "wof:name":"Ship Ahoy Cruises",
    "wof:placetype":"venue"
},
  "geometry": {"coordinates":[-87.797033,41.576254],"type":"Point"}
}