{
  "type": "Feature",
  "properties": {
    "addr:full":"2534 N Greenview Avenue Chicago IL 60614",
    "addr:housenumber":"2534",
    "addr:postcode":"60614",
    "addr:street":"N Greenview Avenue",
    "iso:country":"US",
    "sg:address":"2534 N Greenview Avenue",
    "sg:city":"Chicago",
    "sg:classifiers":[
        {
            "category":"Park",
            "type":"Public Place"
        }
    ],
    "sg:phone":"+1 312 742 7816",
    "sg:postcode":"60614",
    "sg:province":"IL",
    "wof:name":"Chicago Park District",
    "wof:placetype":"venue"
},
  "geometry": {"coordinates":[-87.665668,41.928254],"type":"Point"}
}