{
  "type": "Feature",
  "properties": {
    "iso:country":"US",
    "sg:address":"961 W Wood St",
    "sg:city":"Palatine",
    "sg:classifiers":[
        {
            "category":"Wholesale",
            "subcategory":"Non-durable Goods",
            "type":"Manufacturing & Wholesale Goods"
        }
    ],
    "sg:phone":"+1 847 776 6815",
    "sg:postcode":"60067",
    "sg:province":"IL",
    "sg:tags":[
        "promotional"
    ],
    "wof:name":"Lighthouse Incentives",
    "wof:placetype":"venue"
},
  "geometry": {"coordinates":[-88.066622,42.113953],"type":"Point"}
}