{
  "type": "Feature",
  "properties": {
    "addr:full":"7340 15th St Forest Park IL 60130",
    "addr:housenumber":"7340",
    "addr:postcode":"60130",
    "addr:street":"15Th St",
    "iso:country":"US",
    "sg:address":"7340 15th St",
    "sg:city":"Forest Park",
    "sg:classifiers":[
        {
            "category":"Building & Trades",
            "subcategory":"Electrical",
            "type":"Services"
        }
    ],
    "sg:phone":"+1 708 366 2400",
    "sg:postcode":"60130",
    "sg:province":"IL",
    "sg:tags":[
        "specializing",
        "system",
        "contractor",
        "safety",
        "security",
        "ins"
    ],
    "wof:name":"III Alarm Service",
    "wof:placetype":"venue"
},
  "geometry": {"coordinates":[-87.808672,41.859406],"type":"Point"}
}