{
  "type": "Feature",
  "properties": {
    "addr:full":"5303 W 123rd Pl Alsip IL 60803",
    "addr:housenumber":"5303",
    "addr:postcode":"60803",
    "addr:street":"W 123Rd Pl",
    "iso:country":"US",
    "sg:address":"5303 W 123rd Pl",
    "sg:city":"Alsip",
    "sg:classifiers":[
        {
            "category":"Manufacturing",
            "subcategory":"Metals",
            "type":"Manufacturing & Wholesale Goods"
        }
    ],
    "sg:phone":"+1 773 568 4950",
    "sg:postcode":"60803",
    "sg:province":"IL",
    "sg:tags":[
        "fabricates"
    ],
    "wof:name":"Allsteel Indus Met Fabricators",
    "wof:placetype":"venue"
},
  "geometry": {"coordinates":[-87.750197,41.668025],"type":"Point"}
}