{
  "type": "Feature",
  "properties": {
    "addr:full":"270 E 102nd Street Chicago IL 60628",
    "addr:housenumber":"270",
    "addr:postcode":"60628",
    "addr:street":"E 102Nd Street",
    "iso:country":"US",
    "sg:address":"270 E 102nd Street",
    "sg:city":"Chicago",
    "sg:classifiers":[
        {
            "category":"Education",
            "subcategory":"School",
            "type":"Public Place"
        }
    ],
    "sg:phone":"+1 773 535 5364",
    "sg:postcode":"60628",
    "sg:province":"IL",
    "wof:name":"Schools Public",
    "wof:placetype":"venue"
},
  "geometry": {"coordinates":[-87.623099,41.693653],"type":"Point"}
}