{
  "type": "Feature",
  "properties": {
    "addr:full":"848 W 27th St Chicago IL 60608",
    "addr:housenumber":"848",
    "addr:postcode":"60608",
    "addr:street":"W 27Th St",
    "iso:country":"US",
    "sg:address":"848 W 27th St",
    "sg:city":"Chicago",
    "sg:classifiers":[
        {
            "category":"Organizations",
            "subcategory":"Membership Organization",
            "type":"Services"
        }
    ],
    "sg:phone":"+1 312 326 5882",
    "sg:postcode":"60608",
    "sg:province":"IL",
    "sg:tags":[
        "fraternal"
    ],
    "sg:website":"http://www.kofc.org",
    "wof:name":"Knights of Columbus",
    "wof:placetype":"venue"
},
  "geometry": {"coordinates":[-87.64825999999999,41.844448],"type":"Point"}
}