{
  "type": "Feature",
  "properties": {
    "addr:full":"8105 Forest Hills Rd Loves Park IL 61111",
    "addr:housenumber":"8105",
    "addr:postcode":"61111",
    "addr:street":"Forest Hills Rd",
    "iso:country":"US",
    "sg:address":"8105 Forest Hills Rd",
    "sg:city":"Loves Park",
    "sg:classifiers":[
        {
            "category":"Shopping",
            "subcategory":"Gifts & Souvenirs",
            "type":"Retail Goods"
        }
    ],
    "sg:phone":"+1 815 877 6608",
    "sg:postcode":"61111",
    "sg:province":"IL",
    "sg:tags":[
        "shop"
    ],
    "wof:name":"Trinket-N-Treasures",
    "wof:placetype":"venue"
},
  "geometry": {"coordinates":[-89.017027,42.342094],"type":"Point"}
}