{
  "type": "Feature",
  "properties": {
    "iso:country":"US",
    "sg:address":"10345 S Western Avenue",
    "sg:city":"Chicago",
    "sg:classifiers":[
        {
            "category":"Professional",
            "subcategory":"Lawyer & Legal Services",
            "type":"Services"
        }
    ],
    "sg:phone":"+1 773 233 5700",
    "sg:postcode":"60643",
    "sg:province":"IL",
    "wof:name":"Burke James J Atty",
    "wof:placetype":"venue"
},
  "geometry": {"coordinates":[-87.681366,41.705152],"type":"Point"}
}