{
  "type": "Feature",
  "properties": {
    "iso:country":"US",
    "sg:address":"14 W Edwardsville Rd",
    "sg:city":"Wood River",
    "sg:classifiers":[
        {
            "category":"Banks & Credit Unions",
            "subcategory":"Bank",
            "type":"Services"
        }
    ],
    "sg:phone":"+1 618 254 7686",
    "sg:postcode":"62095",
    "sg:province":"IL",
    "sg:tags":[
        "personal",
        "institution"
    ],
    "wof:name":"Advance America",
    "wof:placetype":"venue"
},
  "geometry": {"coordinates":[-90.09997,38.874393],"type":"Point"}
}