{
  "type": "Feature",
  "properties": {
    "iso:country":"US",
    "sg:address":"2627 W 63rd St",
    "sg:city":"Chicago",
    "sg:classifiers":[
        {
            "category":"Food & Beverages",
            "subcategory":"Liquor & Beverages",
            "type":"Retail Goods"
        }
    ],
    "sg:phone":"+1 773 436 7085",
    "sg:postcode":"60629",
    "sg:province":"IL",
    "sg:tags":[
        "beer",
        "spirit",
        "wine"
    ],
    "wof:name":"Midwest Candy Enterprise",
    "wof:placetype":"venue"
},
  "geometry": {"coordinates":[-87.68940000000001,41.778999],"type":"Point"}
}