{
  "type": "Feature",
  "properties": {
    "addr:full":"595 N Pinecrest Rd Bolingbrook IL 60440",
    "addr:housenumber":"595",
    "addr:postcode":"60440",
    "addr:street":"N Pinecrest Rd",
    "iso:country":"US",
    "sg:address":"595 N Pinecrest Rd",
    "sg:city":"Bolingbrook",
    "sg:classifiers":[
        {
            "category":"Shopping",
            "subcategory":"Clothing, Apparel, & Fashions",
            "type":"Retail Goods"
        },
        {
            "category":"Personal",
            "type":"Services"
        }
    ],
    "sg:phone":"+1 630 812 0387",
    "sg:postcode":"60440",
    "sg:province":"IL",
    "sg:tags":[
        "telegrams-novelty",
        "costume"
    ],
    "sg:website":"http://www.illusionscotume.com",
    "wof:name":"Illusions Costume Company",
    "wof:placetype":"venue"
},
  "geometry": {"coordinates":[-88.050235,41.717231],"type":"Point"}
}