{
  "type": "Feature",
  "properties": {
    "addr:full":"31 Danada Sq E Wheaton IL 60187",
    "addr:housenumber":"31",
    "addr:postcode":"60187",
    "addr:street":"Danada Sq E",
    "iso:country":"US",
    "sg:address":"31 Danada Sq E",
    "sg:city":"Wheaton",
    "sg:classifiers":[
        {
            "category":"Shopping",
            "subcategory":"Computers & Home Electronics",
            "type":"Retail Goods"
        }
    ],
    "sg:phone":"+1   ",
    "sg:postcode":"60187",
    "sg:province":"IL",
    "wof:name":"Radio Shack",
    "wof:placetype":"venue"
},
  "geometry": {"coordinates":[-88.10216200000001,41.832901],"type":"Point"}
}