{
  "type": "Feature",
  "properties": {
    "iso:country":"US",
    "sg:address":"1640 Tilton Rd",
    "sg:city":"Tilton",
    "sg:classifiers":[
        {
            "category":"Utilities",
            "subcategory":"Fuel Oil & Lpg",
            "type":"Services"
        }
    ],
    "sg:phone":"+1 217 446 0795",
    "sg:postcode":"61833",
    "sg:province":"IL",
    "sg:tags":[
        "propane",
        "gas"
    ],
    "wof:name":"Ferrellgas",
    "wof:placetype":"venue"
},
  "geometry": {"coordinates":[-87.641293,40.104139],"type":"Point"}
}