{
  "type": "Feature",
  "properties": {
    "iso:country":"US",
    "sg:address":"1121 Stanton Rd",
    "sg:city":"Lake Zurich",
    "sg:classifiers":[
        {
            "category":"Building & Trades",
            "subcategory":"Landscaping Services",
            "type":"Services"
        }
    ],
    "sg:phone":"+1 847 438 1946",
    "sg:postcode":"60047",
    "sg:province":"IL",
    "sg:tags":[
        "designer",
        "landscape"
    ],
    "wof:name":"Brandon Groves Landscape Arch",
    "wof:placetype":"venue"
},
  "geometry": {"coordinates":[-88.065648,42.187451],"type":"Point"}
}