{
  "type": "Feature",
  "properties": {
    "addr:full":"4016 Seeley Ave Downers Grove IL 60515",
    "addr:housenumber":"4016",
    "addr:postcode":"60515",
    "addr:street":"Seeley Ave",
    "iso:country":"US",
    "sg:address":"4016 Seeley Ave",
    "sg:city":"Downers Grove",
    "sg:classifiers":[
        {
            "category":"Professional",
            "subcategory":"Management & Consulting",
            "type":"Services"
        }
    ],
    "sg:phone":"+1 630 541 6736",
    "sg:postcode":"60515",
    "sg:province":"IL",
    "sg:tags":[
        "computer",
        "business",
        "programing",
        "custom"
    ],
    "wof:name":"Xpertex LLC",
    "wof:placetype":"venue"
},
  "geometry": {"coordinates":[-88.023048,41.814487],"type":"Point"}
}