{
  "type": "Feature",
  "properties": {
    "iso:country":"US",
    "sg:address":"1916 16th St",
    "sg:city":"North Chicago",
    "sg:classifiers":[
        {
            "category":"Health Services",
            "subcategory":"Nursing And Care Facility",
            "type":"Services"
        }
    ],
    "sg:phone":"+1 847 473 2811",
    "sg:postcode":"60064",
    "sg:province":"IL",
    "sg:tags":[
        "home",
        "convalescent"
    ],
    "wof:name":"Lewis Terrace",
    "wof:placetype":"venue"
},
  "geometry": {"coordinates":[-87.855789,42.330595],"type":"Point"}
}