{
  "type": "Feature",
  "properties": {
    "iso:country":"US",
    "sg:address":"218 Lake St",
    "sg:city":"Oak Park",
    "sg:classifiers":[
        {
            "category":"Professional",
            "subcategory":"Lawyer & Legal Services",
            "type":"Services"
        }
    ],
    "sg:phone":"+1 708 386 4900",
    "sg:postcode":"60302",
    "sg:province":"IL",
    "wof:name":"Rifis Jordan B Attorney At Law",
    "wof:placetype":"venue"
},
  "geometry": {"coordinates":[-87.7808,41.888199],"type":"Point"}
}