{
  "type": "Feature",
  "properties": {
    "iso:country":"US",
    "sg:address":"3300 E State St",
    "sg:city":"Rockford",
    "sg:classifiers":[
        {
            "category":"Banks & Credit Unions",
            "subcategory":"Investment Brokerage",
            "type":"Services"
        }
    ],
    "sg:phone":"+1 815 509 3169",
    "sg:postcode":"61108",
    "sg:province":"IL",
    "sg:tags":[
        "trust"
    ],
    "wof:name":"District 100 Foundation For Excellence In Educatio",
    "wof:placetype":"venue"
},
  "geometry": {"coordinates":[-89.045258,42.266449],"type":"Point"}
}