{
  "type": "Feature",
  "properties": {
    "iso:country":"US",
    "sg:address":"14430 Shepard Dr",
    "sg:city":"Dolton",
    "sg:classifiers":[
        {
            "category":"Personal",
            "subcategory":"Beauty Salon",
            "type":"Services"
        }
    ],
    "sg:phone":"+1 708 880 0603",
    "sg:postcode":"60419",
    "sg:province":"IL",
    "wof:name":"Hair Style",
    "wof:placetype":"venue"
},
  "geometry": {"coordinates":[-87.595834,41.632168],"type":"Point"}
}