{
  "type": "Feature",
  "properties": {
    "addr:full":"1521 N Sandburg Ter Chicago IL 60610",
    "addr:housenumber":"1521",
    "addr:postcode":"60610",
    "addr:street":"N Sandburg Ter",
    "iso:country":"US",
    "sg:address":"1521 N Sandburg Ter",
    "sg:city":"Chicago",
    "sg:classifiers":[
        {
            "category":"Real Estate",
            "subcategory":"Architect",
            "type":"Services"
        }
    ],
    "sg:phone":"+1 312 337 9879",
    "sg:postcode":"60610",
    "sg:province":"IL",
    "wof:name":"Vranas Olsen",
    "wof:placetype":"venue"
},
  "geometry": {"coordinates":[-87.63216799999999,41.909958],"type":"Point"}
}