{
  "type": "Feature",
  "properties": {
    "iso:country":"US",
    "sg:address":"1674 N Alpine Rd",
    "sg:city":"Rockford",
    "sg:classifiers":[
        {
            "category":"Restaurant",
            "type":"Food & Drink"
        }
    ],
    "sg:menulink":"http://www.allmenus.com/il/rockford/79946-pizza-hut/menu/",
    "sg:phone":"+1 815 226 1110",
    "sg:postcode":"61107",
    "sg:province":"IL",
    "sg:tags":[
        "american",
        "pizza"
    ],
    "wof:name":"Pizza Hut",
    "wof:placetype":"venue"
},
  "geometry": {"coordinates":[-89.0291,42.285878],"type":"Point"}
}