{
  "type": "Feature",
  "properties": {
    "iso:country":"US",
    "sg:address":"135 W Main St",
    "sg:city":"Mascoutah",
    "sg:classifiers":[
        {
            "category":"Organizations",
            "subcategory":"Religious Organization",
            "type":"Services"
        }
    ],
    "sg:phone":"+1 618 566 2704",
    "sg:postcode":"62258",
    "sg:province":"IL",
    "sg:tags":[
        "place",
        "assembly",
        "worship",
        "god",
        "church"
    ],
    "wof:name":"First Assembly Of God (Inc)",
    "wof:placetype":"venue"
},
  "geometry": {"coordinates":[-89.801294,38.490292],"type":"Point"}
}