{
  "type": "Feature",
  "properties": {
    "iso:country":"US",
    "sg:address":"55 E Park Blvd",
    "sg:city":"Villa Park",
    "sg:classifiers":[
        {
            "category":"Health Services",
            "subcategory":"Doctor",
            "type":"Services"
        }
    ],
    "sg:phone":"+1 630 834 4878",
    "sg:postcode":"60181",
    "sg:province":"IL",
    "sg:tags":[
        "dentist"
    ],
    "wof:name":"Dean P Nicholas & Associates",
    "wof:placetype":"venue"
},
  "geometry": {"coordinates":[-87.974217,41.8844],"type":"Point"}
}