{
  "type": "Feature",
  "properties": {
    "iso:country":"US",
    "sg:address":"406 N Schuyler Ave",
    "sg:city":"Kankakee",
    "sg:classifiers":[
        {
            "category":"Restaurant",
            "type":"Food & Drink"
        }
    ],
    "sg:phone":"+1 815 929 0178",
    "sg:postcode":"60901",
    "sg:province":"IL",
    "sg:tags":[
        "barbecue"
    ],
    "wof:name":"Ruth & Lennie's Barbeque",
    "wof:placetype":"venue"
},
  "geometry": {"coordinates":[-87.862952,41.124933],"type":"Point"}
}