{
  "type": "Feature",
  "properties": {
    "iso:country":"US",
    "sg:address":"270 Remington Blvd",
    "sg:city":"Bolingbrook",
    "sg:classifiers":[
        {
            "category":"Professional",
            "subcategory":"Detective & Security Services",
            "type":"Services"
        }
    ],
    "sg:phone":"+1 630 771 0800",
    "sg:postcode":"60440",
    "sg:province":"IL",
    "sg:tags":[
        "airport",
        "for"
    ],
    "wof:name":"Convenant Aviation SEC LLC",
    "wof:placetype":"venue"
},
  "geometry": {"coordinates":[-88.07301,41.684769],"type":"Point"}
}