{
  "type": "Feature",
  "properties": {
    "iso:country":"US",
    "sg:address":"8839 Camp Drake Rd",
    "sg:city":"Fairmount",
    "sg:classifiers":[
        {
            "category":"Real Estate",
            "subcategory":"Real Estate Operator",
            "type":"Services"
        }
    ],
    "sg:phone":"+1 217 733 2351",
    "sg:postcode":"61841",
    "sg:province":"IL",
    "sg:tags":[
        "property",
        "lessor"
    ],
    "wof:name":"Paul Cooley",
    "wof:placetype":"venue"
},
  "geometry": {"coordinates":[-87.77447,40.079409],"type":"Point"}
}