{
  "type": "Feature",
  "properties": {
    "iso:country":"US",
    "sg:address":"2323 Burr Oak Ave",
    "sg:city":"Blue Island",
    "sg:classifiers":[
        {
            "category":"Bakery",
            "type":"Food & Drink"
        },
        {
            "category":"Coffee & Tea",
            "type":"Food & Drink"
        },
        {
            "category":"Bagels",
            "type":"Food & Drink"
        },
        {
            "category":"Donuts",
            "type":"Food & Drink"
        }
    ],
    "sg:menulink":"http://www.allmenus.com/il/calumet/134978-dunkin-donuts/menu/",
    "sg:phone":"+1 708 371 8558",
    "sg:postcode":"60406",
    "sg:province":"IL",
    "sg:tags":[
        "american",
        "pastry"
    ],
    "wof:name":"Dunkin' Donuts",
    "wof:placetype":"venue"
},
  "geometry": {"coordinates":[-87.67860899999999,41.66254],"type":"Point"}
}