{
  "type": "Feature",
  "properties": {
    "addr:full":"227 Des Plaines Ave Forest Park IL 60130",
    "addr:housenumber":"227",
    "addr:postcode":"60130",
    "addr:street":"Des Plaines Ave",
    "iso:country":"US",
    "sg:address":"227 Des Plaines Ave",
    "sg:city":"Forest Park",
    "sg:classifiers":[
        {
            "category":"Cinema",
            "subcategory":"Movie Rental",
            "type":"Entertainment"
        }
    ],
    "sg:phone":"+1 708 366 0807",
    "sg:postcode":"60130",
    "sg:province":"IL",
    "sg:tags":[
        "video",
        "tape"
    ],
    "wof:name":"Jultara Video & Sound",
    "wof:placetype":"venue"
},
  "geometry": {"coordinates":[-87.81286299999999,41.881465],"type":"Point"}
}