{
  "type": "Feature",
  "properties": {
    "addr:full":"66 S Old Rand Rd Lake Zurich IL 60047",
    "addr:housenumber":"66",
    "addr:postcode":"60047",
    "addr:street":"S Old Rand Rd",
    "iso:country":"US",
    "sg:address":"66 S Old Rand Rd",
    "sg:city":"Lake Zurich",
    "sg:classifiers":[
        {
            "category":"Health Services",
            "subcategory":"Doctor",
            "type":"Services"
        }
    ],
    "sg:phone":"+1 847 438 8136",
    "sg:postcode":"60047",
    "sg:province":"IL",
    "wof:name":"Eugene F Ingles Sr DDS",
    "wof:placetype":"venue"
},
  "geometry": {"coordinates":[-88.091886,42.1965],"type":"Point"}
}