{
  "type": "Feature",
  "properties": {
    "addr:full":"9050 Pine Rd Leland IL 60531",
    "addr:housenumber":"9050",
    "addr:postcode":"60531",
    "addr:street":"Pine Rd",
    "iso:country":"US",
    "sg:address":"9050 Pine Rd",
    "sg:city":"Leland",
    "sg:classifiers":[
        {
            "category":"Wholesale",
            "subcategory":"Farm Supplies",
            "type":"Manufacturing & Wholesale Goods"
        }
    ],
    "sg:phone":"+1 815 498 3436",
    "sg:postcode":"60531",
    "sg:province":"IL",
    "sg:tags":[
        "grain"
    ],
    "wof:name":"J W Grains Ltd",
    "wof:placetype":"venue"
},
  "geometry": {"coordinates":[-88.770004,41.674564],"type":"Point"}
}