{
  "type": "Feature",
  "properties": {
    "addr:full":"900 N Franklin St Ste 709 Chicago IL 60610",
    "addr:housenumber":"900",
    "addr:postcode":"60610",
    "addr:street":"N Franklin St Ste 709",
    "iso:country":"US",
    "sg:address":"900 N Franklin St Ste 709",
    "sg:city":"Chicago",
    "sg:classifiers":[
        {
            "category":"Professional",
            "subcategory":"Employment Agencies",
            "type":"Services"
        }
    ],
    "sg:phone":"+1 312 563 0136",
    "sg:postcode":"60610",
    "sg:province":"IL",
    "sg:website":"www.nakedvoices.com",
    "wof:name":"Naked Voices",
    "wof:placetype":"venue"
},
  "geometry": {"coordinates":[-87.63589,41.899206],"type":"Point"}
}