{
  "type": "Feature",
  "properties": {
    "addr:full":"50 River Oaks Center Dr Calumet City IL 60409",
    "addr:housenumber":"50",
    "addr:postcode":"60409",
    "addr:street":"River Oaks Center Dr",
    "iso:country":"US",
    "sg:address":"50 River Oaks Center Dr",
    "sg:city":"Calumet City",
    "sg:classifiers":[
        {
            "category":"Shopping",
            "subcategory":"Shoes",
            "type":"Retail Goods"
        }
    ],
    "sg:phone":"+1   ",
    "sg:postcode":"60409",
    "sg:province":"IL",
    "wof:name":"Bakers Shoes",
    "wof:placetype":"venue"
},
  "geometry": {"coordinates":[-87.532191,41.596991],"type":"Point"}
}