{
  "type": "Feature",
  "properties": {
    "iso:country":"US",
    "sg:address":"2665 S 25th Ave",
    "sg:city":"Broadview",
    "sg:classifiers":[
        {
            "category":"Building & Trades",
            "subcategory":"Construction",
            "type":"Services"
        }
    ],
    "sg:phone":"+1 708 343 5900",
    "sg:postcode":"60155",
    "sg:province":"IL",
    "sg:tags":[
        "sealcoating",
        "asphalt",
        "paving"
    ],
    "sg:website":"http://www.mertes.com",
    "wof:name":"Asphalt",
    "wof:placetype":"venue"
},
  "geometry": {"coordinates":[-87.862464,41.85531],"type":"Point"}
}