{
  "type": "Feature",
  "properties": {
    "iso:country":"US",
    "sg:address":"1000 Main St",
    "sg:city":"Evanston",
    "sg:classifiers":[
        {
            "category":"Manufacturing",
            "subcategory":"Metals",
            "type":"Manufacturing & Wholesale Goods"
        }
    ],
    "sg:phone":"+1 847 869 3742",
    "sg:postcode":"60202",
    "sg:province":"IL",
    "sg:tags":[
        "product",
        "manufacturer",
        "giftware's-wholesale",
        "fabricated",
        "mfg"
    ],
    "wof:name":"Sisyphus Enterprise Inc",
    "wof:placetype":"venue"
},
  "geometry": {"coordinates":[-87.685211,42.033989],"type":"Point"}
}