{
  "type": "Feature",
  "properties": {
    "addr:full":"3350 W Diversey Ave Chicago IL 60647",
    "addr:housenumber":"3350",
    "addr:postcode":"60647",
    "addr:street":"W Diversey Ave",
    "iso:country":"US",
    "sg:address":"3350 W Diversey Ave",
    "sg:city":"Chicago",
    "sg:classifiers":[
        {
            "category":"Banks & Credit Unions",
            "subcategory":"Bank",
            "type":"Services"
        },
        {
            "category":"Banks & Credit Unions",
            "subcategory":"Financial Services",
            "type":"Services"
        }
    ],
    "sg:phone":"+1 773 486 5200",
    "sg:postcode":"60647",
    "sg:province":"IL",
    "sg:tags":[
        "saving",
        "loan",
        "commercial",
        "banking",
        "internet"
    ],
    "sg:website":"bofa.com",
    "wof:name":"Bank of America",
    "wof:placetype":"venue"
},
  "geometry": {"coordinates":[-87.71181,41.93225],"type":"Point"}
}