{
  "type": "Feature",
  "properties": {
    "iso:country":"US",
    "sg:address":"3312 N Milwaukee Ave",
    "sg:city":"Chicago",
    "sg:classifiers":[
        {
            "category":"Insurance",
            "subcategory":"Insurance Agent",
            "type":"Services"
        }
    ],
    "sg:phone":"+1 773 282 2022",
    "sg:postcode":"60641",
    "sg:province":"IL",
    "wof:name":"First Illinois Insurance Agcy",
    "wof:placetype":"venue"
},
  "geometry": {"coordinates":[-87.727974,41.94151],"type":"Point"}
}