{
  "type": "Feature",
  "properties": {
    "iso:country":"US",
    "sg:address":"1825 2nd Ave",
    "sg:city":"Rock Island",
    "sg:classifiers":[
        {
            "category":"Restaurant",
            "type":"Food & Drink"
        }
    ],
    "sg:phone":"+1   ",
    "sg:postcode":"61201",
    "sg:province":"IL",
    "sg:tags":[
        "eating"
    ],
    "wof:name":"East Town",
    "wof:placetype":"venue"
},
  "geometry": {"coordinates":[-90.573548,41.511122],"type":"Point"}
}