{
  "type": "Feature",
  "properties": {
    "iso:country":"US",
    "sg:address":"6332 Park Ridge Rd",
    "sg:city":"Loves Park",
    "sg:classifiers":[
        {
            "category":"Shopping",
            "subcategory":"Musical Instruments",
            "type":"Retail Goods"
        }
    ],
    "sg:phone":"+1   ",
    "sg:postcode":"61111",
    "sg:province":"IL",
    "wof:name":"Quality Keyboard Services",
    "wof:placetype":"venue"
},
  "geometry": {"coordinates":[-89.06488400000001,42.32304],"type":"Point"}
}