{
  "type": "Feature",
  "properties": {
    "iso:country":"US",
    "sg:address":"1001 SW 9th Ave",
    "sg:city":"Aledo",
    "sg:classifiers":[
        {
            "category":"Real Estate",
            "subcategory":"Real Estate Operator",
            "type":"Services"
        }
    ],
    "sg:phone":"+1 309 582 7349",
    "sg:postcode":"61231",
    "sg:province":"IL",
    "sg:tags":[
        "property",
        "lessor"
    ],
    "wof:name":"Cathrine Smith",
    "wof:placetype":"venue"
},
  "geometry": {"coordinates":[-90.758643,41.192958],"type":"Point"}
}