{
  "type": "Feature",
  "properties": {
    "iso:country":"US",
    "sg:address":"562 E Mill Valley Rd",
    "sg:city":"Palatine",
    "sg:classifiers":[
        {
            "category":"Shopping",
            "type":"Retail Goods"
        },
        {
            "category":"Professional",
            "subcategory":"Management & Consulting",
            "type":"Services"
        }
    ],
    "sg:phone":"+1 847 705 0085",
    "sg:postcode":"60074",
    "sg:province":"IL",
    "sg:tags":[
        "trophy",
        "medal",
        "award"
    ],
    "sg:website":"www.cmcincentives.com",
    "wof:name":"Corporate Markets Company",
    "wof:placetype":"venue"
},
  "geometry": {"coordinates":[-88.028958,42.129363],"type":"Point"}
}