{
  "type": "Feature",
  "properties": {
    "iso:country":"US",
    "sg:address":"176 Thomas Ct",
    "sg:city":"Wauconda",
    "sg:classifiers":[
        {
            "category":"Health Services",
            "subcategory":"Nursing And Care Facility",
            "type":"Services"
        }
    ],
    "sg:phone":"+1 847 526 5551",
    "sg:postcode":"60084",
    "sg:province":"IL",
    "sg:tags":[
        "home",
        "convalescent"
    ],
    "sg:website":"www.waucondacare.com",
    "wof:name":"Wauconda Health Care & Rehab",
    "wof:placetype":"venue"
},
  "geometry": {"coordinates":[-88.147913,42.254899],"type":"Point"}
}