{
  "type": "Feature",
  "properties": {
    "iso:country":"US",
    "sg:address":"1001 Main St",
    "sg:city":"Melrose Park",
    "sg:classifiers":[
        {
            "category":"Personal",
            "type":"Services"
        },
        {
            "category":"Retail",
            "subcategory":"Auto Repair",
            "type":"Services"
        }
    ],
    "sg:phone":"+1 708 345 5558",
    "sg:postcode":"60160",
    "sg:province":"IL",
    "sg:tags":[
        "towing"
    ],
    "sg:website":"uptowngarage.lub.com",
    "wof:name":"Uptown Garage",
    "wof:placetype":"venue"
},
  "geometry": {"coordinates":[-87.845488,41.88933],"type":"Point"}
}