{
  "type": "Feature",
  "properties": {
    "iso:country":"US",
    "sg:address":"5817 N Christiana Ave",
    "sg:city":"Chicago",
    "sg:classifiers":[
        {
            "category":"Health Services",
            "subcategory":"Doctor",
            "type":"Services"
        },
        {
            "category":"Health Services",
            "subcategory":"Hospital",
            "type":"Services"
        }
    ],
    "sg:phone":"+1 773 588 3364",
    "sg:postcode":"60659",
    "sg:province":"IL",
    "sg:tags":[
        "consultant",
        "medical",
        "practice",
        "nursing",
        "home"
    ],
    "wof:name":"Behavioral Health Consultants Pc",
    "wof:placetype":"venue"
},
  "geometry": {"coordinates":[-87.712622,41.986965],"type":"Point"}
}