{
  "type": "Feature",
  "properties": {
    "iso:country":"US",
    "sg:address":"880 Estes Ave",
    "sg:city":"Elk Grove Village",
    "sg:classifiers":[
        {
            "category":"Wholesale",
            "subcategory":"Plants",
            "type":"Manufacturing & Wholesale Goods"
        }
    ],
    "sg:phone":"+1 847 734 8660",
    "sg:postcode":"60007",
    "sg:province":"IL",
    "sg:tags":[
        "supply"
    ],
    "wof:name":"AMC Floral International",
    "wof:placetype":"venue"
},
  "geometry": {"coordinates":[-87.976143,42.006564],"type":"Point"}
}