{
  "type": "Feature",
  "properties": {
    "addr:full":"151 E Dundee Rd Buffalo Grove IL 60089",
    "addr:housenumber":"151",
    "addr:postcode":"60089",
    "addr:street":"E Dundee Rd",
    "iso:country":"US",
    "sg:address":"151 E Dundee Rd",
    "sg:city":"Buffalo Grove",
    "sg:classifiers":[
        {
            "category":"Personal",
            "subcategory":"Beauty Salon",
            "type":"Services"
        }
    ],
    "sg:phone":"+1 847 465 0906",
    "sg:postcode":"60089",
    "sg:province":"IL",
    "wof:name":"Artistic Feelings",
    "wof:placetype":"venue"
},
  "geometry": {"coordinates":[-87.955546,42.138783],"type":"Point"}
}