{
  "type": "Feature",
  "properties": {
    "addr:full":"326 Blackhawk Blvd South Beloit IL 61080",
    "addr:housenumber":"326",
    "addr:postcode":"61080",
    "addr:street":"Blackhawk Blvd",
    "iso:country":"US",
    "sg:address":"326 Blackhawk Blvd",
    "sg:city":"South Beloit",
    "sg:classifiers":[
        {
            "category":"Restaurant",
            "type":"Food & Drink"
        }
    ],
    "sg:menulink":"http://www.allmenus.com/il/rockton/83891-papa-johns-pizza/menu/",
    "sg:phone":"+1 608 363 7272",
    "sg:postcode":"61080",
    "sg:province":"IL",
    "sg:tags":[
        "american",
        "pizza"
    ],
    "wof:name":"Papa John's Pizza",
    "wof:placetype":"venue"
},
  "geometry": {"coordinates":[-89.037207,42.493513],"type":"Point"}
}