{
  "type": "Feature",
  "properties": {
    "iso:country":"US",
    "sg:address":"910 N 2nd St",
    "sg:city":"Belleville",
    "sg:classifiers":[
        {
            "category":"Professional",
            "subcategory":"Business Services",
            "type":"Services"
        }
    ],
    "sg:phone":"+1 618 234 3771",
    "sg:postcode":"62226",
    "sg:province":"IL",
    "wof:name":"Alex Domyan Tele Answering Svc",
    "wof:placetype":"venue"
},
  "geometry": {"coordinates":[-89.987927,38.52251],"type":"Point"}
}