{
  "type": "Feature",
  "properties": {
    "iso:country":"US",
    "sg:address":"50 N Western Ave",
    "sg:city":"Carpentersville",
    "sg:classifiers":[
        {
            "category":"Professional",
            "type":"Services"
        },
        {
            "category":"Personal",
            "type":"Services"
        },
        {
            "category":"Arts & Performance",
            "subcategory":"Music",
            "type":"Entertainment"
        }
    ],
    "sg:phone":"+1 847 426 4700",
    "sg:postcode":"60110",
    "sg:province":"IL",
    "sg:tags":[
        "planning",
        "dj",
        "caterer",
        "wedding"
    ],
    "sg:website":"www.savageentertainment.net",
    "wof:name":"Savage Entertainment",
    "wof:placetype":"venue"
},
  "geometry": {"coordinates":[-88.296204,42.111099],"type":"Point"}
}