{
  "type": "Feature",
  "properties": {
    "addr:full":"345 E Fullerton Ave Carol Stream IL 60188",
    "addr:housenumber":"345",
    "addr:postcode":"60188",
    "addr:street":"E Fullerton Ave",
    "iso:country":"US",
    "sg:address":"345 E Fullerton Ave",
    "sg:city":"Carol Stream",
    "sg:classifiers":[
        {
            "category":"Freight",
            "type":"Transportation"
        }
    ],
    "sg:phone":"+1 630 665 0362",
    "sg:postcode":"60188",
    "sg:province":"IL",
    "sg:tags":[
        "trucking"
    ],
    "wof:name":"Chris Truck Line",
    "wof:placetype":"venue"
},
  "geometry": {"coordinates":[-88.11247299999999,41.916716],"type":"Point"}
}