{
  "type": "Feature",
  "properties": {
    "iso:country":"US",
    "sg:address":"345 E Fullerton Ave",
    "sg:city":"Carol Stream",
    "sg:classifiers":[
        {
            "category":"Freight",
            "type":"Transportation"
        }
    ],
    "sg:phone":"+1 630 665 0362",
    "sg:postcode":"60188",
    "sg:province":"IL",
    "sg:tags":[
        "trucking"
    ],
    "wof:name":"Chris Truck Line",
    "wof:placetype":"venue"
},
  "geometry": {"coordinates":[-88.112473,41.916716],"type":"Point"}
}