{
  "type": "Feature",
  "properties": {
    "addr:full":"5 E Phillip Rd Vernon Hills IL 60061",
    "addr:housenumber":"5",
    "addr:postcode":"60061",
    "addr:street":"E Phillip Rd",
    "iso:country":"US",
    "sg:address":"5 E Phillip Rd",
    "sg:city":"Vernon Hills",
    "sg:classifiers":[
        {
            "category":"Social Services",
            "subcategory":"Child Care",
            "type":"Services"
        }
    ],
    "sg:phone":"+1 847 680 7771",
    "sg:postcode":"60061",
    "sg:province":"IL",
    "sg:tags":[
        "center",
        "day"
    ],
    "wof:name":"Knowledge Learning Corporation",
    "wof:placetype":"venue"
},
  "geometry": {"coordinates":[-87.95959499999999,42.23859],"type":"Point"}
}