{
  "type": "Feature",
  "properties": {
    "iso:country":"US",
    "sg:address":"1 S Wacker Dr",
    "sg:city":"Chicago",
    "sg:classifiers":[
        {
            "category":"Professional",
            "subcategory":"Business Services",
            "type":"Services"
        }
    ],
    "sg:phone":"+1 312 346 5054",
    "sg:postcode":"60606",
    "sg:province":"IL",
    "sg:tags":[
        "holding"
    ],
    "wof:name":"Robert James Holdings Ltd.",
    "wof:placetype":"venue"
},
  "geometry": {"coordinates":[-87.636757,41.881939],"type":"Point"}
}