{
  "type": "Feature",
  "properties": {
    "addr:full":"1419 Center Cir Dr Downers Grove IL 60515",
    "addr:housenumber":"1419",
    "addr:postcode":"60515",
    "addr:street":"Center Cir Dr",
    "iso:country":"US",
    "sg:address":"1419 Center Cir Dr",
    "sg:city":"Downers Grove",
    "sg:classifiers":[
        {
            "category":"Home & Garden",
            "subcategory":"Furniture",
            "type":"Retail Goods"
        }
    ],
    "sg:phone":"+1 630 268 0204",
    "sg:postcode":"60515",
    "sg:province":"IL",
    "sg:tags":[
        "mattress"
    ],
    "wof:name":"Bed Mart",
    "wof:placetype":"venue"
},
  "geometry": {"coordinates":[-88.02403099999999,41.837663],"type":"Point"}
}