{
  "type": "Feature",
  "properties": {
    "iso:country":"US",
    "sg:address":"930 Lunt Ave",
    "sg:city":"Schaumburg",
    "sg:classifiers":[
        {
            "category":"Wholesale",
            "subcategory":"Durable Goods & Equipment",
            "type":"Manufacturing & Wholesale Goods"
        }
    ],
    "sg:phone":"+1 847 301 8231",
    "sg:postcode":"60193",
    "sg:province":"IL",
    "sg:tags":[
        "laser"
    ],
    "wof:name":"Estes Laser & Mfg Inc",
    "wof:placetype":"venue"
},
  "geometry": {"coordinates":[-88.108897,42.001245],"type":"Point"}
}