{
  "type": "Feature",
  "properties": {
    "addr:full":"5809 Lyman Ave Downers Grove IL 60516",
    "addr:housenumber":"5809",
    "addr:postcode":"60516",
    "addr:street":"Lyman Ave",
    "iso:country":"US",
    "sg:address":"5809 Lyman Ave",
    "sg:city":"Downers Grove",
    "sg:classifiers":[
        {
            "category":"Building & Trades",
            "subcategory":"Landscaping Services",
            "type":"Services"
        }
    ],
    "sg:phone":"+1 630 852 8849",
    "sg:postcode":"60516",
    "sg:province":"IL",
    "wof:name":"Mike Laslo Landscaping",
    "wof:placetype":"venue"
},
  "geometry": {"coordinates":[-88.003857,41.781837],"type":"Point"}
}