{
  "type": "Feature",
  "properties": {
    "addr:full":"2260 E 75th Street Chicago IL 60649",
    "addr:housenumber":"2260",
    "addr:postcode":"60649",
    "addr:street":"E 75Th Street",
    "iso:country":"US",
    "sg:address":"2260 E 75th Street",
    "sg:city":"Chicago",
    "sg:classifiers":[
        {
            "category":"Home & Garden",
            "subcategory":"Hardware",
            "type":"Retail Goods"
        }
    ],
    "sg:phone":"+1 773 734 3990",
    "sg:postcode":"60649",
    "sg:province":"IL",
    "sg:tags":[
        "store"
    ],
    "wof:name":"Saifi Dba Metro Hardware",
    "wof:placetype":"venue"
},
  "geometry": {"coordinates":[-87.56901000000001,41.75886],"type":"Point"}
}