{
  "type": "Feature",
  "properties": {
    "addr:full":"702 Kochs Ln Quincy IL 62305",
    "addr:housenumber":"702",
    "addr:postcode":"62305",
    "addr:street":"Kochs Ln",
    "iso:country":"US",
    "sg:address":"702 Kochs Ln",
    "sg:city":"Quincy",
    "sg:classifiers":[
        {
            "category":"Shopping",
            "subcategory":"Clothing, Apparel, & Fashions",
            "type":"Retail Goods"
        }
    ],
    "sg:phone":"+1   ",
    "sg:postcode":"62305",
    "sg:province":"IL",
    "sg:tags":[
        "national",
        "security"
    ],
    "wof:name":"Oms 20",
    "wof:placetype":"venue"
},
  "geometry": {"coordinates":[-91.40367500000001,39.96505],"type":"Point"}
}