{
  "type": "Feature",
  "properties": {
    "addr:full":"1200 Dekalb Ave Sycamore IL 60178",
    "addr:housenumber":"1200",
    "addr:postcode":"60178",
    "addr:street":"Dekalb Ave",
    "iso:country":"US",
    "sg:address":"1200 Dekalb Ave",
    "sg:city":"Sycamore",
    "sg:classifiers":[
        {
            "category":"Ice Cream",
            "type":"Food & Drink"
        }
    ],
    "sg:menulink":"http://www.allmenus.com/il/sycamore/182743-culvers/menu/",
    "sg:phone":"+1 815 899 0200",
    "sg:postcode":"60178",
    "sg:province":"IL",
    "sg:tags":[
        "burger",
        "american"
    ],
    "wof:name":"Culver's",
    "wof:placetype":"venue"
},
  "geometry": {"coordinates":[-88.70502,41.981726],"type":"Point"}
}