{
  "type": "Feature",
  "properties": {
    "addr:full":"2637 Sommerset Dr Westchester IL 60154",
    "addr:housenumber":"2637",
    "addr:postcode":"60154",
    "addr:street":"Sommerset Dr",
    "iso:country":"US",
    "sg:address":"2637 Sommerset Dr",
    "sg:city":"Westchester",
    "sg:classifiers":[
        {
            "category":"Real Estate",
            "subcategory":"Real Estate Agent",
            "type":"Services"
        }
    ],
    "sg:phone":"+1 708 562 9328",
    "sg:postcode":"60154",
    "sg:province":"IL",
    "wof:name":"Coldwell Banker",
    "wof:placetype":"venue"
},
  "geometry": {"coordinates":[-87.88505600000001,41.840899],"type":"Point"}
}