{
  "type": "Feature",
  "properties": {
    "iso:country":"US",
    "sg:address":"16334 Kilbourne St",
    "sg:city":"Oak Forest",
    "sg:classifiers":[
        {
            "category":"Wholesale",
            "subcategory":"Hardware",
            "type":"Manufacturing & Wholesale Goods"
        }
    ],
    "sg:phone":"+1 708 429 6363",
    "sg:postcode":"60452",
    "sg:province":"IL",
    "wof:name":"Mid-Way Supply Inc",
    "wof:placetype":"venue"
},
  "geometry": {"coordinates":[-87.718734,41.58842],"type":"Point"}
}