{
  "type": "Feature",
  "properties": {
    "addr:full":"2235 E 71st Street Chicago IL 60649",
    "addr:housenumber":"2235",
    "addr:postcode":"60649",
    "addr:street":"E 71St Street",
    "iso:country":"US",
    "sg:address":"2235 E 71st Street",
    "sg:city":"Chicago",
    "sg:classifiers":[
        {
            "category":"Cinema",
            "subcategory":"Movie Rental",
            "type":"Entertainment"
        },
        {
            "category":"Shopping",
            "subcategory":"Music",
            "type":"Retail Goods"
        }
    ],
    "sg:phone":"+1 773 752 4012",
    "sg:postcode":"60649",
    "sg:province":"IL",
    "sg:tags":[
        "game",
        "video",
        "dvd's"
    ],
    "wof:name":"Chatham Park Video",
    "wof:placetype":"venue"
},
  "geometry": {"coordinates":[-87.569664,41.766287],"type":"Point"}
}