{
  "type": "Feature",
  "properties": {
    "addr:full":"1309 W Hensley Rd Champaign IL 61822",
    "addr:housenumber":"1309",
    "addr:postcode":"61822",
    "addr:street":"W Hensley Rd",
    "iso:country":"US",
    "sg:address":"1309 W Hensley Rd",
    "sg:city":"Champaign",
    "sg:classifiers":[
        {
            "category":"Retail",
            "subcategory":"Repair Shop",
            "type":"Services"
        }
    ],
    "sg:phone":"+1 217 359 2632",
    "sg:postcode":"61822",
    "sg:province":"IL",
    "sg:tags":[
        "residential",
        "door",
        "garage"
    ],
    "wof:name":"George Malloch Co",
    "wof:placetype":"venue"
},
  "geometry": {"coordinates":[-88.268017,40.185637],"type":"Point"}
}