{
  "type": "Feature",
  "properties": {
    "iso:country":"US",
    "sg:address":"5500 W Montrose Avenue",
    "sg:city":"Chicago",
    "sg:classifiers":[
        {
            "category":"Food & Beverages",
            "subcategory":"Groceries & Convenience Stores",
            "type":"Retail Goods"
        }
    ],
    "sg:phone":"+1 773 286 7511",
    "sg:postcode":"60641",
    "sg:province":"IL",
    "wof:name":"Kwik Mart",
    "wof:placetype":"venue"
},
  "geometry": {"coordinates":[-87.765046,41.960502],"type":"Point"}
}