{
  "type": "Feature",
  "properties": {
    "iso:country":"US",
    "sg:address":"910 S 3rd St",
    "sg:city":"Champaign",
    "sg:classifiers":[
        {
            "category":"Personal",
            "subcategory":"Tanning Parlor",
            "type":"Services"
        },
        {
            "category":"Sports & Exercise",
            "subcategory":"Gym",
            "type":"Entertainment"
        }
    ],
    "sg:phone":"+1 217 384 0704",
    "sg:postcode":"61820",
    "sg:province":"IL",
    "sg:tags":[
        "trainer"
    ],
    "wof:name":"Nautilus Poolside Fitness Center",
    "wof:placetype":"venue"
},
  "geometry": {"coordinates":[-88.23519899999999,40.1078],"type":"Point"}
}