{
  "type": "Feature",
  "properties": {
    "addr:full":"1937 W Fulton Street Chicago IL 60612",
    "addr:housenumber":"1937",
    "addr:postcode":"60612",
    "addr:street":"W Fulton Street",
    "iso:country":"US",
    "sg:address":"1937 W Fulton Street",
    "sg:city":"Chicago",
    "sg:classifiers":[
        {
            "category":"Building & Trades",
            "subcategory":"Construction",
            "type":"Services"
        }
    ],
    "sg:phone":"+1 312 491 0600",
    "sg:postcode":"60612",
    "sg:province":"IL",
    "sg:tags":[
        "contractor"
    ],
    "wof:name":"Clarke Construction",
    "wof:placetype":"venue"
},
  "geometry": {"coordinates":[-87.67523199999999,41.886794],"type":"Point"}
}