{
  "type": "Feature",
  "properties": {
    "iso:country":"US",
    "sg:address":"730 Euclid Ave",
    "sg:city":"Glen Ellyn",
    "sg:classifiers":[
        {
            "category":"Professional",
            "subcategory":"Business Services",
            "type":"Services"
        }
    ],
    "sg:phone":"+1 630 545 9486",
    "sg:postcode":"60137",
    "sg:province":"IL",
    "sg:tags":[
        "interior",
        "consultant",
        "design",
        "decorator"
    ],
    "wof:name":"Goranov & Assoc",
    "wof:placetype":"venue"
},
  "geometry": {"coordinates":[-88.06834000000001,41.885712],"type":"Point"}
}