{
  "type": "Feature",
  "properties": {
    "iso:country":"US",
    "sg:address":"2423 16th St",
    "sg:city":"Moline",
    "sg:classifiers":[
        {
            "category":"Shopping",
            "type":"Retail Goods"
        }
    ],
    "sg:phone":"+1   ",
    "sg:postcode":"61265",
    "sg:province":"IL",
    "sg:tags":[
        "lawn",
        "garden",
        "supply",
        "pet",
        "equipment",
        "s"
    ],
    "wof:name":"Teske Pet & Garden Center Inc",
    "wof:placetype":"venue"
},
  "geometry": {"coordinates":[-90.51367,41.487684],"type":"Point"}
}