{
  "type": "Feature",
  "properties": {
    "iso:country":"US",
    "sg:address":"541 N Milwaukee Ave",
    "sg:city":"Libertyville",
    "sg:classifiers":[
        {
            "category":"Food & Beverages",
            "subcategory":"Candy",
            "type":"Retail Goods"
        }
    ],
    "sg:phone":"+1   ",
    "sg:postcode":"60048",
    "sg:province":"IL",
    "wof:name":"Rocky Mountain Chocolates",
    "wof:placetype":"venue"
},
  "geometry": {"coordinates":[-87.954532,42.288613],"type":"Point"}
}