{
  "type": "Feature",
  "properties": {
    "addr:full":"2709 Pelham Rd Rockford IL 61107",
    "addr:housenumber":"2709",
    "addr:postcode":"61107",
    "addr:street":"Pelham Rd",
    "iso:country":"US",
    "sg:address":"2709 Pelham Rd",
    "sg:city":"Rockford",
    "sg:classifiers":[
        {
            "category":"Building & Trades",
            "subcategory":"Construction",
            "type":"Services"
        }
    ],
    "sg:phone":"+1 815 397 6851",
    "sg:postcode":"61107",
    "sg:province":"IL",
    "sg:tags":[
        "hanging",
        "contractor"
    ],
    "wof:name":"Gustafson Painting & Papering",
    "wof:placetype":"venue"
},
  "geometry": {"coordinates":[-89.051855,42.282915],"type":"Point"}
}