{
  "type": "Feature",
  "properties": {
    "iso:country":"US",
    "sg:address":"5500 Forest Hills Rd",
    "sg:city":"Loves Park",
    "sg:classifiers":[
        {
            "category":"Banks & Credit Unions",
            "subcategory":"Bank",
            "type":"Services"
        }
    ],
    "sg:phone":"+1 815 282 5631",
    "sg:postcode":"61111",
    "sg:province":"IL",
    "wof:name":"Parda Federal Credit Union",
    "wof:placetype":"venue"
},
  "geometry": {"coordinates":[-89.046188,42.306395],"type":"Point"}
}