{
  "type": "Feature",
  "properties": {
    "iso:country":"US",
    "sg:address":"1801 1st Ave",
    "sg:city":"Rock Falls",
    "sg:classifiers":[
        {
            "category":"Banks & Credit Unions",
            "subcategory":"Financial Services",
            "type":"Services"
        }
    ],
    "sg:phone":"+1 815 625 1110",
    "sg:postcode":"61071",
    "sg:province":"IL",
    "sg:tags":[
        "company",
        "holding"
    ],
    "wof:name":"Community Illinois Corp",
    "wof:placetype":"venue"
},
  "geometry": {"coordinates":[-89.689288,41.764536],"type":"Point"}
}