{
  "type": "Feature",
  "properties": {
    "addr:full":"2417 N Campbell Ave Chicago IL 60647",
    "addr:housenumber":"2417",
    "addr:postcode":"60647",
    "addr:street":"N Campbell Ave",
    "iso:country":"US",
    "sg:address":"2417 N Campbell Ave",
    "sg:city":"Chicago",
    "sg:classifiers":[
        {
            "category":"Organizations",
            "subcategory":"Religious Organization",
            "type":"Services"
        }
    ],
    "sg:phone":"+1 773 342 0836",
    "sg:postcode":"60647",
    "sg:province":"IL",
    "sg:tags":[
        "church"
    ],
    "wof:name":"Central Spanish Baptist Church",
    "wof:placetype":"venue"
},
  "geometry": {"coordinates":[-87.69001799999999,41.925111],"type":"Point"}
}