{
  "type": "Feature",
  "properties": {
    "iso:country":"US",
    "sg:address":"2028 S Prospect Ave",
    "sg:city":"Champaign",
    "sg:classifiers":[
        {
            "category":"Shopping",
            "subcategory":"Clothing, Apparel, & Fashions",
            "type":"Retail Goods"
        }
    ],
    "sg:phone":"+1   ",
    "sg:postcode":"61820",
    "sg:province":"IL",
    "wof:name":"Ave 413 Ave",
    "wof:placetype":"venue"
},
  "geometry": {"coordinates":[-88.25746,40.088708],"type":"Point"}
}