{
  "type": "Feature",
  "properties": {
    "iso:country":"US",
    "sg:address":"508 Palace Ct",
    "sg:city":"Schaumburg",
    "sg:classifiers":[
        {
            "category":"Professional",
            "subcategory":"Management & Consulting",
            "type":"Services"
        }
    ],
    "sg:phone":"+1 847 885 7251",
    "sg:postcode":"60194",
    "sg:province":"IL",
    "sg:tags":[
        "business"
    ],
    "wof:name":"Info Comtech Consulting Inc",
    "wof:placetype":"venue"
},
  "geometry": {"coordinates":[-88.137348,42.035189],"type":"Point"}
}