{
  "type": "Feature",
  "properties": {
    "iso:country":"US",
    "sg:address":"4727 N Lincoln Ave",
    "sg:city":"Chicago",
    "sg:classifiers":[
        {
            "category":"Shopping",
            "subcategory":"Clothing, Apparel, & Fashions",
            "type":"Retail Goods"
        }
    ],
    "sg:phone":"+1 773 754 8176",
    "sg:postcode":"60625",
    "sg:province":"IL",
    "sg:tags":[
        "men's",
        "clothing",
        "women's"
    ],
    "sg:website":"www.planetaccesscompanystore.com",
    "wof:name":"Planet Access Company Store",
    "wof:placetype":"venue"
},
  "geometry": {"coordinates":[-87.687726,41.96741],"type":"Point"}
}