{
  "type": "Feature",
  "properties": {
    "iso:country":"US",
    "sg:address":"1340 W Bowshier Ln",
    "sg:city":"Decatur",
    "sg:classifiers":[
        {
            "category":"Recreation",
            "subcategory":"Playground",
            "type":"Entertainment"
        }
    ],
    "sg:phone":"+1 217 422 3088",
    "sg:postcode":"62522",
    "sg:province":"IL",
    "wof:name":"Plutronics",
    "wof:placetype":"venue"
},
  "geometry": {"coordinates":[-88.978203,39.832689],"type":"Point"}
}