{
  "type": "Feature",
  "properties": {
    "addr:full":"4835 S Perryville Rd Cherry Valley IL 61016",
    "addr:housenumber":"4835",
    "addr:postcode":"61016",
    "addr:street":"S Perryville Rd",
    "iso:country":"US",
    "sg:address":"4835 S Perryville Rd",
    "sg:city":"Cherry Valley",
    "sg:classifiers":[
        {
            "category":"Professional",
            "subcategory":"Management & Consulting",
            "type":"Services"
        }
    ],
    "sg:phone":"+1   ",
    "sg:postcode":"61016",
    "sg:province":"IL",
    "sg:tags":[
        "retail",
        "direct",
        "sales"
    ],
    "wof:name":"Fedie and Associates",
    "wof:placetype":"venue"
},
  "geometry": {"coordinates":[-88.979373,42.20962],"type":"Point"}
}