{
  "type": "Feature",
  "properties": {
    "iso:country":"US",
    "sg:address":"2474 W Schaumburg Rd",
    "sg:city":"Schaumburg",
    "sg:classifiers":[
        {
            "category":"Personal",
            "subcategory":"Beauty Salon",
            "type":"Services"
        },
        {
            "category":"Personal",
            "subcategory":"Barber",
            "type":"Services"
        }
    ],
    "sg:phone":"+1 847 885 4115",
    "sg:postcode":"60194",
    "sg:province":"IL",
    "sg:tags":[
        "hair",
        "stylist"
    ],
    "sg:website":"http://www.sportclips.com",
    "wof:name":"Sport Clips",
    "wof:placetype":"venue"
},
  "geometry": {"coordinates":[-88.14241699999999,42.02484],"type":"Point"}
}