{
  "type": "Feature",
  "properties": {
    "addr:full":"313 W Jefferson Ave Effingham IL 62401",
    "addr:housenumber":"313",
    "addr:postcode":"62401",
    "addr:street":"W Jefferson Ave",
    "iso:country":"US",
    "sg:address":"313 W Jefferson Ave",
    "sg:city":"Effingham",
    "sg:classifiers":[
        {
            "category":"Personal",
            "subcategory":"Tanning Parlor",
            "type":"Services"
        },
        {
            "category":"Shopping",
            "subcategory":"Clothing, Apparel, & Fashions",
            "type":"Retail Goods"
        }
    ],
    "sg:phone":"+1 217 347 5993",
    "sg:postcode":"62401",
    "sg:province":"IL",
    "sg:tags":[
        "me",
        "salon",
        "used"
    ],
    "wof:name":"Elephant's Attic Inc",
    "wof:placetype":"venue"
},
  "geometry": {"coordinates":[-88.54484600000001,39.121477],"type":"Point"}
}