{
  "type": "Feature",
  "properties": {
    "addr:full":"5117 S Ingleside Ave Chicago IL 60615",
    "addr:housenumber":"5117",
    "addr:postcode":"60615",
    "addr:street":"S Ingleside Ave",
    "iso:country":"US",
    "sg:address":"5117 S Ingleside Ave",
    "sg:city":"Chicago",
    "sg:classifiers":[
        {
            "category":"Food & Beverages",
            "subcategory":"Supermarket",
            "type":"Retail Goods"
        }
    ],
    "sg:phone":"+1 773 288 7194",
    "sg:postcode":"60615",
    "sg:province":"IL",
    "sg:tags":[
        "super",
        "store"
    ],
    "wof:name":"Hyde Park Foods",
    "wof:placetype":"venue"
},
  "geometry": {"coordinates":[-87.602879,41.802061],"type":"Point"}
}