{
  "type": "Feature",
  "properties": {
    "addr:full":"3075 Highland Ave Downers Grove IL 60515",
    "addr:housenumber":"3075",
    "addr:postcode":"60515",
    "addr:street":"Highland Ave",
    "iso:country":"US",
    "sg:address":"3075 Highland Ave",
    "sg:city":"Downers Grove",
    "sg:classifiers":[
        {
            "category":"Wholesale",
            "subcategory":"Office Equipment",
            "type":"Manufacturing & Wholesale Goods"
        }
    ],
    "sg:phone":"+1 630 852 1180",
    "sg:postcode":"60515",
    "sg:province":"IL",
    "sg:tags":[
        "machine",
        "duplicating",
        "copying"
    ],
    "wof:name":"Gordon Flesch Co",
    "wof:placetype":"venue"
},
  "geometry": {"coordinates":[-88.010755,41.831826],"type":"Point"}
}