{
  "type": "Feature",
  "properties": {
    "iso:country":"US",
    "sg:address":"1521-25 E 87th St",
    "sg:city":"Chicago",
    "sg:classifiers":[
        {
            "category":"Home & Garden",
            "subcategory":"Carpets & Floor Coverings",
            "type":"Retail Goods"
        }
    ],
    "sg:phone":"+1 773 375 0640",
    "sg:postcode":"60619",
    "sg:province":"IL",
    "sg:tags":[
        "mattress"
    ],
    "sg:website":"www.beddingexperts.com",
    "wof:name":"The Bedding Experts",
    "wof:placetype":"venue"
},
  "geometry": {"coordinates":[-87.62309999999999,41.736068],"type":"Point"}
}