{
  "type": "Feature",
  "properties": {
    "iso:country":"US",
    "sg:address":"644 Anderson Blvd",
    "sg:city":"Geneva",
    "sg:classifiers":[
        {
            "category":"Insurance",
            "subcategory":"Insurance Agent",
            "type":"Services"
        }
    ],
    "sg:phone":"+1 630 232 7805",
    "sg:postcode":"60134",
    "sg:province":"IL",
    "wof:name":"B A Schmidt Insurance Inc",
    "wof:placetype":"venue"
},
  "geometry": {"coordinates":[-88.31499100000001,41.89546],"type":"Point"}
}