{
  "type": "Feature",
  "properties": {
    "iso:country":"US",
    "sg:address":"6234 S Archer Rd Ste 1",
    "sg:city":"Summit Argo",
    "sg:classifiers":[
        {
            "category":"Personal",
            "subcategory":"Beauty Salon",
            "type":"Services"
        }
    ],
    "sg:phone":"+1 708 496 9392",
    "sg:postcode":"60501",
    "sg:province":"IL",
    "sg:tags":[
        "hair"
    ],
    "wof:name":"Phacez",
    "wof:placetype":"venue"
},
  "geometry": {"coordinates":[-87.813669,41.777903],"type":"Point"}
}