{
  "type": "Feature",
  "properties": {
    "addr:full":"425 S West St Olney IL 62450",
    "addr:housenumber":"425",
    "addr:postcode":"62450",
    "addr:street":"S;St",
    "iso:country":"US",
    "sg:address":"425 S West St",
    "sg:city":"Olney",
    "sg:classifiers":[
        {
            "category":"Travel",
            "subcategory":"Hotels & Motels",
            "type":"Entertainment"
        }
    ],
    "sg:phone":"+1 618 392 7888",
    "sg:postcode":"62450",
    "sg:province":"IL",
    "sg:tags":[
        "lodging"
    ],
    "sg:website":"http://www.super8.com",
    "wof:name":"Super 8 Motel",
    "wof:placetype":"venue"
},
  "geometry": {"coordinates":[-88.09410099999999,38.727486],"type":"Point"}
}