{
  "type": "Feature",
  "properties": {
    "addr:full":"2453 N Spaulding Avenue Chicago IL 60647",
    "addr:housenumber":"2453",
    "addr:postcode":"60647",
    "addr:street":"N Spaulding Avenue",
    "iso:country":"US",
    "sg:address":"2453 N Spaulding Avenue",
    "sg:city":"Chicago",
    "sg:classifiers":[
        {
            "category":"Shopping",
            "subcategory":"Adult",
            "type":"Retail Goods"
        }
    ],
    "sg:phone":"+1 773 772 7171",
    "sg:postcode":"60647",
    "sg:province":"IL",
    "sg:tags":[
        "entertainment"
    ],
    "wof:name":"Holli Wood Entertainment",
    "wof:placetype":"venue"
},
  "geometry": {"coordinates":[-87.710759,41.925754],"type":"Point"}
}