{
  "type": "Feature",
  "properties": {
    "iso:country":"US",
    "sg:address":"2406 Meadow Dr N",
    "sg:city":"Wilmette",
    "sg:classifiers":[
        {
            "category":"Professional",
            "subcategory":"Lawyer & Legal Services",
            "type":"Services"
        }
    ],
    "sg:phone":"+1 847 256 1428",
    "sg:postcode":"60091",
    "sg:province":"IL",
    "sg:tags":[
        "attorney",
        "practice"
    ],
    "wof:name":"Siegel, Jack M",
    "wof:placetype":"venue"
},
  "geometry": {"coordinates":[-87.73381999999999,42.073309],"type":"Point"}
}