{
  "type": "Feature",
  "properties": {
    "iso:country":"US",
    "sg:address":"4190 N Harlem Ave",
    "sg:city":"Norridge",
    "sg:classifiers":[
        {
            "category":"Shopping",
            "subcategory":"Clothing, Apparel, & Fashions",
            "type":"Retail Goods"
        }
    ],
    "sg:phone":"+1 773 625 3986",
    "sg:postcode":"60706",
    "sg:province":"IL",
    "sg:tags":[
        "accessory",
        "clothing",
        "women's"
    ],
    "sg:website":"www.nyandcompany.com",
    "wof:name":"New York & Company",
    "wof:placetype":"venue"
},
  "geometry": {"coordinates":[-87.806999,41.956799],"type":"Point"}
}