{
  "type": "Feature",
  "properties": {
    "addr:full":"141 Harrison St Oak Park IL 60304",
    "addr:housenumber":"141",
    "addr:postcode":"60304",
    "addr:street":"Harrison St",
    "iso:country":"US",
    "sg:address":"141 Harrison St",
    "sg:city":"Oak Park",
    "sg:classifiers":[
        {
            "category":"Real Estate",
            "subcategory":"Architect",
            "type":"Services"
        }
    ],
    "sg:phone":"+1 708 386 7218",
    "sg:postcode":"60304",
    "sg:province":"IL",
    "sg:tags":[
        "architectural"
    ],
    "wof:name":"Rozovics & Assoc Architects",
    "wof:placetype":"venue"
},
  "geometry": {"coordinates":[-87.77848299999999,41.872646],"type":"Point"}
}