{
  "type": "Feature",
  "properties": {
    "iso:country":"US",
    "sg:address":"2720 N Austin Ave",
    "sg:city":"Chicago",
    "sg:classifiers":[
        {
            "category":"Building & Trades",
            "subcategory":"Construction",
            "type":"Services"
        },
        {
            "category":"Building & Trades",
            "subcategory":"Electrical",
            "type":"Services"
        }
    ],
    "sg:phone":"+1 866 680 9906",
    "sg:postcode":"60639",
    "sg:province":"IL",
    "sg:tags":[
        "industrial",
        "electrician",
        "electric",
        "system",
        "specialty",
        "heating",
        "contractors-commercial",
        "contractor",
        "air conditioning"
    ],
    "wof:name":"Professional Heating and Cooling",
    "wof:placetype":"venue"
},
  "geometry": {"coordinates":[-87.77590600000001,41.929672],"type":"Point"}
}