{
  "type": "Feature",
  "properties": {
    "iso:country":"US",
    "sg:address":"2916 N. Damen Ave Ste 2",
    "sg:city":"Chicago",
    "sg:classifiers":[
        {
            "category":"Retail",
            "subcategory":"Repair Shop",
            "type":"Services"
        },
        {
            "category":"Professional",
            "subcategory":"Computer Services",
            "type":"Services"
        }
    ],
    "sg:phone":"+1 847 970 0260",
    "sg:postcode":"60618",
    "sg:province":"IL",
    "sg:tags":[
        "electronics"
    ],
    "sg:website":"www.interactivepix.com/",
    "wof:name":"InteractivePix Computer Repair, Network, Technology & Security",
    "wof:placetype":"venue"
},
  "geometry": {"coordinates":[-87.67853700000001,41.934654],"type":"Point"}
}