{
  "type": "Feature",
  "properties": {
    "addr:full":"3023 N Clark St Chicago IL 60657",
    "addr:housenumber":"3023",
    "addr:postcode":"60657",
    "addr:street":"N Clark St",
    "iso:country":"US",
    "sg:address":"3023 N Clark St",
    "sg:city":"Chicago",
    "sg:classifiers":[
        {
            "category":"Professional",
            "subcategory":"Management & Consulting",
            "type":"Services"
        }
    ],
    "sg:phone":"+1   ",
    "sg:postcode":"60657",
    "sg:province":"IL",
    "sg:tags":[
        "distribution",
        "sales"
    ],
    "wof:name":"Neuturn Corp",
    "wof:placetype":"venue"
},
  "geometry": {"coordinates":[-87.647823,41.936426],"type":"Point"}
}