{
  "type": "Feature",
  "properties": {
    "addr:full":"5600 W Addison St Chicago IL 60634",
    "addr:housenumber":"5600",
    "addr:postcode":"60634",
    "addr:street":"W Addison St",
    "iso:country":"US",
    "sg:address":"5600 W Addison St",
    "sg:city":"Chicago",
    "sg:classifiers":[
        {
            "category":"Health Services",
            "subcategory":"Optometrist",
            "type":"Services"
        }
    ],
    "sg:phone":"+1 773 736 7873",
    "sg:postcode":"60634",
    "sg:province":"IL",
    "sg:tags":[
        "ophthalmologist"
    ],
    "wof:name":"Kraff Eye Institute",
    "wof:placetype":"venue"
},
  "geometry": {"coordinates":[-87.766701,41.9459],"type":"Point"}
}