{
  "type": "Feature",
  "properties": {
    "iso:country":"US",
    "sg:address":"2004 State St",
    "sg:city":"Lawrenceville",
    "sg:classifiers":[
        {
            "category":"Organizations",
            "subcategory":"Community Association",
            "type":"Services"
        }
    ],
    "sg:phone":"+1 618 943 4291",
    "sg:postcode":"62439",
    "sg:province":"IL",
    "wof:name":"Kiwanis International Inc",
    "wof:placetype":"venue"
},
  "geometry": {"coordinates":[-87.694743,38.729411],"type":"Point"}
}