{
  "type": "Feature",
  "properties": {
    "addr:full":"121 N Main St 3rd Fl Bloomington IL 61701",
    "addr:housenumber":"121;3rd fl",
    "addr:postcode":"61701",
    "addr:street":"N Main St",
    "iso:country":"US",
    "sg:address":"121 N Main St 3rd Fl",
    "sg:city":"Bloomington",
    "sg:classifiers":[
        {
            "category":"Professional",
            "subcategory":"Lawyer & Legal Services",
            "type":"Services"
        }
    ],
    "sg:phone":"+1 309 820 0600",
    "sg:postcode":"61701",
    "sg:province":"IL",
    "sg:tags":[
        "attorney",
        "accident",
        "personal",
        "medical",
        "damage",
        "malpractice",
        "injury",
        "property",
        "law"
    ],
    "sg:website":"http://www.kellylawoffices.com",
    "wof:name":"Kelly Law Office, P.C.",
    "wof:placetype":"venue"
},
  "geometry": {"coordinates":[-88.993618,40.478858],"type":"Point"}
}