{
  "type": "Feature",
  "properties": {
    "iso:country":"US",
    "sg:address":"1108 Berkshire Ln",
    "sg:city":"Barrington",
    "sg:classifiers":[
        {
            "category":"Home & Garden",
            "subcategory":"Furniture",
            "type":"Retail Goods"
        }
    ],
    "sg:phone":"+1   ",
    "sg:postcode":"60010",
    "sg:province":"IL",
    "wof:name":"Pineapple Shop Furniture",
    "wof:placetype":"venue"
},
  "geometry": {"coordinates":[-88.10405,42.181514],"type":"Point"}
}