{
  "type": "Feature",
  "properties": {
    "iso:country":"US",
    "sg:address":"12549 S Laramie Ave",
    "sg:city":"Alsip",
    "sg:classifiers":[
        {
            "category":"Manufacturing",
            "subcategory":"Tools & Machinery",
            "type":"Manufacturing & Wholesale Goods"
        }
    ],
    "sg:phone":"+1 708 597 1200",
    "sg:postcode":"60803",
    "sg:province":"IL",
    "sg:tags":[
        "mfg"
    ],
    "wof:name":"Machine Control Systems Inc",
    "wof:placetype":"venue"
},
  "geometry": {"coordinates":[-87.74826400000001,41.661928],"type":"Point"}
}