{
  "type": "Feature",
  "properties": {
    "iso:country":"US",
    "sg:address":"4617 W Division St",
    "sg:city":"Chicago",
    "sg:classifiers":[
        {
            "category":"Bus Charters",
            "type":"Transportation"
        }
    ],
    "sg:phone":"+1 773 378 3411",
    "sg:postcode":"60651",
    "sg:province":"IL",
    "wof:name":"Radison Bus Co",
    "wof:placetype":"venue"
},
  "geometry": {"coordinates":[-87.741585,41.902351],"type":"Point"}
}