{
  "type": "Feature",
  "properties": {
    "iso:country":"US",
    "sg:address":"505 E South Mahomet Rd",
    "sg:city":"Mahomet",
    "sg:classifiers":[
        {
            "category":"Recreation",
            "type":"Entertainment"
        }
    ],
    "sg:phone":"+1 217 586 5142",
    "sg:postcode":"61853",
    "sg:province":"IL",
    "wof:name":"Long Leap Farm LLC",
    "wof:placetype":"venue"
},
  "geometry": {"coordinates":[-88.402194,40.178543],"type":"Point"}
}