{
  "type": "Feature",
  "properties": {
    "iso:country":"US",
    "sg:address":"422 N Northwest Hwy",
    "sg:city":"Park Ridge",
    "sg:classifiers":[
        {
            "category":"Professional",
            "subcategory":"Lawyer & Legal Services",
            "type":"Services"
        }
    ],
    "sg:phone":"+1 847 698 3080",
    "sg:postcode":"60068",
    "sg:province":"IL",
    "wof:name":"Accurate Clerking Inc",
    "wof:placetype":"venue"
},
  "geometry": {"coordinates":[-87.840407,42.017945],"type":"Point"}
}