{
  "type": "Feature",
  "properties": {
    "addr:full":"7330 W Palos Ave Palos Heights IL 60463",
    "addr:housenumber":"7330",
    "addr:postcode":"60463",
    "addr:street":"W Palos Ave",
    "iso:country":"US",
    "sg:address":"7330 W Palos Ave",
    "sg:city":"Palos Heights",
    "sg:classifiers":[
        {
            "category":"Wholesale",
            "subcategory":"Stationery",
            "type":"Manufacturing & Wholesale Goods"
        }
    ],
    "sg:phone":"+1 708 361 6400",
    "sg:postcode":"60463",
    "sg:province":"IL",
    "sg:tags":[
        "supply"
    ],
    "wof:name":"Standard Register Company",
    "wof:placetype":"venue"
},
  "geometry": {"coordinates":[-87.799103,41.659436],"type":"Point"}
}