{
  "type": "Feature",
  "properties": {
    "addr:full":"107 E Chatham St Lexington IL 61753",
    "addr:housenumber":"107",
    "addr:postcode":"61753",
    "addr:street":"E Chatham St",
    "iso:country":"US",
    "sg:address":"107 E Chatham St",
    "sg:city":"Lexington",
    "sg:classifiers":[
        {
            "category":"Organizations",
            "subcategory":"Religious Organization",
            "type":"Services"
        }
    ],
    "sg:phone":"+1 309 365 5100",
    "sg:postcode":"61753",
    "sg:province":"IL",
    "sg:tags":[
        "church"
    ],
    "sg:website":"www.stpaul-lex.org",
    "wof:name":"St Paul Eve Lutheran Church",
    "wof:placetype":"venue"
},
  "geometry": {"coordinates":[-88.77987,40.646169],"type":"Point"}
}