{
  "type": "Feature",
  "properties": {
    "iso:country":"US",
    "sg:address":"224 N High St",
    "sg:city":"Belleville",
    "sg:classifiers":[
        {
            "category":"Building & Trades",
            "subcategory":"Construction",
            "type":"Services"
        }
    ],
    "sg:phone":"+1 618 277 3744",
    "sg:postcode":"62220",
    "sg:province":"IL",
    "sg:tags":[
        "sewer",
        "contractor"
    ],
    "wof:name":"Jack Lindsay Sewer Svc",
    "wof:placetype":"venue"
},
  "geometry": {"coordinates":[-89.982759,38.516355],"type":"Point"}
}