{
  "type": "Feature",
  "properties": {
    "addr:full":"3941 S Keeler Ave Chicago IL 60632",
    "addr:housenumber":"3941",
    "addr:postcode":"60632",
    "addr:street":"S Keeler Ave",
    "iso:country":"US",
    "sg:address":"3941 S Keeler Ave",
    "sg:city":"Chicago",
    "sg:classifiers":[
        {
            "category":"Education",
            "subcategory":"Music School",
            "type":"Public Place"
        }
    ],
    "sg:phone":"+1 773 890 4907",
    "sg:postcode":"60632",
    "sg:province":"IL",
    "sg:tags":[
        "instrument",
        "teacher",
        "musical"
    ],
    "sg:website":"www.apmchicago.com",
    "wof:name":"American Plating & Mfg Co",
    "wof:placetype":"venue"
},
  "geometry": {"coordinates":[-87.728104,41.820499],"type":"Point"}
}