{
  "type": "Feature",
  "properties": {
    "iso:country":"US",
    "sg:address":"15302 S Joliet Rd",
    "sg:city":"Plainfield",
    "sg:phone":"+1 815 577 8187",
    "sg:postcode":"60544",
    "sg:province":"IL",
    "wof:name":"Canine Creations By Tracy",
    "wof:placetype":"venue"
},
  "geometry": {"coordinates":[-88.20115199999999,41.604781],"type":"Point"}
}