{
  "type": "Feature",
  "properties": {
    "addr:full":"5101 Washington St Gurnee IL 60031",
    "addr:housenumber":"5101",
    "addr:postcode":"60031",
    "addr:street":"Washington St",
    "iso:country":"US",
    "sg:address":"5101 Washington St",
    "sg:city":"Gurnee",
    "sg:classifiers":[
        {
            "category":"Personal",
            "subcategory":"Beauty Salon",
            "type":"Services"
        },
        {
            "category":"Personal",
            "subcategory":"Barber",
            "type":"Services"
        },
        {
            "category":"Personal",
            "subcategory":"Day Spa",
            "type":"Services"
        },
        {
            "category":"Personal",
            "subcategory":"Skin Care",
            "type":"Services"
        },
        {
            "category":"Personal",
            "subcategory":"Nail Salon",
            "type":"Services"
        }
    ],
    "sg:phone":"+1 224 207 8226",
    "sg:postcode":"60031",
    "sg:province":"IL",
    "sg:website":"http://national.citysearch.com/profile/external/3455496/gurnee_il/studio_21_hair_day_spa.html?publisher=yellowpages&reference_id=1&placement=ypwebsitemip",
    "wof:name":"Studio 21 Hair & Day Spa",
    "wof:placetype":"venue"
},
  "geometry": {"coordinates":[-87.928499,42.363301],"type":"Point"}
}