{
  "type": "Feature",
  "properties": {
    "iso:country":"US",
    "sg:address":"639 York St",
    "sg:city":"Quincy",
    "sg:classifiers":[
        {
            "category":"Organizations",
            "subcategory":"Non-profit Organization",
            "type":"Services"
        }
    ],
    "sg:phone":"+1 217 223 7904",
    "sg:postcode":"62301",
    "sg:province":"IL",
    "sg:tags":[
        "affordable",
        "for",
        "housing",
        "elderly",
        "owns",
        "lease"
    ],
    "wof:name":"Community Housing Development",
    "wof:placetype":"venue"
},
  "geometry": {"coordinates":[-91.40614600000001,39.929265],"type":"Point"}
}