{
  "type": "Feature",
  "properties": {
    "addr:full":"4379 W Winneshiek Rd Freeport IL 61032",
    "addr:housenumber":"4379",
    "addr:postcode":"61032",
    "addr:street":"W Winneshiek Rd",
    "iso:country":"US",
    "sg:address":"4379 W Winneshiek Rd",
    "sg:city":"Freeport",
    "sg:phone":"+1 815 232 8174",
    "sg:postcode":"61032",
    "sg:province":"IL",
    "sg:tags":[
        "farm",
        "corn",
        "grain",
        "cash",
        "soybean"
    ],
    "wof:name":"Fred Scheider",
    "wof:placetype":"venue"
},
  "geometry": {"coordinates":[-89.696809,42.336647],"type":"Point"}
}