{
  "type": "Feature",
  "properties": {
    "addr:full":"910 14th Ave Fulton IL 61252",
    "addr:housenumber":"910",
    "addr:postcode":"61252",
    "addr:street":"14Th Ave",
    "iso:country":"US",
    "sg:address":"910 14th Ave",
    "sg:city":"Fulton",
    "sg:classifiers":[
        {
            "category":"Autos & Motor Vehicles",
            "subcategory":"Fuel & Gas Station",
            "type":"Retail Goods"
        }
    ],
    "sg:phone":"+1   ",
    "sg:postcode":"61252",
    "sg:province":"IL",
    "sg:tags":[
        "station"
    ],
    "wof:name":"Kings Korner Auto Repair",
    "wof:placetype":"venue"
},
  "geometry": {"coordinates":[-90.15942,41.86366],"type":"Point"}
}