{
  "type": "Feature",
  "properties": {
    "addr:full":"1508 Grand Ave Waukegan IL 60085",
    "addr:housenumber":"1508",
    "addr:postcode":"60085",
    "addr:street":"Grand Ave",
    "iso:country":"US",
    "sg:address":"1508 Grand Ave",
    "sg:city":"Waukegan",
    "sg:classifiers":[
        {
            "category":"Health Services",
            "subcategory":"Doctor",
            "type":"Services"
        }
    ],
    "sg:phone":"+1 847 623 1508",
    "sg:postcode":"60085",
    "sg:province":"IL",
    "sg:tags":[
        "medical"
    ],
    "wof:name":"Dr Ronald Regal and Assoc",
    "wof:placetype":"venue"
},
  "geometry": {"coordinates":[-87.85061399999999,42.370345],"type":"Point"}
}