{
  "type": "Feature",
  "properties": {
    "addr:full":"2337 17th St Franklin Park IL 60131",
    "addr:housenumber":"2337",
    "addr:postcode":"60131",
    "addr:street":"17Th St",
    "iso:country":"US",
    "sg:address":"2337 17th St",
    "sg:city":"Franklin Park",
    "sg:classifiers":[
        {
            "category":"Manufacturing",
            "subcategory":"Metals",
            "type":"Manufacturing & Wholesale Goods"
        }
    ],
    "sg:phone":"+1 847 451 4230",
    "sg:postcode":"60131",
    "sg:province":"IL",
    "sg:tags":[
        "painting",
        "spray",
        "coating",
        "powder",
        "plastic"
    ],
    "wof:name":"Industrial Finishing Inc",
    "wof:placetype":"venue"
},
  "geometry": {"coordinates":[-87.85544400000001,41.92199],"type":"Point"}
}