{
  "type": "Feature",
  "properties": {
    "iso:country":"US",
    "sg:address":"1837 N Wolcott Ave",
    "sg:city":"Chicago",
    "sg:classifiers":[
        {
            "category":"Professional",
            "subcategory":"Computer Services",
            "type":"Services"
        }
    ],
    "sg:phone":"+1 773 342 6373",
    "sg:postcode":"60622",
    "sg:province":"IL",
    "sg:tags":[
        "repair"
    ],
    "sg:website":"www.NerdsByDesign.com",
    "wof:name":"Nerds By Design",
    "wof:placetype":"venue"
},
  "geometry": {"coordinates":[-87.674846,41.915278],"type":"Point"}
}