{
  "type": "Feature",
  "properties": {
    "addr:full":"4540 Oakton St Skokie IL 60076",
    "addr:housenumber":"4540",
    "addr:postcode":"60076",
    "addr:street":"Oakton St",
    "iso:country":"US",
    "sg:address":"4540 Oakton St",
    "sg:city":"Skokie",
    "sg:classifiers":[
        {
            "category":"Shopping",
            "subcategory":"Used Merchandise",
            "type":"Retail Goods"
        }
    ],
    "sg:phone":"+1   ",
    "sg:postcode":"60076",
    "sg:province":"IL",
    "wof:name":"Loren Ashley Antiques",
    "wof:placetype":"venue"
},
  "geometry": {"coordinates":[-87.74253899999999,42.026325],"type":"Point"}
}