{
  "type": "Feature",
  "properties": {
    "iso:country":"US",
    "sg:address":"40W006 Prairie St",
    "sg:city":"Aurora",
    "sg:classifiers":[
        {
            "category":"Professional",
            "subcategory":"Engineering",
            "type":"Services"
        }
    ],
    "sg:phone":"+1 630 896 0402",
    "sg:postcode":"60506",
    "sg:province":"IL",
    "sg:tags":[
        "refrigeration",
        "engineer"
    ],
    "wof:name":"Powell Refrigeration",
    "wof:placetype":"venue"
},
  "geometry": {"coordinates":[-88.396557,41.75141],"type":"Point"}
}