{
  "type": "Feature",
  "properties": {
    "iso:country":"US",
    "sg:address":"23466 N Elm Rd",
    "sg:city":"Prairie View",
    "sg:classifiers":[
        {
            "category":"Professional",
            "subcategory":"Management & Consulting",
            "type":"Services"
        }
    ],
    "sg:phone":"+1 847 478 0605",
    "sg:postcode":"60069",
    "sg:province":"IL",
    "sg:tags":[
        "consultant",
        "business"
    ],
    "wof:name":"Jas Consulting Solutions",
    "wof:placetype":"venue"
},
  "geometry": {"coordinates":[-87.915964,42.204194],"type":"Point"}
}