{
  "type": "Feature",
  "properties": {
    "addr:full":"2231 N Clybourn Ave Chicago IL 60686",
    "addr:housenumber":"2231",
    "addr:postcode":"60686",
    "addr:street":"N Clybourn Ave",
    "iso:country":"US",
    "sg:address":"2231 N Clybourn Ave",
    "sg:city":"Chicago",
    "sg:classifiers":[
        {
            "category":"Bakery",
            "type":"Food & Drink"
        }
    ],
    "sg:phone":"+1 312 545 3655",
    "sg:postcode":"60686",
    "sg:province":"IL",
    "sg:website":"www.amybeckcakedesign.com",
    "wof:name":"Amy Beck Cake Design",
    "wof:placetype":"venue"
},
  "geometry": {"coordinates":[-87.664974,41.922407],"type":"Point"}
}