{
  "type": "Feature",
  "properties": {
    "addr:full":"1270 Kyle Ct Wauconda IL 60084",
    "addr:housenumber":"1270",
    "addr:postcode":"60084",
    "addr:street":"Kyle Ct",
    "iso:country":"US",
    "sg:address":"1270 Kyle Ct",
    "sg:city":"Wauconda",
    "sg:classifiers":[
        {
            "category":"Autos & Motor Vehicles",
            "subcategory":"Boat Sales",
            "type":"Retail Goods"
        }
    ],
    "sg:phone":"+1 847 353 8400",
    "sg:postcode":"60084",
    "sg:province":"IL",
    "sg:tags":[
        "equipment",
        "marine",
        "supply"
    ],
    "wof:name":"Mack Boring & Parts Co",
    "wof:placetype":"venue"
},
  "geometry": {"coordinates":[-88.14906000000001,42.281692],"type":"Point"}
}