{
  "type": "Feature",
  "properties": {
    "addr:full":"1534 S Taylor Ave Oak Park IL 60304",
    "addr:housenumber":"1534",
    "addr:postcode":"60304",
    "addr:street":"S Taylor Ave",
    "iso:country":"US",
    "sg:address":"1534 S Taylor Ave",
    "sg:city":"Oak Park",
    "sg:classifiers":[
        {
            "category":"Building & Trades",
            "subcategory":"Locksmith",
            "type":"Services"
        }
    ],
    "sg:phone":"+1 708 801 3337",
    "sg:postcode":"60304",
    "sg:province":"IL",
    "sg:tags":[
        "key"
    ],
    "wof:name":"A A Jamal Locksmith",
    "wof:placetype":"venue"
},
  "geometry": {"coordinates":[-87.777821,41.865453],"type":"Point"}
}