{
  "type": "Feature",
  "properties": {
    "addr:full":"2906 S 49th Ave Cicero IL 60804",
    "addr:housenumber":"2906",
    "addr:postcode":"60804",
    "addr:street":"S 49Th Ave",
    "iso:country":"US",
    "sg:address":"2906 S 49th Ave",
    "sg:city":"Cicero",
    "sg:classifiers":[
        {
            "category":"Organizations",
            "subcategory":"Religious Organization",
            "type":"Services"
        }
    ],
    "sg:phone":"+1 708 222 1404",
    "sg:postcode":"60804",
    "sg:province":"IL",
    "wof:name":"Maranatha Revival Church",
    "wof:placetype":"venue"
},
  "geometry": {"coordinates":[-87.747227,41.84009],"type":"Point"}
}