{
  "type": "Feature",
  "properties": {
    "addr:full":"4152 N Keystone Ave Chicago IL 60641",
    "addr:housenumber":"4152",
    "addr:postcode":"60641",
    "addr:street":"N Keystone Ave",
    "iso:country":"US",
    "sg:address":"4152 N Keystone Ave",
    "sg:city":"Chicago",
    "sg:classifiers":[
        {
            "category":"Social Services",
            "subcategory":"Adult Care",
            "type":"Services"
        }
    ],
    "sg:phone":"+1 773 283 9071",
    "sg:postcode":"60641",
    "sg:province":"IL",
    "sg:tags":[
        "residential",
        "aged",
        "homes-institutional"
    ],
    "wof:name":"Keystone Group Home",
    "wof:placetype":"venue"
},
  "geometry": {"coordinates":[-87.72928,41.956421],"type":"Point"}
}