{
  "type": "Feature",
  "properties": {
    "iso:country":"US",
    "sg:address":"1038 Woodlawn Ave",
    "sg:city":"Des Plaines",
    "sg:classifiers":[
        {
            "category":"Professional",
            "subcategory":"Accounting & Tax Preparation",
            "type":"Services"
        }
    ],
    "sg:phone":"+1 847 299 7439",
    "sg:postcode":"60016",
    "sg:province":"IL",
    "wof:name":"Kenneth Zwolinski",
    "wof:placetype":"venue"
},
  "geometry": {"coordinates":[-87.897565,42.043261],"type":"Point"}
}