{
  "type": "Feature",
  "properties": {
    "addr:full":"11250 Moraine Dr Palos Hills IL 60465",
    "addr:housenumber":"11250",
    "addr:postcode":"60465",
    "addr:street":"Moraine Dr Palos",
    "iso:country":"US",
    "sg:address":"11250 Moraine Dr",
    "sg:city":"Palos Hills",
    "sg:classifiers":[
        {
            "category":"Professional",
            "subcategory":"Engineering",
            "type":"Services"
        }
    ],
    "sg:phone":"+1 708 974 4373",
    "sg:postcode":"60465",
    "sg:province":"IL",
    "wof:name":"Truposition Tooling Cons",
    "wof:placetype":"venue"
},
  "geometry": {"coordinates":[-87.815568,41.686027],"type":"Point"}
}