{
  "type": "Feature",
  "properties": {
    "iso:country":"US",
    "sg:address":"530 S Forest Ave",
    "sg:city":"Batavia",
    "sg:classifiers":[
        {
            "category":"Professional",
            "subcategory":"Accounting & Tax Preparation",
            "type":"Services"
        }
    ],
    "sg:phone":"+1 630 482 9987",
    "sg:postcode":"60510",
    "sg:province":"IL",
    "wof:name":"Liberty Business Services",
    "wof:placetype":"venue"
},
  "geometry": {"coordinates":[-88.295484,41.846092],"type":"Point"}
}