{
  "type": "Feature",
  "properties": {
    "iso:country":"US",
    "sg:address":"519 Beltline Rd",
    "sg:city":"Collinsville",
    "sg:classifiers":[
        {
            "category":"Restaurant",
            "type":"Food & Drink"
        }
    ],
    "sg:phone":"+1   ",
    "sg:postcode":"62234",
    "sg:province":"IL",
    "sg:tags":[
        "eating"
    ],
    "wof:name":"Hardees",
    "wof:placetype":"venue"
},
  "geometry": {"coordinates":[-89.975551,38.690929],"type":"Point"}
}