{
  "type": "Feature",
  "properties": {
    "iso:country":"US",
    "sg:address":"10772 Main St Ste 1",
    "sg:city":"Roscoe",
    "sg:classifiers":[
        {
            "category":"Professional",
            "subcategory":"Management & Consulting",
            "type":"Services"
        },
        {
            "category":"Banks & Credit Unions",
            "subcategory":"Investment Brokerage",
            "type":"Services"
        },
        {
            "category":"Insurance",
            "subcategory":"Hazard Insurance",
            "type":"Services"
        },
        {
            "category":"Banks & Credit Unions",
            "subcategory":"Financial Services",
            "type":"Services"
        }
    ],
    "sg:phone":"+1 815 623 1511",
    "sg:postcode":"61073",
    "sg:province":"IL",
    "sg:tags":[
        "advisory",
        "financing",
        "planner",
        "business",
        "consultant",
        "commercial",
        "planning"
    ],
    "wof:name":"Hale Investments",
    "wof:placetype":"venue"
},
  "geometry": {"coordinates":[-89.009535,42.417131],"type":"Point"}
}