{
  "type": "Feature",
  "properties": {
    "iso:country":"US",
    "sg:address":"1561 Naylor Rd",
    "sg:city":"Franklin Grove",
    "sg:classifiers":[
        {
            "category":"Travel",
            "subcategory":"Hotels & Motels",
            "type":"Entertainment"
        }
    ],
    "sg:phone":"+1 815 456 3111",
    "sg:postcode":"61031",
    "sg:province":"IL",
    "sg:tags":[
        "breakfast",
        "accommodation",
        "bed"
    ],
    "wof:name":"Evergreen Bed & Breakfast",
    "wof:placetype":"venue"
},
  "geometry": {"coordinates":[-89.33004099999999,41.866597],"type":"Point"}
}