{
  "type": "Feature",
  "properties": {
    "iso:country":"US",
    "sg:address":"134 E Fort St",
    "sg:city":"Farmington",
    "sg:classifiers":[
        {
            "category":"Organizations",
            "subcategory":"Community Association",
            "type":"Services"
        }
    ],
    "sg:phone":"+1 309 245 4230",
    "sg:postcode":"61531",
    "sg:province":"IL",
    "sg:tags":[
        "fraternal"
    ],
    "wof:name":"Masonic Lodge",
    "wof:placetype":"venue"
},
  "geometry": {"coordinates":[-90.004093,40.698116],"type":"Point"}
}