{
  "type": "Feature",
  "properties": {
    "iso:country":"US",
    "sg:address":"2314 Green Bay Rd",
    "sg:city":"North Chicago",
    "sg:classifiers":[
        {
            "category":"Restaurant",
            "type":"Food & Drink"
        }
    ],
    "sg:menulink":"http://www.allmenus.com/il/shields/124280-quiznos-sub/menu/",
    "sg:phone":"+1 847 689 1980",
    "sg:postcode":"60064",
    "sg:province":"IL",
    "sg:tags":[
        "wrap",
        "american",
        "sandwich"
    ],
    "wof:name":"Quiznos Sub",
    "wof:placetype":"venue"
},
  "geometry": {"coordinates":[-87.865216,42.316927],"type":"Point"}
}