{
  "type": "Feature",
  "properties": {
    "addr:full":"3510 S Halsted Street Chicago IL 60609",
    "addr:housenumber":"3510",
    "addr:postcode":"60609",
    "addr:street":"S Halsted Street",
    "iso:country":"US",
    "sg:address":"3510 S Halsted Street",
    "sg:city":"Chicago",
    "sg:classifiers":[
        {
            "category":"Restaurant",
            "type":"Food & Drink"
        }
    ],
    "sg:phone":"+1 773 847 9058",
    "sg:postcode":"60609",
    "sg:province":"IL",
    "sg:tags":[
        "diner"
    ],
    "wof:name":"Ramova Grill",
    "wof:placetype":"venue"
},
  "geometry": {"coordinates":[-87.646484,41.830373],"type":"Point"}
}