{
  "type": "Feature",
  "properties": {
    "iso:country":"US",
    "sg:address":"410 Green Bay Rd",
    "sg:city":"Kenilworth",
    "sg:classifiers":[
        {
            "category":"Real Estate",
            "subcategory":"Real Estate Agent",
            "type":"Services"
        }
    ],
    "sg:phone":"+1 847 251 5600",
    "sg:postcode":"60043",
    "sg:province":"IL",
    "sg:tags":[
        "insurance"
    ],
    "wof:name":"Kenilworth Realty Co",
    "wof:placetype":"venue"
},
  "geometry": {"coordinates":[-87.71819000000001,42.087405],"type":"Point"}
}