{
  "type": "Feature",
  "properties": {
    "iso:country":"US",
    "sg:address":"18337 Oakwood Ave",
    "sg:city":"Lansing",
    "sg:classifiers":[
        {
            "category":"Building & Trades",
            "subcategory":"Construction",
            "type":"Services"
        }
    ],
    "sg:phone":"+1 312 485 9652",
    "sg:postcode":"60438",
    "sg:province":"IL",
    "sg:tags":[
        "contractor"
    ],
    "wof:name":"Thielen Masonry",
    "wof:placetype":"venue"
},
  "geometry": {"coordinates":[-87.546519,41.561781],"type":"Point"}
}