{
  "type": "Feature",
  "properties": {
    "addr:full":"448 E 76th St Chicago IL 60619",
    "addr:housenumber":"448",
    "addr:postcode":"60619",
    "addr:street":"E 76Th St",
    "iso:country":"US",
    "sg:address":"448 E 76th St",
    "sg:city":"Chicago",
    "sg:classifiers":[
        {
            "category":"Education",
            "subcategory":"Special Training",
            "type":"Public Place"
        }
    ],
    "sg:phone":"+1 773 403 9894",
    "sg:postcode":"60619",
    "sg:province":"IL",
    "sg:tags":[
        "tutoring"
    ],
    "wof:name":"Best Of Both Worlds Tutoring Services, Nfp",
    "wof:placetype":"venue"
},
  "geometry": {"coordinates":[-87.613558,41.756607],"type":"Point"}
}