{
  "type": "Feature",
  "properties": {
    "addr:full":"7185 E State Rte 15 Woodlawn IL 62898",
    "addr:housenumber":"7185",
    "addr:postcode":"62898",
    "addr:street":"E State Rte 15",
    "iso:country":"US",
    "sg:address":"7185 E State Rte 15",
    "sg:city":"Woodlawn",
    "sg:classifiers":[
        {
            "category":"Social Services",
            "subcategory":"Child Care",
            "type":"Services"
        }
    ],
    "sg:phone":"+1 618 735 2497",
    "sg:postcode":"62898",
    "sg:province":"IL",
    "sg:tags":[
        "day"
    ],
    "wof:name":"Tammys Toddler House",
    "wof:placetype":"venue"
},
  "geometry": {"coordinates":[-89.02087899999999,38.307437],"type":"Point"}
}