{
  "type": "Feature",
  "properties": {
    "addr:full":"1795 Grandstand Pl Elgin IL 60123",
    "addr:housenumber":"1795",
    "addr:postcode":"60123",
    "addr:street":"Grandstand Pl",
    "iso:country":"US",
    "sg:address":"1795 Grandstand Pl",
    "sg:city":"Elgin",
    "sg:classifiers":[
        {
            "category":"Health Services",
            "subcategory":"Doctor",
            "type":"Services"
        },
        {
            "category":"Health Services",
            "subcategory":"Podiatrist",
            "type":"Services"
        }
    ],
    "sg:phone":"+1 847 742 0500",
    "sg:postcode":"60123",
    "sg:province":"IL",
    "sg:tags":[
        "physician",
        "medical",
        "surgeons"
    ],
    "wof:name":"Alm Foot Care",
    "wof:placetype":"venue"
},
  "geometry": {"coordinates":[-88.32226900000001,42.03417],"type":"Point"}
}