{
  "type": "Feature",
  "properties": {
    "iso:country":"US",
    "sg:address":"3602 N Kennicott Ave",
    "sg:city":"Arlington Hts",
    "sg:classifiers":[
        {
            "category":"Recreation",
            "type":"Entertainment"
        }
    ],
    "sg:phone":"+1 847 463 8099",
    "sg:postcode":"60004",
    "sg:province":"IL",
    "sg:tags":[
        "amusement"
    ],
    "wof:name":"Atrix Inc",
    "wof:placetype":"venue"
},
  "geometry": {"coordinates":[-87.994929,42.141361],"type":"Point"}
}