{
  "type": "Feature",
  "properties": {
    "addr:full":"1031 N Raddant Rd Batavia IL 60510",
    "addr:housenumber":"1031",
    "addr:postcode":"60510",
    "addr:street":"N Raddant Rd",
    "iso:country":"US",
    "sg:address":"1031 N Raddant Rd",
    "sg:city":"Batavia",
    "sg:classifiers":[
        {
            "category":"Wholesale",
            "subcategory":"Electrical",
            "type":"Manufacturing & Wholesale Goods"
        }
    ],
    "sg:phone":"+1 630 406 8922",
    "sg:postcode":"60510",
    "sg:province":"IL",
    "sg:tags":[
        "equipment"
    ],
    "wof:name":"Ctc Lighting",
    "wof:placetype":"venue"
},
  "geometry": {"coordinates":[-88.29260499999999,41.855681],"type":"Point"}
}