{
  "type": "Feature",
  "properties": {
    "iso:country":"US",
    "sg:address":"649 Devonshire Ln",
    "sg:city":"Wheaton",
    "sg:classifiers":[
        {
            "category":"Real Estate",
            "subcategory":"Real Estate Services",
            "type":"Services"
        },
        {
            "category":"Real Estate",
            "subcategory":"Real Estate Agent",
            "type":"Services"
        }
    ],
    "sg:phone":"+1 630 665 1485",
    "sg:postcode":"60189",
    "sg:province":"IL",
    "sg:tags":[
        "buyer",
        "broker"
    ],
    "wof:name":"Chelchowski Real Estate",
    "wof:placetype":"venue"
},
  "geometry": {"coordinates":[-88.095151,41.847291],"type":"Point"}
}