{
  "type": "Feature",
  "properties": {
    "addr:full":"1101 Hackman St Staunton IL 62088",
    "addr:housenumber":"1101",
    "addr:postcode":"62088",
    "addr:street":"Hackman St",
    "iso:country":"US",
    "sg:address":"1101 Hackman St",
    "sg:city":"Staunton",
    "sg:classifiers":[
        {
            "category":"Education",
            "subcategory":"Special Training",
            "type":"Public Place"
        }
    ],
    "sg:phone":"+1 618 635 8502",
    "sg:postcode":"62088",
    "sg:province":"IL",
    "wof:name":"American Federation of Te",
    "wof:placetype":"venue"
},
  "geometry": {"coordinates":[-89.79674799999999,39.003588],"type":"Point"}
}