{
  "type": "Feature",
  "properties": {
    "iso:country":"US",
    "sg:address":"3412 W 79th St",
    "sg:city":"Chicago",
    "sg:classifiers":[
        {
            "category":"Restaurant",
            "type":"Food & Drink"
        }
    ],
    "sg:phone":"+1 773 863 6922",
    "sg:postcode":"60652",
    "sg:province":"IL",
    "sg:tags":[
        "steakhouse",
        "pizza"
    ],
    "wof:name":"Ashburn Pizza and Ribs",
    "wof:placetype":"venue"
},
  "geometry": {"coordinates":[-87.707741,41.74994],"type":"Point"}
}