{
  "type": "Feature",
  "properties": {
    "iso:country":"US",
    "sg:address":"329 N Illinois St",
    "sg:city":"Belleville",
    "sg:classifiers":[
        {
            "category":"Personal",
            "subcategory":"Beauty Salon",
            "type":"Services"
        },
        {
            "category":"Personal",
            "subcategory":"Barber",
            "type":"Services"
        }
    ],
    "sg:phone":"+1 618 234 4424",
    "sg:postcode":"62220",
    "sg:province":"IL",
    "wof:name":"Cosby's Barber Shop",
    "wof:placetype":"venue"
},
  "geometry": {"coordinates":[-89.984222,38.51693],"type":"Point"}
}