{
  "type": "Feature",
  "properties": {
    "addr:full":"216 Honeysuckle Dr Northbrook IL 60062",
    "addr:housenumber":"216",
    "addr:postcode":"60062",
    "addr:street":"Honeysuckle Dr",
    "iso:country":"US",
    "sg:address":"216 Honeysuckle Dr",
    "sg:city":"Northbrook",
    "sg:classifiers":[
        {
            "category":"Professional",
            "subcategory":"Management & Consulting",
            "type":"Services"
        }
    ],
    "sg:phone":"+1 847 564 5477",
    "sg:postcode":"60062",
    "sg:province":"IL",
    "wof:name":"NW Consulting",
    "wof:placetype":"venue"
},
  "geometry": {"coordinates":[-87.891983,42.147847],"type":"Point"}
}