{
  "type": "Feature",
  "properties": {
    "iso:country":"US",
    "sg:address":"222 S Spring St",
    "sg:city":"Geneseo",
    "sg:classifiers":[
        {
            "category":"Personal",
            "subcategory":"Beauty Salon",
            "type":"Services"
        }
    ],
    "sg:phone":"+1 309 944 4382",
    "sg:postcode":"61254",
    "sg:province":"IL",
    "sg:tags":[
        "shop"
    ],
    "wof:name":"Ruth's Beauty Salon",
    "wof:placetype":"venue"
},
  "geometry": {"coordinates":[-90.151699,41.450897],"type":"Point"}
}