{
  "type": "Feature",
  "properties": {
    "iso:country":"US",
    "sg:address":"2710 Laude Dr",
    "sg:city":"Rockford",
    "sg:classifiers":[
        {
            "category":"Manufacturing",
            "subcategory":"Glass & Minerals",
            "type":"Manufacturing & Wholesale Goods"
        }
    ],
    "sg:phone":"+1 815 226 4627",
    "sg:postcode":"61109",
    "sg:province":"IL",
    "sg:tags":[
        "insulation"
    ],
    "wof:name":"Owens-Corning Inc",
    "wof:placetype":"venue"
},
  "geometry": {"coordinates":[-89.05321499999999,42.233931],"type":"Point"}
}