{
  "type": "Feature",
  "properties": {
    "iso:country":"US",
    "sg:address":"832 S 6th St",
    "sg:city":"Princeton",
    "sg:classifiers":[
        {
            "category":"Health Services",
            "subcategory":"Doctor",
            "type":"Services"
        }
    ],
    "sg:phone":"+1 815 875 1217",
    "sg:postcode":"61356",
    "sg:province":"IL",
    "sg:tags":[
        "dentist"
    ],
    "wof:name":"Timothy J Puhr PC",
    "wof:placetype":"venue"
},
  "geometry": {"coordinates":[-89.450541,41.367481],"type":"Point"}
}