{
  "type": "Feature",
  "properties": {
    "addr:full":"1401 N 2nd St Rockford IL 61107",
    "addr:housenumber":"1401",
    "addr:postcode":"61107",
    "addr:street":"N 2Nd St",
    "iso:country":"US",
    "sg:address":"1401 N 2nd St",
    "sg:city":"Rockford",
    "sg:classifiers":[
        {
            "category":"Recreation",
            "type":"Entertainment"
        }
    ],
    "sg:phone":"+1 815 987 8800",
    "sg:postcode":"61107",
    "sg:province":"IL",
    "sg:tags":[
        "park",
        "district"
    ],
    "wof:name":"Sinnissippi Golf Course",
    "wof:placetype":"venue"
},
  "geometry": {"coordinates":[-89.07044999999999,42.281824],"type":"Point"}
}