{
  "type": "Feature",
  "properties": {
    "iso:country":"US",
    "sg:address":"207 Lonsdale Rd",
    "sg:city":"Prospect Heights",
    "sg:classifiers":[
        {
            "category":"Building & Trades",
            "subcategory":"Construction",
            "type":"Services"
        }
    ],
    "sg:phone":"+1 847 394 9009",
    "sg:postcode":"60070",
    "sg:province":"IL",
    "sg:tags":[
        "painter"
    ],
    "wof:name":"Essex Painting & Remodeling Co",
    "wof:placetype":"venue"
},
  "geometry": {"coordinates":[-87.929365,42.091206],"type":"Point"}
}