{
  "type": "Feature",
  "properties": {
    "iso:country":"US",
    "sg:address":"180 Old Sutton Rd",
    "sg:city":"Barrington",
    "sg:classifiers":[
        {
            "category":"Farming",
            "subcategory":"Livestock Farm",
            "type":"Manufacturing & Wholesale Goods"
        }
    ],
    "sg:phone":"+1 847 921 3560",
    "sg:postcode":"60010",
    "sg:province":"IL",
    "sg:tags":[
        "equine"
    ],
    "wof:name":"TLC Farm Inc",
    "wof:placetype":"venue"
},
  "geometry": {"coordinates":[-88.194569,42.097966],"type":"Point"}
}