{
  "type": "Feature",
  "properties": {
    "iso:country":"US",
    "sg:address":"11700 S Western Ave",
    "sg:city":"Chicago",
    "sg:classifiers":[
        {
            "category":"Museum",
            "subcategory":"Botanical Garden",
            "type":"Entertainment"
        }
    ],
    "sg:phone":"+1 773 239 1338",
    "sg:postcode":"60643",
    "sg:province":"IL",
    "sg:tags":[
        "center",
        "nature"
    ],
    "wof:name":"Avon Inc",
    "wof:placetype":"venue"
},
  "geometry": {"coordinates":[-87.68075899999999,41.679111],"type":"Point"}
}