{
  "type": "Feature",
  "properties": {
    "addr:full":"23950 N Hillfarm Rd Lake Barrington IL 60010",
    "addr:housenumber":"23950",
    "addr:postcode":"60010",
    "addr:street":"N Hillfarm Rd",
    "iso:country":"US",
    "sg:address":"23950 N Hillfarm Rd",
    "sg:city":"Lake Barrington",
    "sg:classifiers":[
        {
            "category":"Real Estate",
            "subcategory":"Real Estate Agent",
            "type":"Services"
        }
    ],
    "sg:phone":"+1 847 304 8131",
    "sg:postcode":"60010",
    "sg:province":"IL",
    "wof:name":"Toll Brothers Inc",
    "wof:placetype":"venue"
},
  "geometry": {"coordinates":[-88.167602,42.211784],"type":"Point"}
}