{
  "type": "Feature",
  "properties": {
    "addr:full":"9337 Drake Ave Evanston IL 60203",
    "addr:housenumber":"9337",
    "addr:postcode":"60203",
    "addr:street":"Drake Ave",
    "iso:country":"US",
    "sg:address":"9337 Drake Ave",
    "sg:city":"Evanston",
    "sg:classifiers":[
        {
            "category":"Professional",
            "subcategory":"Art Services",
            "type":"Services"
        }
    ],
    "sg:phone":"+1 847 674 7736",
    "sg:postcode":"60203",
    "sg:province":"IL",
    "sg:tags":[
        "graphic",
        "design"
    ],
    "wof:name":"Bowlby Joseph Graphic Designs",
    "wof:placetype":"venue"
},
  "geometry": {"coordinates":[-87.716624,42.051083],"type":"Point"}
}