{
  "type": "Feature",
  "properties": {
    "iso:country":"US",
    "sg:address":"6628 West Cermak Road",
    "sg:city":"Berwyn",
    "sg:classifiers":[
        {
            "category":"Real Estate",
            "subcategory":"Real Estate Agent",
            "type":"Services"
        }
    ],
    "sg:phone":"+1 630 250 4513",
    "sg:postcode":"60402",
    "sg:province":"IL",
    "wof:name":"Jax Realtors & REO Group",
    "wof:placetype":"venue"
},
  "geometry": {"coordinates":[-87.78980799999999,41.850684],"type":"Point"}
}