{
  "type": "Feature",
  "properties": {
    "iso:country":"US",
    "sg:address":"249 W Lake St",
    "sg:city":"Elmhurst",
    "sg:classifiers":[
        {
            "category":"Building & Trades",
            "subcategory":"Construction",
            "type":"Services"
        }
    ],
    "sg:phone":"+1 630 834 9555",
    "sg:postcode":"60126",
    "sg:province":"IL",
    "sg:tags":[
        "excavation",
        "contractor"
    ],
    "wof:name":"E Company",
    "wof:placetype":"venue"
},
  "geometry": {"coordinates":[-87.94517399999999,41.91539],"type":"Point"}
}