{
  "type": "Feature",
  "properties": {
    "iso:country":"US",
    "sg:address":"296 Williams Pl",
    "sg:city":"East Dundee",
    "sg:classifiers":[
        {
            "category":"Professional",
            "subcategory":"Computer Services",
            "type":"Services"
        }
    ],
    "sg:phone":"+1 847 428 9199",
    "sg:postcode":"60118",
    "sg:province":"IL",
    "sg:tags":[
        "repair"
    ],
    "sg:website":"www.a-techinc.com",
    "wof:name":"A-Tech Computer Service Inc",
    "wof:placetype":"venue"
},
  "geometry": {"coordinates":[-88.27269699999999,42.0947],"type":"Point"}
}