{
  "type": "Feature",
  "properties": {
    "iso:country":"US",
    "sg:address":"2 Buckingham Ln",
    "sg:city":"Buffalo Grove",
    "sg:classifiers":[
        {
            "category":"Utilities",
            "subcategory":"Cable",
            "type":"Services"
        }
    ],
    "sg:phone":"+1 847 229 7056",
    "sg:postcode":"60089",
    "sg:province":"IL",
    "sg:tags":[
        "satellite",
        "carrier"
    ],
    "wof:name":"Dish Network",
    "wof:placetype":"venue"
},
  "geometry": {"coordinates":[-87.956336,42.160157],"type":"Point"}
}