{
  "type": "Feature",
  "properties": {
    "iso:country":"US",
    "sg:address":"2980 Hart Ct",
    "sg:city":"Franklin Park",
    "sg:classifiers":[
        {
            "category":"Farming",
            "subcategory":"Farm & Veterinary Services",
            "type":"Manufacturing & Wholesale Goods"
        }
    ],
    "sg:phone":"+1 847 451 0026",
    "sg:postcode":"60131",
    "sg:province":"IL",
    "sg:tags":[
        "preparation",
        "crop",
        "for",
        "market"
    ],
    "wof:name":"General Produce Distributors",
    "wof:placetype":"venue"
},
  "geometry": {"coordinates":[-87.89011,41.932374],"type":"Point"}
}