{
  "type": "Feature",
  "properties": {
    "addr:full":"595 Thornhill Dr Carol Stream IL 60188",
    "addr:housenumber":"595",
    "addr:postcode":"60188",
    "addr:street":"Thornhill Dr",
    "iso:country":"US",
    "sg:address":"595 Thornhill Dr",
    "sg:city":"Carol Stream",
    "sg:classifiers":[
        {
            "category":"Building & Trades",
            "subcategory":"Construction",
            "type":"Services"
        }
    ],
    "sg:phone":"+1 630 439 4112",
    "sg:postcode":"60188",
    "sg:province":"IL",
    "sg:tags":[
        "resurfacing",
        "laying",
        "refinishing",
        "floor"
    ],
    "wof:name":"G & J Flooring",
    "wof:placetype":"venue"
},
  "geometry": {"coordinates":[-88.097026,41.891292],"type":"Point"}
}