{
  "type": "Feature",
  "properties": {
    "addr:full":"13751 N 300th St Wheeler IL 62479",
    "addr:housenumber":"13751",
    "addr:postcode":"62479",
    "addr:street":"N 300Th St",
    "iso:country":"US",
    "sg:address":"13751 N 300th St",
    "sg:city":"Wheeler",
    "sg:classifiers":[
        {
            "category":"Farming",
            "subcategory":"Livestock Farm",
            "type":"Manufacturing & Wholesale Goods"
        }
    ],
    "sg:phone":"+1 217 925 5389",
    "sg:postcode":"62479",
    "sg:province":"IL",
    "sg:tags":[
        "beef",
        "feedlot",
        "cattle"
    ],
    "wof:name":"Maple Lawn Herford Farm",
    "wof:placetype":"venue"
},
  "geometry": {"coordinates":[-88.316596,39.05407],"type":"Point"}
}