{
  "type": "Feature",
  "properties": {
    "addr:full":"8 E Galena Blvd Aurora IL 60506",
    "addr:housenumber":"8",
    "addr:postcode":"60506",
    "addr:street":"E Galena Blvd",
    "iso:country":"US",
    "sg:address":"8 E Galena Blvd",
    "sg:city":"Aurora",
    "sg:classifiers":[
        {
            "category":"Shopping",
            "subcategory":"Computers & Home Electronics",
            "type":"Retail Goods"
        }
    ],
    "sg:phone":"+1 630 897 2884",
    "sg:postcode":"60506",
    "sg:province":"IL",
    "sg:tags":[
        "software"
    ],
    "wof:name":"Proactive Software Inc",
    "wof:placetype":"venue"
},
  "geometry": {"coordinates":[-88.413465,41.769179],"type":"Point"}
}