{
  "type": "Feature",
  "properties": {
    "iso:country":"US",
    "sg:address":"112 RIDGE RD",
    "sg:city":"MINOOKA",
    "sg:classifiers":[
        {
            "category":"Wholesale",
            "subcategory":"Machinery & Supplies",
            "type":"Manufacturing & Wholesale Goods"
        },
        {
            "category":"Recreation",
            "type":"Entertainment"
        }
    ],
    "sg:phone":"+1 815 467 5600",
    "sg:postcode":"60447",
    "sg:province":"IL",
    "sg:tags":[
        "valves-repairing",
        "valve"
    ],
    "sg:website":"http://www.mwvalve.com",
    "wof:name":"Midwest Valve Services Inc",
    "wof:placetype":"venue"
},
  "geometry": {"coordinates":[-88.271323,41.455272],"type":"Point"}
}