{
  "type": "Feature",
  "properties": {
    "iso:country":"US",
    "sg:address":"404 N Wabash Ave",
    "sg:city":"Chicago",
    "sg:classifiers":[
        {
            "category":"Food & Beverages",
            "subcategory":"Groceries & Convenience Stores",
            "type":"Retail Goods"
        }
    ],
    "sg:phone":"+1 312 494 9904",
    "sg:postcode":"60611",
    "sg:province":"IL",
    "wof:name":"Metro Mart",
    "wof:placetype":"venue"
},
  "geometry": {"coordinates":[-87.626503,41.889301],"type":"Point"}
}