{
  "type": "Feature",
  "properties": {
    "addr:full":"302 E Grant Hwy Marengo IL 60152",
    "addr:housenumber":"302",
    "addr:postcode":"60152",
    "addr:street":"E Grant Hwy",
    "iso:country":"US",
    "sg:address":"302 E Grant Hwy",
    "sg:city":"Marengo",
    "sg:classifiers":[
        {
            "category":"Autos & Motor Vehicles",
            "subcategory":"Fuel & Gas Station",
            "type":"Retail Goods"
        },
        {
            "category":"Food & Beverages",
            "subcategory":"Groceries & Convenience Stores",
            "type":"Retail Goods"
        }
    ],
    "sg:phone":"+1 815 568 8363",
    "sg:postcode":"60152",
    "sg:province":"IL",
    "sg:website":"http://www.shell.com",
    "wof:name":"Marengo Quick Mart",
    "wof:placetype":"venue"
},
  "geometry": {"coordinates":[-88.6058,42.247681],"type":"Point"}
}