{
  "type": "Feature",
  "properties": {
    "addr:full":"213 S State St Jerseyville IL 62052",
    "addr:housenumber":"213",
    "addr:postcode":"62052",
    "addr:street":"S State St",
    "iso:country":"US",
    "sg:address":"213 S State St",
    "sg:city":"Jerseyville",
    "sg:classifiers":[
        {
            "category":"Home & Garden",
            "subcategory":"Carpets & Floor Coverings",
            "type":"Retail Goods"
        }
    ],
    "sg:phone":"+1 618 498 4832",
    "sg:postcode":"62052",
    "sg:province":"IL",
    "sg:tags":[
        "material"
    ],
    "wof:name":"Gundlach Floors & More",
    "wof:placetype":"venue"
},
  "geometry": {"coordinates":[-90.32693999999999,39.118606],"type":"Point"}
}