{
  "type": "Feature",
  "properties": {
    "iso:country":"US",
    "sg:address":"1525 N 2nd St",
    "sg:city":"Dupo",
    "sg:classifiers":[
        {
            "category":"Real Estate",
            "subcategory":"Developer",
            "type":"Services"
        }
    ],
    "sg:phone":"+1 618 286 4094",
    "sg:postcode":"62239",
    "sg:province":"IL",
    "wof:name":"Prairie Dupont Business Park",
    "wof:placetype":"venue"
},
  "geometry": {"coordinates":[-90.200323,38.53632],"type":"Point"}
}