{
  "type": "Feature",
  "properties": {
    "addr:full":"2777 Carriage Way Aurora IL 60504",
    "addr:housenumber":"2777",
    "addr:postcode":"60504",
    "addr:street":"Carriage Way",
    "iso:country":"US",
    "sg:address":"2777 Carriage Way",
    "sg:city":"Aurora",
    "sg:classifiers":[
        {
            "category":"Professional",
            "subcategory":"Business Services",
            "type":"Services"
        }
    ],
    "sg:phone":"+1 630 820 6371",
    "sg:postcode":"60504",
    "sg:province":"IL",
    "wof:name":"Tj Miniatures Inc",
    "wof:placetype":"venue"
},
  "geometry": {"coordinates":[-88.247901,41.75246],"type":"Point"}
}