{
  "type": "Feature",
  "properties": {
    "iso:country":"US",
    "sg:address":"3121 Barreville Rd",
    "sg:city":"Crystal Lake",
    "sg:classifiers":[
        {
            "category":"Government",
            "subcategory":"Police Station",
            "type":"Public Place"
        }
    ],
    "sg:phone":"+1 815 455 3918",
    "sg:postcode":"60012",
    "sg:province":"IL",
    "sg:tags":[
        "department"
    ],
    "sg:website":"www.prairiegrove.org",
    "wof:name":"Prairie Grove Police Dept",
    "wof:placetype":"venue"
},
  "geometry": {"coordinates":[-88.26104,42.287308],"type":"Point"}
}