{
  "type": "Feature",
  "properties": {
    "addr:full":"103 Ivy Ln Bolingbrook IL 60490",
    "addr:housenumber":"103",
    "addr:postcode":"60490",
    "addr:street":"Ivy Ln",
    "iso:country":"US",
    "sg:address":"103 Ivy Ln",
    "sg:city":"Bolingbrook",
    "sg:classifiers":[
        {
            "category":"Health Services",
            "subcategory":"Doctor",
            "type":"Services"
        }
    ],
    "sg:phone":"+1 224 764 0786",
    "sg:postcode":"60490",
    "sg:province":"IL",
    "sg:tags":[
        "medicine",
        "physician",
        "practice",
        "surgeons",
        "family"
    ],
    "wof:name":"Imed Practice Solutions",
    "wof:placetype":"venue"
},
  "geometry": {"coordinates":[-88.155948,41.693635],"type":"Point"}
}