{
  "type": "Feature",
  "properties": {
    "addr:full":"6835 N Concord Ln Niles IL 60714",
    "addr:housenumber":"6835",
    "addr:postcode":"60714",
    "addr:street":"N Concord Ln",
    "iso:country":"US",
    "sg:address":"6835 N Concord Ln",
    "sg:city":"Niles",
    "sg:classifiers":[
        {
            "category":"Health Services",
            "subcategory":"Optometrist",
            "type":"Services"
        }
    ],
    "sg:phone":"+1 312 519 3230",
    "sg:postcode":"60714",
    "sg:province":"IL",
    "wof:name":"Pamela A Lowe Dr",
    "wof:placetype":"venue"
},
  "geometry": {"coordinates":[-87.784352,42.005768],"type":"Point"}
}