{
  "type": "Feature",
  "properties": {
    "addr:full":"2841 N Pulaski Rd Chicago IL 60641",
    "addr:housenumber":"2841",
    "addr:postcode":"60641",
    "addr:street":"N Pulaski Rd",
    "iso:country":"US",
    "sg:address":"2841 N Pulaski Rd",
    "sg:city":"Chicago",
    "sg:classifiers":[
        {
            "category":"Restaurant",
            "type":"Food & Drink"
        }
    ],
    "sg:phone":"+1 773 202 8512",
    "sg:postcode":"60641",
    "sg:province":"IL",
    "wof:name":"Burger Land",
    "wof:placetype":"venue"
},
  "geometry": {"coordinates":[-87.726906,41.931897],"type":"Point"}
}