{
  "type": "Feature",
  "properties": {
    "addr:full":"1537 W Rosemont Ave Chicago IL 60660",
    "addr:housenumber":"1537",
    "addr:postcode":"60660",
    "addr:street":"W Rosemont Ave",
    "iso:country":"US",
    "sg:address":"1537 W Rosemont Ave",
    "sg:city":"Chicago",
    "sg:classifiers":[
        {
            "category":"Social Services",
            "subcategory":"Adult Care",
            "type":"Services"
        }
    ],
    "sg:phone":"+1 773 465 3685",
    "sg:postcode":"60660",
    "sg:province":"IL",
    "sg:tags":[
        "residential"
    ],
    "wof:name":"HOME",
    "wof:placetype":"venue"
},
  "geometry": {"coordinates":[-87.668933,41.996331],"type":"Point"}
}