{
  "type": "Feature",
  "properties": {
    "iso:country":"US",
    "sg:address":"38360 N Shagbark Ln",
    "sg:city":"Wadsworth",
    "sg:classifiers":[
        {
            "category":"Professional",
            "type":"Services"
        }
    ],
    "sg:phone":"+1 847 244 4918",
    "sg:postcode":"60083",
    "sg:province":"IL",
    "wof:name":"Jane L Osa & Associates Inc",
    "wof:placetype":"venue"
},
  "geometry": {"coordinates":[-87.912609,42.424542],"type":"Point"}
}