{
  "type": "Feature",
  "properties": {
    "iso:country":"US",
    "sg:address":"1107 Peoria St",
    "sg:city":"Washington",
    "sg:classifiers":[
        {
            "category":"Building & Trades",
            "subcategory":"Construction",
            "type":"Services"
        }
    ],
    "sg:phone":"+1 309 444 2781",
    "sg:postcode":"61536",
    "sg:province":"IL",
    "sg:tags":[
        "hanging",
        "contractor"
    ],
    "wof:name":"Painting Plus",
    "wof:placetype":"venue"
},
  "geometry": {"coordinates":[-89.79571799999999,40.694141],"type":"Point"}
}