{
  "type": "Feature",
  "properties": {
    "addr:full":"147 N White St Frankfort IL 60423",
    "addr:housenumber":"147",
    "addr:postcode":"60423",
    "addr:street":"N White St",
    "iso:country":"US",
    "sg:address":"147 N White St",
    "sg:city":"Frankfort",
    "sg:classifiers":[
        {
            "category":"Professional",
            "subcategory":"Business Services",
            "type":"Services"
        }
    ],
    "sg:phone":"+1 815 469 1918",
    "sg:postcode":"60423",
    "sg:province":"IL",
    "sg:tags":[
        "contractor"
    ],
    "wof:name":"White Street Inspection Svc",
    "wof:placetype":"venue"
},
  "geometry": {"coordinates":[-87.849226,41.502587],"type":"Point"}
}