{
  "type": "Feature",
  "properties": {
    "iso:country":"US",
    "sg:address":"1725 W Harrison St Ste 250",
    "sg:city":"Chicago",
    "sg:classifiers":[
        {
            "category":"Health Services",
            "subcategory":"Doctor",
            "type":"Services"
        }
    ],
    "sg:phone":"+1 312 942 6163",
    "sg:postcode":"60612",
    "sg:province":"IL",
    "sg:tags":[
        "medicine",
        "internal"
    ],
    "sg:website":"rush.photobooks.com/directory/pr...",
    "wof:name":"Dr David Baldwin Jr, MD",
    "wof:placetype":"venue"
},
  "geometry": {"coordinates":[-87.669353,41.874152],"type":"Point"}
}