{
  "type": "Feature",
  "properties": {
    "iso:country":"US",
    "sg:address":"17936 Halsted St",
    "sg:city":"Homewood",
    "sg:classifiers":[
        {
            "category":"Education",
            "subcategory":"Special Training",
            "type":"Public Place"
        }
    ],
    "sg:phone":"+1 708 798 0238",
    "sg:postcode":"60430",
    "sg:province":"IL",
    "wof:name":"Sylvan Learning Centers",
    "wof:placetype":"venue"
},
  "geometry": {"coordinates":[-87.63628799999999,41.563156],"type":"Point"}
}