{
  "type": "Feature",
  "properties": {
    "addr:full":"1124 Florence Ave Evanston IL 60202",
    "addr:housenumber":"1124",
    "addr:postcode":"60202",
    "addr:street":"Florence Ave",
    "iso:country":"US",
    "sg:address":"1124 Florence Ave",
    "sg:city":"Evanston",
    "sg:classifiers":[
        {
            "category":"Building & Trades",
            "subcategory":"Construction",
            "type":"Services"
        }
    ],
    "sg:phone":"+1 847 570 9956",
    "sg:postcode":"60202",
    "sg:province":"IL",
    "sg:tags":[
        "designer"
    ],
    "wof:name":"CJB Assoc",
    "wof:placetype":"venue"
},
  "geometry": {"coordinates":[-87.69466,42.03767],"type":"Point"}
}