{
  "type": "Feature",
  "properties": {
    "iso:country":"US",
    "sg:address":"8051 Knox Ave",
    "sg:city":"Skokie",
    "sg:classifiers":[
        {
            "category":"Freight",
            "type":"Transportation"
        }
    ],
    "sg:phone":"+1 847 679 4338",
    "sg:postcode":"60076",
    "sg:province":"IL",
    "sg:tags":[
        "operator",
        "local",
        "trucking"
    ],
    "wof:name":"Olympic Moving & Storage Svc",
    "wof:placetype":"venue"
},
  "geometry": {"coordinates":[-87.743766,42.02762],"type":"Point"}
}