{
  "type": "Feature",
  "properties": {
    "iso:country":"US",
    "sg:address":"4341 W Diversey Ave",
    "sg:city":"Chicago",
    "sg:classifiers":[
        {
            "category":"Wholesale",
            "subcategory":"Hardware",
            "type":"Manufacturing & Wholesale Goods"
        },
        {
            "category":"Home & Garden",
            "subcategory":"Garden Supply",
            "type":"Retail Goods"
        },
        {
            "category":"Retail",
            "subcategory":"Repair Shop",
            "type":"Services"
        }
    ],
    "sg:phone":"+1 773 276 0094",
    "sg:postcode":"60639",
    "sg:province":"IL",
    "sg:tags":[
        "renting",
        "lawn",
        "outdoor",
        "power",
        "landscaping",
        "equipment-sales",
        "equipment",
        "saw"
    ],
    "sg:website":"http://www.stihlusa.com/",
    "wof:name":"Bird Engines",
    "wof:placetype":"venue"
},
  "geometry": {"coordinates":[-87.73535699999999,41.93169],"type":"Point"}
}