{
  "type": "Feature",
  "properties": {
    "addr:full":"11767 Juanita Dr Orland Park IL 60467",
    "addr:housenumber":"11767",
    "addr:postcode":"60467",
    "addr:street":"Juanita Dr",
    "iso:country":"US",
    "sg:address":"11767 Juanita Dr",
    "sg:city":"Orland Park",
    "sg:classifiers":[
        {
            "category":"Building & Trades",
            "subcategory":"Construction",
            "type":"Services"
        }
    ],
    "sg:phone":"+1 708 349 2021",
    "sg:postcode":"60467",
    "sg:province":"IL",
    "sg:tags":[
        "contractor"
    ],
    "wof:name":"Creative Counters Inc",
    "wof:placetype":"venue"
},
  "geometry": {"coordinates":[-87.90393400000001,41.597774],"type":"Point"}
}