{
  "type": "Feature",
  "properties": {
    "iso:country":"US",
    "sg:address":"1875 Dempster St",
    "sg:city":"Park Ridge",
    "sg:classifiers":[
        {
            "category":"Health Services",
            "subcategory":"Doctor",
            "type":"Services"
        }
    ],
    "sg:phone":"+1 847 696 1200",
    "sg:postcode":"60068",
    "sg:province":"IL",
    "sg:tags":[
        "cardiology"
    ],
    "wof:name":"Thomas A Pavlovic MD",
    "wof:placetype":"venue"
},
  "geometry": {"coordinates":[-87.85105299999999,42.039593],"type":"Point"}
}