{
  "type": "Feature",
  "properties": {
    "addr:full":"14101 S Hoxie Ave Chicago IL 60633",
    "addr:housenumber":"14101",
    "addr:postcode":"60633",
    "addr:street":"S Hoxie Ave",
    "iso:country":"US",
    "sg:address":"14101 S Hoxie Ave",
    "sg:city":"Chicago",
    "sg:classifiers":[
        {
            "category":"Government",
            "subcategory":"Fire Station",
            "type":"Public Place"
        }
    ],
    "sg:phone":"+1 708 862 4686",
    "sg:postcode":"60633",
    "sg:province":"IL",
    "sg:tags":[
        "department"
    ],
    "wof:name":"Burnham Vfd",
    "wof:placetype":"venue"
},
  "geometry": {"coordinates":[-87.56047100000001,41.639069],"type":"Point"}
}