{
  "type": "Feature",
  "properties": {
    "iso:country":"US",
    "sg:address":"1091 Franklin St",
    "sg:city":"Mundelein",
    "sg:classifiers":[
        {
            "category":"Professional",
            "subcategory":"Management & Consulting",
            "type":"Services"
        }
    ],
    "sg:phone":"+1 847 949 9633",
    "sg:postcode":"60060",
    "sg:province":"IL",
    "sg:tags":[
        "business"
    ],
    "wof:name":"Renz Consulting",
    "wof:placetype":"venue"
},
  "geometry": {"coordinates":[-88.026412,42.281241],"type":"Point"}
}