{
  "type": "Feature",
  "properties": {
    "iso:country":"US",
    "sg:address":"2104 Oak Leaf St",
    "sg:city":"Joliet",
    "sg:classifiers":[
        {
            "category":"Home & Garden",
            "subcategory":"Furniture",
            "type":"Retail Goods"
        }
    ],
    "sg:phone":"+1 815 621 5482",
    "sg:postcode":"60436",
    "sg:province":"IL",
    "sg:tags":[
        "cabinet"
    ],
    "wof:name":"Midwest Storage Solutions LLC",
    "wof:placetype":"venue"
},
  "geometry": {"coordinates":[-88.13409900000001,41.512327],"type":"Point"}
}