{
  "type": "Feature",
  "properties": {
    "iso:country":"US",
    "sg:address":"7041 Pershing Rd",
    "sg:city":"Berwyn",
    "sg:classifiers":[
        {
            "category":"Retail",
            "subcategory":"Auto Repair",
            "type":"Services"
        }
    ],
    "sg:phone":"+1 708 795 6439",
    "sg:postcode":"60402",
    "sg:province":"IL",
    "sg:tags":[
        "machine",
        "shop"
    ],
    "wof:name":"R & R Machine Works Inc",
    "wof:placetype":"venue"
},
  "geometry": {"coordinates":[-87.799626,41.821132],"type":"Point"}
}