{
  "type": "Feature",
  "properties": {
    "addr:full":"28 Delburne Dr Davis IL 61019",
    "addr:housenumber":"28",
    "addr:postcode":"61019",
    "addr:street":"Delburne Dr",
    "iso:country":"US",
    "sg:address":"28 Delburne Dr",
    "sg:city":"Davis",
    "sg:classifiers":[
        {
            "category":"Professional",
            "type":"Services"
        }
    ],
    "sg:phone":"+1 815 248 3720",
    "sg:postcode":"61019",
    "sg:province":"IL",
    "sg:tags":[
        "establishment"
    ],
    "wof:name":"Betson Imperial Parts",
    "wof:placetype":"venue"
},
  "geometry": {"coordinates":[-89.41562500000001,42.454924],"type":"Point"}
}