{
  "type": "Feature",
  "properties": {
    "addr:full":"20895 E Il Route 64 Esmond IL 60129",
    "addr:housenumber":"20895",
    "addr:postcode":"60129",
    "addr:street":"E Il Route 64",
    "iso:country":"US",
    "sg:address":"20895 E Il Route 64",
    "sg:city":"Esmond",
    "sg:classifiers":[
        {
            "category":"Manufacturing",
            "subcategory":"Food",
            "type":"Manufacturing & Wholesale Goods"
        },
        {
            "category":"Farming",
            "subcategory":"Farm",
            "type":"Manufacturing & Wholesale Goods"
        }
    ],
    "sg:phone":"+1 815 393 4225",
    "sg:postcode":"60129",
    "sg:province":"IL",
    "sg:tags":[
        "corn",
        "product"
    ],
    "wof:name":"Walter Roush",
    "wof:placetype":"venue"
},
  "geometry": {"coordinates":[-88.917354,42.000849],"type":"Point"}
}