{
  "type": "Feature",
  "properties": {
    "iso:country":"US",
    "sg:address":"261 E Helen Rd",
    "sg:city":"Palatine",
    "sg:classifiers":[
        {
            "category":"Home & Garden",
            "subcategory":"Carpets & Floor Coverings",
            "type":"Retail Goods"
        }
    ],
    "sg:phone":"+1 847 934 4670",
    "sg:postcode":"60067",
    "sg:province":"IL",
    "wof:name":"Northern Carpet Co",
    "wof:placetype":"venue"
},
  "geometry": {"coordinates":[-88.036269,42.103991],"type":"Point"}
}