{
  "type": "Feature",
  "properties": {
    "addr:full":"1500 Shermer Rd Northbrook IL 60062",
    "addr:housenumber":"1500",
    "addr:postcode":"60062",
    "addr:street":"Shermer Rd",
    "iso:country":"US",
    "sg:address":"1500 Shermer Rd",
    "sg:city":"Northbrook",
    "sg:classifiers":[
        {
            "category":"Health Services",
            "subcategory":"Doctor",
            "type":"Services"
        }
    ],
    "sg:phone":"+1 847 564 2205",
    "sg:postcode":"60062",
    "sg:province":"IL",
    "wof:name":"Jeffery A Arnold DDS PC",
    "wof:placetype":"venue"
},
  "geometry": {"coordinates":[-87.82924,42.124641],"type":"Point"}
}