{
  "type": "Feature",
  "properties": {
    "iso:country":"US",
    "sg:address":"9388 Renken Rd",
    "sg:city":"Staunton",
    "sg:classifiers":[
        {
            "category":"Autos & Motor Vehicles",
            "subcategory":"Motorcycle Sales",
            "type":"Retail Goods"
        }
    ],
    "sg:phone":"+1   ",
    "sg:postcode":"62088",
    "sg:province":"IL",
    "wof:name":"Scooters & More Inc",
    "wof:placetype":"venue"
},
  "geometry": {"coordinates":[-89.826018,38.991773],"type":"Point"}
}