{
  "type": "Feature",
  "properties": {
    "iso:country":"US",
    "sg:address":"PO Box 1356",
    "sg:city":"Carbondale",
    "sg:classifiers":[
        {
            "category":"Building & Trades",
            "subcategory":"Construction",
            "type":"Services"
        }
    ],
    "sg:phone":"+1 618 684 5464",
    "sg:postcode":"62903",
    "sg:province":"IL",
    "sg:tags":[
        "contractor"
    ],
    "sg:website":"www.emcgroup.com",
    "wof:name":"Emc Construction Group",
    "wof:placetype":"venue"
},
  "geometry": {"coordinates":[-89.2239,37.685398],"type":"Point"}
}