{
  "type": "Feature",
  "properties": {
    "iso:country":"US",
    "sg:address":"20 S 2nd St",
    "sg:city":"Geneva",
    "sg:classifiers":[
        {
            "category":"Banks & Credit Unions",
            "subcategory":"Investment Brokerage",
            "type":"Services"
        }
    ],
    "sg:phone":"+1 630 406 0000",
    "sg:postcode":"60134",
    "sg:province":"IL",
    "sg:tags":[
        "consultant",
        "planning",
        "financial"
    ],
    "wof:name":"Lebin Financial Planning",
    "wof:placetype":"venue"
},
  "geometry": {"coordinates":[-88.306775,41.886888],"type":"Point"}
}