{
  "type": "Feature",
  "properties": {
    "iso:country":"US",
    "sg:address":"1531 W Main St",
    "sg:city":"Salem",
    "sg:classifiers":[
        {
            "category":"Food & Beverages",
            "subcategory":"Groceries & Convenience Stores",
            "type":"Retail Goods"
        }
    ],
    "sg:phone":"+1   ",
    "sg:postcode":"62881",
    "sg:province":"IL",
    "wof:name":"Big Foot Shell",
    "wof:placetype":"venue"
},
  "geometry": {"coordinates":[-88.969903,38.624635],"type":"Point"}
}