{
  "type": "Feature",
  "properties": {
    "iso:country":"US",
    "sg:address":"2150 Western Ave",
    "sg:city":"Lisle",
    "sg:classifiers":[
        {
            "category":"Wholesale",
            "subcategory":"Machinery & Supplies",
            "type":"Manufacturing & Wholesale Goods"
        }
    ],
    "sg:phone":"+1 630 434 8774",
    "sg:postcode":"60532",
    "sg:province":"IL",
    "sg:tags":[
        "equipment",
        "industrial"
    ],
    "wof:name":"Technical Prtg Solutions Group",
    "wof:placetype":"venue"
},
  "geometry": {"coordinates":[-88.09532,41.803949],"type":"Point"}
}