{
  "type": "Feature",
  "properties": {
    "addr:full":"615 Lathrop Ave River Forest IL 60305",
    "addr:housenumber":"615",
    "addr:postcode":"60305",
    "addr:street":"Lathrop Ave",
    "iso:country":"US",
    "sg:address":"615 Lathrop Ave",
    "sg:city":"River Forest",
    "sg:classifiers":[
        {
            "category":"Sports & Exercise",
            "subcategory":"Tennis Court",
            "type":"Entertainment"
        }
    ],
    "sg:phone":"+1 708 771 7783",
    "sg:postcode":"60305",
    "sg:province":"IL",
    "wof:name":"River Forest Tennis Club",
    "wof:placetype":"venue"
},
  "geometry": {"coordinates":[-87.814903,41.8908],"type":"Point"}
}