{
  "type": "Feature",
  "properties": {
    "iso:country":"US",
    "sg:address":"8844 Hillside Dr",
    "sg:city":"Oak Lawn",
    "sg:classifiers":[
        {
            "category":"Building & Trades",
            "subcategory":"Construction",
            "type":"Services"
        }
    ],
    "sg:phone":"+1 708 430 4234",
    "sg:postcode":"60457",
    "sg:province":"IL",
    "sg:tags":[
        "hanging",
        "co",
        "contractor"
    ],
    "wof:name":"Exquisite Interiors",
    "wof:placetype":"venue"
},
  "geometry": {"coordinates":[-87.834164,41.730064],"type":"Point"}
}