{
  "type": "Feature",
  "properties": {
    "addr:full":"218 S Broadway Salem IL 62881",
    "addr:housenumber":"218",
    "addr:postcode":"62881",
    "addr:street":"S Broadway",
    "iso:country":"US",
    "sg:address":"218 S Broadway",
    "sg:city":"Salem",
    "sg:classifiers":[
        {
            "category":"Personal",
            "subcategory":"Beauty Salon",
            "type":"Services"
        }
    ],
    "sg:phone":"+1 618 548 4786",
    "sg:postcode":"62881",
    "sg:province":"IL",
    "sg:tags":[
        "shop"
    ],
    "wof:name":"Corner Cuts",
    "wof:placetype":"venue"
},
  "geometry": {"coordinates":[-88.945599,38.626112],"type":"Point"}
}