{
  "type": "Feature",
  "properties": {
    "iso:country":"US",
    "sg:address":"645 Industrial Dr",
    "sg:city":"Cary",
    "sg:classifiers":[
        {
            "category":"Restaurant",
            "type":"Food & Drink"
        }
    ],
    "sg:phone":"+1   ",
    "sg:postcode":"60013",
    "sg:province":"IL",
    "wof:name":"Colemans In The Park",
    "wof:placetype":"venue"
},
  "geometry": {"coordinates":[-88.25967799999999,42.215779],"type":"Point"}
}