{
  "type": "Feature",
  "properties": {
    "iso:country":"US",
    "sg:address":"114 N 4th St",
    "sg:city":"Coulterville",
    "sg:classifiers":[
        {
            "category":"Government",
            "subcategory":"Office",
            "type":"Public Place"
        }
    ],
    "sg:phone":"+1 618 758 2813",
    "sg:postcode":"62237",
    "sg:province":"IL",
    "sg:tags":[
        "city"
    ],
    "wof:name":"Coulterville City Clerk",
    "wof:placetype":"venue"
},
  "geometry": {"coordinates":[-89.60372700000001,38.18701],"type":"Point"}
}