{
  "type": "Feature",
  "properties": {
    "iso:country":"US",
    "sg:address":"1824 S Cicero Ave",
    "sg:city":"Cicero",
    "sg:classifiers":[
        {
            "category":"Wholesale",
            "subcategory":"Machinery & Supplies",
            "type":"Manufacturing & Wholesale Goods"
        }
    ],
    "sg:phone":"+1 708 780 7155",
    "sg:postcode":"60804",
    "sg:province":"IL",
    "sg:tags":[
        "industrial",
        "equipment",
        "used",
        "machinery-new",
        "supplies-wholesale"
    ],
    "sg:website":"http://www.expoengineered.com",
    "wof:name":"Expo Engineered Inc",
    "wof:placetype":"venue"
},
  "geometry": {"coordinates":[-87.74441899999999,41.855738],"type":"Point"}
}