{
  "type": "Feature",
  "properties": {
    "iso:country":"US",
    "sg:address":"351 W Hubbard Street",
    "sg:city":"Chicago",
    "sg:classifiers":[
        {
            "category":"Shopping",
            "subcategory":"Florist",
            "type":"Retail Goods"
        }
    ],
    "sg:phone":"+1 312 828 1111",
    "sg:postcode":"60610",
    "sg:province":"IL",
    "wof:name":"Parisain Floral Design",
    "wof:placetype":"venue"
},
  "geometry": {"coordinates":[-87.63724999999999,41.889931],"type":"Point"}
}