{
  "type": "Feature",
  "properties": {
    "iso:country":"US",
    "sg:address":"118 N 1st St",
    "sg:city":"Belleville",
    "sg:classifiers":[
        {
            "category":"Professional",
            "type":"Services"
        }
    ],
    "sg:phone":"+1 618 355 0080",
    "sg:postcode":"62220",
    "sg:province":"IL",
    "sg:tags":[
        "establishment"
    ],
    "wof:name":"Circus Skates",
    "wof:placetype":"venue"
},
  "geometry": {"coordinates":[-89.985483,38.515362],"type":"Point"}
}