{
  "type": "Feature",
  "properties": {
    "addr:full":"818 N State St Chicago IL 60610",
    "addr:housenumber":"818",
    "addr:postcode":"60610",
    "addr:street":"N State St",
    "iso:country":"US",
    "sg:address":"818 N State St",
    "sg:city":"Chicago",
    "sg:classifiers":[
        {
            "category":"Real Estate",
            "subcategory":"Real Estate Services",
            "type":"Services"
        },
        {
            "category":"Real Estate",
            "subcategory":"Real Estate Operator",
            "type":"Services"
        }
    ],
    "sg:phone":"+1 888 346 3377",
    "sg:postcode":"60610",
    "sg:province":"IL",
    "sg:tags":[
        "apartment"
    ],
    "sg:website":"www.chicagoapartmentfinders.com",
    "wof:name":"Chicago Apartment Finders",
    "wof:placetype":"venue"
},
  "geometry": {"coordinates":[-87.628328,41.897331],"type":"Point"}
}