{
  "type": "Feature",
  "properties": {
    "addr:full":"1737 N Campbell Ave Chicago IL 60647",
    "addr:housenumber":"1737",
    "addr:postcode":"60647",
    "addr:street":"N Campbell Ave",
    "iso:country":"US",
    "sg:address":"1737 N Campbell Ave",
    "sg:city":"Chicago",
    "sg:classifiers":[
        {
            "category":"Wholesale",
            "subcategory":"Non-durable Goods",
            "type":"Manufacturing & Wholesale Goods"
        },
        {
            "category":"Wholesale",
            "subcategory":"Stationery",
            "type":"Manufacturing & Wholesale Goods"
        }
    ],
    "sg:phone":"+1 773 278 8780",
    "sg:postcode":"60647",
    "sg:province":"IL",
    "sg:tags":[
        "school",
        "material",
        "art",
        "supply"
    ],
    "wof:name":"Fox School Supply",
    "wof:placetype":"venue"
},
  "geometry": {"coordinates":[-87.68973099999999,41.912778],"type":"Point"}
}