{
  "type": "Feature",
  "properties": {
    "iso:country":"US",
    "sg:address":"66 Stratford Dr",
    "sg:city":"Bloomingdale",
    "sg:classifiers":[
        {
            "category":"Shopping",
            "subcategory":"Party Supplies",
            "type":"Retail Goods"
        },
        {
            "category":"Building & Trades",
            "subcategory":"Equipment Rental",
            "type":"Services"
        },
        {
            "category":"Shopping",
            "subcategory":"Bicycles & Sporting Goods",
            "type":"Retail Goods"
        }
    ],
    "sg:phone":"+1 630 893 4311",
    "sg:postcode":"60108",
    "sg:province":"IL",
    "sg:tags":[
        "yard",
        "store",
        "tent"
    ],
    "sg:website":"http://partycentral.org",
    "wof:name":"Party Central",
    "wof:placetype":"venue"
},
  "geometry": {"coordinates":[-88.119331,41.949921],"type":"Point"}
}