{
  "type": "Feature",
  "properties": {
    "addr:full":"510 State Ave Hampton IL 61256",
    "addr:housenumber":"510",
    "addr:postcode":"61256",
    "addr:street":"State Ave",
    "iso:country":"US",
    "sg:address":"510 State Ave",
    "sg:city":"Hampton",
    "sg:classifiers":[
        {
            "category":"Deli",
            "type":"Food & Drink"
        }
    ],
    "sg:menulink":"http://www.allmenus.com/il/hampton/127162-blimpie-subs--sandwiches/menu/",
    "sg:phone":"+1 309 755 7827",
    "sg:postcode":"61256",
    "sg:province":"IL",
    "sg:tags":[
        "wrap",
        "american",
        "sandwich"
    ],
    "wof:name":"Blimpie Subs & Sandwiches",
    "wof:placetype":"venue"
},
  "geometry": {"coordinates":[-90.409834,41.5546],"type":"Point"}
}