{
  "type": "Feature",
  "properties": {
    "iso:country":"US",
    "sg:address":"313 W Highland Ave",
    "sg:city":"Elgin",
    "sg:classifiers":[
        {
            "category":"Retail",
            "subcategory":"Repair Shop",
            "type":"Services"
        }
    ],
    "sg:phone":"+1 847 695 1858",
    "sg:postcode":"60123",
    "sg:province":"IL",
    "sg:tags":[
        "refinishing"
    ],
    "wof:name":"Elgin Refinishing",
    "wof:placetype":"venue"
},
  "geometry": {"coordinates":[-88.290462,42.036428],"type":"Point"}
}