{
  "type": "Feature",
  "properties": {
    "iso:country":"US",
    "sg:address":"201 Madison St",
    "sg:city":"Oak Park",
    "sg:classifiers":[
        {
            "category":"Autos & Motor Vehicles",
            "subcategory":"Fuel & Gas Station",
            "type":"Retail Goods"
        },
        {
            "category":"Food & Beverages",
            "subcategory":"Groceries & Convenience Stores",
            "type":"Retail Goods"
        }
    ],
    "sg:phone":"+1 708 383 5178",
    "sg:postcode":"60302",
    "sg:province":"IL",
    "wof:name":"Amoco Food Shop",
    "wof:placetype":"venue"
},
  "geometry": {"coordinates":[-87.77979999999999,41.879799],"type":"Point"}
}