{
  "type": "Feature",
  "properties": {
    "addr:full":"625 10th St North Chicago IL 60064",
    "addr:housenumber":"625",
    "addr:postcode":"60064",
    "addr:street":"10Th St",
    "iso:country":"US",
    "sg:address":"625 10th St",
    "sg:city":"North Chicago",
    "sg:classifiers":[
        {
            "category":"Restaurant",
            "type":"Food & Drink"
        }
    ],
    "sg:phone":"+1 847 578 0218",
    "sg:postcode":"60064",
    "sg:province":"IL",
    "wof:name":"Teresita Restaurant",
    "wof:placetype":"venue"
},
  "geometry": {"coordinates":[-87.83895800000001,42.341206],"type":"Point"}
}