{
  "type": "Feature",
  "properties": {
    "iso:country":"US",
    "sg:address":"4741 W 103rd St",
    "sg:city":"Oak Lawn",
    "sg:classifiers":[
        {
            "category":"Shopping",
            "type":"Retail Goods"
        }
    ],
    "sg:phone":"+1   ",
    "sg:postcode":"60453",
    "sg:province":"IL",
    "sg:tags":[
        "merchandise"
    ],
    "wof:name":"Corporate Fin Asso Worldwi LLC",
    "wof:placetype":"venue"
},
  "geometry": {"coordinates":[-87.740178,41.705498],"type":"Point"}
}