{
  "type": "Feature",
  "properties": {
    "iso:country":"US",
    "sg:address":"1820 Ridge Ave",
    "sg:city":"Evanston",
    "sg:classifiers":[
        {
            "category":"Professional",
            "subcategory":"Engineering",
            "type":"Services"
        }
    ],
    "sg:phone":"+1 847 328 5800",
    "sg:postcode":"60201",
    "sg:province":"IL",
    "sg:tags":[
        "computational",
        "material",
        "design"
    ],
    "wof:name":"Questek Innovations LLC",
    "wof:placetype":"venue"
},
  "geometry": {"coordinates":[-87.688037,42.051921],"type":"Point"}
}