{
  "type": "Feature",
  "properties": {
    "addr:full":"333 Lexington Dr Buffalo Grove IL 60089",
    "addr:housenumber":"333",
    "addr:postcode":"60089",
    "addr:street":"Lexington Dr",
    "iso:country":"US",
    "sg:address":"333 Lexington Dr",
    "sg:city":"Buffalo Grove",
    "sg:classifiers":[
        {
            "category":"Shopping",
            "subcategory":"Gifts & Souvenirs",
            "type":"Retail Goods"
        }
    ],
    "sg:phone":"+1 847 459 3100",
    "sg:postcode":"60089",
    "sg:province":"IL",
    "sg:tags":[
        "florist",
        "shop"
    ],
    "wof:name":"Hbm Corporation",
    "wof:placetype":"venue"
},
  "geometry": {"coordinates":[-87.942564,42.1585],"type":"Point"}
}