{
  "type": "Feature",
  "properties": {
    "iso:country":"US",
    "sg:address":"256 S Randall Rd",
    "sg:city":"Algonquin",
    "sg:classifiers":[
        {
            "category":"Retail",
            "subcategory":"Laundry & Dry Cleaning",
            "type":"Services"
        }
    ],
    "sg:phone":"+1 847 458 8377",
    "sg:postcode":"60102",
    "sg:province":"IL",
    "wof:name":"Royal Cleaner",
    "wof:placetype":"venue"
},
  "geometry": {"coordinates":[-88.335403,42.173199],"type":"Point"}
}