{
  "type": "Feature",
  "properties": {
    "addr:full":"407 S Dearborn St Chicago IL 60605",
    "addr:housenumber":"407",
    "addr:postcode":"60605",
    "addr:street":"S Dearborn St",
    "iso:country":"US",
    "sg:address":"407 S Dearborn St",
    "sg:city":"Chicago",
    "sg:classifiers":[
        {
            "category":"Professional",
            "subcategory":"Management & Consulting",
            "type":"Services"
        },
        {
            "category":"Banks & Credit Unions",
            "subcategory":"Investment Brokerage",
            "type":"Services"
        },
        {
            "category":"Banks & Credit Unions",
            "subcategory":"Financial Services",
            "type":"Services"
        }
    ],
    "sg:phone":"+1 312 566 0111",
    "sg:postcode":"60605",
    "sg:province":"IL",
    "sg:tags":[
        "consultant",
        "financing",
        "planner",
        "security"
    ],
    "sg:website":"http://www.ameriprise.com",
    "wof:name":"Ameriprise Financial",
    "wof:placetype":"venue"
},
  "geometry": {"coordinates":[-87.629248,41.876826],"type":"Point"}
}