{
  "type": "Feature",
  "properties": {
    "iso:country":"US",
    "sg:address":"330 W Walnut St",
    "sg:city":"Jacksonville",
    "sg:classifiers":[
        {
            "category":"Building & Trades",
            "subcategory":"Construction",
            "type":"Services"
        }
    ],
    "sg:phone":"+1 217 243 9731",
    "sg:postcode":"62650",
    "sg:province":"IL",
    "sg:tags":[
        "home",
        "improvement"
    ],
    "wof:name":"Campbell's Mobile Home Repair",
    "wof:placetype":"venue"
},
  "geometry": {"coordinates":[-90.232014,39.745302],"type":"Point"}
}