{
  "type": "Feature",
  "properties": {
    "iso:country":"US",
    "sg:address":"6733 W Pershing Rd",
    "sg:city":"Stickney",
    "sg:classifiers":[
        {
            "category":"Food & Beverages",
            "subcategory":"Ethnic Foods",
            "type":"Retail Goods"
        }
    ],
    "sg:phone":"+1 708 749 7868",
    "sg:postcode":"60402",
    "sg:province":"IL",
    "sg:website":"www.josiesdumplings.com/",
    "wof:name":"Czech Kitchens Home of Josie's Dumplings",
    "wof:placetype":"venue"
},
  "geometry": {"coordinates":[-87.79175499999999,41.821227],"type":"Point"}
}