{
  "type": "Feature",
  "properties": {
    "iso:country":"US",
    "sg:address":"1900 Estes Ave",
    "sg:city":"Elk Grove Vlg",
    "sg:classifiers":[
        {
            "category":"Wholesale",
            "subcategory":"Metals & Minerals",
            "type":"Manufacturing & Wholesale Goods"
        }
    ],
    "sg:phone":"+1 847 364 2090",
    "sg:postcode":"60007",
    "sg:province":"IL",
    "sg:tags":[
        "alloy"
    ],
    "wof:name":"Alpha Omega Profile",
    "wof:placetype":"venue"
},
  "geometry": {"coordinates":[-87.952988,42.006176],"type":"Point"}
}