{
  "type": "Feature",
  "properties": {
    "addr:full":"8543 N Ozanam Ave Niles IL 60714",
    "addr:housenumber":"8543",
    "addr:postcode":"60714",
    "addr:street":"N Ozanam Ave",
    "iso:country":"US",
    "sg:address":"8543 N Ozanam Ave",
    "sg:city":"Niles",
    "sg:classifiers":[
        {
            "category":"Professional",
            "subcategory":"Accounting & Tax Preparation",
            "type":"Services"
        }
    ],
    "sg:phone":"+1 847 966 6400",
    "sg:postcode":"60714",
    "sg:province":"IL",
    "sg:tags":[
        "public",
        "accountants-certified"
    ],
    "wof:name":"Andrea H Izykowski Cpa",
    "wof:placetype":"venue"
},
  "geometry": {"coordinates":[-87.821006,42.036074],"type":"Point"}
}