{
  "type": "Feature",
  "properties": {
    "iso:country":"US",
    "sg:address":"17701 Saint Rose Rd",
    "sg:city":"Breese",
    "sg:classifiers":[
        {
            "category":"Freight",
            "type":"Transportation"
        }
    ],
    "sg:phone":"+1 618 526 7522",
    "sg:postcode":"62230",
    "sg:province":"IL",
    "sg:tags":[
        "local",
        "milk"
    ],
    "wof:name":"Timmerman Milk Service Inc",
    "wof:placetype":"venue"
},
  "geometry": {"coordinates":[-89.554498,38.678673],"type":"Point"}
}