{
  "type": "Feature",
  "properties": {
    "addr:full":"6010 Oakwood Dr Lisle IL 60532",
    "addr:housenumber":"6010",
    "addr:postcode":"60532",
    "addr:street":"Oakwood Dr",
    "iso:country":"US",
    "sg:address":"6010 Oakwood Dr",
    "sg:city":"Lisle",
    "sg:classifiers":[
        {
            "category":"Utilities",
            "subcategory":"Recycling",
            "type":"Services"
        }
    ],
    "sg:phone":"+1 630 963 4293",
    "sg:postcode":"60532",
    "sg:province":"IL",
    "sg:tags":[
        "disposal",
        "waste",
        "equipment"
    ],
    "wof:name":"Waste Management",
    "wof:placetype":"venue"
},
  "geometry": {"coordinates":[-88.08300800000001,41.774429],"type":"Point"}
}