{
  "type": "Feature",
  "properties": {
    "addr:full":"701 N Morgan St Bement IL 61813",
    "addr:housenumber":"701",
    "addr:postcode":"61813",
    "addr:street":"N Morgan St",
    "iso:country":"US",
    "sg:address":"701 N Morgan St",
    "sg:city":"Bement",
    "sg:classifiers":[
        {
            "category":"Social Services",
            "type":"Services"
        }
    ],
    "sg:phone":"+1 217 678 8484",
    "sg:postcode":"61813",
    "sg:province":"IL",
    "sg:tags":[
        "organization",
        "welfare"
    ],
    "wof:name":"National Child Search",
    "wof:placetype":"venue"
},
  "geometry": {"coordinates":[-88.57482,39.928262],"type":"Point"}
}