{
  "type": "Feature",
  "properties": {
    "iso:country":"US",
    "sg:address":"15857 Crawford Ave",
    "sg:city":"Markham",
    "sg:classifiers":[
        {
            "category":"Autos & Motor Vehicles",
            "subcategory":"Automobile Sales",
            "type":"Retail Goods"
        }
    ],
    "sg:phone":"+1 708 331 8995",
    "sg:postcode":"60428",
    "sg:province":"IL",
    "sg:tags":[
        "used",
        "car",
        "dealers-used",
        "new",
        "cars-wholesale"
    ],
    "wof:name":"First Choice Auto Sales Inc",
    "wof:placetype":"venue"
},
  "geometry": {"coordinates":[-87.716785,41.601311],"type":"Point"}
}