{
  "type": "Feature",
  "properties": {
    "iso:country":"US",
    "sg:address":"1116 W Bryn Mawr Ave",
    "sg:city":"Chicago",
    "sg:classifiers":[
        {
            "category":"Shopping",
            "subcategory":"Clothing, Apparel, & Fashions",
            "type":"Retail Goods"
        }
    ],
    "sg:phone":"+1   ",
    "sg:postcode":"60660",
    "sg:province":"IL",
    "sg:tags":[
        "hat",
        "sportswear",
        "suit"
    ],
    "wof:name":"Jean Sunflower Store",
    "wof:placetype":"venue"
},
  "geometry": {"coordinates":[-87.65871300000001,41.983647],"type":"Point"}
}