{
  "type": "Feature",
  "properties": {
    "iso:country":"US",
    "sg:address":"1641 N Milwaukee Ave",
    "sg:city":"Libertyville",
    "sg:classifiers":[
        {
            "category":"Health Services",
            "subcategory":"Doctor",
            "type":"Services"
        }
    ],
    "sg:phone":"+1 847 367 6360",
    "sg:postcode":"60048",
    "sg:province":"IL",
    "sg:tags":[
        "dentist"
    ],
    "sg:website":"www.libertyvilledental.com",
    "wof:name":"Libertyville Dental Associates",
    "wof:placetype":"venue"
},
  "geometry": {"coordinates":[-87.958102,42.302678],"type":"Point"}
}