{
  "type": "Feature",
  "properties": {
    "addr:full":"100 W Monroe St Ste 1605 Chicago IL 60603",
    "addr:housenumber":"100",
    "addr:postcode":"60603",
    "addr:street":"W Monroe St Ste 1605",
    "iso:country":"US",
    "sg:address":"100 W Monroe St Ste 1605",
    "sg:city":"Chicago",
    "sg:classifiers":[
        {
            "category":"Professional",
            "subcategory":"Lawyer & Legal Services",
            "type":"Services"
        }
    ],
    "sg:phone":"+1 312 263 3040",
    "sg:postcode":"60603",
    "sg:province":"IL",
    "sg:tags":[
        "personal",
        "injury"
    ],
    "wof:name":"Taxman and Hurst",
    "wof:placetype":"venue"
},
  "geometry": {"coordinates":[-87.630798,41.880699],"type":"Point"}
}