{
  "type": "Feature",
  "properties": {
    "addr:full":"20530 Milwaukee Ave Deerfield IL 60015",
    "addr:housenumber":"20530",
    "addr:postcode":"60015",
    "addr:street":"Milwaukee Ave",
    "iso:country":"US",
    "sg:address":"20530 Milwaukee Ave",
    "sg:city":"Deerfield",
    "sg:classifiers":[
        {
            "category":"Professional",
            "subcategory":"Employment Agencies",
            "type":"Services"
        }
    ],
    "sg:phone":"+1 847 537 7007",
    "sg:postcode":"60015",
    "sg:province":"IL",
    "sg:tags":[
        "help",
        "contractor"
    ],
    "wof:name":"Salem Services Inc",
    "wof:placetype":"venue"
},
  "geometry": {"coordinates":[-87.91655299999999,42.156021],"type":"Point"}
}