{
  "type": "Feature",
  "properties": {
    "iso:country":"US",
    "sg:address":"210 Easy St",
    "sg:city":"Carol Stream",
    "sg:classifiers":[
        {
            "category":"Home & Garden",
            "subcategory":"Carpets & Floor Coverings",
            "type":"Retail Goods"
        }
    ],
    "sg:phone":"+1   ",
    "sg:postcode":"60188",
    "sg:province":"IL",
    "wof:name":"Karmis Carpet & Rugs",
    "wof:placetype":"venue"
},
  "geometry": {"coordinates":[-88.115607,41.896634],"type":"Point"}
}