{
  "type": "Feature",
  "properties": {
    "addr:full":"1425 Boyce Memorial Dr Ottawa IL 61350",
    "addr:housenumber":"1425",
    "addr:postcode":"61350",
    "addr:street":"Boyce Memorial Dr",
    "iso:country":"US",
    "sg:address":"1425 Boyce Memorial Dr",
    "sg:city":"Ottawa",
    "sg:classifiers":[
        {
            "category":"Manufacturing",
            "subcategory":"Motor Vehicles & Parts",
            "type":"Manufacturing & Wholesale Goods"
        }
    ],
    "sg:phone":"+1 815 433 5305",
    "sg:postcode":"61350",
    "sg:province":"IL",
    "sg:tags":[
        "mfg"
    ],
    "sg:website":"www.gilletteparade.com",
    "wof:name":"Gillette Parade Products",
    "wof:placetype":"venue"
},
  "geometry": {"coordinates":[-88.86506900000001,41.352417],"type":"Point"}
}