{
  "type": "Feature",
  "properties": {
    "iso:country":"US",
    "sg:address":"221 N 48th St",
    "sg:city":"Quincy",
    "sg:classifiers":[
        {
            "category":"Social Services",
            "type":"Services"
        }
    ],
    "sg:phone":"+1 217 222 5389",
    "sg:postcode":"62305",
    "sg:province":"IL",
    "sg:tags":[
        "organization",
        "welfare"
    ],
    "wof:name":"Easter Seals Western Region",
    "wof:placetype":"venue"
},
  "geometry": {"coordinates":[-91.33946,39.93092],"type":"Point"}
}