{
  "type": "Feature",
  "properties": {
    "iso:country":"US",
    "sg:address":"335 N Milwaukee Ave",
    "sg:city":"Vernon Hills",
    "sg:classifiers":[
        {
            "category":"Shopping",
            "subcategory":"Discount & Variety Stores",
            "type":"Retail Goods"
        }
    ],
    "sg:phone":"+1   ",
    "sg:postcode":"60061",
    "sg:province":"IL",
    "sg:tags":[
        "merchandise",
        "general"
    ],
    "wof:name":"Wal-Mart",
    "wof:placetype":"venue"
},
  "geometry": {"coordinates":[-87.942922,42.232688],"type":"Point"}
}