{
  "type": "Feature",
  "properties": {
    "iso:country":"US",
    "sg:address":"623 N 37th St",
    "sg:city":"East Saint Louis",
    "sg:classifiers":[
        {
            "category":"Professional",
            "subcategory":"Management & Consulting",
            "type":"Services"
        }
    ],
    "sg:phone":"+1 618 875 7371",
    "sg:postcode":"62205",
    "sg:province":"IL",
    "wof:name":"Max Dozier",
    "wof:placetype":"venue"
},
  "geometry": {"coordinates":[-90.115001,38.611932],"type":"Point"}
}