{
  "type": "Feature",
  "properties": {
    "addr:full":"20 N Wacker Drive Chicago IL 60606",
    "addr:housenumber":"20",
    "addr:postcode":"60606",
    "addr:street":"N Wacker Drive",
    "iso:country":"US",
    "sg:address":"20 N Wacker Drive",
    "sg:city":"Chicago",
    "sg:classifiers":[
        {
            "category":"Professional",
            "subcategory":"Lawyer & Legal Services",
            "type":"Services"
        }
    ],
    "sg:phone":"+1 312 372 1033",
    "sg:postcode":"60606",
    "sg:province":"IL",
    "wof:name":"Vander Woude Paul S Atty",
    "wof:placetype":"venue"
},
  "geometry": {"coordinates":[-87.637156,41.882258],"type":"Point"}
}