{
  "type": "Feature",
  "properties": {
    "addr:full":"325 Washington St Waukegan IL 60085",
    "addr:housenumber":"325",
    "addr:postcode":"60085",
    "addr:street":"Washington St",
    "iso:country":"US",
    "sg:address":"325 Washington St",
    "sg:city":"Waukegan",
    "sg:classifiers":[
        {
            "category":"Insurance",
            "subcategory":"Title Insurance",
            "type":"Services"
        }
    ],
    "sg:phone":"+1 847 244 5252",
    "sg:postcode":"60085",
    "sg:province":"IL",
    "wof:name":"First American Title Ins Co",
    "wof:placetype":"venue"
},
  "geometry": {"coordinates":[-87.833673,42.35949],"type":"Point"}
}