{
  "type": "Feature",
  "properties": {
    "iso:country":"US",
    "sg:address":"440 S Schuyler Ave",
    "sg:city":"Bradley",
    "sg:classifiers":[
        {
            "category":"Building & Trades",
            "subcategory":"Plumbing",
            "type":"Services"
        }
    ],
    "sg:phone":"+1 815 933 4504",
    "sg:postcode":"60915",
    "sg:province":"IL",
    "sg:tags":[
        "plumbing",
        "contractor"
    ],
    "wof:name":"Brush Plumbing & Heating Inc",
    "wof:placetype":"venue"
},
  "geometry": {"coordinates":[-87.860493,41.137972],"type":"Point"}
}