{
  "type": "Feature",
  "properties": {
    "addr:full":"113 S Walnut St Champaign IL 61820",
    "addr:housenumber":"113",
    "addr:postcode":"61820",
    "addr:street":"S Walnut St",
    "iso:country":"US",
    "sg:address":"113 S Walnut St",
    "sg:city":"Champaign",
    "sg:classifiers":[
        {
            "category":"Organizations",
            "subcategory":"Non-profit Organization",
            "type":"Services"
        }
    ],
    "sg:phone":"+1 217 356 9812",
    "sg:postcode":"61820",
    "sg:province":"IL",
    "sg:website":"www.conservatorycentralil.org",
    "wof:name":"Conservatory Of Central Il",
    "wof:placetype":"venue"
},
  "geometry": {"coordinates":[-88.24312999999999,40.115396],"type":"Point"}
}