{
  "type": "Feature",
  "properties": {
    "addr:full":"6318 S Gras Rd Elizabeth IL 61028",
    "addr:housenumber":"6318",
    "addr:postcode":"61028",
    "addr:street":"S Gras Rd",
    "iso:country":"US",
    "sg:address":"6318 S Gras Rd",
    "sg:city":"Elizabeth",
    "sg:classifiers":[
        {
            "category":"Farming",
            "subcategory":"Dairy Farm",
            "type":"Manufacturing & Wholesale Goods"
        }
    ],
    "sg:phone":"+1 815 598 3232",
    "sg:postcode":"61028",
    "sg:province":"IL",
    "wof:name":"Richard Groezinger",
    "wof:placetype":"venue"
},
  "geometry": {"coordinates":[-90.121877,42.281951],"type":"Point"}
}