{
  "type": "Feature",
  "properties": {
    "addr:full":"3218 W Irving Park Rd Chicago IL 60686",
    "addr:housenumber":"3218",
    "addr:postcode":"60686",
    "addr:street":"W Irving Park Rd",
    "iso:country":"US",
    "sg:address":"3218 W Irving Park Rd",
    "sg:city":"Chicago",
    "sg:classifiers":[
        {
            "category":"Retail",
            "subcategory":"Car Wash",
            "type":"Services"
        }
    ],
    "sg:phone":"+1 773 583 7966",
    "sg:postcode":"60686",
    "sg:province":"IL",
    "wof:name":"Minute Man Car/Van Wash",
    "wof:placetype":"venue"
},
  "geometry": {"coordinates":[-87.708839,41.953959],"type":"Point"}
}