{
  "type": "Feature",
  "properties": {
    "iso:country":"US",
    "sg:address":"719 W Lincoln Ave",
    "sg:city":"Charleston",
    "sg:classifiers":[
        {
            "category":"Banks & Credit Unions",
            "subcategory":"Bank",
            "type":"Services"
        }
    ],
    "sg:phone":"+1 217 345 3971",
    "sg:postcode":"61920",
    "sg:province":"IL",
    "sg:tags":[
        "loan"
    ],
    "wof:name":"Farm Credit Svc",
    "wof:placetype":"venue"
},
  "geometry": {"coordinates":[-88.188788,39.484393],"type":"Point"}
}