{
  "type": "Feature",
  "properties": {
    "iso:country":"US",
    "sg:address":"3435 N Sheffield Ave",
    "sg:city":"Chicago",
    "sg:classifiers":[
        {
            "category":"Real Estate",
            "subcategory":"Real Estate Services",
            "type":"Services"
        },
        {
            "category":"Personal",
            "type":"Services"
        },
        {
            "category":"Real Estate",
            "subcategory":"Real Estate Agent",
            "type":"Services"
        }
    ],
    "sg:phone":"+1 773 868 0741",
    "sg:postcode":"60657",
    "sg:province":"IL",
    "sg:tags":[
        "property",
        "management",
        "maintenance"
    ],
    "wof:name":"Sheffield Properties",
    "wof:placetype":"venue"
},
  "geometry": {"coordinates":[-87.65410799999999,41.944532],"type":"Point"}
}