{
  "type": "Feature",
  "properties": {
    "addr:full":"661 E 69th St Chicago IL 60637",
    "addr:housenumber":"661",
    "addr:postcode":"60637",
    "addr:street":"E 69Th St",
    "iso:country":"US",
    "sg:address":"661 E 69th St",
    "sg:city":"Chicago",
    "sg:classifiers":[
        {
            "category":"Real Estate",
            "subcategory":"Real Estate Operator",
            "type":"Services"
        }
    ],
    "sg:phone":"+1 773 955 9139",
    "sg:postcode":"60637",
    "sg:province":"IL",
    "sg:tags":[
        "apartment"
    ],
    "wof:name":"69th So Chicago Apts",
    "wof:placetype":"venue"
},
  "geometry": {"coordinates":[-87.609008,41.769283],"type":"Point"}
}