{
  "type": "Feature",
  "properties": {
    "addr:full":"6215 Lou St Crystal Lake IL 60014",
    "addr:housenumber":"6215",
    "addr:postcode":"60014",
    "addr:street":"Lou St",
    "iso:country":"US",
    "sg:address":"6215 Lou St",
    "sg:city":"Crystal Lake",
    "sg:classifiers":[
        {
            "category":"Manufacturing",
            "subcategory":"Tools & Machinery",
            "type":"Manufacturing & Wholesale Goods"
        }
    ],
    "sg:phone":"+1 815 477 7713",
    "sg:postcode":"60014",
    "sg:province":"IL",
    "sg:tags":[
        "equipment",
        "safety",
        "clothing"
    ],
    "sg:website":"www.miraclepoint.com",
    "wof:name":"Miracle Point",
    "wof:placetype":"venue"
},
  "geometry": {"coordinates":[-88.31725299999999,42.224862],"type":"Point"}
}