{
  "type": "Feature",
  "properties": {
    "iso:country":"US",
    "sg:address":"1030 N Walnut St",
    "sg:city":"Breese",
    "sg:classifiers":[
        {
            "category":"Farming",
            "subcategory":"Farm",
            "type":"Manufacturing & Wholesale Goods"
        }
    ],
    "sg:phone":"+1 618 526 4687",
    "sg:postcode":"62230",
    "sg:province":"IL",
    "sg:tags":[
        "crop",
        "general"
    ],
    "wof:name":"Ralph Langhauser",
    "wof:placetype":"venue"
},
  "geometry": {"coordinates":[-89.525789,38.61651],"type":"Point"}
}