{
  "type": "Feature",
  "properties": {
    "iso:country":"US",
    "sg:address":"1 N Franklin St",
    "sg:city":"Chicago",
    "sg:classifiers":[
        {
            "category":"Utilities",
            "subcategory":"Telephone",
            "type":"Services"
        },
        {
            "category":"Professional",
            "subcategory":"Computer Services",
            "type":"Services"
        }
    ],
    "sg:phone":"+1 312 251 1235",
    "sg:postcode":"60606",
    "sg:province":"IL",
    "sg:tags":[
        "distance",
        "telecommunication",
        "companies-long",
        "communication"
    ],
    "sg:website":"http://www.qwest.com",
    "wof:name":"Qwest",
    "wof:placetype":"venue"
},
  "geometry": {"coordinates":[-87.635323,41.881939],"type":"Point"}
}