{
  "type": "Feature",
  "properties": {
    "addr:full":"18600 Northstar Ct Tinley Park IL 60487",
    "addr:housenumber":"18600",
    "addr:postcode":"60487",
    "addr:street":"Northstar Ct",
    "iso:country":"US",
    "sg:address":"18600 Northstar Ct",
    "sg:city":"Tinley Park",
    "sg:classifiers":[
        {
            "category":"Wholesale",
            "subcategory":"Durable Goods & Equipment",
            "type":"Manufacturing & Wholesale Goods"
        },
        {
            "category":"Manufacturing",
            "subcategory":"Tools & Machinery",
            "type":"Manufacturing & Wholesale Goods"
        }
    ],
    "sg:phone":"+1 708 429 0800",
    "sg:postcode":"60487",
    "sg:province":"IL",
    "sg:tags":[
        "mfg",
        "metal",
        "representative",
        "stampings",
        "manufacturer",
        "structural"
    ],
    "wof:name":"Beverly Manufacturing Company",
    "wof:placetype":"venue"
},
  "geometry": {"coordinates":[-87.819036,41.553498],"type":"Point"}
}