{
  "type": "Feature",
  "properties": {
    "addr:full":"928 Lincoln Hwy Fairview Heights IL 62208",
    "addr:housenumber":"928",
    "addr:postcode":"62208",
    "addr:street":"Lincoln Hwy",
    "iso:country":"US",
    "sg:address":"928 Lincoln Hwy",
    "sg:city":"Fairview Heights",
    "sg:classifiers":[
        {
            "category":"Social Services",
            "subcategory":"Child Care",
            "type":"Services"
        },
        {
            "category":"Education",
            "subcategory":"Preschool",
            "type":"Public Place"
        },
        {
            "category":"Education",
            "subcategory":"School",
            "type":"Public Place"
        }
    ],
    "sg:phone":"+1 618 632 7339",
    "sg:postcode":"62208",
    "sg:province":"IL",
    "sg:tags":[
        "elementary",
        "day"
    ],
    "wof:name":"Magic Building Block Preschool & Childcare Center",
    "wof:placetype":"venue"
},
  "geometry": {"coordinates":[-89.969498,38.592602],"type":"Point"}
}