{
  "type": "Feature",
  "properties": {
    "addr:full":"108 N Raddant Rd Batavia IL 60510",
    "addr:housenumber":"108",
    "addr:postcode":"60510",
    "addr:street":"N Raddant Rd",
    "iso:country":"US",
    "sg:address":"108 N Raddant Rd",
    "sg:city":"Batavia",
    "sg:classifiers":[
        {
            "category":"Building & Trades",
            "subcategory":"Construction",
            "type":"Services"
        }
    ],
    "sg:phone":"+1 630 761 9800",
    "sg:postcode":"60510",
    "sg:province":"IL",
    "sg:tags":[
        "general",
        "installation",
        "antenna",
        "contractor"
    ],
    "wof:name":"Cellular Construction Inc",
    "wof:placetype":"venue"
},
  "geometry": {"coordinates":[-88.29046700000001,41.852757],"type":"Point"}
}