{
  "type": "Feature",
  "properties": {
    "iso:country":"US",
    "sg:address":"346 Taft Ave",
    "sg:city":"Glen Ellyn",
    "sg:classifiers":[
        {
            "category":"Social Services",
            "type":"Services"
        }
    ],
    "sg:phone":"+1 630 942 1883",
    "sg:postcode":"60137",
    "sg:province":"IL",
    "sg:tags":[
        "counselor",
        "marriage",
        "family"
    ],
    "wof:name":"Counseling & Consulation Pros",
    "wof:placetype":"venue"
},
  "geometry": {"coordinates":[-88.071544,41.858481],"type":"Point"}
}