{
  "type": "Feature",
  "properties": {
    "iso:country":"US",
    "sg:address":"9928 S Vincennes Avenue",
    "sg:city":"Chicago",
    "sg:classifiers":[
        {
            "category":"Retail",
            "subcategory":"Auto Repair",
            "type":"Services"
        }
    ],
    "sg:phone":"+1 773 238 8555",
    "sg:postcode":"60643",
    "sg:province":"IL",
    "wof:name":"Autopro Collision Clinic",
    "wof:placetype":"venue"
},
  "geometry": {"coordinates":[-87.653766,41.713326],"type":"Point"}
}