{
  "type": "Feature",
  "properties": {
    "iso:country":"US",
    "sg:address":"2716 Maryville Rd",
    "sg:city":"Maryville",
    "sg:classifiers":[
        {
            "category":"Personal",
            "subcategory":"Barber",
            "type":"Services"
        }
    ],
    "sg:phone":"+1 618 344 3207",
    "sg:postcode":"62062",
    "sg:province":"IL",
    "wof:name":"John's Barber Shop",
    "wof:placetype":"venue"
},
  "geometry": {"coordinates":[-89.95590199999999,38.709202],"type":"Point"}
}