{
  "type": "Feature",
  "properties": {
    "iso:country":"US",
    "sg:address":"25608 S Dixie Hwy",
    "sg:city":"Crete",
    "sg:classifiers":[
        {
            "category":"Freight",
            "type":"Transportation"
        }
    ],
    "sg:phone":"+1 708 672 3300",
    "sg:postcode":"60417",
    "sg:province":"IN",
    "sg:tags":[
        "commercial",
        "storage"
    ],
    "wof:name":"Crete Self Storage",
    "wof:placetype":"venue"
},
  "geometry": {"coordinates":[-87.629653,41.418552],"type":"Point"}
}