{
  "type": "Feature",
  "properties": {
    "iso:country":"US",
    "sg:address":"711 Liberty St",
    "sg:city":"Morris",
    "sg:classifiers":[
        {
            "category":"Shopping",
            "subcategory":"Bicycles & Sporting Goods",
            "type":"Retail Goods"
        }
    ],
    "sg:phone":"+1 815 942 1510",
    "sg:postcode":"60450",
    "sg:province":"IL",
    "sg:tags":[
        "shop"
    ],
    "wof:name":"Grand Schwinn Cyclery",
    "wof:placetype":"venue"
},
  "geometry": {"coordinates":[-88.4239,41.362032],"type":"Point"}
}