{
  "type": "Feature",
  "properties": {
    "iso:country":"US",
    "sg:address":"407 N Lombard Ave",
    "sg:city":"Oak Park",
    "sg:classifiers":[
        {
            "category":"Professional",
            "subcategory":"Business Services",
            "type":"Services"
        }
    ],
    "sg:phone":"+1 708 383 4546",
    "sg:postcode":"60302",
    "sg:province":"IL",
    "wof:name":"Carmel Failor Interior De",
    "wof:placetype":"venue"
},
  "geometry": {"coordinates":[-87.780071,41.894544],"type":"Point"}
}