{
  "type": "Feature",
  "properties": {
    "iso:country":"US",
    "sg:address":"107 N Galena Ave",
    "sg:city":"Wyoming",
    "sg:classifiers":[
        {
            "category":"Freight",
            "type":"Transportation"
        }
    ],
    "sg:phone":"+1 309 695 2324",
    "sg:postcode":"61491",
    "sg:province":"IL",
    "sg:tags":[
        "operator",
        "trucking"
    ],
    "wof:name":"Ratcliff Enterprises Inc",
    "wof:placetype":"venue"
},
  "geometry": {"coordinates":[-89.77157699999999,41.062732],"type":"Point"}
}