{
  "type": "Feature",
  "properties": {
    "iso:country":"US",
    "sg:address":"100 Trade Centre Dr",
    "sg:city":"Champaign",
    "sg:classifiers":[
        {
            "category":"Professional",
            "subcategory":"Advertising",
            "type":"Services"
        }
    ],
    "sg:phone":"+1 217 355 8741",
    "sg:postcode":"61820",
    "sg:province":"IL",
    "sg:tags":[
        "agency"
    ],
    "wof:name":"Rent-A-Center",
    "wof:placetype":"venue"
},
  "geometry": {"coordinates":[-88.24664199999999,40.097739],"type":"Point"}
}