{
  "type": "Feature",
  "properties": {
    "iso:country":"US",
    "sg:address":"11629 Main St",
    "sg:city":"Roscoe",
    "sg:classifiers":[
        {
            "category":"Retail",
            "subcategory":"Car Wash",
            "type":"Services"
        }
    ],
    "sg:phone":"+1 815 623 9588",
    "sg:postcode":"61073",
    "sg:province":"IL",
    "sg:tags":[
        "carwash"
    ],
    "wof:name":"Precision Auto Wash",
    "wof:placetype":"venue"
},
  "geometry": {"coordinates":[-89.01514400000001,42.431536],"type":"Point"}
}