{
  "type": "Feature",
  "properties": {
    "iso:country":"US",
    "sg:address":"19300 Marydale Rd",
    "sg:city":"Carlyle",
    "sg:classifiers":[
        {
            "category":"Professional",
            "subcategory":"Testing Lab",
            "type":"Services"
        },
        {
            "category":"Science Facility",
            "type":"Public Place"
        }
    ],
    "sg:phone":"+1 618 594 7645",
    "sg:postcode":"62231",
    "sg:province":"IL",
    "sg:tags":[
        "development",
        "analytical",
        "laboratories-research",
        "laboratory"
    ],
    "sg:website":"http://www.sgs.com",
    "wof:name":"Alvey Ag",
    "wof:placetype":"venue"
},
  "geometry": {"coordinates":[-89.351137,38.697786],"type":"Point"}
}