{
  "type": "Feature",
  "properties": {
    "iso:country":"US",
    "sg:address":"3711 N Ravenswood Ave",
    "sg:city":"Chicago",
    "sg:classifiers":[
        {
            "category":"Communications",
            "type":"Services"
        }
    ],
    "sg:phone":"+1 773 244 0305",
    "sg:postcode":"60613",
    "sg:province":"IL",
    "sg:tags":[
        "web",
        "design"
    ],
    "wof:name":"Edgeworks Technology",
    "wof:placetype":"venue"
},
  "geometry": {"coordinates":[-87.67362,41.948951],"type":"Point"}
}