{
  "type": "Feature",
  "properties": {
    "iso:country":"US",
    "sg:address":"2500 S Raney St",
    "sg:city":"Effingham",
    "sg:classifiers":[
        {
            "category":"Transit Center",
            "subcategory":"Freight",
            "type":"Transportation"
        },
        {
            "category":"Freight",
            "type":"Transportation"
        },
        {
            "category":"Government",
            "subcategory":"Post Office",
            "type":"Public Place"
        }
    ],
    "sg:phone":"+1 217 347 3962",
    "sg:postcode":"62401",
    "sg:province":"IL",
    "sg:tags":[
        "delivery",
        "trucking-motor",
        "courier",
        "trucking"
    ],
    "wof:name":"Estes Express Lines, Inc.",
    "wof:placetype":"venue"
},
  "geometry": {"coordinates":[-88.561401,39.09861],"type":"Point"}
}