{
  "type": "Feature",
  "properties": {
    "iso:country":"US",
    "sg:address":"909 Chestnut St Ste 105",
    "sg:city":"Saint Louis",
    "sg:classifiers":[
        {
            "category":"Shopping",
            "subcategory":"Pharmacy",
            "type":"Retail Goods"
        }
    ],
    "sg:phone":"+1 314 588 0356",
    "sg:postcode":"63101",
    "sg:province":"MO",
    "sg:tags":[
        "drugstore"
    ],
    "sg:website":"www.cvs.com",
    "wof:name":"Cvs Pharmacy",
    "wof:placetype":"venue"
},
  "geometry": {"coordinates":[-90.19416,38.627475],"type":"Point"}
}