{
  "type": "Feature",
  "properties": {
    "addr:full":"1162 80th St Roseville IL 61473",
    "addr:housenumber":"1162",
    "addr:postcode":"61473",
    "addr:street":"80Th St",
    "iso:country":"US",
    "sg:address":"1162 80th St",
    "sg:city":"Roseville",
    "sg:classifiers":[
        {
            "category":"Farming",
            "subcategory":"Farm",
            "type":"Manufacturing & Wholesale Goods"
        }
    ],
    "sg:phone":"+1 309 734 5083",
    "sg:postcode":"61473",
    "sg:province":"IL",
    "wof:name":"Ronald Moore",
    "wof:placetype":"venue"
},
  "geometry": {"coordinates":[-90.635042,40.7418],"type":"Point"}
}