{
  "type": "Feature",
  "properties": {
    "iso:country":"US",
    "sg:address":"60 W Terra Cotta Ave",
    "sg:city":"Crystal Lake",
    "sg:classifiers":[
        {
            "category":"Building & Trades",
            "subcategory":"Construction",
            "type":"Services"
        }
    ],
    "sg:phone":"+1 847 891 4775",
    "sg:postcode":"60014",
    "sg:province":"IL",
    "sg:tags":[
        "nonresidential"
    ],
    "wof:name":"J W Skutnick Construction",
    "wof:placetype":"venue"
},
  "geometry": {"coordinates":[-88.322859,42.248274],"type":"Point"}
}