{
  "type": "Feature",
  "properties": {
    "iso:country":"US",
    "sg:address":"419 Hill Ave",
    "sg:city":"Glen Ellyn",
    "sg:classifiers":[
        {
            "category":"Building & Trades",
            "subcategory":"Cleaning & Sanitation",
            "type":"Services"
        }
    ],
    "sg:phone":"+1 630 545 9551",
    "sg:postcode":"60137",
    "sg:province":"IL",
    "sg:tags":[
        "home",
        "maintenance"
    ],
    "sg:website":"www.powercleaninc.com",
    "wof:name":"Power Clean Inc",
    "wof:placetype":"venue"
},
  "geometry": {"coordinates":[-88.071602,41.8708],"type":"Point"}
}