{
  "type": "Feature",
  "properties": {
    "addr:full":"215 W Romeo Rd Romeoville IL 60446",
    "addr:housenumber":"215",
    "addr:postcode":"60446",
    "addr:street":"W Romeo Rd",
    "iso:country":"US",
    "sg:address":"215 W Romeo Rd",
    "sg:city":"Romeoville",
    "sg:classifiers":[
        {
            "category":"Professional",
            "subcategory":"Employment Agencies",
            "type":"Services"
        }
    ],
    "sg:phone":"+1 815 293 3900",
    "sg:postcode":"60446",
    "sg:province":"IL",
    "sg:tags":[
        "opportunity"
    ],
    "wof:name":"Debbie's Customize Staffing",
    "wof:placetype":"venue"
},
  "geometry": {"coordinates":[-88.084568,41.639905],"type":"Point"}
}