{
  "type": "Feature",
  "properties": {
    "addr:full":"1605 N State Route 50 Bourbonnais IL 60914",
    "addr:housenumber":"1605",
    "addr:postcode":"60914",
    "addr:street":"N State Route 50 Bourbonnais",
    "iso:country":"US",
    "sg:address":"1605 N State Route 50",
    "sg:city":"Bourbonnais",
    "sg:classifiers":[
        {
            "category":"Restaurant",
            "type":"Food & Drink"
        }
    ],
    "sg:menulink":"http://www.allmenus.com/il/bourbonnais/95343-lone-star-steakhouse--saloon/menu/",
    "sg:phone":"+1 815 939 1355",
    "sg:postcode":"60914",
    "sg:province":"IL",
    "sg:tags":[
        "american",
        "steakhouse"
    ],
    "wof:name":"Lone Star Steakhouse & Saloon",
    "wof:placetype":"venue"
},
  "geometry": {"coordinates":[-87.851309,41.170007],"type":"Point"}
}