{
  "type": "Feature",
  "properties": {
    "iso:country":"US",
    "sg:address":"23404 State Rte 1",
    "sg:city":"Chrisman",
    "sg:classifiers":[
        {
            "category":"Manufacturing",
            "subcategory":"Printing",
            "type":"Manufacturing & Wholesale Goods"
        }
    ],
    "sg:phone":"+1 217 269 2892",
    "sg:postcode":"61924",
    "sg:province":"IL",
    "sg:tags":[
        "publisher",
        "guide"
    ],
    "wof:name":"Larry Stuffle Consulting",
    "wof:placetype":"venue"
},
  "geometry": {"coordinates":[-87.671933,39.810186],"type":"Point"}
}