{
  "type": "Feature",
  "properties": {
    "addr:full":"1904 Alder Ln Champaign IL 61821",
    "addr:housenumber":"1904",
    "addr:postcode":"61821",
    "addr:street":"Alder Ln",
    "iso:country":"US",
    "sg:address":"1904 Alder Ln",
    "sg:city":"Champaign",
    "sg:classifiers":[
        {
            "category":"Autos & Motor Vehicles",
            "subcategory":"Automobile Sales",
            "type":"Retail Goods"
        }
    ],
    "sg:phone":"+1 217 398 8557",
    "sg:postcode":"61821",
    "sg:province":"IL",
    "sg:tags":[
        "performance",
        "race",
        "dealer"
    ],
    "wof:name":"Dressler Enterprises",
    "wof:placetype":"venue"
},
  "geometry": {"coordinates":[-88.278603,40.092023],"type":"Point"}
}