{
  "type": "Feature",
  "properties": {
    "iso:country":"US",
    "sg:address":"181 Army Trail Rd",
    "sg:city":"Glendale Heights",
    "sg:classifiers":[
        {
            "category":"Restaurant",
            "type":"Food & Drink"
        }
    ],
    "sg:phone":"+1 630 523 5990",
    "sg:postcode":"60139",
    "sg:province":"IL",
    "sg:tags":[
        "shop",
        "coffee"
    ],
    "wof:name":"A Lavazza Cafe",
    "wof:placetype":"venue"
},
  "geometry": {"coordinates":[-88.083291,41.937283],"type":"Point"}
}