{
  "type": "Feature",
  "properties": {
    "addr:full":"670 E Main St Lake Zurich IL 60047",
    "addr:housenumber":"670",
    "addr:postcode":"60047",
    "addr:street":"E Main St",
    "iso:country":"US",
    "sg:address":"670 E Main St",
    "sg:city":"Lake Zurich",
    "sg:classifiers":[
        {
            "category":"Restaurant",
            "type":"Food & Drink"
        }
    ],
    "sg:phone":"+1   ",
    "sg:postcode":"60047",
    "sg:province":"IL",
    "sg:tags":[
        "eating"
    ],
    "wof:name":"Riccis Grill",
    "wof:placetype":"venue"
},
  "geometry": {"coordinates":[-88.074062,42.197511],"type":"Point"}
}