{
  "type": "Feature",
  "properties": {
    "iso:country":"US",
    "sg:address":"2808 Wake Island Dr",
    "sg:city":"Joliet",
    "sg:classifiers":[
        {
            "category":"Building & Trades",
            "subcategory":"Construction",
            "type":"Services"
        }
    ],
    "sg:phone":"+1 815 341 1413",
    "sg:postcode":"60435",
    "sg:province":"IL",
    "sg:tags":[
        "hanging"
    ],
    "wof:name":"Exceptional Painting & Dctg",
    "wof:placetype":"venue"
},
  "geometry": {"coordinates":[-88.15156500000001,41.553011],"type":"Point"}
}