{
  "type": "Feature",
  "properties": {
    "addr:full":"1725 Kishwaukee St Rockford IL 61104",
    "addr:housenumber":"1725",
    "addr:postcode":"61104",
    "addr:street":"Kishwaukee St",
    "iso:country":"US",
    "sg:address":"1725 Kishwaukee St",
    "sg:city":"Rockford",
    "sg:classifiers":[
        {
            "category":"Food & Beverages",
            "subcategory":"Groceries & Convenience Stores",
            "type":"Retail Goods"
        }
    ],
    "sg:phone":"+1 815 964 7766",
    "sg:postcode":"61104",
    "sg:province":"IL",
    "wof:name":"Rockford Food & Liquor",
    "wof:placetype":"venue"
},
  "geometry": {"coordinates":[-89.086889,42.247874],"type":"Point"}
}