{
  "type": "Feature",
  "properties": {
    "addr:full":"750 N 19th St Springfield IL 62702",
    "addr:housenumber":"750",
    "addr:postcode":"62702",
    "addr:street":"N 19Th St",
    "iso:country":"US",
    "sg:address":"750 N 19th St",
    "sg:city":"Springfield",
    "sg:classifiers":[
        {
            "category":"Arena",
            "subcategory":"Indoor Arena",
            "type":"Entertainment"
        }
    ],
    "sg:phone":"+1 217 789 1047",
    "sg:postcode":"62702",
    "sg:province":"IL",
    "sg:tags":[
        "bingo",
        "hall"
    ],
    "sg:website":"http://home.comcast.net/~VictoryHall750/",
    "wof:name":"Victory Hall",
    "wof:placetype":"venue"
},
  "geometry": {"coordinates":[-89.62999000000001,39.808688],"type":"Point"}
}