{
  "type": "Feature",
  "properties": {
    "iso:country":"US",
    "sg:address":"1451 Landmeier Rd",
    "sg:city":"Elk Grove Village",
    "sg:classifiers":[
        {
            "category":"Manufacturing",
            "subcategory":"Printing",
            "type":"Manufacturing & Wholesale Goods"
        }
    ],
    "sg:phone":"+1 847 228 7080",
    "sg:postcode":"60007",
    "sg:province":"IL",
    "sg:tags":[
        "letterpress"
    ],
    "wof:name":"Duo Graphics",
    "wof:placetype":"venue"
},
  "geometry": {"coordinates":[-87.96391,42.011285],"type":"Point"}
}