{
  "type": "Feature",
  "properties": {
    "addr:full":"505 S Dunlap Ave Savoy IL 61874",
    "addr:housenumber":"505",
    "addr:postcode":"61874",
    "addr:street":"S Dunlap Ave",
    "iso:country":"US",
    "sg:address":"505 S Dunlap Ave",
    "sg:city":"Savoy",
    "sg:classifiers":[
        {
            "category":"Personal",
            "subcategory":"Nail Salon",
            "type":"Services"
        }
    ],
    "sg:phone":"+1 217 398 0853",
    "sg:postcode":"61874",
    "sg:province":"IL",
    "sg:website":"www.regalnails.com",
    "wof:name":"Regal Nails",
    "wof:placetype":"venue"
},
  "geometry": {"coordinates":[-88.252197,40.048901],"type":"Point"}
}