{
  "type": "Feature",
  "properties": {
    "iso:country":"US",
    "sg:address":"1519 W Harrison St",
    "sg:city":"Freeport",
    "sg:classifiers":[
        {
            "category":"Personal",
            "subcategory":"Beauty Salon",
            "type":"Services"
        }
    ],
    "sg:phone":"+1 815 235 9259",
    "sg:postcode":"61032",
    "sg:province":"IL",
    "sg:tags":[
        "shop"
    ],
    "wof:name":"Electrolisis By Emily",
    "wof:placetype":"venue"
},
  "geometry": {"coordinates":[-89.648742,42.292113],"type":"Point"}
}