{
  "type": "Feature",
  "properties": {
    "addr:full":"6058 N Rockwell St Chicago IL 60659",
    "addr:housenumber":"6058",
    "addr:postcode":"60659",
    "addr:street":"N Rockwell St",
    "iso:country":"US",
    "sg:address":"6058 N Rockwell St",
    "sg:city":"Chicago",
    "sg:classifiers":[
        {
            "category":"Personal",
            "subcategory":"Beauty Salon",
            "type":"Services"
        }
    ],
    "sg:phone":"+1 773 262 0909",
    "sg:postcode":"60659",
    "sg:province":"IL",
    "sg:tags":[
        "shop"
    ],
    "wof:name":"Lt Nails",
    "wof:placetype":"venue"
},
  "geometry": {"coordinates":[-87.69464499999999,41.991606],"type":"Point"}
}