{
  "type": "Feature",
  "properties": {
    "iso:country":"US",
    "sg:address":"120 Maguire St",
    "sg:city":"Dalton City",
    "sg:classifiers":[
        {
            "category":"Retail",
            "subcategory":"Repair Shop",
            "type":"Services"
        }
    ],
    "sg:phone":"+1 217 874 2055",
    "sg:postcode":"61925",
    "sg:province":"IL",
    "sg:tags":[
        "related"
    ],
    "wof:name":"JBT Svc",
    "wof:placetype":"venue"
},
  "geometry": {"coordinates":[-88.808043,39.711578],"type":"Point"}
}