{
  "type": "Feature",
  "properties": {
    "addr:full":"707 Garfield Ave Aurora IL 60506",
    "addr:housenumber":"707",
    "addr:postcode":"60506",
    "addr:street":"Garfield Ave",
    "iso:country":"US",
    "sg:address":"707 Garfield Ave",
    "sg:city":"Aurora",
    "sg:classifiers":[
        {
            "category":"Building & Trades",
            "subcategory":"Cleaning & Sanitation",
            "type":"Services"
        }
    ],
    "sg:phone":"+1 630 896 7960",
    "sg:postcode":"60506",
    "sg:province":"IL",
    "sg:tags":[
        "maintenance"
    ],
    "wof:name":"JD&k Cleaning Service",
    "wof:placetype":"venue"
},
  "geometry": {"coordinates":[-88.33497,41.759516],"type":"Point"}
}