{
  "type": "Feature",
  "properties": {
    "iso:country":"US",
    "sg:address":"314 Woolard Rd",
    "sg:city":"Jonesboro",
    "sg:classifiers":[
        {
            "category":"Health Services",
            "subcategory":"Doctor",
            "type":"Services"
        }
    ],
    "sg:phone":"+1 618 833 1383",
    "sg:postcode":"62930",
    "sg:province":"IL",
    "sg:tags":[
        "clinic"
    ],
    "wof:name":"Ulrich Medical Concepts Inc",
    "wof:placetype":"venue"
},
  "geometry": {"coordinates":[-88.496669,37.836617],"type":"Point"}
}