{
  "type": "Feature",
  "properties": {
    "addr:full":"1144 N Milwaukee Ave Chicago IL 60622",
    "addr:housenumber":"1144",
    "addr:postcode":"60622",
    "addr:street":"N Milwaukee Ave",
    "iso:country":"US",
    "sg:address":"1144 N Milwaukee Ave",
    "sg:city":"Chicago",
    "sg:classifiers":[
        {
            "category":"Food & Beverages",
            "subcategory":"Liquor & Beverages",
            "type":"Retail Goods"
        }
    ],
    "sg:phone":"+1 773 862 4353",
    "sg:postcode":"60622",
    "sg:province":"IL",
    "sg:tags":[
        "beer",
        "spirit",
        "wine"
    ],
    "wof:name":"Crater Food & Liquor",
    "wof:placetype":"venue"
},
  "geometry": {"coordinates":[-87.66480300000001,41.902401],"type":"Point"}
}