{
  "type": "Feature",
  "properties": {
    "iso:country":"US",
    "sg:address":"327 Gundersen Dr",
    "sg:city":"Carol Stream",
    "sg:classifiers":[
        {
            "category":"Health Services",
            "subcategory":"Doctor",
            "type":"Services"
        }
    ],
    "sg:phone":"+1 630 653 2599",
    "sg:postcode":"60188",
    "sg:province":"IL",
    "wof:name":"Uteg Robt P MD",
    "wof:placetype":"venue"
},
  "geometry": {"coordinates":[-88.111,41.8946],"type":"Point"}
}