{
  "type": "Feature",
  "properties": {
    "addr:full":"12707 Drive In Rd Breese IL 62230",
    "addr:housenumber":"12707",
    "addr:postcode":"62230",
    "addr:street":"Drive In Rd",
    "iso:country":"US",
    "sg:address":"12707 Drive In Rd",
    "sg:city":"Breese",
    "sg:classifiers":[
        {
            "category":"Home & Garden",
            "subcategory":"Building Materials",
            "type":"Retail Goods"
        },
        {
            "category":"Wholesale",
            "subcategory":"Construction Materials",
            "type":"Manufacturing & Wholesale Goods"
        },
        {
            "category":"Professional",
            "subcategory":"Business Services",
            "type":"Services"
        }
    ],
    "sg:phone":"+1 618 526 0800",
    "sg:postcode":"62230",
    "sg:province":"IL",
    "sg:tags":[
        "supply",
        "marble-natural",
        "marble-natural-wholesale",
        "equipment",
        "masonry",
        "manufacturer"
    ],
    "sg:website":"http://www.marblesystems.com",
    "wof:name":"Marble Systems Inc",
    "wof:placetype":"venue"
},
  "geometry": {"coordinates":[-89.553888,38.602978],"type":"Point"}
}