{
  "type": "Feature",
  "properties": {
    "iso:country":"US",
    "sg:address":"6255 N Newcastle Ave",
    "sg:city":"Chicago",
    "sg:classifiers":[
        {
            "category":"Arts & Performance",
            "subcategory":"Arts Center",
            "type":"Entertainment"
        }
    ],
    "sg:phone":"+1 773 775 9807",
    "sg:postcode":"60631",
    "sg:province":"IL",
    "sg:tags":[
        "performing"
    ],
    "sg:website":"www.mullanehealyobrien.com",
    "wof:name":"Mullane Champion Irish Dancers",
    "wof:placetype":"venue"
},
  "geometry": {"coordinates":[-87.796418,41.994299],"type":"Point"}
}