{
  "type": "Feature",
  "properties": {
    "addr:full":"1151 Ashland Ave Evanston IL 60202",
    "addr:housenumber":"1151",
    "addr:postcode":"60202",
    "addr:street":"Ashland Ave",
    "iso:country":"US",
    "sg:address":"1151 Ashland Ave",
    "sg:city":"Evanston",
    "sg:classifiers":[
        {
            "category":"Social Services",
            "type":"Services"
        }
    ],
    "sg:phone":"+1 847 866 7357",
    "sg:postcode":"60202",
    "sg:province":"IL",
    "sg:tags":[
        "human"
    ],
    "wof:name":"Reed, Sidney",
    "wof:placetype":"venue"
},
  "geometry": {"coordinates":[-87.693647,42.038906],"type":"Point"}
}