{
  "type": "Feature",
  "properties": {
    "iso:country":"US",
    "sg:address":"3219 S Wright Rd",
    "sg:city":"Mc Henry",
    "sg:classifiers":[
        {
            "category":"Professional",
            "subcategory":"Business Services",
            "type":"Services"
        }
    ],
    "sg:phone":"+1 815 459 5546",
    "sg:postcode":"60050",
    "sg:province":"IL",
    "wof:name":"Schott Enterprises Inc",
    "wof:placetype":"venue"
},
  "geometry": {"coordinates":[-88.231436,42.284728],"type":"Point"}
}