{
  "type": "Feature",
  "properties": {
    "addr:full":"7203 S Exchange Ave Chicago IL 60649",
    "addr:housenumber":"7203",
    "addr:postcode":"60649",
    "addr:street":"S Exchange Ave",
    "iso:country":"US",
    "sg:address":"7203 S Exchange Ave",
    "sg:city":"Chicago",
    "sg:classifiers":[
        {
            "category":"Personal",
            "subcategory":"Beauty Salon",
            "type":"Services"
        }
    ],
    "sg:phone":"+1 773 221 8561",
    "sg:postcode":"60649",
    "sg:province":"IL",
    "wof:name":"Hair 4U",
    "wof:placetype":"venue"
},
  "geometry": {"coordinates":[-87.563744,41.763317],"type":"Point"}
}