{
  "type": "Feature",
  "properties": {
    "addr:full":"618 E 47th Street Chicago IL 60653",
    "addr:housenumber":"618",
    "addr:postcode":"60653",
    "addr:street":"E 47Th Street",
    "iso:country":"US",
    "sg:address":"618 E 47th Street",
    "sg:city":"Chicago",
    "sg:classifiers":[
        {
            "category":"Personal",
            "subcategory":"Beauty Salon",
            "type":"Services"
        }
    ],
    "sg:phone":"+1 773 373 9482",
    "sg:postcode":"60653",
    "sg:province":"IL",
    "sg:tags":[
        "hair"
    ],
    "wof:name":"Sims Barber Shop",
    "wof:placetype":"venue"
},
  "geometry": {"coordinates":[-87.61117900000001,41.809229],"type":"Point"}
}