{
  "type": "Feature",
  "properties": {
    "addr:full":"3516 Ridge Rd Lansing IL 60438",
    "addr:housenumber":"3516",
    "addr:postcode":"60438",
    "addr:street":"Ridge Rd",
    "iso:country":"US",
    "sg:address":"3516 Ridge Rd",
    "sg:city":"Lansing",
    "sg:classifiers":[
        {
            "category":"Shopping",
            "type":"Retail Goods"
        }
    ],
    "sg:phone":"+1   ",
    "sg:postcode":"60438",
    "sg:province":"IL",
    "sg:tags":[
        "merchandise"
    ],
    "wof:name":"All Saints Religious Goods",
    "wof:placetype":"venue"
},
  "geometry": {"coordinates":[-87.529741,41.564102],"type":"Point"}
}