{
  "type": "Feature",
  "properties": {
    "addr:full":"518 S Fritz St Lebanon IL 62254",
    "addr:housenumber":"518",
    "addr:postcode":"62254",
    "addr:street":"S Fritz St",
    "iso:country":"US",
    "sg:address":"518 S Fritz St",
    "sg:city":"Lebanon",
    "sg:classifiers":[
        {
            "category":"Insurance",
            "subcategory":"Hazard Insurance",
            "type":"Services"
        }
    ],
    "sg:phone":"+1 618 580 2774",
    "sg:postcode":"62254",
    "sg:province":"IL",
    "wof:name":"Dee Price",
    "wof:placetype":"venue"
},
  "geometry": {"coordinates":[-89.806201,38.599868],"type":"Point"}
}