{
  "type": "Feature",
  "properties": {
    "addr:full":"6737 W 95th St Oak Lawn IL 60453",
    "addr:housenumber":"6737",
    "addr:postcode":"60453",
    "addr:street":"W 95Th St",
    "iso:country":"US",
    "sg:address":"6737 W 95th St",
    "sg:city":"Oak Lawn",
    "sg:classifiers":[
        {
            "category":"Manufacturing",
            "subcategory":"Printing",
            "type":"Manufacturing & Wholesale Goods"
        }
    ],
    "sg:phone":"+1 708 599 9866",
    "sg:postcode":"60453",
    "sg:province":"IL",
    "sg:tags":[
        "print",
        "lithographic",
        "commercial",
        "typesetting"
    ],
    "wof:name":"Ace Commercial Printers",
    "wof:placetype":"venue"
},
  "geometry": {"coordinates":[-87.78945899999999,41.719349],"type":"Point"}
}