{
  "type": "Feature",
  "properties": {
    "addr:full":"14786 Route 111 Chesterfield IL 62630",
    "addr:housenumber":"14786",
    "addr:postcode":"62630",
    "addr:street":"Route 111",
    "iso:country":"US",
    "sg:address":"14786 Route 111",
    "sg:city":"Chesterfield",
    "sg:classifiers":[
        {
            "category":"Manufacturing",
            "subcategory":"Pet Food",
            "type":"Manufacturing & Wholesale Goods"
        },
        {
            "category":"Farming",
            "subcategory":"Farm",
            "type":"Manufacturing & Wholesale Goods"
        }
    ],
    "sg:phone":"+1 618 753 3256",
    "sg:postcode":"62630",
    "sg:province":"IL",
    "sg:tags":[
        "hay"
    ],
    "wof:name":"Albert Dowland",
    "wof:placetype":"venue"
},
  "geometry": {"coordinates":[-90.08763999999999,39.216744],"type":"Point"}
}