{
  "type": "Feature",
  "properties": {
    "iso:country":"US",
    "sg:address":"9311 W 122nd St",
    "sg:city":"Palos Park",
    "sg:classifiers":[
        {
            "category":"Wholesale",
            "subcategory":"Furniture",
            "type":"Manufacturing & Wholesale Goods"
        }
    ],
    "sg:phone":"+1 708 448 3606",
    "sg:postcode":"60464",
    "sg:province":"IL",
    "wof:name":"Park Place Incentives",
    "wof:placetype":"venue"
},
  "geometry": {"coordinates":[-87.849761,41.668669],"type":"Point"}
}