{
  "type": "Feature",
  "properties": {
    "addr:full":"1111 Dixie Hwy Beecher IL 60401",
    "addr:housenumber":"1111",
    "addr:postcode":"60401",
    "addr:street":"Dixie Hwy",
    "iso:country":"US",
    "sg:address":"1111 Dixie Hwy",
    "sg:city":"Beecher",
    "sg:classifiers":[
        {
            "category":"Shopping",
            "subcategory":"Florist",
            "type":"Retail Goods"
        }
    ],
    "sg:phone":"+1 708 946 2541",
    "sg:postcode":"60401",
    "sg:province":"IL",
    "wof:name":"Beecher Florists",
    "wof:placetype":"venue"
},
  "geometry": {"coordinates":[-87.62145,41.355261],"type":"Point"}
}