{
  "type": "Feature",
  "properties": {
    "addr:full":"3660 S Indiana Ave Chicago IL 60689",
    "addr:housenumber":"3660",
    "addr:postcode":"60689",
    "addr:street":"S Indiana Ave",
    "iso:country":"US",
    "sg:address":"3660 S Indiana Ave",
    "sg:city":"Chicago",
    "sg:classifiers":[
        {
            "category":"Restaurant",
            "type":"Food & Drink"
        }
    ],
    "sg:phone":"+1 773 924 1900",
    "sg:postcode":"60689",
    "sg:province":"IL",
    "sg:tags":[
        "caribbean"
    ],
    "wof:name":"J & R's Caribbean",
    "wof:placetype":"venue"
},
  "geometry": {"coordinates":[-87.62170399999999,41.828094],"type":"Point"}
}