{
  "type": "Feature",
  "properties": {
    "addr:full":"1247 S Wabash Ave Chicago IL 60605",
    "addr:housenumber":"1247",
    "addr:postcode":"60605",
    "addr:street":"S Wabash Ave",
    "iso:country":"US",
    "sg:address":"1247 S Wabash Ave",
    "sg:city":"Chicago",
    "sg:classifiers":[
        {
            "category":"Health Services",
            "subcategory":"Dentist",
            "type":"Services"
        }
    ],
    "sg:phone":"+1 312 662 1108",
    "sg:postcode":"60605",
    "sg:province":"IL",
    "sg:tags":[
        "cosmetic"
    ],
    "sg:website":"www.smiling-bright.com/",
    "wof:name":"Smiling Bright",
    "wof:placetype":"venue"
},
  "geometry": {"coordinates":[-87.62576199999999,41.866108],"type":"Point"}
}