{
  "type": "Feature",
  "properties": {
    "addr:full":"5901 N Cicero Ave Chicago IL 60646",
    "addr:housenumber":"5901",
    "addr:postcode":"60646",
    "addr:street":"N Cicero Ave",
    "iso:country":"US",
    "sg:address":"5901 N Cicero Ave",
    "sg:city":"Chicago",
    "sg:classifiers":[
        {
            "category":"Insurance",
            "subcategory":"Insurance Agent",
            "type":"Services"
        }
    ],
    "sg:phone":"+1 773 725 7820",
    "sg:postcode":"60646",
    "sg:province":"IL",
    "wof:name":"Disability Resource Group Inc",
    "wof:placetype":"venue"
},
  "geometry": {"coordinates":[-87.74832499999999,41.989889],"type":"Point"}
}