{
  "type": "Feature",
  "properties": {
    "addr:full":"101 E Park St Clayton IL 62324",
    "addr:housenumber":"101",
    "addr:postcode":"62324",
    "addr:street":"E Park St",
    "iso:country":"US",
    "sg:address":"101 E Park St",
    "sg:city":"Clayton",
    "sg:classifiers":[
        {
            "category":"Personal",
            "subcategory":"Beauty Salon",
            "type":"Services"
        }
    ],
    "sg:phone":"+1 217 894 7014",
    "sg:postcode":"62324",
    "sg:province":"IL",
    "wof:name":"Barb's Beauty Shop",
    "wof:placetype":"venue"
},
  "geometry": {"coordinates":[-90.959452,40.031179],"type":"Point"}
}