{
  "type": "Feature",
  "properties": {
    "iso:country":"US",
    "sg:address":"9115 Medill Ave",
    "sg:city":"Franklin Park",
    "sg:classifiers":[
        {
            "category":"Retail",
            "subcategory":"Auto Repair",
            "type":"Services"
        }
    ],
    "sg:phone":"+1 847 451 7066",
    "sg:postcode":"60131",
    "sg:province":"IL",
    "wof:name":"Glassource",
    "wof:placetype":"venue"
},
  "geometry": {"coordinates":[-87.855274,41.920392],"type":"Point"}
}