{
  "type": "Feature",
  "properties": {
    "iso:country":"US",
    "sg:address":"5818 S Washtenaw Ave",
    "sg:city":"Chicago",
    "sg:classifiers":[
        {
            "category":"Shopping",
            "subcategory":"Beauty & Cosmetics",
            "type":"Retail Goods"
        }
    ],
    "sg:phone":"+1 773 776 1320",
    "sg:postcode":"60629",
    "sg:province":"IL",
    "sg:tags":[
        "perfume"
    ],
    "wof:name":"Tabu Perfume",
    "wof:placetype":"venue"
},
  "geometry": {"coordinates":[-87.69119000000001,41.787916],"type":"Point"}
}