{
  "type": "Feature",
  "properties": {
    "iso:country":"US",
    "sg:address":"1 E Division St",
    "sg:city":"Amboy",
    "sg:classifiers":[
        {
            "category":"Food & Beverages",
            "subcategory":"Liquor & Beverages",
            "type":"Retail Goods"
        }
    ],
    "sg:phone":"+1   ",
    "sg:postcode":"61310",
    "sg:province":"IL",
    "sg:tags":[
        "tape",
        "video",
        "rental",
        "alcoholic"
    ],
    "wof:name":"Amboy Bottling",
    "wof:placetype":"venue"
},
  "geometry": {"coordinates":[-89.333134,41.714987],"type":"Point"}
}