{
  "type": "Feature",
  "properties": {
    "iso:country":"US",
    "sg:address":"8258 S Harlem Ave",
    "sg:city":"Bridgeview",
    "sg:classifiers":[
        {
            "category":"Food & Beverages",
            "subcategory":"Groceries & Convenience Stores",
            "type":"Retail Goods"
        }
    ],
    "sg:phone":"+1 708 924 1976",
    "sg:postcode":"60455",
    "sg:province":"IL",
    "wof:name":"Rmart",
    "wof:placetype":"venue"
},
  "geometry": {"coordinates":[-87.79944399999999,41.741313],"type":"Point"}
}