{
  "type": "Feature",
  "properties": {
    "addr:full":"6825 Weaver Rd Rockford IL 61114",
    "addr:housenumber":"6825",
    "addr:postcode":"61114",
    "addr:street":"Weaver Rd",
    "iso:country":"US",
    "sg:address":"6825 Weaver Rd",
    "sg:city":"Rockford",
    "sg:classifiers":[
        {
            "category":"Retail",
            "subcategory":"Funeral Services",
            "type":"Services"
        }
    ],
    "sg:phone":"+1 815 282 6202",
    "sg:postcode":"61114",
    "sg:province":"IL",
    "sg:tags":[
        "director"
    ],
    "wof:name":"Cremation Society Of Illinois",
    "wof:placetype":"venue"
},
  "geometry": {"coordinates":[-88.983362,42.317139],"type":"Point"}
}