{
  "type": "Feature",
  "properties": {
    "iso:country":"US",
    "sg:address":"6620 Ogden Ave",
    "sg:city":"Berwyn",
    "sg:classifiers":[
        {
            "category":"Banks & Credit Unions",
            "subcategory":"Bank",
            "type":"Services"
        }
    ],
    "sg:phone":"+1 708 222 6200",
    "sg:postcode":"60402",
    "sg:province":"IL",
    "sg:website":"www.nationalcity.com",
    "wof:name":"National City Bank",
    "wof:placetype":"venue"
},
  "geometry": {"coordinates":[-87.78870000000001,41.828451],"type":"Point"}
}