{
  "type": "Feature",
  "properties": {
    "iso:country":"US",
    "sg:address":"717 First St",
    "sg:city":"Batavia",
    "sg:classifiers":[
        {
            "category":"Manufacturing",
            "subcategory":"Metals",
            "type":"Manufacturing & Wholesale Goods"
        }
    ],
    "sg:phone":"+1 630 879 1319",
    "sg:postcode":"60510",
    "sg:province":"IL",
    "sg:tags":[
        "foundry"
    ],
    "wof:name":"Batavia Foundry & Machine",
    "wof:placetype":"venue"
},
  "geometry": {"coordinates":[-88.318894,41.848331],"type":"Point"}
}