{
  "type": "Feature",
  "properties": {
    "addr:full":"404 E Lake Shore Dr Round Lake IL 60073",
    "addr:housenumber":"404",
    "addr:postcode":"60073",
    "addr:street":"E Lake Shore Dr",
    "iso:country":"US",
    "sg:address":"404 E Lake Shore Dr",
    "sg:city":"Round Lake",
    "sg:classifiers":[
        {
            "category":"Building & Trades",
            "subcategory":"Construction",
            "type":"Services"
        }
    ],
    "sg:phone":"+1 847 546 1945",
    "sg:postcode":"60073",
    "sg:province":"IL",
    "sg:tags":[
        "general",
        "contractor"
    ],
    "wof:name":"Lannan Woodworks Inc",
    "wof:placetype":"venue"
},
  "geometry": {"coordinates":[-88.07464400000001,42.35998],"type":"Point"}
}