{
  "type": "Feature",
  "properties": {
    "addr:full":"5539 N Broadway Street Chicago IL 60640",
    "addr:housenumber":"5539",
    "addr:postcode":"60640",
    "addr:street":"N Broadway Street",
    "iso:country":"US",
    "sg:address":"5539 N Broadway Street",
    "sg:city":"Chicago",
    "sg:classifiers":[
        {
            "category":"Real Estate",
            "subcategory":"Real Estate Services",
            "type":"Services"
        }
    ],
    "sg:phone":"+1 773 878 4599",
    "sg:postcode":"60640",
    "sg:province":"IL",
    "wof:name":"Catalpa Gardens",
    "wof:placetype":"venue"
},
  "geometry": {"coordinates":[-87.66,41.982503],"type":"Point"}
}