{
  "type": "Feature",
  "properties": {
    "addr:full":"1477 Keokuk St Hamilton IL 62341",
    "addr:housenumber":"1477",
    "addr:postcode":"62341",
    "addr:street":"Keokuk St",
    "iso:country":"US",
    "sg:address":"1477 Keokuk St",
    "sg:city":"Hamilton",
    "sg:classifiers":[
        {
            "category":"Personal",
            "type":"Services"
        }
    ],
    "sg:phone":"+1 217 847 6159",
    "sg:postcode":"62341",
    "sg:province":"IL",
    "sg:tags":[
        "therapist",
        "massage"
    ],
    "wof:name":"Innerpeace Massage Therapy",
    "wof:placetype":"venue"
},
  "geometry": {"coordinates":[-91.338069,40.396542],"type":"Point"}
}