{
  "type": "Feature",
  "properties": {
    "iso:country":"US",
    "sg:address":"324 N Gardiner Ave",
    "sg:city":"Rockford",
    "sg:classifiers":[
        {
            "category":"Manufacturing",
            "subcategory":"Tools & Machinery",
            "type":"Manufacturing & Wholesale Goods"
        }
    ],
    "sg:phone":"+1 815 226 0452",
    "sg:postcode":"61107",
    "sg:province":"IL",
    "sg:tags":[
        "surgical",
        "mask",
        "mfg"
    ],
    "wof:name":"Rondex Products Incorporated",
    "wof:placetype":"venue"
},
  "geometry": {"coordinates":[-89.066593,42.271183],"type":"Point"}
}