{
  "type": "Feature",
  "properties": {
    "iso:country":"US",
    "sg:address":"3426 21st St",
    "sg:city":"Rock Island",
    "sg:classifiers":[
        {
            "category":"Organizations",
            "subcategory":"Community Association",
            "type":"Services"
        }
    ],
    "sg:phone":"+1 309 794 0957",
    "sg:postcode":"61201",
    "sg:province":"IL",
    "wof:name":"Illinois Demolay",
    "wof:placetype":"venue"
},
  "geometry": {"coordinates":[-90.571358,41.473907],"type":"Point"}
}