{
  "type": "Feature",
  "properties": {
    "addr:full":"4921 Forest Ave Downers Grove IL 60515",
    "addr:housenumber":"4921",
    "addr:postcode":"60515",
    "addr:street":"Forest Ave",
    "iso:country":"US",
    "sg:address":"4921 Forest Ave",
    "sg:city":"Downers Grove",
    "sg:classifiers":[
        {
            "category":"Real Estate",
            "subcategory":"Real Estate Agent",
            "type":"Services"
        }
    ],
    "sg:phone":"+1 630 852 7500",
    "sg:postcode":"60515",
    "sg:province":"IL",
    "wof:name":"Joe Pepitone Realtors",
    "wof:placetype":"venue"
},
  "geometry": {"coordinates":[-88.011799,41.79593],"type":"Point"}
}