{
  "type": "Feature",
  "properties": {
    "iso:country":"US",
    "sg:address":"7020 N Mount Hawley Rd",
    "sg:city":"Peoria",
    "sg:classifiers":[
        {
            "category":"Place Of Worship",
            "subcategory":"Church",
            "type":"Public Place"
        },
        {
            "category":"Place Of Worship",
            "type":"Public Place"
        },
        {
            "category":"Organizations",
            "subcategory":"Religious Organization",
            "type":"Services"
        }
    ],
    "sg:phone":"+1 309 691 8620",
    "sg:postcode":"61614",
    "sg:province":"IL",
    "sg:tags":[
        "christ",
        "science",
        "christ-new",
        "churches-religious",
        "testament",
        "churches-church",
        "churches-christian"
    ],
    "sg:website":"http://www.seattlecsdrr.com",
    "wof:name":"Second Church",
    "wof:placetype":"venue"
},
  "geometry": {"coordinates":[-89.59972999999999,40.772821],"type":"Point"}
}