{
  "type": "Feature",
  "properties": {
    "iso:country":"US",
    "sg:address":"1013 N Cicero Ave",
    "sg:city":"Chicago",
    "sg:classifiers":[
        {
            "category":"Manufacturing",
            "subcategory":"Tools & Machinery",
            "type":"Manufacturing & Wholesale Goods"
        }
    ],
    "sg:phone":"+1 773 921 8700",
    "sg:postcode":"60651",
    "sg:province":"IL",
    "sg:tags":[
        "food",
        "mfg",
        "mach"
    ],
    "wof:name":"Freeze King",
    "wof:placetype":"venue"
},
  "geometry": {"coordinates":[-87.74583199999999,41.899394],"type":"Point"}
}