{
  "type": "Feature",
  "properties": {
    "iso:country":"US",
    "sg:address":"13527 Natchez Trl",
    "sg:city":"Orland Park",
    "sg:classifiers":[
        {
            "category":"Food & Beverages",
            "subcategory":"Specialty",
            "type":"Retail Goods"
        }
    ],
    "sg:phone":"+1   ",
    "sg:postcode":"60467",
    "sg:province":"IL",
    "wof:name":"Health Advantage Inc",
    "wof:placetype":"venue"
},
  "geometry": {"coordinates":[-87.907661,41.642778],"type":"Point"}
}