{
  "type": "Feature",
  "properties": {
    "addr:full":"6348 W 95th St Oak Lawn IL 60453",
    "addr:housenumber":"6348",
    "addr:postcode":"60453",
    "addr:street":"W 95Th St",
    "iso:country":"US",
    "sg:address":"6348 W 95th St",
    "sg:city":"Oak Lawn",
    "sg:classifiers":[
        {
            "category":"Professional",
            "subcategory":"Business Services",
            "type":"Services"
        }
    ],
    "sg:phone":"+1 708 499 8633",
    "sg:postcode":"60453",
    "sg:province":"IL",
    "sg:tags":[
        "relocation"
    ],
    "wof:name":"Fire & Disaster Relocation Svc",
    "wof:placetype":"venue"
},
  "geometry": {"coordinates":[-87.779771,41.719682],"type":"Point"}
}