{
  "type": "Feature",
  "properties": {
    "addr:full":"1625 N Milwaukee Avenue Chicago IL 60647",
    "addr:housenumber":"1625",
    "addr:postcode":"60647",
    "addr:street":"N Milwaukee Avenue",
    "iso:country":"US",
    "sg:address":"1625 N Milwaukee Avenue",
    "sg:city":"Chicago",
    "sg:classifiers":[
        {
            "category":"Retail",
            "subcategory":"Portrait Studio",
            "type":"Services"
        },
        {
            "category":"Professional",
            "subcategory":"Art Services",
            "type":"Services"
        }
    ],
    "sg:phone":"+1 773 235 0161",
    "sg:postcode":"60647",
    "sg:province":"IL",
    "sg:tags":[
        "photographer",
        "photography",
        "store"
    ],
    "wof:name":"Seymour Ronald Photgrphr",
    "wof:placetype":"venue"
},
  "geometry": {"coordinates":[-87.678541,41.910947],"type":"Point"}
}