{
  "type": "Feature",
  "properties": {
    "addr:full":"5103 W Grace St Chicago IL 60641",
    "addr:housenumber":"5103",
    "addr:postcode":"60641",
    "addr:street":"W Grace St",
    "iso:country":"US",
    "sg:address":"5103 W Grace St",
    "sg:city":"Chicago",
    "sg:classifiers":[
        {
            "category":"Building & Trades",
            "subcategory":"Cleaning & Sanitation",
            "type":"Services"
        }
    ],
    "sg:phone":"+1 708 768 8053",
    "sg:postcode":"60641",
    "sg:province":"IL",
    "sg:tags":[
        "cleaner",
        "repairer",
        "sewer"
    ],
    "wof:name":"A-Priority Sewer & Drainage",
    "wof:placetype":"venue"
},
  "geometry": {"coordinates":[-87.754628,41.949661],"type":"Point"}
}