{
  "type": "Feature",
  "properties": {
    "iso:country":"US",
    "sg:address":"1955 Shermer Rd",
    "sg:city":"Northbrook",
    "sg:classifiers":[
        {
            "category":"Professional",
            "subcategory":"Lawyer & Legal Services",
            "type":"Services"
        }
    ],
    "sg:phone":"+1 847 635 1217",
    "sg:postcode":"60062",
    "sg:province":"IL",
    "sg:tags":[
        "attorney",
        "law"
    ],
    "wof:name":"Bach Paul Attorney At Law",
    "wof:placetype":"venue"
},
  "geometry": {"coordinates":[-87.829266,42.117166],"type":"Point"}
}