{
  "type": "Feature",
  "properties": {
    "iso:country":"US",
    "sg:address":"1082 N 36th Rd",
    "sg:city":"Ottawa",
    "sg:phone":"+1 815 434 0315",
    "sg:postcode":"61350",
    "sg:province":"IL",
    "sg:tags":[
        "farm",
        "corn",
        "product"
    ],
    "wof:name":"Glenn Selvig",
    "wof:placetype":"venue"
},
  "geometry": {"coordinates":[-88.95679699999999,41.454586],"type":"Point"}
}