{
  "type": "Feature",
  "properties": {
    "addr:full":"5250 N Broadway St Chicago IL 60640",
    "addr:housenumber":"5250",
    "addr:postcode":"60640",
    "addr:street":"N Broadway St",
    "iso:country":"US",
    "sg:address":"5250 N Broadway St",
    "sg:city":"Chicago",
    "sg:classifiers":[
        {
            "category":"Wholesale",
            "subcategory":"Non-durable Goods",
            "type":"Manufacturing & Wholesale Goods"
        }
    ],
    "sg:phone":"+1 773 989 1960",
    "sg:postcode":"60640",
    "sg:province":"IL",
    "wof:name":"Reno Lovison Advg & Mktg",
    "wof:placetype":"venue"
},
  "geometry": {"coordinates":[-87.659969,41.977213],"type":"Point"}
}