{
  "type": "Feature",
  "properties": {
    "addr:full":"3 Clock Tower Plz Elgin IL 60120",
    "addr:housenumber":"3",
    "addr:postcode":"60120",
    "addr:street":"Clock Tower Plz",
    "iso:country":"US",
    "sg:address":"3 Clock Tower Plz",
    "sg:city":"Elgin",
    "sg:classifiers":[
        {
            "category":"Food & Beverages",
            "subcategory":"Supermarket",
            "type":"Retail Goods"
        }
    ],
    "sg:phone":"+1 847 741 9551",
    "sg:postcode":"60120",
    "sg:province":"IL",
    "sg:tags":[
        "super",
        "store"
    ],
    "sg:website":"http://www.buterafinerfoods.com",
    "wof:name":"Butera Finer Foods, Inc.",
    "wof:placetype":"venue"
},
  "geometry": {"coordinates":[-88.27741899999999,42.029821],"type":"Point"}
}