{
  "type": "Feature",
  "properties": {
    "addr:full":"2324 W 111th St Suite 1C Chicago IL 60643",
    "addr:housenumber":"2324",
    "addr:postcode":"60643",
    "addr:street":"W 111Th St Suite 1C",
    "iso:country":"US",
    "sg:address":"2324 W 111th St Suite 1C",
    "sg:city":"Chicago",
    "sg:classifiers":[
        {
            "category":"Airline",
            "type":"Transportation"
        },
        {
            "category":"Travel",
            "subcategory":"Travel Agent",
            "type":"Entertainment"
        }
    ],
    "sg:phone":"+1 773 456 7530",
    "sg:postcode":"60643",
    "sg:province":"IL",
    "sg:tags":[
        "ticket",
        "agency"
    ],
    "sg:website":"http://www.besthomebizstartups.com",
    "wof:name":"BestHomeBizStartups.com",
    "wof:placetype":"venue"
},
  "geometry": {"coordinates":[-87.679534,41.691792],"type":"Point"}
}