{
  "type": "Feature",
  "properties": {
    "iso:country":"US",
    "sg:address":"12547 State Route 143",
    "sg:city":"Highland",
    "sg:classifiers":[
        {
            "category":"Restaurant",
            "type":"Food & Drink"
        }
    ],
    "sg:menulink":"http://www.allmenus.com/il/saline/124086-quiznos-sub/menu/",
    "sg:phone":"+1 618 651 9904",
    "sg:postcode":"62249",
    "sg:province":"IL",
    "sg:tags":[
        "wrap",
        "american",
        "sandwich"
    ],
    "wof:name":"Quiznos Sub",
    "wof:placetype":"venue"
},
  "geometry": {"coordinates":[-89.683339,38.758833],"type":"Point"}
}