{
  "type": "Feature",
  "properties": {
    "iso:country":"US",
    "sg:address":"149 N Vermilion St",
    "sg:city":"Danville",
    "sg:classifiers":[
        {
            "category":"Professional",
            "subcategory":"Management & Consulting",
            "type":"Services"
        }
    ],
    "sg:phone":"+1 217 442 6775",
    "sg:postcode":"61832",
    "sg:province":"IL",
    "sg:tags":[
        "consultant",
        "transportation"
    ],
    "wof:name":"Distribution Solutions",
    "wof:placetype":"venue"
},
  "geometry": {"coordinates":[-87.62996,40.12715],"type":"Point"}
}