{
  "type": "Feature",
  "properties": {
    "addr:full":"310 Waukegan Ave Highwood IL 60040",
    "addr:housenumber":"310",
    "addr:postcode":"60040",
    "addr:street":"Waukegan Ave",
    "iso:country":"US",
    "sg:address":"310 Waukegan Ave",
    "sg:city":"Highwood",
    "sg:classifiers":[
        {
            "category":"Banks & Credit Unions",
            "subcategory":"Bank",
            "type":"Services"
        },
        {
            "category":"Banks & Credit Unions",
            "subcategory":"Financial Services",
            "type":"Services"
        }
    ],
    "sg:phone":"+1 847 433 3000",
    "sg:postcode":"60040",
    "sg:province":"IL",
    "sg:tags":[
        "saving",
        "loan",
        "commercial"
    ],
    "sg:website":"http://www.firstar.com",
    "wof:name":"Us Bank",
    "wof:placetype":"venue"
},
  "geometry": {"coordinates":[-87.808691,42.202049],"type":"Point"}
}