{
  "type": "Feature",
  "properties": {
    "iso:country":"US",
    "sg:address":"225 Willard Ave",
    "sg:city":"Elgin",
    "sg:classifiers":[
        {
            "category":"Wholesale",
            "subcategory":"Auto Parts",
            "type":"Manufacturing & Wholesale Goods"
        }
    ],
    "sg:phone":"+1 847 695 4000",
    "sg:postcode":"60120",
    "sg:province":"IL",
    "sg:tags":[
        "automobile",
        "par",
        "used",
        "rebuilt"
    ],
    "wof:name":"Elgin Super Auto Parts Inc",
    "wof:placetype":"venue"
},
  "geometry": {"coordinates":[-88.260321,42.030579],"type":"Point"}
}