{
  "type": "Feature",
  "properties": {
    "iso:country":"US",
    "sg:address":"226 E Weaver Dr",
    "sg:city":"Cary",
    "sg:classifiers":[
        {
            "category":"Communications",
            "subcategory":"Film & Video Production",
            "type":"Services"
        }
    ],
    "sg:phone":"+1 815 338 6272",
    "sg:postcode":"60013",
    "sg:province":"IL",
    "sg:tags":[
        "motion",
        "picture"
    ],
    "wof:name":"Rld Interactive Studios",
    "wof:placetype":"venue"
},
  "geometry": {"coordinates":[-88.231455,42.209788],"type":"Point"}
}