{
  "type": "Feature",
  "properties": {
    "addr:full":"406 Green Bay Rd Kenilworth IL 60043",
    "addr:housenumber":"406",
    "addr:postcode":"60043",
    "addr:street":"Green Bay Rd",
    "iso:country":"US",
    "sg:address":"406 Green Bay Rd",
    "sg:city":"Kenilworth",
    "sg:classifiers":[
        {
            "category":"Wholesale",
            "subcategory":"Construction Materials",
            "type":"Manufacturing & Wholesale Goods"
        }
    ],
    "sg:phone":"+1 847 920 1620",
    "sg:postcode":"60043",
    "sg:province":"IL",
    "sg:tags":[
        "granite",
        "stone",
        "marble"
    ],
    "wof:name":"Mona Lisa Stone and Marble",
    "wof:placetype":"venue"
},
  "geometry": {"coordinates":[-87.71819000000001,42.087405],"type":"Point"}
}