{
  "type": "Feature",
  "properties": {
    "iso:country":"US",
    "sg:address":"706 Church St",
    "sg:city":"Evanston",
    "sg:classifiers":[
        {
            "category":"Shopping",
            "subcategory":"Gifts & Souvenirs",
            "type":"Retail Goods"
        }
    ],
    "sg:phone":"+1   ",
    "sg:postcode":"60201",
    "sg:province":"IL",
    "wof:name":"Peacock of Evanston Inc",
    "wof:placetype":"venue"
},
  "geometry": {"coordinates":[-87.680982,42.048379],"type":"Point"}
}