{
  "type": "Feature",
  "properties": {
    "iso:country":"US",
    "sg:address":"538 Duane St",
    "sg:city":"Glen Ellyn",
    "sg:classifiers":[
        {
            "category":"Shopping",
            "subcategory":"Clothing, Apparel, & Fashions",
            "type":"Retail Goods"
        }
    ],
    "sg:phone":"+1 630 469 7465",
    "sg:postcode":"60137",
    "sg:province":"IL",
    "sg:tags":[
        "accessory"
    ],
    "sg:website":"www.shopfuschia.com",
    "wof:name":"Fuschia",
    "wof:placetype":"venue"
},
  "geometry": {"coordinates":[-88.065791,41.875627],"type":"Point"}
}