{
  "type": "Feature",
  "properties": {
    "iso:country":"US",
    "sg:address":"18761 E Terre Haute Rd",
    "sg:city":"Paris",
    "sg:classifiers":[
        {
            "category":"Personal",
            "type":"Services"
        },
        {
            "category":"Professional",
            "subcategory":"Art Services",
            "type":"Services"
        }
    ],
    "sg:phone":"+1 217 275 3724",
    "sg:postcode":"61944",
    "sg:province":"IL",
    "sg:tags":[
        "photography",
        "videography",
        "wedding"
    ],
    "wof:name":"Phil's Contemporary Photography",
    "wof:placetype":"venue"
},
  "geometry": {"coordinates":[-87.540798,39.490027],"type":"Point"}
}