{
  "type": "Feature",
  "properties": {
    "addr:full":"2024 N Halsted St Chicago IL 60614",
    "addr:housenumber":"2024",
    "addr:postcode":"60614",
    "addr:street":"N Halsted St",
    "iso:country":"US",
    "sg:address":"2024 N Halsted St",
    "sg:city":"Chicago",
    "sg:classifiers":[
        {
            "category":"Cafe",
            "type":"Food & Drink"
        }
    ],
    "sg:menulink":"http://www.allmenus.com/il/chicago/11982-cafe-ba-ba-reeba/menu/",
    "sg:phone":"+1 773 935 5000",
    "sg:postcode":"60614",
    "sg:province":"IL",
    "sg:tags":[
        "spanish"
    ],
    "wof:name":"Cafe Ba Ba Reeba",
    "wof:placetype":"venue"
},
  "geometry": {"coordinates":[-87.648535,41.919252],"type":"Point"}
}