{
  "type": "Feature",
  "properties": {
    "addr:full":"1511 S State St Chicago IL 60605",
    "addr:housenumber":"1511",
    "addr:postcode":"60605",
    "addr:street":"S State St",
    "iso:country":"US",
    "sg:address":"1511 S State St",
    "sg:city":"Chicago",
    "sg:classifiers":[
        {
            "category":"Bakery",
            "type":"Food & Drink"
        }
    ],
    "sg:phone":"+1 312 922 5007",
    "sg:postcode":"60605",
    "sg:province":"IL",
    "sg:website":"www.carolinacaramel.com",
    "wof:name":"Carolina Caramel",
    "wof:placetype":"venue"
},
  "geometry": {"coordinates":[-87.62721500000001,41.861482],"type":"Point"}
}