{
  "type": "Feature",
  "properties": {
    "iso:country":"US",
    "sg:address":"10S059 Schoger Dr",
    "sg:city":"Naperville",
    "sg:classifiers":[
        {
            "category":"Building & Trades",
            "subcategory":"Landscaping Services",
            "type":"Services"
        }
    ],
    "sg:phone":"+1 630 236 0100",
    "sg:postcode":"60564",
    "sg:province":"IL",
    "sg:tags":[
        "lawn",
        "maintenance"
    ],
    "sg:website":"http://www.greenstarlawn.com",
    "wof:name":"Green Star Lawn Care Inc",
    "wof:placetype":"venue"
},
  "geometry": {"coordinates":[-88.227341,41.71875],"type":"Point"}
}