{
  "type": "Feature",
  "properties": {
    "iso:country":"US",
    "sg:address":"19460 la Grange Rd",
    "sg:city":"Mokena",
    "sg:classifiers":[
        {
            "category":"Personal",
            "subcategory":"Beauty Salon",
            "type":"Services"
        }
    ],
    "sg:phone":"+1 708 479 7001",
    "sg:postcode":"60448",
    "sg:province":"IL",
    "wof:name":"Shear Styles",
    "wof:placetype":"venue"
},
  "geometry": {"coordinates":[-87.850424,41.536438],"type":"Point"}
}