{
  "type": "Feature",
  "properties": {
    "iso:country":"US",
    "sg:address":"6720 Cermak Rd",
    "sg:city":"Berwyn",
    "sg:classifiers":[
        {
            "category":"Personal",
            "type":"Services"
        }
    ],
    "sg:phone":"+1 708 749 8282",
    "sg:postcode":"60402",
    "sg:province":"IL",
    "wof:name":"Bada Boom Tattoo Inc",
    "wof:placetype":"venue"
},
  "geometry": {"coordinates":[-87.791107,41.850669],"type":"Point"}
}