{
  "type": "Feature",
  "properties": {
    "iso:country":"US",
    "sg:address":"2203 SE 3rd St",
    "sg:city":"Aledo",
    "sg:classifiers":[
        {
            "category":"Personal",
            "subcategory":"Beauty Salon",
            "type":"Services"
        }
    ],
    "sg:phone":"+1 309 582 0599",
    "sg:postcode":"61231",
    "sg:province":"IL",
    "wof:name":"Lyndas Cut Above",
    "wof:placetype":"venue"
},
  "geometry": {"coordinates":[-90.72416699999999,41.199429],"type":"Point"}
}