{
  "type": "Feature",
  "properties": {
    "iso:country":"US",
    "sg:address":"98 S Galena Ave",
    "sg:city":"Dixon",
    "sg:classifiers":[
        {
            "category":"Banks & Credit Unions",
            "subcategory":"Bank",
            "type":"Services"
        }
    ],
    "sg:phone":"+1 815 288 3315",
    "sg:postcode":"61021",
    "sg:province":"IL",
    "wof:name":"US Bank",
    "wof:placetype":"venue"
},
  "geometry": {"coordinates":[-89.482682,41.843592],"type":"Point"}
}