{
  "type": "Feature",
  "properties": {
    "iso:country":"US",
    "sg:address":"5536 Oak Center Dr",
    "sg:city":"Oak Lawn",
    "sg:classifiers":[
        {
            "category":"Building & Trades",
            "subcategory":"Locksmith",
            "type":"Services"
        }
    ],
    "sg:phone":"+1 708 572 4124",
    "sg:postcode":"60453",
    "sg:province":"IL",
    "sg:tags":[
        "key"
    ],
    "sg:website":"www.locksandkeysspecialists.com/",
    "wof:name":"Locks and Keys Specialists",
    "wof:placetype":"venue"
},
  "geometry": {"coordinates":[-87.7585,41.709148],"type":"Point"}
}