{
  "type": "Feature",
  "properties": {
    "addr:full":"610 W Campbell St Arlington Heights IL 60005",
    "addr:housenumber":"610",
    "addr:postcode":"60005",
    "addr:street":"W Campbell St",
    "iso:country":"US",
    "sg:address":"610 W Campbell St",
    "sg:city":"Arlington Heights",
    "sg:classifiers":[
        {
            "category":"Professional",
            "subcategory":"Business Services",
            "type":"Services"
        }
    ],
    "sg:phone":"+1 847 506 9070",
    "sg:postcode":"60005",
    "sg:province":"IL",
    "sg:tags":[
        "consulting",
        "design",
        "architectural"
    ],
    "wof:name":"Mdi",
    "wof:placetype":"venue"
},
  "geometry": {"coordinates":[-87.99113199999999,42.082871],"type":"Point"}
}