{
  "type": "Feature",
  "properties": {
    "iso:country":"US",
    "sg:address":"100 N Broadway",
    "sg:city":"Saint Louis",
    "sg:classifiers":[
        {
            "category":"Professional",
            "subcategory":"Lawyer & Legal Services",
            "type":"Services"
        }
    ],
    "sg:phone":"+1 314 231 6700",
    "sg:postcode":"63102",
    "sg:province":"MO",
    "sg:website":"www.herzogcrebs.com",
    "wof:name":"Vitale Michael A Atty",
    "wof:placetype":"venue"
},
  "geometry": {"coordinates":[-90.188999,38.626393],"type":"Point"}
}