{
  "type": "Feature",
  "properties": {
    "addr:full":"1605 W Wilson St Batavia IL 60510",
    "addr:housenumber":"1605",
    "addr:postcode":"60510",
    "addr:street":"W Wilson St",
    "iso:country":"US",
    "sg:address":"1605 W Wilson St",
    "sg:city":"Batavia",
    "sg:classifiers":[
        {
            "category":"Professional",
            "subcategory":"Accounting & Tax Preparation",
            "type":"Services"
        },
        {
            "category":"Professional",
            "subcategory":"Management & Consulting",
            "type":"Services"
        },
        {
            "category":"Banks & Credit Unions",
            "subcategory":"Financial Services",
            "type":"Services"
        }
    ],
    "sg:phone":"+1 630 761 1076",
    "sg:postcode":"60510",
    "sg:province":"IL",
    "sg:tags":[
        "financing",
        "return",
        "preparation-business",
        "consultant",
        "planning",
        "bookkeeping"
    ],
    "wof:name":"Your Tax Team",
    "wof:placetype":"venue"
},
  "geometry": {"coordinates":[-88.337615,41.849758],"type":"Point"}
}