{
  "type": "Feature",
  "properties": {
    "iso:country":"US",
    "sg:address":"18516 Il Route 176",
    "sg:city":"Marengo",
    "sg:classifiers":[
        {
            "category":"Building & Trades",
            "subcategory":"Landscaping Services",
            "type":"Services"
        },
        {
            "category":"Shopping",
            "subcategory":"Pets & Pet Supplies",
            "type":"Retail Goods"
        }
    ],
    "sg:phone":"+1 815 568 1400",
    "sg:postcode":"60152",
    "sg:province":"IL",
    "sg:tags":[
        "pond",
        "construction",
        "lake",
        "store"
    ],
    "sg:website":"http://www.koipondjapan.com",
    "wof:name":"Koi Pond Supply Of Japan Inc",
    "wof:placetype":"venue"
},
  "geometry": {"coordinates":[-88.563447,42.255116],"type":"Point"}
}