{
  "type": "Feature",
  "properties": {
    "addr:full":"104 E Carter St Cerro Gordo IL 61818",
    "addr:housenumber":"104",
    "addr:postcode":"61818",
    "addr:street":"E Carter St",
    "iso:country":"US",
    "sg:address":"104 E Carter St",
    "sg:city":"Cerro Gordo",
    "sg:classifiers":[
        {
            "category":"Organizations",
            "subcategory":"Religious Organization",
            "type":"Services"
        }
    ],
    "sg:phone":"+1 217 763 8411",
    "sg:postcode":"61818",
    "sg:province":"IL",
    "sg:tags":[
        "church"
    ],
    "wof:name":"United Methodist Church",
    "wof:placetype":"venue"
},
  "geometry": {"coordinates":[-88.733058,39.892952],"type":"Point"}
}