{
  "type": "Feature",
  "properties": {
    "iso:country":"US",
    "sg:address":"824 Chickory Dr",
    "sg:city":"Champaign",
    "sg:classifiers":[
        {
            "category":"Banks & Credit Unions",
            "subcategory":"Investment Brokerage",
            "type":"Services"
        },
        {
            "category":"Banks & Credit Unions",
            "subcategory":"Financial Services",
            "type":"Services"
        }
    ],
    "sg:phone":"+1 217 355 3652",
    "sg:postcode":"61822",
    "sg:province":"IL",
    "sg:tags":[
        "advisory",
        "planner"
    ],
    "wof:name":"Lm Tax & Financial",
    "wof:placetype":"venue"
},
  "geometry": {"coordinates":[-88.313395,40.122498],"type":"Point"}
}