{
  "type": "Feature",
  "properties": {
    "iso:country":"US",
    "sg:address":"1006 Ridge Ave",
    "sg:city":"Greenville",
    "sg:classifiers":[
        {
            "category":"Freight",
            "type":"Transportation"
        }
    ],
    "sg:phone":"+1 618 664 3050",
    "sg:postcode":"62246",
    "sg:province":"IL",
    "sg:tags":[
        "operator",
        "local",
        "trucking"
    ],
    "sg:website":"http://www.ollieoliver.com",
    "wof:name":"Schaefer Trucking",
    "wof:placetype":"venue"
},
  "geometry": {"coordinates":[-89.39852999999999,38.884649],"type":"Point"}
}