{
  "type": "Feature",
  "properties": {
    "iso:country":"US",
    "sg:address":"510 Oak St",
    "sg:city":"Dallas City",
    "sg:classifiers":[
        {
            "category":"Restaurant",
            "type":"Food & Drink"
        }
    ],
    "sg:phone":"+1 217 852 3565",
    "sg:postcode":"62330",
    "sg:province":"IL",
    "wof:name":"Ruthie's Place",
    "wof:placetype":"venue"
},
  "geometry": {"coordinates":[-91.166472,40.634782],"type":"Point"}
}