{
  "type": "Feature",
  "properties": {
    "addr:full":"4524 W Wrightwood Ave Chicago IL 60639",
    "addr:housenumber":"4524",
    "addr:postcode":"60639",
    "addr:street":"W Wrightwood Ave",
    "iso:country":"US",
    "sg:address":"4524 W Wrightwood Ave",
    "sg:city":"Chicago",
    "sg:classifiers":[
        {
            "category":"Home & Garden",
            "subcategory":"Building Materials",
            "type":"Retail Goods"
        },
        {
            "category":"Building & Trades",
            "subcategory":"Construction",
            "type":"Services"
        }
    ],
    "sg:phone":"+1 773 278 3218",
    "sg:postcode":"60639",
    "sg:province":"IL",
    "sg:tags":[
        "concrete",
        "staining",
        "contractor"
    ],
    "wof:name":"Dominick Concrete",
    "wof:placetype":"venue"
},
  "geometry": {"coordinates":[-87.741291,41.9286],"type":"Point"}
}