{
  "type": "Feature",
  "properties": {
    "iso:country":"US",
    "sg:address":"4171 S Archer Ave",
    "sg:city":"Chicago",
    "sg:classifiers":[
        {
            "category":"Restaurant",
            "type":"Food & Drink"
        }
    ],
    "sg:phone":"+1 773 376 1444",
    "sg:postcode":"60632",
    "sg:province":"IL",
    "sg:tags":[
        "mexican"
    ],
    "wof:name":"Mi Taquito",
    "wof:placetype":"venue"
},
  "geometry": {"coordinates":[-87.69828200000001,41.817603],"type":"Point"}
}