{
  "type": "Feature",
  "properties": {
    "iso:country":"US",
    "sg:address":"324 Thistle Dr",
    "sg:city":"Bolingbrook",
    "sg:classifiers":[
        {
            "category":"Professional",
            "subcategory":"Management & Consulting",
            "type":"Services"
        }
    ],
    "sg:phone":"+1 630 759 3962",
    "sg:postcode":"60490",
    "sg:province":"IL",
    "wof:name":"Maritime Safety & Security",
    "wof:placetype":"venue"
},
  "geometry": {"coordinates":[-88.117419,41.686554],"type":"Point"}
}