{
  "type": "Feature",
  "properties": {
    "addr:full":"3946 N Cicero Ave Chicago IL 60641",
    "addr:housenumber":"3946",
    "addr:postcode":"60641",
    "addr:street":"N Cicero Ave",
    "iso:country":"US",
    "sg:address":"3946 N Cicero Ave",
    "sg:city":"Chicago",
    "sg:classifiers":[
        {
            "category":"Health Services",
            "subcategory":"Doctor",
            "type":"Services"
        }
    ],
    "sg:phone":"+1 773 685 1213",
    "sg:postcode":"60641",
    "sg:province":"IL",
    "wof:name":"Geopp I Pineiro DDS",
    "wof:placetype":"venue"
},
  "geometry": {"coordinates":[-87.747343,41.951607],"type":"Point"}
}