{
  "type": "Feature",
  "properties": {
    "addr:full":"3121 W Jackson Blvd Chicago IL 60612",
    "addr:housenumber":"3121",
    "addr:postcode":"60612",
    "addr:street":"W Jackson Blvd",
    "iso:country":"US",
    "sg:address":"3121 W Jackson Blvd",
    "sg:city":"Chicago",
    "sg:classifiers":[
        {
            "category":"Shopping",
            "type":"Retail Goods"
        }
    ],
    "sg:phone":"+1 773 638 0646",
    "sg:postcode":"60612",
    "sg:province":"IL",
    "sg:tags":[
        "religious"
    ],
    "wof:name":"Marian Center",
    "wof:placetype":"venue"
},
  "geometry": {"coordinates":[-87.704041,41.87733],"type":"Point"}
}