{
  "type": "Feature",
  "properties": {
    "iso:country":"US",
    "sg:address":"111 Broadway St",
    "sg:city":"Quincy",
    "sg:classifiers":[
        {
            "category":"Home & Garden",
            "subcategory":"Building Materials",
            "type":"Retail Goods"
        }
    ],
    "sg:phone":"+1 217 223 3054",
    "sg:postcode":"62301",
    "sg:province":"IL",
    "sg:tags":[
        "mixed",
        "concrete"
    ],
    "wof:name":"Gem City Concrete Lic",
    "wof:placetype":"venue"
},
  "geometry": {"coordinates":[-91.413686,39.935889],"type":"Point"}
}