{
  "type": "Feature",
  "properties": {
    "iso:country":"US",
    "sg:address":"23 N Ayer St",
    "sg:city":"Harvard",
    "sg:classifiers":[
        {
            "category":"Personal",
            "subcategory":"Beauty Salon",
            "type":"Services"
        }
    ],
    "sg:phone":"+1 815 943 5856",
    "sg:postcode":"60033",
    "sg:province":"IL",
    "wof:name":"Salon Belleza Morelos",
    "wof:placetype":"venue"
},
  "geometry": {"coordinates":[-88.615736,42.420072],"type":"Point"}
}