{
  "type": "Feature",
  "properties": {
    "iso:country":"US",
    "sg:address":"101 3rd St",
    "sg:city":"Charleston",
    "sg:classifiers":[
        {
            "category":"Organizations",
            "subcategory":"Non-profit Organization",
            "type":"Services"
        }
    ],
    "sg:phone":"+1 217 345 1413",
    "sg:postcode":"61920",
    "sg:province":"IL",
    "sg:tags":[
        "handicapped"
    ],
    "wof:name":"Development Foundations",
    "wof:placetype":"venue"
},
  "geometry": {"coordinates":[-88.179181,39.4978],"type":"Point"}
}