{
  "type": "Feature",
  "properties": {
    "iso:country":"US",
    "sg:address":"5330 N Cumberland Ave",
    "sg:city":"Chicago",
    "sg:classifiers":[
        {
            "category":"Retail",
            "subcategory":"Laundry & Dry Cleaning",
            "type":"Services"
        }
    ],
    "sg:phone":"+1 773 380 0248",
    "sg:postcode":"60656",
    "sg:province":"IL",
    "sg:tags":[
        "garment",
        "agent"
    ],
    "wof:name":"Mystic-Craft Cleaners",
    "wof:placetype":"venue"
},
  "geometry": {"coordinates":[-87.836403,41.976002],"type":"Point"}
}