{
  "type": "Feature",
  "properties": {
    "iso:country":"US",
    "sg:address":"580 Market St",
    "sg:city":"Waukegan",
    "sg:classifiers":[
        {
            "category":"Retail",
            "subcategory":"Auto Repair",
            "type":"Services"
        }
    ],
    "sg:phone":"+1 847 244 8146",
    "sg:postcode":"60085",
    "sg:province":"IL",
    "sg:tags":[
        "automotive"
    ],
    "wof:name":"Montez Towing",
    "wof:placetype":"venue"
},
  "geometry": {"coordinates":[-87.82871400000001,42.353416],"type":"Point"}
}