{
  "type": "Feature",
  "properties": {
    "addr:full":"672 Claridge Cir Schaumburg IL 60194",
    "addr:housenumber":"672",
    "addr:postcode":"60194",
    "addr:street":"Claridge Cir",
    "iso:country":"US",
    "sg:address":"672 Claridge Cir",
    "sg:city":"Schaumburg",
    "sg:classifiers":[
        {
            "category":"Communications",
            "subcategory":"Film & Video Production",
            "type":"Services"
        }
    ],
    "sg:phone":"+1 847 885 8293",
    "sg:postcode":"60194",
    "sg:province":"IL",
    "sg:tags":[
        "motion"
    ],
    "wof:name":"Eisen Video Productions Inc",
    "wof:placetype":"venue"
},
  "geometry": {"coordinates":[-88.105626,42.038335],"type":"Point"}
}