{
  "type": "Feature",
  "properties": {
    "addr:full":"3528 Rotary Rd Rockford IL 61109",
    "addr:housenumber":"3528",
    "addr:postcode":"61109",
    "addr:street":"Rotary Rd",
    "iso:country":"US",
    "sg:address":"3528 Rotary Rd",
    "sg:city":"Rockford",
    "sg:classifiers":[
        {
            "category":"Recreation",
            "type":"Entertainment"
        }
    ],
    "sg:phone":"+1 815 874 5517",
    "sg:postcode":"61109",
    "sg:province":"IL",
    "sg:tags":[
        "stable"
    ],
    "wof:name":"Equestrian Glen Stables",
    "wof:placetype":"venue"
},
  "geometry": {"coordinates":[-89.038043,42.173042],"type":"Point"}
}