{
  "type": "Feature",
  "properties": {
    "addr:full":"5133 W 66th St Chicago IL 60638",
    "addr:housenumber":"5133",
    "addr:postcode":"60638",
    "addr:street":"W 66Th St",
    "iso:country":"US",
    "sg:address":"5133 W 66th St",
    "sg:city":"Chicago",
    "sg:classifiers":[
        {
            "category":"Professional",
            "type":"Services"
        },
        {
            "category":"Manufacturing",
            "subcategory":"Wood Products",
            "type":"Manufacturing & Wholesale Goods"
        },
        {
            "category":"Professional",
            "subcategory":"Business Services",
            "type":"Services"
        },
        {
            "category":"Manufacturing",
            "subcategory":"Paper Products",
            "type":"Manufacturing & Wholesale Goods"
        }
    ],
    "sg:phone":"+1 708 458 7711",
    "sg:postcode":"60638",
    "sg:province":"IL",
    "sg:tags":[
        "fiber-wholesale",
        "fiber",
        "materials-wholesale",
        "labeling",
        "packaging",
        "boxes-corrugated",
        "boxes-folding-manufacturers",
        "manufacturer"
    ],
    "sg:website":"http://www.questcorrugated.com",
    "wof:name":"Questcor",
    "wof:placetype":"venue"
},
  "geometry": {"coordinates":[-87.75072400000001,41.772764],"type":"Point"}
}