{
  "type": "Feature",
  "properties": {
    "iso:country":"US",
    "sg:address":"940 N 2nd St",
    "sg:city":"Chillicothe",
    "sg:classifiers":[
        {
            "category":"Shopping",
            "subcategory":"Hobbies, Toys, & Games",
            "type":"Retail Goods"
        }
    ],
    "sg:phone":"+1 309 274 3928",
    "sg:postcode":"61523",
    "sg:province":"IL",
    "sg:tags":[
        "equipment",
        "ceramic",
        "supply"
    ],
    "wof:name":"Jane's Ceramics",
    "wof:placetype":"venue"
},
  "geometry": {"coordinates":[-89.485449,40.916732],"type":"Point"}
}