{
  "type": "Feature",
  "properties": {
    "iso:country":"US",
    "sg:address":"6367 Prideham St",
    "sg:city":"Downers Grove",
    "sg:classifiers":[
        {
            "category":"Retail",
            "subcategory":"Auto Repair",
            "type":"Services"
        }
    ],
    "sg:phone":"+1 630 964 7019",
    "sg:postcode":"60516",
    "sg:province":"IL",
    "sg:tags":[
        "automotive"
    ],
    "wof:name":"Fabrion Systems West",
    "wof:placetype":"venue"
},
  "geometry": {"coordinates":[-88.02740900000001,41.771702],"type":"Point"}
}