{
  "type": "Feature",
  "properties": {
    "iso:country":"US",
    "sg:address":"210 Lamar Dr",
    "sg:city":"Salem",
    "sg:classifiers":[
        {
            "category":"Building & Trades",
            "subcategory":"Landscaping Services",
            "type":"Services"
        }
    ],
    "sg:phone":"+1 618 548 5381",
    "sg:postcode":"62881",
    "sg:province":"IL",
    "sg:tags":[
        "lawn"
    ],
    "wof:name":"Harrys Landscaping",
    "wof:placetype":"venue"
},
  "geometry": {"coordinates":[-88.970215,38.631978],"type":"Point"}
}