{
  "type": "Feature",
  "properties": {
    "addr:full":"4305 S Archer Ave Chicago IL 60632",
    "addr:housenumber":"4305",
    "addr:postcode":"60632",
    "addr:street":"S Archer Ave",
    "iso:country":"US",
    "sg:address":"4305 S Archer Ave",
    "sg:city":"Chicago",
    "sg:classifiers":[
        {
            "category":"Banks & Credit Unions",
            "subcategory":"Bureau De Change",
            "type":"Services"
        }
    ],
    "sg:phone":"+1 773 927 3160",
    "sg:postcode":"60632",
    "sg:province":"IL",
    "sg:tags":[
        "currency",
        "exchange",
        "broker",
        "foreign"
    ],
    "wof:name":"Remesas Universal",
    "wof:placetype":"venue"
},
  "geometry": {"coordinates":[-87.702191,41.815356],"type":"Point"}
}