{
  "type": "Feature",
  "properties": {
    "addr:full":"50 E Congress Pkwy Chicago IL 60605",
    "addr:housenumber":"50",
    "addr:postcode":"60605",
    "addr:street":"E Congress Pkwy",
    "iso:country":"US",
    "sg:address":"50 E Congress Pkwy",
    "sg:city":"Chicago",
    "sg:classifiers":[
        {
            "category":"Arts & Performance",
            "subcategory":"Arts Center",
            "type":"Entertainment"
        }
    ],
    "sg:postcode":"60605",
    "sg:province":"IL",
    "sg:tags":[
        "performing"
    ],
    "sg:website":"auditoriumtheatre.org/wb/",
    "wof:name":"Fuerza Bruta : Look Up",
    "wof:placetype":"venue"
},
  "geometry": {"coordinates":[-87.62451900000001,41.875702],"type":"Point"}
}