{
  "type": "Feature",
  "properties": {
    "iso:country":"US",
    "sg:address":"88 E Fort St",
    "sg:city":"Farmington",
    "sg:classifiers":[
        {
            "category":"Social Services",
            "type":"Services"
        }
    ],
    "sg:phone":"+1 309 245 4813",
    "sg:postcode":"61531",
    "sg:province":"IL",
    "wof:name":"Tri County Senior Center Inc",
    "wof:placetype":"venue"
},
  "geometry": {"coordinates":[-90.00473100000001,40.698126],"type":"Point"}
}