{
  "type": "Feature",
  "properties": {
    "iso:country":"US",
    "sg:address":"1551 Regency Ct",
    "sg:city":"Calumet City",
    "sg:classifiers":[
        {
            "category":"Manufacturing",
            "subcategory":"Printing",
            "type":"Manufacturing & Wholesale Goods"
        }
    ],
    "sg:phone":"+1 708 868 7100",
    "sg:postcode":"60409",
    "sg:province":"IL",
    "sg:tags":[
        "professional",
        "book",
        "m",
        "equipment"
    ],
    "wof:name":"Urban Ministries Inc",
    "wof:placetype":"venue"
},
  "geometry": {"coordinates":[-87.564049,41.590857],"type":"Point"}
}