{
  "type": "Feature",
  "properties": {
    "iso:country":"US",
    "sg:address":"427 Creve Coeur St",
    "sg:city":"La Salle",
    "sg:classifiers":[
        {
            "category":"Bars & Pubs",
            "type":"Food & Drink"
        }
    ],
    "sg:phone":"+1   ",
    "sg:postcode":"61301",
    "sg:province":"IL",
    "sg:tags":[
        "drinking",
        "eating"
    ],
    "wof:name":"Papa Murphys",
    "wof:placetype":"venue"
},
  "geometry": {"coordinates":[-89.102982,41.330836],"type":"Point"}
}