{
  "type": "Feature",
  "properties": {
    "iso:country":"US",
    "sg:address":"104 S Memorial St",
    "sg:city":"Pittsfield",
    "sg:classifiers":[
        {
            "category":"Organizations",
            "subcategory":"Religious Organization",
            "type":"Services"
        }
    ],
    "sg:phone":"+1 217 285 2237",
    "sg:postcode":"62363",
    "sg:province":"IL",
    "wof:name":"First Baptist Church GARB",
    "wof:placetype":"venue"
},
  "geometry": {"coordinates":[-90.807485,39.606722],"type":"Point"}
}