{
  "type": "Feature",
  "properties": {
    "iso:country":"US",
    "sg:address":"453 Kenilworth Ave",
    "sg:city":"Glen Ellyn",
    "sg:classifiers":[
        {
            "category":"Travel",
            "subcategory":"Hotels & Motels",
            "type":"Entertainment"
        }
    ],
    "sg:phone":"+1 630 545 0505",
    "sg:postcode":"60137",
    "sg:province":"IL",
    "wof:name":"Courtyard of Glen Ellyn Llc",
    "wof:placetype":"venue"
},
  "geometry": {"coordinates":[-88.078352,41.874818],"type":"Point"}
}