{
  "type": "Feature",
  "properties": {
    "iso:country":"US",
    "sg:address":"4747 W 19th St",
    "sg:city":"Cicero",
    "sg:classifiers":[
        {
            "category":"Health Services",
            "subcategory":"Nursing And Care Facility",
            "type":"Services"
        }
    ],
    "sg:phone":"+1 708 656 1515",
    "sg:postcode":"60804",
    "sg:province":"IL",
    "wof:name":"Golden Age Retirement Home",
    "wof:placetype":"venue"
},
  "geometry": {"coordinates":[-87.743361,41.854875],"type":"Point"}
}