{
  "type": "Feature",
  "properties": {
    "addr:full":"4747 W 19th St Cicero IL 60804",
    "addr:housenumber":"4747",
    "addr:postcode":"60804",
    "addr:street":"W 19Th St",
    "iso:country":"US",
    "sg:address":"4747 W 19th St",
    "sg:city":"Cicero",
    "sg:classifiers":[
        {
            "category":"Health Services",
            "subcategory":"Nursing And Care Facility",
            "type":"Services"
        }
    ],
    "sg:phone":"+1 708 656 1515",
    "sg:postcode":"60804",
    "sg:province":"IL",
    "wof:name":"Golden Age Retirement Home",
    "wof:placetype":"venue"
},
  "geometry": {"coordinates":[-87.74336099999999,41.854875],"type":"Point"}
}