{
  "type": "Feature",
  "properties": {
    "addr:full":"1509 Clear Dr Bolingbrook IL 60490",
    "addr:housenumber":"1509",
    "addr:postcode":"60490",
    "addr:street":"Clear Dr",
    "iso:country":"US",
    "sg:address":"1509 Clear Dr",
    "sg:city":"Bolingbrook",
    "sg:classifiers":[
        {
            "category":"Building & Trades",
            "subcategory":"Construction",
            "type":"Services"
        }
    ],
    "sg:phone":"+1 630 759 0583",
    "sg:postcode":"60490",
    "sg:province":"IL",
    "sg:tags":[
        "contractor"
    ],
    "wof:name":"Clowes Cox Plastering",
    "wof:placetype":"venue"
},
  "geometry": {"coordinates":[-88.136259,41.696501],"type":"Point"}
}