{
  "type": "Feature",
  "properties": {
    "iso:country":"US",
    "sg:address":"2114 S Cicero Ave",
    "sg:city":"Cicero",
    "sg:classifiers":[
        {
            "category":"Shopping",
            "subcategory":"Florist",
            "type":"Retail Goods"
        }
    ],
    "sg:phone":"+1 708 652 4532",
    "sg:postcode":"60804",
    "sg:province":"IL",
    "wof:name":"Lilliana's Flowers & Lace",
    "wof:placetype":"venue"
},
  "geometry": {"coordinates":[-87.74430099999999,41.852699],"type":"Point"}
}