{
  "type": "Feature",
  "properties": {
    "addr:full":"955 N Ashland Ave Chicago IL 60622",
    "addr:housenumber":"955",
    "addr:postcode":"60622",
    "addr:street":"N Ashland Ave",
    "iso:country":"US",
    "sg:address":"955 N Ashland Ave",
    "sg:city":"Chicago",
    "sg:classifiers":[
        {
            "category":"Personal",
            "subcategory":"Day Spa",
            "type":"Services"
        }
    ],
    "sg:phone":"+1 773 276 0606",
    "sg:postcode":"60622",
    "sg:province":"IL",
    "wof:name":"Rose's Spa",
    "wof:placetype":"venue"
},
  "geometry": {"coordinates":[-87.667159,41.899133],"type":"Point"}
}