{
  "type": "Feature",
  "properties": {
    "addr:full":"728 Florsheim Dr Libertyville IL 60048",
    "addr:housenumber":"728",
    "addr:postcode":"60048",
    "addr:street":"Florsheim Dr",
    "iso:country":"US",
    "sg:address":"728 Florsheim Dr",
    "sg:city":"Libertyville",
    "sg:classifiers":[
        {
            "category":"Professional",
            "subcategory":"Lawyer & Legal Services",
            "type":"Services"
        }
    ],
    "sg:phone":"+1 847 680 7240",
    "sg:postcode":"60048",
    "sg:province":"IL",
    "sg:tags":[
        "attorney"
    ],
    "wof:name":"Patrick J Hart CPA",
    "wof:placetype":"venue"
},
  "geometry": {"coordinates":[-87.943202,42.25873],"type":"Point"}
}