{
  "type": "Feature",
  "properties": {
    "iso:country":"US",
    "sg:address":"601 1st St",
    "sg:city":"La Salle",
    "sg:classifiers":[
        {
            "category":"Restaurant",
            "type":"Food & Drink"
        }
    ],
    "sg:phone":"+1 815 224 4545",
    "sg:postcode":"61301",
    "sg:province":"IL",
    "sg:website":"www.uptowngrill.com",
    "wof:name":"Uptown",
    "wof:placetype":"venue"
},
  "geometry": {"coordinates":[-89.095411,41.328096],"type":"Point"}
}