{
  "type": "Feature",
  "properties": {
    "addr:full":"4316 175th Pl Country Club Hills IL 60478",
    "addr:housenumber":"4316",
    "addr:postcode":"60478",
    "addr:street":"175Th Pl",
    "iso:country":"US",
    "sg:address":"4316 175th Pl",
    "sg:city":"Country Club Hills",
    "sg:classifiers":[
        {
            "category":"Retail",
            "subcategory":"Laundry & Dry Cleaning",
            "type":"Services"
        }
    ],
    "sg:phone":"+1 708 799 9220",
    "sg:postcode":"60478",
    "sg:province":"IL",
    "sg:tags":[
        "garment",
        "agent"
    ],
    "wof:name":"Neighbor Hood Cleaners",
    "wof:placetype":"venue"
},
  "geometry": {"coordinates":[-87.720356,41.571133],"type":"Point"}
}