{
  "type": "Feature",
  "properties": {
    "addr:full":"620 Dean Ct Canton IL 61520",
    "addr:housenumber":"620",
    "addr:postcode":"61520",
    "addr:street":"Dean Ct",
    "iso:country":"US",
    "sg:address":"620 Dean Ct",
    "sg:city":"Canton",
    "sg:classifiers":[
        {
            "category":"Recreation",
            "type":"Entertainment"
        }
    ],
    "sg:phone":"+1 309 647 0543",
    "sg:postcode":"61520",
    "sg:province":"IL",
    "sg:tags":[
        "club",
        "membership"
    ],
    "wof:name":"Elmwood Trap Club Inc",
    "wof:placetype":"venue"
},
  "geometry": {"coordinates":[-90.027012,40.561588],"type":"Point"}
}