{
  "type": "Feature",
  "properties": {
    "iso:country":"US",
    "sg:address":"27W132 Barnes St",
    "sg:city":"Winfield",
    "sg:classifiers":[
        {
            "category":"Health Services",
            "subcategory":"Doctor",
            "type":"Services"
        }
    ],
    "sg:phone":"+1 630 665 6307",
    "sg:postcode":"60190",
    "sg:province":"IL",
    "sg:tags":[
        "medicine",
        "physician",
        "practice",
        "surgeons",
        "family"
    ],
    "wof:name":"Johnson Medical Services",
    "wof:placetype":"venue"
},
  "geometry": {"coordinates":[-88.15800900000001,41.872118],"type":"Point"}
}