{
  "type": "Feature",
  "properties": {
    "iso:country":"US",
    "sg:address":"9119 S Exchange Ave",
    "sg:city":"Chicago",
    "sg:classifiers":[
        {
            "category":"Community Center",
            "type":"Public Place"
        }
    ],
    "sg:phone":"+1 773 768 1327",
    "sg:postcode":"60617",
    "sg:province":"IL",
    "sg:tags":[
        "medical"
    ],
    "wof:name":"Claretian Medical Center",
    "wof:placetype":"venue"
},
  "geometry": {"coordinates":[-87.552498,41.729801],"type":"Point"}
}