{
  "type": "Feature",
  "properties": {
    "addr:full":"7303 S Madison St Hinsdale IL 60521",
    "addr:housenumber":"7303",
    "addr:postcode":"60521",
    "addr:street":"S Madison St",
    "iso:country":"US",
    "sg:address":"7303 S Madison St",
    "sg:city":"Hinsdale",
    "sg:classifiers":[
        {
            "category":"Building & Trades",
            "subcategory":"Construction",
            "type":"Services"
        }
    ],
    "sg:phone":"+1 630 325 7473",
    "sg:postcode":"60521",
    "sg:province":"IL",
    "sg:tags":[
        "altering",
        "roofing",
        "contractor",
        "remodeling",
        "consultant"
    ],
    "wof:name":"Act Now Roofing",
    "wof:placetype":"venue"
},
  "geometry": {"coordinates":[-87.936058,41.781544],"type":"Point"}
}