{
  "type": "Feature",
  "properties": {
    "iso:country":"US",
    "sg:address":"1936 11th St",
    "sg:city":"Rockford",
    "sg:classifiers":[
        {
            "category":"Wholesale",
            "subcategory":"Machinery & Supplies",
            "type":"Manufacturing & Wholesale Goods"
        }
    ],
    "sg:phone":"+1 815 962 6338",
    "sg:postcode":"61104",
    "sg:province":"IL",
    "sg:tags":[
        "industrial",
        "equipment",
        "used",
        "machinery-new",
        "supplies-wholesale"
    ],
    "wof:name":"Ctc Corporation",
    "wof:placetype":"venue"
},
  "geometry": {"coordinates":[-89.07218399999999,42.247489],"type":"Point"}
}