{
  "type": "Feature",
  "properties": {
    "iso:country":"US",
    "sg:address":"9250 State Rte 33",
    "sg:city":"Shumway",
    "sg:classifiers":[
        {
            "category":"Manufacturing",
            "subcategory":"Printing",
            "type":"Manufacturing & Wholesale Goods"
        }
    ],
    "sg:phone":"+1 217 868 5911",
    "sg:postcode":"62461",
    "sg:province":"IL",
    "sg:tags":[
        "lithographic",
        "commercial"
    ],
    "wof:name":"Effingham Business Cards",
    "wof:placetype":"venue"
},
  "geometry": {"coordinates":[-88.634326,39.169925],"type":"Point"}
}