{
  "type": "Feature",
  "properties": {
    "iso:country":"US",
    "sg:address":"246 E Dean St",
    "sg:city":"Virden",
    "sg:classifiers":[
        {
            "category":"Manufacturing",
            "subcategory":"Printing",
            "type":"Manufacturing & Wholesale Goods"
        }
    ],
    "sg:phone":"+1 217 965 5885",
    "sg:postcode":"62690",
    "sg:province":"IL",
    "sg:tags":[
        "bookbinder"
    ],
    "wof:name":"Master Engraving",
    "wof:placetype":"venue"
},
  "geometry": {"coordinates":[-89.765933,39.500163],"type":"Point"}
}