{
  "type": "Feature",
  "properties": {
    "iso:country":"US",
    "sg:address":"1870 N Dayton St",
    "sg:city":"Chicago",
    "sg:classifiers":[
        {
            "category":"Wholesale",
            "subcategory":"Furniture",
            "type":"Manufacturing & Wholesale Goods"
        }
    ],
    "sg:phone":"+1 312 944 7153",
    "sg:postcode":"60614",
    "sg:province":"IL",
    "sg:tags":[
        "beds-wholesale",
        "manufacturer"
    ],
    "wof:name":"Annie S Lincoln Park Bed And Breakfast",
    "wof:placetype":"venue"
},
  "geometry": {"coordinates":[-87.64961700000001,41.915383],"type":"Point"}
}