{
  "type": "Feature",
  "properties": {
    "addr:full":"1150 W Diversey Parkway Chicago IL 60614",
    "addr:housenumber":"1150",
    "addr:postcode":"60614",
    "addr:street":"W Diversey Parkway",
    "iso:country":"US",
    "sg:address":"1150 W Diversey Parkway",
    "sg:city":"Chicago",
    "sg:classifiers":[
        {
            "category":"Personal",
            "subcategory":"Beauty Salon",
            "type":"Services"
        },
        {
            "category":"Personal",
            "subcategory":"Hair Removal",
            "type":"Services"
        }
    ],
    "sg:phone":"+1 773 472 8102",
    "sg:postcode":"60614",
    "sg:province":"IL",
    "wof:name":"Lynn's Hair & Spa",
    "wof:placetype":"venue"
},
  "geometry": {"coordinates":[-87.658283,41.932681],"type":"Point"}
}