{
  "type": "Feature",
  "properties": {
    "addr:full":"7447 W Talcott Ave Ste 225 Chicago IL 60631",
    "addr:housenumber":"7447",
    "addr:postcode":"60631",
    "addr:street":"W Talcott Ave Ste 225",
    "iso:country":"US",
    "sg:address":"7447 W Talcott Ave Ste 225",
    "sg:city":"Chicago",
    "sg:classifiers":[
        {
            "category":"Health Services",
            "subcategory":"Doctor",
            "type":"Services"
        }
    ],
    "sg:phone":"+1 773 763 2204",
    "sg:postcode":"60631",
    "sg:province":"IL",
    "sg:tags":[
        "throat",
        "ear",
        "nose"
    ],
    "wof:name":"Schier Leslie K MD",
    "wof:placetype":"venue"
},
  "geometry": {"coordinates":[-87.813402,41.988913],"type":"Point"}
}