{
  "type": "Feature",
  "properties": {
    "addr:full":"11 S Lasalle St Ste 1100 Chicago IL 60603",
    "addr:housenumber":"11",
    "addr:postcode":"60603",
    "addr:street":"S Lasalle St Ste 1100",
    "iso:country":"US",
    "sg:address":"11 S Lasalle St Ste 1100",
    "sg:city":"Chicago",
    "sg:classifiers":[
        {
            "category":"Professional",
            "subcategory":"Employment Agencies",
            "type":"Services"
        }
    ],
    "sg:phone":"+1 312 566 0420",
    "sg:postcode":"60603",
    "sg:province":"IL",
    "sg:website":"www.todays.com",
    "wof:name":"Today's Office Professionals",
    "wof:placetype":"venue"
},
  "geometry": {"coordinates":[-87.625502,41.880995],"type":"Point"}
}