{
  "type": "Feature",
  "properties": {
    "addr:full":"Jameson Realty Group 425 W North Ave Chicago IL 60610",
    "addr:housenumber":"425",
    "addr:postcode":"60610",
    "addr:street":"W North Ave",
    "iso:country":"US",
    "sg:address":"Jameson Realty Group 425 W North Ave",
    "sg:city":"Chicago",
    "sg:classifiers":[
        {
            "category":"Real Estate",
            "subcategory":"Real Estate Services",
            "type":"Services"
        },
        {
            "category":"Real Estate",
            "subcategory":"Real Estate Agent",
            "type":"Services"
        }
    ],
    "sg:phone":"+1 312 867 2042",
    "sg:postcode":"60610",
    "sg:province":"IL",
    "sg:website":"www.kimkorber.com",
    "wof:name":"Kim Korber",
    "wof:placetype":"venue"
},
  "geometry": {"coordinates":[-87.63973799999999,41.910944],"type":"Point"}
}