{
  "type": "Feature",
  "properties": {
    "iso:country":"US",
    "sg:address":"202 E 6th St",
    "sg:city":"Staunton",
    "sg:classifiers":[
        {
            "category":"Railroad",
            "type":"Transportation"
        }
    ],
    "sg:phone":"+1 618 635 2554",
    "sg:postcode":"62088",
    "sg:province":"IL",
    "wof:name":"Norfolk Southern Railway Co",
    "wof:placetype":"venue"
},
  "geometry": {"coordinates":[-89.785601,39.005743],"type":"Point"}
}