{
  "type": "Feature",
  "properties": {
    "iso:country":"US",
    "sg:address":"345 N Rand Rd",
    "sg:city":"Lake Zurich",
    "sg:classifiers":[
        {
            "category":"Banks & Credit Unions",
            "subcategory":"Bank",
            "type":"Services"
        }
    ],
    "sg:phone":"+1 847 550 1130",
    "sg:postcode":"60047",
    "sg:province":"IL",
    "wof:name":"Bank One",
    "wof:placetype":"venue"
},
  "geometry": {"coordinates":[-88.10767800000001,42.191229],"type":"Point"}
}