{
  "type": "Feature",
  "properties": {
    "addr:full":"222 1st Ave Rochelle IL 61068",
    "addr:housenumber":"222",
    "addr:postcode":"61068",
    "addr:street":"1St Ave",
    "iso:country":"US",
    "sg:address":"222 1st Ave",
    "sg:city":"Rochelle",
    "sg:classifiers":[
        {
            "category":"Organizations",
            "subcategory":"Religious Organization",
            "type":"Services"
        }
    ],
    "sg:phone":"+1 815 562 6821",
    "sg:postcode":"61068",
    "sg:province":"IL",
    "sg:tags":[
        "church"
    ],
    "wof:name":"Church Of God",
    "wof:placetype":"venue"
},
  "geometry": {"coordinates":[-89.062437,41.919467],"type":"Point"}
}