{
  "type": "Feature",
  "properties": {
    "iso:country":"US",
    "sg:address":"1525 E 53rd St #803",
    "sg:city":"Chicago",
    "sg:classifiers":[
        {
            "category":"Insurance",
            "subcategory":"Insurance Agent",
            "type":"Services"
        },
        {
            "category":"Insurance",
            "subcategory":"Hazard Insurance",
            "type":"Services"
        },
        {
            "category":"Insurance",
            "subcategory":"Title Insurance",
            "type":"Services"
        },
        {
            "category":"Insurance",
            "subcategory":"Life Insurance",
            "type":"Services"
        }
    ],
    "sg:phone":"+1 773 752 5224",
    "sg:postcode":"60615",
    "sg:province":"IL",
    "sg:tags":[
        "auto",
        "commercial",
        "business",
        "homeowner"
    ],
    "sg:website":"http://www.farmersagent.com/phill/",
    "wof:name":"Patricia A Hill - Farmers Insurance",
    "wof:placetype":"venue"
},
  "geometry": {"coordinates":[-87.58802300000001,41.799558],"type":"Point"}
}