{
  "type": "Feature",
  "properties": {
    "iso:country":"US",
    "sg:address":"13252 Bittersweet Ln",
    "sg:city":"Huntley",
    "sg:classifiers":[
        {
            "category":"Wholesale",
            "subcategory":"Office Equipment",
            "type":"Manufacturing & Wholesale Goods"
        },
        {
            "category":"Shopping",
            "subcategory":"Computers & Home Electronics",
            "type":"Retail Goods"
        },
        {
            "category":"Professional",
            "subcategory":"Printing & Photocopies",
            "type":"Services"
        }
    ],
    "sg:phone":"+1 847 298 2555",
    "sg:postcode":"60142",
    "sg:province":"IL",
    "sg:tags":[
        "scanning",
        "printer",
        "supply",
        "duplicating",
        "copying",
        "plotting"
    ],
    "sg:website":"http://www.insty-prints.com",
    "wof:name":"Insty-Prints",
    "wof:placetype":"venue"
},
  "geometry": {"coordinates":[-88.454081,42.154961],"type":"Point"}
}