{
  "type": "Feature",
  "properties": {
    "iso:country":"US",
    "sg:address":"5739 N Meridian Rd",
    "sg:city":"Rockford",
    "sg:classifiers":[
        {
            "category":"Freight",
            "type":"Transportation"
        }
    ],
    "sg:phone":"+1 815 961 9671",
    "sg:postcode":"61101",
    "sg:province":"IL",
    "sg:tags":[
        "arrangement"
    ],
    "wof:name":"Myers Auto Transport",
    "wof:placetype":"venue"
},
  "geometry": {"coordinates":[-89.173973,42.338715],"type":"Point"}
}