{
  "type": "Feature",
  "properties": {
    "addr:full":"7205 S Stony Island Ave Chicago IL 60649",
    "addr:housenumber":"7205",
    "addr:postcode":"60649",
    "addr:street":"S Stony Island Ave",
    "iso:country":"US",
    "sg:address":"7205 S Stony Island Ave",
    "sg:city":"Chicago",
    "sg:classifiers":[
        {
            "category":"Retail",
            "subcategory":"Funeral Services",
            "type":"Services"
        }
    ],
    "sg:phone":"+1 773 288 7110",
    "sg:postcode":"60649",
    "sg:province":"IL",
    "sg:tags":[
        "parlor"
    ],
    "wof:name":"Progressive Funeral Parlor",
    "wof:placetype":"venue"
},
  "geometry": {"coordinates":[-87.586181,41.763402],"type":"Point"}
}