{
  "type": "Feature",
  "properties": {
    "addr:full":"108 S Timber St Knoxville IL 61448",
    "addr:housenumber":"108",
    "addr:postcode":"61448",
    "addr:street":"S Timber St",
    "iso:country":"US",
    "sg:address":"108 S Timber St",
    "sg:city":"Knoxville",
    "sg:classifiers":[
        {
            "category":"Organizations",
            "subcategory":"Religious Organization",
            "type":"Services"
        }
    ],
    "sg:phone":"+1 309 289 4664",
    "sg:postcode":"61448",
    "sg:province":"IL",
    "sg:tags":[
        "lutheran",
        "church"
    ],
    "wof:name":"Grace Lutheran Church",
    "wof:placetype":"venue"
},
  "geometry": {"coordinates":[-90.283584,40.907933],"type":"Point"}
}