{
  "type": "Feature",
  "properties": {
    "iso:country":"US",
    "sg:address":"7799 E Countryside Ln",
    "sg:city":"Claremont",
    "sg:classifiers":[
        {
            "category":"Professional",
            "subcategory":"Business Services",
            "type":"Services"
        }
    ],
    "sg:phone":"+1 618 869 2610",
    "sg:postcode":"62421",
    "sg:province":"IL",
    "sg:tags":[
        "consultant",
        "coach"
    ],
    "wof:name":"Donna Henry",
    "wof:placetype":"venue"
},
  "geometry": {"coordinates":[-87.937622,38.673111],"type":"Point"}
}