{
  "type": "Feature",
  "properties": {
    "addr:full":"1348 N Hamlin Ave Chicago IL 60651",
    "addr:housenumber":"1348",
    "addr:postcode":"60651",
    "addr:street":"N Hamlin Ave",
    "iso:country":"US",
    "sg:address":"1348 N Hamlin Ave",
    "sg:city":"Chicago",
    "sg:classifiers":[
        {
            "category":"Retail",
            "subcategory":"Laundry & Dry Cleaning",
            "type":"Services"
        }
    ],
    "sg:phone":"+1 773 278 3399",
    "sg:postcode":"60651",
    "sg:province":"IL",
    "sg:tags":[
        "cleaner",
        "rug",
        "carpet"
    ],
    "wof:name":"A & A Carpet Cleaning",
    "wof:placetype":"venue"
},
  "geometry": {"coordinates":[-87.72148799999999,41.905063],"type":"Point"}
}