{
  "type": "Feature",
  "properties": {
    "iso:country":"US",
    "sg:address":"1405 W Park St Ste 200",
    "sg:city":"Urbana",
    "sg:classifiers":[
        {
            "category":"Health Services",
            "subcategory":"Doctor",
            "type":"Services"
        }
    ],
    "sg:phone":"+1 217 384 8080",
    "sg:postcode":"61801",
    "sg:province":"IL",
    "sg:tags":[
        "medicine",
        "sport",
        "orthopedist"
    ],
    "wof:name":"Orthopedic Associates of Kankakee S C",
    "wof:placetype":"venue"
},
  "geometry": {"coordinates":[-88.226997,40.117298],"type":"Point"}
}