{
  "type": "Feature",
  "properties": {
    "iso:country":"US",
    "sg:address":"5411 E State St",
    "sg:city":"Rockford",
    "sg:classifiers":[
        {
            "category":"Banks & Credit Unions",
            "subcategory":"Bank",
            "type":"Services"
        }
    ],
    "sg:phone":"+1 815 398 8880",
    "sg:postcode":"61108",
    "sg:province":"IL",
    "sg:tags":[
        "loan",
        "real estate"
    ],
    "wof:name":"Prime Financial Group",
    "wof:placetype":"venue"
},
  "geometry": {"coordinates":[-89.00981,42.265211],"type":"Point"}
}