{
  "type": "Feature",
  "properties": {
    "addr:full":"235 Surrey Ln Lake Forest IL 60045",
    "addr:housenumber":"235",
    "addr:postcode":"60045",
    "addr:street":"Surrey Ln",
    "iso:country":"US",
    "sg:address":"235 Surrey Ln",
    "sg:city":"Lake Forest",
    "sg:classifiers":[
        {
            "category":"Wholesale",
            "subcategory":"Electrical",
            "type":"Manufacturing & Wholesale Goods"
        }
    ],
    "sg:phone":"+1 847 735 8701",
    "sg:postcode":"60045",
    "sg:province":"IL",
    "sg:tags":[
        "sound",
        "equipment",
        "system"
    ],
    "wof:name":"Leslie's",
    "wof:placetype":"venue"
},
  "geometry": {"coordinates":[-87.904507,42.205932],"type":"Point"}
}