{
  "type": "Feature",
  "properties": {
    "iso:country":"US",
    "sg:address":"952 S Arthur Ave",
    "sg:city":"Arlington Heights",
    "sg:classifiers":[
        {
            "category":"Restaurant",
            "type":"Food & Drink"
        }
    ],
    "sg:phone":"+1   ",
    "sg:postcode":"60005",
    "sg:province":"IL",
    "sg:tags":[
        "eating"
    ],
    "wof:name":"Joe & Giuseppe Inc",
    "wof:placetype":"venue"
},
  "geometry": {"coordinates":[-87.966143,42.073602],"type":"Point"}
}