{
  "type": "Feature",
  "properties": {
    "addr:full":"800 Carlow Dr Des Plaines IL 60016",
    "addr:housenumber":"800",
    "addr:postcode":"60016",
    "addr:street":"Carlow Dr",
    "iso:country":"US",
    "sg:address":"800 Carlow Dr",
    "sg:city":"Des Plaines",
    "sg:classifiers":[
        {
            "category":"Wholesale",
            "subcategory":"Construction Materials",
            "type":"Manufacturing & Wholesale Goods"
        },
        {
            "category":"Building & Trades",
            "subcategory":"Construction",
            "type":"Services"
        }
    ],
    "sg:phone":"+1 847 299 3550",
    "sg:postcode":"60016",
    "sg:province":"IL",
    "sg:tags":[
        "house",
        "fence"
    ],
    "wof:name":"Fence Depot & Home Improvement",
    "wof:placetype":"venue"
},
  "geometry": {"coordinates":[-87.901808,42.066735],"type":"Point"}
}