{
  "type": "Feature",
  "properties": {
    "iso:country":"US",
    "sg:address":"2452 Maple Rd",
    "sg:city":"Homewood",
    "sg:classifiers":[
        {
            "category":"Building & Trades",
            "subcategory":"Construction",
            "type":"Services"
        }
    ],
    "sg:phone":"+1 708 647 8546",
    "sg:postcode":"60430",
    "sg:province":"IL",
    "sg:tags":[
        "general",
        "contractor"
    ],
    "wof:name":"A & R Contractors",
    "wof:placetype":"venue"
},
  "geometry": {"coordinates":[-87.676702,41.56823],"type":"Point"}
}