{
  "type": "Feature",
  "properties": {
    "iso:country":"US",
    "sg:address":"612 Jackson Ave",
    "sg:city":"Charleston",
    "sg:classifiers":[
        {
            "category":"Real Estate",
            "subcategory":"Architect",
            "type":"Services"
        }
    ],
    "sg:phone":"+1 217 348 8813",
    "sg:postcode":"61920",
    "sg:province":"IL",
    "wof:name":"Vikas Architects Engineers",
    "wof:placetype":"venue"
},
  "geometry": {"coordinates":[-88.174615,39.494495],"type":"Point"}
}