{
  "type": "Feature",
  "properties": {
    "addr:full":"7752 Milan Way Gurnee IL 60031",
    "addr:housenumber":"7752",
    "addr:postcode":"60031",
    "addr:street":"Milan Way",
    "iso:country":"US",
    "sg:address":"7752 Milan Way",
    "sg:city":"Gurnee",
    "sg:classifiers":[
        {
            "category":"Shopping",
            "subcategory":"Clothing, Apparel, & Fashions",
            "type":"Retail Goods"
        }
    ],
    "sg:phone":"+1 847 548 0479",
    "sg:postcode":"60031",
    "sg:province":"IL",
    "sg:tags":[
        "clothing",
        "store"
    ],
    "wof:name":"X-Treme Value",
    "wof:placetype":"venue"
},
  "geometry": {"coordinates":[-87.995002,42.365872],"type":"Point"}
}