{
  "type": "Feature",
  "properties": {
    "addr:full":"601 W Division St Altamont IL 62411",
    "addr:housenumber":"601",
    "addr:postcode":"62411",
    "addr:street":"W Division St",
    "iso:country":"US",
    "sg:address":"601 W Division St",
    "sg:city":"Altamont",
    "sg:classifiers":[
        {
            "category":"Freight",
            "type":"Transportation"
        }
    ],
    "sg:phone":"+1 618 483 6171",
    "sg:postcode":"62411",
    "sg:province":"IL",
    "sg:tags":[
        "grain",
        "elevator"
    ],
    "wof:name":"Adm Grain",
    "wof:placetype":"venue"
},
  "geometry": {"coordinates":[-88.753435,39.059584],"type":"Point"}
}