{
  "type": "Feature",
  "properties": {
    "iso:country":"US",
    "sg:address":"7124 Windsor Lake Pkwy",
    "sg:city":"Loves Park",
    "sg:classifiers":[
        {
            "category":"Professional",
            "subcategory":"Accounting & Tax Preparation",
            "type":"Services"
        }
    ],
    "sg:phone":"+1 815 633 7660",
    "sg:postcode":"61111",
    "sg:province":"IL",
    "sg:tags":[
        "return",
        "filing"
    ],
    "wof:name":"J L Tax Svc",
    "wof:placetype":"venue"
},
  "geometry": {"coordinates":[-89.034281,42.327643],"type":"Point"}
}