{
  "type": "Feature",
  "properties": {
    "addr:full":"2030 E 71st Street Chicago IL 60649",
    "addr:housenumber":"2030",
    "addr:postcode":"60649",
    "addr:street":"E 71St Street",
    "iso:country":"US",
    "sg:address":"2030 E 71st Street",
    "sg:city":"Chicago",
    "sg:classifiers":[
        {
            "category":"Shopping",
            "subcategory":"Shoes",
            "type":"Retail Goods"
        }
    ],
    "sg:phone":"+1 773 667 9680",
    "sg:postcode":"60649",
    "sg:province":"IL",
    "sg:tags":[
        "store"
    ],
    "wof:name":"Shoetime",
    "wof:placetype":"venue"
},
  "geometry": {"coordinates":[-87.57525,41.766128],"type":"Point"}
}