{
  "type": "Feature",
  "properties": {
    "iso:country":"US",
    "sg:address":"3423 N Milwaukee Ave",
    "sg:city":"Chicago",
    "sg:classifiers":[
        {
            "category":"Building & Trades",
            "subcategory":"Construction",
            "type":"Services"
        }
    ],
    "sg:phone":"+1 773 286 9183",
    "sg:postcode":"60641",
    "sg:province":"IL",
    "sg:tags":[
        "carpentry",
        "contractor"
    ],
    "wof:name":"Will Products",
    "wof:placetype":"venue"
},
  "geometry": {"coordinates":[-87.730712,41.9433],"type":"Point"}
}