{
  "type": "Feature",
  "properties": {
    "iso:country":"US",
    "sg:address":"5 Charles Ct",
    "sg:city":"Buffalo Grove",
    "sg:classifiers":[
        {
            "category":"Professional",
            "subcategory":"Lawyer & Legal Services",
            "type":"Services"
        }
    ],
    "sg:phone":"+1 847 229 1107",
    "sg:postcode":"60089",
    "sg:province":"IL",
    "wof:name":"Mueller & Associates",
    "wof:placetype":"venue"
},
  "geometry": {"coordinates":[-87.952316,42.133159],"type":"Point"}
}