{
  "type": "Feature",
  "properties": {
    "addr:full":"715 S Claremont Ave Chicago IL 60612",
    "addr:housenumber":"715",
    "addr:postcode":"60612",
    "addr:street":"S Claremont Ave",
    "iso:country":"US",
    "sg:address":"715 S Claremont Ave",
    "sg:city":"Chicago",
    "sg:classifiers":[
        {
            "category":"Manufacturing",
            "subcategory":"Electronics",
            "type":"Manufacturing & Wholesale Goods"
        }
    ],
    "sg:phone":"+1 312 491 9910",
    "sg:postcode":"60612",
    "sg:province":"IL",
    "sg:tags":[
        "printers-equipment",
        "supply"
    ],
    "wof:name":"Mrp Group",
    "wof:placetype":"venue"
},
  "geometry": {"coordinates":[-87.68498099999999,41.87279],"type":"Point"}
}