{
  "type": "Feature",
  "properties": {
    "iso:country":"US",
    "sg:address":"600 Tollgate Rd",
    "sg:city":"Elgin",
    "sg:classifiers":[
        {
            "category":"Insurance",
            "subcategory":"Insurance Agent",
            "type":"Services"
        }
    ],
    "sg:phone":"+1 847 531 5417",
    "sg:postcode":"60123",
    "sg:province":"IL",
    "wof:name":"Auto-Owners Insurance Co",
    "wof:placetype":"venue"
},
  "geometry": {"coordinates":[-88.29367999999999,42.070949],"type":"Point"}
}