{
  "type": "Feature",
  "properties": {
    "iso:country":"US",
    "sg:address":"922 23rd Ave",
    "sg:city":"Moline",
    "sg:classifiers":[
        {
            "category":"Health Services",
            "subcategory":"Doctor",
            "type":"Services"
        }
    ],
    "sg:phone":"+1 309 762 2922",
    "sg:postcode":"61265",
    "sg:province":"IL",
    "sg:tags":[
        "medical"
    ],
    "wof:name":"Kirk Witherspoon PHD",
    "wof:placetype":"venue"
},
  "geometry": {"coordinates":[-90.522815,41.489565],"type":"Point"}
}