{
  "type": "Feature",
  "properties": {
    "iso:country":"US",
    "sg:address":"38654 N Green Bay Rd",
    "sg:city":"Beach Park",
    "sg:classifiers":[
        {
            "category":"Building & Trades",
            "subcategory":"Landscaping Services",
            "type":"Services"
        }
    ],
    "sg:phone":"+1 847 662 0456",
    "sg:postcode":"60087",
    "sg:province":"IL",
    "sg:tags":[
        "landscape",
        "contractor"
    ],
    "wof:name":"Colin Landscaping",
    "wof:placetype":"venue"
},
  "geometry": {"coordinates":[-87.877049,42.423691],"type":"Point"}
}