{
  "type": "Feature",
  "properties": {
    "addr:full":"22825 E Rush Rd Bluford IL 62814",
    "addr:housenumber":"22825",
    "addr:postcode":"62814",
    "addr:street":"E Rush Rd",
    "iso:country":"US",
    "sg:address":"22825 E Rush Rd",
    "sg:city":"Bluford",
    "sg:classifiers":[
        {
            "category":"Manufacturing",
            "subcategory":"Buildings",
            "type":"Manufacturing & Wholesale Goods"
        }
    ],
    "sg:phone":"+1 618 732 6048",
    "sg:postcode":"62814",
    "sg:province":"IL",
    "sg:tags":[
        "prefabricated",
        "wood",
        "mfg"
    ],
    "wof:name":"Honest Abe",
    "wof:placetype":"venue"
},
  "geometry": {"coordinates":[-88.727217,38.2987],"type":"Point"}
}