{
  "type": "Feature",
  "properties": {
    "iso:country":"US",
    "sg:address":"4751 W Harrison St",
    "sg:city":"Chicago",
    "sg:classifiers":[
        {
            "category":"Professional",
            "subcategory":"Business Services",
            "type":"Services"
        }
    ],
    "sg:phone":"+1 773 287 3700",
    "sg:postcode":"60644",
    "sg:province":"IL",
    "wof:name":"Siddiqui Khalid J",
    "wof:placetype":"venue"
},
  "geometry": {"coordinates":[-87.743253,41.873118],"type":"Point"}
}