{
  "type": "Feature",
  "properties": {
    "iso:country":"US",
    "sg:address":"2006 Cindy Lynn St",
    "sg:city":"Urbana",
    "sg:classifiers":[
        {
            "category":"Wholesale",
            "subcategory":"Machinery & Supplies",
            "type":"Manufacturing & Wholesale Goods"
        }
    ],
    "sg:phone":"+1 217 384 4136",
    "sg:postcode":"61802",
    "sg:province":"IL",
    "sg:tags":[
        "equipment",
        "establishment"
    ],
    "wof:name":"Ctc Consolidated Trading",
    "wof:placetype":"venue"
},
  "geometry": {"coordinates":[-88.165313,40.13249],"type":"Point"}
}