{
  "type": "Feature",
  "properties": {
    "addr:full":"910 Sivert Dr Wood Dale IL 60191",
    "addr:housenumber":"910",
    "addr:postcode":"60191",
    "addr:street":"Sivert Dr",
    "iso:country":"US",
    "sg:address":"910 Sivert Dr",
    "sg:city":"Wood Dale",
    "sg:classifiers":[
        {
            "category":"Wholesale",
            "subcategory":"Machinery & Supplies",
            "type":"Manufacturing & Wholesale Goods"
        }
    ],
    "sg:phone":"+1 630 860 7200",
    "sg:postcode":"60191",
    "sg:province":"IL",
    "sg:tags":[
        "equipment",
        "establishment"
    ],
    "wof:name":"Viking Industrial Products",
    "wof:placetype":"venue"
},
  "geometry": {"coordinates":[-87.977632,41.978931],"type":"Point"}
}