{
  "type": "Feature",
  "properties": {
    "addr:full":"629 Ivy Ln Bradley IL 60915",
    "addr:housenumber":"629",
    "addr:postcode":"60915",
    "addr:street":"Ivy Ln",
    "iso:country":"US",
    "sg:address":"629 Ivy Ln",
    "sg:city":"Bradley",
    "sg:classifiers":[
        {
            "category":"Home & Garden",
            "subcategory":"Household Appliances",
            "type":"Retail Goods"
        }
    ],
    "sg:phone":"+1   ",
    "sg:postcode":"60915",
    "sg:province":"IL",
    "sg:tags":[
        "repair",
        "rep",
        "electrical"
    ],
    "wof:name":"Bradley Sewing Ctr",
    "wof:placetype":"venue"
},
  "geometry": {"coordinates":[-87.861801,41.15404],"type":"Point"}
}