{
  "type": "Feature",
  "properties": {
    "addr:full":"824 S Morrison Ave Collinsville IL 62234",
    "addr:housenumber":"824",
    "addr:postcode":"62234",
    "addr:street":"S Morrison Ave",
    "iso:country":"US",
    "sg:address":"824 S Morrison Ave",
    "sg:city":"Collinsville",
    "sg:classifiers":[
        {
            "category":"Personal",
            "subcategory":"Beauty Salon",
            "type":"Services"
        }
    ],
    "sg:phone":"+1 618 343 4228",
    "sg:postcode":"62234",
    "sg:province":"IL",
    "wof:name":"Xcentric Designs Salon",
    "wof:placetype":"venue"
},
  "geometry": {"coordinates":[-89.98487900000001,38.659541],"type":"Point"}
}