{
  "type": "Feature",
  "properties": {
    "addr:full":"705 S Remann St Vandalia IL 62471",
    "addr:housenumber":"705",
    "addr:postcode":"62471",
    "addr:street":"S Remann St",
    "iso:country":"US",
    "sg:address":"705 S Remann St",
    "sg:city":"Vandalia",
    "sg:classifiers":[
        {
            "category":"Building & Trades",
            "subcategory":"Pest Control",
            "type":"Services"
        }
    ],
    "sg:phone":"+1 618 283 4072",
    "sg:postcode":"62471",
    "sg:province":"IL",
    "wof:name":"D C Pest Control",
    "wof:placetype":"venue"
},
  "geometry": {"coordinates":[-89.10539,38.955616],"type":"Point"}
}