{
  "type": "Feature",
  "properties": {
    "iso:country":"US",
    "sg:address":"1000 N Main St",
    "sg:city":"Vermont",
    "sg:classifiers":[
        {
            "category":"Farming",
            "subcategory":"Livestock Farm",
            "type":"Manufacturing & Wholesale Goods"
        }
    ],
    "sg:phone":"+1 309 784 3281",
    "sg:postcode":"61484",
    "sg:province":"IL",
    "sg:tags":[
        "feeding"
    ],
    "wof:name":"O Kost",
    "wof:placetype":"venue"
},
  "geometry": {"coordinates":[-90.427464,40.304825],"type":"Point"}
}