{
  "type": "Feature",
  "properties": {
    "addr:full":"850 Wheeling Rd Wheeling IL 60090",
    "addr:housenumber":"850",
    "addr:postcode":"60090",
    "addr:street":"Wheeling Rd",
    "iso:country":"US",
    "sg:address":"850 Wheeling Rd",
    "sg:city":"Wheeling",
    "sg:classifiers":[
        {
            "category":"Personal",
            "subcategory":"Beauty Salon",
            "type":"Services"
        }
    ],
    "sg:phone":"+1 847 537 6192",
    "sg:postcode":"60090",
    "sg:province":"IL",
    "sg:tags":[
        "hair",
        "stylist"
    ],
    "wof:name":"Sleek Hair Beauty Salon",
    "wof:placetype":"venue"
},
  "geometry": {"coordinates":[-87.92701,42.123365],"type":"Point"}
}