{
  "type": "Feature",
  "properties": {
    "iso:country":"US",
    "sg:address":"1346 W Cruger Rd",
    "sg:city":"Washington",
    "sg:classifiers":[
        {
            "category":"Professional",
            "subcategory":"Advertising",
            "type":"Services"
        },
        {
            "category":"Professional",
            "subcategory":"Art Services",
            "type":"Services"
        },
        {
            "category":"Professional",
            "subcategory":"Computer Services",
            "type":"Services"
        }
    ],
    "sg:phone":"+1 309 444 7455",
    "sg:postcode":"61571",
    "sg:province":"IL",
    "sg:tags":[
        "web",
        "graphic",
        "artist",
        "agency",
        "commercial",
        "site",
        "designer",
        "design"
    ],
    "sg:website":"http://www.squarecrow.com",
    "wof:name":"Squarecrow Creative",
    "wof:placetype":"venue"
},
  "geometry": {"coordinates":[-89.427638,40.71924],"type":"Point"}
}