{
  "type": "Feature",
  "properties": {
    "iso:country":"US",
    "sg:address":"1041 Evergreen Dr",
    "sg:city":"Carol Stream",
    "sg:classifiers":[
        {
            "category":"Education",
            "subcategory":"School",
            "type":"Public Place"
        }
    ],
    "sg:phone":"+1 630 231 0040",
    "sg:postcode":"60188",
    "sg:province":"IL",
    "sg:tags":[
        "high",
        "middle",
        "elementary"
    ],
    "wof:name":"Evergreen School",
    "wof:placetype":"venue"
},
  "geometry": {"coordinates":[-88.15660099999999,41.921501],"type":"Point"}
}