{
  "type": "Feature",
  "properties": {
    "iso:country":"US",
    "sg:address":"4109 Dundee Rd",
    "sg:city":"Northbrook",
    "sg:classifiers":[
        {
            "category":"Professional",
            "subcategory":"Accounting & Tax Preparation",
            "type":"Services"
        }
    ],
    "sg:phone":"+1 847 498 2199",
    "sg:postcode":"60062",
    "sg:province":"IL",
    "sg:tags":[
        "return",
        "business"
    ],
    "wof:name":"H & R Block",
    "wof:placetype":"venue"
},
  "geometry": {"coordinates":[-87.882807,42.13847],"type":"Point"}
}