{
  "type": "Feature",
  "properties": {
    "iso:country":"US",
    "sg:address":"6910 27th St",
    "sg:city":"Moline",
    "sg:classifiers":[
        {
            "category":"Professional",
            "subcategory":"Management & Consulting",
            "type":"Services"
        }
    ],
    "sg:phone":"+1 309 762 8300",
    "sg:postcode":"61265",
    "sg:province":"IL",
    "wof:name":"Holiday Inn",
    "wof:placetype":"venue"
},
  "geometry": {"coordinates":[-90.498921,41.453673],"type":"Point"}
}