{
  "type": "Feature",
  "properties": {
    "iso:country":"US",
    "sg:address":"23719 N Elm Rd",
    "sg:city":"Lincolnshire",
    "sg:classifiers":[
        {
            "category":"Real Estate",
            "subcategory":"Real Estate Agent",
            "type":"Services"
        }
    ],
    "sg:phone":"+1 847 913 1886",
    "sg:postcode":"60069",
    "sg:province":"IL",
    "wof:name":"Betty White-Zappa RE",
    "wof:placetype":"venue"
},
  "geometry": {"coordinates":[-87.915764,42.206875],"type":"Point"}
}