{
  "type": "Feature",
  "properties": {
    "addr:full":"2336 53rd St Moline IL 61265",
    "addr:housenumber":"2336",
    "addr:postcode":"61265",
    "addr:street":"53Rd St",
    "iso:country":"US",
    "sg:address":"2336 53rd St",
    "sg:city":"Moline",
    "sg:classifiers":[
        {
            "category":"Personal",
            "subcategory":"Beauty Salon",
            "type":"Services"
        }
    ],
    "sg:phone":"+1 309 755 9980",
    "sg:postcode":"61265",
    "sg:province":"IL",
    "wof:name":"Strategic Hair Command",
    "wof:placetype":"venue"
},
  "geometry": {"coordinates":[-90.465642,41.489674],"type":"Point"}
}