{
  "type": "Feature",
  "properties": {
    "iso:country":"US",
    "sg:address":"1001 Warrenville Rd",
    "sg:city":"Lisle",
    "sg:classifiers":[
        {
            "category":"Professional",
            "subcategory":"Business Services",
            "type":"Services"
        }
    ],
    "sg:phone":"+1 630 437 5510",
    "sg:postcode":"60532",
    "sg:province":"IL",
    "wof:name":"Fidlar Gbs",
    "wof:placetype":"venue"
},
  "geometry": {"coordinates":[-88.070827,41.808552],"type":"Point"}
}