{
  "type": "Feature",
  "properties": {
    "addr:full":"1724 E Kensington Rd Mount Prospect IL 60056",
    "addr:housenumber":"1724",
    "addr:postcode":"60056",
    "addr:street":"E Kensington Rd",
    "iso:country":"US",
    "sg:address":"1724 E Kensington Rd",
    "sg:city":"Mount Prospect",
    "sg:classifiers":[
        {
            "category":"Restaurant",
            "type":"Food & Drink"
        }
    ],
    "sg:menulink":"http://www.allmenus.com/il/wheeling/126853-subway/menu/",
    "sg:phone":"+1 847 827 2244",
    "sg:postcode":"60056",
    "sg:province":"IL",
    "sg:tags":[
        "american",
        "sandwich"
    ],
    "wof:name":"Subway",
    "wof:placetype":"venue"
},
  "geometry": {"coordinates":[-87.901293,42.080469],"type":"Point"}
}