{
  "type": "Feature",
  "properties": {
    "addr:full":"16601 S Windsor Ln Lockport IL 60441",
    "addr:housenumber":"16601",
    "addr:postcode":"60441",
    "addr:street":"S Windsor Ln",
    "iso:country":"US",
    "sg:address":"16601 S Windsor Ln",
    "sg:city":"Lockport",
    "sg:classifiers":[
        {
            "category":"Home & Garden",
            "subcategory":"Home Furnishings",
            "type":"Retail Goods"
        }
    ],
    "sg:phone":"+1 815 834 2471",
    "sg:postcode":"60441",
    "sg:province":"IL",
    "sg:tags":[
        "curtain",
        "made",
        "drapery"
    ],
    "wof:name":"Executive Interiors",
    "wof:placetype":"venue"
},
  "geometry": {"coordinates":[-87.980729,41.585714],"type":"Point"}
}