{
  "type": "Feature",
  "properties": {
    "addr:full":"601 Burton Dr Lake Forest IL 60045",
    "addr:housenumber":"601",
    "addr:postcode":"60045",
    "addr:street":"Burton Dr",
    "iso:country":"US",
    "sg:address":"601 Burton Dr",
    "sg:city":"Lake Forest",
    "sg:classifiers":[
        {
            "category":"Building & Trades",
            "subcategory":"Construction",
            "type":"Services"
        }
    ],
    "sg:phone":"+1 847 234 5565",
    "sg:postcode":"60045",
    "sg:province":"IL",
    "sg:tags":[
        "housing"
    ],
    "wof:name":"Pawlish Jos H General Contrs",
    "wof:placetype":"venue"
},
  "geometry": {"coordinates":[-87.870155,42.250389],"type":"Point"}
}