{
  "type": "Feature",
  "properties": {
    "addr:full":"108 Industrial Dr Unit C Minooka IL 60447",
    "addr:housenumber":"108",
    "addr:postcode":"60447",
    "addr:street":"Industrial Dr Unit C",
    "iso:country":"US",
    "sg:address":"108 Industrial Dr Unit C",
    "sg:city":"Minooka",
    "sg:classifiers":[
        {
            "category":"Transit Center",
            "subcategory":"Freight",
            "type":"Transportation"
        },
        {
            "category":"Freight",
            "type":"Transportation"
        }
    ],
    "sg:phone":"+1 815 467 8440",
    "sg:postcode":"60447",
    "sg:province":"IL",
    "sg:tags":[
        "trucking-motor",
        "trucking"
    ],
    "wof:name":"Proficient Transport Inc",
    "wof:placetype":"venue"
},
  "geometry": {"coordinates":[-88.272762,41.448451],"type":"Point"}
}