{
  "type": "Feature",
  "properties": {
    "iso:country":"US",
    "sg:address":"4 Market Sq",
    "sg:city":"Lake Forest",
    "sg:classifiers":[
        {
            "category":"Real Estate",
            "subcategory":"Developer",
            "type":"Services"
        }
    ],
    "sg:phone":"+1 847 234 1629",
    "sg:postcode":"60045",
    "sg:province":"IL",
    "wof:name":"Broadacre Management Co",
    "wof:placetype":"venue"
},
  "geometry": {"coordinates":[-87.84001000000001,42.252356],"type":"Point"}
}