{
  "type": "Feature",
  "properties": {
    "addr:full":"1500 Midway Ct Elk Grove Village IL 60007",
    "addr:housenumber":"1500",
    "addr:postcode":"60007",
    "addr:street":"Midway Ct",
    "iso:country":"US",
    "sg:address":"1500 Midway Ct",
    "sg:city":"Elk Grove Village",
    "sg:classifiers":[
        {
            "category":"Building & Trades",
            "subcategory":"Construction",
            "type":"Services"
        }
    ],
    "sg:phone":"+1 847 758 0570",
    "sg:postcode":"60007",
    "sg:province":"IL",
    "sg:tags":[
        "subcontractor",
        "carpentry"
    ],
    "wof:name":"OPC Construction Inc",
    "wof:placetype":"venue"
},
  "geometry": {"coordinates":[-87.96407499999999,42.02551],"type":"Point"}
}