{
  "type": "Feature",
  "properties": {
    "iso:country":"US",
    "sg:address":"9366 Landings Ln",
    "sg:city":"Des Plaines",
    "sg:classifiers":[
        {
            "category":"Organizations",
            "subcategory":"Community Association",
            "type":"Services"
        }
    ],
    "sg:phone":"+1 847 635 0194",
    "sg:postcode":"60016",
    "sg:province":"IL",
    "sg:tags":[
        "owner",
        "home"
    ],
    "wof:name":"Landings Condominium Assn",
    "wof:placetype":"venue"
},
  "geometry": {"coordinates":[-87.858498,42.042257],"type":"Point"}
}