{
  "type": "Feature",
  "properties": {
    "iso:country":"US",
    "sg:address":"501 W Diversey Pkwy",
    "sg:city":"Chicago",
    "sg:classifiers":[
        {
            "category":"Restaurant",
            "type":"Food & Drink"
        }
    ],
    "sg:phone":"+1 773 248 0398",
    "sg:postcode":"60614",
    "sg:province":"IL",
    "sg:tags":[
        "traditional",
        "american"
    ],
    "wof:name":"The Grove",
    "wof:placetype":"venue"
},
  "geometry": {"coordinates":[-87.641502,41.932701],"type":"Point"}
}