{
  "type": "Feature",
  "properties": {
    "iso:country":"US",
    "sg:address":"824 W Center St",
    "sg:city":"Girard",
    "sg:classifiers":[
        {
            "category":"Banks & Credit Unions",
            "subcategory":"Bank",
            "type":"Services"
        }
    ],
    "sg:phone":"+1 217 627 3240",
    "sg:postcode":"62640",
    "sg:province":"IL",
    "sg:tags":[
        "mortgage"
    ],
    "wof:name":"J C Enterprises",
    "wof:placetype":"venue"
},
  "geometry": {"coordinates":[-89.791033,39.446311],"type":"Point"}
}