{
  "type": "Feature",
  "properties": {
    "addr:full":"335 W Wise Rd Schaumburg IL 60193",
    "addr:housenumber":"335",
    "addr:postcode":"60193",
    "addr:street":"W Wise Rd",
    "iso:country":"US",
    "sg:address":"335 W Wise Rd",
    "sg:city":"Schaumburg",
    "sg:classifiers":[
        {
            "category":"Health Services",
            "subcategory":"Chiropractor",
            "type":"Services"
        }
    ],
    "sg:phone":"+1 847 352 6776",
    "sg:postcode":"60193",
    "sg:province":"IL",
    "wof:name":"Furlett Chiropractic Ctr LTD",
    "wof:placetype":"venue"
},
  "geometry": {"coordinates":[-88.08871499999999,42.004899],"type":"Point"}
}