{
  "type": "Feature",
  "properties": {
    "addr:full":"203 N Lasalle Chicago IL 60601",
    "addr:housenumber":"203",
    "addr:postcode":"60601",
    "addr:street":"N Lasalle",
    "iso:country":"US",
    "sg:address":"203 N Lasalle",
    "sg:city":"Chicago",
    "sg:classifiers":[
        {
            "category":"Personal",
            "subcategory":"Shoe Repair & Shine",
            "type":"Services"
        }
    ],
    "sg:postcode":"60601",
    "sg:province":"IL",
    "sg:website":"shoecrafters.com",
    "wof:name":"Sam the Shoe Doctor",
    "wof:placetype":"venue"
},
  "geometry": {"coordinates":[-87.632336,41.885808],"type":"Point"}
}