{
  "type": "Feature",
  "properties": {
    "addr:full":"7021 N Oriole Ave Chicago IL 60631",
    "addr:housenumber":"7021",
    "addr:postcode":"60631",
    "addr:street":"N Oriole Ave",
    "iso:country":"US",
    "sg:address":"7021 N Oriole Ave",
    "sg:city":"Chicago",
    "sg:classifiers":[
        {
            "category":"Parking",
            "type":"Transportation"
        },
        {
            "category":"Retail",
            "subcategory":"Event Space",
            "type":"Services"
        },
        {
            "category":"Professional",
            "type":"Services"
        }
    ],
    "sg:phone":"+1 773 763 7770",
    "sg:postcode":"60631",
    "sg:province":"IL",
    "sg:tags":[
        "attendant",
        "planning",
        "meeting",
        "valet"
    ],
    "sg:website":"http://www.lavaletinc.com",
    "wof:name":"LA Valet",
    "wof:placetype":"venue"
},
  "geometry": {"coordinates":[-87.816417,42.008201],"type":"Point"}
}