{
  "type": "Feature",
  "properties": {
    "iso:country":"US",
    "sg:address":"452 W Aldine Ave",
    "sg:city":"Chicago",
    "sg:classifiers":[
        {
            "category":"Professional",
            "type":"Services"
        }
    ],
    "sg:phone":"+1 773 296 4918",
    "sg:postcode":"60657",
    "sg:province":"IL",
    "wof:name":"Nach-Air Communications Servic",
    "wof:placetype":"venue"
},
  "geometry": {"coordinates":[-87.642574,41.942329],"type":"Point"}
}