{
  "type": "Feature",
  "properties": {
    "iso:country":"US",
    "sg:address":"270 Bluff Ct Apt D",
    "sg:city":"Barrington",
    "sg:classifiers":[
        {
            "category":"Professional",
            "subcategory":"Management & Consulting",
            "type":"Services"
        },
        {
            "category":"Professional",
            "subcategory":"Advertising",
            "type":"Services"
        }
    ],
    "sg:phone":"+1 847 650 6791",
    "sg:postcode":"60010",
    "sg:province":"IL",
    "sg:tags":[
        "marketing",
        "program",
        "consultant"
    ],
    "wof:name":"Quinta Edge Inc",
    "wof:placetype":"venue"
},
  "geometry": {"coordinates":[-88.15647300000001,42.216783],"type":"Point"}
}