{
  "type": "Feature",
  "properties": {
    "iso:country":"US",
    "sg:address":"1631 W Walnut Street",
    "sg:city":"Chicago",
    "sg:classifiers":[
        {
            "category":"Manufacturing",
            "subcategory":"Food",
            "type":"Manufacturing & Wholesale Goods"
        },
        {
            "category":"Wholesale",
            "subcategory":"Groceries",
            "type":"Manufacturing & Wholesale Goods"
        },
        {
            "category":"Ice Cream",
            "type":"Food & Drink"
        }
    ],
    "sg:phone":"+1 312 563 9732",
    "sg:postcode":"60612",
    "sg:province":"IL",
    "sg:tags":[
        "frozen",
        "desserts-manufacturers",
        "distributor",
        "foods-wholesale",
        "yogurt"
    ],
    "sg:website":"www.dianasbananas.com/",
    "wof:name":"Diana's Bananas",
    "wof:placetype":"venue"
},
  "geometry": {"coordinates":[-87.66780300000001,41.886117],"type":"Point"}
}