{
  "type": "Feature",
  "properties": {
    "iso:country":"US",
    "sg:address":"95 W Grand Ave",
    "sg:city":"Lake Villa",
    "sg:classifiers":[
        {
            "category":"Professional",
            "subcategory":"Accounting & Tax Preparation",
            "type":"Services"
        }
    ],
    "sg:phone":"+1 847 356 1199",
    "sg:postcode":"60046",
    "sg:province":"IL",
    "sg:tags":[
        "accountant"
    ],
    "wof:name":"Michael K Simmer & Co",
    "wof:placetype":"venue"
},
  "geometry": {"coordinates":[-88.084476,42.415418],"type":"Point"}
}