{
  "type": "Feature",
  "properties": {
    "iso:country":"US",
    "sg:address":"14820 Ridgewood Dr",
    "sg:city":"Oak Forest",
    "sg:classifiers":[
        {
            "category":"Building & Trades",
            "subcategory":"Construction",
            "type":"Services"
        }
    ],
    "sg:phone":"+1 708 687 1593",
    "sg:postcode":"60452",
    "sg:province":"IL",
    "sg:tags":[
        "specializing",
        "c",
        "general",
        "new",
        "contractor",
        "remodeling"
    ],
    "wof:name":"B & D Construction Inc",
    "wof:placetype":"venue"
},
  "geometry": {"coordinates":[-87.775732,41.622704],"type":"Point"}
}