{
  "type": "Feature",
  "properties": {
    "iso:country":"US",
    "sg:address":"1531 Division St",
    "sg:city":"Charleston",
    "sg:classifiers":[
        {
            "category":"Shopping",
            "subcategory":"Hobbies, Toys, & Games",
            "type":"Retail Goods"
        }
    ],
    "sg:phone":"+1 217 345 6059",
    "sg:postcode":"61920",
    "sg:province":"IL",
    "sg:tags":[
        "craft",
        "supply"
    ],
    "wof:name":"Eve Spinning & Weaving Equip",
    "wof:placetype":"venue"
},
  "geometry": {"coordinates":[-88.18159300000001,39.484047],"type":"Point"}
}