{
  "type": "Feature",
  "properties": {
    "iso:country":"US",
    "sg:address":"281 S Bolingbrook Dr",
    "sg:city":"Bolingbrook",
    "sg:classifiers":[
        {
            "category":"Professional",
            "subcategory":"Employment Agencies",
            "type":"Services"
        }
    ],
    "sg:phone":"+1 630 226 1450",
    "sg:postcode":"60440",
    "sg:province":"IL",
    "sg:tags":[
        "opportunity"
    ],
    "wof:name":"Accurate Personnel",
    "wof:placetype":"venue"
},
  "geometry": {"coordinates":[-88.06822699999999,41.692271],"type":"Point"}
}