{
  "type": "Feature",
  "properties": {
    "iso:country":"US",
    "sg:address":"100 N Rolling Green Ln",
    "sg:city":"Rochelle",
    "sg:classifiers":[
        {
            "category":"Real Estate",
            "subcategory":"Developer",
            "type":"Services"
        }
    ],
    "sg:phone":"+1 815 562 8202",
    "sg:postcode":"61068",
    "sg:province":"IL",
    "sg:tags":[
        "mobile",
        "home"
    ],
    "wof:name":"Rolling Green Ests Mobile Home",
    "wof:placetype":"venue"
},
  "geometry": {"coordinates":[-89.105522,41.937232],"type":"Point"}
}