{
  "type": "Feature",
  "properties": {
    "iso:country":"US",
    "sg:address":"10 Gateway Dr",
    "sg:city":"Collinsville",
    "sg:classifiers":[
        {
            "category":"Recreation",
            "subcategory":"Amusement Park",
            "type":"Entertainment"
        }
    ],
    "sg:phone":"+1 618 346 4571",
    "sg:postcode":"62234",
    "sg:province":"IL",
    "wof:name":"Splash City Family Waterpark",
    "wof:placetype":"venue"
},
  "geometry": {"coordinates":[-90.015297,38.6824],"type":"Point"}
}