{
  "type": "Feature",
  "properties": {
    "iso:country":"US",
    "sg:address":"2118 5th Ave",
    "sg:city":"Sterling",
    "sg:classifiers":[
        {
            "category":"Home & Garden",
            "subcategory":"Building Materials",
            "type":"Retail Goods"
        },
        {
            "category":"Building & Trades",
            "subcategory":"Construction",
            "type":"Services"
        },
        {
            "category":"Manufacturing",
            "subcategory":"Building Materials",
            "type":"Manufacturing & Wholesale Goods"
        }
    ],
    "sg:phone":"+1 815 625 1484",
    "sg:postcode":"61081",
    "sg:province":"IL",
    "sg:tags":[
        "roofing",
        "industrial",
        "altering",
        "siding",
        "contractor",
        "window",
        "contractors-commercial",
        "doors",
        "frames",
        "accessory",
        "remodeling"
    ],
    "wof:name":"Stewart Home Improvement",
    "wof:placetype":"venue"
},
  "geometry": {"coordinates":[-89.69065000000001,41.806388],"type":"Point"}
}