{
  "type": "Feature",
  "properties": {
    "iso:country":"US",
    "sg:address":"5257 W Diversey Ave",
    "sg:city":"Chicago",
    "sg:classifiers":[
        {
            "category":"Retail",
            "subcategory":"Auto Repair",
            "type":"Services"
        }
    ],
    "sg:phone":"+1 773 637 8431",
    "sg:postcode":"60639",
    "sg:province":"IL",
    "wof:name":"G & S Automotive",
    "wof:placetype":"venue"
},
  "geometry": {"coordinates":[-87.75859800000001,41.931198],"type":"Point"}
}