{
  "type": "Feature",
  "properties": {
    "iso:country":"US",
    "sg:address":"2659 W Devon Ave",
    "sg:city":"Chicago",
    "sg:classifiers":[
        {
            "category":"Shopping",
            "subcategory":"Clothing, Apparel, & Fashions",
            "type":"Retail Goods"
        },
        {
            "category":"Shopping",
            "subcategory":"Jewelry",
            "type":"Retail Goods"
        }
    ],
    "sg:phone":"+1 773 338 3252",
    "sg:postcode":"60659",
    "sg:province":"IL",
    "sg:tags":[
        "clothing",
        "women's"
    ],
    "wof:name":"Unique Fashions",
    "wof:placetype":"venue"
},
  "geometry": {"coordinates":[-87.696962,41.997346],"type":"Point"}
}