{
  "type": "Feature",
  "properties": {
    "iso:country":"US",
    "sg:address":"1009 5th Ave",
    "sg:city":"Rock Falls",
    "sg:classifiers":[
        {
            "category":"Building & Trades",
            "subcategory":"Construction",
            "type":"Services"
        }
    ],
    "sg:phone":"+1 815 622 7909",
    "sg:postcode":"61071",
    "sg:province":"IL",
    "sg:tags":[
        "house"
    ],
    "wof:name":"Krug Custom Builders",
    "wof:placetype":"venue"
},
  "geometry": {"coordinates":[-89.69239899999999,41.772419],"type":"Point"}
}