{
  "type": "Feature",
  "properties": {
    "addr:full":"4214 S Saint Lawrence Avenue Chicago IL 60653",
    "addr:housenumber":"4214",
    "addr:postcode":"60653",
    "addr:street":"S Saint Lawrence Avenue",
    "iso:country":"US",
    "sg:address":"4214 S Saint Lawrence Avenue",
    "sg:city":"Chicago",
    "sg:classifiers":[
        {
            "category":"Education",
            "subcategory":"School",
            "type":"Public Place"
        }
    ],
    "sg:phone":"+1 773 535 1687",
    "sg:postcode":"60653",
    "sg:province":"IL",
    "wof:name":"Schools Public",
    "wof:placetype":"venue"
},
  "geometry": {"coordinates":[-87.61166799999999,41.818106],"type":"Point"}
}