{
  "type": "Feature",
  "properties": {
    "addr:full":"850 S Wabash Ave Ste 250 Chicago IL 60686",
    "addr:housenumber":"850",
    "addr:postcode":"60686",
    "addr:street":"S Wabash Ave Ste 250",
    "iso:country":"US",
    "sg:address":"850 S Wabash Ave Ste 250",
    "sg:city":"Chicago",
    "sg:classifiers":[
        {
            "category":"Health Services",
            "subcategory":"Dentist",
            "type":"Services"
        }
    ],
    "sg:phone":"+1 312 922 3411",
    "sg:postcode":"60686",
    "sg:province":"IL",
    "sg:website":"www.smartsmilesdental.org",
    "wof:name":"Smart Smiles Dental",
    "wof:placetype":"venue"
},
  "geometry": {"coordinates":[-87.625918,41.870999],"type":"Point"}
}