{
  "type": "Feature",
  "properties": {
    "iso:country":"US",
    "sg:address":"512 E John St",
    "sg:city":"Champaign",
    "sg:classifiers":[
        {
            "category":"Shopping",
            "subcategory":"Florist",
            "type":"Retail Goods"
        }
    ],
    "sg:phone":"+1 217 328 0038",
    "sg:postcode":"61820",
    "sg:province":"IL",
    "wof:name":"April's Country Florist",
    "wof:placetype":"venue"
},
  "geometry": {"coordinates":[-88.23067899999999,40.109244],"type":"Point"}
}