{
  "type": "Feature",
  "properties": {
    "addr:full":"1991 S Mount Zion Rd Decatur IL 62521",
    "addr:housenumber":"1991",
    "addr:postcode":"62521",
    "addr:street":"S Mount Zion Rd",
    "iso:country":"US",
    "sg:address":"1991 S Mount Zion Rd",
    "sg:city":"Decatur",
    "sg:classifiers":[
        {
            "category":"Restaurant",
            "type":"Food & Drink"
        }
    ],
    "sg:menulink":"http://www.allmenus.com/il/long-creek/196209-taco-bell/menu/",
    "sg:postcode":"62521",
    "sg:province":"IL",
    "sg:tags":[
        "mexican"
    ],
    "wof:name":"Taco Bell",
    "wof:placetype":"venue"
},
  "geometry": {"coordinates":[-88.878462,39.820368],"type":"Point"}
}