{
  "type": "Feature",
  "properties": {
    "iso:country":"US",
    "sg:address":"3520 S Morgan St",
    "sg:city":"Chicago",
    "sg:classifiers":[
        {
            "category":"Home & Garden",
            "subcategory":"Building Materials",
            "type":"Retail Goods"
        }
    ],
    "sg:phone":"+1 773 247 8282",
    "sg:postcode":"60609",
    "sg:province":"IL",
    "sg:tags":[
        "supply"
    ],
    "sg:website":"www.amberleafcabinetry.com/",
    "wof:name":"Amberleaf Cabinetry",
    "wof:placetype":"venue"
},
  "geometry": {"coordinates":[-87.65093899999999,41.830102],"type":"Point"}
}