{
  "type": "Feature",
  "properties": {
    "iso:country":"US",
    "sg:address":"1065 N Fayette St",
    "sg:city":"Jacksonville",
    "sg:classifiers":[
        {
            "category":"Building & Trades",
            "subcategory":"Landscaping Services",
            "type":"Services"
        }
    ],
    "sg:phone":"+1 217 479 0654",
    "sg:postcode":"62650",
    "sg:province":"IL",
    "sg:tags":[
        "landscape"
    ],
    "wof:name":"J & M Putting Greens & Ldscpg",
    "wof:placetype":"venue"
},
  "geometry": {"coordinates":[-90.23575700000001,39.742962],"type":"Point"}
}