{
  "type": "Feature",
  "properties": {
    "addr:full":"2019 N President St Wheaton IL 60187",
    "addr:housenumber":"2019",
    "addr:postcode":"60187",
    "addr:street":"N President St",
    "iso:country":"US",
    "sg:address":"2019 N President St",
    "sg:city":"Wheaton",
    "sg:classifiers":[
        {
            "category":"Manufacturing",
            "subcategory":"Printing",
            "type":"Manufacturing & Wholesale Goods"
        }
    ],
    "sg:phone":"+1 630 886 4359",
    "sg:postcode":"60187",
    "sg:province":"IL",
    "sg:tags":[
        "commercial"
    ],
    "wof:name":"Personalized Hahn Marketing",
    "wof:placetype":"venue"
},
  "geometry": {"coordinates":[-88.091998,41.887215],"type":"Point"}
}