{
  "type": "Feature",
  "properties": {
    "iso:country":"US",
    "sg:address":"155 Boulder Hill Pass",
    "sg:city":"Montgomery",
    "sg:classifiers":[
        {
            "category":"Social Services",
            "subcategory":"Child Care",
            "type":"Services"
        }
    ],
    "sg:phone":"+1 630 897 3347",
    "sg:postcode":"60538",
    "sg:province":"IL",
    "sg:tags":[
        "day"
    ],
    "wof:name":"All Gods Children Pre-School",
    "wof:placetype":"venue"
},
  "geometry": {"coordinates":[-88.34006,41.7098],"type":"Point"}
}