{
  "type": "Feature",
  "properties": {
    "iso:country":"US",
    "sg:address":"2749 W Algonquin Rd",
    "sg:city":"Algonquin",
    "sg:classifiers":[
        {
            "category":"Restaurant",
            "type":"Food & Drink"
        }
    ],
    "sg:phone":"+1 847 658 1010",
    "sg:postcode":"60102",
    "sg:province":"IL",
    "sg:tags":[
        "pizza"
    ],
    "sg:website":"www.itsagoodpizza.com",
    "wof:name":"Buddyz A Chicago Pizzaria",
    "wof:placetype":"venue"
},
  "geometry": {"coordinates":[-88.326305,42.175559],"type":"Point"}
}