{
  "type": "Feature",
  "properties": {
    "addr:full":"814 S Maple St Mount Prospect IL 60056",
    "addr:housenumber":"814",
    "addr:postcode":"60056",
    "addr:street":"S Maple St",
    "iso:country":"US",
    "sg:address":"814 S Maple St",
    "sg:city":"Mount Prospect",
    "sg:classifiers":[
        {
            "category":"Real Estate",
            "subcategory":"Real Estate Agent",
            "type":"Services"
        }
    ],
    "sg:phone":"+1 847 255 8360",
    "sg:postcode":"60056",
    "sg:province":"IL",
    "wof:name":"Regan Jim",
    "wof:placetype":"venue"
},
  "geometry": {"coordinates":[-87.93405,42.050343],"type":"Point"}
}