{
  "type": "Feature",
  "properties": {
    "iso:country":"US",
    "sg:address":"22 Church St",
    "sg:city":"Lake Zurich",
    "sg:classifiers":[
        {
            "category":"Insurance",
            "subcategory":"Insurance Agent",
            "type":"Services"
        }
    ],
    "sg:phone":"+1 847 438 1750",
    "sg:postcode":"60047",
    "sg:province":"IL",
    "wof:name":"Robillard Family Financial",
    "wof:placetype":"venue"
},
  "geometry": {"coordinates":[-88.08908700000001,42.199343],"type":"Point"}
}