{
  "type": "Feature",
  "properties": {
    "addr:full":"5757 N Milwaukee Ave Chicago IL 60646",
    "addr:housenumber":"5757",
    "addr:postcode":"60646",
    "addr:street":"N Milwaukee Ave",
    "iso:country":"US",
    "sg:address":"5757 N Milwaukee Ave",
    "sg:city":"Chicago",
    "sg:classifiers":[
        {
            "category":"Banks & Credit Unions",
            "subcategory":"Bank",
            "type":"Services"
        }
    ],
    "sg:phone":"+1 773 467 0500",
    "sg:postcode":"60646",
    "sg:province":"IL",
    "wof:name":"First Nations Bank",
    "wof:placetype":"venue"
},
  "geometry": {"coordinates":[-87.777022,41.986134],"type":"Point"}
}