{
  "type": "Feature",
  "properties": {
    "addr:full":"15651 S Parker Rd Homer Glen IL 60491",
    "addr:housenumber":"15651",
    "addr:postcode":"60491",
    "addr:street":"S Parker Rd",
    "iso:country":"US",
    "sg:address":"15651 S Parker Rd",
    "sg:city":"Homer Glen",
    "sg:classifiers":[
        {
            "category":"Professional",
            "subcategory":"Business Services",
            "type":"Services"
        }
    ],
    "sg:phone":"+1 708 301 9885",
    "sg:postcode":"60491",
    "sg:province":"IL",
    "sg:tags":[
        "interior",
        "consultant",
        "design",
        "decorator"
    ],
    "wof:name":"Bishop Decorating",
    "wof:placetype":"venue"
},
  "geometry": {"coordinates":[-87.94923900000001,41.600925],"type":"Point"}
}