{
  "type": "Feature",
  "properties": {
    "iso:country":"US",
    "sg:address":"3015 N Lincoln Ave",
    "sg:city":"Chicago",
    "sg:classifiers":[
        {
            "category":"Home & Garden",
            "subcategory":"Furniture",
            "type":"Retail Goods"
        }
    ],
    "sg:phone":"+1   ",
    "sg:postcode":"60657",
    "sg:province":"IL",
    "wof:name":"Modern Home Furnishing",
    "wof:placetype":"venue"
},
  "geometry": {"coordinates":[-87.665813,41.937693],"type":"Point"}
}