{
  "type": "Feature",
  "properties": {
    "addr:full":"1100 Chicago Ave Oak Park IL 60302",
    "addr:housenumber":"1100",
    "addr:postcode":"60302",
    "addr:street":"Chicago Ave",
    "iso:country":"US",
    "sg:address":"1100 Chicago Ave",
    "sg:city":"Oak Park",
    "sg:classifiers":[
        {
            "category":"Ice Cream",
            "type":"Food & Drink"
        }
    ],
    "sg:phone":"+1 708 386 6131",
    "sg:postcode":"60302",
    "sg:province":"IL",
    "sg:tags":[
        "frozen",
        "yogurt"
    ],
    "wof:name":"Petersen's Sweet Shoppe",
    "wof:placetype":"venue"
},
  "geometry": {"coordinates":[-87.803299,41.894299],"type":"Point"}
}