{
  "type": "Feature",
  "properties": {
    "iso:country":"US",
    "sg:address":"7501 Roosevelt Rd",
    "sg:city":"Forest Park",
    "sg:classifiers":[
        {
            "category":"Restaurant",
            "type":"Food & Drink"
        }
    ],
    "sg:phone":"+1 708 488 0123",
    "sg:postcode":"60130",
    "sg:province":"IL",
    "sg:tags":[
        "barbeque"
    ],
    "wof:name":"Smokin M's",
    "wof:placetype":"venue"
},
  "geometry": {"coordinates":[-87.81179400000001,41.86489],"type":"Point"}
}