{
  "type": "Feature",
  "properties": {
    "iso:country":"US",
    "sg:address":"303 Cedar St",
    "sg:city":"Champaign",
    "sg:classifiers":[
        {
            "category":"Restaurant",
            "type":"Food & Drink"
        }
    ],
    "sg:phone":"+1 217 351 7878",
    "sg:postcode":"61820",
    "sg:province":"IL",
    "sg:tags":[
        "sushi",
        "bar",
        "japanese"
    ],
    "wof:name":"Yellowfin",
    "wof:placetype":"venue"
},
  "geometry": {"coordinates":[-88.246734,40.09901],"type":"Point"}
}