{
  "type": "Feature",
  "properties": {
    "iso:country":"US",
    "sg:address":"12 S Locust St",
    "sg:city":"Manteno",
    "sg:classifiers":[
        {
            "category":"Restaurant",
            "type":"Food & Drink"
        }
    ],
    "sg:phone":"+1 815 468 7409",
    "sg:postcode":"60950",
    "sg:province":"IL",
    "sg:tags":[
        "pizza"
    ],
    "wof:name":"Monicals Pizza",
    "wof:placetype":"venue"
},
  "geometry": {"coordinates":[-87.833128,41.248164],"type":"Point"}
}