{
  "type": "Feature",
  "properties": {
    "iso:country":"US",
    "sg:address":"1401 Hill Avenue",
    "sg:city":"Wheaton",
    "sg:classifiers":[
        {
            "category":"Retail",
            "subcategory":"Pet Boarding",
            "type":"Services"
        }
    ],
    "sg:phone":"+1 630 588 8011",
    "sg:postcode":"60187",
    "sg:province":"IL",
    "sg:tags":[
        "boarding/pet",
        "sitting"
    ],
    "wof:name":"Three Bears Inn",
    "wof:placetype":"venue"
},
  "geometry": {"coordinates":[-88.086794,41.869762],"type":"Point"}
}