{
  "type": "Feature",
  "properties": {
    "addr:full":"110 E Main St Streator IL 61364",
    "addr:housenumber":"110",
    "addr:postcode":"61364",
    "addr:street":"E Main St",
    "iso:country":"US",
    "sg:address":"110 E Main St",
    "sg:city":"Streator",
    "sg:classifiers":[
        {
            "category":"Food & Beverages",
            "subcategory":"Supermarket",
            "type":"Retail Goods"
        },
        {
            "category":"Food & Beverages",
            "subcategory":"Groceries & Convenience Stores",
            "type":"Retail Goods"
        }
    ],
    "sg:phone":"+1 815 672 4145",
    "sg:postcode":"61364",
    "sg:province":"IL",
    "sg:tags":[
        "super"
    ],
    "wof:name":"La Mexicana",
    "wof:placetype":"venue"
},
  "geometry": {"coordinates":[-88.834789,41.120921],"type":"Point"}
}