{
  "type": "Feature",
  "properties": {
    "addr:full":"1517 Peoria St Peru IL 61354",
    "addr:housenumber":"1517",
    "addr:postcode":"61354",
    "addr:street":"Peoria St",
    "iso:country":"US",
    "sg:address":"1517 Peoria St",
    "sg:city":"Peru",
    "sg:classifiers":[
        {
            "category":"Bars & Pubs",
            "type":"Food & Drink"
        }
    ],
    "sg:phone":"+1 815 224 2443",
    "sg:postcode":"61354",
    "sg:province":"IL",
    "wof:name":"Vinnie's Tap",
    "wof:placetype":"venue"
},
  "geometry": {"coordinates":[-89.129142,41.334733],"type":"Point"}
}