{
  "type": "Feature",
  "properties": {
    "iso:country":"US",
    "sg:address":"101 W College St",
    "sg:city":"Carbondale",
    "sg:classifiers":[
        {
            "category":"Bars & Pubs",
            "type":"Food & Drink"
        }
    ],
    "sg:phone":"+1 618 351 8186",
    "sg:postcode":"62901",
    "sg:province":"IL",
    "sg:tags":[
        "restaurant"
    ],
    "sg:website":"http://www.sidetracksbar.com",
    "wof:name":"Sidetracks Bar & Grill",
    "wof:placetype":"venue"
},
  "geometry": {"coordinates":[-89.215698,37.721802],"type":"Point"}
}