{
  "type": "Feature",
  "properties": {
    "iso:country":"US",
    "sg:address":"5533 W Cermak Rd",
    "sg:city":"Cicero",
    "sg:classifiers":[
        {
            "category":"Health Services",
            "subcategory":"Doctor",
            "type":"Services"
        }
    ],
    "sg:phone":"+1 708 863 6366",
    "sg:postcode":"60804",
    "sg:province":"IL",
    "sg:tags":[
        "surgeon",
        "oral"
    ],
    "wof:name":"Valenciano Annamaria DDS",
    "wof:placetype":"venue"
},
  "geometry": {"coordinates":[-87.763397,41.8507],"type":"Point"}
}