{
  "type": "Feature",
  "properties": {
    "iso:country":"US",
    "sg:address":"76 N Country Club Rd",
    "sg:city":"Decatur",
    "sg:classifiers":[
        {
            "category":"Shopping",
            "subcategory":"Musical Instruments",
            "type":"Retail Goods"
        },
        {
            "category":"Retail",
            "subcategory":"Repair Shop",
            "type":"Services"
        }
    ],
    "sg:phone":"+1 217 429 5651",
    "sg:postcode":"62521",
    "sg:province":"IL",
    "sg:tags":[
        "organ",
        "supply",
        "pianos-parts",
        "organ-tuning",
        "piano",
        "restoration"
    ],
    "wof:name":"Baird, John",
    "wof:placetype":"venue"
},
  "geometry": {"coordinates":[-88.875015,39.850576],"type":"Point"}
}