{
  "type": "Feature",
  "properties": {
    "addr:full":"502 N Main St Homer IL 61849",
    "addr:housenumber":"502",
    "addr:postcode":"61849",
    "addr:street":"N Main St",
    "iso:country":"US",
    "sg:address":"502 N Main St",
    "sg:city":"Homer",
    "sg:phone":"+1 217 896 3328",
    "sg:postcode":"61849",
    "sg:province":"IL",
    "sg:website":"http://www.caseys.com",
    "wof:name":"Casey's General Store",
    "wof:placetype":"venue"
},
  "geometry": {"coordinates":[-87.95805900000001,40.038759],"type":"Point"}
}