{
  "type": "Feature",
  "properties": {
    "iso:country":"US",
    "sg:address":"3525 Arden Ave",
    "sg:city":"Brookfield",
    "sg:classifiers":[
        {
            "category":"Manufacturing",
            "subcategory":"Buildings",
            "type":"Manufacturing & Wholesale Goods"
        },
        {
            "category":"Building & Trades",
            "subcategory":"Construction",
            "type":"Services"
        }
    ],
    "sg:phone":"+1 708 485 0967",
    "sg:postcode":"60513",
    "sg:province":"IL",
    "sg:tags":[
        "home",
        "builder",
        "management",
        "contractor"
    ],
    "wof:name":"Corsini Construction Inc",
    "wof:placetype":"venue"
},
  "geometry": {"coordinates":[-87.83964,41.827386],"type":"Point"}
}