{
  "type": "Feature",
  "properties": {
    "iso:country":"US",
    "sg:address":"810 Biesterfield Rd",
    "sg:city":"Elk Grove Village",
    "sg:classifiers":[
        {
            "category":"Health Services",
            "subcategory":"Doctor",
            "type":"Services"
        }
    ],
    "sg:phone":"+1 847 981 8866",
    "sg:postcode":"60007",
    "sg:province":"IL",
    "sg:tags":[
        "medical"
    ],
    "wof:name":"Personal Wns Healthcare Svcs",
    "wof:placetype":"venue"
},
  "geometry": {"coordinates":[-88.017518,42.003531],"type":"Point"}
}