{
  "type": "Feature",
  "properties": {
    "iso:country":"US",
    "sg:address":"841 E 162nd St",
    "sg:city":"South Holland",
    "sg:classifiers":[
        {
            "category":"Health Services",
            "subcategory":"Chiropractor",
            "type":"Services"
        }
    ],
    "sg:phone":"+1 708 333 2211",
    "sg:postcode":"60473",
    "sg:province":"IL",
    "wof:name":"Halberstadt Chiropractic Clinic",
    "wof:placetype":"venue"
},
  "geometry": {"coordinates":[-87.59630300000001,41.600791],"type":"Point"}
}