{
  "type": "Feature",
  "properties": {
    "addr:full":"419 Bessie St Rushville IL 62681",
    "addr:housenumber":"419",
    "addr:postcode":"62681",
    "addr:street":"Bessie St",
    "iso:country":"US",
    "sg:address":"419 Bessie St",
    "sg:city":"Rushville",
    "sg:classifiers":[
        {
            "category":"Building & Trades",
            "subcategory":"Construction",
            "type":"Services"
        }
    ],
    "sg:phone":"+1 217 322 6396",
    "sg:postcode":"62681",
    "sg:province":"IL",
    "sg:tags":[
        "home",
        "builder"
    ],
    "wof:name":"Mark S Tyson",
    "wof:placetype":"venue"
},
  "geometry": {"coordinates":[-90.560632,40.12447],"type":"Point"}
}