{
  "type": "Feature",
  "properties": {
    "addr:full":"5444 S. Kedzie Chicago IL 60632",
    "addr:housenumber":"5444",
    "addr:postcode":"60632",
    "addr:street":"S. Kedzie",
    "iso:country":"US",
    "sg:address":"5444 S. Kedzie",
    "sg:city":"Chicago",
    "sg:classifiers":[
        {
            "category":"Personal",
            "subcategory":"Shoe Repair & Shine",
            "type":"Services"
        }
    ],
    "sg:postcode":"60632",
    "sg:province":"IL",
    "wof:name":"Leo's shoe repair",
    "wof:placetype":"venue"
},
  "geometry": {"coordinates":[-87.703918,41.794023],"type":"Point"}
}