{
  "type": "Feature",
  "properties": {
    "addr:full":"2905 Hanford Dr Rockford IL 61114",
    "addr:housenumber":"2905",
    "addr:postcode":"61114",
    "addr:street":"Hanford Dr",
    "iso:country":"US",
    "sg:address":"2905 Hanford Dr",
    "sg:city":"Rockford",
    "sg:classifiers":[
        {
            "category":"Building & Trades",
            "subcategory":"Construction",
            "type":"Services"
        }
    ],
    "sg:phone":"+1 815 986 0336",
    "sg:postcode":"61114",
    "sg:province":"IL",
    "sg:tags":[
        "general",
        "contractor"
    ],
    "wof:name":"Milestone",
    "wof:placetype":"venue"
},
  "geometry": {"coordinates":[-89.00241,42.302601],"type":"Point"}
}