{
  "type": "Feature",
  "properties": {
    "iso:country":"US",
    "sg:address":"3740 S Michigan Ave",
    "sg:city":"Chicago",
    "sg:classifiers":[
        {
            "category":"Building & Trades",
            "subcategory":"Construction",
            "type":"Services"
        }
    ],
    "sg:phone":"+1 773 268 2413",
    "sg:postcode":"60653",
    "sg:province":"IL",
    "wof:name":"Garth & Spears Cnstr Spc Co",
    "wof:placetype":"venue"
},
  "geometry": {"coordinates":[-87.623192,41.825466],"type":"Point"}
}