{
  "type": "Feature",
  "properties": {
    "iso:country":"US",
    "sg:address":"715 de Lasalle Ct",
    "sg:city":"Naperville",
    "sg:classifiers":[
        {
            "category":"Retail",
            "subcategory":"Storage",
            "type":"Services"
        }
    ],
    "sg:phone":"+1 630 717 5400",
    "sg:postcode":"60565",
    "sg:province":"IL",
    "sg:tags":[
        "container"
    ],
    "wof:name":"C & L America Inc",
    "wof:placetype":"venue"
},
  "geometry": {"coordinates":[-88.16096400000001,41.715177],"type":"Point"}
}