{
  "type": "Feature",
  "properties": {
    "addr:full":"5697 S Archer Ave Chicago IL 60638",
    "addr:housenumber":"5697",
    "addr:postcode":"60638",
    "addr:street":"S Archer Ave",
    "iso:country":"US",
    "sg:address":"5697 S Archer Ave",
    "sg:city":"Chicago",
    "sg:classifiers":[
        {
            "category":"Education",
            "subcategory":"Special Training",
            "type":"Public Place"
        }
    ],
    "sg:phone":"+1 773 585 6000",
    "sg:postcode":"60638",
    "sg:province":"IL",
    "sg:tags":[
        "tutoring"
    ],
    "wof:name":"Learning Specialties",
    "wof:placetype":"venue"
},
  "geometry": {"coordinates":[-87.75378600000001,41.797022],"type":"Point"}
}