{
  "type": "Feature",
  "properties": {
    "addr:full":"469 Chesterfield Ln Vernon Hills IL 60061",
    "addr:housenumber":"469",
    "addr:postcode":"60061",
    "addr:street":"Chesterfield Ln",
    "iso:country":"US",
    "sg:address":"469 Chesterfield Ln",
    "sg:city":"Vernon Hills",
    "sg:classifiers":[
        {
            "category":"Professional",
            "subcategory":"Management & Consulting",
            "type":"Services"
        }
    ],
    "sg:phone":"+1 847 816 8611",
    "sg:postcode":"60061",
    "sg:province":"IL",
    "sg:tags":[
        "consultant",
        "business"
    ],
    "sg:website":"www.orf-usa.com",
    "wof:name":"Organizational Research Forum",
    "wof:placetype":"venue"
},
  "geometry": {"coordinates":[-87.970411,42.21822],"type":"Point"}
}