{
  "type": "Feature",
  "properties": {
    "addr:full":"701 Belvidere St Waukegan IL 60085",
    "addr:housenumber":"701",
    "addr:postcode":"60085",
    "addr:street":"Belvidere St",
    "iso:country":"US",
    "sg:address":"701 Belvidere St",
    "sg:city":"Waukegan",
    "sg:classifiers":[
        {
            "category":"Wholesale",
            "subcategory":"Fruits & Vegetables",
            "type":"Manufacturing & Wholesale Goods"
        }
    ],
    "sg:phone":"+1 847 623 2370",
    "sg:postcode":"60085",
    "sg:province":"IL",
    "wof:name":"Corso Produce Co Inc",
    "wof:placetype":"venue"
},
  "geometry": {"coordinates":[-87.83969,42.352889],"type":"Point"}
}