{
  "type": "Feature",
  "properties": {
    "addr:full":"24041 103rd St Naperville IL 60564",
    "addr:housenumber":"24041",
    "addr:postcode":"60564",
    "addr:street":"103Rd St",
    "iso:country":"US",
    "sg:address":"24041 103rd St",
    "sg:city":"Naperville",
    "sg:classifiers":[
        {
            "category":"Retail",
            "subcategory":"Veterinary Services",
            "type":"Services"
        }
    ],
    "sg:phone":"+1 888 527 0327",
    "sg:postcode":"60564",
    "sg:province":"IL",
    "sg:tags":[
        "hospital",
        "veterinarian",
        "clinic",
        "laboratories-veterinary"
    ],
    "sg:website":"http://local.ingenio.com/Listings/Details.aspx?NUM=a%3a9243408%3a13%3a4859924%3a14%3a0%3a7",
    "wof:name":"Wheatland Animal Hospital",
    "wof:placetype":"venue"
},
  "geometry": {"coordinates":[-88.206017,41.69521],"type":"Point"}
}