{
  "type": "Feature",
  "properties": {
    "addr:full":"1510 Frontage Rd Okawville IL 62271",
    "addr:housenumber":"1510",
    "addr:postcode":"62271",
    "addr:street":"Frontage Rd",
    "iso:country":"US",
    "sg:address":"1510 Frontage Rd",
    "sg:city":"Okawville",
    "sg:classifiers":[
        {
            "category":"Restaurant",
            "type":"Food & Drink"
        }
    ],
    "sg:menulink":"http://www.allmenus.com/il/okawville/127178-subway/menu/",
    "sg:phone":"+1 618 243 1001",
    "sg:postcode":"62271",
    "sg:province":"IL",
    "sg:tags":[
        "american",
        "sandwich"
    ],
    "wof:name":"Subway",
    "wof:placetype":"venue"
},
  "geometry": {"coordinates":[-89.53842400000001,38.436153],"type":"Point"}
}