{
  "type": "Feature",
  "properties": {
    "iso:country":"US",
    "sg:address":"5557 E Hunts Grove Rd",
    "sg:city":"Ashton",
    "sg:phone":"+1 815 453 2426",
    "sg:postcode":"61006",
    "sg:province":"IL",
    "sg:tags":[
        "farm",
        "soybean"
    ],
    "wof:name":"Frances Young",
    "wof:placetype":"venue"
},
  "geometry": {"coordinates":[-89.236823,41.908345],"type":"Point"}
}