{
  "type": "Feature",
  "properties": {
    "iso:country":"US",
    "sg:address":"56 Norfolk Ave",
    "sg:city":"Clarendon Hills",
    "sg:classifiers":[
        {
            "category":"Professional",
            "subcategory":"Computer Services",
            "type":"Services"
        }
    ],
    "sg:phone":"+1 630 323 1022",
    "sg:postcode":"60514",
    "sg:province":"IL",
    "sg:tags":[
        "programing",
        "custom"
    ],
    "wof:name":"Derer Systems Inc",
    "wof:placetype":"venue"
},
  "geometry": {"coordinates":[-87.949545,41.802302],"type":"Point"}
}