{
  "type": "Feature",
  "properties": {
    "addr:full":"1137 Pine St Batavia IL 60510",
    "addr:housenumber":"1137",
    "addr:postcode":"60510",
    "addr:street":"Pine St",
    "iso:country":"US",
    "sg:address":"1137 Pine St",
    "sg:city":"Batavia",
    "sg:classifiers":[
        {
            "category":"Professional",
            "subcategory":"Business Services",
            "type":"Services"
        }
    ],
    "sg:phone":"+1 630 879 2204",
    "sg:postcode":"60510",
    "sg:province":"IL",
    "sg:tags":[
        "school",
        "vocational"
    ],
    "wof:name":"Illinois Drafting Educaters",
    "wof:placetype":"venue"
},
  "geometry": {"coordinates":[-88.286655,41.842039],"type":"Point"}
}