{
  "type": "Feature",
  "properties": {
    "addr:full":"3932 W. Irving Park Rd Chicago IL 60618",
    "addr:housenumber":"3932",
    "addr:postcode":"60618",
    "addr:street":"W. Irving Park Rd",
    "iso:country":"US",
    "sg:address":"3932 W. Irving Park Rd",
    "sg:city":"Chicago",
    "sg:classifiers":[
        {
            "category":"Bars & Pubs",
            "type":"Food & Drink"
        }
    ],
    "sg:phone":"+1 773 588 2385",
    "sg:postcode":"60618",
    "sg:province":"IL",
    "wof:name":"Independence Tap",
    "wof:placetype":"venue"
},
  "geometry": {"coordinates":[-87.726547,41.953727],"type":"Point"}
}