{
  "type": "Feature",
  "properties": {
    "addr:full":"117 N College Ave Aledo IL 61231",
    "addr:housenumber":"117",
    "addr:postcode":"61231",
    "addr:street":"N College Ave",
    "iso:country":"US",
    "sg:address":"117 N College Ave",
    "sg:city":"Aledo",
    "sg:classifiers":[
        {
            "category":"Government",
            "subcategory":"Post Office",
            "type":"Public Place"
        }
    ],
    "sg:phone":"+1 309 582 7113",
    "sg:postcode":"61231",
    "sg:province":"IL",
    "sg:tags":[
        "postal",
        "us"
    ],
    "wof:name":"US Post Office",
    "wof:placetype":"venue"
},
  "geometry": {"coordinates":[-90.749292,41.202411],"type":"Point"}
}