{
  "type": "Feature",
  "properties": {
    "iso:country":"US",
    "sg:address":"160 Halfmoon Ct",
    "sg:city":"Lincoln",
    "sg:classifiers":[
        {
            "category":"Manufacturing",
            "subcategory":"Musical Instruments",
            "type":"Manufacturing & Wholesale Goods"
        }
    ],
    "sg:phone":"+1 217 732 6933",
    "sg:postcode":"62656",
    "sg:province":"IL",
    "sg:tags":[
        "mfg"
    ],
    "wof:name":"Hollenbeck Guitar",
    "wof:placetype":"venue"
},
  "geometry": {"coordinates":[-89.341404,40.158802],"type":"Point"}
}