{
  "type": "Feature",
  "properties": {
    "addr:full":"10339 S Troy Street Chicago IL 60655",
    "addr:housenumber":"10339",
    "addr:postcode":"60655",
    "addr:street":"S Troy Street",
    "iso:country":"US",
    "sg:address":"10339 S Troy Street",
    "sg:city":"Chicago",
    "sg:classifiers":[
        {
            "category":"Shopping",
            "subcategory":"Stationery & Office Supplies",
            "type":"Retail Goods"
        },
        {
            "category":"Wholesale",
            "subcategory":"Office Equipment",
            "type":"Manufacturing & Wholesale Goods"
        },
        {
            "category":"Professional",
            "subcategory":"Business Services",
            "type":"Services"
        },
        {
            "category":"Professional",
            "subcategory":"Printing & Photocopies",
            "type":"Services"
        },
        {
            "category":"Wholesale",
            "subcategory":"Computers",
            "type":"Manufacturing & Wholesale Goods"
        }
    ],
    "sg:phone":"+1 773 779 3619",
    "sg:postcode":"60655",
    "sg:province":"IL",
    "sg:tags":[
        "form",
        "register",
        "autographic",
        "system",
        "printers-business"
    ],
    "wof:name":"F B S Business Forms",
    "wof:placetype":"venue"
},
  "geometry": {"coordinates":[-87.69994699999999,41.705561],"type":"Point"}
}