{
  "type": "Feature",
  "properties": {
    "addr:full":"2218 N Geneva Ter Chicago IL 60614",
    "addr:housenumber":"2218",
    "addr:postcode":"60614",
    "addr:street":"N Geneva Ter",
    "iso:country":"US",
    "sg:address":"2218 N Geneva Ter",
    "sg:city":"Chicago",
    "sg:classifiers":[
        {
            "category":"Real Estate",
            "subcategory":"Real Estate Services",
            "type":"Services"
        }
    ],
    "sg:phone":"+1 773 883 5151",
    "sg:postcode":"60614",
    "sg:province":"IL",
    "sg:tags":[
        "management",
        "property"
    ],
    "wof:name":"Val Realty & Management Co Inc",
    "wof:placetype":"venue"
},
  "geometry": {"coordinates":[-87.64360000000001,41.922199],"type":"Point"}
}