{
  "type": "Feature",
  "properties": {
    "iso:country":"US",
    "sg:address":"2580 Prospect Ct Ste 101",
    "sg:city":"Aurora",
    "sg:classifiers":[
        {
            "category":"Manufacturing",
            "subcategory":"Printing",
            "type":"Manufacturing & Wholesale Goods"
        }
    ],
    "sg:phone":"+1 630 499 5900",
    "sg:postcode":"60502",
    "sg:province":"IL",
    "sg:tags":[
        "supplies-wholesale",
        "copier",
        "manufacturer"
    ],
    "wof:name":"Canon U.S.A., Inc.",
    "wof:placetype":"venue"
},
  "geometry": {"coordinates":[-88.234843,41.808882],"type":"Point"}
}