{
  "type": "Feature",
  "properties": {
    "addr:full":"320 Kress Rd West Chicago IL 60185",
    "addr:housenumber":"320",
    "addr:postcode":"60185",
    "addr:street":"Kress Rd West",
    "iso:country":"US",
    "sg:address":"320 Kress Rd",
    "sg:city":"West Chicago",
    "sg:classifiers":[
        {
            "category":"Airline",
            "type":"Transportation"
        }
    ],
    "sg:phone":"+1 630 293 3600",
    "sg:postcode":"60185",
    "sg:province":"IL",
    "sg:tags":[
        "helicopter"
    ],
    "wof:name":"Great Lakes Helicopters Inc",
    "wof:placetype":"venue"
},
  "geometry": {"coordinates":[-88.24320299999999,41.892382],"type":"Point"}
}