{
  "type": "Feature",
  "properties": {
    "iso:country":"US",
    "sg:address":"8810 W Johnson Farm Rd",
    "sg:city":"Peoria",
    "sg:classifiers":[
        {
            "category":"Building & Trades",
            "subcategory":"Construction",
            "type":"Services"
        }
    ],
    "sg:phone":"+1 309 697 1600",
    "sg:postcode":"61607",
    "sg:province":"IL",
    "sg:tags":[
        "wallcoverings-installation",
        "wallpaper",
        "painting",
        "contractor"
    ],
    "wof:name":"Hoerdeman Painting & Decorating",
    "wof:placetype":"venue"
},
  "geometry": {"coordinates":[-89.734396,40.667042],"type":"Point"}
}