{
  "type": "Feature",
  "properties": {
    "addr:full":"3650 183rd St Homewood IL 60430",
    "addr:housenumber":"3650",
    "addr:postcode":"60430",
    "addr:street":"183Rd St",
    "iso:country":"US",
    "sg:address":"3650 183rd St",
    "sg:city":"Homewood",
    "sg:classifiers":[
        {
            "category":"Manufacturing",
            "subcategory":"Printing",
            "type":"Manufacturing & Wholesale Goods"
        }
    ],
    "sg:phone":"+1 708 206 2054",
    "sg:postcode":"60430",
    "sg:province":"IL",
    "sg:tags":[
        "consulting",
        "management",
        "book"
    ],
    "wof:name":"High Tide Press",
    "wof:placetype":"venue"
},
  "geometry": {"coordinates":[-87.706434,41.557145],"type":"Point"}
}