{
  "type": "Feature",
  "properties": {
    "iso:country":"US",
    "sg:address":"1007 Hampton Rd",
    "sg:city":"Washington",
    "sg:classifiers":[
        {
            "category":"Manufacturing",
            "subcategory":"Food",
            "type":"Manufacturing & Wholesale Goods"
        }
    ],
    "sg:phone":"+1 309 696 1536",
    "sg:postcode":"61571",
    "sg:province":"IL",
    "sg:tags":[
        "product"
    ],
    "wof:name":"Wissel Enterprise",
    "wof:placetype":"venue"
},
  "geometry": {"coordinates":[-89.41640599999999,40.71445],"type":"Point"}
}