{
  "type": "Feature",
  "properties": {
    "iso:country":"US",
    "sg:address":"230 Virginia Rd",
    "sg:city":"Crystal Lake",
    "sg:classifiers":[
        {
            "category":"Shopping",
            "subcategory":"Computers & Home Electronics",
            "type":"Retail Goods"
        }
    ],
    "sg:phone":"+1 815 459 7874",
    "sg:postcode":"60014",
    "sg:province":"IL",
    "sg:tags":[
        "equipment",
        "electronic",
        "supply"
    ],
    "wof:name":"Best Buy",
    "wof:placetype":"venue"
},
  "geometry": {"coordinates":[-88.311054,42.212067],"type":"Point"}
}