{
  "type": "Feature",
  "properties": {
    "iso:country":"US",
    "sg:address":"5521 Meadowbrook Ct",
    "sg:city":"Rolling Meadows",
    "sg:classifiers":[
        {
            "category":"Manufacturing",
            "subcategory":"Electronics",
            "type":"Manufacturing & Wholesale Goods"
        }
    ],
    "sg:phone":"+1 847 228 0900",
    "sg:postcode":"60008",
    "sg:province":"IL",
    "sg:tags":[
        "electronic",
        "assembles",
        "component",
        "mfg"
    ],
    "sg:website":"www.injectit.com",
    "wof:name":"Four Star Tool Inc",
    "wof:placetype":"venue"
},
  "geometry": {"coordinates":[-88.009722,42.055455],"type":"Point"}
}