{
  "type": "Feature",
  "properties": {
    "iso:country":"US",
    "sg:address":"209 E Grantley Ave",
    "sg:city":"Elmhurst",
    "sg:classifiers":[
        {
            "category":"Shopping",
            "subcategory":"Gifts & Souvenirs",
            "type":"Retail Goods"
        }
    ],
    "sg:phone":"+1   ",
    "sg:postcode":"60126",
    "sg:province":"IL",
    "wof:name":"Brittish Shop Inc",
    "wof:placetype":"venue"
},
  "geometry": {"coordinates":[-87.936047,41.908541],"type":"Point"}
}