{
  "type": "Feature",
  "properties": {
    "addr:full":"8010 S Kedzie Ave Chicago IL 60652",
    "addr:housenumber":"8010",
    "addr:postcode":"60652",
    "addr:street":"S Kedzie Ave",
    "iso:country":"US",
    "sg:address":"8010 S Kedzie Ave",
    "sg:city":"Chicago",
    "sg:classifiers":[
        {
            "category":"Food & Beverages",
            "subcategory":"Liquor & Beverages",
            "type":"Retail Goods"
        }
    ],
    "sg:phone":"+1 773 476 2600",
    "sg:postcode":"60652",
    "sg:province":"IL",
    "sg:tags":[
        "beer",
        "spirit",
        "wine"
    ],
    "wof:name":"Locascio Sports Bar",
    "wof:placetype":"venue"
},
  "geometry": {"coordinates":[-87.7024,41.747501],"type":"Point"}
}