{
  "type": "Feature",
  "properties": {
    "addr:full":"1405 Adams St Lake In The Hills IL 60156",
    "addr:housenumber":"1405",
    "addr:postcode":"60156",
    "addr:street":"Adams St",
    "iso:country":"US",
    "sg:address":"1405 Adams St",
    "sg:city":"Lake In The Hills",
    "sg:classifiers":[
        {
            "category":"Building & Trades",
            "subcategory":"Construction",
            "type":"Services"
        }
    ],
    "sg:phone":"+1 847 658 6752",
    "sg:postcode":"60156",
    "sg:province":"IL",
    "sg:tags":[
        "installation",
        "drapery"
    ],
    "wof:name":"Hoeks Quality Services",
    "wof:placetype":"venue"
},
  "geometry": {"coordinates":[-88.331676,42.194757],"type":"Point"}
}