{
  "type": "Feature",
  "properties": {
    "iso:country":"US",
    "sg:address":"325 Gladstone St",
    "sg:city":"Jacksonville",
    "sg:phone":"+1 217 245 4001",
    "sg:postcode":"62650",
    "sg:province":"IL",
    "sg:tags":[
        "farm",
        "corn",
        "soybean"
    ],
    "wof:name":"Cully Farm",
    "wof:placetype":"venue"
},
  "geometry": {"coordinates":[-90.24344600000001,39.730609],"type":"Point"}
}