{
  "type": "Feature",
  "properties": {
    "iso:country":"US",
    "sg:address":"320 W South St",
    "sg:city":"Cambridge",
    "sg:classifiers":[
        {
            "category":"Personal",
            "subcategory":"Beauty Salon",
            "type":"Services"
        }
    ],
    "sg:phone":"+1 309 937 1133",
    "sg:postcode":"61238",
    "sg:province":"IL",
    "wof:name":"Becht Darla Hair & Nail Salon",
    "wof:placetype":"venue"
},
  "geometry": {"coordinates":[-90.196613,41.299512],"type":"Point"}
}