{
  "type": "Feature",
  "properties": {
    "iso:country":"US",
    "sg:address":"1000 N Monticello Ave",
    "sg:city":"Chicago",
    "sg:classifiers":[
        {
            "category":"Food & Beverages",
            "subcategory":"Groceries & Convenience Stores",
            "type":"Retail Goods"
        }
    ],
    "sg:phone":"+1   ",
    "sg:postcode":"60651",
    "sg:province":"IL",
    "wof:name":"Monticello Food",
    "wof:placetype":"venue"
},
  "geometry": {"coordinates":[-87.717717,41.900919],"type":"Point"}
}