{
  "type": "Feature",
  "properties": {
    "iso:country":"US",
    "sg:address":"2044 Ridge Rd",
    "sg:city":"Homewood",
    "sg:classifiers":[
        {
            "category":"Professional",
            "subcategory":"Lawyer & Legal Services",
            "type":"Services"
        }
    ],
    "sg:phone":"+1 708 799 0600",
    "sg:postcode":"60430",
    "sg:province":"IL",
    "sg:tags":[
        "attorney"
    ],
    "wof:name":"William P Butcher",
    "wof:placetype":"venue"
},
  "geometry": {"coordinates":[-87.667476,41.56208],"type":"Point"}
}