{
  "type": "Feature",
  "properties": {
    "addr:full":"276 W Rand Rd Arlington Hts IL 60004",
    "addr:housenumber":"276",
    "addr:postcode":"60004",
    "addr:street":"W Rand Rd",
    "iso:country":"US",
    "sg:address":"276 W Rand Rd",
    "sg:city":"Arlington Hts",
    "sg:classifiers":[
        {
            "category":"Personal",
            "subcategory":"Beauty Salon",
            "type":"Services"
        }
    ],
    "sg:phone":"+1 847 670 8030",
    "sg:postcode":"60004",
    "sg:province":"IL",
    "sg:tags":[
        "manicuring"
    ],
    "wof:name":"Expert Nails",
    "wof:placetype":"venue"
},
  "geometry": {"coordinates":[-87.986441,42.116631],"type":"Point"}
}