{
  "type": "Feature",
  "properties": {
    "addr:full":"202 E Greenwood Ave Jacksonville IL 62650",
    "addr:housenumber":"202",
    "addr:postcode":"62650",
    "addr:street":"E Greenwood Ave",
    "iso:country":"US",
    "sg:address":"202 E Greenwood Ave",
    "sg:city":"Jacksonville",
    "sg:classifiers":[
        {
            "category":"Shopping",
            "subcategory":"Used Merchandise",
            "type":"Retail Goods"
        }
    ],
    "sg:phone":"+1   ",
    "sg:postcode":"62650",
    "sg:province":"IL",
    "wof:name":"Just Like New",
    "wof:placetype":"venue"
},
  "geometry": {"coordinates":[-90.226899,39.712271],"type":"Point"}
}