{
  "type": "Feature",
  "properties": {
    "addr:full":"4432 N Troy Street Chicago IL 60625",
    "addr:housenumber":"4432",
    "addr:postcode":"60625",
    "addr:street":"N Troy Street",
    "iso:country":"US",
    "sg:address":"4432 N Troy Street",
    "sg:city":"Chicago",
    "sg:classifiers":[
        {
            "category":"Place Of Worship",
            "subcategory":"Church",
            "type":"Public Place"
        },
        {
            "category":"Place Of Worship",
            "type":"Public Place"
        },
        {
            "category":"Organizations",
            "subcategory":"Religious Organization",
            "type":"Services"
        }
    ],
    "sg:phone":"+1 773 588 2620",
    "sg:postcode":"60625",
    "sg:province":"IL",
    "sg:tags":[
        "churches-catholic-traditional",
        "churches-catholic"
    ],
    "sg:website":"http://www.olmchicago.com/",
    "wof:name":"Our Lady of Mercy Church",
    "wof:placetype":"venue"
},
  "geometry": {"coordinates":[-87.706931,41.9621],"type":"Point"}
}