{
  "type": "Feature",
  "properties": {
    "addr:full":"60 W Randolph St Ste 200 Chicago IL 60601",
    "addr:housenumber":"60",
    "addr:postcode":"60601",
    "addr:street":"W Randolph St Ste 200",
    "iso:country":"US",
    "sg:address":"60 W Randolph St Ste 200",
    "sg:city":"Chicago",
    "sg:classifiers":[
        {
            "category":"Travel",
            "subcategory":"Hotels & Motels",
            "type":"Entertainment"
        },
        {
            "category":"Travel",
            "subcategory":"Bed & Breakfast",
            "type":"Entertainment"
        }
    ],
    "sg:phone":"+1 312 795 1700",
    "sg:postcode":"60601",
    "sg:province":"IL",
    "wof:name":"Chicago Plus",
    "wof:placetype":"venue"
},
  "geometry": {"coordinates":[-87.62979900000001,41.884506],"type":"Point"}
}