{
  "type": "Feature",
  "properties": {
    "iso:country":"US",
    "sg:address":"2206 Birch St",
    "sg:city":"Olney",
    "sg:classifiers":[
        {
            "category":"Professional",
            "subcategory":"Lawyer & Legal Services",
            "type":"Services"
        }
    ],
    "sg:phone":"+1 618 392 2613",
    "sg:postcode":"62450",
    "sg:province":"IL",
    "sg:tags":[
        "attorney"
    ],
    "wof:name":"Cindy Foerster",
    "wof:placetype":"venue"
},
  "geometry": {"coordinates":[-88.059122,38.729199],"type":"Point"}
}