{
  "type": "Feature",
  "properties": {
    "iso:country":"US",
    "sg:address":"808 W Front St",
    "sg:city":"Roanoke",
    "sg:classifiers":[
        {
            "category":"Insurance",
            "subcategory":"Hazard Insurance",
            "type":"Services"
        }
    ],
    "sg:phone":"+1 309 923 7215",
    "sg:postcode":"61561",
    "sg:province":"IL",
    "wof:name":"Joe K Brown",
    "wof:placetype":"venue"
},
  "geometry": {"coordinates":[-89.206907,40.793518],"type":"Point"}
}