{
  "type": "Feature",
  "properties": {
    "iso:country":"US",
    "sg:address":"508 E Green St",
    "sg:city":"Champaign",
    "sg:classifiers":[
        {
            "category":"Restaurant",
            "type":"Food & Drink"
        }
    ],
    "sg:phone":"+1 217 344 4000",
    "sg:postcode":"61820",
    "sg:province":"IL",
    "sg:tags":[
        "pizza"
    ],
    "sg:website":"1worldpizza.com",
    "wof:name":"One World Pizza",
    "wof:placetype":"venue"
},
  "geometry": {"coordinates":[-88.23193999999999,40.110286],"type":"Point"}
}