{
  "type": "Feature",
  "properties": {
    "addr:full":"1275 W. Roosevelt Rd Ste 120 Chicago IL 66062",
    "addr:housenumber":"1275",
    "addr:postcode":"66062",
    "addr:street":"W. Roosevelt Rd Ste 120",
    "iso:country":"US",
    "sg:address":"1275 W. Roosevelt Rd Ste 120",
    "sg:city":"Chicago",
    "sg:classifiers":[
        {
            "category":"Health Services",
            "subcategory":"Clinic",
            "type":"Services"
        }
    ],
    "sg:phone":"+1 630 231 0501",
    "sg:postcode":"66062",
    "sg:province":"IL",
    "sg:tags":[
        "medical"
    ],
    "sg:website":"www.silvercross.com",
    "wof:name":"SILVER CROSS Chicago West",
    "wof:placetype":"venue"
},
  "geometry": {"coordinates":[-87.658992,41.866891],"type":"Point"}
}