{
  "type": "Feature",
  "properties": {
    "addr:full":"3529 Union Ave Steger IL 60475",
    "addr:housenumber":"3529",
    "addr:postcode":"60475",
    "addr:street":"Union Ave",
    "iso:country":"US",
    "sg:address":"3529 Union Ave",
    "sg:city":"Steger",
    "sg:classifiers":[
        {
            "category":"Building & Trades",
            "subcategory":"Plumbing",
            "type":"Services"
        }
    ],
    "sg:phone":"+1 708 756 3390",
    "sg:postcode":"60475",
    "sg:province":"IL",
    "sg:tags":[
        "plumber",
        "industrial",
        "contractors-commercial"
    ],
    "wof:name":"Lgm Construction Co.",
    "wof:placetype":"venue"
},
  "geometry": {"coordinates":[-87.632927,41.466874],"type":"Point"}
}