{
  "type": "Feature",
  "properties": {
    "addr:full":"3158 S River Rd Des Plaines IL 60018",
    "addr:housenumber":"3158",
    "addr:postcode":"60018",
    "addr:street":"S River Rd Des",
    "iso:country":"US",
    "sg:address":"3158 S River Rd",
    "sg:city":"Des Plaines",
    "sg:classifiers":[
        {
            "category":"Insurance",
            "subcategory":"Insurance Agent",
            "type":"Services"
        }
    ],
    "sg:phone":"+1 847 299 6670",
    "sg:postcode":"60018",
    "sg:province":"IL",
    "wof:name":"First Midwest Insurance Group",
    "wof:placetype":"venue"
},
  "geometry": {"coordinates":[-87.862666,41.9979],"type":"Point"}
}