{
  "type": "Feature",
  "properties": {
    "addr:full":"3935 W 67th Pl Chicago IL 60629",
    "addr:housenumber":"3935",
    "addr:postcode":"60629",
    "addr:street":"W 67Th Pl",
    "iso:country":"US",
    "sg:address":"3935 W 67th Pl",
    "sg:city":"Chicago",
    "sg:classifiers":[
        {
            "category":"Professional",
            "subcategory":"Art Services",
            "type":"Services"
        },
        {
            "category":"Building & Trades",
            "subcategory":"Construction",
            "type":"Services"
        }
    ],
    "sg:phone":"+1 773 582 5641",
    "sg:postcode":"60629",
    "sg:province":"IL",
    "sg:tags":[
        "designer",
        "wallcoverings-installation",
        "wallpaper",
        "contractor",
        "design",
        "interior",
        "painting",
        "decorator"
    ],
    "wof:name":"New Era Painting",
    "wof:placetype":"venue"
},
  "geometry": {"coordinates":[-87.720932,41.770336],"type":"Point"}
}