{
  "type": "Feature",
  "properties": {
    "iso:country":"US",
    "sg:address":"14902 Freeport Rd",
    "sg:city":"Durand",
    "sg:classifiers":[
        {
            "category":"Professional",
            "type":"Services"
        }
    ],
    "sg:phone":"+1 815 248 2503",
    "sg:postcode":"61024",
    "sg:province":"IL",
    "wof:name":"James W McCartney",
    "wof:placetype":"venue"
},
  "geometry": {"coordinates":[-89.329404,42.418877],"type":"Point"}
}