{
  "type": "Feature",
  "properties": {
    "addr:full":"1510 Bridge Point Ln Champaign IL 61822",
    "addr:housenumber":"1510",
    "addr:postcode":"61822",
    "addr:street":"Bridge Point Ln",
    "iso:country":"US",
    "sg:address":"1510 Bridge Point Ln",
    "sg:city":"Champaign",
    "sg:classifiers":[
        {
            "category":"Health Services",
            "subcategory":"Dentist",
            "type":"Services"
        }
    ],
    "sg:phone":"+1 217 351 5108",
    "sg:postcode":"61822",
    "sg:province":"IL",
    "wof:name":"Namoff, Mike",
    "wof:placetype":"venue"
},
  "geometry": {"coordinates":[-88.30848899999999,40.099826],"type":"Point"}
}