{
  "type": "Feature",
  "properties": {
    "iso:country":"US",
    "sg:address":"729 34th Ave",
    "sg:city":"Rock Island",
    "sg:classifiers":[
        {
            "category":"Social Services",
            "type":"Services"
        }
    ],
    "sg:phone":"+1 309 793 6800",
    "sg:postcode":"61201",
    "sg:province":"IL",
    "sg:tags":[
        "assist",
        "elderly"
    ],
    "wof:name":"Western Illinois Agcy On Aging",
    "wof:placetype":"venue"
},
  "geometry": {"coordinates":[-90.590469,41.477542],"type":"Point"}
}