{
  "type": "Feature",
  "properties": {
    "iso:country":"US",
    "sg:address":"111 N Worrell St",
    "sg:city":"Bowen",
    "sg:classifiers":[
        {
            "category":"Personal",
            "subcategory":"Beauty Salon",
            "type":"Services"
        }
    ],
    "sg:phone":"+1 217 842 5404",
    "sg:postcode":"62316",
    "sg:province":"IL",
    "wof:name":"Head To Toes",
    "wof:placetype":"venue"
},
  "geometry": {"coordinates":[-91.064726,40.232487],"type":"Point"}
}