{
  "type": "Feature",
  "properties": {
    "iso:country":"US",
    "sg:address":"1250 E Beecher Rd",
    "sg:city":"Bristol",
    "sg:classifiers":[
        {
            "category":"Manufacturing",
            "subcategory":"Petroleum Products",
            "type":"Manufacturing & Wholesale Goods"
        }
    ],
    "sg:phone":"+1 630 553 6610",
    "sg:postcode":"60512",
    "sg:province":"IL",
    "sg:tags":[
        "asphalt",
        "mfg"
    ],
    "wof:name":"Aurora Blacktop Inc",
    "wof:placetype":"venue"
},
  "geometry": {"coordinates":[-88.467905,41.703729],"type":"Point"}
}