{
  "type": "Feature",
  "properties": {
    "iso:country":"US",
    "sg:address":"2002 W Ringwood Rd",
    "sg:city":"Mchenry",
    "sg:classifiers":[
        {
            "category":"Place Of Worship",
            "subcategory":"Church",
            "type":"Public Place"
        },
        {
            "category":"Place Of Worship",
            "type":"Public Place"
        }
    ],
    "sg:phone":"+1 815 363 7800",
    "sg:postcode":"60051",
    "sg:province":"IL",
    "sg:tags":[
        "christ",
        "churches-non-denominational",
        "churches-christian",
        "churches-community"
    ],
    "sg:website":"http://www.meadowlandchurch.org",
    "wof:name":"Meadowland Church",
    "wof:placetype":"venue"
},
  "geometry": {"coordinates":[-88.236395,42.401406],"type":"Point"}
}