{
  "type": "Feature",
  "properties": {
    "addr:full":"16294 Mission Field Rd Oakwood IL 61858",
    "addr:housenumber":"16294",
    "addr:postcode":"61858",
    "addr:street":"Mission Field Rd",
    "iso:country":"US",
    "sg:address":"16294 Mission Field Rd",
    "sg:city":"Oakwood",
    "sg:classifiers":[
        {
            "category":"Freight",
            "type":"Transportation"
        }
    ],
    "sg:phone":"+1 217 354 4495",
    "sg:postcode":"61858",
    "sg:province":"IL",
    "sg:tags":[
        "operator",
        "trucking"
    ],
    "wof:name":"Dean McVey Trucking Inc",
    "wof:placetype":"venue"
},
  "geometry": {"coordinates":[-87.753714,40.105054],"type":"Point"}
}