{
  "type": "Feature",
  "properties": {
    "iso:country":"US",
    "sg:address":"231 N Pine Avenue",
    "sg:city":"Chicago",
    "sg:classifiers":[
        {
            "category":"Education",
            "subcategory":"School",
            "type":"Public Place"
        }
    ],
    "sg:phone":"+1 773 534 6300",
    "sg:postcode":"60644",
    "sg:province":"IL",
    "sg:tags":[
        "high",
        "middle",
        "elementary"
    ],
    "wof:name":"City of Chicago School District 299",
    "wof:placetype":"venue"
},
  "geometry": {"coordinates":[-87.76335899999999,41.884772],"type":"Point"}
}