{
  "type": "Feature",
  "properties": {
    "iso:country":"US",
    "sg:address":"1777 N Cedar Lake Rd",
    "sg:city":"Round Lake",
    "sg:classifiers":[
        {
            "category":"Organizations",
            "subcategory":"Professional Association",
            "type":"Services"
        }
    ],
    "sg:phone":"+1 847 546 2002",
    "sg:postcode":"60073",
    "sg:province":"IL",
    "sg:tags":[
        "business"
    ],
    "wof:name":"Round Lk Area Chamber Commerce",
    "wof:placetype":"venue"
},
  "geometry": {"coordinates":[-88.089724,42.366192],"type":"Point"}
}