{
  "type": "Feature",
  "properties": {
    "addr:full":"2551 N Clark St Ste 303 Chicago IL 60614",
    "addr:housenumber":"2551",
    "addr:postcode":"60614",
    "addr:street":"N Clark St Ste 303",
    "iso:country":"US",
    "sg:address":"2551 N Clark St Ste 303",
    "sg:city":"Chicago",
    "sg:classifiers":[
        {
            "category":"Health Services",
            "subcategory":"Doctor",
            "type":"Services"
        }
    ],
    "sg:phone":"+1 312 623 2625",
    "sg:postcode":"60614",
    "sg:province":"IL",
    "sg:tags":[
        "practice",
        "family"
    ],
    "sg:website":"www.AnalDysplasiaClinic.com",
    "wof:name":"Gary Bucher, MD",
    "wof:placetype":"venue"
},
  "geometry": {"coordinates":[-87.64251,41.92927],"type":"Point"}
}