{
  "type": "Feature",
  "properties": {
    "addr:full":"501 18th Ave Rockford IL 61104",
    "addr:housenumber":"501",
    "addr:postcode":"61104",
    "addr:street":"18Th Ave",
    "iso:country":"US",
    "sg:address":"501 18th Ave",
    "sg:city":"Rockford",
    "sg:classifiers":[
        {
            "category":"Wholesale",
            "subcategory":"Machinery & Supplies",
            "type":"Manufacturing & Wholesale Goods"
        }
    ],
    "sg:phone":"+1 815 961 9600",
    "sg:postcode":"61104",
    "sg:province":"IL",
    "sg:tags":[
        "equipment",
        "industrial"
    ],
    "sg:website":"www.machineryinmotion.com",
    "wof:name":"Machinery In Motion Inc",
    "wof:placetype":"venue"
},
  "geometry": {"coordinates":[-89.08935099999999,42.247764],"type":"Point"}
}