{
  "type": "Feature",
  "properties": {
    "iso:country":"US",
    "sg:address":"360 E John Casey Rd",
    "sg:city":"Bourbonnais",
    "sg:classifiers":[
        {
            "category":"Professional",
            "subcategory":"Management & Consulting",
            "type":"Services"
        },
        {
            "category":"Social Services",
            "type":"Services"
        }
    ],
    "sg:phone":"+1 815 939 4926",
    "sg:postcode":"60914",
    "sg:province":"IL",
    "sg:tags":[
        "consultant",
        "training",
        "organization",
        "welfare"
    ],
    "wof:name":"Kankakee County Training Ctr",
    "wof:placetype":"venue"
},
  "geometry": {"coordinates":[-87.866612,41.165032],"type":"Point"}
}