{
  "type": "Feature",
  "properties": {
    "iso:country":"US",
    "sg:address":"2 Executive Dr",
    "sg:city":"Collinsville",
    "sg:classifiers":[
        {
            "category":"Manufacturing",
            "subcategory":"Printing",
            "type":"Manufacturing & Wholesale Goods"
        }
    ],
    "sg:phone":"+1 618 877 7700",
    "sg:postcode":"62234",
    "sg:province":"IL",
    "sg:tags":[
        "newspaper"
    ],
    "wof:name":"Press Record",
    "wof:placetype":"venue"
},
  "geometry": {"coordinates":[-89.68694,38.744414],"type":"Point"}
}