{
  "type": "Feature",
  "properties": {
    "addr:full":"35 Tower Ct Gurnee IL 60031",
    "addr:housenumber":"35",
    "addr:postcode":"60031",
    "addr:street":"Tower Ct",
    "iso:country":"US",
    "sg:address":"35 Tower Ct",
    "sg:city":"Gurnee",
    "sg:classifiers":[
        {
            "category":"Health Services",
            "subcategory":"Clinic",
            "type":"Services"
        }
    ],
    "sg:phone":"+1 847 360 8440",
    "sg:postcode":"60031",
    "sg:province":"IL",
    "sg:tags":[
        "osteopathic"
    ],
    "wof:name":"Koch Robert Doctor of Osteopathi",
    "wof:placetype":"venue"
},
  "geometry": {"coordinates":[-87.899097,42.358553],"type":"Point"}
}