{
  "type": "Feature",
  "properties": {
    "iso:country":"US",
    "sg:address":"830 N Roselle Rd",
    "sg:city":"Schaumburg",
    "sg:classifiers":[
        {
            "category":"Restaurant",
            "type":"Food & Drink"
        }
    ],
    "sg:phone":"+1   ",
    "sg:postcode":"60195",
    "sg:province":"IL",
    "sg:tags":[
        "eating"
    ],
    "wof:name":"Zippys Inc",
    "wof:placetype":"venue"
},
  "geometry": {"coordinates":[-88.079816,42.043072],"type":"Point"}
}