{
  "type": "Feature",
  "properties": {
    "iso:country":"US",
    "sg:address":"339 N Milwaukee Ave # 101",
    "sg:city":"Libertyville",
    "sg:classifiers":[
        {
            "category":"Shopping",
            "subcategory":"Gifts & Souvenirs",
            "type":"Retail Goods"
        }
    ],
    "sg:phone":"+1 847 362 4800",
    "sg:postcode":"60048",
    "sg:province":"IL",
    "sg:tags":[
        "basket"
    ],
    "wof:name":"Tell Two Friends Inc",
    "wof:placetype":"venue"
},
  "geometry": {"coordinates":[-87.94581599999999,42.248146],"type":"Point"}
}