{
  "type": "Feature",
  "properties": {
    "addr:full":"450 Hammond Ave Elgin IL 60120",
    "addr:housenumber":"450",
    "addr:postcode":"60120",
    "addr:street":"Hammond Ave",
    "iso:country":"US",
    "sg:address":"450 Hammond Ave",
    "sg:city":"Elgin",
    "sg:classifiers":[
        {
            "category":"Building & Trades",
            "subcategory":"Plumbing",
            "type":"Services"
        }
    ],
    "sg:phone":"+1 847 888 9292",
    "sg:postcode":"60120",
    "sg:province":"IL",
    "sg:tags":[
        "mechanical",
        "clean",
        "boilers-repair",
        "contractor"
    ],
    "sg:website":"http://skirmont.com",
    "wof:name":"Skirmont Mechanical Contractors",
    "wof:placetype":"venue"
},
  "geometry": {"coordinates":[-88.270088,42.0154],"type":"Point"}
}