{
  "type": "Feature",
  "properties": {
    "addr:full":"9150 Crawford Ave Skokie IL 60076",
    "addr:housenumber":"9150",
    "addr:postcode":"60076",
    "addr:street":"Crawford Ave",
    "iso:country":"US",
    "sg:address":"9150 Crawford Ave",
    "sg:city":"Skokie",
    "sg:classifiers":[
        {
            "category":"Professional",
            "subcategory":"Lawyer & Legal Services",
            "type":"Services"
        }
    ],
    "sg:phone":"+1 847 329 0433",
    "sg:postcode":"60076",
    "sg:province":"IL",
    "sg:tags":[
        "attorney"
    ],
    "wof:name":"Lionel Brazen",
    "wof:placetype":"venue"
},
  "geometry": {"coordinates":[-87.727706,42.046982],"type":"Point"}
}