{
  "type": "Feature",
  "properties": {
    "iso:country":"US",
    "sg:address":"25867 W Grass Lake Rd",
    "sg:city":"Antioch",
    "sg:classifiers":[
        {
            "category":"Health Services",
            "subcategory":"Doctor",
            "type":"Services"
        }
    ],
    "sg:phone":"+1 847 395 1364",
    "sg:postcode":"60002",
    "sg:province":"IL",
    "sg:tags":[
        "dentist"
    ],
    "wof:name":"American Family Dental",
    "wof:placetype":"venue"
},
  "geometry": {"coordinates":[-88.132839,42.446819],"type":"Point"}
}