{
  "type": "Feature",
  "properties": {
    "addr:full":"1815 N Kingsbury St Chicago IL 60614",
    "addr:housenumber":"1815",
    "addr:postcode":"60614",
    "addr:street":"N Kingsbury St",
    "iso:country":"US",
    "sg:address":"1815 N Kingsbury St",
    "sg:city":"Chicago",
    "sg:classifiers":[
        {
            "category":"Wholesale",
            "subcategory":"Scrap",
            "type":"Manufacturing & Wholesale Goods"
        },
        {
            "category":"Utilities",
            "subcategory":"Recycling",
            "type":"Services"
        }
    ],
    "sg:phone":"+1 312 664 4111",
    "sg:postcode":"60614",
    "sg:province":"IL",
    "sg:tags":[
        "metals-wholesale",
        "metal"
    ],
    "wof:name":"City Scrap Metal",
    "wof:placetype":"venue"
},
  "geometry": {"coordinates":[-87.657006,41.914315],"type":"Point"}
}