{
  "type": "Feature",
  "properties": {
    "iso:country":"US",
    "sg:address":"109 Behrens Dr",
    "sg:city":"Edwardsville",
    "sg:classifiers":[
        {
            "category":"Place Of Worship",
            "subcategory":"Church",
            "type":"Public Place"
        },
        {
            "category":"Place Of Worship",
            "type":"Public Place"
        }
    ],
    "sg:phone":"+1 618 656 1871",
    "sg:postcode":"62025",
    "sg:province":"IL",
    "sg:tags":[
        "churches-baptist-general",
        "churches-baptist"
    ],
    "wof:name":"West 22nd St Baptist Chur",
    "wof:placetype":"venue"
},
  "geometry": {"coordinates":[-89.9402,38.785558],"type":"Point"}
}