{
  "type": "Feature",
  "properties": {
    "addr:full":"604 57th St Downers Grove IL 60516",
    "addr:housenumber":"604",
    "addr:postcode":"60516",
    "addr:street":"57Th St",
    "iso:country":"US",
    "sg:address":"604 57th St",
    "sg:city":"Downers Grove",
    "sg:classifiers":[
        {
            "category":"Professional",
            "subcategory":"Accounting & Tax Preparation",
            "type":"Services"
        }
    ],
    "sg:phone":"+1 630 852 0740",
    "sg:postcode":"60516",
    "sg:province":"IL",
    "wof:name":"Deborah Faber Accountant",
    "wof:placetype":"venue"
},
  "geometry": {"coordinates":[-87.999579,41.783898],"type":"Point"}
}