{
  "type": "Feature",
  "properties": {
    "addr:full":"865 E Wilmette Rd Palatine IL 60074",
    "addr:housenumber":"865",
    "addr:postcode":"60074",
    "addr:street":"E Wilmette Rd",
    "iso:country":"US",
    "sg:address":"865 E Wilmette Rd",
    "sg:city":"Palatine",
    "sg:classifiers":[
        {
            "category":"Insurance",
            "subcategory":"Insurance Agent",
            "type":"Services"
        }
    ],
    "sg:phone":"+1 847 221 2551",
    "sg:postcode":"60074",
    "sg:province":"IL",
    "wof:name":"Benefit Marketing Services",
    "wof:placetype":"venue"
},
  "geometry": {"coordinates":[-88.023736,42.104656],"type":"Point"}
}