{
  "type": "Feature",
  "properties": {
    "iso:country":"US",
    "sg:address":"2930 S Michigan Ave Ste 102A",
    "sg:city":"Chicago",
    "sg:classifiers":[
        {
            "category":"Shopping",
            "subcategory":"Beauty & Cosmetics",
            "type":"Retail Goods"
        }
    ],
    "sg:phone":"+1 312 842 8018",
    "sg:postcode":"60616",
    "sg:province":"IL",
    "sg:tags":[
        "supply"
    ],
    "wof:name":"Dr Earles Llc",
    "wof:placetype":"venue"
},
  "geometry": {"coordinates":[-87.623712,41.841439],"type":"Point"}
}