{
  "type": "Feature",
  "properties": {
    "addr:full":"2466 W Schaumburg Rd Schaumburg IL 60194",
    "addr:housenumber":"2466",
    "addr:postcode":"60194",
    "addr:street":"W Schaumburg Rd",
    "iso:country":"US",
    "sg:address":"2466 W Schaumburg Rd",
    "sg:city":"Schaumburg",
    "sg:classifiers":[
        {
            "category":"Personal",
            "subcategory":"Beauty Salon",
            "type":"Services"
        }
    ],
    "sg:phone":"+1 847 839 9548",
    "sg:postcode":"60194",
    "sg:province":"IL",
    "sg:tags":[
        "manicuring"
    ],
    "wof:name":"Art Nails",
    "wof:placetype":"venue"
},
  "geometry": {"coordinates":[-88.153927,42.029765],"type":"Point"}
}