{
  "type": "Feature",
  "properties": {
    "addr:full":"4776 Huxley Dr Rockford IL 61101",
    "addr:housenumber":"4776",
    "addr:postcode":"61101",
    "addr:street":"Huxley Dr",
    "iso:country":"US",
    "sg:address":"4776 Huxley Dr",
    "sg:city":"Rockford",
    "sg:classifiers":[
        {
            "category":"Manufacturing",
            "subcategory":"Tools & Machinery",
            "type":"Manufacturing & Wholesale Goods"
        }
    ],
    "sg:phone":"+1 815 968 8089",
    "sg:postcode":"61101",
    "sg:province":"IL",
    "sg:tags":[
        "cutting",
        "manufacturer"
    ],
    "wof:name":"Fabiano Cutting Tools",
    "wof:placetype":"venue"
},
  "geometry": {"coordinates":[-89.131985,42.319688],"type":"Point"}
}