{
  "type": "Feature",
  "properties": {
    "iso:country":"US",
    "sg:address":"411 Chicago Rd",
    "sg:city":"Oswego",
    "sg:classifiers":[
        {
            "category":"Restaurant",
            "type":"Food & Drink"
        }
    ],
    "sg:menulink":"http://www.allmenus.com/il/oswego/127198-subway/menu/",
    "sg:phone":"+1 630 554 4300",
    "sg:postcode":"60543",
    "sg:province":"IL",
    "sg:tags":[
        "american",
        "sandwich"
    ],
    "wof:name":"Subway",
    "wof:placetype":"venue"
},
  "geometry": {"coordinates":[-88.34098899999999,41.686586],"type":"Point"}
}