{
  "type": "Feature",
  "properties": {
    "iso:country":"US",
    "sg:address":"324 W Liberty Dr",
    "sg:city":"Wheaton",
    "sg:classifiers":[
        {
            "category":"Retail",
            "subcategory":"Laundry & Dry Cleaning",
            "type":"Services"
        }
    ],
    "sg:phone":"+1 630 668 9694",
    "sg:postcode":"60187",
    "sg:province":"IL",
    "wof:name":"Jys Heritage Cleaners",
    "wof:placetype":"venue"
},
  "geometry": {"coordinates":[-88.11019899999999,41.864201],"type":"Point"}
}