{
  "type": "Feature",
  "properties": {
    "addr:full":"1112 E Main St Olney IL 62450",
    "addr:housenumber":"1112",
    "addr:postcode":"62450",
    "addr:street":"E Main St",
    "iso:country":"US",
    "sg:address":"1112 E Main St",
    "sg:city":"Olney",
    "sg:classifiers":[
        {
            "category":"Manufacturing",
            "subcategory":"Glass & Minerals",
            "type":"Manufacturing & Wholesale Goods"
        },
        {
            "category":"Retail",
            "subcategory":"Auto Repair",
            "type":"Services"
        },
        {
            "category":"Building & Trades",
            "subcategory":"Construction",
            "type":"Services"
        }
    ],
    "sg:phone":"+1 618 395 4930",
    "sg:postcode":"62450",
    "sg:province":"IL",
    "sg:tags":[
        "plate",
        "installation",
        "windows-repair",
        "manufacturer",
        "window",
        "glass-wholesale",
        "glass-auto",
        "shape",
        "circle",
        "windshield",
        "special",
        "replacement"
    ],
    "sg:website":"http://www.a1qualityglass.net",
    "wof:name":"A-1 Quality Glass Inc",
    "wof:placetype":"venue"
},
  "geometry": {"coordinates":[-88.073262,38.7314],"type":"Point"}
}