{
  "type": "Feature",
  "properties": {
    "iso:country":"US",
    "sg:address":"351 W Hubbard St",
    "sg:city":"Chicago",
    "sg:classifiers":[
        {
            "category":"Professional",
            "subcategory":"Lawyer & Legal Services",
            "type":"Services"
        }
    ],
    "sg:phone":"+1 312 654 8817",
    "sg:postcode":"60610",
    "sg:province":"IL",
    "wof:name":"Midwest Public Affairs Group",
    "wof:placetype":"venue"
},
  "geometry": {"coordinates":[-87.637001,41.8899],"type":"Point"}
}