{
  "type": "Feature",
  "properties": {
    "addr:full":"678 Fairview Ave Elmhurst IL 60126",
    "addr:housenumber":"678",
    "addr:postcode":"60126",
    "addr:street":"Fairview Ave",
    "iso:country":"US",
    "sg:address":"678 Fairview Ave",
    "sg:city":"Elmhurst",
    "sg:classifiers":[
        {
            "category":"Insurance",
            "subcategory":"Insurance Agent",
            "type":"Services"
        }
    ],
    "sg:phone":"+1 630 833 7523",
    "sg:postcode":"60126",
    "sg:province":"IL",
    "sg:tags":[
        "processing"
    ],
    "wof:name":"Docbillrs",
    "wof:placetype":"venue"
},
  "geometry": {"coordinates":[-87.955668,41.877709],"type":"Point"}
}