{
  "type": "Feature",
  "properties": {
    "iso:country":"US",
    "sg:address":"8836 Ogden Ave",
    "sg:city":"Brookfield",
    "sg:classifiers":[
        {
            "category":"Professional",
            "subcategory":"Accounting & Tax Preparation",
            "type":"Services"
        }
    ],
    "sg:phone":"+1 708 485 6083",
    "sg:postcode":"60513",
    "sg:province":"IL",
    "sg:tags":[
        "return"
    ],
    "wof:name":"Garcia Travel",
    "wof:placetype":"venue"
},
  "geometry": {"coordinates":[-87.841946,41.816566],"type":"Point"}
}