{
  "type": "Feature",
  "properties": {
    "iso:country":"US",
    "sg:address":"796 Royal Saint George Dr",
    "sg:city":"Naperville",
    "sg:classifiers":[
        {
            "category":"Restaurant",
            "type":"Food & Drink"
        }
    ],
    "sg:menulink":"http://www.allmenus.com/il/naperville/16485-braconis-restaurant/menu/",
    "sg:phone":"+1 630 717 9530",
    "sg:postcode":"60563",
    "sg:province":"IL",
    "sg:tags":[
        "italian"
    ],
    "wof:name":"Braconi's Restaurant",
    "wof:placetype":"venue"
},
  "geometry": {"coordinates":[-88.166982,41.784066],"type":"Point"}
}