{
  "type": "Feature",
  "properties": {
    "iso:country":"US",
    "sg:address":"990 N Schuyler Ave",
    "sg:city":"Kankakee",
    "sg:classifiers":[
        {
            "category":"Building & Trades",
            "subcategory":"Cleaning & Sanitation",
            "type":"Services"
        }
    ],
    "sg:phone":"+1 815 933 2678",
    "sg:postcode":"60901",
    "sg:province":"IL",
    "sg:tags":[
        "janitor"
    ],
    "wof:name":"So Fresh So Clean",
    "wof:placetype":"venue"
},
  "geometry": {"coordinates":[-87.86198,41.13005],"type":"Point"}
}