{
  "type": "Feature",
  "properties": {
    "iso:country":"US",
    "sg:address":"8704 S Loomis Street",
    "sg:city":"Chicago",
    "sg:classifiers":[
        {
            "category":"Shopping",
            "subcategory":"Beauty & Cosmetics",
            "type":"Retail Goods"
        }
    ],
    "sg:phone":"+1 773 779 7100",
    "sg:postcode":"60620",
    "sg:province":"IL",
    "sg:tags":[
        "supply"
    ],
    "wof:name":"B J Health and Beauty",
    "wof:placetype":"venue"
},
  "geometry": {"coordinates":[-87.658259,41.73562],"type":"Point"}
}