{
  "type": "Feature",
  "properties": {
    "iso:country":"US",
    "sg:address":"3828 N Lincoln Ave",
    "sg:city":"Chicago",
    "sg:classifiers":[
        {
            "category":"Shopping",
            "subcategory":"Clothing, Apparel, & Fashions",
            "type":"Retail Goods"
        }
    ],
    "sg:phone":"+1 312 226 6677",
    "sg:postcode":"60613",
    "sg:province":"IL",
    "sg:tags":[
        "accessory",
        "clothing",
        "women's"
    ],
    "sg:website":"www.shop2sisters.com",
    "wof:name":"2 Sisters Boutique",
    "wof:placetype":"venue"
},
  "geometry": {"coordinates":[-87.67706099999999,41.951169],"type":"Point"}
}