{
  "type": "Feature",
  "properties": {
    "addr:full":"211 E Ohio St Apt 2116 Chicago IL 60611",
    "addr:housenumber":"211",
    "addr:postcode":"60611",
    "addr:street":"E Ohio St Apt 2116",
    "iso:country":"US",
    "sg:address":"211 E Ohio St Apt 2116",
    "sg:city":"Chicago",
    "sg:classifiers":[
        {
            "category":"Communications",
            "subcategory":"Film & Video Production",
            "type":"Services"
        }
    ],
    "sg:phone":"+1 312 451 7576",
    "sg:postcode":"60611",
    "sg:province":"IL",
    "sg:tags":[
        "recording",
        "service-sound"
    ],
    "wof:name":"Stonecutter Entertainment Group Inc",
    "wof:placetype":"venue"
},
  "geometry": {"coordinates":[-87.62245299999999,41.892574],"type":"Point"}
}