{
  "type": "Feature",
  "properties": {
    "iso:country":"US",
    "sg:address":"153 Canal St",
    "sg:city":"La Salle",
    "sg:classifiers":[
        {
            "category":"Wholesale",
            "subcategory":"Scrap",
            "type":"Manufacturing & Wholesale Goods"
        }
    ],
    "sg:phone":"+1 815 223 0322",
    "sg:postcode":"61301",
    "sg:province":"IL",
    "sg:tags":[
        "recycling",
        "center"
    ],
    "wof:name":"Buckman Iron & Metal Co",
    "wof:placetype":"venue"
},
  "geometry": {"coordinates":[-89.104597,41.327216],"type":"Point"}
}