{
  "type": "Feature",
  "properties": {
    "addr:full":"15259 S Harlem Ave Chicago IL 60638",
    "addr:housenumber":"15259",
    "addr:postcode":"60638",
    "addr:street":"S Harlem Ave",
    "iso:country":"US",
    "sg:address":"15259 S Harlem Ave",
    "sg:city":"Chicago",
    "sg:classifiers":[
        {
            "category":"Professional",
            "type":"Services"
        },
        {
            "category":"Retail",
            "subcategory":"Auto Rental",
            "type":"Services"
        },
        {
            "category":"Building & Trades",
            "subcategory":"Equipment Rental",
            "type":"Services"
        },
        {
            "category":"Retail",
            "subcategory":"Storage",
            "type":"Services"
        }
    ],
    "sg:phone":"+1 866 205 7339",
    "sg:postcode":"60638",
    "sg:province":"IL",
    "sg:tags":[
        "renting",
        "moving-self",
        "leasing",
        "material",
        "moving",
        "services-labor",
        "truck",
        "trailer"
    ],
    "sg:website":"http://www.pensketruckrental.com/personal_rental/?cid=Yptmlist",
    "wof:name":"Penske Truck Rental",
    "wof:placetype":"venue"
},
  "geometry": {"coordinates":[-87.803112,41.773849],"type":"Point"}
}