{
  "type": "Feature",
  "properties": {
    "addr:full":"750 N Orleans St Ste 100 Chicago IL 60656",
    "addr:housenumber":"750",
    "addr:postcode":"60656",
    "addr:street":"N Orleans St Ste 100",
    "iso:country":"US",
    "sg:address":"750 N Orleans St Ste 100",
    "sg:city":"Chicago",
    "sg:classifiers":[
        {
            "category":"Real Estate",
            "subcategory":"Real Estate Agent",
            "type":"Services"
        }
    ],
    "sg:phone":"+1 312 238 9015",
    "sg:postcode":"60656",
    "sg:province":"IL",
    "sg:website":"www.lennevin.com",
    "wof:name":"Len Nevin - Koenig & Strey GMAC Real Estate",
    "wof:placetype":"venue"
},
  "geometry": {"coordinates":[-87.637163,41.896128],"type":"Point"}
}