{
  "type": "Feature",
  "properties": {
    "iso:country":"US",
    "sg:address":"142 W Sibley Blvd",
    "sg:city":"Dolton",
    "sg:classifiers":[
        {
            "category":"Food & Beverages",
            "subcategory":"Liquor & Beverages",
            "type":"Retail Goods"
        }
    ],
    "sg:phone":"+1 708 841 1802",
    "sg:postcode":"60419",
    "sg:province":"IL",
    "sg:tags":[
        "beer",
        "spirit",
        "wine"
    ],
    "wof:name":"Sibley Food & Liquor",
    "wof:placetype":"venue"
},
  "geometry": {"coordinates":[-87.62550400000001,41.623402],"type":"Point"}
}