{
  "type": "Feature",
  "properties": {
    "iso:country":"US",
    "sg:address":"419 Krista Ln",
    "sg:city":"Millstadt",
    "sg:classifiers":[
        {
            "category":"Manufacturing",
            "subcategory":"Food",
            "type":"Manufacturing & Wholesale Goods"
        },
        {
            "category":"Farming",
            "subcategory":"Farm",
            "type":"Manufacturing & Wholesale Goods"
        }
    ],
    "sg:phone":"+1 618 476 3564",
    "sg:postcode":"62260",
    "sg:province":"IL",
    "sg:tags":[
        "corn",
        "product"
    ],
    "wof:name":"Randy Meyer",
    "wof:placetype":"venue"
},
  "geometry": {"coordinates":[-90.065659,38.477211],"type":"Point"}
}