{
  "type": "Feature",
  "properties": {
    "addr:full":"7000 Old Saint Louis Rd Belleville IL 62223",
    "addr:housenumber":"7000",
    "addr:postcode":"62223",
    "addr:street":"Old Saint Louis Rd",
    "iso:country":"US",
    "sg:address":"7000 Old Saint Louis Rd",
    "sg:city":"Belleville",
    "sg:classifiers":[
        {
            "category":"Retail",
            "subcategory":"Auto Repair",
            "type":"Services"
        }
    ],
    "sg:phone":"+1 618 310 1560",
    "sg:postcode":"62223",
    "sg:province":"IL",
    "sg:tags":[
        "repairing",
        "automobile"
    ],
    "wof:name":"D & M Automotive Svc",
    "wof:placetype":"venue"
},
  "geometry": {"coordinates":[-90.048326,38.542574],"type":"Point"}
}