{
  "type": "Feature",
  "properties": {
    "iso:country":"US",
    "sg:address":"2800 S River Rd",
    "sg:city":"Des Plaines",
    "sg:classifiers":[
        {
            "category":"Personal",
            "subcategory":"Beauty Salon",
            "type":"Services"
        }
    ],
    "sg:phone":"+1 847 390 8545",
    "sg:postcode":"60018",
    "sg:province":"IL",
    "wof:name":"Creative Hairdressers",
    "wof:placetype":"venue"
},
  "geometry": {"coordinates":[-87.864783,42.002755],"type":"Point"}
}