{
  "type": "Feature",
  "properties": {
    "addr:full":"1000 Belt Line Rd Collinsville IL 62234",
    "addr:housenumber":"1000",
    "addr:postcode":"62234",
    "addr:street":"Belt Line Rd",
    "iso:country":"US",
    "sg:address":"1000 Belt Line Rd",
    "sg:city":"Collinsville",
    "sg:classifiers":[
        {
            "category":"Food & Beverages",
            "subcategory":"Groceries & Convenience Stores",
            "type":"Retail Goods"
        }
    ],
    "sg:phone":"+1 618 301 3331",
    "sg:postcode":"62234",
    "sg:province":"IL",
    "wof:name":"Buck's Inc of Collinsville",
    "wof:placetype":"venue"
},
  "geometry": {"coordinates":[-89.98473,38.690823],"type":"Point"}
}