{
  "type": "Feature",
  "properties": {
    "iso:country":"US",
    "sg:address":"27300 Shake Rag Rd",
    "sg:city":"Danville",
    "sg:classifiers":[
        {
            "category":"Manufacturing",
            "subcategory":"Tools & Machinery",
            "type":"Manufacturing & Wholesale Goods"
        }
    ],
    "sg:phone":"+1 217 333 0926",
    "sg:postcode":"61834",
    "sg:province":"IL",
    "sg:tags":[
        "forming",
        "metal"
    ],
    "wof:name":"Bk Industries",
    "wof:placetype":"venue"
},
  "geometry": {"coordinates":[-87.623139,40.259415],"type":"Point"}
}