{
  "type": "Feature",
  "properties": {
    "iso:country":"US",
    "sg:address":"410 W Main St",
    "sg:city":"Ottawa",
    "sg:classifiers":[
        {
            "category":"Health Services",
            "subcategory":"Doctor",
            "type":"Services"
        }
    ],
    "sg:phone":"+1 815 434 7231",
    "sg:postcode":"61350",
    "sg:province":"IL",
    "sg:tags":[
        "physician",
        "surgeon"
    ],
    "wof:name":"Psoriasis Treatment Ctr",
    "wof:placetype":"venue"
},
  "geometry": {"coordinates":[-88.846723,41.345797],"type":"Point"}
}