{
  "type": "Feature",
  "properties": {
    "addr:full":"7345 Lake St River Forest IL 60305",
    "addr:housenumber":"7345",
    "addr:postcode":"60305",
    "addr:street":"Lake St",
    "iso:country":"US",
    "sg:address":"7345 Lake St",
    "sg:city":"River Forest",
    "sg:classifiers":[
        {
            "category":"Health Services",
            "subcategory":"Optometrist",
            "type":"Services"
        },
        {
            "category":"Shopping",
            "subcategory":"Optician",
            "type":"Retail Goods"
        }
    ],
    "sg:phone":"+1 708 771 1946",
    "sg:postcode":"60305",
    "sg:province":"IL",
    "sg:tags":[
        "eyewear"
    ],
    "sg:website":"www.lenscrafters.com",
    "wof:name":"Lenscrafters",
    "wof:placetype":"venue"
},
  "geometry": {"coordinates":[-87.80849499999999,41.888352],"type":"Point"}
}