{
  "type": "Feature",
  "properties": {
    "iso:country":"US",
    "sg:address":"101 S Broadway St",
    "sg:city":"Little York",
    "sg:classifiers":[
        {
            "category":"Restaurant",
            "type":"Food & Drink"
        }
    ],
    "sg:phone":"+1 309 729 1500",
    "sg:postcode":"61453",
    "sg:province":"IL",
    "wof:name":"Dew's Diner",
    "wof:placetype":"venue"
},
  "geometry": {"coordinates":[-90.746353,41.010808],"type":"Point"}
}