{
  "type": "Feature",
  "properties": {
    "addr:full":"1504 S Oak Ave Freeport IL 61032",
    "addr:housenumber":"1504",
    "addr:postcode":"61032",
    "addr:street":"S Oak Ave",
    "iso:country":"US",
    "sg:address":"1504 S Oak Ave",
    "sg:city":"Freeport",
    "sg:classifiers":[
        {
            "category":"Wholesale",
            "subcategory":"Office Equipment",
            "type":"Manufacturing & Wholesale Goods"
        }
    ],
    "sg:phone":"+1 815 235 3212",
    "sg:postcode":"61032",
    "sg:province":"IL",
    "sg:tags":[
        "machine",
        "duplicating",
        "copying"
    ],
    "wof:name":"C F Stocker Copy Equipment Co",
    "wof:placetype":"venue"
},
  "geometry": {"coordinates":[-89.61879399999999,42.283976],"type":"Point"}
}