{
  "type": "Feature",
  "properties": {
    "iso:country":"US",
    "sg:address":"119 E Adams St",
    "sg:city":"Rushville",
    "sg:classifiers":[
        {
            "category":"Food & Beverages",
            "subcategory":"Liquor & Beverages",
            "type":"Retail Goods"
        }
    ],
    "sg:phone":"+1 217 322 6231",
    "sg:postcode":"62681",
    "sg:province":"IL",
    "wof:name":"Don & Char's Package Liquor",
    "wof:placetype":"venue"
},
  "geometry": {"coordinates":[-90.561563,40.123891],"type":"Point"}
}