{
  "type": "Feature",
  "properties": {
    "iso:country":"US",
    "sg:address":"314 SE 3rd St",
    "sg:city":"Aledo",
    "sg:classifiers":[
        {
            "category":"Ice Cream",
            "type":"Food & Drink"
        }
    ],
    "sg:menulink":"http://www.allmenus.com/il/mercer/74342-happy-joes/menu/",
    "sg:phone":"+1 309 582 5636",
    "sg:postcode":"61231",
    "sg:province":"IL",
    "sg:tags":[
        "american",
        "pizza"
    ],
    "wof:name":"Happy Joe's",
    "wof:placetype":"venue"
},
  "geometry": {"coordinates":[-90.74675000000001,41.199875],"type":"Point"}
}