{
  "type": "Feature",
  "properties": {
    "iso:country":"US",
    "sg:address":"121 E Martin St",
    "sg:city":"Forrest",
    "sg:classifiers":[
        {
            "category":"Building & Trades",
            "subcategory":"Construction",
            "type":"Services"
        }
    ],
    "sg:phone":"+1 309 830 4679",
    "sg:postcode":"61741",
    "sg:province":"IL",
    "sg:tags":[
        "carpenter"
    ],
    "wof:name":"Tim Robertson Carpentry",
    "wof:placetype":"venue"
},
  "geometry": {"coordinates":[-88.40961,40.752448],"type":"Point"}
}