{
  "type": "Feature",
  "properties": {
    "addr:full":"1000 N Allen St Robinson IL 62454",
    "addr:housenumber":"1000",
    "addr:postcode":"62454",
    "addr:street":"N Allen St",
    "iso:country":"US",
    "sg:address":"1000 N Allen St",
    "sg:city":"Robinson",
    "sg:classifiers":[
        {
            "category":"Health Services",
            "subcategory":"Doctor",
            "type":"Services"
        },
        {
            "category":"Health Services",
            "subcategory":"Clinic",
            "type":"Services"
        }
    ],
    "sg:phone":"+1 618 546 2618",
    "sg:postcode":"62454",
    "sg:province":"IL",
    "sg:tags":[
        "physician",
        "surgeons",
        "osteopathic",
        "medicine",
        "surgeon",
        "rehabilitation",
        "physical"
    ],
    "wof:name":"Fred Scott Do",
    "wof:placetype":"venue"
},
  "geometry": {"coordinates":[-87.750137,39.01263],"type":"Point"}
}