{
  "type": "Feature",
  "properties": {
    "iso:country":"US",
    "sg:address":"26 Greenfield Dr",
    "sg:city":"Freeport",
    "sg:classifiers":[
        {
            "category":"Real Estate",
            "subcategory":"Real Estate Operator",
            "type":"Services"
        }
    ],
    "sg:phone":"+1 815 398 8913",
    "sg:postcode":"61032",
    "sg:province":"IL",
    "sg:tags":[
        "building",
        "apartment"
    ],
    "wof:name":"West Port Village",
    "wof:placetype":"venue"
},
  "geometry": {"coordinates":[-89.65943900000001,42.294564],"type":"Point"}
}