{
  "type": "Feature",
  "properties": {
    "addr:full":"940 E Rand Rd Mount Prospect IL 60056",
    "addr:housenumber":"940",
    "addr:postcode":"60056",
    "addr:street":"E Rand Rd",
    "iso:country":"US",
    "sg:address":"940 E Rand Rd",
    "sg:city":"Mount Prospect",
    "sg:classifiers":[
        {
            "category":"Banks & Credit Unions",
            "subcategory":"Bank",
            "type":"Services"
        }
    ],
    "sg:phone":"+1 847 259 7575",
    "sg:postcode":"60056",
    "sg:province":"IL",
    "sg:tags":[
        "national",
        "commercial"
    ],
    "wof:name":"Charter One",
    "wof:placetype":"venue"
},
  "geometry": {"coordinates":[-87.922456,42.067221],"type":"Point"}
}