{
  "type": "Feature",
  "properties": {
    "iso:country":"US",
    "sg:address":"4845 W North Avenue",
    "sg:city":"Chicago",
    "sg:classifiers":[
        {
            "category":"Shopping",
            "subcategory":"Shoes",
            "type":"Retail Goods"
        }
    ],
    "sg:phone":"+1 773 292 0711",
    "sg:postcode":"60639",
    "sg:province":"IL",
    "sg:tags":[
        "store"
    ],
    "wof:name":"City Sports",
    "wof:placetype":"venue"
},
  "geometry": {"coordinates":[-87.747254,41.909449],"type":"Point"}
}