{
  "type": "Feature",
  "properties": {
    "addr:full":"5035 Oakton St Skokie IL 60077",
    "addr:housenumber":"5035",
    "addr:postcode":"60077",
    "addr:street":"Oakton St",
    "iso:country":"US",
    "sg:address":"5035 Oakton St",
    "sg:city":"Skokie",
    "sg:classifiers":[
        {
            "category":"Home & Garden",
            "subcategory":"Hardware",
            "type":"Retail Goods"
        }
    ],
    "sg:phone":"+1   ",
    "sg:postcode":"60077",
    "sg:province":"IL",
    "wof:name":"Ace Hardware",
    "wof:placetype":"venue"
},
  "geometry": {"coordinates":[-87.75461300000001,42.026251],"type":"Point"}
}