{
  "type": "Feature",
  "properties": {
    "addr:full":"502 N Waukegan Rd Lake Bluff IL 60044",
    "addr:housenumber":"502",
    "addr:postcode":"60044",
    "addr:street":"N Waukegan Rd",
    "iso:country":"US",
    "sg:address":"502 N Waukegan Rd",
    "sg:city":"Lake Bluff",
    "sg:classifiers":[
        {
            "category":"Organizations",
            "subcategory":"Non-profit Organization",
            "type":"Services"
        }
    ],
    "sg:phone":"+1 847 295 1550",
    "sg:postcode":"60044",
    "sg:province":"IL",
    "wof:name":"Hill Top Ctr",
    "wof:placetype":"venue"
},
  "geometry": {"coordinates":[-87.88800999999999,42.292489],"type":"Point"}
}