{
  "type": "Feature",
  "properties": {
    "iso:country":"US",
    "sg:address":"439 N Western Avenue",
    "sg:city":"Chicago",
    "sg:classifiers":[
        {
            "category":"Professional",
            "subcategory":"Lawyer & Legal Services",
            "type":"Services"
        }
    ],
    "sg:phone":"+1 312 649 0113",
    "sg:postcode":"60612",
    "sg:province":"IL",
    "wof:name":"Rubin Richard J Atty",
    "wof:placetype":"venue"
},
  "geometry": {"coordinates":[-87.686753,41.889756],"type":"Point"}
}