{
  "type": "Feature",
  "properties": {
    "addr:full":"204 W South St Peotone IL 60468",
    "addr:housenumber":"204",
    "addr:postcode":"60468",
    "addr:street":"W South St",
    "iso:country":"US",
    "sg:address":"204 W South St",
    "sg:city":"Peotone",
    "sg:classifiers":[
        {
            "category":"Retail",
            "subcategory":"Auto Repair",
            "type":"Services"
        }
    ],
    "sg:phone":"+1 708 534 8697",
    "sg:postcode":"60468",
    "sg:province":"IL",
    "sg:tags":[
        "automotive",
        "wrecker"
    ],
    "wof:name":"Central Towing & Recovery Inc",
    "wof:placetype":"venue"
},
  "geometry": {"coordinates":[-87.792401,41.329778],"type":"Point"}
}