{
  "type": "Feature",
  "properties": {
    "iso:country":"US",
    "sg:address":"5317 Oak Park Rd",
    "sg:city":"Oakwood Hills",
    "sg:classifiers":[
        {
            "category":"Banks & Credit Unions",
            "subcategory":"Investment Brokerage",
            "type":"Services"
        }
    ],
    "sg:phone":"+1 847 516 5446",
    "sg:postcode":"60013",
    "sg:province":"IL",
    "sg:tags":[
        "consultant",
        "planning",
        "financial"
    ],
    "wof:name":"Smith & Assoc Inc",
    "wof:placetype":"venue"
},
  "geometry": {"coordinates":[-88.251093,42.248944],"type":"Point"}
}