{
  "type": "Feature",
  "properties": {
    "iso:country":"US",
    "sg:address":"490 N Main St",
    "sg:city":"Canton",
    "sg:classifiers":[
        {
            "category":"Shopping",
            "subcategory":"Pharmacy",
            "type":"Retail Goods"
        }
    ],
    "sg:phone":"+1 309 647 1717",
    "sg:postcode":"61520",
    "sg:province":"IL",
    "wof:name":"Medicine Shoppe Pharmacy",
    "wof:placetype":"venue"
},
  "geometry": {"coordinates":[-90.03515899999999,40.560752],"type":"Point"}
}