{
  "type": "Feature",
  "properties": {
    "iso:country":"US",
    "sg:address":"401 Madison St",
    "sg:city":"Oak Park",
    "sg:classifiers":[
        {
            "category":"Autos & Motor Vehicles",
            "subcategory":"Fuel & Gas Station",
            "type":"Retail Goods"
        }
    ],
    "sg:phone":"+1   ",
    "sg:postcode":"60302",
    "sg:province":"IL",
    "sg:tags":[
        "station",
        "gasoline"
    ],
    "wof:name":"Madison & Ridgeland Shell",
    "wof:placetype":"venue"
},
  "geometry": {"coordinates":[-87.785683,41.87995],"type":"Point"}
}