{
  "type": "Feature",
  "properties": {
    "addr:full":"1121 Shooting Park Rd Peru IL 61354",
    "addr:housenumber":"1121",
    "addr:postcode":"61354",
    "addr:street":"Shooting Park Rd",
    "iso:country":"US",
    "sg:address":"1121 Shooting Park Rd",
    "sg:city":"Peru",
    "sg:classifiers":[
        {
            "category":"Restaurant",
            "type":"Food & Drink"
        }
    ],
    "sg:phone":"+1   ",
    "sg:postcode":"61354",
    "sg:province":"IL",
    "sg:tags":[
        "eating"
    ],
    "wof:name":"Pizza Hut",
    "wof:placetype":"venue"
},
  "geometry": {"coordinates":[-89.12042599999999,41.338574],"type":"Point"}
}