{
  "type": "Feature",
  "properties": {
    "iso:country":"US",
    "sg:address":"355 W Washington Ave",
    "sg:city":"Lake Bluff",
    "sg:classifiers":[
        {
            "category":"Sports & Exercise",
            "subcategory":"Golf",
            "type":"Entertainment"
        }
    ],
    "sg:phone":"+1 847 234 6945",
    "sg:postcode":"60044",
    "sg:province":"IL",
    "sg:tags":[
        "course"
    ],
    "wof:name":"Lake Bluff Park District",
    "wof:placetype":"venue"
},
  "geometry": {"coordinates":[-87.857322,42.282789],"type":"Point"}
}