{
  "type": "Feature",
  "properties": {
    "iso:country":"US",
    "sg:address":"55 W Industrial Park Dr",
    "sg:city":"Kankakee",
    "sg:classifiers":[
        {
            "category":"Freight",
            "type":"Transportation"
        }
    ],
    "sg:phone":"+1 815 932 0260",
    "sg:postcode":"60901",
    "sg:province":"IL",
    "sg:tags":[
        "terminal",
        "truck"
    ],
    "wof:name":"Bertram Trucking Co",
    "wof:placetype":"venue"
},
  "geometry": {"coordinates":[-87.870219,41.08118],"type":"Point"}
}