{
  "type": "Feature",
  "properties": {
    "iso:country":"US",
    "sg:address":"2859 S Pulaski Rd",
    "sg:city":"Chicago",
    "sg:classifiers":[
        {
            "category":"Shopping",
            "subcategory":"Pharmacy",
            "type":"Retail Goods"
        }
    ],
    "sg:phone":"+1 773 522 2900",
    "sg:postcode":"60623",
    "sg:province":"IL",
    "sg:tags":[
        "drugstore"
    ],
    "wof:name":"Desai Pharmacy Inc",
    "wof:placetype":"venue"
},
  "geometry": {"coordinates":[-87.724197,41.839699],"type":"Point"}
}