{
  "type": "Feature",
  "properties": {
    "iso:country":"US",
    "sg:address":"1423 W 79th St",
    "sg:city":"Chicago",
    "sg:classifiers":[
        {
            "category":"Restaurant",
            "type":"Food & Drink"
        },
        {
            "category":"Food & Beverages",
            "subcategory":"Ethnic Foods",
            "type":"Retail Goods"
        }
    ],
    "sg:phone":"+1 773 723 5185",
    "sg:postcode":"60620",
    "sg:province":"IL",
    "sg:tags":[
        "soul"
    ],
    "wof:name":"Soul Food Unlimited",
    "wof:placetype":"venue"
},
  "geometry": {"coordinates":[-87.659302,41.750198],"type":"Point"}
}