{
  "type": "Feature",
  "properties": {
    "iso:country":"US",
    "sg:address":"8 W Ohio St",
    "sg:city":"Chicago",
    "sg:classifiers":[
        {
            "category":"Shopping",
            "subcategory":"Mobile Phones",
            "type":"Retail Goods"
        },
        {
            "category":"Shopping",
            "subcategory":"Computers & Home Electronics",
            "type":"Retail Goods"
        },
        {
            "category":"Utilities",
            "type":"Services"
        }
    ],
    "sg:phone":"+1 312 202 9100",
    "sg:postcode":"60654",
    "sg:province":"IL",
    "sg:tags":[
        "provider",
        "internet"
    ],
    "wof:name":"Personal Electronic Solutions",
    "wof:placetype":"venue"
},
  "geometry": {"coordinates":[-87.628507,41.89259],"type":"Point"}
}