{
  "type": "Feature",
  "properties": {
    "addr:full":"215 S Northwest Hwy Barrington IL 60010",
    "addr:housenumber":"215",
    "addr:postcode":"60010",
    "addr:street":"S Northwest Hwy",
    "iso:country":"US",
    "sg:address":"215 S Northwest Hwy",
    "sg:city":"Barrington",
    "sg:classifiers":[
        {
            "category":"Building & Trades",
            "subcategory":"Construction",
            "type":"Services"
        }
    ],
    "sg:phone":"+1 847 277 9300",
    "sg:postcode":"60010",
    "sg:province":"IL",
    "sg:tags":[
        "management"
    ],
    "wof:name":"Di Moda Development",
    "wof:placetype":"venue"
},
  "geometry": {"coordinates":[-88.128259,42.151979],"type":"Point"}
}