{
  "type": "Feature",
  "properties": {
    "addr:full":"31303 S Martin Long Rd Wilmington IL 60481",
    "addr:housenumber":"31303",
    "addr:postcode":"60481",
    "addr:street":"S Martin Long Rd",
    "iso:country":"US",
    "sg:address":"31303 S Martin Long Rd",
    "sg:city":"Wilmington",
    "sg:classifiers":[
        {
            "category":"Farming",
            "subcategory":"Livestock Farm",
            "type":"Manufacturing & Wholesale Goods"
        }
    ],
    "sg:phone":"+1 815 476 5731",
    "sg:postcode":"60481",
    "sg:province":"IL",
    "sg:tags":[
        "ranch"
    ],
    "wof:name":"Lay A Bout Ranch",
    "wof:placetype":"venue"
},
  "geometry": {"coordinates":[-88.035838,41.321088],"type":"Point"}
}