{
  "type": "Feature",
  "properties": {
    "iso:country":"US",
    "sg:address":"324 W Charles St",
    "sg:city":"Buffalo",
    "sg:classifiers":[
        {
            "category":"Education",
            "subcategory":"School",
            "type":"Public Place"
        }
    ],
    "sg:phone":"+1 217 364 4035",
    "sg:postcode":"62515",
    "sg:province":"IL",
    "wof:name":"Tri-City Elementary School",
    "wof:placetype":"venue"
},
  "geometry": {"coordinates":[-89.411121,39.851279],"type":"Point"}
}