{
  "type": "Feature",
  "properties": {
    "iso:country":"US",
    "sg:address":"4510 N Hermitage Ave",
    "sg:city":"Chicago",
    "sg:classifiers":[
        {
            "category":"Professional",
            "subcategory":"Lawyer & Legal Services",
            "type":"Services"
        }
    ],
    "sg:phone":"+1 773 728 9219",
    "sg:postcode":"60640",
    "sg:province":"IL",
    "sg:tags":[
        "real estate"
    ],
    "wof:name":"Alfred E Aspengren Real Estate",
    "wof:placetype":"venue"
},
  "geometry": {"coordinates":[-87.672582,41.965004],"type":"Point"}
}