{
  "type": "Feature",
  "properties": {
    "iso:country":"US",
    "sg:address":"2601 Grand Ave",
    "sg:city":"Waukegan",
    "sg:classifiers":[
        {
            "category":"Autos & Motor Vehicles",
            "subcategory":"Fuel & Gas Station",
            "type":"Retail Goods"
        }
    ],
    "sg:phone":"+1 847 662 6009",
    "sg:postcode":"60085",
    "sg:province":"IL",
    "sg:tags":[
        "station",
        "gasoline",
        "oil"
    ],
    "wof:name":"Baig's Amoco",
    "wof:placetype":"venue"
},
  "geometry": {"coordinates":[-87.867258,42.370326],"type":"Point"}
}