{
  "type": "Feature",
  "properties": {
    "iso:country":"US",
    "sg:address":"1000 W Rte 64",
    "sg:city":"Oregon",
    "sg:classifiers":[
        {
            "category":"Organizations",
            "subcategory":"Religious Organization",
            "type":"Services"
        }
    ],
    "sg:phone":"+1 815 732 7211",
    "sg:postcode":"61061",
    "sg:province":"IL",
    "sg:tags":[
        "church"
    ],
    "wof:name":"St Brides Episcopal Church",
    "wof:placetype":"venue"
},
  "geometry": {"coordinates":[-89.35756000000001,42.027608],"type":"Point"}
}