{
  "type": "Feature",
  "properties": {
    "iso:country":"US",
    "sg:address":"11128 S 84th Ave",
    "sg:city":"Palos Hills",
    "sg:classifiers":[
        {
            "category":"Shopping",
            "subcategory":"Computers & Home Electronics",
            "type":"Retail Goods"
        }
    ],
    "sg:phone":"+1   ",
    "sg:postcode":"60465",
    "sg:province":"IL",
    "wof:name":"Compudoc Chicago Inc",
    "wof:placetype":"venue"
},
  "geometry": {"coordinates":[-87.825661,41.688632],"type":"Point"}
}