{
  "type": "Feature",
  "properties": {
    "iso:country":"US",
    "sg:address":"520 W Ringold St",
    "sg:city":"Freeport",
    "sg:classifiers":[
        {
            "category":"Organizations",
            "subcategory":"Religious Organization",
            "type":"Services"
        }
    ],
    "sg:phone":"+1 815 233 0691",
    "sg:postcode":"61032",
    "sg:province":"IL",
    "wof:name":"Holy Temple Church",
    "wof:placetype":"venue"
},
  "geometry": {"coordinates":[-89.62705099999999,42.302297],"type":"Point"}
}