{
  "type": "Feature",
  "properties": {
    "iso:country":"US",
    "sg:address":"6344 N Claremont Ave",
    "sg:city":"Chicago",
    "sg:classifiers":[
        {
            "category":"Wholesale",
            "subcategory":"Groceries",
            "type":"Manufacturing & Wholesale Goods"
        }
    ],
    "sg:phone":"+1 773 338 4590",
    "sg:postcode":"60659",
    "sg:province":"IL",
    "sg:tags":[
        "grocers-wholesale"
    ],
    "wof:name":"Pantrax International, Inc.",
    "wof:placetype":"venue"
},
  "geometry": {"coordinates":[-87.688641,41.996755],"type":"Point"}
}