{
  "type": "Feature",
  "properties": {
    "iso:country":"US",
    "sg:address":"18525 Torrence Ave Ste C2",
    "sg:city":"Lansing",
    "sg:classifiers":[
        {
            "category":"Banks & Credit Unions",
            "subcategory":"Bank",
            "type":"Services"
        }
    ],
    "sg:phone":"+1 708 418 2334",
    "sg:postcode":"60438",
    "sg:province":"IL",
    "wof:name":"General Mills Employee Credit Union",
    "wof:placetype":"venue"
},
  "geometry": {"coordinates":[-87.558701,41.5588],"type":"Point"}
}