{
  "type": "Feature",
  "properties": {
    "iso:country":"US",
    "sg:address":"1440 W 127th St",
    "sg:city":"Calumet Park",
    "sg:classifiers":[
        {
            "category":"Professional",
            "subcategory":"Detective & Security Services",
            "type":"Services"
        }
    ],
    "sg:phone":"+1 708 389 7900",
    "sg:postcode":"60827",
    "sg:province":"IL",
    "sg:website":"www.benecoindustries.com",
    "wof:name":"Beneco Industries",
    "wof:placetype":"venue"
},
  "geometry": {"coordinates":[-87.65758599999999,41.663076],"type":"Point"}
}