{
  "type": "Feature",
  "properties": {
    "iso:country":"US",
    "sg:address":"1560 Oak Ave",
    "sg:city":"Evanston",
    "sg:classifiers":[
        {
            "category":"Organizations",
            "subcategory":"Community Association",
            "type":"Services"
        }
    ],
    "sg:phone":"+1 847 475 9042",
    "sg:postcode":"60201",
    "sg:province":"IL",
    "sg:tags":[
        "club"
    ],
    "wof:name":"Evanston Catholic Woman's Club",
    "wof:placetype":"venue"
},
  "geometry": {"coordinates":[-87.686925,42.046011],"type":"Point"}
}