{
  "type": "Feature",
  "properties": {
    "iso:country":"US",
    "sg:address":"6105 Factory Rd",
    "sg:city":"Crystal Lake",
    "sg:classifiers":[
        {
            "category":"Professional",
            "subcategory":"Advertising",
            "type":"Services"
        }
    ],
    "sg:phone":"+1 815 455 7327",
    "sg:postcode":"60014",
    "sg:province":"IL",
    "sg:tags":[
        "mailing",
        "shipping"
    ],
    "wof:name":"Mailways",
    "wof:placetype":"venue"
},
  "geometry": {"coordinates":[-88.31630699999999,42.222596],"type":"Point"}
}