{
  "type": "Feature",
  "properties": {
    "addr:full":"1003 Plainfield Rd Joliet IL 60435",
    "addr:housenumber":"1003",
    "addr:postcode":"60435",
    "addr:street":"Plainfield Rd",
    "iso:country":"US",
    "sg:address":"1003 Plainfield Rd",
    "sg:city":"Joliet",
    "sg:classifiers":[
        {
            "category":"Food & Beverages",
            "subcategory":"Candy",
            "type":"Retail Goods"
        }
    ],
    "sg:phone":"+1 815 722 0712",
    "sg:postcode":"60435",
    "sg:province":"IL",
    "sg:tags":[
        "confectionery"
    ],
    "wof:name":"Dan's Home Made Candy",
    "wof:placetype":"venue"
},
  "geometry": {"coordinates":[-88.107686,41.542294],"type":"Point"}
}