{
  "type": "Feature",
  "properties": {
    "iso:country":"US",
    "sg:address":"3052 W Cermak Rd",
    "sg:city":"Chicago",
    "sg:classifiers":[
        {
            "category":"Building & Trades",
            "subcategory":"Construction",
            "type":"Services"
        },
        {
            "category":"Building & Trades",
            "subcategory":"Electrical",
            "type":"Services"
        }
    ],
    "sg:phone":"+1 773 542 1520",
    "sg:postcode":"60623",
    "sg:province":"IL",
    "sg:tags":[
        "industrial",
        "electrician",
        "electric",
        "altering",
        "contractor",
        "contractors-commercial",
        "remodeling"
    ],
    "wof:name":"Garza Electrical Inc",
    "wof:placetype":"venue"
},
  "geometry": {"coordinates":[-87.701831,41.851822],"type":"Point"}
}