{
  "type": "Feature",
  "properties": {
    "iso:country":"US",
    "sg:address":"2241 W Howard St",
    "sg:city":"Chicago",
    "sg:classifiers":[
        {
            "category":"Professional",
            "type":"Services"
        }
    ],
    "sg:phone":"+1 773 338 2892",
    "sg:postcode":"60645",
    "sg:province":"IL",
    "sg:tags":[
        "writer",
        "publication",
        "editorial"
    ],
    "wof:name":"John Kirby Roche",
    "wof:placetype":"venue"
},
  "geometry": {"coordinates":[-87.68626,42.019505],"type":"Point"}
}