{
  "type": "Feature",
  "properties": {
    "iso:country":"US",
    "sg:address":"700 S Mazon St",
    "sg:city":"Coal City",
    "sg:classifiers":[
        {
            "category":"Building & Trades",
            "subcategory":"Construction",
            "type":"Services"
        }
    ],
    "sg:phone":"+1 815 634 8797",
    "sg:postcode":"60416",
    "sg:province":"IL",
    "sg:tags":[
        "maker",
        "cabinet"
    ],
    "wof:name":"Caliber Custom Cabinets",
    "wof:placetype":"venue"
},
  "geometry": {"coordinates":[-88.286636,41.279376],"type":"Point"}
}