{
  "type": "Feature",
  "properties": {
    "addr:full":"401 S Cicero Ave Chicago IL 60644",
    "addr:housenumber":"401",
    "addr:postcode":"60644",
    "addr:street":"S Cicero Ave",
    "iso:country":"US",
    "sg:address":"401 S Cicero Ave",
    "sg:city":"Chicago",
    "sg:classifiers":[
        {
            "category":"Shopping",
            "type":"Retail Goods"
        }
    ],
    "sg:phone":"+1   ",
    "sg:postcode":"60644",
    "sg:province":"IL",
    "sg:tags":[
        "merchandise"
    ],
    "wof:name":"HI Tech Wireless Inc",
    "wof:placetype":"venue"
},
  "geometry": {"coordinates":[-87.745035,41.87409],"type":"Point"}
}