{
  "type": "Feature",
  "properties": {
    "iso:country":"US",
    "sg:address":"1344 N Western",
    "sg:city":"Chicago",
    "sg:classifiers":[
        {
            "category":"Shopping",
            "subcategory":"Pharmacy",
            "type":"Retail Goods"
        }
    ],
    "sg:phone":"+1 773 278 5337",
    "sg:postcode":"60647",
    "sg:province":"IL",
    "sg:tags":[
        "drugstore"
    ],
    "wof:name":"J Discount Pharmacy & Pantry",
    "wof:placetype":"venue"
},
  "geometry": {"coordinates":[-87.68711999999999,41.90618],"type":"Point"}
}