{
  "type": "Feature",
  "properties": {
    "iso:country":"US",
    "sg:address":"605 E 8th St",
    "sg:city":"Gibson City",
    "sg:classifiers":[
        {
            "category":"Government",
            "subcategory":"Fire Station",
            "type":"Public Place"
        }
    ],
    "sg:phone":"+1 217 784 4221",
    "sg:postcode":"60936",
    "sg:province":"IL",
    "sg:tags":[
        "department"
    ],
    "wof:name":"Gibson City Fire Dept",
    "wof:placetype":"venue"
},
  "geometry": {"coordinates":[-88.367517,40.464892],"type":"Point"}
}