{
  "type": "Feature",
  "properties": {
    "iso:country":"US",
    "sg:address":"4555 20th St",
    "sg:city":"Rockford",
    "sg:classifiers":[
        {
            "category":"Education",
            "subcategory":"School",
            "type":"Public Place"
        }
    ],
    "sg:phone":"+1 815 874 2464",
    "sg:postcode":"61109",
    "sg:province":"IL",
    "wof:name":"Arthur W Frberg Elmentary Schl",
    "wof:placetype":"venue"
},
  "geometry": {"coordinates":[-89.05753199999999,42.219425],"type":"Point"}
}