{
  "type": "Feature",
  "properties": {
    "addr:full":"1921 Vaughn Rd Wood River IL 62095",
    "addr:housenumber":"1921",
    "addr:postcode":"62095",
    "addr:street":"Vaughn Rd",
    "iso:country":"US",
    "sg:address":"1921 Vaughn Rd",
    "sg:city":"Wood River",
    "sg:classifiers":[
        {
            "category":"Restaurant",
            "type":"Food & Drink"
        }
    ],
    "sg:menulink":"http://www.allmenus.com/il/wood-river/88562-applebees/menu/",
    "sg:phone":"+1 618 258 1051",
    "sg:postcode":"62095",
    "sg:province":"IL",
    "sg:tags":[
        "burger",
        "american",
        "sandwich",
        "soup"
    ],
    "wof:name":"Applebee's",
    "wof:placetype":"venue"
},
  "geometry": {"coordinates":[-90.065691,38.867288],"type":"Point"}
}