{
  "type": "Feature",
  "properties": {
    "addr:full":"8750 W Bryn Mawr Ave Suite 1000 Chicago IL 60631",
    "addr:housenumber":"8750",
    "addr:postcode":"60631",
    "addr:street":"W Bryn Mawr Ave Suite 1000",
    "iso:country":"US",
    "sg:address":"8750 W Bryn Mawr Ave Suite 1000",
    "sg:city":"Chicago",
    "sg:classifiers":[
        {
            "category":"Professional",
            "type":"Services"
        }
    ],
    "sg:phone":"+1 773 867 9204",
    "sg:postcode":"60631",
    "sg:province":"IL",
    "sg:website":"www.levysecurity.com",
    "wof:name":"Levy Security Corporation",
    "wof:placetype":"venue"
},
  "geometry": {"coordinates":[-87.845157,41.980993],"type":"Point"}
}