{
  "type": "Feature",
  "properties": {
    "addr:full":"417 S Main St Bourbonnais IL 60914",
    "addr:housenumber":"417",
    "addr:postcode":"60914",
    "addr:street":"S Main St",
    "iso:country":"US",
    "sg:address":"417 S Main St",
    "sg:city":"Bourbonnais",
    "sg:classifiers":[
        {
            "category":"Home & Garden",
            "subcategory":"Furniture",
            "type":"Retail Goods"
        }
    ],
    "sg:phone":"+1   ",
    "sg:postcode":"60914",
    "sg:province":"IL",
    "wof:name":"Country Oaks Furniture Inc",
    "wof:placetype":"venue"
},
  "geometry": {"coordinates":[-87.876895,41.152818],"type":"Point"}
}