{
  "type": "Feature",
  "properties": {
    "iso:country":"US",
    "sg:address":"1821 Dewitt Ave",
    "sg:city":"Mattoon",
    "sg:classifiers":[
        {
            "category":"Autos & Motor Vehicles",
            "subcategory":"Fuel & Gas Station",
            "type":"Retail Goods"
        }
    ],
    "sg:phone":"+1   ",
    "sg:postcode":"61938",
    "sg:province":"IL",
    "sg:tags":[
        "station",
        "gasoline"
    ],
    "wof:name":"Wareco",
    "wof:placetype":"venue"
},
  "geometry": {"coordinates":[-88.377639,39.488964],"type":"Point"}
}