{
  "type": "Feature",
  "properties": {
    "iso:country":"US",
    "sg:address":"17025 S Park Ave",
    "sg:city":"Harvey",
    "sg:classifiers":[
        {
            "category":"Social Services",
            "subcategory":"Child Care",
            "type":"Services"
        },
        {
            "category":"Education",
            "subcategory":"Preschool",
            "type":"Public Place"
        },
        {
            "category":"Education",
            "subcategory":"School",
            "type":"Public Place"
        }
    ],
    "sg:phone":"+1 708 331 2511",
    "sg:postcode":"60473",
    "sg:province":"IL",
    "sg:tags":[
        "elementary",
        "day"
    ],
    "sg:website":"www.kindercare.com",
    "wof:name":"Kindercare Learning Centers",
    "wof:placetype":"venue"
},
  "geometry": {"coordinates":[-87.606707,41.585591],"type":"Point"}
}