{
  "type": "Feature",
  "properties": {
    "addr:full":"2087 Nathan Ave Mascoutah IL 62258",
    "addr:housenumber":"2087",
    "addr:postcode":"62258",
    "addr:street":"Nathan Ave",
    "iso:country":"US",
    "sg:address":"2087 Nathan Ave",
    "sg:city":"Mascoutah",
    "sg:classifiers":[
        {
            "category":"Professional",
            "subcategory":"Business Services",
            "type":"Services"
        }
    ],
    "sg:phone":"+1 618 566 3517",
    "sg:postcode":"62258",
    "sg:province":"IL",
    "wof:name":"Aquashop",
    "wof:placetype":"venue"
},
  "geometry": {"coordinates":[-89.804115,38.509371],"type":"Point"}
}