{
  "type": "Feature",
  "properties": {
    "iso:country":"US",
    "sg:address":"346 W Maple St",
    "sg:city":"New Lenox",
    "sg:classifiers":[
        {
            "category":"Personal",
            "subcategory":"Beauty Salon",
            "type":"Services"
        }
    ],
    "sg:phone":"+1 815 485 9316",
    "sg:postcode":"60451",
    "sg:province":"IL",
    "sg:tags":[
        "shop"
    ],
    "wof:name":"New Beginnings Hair Design",
    "wof:placetype":"venue"
},
  "geometry": {"coordinates":[-87.97353,41.515515],"type":"Point"}
}