{
  "type": "Feature",
  "properties": {
    "addr:full":"4346 Howard St Skokie IL 60076",
    "addr:housenumber":"4346",
    "addr:postcode":"60076",
    "addr:street":"Howard St",
    "iso:country":"US",
    "sg:address":"4346 Howard St",
    "sg:city":"Skokie",
    "sg:classifiers":[
        {
            "category":"Social Services",
            "subcategory":"Child Care",
            "type":"Services"
        }
    ],
    "sg:phone":"+1 847 675 6619",
    "sg:postcode":"60076",
    "sg:province":"IL",
    "sg:tags":[
        "kindergarten",
        "day",
        "preschool"
    ],
    "sg:website":"http://www.tinytotskokie.com",
    "wof:name":"Tiny Tot Preschool & Kindergarten",
    "wof:placetype":"venue"
},
  "geometry": {"coordinates":[-87.73706900000001,42.019005],"type":"Point"}
}