{
  "type": "Feature",
  "properties": {
    "addr:full":"3525 S Michigan Ave Chicago IL 60653",
    "addr:housenumber":"3525",
    "addr:postcode":"60653",
    "addr:street":"S Michigan Ave",
    "iso:country":"US",
    "sg:address":"3525 S Michigan Ave",
    "sg:city":"Chicago",
    "sg:classifiers":[
        {
            "category":"Health Services",
            "subcategory":"Nursing And Care Facility",
            "type":"Services"
        },
        {
            "category":"Health Services",
            "subcategory":"Health Practitioner",
            "type":"Services"
        }
    ],
    "sg:phone":"+1 312 945 4010",
    "sg:postcode":"60653",
    "sg:province":"IL",
    "sg:tags":[
        "home",
        "eldercare-home"
    ],
    "wof:name":"Cook County Bureau Of Health Services",
    "wof:placetype":"venue"
},
  "geometry": {"coordinates":[-87.623251,41.830683],"type":"Point"}
}