{
  "type": "Feature",
  "properties": {
    "addr:full":"20 Lincoln Rd Canton IL 61520",
    "addr:housenumber":"20",
    "addr:postcode":"61520",
    "addr:street":"Lincoln Rd",
    "iso:country":"US",
    "sg:address":"20 Lincoln Rd",
    "sg:city":"Canton",
    "sg:classifiers":[
        {
            "category":"Education",
            "subcategory":"School",
            "type":"Public Place"
        }
    ],
    "sg:phone":"+1 309 647 7594",
    "sg:postcode":"61520",
    "sg:province":"IL",
    "wof:name":"Lincoln Elementary School",
    "wof:placetype":"venue"
},
  "geometry": {"coordinates":[-90.03411199999999,40.579574],"type":"Point"}
}