{
  "type": "Feature",
  "properties": {
    "addr:full":"1013 5th St Aurora IL 60505",
    "addr:housenumber":"1013",
    "addr:postcode":"60505",
    "addr:street":"5Th St",
    "iso:country":"US",
    "sg:address":"1013 5th St",
    "sg:city":"Aurora",
    "sg:classifiers":[
        {
            "category":"Farming",
            "subcategory":"Livestock Farm",
            "type":"Manufacturing & Wholesale Goods"
        }
    ],
    "sg:phone":"+1 630 892 7202",
    "sg:postcode":"60505",
    "sg:province":"IL",
    "sg:tags":[
        "hog",
        "beef",
        "corn",
        "cattle",
        "or",
        "feedlot"
    ],
    "wof:name":"Paul Eggertt",
    "wof:placetype":"venue"
},
  "geometry": {"coordinates":[-88.313305,41.735752],"type":"Point"}
}