{
  "type": "Feature",
  "properties": {
    "iso:country":"US",
    "sg:address":"607 W Main St # 100",
    "sg:city":"Carbondale",
    "sg:classifiers":[
        {
            "category":"Health Services",
            "subcategory":"Clinic",
            "type":"Services"
        }
    ],
    "sg:phone":"+1 618 457 4890",
    "sg:postcode":"62901",
    "sg:province":"IL",
    "sg:tags":[
        "counseling",
        "mental"
    ],
    "wof:name":"Budslick Counseling & Psychotherapy Services",
    "wof:placetype":"venue"
},
  "geometry": {"coordinates":[-89.223396,37.726601],"type":"Point"}
}