{
  "type": "Feature",
  "properties": {
    "iso:country":"US",
    "sg:address":"1701 E Wilson St",
    "sg:city":"Batavia",
    "sg:classifiers":[
        {
            "category":"Professional",
            "subcategory":"Research",
            "type":"Services"
        }
    ],
    "sg:phone":"+1 630 406 7673",
    "sg:postcode":"60510",
    "sg:province":"IL",
    "sg:tags":[
        "environmental",
        "ecological"
    ],
    "wof:name":"Direct Push Analytical",
    "wof:placetype":"venue"
},
  "geometry": {"coordinates":[-88.265386,41.853868],"type":"Point"}
}