{
  "type": "Feature",
  "properties": {
    "iso:country":"US",
    "sg:address":"1387 N Galena Ave",
    "sg:city":"Dixon",
    "sg:classifiers":[
        {
            "category":"Food & Beverages",
            "subcategory":"Groceries & Convenience Stores",
            "type":"Retail Goods"
        }
    ],
    "sg:phone":"+1 815 000 1111",
    "sg:postcode":"61021",
    "sg:province":"IL",
    "sg:tags":[
        "grocer"
    ],
    "wof:name":"Aldi",
    "wof:placetype":"venue"
},
  "geometry": {"coordinates":[-89.497766,41.861117],"type":"Point"}
}