{
  "type": "Feature",
  "properties": {
    "addr:full":"1429 Hoffman Ave Park Ridge IL 60068",
    "addr:housenumber":"1429",
    "addr:postcode":"60068",
    "addr:street":"Hoffman Ave",
    "iso:country":"US",
    "sg:address":"1429 Hoffman Ave",
    "sg:city":"Park Ridge",
    "sg:classifiers":[
        {
            "category":"Professional",
            "subcategory":"Employment Agencies",
            "type":"Services"
        }
    ],
    "sg:phone":"+1 847 692 6385",
    "sg:postcode":"60068",
    "sg:province":"IL",
    "sg:tags":[
        "specializing",
        "executive",
        "operates",
        "an"
    ],
    "wof:name":"Advantage Group",
    "wof:placetype":"venue"
},
  "geometry": {"coordinates":[-87.861158,42.033325],"type":"Point"}
}