{
  "type": "Feature",
  "properties": {
    "iso:country":"US",
    "sg:address":"225 S Locust St",
    "sg:city":"Arcola",
    "sg:classifiers":[
        {
            "category":"Home & Garden",
            "subcategory":"Garden Supply",
            "type":"Retail Goods"
        }
    ],
    "sg:phone":"+1 217 268 3838",
    "sg:postcode":"61910",
    "sg:province":"IL",
    "sg:tags":[
        "bulb",
        "seed"
    ],
    "wof:name":"Sturdy-Grow Hybrids",
    "wof:placetype":"venue"
},
  "geometry": {"coordinates":[-88.306847,39.682488],"type":"Point"}
}