{
  "type": "Feature",
  "properties": {
    "iso:country":"US",
    "sg:address":"3712 E University Ave",
    "sg:city":"Urbana",
    "sg:classifiers":[
        {
            "category":"Manufacturing",
            "subcategory":"Glass & Minerals",
            "type":"Manufacturing & Wholesale Goods"
        }
    ],
    "sg:phone":"+1 217 367 0654",
    "sg:postcode":"61802",
    "sg:province":"IL",
    "sg:tags":[
        "product",
        "nonmetallic",
        "mfg"
    ],
    "wof:name":"Sculpture Scope Production",
    "wof:placetype":"venue"
},
  "geometry": {"coordinates":[-88.180762,40.114508],"type":"Point"}
}