{
  "type": "Feature",
  "properties": {
    "iso:country":"US",
    "sg:address":"4545 W 103rd St",
    "sg:city":"Oak Lawn",
    "sg:classifiers":[
        {
            "category":"Health Services",
            "subcategory":"Doctor",
            "type":"Services"
        }
    ],
    "sg:phone":"+1 708 425 3494",
    "sg:postcode":"60453",
    "sg:province":"IL",
    "sg:tags":[
        "medical"
    ],
    "wof:name":"Abraham Malik MD",
    "wof:placetype":"venue"
},
  "geometry": {"coordinates":[-87.73527,41.705572],"type":"Point"}
}