{
  "type": "Feature",
  "properties": {
    "addr:full":"926 Bowling Green Dr Homewood IL 60430",
    "addr:housenumber":"926",
    "addr:postcode":"60430",
    "addr:street":"Bowling Green Dr",
    "iso:country":"US",
    "sg:address":"926 Bowling Green Dr",
    "sg:city":"Homewood",
    "sg:classifiers":[
        {
            "category":"Education",
            "subcategory":"Special Training",
            "type":"Public Place"
        }
    ],
    "sg:phone":"+1 708 799 4088",
    "sg:postcode":"60430",
    "sg:province":"IL",
    "sg:tags":[
        "school",
        "educational"
    ],
    "wof:name":"Irvin J Roth",
    "wof:placetype":"venue"
},
  "geometry": {"coordinates":[-87.639698,41.546027],"type":"Point"}
}