{
  "type": "Feature",
  "properties": {
    "addr:full":"5840 North Lincoln Ave Chicago IL 60659",
    "addr:housenumber":"5840",
    "addr:postcode":"60659",
    "addr:street":"North Lincoln Ave",
    "iso:country":"US",
    "sg:address":"5840 North Lincoln Ave",
    "sg:city":"Chicago",
    "sg:classifiers":[
        {
            "category":"Building & Trades",
            "subcategory":"Pest Control",
            "type":"Services"
        }
    ],
    "sg:phone":"+1 773 334 1243",
    "sg:postcode":"60659",
    "sg:province":"IL",
    "sg:website":"www.orkin.com",
    "wof:name":"Orkin Pest Control Services",
    "wof:placetype":"venue"
},
  "geometry": {"coordinates":[-87.70274000000001,41.987496],"type":"Point"}
}