{
  "type": "Feature",
  "properties": {
    "addr:full":"2605 Rolling Acres Dr Champaign IL 61822",
    "addr:housenumber":"2605",
    "addr:postcode":"61822",
    "addr:street":"Rolling Acres Dr",
    "iso:country":"US",
    "sg:address":"2605 Rolling Acres Dr",
    "sg:city":"Champaign",
    "sg:classifiers":[
        {
            "category":"Manufacturing",
            "subcategory":"Tools & Machinery",
            "type":"Manufacturing & Wholesale Goods"
        }
    ],
    "sg:phone":"+1 217 355 0017",
    "sg:postcode":"61822",
    "sg:province":"IL",
    "sg:tags":[
        "electrical",
        "mfg"
    ],
    "wof:name":"Opal Kelly Inc",
    "wof:placetype":"venue"
},
  "geometry": {"coordinates":[-88.289135,40.067102],"type":"Point"}
}