{
  "type": "Feature",
  "properties": {
    "iso:country":"US",
    "sg:address":"1000 Hart Rd Ste 110",
    "sg:city":"Barrington",
    "sg:classifiers":[
        {
            "category":"Recreation",
            "type":"Entertainment"
        }
    ],
    "sg:phone":"+1 847 381 6607",
    "sg:postcode":"60010",
    "sg:province":"IL",
    "sg:tags":[
        "entertainers-family",
        "business"
    ],
    "wof:name":"Barrington Childrens Choir",
    "wof:placetype":"venue"
},
  "geometry": {"coordinates":[-88.152776,42.163214],"type":"Point"}
}