{
  "type": "Feature",
  "properties": {
    "iso:country":"US",
    "sg:address":"810 E State St",
    "sg:city":"Rockford",
    "sg:classifiers":[
        {
            "category":"Professional",
            "subcategory":"Computer Services",
            "type":"Services"
        }
    ],
    "sg:phone":"+1 815 963 4055",
    "sg:postcode":"61104",
    "sg:province":"IL",
    "sg:tags":[
        "website",
        "design",
        "related"
    ],
    "wof:name":"Myers Computer Consulting",
    "wof:placetype":"venue"
},
  "geometry": {"coordinates":[-89.082339,42.266946],"type":"Point"}
}