{
  "type": "Feature",
  "properties": {
    "addr:full":"1 Metropolitan Sq Saint Louis MO 63102",
    "addr:housenumber":"1",
    "addr:postcode":"63102",
    "addr:street":"Metropolitan Sq",
    "iso:country":"US",
    "sg:address":"1 Metropolitan Sq",
    "sg:city":"Saint Louis",
    "sg:classifiers":[
        {
            "category":"Professional",
            "subcategory":"Lawyer & Legal Services",
            "type":"Services"
        }
    ],
    "sg:phone":"+1 314 231 5400",
    "sg:postcode":"63102",
    "sg:province":"MO",
    "wof:name":"Petrillo Kathleen M Atty",
    "wof:placetype":"venue"
},
  "geometry": {"coordinates":[-90.189598,38.626202],"type":"Point"}
}