{
  "type": "Feature",
  "properties": {
    "addr:full":"450 Airport Rd Elgin IL 60123",
    "addr:housenumber":"450",
    "addr:postcode":"60123",
    "addr:street":"Airport Rd",
    "iso:country":"US",
    "sg:address":"450 Airport Rd",
    "sg:city":"Elgin",
    "sg:classifiers":[
        {
            "category":"Professional",
            "subcategory":"Computer Services",
            "type":"Services"
        }
    ],
    "sg:phone":"+1 847 741 1861",
    "sg:postcode":"60123",
    "sg:province":"IL",
    "sg:tags":[
        "repair"
    ],
    "wof:name":"Jobpack Inc",
    "wof:placetype":"venue"
},
  "geometry": {"coordinates":[-88.28861499999999,42.071274],"type":"Point"}
}