{
  "type": "Feature",
  "properties": {
    "addr:full":"2007 Halsted Rd Rockford IL 61103",
    "addr:housenumber":"2007",
    "addr:postcode":"61103",
    "addr:street":"Halsted Rd",
    "iso:country":"US",
    "sg:address":"2007 Halsted Rd",
    "sg:city":"Rockford",
    "sg:classifiers":[
        {
            "category":"Utilities",
            "subcategory":"Telephone",
            "type":"Services"
        }
    ],
    "sg:phone":"+1 815 877 7611",
    "sg:postcode":"61103",
    "sg:province":"IL",
    "sg:tags":[
        "communications"
    ],
    "wof:name":"AAA Communications",
    "wof:placetype":"venue"
},
  "geometry": {"coordinates":[-89.08883299999999,42.310369],"type":"Point"}
}