{
  "type": "Feature",
  "properties": {
    "addr:full":"2419 N Talman Ave Chicago IL 60647",
    "addr:housenumber":"2419",
    "addr:postcode":"60647",
    "addr:street":"N Talman Ave",
    "iso:country":"US",
    "sg:address":"2419 N Talman Ave",
    "sg:city":"Chicago",
    "sg:classifiers":[
        {
            "category":"Retail",
            "subcategory":"Portrait Studio",
            "type":"Services"
        }
    ],
    "sg:phone":"+1 773 770 9148",
    "sg:postcode":"60647",
    "sg:province":"IL",
    "sg:tags":[
        "photo"
    ],
    "wof:name":"Emily Dewan Photography",
    "wof:placetype":"venue"
},
  "geometry": {"coordinates":[-87.69368,41.925038],"type":"Point"}
}