{
  "type": "Feature",
  "properties": {
    "iso:country":"US",
    "sg:address":"221 S Main St",
    "sg:city":"Wauconda",
    "sg:classifiers":[
        {
            "category":"Retail",
            "subcategory":"Auto Repair",
            "type":"Services"
        }
    ],
    "sg:phone":"+1 847 526 7250",
    "sg:postcode":"60084",
    "sg:province":"IL",
    "sg:tags":[
        "repairing",
        "automobile",
        "automotive",
        "general"
    ],
    "wof:name":"Johns Automotive Repair Inc",
    "wof:placetype":"venue"
},
  "geometry": {"coordinates":[-88.138354,42.25763],"type":"Point"}
}