{
  "type": "Feature",
  "properties": {
    "iso:country":"US",
    "sg:address":"2421 East Ave",
    "sg:city":"Berwyn",
    "sg:classifiers":[
        {
            "category":"Building & Trades",
            "subcategory":"Landscaping Services",
            "type":"Services"
        }
    ],
    "sg:phone":"+1 708 788 9916",
    "sg:postcode":"60402",
    "sg:province":"IL",
    "sg:tags":[
        "landscape"
    ],
    "wof:name":"R&R Landscaping Inc",
    "wof:placetype":"venue"
},
  "geometry": {"coordinates":[-87.788225,41.845531],"type":"Point"}
}