{
  "type": "Feature",
  "properties": {
    "iso:country":"US",
    "sg:address":"408 N Prairie Ave",
    "sg:city":"Polo",
    "sg:classifiers":[
        {
            "category":"Freight",
            "type":"Transportation"
        }
    ],
    "sg:phone":"+1 815 946 2162",
    "sg:postcode":"61064",
    "sg:province":"IL",
    "sg:tags":[
        "operator",
        "trucking"
    ],
    "wof:name":"G&W Trucking",
    "wof:placetype":"venue"
},
  "geometry": {"coordinates":[-89.573751,41.991384],"type":"Point"}
}