{
  "type": "Feature",
  "properties": {
    "iso:country":"US",
    "sg:address":"6116 Mulford Village Dr",
    "sg:city":"Rockford",
    "sg:classifiers":[
        {
            "category":"Professional",
            "subcategory":"Accounting & Tax Preparation",
            "type":"Services"
        }
    ],
    "sg:phone":"+1 815 316 1871",
    "sg:postcode":"61107",
    "sg:province":"IL",
    "sg:tags":[
        "billing"
    ],
    "wof:name":"Medical Billing Professionals",
    "wof:placetype":"venue"
},
  "geometry": {"coordinates":[-88.998283,42.268051],"type":"Point"}
}