{
  "type": "Feature",
  "properties": {
    "iso:country":"US",
    "sg:address":"1206 N Drury Ln",
    "sg:city":"Arlington Heights",
    "sg:classifiers":[
        {
            "category":"Home & Garden",
            "subcategory":"Furniture",
            "type":"Retail Goods"
        }
    ],
    "sg:phone":"+1   ",
    "sg:postcode":"60004",
    "sg:province":"IL",
    "wof:name":"Arl Furniture",
    "wof:placetype":"venue"
},
  "geometry": {"coordinates":[-87.963775,42.097993],"type":"Point"}
}