{
  "type": "Feature",
  "properties": {
    "iso:country":"US",
    "sg:address":"3001 N Lincoln Ave",
    "sg:city":"Urbana",
    "sg:classifiers":[
        {
            "category":"Freight",
            "type":"Transportation"
        }
    ],
    "sg:phone":"+1 217 344 0615",
    "sg:postcode":"61802",
    "sg:province":"IL",
    "sg:tags":[
        "delivery"
    ],
    "wof:name":"Emery Worldwide",
    "wof:placetype":"venue"
},
  "geometry": {"coordinates":[-88.220037,40.144277],"type":"Point"}
}