{
  "type": "Feature",
  "properties": {
    "addr:full":"617 N Galena Ave Dixon IL 61021",
    "addr:housenumber":"617",
    "addr:postcode":"61021",
    "addr:street":"N Galena Ave",
    "iso:country":"US",
    "sg:address":"617 N Galena Ave",
    "sg:city":"Dixon",
    "sg:classifiers":[
        {
            "category":"Building & Trades",
            "subcategory":"Construction",
            "type":"Services"
        }
    ],
    "sg:phone":"+1 815 288 1307",
    "sg:postcode":"61021",
    "sg:province":"IL",
    "sg:tags":[
        "system",
        "contractor",
        "air conditioning"
    ],
    "wof:name":"Bill's Plumbing & Heating",
    "wof:placetype":"venue"
},
  "geometry": {"coordinates":[-89.486289,41.851915],"type":"Point"}
}