{
  "type": "Feature",
  "properties": {
    "iso:country":"US",
    "sg:address":"550 Landmarks Blvd",
    "sg:city":"Alton",
    "sg:classifiers":[
        {
            "category":"Health Services",
            "subcategory":"Doctor",
            "type":"Services"
        }
    ],
    "sg:phone":"+1 618 463 0649",
    "sg:postcode":"62002",
    "sg:province":"IL",
    "sg:tags":[
        "medical"
    ],
    "wof:name":"Sirisak Sun MD",
    "wof:placetype":"venue"
},
  "geometry": {"coordinates":[-90.178103,38.888944],"type":"Point"}
}