{
  "type": "Feature",
  "properties": {
    "iso:country":"US",
    "sg:address":"4210 W Irving Park Rd",
    "sg:city":"Chicago",
    "sg:classifiers":[
        {
            "category":"Health Services",
            "subcategory":"Health Practitioner",
            "type":"Services"
        }
    ],
    "sg:phone":"+1 773 777 7055",
    "sg:postcode":"60641",
    "sg:province":"IL",
    "sg:tags":[
        "naturopathic/holistic"
    ],
    "sg:website":"www.mesomuscledocs.com/index.html",
    "wof:name":"In Balance Naprapaths",
    "wof:placetype":"venue"
},
  "geometry": {"coordinates":[-87.732832,41.953742],"type":"Point"}
}