{
  "type": "Feature",
  "properties": {
    "iso:country":"US",
    "sg:address":"1905 W 103rd St",
    "sg:city":"Chicago",
    "sg:classifiers":[
        {
            "category":"Deli",
            "type":"Food & Drink"
        },
        {
            "category":"Restaurant",
            "type":"Food & Drink"
        }
    ],
    "sg:phone":"+1 773 396 5800",
    "sg:postcode":"60643",
    "sg:province":"IL",
    "sg:tags":[
        "italian"
    ],
    "sg:website":"www.calabria-imports.com/",
    "wof:name":"Calabria Imports",
    "wof:placetype":"venue"
},
  "geometry": {"coordinates":[-87.669601,41.706402],"type":"Point"}
}