{
  "type": "Feature",
  "properties": {
    "iso:country":"US",
    "sg:address":"500 46th St",
    "sg:city":"Rock Island",
    "sg:classifiers":[
        {
            "category":"Wholesale",
            "subcategory":"Fruits & Vegetables",
            "type":"Manufacturing & Wholesale Goods"
        }
    ],
    "sg:phone":"+1 309 786 0969",
    "sg:postcode":"61201",
    "sg:province":"IL",
    "wof:name":"Loffredo Produce",
    "wof:placetype":"venue"
},
  "geometry": {"coordinates":[-90.537323,41.505694],"type":"Point"}
}