{
  "type": "Feature",
  "properties": {
    "addr:full":"506 S Commonwealth Ave Elgin IL 60123",
    "addr:housenumber":"506",
    "addr:postcode":"60123",
    "addr:street":"S Commonwealth Ave",
    "iso:country":"US",
    "sg:address":"506 S Commonwealth Ave",
    "sg:city":"Elgin",
    "sg:classifiers":[
        {
            "category":"Professional",
            "subcategory":"Business Services",
            "type":"Services"
        }
    ],
    "sg:phone":"+1 847 608 7520",
    "sg:postcode":"60123",
    "sg:province":"IL",
    "wof:name":"J & S Computer Solutions",
    "wof:placetype":"venue"
},
  "geometry": {"coordinates":[-88.30139200000001,42.023474],"type":"Point"}
}