{
  "type": "Feature",
  "properties": {
    "iso:country":"US",
    "sg:address":"1129 Oak St",
    "sg:city":"Quincy",
    "sg:classifiers":[
        {
            "category":"Organizations",
            "subcategory":"Non-profit Organization",
            "type":"Services"
        }
    ],
    "sg:phone":"+1 217 228 3022",
    "sg:postcode":"62301",
    "sg:province":"IL",
    "sg:tags":[
        "social"
    ],
    "wof:name":"Quincy Hospitality House",
    "wof:placetype":"venue"
},
  "geometry": {"coordinates":[-91.397962,39.938213],"type":"Point"}
}