{
  "type": "Feature",
  "properties": {
    "iso:country":"US",
    "sg:address":"4715 N Damen Ave Ste 4",
    "sg:city":"Chicago",
    "sg:classifiers":[
        {
            "category":"Professional",
            "subcategory":"Art Services",
            "type":"Services"
        }
    ],
    "sg:phone":"+1 847 571 1473",
    "sg:postcode":"60202",
    "sg:province":"IL",
    "sg:tags":[
        "photographer"
    ],
    "sg:website":"www.erikdavisphotography.com",
    "wof:name":"Erik Davis Photography",
    "wof:placetype":"venue"
},
  "geometry": {"coordinates":[-87.678645,41.967479],"type":"Point"}
}