{
  "type": "Feature",
  "properties": {
    "iso:country":"US",
    "sg:address":"3061 N Lincoln Ave",
    "sg:city":"Chicago",
    "sg:classifiers":[
        {
            "category":"Professional",
            "type":"Services"
        }
    ],
    "sg:phone":"+1 773 528 5100",
    "sg:postcode":"60657",
    "sg:province":"IL",
    "sg:tags":[
        "consultant",
        "coach",
        "business"
    ],
    "wof:name":"American Institute-Serbia",
    "wof:placetype":"venue"
},
  "geometry": {"coordinates":[-87.665386,41.937344],"type":"Point"}
}