{
  "type": "Feature",
  "properties": {
    "iso:country":"US",
    "sg:address":"946 E 2000 North Rd",
    "sg:city":"Edinburg",
    "sg:classifiers":[
        {
            "category":"Wholesale",
            "subcategory":"Farm Supplies",
            "type":"Manufacturing & Wholesale Goods"
        },
        {
            "category":"Farming",
            "subcategory":"Farm",
            "type":"Manufacturing & Wholesale Goods"
        }
    ],
    "sg:phone":"+1 217 623 4208",
    "sg:postcode":"62531",
    "sg:province":"IL",
    "sg:tags":[
        "grain"
    ],
    "wof:name":"Lee Brockelsby",
    "wof:placetype":"venue"
},
  "geometry": {"coordinates":[-89.270164,39.640675],"type":"Point"}
}