{
  "type": "Feature",
  "properties": {
    "addr:full":"3376 N Central Avenue Chicago IL 60634",
    "addr:housenumber":"3376",
    "addr:postcode":"60634",
    "addr:street":"N Central Avenue",
    "iso:country":"US",
    "sg:address":"3376 N Central Avenue",
    "sg:city":"Chicago",
    "sg:classifiers":[
        {
            "category":"Professional",
            "subcategory":"Lawyer & Legal Services",
            "type":"Services"
        }
    ],
    "sg:phone":"+1 773 777 2022",
    "sg:postcode":"60634",
    "sg:province":"IL",
    "sg:tags":[
        "personal",
        "injury"
    ],
    "wof:name":"Law Offices of Jerry A Kugler",
    "wof:placetype":"venue"
},
  "geometry": {"coordinates":[-87.766386,41.94199],"type":"Point"}
}