{
  "type": "Feature",
  "properties": {
    "addr:full":"312 Clarksville Rd Pittsfield IL 62363",
    "addr:housenumber":"312",
    "addr:postcode":"62363",
    "addr:street":"Clarksville Rd",
    "iso:country":"US",
    "sg:address":"312 Clarksville Rd",
    "sg:city":"Pittsfield",
    "sg:classifiers":[
        {
            "category":"Personal",
            "type":"Services"
        }
    ],
    "sg:phone":"+1   ",
    "sg:postcode":"62363",
    "sg:province":"IL",
    "sg:tags":[
        "fitness",
        "physical",
        "sp",
        "facility"
    ],
    "wof:name":"Reel Net & Twine",
    "wof:placetype":"venue"
},
  "geometry": {"coordinates":[-90.809353,39.603958],"type":"Point"}
}