{
  "type": "Feature",
  "properties": {
    "iso:country":"US",
    "sg:address":"9953 Southwest Hwy",
    "sg:city":"Oak Lawn",
    "sg:classifiers":[
        {
            "category":"Bars & Pubs",
            "type":"Food & Drink"
        }
    ],
    "sg:phone":"+1   ",
    "sg:postcode":"60453",
    "sg:province":"IL",
    "sg:tags":[
        "drinking",
        "eating"
    ],
    "wof:name":"Costello",
    "wof:placetype":"venue"
},
  "geometry": {"coordinates":[-87.778449,41.710572],"type":"Point"}
}