{
  "type": "Feature",
  "properties": {
    "iso:country":"US",
    "sg:address":"340 E Superior",
    "sg:city":"Chicago",
    "sg:classifiers":[
        {
            "category":"Restaurant",
            "type":"Food & Drink"
        }
    ],
    "sg:phone":"+1 773 525 2695",
    "sg:postcode":"60611",
    "sg:province":"IL",
    "sg:tags":[
        "italian"
    ],
    "sg:website":"www.pastabowl.com",
    "wof:name":"The Pasta Bowl Truck",
    "wof:placetype":"venue"
},
  "geometry": {"coordinates":[-87.618775,41.896286],"type":"Point"}
}