{
  "type": "Feature",
  "properties": {
    "iso:country":"US",
    "sg:address":"303 S College Ave",
    "sg:city":"Aledo",
    "sg:classifiers":[
        {
            "category":"Real Estate",
            "subcategory":"Real Estate Agent",
            "type":"Services"
        }
    ],
    "sg:phone":"+1 309 582 5353",
    "sg:postcode":"61231",
    "sg:province":"IL",
    "wof:name":"Malone Agency RE & Insur",
    "wof:placetype":"venue"
},
  "geometry": {"coordinates":[-90.749331,41.199899],"type":"Point"}
}