{
  "type": "Feature",
  "properties": {
    "iso:country":"US",
    "sg:address":"9640 Jolliff Bridge Rd",
    "sg:city":"Centralia",
    "sg:classifiers":[
        {
            "category":"Autos & Motor Vehicles",
            "subcategory":"Auto Supplies",
            "type":"Retail Goods"
        }
    ],
    "sg:phone":"+1 618 532 2411",
    "sg:postcode":"62801",
    "sg:province":"IL",
    "sg:tags":[
        "equipment",
        "air",
        "conditioning",
        "automobile"
    ],
    "wof:name":"Doug Loy Auto Svc Ctr",
    "wof:placetype":"venue"
},
  "geometry": {"coordinates":[-89.15609000000001,38.559831],"type":"Point"}
}