{
  "type": "Feature",
  "properties": {
    "iso:country":"US",
    "sg:address":"44 Main St",
    "sg:city":"Champaign",
    "sg:classifiers":[
        {
            "category":"Professional",
            "subcategory":"Management & Consulting",
            "type":"Services"
        }
    ],
    "sg:phone":"+1 217 351 9840",
    "sg:postcode":"61820",
    "sg:province":"IL",
    "sg:tags":[
        "consultant",
        "educational"
    ],
    "wof:name":"Educational Resources Inc",
    "wof:placetype":"venue"
},
  "geometry": {"coordinates":[-88.241804,40.117672],"type":"Point"}
}