{
  "type": "Feature",
  "properties": {
    "iso:country":"US",
    "sg:address":"1950 W Cermak Road",
    "sg:city":"Chicago",
    "sg:classifiers":[
        {
            "category":"Health Services",
            "subcategory":"Dentist",
            "type":"Services"
        }
    ],
    "sg:phone":"+1 773 376 2777",
    "sg:postcode":"60608",
    "sg:province":"IL",
    "wof:name":"Subbaraju Nandini",
    "wof:placetype":"venue"
},
  "geometry": {"coordinates":[-87.675372,41.85229],"type":"Point"}
}