{
  "type": "Feature",
  "properties": {
    "iso:country":"US",
    "sg:address":"200 Williams Dr",
    "sg:city":"Schaumburg",
    "sg:classifiers":[
        {
            "category":"Organizations",
            "subcategory":"Religious Organization",
            "type":"Services"
        }
    ],
    "sg:phone":"+1 630 894 4764",
    "sg:postcode":"60193",
    "sg:province":"IL",
    "wof:name":"Chinese Gospel Church Inc",
    "wof:placetype":"venue"
},
  "geometry": {"coordinates":[-88.10173399999999,42.021081],"type":"Point"}
}