{
  "type": "Feature",
  "properties": {
    "addr:full":"7373 Harrison Ave Rockford IL 61112",
    "addr:housenumber":"7373",
    "addr:postcode":"61112",
    "addr:street":"Harrison Ave",
    "iso:country":"US",
    "sg:address":"7373 Harrison Ave",
    "sg:city":"Rockford",
    "sg:classifiers":[
        {
            "category":"Autos & Motor Vehicles",
            "subcategory":"Recreational Vehicle Sales",
            "type":"Retail Goods"
        }
    ],
    "sg:phone":"+1 815 332 3322",
    "sg:postcode":"61112",
    "sg:province":"IL",
    "sg:website":"www.collierrv.com",
    "wof:name":"Collier Rv Ctr",
    "wof:placetype":"venue"
},
  "geometry": {"coordinates":[-88.974465,42.24108],"type":"Point"}
}