{
  "type": "Feature",
  "properties": {
    "addr:full":"195 N Milwaukee Ave Vernon Hills IL 60061",
    "addr:housenumber":"195",
    "addr:postcode":"60061",
    "addr:street":"N Milwaukee Ave",
    "iso:country":"US",
    "sg:address":"195 N Milwaukee Ave",
    "sg:city":"Vernon Hills",
    "sg:classifiers":[
        {
            "category":"Professional",
            "subcategory":"Business Services",
            "type":"Services"
        },
        {
            "category":"Home & Garden",
            "subcategory":"Carpets & Floor Coverings",
            "type":"Retail Goods"
        }
    ],
    "sg:phone":"+1 847 415 2000",
    "sg:postcode":"60061",
    "sg:province":"IL",
    "sg:tags":[
        "dealer",
        "rug"
    ],
    "wof:name":"Wholesale Carpet Designs Inc",
    "wof:placetype":"venue"
},
  "geometry": {"coordinates":[-87.941654,42.228331],"type":"Point"}
}