{
  "type": "Feature",
  "properties": {
    "addr:full":"3035 E. 130th St Chicago IL 60633",
    "addr:housenumber":"3035",
    "addr:postcode":"60633",
    "addr:street":"E. 130Th St",
    "iso:country":"US",
    "sg:address":"3035 E. 130th St",
    "sg:city":"Chicago",
    "sg:classifiers":[
        {
            "category":"Park",
            "type":"Public Place"
        }
    ],
    "sg:phone":"+1 773 646 0210",
    "sg:postcode":"60633",
    "sg:province":"IL",
    "sg:website":"www.chicagoparkdistrict.com/inde...",
    "wof:name":"Mann Park",
    "wof:placetype":"venue"
},
  "geometry": {"coordinates":[-87.549458,41.659157],"type":"Point"}
}