{
  "type": "Feature",
  "properties": {
    "iso:country":"US",
    "sg:address":"333 S Desplaines St A",
    "sg:city":"Chicago",
    "sg:classifiers":[
        {
            "category":"Professional",
            "subcategory":"Art Services",
            "type":"Services"
        }
    ],
    "sg:phone":"+1 312 454 3243",
    "sg:postcode":"60661",
    "sg:province":"IL",
    "sg:tags":[
        "designer",
        "display",
        "producer"
    ],
    "wof:name":"Eric Tryba Creative",
    "wof:placetype":"venue"
},
  "geometry": {"coordinates":[-87.643992,41.877563],"type":"Point"}
}