{
  "type": "Feature",
  "properties": {
    "iso:country":"US",
    "sg:address":"1256 W Jefferson St",
    "sg:city":"Joliet",
    "sg:classifiers":[
        {
            "category":"Professional",
            "subcategory":"Credit Reporting & Collection",
            "type":"Services"
        }
    ],
    "sg:phone":"+1 815 722 6300",
    "sg:postcode":"60435",
    "sg:province":"IL",
    "sg:tags":[
        "agency"
    ],
    "wof:name":"Collection Professionals Inc",
    "wof:placetype":"venue"
},
  "geometry": {"coordinates":[-88.112381,41.522893],"type":"Point"}
}