{
  "type": "Feature",
  "properties": {
    "addr:full":"4901 W 79th St Bedford Park IL 60459",
    "addr:housenumber":"4901",
    "addr:postcode":"60459",
    "addr:street":"W 79Th St",
    "iso:country":"US",
    "sg:address":"4901 W 79th St",
    "sg:city":"Bedford Park",
    "sg:classifiers":[
        {
            "category":"Health Services",
            "subcategory":"Doctor",
            "type":"Services"
        }
    ],
    "sg:phone":"+1 708 636 1173",
    "sg:postcode":"60459",
    "sg:province":"IL",
    "sg:tags":[
        "medical"
    ],
    "wof:name":"Timothy Brandt MD",
    "wof:placetype":"venue"
},
  "geometry": {"coordinates":[-87.74499299999999,41.749088],"type":"Point"}
}