{
  "type": "Feature",
  "properties": {
    "iso:country":"US",
    "sg:address":"1100 W Jeffery St",
    "sg:city":"Kankakee",
    "sg:classifiers":[
        {
            "category":"Real Estate",
            "subcategory":"Real Estate Operator",
            "type":"Services"
        }
    ],
    "sg:phone":"+1 815 932 9313",
    "sg:postcode":"60901",
    "sg:province":"IL",
    "sg:tags":[
        "apartment",
        "complex"
    ],
    "wof:name":"Sherwood Forest Apartments",
    "wof:placetype":"venue"
},
  "geometry": {"coordinates":[-87.884883,41.105995],"type":"Point"}
}