{
  "type": "Feature",
  "properties": {
    "iso:country":"US",
    "sg:address":"400 Lake Cook Rd",
    "sg:city":"Deerfield",
    "sg:classifiers":[
        {
            "category":"Home & Garden",
            "subcategory":"Home Furnishings",
            "type":"Retail Goods"
        }
    ],
    "sg:phone":"+1   ",
    "sg:postcode":"60015",
    "sg:province":"IL",
    "wof:name":"H&R Custom Designs",
    "wof:placetype":"venue"
},
  "geometry": {"coordinates":[-87.837295,42.152686],"type":"Point"}
}