{
  "type": "Feature",
  "properties": {
    "addr:full":"1334 N. Kostner Chicago IL 60686",
    "addr:housenumber":"1334",
    "addr:postcode":"60686",
    "addr:street":"N. Kostner",
    "iso:country":"US",
    "sg:address":"1334 N. Kostner",
    "sg:city":"Chicago",
    "sg:classifiers":[
        {
            "category":"Personal",
            "type":"Services"
        }
    ],
    "sg:phone":"+1 773 761 5937",
    "sg:postcode":"60686",
    "sg:province":"IL",
    "sg:tags":[
        "local"
    ],
    "wof:name":"Recycle Plus",
    "wof:placetype":"venue"
},
  "geometry": {"coordinates":[-87.737835,41.905567],"type":"Point"}
}