{
  "type": "Feature",
  "properties": {
    "addr:full":"6776 E State St Rockford IL 61108",
    "addr:housenumber":"6776",
    "addr:postcode":"61108",
    "addr:street":"E State St",
    "iso:country":"US",
    "sg:address":"6776 E State St",
    "sg:city":"Rockford",
    "sg:classifiers":[
        {
            "category":"Real Estate",
            "subcategory":"Real Estate Agent",
            "type":"Services"
        },
        {
            "category":"Organizations",
            "subcategory":"Professional Association",
            "type":"Services"
        }
    ],
    "sg:phone":"+1 815 395 6776",
    "sg:postcode":"61108",
    "sg:province":"IL",
    "wof:name":"Rockford Area Assn Of Realtors",
    "wof:placetype":"venue"
},
  "geometry": {"coordinates":[-88.983328,42.268751],"type":"Point"}
}