{
  "type": "Feature",
  "properties": {
    "addr:full":"4849 N Milwaukee Ave Ste 801 Chicago IL 60630",
    "addr:housenumber":"4849",
    "addr:postcode":"60630",
    "addr:street":"N Milwaukee Ave Ste 801",
    "iso:country":"US",
    "sg:address":"4849 N Milwaukee Ave Ste 801",
    "sg:city":"Chicago",
    "sg:classifiers":[
        {
            "category":"Real Estate",
            "subcategory":"Real Estate Services",
            "type":"Services"
        }
    ],
    "sg:phone":"+1 312 869 4727",
    "sg:postcode":"60630",
    "sg:province":"IL",
    "sg:website":"www.premiercapsolutions.com",
    "wof:name":"Premier Capital Solutions",
    "wof:placetype":"venue"
},
  "geometry": {"coordinates":[-87.76128,41.96926],"type":"Point"}
}