{
  "type": "Feature",
  "properties": {
    "addr:full":"7321 S Ridgeland Ave Chicago IL 60649",
    "addr:housenumber":"7321",
    "addr:postcode":"60649",
    "addr:street":"S Ridgeland Ave",
    "iso:country":"US",
    "sg:address":"7321 S Ridgeland Ave",
    "sg:city":"Chicago",
    "sg:classifiers":[
        {
            "category":"Professional",
            "type":"Services"
        }
    ],
    "sg:phone":"+1 773 643 1595",
    "sg:postcode":"60649",
    "sg:province":"IL",
    "wof:name":"Kidsgrow",
    "wof:placetype":"venue"
},
  "geometry": {"coordinates":[-87.582241,41.76167],"type":"Point"}
}