{
  "type": "Feature",
  "properties": {
    "addr:full":"217 S Neil St Champaign IL 61820",
    "addr:housenumber":"217",
    "addr:postcode":"61820",
    "addr:street":"S Neil St",
    "iso:country":"US",
    "sg:address":"217 S Neil St",
    "sg:city":"Champaign",
    "sg:classifiers":[
        {
            "category":"Professional",
            "subcategory":"Computer Services",
            "type":"Services"
        }
    ],
    "sg:phone":"+1 217 378 9680",
    "sg:postcode":"61820",
    "sg:province":"IL",
    "sg:tags":[
        "stereo",
        "installation"
    ],
    "wof:name":"Unlimited Auto Sports",
    "wof:placetype":"venue"
},
  "geometry": {"coordinates":[-88.24369900000001,40.115169],"type":"Point"}
}