{
  "type": "Feature",
  "properties": {
    "iso:country":"US",
    "sg:address":"4401 N Sheridan Rd",
    "sg:city":"Chicago",
    "sg:classifiers":[
        {
            "category":"Deli",
            "type":"Food & Drink"
        }
    ],
    "sg:menulink":"http://www.allmenus.com/il/chicago/196356-chicken-eaters-paradise/menu/",
    "sg:phone":"+1 773 728 1188",
    "sg:postcode":"60640",
    "sg:province":"IL",
    "sg:tags":[
        "american"
    ],
    "wof:name":"Chicken Eater's Paradise",
    "wof:placetype":"venue"
},
  "geometry": {"coordinates":[-87.654724,41.961796],"type":"Point"}
}