{
  "type": "Feature",
  "properties": {
    "addr:full":"537 N Cuyler Ave Oak Park IL 60302",
    "addr:housenumber":"537",
    "addr:postcode":"60302",
    "addr:street":"N Cuyler Ave",
    "iso:country":"US",
    "sg:address":"537 N Cuyler Ave",
    "sg:city":"Oak Park",
    "sg:classifiers":[
        {
            "category":"Professional",
            "subcategory":"Management & Consulting",
            "type":"Services"
        },
        {
            "category":"Education",
            "subcategory":"Special Training",
            "type":"Public Place"
        }
    ],
    "sg:phone":"+1 708 386 5891",
    "sg:postcode":"60302",
    "sg:province":"IL",
    "sg:tags":[
        "consultant",
        "educational",
        "production",
        "company"
    ],
    "wof:name":"Catharsis Productions LLC",
    "wof:placetype":"venue"
},
  "geometry": {"coordinates":[-87.78334599999999,41.895254],"type":"Point"}
}