{
  "type": "Feature",
  "properties": {
    "addr:full":"1810 S Main St Dupo IL 62239",
    "addr:housenumber":"1810",
    "addr:postcode":"62239",
    "addr:street":"S Main St",
    "iso:country":"US",
    "sg:address":"1810 S Main St",
    "sg:city":"Dupo",
    "sg:classifiers":[
        {
            "category":"Retail",
            "subcategory":"Repair Shop",
            "type":"Services"
        },
        {
            "category":"Recreation",
            "subcategory":"Marina",
            "type":"Entertainment"
        }
    ],
    "sg:phone":"+1 618 286 5995",
    "sg:postcode":"62239",
    "sg:province":"IL",
    "sg:tags":[
        "repairing",
        "boat"
    ],
    "wof:name":"Ken's Boat & Motor",
    "wof:placetype":"venue"
},
  "geometry": {"coordinates":[-90.206581,38.504242],"type":"Point"}
}