{
  "type": "Feature",
  "properties": {
    "iso:country":"US",
    "sg:address":"13244 E Lindenwood Rd",
    "sg:city":"Rochelle",
    "sg:classifiers":[
        {
            "category":"Building & Trades",
            "subcategory":"Construction",
            "type":"Services"
        }
    ],
    "sg:phone":"+1 815 393 3230",
    "sg:postcode":"61068",
    "sg:province":"IL",
    "sg:tags":[
        "contractor"
    ],
    "wof:name":"West Raven Limited",
    "wof:placetype":"venue"
},
  "geometry": {"coordinates":[-89.092514,42.045516],"type":"Point"}
}