{
  "type": "Feature",
  "properties": {
    "addr:full":"715 Lake St, Ste 612 Oak Park IL 60301",
    "addr:housenumber":"715",
    "addr:postcode":"60301",
    "addr:street":"Lake St Ste 612",
    "iso:country":"US",
    "sg:address":"715 Lake St, Ste 612",
    "sg:city":"Oak Park",
    "sg:classifiers":[
        {
            "category":"Health Services",
            "subcategory":"Health Practitioner",
            "type":"Services"
        }
    ],
    "sg:phone":"+1 708 848 7789",
    "sg:postcode":"60301",
    "sg:province":"IL",
    "sg:tags":[
        "nutritionist"
    ],
    "sg:website":"www.benuts.com",
    "wof:name":"Beulah Land Nutritionals",
    "wof:placetype":"venue"
},
  "geometry": {"coordinates":[-87.79343299999999,41.88838],"type":"Point"}
}