{
  "type": "Feature",
  "properties": {
    "iso:country":"US",
    "sg:address":"211 James St Ste 1",
    "sg:city":"Geneva",
    "sg:phone":"+1 630 845 1570",
    "sg:postcode":"60134",
    "sg:province":"IL",
    "wof:name":"Nosh",
    "wof:placetype":"venue"
},
  "geometry": {"coordinates":[-88.30688499999999,41.8867],"type":"Point"}
}