{
  "type": "Feature",
  "properties": {
    "addr:full":"3541 W North Ave Chicago IL 60647",
    "addr:housenumber":"3541",
    "addr:postcode":"60647",
    "addr:street":"W North Ave",
    "iso:country":"US",
    "sg:address":"3541 W North Ave",
    "sg:city":"Chicago",
    "sg:classifiers":[
        {
            "category":"Social Services",
            "type":"Services"
        },
        {
            "category":"Government",
            "subcategory":"City Hall",
            "type":"Public Place"
        },
        {
            "category":"Real Estate",
            "subcategory":"Real Estate Services",
            "type":"Services"
        }
    ],
    "sg:phone":"+1 773 276 5338",
    "sg:postcode":"60647",
    "sg:province":"IL",
    "sg:tags":[
        "consultant",
        "housing",
        "referral"
    ],
    "wof:name":"Latin United Community Housing",
    "wof:placetype":"venue"
},
  "geometry": {"coordinates":[-87.716202,41.909801],"type":"Point"}
}