{
  "type": "Feature",
  "properties": {
    "addr:full":"3168 S Ashland Ave Chicago IL 60608",
    "addr:housenumber":"3168",
    "addr:postcode":"60608",
    "addr:street":"S Ashland Ave",
    "iso:country":"US",
    "sg:address":"3168 S Ashland Ave",
    "sg:city":"Chicago",
    "sg:classifiers":[
        {
            "category":"Banks & Credit Unions",
            "subcategory":"Financial Services",
            "type":"Services"
        }
    ],
    "sg:phone":"+1 773 247 7300",
    "sg:postcode":"60608",
    "sg:province":"IL",
    "sg:tags":[
        "cashing",
        "loan",
        "check"
    ],
    "sg:website":"http://www.QCHoldings.com/StorePages/IL/Store451.htm",
    "wof:name":"National Quik Cash",
    "wof:placetype":"venue"
},
  "geometry": {"coordinates":[-87.66570400000001,41.835892],"type":"Point"}
}