{
  "type": "Feature",
  "properties": {
    "iso:country":"US",
    "sg:address":"13322 Church Rd",
    "sg:city":"Carlyle",
    "sg:classifiers":[
        {
            "category":"Organizations",
            "subcategory":"Religious Organization",
            "type":"Services"
        }
    ],
    "sg:phone":"+1 618 594 3040",
    "sg:postcode":"62231",
    "sg:province":"IL",
    "sg:tags":[
        "church"
    ],
    "wof:name":"St Felicitas",
    "wof:placetype":"venue"
},
  "geometry": {"coordinates":[-89.45211399999999,38.696702],"type":"Point"}
}