{
  "type": "Feature",
  "properties": {
    "iso:country":"US",
    "sg:address":"14111 N County Road 1700E",
    "sg:city":"Charleston",
    "sg:classifiers":[
        {
            "category":"Building & Trades",
            "subcategory":"Construction",
            "type":"Services"
        },
        {
            "category":"Military Area",
            "subcategory":"Armory",
            "type":"Public Place"
        }
    ],
    "sg:phone":"+1 217 234 3784",
    "sg:postcode":"61920",
    "sg:province":"IL",
    "sg:tags":[
        "repair",
        "fence-sales",
        "fence",
        "contractor"
    ],
    "wof:name":"B Free Pet Fence",
    "wof:placetype":"venue"
},
  "geometry": {"coordinates":[-88.15853799999999,39.579902],"type":"Point"}
}