{
  "type": "Feature",
  "properties": {
    "addr:full":"427 E 75th St Chicago IL 60619",
    "addr:housenumber":"427",
    "addr:postcode":"60619",
    "addr:street":"E 75Th St",
    "iso:country":"US",
    "sg:address":"427 E 75th St",
    "sg:city":"Chicago",
    "sg:classifiers":[
        {
            "category":"Shopping",
            "subcategory":"Clothing, Apparel, & Fashions",
            "type":"Retail Goods"
        }
    ],
    "sg:phone":"+1 773 483 9830",
    "sg:postcode":"60619",
    "sg:province":"IL",
    "sg:tags":[
        "accessory",
        "clothing",
        "women's"
    ],
    "wof:name":"Pazaz",
    "wof:placetype":"venue"
},
  "geometry": {"coordinates":[-87.613927,41.758273],"type":"Point"}
}