{
  "type": "Feature",
  "properties": {
    "iso:country":"US",
    "sg:address":"700 E Golf Rd",
    "sg:city":"Arlington Heights",
    "sg:classifiers":[
        {
            "category":"Real Estate",
            "subcategory":"Real Estate Agent",
            "type":"Services"
        }
    ],
    "sg:phone":"+1 847 228 1212",
    "sg:postcode":"60005",
    "sg:province":"IL",
    "wof:name":"Linden Place Apartments",
    "wof:placetype":"venue"
},
  "geometry": {"coordinates":[-87.973834,42.051513],"type":"Point"}
}