{
  "type": "Feature",
  "properties": {
    "iso:country":"US",
    "sg:address":"251 Wille Rd",
    "sg:city":"Des Plaines",
    "sg:classifiers":[
        {
            "category":"Autos & Motor Vehicles",
            "subcategory":"Automobile Sales",
            "type":"Retail Goods"
        }
    ],
    "sg:phone":"+1 847 553 0172",
    "sg:postcode":"60018",
    "sg:province":"IL",
    "sg:tags":[
        "aircraft"
    ],
    "wof:name":"Bombardier Learjet",
    "wof:placetype":"venue"
},
  "geometry": {"coordinates":[-87.930093,42.019073],"type":"Point"}
}