{
  "type": "Feature",
  "properties": {
    "addr:full":"42W373 Plato Rd Elgin IL 60124",
    "addr:housenumber":"42w373",
    "addr:postcode":"60124",
    "addr:street":"Plato Rd",
    "iso:country":"US",
    "sg:address":"42W373 Plato Rd",
    "sg:city":"Elgin",
    "sg:classifiers":[
        {
            "category":"Manufacturing",
            "subcategory":"Food",
            "type":"Manufacturing & Wholesale Goods"
        },
        {
            "category":"Farming",
            "subcategory":"Farm",
            "type":"Manufacturing & Wholesale Goods"
        }
    ],
    "sg:phone":"+1 847 464 5155",
    "sg:postcode":"60124",
    "sg:province":"IL",
    "sg:tags":[
        "corn",
        "product"
    ],
    "wof:name":"Emil Winkelman",
    "wof:placetype":"venue"
},
  "geometry": {"coordinates":[-88.433697,42.019945],"type":"Point"}
}