{
  "type": "Feature",
  "properties": {
    "iso:country":"US",
    "sg:address":"1525 W Wiesbrook Rd",
    "sg:city":"Wheaton",
    "sg:classifiers":[
        {
            "category":"Building & Trades",
            "subcategory":"Construction",
            "type":"Services"
        }
    ],
    "sg:phone":"+1 630 752 9110",
    "sg:postcode":"60187",
    "sg:province":"IL",
    "sg:tags":[
        "contractor"
    ],
    "wof:name":"Westwood Homes Inc",
    "wof:placetype":"venue"
},
  "geometry": {"coordinates":[-88.127197,41.846199],"type":"Point"}
}