{
  "type": "Feature",
  "properties": {
    "addr:full":"3420 N Lake Shore Dr Chicago IL 60657",
    "addr:housenumber":"3420",
    "addr:postcode":"60657",
    "addr:street":"N Lake Shore Dr",
    "iso:country":"US",
    "sg:address":"3420 N Lake Shore Dr",
    "sg:city":"Chicago",
    "sg:classifiers":[
        {
            "category":"Professional",
            "subcategory":"Computer Services",
            "type":"Services"
        }
    ],
    "sg:phone":"+1 773 665 4746",
    "sg:postcode":"60657",
    "sg:province":"IL",
    "sg:tags":[
        "related"
    ],
    "wof:name":"Clavis Solutions Inc",
    "wof:placetype":"venue"
},
  "geometry": {"coordinates":[-87.640559,41.943916],"type":"Point"}
}