{
  "type": "Feature",
  "properties": {
    "addr:full":"2957 W Belden Ave Chicago IL 60647",
    "addr:housenumber":"2957",
    "addr:postcode":"60647",
    "addr:street":"W Belden Ave",
    "iso:country":"US",
    "sg:address":"2957 W Belden Ave",
    "sg:city":"Chicago",
    "sg:classifiers":[
        {
            "category":"Real Estate",
            "subcategory":"Real Estate Services",
            "type":"Services"
        },
        {
            "category":"Real Estate",
            "subcategory":"Surveying",
            "type":"Services"
        }
    ],
    "sg:phone":"+1 773 603 6711",
    "sg:postcode":"60647",
    "sg:province":"IL",
    "sg:tags":[
        "industrial",
        "appraisers-commercial",
        "appraiser"
    ],
    "wof:name":"For What It's Worth Real Estate Appraisals, Inc.",
    "wof:placetype":"venue"
},
  "geometry": {"coordinates":[-87.70135000000001,41.923273],"type":"Point"}
}