{
  "type": "Feature",
  "properties": {
    "addr:full":"4151 W Belmont Ave Chicago IL 60641",
    "addr:housenumber":"4151",
    "addr:postcode":"60641",
    "addr:street":"W Belmont Ave",
    "iso:country":"US",
    "sg:address":"4151 W Belmont Ave",
    "sg:city":"Chicago",
    "sg:classifiers":[
        {
            "category":"Autos & Motor Vehicles",
            "subcategory":"Automobile Sales",
            "type":"Retail Goods"
        }
    ],
    "sg:phone":"+1 773 736 7599",
    "sg:postcode":"60641",
    "sg:province":"IL",
    "sg:tags":[
        "car",
        "dealer"
    ],
    "wof:name":"Far Auto Brokers",
    "wof:placetype":"venue"
},
  "geometry": {"coordinates":[-87.729956,41.938982],"type":"Point"}
}