{
  "type": "Feature",
  "properties": {
    "iso:country":"US",
    "sg:address":"341 E Williams St",
    "sg:city":"Wyoming",
    "sg:classifiers":[
        {
            "category":"Manufacturing",
            "subcategory":"Tools & Machinery",
            "type":"Manufacturing & Wholesale Goods"
        }
    ],
    "sg:phone":"+1 309 695 2311",
    "sg:postcode":"61491",
    "sg:province":"IL",
    "sg:tags":[
        "water",
        "heater"
    ],
    "sg:website":"www.aldrichco.com",
    "wof:name":"Aldrich Co",
    "wof:placetype":"venue"
},
  "geometry": {"coordinates":[-89.769522,41.061525],"type":"Point"}
}