{
  "type": "Feature",
  "properties": {
    "addr:full":"3100 Theodore St Joliet IL 60435",
    "addr:housenumber":"3100",
    "addr:postcode":"60435",
    "addr:street":"Theodore St",
    "iso:country":"US",
    "sg:address":"3100 Theodore St",
    "sg:city":"Joliet",
    "sg:classifiers":[
        {
            "category":"Professional",
            "subcategory":"Lawyer & Legal Services",
            "type":"Services"
        }
    ],
    "sg:phone":"+1 815 729 3600",
    "sg:postcode":"60435",
    "sg:province":"IL",
    "sg:tags":[
        "attorney",
        "family",
        "worker",
        "disability",
        "benefit",
        "compensation",
        "social",
        "employee",
        "security",
        "law",
        "bankruptcy"
    ],
    "sg:website":"http://www.kcccp.com",
    "wof:name":"Krockey, Cernugel, Cowgill & Clark, Ltd.",
    "wof:placetype":"venue"
},
  "geometry": {"coordinates":[-88.15834,41.551048],"type":"Point"}
}