{
  "type": "Feature",
  "properties": {
    "iso:country":"US",
    "sg:address":"1695 Elmhurst Rd",
    "sg:city":"Elk Grove Village",
    "sg:classifiers":[
        {
            "category":"Wholesale",
            "subcategory":"Construction Materials",
            "type":"Manufacturing & Wholesale Goods"
        }
    ],
    "sg:phone":"+1 847 228 9616",
    "sg:postcode":"60007",
    "sg:province":"IL",
    "sg:tags":[
        "granite",
        "marble"
    ],
    "wof:name":"Select Marble and Granite",
    "wof:placetype":"venue"
},
  "geometry": {"coordinates":[-87.94004700000001,42.001914],"type":"Point"}
}