{
  "type": "Feature",
  "properties": {
    "iso:country":"US",
    "sg:address":"411 W Ontario St Ofc",
    "sg:city":"Chicago",
    "sg:classifiers":[
        {
            "category":"Retail",
            "subcategory":"Laundry & Dry Cleaning",
            "type":"Services"
        }
    ],
    "sg:phone":"+1 312 944 5772",
    "sg:postcode":"60610",
    "sg:province":"IL",
    "wof:name":"411 Cleaners",
    "wof:placetype":"venue"
},
  "geometry": {"coordinates":[-87.638901,41.893101],"type":"Point"}
}