{
  "type": "Feature",
  "properties": {
    "iso:country":"US",
    "sg:address":"415 N Commercial St",
    "sg:city":"Lacon",
    "sg:classifiers":[
        {
            "category":"Retail",
            "subcategory":"Auto Repair",
            "type":"Services"
        }
    ],
    "sg:phone":"+1 309 246 8045",
    "sg:postcode":"61537",
    "sg:province":"IL",
    "sg:tags":[
        "repairing",
        "automobile"
    ],
    "wof:name":"Danny's Auto Repair",
    "wof:placetype":"venue"
},
  "geometry": {"coordinates":[-89.369308,41.109487],"type":"Point"}
}