{
  "type": "Feature",
  "properties": {
    "iso:country":"US",
    "sg:address":"340 N Dearborn Ave",
    "sg:city":"Kankakee",
    "sg:classifiers":[
        {
            "category":"Education",
            "subcategory":"Special Training",
            "type":"Public Place"
        }
    ],
    "sg:phone":"+1 815 929 9125",
    "sg:postcode":"60901",
    "sg:province":"IL",
    "sg:tags":[
        "program"
    ],
    "wof:name":"Kankakee County Trng Ctr",
    "wof:placetype":"venue"
},
  "geometry": {"coordinates":[-87.861788,41.123501],"type":"Point"}
}