{
  "type": "Feature",
  "properties": {
    "addr:full":"3600 Thayer Ct Aurora IL 60504",
    "addr:housenumber":"3600",
    "addr:postcode":"60504",
    "addr:street":"Thayer Ct",
    "iso:country":"US",
    "sg:address":"3600 Thayer Ct",
    "sg:city":"Aurora",
    "sg:classifiers":[
        {
            "category":"Freight",
            "type":"Transportation"
        }
    ],
    "sg:phone":"+1 630 898 5600",
    "sg:postcode":"60504",
    "sg:province":"IL",
    "sg:tags":[
        "management",
        "general"
    ],
    "wof:name":"Verizon",
    "wof:placetype":"venue"
},
  "geometry": {"coordinates":[-88.22913200000001,41.739156],"type":"Point"}
}