{
  "type": "Feature",
  "properties": {
    "iso:country":"US",
    "sg:address":"4725 Woodward Ave",
    "sg:city":"Downers Grove",
    "sg:classifiers":[
        {
            "category":"Real Estate",
            "subcategory":"Real Estate Operator",
            "type":"Services"
        }
    ],
    "sg:phone":"+1 630 969 0205",
    "sg:postcode":"60515",
    "sg:province":"IL",
    "sg:tags":[
        "building",
        "nonresidential"
    ],
    "wof:name":"Schulz Properties Ltd",
    "wof:placetype":"venue"
},
  "geometry": {"coordinates":[-88.03307,41.799986],"type":"Point"}
}