{
  "type": "Feature",
  "properties": {
    "iso:country":"US",
    "sg:address":"165 N Schuyler Ave",
    "sg:city":"Kankakee",
    "sg:classifiers":[
        {
            "category":"Government",
            "subcategory":"Office",
            "type":"Public Place"
        }
    ],
    "sg:phone":"+1 815 933 0476",
    "sg:postcode":"60901",
    "sg:province":"IL",
    "sg:tags":[
        "village"
    ],
    "wof:name":"Kankakee Building Inspector",
    "wof:placetype":"venue"
},
  "geometry": {"coordinates":[-87.863868,41.120786],"type":"Point"}
}