{
  "type": "Feature",
  "properties": {
    "addr:full":"5720 W Touhy Ave Niles IL 60714",
    "addr:housenumber":"5720",
    "addr:postcode":"60714",
    "addr:street":"W Touhy Ave",
    "iso:country":"US",
    "sg:address":"5720 W Touhy Ave",
    "sg:city":"Niles",
    "sg:classifiers":[
        {
            "category":"Coffee & Tea",
            "type":"Food & Drink"
        }
    ],
    "sg:menulink":"http://www.allmenus.com/il/niles/112562-starbucks-coffee/menu/",
    "sg:phone":"+1 847 647 9389",
    "sg:postcode":"60714",
    "sg:province":"IL",
    "sg:tags":[
        "american"
    ],
    "wof:name":"Starbucks Coffee",
    "wof:placetype":"venue"
},
  "geometry": {"coordinates":[-87.771069,42.012021],"type":"Point"}
}