{
  "type": "Feature",
  "properties": {
    "addr:full":"2500 Galvin Dr Elgin IL 60124",
    "addr:housenumber":"2500",
    "addr:postcode":"60124",
    "addr:street":"Galvin Dr",
    "iso:country":"US",
    "sg:address":"2500 Galvin Dr",
    "sg:city":"Elgin",
    "sg:classifiers":[
        {
            "category":"Autos & Motor Vehicles",
            "subcategory":"Auto Supplies",
            "type":"Retail Goods"
        }
    ],
    "sg:phone":"+1 847 426 5300",
    "sg:postcode":"60124",
    "sg:province":"IL",
    "sg:tags":[
        "tire"
    ],
    "wof:name":"Colony Inc",
    "wof:placetype":"venue"
},
  "geometry": {"coordinates":[-88.344989,42.093348],"type":"Point"}
}