{
  "type": "Feature",
  "properties": {
    "addr:full":"920 Chestnut St Ottawa IL 61350",
    "addr:housenumber":"920",
    "addr:postcode":"61350",
    "addr:street":"Chestnut St",
    "iso:country":"US",
    "sg:address":"920 Chestnut St",
    "sg:city":"Ottawa",
    "sg:classifiers":[
        {
            "category":"Retail",
            "subcategory":"Repair Shop",
            "type":"Services"
        },
        {
            "category":"Home & Garden",
            "subcategory":"Garden Supply",
            "type":"Retail Goods"
        }
    ],
    "sg:phone":"+1 815 433 4429",
    "sg:postcode":"61350",
    "sg:province":"IL",
    "sg:tags":[
        "repairing",
        "equipment",
        "lawn",
        "mower"
    ],
    "wof:name":"Richards Lawn & Garden Center",
    "wof:placetype":"venue"
},
  "geometry": {"coordinates":[-88.848726,41.349725],"type":"Point"}
}