{
  "type": "Feature",
  "properties": {
    "iso:country":"US",
    "sg:address":"10033 S Roberts Rd",
    "sg:city":"Palos Hills",
    "sg:classifiers":[
        {
            "category":"Banks & Credit Unions",
            "subcategory":"Bank",
            "type":"Services"
        }
    ],
    "sg:phone":"+1 708 233 0230",
    "sg:postcode":"60465",
    "sg:province":"IL",
    "sg:tags":[
        "loan",
        "real estate"
    ],
    "wof:name":"First Metropolitan Mortgage",
    "wof:placetype":"venue"
},
  "geometry": {"coordinates":[-87.817385,41.707665],"type":"Point"}
}