{
  "type": "Feature",
  "properties": {
    "iso:country":"US",
    "sg:address":"6944 W Niles Ter",
    "sg:city":"Niles",
    "sg:classifiers":[
        {
            "category":"Building & Trades",
            "subcategory":"Construction",
            "type":"Services"
        }
    ],
    "sg:phone":"+1 847 647 1950",
    "sg:postcode":"60714",
    "sg:province":"IL",
    "sg:tags":[
        "welder"
    ],
    "wof:name":"Able Welding Inc",
    "wof:placetype":"venue"
},
  "geometry": {"coordinates":[-87.800031,42.015291],"type":"Point"}
}