{
  "type": "Feature",
  "properties": {
    "iso:country":"US",
    "sg:address":"301 N Kedzie Ave",
    "sg:city":"Chicago",
    "sg:classifiers":[
        {
            "category":"Banks & Credit Unions",
            "subcategory":"Investment Brokerage",
            "type":"Services"
        },
        {
            "category":"Government",
            "subcategory":"Office",
            "type":"Public Place"
        }
    ],
    "sg:phone":"+1 773 826 2244",
    "sg:postcode":"60612",
    "sg:province":"IL",
    "sg:tags":[
        "development",
        "councils",
        "commissions",
        "economic",
        "authorities"
    ],
    "wof:name":"Midwest Community Council",
    "wof:placetype":"venue"
},
  "geometry": {"coordinates":[-87.706253,41.88641],"type":"Point"}
}