{
  "type": "Feature",
  "properties": {
    "iso:country":"US",
    "sg:address":"2020 N Lewis Ave",
    "sg:city":"Waukegan",
    "sg:classifiers":[
        {
            "category":"Building & Trades",
            "subcategory":"Construction",
            "type":"Services"
        }
    ],
    "sg:phone":"+1 847 336 8575",
    "sg:postcode":"60087",
    "sg:province":"IL",
    "sg:tags":[
        "general",
        "commercial",
        "contractor"
    ],
    "sg:website":"www.stuckeyconstruction.com",
    "wof:name":"Stuckey Construction Company",
    "wof:placetype":"venue"
},
  "geometry": {"coordinates":[-87.855373,42.389879],"type":"Point"}
}