{
  "type": "Feature",
  "properties": {
    "addr:full":"437 E Drury Ln Barrington IL 60010",
    "addr:housenumber":"437",
    "addr:postcode":"60010",
    "addr:street":"E Drury Ln",
    "iso:country":"US",
    "sg:address":"437 E Drury Ln",
    "sg:city":"Barrington",
    "sg:classifiers":[
        {
            "category":"Real Estate",
            "subcategory":"Architect",
            "type":"Services"
        }
    ],
    "sg:phone":"+1 847 382 7037",
    "sg:postcode":"60010",
    "sg:province":"IL",
    "sg:tags":[
        "architectural"
    ],
    "wof:name":"Harry Swihart Architype",
    "wof:placetype":"venue"
},
  "geometry": {"coordinates":[-88.130635,42.160471],"type":"Point"}
}