{
  "type": "Feature",
  "properties": {
    "iso:country":"US",
    "sg:address":"433 Normandie Ln",
    "sg:city":"Round Lake Beach",
    "sg:classifiers":[
        {
            "category":"Retail",
            "subcategory":"Portrait Studio",
            "type":"Services"
        }
    ],
    "sg:phone":"+1 847 546 4458",
    "sg:postcode":"60073",
    "sg:province":"IL",
    "sg:tags":[
        "photographer"
    ],
    "wof:name":"R T Photography",
    "wof:placetype":"venue"
},
  "geometry": {"coordinates":[-88.094432,42.38593],"type":"Point"}
}