{
  "type": "Feature",
  "properties": {
    "iso:country":"US",
    "sg:address":"8609 S Kolin Ave",
    "sg:city":"Chicago",
    "sg:classifiers":[
        {
            "category":"Real Estate",
            "subcategory":"Developer",
            "type":"Services"
        }
    ],
    "sg:phone":"+1 773 581 2107",
    "sg:postcode":"60652",
    "sg:province":"IL",
    "sg:tags":[
        "business"
    ],
    "wof:name":"Durrett Design Inc",
    "wof:placetype":"venue"
},
  "geometry": {"coordinates":[-87.729871,41.73537],"type":"Point"}
}