{
  "type": "Feature",
  "properties": {
    "iso:country":"US",
    "sg:address":"1231 Lincoln Dr",
    "sg:city":"Carbondale",
    "sg:classifiers":[
        {
            "category":"Professional",
            "subcategory":"Management & Consulting",
            "type":"Services"
        }
    ],
    "sg:phone":"+1 618 453 4009",
    "sg:postcode":"62901",
    "sg:province":"IL",
    "sg:tags":[
        "marketing",
        "program"
    ],
    "wof:name":"Public Policy Institute",
    "wof:placetype":"venue"
},
  "geometry": {"coordinates":[-89.220898,37.710978],"type":"Point"}
}