{
  "type": "Feature",
  "properties": {
    "addr:full":"699 N Maplewood Dr Rantoul IL 61866",
    "addr:housenumber":"699",
    "addr:postcode":"61866",
    "addr:street":"N Maplewood Dr",
    "iso:country":"US",
    "sg:address":"699 N Maplewood Dr",
    "sg:city":"Rantoul",
    "sg:classifiers":[
        {
            "category":"Building & Trades",
            "subcategory":"Construction",
            "type":"Services"
        }
    ],
    "sg:phone":"+1 217 893 8290",
    "sg:postcode":"61866",
    "sg:province":"IL",
    "sg:tags":[
        "hanging",
        "contractor"
    ],
    "wof:name":"Gerdes Painting Company",
    "wof:placetype":"venue"
},
  "geometry": {"coordinates":[-88.136504,40.31608],"type":"Point"}
}