{
  "type": "Feature",
  "properties": {
    "addr:full":"5823 E Riverside Blvd Rockford IL 61114",
    "addr:housenumber":"5823",
    "addr:postcode":"61114",
    "addr:street":"E Riverside Blvd",
    "iso:country":"US",
    "sg:address":"5823 E Riverside Blvd",
    "sg:city":"Rockford",
    "sg:classifiers":[
        {
            "category":"Shopping",
            "subcategory":"Shoes",
            "type":"Retail Goods"
        }
    ],
    "sg:phone":"+1   ",
    "sg:postcode":"61114",
    "sg:province":"IL",
    "wof:name":"Good Feet Store",
    "wof:placetype":"venue"
},
  "geometry": {"coordinates":[-89.002639,42.318591],"type":"Point"}
}