{
  "type": "Feature",
  "properties": {
    "addr:full":"460 N Main St Glen Ellyn IL 60137",
    "addr:housenumber":"460",
    "addr:postcode":"60137",
    "addr:street":"N Main St",
    "iso:country":"US",
    "sg:address":"460 N Main St",
    "sg:city":"Glen Ellyn",
    "sg:classifiers":[
        {
            "category":"Education",
            "subcategory":"School",
            "type":"Public Place"
        }
    ],
    "sg:phone":"+1 630 793 9272",
    "sg:postcode":"60137",
    "sg:province":"IL",
    "sg:tags":[
        "high",
        "middle",
        "elementary"
    ],
    "wof:name":"Univ Notre Dame Development Office",
    "wof:placetype":"venue"
},
  "geometry": {"coordinates":[-88.06690399999999,41.87623],"type":"Point"}
}