{
  "type": "Feature",
  "properties": {
    "iso:country":"US",
    "sg:address":"1628 N Mango Avenue",
    "sg:city":"Chicago",
    "sg:classifiers":[
        {
            "category":"Building & Trades",
            "subcategory":"Construction",
            "type":"Services"
        }
    ],
    "sg:phone":"+1 773 637 0343",
    "sg:postcode":"60639",
    "sg:province":"IL",
    "sg:tags":[
        "contractor"
    ],
    "wof:name":"N & S Construction Company",
    "wof:placetype":"venue"
},
  "geometry": {"coordinates":[-87.768995,41.91005],"type":"Point"}
}