{
  "type": "Feature",
  "properties": {
    "addr:full":"900 S 1st Ave Carbon Cliff IL 61239",
    "addr:housenumber":"900",
    "addr:postcode":"61239",
    "addr:street":"S 1St Ave Carbon",
    "iso:country":"US",
    "sg:address":"900 S 1st Ave",
    "sg:city":"Carbon Cliff",
    "sg:classifiers":[
        {
            "category":"Personal",
            "subcategory":"Barber",
            "type":"Services"
        }
    ],
    "sg:phone":"+1 309 792 3212",
    "sg:postcode":"61239",
    "sg:province":"IL",
    "wof:name":"First Avenue Barbershop",
    "wof:placetype":"venue"
},
  "geometry": {"coordinates":[-90.386482,41.487652],"type":"Point"}
}