{
  "type": "Feature",
  "properties": {
    "addr:full":"230 W Root St Chicago IL 60609",
    "addr:housenumber":"230",
    "addr:postcode":"60609",
    "addr:street":"W Root St",
    "iso:country":"US",
    "sg:address":"230 W Root St",
    "sg:city":"Chicago",
    "sg:classifiers":[
        {
            "category":"Bars & Pubs",
            "subcategory":"Nightclub",
            "type":"Food & Drink"
        }
    ],
    "sg:phone":"+1 773 268 1525",
    "sg:postcode":"60609",
    "sg:province":"IL",
    "sg:tags":[
        "nightlife"
    ],
    "wof:name":"Root Inn the",
    "wof:placetype":"venue"
},
  "geometry": {"coordinates":[-87.63272000000001,41.819287],"type":"Point"}
}