{
  "type": "Feature",
  "properties": {
    "iso:country":"US",
    "sg:address":"118 S Main St",
    "sg:city":"Wauconda",
    "sg:classifiers":[
        {
            "category":"Real Estate",
            "subcategory":"Developer",
            "type":"Services"
        }
    ],
    "sg:phone":"+1 847 526 1514",
    "sg:postcode":"60084",
    "sg:province":"IL",
    "wof:name":"Four Oaks Development Corp",
    "wof:placetype":"venue"
},
  "geometry": {"coordinates":[-88.137596,42.256874],"type":"Point"}
}