{
  "type": "Feature",
  "properties": {
    "addr:full":"937 S Elm St Palatine IL 60067",
    "addr:housenumber":"937",
    "addr:postcode":"60067",
    "addr:street":"S Elm St",
    "iso:country":"US",
    "sg:address":"937 S Elm St",
    "sg:city":"Palatine",
    "sg:classifiers":[
        {
            "category":"Manufacturing",
            "subcategory":"Printing",
            "type":"Manufacturing & Wholesale Goods"
        }
    ],
    "sg:phone":"+1 847 358 8487",
    "sg:postcode":"60067",
    "sg:province":"IL",
    "sg:tags":[
        "newspaper",
        "business",
        "association"
    ],
    "wof:name":"Food Trends Letter",
    "wof:placetype":"venue"
},
  "geometry": {"coordinates":[-88.058418,42.093268],"type":"Point"}
}