{
  "type": "Feature",
  "properties": {
    "addr:full":"201 N Clark Street Chicago IL 60601",
    "addr:housenumber":"201",
    "addr:postcode":"60601",
    "addr:street":"N Clark Street",
    "iso:country":"US",
    "sg:address":"201 N Clark Street",
    "sg:city":"Chicago",
    "sg:classifiers":[
        {
            "category":"Restaurant",
            "type":"Food & Drink"
        },
        {
            "category":"Food & Beverages",
            "subcategory":"Bakery",
            "type":"Retail Goods"
        }
    ],
    "sg:phone":"+1 312 853 0995",
    "sg:postcode":"60601",
    "sg:province":"IL",
    "sg:tags":[
        "sandwich"
    ],
    "sg:website":"www.subway.com",
    "wof:name":"Subway Sandwiches",
    "wof:placetype":"venue"
},
  "geometry": {"coordinates":[-87.63094100000001,41.885666],"type":"Point"}
}