{
  "type": "Feature",
  "properties": {
    "addr:full":"201 E Main St Thayer IL 62689",
    "addr:housenumber":"201",
    "addr:postcode":"62689",
    "addr:street":"E Main St",
    "iso:country":"US",
    "sg:address":"201 E Main St",
    "sg:city":"Thayer",
    "sg:classifiers":[
        {
            "category":"Building & Trades",
            "subcategory":"Plumbing",
            "type":"Services"
        }
    ],
    "sg:phone":"+1 217 965 5578",
    "sg:postcode":"62689",
    "sg:province":"IL",
    "sg:tags":[
        "conditioning",
        "air",
        "system",
        "contractor"
    ],
    "wof:name":"New Air Heating & AC",
    "wof:placetype":"venue"
},
  "geometry": {"coordinates":[-89.761674,39.537547],"type":"Point"}
}