{
  "type": "Feature",
  "properties": {
    "addr:full":"6014 S Kolmar Ave Chicago IL 60629",
    "addr:housenumber":"6014",
    "addr:postcode":"60629",
    "addr:street":"S Kolmar Ave",
    "iso:country":"US",
    "sg:address":"6014 S Kolmar Ave",
    "sg:city":"Chicago",
    "sg:classifiers":[
        {
            "category":"Building & Trades",
            "subcategory":"Construction",
            "type":"Services"
        }
    ],
    "sg:phone":"+1 773 476 8400",
    "sg:postcode":"60629",
    "sg:province":"IL",
    "sg:tags":[
        "system",
        "contractor",
        "air conditioning"
    ],
    "wof:name":"Mcgrath Srvcs",
    "wof:placetype":"venue"
},
  "geometry": {"coordinates":[-87.736318,41.78372],"type":"Point"}
}