{
  "type": "Feature",
  "properties": {
    "addr:full":"3110 N Sheridan Rd # 705 Chicago IL 60657",
    "addr:housenumber":"3110",
    "addr:postcode":"60657",
    "addr:street":"N Sheridan Rd # 705",
    "iso:country":"US",
    "sg:address":"3110 N Sheridan Rd # 705",
    "sg:city":"Chicago",
    "sg:classifiers":[
        {
            "category":"Building & Trades",
            "subcategory":"Construction",
            "type":"Services"
        },
        {
            "category":"Home & Garden",
            "subcategory":"Furniture",
            "type":"Retail Goods"
        }
    ],
    "sg:phone":"+1 312 617 3678",
    "sg:postcode":"60657",
    "sg:province":"IL",
    "sg:tags":[
        "equipment-household",
        "maker",
        "kitchen",
        "cabinet"
    ],
    "wof:name":"Esiner Construction Co Inc",
    "wof:placetype":"venue"
},
  "geometry": {"coordinates":[-87.639376,41.938049],"type":"Point"}
}