{
  "type": "Feature",
  "properties": {
    "iso:country":"US",
    "sg:address":"116 N Willard Ct",
    "sg:city":"Chicago",
    "sg:classifiers":[
        {
            "category":"Professional",
            "type":"Services"
        }
    ],
    "sg:phone":"+1 312 942 1515",
    "sg:postcode":"60607",
    "sg:province":"IL",
    "sg:tags":[
        "caterer"
    ],
    "sg:website":"www.occasionschicago.com",
    "wof:name":"Occasions Chicago",
    "wof:placetype":"venue"
},
  "geometry": {"coordinates":[-87.657501,41.8834],"type":"Point"}
}