{
  "type": "Feature",
  "properties": {
    "addr:full":"55 E Monroe St Ste 20 Chicago IL 60603",
    "addr:housenumber":"55",
    "addr:postcode":"60603",
    "addr:street":"E Monroe St Ste 20",
    "iso:country":"US",
    "sg:address":"55 E Monroe St Ste 20",
    "sg:city":"Chicago",
    "sg:classifiers":[
        {
            "category":"Organizations",
            "subcategory":"Professional Association",
            "type":"Services"
        }
    ],
    "sg:phone":"+1 312 759 4001",
    "sg:postcode":"60603",
    "sg:province":"IL",
    "wof:name":"Norc-U Chicago",
    "wof:placetype":"venue"
},
  "geometry": {"coordinates":[-87.625998,41.880783],"type":"Point"}
}