{
  "type": "Feature",
  "properties": {
    "iso:country":"US",
    "sg:address":"1000 Baytowne Dr",
    "sg:city":"Champaign",
    "sg:classifiers":[
        {
            "category":"Real Estate",
            "subcategory":"Real Estate Operator",
            "type":"Services"
        }
    ],
    "sg:phone":"+1 217 352 1000",
    "sg:postcode":"61822",
    "sg:province":"IL",
    "sg:tags":[
        "apartment"
    ],
    "wof:name":"Baytowne Apartments",
    "wof:placetype":"venue"
},
  "geometry": {"coordinates":[-88.2603,40.140999],"type":"Point"}
}