{
  "type": "Feature",
  "properties": {
    "iso:country":"US",
    "sg:address":"1501 E Vernon Ave",
    "sg:city":"Bloomington",
    "sg:classifiers":[
        {
            "category":"Restaurant",
            "type":"Food & Drink"
        }
    ],
    "sg:menulink":"http://www.allmenus.com/il/bloomington-city/270865-la-gondola-spaghetti-house/menu/",
    "sg:phone":"+1 309 828 4141",
    "sg:postcode":"61701",
    "sg:province":"IL",
    "sg:tags":[
        "italian"
    ],
    "wof:name":"La Gondola Spaghetti House",
    "wof:placetype":"venue"
},
  "geometry": {"coordinates":[-88.956923,40.502585],"type":"Point"}
}