{
  "type": "Feature",
  "properties": {
    "addr:full":"221 Sunset Dr Belleville IL 62223",
    "addr:housenumber":"221",
    "addr:postcode":"62223",
    "addr:street":"Sunset Dr",
    "iso:country":"US",
    "sg:address":"221 Sunset Dr",
    "sg:city":"Belleville",
    "sg:classifiers":[
        {
            "category":"Shopping",
            "subcategory":"Gifts & Souvenirs",
            "type":"Retail Goods"
        }
    ],
    "sg:phone":"+1 618 397 1003",
    "sg:postcode":"62223",
    "sg:province":"IL",
    "sg:tags":[
        "shop"
    ],
    "wof:name":"Clowns N' Cases",
    "wof:placetype":"venue"
},
  "geometry": {"coordinates":[-90.04871300000001,38.554975],"type":"Point"}
}