{
  "type": "Feature",
  "properties": {
    "iso:country":"US",
    "sg:address":"247 W Grantley Ave",
    "sg:city":"Elmhurst",
    "sg:classifiers":[
        {
            "category":"Professional",
            "subcategory":"Computer Services",
            "type":"Services"
        }
    ],
    "sg:phone":"+1 630 258 4383",
    "sg:postcode":"60126",
    "sg:province":"IL",
    "sg:tags":[
        "related"
    ],
    "wof:name":"Practicorp Inc",
    "wof:placetype":"venue"
},
  "geometry": {"coordinates":[-87.948511,41.908231],"type":"Point"}
}