{
  "type": "Feature",
  "properties": {
    "iso:country":"US",
    "sg:address":"2360 Walnut Ave",
    "sg:city":"Hanover Park",
    "sg:classifiers":[
        {
            "category":"Retail",
            "subcategory":"Self-service Laundry",
            "type":"Services"
        }
    ],
    "sg:phone":"+1 630 372 1825",
    "sg:postcode":"60133",
    "sg:province":"IL",
    "wof:name":"Chi Chi Laundromat",
    "wof:placetype":"venue"
},
  "geometry": {"coordinates":[-88.162443,41.993775],"type":"Point"}
}