{
  "type": "Feature",
  "properties": {
    "iso:country":"US",
    "sg:address":"2736 Sheridan Rd",
    "sg:city":"Zion",
    "sg:phone":"+1 847 731 8336",
    "sg:postcode":"60099",
    "sg:province":"IL",
    "wof:name":"Chosen Royalty Barber Salon",
    "wof:placetype":"venue"
},
  "geometry": {"coordinates":[-87.825503,42.445435],"type":"Point"}
}