{
  "type": "Feature",
  "properties": {
    "addr:full":"2200 McNeal Rd Kirkland IL 60146",
    "addr:housenumber":"2200",
    "addr:postcode":"60146",
    "addr:street":"Mcneal Rd",
    "iso:country":"US",
    "sg:address":"2200 McNeal Rd",
    "sg:city":"Kirkland",
    "sg:classifiers":[
        {
            "category":"Recreation",
            "type":"Entertainment"
        }
    ],
    "sg:phone":"+1 815 522 9976",
    "sg:postcode":"60146",
    "sg:province":"IL",
    "sg:tags":[
        "stable"
    ],
    "wof:name":"Everbold Farms",
    "wof:placetype":"venue"
},
  "geometry": {"coordinates":[-88.908321,42.137946],"type":"Point"}
}