{
  "type": "Feature",
  "properties": {
    "iso:country":"US",
    "sg:address":"3938 W 110th St",
    "sg:city":"Chicago",
    "sg:classifiers":[
        {
            "category":"Insurance",
            "subcategory":"Insurance Agent",
            "type":"Services"
        }
    ],
    "sg:phone":"+1 773 233 9600",
    "sg:postcode":"60655",
    "sg:province":"IL",
    "wof:name":"Farmers Insurance Group",
    "wof:placetype":"venue"
},
  "geometry": {"coordinates":[-87.719695,41.693145],"type":"Point"}
}