{
  "type": "Feature",
  "properties": {
    "addr:full":"321 N Laramie Ave Chicago IL 60644",
    "addr:housenumber":"321",
    "addr:postcode":"60644",
    "addr:street":"N Laramie Ave",
    "iso:country":"US",
    "sg:address":"321 N Laramie Ave",
    "sg:city":"Chicago",
    "sg:classifiers":[
        {
            "category":"Deli",
            "type":"Food & Drink"
        }
    ],
    "sg:phone":"+1 773 378 8380",
    "sg:postcode":"60644",
    "sg:province":"IL",
    "wof:name":"Sun Subs",
    "wof:placetype":"venue"
},
  "geometry": {"coordinates":[-87.755302,41.885899],"type":"Point"}
}