{
  "type": "Feature",
  "properties": {
    "iso:country":"US",
    "sg:address":"802 Vista Ter",
    "sg:city":"Rockford",
    "sg:classifiers":[
        {
            "category":"Education",
            "subcategory":"School",
            "type":"Public Place"
        }
    ],
    "sg:phone":"+1 815 967 0396",
    "sg:postcode":"61102",
    "sg:province":"IL",
    "wof:name":"Ella's Little Shepards Day",
    "wof:placetype":"venue"
},
  "geometry": {"coordinates":[-89.131957,42.267644],"type":"Point"}
}