{
  "type": "Feature",
  "properties": {
    "addr:full":"1204 W Grand Ave. Chicago IL 60610",
    "addr:housenumber":"1204",
    "addr:postcode":"60610",
    "addr:street":"W Grand Ave.",
    "iso:country":"US",
    "sg:address":"1204 W Grand Ave.",
    "sg:city":"Chicago",
    "sg:classifiers":[
        {
            "category":"Deli",
            "type":"Food & Drink"
        },
        {
            "category":"Food & Beverages",
            "subcategory":"Bakery",
            "type":"Retail Goods"
        }
    ],
    "sg:phone":"+1 312 738 2985",
    "sg:postcode":"60610",
    "sg:province":"IL",
    "sg:tags":[
        "sandwich"
    ],
    "wof:name":"Vinnie's Sub Shop",
    "wof:placetype":"venue"
},
  "geometry": {"coordinates":[-87.657718,41.89134],"type":"Point"}
}