{
  "type": "Feature",
  "properties": {
    "addr:full":"1011 5th Ave Rockford IL 61104",
    "addr:housenumber":"1011",
    "addr:postcode":"61104",
    "addr:street":"5Th Ave",
    "iso:country":"US",
    "sg:address":"1011 5th Ave",
    "sg:city":"Rockford",
    "sg:classifiers":[
        {
            "category":"Cinema",
            "subcategory":"Movie Rental",
            "type":"Entertainment"
        }
    ],
    "sg:phone":"+1 815 964 5766",
    "sg:postcode":"61104",
    "sg:province":"IL",
    "sg:tags":[
        "video",
        "tape"
    ],
    "wof:name":"Asian Video",
    "wof:placetype":"venue"
},
  "geometry": {"coordinates":[-89.08093100000001,42.261451],"type":"Point"}
}