{
  "type": "Feature",
  "properties": {
    "iso:country":"US",
    "sg:address":"1145 W Wilson Ave",
    "sg:city":"Chicago",
    "sg:classifiers":[
        {
            "category":"Arts & Performance",
            "subcategory":"Arts Center",
            "type":"Entertainment"
        },
        {
            "category":"Education",
            "subcategory":"University",
            "type":"Public Place"
        }
    ],
    "sg:phone":"+1 773 878 9761",
    "sg:postcode":"60640",
    "sg:province":"IL",
    "sg:tags":[
        "performing",
        "college"
    ],
    "wof:name":"Pegasus Player Theatre",
    "wof:placetype":"venue"
},
  "geometry": {"coordinates":[-87.658997,41.965401],"type":"Point"}
}