{
  "type": "Feature",
  "properties": {
    "addr:full":"200 Vine Ave Park Ridge IL 60068",
    "addr:housenumber":"200",
    "addr:postcode":"60068",
    "addr:street":"Vine Ave",
    "iso:country":"US",
    "sg:address":"200 Vine Ave",
    "sg:city":"Park Ridge",
    "sg:classifiers":[
        {
            "category":"Government",
            "subcategory":"Police Station",
            "type":"Public Place"
        }
    ],
    "sg:phone":"+1   ",
    "sg:postcode":"60068",
    "sg:province":"IL",
    "sg:tags":[
        "protection"
    ],
    "wof:name":"Park Ridge Police Department",
    "wof:placetype":"venue"
},
  "geometry": {"coordinates":[-87.828211,42.007356],"type":"Point"}
}