{
  "type": "Feature",
  "properties": {
    "addr:full":"2629 N Cicero Avenue Chicago IL 60639",
    "addr:housenumber":"2629",
    "addr:postcode":"60639",
    "addr:street":"N Cicero Avenue",
    "iso:country":"US",
    "sg:address":"2629 N Cicero Avenue",
    "sg:city":"Chicago",
    "sg:classifiers":[
        {
            "category":"Retail",
            "subcategory":"Auto Repair",
            "type":"Services"
        }
    ],
    "sg:phone":"+1 773 489 1299",
    "sg:postcode":"60639",
    "sg:province":"IL",
    "wof:name":"Ram Air Research",
    "wof:placetype":"venue"
},
  "geometry": {"coordinates":[-87.74659,41.929189],"type":"Point"}
}