{
  "type": "Feature",
  "properties": {
    "addr:full":"1020 Garfield Ave Lockport IL 60441",
    "addr:housenumber":"1020",
    "addr:postcode":"60441",
    "addr:street":"Garfield Ave",
    "iso:country":"US",
    "sg:address":"1020 Garfield Ave",
    "sg:city":"Lockport",
    "sg:classifiers":[
        {
            "category":"Shopping",
            "type":"Retail Goods"
        }
    ],
    "sg:phone":"+1   ",
    "sg:postcode":"60441",
    "sg:province":"IL",
    "sg:tags":[
        "merchandise"
    ],
    "wof:name":"A Touch Of Sea",
    "wof:placetype":"venue"
},
  "geometry": {"coordinates":[-88.048148,41.585288],"type":"Point"}
}