{
  "type": "Feature",
  "properties": {
    "iso:country":"US",
    "sg:address":"613 E Roosevelt Rd",
    "sg:city":"Glen Ellyn",
    "sg:classifiers":[
        {
            "category":"Banks & Credit Unions",
            "subcategory":"Bank",
            "type":"Services"
        }
    ],
    "sg:phone":"+1 630 790 3383",
    "sg:postcode":"60137",
    "sg:province":"IL",
    "sg:tags":[
        "currency",
        "exchange"
    ],
    "wof:name":"Glen Ellyn Currency Exchange",
    "wof:placetype":"venue"
},
  "geometry": {"coordinates":[-88.063631,41.859293],"type":"Point"}
}