{
  "type": "Feature",
  "properties": {
    "iso:country":"US",
    "sg:address":"15849 W Buckley Rd",
    "sg:city":"Libertyville",
    "sg:classifiers":[
        {
            "category":"Building & Trades",
            "subcategory":"Landscaping Services",
            "type":"Services"
        }
    ],
    "sg:phone":"+1 847 549 1361",
    "sg:postcode":"60048",
    "sg:province":"IL",
    "sg:tags":[
        "lawn",
        "landscape",
        "contractor"
    ],
    "sg:website":"http://www.rosboroughpartners.com",
    "wof:name":"Rosborough Partners Inc",
    "wof:placetype":"venue"
},
  "geometry": {"coordinates":[-87.942932,42.305771],"type":"Point"}
}