{
  "type": "Feature",
  "properties": {
    "iso:country":"US",
    "sg:address":"4201 W 59th St",
    "sg:city":"Chicago",
    "sg:classifiers":[
        {
            "category":"Food & Beverages",
            "subcategory":"Groceries & Convenience Stores",
            "type":"Retail Goods"
        }
    ],
    "sg:phone":"+1 773 581 9550",
    "sg:postcode":"60629",
    "sg:province":"IL",
    "wof:name":"La Montana",
    "wof:placetype":"venue"
},
  "geometry": {"coordinates":[-87.727839,41.785733],"type":"Point"}
}