{
  "type": "Feature",
  "properties": {
    "iso:country":"US",
    "sg:address":"2003 Philo Rd",
    "sg:city":"Urbana",
    "sg:classifiers":[
        {
            "category":"Health Services",
            "subcategory":"Doctor",
            "type":"Services"
        }
    ],
    "sg:phone":"+1 217 383 3060",
    "sg:postcode":"61802",
    "sg:province":"IL",
    "sg:tags":[
        "practice",
        "family"
    ],
    "wof:name":"Wagner Christian E MD",
    "wof:placetype":"venue"
},
  "geometry": {"coordinates":[-88.19090300000001,40.0924],"type":"Point"}
}