{
  "type": "Feature",
  "properties": {
    "iso:country":"US",
    "sg:address":"3275 Bremerton Ln",
    "sg:city":"Aurora",
    "sg:classifiers":[
        {
            "category":"Building & Trades",
            "subcategory":"Landscaping Services",
            "type":"Services"
        }
    ],
    "sg:phone":"+1 630 978 9731",
    "sg:postcode":"60504",
    "sg:province":"IL",
    "wof:name":"Lindo S Lush Lawns",
    "wof:placetype":"venue"
},
  "geometry": {"coordinates":[-88.234491,41.746381],"type":"Point"}
}