{
  "type": "Feature",
  "properties": {
    "iso:country":"US",
    "sg:address":"1 Goodlife Dr",
    "sg:city":"Effingham",
    "sg:classifiers":[
        {
            "category":"Freight",
            "type":"Transportation"
        }
    ],
    "sg:phone":"+1 217 342 3900",
    "sg:postcode":"62401",
    "sg:province":"IL",
    "sg:tags":[
        "trucking"
    ],
    "wof:name":"ADM Trucking",
    "wof:placetype":"venue"
},
  "geometry": {"coordinates":[-88.53402699999999,39.118826],"type":"Point"}
}