{
  "type": "Feature",
  "properties": {
    "addr:full":"3344 N Kimball Ave Chicago IL 60618",
    "addr:housenumber":"3344",
    "addr:postcode":"60618",
    "addr:street":"N Kimball Ave",
    "iso:country":"US",
    "sg:address":"3344 N Kimball Ave",
    "sg:city":"Chicago",
    "sg:phone":"+1 773 763 0660",
    "sg:postcode":"60618",
    "sg:province":"IL",
    "wof:name":"Superdawg Drive-In",
    "wof:placetype":"venue"
},
  "geometry": {"coordinates":[-87.712563,41.942261],"type":"Point"}
}