{
  "type": "Feature",
  "properties": {
    "addr:full":"3935 Elm St Downers Grove IL 60515",
    "addr:housenumber":"3935",
    "addr:postcode":"60515",
    "addr:street":"Elm St",
    "iso:country":"US",
    "sg:address":"3935 Elm St",
    "sg:city":"Downers Grove",
    "sg:classifiers":[
        {
            "category":"Professional",
            "subcategory":"Management & Consulting",
            "type":"Services"
        }
    ],
    "sg:phone":"+1 630 969 5935",
    "sg:postcode":"60515",
    "sg:province":"IL",
    "wof:name":"Timothy P Cahill Consulting",
    "wof:placetype":"venue"
},
  "geometry": {"coordinates":[-88.005719,41.814566],"type":"Point"}
}