{
  "type": "Feature",
  "properties": {
    "iso:country":"US",
    "sg:address":"2001 52nd St",
    "sg:city":"Moline",
    "sg:classifiers":[
        {
            "category":"Professional",
            "subcategory":"Employment Agencies",
            "type":"Services"
        }
    ],
    "sg:phone":"+1 309 764 9889",
    "sg:postcode":"61265",
    "sg:province":"IL",
    "wof:name":"Kelly Services",
    "wof:placetype":"venue"
},
  "geometry": {"coordinates":[-90.466766,41.493539],"type":"Point"}
}