{
  "type": "Feature",
  "properties": {
    "iso:country":"US",
    "sg:address":"2001 Forest St",
    "sg:city":"Eldorado",
    "sg:classifiers":[
        {
            "category":"Retail",
            "subcategory":"Repair Shop",
            "type":"Services"
        }
    ],
    "sg:phone":"+1 618 273 5914",
    "sg:postcode":"62930",
    "sg:province":"IL",
    "sg:tags":[
        "lock",
        "locksmith"
    ],
    "wof:name":"Mister M's Lock & Key",
    "wof:placetype":"venue"
},
  "geometry": {"coordinates":[-88.44051399999999,37.818477],"type":"Point"}
}