{
  "type": "Feature",
  "properties": {
    "iso:country":"US",
    "sg:address":"20 East Jackson Blvd Ste 600",
    "sg:city":"Chicago",
    "sg:classifiers":[
        {
            "category":"Professional",
            "subcategory":"Lawyer & Legal Services",
            "type":"Services"
        }
    ],
    "sg:phone":"+1 312 217 0321",
    "sg:postcode":"60604",
    "sg:province":"IL",
    "sg:website":"www.yourpersonallawyer.com",
    "wof:name":"Law Offices of Jonathan Dixon",
    "wof:placetype":"venue"
},
  "geometry": {"coordinates":[-87.62687200000001,41.878228],"type":"Point"}
}