{
  "type": "Feature",
  "properties": {
    "iso:country":"US",
    "sg:address":"4992 W Beaver Rd",
    "sg:city":"Freeport",
    "sg:phone":"+1 815 563 4810",
    "sg:postcode":"61032",
    "sg:province":"IL",
    "sg:tags":[
        "farm",
        "corn",
        "soybean"
    ],
    "wof:name":"Elmer Lubenow",
    "wof:placetype":"venue"
},
  "geometry": {"coordinates":[-89.71016899999999,42.387126],"type":"Point"}
}