{
  "type": "Feature",
  "properties": {
    "iso:country":"US",
    "sg:address":"1003 Lakeside Dr",
    "sg:city":"Gurnee",
    "sg:classifiers":[
        {
            "category":"Wholesale",
            "subcategory":"Medical Equipment & Supplies",
            "type":"Manufacturing & Wholesale Goods"
        },
        {
            "category":"Personal",
            "subcategory":"Skin Care",
            "type":"Services"
        }
    ],
    "sg:phone":"+1 847 855 0999",
    "sg:postcode":"60031",
    "sg:province":"IL",
    "sg:tags":[
        "laboratory",
        "sterilizing"
    ],
    "sg:website":"http://www.sterigenics.com",
    "wof:name":"Sterigenics U.S",
    "wof:placetype":"venue"
},
  "geometry": {"coordinates":[-87.951826,42.37247],"type":"Point"}
}