{
  "type": "Feature",
  "properties": {
    "iso:country":"US",
    "sg:address":"1091 Methodist St",
    "sg:city":"Carlyle",
    "sg:classifiers":[
        {
            "category":"Wholesale",
            "subcategory":"Farm Supplies",
            "type":"Manufacturing & Wholesale Goods"
        }
    ],
    "sg:phone":"+1 618 594 2223",
    "sg:postcode":"62231",
    "sg:province":"IL",
    "sg:tags":[
        "feed"
    ],
    "wof:name":"Consolidated Exchange Inc",
    "wof:placetype":"venue"
},
  "geometry": {"coordinates":[-89.370366,38.608283],"type":"Point"}
}