{
  "type": "Feature",
  "properties": {
    "iso:country":"US",
    "sg:address":"3231 Euclid Ave Ste 409",
    "sg:city":"Berwyn",
    "sg:classifiers":[
        {
            "category":"Health Services",
            "subcategory":"Doctor",
            "type":"Services"
        }
    ],
    "sg:phone":"+1 708 788 2201",
    "sg:postcode":"60402",
    "sg:province":"IL",
    "wof:name":"Orthopedics Midwest",
    "wof:placetype":"venue"
},
  "geometry": {"coordinates":[-87.79136800000001,41.833118],"type":"Point"}
}