{
  "type": "Feature",
  "properties": {
    "addr:full":"4204 W North Ave Chicago IL 60639",
    "addr:housenumber":"4204",
    "addr:postcode":"60639",
    "addr:street":"W North Ave",
    "iso:country":"US",
    "sg:address":"4204 W North Ave",
    "sg:city":"Chicago",
    "sg:classifiers":[
        {
            "category":"Professional",
            "subcategory":"Lawyer & Legal Services",
            "type":"Services"
        }
    ],
    "sg:phone":"+1 773 489 6400",
    "sg:postcode":"60639",
    "sg:province":"IL",
    "wof:name":"North Avenue Services",
    "wof:placetype":"venue"
},
  "geometry": {"coordinates":[-87.73150200000001,41.910016],"type":"Point"}
}