{
  "type": "Feature",
  "properties": {
    "addr:full":"5300 W Harrison St Chicago IL 60644",
    "addr:housenumber":"5300",
    "addr:postcode":"60644",
    "addr:street":"W Harrison St",
    "iso:country":"US",
    "sg:address":"5300 W Harrison St",
    "sg:city":"Chicago",
    "sg:classifiers":[
        {
            "category":"Food & Beverages",
            "subcategory":"Groceries & Convenience Stores",
            "type":"Retail Goods"
        }
    ],
    "sg:phone":"+1 773 261 8490",
    "sg:postcode":"60644",
    "sg:province":"IL",
    "wof:name":"Noor Foods",
    "wof:placetype":"venue"
},
  "geometry": {"coordinates":[-87.757401,41.873001],"type":"Point"}
}