{
  "type": "Feature",
  "properties": {
    "addr:full":"1792 S Arlington Heights Rd Arlington Hts IL 60005",
    "addr:housenumber":"1792",
    "addr:postcode":"60005",
    "addr:street":"S Arlington Heights Rd",
    "iso:country":"US",
    "sg:address":"1792 S Arlington Heights Rd",
    "sg:city":"Arlington Hts",
    "sg:classifiers":[
        {
            "category":"Health Services",
            "subcategory":"Doctor",
            "type":"Services"
        }
    ],
    "sg:phone":"+1 847 806 6100",
    "sg:postcode":"60005",
    "sg:province":"IL",
    "sg:tags":[
        "dentist"
    ],
    "wof:name":"Dennis Costis DDS",
    "wof:placetype":"venue"
},
  "geometry": {"coordinates":[-87.98191799999999,42.052622],"type":"Point"}
}