{
  "type": "Feature",
  "properties": {
    "iso:country":"US",
    "sg:address":"23807 W Andrew Rd",
    "sg:city":"Plainfield",
    "sg:classifiers":[
        {
            "category":"Manufacturing",
            "subcategory":"Buildings",
            "type":"Manufacturing & Wholesale Goods"
        },
        {
            "category":"Building & Trades",
            "subcategory":"Construction",
            "type":"Services"
        }
    ],
    "sg:phone":"+1 815 436 7435",
    "sg:postcode":"60585",
    "sg:province":"IL",
    "sg:tags":[
        "industrial",
        "system",
        "specialty",
        "builder",
        "heating",
        "contractor",
        "contractors-commercial",
        "home",
        "air conditioning"
    ],
    "wof:name":"Cb Enterprises Ltd",
    "wof:placetype":"venue"
},
  "geometry": {"coordinates":[-88.19926700000001,41.659857],"type":"Point"}
}