{
  "type": "Feature",
  "properties": {
    "iso:country":"US",
    "sg:address":"1227 Glen Ellyn Rd",
    "sg:city":"Glendale Heights",
    "sg:classifiers":[
        {
            "category":"Banks & Credit Unions",
            "subcategory":"Bank",
            "type":"Services"
        }
    ],
    "sg:phone":"+1 630 469 8597",
    "sg:postcode":"60139",
    "sg:province":"IL",
    "sg:tags":[
        "institution",
        "business"
    ],
    "wof:name":"Short Term Loans",
    "wof:placetype":"venue"
},
  "geometry": {"coordinates":[-88.062983,41.903983],"type":"Point"}
}