{
  "type": "Feature",
  "properties": {
    "addr:full":"7243 N Harlem Ave Niles IL 60714",
    "addr:housenumber":"7243",
    "addr:postcode":"60714",
    "addr:street":"N Harlem Ave",
    "iso:country":"US",
    "sg:address":"7243 N Harlem Ave",
    "sg:city":"Niles",
    "sg:classifiers":[
        {
            "category":"Restaurant",
            "type":"Food & Drink"
        }
    ],
    "sg:menulink":"http://www.allmenus.com/il/niles/181058-wendys/menu/",
    "sg:phone":"+1 847 647 0474",
    "sg:postcode":"60714",
    "sg:province":"IL",
    "sg:tags":[
        "burger",
        "american",
        "soup"
    ],
    "wof:name":"Wendy's",
    "wof:placetype":"venue"
},
  "geometry": {"coordinates":[-87.80654199999999,42.013467],"type":"Point"}
}