{
  "type": "Feature",
  "properties": {
    "iso:country":"US",
    "sg:address":"1327 N Fairfield Rd",
    "sg:city":"Round Lake Beach",
    "sg:classifiers":[
        {
            "category":"Retail",
            "subcategory":"Auto Rental",
            "type":"Services"
        }
    ],
    "sg:phone":"+1 847 740 3627",
    "sg:postcode":"60073",
    "sg:province":"IL",
    "sg:tags":[
        "renting",
        "truck",
        "leasing"
    ],
    "wof:name":"U-Haul Co",
    "wof:placetype":"venue"
},
  "geometry": {"coordinates":[-88.109927,42.372222],"type":"Point"}
}