{
  "type": "Feature",
  "properties": {
    "addr:full":"8960 Benoy Ct Woodstock IL 60014",
    "addr:postcode":"8960;60014",
    "addr:street":"Benoy Ct",
    "iso:country":"US",
    "sg:address":"8960 Benoy Ct",
    "sg:city":"Woodstock",
    "sg:classifiers":[
        {
            "category":"Recreation",
            "subcategory":"Marina",
            "type":"Entertainment"
        }
    ],
    "sg:phone":"+1 815 337 0940",
    "sg:postcode":"60014",
    "sg:province":"IL",
    "sg:tags":[
        "sales",
        "boat"
    ],
    "wof:name":"Wauconda Boat",
    "wof:placetype":"venue"
},
  "geometry": {"coordinates":[-88.371675,42.214369],"type":"Point"}
}