{
  "type": "Feature",
  "properties": {
    "addr:full":"1901 N Elston Ave Chicago IL 60642",
    "addr:housenumber":"1901",
    "addr:postcode":"60642",
    "addr:street":"N Elston Ave",
    "iso:country":"US",
    "sg:address":"1901 N Elston Ave",
    "sg:city":"Chicago",
    "sg:classifiers":[
        {
            "category":"Autos & Motor Vehicles",
            "subcategory":"Fuel & Gas Station",
            "type":"Retail Goods"
        }
    ],
    "sg:phone":"+1 773 772 4095",
    "sg:postcode":"60642",
    "sg:province":"IL",
    "wof:name":"Fireking Oil",
    "wof:placetype":"venue"
},
  "geometry": {"coordinates":[-87.666196,41.916556],"type":"Point"}
}