{
  "type": "Feature",
  "properties": {
    "addr:full":"4200 W Madison St Chicago IL 60624",
    "addr:housenumber":"4200",
    "addr:postcode":"60624",
    "addr:street":"W Madison St",
    "iso:country":"US",
    "sg:address":"4200 W Madison St",
    "sg:city":"Chicago",
    "sg:classifiers":[
        {
            "category":"Restaurant",
            "type":"Food & Drink"
        }
    ],
    "sg:phone":"+1 773 638 7000",
    "sg:postcode":"60624",
    "sg:province":"IL",
    "sg:tags":[
        "seafood"
    ],
    "wof:name":"Fisher Fish & Chicken",
    "wof:placetype":"venue"
},
  "geometry": {"coordinates":[-87.730723,41.880999],"type":"Point"}
}