{
  "type": "Feature",
  "properties": {
    "addr:full":"8830 Ogden Ave Brookfield IL 60513",
    "addr:housenumber":"8830",
    "addr:postcode":"60513",
    "addr:street":"Ogden Ave",
    "iso:country":"US",
    "sg:address":"8830 Ogden Ave",
    "sg:city":"Brookfield",
    "sg:classifiers":[
        {
            "category":"Building & Trades",
            "subcategory":"Construction",
            "type":"Services"
        }
    ],
    "sg:phone":"+1 708 485 1833",
    "sg:postcode":"60513",
    "sg:province":"IL",
    "sg:tags":[
        "granite",
        "top",
        "counter",
        "installation",
        "fabrication"
    ],
    "sg:website":"http://www.themarbleplace.com",
    "wof:name":"Marble Place",
    "wof:placetype":"venue"
},
  "geometry": {"coordinates":[-87.84176100000001,41.816483],"type":"Point"}
}