{
  "type": "Feature",
  "properties": {
    "iso:country":"US",
    "sg:address":"2580 Charles St",
    "sg:city":"Rockford",
    "sg:classifiers":[
        {
            "category":"Professional",
            "subcategory":"Employment Agencies",
            "type":"Services"
        }
    ],
    "sg:phone":"+1 815 229 7810",
    "sg:postcode":"61108",
    "sg:province":"IL",
    "sg:tags":[
        "opportunity"
    ],
    "sg:website":"www.furststaff.com",
    "wof:name":"Furst Staffing",
    "wof:placetype":"venue"
},
  "geometry": {"coordinates":[-89.055308,42.259781],"type":"Point"}
}