{
  "type": "Feature",
  "properties": {
    "iso:country":"US",
    "sg:address":"9607 S Sangamon St",
    "sg:city":"Chicago",
    "sg:classifiers":[
        {
            "category":"Manufacturing",
            "subcategory":"Furniture",
            "type":"Manufacturing & Wholesale Goods"
        }
    ],
    "sg:phone":"+1 773 779 0949",
    "sg:postcode":"60643",
    "sg:province":"IL",
    "sg:tags":[
        "household",
        "mfg"
    ],
    "wof:name":"Sherman A Towner",
    "wof:placetype":"venue"
},
  "geometry": {"coordinates":[-87.646691,41.717684],"type":"Point"}
}