{
  "type": "Feature",
  "properties": {
    "addr:full":"1217 Wenonah Ave Berwyn IL 60402",
    "addr:housenumber":"1217",
    "addr:postcode":"60402",
    "addr:street":"Wenonah Ave",
    "iso:country":"US",
    "sg:address":"1217 Wenonah Ave",
    "sg:city":"Berwyn",
    "sg:classifiers":[
        {
            "category":"Building & Trades",
            "subcategory":"Construction",
            "type":"Services"
        }
    ],
    "sg:phone":"+1 708 795 4227",
    "sg:postcode":"60402",
    "sg:province":"IL",
    "sg:tags":[
        "contractor"
    ],
    "wof:name":"Azteca Plastering Inc",
    "wof:placetype":"venue"
},
  "geometry": {"coordinates":[-87.800102,41.864601],"type":"Point"}
}