{
  "type": "Feature",
  "properties": {
    "iso:country":"US",
    "sg:address":"601 W 10th St",
    "sg:city":"Rock Falls",
    "sg:classifiers":[
        {
            "category":"Organizations",
            "subcategory":"Professional Association",
            "type":"Services"
        }
    ],
    "sg:phone":"+1 815 625 4500",
    "sg:postcode":"61071",
    "sg:province":"IL",
    "sg:tags":[
        "chamber",
        "commerce"
    ],
    "wof:name":"Rock Falls Chamber Of Commerce",
    "wof:placetype":"venue"
},
  "geometry": {"coordinates":[-89.69646899999999,41.772472],"type":"Point"}
}