{
  "type": "Feature",
  "properties": {
    "iso:country":"US",
    "sg:address":"821 E Grant Hwy",
    "sg:city":"Marengo",
    "sg:classifiers":[
        {
            "category":"Insurance",
            "subcategory":"Insurance Agent",
            "type":"Services"
        },
        {
            "category":"Insurance",
            "subcategory":"Hazard Insurance",
            "type":"Services"
        },
        {
            "category":"Insurance",
            "subcategory":"Title Insurance",
            "type":"Services"
        }
    ],
    "sg:phone":"+1 815 568 8050",
    "sg:postcode":"60152",
    "sg:province":"IL",
    "sg:tags":[
        "auto",
        "homeowner"
    ],
    "sg:website":"http://apps.amfam.com/agentlocator/RJONE3?sourceid=yp3",
    "wof:name":"American Family Insurance- Ray Jones",
    "wof:placetype":"venue"
},
  "geometry": {"coordinates":[-88.59554199999999,42.243584],"type":"Point"}
}