{
  "type": "Feature",
  "properties": {
    "addr:full":"3217 N Main St Rockford IL 61103",
    "addr:housenumber":"3217",
    "addr:postcode":"61103",
    "addr:street":"N Main St",
    "iso:country":"US",
    "sg:address":"3217 N Main St",
    "sg:city":"Rockford",
    "sg:classifiers":[
        {
            "category":"Personal",
            "type":"Services"
        }
    ],
    "sg:phone":"+1 815 633 6734",
    "sg:postcode":"61103",
    "sg:province":"IL",
    "sg:tags":[
        "bureau"
    ],
    "wof:name":"Michael D Mc Neeley",
    "wof:placetype":"venue"
},
  "geometry": {"coordinates":[-89.07708700000001,42.308914],"type":"Point"}
}