{
  "type": "Feature",
  "properties": {
    "addr:full":"300 E 147TH ST HARVEY IL 60426",
    "addr:housenumber":"300",
    "addr:postcode":"60426",
    "addr:street":"E 147Th St",
    "iso:country":"US",
    "sg:address":"300 E 147TH ST",
    "sg:city":"HARVEY",
    "sg:classifiers":[
        {
            "category":"Insurance",
            "subcategory":"Hazard Insurance",
            "type":"Services"
        },
        {
            "category":"Insurance",
            "subcategory":"Insurance Agent",
            "type":"Services"
        },
        {
            "category":"Insurance",
            "subcategory":"Life Insurance",
            "type":"Services"
        },
        {
            "category":"Insurance",
            "subcategory":"Title Insurance",
            "type":"Services"
        }
    ],
    "sg:phone":"+1 708 474 3700",
    "sg:postcode":"60426",
    "sg:province":"IL",
    "sg:tags":[
        "auto",
        "homeowner"
    ],
    "wof:name":"InsureOne-Harvey II",
    "wof:placetype":"venue"
},
  "geometry": {"coordinates":[-87.63893899999999,41.622639],"type":"Point"}
}