{
  "type": "Feature",
  "properties": {
    "iso:country":"US",
    "sg:address":"1812 McNeil Rd",
    "sg:city":"Rock Falls",
    "sg:classifiers":[
        {
            "category":"Building & Trades",
            "subcategory":"Construction",
            "type":"Services"
        }
    ],
    "sg:phone":"+1 815 626 0789",
    "sg:postcode":"61071",
    "sg:province":"IL",
    "sg:tags":[
        "general",
        "contractor"
    ],
    "wof:name":"Northwest Illinois Constr Co",
    "wof:placetype":"venue"
},
  "geometry": {"coordinates":[-89.665406,41.766383],"type":"Point"}
}