{
  "type": "Feature",
  "properties": {
    "iso:country":"US",
    "sg:address":"3203 N Clark St",
    "sg:city":"Chicago",
    "sg:classifiers":[
        {
            "category":"Restaurant",
            "type":"Food & Drink"
        }
    ],
    "sg:phone":"+1 773 281 9000",
    "sg:postcode":"60657",
    "sg:province":"IL",
    "sg:tags":[
        "chinese"
    ],
    "wof:name":"Bamboo Garden",
    "wof:placetype":"venue"
},
  "geometry": {"coordinates":[-87.65070299999999,41.939999],"type":"Point"}
}