{
  "type": "Feature",
  "properties": {
    "addr:full":"4839 N Elston Ave Chicago IL 60630",
    "addr:housenumber":"4839",
    "addr:postcode":"60630",
    "addr:street":"N Elston Ave",
    "iso:country":"US",
    "sg:address":"4839 N Elston Ave",
    "sg:city":"Chicago",
    "sg:classifiers":[
        {
            "category":"Professional",
            "subcategory":"Advertising",
            "type":"Services"
        }
    ],
    "sg:phone":"+1 773 283 0718",
    "sg:postcode":"60630",
    "sg:province":"IL",
    "sg:tags":[
        "telemarketing"
    ],
    "wof:name":"Harvard Collection Svc Inc",
    "wof:placetype":"venue"
},
  "geometry": {"coordinates":[-87.74132,41.968811],"type":"Point"}
}