{
  "type": "Feature",
  "properties": {
    "addr:full":"529 Park Dr Glenwood IL 60425",
    "addr:housenumber":"529",
    "addr:postcode":"60425",
    "addr:street":"Park Dr",
    "iso:country":"US",
    "sg:address":"529 Park Dr",
    "sg:city":"Glenwood",
    "sg:classifiers":[
        {
            "category":"Health Services",
            "subcategory":"Medical Lab",
            "type":"Services"
        }
    ],
    "sg:phone":"+1 708 754 1471",
    "sg:postcode":"60425",
    "sg:province":"IL",
    "sg:tags":[
        "laboratory",
        "dental"
    ],
    "wof:name":"Aragon Dental Laboratory Inc",
    "wof:placetype":"venue"
},
  "geometry": {"coordinates":[-87.628041,41.553992],"type":"Point"}
}