{
  "type": "Feature",
  "properties": {
    "addr:full":"745 2nd St La Salle IL 61301",
    "addr:housenumber":"745",
    "addr:postcode":"61301",
    "addr:street":"2Nd St",
    "iso:country":"US",
    "sg:address":"745 2nd St",
    "sg:city":"La Salle",
    "sg:classifiers":[
        {
            "category":"Government",
            "subcategory":"Office",
            "type":"Public Place"
        }
    ],
    "sg:phone":"+1 815 223 2689",
    "sg:postcode":"61301",
    "sg:province":"IL",
    "sg:tags":[
        "state",
        "security"
    ],
    "wof:name":"Military Affairs Dept",
    "wof:placetype":"venue"
},
  "geometry": {"coordinates":[-89.09475999999999,41.32936],"type":"Point"}
}