{
  "type": "Feature",
  "properties": {
    "addr:full":"1165 Willoby Ln Elgin IL 60120",
    "addr:housenumber":"1165",
    "addr:postcode":"60120",
    "addr:street":"Willoby Ln",
    "iso:country":"US",
    "sg:address":"1165 Willoby Ln",
    "sg:city":"Elgin",
    "sg:classifiers":[
        {
            "category":"Health Services",
            "subcategory":"Health Practitioner",
            "type":"Services"
        }
    ],
    "sg:phone":"+1 847 697 4433",
    "sg:postcode":"60120",
    "sg:province":"IL",
    "sg:tags":[
        "psychologist"
    ],
    "wof:name":"Palatine Center For Family LTD",
    "wof:placetype":"venue"
},
  "geometry": {"coordinates":[-88.24509999999999,42.05499],"type":"Point"}
}