{
  "type": "Feature",
  "properties": {
    "addr:full":"912 N College Ave Geneseo IL 61254",
    "addr:housenumber":"912",
    "addr:postcode":"61254",
    "addr:street":"N College Ave",
    "iso:country":"US",
    "sg:address":"912 N College Ave",
    "sg:city":"Geneseo",
    "sg:phone":"+1 309 944 5756",
    "sg:postcode":"61254",
    "sg:province":"IL",
    "sg:tags":[
        "farm",
        "corn"
    ],
    "wof:name":"Scott Rice",
    "wof:placetype":"venue"
},
  "geometry": {"coordinates":[-90.158242,41.46924],"type":"Point"}
}