{
  "type": "Feature",
  "properties": {
    "iso:country":"US",
    "sg:address":"318 W Washington St Ste 1",
    "sg:city":"Bloomington",
    "sg:classifiers":[
        {
            "category":"Professional",
            "subcategory":"Lawyer & Legal Services",
            "type":"Services"
        }
    ],
    "sg:phone":"+1 309 828 1800",
    "sg:postcode":"61701",
    "sg:province":"IL",
    "sg:tags":[
        "attorney",
        "negligence",
        "practice",
        "worker",
        "compensation",
        "labor",
        "liability",
        "benefit",
        "malpractice",
        "employee",
        "law",
        "employment"
    ],
    "sg:website":"http://www.bloomingtoninjurylawyer.com",
    "wof:name":"Kim Maccloskey & Associates",
    "wof:placetype":"venue"
},
  "geometry": {"coordinates":[-88.99573700000001,40.479543],"type":"Point"}
}