{
  "type": "Feature",
  "properties": {
    "iso:country":"US",
    "sg:address":"2071 Irving Park Rd",
    "sg:city":"Bartlett",
    "sg:classifiers":[
        {
            "category":"Professional",
            "subcategory":"Business Services",
            "type":"Services"
        },
        {
            "category":"Wholesale",
            "subcategory":"Groceries",
            "type":"Manufacturing & Wholesale Goods"
        }
    ],
    "sg:phone":"+1 630 736 4704",
    "sg:postcode":"60133",
    "sg:province":"IL",
    "sg:tags":[
        "broker"
    ],
    "wof:name":"Grasemann Group LTD",
    "wof:placetype":"venue"
},
  "geometry": {"coordinates":[-88.155495,42.008424],"type":"Point"}
}