{
  "type": "Feature",
  "properties": {
    "iso:country":"US",
    "sg:address":"109 Industrial Dr",
    "sg:city":"Minooka",
    "sg:classifiers":[
        {
            "category":"Building & Trades",
            "subcategory":"Construction",
            "type":"Services"
        }
    ],
    "sg:phone":"+1 815 467 4600",
    "sg:postcode":"60447",
    "sg:province":"IL",
    "sg:tags":[
        "contractor"
    ],
    "wof:name":"Johnston Construction",
    "wof:placetype":"venue"
},
  "geometry": {"coordinates":[-88.275299,41.448299],"type":"Point"}
}