{
  "type": "Feature",
  "properties": {
    "iso:country":"US",
    "sg:address":"3421 Pearl St",
    "sg:city":"Mc Henry",
    "sg:classifiers":[
        {
            "category":"Retail",
            "subcategory":"Repair Shop",
            "type":"Services"
        }
    ],
    "sg:phone":"+1 815 759 1575",
    "sg:postcode":"60050",
    "sg:province":"IL",
    "wof:name":"Elite Furniture Service",
    "wof:placetype":"venue"
},
  "geometry": {"coordinates":[-88.264825,42.346667],"type":"Point"}
}