{
  "type": "Feature",
  "properties": {
    "addr:full":"13101 Chicago St Blue Island IL 60406",
    "addr:housenumber":"13101",
    "addr:postcode":"60406",
    "addr:street":"Chicago St",
    "iso:country":"US",
    "sg:address":"13101 Chicago St",
    "sg:city":"Blue Island",
    "sg:classifiers":[
        {
            "category":"Health Services",
            "subcategory":"Doctor",
            "type":"Services"
        }
    ],
    "sg:phone":"+1 708 385 3511",
    "sg:postcode":"60406",
    "sg:province":"IL",
    "sg:tags":[
        "surgeon",
        "oral"
    ],
    "wof:name":"Ilardo Anthony DDS",
    "wof:placetype":"venue"
},
  "geometry": {"coordinates":[-87.674004,41.6553],"type":"Point"}
}