{
  "type": "Feature",
  "properties": {
    "iso:country":"US",
    "sg:address":"37 E 34th St",
    "sg:city":"Steger",
    "sg:classifiers":[
        {
            "category":"Restaurant",
            "type":"Food & Drink"
        }
    ],
    "sg:phone":"+1 708 755 6200",
    "sg:postcode":"60475",
    "sg:province":"IL",
    "wof:name":"Bambino's Family Restaurant",
    "wof:placetype":"venue"
},
  "geometry": {"coordinates":[-87.633488,41.469879],"type":"Point"}
}