{
  "type": "Feature",
  "properties": {
    "iso:country":"US",
    "sg:address":"534 Gold River Ave",
    "sg:city":"Rockford",
    "sg:classifiers":[
        {
            "category":"Organizations",
            "subcategory":"Labor Organization",
            "type":"Services"
        }
    ],
    "sg:phone":"+1 815 963 1976",
    "sg:postcode":"61102",
    "sg:province":"IL",
    "wof:name":"Local 448",
    "wof:placetype":"venue"
},
  "geometry": {"coordinates":[-89.16373400000001,42.183686],"type":"Point"}
}