{
  "type": "Feature",
  "properties": {
    "addr:full":"240 Regency Ctr Collinsville IL 62234",
    "addr:housenumber":"240",
    "addr:postcode":"62234",
    "addr:street":"Regency Ctr",
    "iso:country":"US",
    "sg:address":"240 Regency Ctr",
    "sg:city":"Collinsville",
    "sg:classifiers":[
        {
            "category":"Education",
            "subcategory":"School",
            "type":"Public Place"
        }
    ],
    "sg:phone":"+1 618 343 2878",
    "sg:postcode":"62234",
    "sg:province":"IL",
    "sg:tags":[
        "high",
        "middle",
        "elementary"
    ],
    "wof:name":"Collinsville Community",
    "wof:placetype":"venue"
},
  "geometry": {"coordinates":[-89.987396,38.691502],"type":"Point"}
}