{
  "type": "Feature",
  "properties": {
    "addr:full":"141 W North Ave Northlake IL 60164",
    "addr:housenumber":"141",
    "addr:postcode":"60164",
    "addr:street":"W North Ave",
    "iso:country":"US",
    "sg:address":"141 W North Ave",
    "sg:city":"Northlake",
    "sg:classifiers":[
        {
            "category":"Health Services",
            "subcategory":"Optometrist",
            "type":"Services"
        },
        {
            "category":"Shopping",
            "subcategory":"Discount & Variety Stores",
            "type":"Retail Goods"
        },
        {
            "category":"Shopping",
            "subcategory":"Pharmacy",
            "type":"Retail Goods"
        },
        {
            "category":"Shopping",
            "subcategory":"Florist",
            "type":"Retail Goods"
        }
    ],
    "sg:phone":"+1 708 531 0807",
    "sg:postcode":"60164",
    "sg:province":"IL",
    "sg:tags":[
        "optical"
    ],
    "sg:website":"http://www.samsclub.com",
    "wof:name":"Sam's Club",
    "wof:placetype":"venue"
},
  "geometry": {"coordinates":[-87.911058,41.906868],"type":"Point"}
}