{
  "type": "Feature",
  "properties": {
    "addr:full":"4765 Wild Deer Trl Roscoe IL 61073",
    "addr:housenumber":"4765",
    "addr:postcode":"61073",
    "addr:street":"Wild Deer Trl",
    "iso:country":"US",
    "sg:address":"4765 Wild Deer Trl",
    "sg:city":"Roscoe",
    "sg:classifiers":[
        {
            "category":"Professional",
            "subcategory":"Advertising",
            "type":"Services"
        }
    ],
    "sg:phone":"+1 815 623 7258",
    "sg:postcode":"61073",
    "sg:province":"IL",
    "sg:tags":[
        "counselor"
    ],
    "wof:name":"Action Advertising",
    "wof:placetype":"venue"
},
  "geometry": {"coordinates":[-89.02068800000001,42.427421],"type":"Point"}
}