{
  "type": "Feature",
  "properties": {
    "addr:full":"1100 Nerge Rd Elk Grove Vlg IL 60007",
    "addr:housenumber":"1100",
    "addr:postcode":"60007",
    "addr:street":"Nerge Rd",
    "iso:country":"US",
    "sg:address":"1100 Nerge Rd",
    "sg:city":"Elk Grove Vlg",
    "sg:classifiers":[
        {
            "category":"Professional",
            "subcategory":"Accounting & Tax Preparation",
            "type":"Services"
        }
    ],
    "sg:phone":"+1 847 301 6252",
    "sg:postcode":"60007",
    "sg:province":"IL",
    "sg:tags":[
        "accountant"
    ],
    "wof:name":"G L Wentzel & Co",
    "wof:placetype":"venue"
},
  "geometry": {"coordinates":[-88.0415,41.999439],"type":"Point"}
}