{
  "type": "Feature",
  "properties": {
    "addr:full":"16725 Richmond Ave Harvey IL 60426",
    "addr:housenumber":"16725",
    "addr:postcode":"60426",
    "addr:street":"Richmond Ave",
    "iso:country":"US",
    "sg:address":"16725 Richmond Ave",
    "sg:city":"Harvey",
    "sg:classifiers":[
        {
            "category":"Building & Trades",
            "subcategory":"Cleaning & Sanitation",
            "type":"Services"
        }
    ],
    "sg:phone":"+1 708 596 0200",
    "sg:postcode":"60426",
    "sg:province":"IL",
    "sg:tags":[
        "carpet"
    ],
    "wof:name":"Collins Carpet Cleaning Inc",
    "wof:placetype":"venue"
},
  "geometry": {"coordinates":[-87.663101,41.6119],"type":"Point"}
}