{
  "type": "Feature",
  "properties": {
    "addr:full":"4905 Oakton St Skokie IL 60077",
    "addr:housenumber":"4905",
    "addr:postcode":"60077",
    "addr:street":"Oakton St",
    "iso:country":"US",
    "sg:address":"4905 Oakton St",
    "sg:city":"Skokie",
    "sg:classifiers":[
        {
            "category":"Health Services",
            "subcategory":"Doctor",
            "type":"Services"
        }
    ],
    "sg:phone":"+1 847 673 4757",
    "sg:postcode":"60077",
    "sg:province":"IL",
    "sg:tags":[
        "medical"
    ],
    "wof:name":"Donald Saltzman DDS",
    "wof:placetype":"venue"
},
  "geometry": {"coordinates":[-87.75168600000001,42.026214],"type":"Point"}
}