{
  "type": "Feature",
  "properties": {
    "iso:country":"US",
    "sg:address":"20 S Central Ave",
    "sg:city":"Casey",
    "sg:classifiers":[
        {
            "category":"Communications",
            "type":"Services"
        }
    ],
    "sg:phone":"+1 217 932 5208",
    "sg:postcode":"62420",
    "sg:province":"IL",
    "wof:name":"Bolin Communications Inc",
    "wof:placetype":"venue"
},
  "geometry": {"coordinates":[-87.992714,39.299113],"type":"Point"}
}