{
  "type": "Feature",
  "properties": {
    "iso:country":"US",
    "sg:address":"109 W Beardstown St",
    "sg:city":"Virginia",
    "sg:classifiers":[
        {
            "category":"Government",
            "subcategory":"Office",
            "type":"Public Place"
        }
    ],
    "sg:phone":"+1 217 452 3631",
    "sg:postcode":"62691",
    "sg:province":"IL",
    "sg:tags":[
        "village"
    ],
    "wof:name":"Virginia Relief Office",
    "wof:placetype":"venue"
},
  "geometry": {"coordinates":[-90.211911,39.950587],"type":"Point"}
}