{
  "type": "Feature",
  "properties": {
    "iso:country":"US",
    "sg:address":"910 W Van Buren St # 131",
    "sg:city":"Chicago",
    "sg:classifiers":[
        {
            "category":"Banks & Credit Unions",
            "subcategory":"Investment Brokerage",
            "type":"Services"
        },
        {
            "category":"Real Estate",
            "subcategory":"Developer",
            "type":"Services"
        }
    ],
    "sg:phone":"+1 312 371 3325",
    "sg:postcode":"60607",
    "sg:province":"IL",
    "sg:tags":[
        "investing"
    ],
    "wof:name":"Lighthouse Investment Group",
    "wof:placetype":"venue"
},
  "geometry": {"coordinates":[-87.64993,41.876629],"type":"Point"}
}