{
  "type": "Feature",
  "properties": {
    "addr:full":"9101 W Oaks Ave Des Plaines IL 60016",
    "addr:housenumber":"9101",
    "addr:postcode":"60016",
    "addr:street":"W Oaks Ave",
    "iso:country":"US",
    "sg:address":"9101 W Oaks Ave",
    "sg:city":"Des Plaines",
    "sg:classifiers":[
        {
            "category":"Professional",
            "subcategory":"Business Services",
            "type":"Services"
        }
    ],
    "sg:phone":"+1 847 390 7588",
    "sg:postcode":"60016",
    "sg:province":"IL",
    "wof:name":"Woodland Partnership LLC",
    "wof:placetype":"venue"
},
  "geometry": {"coordinates":[-87.85233100000001,42.04877],"type":"Point"}
}