{
  "type": "Feature",
  "properties": {
    "iso:country":"US",
    "sg:address":"16784 Head Ave",
    "sg:city":"Hazel Crest",
    "sg:classifiers":[
        {
            "category":"Professional",
            "subcategory":"Business Services",
            "type":"Services"
        }
    ],
    "sg:phone":"+1 708 335 1230",
    "sg:postcode":"60429",
    "sg:province":"IL",
    "wof:name":"Medical Equipment Consulting",
    "wof:placetype":"venue"
},
  "geometry": {"coordinates":[-87.670415,41.585514],"type":"Point"}
}