{
  "type": "Feature",
  "properties": {
    "iso:country":"US",
    "sg:address":"2416 Mannheim Rd",
    "sg:city":"Franklin Park",
    "sg:classifiers":[
        {
            "category":"Restaurant",
            "type":"Food & Drink"
        }
    ],
    "sg:phone":"+1 847 455 9999",
    "sg:postcode":"60131",
    "sg:province":"IL",
    "wof:name":"Chicago's Best Pizza & Pasta",
    "wof:placetype":"venue"
},
  "geometry": {"coordinates":[-87.884439,41.922626],"type":"Point"}
}