{
  "type": "Feature",
  "properties": {
    "iso:country":"US",
    "sg:address":"705 Strong Ave",
    "sg:city":"Collinsville",
    "sg:classifiers":[
        {
            "category":"Professional",
            "subcategory":"Computer Services",
            "type":"Services"
        }
    ],
    "sg:phone":"+1 618 345 9608",
    "sg:postcode":"62234",
    "sg:province":"IL",
    "wof:name":"Wang 11424",
    "wof:placetype":"venue"
},
  "geometry": {"coordinates":[-89.990984,38.678806],"type":"Point"}
}