{
  "type": "Feature",
  "properties": {
    "addr:full":"1223 Berry Ln Flossmoor IL 60422",
    "addr:housenumber":"1223",
    "addr:postcode":"60422",
    "addr:street":"Berry Ln",
    "iso:country":"US",
    "sg:address":"1223 Berry Ln",
    "sg:city":"Flossmoor",
    "sg:classifiers":[
        {
            "category":"Health Services",
            "subcategory":"Clinic",
            "type":"Services"
        }
    ],
    "sg:phone":"+1 708 799 3088",
    "sg:postcode":"60422",
    "sg:province":"IL",
    "wof:name":"L I Silverman & Associates",
    "wof:placetype":"venue"
},
  "geometry": {"coordinates":[-87.68626500000001,41.539315],"type":"Point"}
}