{
  "type": "Feature",
  "properties": {
    "iso:country":"US",
    "sg:address":"3141 W 63rd St",
    "sg:city":"Chicago",
    "sg:classifiers":[
        {
            "category":"Restaurant",
            "type":"Food & Drink"
        }
    ],
    "sg:phone":"+1 773 434 2927",
    "sg:postcode":"60629",
    "sg:province":"IL",
    "sg:tags":[
        "grill",
        "bar"
    ],
    "wof:name":"S & M Grill",
    "wof:placetype":"venue"
},
  "geometry": {"coordinates":[-87.70208100000001,41.778979],"type":"Point"}
}