{
  "type": "Feature",
  "properties": {
    "addr:full":"114 W Beardstown St Virginia IL 62691",
    "addr:housenumber":"114",
    "addr:postcode":"62691",
    "addr:street":"W Beardstown St",
    "iso:country":"US",
    "sg:address":"114 W Beardstown St",
    "sg:city":"Virginia",
    "sg:classifiers":[
        {
            "category":"Shopping",
            "type":"Retail Goods"
        }
    ],
    "sg:phone":"+1 217 452 3656",
    "sg:postcode":"62691",
    "sg:province":"IL",
    "sg:tags":[
        "art",
        "gallery",
        "dealer"
    ],
    "wof:name":"Tower Gallery",
    "wof:placetype":"venue"
},
  "geometry": {"coordinates":[-90.211883,39.950387],"type":"Point"}
}