{
  "type": "Feature",
  "properties": {
    "iso:country":"US",
    "sg:address":"440 Quadrangle Dr",
    "sg:city":"Bolingbrook",
    "sg:classifiers":[
        {
            "category":"Health Services",
            "subcategory":"Doctor",
            "type":"Services"
        }
    ],
    "sg:phone":"+1 630 226 5454",
    "sg:postcode":"60440",
    "sg:province":"IL",
    "sg:tags":[
        "physician",
        "surgeon"
    ],
    "wof:name":"Bolingbrook Family Health Care",
    "wof:placetype":"venue"
},
  "geometry": {"coordinates":[-88.075219,41.685789],"type":"Point"}
}