{
  "type": "Feature",
  "properties": {
    "addr:full":"1223 N Henderson St Galesburg IL 61401",
    "addr:housenumber":"1223",
    "addr:postcode":"61401",
    "addr:street":"N Henderson St",
    "iso:country":"US",
    "sg:address":"1223 N Henderson St",
    "sg:city":"Galesburg",
    "sg:classifiers":[
        {
            "category":"Autos & Motor Vehicles",
            "subcategory":"Auto Supplies",
            "type":"Retail Goods"
        },
        {
            "category":"Retail",
            "subcategory":"Auto Repair",
            "type":"Services"
        }
    ],
    "sg:phone":"+1 309 342 8174",
    "sg:postcode":"61401",
    "sg:province":"IL",
    "sg:tags":[
        "exhaust",
        "oil",
        "tire",
        "automobile",
        "system",
        "accessory",
        "lube",
        "part",
        "brake",
        "muffler"
    ],
    "sg:website":"http://www.midas.com",
    "wof:name":"Midas Auto Svc Experts",
    "wof:placetype":"venue"
},
  "geometry": {"coordinates":[-90.383741,40.932727],"type":"Point"}
}