{
  "type": "Feature",
  "properties": {
    "addr:full":"1800 Maple Ave Belvidere IL 61008",
    "addr:housenumber":"1800",
    "addr:postcode":"61008",
    "addr:street":"Maple Ave",
    "iso:country":"US",
    "sg:address":"1800 Maple Ave",
    "sg:city":"Belvidere",
    "sg:classifiers":[
        {
            "category":"Banks & Credit Unions",
            "subcategory":"Bank",
            "type":"Services"
        }
    ],
    "sg:phone":"+1 815 544 4300",
    "sg:postcode":"61008",
    "sg:province":"IL",
    "sg:tags":[
        "short",
        "institution",
        "business"
    ],
    "wof:name":"Sheffield Meadows",
    "wof:placetype":"venue"
},
  "geometry": {"coordinates":[-88.845429,42.243548],"type":"Point"}
}