{
  "type": "Feature",
  "properties": {
    "addr:full":"4 Lincoln Ave Charleston IL 61920",
    "addr:housenumber":"4",
    "addr:postcode":"61920",
    "addr:street":"Lincoln Ave",
    "iso:country":"US",
    "sg:address":"4 Lincoln Ave",
    "sg:city":"Charleston",
    "sg:classifiers":[
        {
            "category":"Restaurant",
            "type":"Food & Drink"
        }
    ],
    "sg:phone":"+1 217 345 1071",
    "sg:postcode":"61920",
    "sg:province":"IL",
    "wof:name":"Mc Hugh's Double Drive Thru",
    "wof:placetype":"venue"
},
  "geometry": {"coordinates":[-88.18165999999999,39.484344],"type":"Point"}
}