{
  "type": "Feature",
  "properties": {
    "addr:full":"1643 N Damen Ave Chicago IL 60647",
    "addr:housenumber":"1643",
    "addr:postcode":"60647",
    "addr:street":"N Damen Ave",
    "iso:country":"US",
    "sg:address":"1643 N Damen Ave",
    "sg:city":"Chicago",
    "sg:classifiers":[
        {
            "category":"Banks & Credit Unions",
            "subcategory":"Investment Brokerage",
            "type":"Services"
        }
    ],
    "sg:phone":"+1 773 394 1080",
    "sg:postcode":"60647",
    "sg:province":"IL",
    "sg:tags":[
        "stock"
    ],
    "wof:name":"Spears Inc",
    "wof:placetype":"venue"
},
  "geometry": {"coordinates":[-87.677498,41.911925],"type":"Point"}
}