{
  "type": "Feature",
  "properties": {
    "iso:country":"US",
    "sg:address":"2 Executive Ct",
    "sg:city":"South Barrington",
    "sg:classifiers":[
        {
            "category":"Health Services",
            "subcategory":"Doctor",
            "type":"Services"
        }
    ],
    "sg:phone":"+1 847 304 4442",
    "sg:postcode":"60010",
    "sg:province":"IL",
    "sg:tags":[
        "dentist"
    ],
    "wof:name":"South Barrington Dental Spa",
    "wof:placetype":"venue"
},
  "geometry": {"coordinates":[-88.14204100000001,42.079806],"type":"Point"}
}