{
  "type": "Feature",
  "properties": {
    "iso:country":"US",
    "sg:address":"22904 Valley Dr",
    "sg:city":"Richton Park",
    "sg:classifiers":[
        {
            "category":"Communications",
            "subcategory":"Radio Station",
            "type":"Services"
        }
    ],
    "sg:phone":"+1 708 283 9301",
    "sg:postcode":"60471",
    "sg:province":"IL",
    "sg:tags":[
        "broadcast"
    ],
    "wof:name":"Hiddne Mnna Otreach Ministries",
    "wof:placetype":"venue"
},
  "geometry": {"coordinates":[-87.73524999999999,41.471458],"type":"Point"}
}