{
  "type": "Feature",
  "properties": {
    "addr:full":"928 Wakley Dr Danville IL 61832",
    "addr:housenumber":"928",
    "addr:postcode":"61832",
    "addr:street":"Wakley Dr",
    "iso:country":"US",
    "sg:address":"928 Wakley Dr",
    "sg:city":"Danville",
    "sg:classifiers":[
        {
            "category":"Social Services",
            "subcategory":"Child Care",
            "type":"Services"
        }
    ],
    "sg:phone":"+1 217 446 5211",
    "sg:postcode":"61832",
    "sg:province":"IL",
    "wof:name":"Mama's Daycare",
    "wof:placetype":"venue"
},
  "geometry": {"coordinates":[-87.590322,40.141099],"type":"Point"}
}