{
  "type": "Feature",
  "properties": {
    "iso:country":"US",
    "sg:address":"6805 S Ridgeland Ave",
    "sg:city":"Chicago",
    "sg:classifiers":[
        {
            "category":"Freight",
            "type":"Transportation"
        }
    ],
    "sg:phone":"+1 773 493 3139",
    "sg:postcode":"60649",
    "sg:province":"IL",
    "wof:name":"Bills Friendly Transport",
    "wof:placetype":"venue"
},
  "geometry": {"coordinates":[-87.58248,41.769816],"type":"Point"}
}