{
  "type": "Feature",
  "properties": {
    "iso:country":"US",
    "sg:address":"1031 Cambridge Dr",
    "sg:city":"Grayslake",
    "sg:classifiers":[
        {
            "category":"Education",
            "subcategory":"Special Training",
            "type":"Public Place"
        }
    ],
    "sg:phone":"+1 847 543 4357",
    "sg:postcode":"60030",
    "sg:province":"IL",
    "sg:tags":[
        "school",
        "instruction",
        "art"
    ],
    "wof:name":"Neil Estrick Gallery",
    "wof:placetype":"venue"
},
  "geometry": {"coordinates":[-88.019852,42.345268],"type":"Point"}
}