{
  "type": "Feature",
  "properties": {
    "iso:country":"US",
    "sg:address":"2524 College Ave",
    "sg:city":"Alton",
    "sg:classifiers":[
        {
            "category":"Shopping",
            "subcategory":"Florist",
            "type":"Retail Goods"
        }
    ],
    "sg:phone":"+1 618 462 0668",
    "sg:postcode":"62002",
    "sg:province":"IL",
    "wof:name":"Lammers Floral",
    "wof:placetype":"venue"
},
  "geometry": {"coordinates":[-90.148205,38.90339],"type":"Point"}
}