{
  "type": "Feature",
  "properties": {
    "iso:country":"US",
    "sg:address":"1550 Stratford Rd",
    "sg:city":"Deerfield",
    "sg:classifiers":[
        {
            "category":"Professional",
            "subcategory":"Lawyer & Legal Services",
            "type":"Services"
        }
    ],
    "sg:phone":"+1 847 940 1713",
    "sg:postcode":"60015",
    "sg:province":"IL",
    "wof:name":"Grant R Niehus Ltd PC",
    "wof:placetype":"venue"
},
  "geometry": {"coordinates":[-87.858056,42.180845],"type":"Point"}
}