{
  "type": "Feature",
  "properties": {
    "iso:country":"US",
    "sg:address":"2700 S River Rd",
    "sg:city":"Des Plaines",
    "sg:classifiers":[
        {
            "category":"Professional",
            "subcategory":"Accounting & Tax Preparation",
            "type":"Services"
        }
    ],
    "sg:phone":"+1 847 297 3650",
    "sg:postcode":"60018",
    "sg:province":"IL",
    "sg:tags":[
        "accountant"
    ],
    "wof:name":"Choi Benjamin CPA",
    "wof:placetype":"venue"
},
  "geometry": {"coordinates":[-87.864826,42.002835],"type":"Point"}
}