{
  "type": "Feature",
  "properties": {
    "addr:full":"10301 96th Street Ct W Taylor Ridge IL 61284",
    "addr:housenumber":"10301",
    "addr:postcode":"61284",
    "addr:street":"96Th Street Ct W Taylor",
    "iso:country":"US",
    "sg:address":"10301 96th Street Ct W",
    "sg:city":"Taylor Ridge",
    "sg:classifiers":[
        {
            "category":"Building & Trades",
            "subcategory":"Construction",
            "type":"Services"
        }
    ],
    "sg:phone":"+1 309 798 5014",
    "sg:postcode":"61284",
    "sg:province":"IL",
    "sg:tags":[
        "waterproofing",
        "contractor"
    ],
    "wof:name":"Midwest Best Waterproofing",
    "wof:placetype":"venue"
},
  "geometry": {"coordinates":[-90.702158,41.419188],"type":"Point"}
}