{
  "type": "Feature",
  "properties": {
    "addr:full":"22803 N Berchtold Rd Chillicothe IL 61523",
    "addr:housenumber":"22803",
    "addr:postcode":"61523",
    "addr:street":"N Berchtold Rd",
    "iso:country":"US",
    "sg:address":"22803 N Berchtold Rd",
    "sg:city":"Chillicothe",
    "sg:classifiers":[
        {
            "category":"Building & Trades",
            "subcategory":"Electrical",
            "type":"Services"
        }
    ],
    "sg:phone":"+1 309 274 6070",
    "sg:postcode":"61523",
    "sg:province":"IL",
    "sg:tags":[
        "electrical",
        "contractor"
    ],
    "wof:name":"DLM Electric",
    "wof:placetype":"venue"
},
  "geometry": {"coordinates":[-89.535828,40.950732],"type":"Point"}
}