{
  "type": "Feature",
  "properties": {
    "addr:full":"23840 W Eames St Channahon IL 60410",
    "addr:housenumber":"23840",
    "addr:postcode":"60410",
    "addr:street":"W Eames St",
    "iso:country":"US",
    "sg:address":"23840 W Eames St",
    "sg:city":"Channahon",
    "sg:classifiers":[
        {
            "category":"Banks & Credit Unions",
            "subcategory":"Bank",
            "type":"Services"
        }
    ],
    "sg:phone":"+1 815 467 5321",
    "sg:postcode":"60410",
    "sg:province":"IL",
    "sg:website":"www.foundersbank.com",
    "wof:name":"Founders Bank",
    "wof:placetype":"venue"
},
  "geometry": {"coordinates":[-88.235497,41.423302],"type":"Point"}
}