{
  "type": "Feature",
  "properties": {
    "addr:full":"5310 W Devon Ave Chicago IL 60646",
    "addr:housenumber":"5310",
    "addr:postcode":"60646",
    "addr:street":"W Devon Ave",
    "iso:country":"US",
    "sg:address":"5310 W Devon Ave",
    "sg:city":"Chicago",
    "sg:phone":"+1 773 467 1954",
    "sg:postcode":"60646",
    "sg:province":"IL",
    "wof:name":"Moher",
    "wof:placetype":"venue"
},
  "geometry": {"coordinates":[-87.761109,41.997377],"type":"Point"}
}