{
  "type": "Feature",
  "properties": {
    "iso:country":"US",
    "sg:address":"269 E Chestnut St",
    "sg:city":"Canton",
    "sg:classifiers":[
        {
            "category":"Organizations",
            "subcategory":"Religious Organization",
            "type":"Services"
        }
    ],
    "sg:phone":"+1 309 647 4828",
    "sg:postcode":"61520",
    "sg:province":"IL",
    "sg:tags":[
        "churches-brethren"
    ],
    "wof:name":"Church Of The Brethren Inc",
    "wof:placetype":"venue"
},
  "geometry": {"coordinates":[-90.030776,40.557121],"type":"Point"}
}