{
  "type": "Feature",
  "properties": {
    "addr:full":"1231 Bishop St West Chicago IL 60185",
    "addr:housenumber":"1231",
    "addr:postcode":"60185",
    "addr:street":"Bishop St West",
    "iso:country":"US",
    "sg:address":"1231 Bishop St",
    "sg:city":"West Chicago",
    "sg:classifiers":[
        {
            "category":"Wholesale",
            "subcategory":"Painting Supplies",
            "type":"Manufacturing & Wholesale Goods"
        }
    ],
    "sg:phone":"+1 630 231 7784",
    "sg:postcode":"60185",
    "sg:province":"IL",
    "wof:name":"Murals By Steve",
    "wof:placetype":"venue"
},
  "geometry": {"coordinates":[-88.199656,41.864456],"type":"Point"}
}