{
  "type": "Feature",
  "properties": {
    "iso:country":"US",
    "sg:address":"15 Pershing Ave",
    "sg:city":"Lake In The Hls",
    "sg:classifiers":[
        {
            "category":"Autos & Motor Vehicles",
            "subcategory":"Auto Supplies",
            "type":"Retail Goods"
        }
    ],
    "sg:phone":"+1 847 458 4858",
    "sg:postcode":"60156",
    "sg:province":"IL",
    "sg:tags":[
        "equipment",
        "racing",
        "car",
        "automobile"
    ],
    "wof:name":"Nasty Performance",
    "wof:placetype":"venue"
},
  "geometry": {"coordinates":[-88.33259,42.189676],"type":"Point"}
}