{
  "type": "Feature",
  "properties": {
    "iso:country":"US",
    "sg:address":"310 Julia Pl",
    "sg:city":"Belleville",
    "sg:classifiers":[
        {
            "category":"Professional",
            "subcategory":"Lawyer & Legal Services",
            "type":"Services"
        }
    ],
    "sg:phone":"+1 618 397 0550",
    "sg:postcode":"62223",
    "sg:province":"IL",
    "wof:name":"Scherck Roger L Atty",
    "wof:placetype":"venue"
},
  "geometry": {"coordinates":[-90.066704,38.577],"type":"Point"}
}