{
  "type": "Feature",
  "properties": {
    "addr:full":"750 W Wellington Ave Chicago IL 60657",
    "addr:housenumber":"750",
    "addr:postcode":"60657",
    "addr:street":"W Wellington Ave",
    "iso:country":"US",
    "sg:address":"750 W Wellington Ave",
    "sg:city":"Chicago",
    "sg:classifiers":[
        {
            "category":"Cinema",
            "subcategory":"Movie Theater",
            "type":"Entertainment"
        }
    ],
    "sg:phone":"+1 312 335 8499",
    "sg:postcode":"60657",
    "sg:province":"IL",
    "wof:name":"Douglas Theater Corp",
    "wof:placetype":"venue"
},
  "geometry": {"coordinates":[-87.648689,41.936475],"type":"Point"}
}