{
  "type": "Feature",
  "properties": {
    "iso:country":"US",
    "sg:address":"1515 Clinton Pl",
    "sg:city":"River Forest",
    "sg:classifiers":[
        {
            "category":"Professional",
            "subcategory":"Business Services",
            "type":"Services"
        }
    ],
    "sg:phone":"+1 708 366 1211",
    "sg:postcode":"60305",
    "sg:province":"IL",
    "sg:tags":[
        "printing",
        "broker"
    ],
    "wof:name":"K Diversified Inc",
    "wof:placetype":"venue"
},
  "geometry": {"coordinates":[-87.808924,41.908072],"type":"Point"}
}