{
  "type": "Feature",
  "properties": {
    "iso:country":"US",
    "sg:address":"1144 Maple Ave",
    "sg:city":"Evanston",
    "sg:classifiers":[
        {
            "category":"Professional",
            "subcategory":"Management & Consulting",
            "type":"Services"
        }
    ],
    "sg:phone":"+1 847 475 8626",
    "sg:postcode":"60202",
    "sg:province":"IL",
    "wof:name":"B C G Trading",
    "wof:placetype":"venue"
},
  "geometry": {"coordinates":[-87.685213,42.038612],"type":"Point"}
}