{
  "type": "Feature",
  "properties": {
    "addr:full":"2806 S 4th St Rockford IL 61109",
    "addr:housenumber":"2806",
    "addr:postcode":"61109",
    "addr:street":"S 4Th St",
    "iso:country":"US",
    "sg:address":"2806 S 4th St",
    "sg:city":"Rockford",
    "sg:classifiers":[
        {
            "category":"Building & Trades",
            "subcategory":"Plumbing",
            "type":"Services"
        }
    ],
    "sg:phone":"+1 815 397 9368",
    "sg:postcode":"61109",
    "sg:province":"IL",
    "sg:tags":[
        "contractor"
    ],
    "wof:name":"Grant Park Plumbing",
    "wof:placetype":"venue"
},
  "geometry": {"coordinates":[-89.085521,42.232279],"type":"Point"}
}