{
  "type": "Feature",
  "properties": {
    "addr:full":"31074 N 3360 East Rd Chenoa IL 61726",
    "addr:housenumber":"31074;3360",
    "addr:postcode":"61726",
    "addr:street":"N;East Rd",
    "iso:country":"US",
    "sg:address":"31074 N 3360 East Rd",
    "sg:city":"Chenoa",
    "sg:classifiers":[
        {
            "category":"Home & Garden",
            "subcategory":"Garden Supply",
            "type":"Retail Goods"
        },
        {
            "category":"Retail",
            "subcategory":"Storage",
            "type":"Services"
        },
        {
            "category":"Farming",
            "subcategory":"Nursery",
            "type":"Manufacturing & Wholesale Goods"
        }
    ],
    "sg:phone":"+1 815 945 5113",
    "sg:postcode":"61726",
    "sg:province":"IL",
    "sg:tags":[
        "equipment",
        "self",
        "seed",
        "growers'",
        "bulb"
    ],
    "wof:name":"Atkins Seed Service",
    "wof:placetype":"venue"
},
  "geometry": {"coordinates":[-88.622744,40.743658],"type":"Point"}
}