{
  "type": "Feature",
  "properties": {
    "addr:full":"5901 Pine Hollow Rd Carpentersvle IL 60110",
    "addr:housenumber":"5901",
    "addr:postcode":"60110",
    "addr:street":"Pine Hollow Rd",
    "iso:country":"US",
    "sg:address":"5901 Pine Hollow Rd",
    "sg:city":"Carpentersvle",
    "sg:classifiers":[
        {
            "category":"Building & Trades",
            "subcategory":"Pest Control",
            "type":"Services"
        }
    ],
    "sg:phone":"+1 847 426 0601",
    "sg:postcode":"60110",
    "sg:province":"IL",
    "wof:name":"Strickall Pest Control",
    "wof:placetype":"venue"
},
  "geometry": {"coordinates":[-88.322197,42.132],"type":"Point"}
}