{
  "type": "Feature",
  "properties": {
    "iso:country":"US",
    "sg:address":"307 Canal St",
    "sg:city":"Lemont",
    "sg:classifiers":[
        {
            "category":"Retail",
            "subcategory":"Auto Rental",
            "type":"Services"
        }
    ],
    "sg:phone":"+1 630 257 6483",
    "sg:postcode":"60439",
    "sg:province":"IL",
    "sg:tags":[
        "automobile",
        "leasing"
    ],
    "wof:name":"Bev-Aire Leasing",
    "wof:placetype":"venue"
},
  "geometry": {"coordinates":[-87.998855,41.674861],"type":"Point"}
}