{
  "type": "Feature",
  "properties": {
    "iso:country":"US",
    "sg:address":"2115 N. Western Ave.",
    "sg:city":"Chicago",
    "sg:classifiers":[
        {
            "category":"Home & Garden",
            "subcategory":"Household Appliances",
            "type":"Retail Goods"
        }
    ],
    "sg:phone":"+1 773 384 4034",
    "sg:postcode":"60647",
    "sg:province":"IL",
    "wof:name":"Martinez Appliances",
    "wof:placetype":"venue"
},
  "geometry": {"coordinates":[-87.687156,41.920344],"type":"Point"}
}