{
  "type": "Feature",
  "properties": {
    "addr:full":"4710 W 63rd St Chicago IL 60629",
    "addr:housenumber":"4710",
    "addr:postcode":"60629",
    "addr:street":"W 63Rd St",
    "iso:country":"US",
    "sg:address":"4710 W 63rd St",
    "sg:city":"Chicago",
    "sg:classifiers":[
        {
            "category":"Autos & Motor Vehicles",
            "subcategory":"Fuel & Gas Station",
            "type":"Retail Goods"
        }
    ],
    "sg:phone":"+1 773 582 6557",
    "sg:postcode":"60629",
    "sg:province":"IL",
    "wof:name":"Midway Gas Mart",
    "wof:placetype":"venue"
},
  "geometry": {"coordinates":[-87.74050099999999,41.7785],"type":"Point"}
}