{
  "type": "Feature",
  "properties": {
    "iso:country":"US",
    "sg:address":"3536 S 6th St",
    "sg:city":"Quincy",
    "sg:classifiers":[
        {
            "category":"Government",
            "subcategory":"Office",
            "type":"Public Place"
        }
    ],
    "sg:phone":"+1   ",
    "sg:postcode":"62305",
    "sg:province":"IL",
    "sg:tags":[
        "engineering"
    ],
    "wof:name":"US Army Corps of Engineers",
    "wof:placetype":"venue"
},
  "geometry": {"coordinates":[-91.40620800000001,39.886863],"type":"Point"}
}