{
  "type": "Feature",
  "properties": {
    "iso:country":"US",
    "sg:address":"694 Grandview Ln",
    "sg:city":"Lake Forest",
    "sg:classifiers":[
        {
            "category":"Real Estate",
            "subcategory":"Real Estate Agent",
            "type":"Services"
        }
    ],
    "sg:phone":"+1 847 482 0178",
    "sg:postcode":"60045",
    "sg:province":"IL",
    "wof:name":"WD Schorsch Commercial RE",
    "wof:placetype":"venue"
},
  "geometry": {"coordinates":[-87.828986,42.224748],"type":"Point"}
}