{
  "type": "Feature",
  "properties": {
    "iso:country":"US",
    "sg:address":"318 N 30th Rd",
    "sg:city":"La Salle",
    "sg:classifiers":[
        {
            "category":"Manufacturing",
            "subcategory":"Chemicals & Compounds",
            "type":"Manufacturing & Wholesale Goods"
        }
    ],
    "sg:phone":"+1 815 223 2924",
    "sg:postcode":"61301",
    "sg:province":"IL",
    "wof:name":"Air Products Mfg Corp",
    "wof:placetype":"venue"
},
  "geometry": {"coordinates":[-89.099263,41.367743],"type":"Point"}
}