{
  "type": "Feature",
  "properties": {
    "iso:country":"US",
    "sg:address":"2114 E Grand Ave",
    "sg:city":"Lindenhurst",
    "sg:classifiers":[
        {
            "category":"Shopping",
            "type":"Retail Goods"
        }
    ],
    "sg:phone":"+1 847 356 5665",
    "sg:postcode":"60046",
    "sg:province":"IL",
    "sg:tags":[
        "picture",
        "frame"
    ],
    "wof:name":"Bob's Frame Shop",
    "wof:placetype":"venue"
},
  "geometry": {"coordinates":[-88.03148400000001,42.409082],"type":"Point"}
}