{
  "type": "Feature",
  "properties": {
    "iso:country":"US",
    "sg:address":"880 Melody Rd",
    "sg:city":"Lake Forest",
    "sg:classifiers":[
        {
            "category":"Banks & Credit Unions",
            "subcategory":"Investment Brokerage",
            "type":"Services"
        }
    ],
    "sg:phone":"+1 847 735 0054",
    "sg:postcode":"60045",
    "sg:province":"IL",
    "wof:name":"American Century Investments",
    "wof:placetype":"venue"
},
  "geometry": {"coordinates":[-87.868024,42.243016],"type":"Point"}
}