{
  "type": "Feature",
  "properties": {
    "iso:country":"US",
    "sg:address":"8751 W 50th St",
    "sg:city":"Chicago",
    "sg:classifiers":[
        {
            "category":"Food & Beverages",
            "subcategory":"Meat & Fish",
            "type":"Retail Goods"
        }
    ],
    "sg:phone":"+1 773 890 0600",
    "sg:postcode":"60525",
    "sg:province":"IL",
    "sg:tags":[
        "shop"
    ],
    "wof:name":"Capitol Wholesale Meats",
    "wof:placetype":"venue"
},
  "geometry": {"coordinates":[-87.746071,41.733517],"type":"Point"}
}