{
  "type": "Feature",
  "properties": {
    "addr:full":"405 N. Wabash Ave. Chicago IL 60611",
    "addr:housenumber":"405",
    "addr:postcode":"60611",
    "addr:street":"N. Wabash Ave.",
    "iso:country":"US",
    "sg:address":"405 N. Wabash Ave.",
    "sg:city":"Chicago",
    "sg:classifiers":[
        {
            "category":"Personal",
            "type":"Services"
        }
    ],
    "sg:phone":"+1 312 371 7872",
    "sg:postcode":"60611",
    "sg:province":"IL",
    "sg:tags":[
        "party",
        "planning",
        "event",
        "wedding"
    ],
    "wof:name":"Sabrina Hans Events",
    "wof:placetype":"venue"
},
  "geometry": {"coordinates":[-87.62653899999999,41.889943],"type":"Point"}
}