{
  "type": "Feature",
  "properties": {
    "addr:full":"1003 W Rte 30 Rock Falls IL 61071",
    "addr:housenumber":"1003",
    "addr:postcode":"61071",
    "addr:street":"W Rte 30",
    "iso:country":"US",
    "sg:address":"1003 W Rte 30",
    "sg:city":"Rock Falls",
    "sg:classifiers":[
        {
            "category":"Autos & Motor Vehicles",
            "subcategory":"Automobile Sales",
            "type":"Retail Goods"
        }
    ],
    "sg:phone":"+1   ",
    "sg:postcode":"61071",
    "sg:province":"IL",
    "sg:tags":[
        "dealer"
    ],
    "wof:name":"Instnt Car Credit",
    "wof:placetype":"venue"
},
  "geometry": {"coordinates":[-89.702412,41.769663],"type":"Point"}
}