{
  "type": "Feature",
  "properties": {
    "iso:country":"US",
    "sg:address":"508 S Oak Park Ave",
    "sg:city":"Oak Park",
    "sg:classifiers":[
        {
            "category":"Real Estate",
            "subcategory":"Real Estate Agent",
            "type":"Services"
        }
    ],
    "sg:phone":"+1 708 524 9300",
    "sg:postcode":"60304",
    "sg:province":"IL",
    "sg:tags":[
        "manager"
    ],
    "wof:name":"Becker Merrill Knoll & Assoc",
    "wof:placetype":"venue"
},
  "geometry": {"coordinates":[-87.794235,41.87928],"type":"Point"}
}