{
  "type": "Feature",
  "properties": {
    "iso:country":"US",
    "sg:address":"Harlem Irving Plaza 4104 N Harlem Ave",
    "sg:city":"Norridge",
    "sg:classifiers":[
        {
            "category":"Food & Beverages",
            "subcategory":"Specialty",
            "type":"Retail Goods"
        }
    ],
    "sg:phone":"+1 708 453 8778",
    "sg:postcode":"60706",
    "sg:province":"IL",
    "sg:website":"www.shopthehip.com/",
    "wof:name":"Pop A Corn",
    "wof:placetype":"venue"
},
  "geometry": {"coordinates":[-87.80771,41.956559],"type":"Point"}
}