{
  "type": "Feature",
  "properties": {
    "addr:full":"10112 Grand Ave Franklin Park IL 60131",
    "addr:housenumber":"10112",
    "addr:postcode":"60131",
    "addr:street":"Grand Ave",
    "iso:country":"US",
    "sg:address":"10112 Grand Ave",
    "sg:city":"Franklin Park",
    "sg:classifiers":[
        {
            "category":"Professional",
            "subcategory":"Accounting & Tax Preparation",
            "type":"Services"
        }
    ],
    "sg:phone":"+1 847 455 7828",
    "sg:postcode":"60131",
    "sg:province":"IL",
    "sg:tags":[
        "return",
        "filing"
    ],
    "wof:name":"H & R Block Tax Svc",
    "wof:placetype":"venue"
},
  "geometry": {"coordinates":[-87.87808699999999,41.930173],"type":"Point"}
}