{
  "type": "Feature",
  "properties": {
    "iso:country":"US",
    "sg:address":"3643 S Paulina St",
    "sg:city":"Chicago",
    "sg:classifiers":[
        {
            "category":"Professional",
            "subcategory":"Detective & Security Services",
            "type":"Services"
        }
    ],
    "sg:phone":"+1 773 893 1557",
    "sg:postcode":"60609",
    "sg:province":"IL",
    "sg:tags":[
        "information",
        "bureau"
    ],
    "wof:name":"Aaa Roadside Service Of Chicago",
    "wof:placetype":"venue"
},
  "geometry": {"coordinates":[-87.667884,41.827865],"type":"Point"}
}