{
  "type": "Feature",
  "properties": {
    "addr:full":"816 Shell Ct Schaumburg IL 60193",
    "addr:housenumber":"816",
    "addr:postcode":"60193",
    "addr:street":"Shell Ct",
    "iso:country":"US",
    "sg:address":"816 Shell Ct",
    "sg:city":"Schaumburg",
    "sg:classifiers":[
        {
            "category":"Building & Trades",
            "subcategory":"Electrical",
            "type":"Services"
        }
    ],
    "sg:phone":"+1 847 358 3000",
    "sg:postcode":"60193",
    "sg:province":"IL",
    "sg:tags":[
        "electrical",
        "electric",
        "contractor"
    ],
    "wof:name":"All Bright Electric Co Inc",
    "wof:placetype":"venue"
},
  "geometry": {"coordinates":[-88.100176,42.00529],"type":"Point"}
}