{
  "type": "Feature",
  "properties": {
    "addr:full":"5031 N Winchester Ave Chicago IL 60640",
    "addr:housenumber":"5031",
    "addr:postcode":"60640",
    "addr:street":"N Winchester Ave",
    "iso:country":"US",
    "sg:address":"5031 N Winchester Ave",
    "sg:city":"Chicago",
    "sg:classifiers":[
        {
            "category":"Building & Trades",
            "subcategory":"Plumbing",
            "type":"Services"
        }
    ],
    "sg:phone":"+1 773 561 4113",
    "sg:postcode":"60640",
    "sg:province":"IL",
    "sg:tags":[
        "conditioning",
        "contractor"
    ],
    "wof:name":"Vasiles Heating & Construction",
    "wof:placetype":"venue"
},
  "geometry": {"coordinates":[-87.677772,41.974648],"type":"Point"}
}