{
  "type": "Feature",
  "properties": {
    "iso:country":"US",
    "sg:address":"20459 Ela Rd",
    "sg:city":"Deer Park",
    "sg:classifiers":[
        {
            "category":"Shopping",
            "type":"Retail Goods"
        }
    ],
    "sg:phone":"+1 847 277 1495",
    "sg:postcode":"60010",
    "sg:province":"IL",
    "sg:tags":[
        "plant",
        "flower",
        "tree",
        "artificial"
    ],
    "wof:name":"Silkworx By Lori",
    "wof:placetype":"venue"
},
  "geometry": {"coordinates":[-88.101826,42.165928],"type":"Point"}
}