{
  "type": "Feature",
  "properties": {
    "addr:full":"415 S Randall Rd Algonquin IL 60102",
    "addr:housenumber":"415",
    "addr:postcode":"60102",
    "addr:street":"S Randall Rd",
    "iso:country":"US",
    "sg:address":"415 S Randall Rd",
    "sg:city":"Algonquin",
    "sg:classifiers":[
        {
            "category":"Restaurant",
            "type":"Food & Drink"
        }
    ],
    "sg:menulink":"http://www.allmenus.com/il/algonquin/199157-kfc---kentucky-fried-chicken/menu/",
    "sg:phone":"+1 847 854 7386",
    "sg:postcode":"60102",
    "sg:province":"IL",
    "sg:tags":[
        "american",
        "chicken"
    ],
    "wof:name":"KFC - Kentucky Fried Chicken",
    "wof:placetype":"venue"
},
  "geometry": {"coordinates":[-88.33528,42.170696],"type":"Point"}
}