{
  "type": "Feature",
  "properties": {
    "addr:full":"694 Essington Rd Joliet IL 60435",
    "addr:housenumber":"694",
    "addr:postcode":"60435",
    "addr:street":"Essington Rd",
    "iso:country":"US",
    "sg:address":"694 Essington Rd",
    "sg:city":"Joliet",
    "sg:classifiers":[
        {
            "category":"Building & Trades",
            "subcategory":"Plumbing",
            "type":"Services"
        }
    ],
    "sg:phone":"+1 815 730 0559",
    "sg:postcode":"60435",
    "sg:province":"IL",
    "sg:tags":[
        "contractor"
    ],
    "wof:name":"Work Conditioning Systems",
    "wof:placetype":"venue"
},
  "geometry": {"coordinates":[-88.160484,41.535365],"type":"Point"}
}