{
  "type": "Feature",
  "properties": {
    "addr:full":"316 Circle Ave Forest Park IL 60130",
    "addr:housenumber":"316",
    "addr:postcode":"60130",
    "addr:street":"Circle Ave",
    "iso:country":"US",
    "sg:address":"316 Circle Ave",
    "sg:city":"Forest Park",
    "sg:classifiers":[
        {
            "category":"Health Services",
            "subcategory":"Doctor",
            "type":"Services"
        }
    ],
    "sg:phone":"+1 708 366 0145",
    "sg:postcode":"60130",
    "sg:province":"IL",
    "wof:name":"Lin Shiann MD",
    "wof:placetype":"venue"
},
  "geometry": {"coordinates":[-87.80880000000001,41.8806],"type":"Point"}
}