{
  "type": "Feature",
  "properties": {
    "iso:country":"US",
    "sg:address":"7208 W College Dr",
    "sg:city":"Palos Heights",
    "sg:classifiers":[
        {
            "category":"Restaurant",
            "type":"Food & Drink"
        }
    ],
    "sg:phone":"+1 708 923 6467",
    "sg:postcode":"60463",
    "sg:province":"IL",
    "wof:name":"Dee-Ded Restaurant",
    "wof:placetype":"venue"
},
  "geometry": {"coordinates":[-87.797501,41.6754],"type":"Point"}
}