{
  "type": "Feature",
  "properties": {
    "addr:full":"51 S Spring St Elgin IL 60120",
    "addr:housenumber":"51",
    "addr:postcode":"60120",
    "addr:street":"S Spring St",
    "iso:country":"US",
    "sg:address":"51 S Spring St",
    "sg:city":"Elgin",
    "sg:classifiers":[
        {
            "category":"Organizations",
            "subcategory":"Membership Organization",
            "type":"Services"
        }
    ],
    "sg:phone":"+1 847 214 6910",
    "sg:postcode":"60120",
    "sg:province":"IL",
    "wof:name":"Youth Leadership Academy",
    "wof:placetype":"venue"
},
  "geometry": {"coordinates":[-88.282555,42.035399],"type":"Point"}
}