{
  "type": "Feature",
  "properties": {
    "addr:full":"5915 W Race Ave Chicago IL 60644",
    "addr:housenumber":"5915",
    "addr:postcode":"60644",
    "addr:street":"W Race Ave",
    "iso:country":"US",
    "sg:address":"5915 W Race Ave",
    "sg:city":"Chicago",
    "sg:classifiers":[
        {
            "category":"Professional",
            "subcategory":"Accounting & Tax Preparation",
            "type":"Services"
        }
    ],
    "sg:phone":"+1 773 379 0710",
    "sg:postcode":"60644",
    "sg:province":"IL",
    "wof:name":"Stewart Clarke CPA",
    "wof:placetype":"venue"
},
  "geometry": {"coordinates":[-87.774675,41.889945],"type":"Point"}
}