{
  "type": "Feature",
  "properties": {
    "iso:country":"US",
    "sg:address":"605 Abe St",
    "sg:city":"Joliet",
    "sg:classifiers":[
        {
            "category":"Building & Trades",
            "subcategory":"Construction",
            "type":"Services"
        }
    ],
    "sg:phone":"+1 815 722 7754",
    "sg:postcode":"60432",
    "sg:province":"IL",
    "sg:tags":[
        "house"
    ],
    "wof:name":"Martinez Construction",
    "wof:placetype":"venue"
},
  "geometry": {"coordinates":[-88.063059,41.536185],"type":"Point"}
}