{
  "type": "Feature",
  "properties": {
    "addr:full":"4201 Maple Ave Brookfield IL 60513",
    "addr:housenumber":"4201",
    "addr:postcode":"60513",
    "addr:street":"Maple Ave",
    "iso:country":"US",
    "sg:address":"4201 Maple Ave",
    "sg:city":"Brookfield",
    "sg:classifiers":[
        {
            "category":"Professional",
            "subcategory":"Computer Services",
            "type":"Services"
        }
    ],
    "sg:phone":"+1 708 485 2270",
    "sg:postcode":"60513",
    "sg:province":"IL",
    "sg:tags":[
        "datum"
    ],
    "wof:name":"Agoodwebcom",
    "wof:placetype":"venue"
},
  "geometry": {"coordinates":[-87.85122699999999,41.812722],"type":"Point"}
}