{
  "type": "Feature",
  "properties": {
    "addr:full":"79 Water St Park Forest IL 60466",
    "addr:housenumber":"79",
    "addr:postcode":"60466",
    "addr:street":"Water St",
    "iso:country":"US",
    "sg:address":"79 Water St",
    "sg:city":"Park Forest",
    "sg:classifiers":[
        {
            "category":"Professional",
            "subcategory":"Business Services",
            "type":"Services"
        }
    ],
    "sg:phone":"+1 708 747 8038",
    "sg:postcode":"60466",
    "sg:province":"IL",
    "wof:name":"Body By Design",
    "wof:placetype":"venue"
},
  "geometry": {"coordinates":[-87.68104099999999,41.493718],"type":"Point"}
}