{
  "type": "Feature",
  "properties": {
    "iso:country":"US",
    "sg:address":"728 Co Rd 1700 E",
    "sg:city":"Philo",
    "sg:classifiers":[
        {
            "category":"Real Estate",
            "subcategory":"Real Estate Operator",
            "type":"Services"
        }
    ],
    "sg:phone":"+1 217 684 2820",
    "sg:postcode":"61864",
    "sg:province":"IL",
    "sg:tags":[
        "property",
        "lessor"
    ],
    "wof:name":"Francis Lafenhagen",
    "wof:placetype":"venue"
},
  "geometry": {"coordinates":[-88.142228,39.985064],"type":"Point"}
}