{
  "type": "Feature",
  "properties": {
    "iso:country":"US",
    "sg:address":"300 W Adams St",
    "sg:city":"Chicago",
    "sg:classifiers":[
        {
            "category":"Health Services",
            "subcategory":"Doctor",
            "type":"Services"
        },
        {
            "category":"Social Services",
            "type":"Services"
        }
    ],
    "sg:phone":"+1 312 357 0022",
    "sg:postcode":"60606",
    "sg:province":"IL",
    "sg:tags":[
        "family",
        "psychologist",
        "individual",
        "marriage",
        "child",
        "counselor"
    ],
    "sg:website":"http://therapists.psychologytoday.com/rms/name/Alice_M_Bernstein_Chicago_Illinois_21789",
    "wof:name":"Bernstein Alice PhD",
    "wof:placetype":"venue"
},
  "geometry": {"coordinates":[-87.635231,41.879379],"type":"Point"}
}