{
  "type": "Feature",
  "properties": {
    "addr:full":"2001 Formosa Rd Troy IL 62294",
    "addr:housenumber":"2001",
    "addr:postcode":"62294",
    "addr:street":"Formosa Rd",
    "iso:country":"US",
    "sg:address":"2001 Formosa Rd",
    "sg:city":"Troy",
    "sg:classifiers":[
        {
            "category":"Bars & Pubs",
            "type":"Food & Drink"
        }
    ],
    "sg:menulink":"http://www.allmenus.com/il/jarvis/34334-cracker-barrel-old-country-store/menu/",
    "sg:phone":"+1 618 667 2021",
    "sg:postcode":"62294",
    "sg:province":"IL",
    "sg:tags":[
        "american",
        "southern"
    ],
    "wof:name":"Cracker Barrel Old Country Store",
    "wof:placetype":"venue"
},
  "geometry": {"coordinates":[-89.91519599999999,38.732839],"type":"Point"}
}