{
  "type": "Feature",
  "properties": {
    "iso:country":"US",
    "sg:address":"0S118 Winfield Rd",
    "sg:city":"Winfield",
    "sg:classifiers":[
        {
            "category":"Shopping",
            "subcategory":"Florist",
            "type":"Retail Goods"
        }
    ],
    "sg:phone":"+1 630 668 8460",
    "sg:postcode":"60190",
    "sg:province":"IL",
    "sg:website":"www.winfieldflowershoppe.com",
    "wof:name":"Winfield Flower Shoppe",
    "wof:placetype":"venue"
},
  "geometry": {"coordinates":[-88.15790200000001,41.869443],"type":"Point"}
}