{
  "type": "Feature",
  "properties": {
    "addr:full":"8401 W 131st St Orland Park IL 60462",
    "addr:housenumber":"8401",
    "addr:postcode":"60462",
    "addr:street":"W 131St St",
    "iso:country":"US",
    "sg:address":"8401 W 131st St",
    "sg:city":"Orland Park",
    "sg:classifiers":[
        {
            "category":"Manufacturing",
            "subcategory":"Toys & Sporting Goods",
            "type":"Manufacturing & Wholesale Goods"
        }
    ],
    "sg:phone":"+1 708 361 0352",
    "sg:postcode":"60462",
    "sg:province":"IL",
    "sg:tags":[
        "mfg"
    ],
    "wof:name":"Happywear",
    "wof:placetype":"venue"
},
  "geometry": {"coordinates":[-87.82445199999999,41.652924],"type":"Point"}
}