{
  "type": "Feature",
  "properties": {
    "iso:country":"US",
    "sg:address":"361 Torrence Ave",
    "sg:city":"Calumet City",
    "sg:classifiers":[
        {
            "category":"Social Services",
            "subcategory":"Child Care",
            "type":"Services"
        }
    ],
    "sg:phone":"+1 708 730 9553",
    "sg:postcode":"60409",
    "sg:province":"IL",
    "sg:tags":[
        "day"
    ],
    "wof:name":"Mansker's Loving Daycare",
    "wof:placetype":"venue"
},
  "geometry": {"coordinates":[-87.558999,41.627236],"type":"Point"}
}