{
  "type": "Feature",
  "properties": {
    "iso:country":"US",
    "sg:address":"134 Briarcliff Rd",
    "sg:city":"Montgomery",
    "sg:classifiers":[
        {
            "category":"Health Services",
            "subcategory":"Nursing And Care Facility",
            "type":"Services"
        },
        {
            "category":"Health Services",
            "subcategory":"Health Practitioner",
            "type":"Services"
        }
    ],
    "sg:phone":"+1 630 897 3668",
    "sg:postcode":"60538",
    "sg:province":"IL",
    "sg:tags":[
        "home",
        "eldercare-home"
    ],
    "wof:name":"Kathys Home Day Care",
    "wof:placetype":"venue"
},
  "geometry": {"coordinates":[-88.33215300000001,41.720181],"type":"Point"}
}