{
  "type": "Feature",
  "properties": {
    "iso:country":"US",
    "sg:address":"2861 Madison Ave",
    "sg:city":"Granite City",
    "sg:classifiers":[
        {
            "category":"Health Services",
            "subcategory":"Chiropractor",
            "type":"Services"
        }
    ],
    "sg:phone":"+1 618 877 4000",
    "sg:postcode":"62040",
    "sg:province":"IL",
    "sg:website":"www.brasfieldchiropractic.com",
    "wof:name":"Brasfield Chiropractic",
    "wof:placetype":"venue"
},
  "geometry": {"coordinates":[-90.128197,38.714298],"type":"Point"}
}