{
  "type": "Feature",
  "properties": {
    "iso:country":"US",
    "sg:address":"7315 N Alpine Rd",
    "sg:city":"Loves Park",
    "sg:classifiers":[
        {
            "category":"Autos & Motor Vehicles",
            "subcategory":"Auto Supplies",
            "type":"Retail Goods"
        },
        {
            "category":"Shopping",
            "subcategory":"Computers & Home Electronics",
            "type":"Retail Goods"
        }
    ],
    "sg:phone":"+1 815 636 2373",
    "sg:postcode":"61111",
    "sg:province":"IL",
    "sg:tags":[
        "automobile",
        "stereo",
        "radio"
    ],
    "wof:name":"Expert Electronics",
    "wof:placetype":"venue"
},
  "geometry": {"coordinates":[-89.028466,42.327277],"type":"Point"}
}