{
  "type": "Feature",
  "properties": {
    "iso:country":"US",
    "sg:address":"110 E Court St",
    "sg:city":"Fairmount",
    "sg:classifiers":[
        {
            "category":"Retail",
            "subcategory":"Funeral Services",
            "type":"Services"
        }
    ],
    "sg:phone":"+1 217 733 2171",
    "sg:postcode":"61841",
    "sg:province":"IL",
    "sg:tags":[
        "director"
    ],
    "wof:name":"Carrington Funeral Home",
    "wof:placetype":"venue"
},
  "geometry": {"coordinates":[-87.82933300000001,40.04648],"type":"Point"}
}