{
  "type": "Feature",
  "properties": {
    "iso:country":"US",
    "sg:address":"923 Coyote Ave",
    "sg:city":"Greenville",
    "sg:classifiers":[
        {
            "category":"Professional",
            "type":"Services"
        }
    ],
    "sg:phone":"+1 618 664 4306",
    "sg:postcode":"62246",
    "sg:province":"IL",
    "sg:tags":[
        "establishment"
    ],
    "wof:name":"Schaefer Construction",
    "wof:placetype":"venue"
},
  "geometry": {"coordinates":[-89.461815,38.915189],"type":"Point"}
}