{
  "type": "Feature",
  "properties": {
    "iso:country":"US",
    "sg:address":"2637 W Peterson Ave",
    "sg:city":"Chicago",
    "sg:classifiers":[
        {
            "category":"Professional",
            "subcategory":"Computer Services",
            "type":"Services"
        }
    ],
    "sg:phone":"+1 773 275 0392",
    "sg:postcode":"60659",
    "sg:province":"IL",
    "sg:tags":[
        "stereo",
        "installation"
    ],
    "wof:name":"R F Tech",
    "wof:placetype":"venue"
},
  "geometry": {"coordinates":[-87.69601400000001,41.990442],"type":"Point"}
}