{
  "type": "Feature",
  "properties": {
    "iso:country":"US",
    "sg:address":"7332 W 72nd St",
    "sg:city":"Bridgeview",
    "sg:classifiers":[
        {
            "category":"Personal",
            "type":"Services"
        }
    ],
    "sg:phone":"+1 708 458 6349",
    "sg:postcode":"60455",
    "sg:province":"IL",
    "wof:name":"Anthony Cole Corporation",
    "wof:placetype":"venue"
},
  "geometry": {"coordinates":[-87.804951,41.760832],"type":"Point"}
}