{
  "type": "Feature",
  "properties": {
    "iso:country":"US",
    "sg:address":"565 Powell Ave",
    "sg:city":"Waukegan",
    "sg:classifiers":[
        {
            "category":"Organizations",
            "subcategory":"Religious Organization",
            "type":"Services"
        }
    ],
    "sg:phone":"+1 847 244 4400",
    "sg:postcode":"60085",
    "sg:province":"IL",
    "sg:tags":[
        "church"
    ],
    "wof:name":"Greater Faith Baptist Church",
    "wof:placetype":"venue"
},
  "geometry": {"coordinates":[-87.841028,42.351583],"type":"Point"}
}