{
  "type": "Feature",
  "properties": {
    "iso:country":"US",
    "sg:address":"2535 N Lincoln Ave",
    "sg:city":"Chicago",
    "sg:classifiers":[
        {
            "category":"Personal",
            "subcategory":"Beauty Salon",
            "type":"Services"
        }
    ],
    "sg:phone":"+1 773 327 2622",
    "sg:postcode":"60614",
    "sg:province":"IL",
    "sg:tags":[
        "hair"
    ],
    "sg:website":"salonuchicago.com/",
    "wof:name":"Salon U",
    "wof:placetype":"venue"
},
  "geometry": {"coordinates":[-87.652322,41.928036],"type":"Point"}
}