{
  "type": "Feature",
  "properties": {
    "addr:full":"943 Edgemere Ct Evanston IL 60202",
    "addr:housenumber":"943",
    "addr:postcode":"60202",
    "addr:street":"Edgemere Ct",
    "iso:country":"US",
    "sg:address":"943 Edgemere Ct",
    "sg:city":"Evanston",
    "sg:classifiers":[
        {
            "category":"Real Estate",
            "subcategory":"Real Estate Agent",
            "type":"Services"
        }
    ],
    "sg:phone":"+1 847 328 0683",
    "sg:postcode":"60202",
    "sg:province":"IL",
    "wof:name":"William & Mary Anne McGrath",
    "wof:placetype":"venue"
},
  "geometry": {"coordinates":[-87.670512,42.034944],"type":"Point"}
}