{
  "type": "Feature",
  "properties": {
    "iso:country":"US",
    "sg:address":"301 W Lake St",
    "sg:city":"Chicago",
    "sg:classifiers":[
        {
            "category":"Autos & Motor Vehicles",
            "subcategory":"Fuel & Gas Station",
            "type":"Retail Goods"
        },
        {
            "category":"Food & Beverages",
            "subcategory":"Groceries & Convenience Stores",
            "type":"Retail Goods"
        }
    ],
    "sg:phone":"+1 312 263 3430",
    "sg:postcode":"60606",
    "sg:province":"IL",
    "wof:name":"J J Peppers",
    "wof:placetype":"venue"
},
  "geometry": {"coordinates":[-87.635498,41.885601],"type":"Point"}
}