{
  "type": "Feature",
  "properties": {
    "iso:country":"US",
    "sg:address":"440 W Hickory St",
    "sg:city":"Canton",
    "sg:classifiers":[
        {
            "category":"Autos & Motor Vehicles",
            "subcategory":"Automobile Sales",
            "type":"Retail Goods"
        }
    ],
    "sg:phone":"+1   ",
    "sg:postcode":"61520",
    "sg:province":"IL",
    "sg:tags":[
        "car",
        "used"
    ],
    "wof:name":"Joseph Martin Long",
    "wof:placetype":"venue"
},
  "geometry": {"coordinates":[-90.042396,40.548376],"type":"Point"}
}