{
  "type": "Feature",
  "properties": {
    "iso:country":"US",
    "sg:address":"1 Fox Run Dr",
    "sg:city":"Altamont",
    "sg:classifiers":[
        {
            "category":"Manufacturing",
            "subcategory":"Buildings",
            "type":"Manufacturing & Wholesale Goods"
        },
        {
            "category":"Building & Trades",
            "subcategory":"Construction",
            "type":"Services"
        }
    ],
    "sg:phone":"+1 618 483 5001",
    "sg:postcode":"62411",
    "sg:province":"IL",
    "sg:tags":[
        "home",
        "builder",
        "contractor"
    ],
    "wof:name":"Altamont Affordable Homes, Inc",
    "wof:placetype":"venue"
},
  "geometry": {"coordinates":[-88.731033,39.060478],"type":"Point"}
}