{
  "type": "Feature",
  "properties": {
    "iso:country":"US",
    "sg:address":"27963 W Industrial Ave",
    "sg:city":"Lake Barrington",
    "sg:classifiers":[
        {
            "category":"Building & Trades",
            "subcategory":"Construction",
            "type":"Services"
        }
    ],
    "sg:phone":"+1 847 381 4900",
    "sg:postcode":"60010",
    "sg:province":"IL",
    "sg:tags":[
        "contractor"
    ],
    "wof:name":"Suburban Iron Works Inc",
    "wof:placetype":"venue"
},
  "geometry": {"coordinates":[-88.179283,42.184242],"type":"Point"}
}