{
  "type": "Feature",
  "properties": {
    "iso:country":"US",
    "sg:address":"11 Galligan Rd",
    "sg:city":"Gilberts",
    "sg:classifiers":[
        {
            "category":"Restaurant",
            "type":"Food & Drink"
        }
    ],
    "sg:phone":"+1 847 836 7272",
    "sg:postcode":"60136",
    "sg:province":"IL",
    "wof:name":"Cruisin",
    "wof:placetype":"venue"
},
  "geometry": {"coordinates":[-88.37260499999999,42.103375],"type":"Point"}
}