{
  "type": "Feature",
  "properties": {
    "iso:country":"US",
    "sg:address":"3250 N Kedzie Avenue",
    "sg:city":"Chicago",
    "sg:classifiers":[
        {
            "category":"Home & Garden",
            "subcategory":"Building Materials",
            "type":"Retail Goods"
        }
    ],
    "sg:phone":"+1 773 509 6700",
    "sg:postcode":"60618",
    "sg:province":"IL",
    "sg:tags":[
        "supply"
    ],
    "sg:website":"www.leelumber.com",
    "wof:name":"Lee Lumber",
    "wof:placetype":"venue"
},
  "geometry": {"coordinates":[-87.707677,41.94061],"type":"Point"}
}