{
  "type": "Feature",
  "properties": {
    "iso:country":"US",
    "sg:address":"1100 10th St",
    "sg:city":"Moline",
    "sg:classifiers":[
        {
            "category":"Insurance",
            "subcategory":"Insurance Agent",
            "type":"Services"
        }
    ],
    "sg:phone":"+1 309 757 0062",
    "sg:postcode":"61265",
    "sg:province":"IL",
    "wof:name":"Stokeld & Company",
    "wof:placetype":"venue"
},
  "geometry": {"coordinates":[-90.52368199999999,41.500457],"type":"Point"}
}