{
  "type": "Feature",
  "properties": {
    "addr:full":"2435 Washington St Waukegan IL 60085",
    "addr:housenumber":"2435",
    "addr:postcode":"60085",
    "addr:street":"Washington St",
    "iso:country":"US",
    "sg:address":"2435 Washington St",
    "sg:city":"Waukegan",
    "sg:classifiers":[
        {
            "category":"Food & Beverages",
            "subcategory":"Groceries & Convenience Stores",
            "type":"Retail Goods"
        }
    ],
    "sg:phone":"+1 847 244 7090",
    "sg:postcode":"60085",
    "sg:province":"IL",
    "wof:name":"7-Eleven",
    "wof:placetype":"venue"
},
  "geometry": {"coordinates":[-87.863924,42.359403],"type":"Point"}
}