{
  "type": "Feature",
  "properties": {
    "iso:country":"US",
    "sg:address":"13119 Western Ave",
    "sg:city":"Blue Island",
    "sg:classifiers":[
        {
            "category":"Personal",
            "subcategory":"Shoe Repair & Shine",
            "type":"Services"
        }
    ],
    "sg:phone":"+1 708 396 1316",
    "sg:postcode":"60406",
    "sg:province":"IL",
    "sg:tags":[
        "parlor"
    ],
    "wof:name":"Marios Shoe Repair",
    "wof:placetype":"venue"
},
  "geometry": {"coordinates":[-87.67998,41.65507],"type":"Point"}
}