{
  "type": "Feature",
  "properties": {
    "iso:country":"US",
    "sg:address":"167 Cherrywood Ct",
    "sg:city":"Romeoville",
    "sg:classifiers":[
        {
            "category":"Professional",
            "subcategory":"Art Services",
            "type":"Services"
        }
    ],
    "sg:phone":"+1 815 886 7954",
    "sg:postcode":"60446",
    "sg:province":"IL",
    "sg:tags":[
        "commercial",
        "design"
    ],
    "wof:name":"Ecm Advertising",
    "wof:placetype":"venue"
},
  "geometry": {"coordinates":[-88.148543,41.617669],"type":"Point"}
}