{
  "type": "Feature",
  "properties": {
    "addr:full":"14544 John Humphrey Dr Orland Park IL 60462",
    "addr:housenumber":"14544",
    "addr:postcode":"60462",
    "addr:street":"John Humphrey Dr",
    "iso:country":"US",
    "sg:address":"14544 John Humphrey Dr",
    "sg:city":"Orland Park",
    "sg:classifiers":[
        {
            "category":"Health Services",
            "subcategory":"Doctor",
            "type":"Services"
        }
    ],
    "sg:phone":"+1 708 460 7990",
    "sg:postcode":"60462",
    "sg:province":"IL",
    "sg:tags":[
        "medical"
    ],
    "wof:name":"M Doshi MD",
    "wof:placetype":"venue"
},
  "geometry": {"coordinates":[-87.85040100000001,41.62732],"type":"Point"}
}