{
  "type": "Feature",
  "properties": {
    "iso:country":"US",
    "sg:address":"640 E Fairchild St",
    "sg:city":"Danville",
    "sg:classifiers":[
        {
            "category":"Manufacturing",
            "subcategory":"Building Materials",
            "type":"Manufacturing & Wholesale Goods"
        }
    ],
    "sg:phone":"+1 217 446 8443",
    "sg:postcode":"61832",
    "sg:province":"IL",
    "sg:tags":[
        "mfg"
    ],
    "wof:name":"T H Snyder Company",
    "wof:placetype":"venue"
},
  "geometry": {"coordinates":[-87.61983,40.13889],"type":"Point"}
}