{
  "type": "Feature",
  "properties": {
    "iso:country":"US",
    "sg:address":"3419 W Fullerton Ave",
    "sg:city":"Chicago",
    "sg:classifiers":[
        {
            "category":"Shopping",
            "subcategory":"Clothing, Apparel, & Fashions",
            "type":"Retail Goods"
        }
    ],
    "sg:phone":"+1   ",
    "sg:postcode":"60647",
    "sg:province":"IL",
    "sg:tags":[
        "family",
        "store"
    ],
    "wof:name":"Florys Fashion",
    "wof:placetype":"venue"
},
  "geometry": {"coordinates":[-87.712248,41.924585],"type":"Point"}
}