{
  "type": "Feature",
  "properties": {
    "iso:country":"US",
    "sg:address":"107 S Walnut St",
    "sg:city":"Calhoun",
    "sg:classifiers":[
        {
            "category":"Building & Trades",
            "subcategory":"Cleaning & Sanitation",
            "type":"Services"
        }
    ],
    "sg:phone":"+1 618 395 8192",
    "sg:postcode":"62419",
    "sg:province":"IL",
    "sg:tags":[
        "janitor"
    ],
    "wof:name":"Dave's Janitorial Svc",
    "wof:placetype":"venue"
},
  "geometry": {"coordinates":[-88.045316,38.648786],"type":"Point"}
}