{
  "type": "Feature",
  "properties": {
    "addr:full":"40821 N Ridge Cir Antioch IL 60002",
    "addr:housenumber":"40821",
    "addr:postcode":"60002",
    "addr:street":"N Ridge Cir",
    "iso:country":"US",
    "sg:address":"40821 N Ridge Cir",
    "sg:city":"Antioch",
    "sg:classifiers":[
        {
            "category":"Building & Trades",
            "subcategory":"Cleaning & Sanitation",
            "type":"Services"
        }
    ],
    "sg:phone":"+1 847 395 4897",
    "sg:postcode":"60002",
    "sg:province":"IL",
    "sg:tags":[
        "maintenance"
    ],
    "wof:name":"Thomas Cleaning Inc",
    "wof:placetype":"venue"
},
  "geometry": {"coordinates":[-88.06744999999999,42.455901],"type":"Point"}
}