{
  "type": "Feature",
  "properties": {
    "addr:full":"2506 N California Ave Chicago IL 60647",
    "addr:housenumber":"2506",
    "addr:postcode":"60647",
    "addr:street":"N California Ave",
    "iso:country":"US",
    "sg:address":"2506 N California Ave",
    "sg:city":"Chicago",
    "sg:classifiers":[
        {
            "category":"Shopping",
            "subcategory":"Used Merchandise",
            "type":"Retail Goods"
        }
    ],
    "sg:phone":"+1 773 384 8427",
    "sg:postcode":"60647",
    "sg:province":"IL",
    "sg:tags":[
        "vintage",
        "consignment"
    ],
    "sg:website":"www.atouchofvintage.com",
    "wof:name":"A Touch of Vintage",
    "wof:placetype":"venue"
},
  "geometry": {"coordinates":[-87.697512,41.927651],"type":"Point"}
}