{
  "type": "Feature",
  "properties": {
    "iso:country":"US",
    "sg:address":"2112 25th Ave",
    "sg:city":"Rock Island",
    "sg:classifiers":[
        {
            "category":"Government",
            "subcategory":"Office",
            "type":"Public Place"
        }
    ],
    "sg:phone":"+1   ",
    "sg:postcode":"61201",
    "sg:province":"IL",
    "sg:tags":[
        "administrative",
        "program",
        "health"
    ],
    "wof:name":"Healthy Moms & Healthy Kids",
    "wof:placetype":"venue"
},
  "geometry": {"coordinates":[-90.572246,41.485555],"type":"Point"}
}