{
  "type": "Feature",
  "properties": {
    "iso:country":"US",
    "sg:address":"1019 S 59th St",
    "sg:city":"Belleville",
    "sg:classifiers":[
        {
            "category":"Travel",
            "subcategory":"Hotels & Motels",
            "type":"Entertainment"
        }
    ],
    "sg:phone":"+1 618 234 0784",
    "sg:postcode":"62223",
    "sg:province":"IL",
    "sg:tags":[
        "unit",
        "three",
        "w",
        "operates"
    ],
    "wof:name":"Shaw Apartment Motel",
    "wof:placetype":"venue"
},
  "geometry": {"coordinates":[-90.036182,38.53504],"type":"Point"}
}