{
  "type": "Feature",
  "properties": {
    "iso:country":"US",
    "sg:address":"6302 North Rd",
    "sg:city":"Coffeen",
    "sg:classifiers":[
        {
            "category":"Farming",
            "subcategory":"Livestock Farm",
            "type":"Manufacturing & Wholesale Goods"
        },
        {
            "category":"Arena",
            "subcategory":"Horse Racetrack",
            "type":"Entertainment"
        }
    ],
    "sg:phone":"+1 217 534 6058",
    "sg:postcode":"62017",
    "sg:province":"IL",
    "sg:tags":[
        "breeder"
    ],
    "wof:name":"Simburger Farms",
    "wof:placetype":"venue"
},
  "geometry": {"coordinates":[-89.39071800000001,39.096885],"type":"Point"}
}