{
  "type": "Feature",
  "properties": {
    "addr:full":"535 N Michigan Ave # 3016 Chicago IL 60611",
    "addr:housenumber":"535",
    "addr:postcode":"60611",
    "addr:street":"N Michigan Ave # 3016",
    "iso:country":"US",
    "sg:address":"535 N Michigan Ave # 3016",
    "sg:city":"Chicago",
    "sg:classifiers":[
        {
            "category":"Health Services",
            "subcategory":"Chiropractor",
            "type":"Services"
        }
    ],
    "sg:phone":"+1 312 828 0046",
    "sg:postcode":"60611",
    "sg:province":"IL",
    "sg:tags":[
        "chiropractic"
    ],
    "wof:name":"Kenneth F Bennett Phd",
    "wof:placetype":"venue"
},
  "geometry": {"coordinates":[-87.624161,41.891978],"type":"Point"}
}