{
  "type": "Feature",
  "properties": {
    "iso:country":"US",
    "sg:address":"520 W 5th Ave",
    "sg:city":"Naperville",
    "sg:classifiers":[
        {
            "category":"Professional",
            "type":"Services"
        },
        {
            "category":"Industrial Area",
            "type":"Public Place"
        },
        {
            "category":"Personal",
            "subcategory":"Day Spa",
            "type":"Services"
        },
        {
            "category":"Sports & Exercise",
            "subcategory":"Swimming Pool",
            "type":"Entertainment"
        }
    ],
    "sg:phone":"+1 630 305 9942",
    "sg:postcode":"60563",
    "sg:province":"IL",
    "sg:tags":[
        "repair",
        "tubs-rentals",
        "tubs-repair",
        "hot",
        "tubs-wholesale",
        "tub",
        "manufacturer"
    ],
    "wof:name":"Turbo Tubs of Chicago",
    "wof:placetype":"venue"
},
  "geometry": {"coordinates":[-88.156829,41.780929],"type":"Point"}
}