{
  "type": "Feature",
  "properties": {
    "iso:country":"US",
    "sg:address":"1203 W Charles St",
    "sg:city":"Champaign",
    "sg:classifiers":[
        {
            "category":"Professional",
            "subcategory":"Lawyer & Legal Services",
            "type":"Services"
        }
    ],
    "sg:phone":"+1 217 356 5703",
    "sg:postcode":"61821",
    "sg:province":"IL",
    "wof:name":"William L Hatch",
    "wof:placetype":"venue"
},
  "geometry": {"coordinates":[-88.267151,40.106303],"type":"Point"}
}