{
  "type": "Feature",
  "properties": {
    "addr:full":"122 Boulder Dr Gridley IL 61744",
    "addr:housenumber":"122",
    "addr:postcode":"61744",
    "addr:street":"Boulder Dr",
    "iso:country":"US",
    "sg:address":"122 Boulder Dr",
    "sg:city":"Gridley",
    "sg:classifiers":[
        {
            "category":"Farming",
            "subcategory":"Farm",
            "type":"Manufacturing & Wholesale Goods"
        }
    ],
    "sg:phone":"+1 309 747 2732",
    "sg:postcode":"61744",
    "sg:province":"IL",
    "sg:tags":[
        "crop",
        "general"
    ],
    "wof:name":"David Zehr",
    "wof:placetype":"venue"
},
  "geometry": {"coordinates":[-88.88484699999999,40.748064],"type":"Point"}
}