{
  "type": "Feature",
  "properties": {
    "iso:country":"US",
    "sg:address":"1814 Colfax St",
    "sg:city":"Evanston",
    "sg:classifiers":[
        {
            "category":"Building & Trades",
            "subcategory":"Landscaping Services",
            "type":"Services"
        }
    ],
    "sg:phone":"+1 847 328 6069",
    "sg:postcode":"60201",
    "sg:province":"IL",
    "sg:tags":[
        "lawn",
        "maintenance"
    ],
    "wof:name":"Four Seasons Lawn Care & Maint",
    "wof:placetype":"venue"
},
  "geometry": {"coordinates":[-87.698166,42.060848],"type":"Point"}
}