{
  "type": "Feature",
  "properties": {
    "addr:full":"1200 McGrath Ave Effingham IL 62401",
    "addr:housenumber":"1200",
    "addr:postcode":"62401",
    "addr:street":"Mcgrath Ave",
    "iso:country":"US",
    "sg:address":"1200 McGrath Ave",
    "sg:city":"Effingham",
    "sg:classifiers":[
        {
            "category":"Manufacturing",
            "subcategory":"Rubber & Plastics",
            "type":"Manufacturing & Wholesale Goods"
        }
    ],
    "sg:phone":"+1 217 342 9600",
    "sg:postcode":"62401",
    "sg:province":"IL",
    "sg:tags":[
        "mfr",
        "beverage",
        "bottle"
    ],
    "wof:name":"Southeastern Container Inc",
    "wof:placetype":"venue"
},
  "geometry": {"coordinates":[-88.558066,39.100252],"type":"Point"}
}