{
  "type": "Feature",
  "properties": {
    "iso:country":"US",
    "sg:address":"135 E Van Buren St",
    "sg:city":"Joliet",
    "sg:classifiers":[
        {
            "category":"Retail",
            "subcategory":"Repair Shop",
            "type":"Services"
        }
    ],
    "sg:phone":"+1 815 740 1719",
    "sg:postcode":"60432",
    "sg:province":"IL",
    "sg:tags":[
        "pipe",
        "fitting",
        "boiler"
    ],
    "wof:name":"Joliet Boiler",
    "wof:placetype":"venue"
},
  "geometry": {"coordinates":[-88.076029,41.526087],"type":"Point"}
}