{
  "type": "Feature",
  "properties": {
    "iso:country":"US",
    "sg:address":"211 N Oak Park Ave",
    "sg:city":"Oak Park",
    "sg:classifiers":[
        {
            "category":"Travel",
            "subcategory":"Hotels & Motels",
            "type":"Entertainment"
        },
        {
            "category":"Travel",
            "subcategory":"Bed & Breakfast",
            "type":"Entertainment"
        }
    ],
    "sg:phone":"+1 708 383 4800",
    "sg:postcode":"60302",
    "sg:province":"IL",
    "sg:website":"www.writeinn.com/",
    "wof:name":"The Write Inn",
    "wof:placetype":"venue"
},
  "geometry": {"coordinates":[-87.794403,41.890202],"type":"Point"}
}