{
  "type": "Feature",
  "properties": {
    "addr:full":"213 N Racine 2nd Floor Chicago IL 60614",
    "addr:housenumber":"213;2nd floor",
    "addr:postcode":"60614",
    "addr:street":"N Racine",
    "iso:country":"US",
    "sg:address":"213 N Racine 2nd Floor",
    "sg:city":"Chicago",
    "sg:classifiers":[
        {
            "category":"Professional",
            "subcategory":"Computer Services",
            "type":"Services"
        }
    ],
    "sg:phone":"+1 312 566 8122",
    "sg:postcode":"60614",
    "sg:province":"IL",
    "sg:tags":[
        "dogs",
        "pets",
        "coupons",
        "dog",
        "cat",
        "discount",
        "deal",
        "social-commerce"
    ],
    "sg:website":"http://www.doggyloot.com",
    "wof:name":"doggyloot",
    "wof:placetype":"venue"
},
  "geometry": {"coordinates":[-87.658219,41.918034],"type":"Point"}
}