{
  "type": "Feature",
  "properties": {
    "addr:full":"25487 Marilyn Ln Hawthorn Woods IL 60047",
    "addr:housenumber":"25487",
    "addr:postcode":"60047",
    "addr:street":"Marilyn Ln",
    "iso:country":"US",
    "sg:address":"25487 Marilyn Ln",
    "sg:city":"Hawthorn Woods",
    "sg:classifiers":[
        {
            "category":"Building & Trades",
            "subcategory":"Construction",
            "type":"Services"
        }
    ],
    "sg:phone":"+1 847 726 0094",
    "sg:postcode":"60047",
    "sg:province":"IL",
    "sg:tags":[
        "painter"
    ],
    "wof:name":"Northlake Painting & Drywall",
    "wof:placetype":"venue"
},
  "geometry": {"coordinates":[-88.060925,42.2336],"type":"Point"}
}