{
  "type": "Feature",
  "properties": {
    "iso:country":"US",
    "sg:address":"3209 N Lakewood Ave",
    "sg:city":"Chicago",
    "sg:classifiers":[
        {
            "category":"Health Services",
            "subcategory":"Hospital",
            "type":"Services"
        },
        {
            "category":"Building & Trades",
            "subcategory":"Equipment Rental",
            "type":"Services"
        }
    ],
    "sg:phone":"+1 773 388 1206",
    "sg:postcode":"60657",
    "sg:province":"IL",
    "sg:tags":[
        "supplies-renting",
        "wheelchairs-rental",
        "supply"
    ],
    "wof:name":"Global Medical Products",
    "wof:placetype":"venue"
},
  "geometry": {"coordinates":[-87.66136400000001,41.940013],"type":"Point"}
}