{
  "type": "Feature",
  "properties": {
    "iso:country":"US",
    "sg:address":"4600 Memorial Dr",
    "sg:city":"Belleville",
    "sg:classifiers":[
        {
            "category":"Health Services",
            "subcategory":"Doctor",
            "type":"Services"
        }
    ],
    "sg:phone":"+1 618 234 9884",
    "sg:postcode":"62226",
    "sg:province":"IL",
    "sg:tags":[
        "medical"
    ],
    "wof:name":"Othropedics and Spt Medicine",
    "wof:placetype":"venue"
},
  "geometry": {"coordinates":[-90.020666,38.548827],"type":"Point"}
}