{
  "type": "Feature",
  "properties": {
    "addr:full":"213 Bonnie Brae Ave Elmhurst IL 60126",
    "addr:housenumber":"213",
    "addr:postcode":"60126",
    "addr:street":"Bonnie Brae Ave",
    "iso:country":"US",
    "sg:address":"213 Bonnie Brae Ave",
    "sg:city":"Elmhurst",
    "sg:classifiers":[
        {
            "category":"Recreation",
            "type":"Entertainment"
        }
    ],
    "sg:phone":"+1 630 833 7975",
    "sg:postcode":"60126",
    "sg:province":"IL",
    "wof:name":"Nice Putt",
    "wof:placetype":"venue"
},
  "geometry": {"coordinates":[-87.963324,41.902408],"type":"Point"}
}