{
  "type": "Feature",
  "properties": {
    "addr:full":"14623 Dante Ave Dolton IL 60419",
    "addr:postcode":"14623;60419",
    "addr:street":"Dante Ave",
    "iso:country":"US",
    "sg:address":"14623 Dante Ave",
    "sg:city":"Dolton",
    "sg:classifiers":[
        {
            "category":"Real Estate",
            "subcategory":"Real Estate Services",
            "type":"Services"
        },
        {
            "category":"Building & Trades",
            "subcategory":"Construction",
            "type":"Services"
        }
    ],
    "sg:phone":"+1 708 841 8669",
    "sg:postcode":"60419",
    "sg:province":"IL",
    "sg:tags":[
        "management",
        "property",
        "painter"
    ],
    "wof:name":"Economy Painting & Wallpaper",
    "wof:placetype":"venue"
},
  "geometry": {"coordinates":[-87.581902,41.6292],"type":"Point"}
}