{
  "type": "Feature",
  "properties": {
    "iso:country":"US",
    "sg:address":"3350 W Jackson Boulevard",
    "sg:city":"Chicago",
    "sg:classifiers":[
        {
            "category":"Organizations",
            "subcategory":"Religious Organization",
            "type":"Services"
        }
    ],
    "sg:phone":"+1 773 265 1900",
    "sg:postcode":"60624",
    "sg:province":"IL",
    "wof:name":"Fifth City Chicago",
    "wof:placetype":"venue"
},
  "geometry": {"coordinates":[-87.71059099999999,41.877395],"type":"Point"}
}