{
  "type": "Feature",
  "properties": {
    "addr:full":"8343 W Irving Park Road Chicago IL 60634",
    "addr:housenumber":"8343",
    "addr:postcode":"60634",
    "addr:street":"W Irving Park Road",
    "iso:country":"US",
    "sg:address":"8343 W Irving Park Road",
    "sg:city":"Chicago",
    "sg:classifiers":[
        {
            "category":"Restaurant",
            "type":"Food & Drink"
        }
    ],
    "sg:phone":"+1 773 589 1501",
    "sg:postcode":"60634",
    "sg:province":"IL",
    "sg:tags":[
        "pizza"
    ],
    "sg:website":"www.allmenus.com/il/chicago/2235...",
    "wof:name":"Lonnie's Pizzaria",
    "wof:placetype":"venue"
},
  "geometry": {"coordinates":[-87.83636300000001,41.951828],"type":"Point"}
}