{
  "type": "Feature",
  "properties": {
    "iso:country":"US",
    "sg:address":"5110 Tollview Dr",
    "sg:city":"Rolling Meadows",
    "sg:classifiers":[
        {
            "category":"Professional",
            "subcategory":"Computer Services",
            "type":"Services"
        }
    ],
    "sg:phone":"+1 847 870 7400",
    "sg:postcode":"60008",
    "sg:province":"IL",
    "sg:tags":[
        "development",
        "software",
        "arts",
        "graphic",
        "mfg"
    ],
    "wof:name":"DS North America Holdings",
    "wof:placetype":"venue"
},
  "geometry": {"coordinates":[-88.021365,42.060452],"type":"Point"}
}