{
  "type": "Feature",
  "properties": {
    "addr:full":"695 N Bradley Rd Lake Forest IL 60045",
    "addr:housenumber":"695",
    "addr:postcode":"60045",
    "addr:street":"N Bradley Rd",
    "iso:country":"US",
    "sg:address":"695 N Bradley Rd",
    "sg:city":"Lake Forest",
    "sg:classifiers":[
        {
            "category":"Restaurant",
            "type":"Food & Drink"
        }
    ],
    "sg:phone":"+1   ",
    "sg:postcode":"60045",
    "sg:province":"IL",
    "sg:tags":[
        "eating"
    ],
    "wof:name":"Wendys",
    "wof:placetype":"venue"
},
  "geometry": {"coordinates":[-87.905472,42.254523],"type":"Point"}
}