{
  "type": "Feature",
  "properties": {
    "addr:full":"39076 N Poplar St Lake Villa IL 60046",
    "addr:housenumber":"39076",
    "addr:postcode":"60046",
    "addr:street":"N Poplar St",
    "iso:country":"US",
    "sg:address":"39076 N Poplar St",
    "sg:city":"Lake Villa",
    "sg:classifiers":[
        {
            "category":"Professional",
            "type":"Services"
        }
    ],
    "sg:phone":"+1 847 356 3358",
    "sg:postcode":"60046",
    "sg:province":"IL",
    "sg:tags":[
        "establishment"
    ],
    "wof:name":"John Allen Productions Inc",
    "wof:placetype":"venue"
},
  "geometry": {"coordinates":[-88.058526,42.431034],"type":"Point"}
}