{
  "type": "Feature",
  "properties": {
    "iso:country":"US",
    "sg:address":"170 Jamestown Ln",
    "sg:city":"Lincolnshire",
    "sg:classifiers":[
        {
            "category":"Health Services",
            "subcategory":"Hospital",
            "type":"Services"
        }
    ],
    "sg:phone":"+1 847 883 9000",
    "sg:postcode":"60069",
    "sg:province":"IL",
    "sg:tags":[
        "sleep",
        "treatment",
        "disorders-information"
    ],
    "wof:name":"Memory Clinic",
    "wof:placetype":"venue"
},
  "geometry": {"coordinates":[-87.929148,42.205324],"type":"Point"}
}