{
  "type": "Feature",
  "properties": {
    "addr:full":"5211 Pin Oak Dr Alton IL 62002",
    "addr:housenumber":"5211",
    "addr:postcode":"62002",
    "addr:street":"Pin Oak Dr",
    "iso:country":"US",
    "sg:address":"5211 Pin Oak Dr",
    "sg:city":"Alton",
    "sg:classifiers":[
        {
            "category":"Professional",
            "subcategory":"Business Services",
            "type":"Services"
        }
    ],
    "sg:phone":"+1 618 466 9201",
    "sg:postcode":"62002",
    "sg:province":"IL",
    "wof:name":"Sue Fiegenbaum",
    "wof:placetype":"venue"
},
  "geometry": {"coordinates":[-90.16992999999999,38.947322],"type":"Point"}
}