{
  "type": "Feature",
  "properties": {
    "iso:country":"US",
    "sg:address":"1210 US Hwy 136",
    "sg:city":"Penfield",
    "sg:classifiers":[
        {
            "category":"Building & Trades",
            "subcategory":"Cleaning & Sanitation",
            "type":"Services"
        }
    ],
    "sg:phone":"+1 217 569 2589",
    "sg:postcode":"61862",
    "sg:province":"IL",
    "sg:tags":[
        "fireplace",
        "chimney"
    ],
    "wof:name":"Michael O Clements",
    "wof:placetype":"venue"
},
  "geometry": {"coordinates":[-87.918025,40.31336],"type":"Point"}
}