{
  "type": "Feature",
  "properties": {
    "iso:country":"US",
    "sg:address":"1985 Bend Rd",
    "sg:city":"Shabbona",
    "sg:classifiers":[
        {
            "category":"Banks & Credit Unions",
            "subcategory":"Investment Brokerage",
            "type":"Services"
        },
        {
            "category":"Banks & Credit Unions",
            "subcategory":"Bank",
            "type":"Services"
        }
    ],
    "sg:phone":"+1 815 627 8034",
    "sg:postcode":"60550",
    "sg:province":"IL",
    "sg:tags":[
        "transfer",
        "bond",
        "broker",
        "agent",
        "stock"
    ],
    "wof:name":"Barbara R Voga",
    "wof:placetype":"venue"
},
  "geometry": {"coordinates":[-88.912806,41.717399],"type":"Point"}
}