{
  "type": "Feature",
  "properties": {
    "addr:full":"7838 W Evan Ter Frankfort IL 60423",
    "addr:housenumber":"7838",
    "addr:postcode":"60423",
    "addr:street":"W Evan Ter",
    "iso:country":"US",
    "sg:address":"7838 W Evan Ter",
    "sg:city":"Frankfort",
    "sg:classifiers":[
        {
            "category":"Banks & Credit Unions",
            "subcategory":"Investment Brokerage",
            "type":"Services"
        }
    ],
    "sg:phone":"+1 815 806 1952",
    "sg:postcode":"60423",
    "sg:province":"IL",
    "sg:tags":[
        "advisory",
        "financial"
    ],
    "wof:name":"Challenge Financial Investors",
    "wof:placetype":"venue"
},
  "geometry": {"coordinates":[-87.80959900000001,41.5321],"type":"Point"}
}