{
  "type": "Feature",
  "properties": {
    "addr:full":"122 N Martin Luther King Jr Ave Waukegan IL 60085",
    "addr:housenumber":"122",
    "addr:postcode":"60085",
    "addr:street":"N Martin Luther King Jr Ave",
    "iso:country":"US",
    "sg:address":"122 N Martin Luther King Jr Ave",
    "sg:city":"Waukegan",
    "sg:classifiers":[
        {
            "category":"Organizations",
            "subcategory":"Religious Organization",
            "type":"Services"
        }
    ],
    "sg:phone":"+1 847 662 6483",
    "sg:postcode":"60085",
    "sg:province":"IL",
    "sg:tags":[
        "church"
    ],
    "sg:website":"www.firstpreswaukegan.org",
    "wof:name":"First Presbyterian Church",
    "wof:placetype":"venue"
},
  "geometry": {"coordinates":[-87.83393599999999,42.361998],"type":"Point"}
}