{
  "type": "Feature",
  "properties": {
    "iso:country":"US",
    "sg:address":"756 E Rollins Rd",
    "sg:city":"Round Lake Beach",
    "sg:classifiers":[
        {
            "category":"Health Services",
            "subcategory":"Doctor",
            "type":"Services"
        }
    ],
    "sg:phone":"+1 847 740 0300",
    "sg:postcode":"60073",
    "sg:province":"IL",
    "sg:tags":[
        "physician",
        "surgeon"
    ],
    "wof:name":"Family Doctors Of Round Lake",
    "wof:placetype":"venue"
},
  "geometry": {"coordinates":[-88.06686999999999,42.379084],"type":"Point"}
}