{
  "type": "Feature",
  "properties": {
    "iso:country":"US",
    "sg:address":"1169 W Jefferson St",
    "sg:city":"Joliet",
    "sg:classifiers":[
        {
            "category":"Shopping",
            "type":"Retail Goods"
        },
        {
            "category":"Building & Trades",
            "subcategory":"Construction",
            "type":"Services"
        }
    ],
    "sg:phone":"+1 815 725 5555",
    "sg:postcode":"60435",
    "sg:province":"IL",
    "sg:tags":[
        "designer",
        "equipment",
        "spa",
        "dealer",
        "pool",
        "swimming"
    ],
    "wof:name":"Sun N Fun Pool & Spa Inc",
    "wof:placetype":"venue"
},
  "geometry": {"coordinates":[-88.109175,41.523087],"type":"Point"}
}