{
  "type": "Feature",
  "properties": {
    "iso:country":"US",
    "sg:address":"5000 S Central Ave",
    "sg:city":"Chicago",
    "sg:classifiers":[
        {
            "category":"Autos & Motor Vehicles",
            "subcategory":"Auto Supplies",
            "type":"Retail Goods"
        },
        {
            "category":"Wholesale",
            "subcategory":"Auto Parts",
            "type":"Manufacturing & Wholesale Goods"
        }
    ],
    "sg:phone":"+1 708 594 9878",
    "sg:postcode":"60638",
    "sg:province":"IL",
    "sg:tags":[
        "automobile",
        "rebuilt-wholesale",
        "supplies-used",
        "rebuilt",
        "manufacturer"
    ],
    "wof:name":"Keene Export Brake And Electric Co.",
    "wof:placetype":"venue"
},
  "geometry": {"coordinates":[-87.76258900000001,41.801861],"type":"Point"}
}