{
  "type": "Feature",
  "properties": {
    "iso:country":"US",
    "sg:address":"17 Farmstead Dr",
    "sg:city":"Galena",
    "sg:classifiers":[
        {
            "category":"Real Estate",
            "subcategory":"Real Estate Agent",
            "type":"Services"
        }
    ],
    "sg:phone":"+1 563 332 9855",
    "sg:postcode":"61036",
    "sg:province":"IL",
    "sg:tags":[
        "housing"
    ],
    "wof:name":"Eagle Ridge Farmstead # 17",
    "wof:placetype":"venue"
},
  "geometry": {"coordinates":[-90.329644,42.404568],"type":"Point"}
}