{
  "type": "Feature",
  "properties": {
    "iso:country":"US",
    "sg:address":"603 Clarksville Rd",
    "sg:city":"Pittsfield",
    "sg:classifiers":[
        {
            "category":"Organizations",
            "subcategory":"Religious Organization",
            "type":"Services"
        }
    ],
    "sg:phone":"+1 217 285 6010",
    "sg:postcode":"62363",
    "sg:province":"IL",
    "sg:tags":[
        "clergy"
    ],
    "wof:name":"Linda Peyla",
    "wof:placetype":"venue"
},
  "geometry": {"coordinates":[-90.809499,39.600852],"type":"Point"}
}