{
  "type": "Feature",
  "properties": {
    "addr:full":"2702 Pine Valley Dr Champaign IL 61822",
    "addr:housenumber":"2702",
    "addr:postcode":"61822",
    "addr:street":"Pine Valley Dr",
    "iso:country":"US",
    "sg:address":"2702 Pine Valley Dr",
    "sg:city":"Champaign",
    "sg:classifiers":[
        {
            "category":"Retail",
            "subcategory":"Repair Shop",
            "type":"Services"
        }
    ],
    "sg:phone":"+1 217 355 0384",
    "sg:postcode":"61822",
    "sg:province":"IL",
    "sg:tags":[
        "project",
        "engineering",
        "management",
        "construction"
    ],
    "wof:name":"Coleman",
    "wof:placetype":"venue"
},
  "geometry": {"coordinates":[-88.290919,40.071932],"type":"Point"}
}