{
  "type": "Feature",
  "properties": {
    "iso:country":"US",
    "sg:address":"3465 N Kimball Ave",
    "sg:city":"Chicago",
    "sg:classifiers":[
        {
            "category":"Shopping",
            "subcategory":"Mobile Phones",
            "type":"Retail Goods"
        }
    ],
    "sg:phone":"+1 773 463 9000",
    "sg:postcode":"60618",
    "sg:province":"IL",
    "wof:name":"World Wireless",
    "wof:placetype":"venue"
},
  "geometry": {"coordinates":[-87.712422,41.944098],"type":"Point"}
}