{
  "type": "Feature",
  "properties": {
    "iso:country":"US",
    "sg:address":"28636 W Lindbergh Dr",
    "sg:city":"Barrington",
    "sg:classifiers":[
        {
            "category":"Retail",
            "subcategory":"Repair Shop",
            "type":"Services"
        }
    ],
    "sg:phone":"+1 847 277 0778",
    "sg:postcode":"60010",
    "sg:province":"IL",
    "sg:tags":[
        "piano",
        "restoration",
        "organ-tuning"
    ],
    "wof:name":"A Joyful Inc",
    "wof:placetype":"venue"
},
  "geometry": {"coordinates":[-88.192159,42.20623],"type":"Point"}
}