{
  "type": "Feature",
  "properties": {
    "addr:full":"107 S 2nd St West Dundee IL 60118",
    "addr:housenumber":"107",
    "addr:postcode":"60118",
    "addr:street":"S 2Nd St",
    "iso:country":"US",
    "sg:address":"107 S 2nd St",
    "sg:city":"West Dundee",
    "sg:classifiers":[
        {
            "category":"Food & Beverages",
            "subcategory":"Candy",
            "type":"Retail Goods"
        }
    ],
    "sg:phone":"+1 847 426 9440",
    "sg:postcode":"60118",
    "sg:province":"IL",
    "sg:tags":[
        "store"
    ],
    "wof:name":"Around The Corner Candy",
    "wof:placetype":"venue"
},
  "geometry": {"coordinates":[-88.278397,42.097401],"type":"Point"}
}