{
  "type": "Feature",
  "properties": {
    "addr:full":"805 S Hemlock St Le Roy IL 61752",
    "addr:housenumber":"805",
    "addr:postcode":"61752",
    "addr:street":"S Hemlock St",
    "iso:country":"US",
    "sg:address":"805 S Hemlock St",
    "sg:city":"Le Roy",
    "sg:classifiers":[
        {
            "category":"Restaurant",
            "type":"Food & Drink"
        }
    ],
    "sg:phone":"+1 309 962 3710",
    "sg:postcode":"61752",
    "sg:province":"IL",
    "sg:tags":[
        "eating"
    ],
    "wof:name":"Woody's Family Restaurant",
    "wof:placetype":"venue"
},
  "geometry": {"coordinates":[-88.769042,40.342072],"type":"Point"}
}