{
  "type": "Feature",
  "properties": {
    "addr:full":"4523 Eberly Ave Brookfield IL 60513",
    "addr:housenumber":"4523",
    "addr:postcode":"60513",
    "addr:street":"Eberly Ave",
    "iso:country":"US",
    "sg:address":"4523 Eberly Ave",
    "sg:city":"Brookfield",
    "sg:classifiers":[
        {
            "category":"Government",
            "subcategory":"Office",
            "type":"Public Place"
        }
    ],
    "sg:phone":"+1 708 387 7004",
    "sg:postcode":"60513",
    "sg:province":"IL",
    "sg:tags":[
        "civil",
        "defense",
        "agency"
    ],
    "wof:name":"Brookfield Civil Defense",
    "wof:placetype":"venue"
},
  "geometry": {"coordinates":[-87.859469,41.807543],"type":"Point"}
}