{
  "type": "Feature",
  "properties": {
    "addr:full":"600 N Lexington Ave Kewanee IL 61443",
    "addr:housenumber":"600",
    "addr:postcode":"61443",
    "addr:street":"N Lexington Ave",
    "iso:country":"US",
    "sg:address":"600 N Lexington Ave",
    "sg:city":"Kewanee",
    "sg:classifiers":[
        {
            "category":"Education",
            "subcategory":"School",
            "type":"Public Place"
        }
    ],
    "sg:phone":"+1 309 853 3052",
    "sg:postcode":"61443",
    "sg:province":"IL",
    "wof:name":"Franklin Middle School",
    "wof:placetype":"venue"
},
  "geometry": {"coordinates":[-89.929592,41.249147],"type":"Point"}
}