{
  "type": "Feature",
  "properties": {
    "addr:full":"4758 W Washington Blvd Chicago IL 60644",
    "addr:housenumber":"4758",
    "addr:postcode":"60644",
    "addr:street":"W Washington Blvd",
    "iso:country":"US",
    "sg:address":"4758 W Washington Blvd",
    "sg:city":"Chicago",
    "sg:classifiers":[
        {
            "category":"Health Services",
            "subcategory":"Doctor",
            "type":"Services"
        }
    ],
    "sg:phone":"+1 773 379 2277",
    "sg:postcode":"60644",
    "sg:province":"IL",
    "wof:name":"Kirn Patari",
    "wof:placetype":"venue"
},
  "geometry": {"coordinates":[-87.744016,41.881907],"type":"Point"}
}