{
  "type": "Feature",
  "properties": {
    "iso:country":"US",
    "sg:address":"1215 Hazel Ave",
    "sg:city":"Deerfield",
    "sg:classifiers":[
        {
            "category":"Internet Cafe",
            "subcategory":"None",
            "type":"Food & Drink"
        },
        {
            "category":"Professional",
            "subcategory":"Computer Services",
            "type":"Services"
        }
    ],
    "sg:phone":"+1 847 236 1850",
    "sg:postcode":"60015",
    "sg:province":"IL",
    "sg:tags":[
        "product",
        "designer",
        "network",
        "consultant",
        "system",
        "design",
        "software"
    ],
    "sg:website":"http://www.outlookcomputing.com",
    "wof:name":"Outlook Computing Inc",
    "wof:placetype":"venue"
},
  "geometry": {"coordinates":[-87.857868,42.171],"type":"Point"}
}