{
  "type": "Feature",
  "properties": {
    "addr:full":"410 Cougar Vlg Apt 2D Edwardsville IL 62025",
    "addr:housenumber":"410",
    "addr:postcode":"62025",
    "addr:street":"Cougar Vlg Apt 2D",
    "iso:country":"US",
    "sg:address":"410 Cougar Vlg Apt 2D",
    "sg:city":"Edwardsville",
    "sg:classifiers":[
        {
            "category":"Building & Trades",
            "subcategory":"Construction",
            "type":"Services"
        }
    ],
    "sg:phone":"+1 618 650 4765",
    "sg:postcode":"62025",
    "sg:province":"IL",
    "sg:tags":[
        "handyman"
    ],
    "wof:name":"Scotts Computer Repair",
    "wof:placetype":"venue"
},
  "geometry": {"coordinates":[-89.957207,38.781872],"type":"Point"}
}