{
  "type": "Feature",
  "properties": {
    "addr:full":"2635 Flossmoor Rd Flossmoor IL 60422",
    "addr:housenumber":"2635",
    "addr:postcode":"60422",
    "addr:street":"Flossmoor Rd",
    "iso:country":"US",
    "sg:address":"2635 Flossmoor Rd",
    "sg:city":"Flossmoor",
    "sg:classifiers":[
        {
            "category":"Professional",
            "subcategory":"Lawyer & Legal Services",
            "type":"Services"
        }
    ],
    "sg:phone":"+1 708 922 0355",
    "sg:postcode":"60422",
    "sg:province":"IL",
    "sg:tags":[
        "attorney",
        "practice"
    ],
    "wof:name":"Mary K Duggan",
    "wof:placetype":"venue"
},
  "geometry": {"coordinates":[-87.681449,41.542585],"type":"Point"}
}