{
  "type": "Feature",
  "properties": {
    "addr:full":"2240 Pearsall Pkwy Waukegan IL 60085",
    "addr:housenumber":"2240",
    "addr:postcode":"60085",
    "addr:street":"Pearsall Pkwy",
    "iso:country":"US",
    "sg:address":"2240 Pearsall Pkwy",
    "sg:city":"Waukegan",
    "sg:classifiers":[
        {
            "category":"Professional",
            "subcategory":"Employment Agencies",
            "type":"Services"
        }
    ],
    "sg:phone":"+1 847 662 0788",
    "sg:postcode":"60085",
    "sg:province":"IL",
    "sg:tags":[
        "contractor"
    ],
    "wof:name":"Temp Tech Professional Svc",
    "wof:placetype":"venue"
},
  "geometry": {"coordinates":[-87.860961,42.34412],"type":"Point"}
}