{
  "type": "Feature",
  "properties": {
    "addr:full":"14350 S Archer Ave Lockport IL 60441",
    "addr:housenumber":"14350",
    "addr:postcode":"60441",
    "addr:street":"S Archer Ave",
    "iso:country":"US",
    "sg:address":"14350 S Archer Ave",
    "sg:city":"Lockport",
    "sg:classifiers":[
        {
            "category":"Building & Trades",
            "subcategory":"Plumbing",
            "type":"Services"
        }
    ],
    "sg:phone":"+1 815 838 0515",
    "sg:postcode":"60441",
    "sg:province":"IL",
    "sg:tags":[
        "plumbing",
        "sewer"
    ],
    "wof:name":"All Community Plumbing & Sewer",
    "wof:placetype":"venue"
},
  "geometry": {"coordinates":[-88.022513,41.62635],"type":"Point"}
}