{
  "type": "Feature",
  "properties": {
    "iso:country":"US",
    "sg:address":"9300 Skokie Blvd",
    "sg:city":"Skokie",
    "sg:classifiers":[
        {
            "category":"Restaurant",
            "type":"Food & Drink"
        }
    ],
    "sg:phone":"+1   ",
    "sg:postcode":"60077",
    "sg:province":"IL",
    "sg:tags":[
        "eating"
    ],
    "wof:name":"Bravo Restaurant",
    "wof:placetype":"venue"
},
  "geometry": {"coordinates":[-87.746888,42.050816],"type":"Point"}
}