{
  "type": "Feature",
  "properties": {
    "iso:country":"US",
    "sg:address":"7245 W 151st St",
    "sg:city":"Orland Park",
    "sg:classifiers":[
        {
            "category":"Restaurant",
            "type":"Food & Drink"
        }
    ],
    "sg:phone":"+1 708 429 3777",
    "sg:postcode":"60462",
    "sg:province":"IL",
    "sg:tags":[
        "eating"
    ],
    "wof:name":"Don's Hot Dogs",
    "wof:placetype":"venue"
},
  "geometry": {"coordinates":[-87.795991,41.616951],"type":"Point"}
}