{
  "type": "Feature",
  "properties": {
    "addr:full":"15701 Wolf Rd Orland Park IL 60467",
    "addr:housenumber":"15701",
    "addr:postcode":"60467",
    "addr:street":"Wolf Rd",
    "iso:country":"US",
    "sg:address":"15701 Wolf Rd",
    "sg:city":"Orland Park",
    "sg:classifiers":[
        {
            "category":"Retail",
            "subcategory":"Animal Services",
            "type":"Services"
        }
    ],
    "sg:phone":"+1 708 403 2121",
    "sg:postcode":"60467",
    "sg:province":"IL",
    "sg:tags":[
        "pet",
        "grooming",
        "washing"
    ],
    "wof:name":"Animal House Grooming Inc",
    "wof:placetype":"venue"
},
  "geometry": {"coordinates":[-87.89152300000001,41.603967],"type":"Point"}
}