{
  "type": "Feature",
  "properties": {
    "iso:country":"US",
    "sg:address":"37293 N Hillside Dr",
    "sg:city":"Lake Villa",
    "sg:classifiers":[
        {
            "category":"Shopping",
            "subcategory":"Gifts & Souvenirs",
            "type":"Retail Goods"
        }
    ],
    "sg:phone":"+1   ",
    "sg:postcode":"60046",
    "sg:province":"IL",
    "wof:name":"Gift Nook",
    "wof:placetype":"venue"
},
  "geometry": {"coordinates":[-88.13023699999999,42.404857],"type":"Point"}
}