{
  "type": "Feature",
  "properties": {
    "addr:full":"205 W Randolph St Ste 1700 Chicago IL 60606",
    "addr:housenumber":"205",
    "addr:postcode":"60606",
    "addr:street":"W Randolph St Ste 1700",
    "iso:country":"US",
    "sg:address":"205 W Randolph St Ste 1700",
    "sg:city":"Chicago",
    "sg:classifiers":[
        {
            "category":"Professional",
            "subcategory":"Lawyer & Legal Services",
            "type":"Services"
        }
    ],
    "sg:phone":"+1 312 726 6234",
    "sg:postcode":"60606",
    "sg:province":"IL",
    "wof:name":"Cohn Lambert Ryan and Schneider Ltd",
    "wof:placetype":"venue"
},
  "geometry": {"coordinates":[-87.637001,41.882301],"type":"Point"}
}