{
  "type": "Feature",
  "properties": {
    "iso:country":"US",
    "sg:address":"955 Brandt Dr",
    "sg:city":"Elgin",
    "sg:classifiers":[
        {
            "category":"Professional",
            "subcategory":"Computer Services",
            "type":"Services"
        }
    ],
    "sg:phone":"+1 847 742 1474",
    "sg:postcode":"60156",
    "sg:province":"IL",
    "sg:tags":[
        "prepackaged",
        "business",
        "software"
    ],
    "wof:name":"USFreightways",
    "wof:placetype":"venue"
},
  "geometry": {"coordinates":[-88.306962,42.184024],"type":"Point"}
}