{
  "type": "Feature",
  "properties": {
    "addr:full":"225 W Pershing Rd Chicago IL 60609",
    "addr:housenumber":"225",
    "addr:postcode":"60609",
    "addr:street":"W Pershing Rd",
    "iso:country":"US",
    "sg:address":"225 W Pershing Rd",
    "sg:city":"Chicago",
    "sg:phone":"+1 773 548 7111",
    "sg:postcode":"60609",
    "sg:province":"IL",
    "wof:name":"Pls Financial",
    "wof:placetype":"venue"
},
  "geometry": {"coordinates":[-87.631981,41.823641],"type":"Point"}
}