{
  "type": "Feature",
  "properties": {
    "iso:country":"US",
    "sg:address":"4712 Reiland Dr",
    "sg:city":"Crystal Lake",
    "sg:classifiers":[
        {
            "category":"Retail",
            "subcategory":"Auto Repair",
            "type":"Services"
        }
    ],
    "sg:phone":"+1 847 854 0170",
    "sg:postcode":"60012",
    "sg:province":"IL",
    "sg:tags":[
        "truck"
    ],
    "wof:name":"Black Eagle Archery Inc",
    "wof:placetype":"venue"
},
  "geometry": {"coordinates":[-88.289047,42.250966],"type":"Point"}
}