{
  "type": "Feature",
  "properties": {
    "addr:full":"1 Tower Ln Villa Park IL 60181",
    "addr:housenumber":"1",
    "addr:postcode":"60181",
    "addr:street":"Tower Ln",
    "iso:country":"US",
    "sg:address":"1 Tower Ln",
    "sg:city":"Villa Park",
    "sg:classifiers":[
        {
            "category":"Banks & Credit Unions",
            "subcategory":"Bank",
            "type":"Services"
        }
    ],
    "sg:phone":"+1 630 645 2277",
    "sg:postcode":"60181",
    "sg:province":"IL",
    "sg:tags":[
        "mortgage"
    ],
    "wof:name":"Benchmark Financial Corp",
    "wof:placetype":"venue"
},
  "geometry": {"coordinates":[-87.951117,41.860913],"type":"Point"}
}