{
  "type": "Feature",
  "properties": {
    "addr:full":"6304 Konarcik Rd Waterloo IL 62298",
    "addr:housenumber":"6304",
    "addr:postcode":"62298",
    "addr:street":"Konarcik Rd",
    "iso:country":"US",
    "sg:address":"6304 Konarcik Rd",
    "sg:city":"Waterloo",
    "sg:classifiers":[
        {
            "category":"Shopping",
            "subcategory":"Computers & Home Electronics",
            "type":"Retail Goods"
        },
        {
            "category":"Communications",
            "type":"Services"
        },
        {
            "category":"Communications",
            "subcategory":"Television Station",
            "type":"Services"
        }
    ],
    "sg:phone":"+1 618 939 4777",
    "sg:postcode":"62298",
    "sg:province":"IL",
    "sg:tags":[
        "sound",
        "satellite",
        "antenna",
        "cable",
        "tv",
        "system",
        "equipment",
        "radio",
        "store"
    ],
    "wof:name":"Link Future Satellite & Antenna Systems",
    "wof:placetype":"venue"
},
  "geometry": {"coordinates":[-90.077704,38.338615],"type":"Point"}
}