{
  "type": "Feature",
  "properties": {
    "addr:full":"529 S Euclid Ave Villa Park IL 60181",
    "addr:housenumber":"529",
    "addr:postcode":"60181",
    "addr:street":"S Euclid Ave",
    "iso:country":"US",
    "sg:address":"529 S Euclid Ave",
    "sg:city":"Villa Park",
    "sg:classifiers":[
        {
            "category":"Organizations",
            "subcategory":"Religious Organization",
            "type":"Services"
        }
    ],
    "sg:phone":"+1 630 832 3034",
    "sg:postcode":"60181",
    "sg:province":"IL",
    "wof:name":"Han Yunchun Rev",
    "wof:placetype":"venue"
},
  "geometry": {"coordinates":[-87.971429,41.881257],"type":"Point"}
}