{
  "type": "Feature",
  "properties": {
    "addr:full":"197 W Laraway Rd Joliet IL 60436",
    "addr:housenumber":"197",
    "addr:postcode":"60436",
    "addr:street":"W Laraway Rd",
    "iso:country":"US",
    "sg:address":"197 W Laraway Rd",
    "sg:city":"Joliet",
    "sg:classifiers":[
        {
            "category":"Professional",
            "subcategory":"Advertising",
            "type":"Services"
        }
    ],
    "sg:phone":"+1 815 726 0315",
    "sg:postcode":"60436",
    "sg:province":"IL",
    "sg:tags":[
        "mail",
        "direct"
    ],
    "wof:name":"Joliet Mailing Services Inc",
    "wof:placetype":"venue"
},
  "geometry": {"coordinates":[-88.085053,41.480651],"type":"Point"}
}