{
  "type": "Feature",
  "properties": {
    "iso:country":"US",
    "sg:address":"1428 W Irving Park Road Suite 1",
    "sg:city":"Chicago",
    "sg:classifiers":[
        {
            "category":"Insurance",
            "subcategory":"Hazard Insurance",
            "type":"Services"
        }
    ],
    "sg:phone":"+1 773 327 5559",
    "sg:postcode":"60613",
    "sg:province":"IL",
    "sg:website":"www.gregjareczek.com",
    "wof:name":"State Farm Insurance Greg Jareczek",
    "wof:placetype":"venue"
},
  "geometry": {"coordinates":[-87.665435,41.954369],"type":"Point"}
}