{
  "type": "Feature",
  "properties": {
    "addr:full":"710 E 47th St 12 Chicago IL 60653",
    "addr:housenumber":"710;12",
    "addr:postcode":"60653",
    "addr:street":"E 47Th St",
    "iso:country":"US",
    "sg:address":"710 E 47th St 12",
    "sg:city":"Chicago",
    "sg:classifiers":[
        {
            "category":"Industrial Area",
            "type":"Public Place"
        }
    ],
    "sg:phone":"+1 773 268 3200",
    "sg:postcode":"60653",
    "sg:province":"IL",
    "sg:tags":[
        "development"
    ],
    "wof:name":"Hyde Park Business Center",
    "wof:placetype":"venue"
},
  "geometry": {"coordinates":[-87.608513,41.809498],"type":"Point"}
}