{
  "type": "Feature",
  "properties": {
    "addr:full":"2826 Thatcher Ave River Grove IL 60171",
    "addr:housenumber":"2826",
    "addr:postcode":"60171",
    "addr:street":"Thatcher Ave",
    "iso:country":"US",
    "sg:address":"2826 Thatcher Ave",
    "sg:city":"River Grove",
    "sg:classifiers":[
        {
            "category":"Deli",
            "type":"Food & Drink"
        },
        {
            "category":"Cafe",
            "type":"Food & Drink"
        }
    ],
    "sg:menulink":"http://www.allmenus.com/il/leyden/224112-the-loon-cafe/menu/",
    "sg:phone":"+1 708 453 1220",
    "sg:postcode":"60171",
    "sg:province":"IL",
    "sg:tags":[
        "american"
    ],
    "wof:name":"The Loon Cafe",
    "wof:placetype":"venue"
},
  "geometry": {"coordinates":[-87.83588399999999,41.930704],"type":"Point"}
}