{
  "type": "Feature",
  "properties": {
    "iso:country":"US",
    "sg:address":"12763 Shawnee Crst",
    "sg:city":"Roscoe",
    "sg:classifiers":[
        {
            "category":"Professional",
            "subcategory":"Business Services",
            "type":"Services"
        }
    ],
    "sg:phone":"+1 815 389 1552",
    "sg:postcode":"61073",
    "sg:province":"IL",
    "sg:tags":[
        "water",
        "treatment"
    ],
    "wof:name":"Puresep Solutions Co",
    "wof:placetype":"venue"
},
  "geometry": {"coordinates":[-88.951489,42.44721],"type":"Point"}
}