{
  "type": "Feature",
  "properties": {
    "iso:country":"US",
    "sg:address":"814 Belvidere St",
    "sg:city":"Waukegan",
    "sg:classifiers":[
        {
            "category":"Real Estate",
            "subcategory":"Architect",
            "type":"Services"
        }
    ],
    "sg:phone":"+1 847 263 4857",
    "sg:postcode":"60085",
    "sg:province":"IL",
    "sg:tags":[
        "estimate",
        "construction"
    ],
    "wof:name":"Libger & Durham",
    "wof:placetype":"venue"
},
  "geometry": {"coordinates":[-87.842241,42.3522],"type":"Point"}
}