{
  "type": "Feature",
  "properties": {
    "iso:country":"US",
    "sg:address":"400 Cemetery Rd",
    "sg:city":"Worden",
    "sg:classifiers":[
        {
            "category":"Government",
            "subcategory":"Office",
            "type":"Public Place"
        }
    ],
    "sg:phone":"+1 618 459 3272",
    "sg:postcode":"62097",
    "sg:province":"IL",
    "sg:tags":[
        "village"
    ],
    "wof:name":"Worden Sewer Plant",
    "wof:placetype":"venue"
},
  "geometry": {"coordinates":[-89.84177099999999,38.938607],"type":"Point"}
}