{
  "type": "Feature",
  "properties": {
    "addr:full":"10637 S Halsted St Chicago IL 60628",
    "addr:housenumber":"10637",
    "addr:postcode":"60628",
    "addr:street":"S Halsted St",
    "iso:country":"US",
    "sg:address":"10637 S Halsted St",
    "sg:city":"Chicago",
    "sg:classifiers":[
        {
            "category":"Shopping",
            "subcategory":"Clothing, Apparel, & Fashions",
            "type":"Retail Goods"
        }
    ],
    "sg:phone":"+1 773 264 3766",
    "sg:postcode":"60628",
    "sg:province":"IL",
    "sg:tags":[
        "accessory",
        "clothing",
        "women's"
    ],
    "wof:name":"Ursula's Closet",
    "wof:placetype":"venue"
},
  "geometry": {"coordinates":[-87.642403,41.7001],"type":"Point"}
}