{
  "type": "Feature",
  "properties": {
    "addr:full":"1639 N Damen Ave Chicago IL 60647",
    "addr:housenumber":"1639",
    "addr:postcode":"60647",
    "addr:street":"N Damen Ave",
    "iso:country":"US",
    "sg:address":"1639 N Damen Ave",
    "sg:city":"Chicago",
    "sg:classifiers":[
        {
            "category":"Home & Garden",
            "subcategory":"Furniture",
            "type":"Retail Goods"
        }
    ],
    "sg:phone":"+1   ",
    "sg:postcode":"60647",
    "sg:province":"IL",
    "sg:tags":[
        "furnishing",
        "accessory"
    ],
    "wof:name":"Embelezar LLC",
    "wof:placetype":"venue"
},
  "geometry": {"coordinates":[-87.677493,41.910497],"type":"Point"}
}