{
  "type": "Feature",
  "properties": {
    "iso:country":"US",
    "sg:address":"4563 W 88th Pl",
    "sg:city":"Oak Lawn",
    "sg:classifiers":[
        {
            "category":"Building & Trades",
            "subcategory":"Construction",
            "type":"Services"
        }
    ],
    "sg:phone":"+1 708 424 6134",
    "sg:postcode":"60456",
    "sg:province":"IL",
    "sg:tags":[
        "house"
    ],
    "wof:name":"Trlak Construction",
    "wof:placetype":"venue"
},
  "geometry": {"coordinates":[-87.737641,41.731124],"type":"Point"}
}