{
  "type": "Feature",
  "properties": {
    "iso:country":"US",
    "sg:address":"1828 Olive Ave",
    "sg:city":"Mattoon",
    "sg:classifiers":[
        {
            "category":"Bars & Pubs",
            "type":"Food & Drink"
        },
        {
            "category":"Restaurant",
            "type":"Food & Drink"
        },
        {
            "category":"Travel",
            "subcategory":"Bed & Breakfast",
            "type":"Entertainment"
        }
    ],
    "sg:phone":"+1 217 235 4841",
    "sg:postcode":"61938",
    "sg:province":"IL",
    "sg:tags":[
        "brew",
        "grill",
        "inn",
        "steak",
        "house"
    ],
    "wof:name":"Castle Inn Lounge Incorporated",
    "wof:placetype":"venue"
},
  "geometry": {"coordinates":[-88.37702400000001,39.469263],"type":"Point"}
}