{
  "type": "Feature",
  "properties": {
    "iso:country":"US",
    "sg:address":"2024 Progress West Dr",
    "sg:city":"Vandalia",
    "sg:classifiers":[
        {
            "category":"Wholesale",
            "subcategory":"Painting Supplies",
            "type":"Manufacturing & Wholesale Goods"
        },
        {
            "category":"Home & Garden",
            "subcategory":"Garden Supply",
            "type":"Retail Goods"
        },
        {
            "category":"Wholesale",
            "subcategory":"Construction Materials",
            "type":"Manufacturing & Wholesale Goods"
        },
        {
            "category":"Home & Garden",
            "subcategory":"Hardware",
            "type":"Retail Goods"
        }
    ],
    "sg:phone":"+1 618 283 9700",
    "sg:postcode":"62471",
    "sg:province":"IL",
    "sg:tags":[
        "lawn",
        "paint",
        "equipment",
        "part",
        "plumbing",
        "fixtures",
        "store"
    ],
    "sg:website":"http://www.truevalue.com/vandalia",
    "wof:name":"True Value Hardware",
    "wof:placetype":"venue"
},
  "geometry": {"coordinates":[-89.11953699999999,38.974548],"type":"Point"}
}