{
  "type": "Feature",
  "properties": {
    "iso:country":"US",
    "sg:address":"4738 N Kenmore Ave",
    "sg:city":"Chicago",
    "sg:classifiers":[
        {
            "category":"Health Services",
            "subcategory":"Doctor",
            "type":"Services"
        }
    ],
    "sg:phone":"+1 773 878 6868",
    "sg:postcode":"60640",
    "sg:province":"IL",
    "wof:name":"David M Sloven MD",
    "wof:placetype":"venue"
},
  "geometry": {"coordinates":[-87.656634,41.968379],"type":"Point"}
}