{
  "type": "Feature",
  "properties": {
    "iso:country":"US",
    "sg:address":"6801 N Western Ave",
    "sg:city":"Chicago",
    "sg:classifiers":[
        {
            "category":"Autos & Motor Vehicles",
            "subcategory":"Fuel & Gas Station",
            "type":"Retail Goods"
        }
    ],
    "sg:phone":"+1   ",
    "sg:postcode":"60645",
    "sg:province":"IL",
    "sg:tags":[
        "station",
        "gasoline"
    ],
    "wof:name":"Citgo Petrolem Corp",
    "wof:placetype":"venue"
},
  "geometry": {"coordinates":[-87.690092,42.005928],"type":"Point"}
}