{
  "type": "Feature",
  "properties": {
    "addr:full":"100 W Locust St Belvidere IL 61008",
    "addr:housenumber":"100",
    "addr:postcode":"61008",
    "addr:street":"W Locust St",
    "iso:country":"US",
    "sg:address":"100 W Locust St",
    "sg:city":"Belvidere",
    "sg:phone":"+1 815 544 6791",
    "sg:postcode":"61008",
    "sg:province":"IL",
    "sg:tags":[
        "product",
        "petroleum"
    ],
    "wof:name":"Boncosky Oil Co",
    "wof:placetype":"venue"
},
  "geometry": {"coordinates":[-88.8411,42.257216],"type":"Point"}
}