{
  "type": "Feature",
  "properties": {
    "iso:country":"US",
    "sg:address":"508 E Vienna St",
    "sg:city":"Anna",
    "sg:classifiers":[
        {
            "category":"Autos & Motor Vehicles",
            "subcategory":"Auto Supplies",
            "type":"Retail Goods"
        }
    ],
    "sg:phone":"+1 618 833 6316",
    "sg:postcode":"62906",
    "sg:province":"IL",
    "sg:tags":[
        "tire"
    ],
    "wof:name":"Jim Carter Tire Ctr",
    "wof:placetype":"venue"
},
  "geometry": {"coordinates":[-89.23601600000001,37.460008],"type":"Point"}
}