{
  "type": "Feature",
  "properties": {
    "iso:country":"US",
    "sg:address":"200 E Myrtle St",
    "sg:city":"Elizabeth",
    "sg:classifiers":[
        {
            "category":"Professional",
            "subcategory":"Lawyer & Legal Services",
            "type":"Services"
        }
    ],
    "sg:phone":"+1 815 858 2416",
    "sg:postcode":"61028",
    "sg:province":"IL",
    "sg:tags":[
        "attorney"
    ],
    "sg:website":"www.abusiveattorney.com",
    "wof:name":"Robert A Bush",
    "wof:placetype":"venue"
},
  "geometry": {"coordinates":[-90.221327,42.317803],"type":"Point"}
}