{
  "type": "Feature",
  "properties": {
    "iso:country":"US",
    "sg:address":"138 E Cass St",
    "sg:city":"Joliet",
    "sg:classifiers":[
        {
            "category":"Home & Garden",
            "subcategory":"Furniture",
            "type":"Retail Goods"
        }
    ],
    "sg:phone":"+1   ",
    "sg:postcode":"60432",
    "sg:province":"IL",
    "sg:tags":[
        "appliance"
    ],
    "wof:name":"Joliet Furniture Mart Inc",
    "wof:placetype":"venue"
},
  "geometry": {"coordinates":[-88.078882,41.527874],"type":"Point"}
}