{
  "type": "Feature",
  "properties": {
    "addr:full":"748 E Sunnyside Ave Libertyville IL 60048",
    "addr:housenumber":"748",
    "addr:postcode":"60048",
    "addr:street":"E Sunnyside Ave",
    "iso:country":"US",
    "sg:address":"748 E Sunnyside Ave",
    "sg:city":"Libertyville",
    "sg:classifiers":[
        {
            "category":"Manufacturing",
            "subcategory":"Petroleum Products",
            "type":"Manufacturing & Wholesale Goods"
        },
        {
            "category":"Shopping",
            "subcategory":"Crafts & Fabrics",
            "type":"Retail Goods"
        }
    ],
    "sg:phone":"+1 847 812 4127",
    "sg:postcode":"60048",
    "sg:province":"IL",
    "sg:tags":[
        "felt",
        "products-wholesale",
        "asphalt",
        "manufacturer"
    ],
    "wof:name":"Acs",
    "wof:placetype":"venue"
},
  "geometry": {"coordinates":[-87.944953,42.280895],"type":"Point"}
}