{
  "type": "Feature",
  "properties": {
    "iso:country":"US",
    "sg:address":"14211 S Bell Rd",
    "sg:city":"Homer Glen",
    "sg:classifiers":[
        {
            "category":"Food & Beverages",
            "subcategory":"Groceries & Convenience Stores",
            "type":"Retail Goods"
        }
    ],
    "sg:phone":"+1 708 301 8689",
    "sg:postcode":"60491",
    "sg:province":"IL",
    "sg:tags":[
        "product"
    ],
    "wof:name":"Golden Sun Chinese Food",
    "wof:placetype":"venue"
},
  "geometry": {"coordinates":[-87.931219,41.632413],"type":"Point"}
}