{
  "type": "Feature",
  "properties": {
    "iso:country":"US",
    "sg:address":"1326 W Albion Ave",
    "sg:city":"Chicago",
    "sg:classifiers":[
        {
            "category":"Landmark",
            "subcategory":"Tourist Information",
            "type":"Public Place"
        }
    ],
    "sg:phone":"+1 773 274 8686",
    "sg:postcode":"60626",
    "sg:province":"IL",
    "sg:tags":[
        "tour"
    ],
    "sg:website":"www.tototours.com",
    "wof:name":"Toto Tours Ltd",
    "wof:placetype":"venue"
},
  "geometry": {"coordinates":[-87.66398,42.002416],"type":"Point"}
}