{
  "type": "Feature",
  "properties": {
    "iso:country":"US",
    "sg:address":"1235 Cedar Ct",
    "sg:city":"Carbondale",
    "sg:classifiers":[
        {
            "category":"Health Services",
            "subcategory":"Doctor",
            "type":"Services"
        }
    ],
    "sg:phone":"+1 618 457 0431",
    "sg:postcode":"62901",
    "sg:province":"IL",
    "sg:tags":[
        "podiatrist"
    ],
    "wof:name":"Moore Christopher C DPM",
    "wof:placetype":"venue"
},
  "geometry": {"coordinates":[-89.252899,37.738701],"type":"Point"}
}