{
  "type": "Feature",
  "properties": {
    "addr:full":"6950 30th Pl Berwyn IL 60402",
    "addr:housenumber":"6950",
    "addr:postcode":"60402",
    "addr:street":"30Th Pl",
    "iso:country":"US",
    "sg:address":"6950 30th Pl",
    "sg:city":"Berwyn",
    "sg:classifiers":[
        {
            "category":"Building & Trades",
            "subcategory":"Construction",
            "type":"Services"
        }
    ],
    "sg:phone":"+1 708 788 0944",
    "sg:postcode":"60402",
    "sg:province":"IL",
    "sg:tags":[
        "demolition",
        "contractor"
    ],
    "wof:name":"D Demolition",
    "wof:placetype":"venue"
},
  "geometry": {"coordinates":[-87.79688299999999,41.83675],"type":"Point"}
}