{
  "type": "Feature",
  "properties": {
    "addr:full":"6135 S Archer Rd Summit Argo IL 60501",
    "addr:housenumber":"6135",
    "addr:postcode":"60501",
    "addr:street":"S Archer Rd",
    "iso:country":"US",
    "sg:address":"6135 S Archer Rd",
    "sg:city":"Summit Argo",
    "sg:classifiers":[
        {
            "category":"Home & Garden",
            "subcategory":"Hardware",
            "type":"Retail Goods"
        }
    ],
    "sg:phone":"+1 708 458 1310",
    "sg:postcode":"60501",
    "sg:province":"IL",
    "wof:name":"Ace Hardware",
    "wof:placetype":"venue"
},
  "geometry": {"coordinates":[-87.813317,41.778859],"type":"Point"}
}