{
  "type": "Feature",
  "properties": {
    "iso:country":"US",
    "sg:address":"1154 Whetstone Rd",
    "sg:city":"Charleston",
    "sg:classifiers":[
        {
            "category":"Shopping",
            "subcategory":"Computers & Home Electronics",
            "type":"Retail Goods"
        }
    ],
    "sg:phone":"+1 217 345 6383",
    "sg:postcode":"61920",
    "sg:province":"IL",
    "sg:tags":[
        "equipment",
        "dealer"
    ],
    "wof:name":"Overload Solutions Inc",
    "wof:placetype":"venue"
},
  "geometry": {"coordinates":[-88.11376199999999,39.405679],"type":"Point"}
}