{
  "type": "Feature",
  "properties": {
    "iso:country":"US",
    "sg:address":"124 State Rte 47",
    "sg:city":"Gibson City",
    "sg:classifiers":[
        {
            "category":"Wholesale",
            "subcategory":"Groceries",
            "type":"Manufacturing & Wholesale Goods"
        }
    ],
    "sg:phone":"+1 217 784 8261",
    "sg:postcode":"60936",
    "sg:province":"IL",
    "sg:tags":[
        "food",
        "product",
        "health"
    ],
    "wof:name":"Solae",
    "wof:placetype":"venue"
},
  "geometry": {"coordinates":[-88.377855,40.456967],"type":"Point"}
}