{
  "type": "Feature",
  "properties": {
    "addr:full":"2106 S Arlington Heights Rd Arlington Heights IL 60005",
    "addr:housenumber":"2106",
    "addr:postcode":"60005",
    "addr:street":"S Arlington Heights Rd",
    "iso:country":"US",
    "sg:address":"2106 S Arlington Heights Rd",
    "sg:city":"Arlington Heights",
    "sg:classifiers":[
        {
            "category":"Bakery",
            "type":"Food & Drink"
        },
        {
            "category":"Coffee & Tea",
            "type":"Food & Drink"
        },
        {
            "category":"Bagels",
            "type":"Food & Drink"
        },
        {
            "category":"Donuts",
            "type":"Food & Drink"
        }
    ],
    "sg:menulink":"http://www.allmenus.com/il/elk-grove/134956-dunkin-donuts/menu/",
    "sg:phone":"+1 847 758 0001",
    "sg:postcode":"60005",
    "sg:province":"IL",
    "sg:tags":[
        "american",
        "pastry"
    ],
    "wof:name":"Dunkin' Donuts",
    "wof:placetype":"venue"
},
  "geometry": {"coordinates":[-87.983148,42.046918],"type":"Point"}
}