{
  "type": "Feature",
  "properties": {
    "iso:country":"US",
    "sg:address":"7346 W 87th St",
    "sg:city":"Bridgeview",
    "sg:classifiers":[
        {
            "category":"Bakery",
            "type":"Food & Drink"
        }
    ],
    "sg:phone":"+1 708 430 8766",
    "sg:postcode":"60455",
    "sg:province":"IL",
    "wof:name":"Rasheed Market",
    "wof:placetype":"venue"
},
  "geometry": {"coordinates":[-87.802696,41.733501],"type":"Point"}
}