{
  "type": "Feature",
  "properties": {
    "iso:country":"US",
    "sg:address":"411 S Kedzie Avenue",
    "sg:city":"Chicago",
    "sg:classifiers":[
        {
            "category":"Restaurant",
            "type":"Food & Drink"
        }
    ],
    "sg:phone":"+1 773 265 1577",
    "sg:postcode":"60612",
    "sg:province":"IL",
    "sg:tags":[
        "seafood"
    ],
    "wof:name":"J & J Fish",
    "wof:placetype":"venue"
},
  "geometry": {"coordinates":[-87.705787,41.875199],"type":"Point"}
}