{
  "type": "Feature",
  "properties": {
    "iso:country":"US",
    "sg:address":"2140 E Co Rd 800",
    "sg:city":"Carthage",
    "sg:classifiers":[
        {
            "category":"Farming",
            "subcategory":"Farm",
            "type":"Manufacturing & Wholesale Goods"
        }
    ],
    "sg:phone":"+1 217 743 5300",
    "sg:postcode":"62321",
    "sg:province":"IL",
    "sg:tags":[
        "crop",
        "general"
    ],
    "wof:name":"Redenius Orland Farm",
    "wof:placetype":"venue"
},
  "geometry": {"coordinates":[-91.09471000000001,40.312444],"type":"Point"}
}