{
  "type": "Feature",
  "properties": {
    "iso:country":"US",
    "sg:address":"9331 S Cottage Grove Ave",
    "sg:city":"Chicago",
    "sg:classifiers":[
        {
            "category":"Personal",
            "subcategory":"Barber",
            "type":"Services"
        }
    ],
    "sg:phone":"+1 773 487 9747",
    "sg:postcode":"60619",
    "sg:province":"IL",
    "wof:name":"Taylor's Barber Shop",
    "wof:placetype":"venue"
},
  "geometry": {"coordinates":[-87.604401,41.724998],"type":"Point"}
}