{
  "type": "Feature",
  "properties": {
    "addr:full":"3521 Western Ave Mattoon IL 61938",
    "addr:housenumber":"3521",
    "addr:postcode":"61938",
    "addr:street":"Western Ave",
    "iso:country":"US",
    "sg:address":"3521 Western Ave",
    "sg:city":"Mattoon",
    "sg:classifiers":[
        {
            "category":"Shopping",
            "subcategory":"Discount & Variety Stores",
            "type":"Retail Goods"
        }
    ],
    "sg:phone":"+1   ",
    "sg:postcode":"61938",
    "sg:province":"IL",
    "sg:tags":[
        "merchandise",
        "general"
    ],
    "wof:name":"Show-N-Tell",
    "wof:placetype":"venue"
},
  "geometry": {"coordinates":[-88.404478,39.483228],"type":"Point"}
}