{
  "type": "Feature",
  "properties": {
    "addr:full":"2256 N Orchard Street Chicago IL 60614",
    "addr:housenumber":"2256",
    "addr:postcode":"60614",
    "addr:street":"N Orchard Street",
    "iso:country":"US",
    "sg:address":"2256 N Orchard Street",
    "sg:city":"Chicago",
    "sg:classifiers":[
        {
            "category":"Restaurant",
            "type":"Food & Drink"
        }
    ],
    "sg:phone":"+1 773 935 6744",
    "sg:postcode":"60614",
    "sg:province":"IL",
    "sg:tags":[
        "mexican"
    ],
    "wof:name":"Chipotle Mexican Grill",
    "wof:placetype":"venue"
},
  "geometry": {"coordinates":[-87.64624499999999,41.922995],"type":"Point"}
}