{
  "type": "Feature",
  "properties": {
    "addr:full":"5211 Center Ave Lisle IL 60532",
    "addr:housenumber":"5211",
    "addr:postcode":"60532",
    "addr:street":"Center Ave",
    "iso:country":"US",
    "sg:address":"5211 Center Ave",
    "sg:city":"Lisle",
    "sg:classifiers":[
        {
            "category":"Education",
            "subcategory":"School",
            "type":"Public Place"
        }
    ],
    "sg:phone":"+1 630 493 8000",
    "sg:postcode":"60532",
    "sg:province":"IL",
    "wof:name":"Educational Foundation Lisle",
    "wof:placetype":"venue"
},
  "geometry": {"coordinates":[-88.071466,41.79131],"type":"Point"}
}