{
  "type": "Feature",
  "properties": {
    "addr:full":"4905 E Vermillion Dr Chillicothe IL 61523",
    "addr:housenumber":"4905",
    "addr:postcode":"61523",
    "addr:street":"E Vermillion Dr",
    "iso:country":"US",
    "sg:address":"4905 E Vermillion Dr",
    "sg:city":"Chillicothe",
    "sg:classifiers":[
        {
            "category":"Social Services",
            "subcategory":"Child Care",
            "type":"Services"
        }
    ],
    "sg:phone":"+1 309 274 2851",
    "sg:postcode":"61523",
    "sg:province":"IL",
    "wof:name":"Helen Moore",
    "wof:placetype":"venue"
},
  "geometry": {"coordinates":[-89.515292,40.876339],"type":"Point"}
}