{
  "type": "Feature",
  "properties": {
    "addr:full":"39 S Milwaukee Ave Wheeling IL 60090",
    "addr:housenumber":"39",
    "addr:postcode":"60090",
    "addr:street":"S Milwaukee Ave",
    "iso:country":"US",
    "sg:address":"39 S Milwaukee Ave",
    "sg:city":"Wheeling",
    "sg:classifiers":[
        {
            "category":"Home & Garden",
            "subcategory":"Building Materials",
            "type":"Retail Goods"
        },
        {
            "category":"Building & Trades",
            "subcategory":"Construction",
            "type":"Services"
        },
        {
            "category":"Home & Garden",
            "subcategory":"Furniture",
            "type":"Retail Goods"
        }
    ],
    "sg:phone":"+1 847 215 1700",
    "sg:postcode":"60090",
    "sg:province":"IL",
    "sg:tags":[
        "bathroom",
        "cabinet",
        "improvement",
        "planning",
        "equipment-household",
        "remodeling",
        "kitchen"
    ],
    "sg:website":"http://www.aracabinets4u.com",
    "wof:name":"ARA Cabinets 4 U",
    "wof:placetype":"venue"
},
  "geometry": {"coordinates":[-87.90733899999999,42.13893],"type":"Point"}
}