{
  "type": "Feature",
  "properties": {
    "addr:full":"7340 S Merrill Ave Chicago IL 60649",
    "addr:housenumber":"7340",
    "addr:postcode":"60649",
    "addr:street":"S Merrill Ave",
    "iso:country":"US",
    "sg:address":"7340 S Merrill Ave",
    "sg:city":"Chicago",
    "sg:classifiers":[
        {
            "category":"Social Services",
            "type":"Services"
        }
    ],
    "sg:phone":"+1 773 955 1610",
    "sg:postcode":"60649",
    "sg:province":"IL",
    "sg:tags":[
        "counselor",
        "marriage",
        "family"
    ],
    "wof:name":"Evans & Evans",
    "wof:placetype":"venue"
},
  "geometry": {"coordinates":[-87.572563,41.761478],"type":"Point"}
}