{
  "type": "Feature",
  "properties": {
    "addr:full":"7217 W Forest Preserve Ave Chicago IL 60634",
    "addr:housenumber":"7217",
    "addr:postcode":"60634",
    "addr:street":"W Forest Preserve Ave",
    "iso:country":"US",
    "sg:address":"7217 W Forest Preserve Ave",
    "sg:city":"Chicago",
    "sg:classifiers":[
        {
            "category":"Professional",
            "type":"Services"
        },
        {
            "category":"Professional",
            "subcategory":"Business Services",
            "type":"Services"
        },
        {
            "category":"Professional",
            "subcategory":"Printing & Photocopies",
            "type":"Services"
        },
        {
            "category":"Shopping",
            "subcategory":"Stationery & Office Supplies",
            "type":"Retail Goods"
        },
        {
            "category":"Manufacturing",
            "subcategory":"Printing",
            "type":"Manufacturing & Wholesale Goods"
        },
        {
            "category":"Manufacturing",
            "subcategory":"Signs",
            "type":"Manufacturing & Wholesale Goods"
        }
    ],
    "sg:phone":"+1 708 456 5737",
    "sg:postcode":"60634",
    "sg:province":"IL",
    "sg:tags":[
        "machine",
        "document",
        "duplicating",
        "shipping",
        "materials-shipping",
        "packaging",
        "packing",
        "imaging",
        "copying",
        "digital",
        "copy"
    ],
    "sg:website":"http://www.fedex.com/Dropoff/start?FY11-FXO-YELLOWPAGES",
    "wof:name":"FedEx Office Print & Ship Center",
    "wof:placetype":"venue"
},
  "geometry": {"coordinates":[-87.836445,41.940346],"type":"Point"}
}