{
  "type": "Feature",
  "properties": {
    "iso:country":"US",
    "sg:address":"4033 N Lincoln Ave",
    "sg:city":"Chicago",
    "sg:classifiers":[
        {
            "category":"Retail",
            "subcategory":"Laundry & Dry Cleaning",
            "type":"Services"
        }
    ],
    "sg:phone":"+1 773 388 3020",
    "sg:postcode":"60618",
    "sg:province":"IL",
    "wof:name":"Four Seasons Dry Cleaning & Tailoring",
    "wof:placetype":"venue"
},
  "geometry": {"coordinates":[-87.679497,41.955002],"type":"Point"}
}