{
  "type": "Feature",
  "properties": {
    "iso:country":"US",
    "sg:address":"186 S Weber Rd",
    "sg:city":"Bolingbrook",
    "sg:classifiers":[
        {
            "category":"Manufacturing",
            "subcategory":"Rubber & Plastics",
            "type":"Manufacturing & Wholesale Goods"
        },
        {
            "category":"Autos & Motor Vehicles",
            "subcategory":"Auto Supplies",
            "type":"Retail Goods"
        },
        {
            "category":"Retail",
            "subcategory":"Auto Repair",
            "type":"Services"
        }
    ],
    "sg:phone":"+1 630 378 9294",
    "sg:postcode":"60490",
    "sg:province":"IL",
    "sg:tags":[
        "wheel",
        "tires-wholesale",
        "tire",
        "retread",
        "balancing",
        "wheels-aligning",
        "recap",
        "brake",
        "manufacturer"
    ],
    "sg:website":"http://www.ntb.com",
    "wof:name":"NTB - National Tire & Battery",
    "wof:placetype":"venue"
},
  "geometry": {"coordinates":[-88.121871,41.694258],"type":"Point"}
}