{
  "type": "Feature",
  "properties": {
    "iso:country":"US",
    "sg:address":"1732 W Bryn Mawr Ave",
    "sg:city":"Chicago",
    "sg:classifiers":[
        {
            "category":"Retail",
            "subcategory":"Photofinishing",
            "type":"Services"
        }
    ],
    "sg:phone":"+1 773 275 1820",
    "sg:postcode":"60660",
    "sg:province":"IL",
    "sg:tags":[
        "photo",
        "restoration",
        "retouching"
    ],
    "sg:website":"http://www.carrillophoto.com",
    "wof:name":"Carrillo Photo",
    "wof:placetype":"venue"
},
  "geometry": {"coordinates":[-87.674187,41.983383],"type":"Point"}
}