{
  "type": "Feature",
  "properties": {
    "addr:full":"500 N Michigan Ave # 300 Chicago IL 60611",
    "addr:housenumber":"500",
    "addr:postcode":"60611",
    "addr:street":"N Michigan Ave # 300",
    "iso:country":"US",
    "sg:address":"500 N Michigan Ave # 300",
    "sg:city":"Chicago",
    "sg:classifiers":[
        {
            "category":"Health Services",
            "subcategory":"Dentist",
            "type":"Services"
        }
    ],
    "sg:phone":"+1 312 644 6400",
    "sg:postcode":"60611",
    "sg:province":"IL",
    "sg:tags":[
        "equipment",
        "dental",
        "supply"
    ],
    "wof:name":"International Investigative Services Incorporated",
    "wof:placetype":"venue"
},
  "geometry": {"coordinates":[-87.624123,41.890911],"type":"Point"}
}