{
  "type": "Feature",
  "properties": {
    "iso:country":"US",
    "sg:address":"1733 W Newport Ave 1R",
    "sg:city":"Chicago",
    "sg:classifiers":[
        {
            "category":"Personal",
            "type":"Services"
        }
    ],
    "sg:phone":"+1 773 310 3737",
    "sg:postcode":"60657",
    "sg:province":"IL",
    "sg:tags":[
        "party",
        "planning",
        "event"
    ],
    "sg:website":"www.photoboothschicago.com",
    "wof:name":"Chicago Photo Booth Company",
    "wof:placetype":"venue"
},
  "geometry": {"coordinates":[-87.672513,41.943942],"type":"Point"}
}