{
  "type": "Feature",
  "properties": {
    "addr:full":"1892 Techny Ct Northbrook IL 60062",
    "addr:housenumber":"1892",
    "addr:postcode":"60062",
    "addr:street":"Techny Ct",
    "iso:country":"US",
    "sg:address":"1892 Techny Ct",
    "sg:city":"Northbrook",
    "sg:classifiers":[
        {
            "category":"Professional",
            "subcategory":"Computer Services",
            "type":"Services"
        }
    ],
    "sg:phone":"+1 847 509 0178",
    "sg:postcode":"60062",
    "sg:province":"IL",
    "sg:tags":[
        "consultant",
        "designer"
    ],
    "wof:name":"Cypress Consulting Group",
    "wof:placetype":"venue"
},
  "geometry": {"coordinates":[-87.82381599999999,42.116522],"type":"Point"}
}