{
  "type": "Feature",
  "properties": {
    "iso:country":"US",
    "sg:address":"253 Old Orchard Shopping Center",
    "sg:city":"Skokie",
    "sg:classifiers":[
        {
            "category":"Shopping",
            "subcategory":"Shoes",
            "type":"Retail Goods"
        }
    ],
    "sg:phone":"+1   ",
    "sg:postcode":"60077",
    "sg:province":"IL",
    "wof:name":"Lady Foot Locker",
    "wof:placetype":"venue"
},
  "geometry": {"coordinates":[-87.74808899999999,42.061588],"type":"Point"}
}