{
  "type": "Feature",
  "properties": {
    "addr:full":"1101 W Fulton Market Chicago IL 60607",
    "addr:housenumber":"1101",
    "addr:postcode":"60607",
    "addr:street":"W;Market",
    "iso:country":"US",
    "sg:address":"1101 W Fulton Market",
    "sg:city":"Chicago",
    "sg:classifiers":[
        {
            "category":"Personal",
            "subcategory":"Beauty Salon",
            "type":"Services"
        }
    ],
    "sg:phone":"+1 312 492 7377",
    "sg:postcode":"60607",
    "sg:province":"IL",
    "sg:tags":[
        "hair"
    ],
    "sg:website":"www.vpsalon.com",
    "wof:name":"VP Hair Salon Italy",
    "wof:placetype":"venue"
},
  "geometry": {"coordinates":[-87.654534,41.8867],"type":"Point"}
}