{
  "type": "Feature",
  "properties": {
    "iso:country":"US",
    "sg:address":"701 3rd Ave",
    "sg:city":"Joliet",
    "sg:classifiers":[
        {
            "category":"Education",
            "subcategory":"School",
            "type":"Public Place"
        }
    ],
    "sg:phone":"+1 815 723 2808",
    "sg:postcode":"60433",
    "sg:province":"IL",
    "wof:name":"Woodland School",
    "wof:placetype":"venue"
},
  "geometry": {"coordinates":[-88.062167,41.519072],"type":"Point"}
}