{
  "type": "Feature",
  "properties": {
    "iso:country":"US",
    "sg:address":"2105 Court St.",
    "sg:city":"Pekin",
    "sg:classifiers":[
        {
            "category":"Health Services",
            "subcategory":"Clinic",
            "type":"Services"
        },
        {
            "category":"Health Services",
            "subcategory":"Health Practitioner",
            "type":"Services"
        }
    ],
    "sg:phone":"+1 309 478 1672",
    "sg:postcode":"61554",
    "sg:province":"IL",
    "sg:tags":[
        "therapist",
        "therapy",
        "physical"
    ],
    "wof:name":"Champion Fitness Physical Therapy",
    "wof:placetype":"venue"
},
  "geometry": {"coordinates":[-89.61688100000001,40.558779],"type":"Point"}
}