{
  "type": "Feature",
  "properties": {
    "addr:full":"1204 Jonathon Ct Wauconda IL 60084",
    "addr:housenumber":"1204",
    "addr:postcode":"60084",
    "addr:street":"Jonathon Ct",
    "iso:country":"US",
    "sg:address":"1204 Jonathon Ct",
    "sg:city":"Wauconda",
    "sg:classifiers":[
        {
            "category":"Organizations",
            "subcategory":"Community Association",
            "type":"Services"
        }
    ],
    "sg:phone":"+1 847 487 4172",
    "sg:postcode":"60084",
    "sg:province":"IL",
    "wof:name":"Apple Ridge Estates",
    "wof:placetype":"venue"
},
  "geometry": {"coordinates":[-88.11759499999999,42.278037],"type":"Point"}
}