{
  "type": "Feature",
  "properties": {
    "addr:full":"5020 47th Ave Moline IL 61265",
    "addr:housenumber":"5020",
    "addr:postcode":"61265",
    "addr:street":"47Th Ave",
    "iso:country":"US",
    "sg:address":"5020 47th Ave",
    "sg:city":"Moline",
    "sg:classifiers":[
        {
            "category":"Health Services",
            "subcategory":"Dentist",
            "type":"Services"
        }
    ],
    "sg:phone":"+1 309 762 6800",
    "sg:postcode":"61265",
    "sg:province":"IL",
    "wof:name":"Gnatovich J",
    "wof:placetype":"venue"
},
  "geometry": {"coordinates":[-90.46639999999999,41.466702],"type":"Point"}
}