{
  "type": "Feature",
  "properties": {
    "iso:country":"US",
    "sg:address":"6616 Cermak Rd",
    "sg:city":"Berwyn",
    "sg:classifiers":[
        {
            "category":"Real Estate",
            "subcategory":"Real Estate Services",
            "type":"Services"
        },
        {
            "category":"Banks & Credit Unions",
            "subcategory":"Financial Services",
            "type":"Services"
        }
    ],
    "sg:phone":"+1 708 850 0002",
    "sg:postcode":"60402",
    "sg:province":"IL",
    "sg:tags":[
        "loan",
        "broker",
        "mortgage"
    ],
    "wof:name":"Quality Mortgage Services",
    "wof:placetype":"venue"
},
  "geometry": {"coordinates":[-87.788803,41.850399],"type":"Point"}
}