{
  "type": "Feature",
  "properties": {
    "iso:country":"US",
    "sg:address":"60 W Terra Cotta Ave",
    "sg:city":"Crystal Lake",
    "sg:classifiers":[
        {
            "category":"Food & Beverages",
            "subcategory":"Groceries & Convenience Stores",
            "type":"Retail Goods"
        }
    ],
    "sg:phone":"+1 815 455 4741",
    "sg:postcode":"60014",
    "sg:province":"IL",
    "sg:website":"www.whitehen.com",
    "wof:name":"White Hen Pantry",
    "wof:placetype":"venue"
},
  "geometry": {"coordinates":[-88.322859,42.248274],"type":"Point"}
}