{
  "type": "Feature",
  "properties": {
    "iso:country":"US",
    "sg:address":"1012 N 5th Ave",
    "sg:city":"Kankakee",
    "sg:classifiers":[
        {
            "category":"Organizations",
            "subcategory":"Labor Organization",
            "type":"Services"
        }
    ],
    "sg:phone":"+1 815 933 5041",
    "sg:postcode":"60901",
    "sg:province":"IL",
    "wof:name":"Carpenters",
    "wof:placetype":"venue"
},
  "geometry": {"coordinates":[-87.877645,41.133097],"type":"Point"}
}