{
  "type": "Feature",
  "properties": {
    "addr:full":"9605 Oak Park Ave Oak Lawn IL 60453",
    "addr:housenumber":"9605",
    "addr:postcode":"60453",
    "addr:street":"Oak Park Ave",
    "iso:country":"US",
    "sg:address":"9605 Oak Park Ave",
    "sg:city":"Oak Lawn",
    "sg:classifiers":[
        {
            "category":"Building & Trades",
            "subcategory":"Construction",
            "type":"Services"
        }
    ],
    "sg:phone":"+1 708 598 5800",
    "sg:postcode":"60453",
    "sg:province":"IL",
    "sg:tags":[
        "painter"
    ],
    "wof:name":"Decom Painting & Decorating Inc",
    "wof:placetype":"venue"
},
  "geometry": {"coordinates":[-87.78923,41.7173],"type":"Point"}
}