{
  "type": "Feature",
  "properties": {
    "iso:country":"US",
    "sg:address":"302 Prairie Ave",
    "sg:city":"Lockport",
    "sg:classifiers":[
        {
            "category":"Taxi",
            "type":"Transportation"
        }
    ],
    "sg:phone":"+1 815 726 8294",
    "sg:postcode":"60441",
    "sg:province":"IL",
    "sg:tags":[
        "taxicab"
    ],
    "wof:name":"Telecab Inc",
    "wof:placetype":"venue"
},
  "geometry": {"coordinates":[-88.061374,41.565714],"type":"Point"}
}