{
  "type": "Feature",
  "properties": {
    "iso:country":"US",
    "sg:address":"103 S Laurel St",
    "sg:city":"Staunton",
    "sg:classifiers":[
        {
            "category":"Home & Garden",
            "subcategory":"Home Furnishings",
            "type":"Retail Goods"
        }
    ],
    "sg:phone":"+1 618 635 2729",
    "sg:postcode":"62088",
    "sg:province":"IL",
    "sg:tags":[
        "quilting"
    ],
    "wof:name":"Warm N Cozy Quilting",
    "wof:placetype":"venue"
},
  "geometry": {"coordinates":[-89.786081,39.01213],"type":"Point"}
}