{
  "type": "Feature",
  "properties": {
    "iso:country":"US",
    "sg:address":"338 Cottage Ave",
    "sg:city":"Glen Ellyn",
    "sg:classifiers":[
        {
            "category":"Professional",
            "subcategory":"Lawyer & Legal Services",
            "type":"Services"
        }
    ],
    "sg:phone":"+1 630 469 0205",
    "sg:postcode":"60137",
    "sg:province":"IL",
    "wof:name":"Lofgren Richard J Atty",
    "wof:placetype":"venue"
},
  "geometry": {"coordinates":[-88.076401,41.8801],"type":"Point"}
}