{
  "type": "Feature",
  "properties": {
    "iso:country":"US",
    "sg:address":"4500 Dempster St",
    "sg:city":"Skokie",
    "sg:classifiers":[
        {
            "category":"Place Of Worship",
            "subcategory":"Synagogue",
            "type":"Public Place"
        },
        {
            "category":"Place Of Worship",
            "type":"Public Place"
        }
    ],
    "sg:phone":"+1 847 675 4152",
    "sg:postcode":"60076",
    "sg:province":"IL",
    "sg:tags":[
        "synagogues-reform",
        "church"
    ],
    "wof:name":"Gan Yeladim Ehntjc",
    "wof:placetype":"venue"
},
  "geometry": {"coordinates":[-87.740531,42.040771],"type":"Point"}
}