{
  "type": "Feature",
  "properties": {
    "iso:country":"US",
    "sg:address":"6124 W Cermak Rd",
    "sg:city":"Cicero",
    "sg:classifiers":[
        {
            "category":"Health Services",
            "subcategory":"Doctor",
            "type":"Services"
        }
    ],
    "sg:phone":"+1 708 484 5499",
    "sg:postcode":"60804",
    "sg:province":"IL",
    "sg:tags":[
        "medical"
    ],
    "wof:name":"Frank C Sedlak",
    "wof:placetype":"venue"
},
  "geometry": {"coordinates":[-87.776381,41.850951],"type":"Point"}
}