{
  "type": "Feature",
  "properties": {
    "iso:country":"US",
    "sg:address":"290 N Main St",
    "sg:city":"Breese",
    "sg:classifiers":[
        {
            "category":"Shopping",
            "subcategory":"Gifts & Souvenirs",
            "type":"Retail Goods"
        }
    ],
    "sg:phone":"+1   ",
    "sg:postcode":"62230",
    "sg:province":"IL",
    "wof:name":"Celebrations",
    "wof:placetype":"venue"
},
  "geometry": {"coordinates":[-89.527417,38.608813],"type":"Point"}
}