{
  "type": "Feature",
  "properties": {
    "iso:country":"US",
    "sg:address":"30115 S Readman Ln",
    "sg:city":"Wilmington",
    "sg:classifiers":[
        {
            "category":"Farming",
            "subcategory":"Farm",
            "type":"Manufacturing & Wholesale Goods"
        }
    ],
    "sg:phone":"+1 815 476 9814",
    "sg:postcode":"60481",
    "sg:province":"IL",
    "sg:tags":[
        "crop",
        "general"
    ],
    "wof:name":"Larry Readman",
    "wof:placetype":"venue"
},
  "geometry": {"coordinates":[-88.18739,41.334916],"type":"Point"}
}