{
  "type": "Feature",
  "properties": {
    "addr:full":"16230 Prince Dr South Holland IL 60473",
    "addr:housenumber":"16230",
    "addr:postcode":"60473",
    "addr:street":"Prince Dr",
    "iso:country":"US",
    "sg:address":"16230 Prince Dr",
    "sg:city":"South Holland",
    "sg:classifiers":[
        {
            "category":"Banks & Credit Unions",
            "subcategory":"Bank",
            "type":"Services"
        }
    ],
    "sg:phone":"+1 708 333 6335",
    "sg:postcode":"60473",
    "sg:province":"IL",
    "wof:name":"St Willibrod Credit Union",
    "wof:placetype":"venue"
},
  "geometry": {"coordinates":[-87.587898,41.600399],"type":"Point"}
}