{
  "type": "Feature",
  "properties": {
    "iso:country":"US",
    "sg:address":"120 Broadview Village Sq",
    "sg:city":"Broadview",
    "sg:classifiers":[
        {
            "category":"Personal",
            "subcategory":"Nail Salon",
            "type":"Services"
        }
    ],
    "sg:phone":"+1 708 343 5233",
    "sg:postcode":"60155",
    "sg:province":"IL",
    "wof:name":"Jade Nail Spa",
    "wof:placetype":"venue"
},
  "geometry": {"coordinates":[-87.852501,41.852901],"type":"Point"}
}