{
  "type": "Feature",
  "properties": {
    "addr:full":"403 N State St Jerseyville IL 62052",
    "addr:housenumber":"403",
    "addr:postcode":"62052",
    "addr:street":"N State St",
    "iso:country":"US",
    "sg:address":"403 N State St",
    "sg:city":"Jerseyville",
    "sg:classifiers":[
        {
            "category":"Restaurant",
            "type":"Food & Drink"
        }
    ],
    "sg:phone":"+1 618 498 9081",
    "sg:postcode":"62052",
    "sg:province":"IL",
    "wof:name":"White Spot",
    "wof:placetype":"venue"
},
  "geometry": {"coordinates":[-90.328997,39.121747],"type":"Point"}
}