{
  "type": "Feature",
  "properties": {
    "addr:full":"7444 West Wilson Avenue Chicago IL 60706-4549",
    "addr:housenumber":"7444",
    "addr:postcode":"60706-4549",
    "addr:street":"West Wilson Avenue",
    "iso:country":"US",
    "sg:address":"7444 West Wilson Avenue",
    "sg:city":"Chicago",
    "sg:classifiers":[
        {
            "category":"Manufacturing",
            "subcategory":"Electronics",
            "type":"Manufacturing & Wholesale Goods"
        }
    ],
    "sg:phone":"+1 708 867 9600",
    "sg:postcode":"60706-4549",
    "sg:province":"IL",
    "sg:website":"http://www.stratosoptical.com/",
    "wof:name":"Stratos International",
    "wof:placetype":"venue"
},
  "geometry": {"coordinates":[-87.814369,41.963539],"type":"Point"}
}