{
  "type": "Feature",
  "properties": {
    "addr:full":"4751 S Laporte Avenue Chicago IL 60638",
    "addr:housenumber":"4751",
    "addr:postcode":"60638",
    "addr:street":"S Laporte Avenue",
    "iso:country":"US",
    "sg:address":"4751 S Laporte Avenue",
    "sg:city":"Chicago",
    "sg:classifiers":[
        {
            "category":"Organizations",
            "subcategory":"Religious Organization",
            "type":"Services"
        }
    ],
    "sg:phone":"+1 773 585 0554",
    "sg:postcode":"60638",
    "sg:province":"IL",
    "wof:name":"Patterson Robert Rev",
    "wof:placetype":"venue"
},
  "geometry": {"coordinates":[-87.746595,41.805982],"type":"Point"}
}