{
  "type": "Feature",
  "properties": {
    "addr:full":"1218 W Main St Belleville IL 62220",
    "addr:housenumber":"1218",
    "addr:postcode":"62220",
    "addr:street":"W Main St",
    "iso:country":"US",
    "sg:address":"1218 W Main St",
    "sg:city":"Belleville",
    "sg:classifiers":[
        {
            "category":"Home & Garden",
            "subcategory":"Carpets & Floor Coverings",
            "type":"Retail Goods"
        }
    ],
    "sg:phone":"+1 618 234 5005",
    "sg:postcode":"62220",
    "sg:province":"IL",
    "sg:tags":[
        "material"
    ],
    "wof:name":"Mc Cullough's Flooring Ent",
    "wof:placetype":"venue"
},
  "geometry": {"coordinates":[-89.999092,38.516098],"type":"Point"}
}