{
  "type": "Feature",
  "properties": {
    "iso:country":"US",
    "sg:address":"3 Executive Woods Ct",
    "sg:city":"Swansea",
    "sg:classifiers":[
        {
            "category":"Insurance",
            "subcategory":"Hazard Insurance",
            "type":"Services"
        }
    ],
    "sg:phone":"+1 618 277 2000",
    "sg:postcode":"62226",
    "sg:province":"IL",
    "sg:tags":[
        "commercial",
        "business"
    ],
    "sg:website":"http://www.alternativesins.com",
    "wof:name":"Alternatives Insurance",
    "wof:placetype":"venue"
},
  "geometry": {"coordinates":[-89.98378,38.562809],"type":"Point"}
}