{
  "type": "Feature",
  "properties": {
    "addr:full":"15100 Central Ave Oak Forest IL 60452",
    "addr:postcode":"15100;60452",
    "addr:street":"Central Ave",
    "iso:country":"US",
    "sg:address":"15100 Central Ave",
    "sg:city":"Oak Forest",
    "sg:classifiers":[
        {
            "category":"Education",
            "subcategory":"Preschool",
            "type":"Public Place"
        },
        {
            "category":"Education",
            "subcategory":"School",
            "type":"Public Place"
        }
    ],
    "sg:phone":"+1 708 687 2170",
    "sg:postcode":"60452",
    "sg:province":"IL",
    "sg:tags":[
        "elementary"
    ],
    "wof:name":"Lutheran Church of the Resurrection",
    "wof:placetype":"venue"
},
  "geometry": {"coordinates":[-87.7565,41.617001],"type":"Point"}
}