{
  "type": "Feature",
  "properties": {
    "iso:country":"US",
    "sg:address":"1072 W Riverside Blvd",
    "sg:city":"Rockford",
    "sg:classifiers":[
        {
            "category":"Professional",
            "type":"Services"
        }
    ],
    "sg:phone":"+1 815 316 8372",
    "sg:postcode":"61103",
    "sg:province":"IL",
    "sg:tags":[
        "establishment"
    ],
    "wof:name":"Barbara Olson Ctr Of Hope",
    "wof:placetype":"venue"
},
  "geometry": {"coordinates":[-89.076447,42.315681],"type":"Point"}
}