{
  "type": "Feature",
  "properties": {
    "addr:full":"16411 Evans Ave South Holland IL 60473",
    "addr:housenumber":"16411",
    "addr:postcode":"60473",
    "addr:street":"Evans Ave",
    "iso:country":"US",
    "sg:address":"16411 Evans Ave",
    "sg:city":"South Holland",
    "sg:classifiers":[
        {
            "category":"Building & Trades",
            "subcategory":"Cleaning & Sanitation",
            "type":"Services"
        }
    ],
    "sg:phone":"+1 708 333 2117",
    "sg:postcode":"60473",
    "sg:province":"IL",
    "sg:tags":[
        "carpet"
    ],
    "wof:name":"Smith & Son Carpet & Upholstery",
    "wof:placetype":"venue"
},
  "geometry": {"coordinates":[-87.600601,41.596802],"type":"Point"}
}