{
  "type": "Feature",
  "properties": {
    "iso:country":"US",
    "sg:address":"165 Falcon Dr",
    "sg:city":"Highland",
    "sg:classifiers":[
        {
            "category":"Building & Trades",
            "subcategory":"Construction",
            "type":"Services"
        }
    ],
    "sg:phone":"+1 618 654 1349",
    "sg:postcode":"62249",
    "sg:province":"IL",
    "sg:tags":[
        "steel",
        "erection",
        "structural"
    ],
    "wof:name":"Brave PTG Wallcovering Ji",
    "wof:placetype":"venue"
},
  "geometry": {"coordinates":[-89.658846,38.741119],"type":"Point"}
}