{
  "type": "Feature",
  "properties": {
    "addr:full":"50 Lakeview Pkwy Vernon Hills IL 60061",
    "addr:housenumber":"50",
    "addr:postcode":"60061",
    "addr:street":"Lakeview Pkwy",
    "iso:country":"US",
    "sg:address":"50 Lakeview Pkwy",
    "sg:city":"Vernon Hills",
    "sg:classifiers":[
        {
            "category":"Manufacturing",
            "subcategory":"Food",
            "type":"Manufacturing & Wholesale Goods"
        }
    ],
    "sg:phone":"+1 847 383 9000",
    "sg:postcode":"60061",
    "sg:province":"IL",
    "sg:tags":[
        "mfg"
    ],
    "wof:name":"Prnod-Ricard USA",
    "wof:placetype":"venue"
},
  "geometry": {"coordinates":[-87.947374,42.22844],"type":"Point"}
}