{
  "type": "Feature",
  "properties": {
    "iso:country":"US",
    "sg:address":"2024 Prairie Ave",
    "sg:city":"Quincy",
    "sg:classifiers":[
        {
            "category":"Manufacturing",
            "subcategory":"Tools & Machinery",
            "type":"Manufacturing & Wholesale Goods"
        }
    ],
    "sg:phone":"+1 217 228 8555",
    "sg:postcode":"62301",
    "sg:province":"IL",
    "sg:tags":[
        "machine",
        "shop"
    ],
    "wof:name":"Degitz Engineerd Product-Mach",
    "wof:placetype":"venue"
},
  "geometry": {"coordinates":[-91.383937,39.929452],"type":"Point"}
}