{
  "type": "Feature",
  "properties": {
    "iso:country":"US",
    "sg:address":"609 S Belt W",
    "sg:city":"Belleville",
    "sg:classifiers":[
        {
            "category":"Autos & Motor Vehicles",
            "subcategory":"Automobile Sales",
            "type":"Retail Goods"
        },
        {
            "category":"Retail",
            "subcategory":"Auto Repair",
            "type":"Services"
        }
    ],
    "sg:phone":"+1 618 222 9950",
    "sg:postcode":"62220",
    "sg:province":"IL",
    "sg:tags":[
        "diagnostic",
        "equipment",
        "brake",
        "air conditioning"
    ],
    "sg:website":"http://www.bertcoautomotive.com",
    "wof:name":"Bertco Automotive Inc",
    "wof:placetype":"venue"
},
  "geometry": {"coordinates":[-89.992223,38.502477],"type":"Point"}
}