{
  "type": "Feature",
  "properties": {
    "iso:country":"US",
    "sg:address":"40751 N Forest View Rd",
    "sg:city":"Wadsworth",
    "sg:classifiers":[
        {
            "category":"Building & Trades",
            "subcategory":"Construction",
            "type":"Services"
        }
    ],
    "sg:phone":"+1 847 872 5550",
    "sg:postcode":"60083",
    "sg:province":"IL",
    "sg:tags":[
        "contractor"
    ],
    "wof:name":"Norms Gutter Shop",
    "wof:placetype":"venue"
},
  "geometry": {"coordinates":[-87.888557,42.45453],"type":"Point"}
}