{
  "type": "Feature",
  "properties": {
    "iso:country":"US",
    "sg:address":"120 S Jacksonville St",
    "sg:city":"White Hall",
    "sg:classifiers":[
        {
            "category":"Government",
            "subcategory":"Post Office",
            "type":"Public Place"
        }
    ],
    "sg:phone":"+1 217 374 2311",
    "sg:postcode":"62092",
    "sg:province":"IL",
    "wof:name":"US Post Office",
    "wof:placetype":"venue"
},
  "geometry": {"coordinates":[-90.402201,39.436614],"type":"Point"}
}