{
  "type": "Feature",
  "properties": {
    "iso:country":"US",
    "sg:address":"1138 State St",
    "sg:city":"Lemont",
    "sg:classifiers":[
        {
            "category":"Restaurant",
            "type":"Food & Drink"
        }
    ],
    "sg:phone":"+1 630 243 0403",
    "sg:postcode":"60439",
    "sg:province":"IL",
    "wof:name":"China Wok",
    "wof:placetype":"venue"
},
  "geometry": {"coordinates":[-88.00001,41.660731],"type":"Point"}
}