{
  "type": "Feature",
  "properties": {
    "iso:country":"US",
    "sg:address":"1525 S Main St",
    "sg:city":"Bloomington",
    "sg:classifiers":[
        {
            "category":"Restaurant",
            "type":"Food & Drink"
        }
    ],
    "sg:menulink":"http://www.allmenus.com/il/bloomington-city/96163-taco-johns/menu/",
    "sg:phone":"+1 309 828 4336",
    "sg:postcode":"61701",
    "sg:province":"IL",
    "sg:tags":[
        "american",
        "mexican"
    ],
    "wof:name":"Taco John's",
    "wof:placetype":"venue"
},
  "geometry": {"coordinates":[-88.992999,40.464481],"type":"Point"}
}