{
  "type": "Feature",
  "properties": {
    "iso:country":"US",
    "sg:address":"3033 E Ogden Ave",
    "sg:city":"Lisle",
    "sg:classifiers":[
        {
            "category":"Real Estate",
            "subcategory":"Real Estate Operator",
            "type":"Services"
        }
    ],
    "sg:phone":"+1 630 548 2175",
    "sg:postcode":"60532",
    "sg:province":"IL",
    "sg:tags":[
        "building",
        "nonresidential"
    ],
    "wof:name":"Midway Ofc Center",
    "wof:placetype":"venue"
},
  "geometry": {"coordinates":[-88.109386,41.796389],"type":"Point"}
}