{
  "type": "Feature",
  "properties": {
    "addr:full":"95 W Grand Ave Lake Villa IL 60046",
    "addr:housenumber":"95",
    "addr:postcode":"60046",
    "addr:street":"W Grand Ave",
    "iso:country":"US",
    "sg:address":"95 W Grand Ave",
    "sg:city":"Lake Villa",
    "sg:classifiers":[
        {
            "category":"Professional",
            "subcategory":"Business Services",
            "type":"Services"
        }
    ],
    "sg:phone":"+1 847 356 5020",
    "sg:postcode":"60046",
    "sg:province":"IL",
    "wof:name":"Complete Business Svc",
    "wof:placetype":"venue"
},
  "geometry": {"coordinates":[-88.084476,42.415418],"type":"Point"}
}