{
  "type": "Feature",
  "properties": {
    "iso:country":"US",
    "sg:address":"3320 N Harlem Ave",
    "sg:city":"Chicago",
    "sg:classifiers":[
        {
            "category":"Shopping",
            "subcategory":"Clothing, Apparel, & Fashions",
            "type":"Retail Goods"
        }
    ],
    "sg:phone":"+1 773 889 5513",
    "sg:postcode":"60634",
    "sg:province":"IL",
    "sg:tags":[
        "clothing",
        "women's"
    ],
    "wof:name":"Annabella's Fashion",
    "wof:placetype":"venue"
},
  "geometry": {"coordinates":[-87.806602,41.940498],"type":"Point"}
}