{
  "type": "Feature",
  "properties": {
    "iso:country":"US",
    "sg:address":"1407 N Lewis Ave",
    "sg:city":"Waukegan",
    "sg:classifiers":[
        {
            "category":"Shopping",
            "subcategory":"Clothing, Apparel, & Fashions",
            "type":"Retail Goods"
        }
    ],
    "sg:phone":"+1 847 336 0573",
    "sg:postcode":"60085",
    "sg:province":"IL",
    "wof:name":"Rainbow",
    "wof:placetype":"venue"
},
  "geometry": {"coordinates":[-87.85538200000001,42.380384],"type":"Point"}
}