{
  "type": "Feature",
  "properties": {
    "addr:full":"2577 United Ln Elk Grove Vlg IL 60007",
    "addr:housenumber":"2577",
    "addr:postcode":"60007",
    "addr:street":"United Ln",
    "iso:country":"US",
    "sg:address":"2577 United Ln",
    "sg:city":"Elk Grove Vlg",
    "sg:classifiers":[
        {
            "category":"Building & Trades",
            "subcategory":"Plumbing",
            "type":"Services"
        }
    ],
    "sg:phone":"+1 847 238 0300",
    "sg:postcode":"60007",
    "sg:province":"IL",
    "sg:tags":[
        "sheet",
        "metal",
        "system",
        "contractor",
        "conditioning",
        "air"
    ],
    "sg:website":"www.doctorheat.com",
    "wof:name":"Al Kaplan Heating & Air Cond",
    "wof:placetype":"venue"
},
  "geometry": {"coordinates":[-87.94584999999999,41.989162],"type":"Point"}
}