{
  "type": "Feature",
  "properties": {
    "iso:country":"US",
    "sg:address":"210 N Saint Paul St",
    "sg:city":"Spring Valley",
    "sg:classifiers":[
        {
            "category":"Insurance",
            "subcategory":"Insurance Agent",
            "type":"Services"
        }
    ],
    "sg:phone":"+1 815 663 6141",
    "sg:postcode":"61326",
    "sg:province":"IL",
    "wof:name":"Guerrini Financial Svc",
    "wof:placetype":"venue"
},
  "geometry": {"coordinates":[-89.251498,41.267156],"type":"Point"}
}