{
  "type": "Feature",
  "properties": {
    "iso:country":"US",
    "sg:address":"300 E College Ave",
    "sg:city":"Eureka",
    "sg:classifiers":[
        {
            "category":"Organizations",
            "subcategory":"Community Association",
            "type":"Services"
        }
    ],
    "sg:phone":"+1 309 467 6317",
    "sg:postcode":"61530",
    "sg:province":"IL",
    "sg:tags":[
        "alumnus"
    ],
    "wof:name":"Department Dev & Alumni Off",
    "wof:placetype":"venue"
},
  "geometry": {"coordinates":[-89.26913999999999,40.714448],"type":"Point"}
}