{
  "type": "Feature",
  "properties": {
    "addr:full":"411 Tiffany Dr Waukegan IL 60085",
    "addr:housenumber":"411",
    "addr:postcode":"60085",
    "addr:street":"Tiffany Dr",
    "iso:country":"US",
    "sg:address":"411 Tiffany Dr",
    "sg:city":"Waukegan",
    "sg:classifiers":[
        {
            "category":"Professional",
            "subcategory":"Business Services",
            "type":"Services"
        }
    ],
    "sg:phone":"+1 847 672 5972",
    "sg:postcode":"60085",
    "sg:province":"IL",
    "wof:name":"Healthwise Enterprise",
    "wof:placetype":"venue"
},
  "geometry": {"coordinates":[-87.86046899999999,42.364824],"type":"Point"}
}