{
  "type": "Feature",
  "properties": {
    "addr:full":"403 E Center St Eureka IL 61530",
    "addr:housenumber":"403",
    "addr:postcode":"61530",
    "addr:street":"E Center St",
    "iso:country":"US",
    "sg:address":"403 E Center St",
    "sg:city":"Eureka",
    "sg:classifiers":[
        {
            "category":"Professional",
            "type":"Services"
        }
    ],
    "sg:phone":"+1 309 467 6257",
    "sg:postcode":"61530",
    "sg:province":"IL",
    "wof:name":"Patient Assistance Svc",
    "wof:placetype":"venue"
},
  "geometry": {"coordinates":[-89.26843,40.721419],"type":"Point"}
}