{
  "type": "Feature",
  "properties": {
    "iso:country":"US",
    "sg:address":"9400 W Foster Ave",
    "sg:city":"Chicago",
    "sg:classifiers":[
        {
            "category":"Banks & Credit Unions",
            "subcategory":"Bank",
            "type":"Services"
        }
    ],
    "sg:phone":"+1 773 992 2000",
    "sg:postcode":"60656",
    "sg:province":"IL",
    "sg:tags":[
        "loan",
        "broker",
        "mortgage"
    ],
    "wof:name":"U S Financial Ltd",
    "wof:placetype":"venue"
},
  "geometry": {"coordinates":[-87.862277,41.97331],"type":"Point"}
}