{
  "type": "Feature",
  "properties": {
    "iso:country":"US",
    "sg:address":"3 E Dundee Rd",
    "sg:city":"Barrington",
    "sg:classifiers":[
        {
            "category":"Health Services",
            "subcategory":"Doctor",
            "type":"Services"
        }
    ],
    "sg:phone":"+1 847 842 2410",
    "sg:postcode":"60010",
    "sg:province":"IL",
    "sg:tags":[
        "dentist"
    ],
    "wof:name":"Barrington Prodental Care P C",
    "wof:placetype":"venue"
},
  "geometry": {"coordinates":[-88.135347,42.128335],"type":"Point"}
}