{
  "type": "Feature",
  "properties": {
    "iso:country":"US",
    "sg:address":"7060 Forest Preserve Dr",
    "sg:city":"Norridge",
    "sg:classifiers":[
        {
            "category":"Restaurant",
            "type":"Food & Drink"
        }
    ],
    "sg:phone":"+1 708 457 0203",
    "sg:postcode":"60706",
    "sg:province":"IL",
    "sg:tags":[
        "pizza"
    ],
    "wof:name":"Pizza Hut & Wing Street",
    "wof:placetype":"venue"
},
  "geometry": {"coordinates":[-87.815378,41.949906],"type":"Point"}
}