{
  "type": "Feature",
  "properties": {
    "iso:country":"US",
    "sg:address":"2910 S 17th Ave",
    "sg:city":"Broadview",
    "sg:classifiers":[
        {
            "category":"Wholesale",
            "subcategory":"Vending Machines",
            "type":"Manufacturing & Wholesale Goods"
        }
    ],
    "sg:phone":"+1 708 344 9170",
    "sg:postcode":"60155",
    "sg:province":"IL",
    "sg:tags":[
        "screw",
        "product"
    ],
    "wof:name":"Merit Screw Machine Products Inc",
    "wof:placetype":"venue"
},
  "geometry": {"coordinates":[-87.852493,41.851073],"type":"Point"}
}