{
  "type": "Feature",
  "properties": {
    "iso:country":"US",
    "sg:address":"2532 N Lincoln Ave",
    "sg:city":"Chicago",
    "sg:classifiers":[
        {
            "category":"Health Services",
            "subcategory":"Doctor",
            "type":"Services"
        }
    ],
    "sg:phone":"+1 773 472 7646",
    "sg:postcode":"60614",
    "sg:province":"IL",
    "sg:tags":[
        "psychologist"
    ],
    "wof:name":"Scott Deborah Ph.D.",
    "wof:placetype":"venue"
},
  "geometry": {"coordinates":[-87.652404,41.928038],"type":"Point"}
}