{
  "type": "Feature",
  "properties": {
    "iso:country":"US",
    "sg:address":"1400 N Western Ave",
    "sg:city":"Lake Forest",
    "sg:classifiers":[
        {
            "category":"Health Services",
            "subcategory":"Doctor",
            "type":"Services"
        }
    ],
    "sg:phone":"+1 847 234 4405",
    "sg:postcode":"60045",
    "sg:province":"IL",
    "sg:tags":[
        "dentist"
    ],
    "wof:name":"Robert E Law DDS",
    "wof:placetype":"venue"
},
  "geometry": {"coordinates":[-87.845081,42.266435],"type":"Point"}
}