{
  "type": "Feature",
  "properties": {
    "iso:country":"US",
    "sg:address":"945 N McLean Blvd",
    "sg:city":"Elgin",
    "sg:classifiers":[
        {
            "category":"Banks & Credit Unions",
            "subcategory":"Bank",
            "type":"Services"
        }
    ],
    "sg:phone":"+1 847 695 5400",
    "sg:postcode":"60123",
    "sg:province":"IL",
    "sg:tags":[
        "cashing",
        "check"
    ],
    "wof:name":"Check 'n Go",
    "wof:placetype":"venue"
},
  "geometry": {"coordinates":[-88.314831,42.010254],"type":"Point"}
}