{
  "type": "Feature",
  "properties": {
    "iso:country":"US",
    "sg:address":"2 N Williams St",
    "sg:city":"Crystal Lake",
    "sg:classifiers":[
        {
            "category":"Social Services",
            "type":"Services"
        }
    ],
    "sg:phone":"+1 847 836 1400",
    "sg:postcode":"60014",
    "sg:province":"IL",
    "sg:website":"www.horizons-blind.org",
    "wof:name":"Horizons For The Blind Inc",
    "wof:placetype":"venue"
},
  "geometry": {"coordinates":[-88.317979,42.24235],"type":"Point"}
}