{
  "type": "Feature",
  "properties": {
    "iso:country":"US",
    "sg:address":"822 W Jefferson St",
    "sg:city":"Joliet",
    "sg:classifiers":[
        {
            "category":"Building & Trades",
            "subcategory":"Construction",
            "type":"Services"
        }
    ],
    "sg:phone":"+1 815 725 4700",
    "sg:postcode":"60435",
    "sg:province":"IL",
    "sg:tags":[
        "general",
        "contractor"
    ],
    "wof:name":"Onsite Construction",
    "wof:placetype":"venue"
},
  "geometry": {"coordinates":[-88.10110299999999,41.523385],"type":"Point"}
}