{
  "type": "Feature",
  "properties": {
    "addr:full":"2975 N Broadway St Chicago IL 60657",
    "addr:housenumber":"2975",
    "addr:postcode":"60657",
    "addr:street":"N Broadway St",
    "iso:country":"US",
    "sg:address":"2975 N Broadway St",
    "sg:city":"Chicago",
    "sg:classifiers":[
        {
            "category":"Education",
            "subcategory":"School",
            "type":"Public Place"
        }
    ],
    "sg:phone":"+1 708 385 2450",
    "sg:postcode":"60657",
    "sg:province":"IL",
    "sg:tags":[
        "child",
        "day",
        "care"
    ],
    "wof:name":"Horace Mann Kindergarten",
    "wof:placetype":"venue"
},
  "geometry": {"coordinates":[-87.644198,41.936289],"type":"Point"}
}