{
  "type": "Feature",
  "properties": {
    "addr:full":"4200 Columbus St Ottawa IL 61350",
    "addr:housenumber":"4200",
    "addr:postcode":"61350",
    "addr:street":"Columbus St",
    "iso:country":"US",
    "sg:address":"4200 Columbus St",
    "sg:city":"Ottawa",
    "sg:classifiers":[
        {
            "category":"Manufacturing",
            "subcategory":"Tools & Machinery",
            "type":"Manufacturing & Wholesale Goods"
        }
    ],
    "sg:phone":"+1 815 431 8100",
    "sg:postcode":"61350",
    "sg:province":"IL",
    "sg:tags":[
        "photographic",
        "mfg"
    ],
    "wof:name":"Clover Business Products",
    "wof:placetype":"venue"
},
  "geometry": {"coordinates":[-88.83584500000001,41.38069],"type":"Point"}
}