{
  "type": "Feature",
  "properties": {
    "iso:country":"US",
    "sg:address":"6611 W Archer Ave",
    "sg:city":"Chicago",
    "sg:classifiers":[
        {
            "category":"Banks & Credit Unions",
            "subcategory":"Bureau De Change",
            "type":"Services"
        }
    ],
    "sg:phone":"+1 773 586 2135",
    "sg:postcode":"60638",
    "sg:province":"IL",
    "sg:tags":[
        "currency",
        "exchange",
        "broker",
        "foreign"
    ],
    "wof:name":"New Archer-Nash Currency Inc",
    "wof:placetype":"venue"
},
  "geometry": {"coordinates":[-87.787069,41.792269],"type":"Point"}
}