{
  "type": "Feature",
  "properties": {
    "addr:full":"500 N Michigan Ave Chicago IL 60611",
    "addr:housenumber":"500",
    "addr:postcode":"60611",
    "addr:street":"N Michigan Ave",
    "iso:country":"US",
    "sg:address":"500 N Michigan Ave",
    "sg:city":"Chicago",
    "sg:classifiers":[
        {
            "category":"Shopping",
            "subcategory":"Mobile Phones",
            "type":"Retail Goods"
        }
    ],
    "sg:phone":"+1 312 464 1390",
    "sg:postcode":"60611",
    "sg:province":"IL",
    "wof:name":"Verizon Wireless",
    "wof:placetype":"venue"
},
  "geometry": {"coordinates":[-87.62190200000001,41.896801],"type":"Point"}
}