{
  "type": "Feature",
  "properties": {
    "addr:full":"1814 Harcourt Dr Woodridge IL 60517",
    "addr:housenumber":"1814",
    "addr:postcode":"60517",
    "addr:street":"Harcourt Dr",
    "iso:country":"US",
    "sg:address":"1814 Harcourt Dr",
    "sg:city":"Woodridge",
    "sg:classifiers":[
        {
            "category":"Travel",
            "subcategory":"Travel Agent",
            "type":"Entertainment"
        }
    ],
    "sg:phone":"+1 630 972 2320",
    "sg:postcode":"60517",
    "sg:province":"IL",
    "wof:name":"Ultimate Dive Travel Ltd",
    "wof:placetype":"venue"
},
  "geometry": {"coordinates":[-88.029619,41.739665],"type":"Point"}
}