{
  "type": "Feature",
  "properties": {
    "iso:country":"US",
    "sg:address":"609 N Heitter Rd",
    "sg:city":"Freeport",
    "sg:phone":"+1 815 232 2504",
    "sg:postcode":"61032",
    "sg:province":"IL",
    "sg:tags":[
        "farm",
        "corn",
        "soybean"
    ],
    "wof:name":"Richard Plager",
    "wof:placetype":"venue"
},
  "geometry": {"coordinates":[-89.768264,42.304972],"type":"Point"}
}