{
  "type": "Feature",
  "properties": {
    "iso:country":"US",
    "sg:address":"10439 S Prospect Ave",
    "sg:city":"Chicago",
    "sg:classifiers":[
        {
            "category":"Manufacturing",
            "subcategory":"Rubber & Plastics",
            "type":"Manufacturing & Wholesale Goods"
        }
    ],
    "sg:phone":"+1 773 233 5083",
    "sg:postcode":"60643",
    "sg:province":"IL",
    "sg:tags":[
        "tube",
        "mfg"
    ],
    "wof:name":"BF Stone Ltd",
    "wof:placetype":"venue"
},
  "geometry": {"coordinates":[-87.66198,41.704692],"type":"Point"}
}