{
  "type": "Feature",
  "properties": {
    "iso:country":"US",
    "sg:address":"8725 Narragansett Ave",
    "sg:city":"Morton Grove",
    "sg:classifiers":[
        {
            "category":"Professional",
            "subcategory":"Accounting & Tax Preparation",
            "type":"Services"
        }
    ],
    "sg:phone":"+1 847 583 8800",
    "sg:postcode":"60053",
    "sg:province":"IL",
    "wof:name":"Chamlin & Associates",
    "wof:placetype":"venue"
},
  "geometry": {"coordinates":[-87.78598599999999,42.040213],"type":"Point"}
}