{
  "type": "Feature",
  "properties": {
    "addr:full":"202 E Kirkwood St Odin IL 62870",
    "addr:housenumber":"202",
    "addr:postcode":"62870",
    "addr:street":"E Kirkwood St",
    "iso:country":"US",
    "sg:address":"202 E Kirkwood St",
    "sg:city":"Odin",
    "sg:classifiers":[
        {
            "category":"Retail",
            "subcategory":"Laundry & Dry Cleaning",
            "type":"Services"
        }
    ],
    "sg:phone":"+1 618 775 6595",
    "sg:postcode":"62870",
    "sg:province":"IL",
    "sg:tags":[
        "cleaners",
        "upholstery"
    ],
    "wof:name":"D & E Upholstery",
    "wof:placetype":"venue"
},
  "geometry": {"coordinates":[-89.05217500000001,38.617255],"type":"Point"}
}