{
  "type": "Feature",
  "properties": {
    "addr:full":"2927 W Devon Ave Chicago IL 60659",
    "addr:housenumber":"2927",
    "addr:postcode":"60659",
    "addr:street":"W Devon Ave",
    "iso:country":"US",
    "sg:address":"2927 W Devon Ave",
    "sg:city":"Chicago",
    "sg:classifiers":[
        {
            "category":"Restaurant",
            "type":"Food & Drink"
        }
    ],
    "sg:phone":"+1 773 743 0297",
    "sg:postcode":"60659",
    "sg:province":"IL",
    "sg:tags":[
        "chinese"
    ],
    "wof:name":"Jumbo House Chinese Restaurant",
    "wof:placetype":"venue"
},
  "geometry": {"coordinates":[-87.70259900000001,41.997299],"type":"Point"}
}