{
  "type": "Feature",
  "properties": {
    "addr:full":"350 N Clark St Chicago IL 60654",
    "addr:housenumber":"350",
    "addr:postcode":"60654",
    "addr:street":"N Clark St",
    "iso:country":"US",
    "sg:address":"350 N Clark St",
    "sg:city":"Chicago",
    "sg:classifiers":[
        {
            "category":"Retail",
            "subcategory":"Auto Repair",
            "type":"Services"
        }
    ],
    "sg:phone":"+1 847 489 2590",
    "sg:postcode":"60654",
    "sg:province":"IL",
    "sg:tags":[
        "detailing"
    ],
    "sg:website":"www.autodetailchicago.com",
    "wof:name":"Auto Detail Chicago, LLC",
    "wof:placetype":"venue"
},
  "geometry": {"coordinates":[-87.63120499999999,41.888836],"type":"Point"}
}