{
  "type": "Feature",
  "properties": {
    "iso:country":"US",
    "sg:address":"541 W Williams St",
    "sg:city":"Kankakee",
    "sg:classifiers":[
        {
            "category":"Building & Trades",
            "subcategory":"Construction",
            "type":"Services"
        }
    ],
    "sg:phone":"+1 815 933 7903",
    "sg:postcode":"60901",
    "sg:province":"IL",
    "sg:tags":[
        "siding",
        "contractor"
    ],
    "wof:name":"Clifford Dunsworth",
    "wof:placetype":"venue"
},
  "geometry": {"coordinates":[-87.872691,41.129802],"type":"Point"}
}