{
  "type": "Feature",
  "properties": {
    "addr:full":"2735 W 99th St Chicago IL 60655",
    "addr:housenumber":"2735",
    "addr:postcode":"60655",
    "addr:street":"W 99Th St",
    "iso:country":"US",
    "sg:address":"2735 W 99th St",
    "sg:city":"Chicago",
    "sg:classifiers":[
        {
            "category":"Professional",
            "type":"Services"
        }
    ],
    "sg:phone":"+1 773 779 3251",
    "sg:postcode":"60655",
    "sg:province":"IL",
    "sg:tags":[
        "art",
        "fine",
        "artist"
    ],
    "wof:name":"Calligraphy & Graphics Inc",
    "wof:placetype":"venue"
},
  "geometry": {"coordinates":[-87.690528,41.71358],"type":"Point"}
}