{
  "type": "Feature",
  "properties": {
    "addr:full":"6050 159th St Oak Forest IL 60452",
    "addr:housenumber":"6050",
    "addr:postcode":"60452",
    "addr:street":"159Th St",
    "iso:country":"US",
    "sg:address":"6050 159th St",
    "sg:city":"Oak Forest",
    "sg:classifiers":[
        {
            "category":"Food & Beverages",
            "subcategory":"Groceries & Convenience Stores",
            "type":"Retail Goods"
        }
    ],
    "sg:phone":"+1   ",
    "sg:postcode":"60452",
    "sg:province":"IL",
    "wof:name":"Kwick Pantry Inc",
    "wof:placetype":"venue"
},
  "geometry": {"coordinates":[-87.767555,41.602777],"type":"Point"}
}