{
  "type": "Feature",
  "properties": {
    "addr:full":"11212 S Western Avenue Chicago IL 60643",
    "addr:housenumber":"11212",
    "addr:postcode":"60643",
    "addr:street":"S Western Avenue",
    "iso:country":"US",
    "sg:address":"11212 S Western Avenue",
    "sg:city":"Chicago",
    "sg:classifiers":[
        {
            "category":"Building & Trades",
            "subcategory":"Cleaning & Sanitation",
            "type":"Services"
        }
    ],
    "sg:phone":"+1 773 239 9900",
    "sg:postcode":"60643",
    "sg:province":"IL",
    "sg:tags":[
        "home"
    ],
    "wof:name":"Ih Professional",
    "wof:placetype":"venue"
},
  "geometry": {"coordinates":[-87.681093,41.689198],"type":"Point"}
}