{
  "type": "Feature",
  "properties": {
    "addr:full":"2238 Lynn Dr Montgomery IL 60538",
    "addr:housenumber":"2238",
    "addr:postcode":"60538",
    "addr:street":"Lynn Dr",
    "iso:country":"US",
    "sg:address":"2238 Lynn Dr",
    "sg:city":"Montgomery",
    "sg:classifiers":[
        {
            "category":"Professional",
            "subcategory":"Computer Services",
            "type":"Services"
        }
    ],
    "sg:phone":"+1 630 362 1005",
    "sg:postcode":"60538",
    "sg:province":"IL",
    "sg:tags":[
        "information",
        "consulting",
        "technology"
    ],
    "wof:name":"PC Service Now Inc",
    "wof:placetype":"venue"
},
  "geometry": {"coordinates":[-88.38958599999999,41.717197],"type":"Point"}
}