{
  "type": "Feature",
  "properties": {
    "addr:full":"4832 N Broadway St Chicago IL 60640",
    "addr:housenumber":"4832",
    "addr:postcode":"60640",
    "addr:street":"N Broadway St",
    "iso:country":"US",
    "sg:address":"4832 N Broadway St",
    "sg:city":"Chicago",
    "sg:classifiers":[
        {
            "category":"Building & Trades",
            "subcategory":"Construction",
            "type":"Services"
        }
    ],
    "sg:phone":"+1 800 222 6815",
    "sg:postcode":"60640",
    "sg:province":"IL",
    "sg:tags":[
        "altering",
        "consultant",
        "remodeling",
        "contractor"
    ],
    "wof:name":"Rapid Restoration- Emergency Sewage Damage Clean-up, Water Damage Restoration",
    "wof:placetype":"venue"
},
  "geometry": {"coordinates":[-87.65969699999999,41.96999],"type":"Point"}
}