{
  "type": "Feature",
  "properties": {
    "addr:full":"1620 Brentwood Dr Mundelein IL 60060",
    "addr:housenumber":"1620",
    "addr:postcode":"60060",
    "addr:street":"Brentwood Dr",
    "iso:country":"US",
    "sg:address":"1620 Brentwood Dr",
    "sg:city":"Mundelein",
    "sg:classifiers":[
        {
            "category":"Professional",
            "subcategory":"Management & Consulting",
            "type":"Services"
        }
    ],
    "sg:phone":"+1 847 949 8772",
    "sg:postcode":"60060",
    "sg:province":"IL",
    "sg:tags":[
        "business"
    ],
    "wof:name":"Debbie Alms",
    "wof:placetype":"venue"
},
  "geometry": {"coordinates":[-88.02886599999999,42.267533],"type":"Point"}
}