{
  "type": "Feature",
  "properties": {
    "addr:full":"13659 Kenton Crestwood IL 60445",
    "addr:housenumber":"13659",
    "addr:postcode":"60445",
    "addr:street":"Kenton",
    "iso:country":"US",
    "sg:address":"13659 Kenton",
    "sg:city":"Crestwood",
    "sg:classifiers":[
        {
            "category":"Building & Trades",
            "subcategory":"Plumbing",
            "type":"Services"
        }
    ],
    "sg:phone":"+1 708 299 4640",
    "sg:postcode":"60445",
    "sg:province":"IL",
    "wof:name":"Sparkling Spas Inc.",
    "wof:placetype":"venue"
},
  "geometry": {"coordinates":[-87.73302099999999,41.644192],"type":"Point"}
}