{
  "type": "Feature",
  "properties": {
    "iso:country":"US",
    "sg:address":"307 Dover Washington St",
    "sg:city":"Princeton",
    "sg:classifiers":[
        {
            "category":"Wholesale",
            "subcategory":"Auto Parts",
            "type":"Manufacturing & Wholesale Goods"
        }
    ],
    "sg:phone":"+1 815 643 2265",
    "sg:postcode":"61356",
    "sg:province":"IL",
    "sg:tags":[
        "automobile",
        "rebuilt"
    ],
    "wof:name":"Jim's Garage & Auto Salvage",
    "wof:placetype":"venue"
},
  "geometry": {"coordinates":[-89.39932,41.435713],"type":"Point"}
}