{
  "type": "Feature",
  "properties": {
    "iso:country":"US",
    "sg:address":"822 S 2nd St",
    "sg:city":"Greenville",
    "sg:phone":"+1 618 664 2030",
    "sg:postcode":"62246",
    "sg:province":"IL",
    "sg:tags":[
        "oil"
    ],
    "wof:name":"South Central FS Inc",
    "wof:placetype":"venue"
},
  "geometry": {"coordinates":[-89.4123,38.886021],"type":"Point"}
}