{
  "type": "Feature",
  "properties": {
    "iso:country":"US",
    "sg:address":"3223 N Main St",
    "sg:city":"Rockford",
    "sg:classifiers":[
        {
            "category":"Manufacturing",
            "subcategory":"Printing",
            "type":"Manufacturing & Wholesale Goods"
        }
    ],
    "sg:phone":"+1 815 877 9416",
    "sg:postcode":"61103",
    "sg:province":"IL",
    "sg:tags":[
        "commercial",
        "typesetting"
    ],
    "wof:name":"Precision Print & Copy Service",
    "wof:placetype":"venue"
},
  "geometry": {"coordinates":[-89.077085,42.308838],"type":"Point"}
}