{
  "type": "Feature",
  "properties": {
    "addr:full":"12109 S Paulina St Calumet Park IL 60827",
    "addr:housenumber":"12109",
    "addr:postcode":"60827",
    "addr:street":"S Paulina St",
    "iso:country":"US",
    "sg:address":"12109 S Paulina St",
    "sg:city":"Calumet Park",
    "sg:classifiers":[
        {
            "category":"Building & Trades",
            "subcategory":"Construction",
            "type":"Services"
        }
    ],
    "sg:phone":"+1 708 388 2230",
    "sg:postcode":"60827",
    "sg:province":"IL",
    "sg:tags":[
        "sewer",
        "contractor"
    ],
    "wof:name":"Di Paolo Construction Co Inc",
    "wof:placetype":"venue"
},
  "geometry": {"coordinates":[-87.663534,41.672667],"type":"Point"}
}