{
  "type": "Feature",
  "properties": {
    "iso:country":"US",
    "sg:address":"2929 Charles St",
    "sg:city":"Rockford",
    "sg:classifiers":[
        {
            "category":"Education",
            "subcategory":"School",
            "type":"Public Place"
        }
    ],
    "sg:phone":"+1 815 229 2100",
    "sg:postcode":"61108",
    "sg:province":"IL",
    "sg:website":"www.rps205.com",
    "wof:name":"Rockford East High School",
    "wof:placetype":"venue"
},
  "geometry": {"coordinates":[-89.04948400000001,42.258115],"type":"Point"}
}