{
  "type": "Feature",
  "properties": {
    "iso:country":"US",
    "sg:address":"901 Bayliss Ave",
    "sg:city":"Beloit",
    "sg:classifiers":[
        {
            "category":"Shopping",
            "subcategory":"Bicycles & Sporting Goods",
            "type":"Retail Goods"
        }
    ],
    "sg:phone":"+1 608 362 8712",
    "sg:postcode":"53511",
    "sg:province":"IL",
    "sg:tags":[
        "bait",
        "fishing"
    ],
    "wof:name":"Dick's Tackle & Bait Shop",
    "wof:placetype":"venue"
},
  "geometry": {"coordinates":[-89.02546599999999,42.525033],"type":"Point"}
}