{
  "type": "Feature",
  "properties": {
    "iso:country":"US",
    "sg:address":"2931 N 21st Rd",
    "sg:city":"Seneca",
    "sg:classifiers":[
        {
            "category":"Manufacturing",
            "subcategory":"Food",
            "type":"Manufacturing & Wholesale Goods"
        },
        {
            "category":"Farming",
            "subcategory":"Farm",
            "type":"Manufacturing & Wholesale Goods"
        }
    ],
    "sg:phone":"+1 815 357 6415",
    "sg:postcode":"61360",
    "sg:province":"IL",
    "sg:tags":[
        "corn",
        "product"
    ],
    "wof:name":"Stan & Susan Johnson",
    "wof:placetype":"venue"
},
  "geometry": {"coordinates":[-88.603279,41.238941],"type":"Point"}
}