{
  "type": "Feature",
  "properties": {
    "iso:country":"US",
    "sg:address":"1625 Churchill Rd",
    "sg:city":"Schaumburg",
    "sg:classifiers":[
        {
            "category":"Real Estate",
            "subcategory":"Architect",
            "type":"Services"
        }
    ],
    "sg:phone":"+1 847 466 5067",
    "sg:postcode":"60195",
    "sg:province":"IL",
    "sg:tags":[
        "architects'",
        "specification",
        "construction",
        "builders'",
        "architectural"
    ],
    "wof:name":"Kevin A. Panek Architect",
    "wof:placetype":"venue"
},
  "geometry": {"coordinates":[-88.10132,42.056733],"type":"Point"}
}