{
  "type": "Feature",
  "properties": {
    "addr:full":"4280 Rosewood Ct Lake In The Hills IL 60156",
    "addr:housenumber":"4280",
    "addr:postcode":"60156",
    "addr:street":"Rosewood Ct",
    "iso:country":"US",
    "sg:address":"4280 Rosewood Ct",
    "sg:city":"Lake In The Hills",
    "sg:classifiers":[
        {
            "category":"Wholesale",
            "subcategory":"Vending Machines",
            "type":"Manufacturing & Wholesale Goods"
        }
    ],
    "sg:phone":"+1   ",
    "sg:postcode":"60156",
    "sg:province":"IL",
    "sg:tags":[
        "operator"
    ],
    "wof:name":"Ron S Allstars Vending Inc",
    "wof:placetype":"venue"
},
  "geometry": {"coordinates":[-88.370644,42.189672],"type":"Point"}
}