{
  "type": "Feature",
  "properties": {
    "iso:country":"US",
    "sg:address":"6903 Cermak Rd",
    "sg:city":"Berwyn",
    "sg:classifiers":[
        {
            "category":"Real Estate",
            "subcategory":"Real Estate Agent",
            "type":"Services"
        }
    ],
    "sg:phone":"+1 708 484 2600",
    "sg:postcode":"60402",
    "sg:province":"IL",
    "wof:name":"Buy Homes Cash Inc",
    "wof:placetype":"venue"
},
  "geometry": {"coordinates":[-87.797066,41.850425],"type":"Point"}
}