{
  "type": "Feature",
  "properties": {
    "iso:country":"US",
    "sg:address":"1513 Evergreen St",
    "sg:city":"Holiday Hills",
    "sg:classifiers":[
        {
            "category":"Home & Garden",
            "subcategory":"Building Materials",
            "type":"Retail Goods"
        }
    ],
    "sg:phone":"+1 815 363 0861",
    "sg:postcode":"60051",
    "sg:province":"IL",
    "sg:tags":[
        "windows"
    ],
    "wof:name":"Mc Henry Window Siding & Trim",
    "wof:placetype":"venue"
},
  "geometry": {"coordinates":[-88.226782,42.28782],"type":"Point"}
}