{
  "type": "Feature",
  "properties": {
    "addr:full":"3322 W Irving Park Rd Chicago IL 60618",
    "addr:housenumber":"3322",
    "addr:postcode":"60618",
    "addr:street":"W Irving Park Rd",
    "iso:country":"US",
    "sg:address":"3322 W Irving Park Rd",
    "sg:city":"Chicago",
    "sg:classifiers":[
        {
            "category":"Retail",
            "subcategory":"Auto Repair",
            "type":"Services"
        }
    ],
    "sg:phone":"+1 773 583 6676",
    "sg:postcode":"60618",
    "sg:province":"IL",
    "wof:name":"C & H Auto Service Inc",
    "wof:placetype":"venue"
},
  "geometry": {"coordinates":[-87.71080000000001,41.953999],"type":"Point"}
}