{
  "type": "Feature",
  "properties": {
    "iso:country":"US",
    "sg:address":"2102 N Neil St",
    "sg:city":"Champaign",
    "sg:classifiers":[
        {
            "category":"Shopping",
            "type":"Retail Goods"
        }
    ],
    "sg:phone":"+1 217 398 2866",
    "sg:postcode":"61820",
    "sg:province":"IL",
    "sg:tags":[
        "miscellaneous",
        "store"
    ],
    "wof:name":"B K's Merchandise Mart",
    "wof:placetype":"venue"
},
  "geometry": {"coordinates":[-88.245735,40.140359],"type":"Point"}
}