{
  "type": "Feature",
  "properties": {
    "iso:country":"US",
    "sg:address":"5333 W Cermak Rd",
    "sg:city":"Cicero",
    "sg:classifiers":[
        {
            "category":"Retail",
            "subcategory":"Car Wash",
            "type":"Services"
        }
    ],
    "sg:phone":"+1 708 222 0657",
    "sg:postcode":"60804",
    "sg:province":"IL",
    "wof:name":"VIP Carwash & Detailing",
    "wof:placetype":"venue"
},
  "geometry": {"coordinates":[-87.757992,41.850723],"type":"Point"}
}