{
  "type": "Feature",
  "properties": {
    "iso:country":"US",
    "sg:address":"1244 E Cooper Dr",
    "sg:city":"Palatine",
    "sg:classifiers":[
        {
            "category":"Education",
            "subcategory":"Special Training",
            "type":"Public Place"
        }
    ],
    "sg:phone":"+1 847 934 8771",
    "sg:postcode":"60074",
    "sg:province":"IL",
    "sg:tags":[
        "aircraft",
        "school"
    ],
    "wof:name":"Av8r Ventures Inc",
    "wof:placetype":"venue"
},
  "geometry": {"coordinates":[-88.012967,42.127935],"type":"Point"}
}