{
  "type": "Feature",
  "properties": {
    "addr:full":"178 W Washington St Ste B West Chicago IL 60185",
    "addr:housenumber":"178",
    "addr:postcode":"60185",
    "addr:street":"W Washington St Ste B West",
    "iso:country":"US",
    "sg:address":"178 W Washington St Ste B",
    "sg:city":"West Chicago",
    "sg:classifiers":[
        {
            "category":"Shopping",
            "subcategory":"Jewelry",
            "type":"Retail Goods"
        }
    ],
    "sg:phone":"+1 630 231 8180",
    "sg:postcode":"60185",
    "sg:province":"IL",
    "wof:name":"Gloria's Jewelry",
    "wof:placetype":"venue"
},
  "geometry": {"coordinates":[-88.20728099999999,41.883546],"type":"Point"}
}