{
  "type": "Feature",
  "properties": {
    "iso:country":"US",
    "sg:address":"5900 W Addison St",
    "sg:city":"Chicago",
    "sg:classifiers":[
        {
            "category":"Retail",
            "subcategory":"Car Wash",
            "type":"Services"
        }
    ],
    "sg:phone":"+1 773 283 3556",
    "sg:postcode":"60634",
    "sg:province":"IL",
    "wof:name":"Four Seasons Auto Wash",
    "wof:placetype":"venue"
},
  "geometry": {"coordinates":[-87.7743,41.945801],"type":"Point"}
}