{
  "type": "Feature",
  "properties": {
    "iso:country":"US",
    "sg:address":"1032 S LaGrange Rd",
    "sg:city":"La Grange",
    "sg:classifiers":[
        {
            "category":"Professional",
            "type":"Services"
        },
        {
            "category":"Shopping",
            "subcategory":"Florist",
            "type":"Retail Goods"
        }
    ],
    "sg:phone":"+1 800 999 7672",
    "sg:postcode":"60525",
    "sg:province":"IL",
    "sg:tags":[
        "planning",
        "event"
    ],
    "sg:website":"www.crystalflowershop.com",
    "wof:name":"Crystal Flower Shop",
    "wof:placetype":"venue"
},
  "geometry": {"coordinates":[-87.868892,41.795301],"type":"Point"}
}