{
  "type": "Feature",
  "properties": {
    "iso:country":"US",
    "sg:address":"605 E North St",
    "sg:city":"Bradley",
    "sg:classifiers":[
        {
            "category":"Home & Garden",
            "subcategory":"Carpets & Floor Coverings",
            "type":"Retail Goods"
        }
    ],
    "sg:phone":"+1   ",
    "sg:postcode":"60915",
    "sg:province":"IL",
    "wof:name":"Carpet Weavers Outlet",
    "wof:placetype":"venue"
},
  "geometry": {"coordinates":[-87.851066,41.148112],"type":"Point"}
}