{
  "type": "Feature",
  "properties": {
    "iso:country":"US",
    "sg:address":"281 W Geneva Rd",
    "sg:city":"Winfield",
    "sg:classifiers":[
        {
            "category":"Health Services",
            "subcategory":"Doctor",
            "type":"Services"
        }
    ],
    "sg:phone":"+1 630 653 9900",
    "sg:postcode":"60190",
    "sg:province":"IL",
    "sg:tags":[
        "medical"
    ],
    "wof:name":"Harding Pauline MD",
    "wof:placetype":"venue"
},
  "geometry": {"coordinates":[-88.15364099999999,41.888242],"type":"Point"}
}