{
  "type": "Feature",
  "properties": {
    "iso:country":"US",
    "sg:address":"2738 W Fulton St",
    "sg:city":"Chicago",
    "sg:classifiers":[
        {
            "category":"Taxi",
            "type":"Transportation"
        }
    ],
    "sg:phone":"+1 312 733 8000",
    "sg:postcode":"60612",
    "sg:province":"IL",
    "wof:name":"Metro Taxi Group Inc.",
    "wof:placetype":"venue"
},
  "geometry": {"coordinates":[-87.69531000000001,41.886548],"type":"Point"}
}