{
  "type": "Feature",
  "properties": {
    "iso:country":"US",
    "sg:address":"4550 Memorial Dr",
    "sg:city":"Belleville",
    "sg:classifiers":[
        {
            "category":"Health Services",
            "subcategory":"Doctor",
            "type":"Services"
        }
    ],
    "sg:phone":"+1 618 628 0959",
    "sg:postcode":"62226",
    "sg:province":"IL",
    "sg:tags":[
        "specializing",
        "medicine",
        "medical",
        "internal",
        "an"
    ],
    "wof:name":"Belleville Heart Center Ltd",
    "wof:placetype":"venue"
},
  "geometry": {"coordinates":[-90.020787,38.548832],"type":"Point"}
}