{
  "type": "Feature",
  "properties": {
    "iso:country":"US",
    "sg:address":"117 N Main St",
    "sg:city":"Canton",
    "sg:classifiers":[
        {
            "category":"Real Estate",
            "subcategory":"Real Estate Agent",
            "type":"Services"
        }
    ],
    "sg:phone":"+1 309 647 8891",
    "sg:postcode":"61520",
    "sg:province":"IL",
    "sg:tags":[
        "appraiser"
    ],
    "wof:name":"Mitchell Appraisal Svc",
    "wof:placetype":"venue"
},
  "geometry": {"coordinates":[-90.035044,40.557691],"type":"Point"}
}