{
  "type": "Feature",
  "properties": {
    "addr:full":"105 S Roselle Rd Schaumburg IL 60193",
    "addr:housenumber":"105",
    "addr:postcode":"60193",
    "addr:street":"S Roselle Rd",
    "iso:country":"US",
    "sg:address":"105 S Roselle Rd",
    "sg:city":"Schaumburg",
    "sg:classifiers":[
        {
            "category":"Building & Trades",
            "subcategory":"Construction",
            "type":"Services"
        }
    ],
    "sg:phone":"+1 847 891 6486",
    "sg:postcode":"60193",
    "sg:province":"IL",
    "sg:tags":[
        "concrete",
        "contractor"
    ],
    "wof:name":"A Lamp Concrete Contractors",
    "wof:placetype":"venue"
},
  "geometry": {"coordinates":[-88.079863,42.024381],"type":"Point"}
}