{
  "type": "Feature",
  "properties": {
    "addr:full":"5211 Bull Valley Rd Mchenry IL 60050",
    "addr:housenumber":"5211",
    "addr:postcode":"60050",
    "addr:street":"Bull Valley Rd",
    "iso:country":"US",
    "sg:address":"5211 Bull Valley Rd",
    "sg:city":"Mchenry",
    "sg:classifiers":[
        {
            "category":"Place Of Worship",
            "subcategory":"Church",
            "type":"Public Place"
        },
        {
            "category":"Place Of Worship",
            "type":"Public Place"
        }
    ],
    "sg:phone":"+1 815 385 5673",
    "sg:postcode":"60050",
    "sg:province":"IL",
    "sg:tags":[
        "churches-catholic-traditional",
        "churches-catholic"
    ],
    "wof:name":"Noah's Ark Preschool",
    "wof:placetype":"venue"
},
  "geometry": {"coordinates":[-88.299707,42.320042],"type":"Point"}
}