{
  "type": "Feature",
  "properties": {
    "addr:full":"450 W Melrose St Chicago IL 60657",
    "addr:housenumber":"450",
    "addr:postcode":"60657",
    "addr:street":"W Melrose St",
    "iso:country":"US",
    "sg:address":"450 W Melrose St",
    "sg:city":"Chicago",
    "sg:classifiers":[
        {
            "category":"Professional",
            "subcategory":"Computer Services",
            "type":"Services"
        }
    ],
    "sg:phone":"+1 773 636 4145",
    "sg:postcode":"60657",
    "sg:province":"IL",
    "sg:tags":[
        "security",
        "video",
        "network",
        "surveillance"
    ],
    "wof:name":"Masslogistics",
    "wof:placetype":"venue"
},
  "geometry": {"coordinates":[-87.640726,41.94126],"type":"Point"}
}