{
  "type": "Feature",
  "properties": {
    "addr:full":"325 E State St Sycamore IL 60178",
    "addr:housenumber":"325",
    "addr:postcode":"60178",
    "addr:street":"E State St",
    "iso:country":"US",
    "sg:address":"325 E State St",
    "sg:city":"Sycamore",
    "sg:classifiers":[
        {
            "category":"Personal",
            "type":"Services"
        },
        {
            "category":"Sports & Exercise",
            "subcategory":"Gym",
            "type":"Entertainment"
        },
        {
            "category":"Health Services",
            "subcategory":"Health Practitioner",
            "type":"Services"
        },
        {
            "category":"Arena",
            "subcategory":"Sports Club",
            "type":"Entertainment"
        }
    ],
    "sg:phone":"+1 800 615 7352",
    "sg:postcode":"60178",
    "sg:province":"IL",
    "sg:tags":[
        "trainer",
        "control",
        "weight",
        "consultant",
        "program",
        "fitness",
        "physical"
    ],
    "sg:website":"http://www.curves.com",
    "wof:name":"Curves",
    "wof:placetype":"venue"
},
  "geometry": {"coordinates":[-88.681213,41.988105],"type":"Point"}
}