{
  "type": "Feature",
  "properties": {
    "addr:full":"908 State St Quincy IL 62301",
    "addr:housenumber":"908",
    "addr:postcode":"62301",
    "addr:street":"State St",
    "iso:country":"US",
    "sg:address":"908 State St",
    "sg:city":"Quincy",
    "sg:classifiers":[
        {
            "category":"Professional",
            "subcategory":"Computer Services",
            "type":"Services"
        }
    ],
    "sg:phone":"+1 217 224 5058",
    "sg:postcode":"62301",
    "sg:province":"IL",
    "sg:tags":[
        "software"
    ],
    "wof:name":"Hit (any) Key Computers",
    "wof:placetype":"venue"
},
  "geometry": {"coordinates":[-91.40156399999999,39.926552],"type":"Point"}
}