{
  "type": "Feature",
  "properties": {
    "iso:country":"US",
    "sg:address":"13600 Will Cook Rd",
    "sg:city":"Orland Park",
    "sg:classifiers":[
        {
            "category":"Building & Trades",
            "subcategory":"Construction",
            "type":"Services"
        }
    ],
    "sg:phone":"+1 630 243 9423",
    "sg:postcode":"60467",
    "sg:province":"IL",
    "sg:tags":[
        "concrete",
        "work"
    ],
    "wof:name":"Pride Concrete Inc",
    "wof:placetype":"venue"
},
  "geometry": {"coordinates":[-87.91189199999999,41.641836],"type":"Point"}
}