{
  "type": "Feature",
  "properties": {
    "addr:full":"3310 Schierhorn Ct Franklin Park IL 60131",
    "addr:postcode":"3310;60131",
    "addr:street":"Schierhorn Ct",
    "iso:country":"US",
    "sg:address":"3310 Schierhorn Ct",
    "sg:city":"Franklin Park",
    "sg:classifiers":[
        {
            "category":"Manufacturing",
            "subcategory":"Tools & Machinery",
            "type":"Manufacturing & Wholesale Goods"
        }
    ],
    "sg:phone":"+1 847 671 4226",
    "sg:postcode":"60131",
    "sg:province":"IL",
    "sg:tags":[
        "machine",
        "shop"
    ],
    "wof:name":"Exact Machine Inc",
    "wof:placetype":"venue"
},
  "geometry": {"coordinates":[-87.85371499999999,41.939741],"type":"Point"}
}