{
  "type": "Feature",
  "properties": {
    "iso:country":"US",
    "sg:address":"1001 Court St",
    "sg:city":"Pekin",
    "sg:classifiers":[
        {
            "category":"Shopping",
            "subcategory":"Florist",
            "type":"Retail Goods"
        },
        {
            "category":"Shopping",
            "subcategory":"Pharmacy",
            "type":"Retail Goods"
        },
        {
            "category":"Food & Beverages",
            "subcategory":"Groceries & Convenience Stores",
            "type":"Retail Goods"
        }
    ],
    "sg:phone":"+1 309 347 6757",
    "sg:postcode":"61554",
    "sg:province":"IL",
    "sg:website":"http://www.schnucks.com",
    "wof:name":"Schnucks Pekin",
    "wof:placetype":"venue"
},
  "geometry": {"coordinates":[-89.63767199999999,40.565681],"type":"Point"}
}