{
  "type": "Feature",
  "properties": {
    "iso:country":"US",
    "sg:address":"1360 Busch Pkwy",
    "sg:city":"Buffalo Grove",
    "sg:classifiers":[
        {
            "category":"Wholesale",
            "subcategory":"Office Equipment",
            "type":"Manufacturing & Wholesale Goods"
        },
        {
            "category":"Shopping",
            "type":"Retail Goods"
        }
    ],
    "sg:phone":"+1 847 459 5060",
    "sg:postcode":"60089",
    "sg:province":"IL",
    "sg:tags":[
        "machine",
        "duplicating",
        "copying",
        "sales"
    ],
    "wof:name":"Frykman Technologies Inc",
    "wof:placetype":"venue"
},
  "geometry": {"coordinates":[-87.931331,42.171442],"type":"Point"}
}