{
  "type": "Feature",
  "properties": {
    "iso:country":"US",
    "sg:address":"1007 N Prospect Ave",
    "sg:city":"Champaign",
    "sg:classifiers":[
        {
            "category":"Personal",
            "subcategory":"Beauty Salon",
            "type":"Services"
        }
    ],
    "sg:phone":"+1 217 398 3185",
    "sg:postcode":"61820",
    "sg:province":"IL",
    "wof:name":"Tanya's Touch",
    "wof:placetype":"venue"
},
  "geometry": {"coordinates":[-88.25794999999999,40.125858],"type":"Point"}
}