{
  "type": "Feature",
  "properties": {
    "addr:full":"1336 Paramount Pkwy Batavia IL 60510",
    "addr:housenumber":"1336",
    "addr:postcode":"60510",
    "addr:street":"Paramount Pkwy",
    "iso:country":"US",
    "sg:address":"1336 Paramount Pkwy",
    "sg:city":"Batavia",
    "sg:classifiers":[
        {
            "category":"Manufacturing",
            "subcategory":"Paper Products",
            "type":"Manufacturing & Wholesale Goods"
        }
    ],
    "sg:phone":"+1 630 406 0560",
    "sg:postcode":"60510",
    "sg:province":"IL",
    "sg:tags":[
        "mfg",
        "foam",
        "plastic"
    ],
    "sg:website":"www.tekpac.com",
    "wof:name":"Tek Pak Inc",
    "wof:placetype":"venue"
},
  "geometry": {"coordinates":[-88.271648,41.865267],"type":"Point"}
}