{
  "type": "Feature",
  "properties": {
    "iso:country":"US",
    "sg:address":"1340 E Lake Dr",
    "sg:city":"Greenville",
    "sg:classifiers":[
        {
            "category":"Manufacturing",
            "subcategory":"Lumber",
            "type":"Manufacturing & Wholesale Goods"
        }
    ],
    "sg:phone":"+1 618 664 0274",
    "sg:postcode":"62246",
    "sg:province":"IL",
    "sg:tags":[
        "operation",
        "timber",
        "tract"
    ],
    "wof:name":"Randys Cntry BARn&chrstms Tre",
    "wof:placetype":"venue"
},
  "geometry": {"coordinates":[-89.387604,38.934652],"type":"Point"}
}