{
  "type": "Feature",
  "properties": {
    "iso:country":"US",
    "sg:address":"481 W Boughton Rd",
    "sg:city":"Bolingbrook",
    "sg:classifiers":[
        {
            "category":"Organizations",
            "subcategory":"Religious Organization",
            "type":"Services"
        }
    ],
    "sg:phone":"+1 630 378 9040",
    "sg:postcode":"60440",
    "sg:province":"IL",
    "wof:name":"New Cvenant Pentecostal Church",
    "wof:placetype":"venue"
},
  "geometry": {"coordinates":[-88.08659299999999,41.707602],"type":"Point"}
}