{
  "type": "Feature",
  "properties": {
    "iso:country":"US",
    "sg:address":"27053 W Wellington Ct",
    "sg:city":"Barrington",
    "sg:classifiers":[
        {
            "category":"Professional",
            "subcategory":"Business Services",
            "type":"Services"
        }
    ],
    "sg:phone":"+1 847 382 1476",
    "sg:postcode":"60010",
    "sg:province":"IL",
    "wof:name":"JM Associates LLC",
    "wof:placetype":"venue"
},
  "geometry": {"coordinates":[-88.160822,42.214623],"type":"Point"}
}