{
  "type": "Feature",
  "properties": {
    "addr:full":"300 E 29th St Chicago IL 60616",
    "addr:housenumber":"300",
    "addr:postcode":"60616",
    "addr:street":"E 29Th St",
    "iso:country":"US",
    "sg:address":"300 E 29th St",
    "sg:city":"Chicago",
    "sg:classifiers":[
        {
            "category":"Government",
            "subcategory":"Police Station",
            "type":"Public Place"
        },
        {
            "category":"Government",
            "subcategory":"Office",
            "type":"Public Place"
        }
    ],
    "sg:phone":"+1 312 747 8340",
    "sg:postcode":"60616",
    "sg:province":"IL",
    "sg:tags":[
        "department",
        "township",
        "government-city",
        "village"
    ],
    "sg:website":"https://portal.chicagopolice.org/portal/page/portal/ClearPath/Communities/Districts/District21",
    "wof:name":"Chicago Police Department - 21st District - Prairie",
    "wof:placetype":"venue"
},
  "geometry": {"coordinates":[-87.620369,41.842018],"type":"Point"}
}