{
  "type": "Feature",
  "properties": {
    "addr:full":"2945 Harlem Ave Berwyn IL 60402",
    "addr:housenumber":"2945",
    "addr:postcode":"60402",
    "addr:street":"Harlem Ave",
    "iso:country":"US",
    "sg:address":"2945 Harlem Ave",
    "sg:city":"Berwyn",
    "sg:classifiers":[
        {
            "category":"Bakery",
            "type":"Food & Drink"
        },
        {
            "category":"Coffee & Tea",
            "type":"Food & Drink"
        },
        {
            "category":"Bagels",
            "type":"Food & Drink"
        },
        {
            "category":"Donuts",
            "type":"Food & Drink"
        }
    ],
    "sg:menulink":"http://www.allmenus.com/il/berwyn/134970-dunkin-donuts/menu/",
    "sg:phone":"+1 708 749 0689",
    "sg:postcode":"60402",
    "sg:province":"IL",
    "sg:tags":[
        "american",
        "pastry"
    ],
    "wof:name":"Dunkin' Donuts",
    "wof:placetype":"venue"
},
  "geometry": {"coordinates":[-87.802858,41.837614],"type":"Point"}
}