{
  "type": "Feature",
  "properties": {
    "addr:full":"5850 W 126th Pl Alsip IL 60803",
    "addr:housenumber":"5850",
    "addr:postcode":"60803",
    "addr:street":"W 126Th Pl",
    "iso:country":"US",
    "sg:address":"5850 W 126th Pl",
    "sg:city":"Alsip",
    "sg:classifiers":[
        {
            "category":"Professional",
            "subcategory":"Management & Consulting",
            "type":"Services"
        }
    ],
    "sg:phone":"+1 708 371 0431",
    "sg:postcode":"60803",
    "sg:province":"IL",
    "wof:name":"Hager & Associates",
    "wof:placetype":"venue"
},
  "geometry": {"coordinates":[-87.766195,41.66219],"type":"Point"}
}