{
  "type": "Feature",
  "properties": {
    "iso:country":"US",
    "sg:address":"15040 S Ravinia Ave",
    "sg:city":"Orland Park",
    "sg:classifiers":[
        {
            "category":"Insurance",
            "subcategory":"Insurance Agent",
            "type":"Services"
        }
    ],
    "sg:phone":"+1 708 403 0355",
    "sg:postcode":"60462",
    "sg:province":"IL",
    "sg:tags":[
        "broker"
    ],
    "wof:name":"Kurland Insurance Agency Inc",
    "wof:placetype":"venue"
},
  "geometry": {"coordinates":[-87.85732899999999,41.618384],"type":"Point"}
}