{
  "type": "Feature",
  "properties": {
    "iso:country":"US",
    "sg:address":"1102 Blake St",
    "sg:city":"Rockford",
    "sg:classifiers":[
        {
            "category":"Manufacturing",
            "subcategory":"Printing",
            "type":"Manufacturing & Wholesale Goods"
        }
    ],
    "sg:phone":"+1 815 962 8223",
    "sg:postcode":"61102",
    "sg:province":"IL",
    "sg:tags":[
        "commercial"
    ],
    "wof:name":"Art-Craft Press",
    "wof:placetype":"venue"
},
  "geometry": {"coordinates":[-89.113179,42.265137],"type":"Point"}
}