{
  "type": "Feature",
  "properties": {
    "addr:full":"856 W Nelson Street Apt 404 Chicago IL 60657",
    "addr:housenumber":"856;404",
    "addr:postcode":"60657",
    "addr:street":"W Nelson Street Apt",
    "iso:country":"US",
    "sg:address":"856 W Nelson Street Apt 404",
    "sg:city":"Chicago",
    "sg:classifiers":[
        {
            "category":"Health Services",
            "subcategory":"Doctor",
            "type":"Services"
        }
    ],
    "sg:phone":"+1 773 529 2062",
    "sg:postcode":"60657",
    "sg:province":"IL",
    "wof:name":"Advocate Illinois Masonic-Trauma Ste",
    "wof:placetype":"venue"
},
  "geometry": {"coordinates":[-87.65174,41.937218],"type":"Point"}
}