{
  "type": "Feature",
  "properties": {
    "addr:full":"1998 N 4750th Rd Leland IL 60531",
    "addr:housenumber":"1998",
    "addr:postcode":"60531",
    "addr:street":"N 4750Th Rd",
    "iso:country":"US",
    "sg:address":"1998 N 4750th Rd",
    "sg:city":"Leland",
    "sg:classifiers":[
        {
            "category":"Building & Trades",
            "subcategory":"Construction",
            "type":"Services"
        }
    ],
    "sg:phone":"+1 815 495 9347",
    "sg:postcode":"60531",
    "sg:province":"IL",
    "sg:tags":[
        "general",
        "contractor"
    ],
    "wof:name":"Nelson Builders",
    "wof:placetype":"venue"
},
  "geometry": {"coordinates":[-88.789934,41.62381],"type":"Point"}
}