{
  "type": "Feature",
  "properties": {
    "addr:full":"12 Bellaire Ct Clinton IL 61727",
    "addr:housenumber":"12",
    "addr:postcode":"61727",
    "addr:street":"Bellaire Ct",
    "iso:country":"US",
    "sg:address":"12 Bellaire Ct",
    "sg:city":"Clinton",
    "sg:classifiers":[
        {
            "category":"Shopping",
            "type":"Retail Goods"
        }
    ],
    "sg:phone":"+1 217 935 3447",
    "sg:postcode":"61727",
    "sg:province":"IL",
    "sg:tags":[
        "merchandise"
    ],
    "wof:name":"Pam S Shop",
    "wof:placetype":"venue"
},
  "geometry": {"coordinates":[-88.970798,40.141239],"type":"Point"}
}