{
  "type": "Feature",
  "properties": {
    "addr:full":"7912 S Pulaski Rd Chicago IL 60652",
    "addr:housenumber":"7912",
    "addr:postcode":"60652",
    "addr:street":"S Pulaski Rd",
    "iso:country":"US",
    "sg:address":"7912 S Pulaski Rd",
    "sg:city":"Chicago",
    "sg:classifiers":[
        {
            "category":"Fast Food",
            "type":"Food & Drink"
        },
        {
            "category":"Restaurant",
            "type":"Food & Drink"
        }
    ],
    "sg:phone":"+1 773 585 1296",
    "sg:postcode":"60652",
    "sg:province":"IL",
    "sg:tags":[
        "american",
        "hot",
        "hamburger",
        "dog"
    ],
    "sg:website":"http://www.whitecastle.com",
    "wof:name":"White Castle",
    "wof:placetype":"venue"
},
  "geometry": {"coordinates":[-87.721909,41.749178],"type":"Point"}
}