{
  "type": "Feature",
  "properties": {
    "iso:country":"US",
    "sg:address":"175 S Main St",
    "sg:city":"Canton",
    "sg:classifiers":[
        {
            "category":"Shopping",
            "subcategory":"Pharmacy",
            "type":"Retail Goods"
        }
    ],
    "sg:phone":"+1 309 647 0884",
    "sg:postcode":"61520",
    "sg:province":"IL",
    "sg:tags":[
        "drug"
    ],
    "wof:name":"Blessman's Pharmacy",
    "wof:placetype":"venue"
},
  "geometry": {"coordinates":[-90.035086,40.553679],"type":"Point"}
}