{
  "type": "Feature",
  "properties": {
    "addr:full":"1000 S 7th St Rochelle IL 61068",
    "addr:housenumber":"1000",
    "addr:postcode":"61068",
    "addr:street":"S 7Th St",
    "iso:country":"US",
    "sg:address":"1000 S 7th St",
    "sg:city":"Rochelle",
    "sg:classifiers":[
        {
            "category":"Deli",
            "type":"Food & Drink"
        }
    ],
    "sg:menulink":"http://www.allmenus.com/il/flagg/127188-blimpie-subs--sandwiches/menu/",
    "sg:phone":"+1 815 562 0071",
    "sg:postcode":"61068",
    "sg:province":"IL",
    "sg:tags":[
        "wrap",
        "american",
        "sandwich"
    ],
    "wof:name":"Blimpie Subs & Sandwiches",
    "wof:placetype":"venue"
},
  "geometry": {"coordinates":[-89.06844,41.909284],"type":"Point"}
}