{
  "type": "Feature",
  "properties": {
    "iso:country":"US",
    "sg:address":"1825 College Ave Ste 130",
    "sg:city":"Wheaton",
    "sg:classifiers":[
        {
            "category":"Real Estate",
            "subcategory":"Real Estate Services",
            "type":"Services"
        },
        {
            "category":"Building & Trades",
            "subcategory":"Construction",
            "type":"Services"
        },
        {
            "category":"Real Estate",
            "subcategory":"Architect",
            "type":"Services"
        }
    ],
    "sg:phone":"+1 630 690 0600",
    "sg:postcode":"60187",
    "sg:province":"IL",
    "sg:tags":[
        "contractor"
    ],
    "sg:website":"www.churchbuilding.com",
    "wof:name":"Church Building Consultants Realty",
    "wof:placetype":"venue"
},
  "geometry": {"coordinates":[-88.08142700000001,41.875217],"type":"Point"}
}