{
  "type": "Feature",
  "properties": {
    "iso:country":"US",
    "sg:address":"186 N Wells St",
    "sg:city":"Chicago",
    "sg:classifiers":[
        {
            "category":"Food & Beverages",
            "subcategory":"Candy",
            "type":"Retail Goods"
        },
        {
            "category":"Coffee & Tea",
            "type":"Food & Drink"
        },
        {
            "category":"Bagels",
            "subcategory":"None",
            "type":"Food & Drink"
        }
    ],
    "sg:phone":"+1 312 345 9040",
    "sg:postcode":"60606",
    "sg:province":"IL",
    "sg:tags":[
        "dessert"
    ],
    "wof:name":"Lith Cafe",
    "wof:placetype":"venue"
},
  "geometry": {"coordinates":[-87.63392399999999,41.88548],"type":"Point"}
}