{
  "type": "Feature",
  "properties": {
    "iso:country":"US",
    "sg:address":"15927 Harlem Ave",
    "sg:city":"Tinley Park",
    "sg:classifiers":[
        {
            "category":"Food & Beverages",
            "subcategory":"Specialty",
            "type":"Retail Goods"
        }
    ],
    "sg:phone":"+1   ",
    "sg:postcode":"60477",
    "sg:province":"IL",
    "wof:name":"GNC",
    "wof:placetype":"venue"
},
  "geometry": {"coordinates":[-87.79397400000001,41.598998],"type":"Point"}
}