{
  "type": "Feature",
  "properties": {
    "addr:full":"1315 W 97th Pl Chicago IL 60643",
    "addr:housenumber":"1315",
    "addr:postcode":"60643",
    "addr:street":"W 97Th Pl",
    "iso:country":"US",
    "sg:address":"1315 W 97th Pl",
    "sg:city":"Chicago",
    "sg:classifiers":[
        {
            "category":"Communications",
            "subcategory":"Film & Video Production",
            "type":"Services"
        }
    ],
    "sg:phone":"+1 773 238 2979",
    "sg:postcode":"60643",
    "sg:province":"IL",
    "sg:tags":[
        "motion"
    ],
    "wof:name":"Two Cents Production",
    "wof:placetype":"venue"
},
  "geometry": {"coordinates":[-87.65732800000001,41.716863],"type":"Point"}
}