{
  "type": "Feature",
  "properties": {
    "iso:country":"US",
    "sg:address":"14236 S Clark St",
    "sg:city":"Riverdale",
    "sg:classifiers":[
        {
            "category":"Professional",
            "subcategory":"Business Services",
            "type":"Services"
        }
    ],
    "sg:phone":"+1 708 860 0770",
    "sg:postcode":"60827",
    "sg:province":"IL",
    "wof:name":"Prepaid Legal Services",
    "wof:placetype":"venue"
},
  "geometry": {"coordinates":[-87.62456400000001,41.635983],"type":"Point"}
}