{
  "type": "Feature",
  "properties": {
    "addr:full":"8208 47th St Lyons IL 60534",
    "addr:housenumber":"8208",
    "addr:postcode":"60534",
    "addr:street":"47Th St",
    "iso:country":"US",
    "sg:address":"8208 47th St",
    "sg:city":"Lyons",
    "sg:classifiers":[
        {
            "category":"Shopping",
            "subcategory":"Adult",
            "type":"Retail Goods"
        }
    ],
    "sg:phone":"+1 708 442 3911",
    "sg:postcode":"60534",
    "sg:province":"IL",
    "sg:tags":[
        "video",
        "store",
        "entertainment"
    ],
    "sg:website":"www.lyonsadultvideo.com",
    "wof:name":"Lyons Adult Video Inc",
    "wof:placetype":"venue"
},
  "geometry": {"coordinates":[-87.82577000000001,41.805916],"type":"Point"}
}