{
  "type": "Feature",
  "properties": {
    "addr:full":"472 N McLean Blvd Elgin IL 60123",
    "addr:housenumber":"472",
    "addr:postcode":"60123",
    "addr:street":"N Mclean Blvd",
    "iso:country":"US",
    "sg:address":"472 N McLean Blvd",
    "sg:city":"Elgin",
    "sg:classifiers":[
        {
            "category":"Shopping",
            "type":"Retail Goods"
        }
    ],
    "sg:phone":"+1   ",
    "sg:postcode":"60123",
    "sg:province":"IL",
    "sg:tags":[
        "merchandise"
    ],
    "wof:name":"Chicagland Adlogy Hring Blance",
    "wof:placetype":"venue"
},
  "geometry": {"coordinates":[-88.31268900000001,42.02202],"type":"Point"}
}