{
  "type": "Feature",
  "properties": {
    "iso:country":"US",
    "sg:address":"7130 E State St",
    "sg:city":"Rockford",
    "sg:classifiers":[
        {
            "category":"Home & Garden",
            "subcategory":"Building Materials",
            "type":"Retail Goods"
        }
    ],
    "sg:phone":"+1 815 394 1300",
    "sg:postcode":"61108",
    "sg:province":"IL",
    "sg:tags":[
        "center"
    ],
    "sg:website":"www.lowes.com",
    "wof:name":"Lowe's",
    "wof:placetype":"venue"
},
  "geometry": {"coordinates":[-88.976427,42.26966],"type":"Point"}
}