{
  "type": "Feature",
  "properties": {
    "iso:country":"US",
    "sg:address":"20052 S Sycamore Dr",
    "sg:city":"Frankfort",
    "sg:classifiers":[
        {
            "category":"Professional",
            "subcategory":"Business Services",
            "type":"Services"
        }
    ],
    "sg:phone":"+1 815 469 9022",
    "sg:postcode":"60423",
    "sg:province":"IL",
    "wof:name":"M S E Appraisal Svc",
    "wof:placetype":"venue"
},
  "geometry": {"coordinates":[-87.81301000000001,41.52551],"type":"Point"}
}