{
  "type": "Feature",
  "properties": {
    "iso:country":"US",
    "sg:address":"800 S 9th St",
    "sg:city":"Monmouth",
    "sg:classifiers":[
        {
            "category":"Real Estate",
            "subcategory":"Real Estate Operator",
            "type":"Services"
        }
    ],
    "sg:phone":"+1 309 734 4083",
    "sg:postcode":"61462",
    "sg:province":"IL",
    "sg:tags":[
        "building",
        "apartment"
    ],
    "wof:name":"Lincoln Homes Tenant Services",
    "wof:placetype":"venue"
},
  "geometry": {"coordinates":[-90.63629299999999,40.904053],"type":"Point"}
}