{
  "type": "Feature",
  "properties": {
    "iso:country":"US",
    "sg:address":"732 Linden Ave",
    "sg:city":"Rockford",
    "sg:classifiers":[
        {
            "category":"Personal",
            "subcategory":"Beauty Salon",
            "type":"Services"
        }
    ],
    "sg:phone":"+1 815 963 5243",
    "sg:postcode":"61102",
    "sg:province":"IL",
    "wof:name":"Lady True Hair Braiding",
    "wof:placetype":"venue"
},
  "geometry": {"coordinates":[-89.108371,42.25692],"type":"Point"}
}