{
  "type": "Feature",
  "properties": {
    "iso:country":"US",
    "sg:address":"8437 Hickory Hills Dr",
    "sg:city":"Argenta",
    "sg:classifiers":[
        {
            "category":"Farming",
            "subcategory":"Farm",
            "type":"Manufacturing & Wholesale Goods"
        }
    ],
    "sg:phone":"+1 217 795 4463",
    "sg:postcode":"62501",
    "sg:province":"IL",
    "wof:name":"Butcher Farms",
    "wof:placetype":"venue"
},
  "geometry": {"coordinates":[-88.816051,39.999734],"type":"Point"}
}