{
  "type": "Feature",
  "properties": {
    "addr:full":"5011 W 63rd St Chicago IL 60638",
    "addr:housenumber":"5011",
    "addr:postcode":"60638",
    "addr:street":"W 63Rd St",
    "iso:country":"US",
    "sg:address":"5011 W 63rd St",
    "sg:city":"Chicago",
    "sg:classifiers":[
        {
            "category":"Autos & Motor Vehicles",
            "subcategory":"Automobile Sales",
            "type":"Retail Goods"
        }
    ],
    "sg:phone":"+1 773 767 8530",
    "sg:postcode":"60638",
    "sg:province":"IL",
    "sg:tags":[
        "new",
        "car"
    ],
    "sg:website":"http://www.buick.com",
    "wof:name":"Ray Buick Inc",
    "wof:placetype":"venue"
},
  "geometry": {"coordinates":[-87.747399,41.778333],"type":"Point"}
}