{
  "type": "Feature",
  "properties": {
    "iso:country":"US",
    "sg:address":"1701 Golf Rd",
    "sg:city":"Rolling Meadows",
    "sg:classifiers":[
        {
            "category":"Health Services",
            "subcategory":"Medical Lab",
            "type":"Services"
        }
    ],
    "sg:phone":"+1 847 640 1377",
    "sg:postcode":"60008",
    "sg:province":"IL",
    "sg:tags":[
        "laboratory"
    ],
    "wof:name":"Biotrition",
    "wof:placetype":"venue"
},
  "geometry": {"coordinates":[-87.999296,42.05129],"type":"Point"}
}