{
  "type": "Feature",
  "properties": {
    "addr:full":"715 S Belt W Belleville IL 62220",
    "addr:housenumber":"715",
    "addr:postcode":"62220",
    "addr:street":"S Belt W",
    "iso:country":"US",
    "sg:address":"715 S Belt W",
    "sg:city":"Belleville",
    "sg:classifiers":[
        {
            "category":"Professional",
            "subcategory":"Engineering",
            "type":"Services"
        },
        {
            "category":"Building & Trades",
            "subcategory":"Cleaning & Sanitation",
            "type":"Services"
        },
        {
            "category":"Building & Trades",
            "subcategory":"Construction",
            "type":"Services"
        }
    ],
    "sg:phone":"+1 618 235 1678",
    "sg:postcode":"62220",
    "sg:province":"IL",
    "sg:tags":[
        "repair",
        "system",
        "specialty",
        "equipment",
        "furnaces-repairing",
        "heating",
        "contractor",
        "air conditioning"
    ],
    "wof:name":"Bluff City Heating & Air Conditioning",
    "wof:placetype":"venue"
},
  "geometry": {"coordinates":[-89.997131,38.50436],"type":"Point"}
}