{
  "type": "Feature",
  "properties": {
    "addr:full":"332 W Main St Carpentersville IL 60110",
    "addr:housenumber":"332",
    "addr:postcode":"60110",
    "addr:street":"W Main St",
    "iso:country":"US",
    "sg:address":"332 W Main St",
    "sg:city":"Carpentersville",
    "sg:classifiers":[
        {
            "category":"Food & Beverages",
            "subcategory":"Liquor & Beverages",
            "type":"Retail Goods"
        }
    ],
    "sg:phone":"+1 847 783 0003",
    "sg:postcode":"60110",
    "sg:province":"IL",
    "sg:tags":[
        "beer",
        "spirit",
        "wine"
    ],
    "wof:name":"Oasis",
    "wof:placetype":"venue"
},
  "geometry": {"coordinates":[-88.298908,42.108021],"type":"Point"}
}