{
  "type": "Feature",
  "properties": {
    "iso:country":"US",
    "sg:address":"1167 W Madison St",
    "sg:city":"Chicago",
    "sg:phone":"+1 312 226 6677",
    "sg:postcode":"60607",
    "sg:province":"IL",
    "sg:website":"http://www.shop2sistersonline.com",
    "wof:name":"2 Sisters Boutique",
    "wof:placetype":"venue"
},
  "geometry": {"coordinates":[-87.656819,41.881609],"type":"Point"}
}