{
  "type": "Feature",
  "properties": {
    "addr:full":"7365 N Damen Ave Bsmt Chicago IL 60645",
    "addr:housenumber":"7365",
    "addr:postcode":"60645",
    "addr:street":"N Damen Ave",
    "iso:country":"US",
    "sg:address":"7365 N Damen Ave Bsmt",
    "sg:city":"Chicago",
    "sg:classifiers":[
        {
            "category":"Retail",
            "subcategory":"Repair Shop",
            "type":"Services"
        }
    ],
    "sg:phone":"+1 773 274 4912",
    "sg:postcode":"60645",
    "sg:province":"IL",
    "sg:tags":[
        "vinyl"
    ],
    "wof:name":"Cool Upholstery",
    "wof:placetype":"venue"
},
  "geometry": {"coordinates":[-87.68042800000001,42.015682],"type":"Point"}
}