{
  "type": "Feature",
  "properties": {
    "addr:full":"8440 S Parnell Ave Chicago IL 60620",
    "addr:housenumber":"8440",
    "addr:postcode":"60620",
    "addr:street":"S Parnell Ave",
    "iso:country":"US",
    "sg:address":"8440 S Parnell Ave",
    "sg:city":"Chicago",
    "sg:classifiers":[
        {
            "category":"Real Estate",
            "subcategory":"Real Estate Operator",
            "type":"Services"
        }
    ],
    "sg:phone":"+1 773 651 9234",
    "sg:postcode":"60620",
    "sg:province":"IL",
    "sg:tags":[
        "apartment"
    ],
    "wof:name":"Stone Terrace Apts",
    "wof:placetype":"venue"
},
  "geometry": {"coordinates":[-87.637604,41.740299],"type":"Point"}
}