{
  "type": "Feature",
  "properties": {
    "iso:country":"US",
    "sg:address":"1125 Nottingham Ln",
    "sg:city":"Elgin",
    "sg:classifiers":[
        {
            "category":"Building & Trades",
            "subcategory":"Construction",
            "type":"Services"
        }
    ],
    "sg:phone":"+1 847 888 8006",
    "sg:postcode":"60120",
    "sg:province":"IL",
    "sg:tags":[
        "insulation",
        "heat",
        "contractor"
    ],
    "wof:name":"General Insulation Co",
    "wof:placetype":"venue"
},
  "geometry": {"coordinates":[-88.22751,42.026426],"type":"Point"}
}