{
  "type": "Feature",
  "properties": {
    "addr:full":"5100 N Marine Dr Chicago IL 60640",
    "addr:housenumber":"5100",
    "addr:postcode":"60640",
    "addr:street":"N Marine Dr",
    "iso:country":"US",
    "sg:address":"5100 N Marine Dr",
    "sg:city":"Chicago",
    "sg:classifiers":[
        {
            "category":"Real Estate",
            "subcategory":"Real Estate Services",
            "type":"Services"
        }
    ],
    "sg:phone":"+1 773 561 7115",
    "sg:postcode":"60640",
    "sg:province":"IL",
    "sg:tags":[
        "vacancy",
        "apartment",
        "rental",
        "finder",
        "listing"
    ],
    "wof:name":"Krohn Studio",
    "wof:placetype":"venue"
},
  "geometry": {"coordinates":[-87.651642,41.975349],"type":"Point"}
}