{
  "type": "Feature",
  "properties": {
    "iso:country":"US",
    "sg:address":"23055 Bussey Dr",
    "sg:city":"Plainfield",
    "sg:classifiers":[
        {
            "category":"Manufacturing",
            "subcategory":"Glass & Minerals",
            "type":"Manufacturing & Wholesale Goods"
        }
    ],
    "sg:phone":"+1 815 439 3713",
    "sg:postcode":"60586",
    "sg:province":"IL",
    "sg:tags":[
        "leaded-commercial",
        "glass-stained",
        "leaded",
        "stained"
    ],
    "wof:name":"Glasart",
    "wof:placetype":"venue"
},
  "geometry": {"coordinates":[-88.17854,41.581125],"type":"Point"}
}