{
  "type": "Feature",
  "properties": {
    "iso:country":"US",
    "sg:address":"124 N 1st St",
    "sg:city":"Champaign",
    "sg:classifiers":[
        {
            "category":"Personal",
            "subcategory":"Barber",
            "type":"Services"
        }
    ],
    "sg:phone":"+1 217 398 9689",
    "sg:postcode":"61820",
    "sg:province":"IL",
    "sg:website":"www.roseandtaylor.com",
    "wof:name":"Rose & Taylor Barber Shop",
    "wof:placetype":"venue"
},
  "geometry": {"coordinates":[-88.23850299999999,40.116699],"type":"Point"}
}