{
  "type": "Feature",
  "properties": {
    "iso:country":"US",
    "sg:address":"77 N Airlite St",
    "sg:city":"Elgin",
    "sg:classifiers":[
        {
            "category":"Health Services",
            "subcategory":"Doctor",
            "type":"Services"
        }
    ],
    "sg:phone":"+1 847 695 3200",
    "sg:postcode":"60123",
    "sg:province":"IL",
    "sg:tags":[
        "medical",
        "hospital",
        "specialty"
    ],
    "wof:name":"Provena St Jsephs Radiologists",
    "wof:placetype":"venue"
},
  "geometry": {"coordinates":[-88.32768799999999,42.037243],"type":"Point"}
}