{
  "type": "Feature",
  "properties": {
    "iso:country":"US",
    "sg:address":"5 Oakbrook Ter",
    "sg:city":"Oakbrook Terrace",
    "sg:classifiers":[
        {
            "category":"Restaurant",
            "type":"Food & Drink"
        }
    ],
    "sg:phone":"+1 630 932 9323",
    "sg:postcode":"60181",
    "sg:province":"IL",
    "sg:website":"www.anywayspub.com",
    "wof:name":"Anyway's Chicago Grill & Bar",
    "wof:placetype":"venue"
},
  "geometry": {"coordinates":[-87.9863,41.84522],"type":"Point"}
}