{
  "type": "Feature",
  "properties": {
    "addr:full":"2261 W 111th St Chicago IL 60643",
    "addr:housenumber":"2261",
    "addr:postcode":"60643",
    "addr:street":"W 111Th St",
    "iso:country":"US",
    "sg:address":"2261 W 111th St",
    "sg:city":"Chicago",
    "sg:classifiers":[
        {
            "category":"Freight",
            "type":"Transportation"
        }
    ],
    "sg:phone":"+1 773 233 7688",
    "sg:postcode":"60643",
    "sg:province":"IL",
    "sg:tags":[
        "testing"
    ],
    "wof:name":"S & G Group Inc",
    "wof:placetype":"venue"
},
  "geometry": {"coordinates":[-87.680605,41.691701],"type":"Point"}
}