{
  "type": "Feature",
  "properties": {
    "addr:full":"8718 Galleria Ct Spring Grove IL 60081",
    "addr:housenumber":"8718",
    "addr:postcode":"60081",
    "addr:street":"Galleria Ct",
    "iso:country":"US",
    "sg:address":"8718 Galleria Ct",
    "sg:city":"Spring Grove",
    "sg:classifiers":[
        {
            "category":"Professional",
            "subcategory":"Advertising",
            "type":"Services"
        }
    ],
    "sg:phone":"+1 847 437 0050",
    "sg:postcode":"60081",
    "sg:province":"IL",
    "sg:tags":[
        "counselor"
    ],
    "wof:name":"Marketing By Design",
    "wof:placetype":"venue"
},
  "geometry": {"coordinates":[-88.25259800000001,42.455113],"type":"Point"}
}