{
  "type": "Feature",
  "properties": {
    "iso:country":"US",
    "sg:address":"5050 S Kedzie Ave",
    "sg:city":"Chicago",
    "sg:classifiers":[
        {
            "category":"Health Services",
            "subcategory":"Dentist",
            "type":"Services"
        }
    ],
    "sg:phone":"+1 773 778 2200",
    "sg:postcode":"60632",
    "sg:province":"IL",
    "sg:website":"www.sonrisafamilydental.com",
    "wof:name":"Sonrisa Family Dental",
    "wof:placetype":"venue"
},
  "geometry": {"coordinates":[-87.70397,41.80211],"type":"Point"}
}