{
  "type": "Feature",
  "properties": {
    "iso:country":"US",
    "sg:address":"6315 N Keystone Ave",
    "sg:city":"Chicago",
    "sg:classifiers":[
        {
            "category":"Wholesale",
            "subcategory":"Furniture",
            "type":"Manufacturing & Wholesale Goods"
        }
    ],
    "sg:phone":"+1 773 794 1541",
    "sg:postcode":"60646",
    "sg:province":"IL",
    "wof:name":"Dick Kimoto Associates",
    "wof:placetype":"venue"
},
  "geometry": {"coordinates":[-87.73004899999999,41.996442],"type":"Point"}
}