{
  "type": "Feature",
  "properties": {
    "iso:country":"US",
    "sg:address":"21 N Brockway St",
    "sg:city":"Palatine",
    "sg:classifiers":[
        {
            "category":"Health Services",
            "subcategory":"Clinic",
            "type":"Services"
        }
    ],
    "sg:phone":"+1 847 202 1249",
    "sg:postcode":"60067",
    "sg:province":"IL",
    "sg:tags":[
        "home"
    ],
    "wof:name":"European Services At Home Inc",
    "wof:placetype":"venue"
},
  "geometry": {"coordinates":[-88.046121,42.1107],"type":"Point"}
}