{
  "type": "Feature",
  "properties": {
    "addr:full":"334 Evergreen Dr Bolingbrook IL 60440",
    "addr:housenumber":"334",
    "addr:postcode":"60440",
    "addr:street":"Evergreen Dr",
    "iso:country":"US",
    "sg:address":"334 Evergreen Dr",
    "sg:city":"Bolingbrook",
    "sg:classifiers":[
        {
            "category":"Building & Trades",
            "subcategory":"Construction",
            "type":"Services"
        }
    ],
    "sg:phone":"+1 630 972 2181",
    "sg:postcode":"60440",
    "sg:province":"IL",
    "sg:tags":[
        "house"
    ],
    "wof:name":"F-Squared LLC",
    "wof:placetype":"venue"
},
  "geometry": {"coordinates":[-88.054802,41.69717],"type":"Point"}
}