{
  "type": "Feature",
  "properties": {
    "iso:country":"US",
    "sg:address":"724 S Broadway Ave",
    "sg:city":"Urbana",
    "sg:classifiers":[
        {
            "category":"Travel",
            "subcategory":"Hotels & Motels",
            "type":"Entertainment"
        }
    ],
    "sg:phone":"+1 217 586 6938",
    "sg:postcode":"61801",
    "sg:province":"IL",
    "sg:tags":[
        "cottage",
        "cabin"
    ],
    "wof:name":"Cozy Cottage",
    "wof:placetype":"venue"
},
  "geometry": {"coordinates":[-88.207172,40.105794],"type":"Point"}
}