{
  "type": "Feature",
  "properties": {
    "addr:full":"3501 N Kostner Ave Chicago IL 60641",
    "addr:housenumber":"3501",
    "addr:postcode":"60641",
    "addr:street":"N Kostner Ave",
    "iso:country":"US",
    "sg:address":"3501 N Kostner Ave",
    "sg:city":"Chicago",
    "sg:classifiers":[
        {
            "category":"Utilities",
            "subcategory":"Sewage",
            "type":"Services"
        }
    ],
    "sg:phone":"+1 773 545 8203",
    "sg:postcode":"60641",
    "sg:province":"IL",
    "sg:tags":[
        "equipment",
        "treatment"
    ],
    "wof:name":"A-Better Way Sewerage",
    "wof:placetype":"venue"
},
  "geometry": {"coordinates":[-87.737218,41.945795],"type":"Point"}
}