{
  "type": "Feature",
  "properties": {
    "iso:country":"US",
    "sg:address":"11692 N 100th St",
    "sg:city":"Altamont",
    "sg:classifiers":[
        {
            "category":"Professional",
            "type":"Services"
        }
    ],
    "sg:phone":"+1 618 483 3355",
    "sg:postcode":"62411",
    "sg:province":"IL",
    "sg:tags":[
        "establishment"
    ],
    "wof:name":"Delta Instrument Co",
    "wof:placetype":"venue"
},
  "geometry": {"coordinates":[-88.785526,39.07754],"type":"Point"}
}