{
  "type": "Feature",
  "properties": {
    "iso:country":"US",
    "sg:address":"1916 Lee St",
    "sg:city":"Evanston",
    "sg:classifiers":[
        {
            "category":"Shopping",
            "type":"Retail Goods"
        }
    ],
    "sg:phone":"+1   ",
    "sg:postcode":"60202",
    "sg:province":"IL",
    "sg:tags":[
        "merchandise"
    ],
    "wof:name":"Happyart",
    "wof:placetype":"venue"
},
  "geometry": {"coordinates":[-87.69985699999999,42.035595],"type":"Point"}
}