{
  "type": "Feature",
  "properties": {
    "addr:full":"909 State Rte 83 Elmhurst IL 60126",
    "addr:housenumber":"909",
    "addr:postcode":"60126",
    "addr:street":"State Rte 83",
    "iso:country":"US",
    "sg:address":"909 State Rte 83",
    "sg:city":"Elmhurst",
    "sg:classifiers":[
        {
            "category":"Professional",
            "subcategory":"Engineering",
            "type":"Services"
        }
    ],
    "sg:phone":"+1 630 782 6399",
    "sg:postcode":"60126",
    "sg:province":"IL",
    "sg:tags":[
        "engineer"
    ],
    "wof:name":"Car Technologies",
    "wof:placetype":"venue"
},
  "geometry": {"coordinates":[-87.96134499999999,41.874844],"type":"Point"}
}