{
  "type": "Feature",
  "properties": {
    "iso:country":"US",
    "sg:address":"316 Main St",
    "sg:city":"Savanna",
    "sg:classifiers":[
        {
            "category":"Professional",
            "type":"Services"
        }
    ],
    "sg:phone":"+1 815 273 5300",
    "sg:postcode":"61074",
    "sg:province":"IL",
    "sg:tags":[
        "weather",
        "forecast"
    ],
    "wof:name":"W C Ci Weather",
    "wof:placetype":"venue"
},
  "geometry": {"coordinates":[-90.156768,42.094251],"type":"Point"}
}