{
  "type": "Feature",
  "properties": {
    "iso:country":"US",
    "sg:address":"7400 S Narragansett Avenue",
    "sg:city":"Chicago",
    "sg:classifiers":[
        {
            "category":"Building & Trades",
            "subcategory":"Construction",
            "type":"Services"
        }
    ],
    "sg:phone":"+1 708 594 1004",
    "sg:postcode":"60638",
    "sg:province":"IL",
    "sg:tags":[
        "contractor"
    ],
    "wof:name":"Gatx Logistics",
    "wof:placetype":"venue"
},
  "geometry": {"coordinates":[-87.780573,41.757541],"type":"Point"}
}