{
  "type": "Feature",
  "properties": {
    "addr:full":"6097 N Northwest Hwy Chicago IL 60631",
    "addr:housenumber":"6097",
    "addr:postcode":"60631",
    "addr:street":"N Northwest Hwy",
    "iso:country":"US",
    "sg:address":"6097 N Northwest Hwy",
    "sg:city":"Chicago",
    "sg:classifiers":[
        {
            "category":"Professional",
            "subcategory":"Lawyer & Legal Services",
            "type":"Services"
        }
    ],
    "sg:phone":"+1 773 792 9100",
    "sg:postcode":"60631",
    "sg:province":"IL",
    "wof:name":"Montemurro Anthony M Atty",
    "wof:placetype":"venue"
},
  "geometry": {"coordinates":[-87.798698,41.9921],"type":"Point"}
}