{
  "type": "Feature",
  "properties": {
    "addr:full":"209 N York St Elmhurst IL 60126",
    "addr:housenumber":"209",
    "addr:postcode":"60126",
    "addr:street":"N York St",
    "iso:country":"US",
    "sg:address":"209 N York St",
    "sg:city":"Elmhurst",
    "sg:classifiers":[
        {
            "category":"Government",
            "subcategory":"Office",
            "type":"Public Place"
        }
    ],
    "sg:phone":"+1   ",
    "sg:postcode":"60126",
    "sg:province":"IL",
    "sg:tags":[
        "city"
    ],
    "wof:name":"City of Elmhurst",
    "wof:placetype":"venue"
},
  "geometry": {"coordinates":[-87.93985000000001,41.902663],"type":"Point"}
}