{
  "type": "Feature",
  "properties": {
    "iso:country":"US",
    "sg:address":"1100 Arlington Heights Rd",
    "sg:city":"Arlington Heights",
    "sg:classifiers":[
        {
            "category":"Health Services",
            "subcategory":"Doctor",
            "type":"Services"
        }
    ],
    "sg:phone":"+1   ",
    "sg:postcode":"60005",
    "sg:province":"IL",
    "sg:tags":[
        "medical",
        "optical",
        "good"
    ],
    "wof:name":"Suburban Optics",
    "wof:placetype":"venue"
},
  "geometry": {"coordinates":[-87.979868,42.062404],"type":"Point"}
}