{
  "type": "Feature",
  "properties": {
    "iso:country":"US",
    "sg:address":"9329 114th Ave W",
    "sg:city":"Taylor Ridge",
    "sg:classifiers":[
        {
            "category":"Building & Trades",
            "subcategory":"Construction",
            "type":"Services"
        }
    ],
    "sg:phone":"+1 309 798 2994",
    "sg:postcode":"61284",
    "sg:province":"IL",
    "sg:tags":[
        "contractor"
    ],
    "wof:name":"Timothy E Gibbons Gen Contr",
    "wof:placetype":"venue"
},
  "geometry": {"coordinates":[-90.688045,41.41146],"type":"Point"}
}