{
  "type": "Feature",
  "properties": {
    "addr:full":"6550 Route 53 Woodridge IL 60517",
    "addr:housenumber":"6550",
    "addr:postcode":"60517",
    "addr:street":"Route 53",
    "iso:country":"US",
    "sg:address":"6550 Route 53",
    "sg:city":"Woodridge",
    "sg:classifiers":[
        {
            "category":"Bakery",
            "type":"Food & Drink"
        }
    ],
    "sg:menulink":"http://www.allmenus.com/il/lisle/121156-krispy-kreme/menu/",
    "sg:phone":"+1 630 241 0700",
    "sg:postcode":"60517",
    "sg:province":"IL",
    "sg:tags":[
        "american",
        "pastry"
    ],
    "wof:name":"Krispy Kreme",
    "wof:placetype":"venue"
},
  "geometry": {"coordinates":[-88.068242,41.767794],"type":"Point"}
}