{
  "type": "Feature",
  "properties": {
    "addr:full":"409 Grand Ave Waukegan IL 60085",
    "addr:housenumber":"409",
    "addr:postcode":"60085",
    "addr:street":"Grand Ave",
    "iso:country":"US",
    "sg:address":"409 Grand Ave",
    "sg:city":"Waukegan",
    "sg:classifiers":[
        {
            "category":"Professional",
            "subcategory":"Lawyer & Legal Services",
            "type":"Services"
        }
    ],
    "sg:phone":"+1 847 623 2424",
    "sg:postcode":"60085",
    "sg:province":"IL",
    "wof:name":"William Margolin",
    "wof:placetype":"venue"
},
  "geometry": {"coordinates":[-87.83528,42.363706],"type":"Point"}
}