{
  "type": "Feature",
  "properties": {
    "iso:country":"US",
    "sg:address":"634 E Northwest Hwy",
    "sg:city":"Palatine",
    "sg:classifiers":[
        {
            "category":"Education",
            "subcategory":"Junior College",
            "type":"Public Place"
        }
    ],
    "sg:phone":"+1 847 991 8658",
    "sg:postcode":"60074",
    "sg:province":"IL",
    "sg:tags":[
        "technical",
        "institute"
    ],
    "wof:name":"Combat Arts Institute",
    "wof:placetype":"venue"
},
  "geometry": {"coordinates":[-88.025883,42.103242],"type":"Point"}
}