{
  "type": "Feature",
  "properties": {
    "iso:country":"US",
    "sg:address":"215 W. Ontario 5th Fl",
    "sg:city":"Chicago",
    "sg:classifiers":[
        {
            "category":"Education",
            "subcategory":"Dance Studio",
            "type":"Public Place"
        },
        {
            "category":"Arts & Performance",
            "subcategory":"Dance",
            "type":"Entertainment"
        }
    ],
    "sg:phone":"+1 312 427 2572",
    "sg:postcode":"60654",
    "sg:province":"IL",
    "sg:tags":[
        "school"
    ],
    "sg:website":"www.laboriqua.com",
    "wof:name":"Latin Street Dancing Inc",
    "wof:placetype":"venue"
},
  "geometry": {"coordinates":[-87.63483600000001,41.892943],"type":"Point"}
}