{
  "type": "Feature",
  "properties": {
    "iso:country":"US",
    "sg:address":"413 S Main St",
    "sg:city":"Princeton",
    "sg:classifiers":[
        {
            "category":"Manufacturing",
            "subcategory":"Printing",
            "type":"Manufacturing & Wholesale Goods"
        }
    ],
    "sg:phone":"+1 815 872 3911",
    "sg:postcode":"61356",
    "sg:province":"IL",
    "sg:tags":[
        "printer"
    ],
    "sg:website":"www.tribuneprinting.com",
    "wof:name":"Tribune Printing Co",
    "wof:placetype":"venue"
},
  "geometry": {"coordinates":[-89.46498099999999,41.371568],"type":"Point"}
}