{
  "type": "Feature",
  "properties": {
    "iso:country":"US",
    "sg:address":"71 S Adams St",
    "sg:city":"Carthage",
    "sg:classifiers":[
        {
            "category":"Social Services",
            "type":"Services"
        }
    ],
    "sg:phone":"+1 217 357 9079",
    "sg:postcode":"62321",
    "sg:province":"IL",
    "sg:tags":[
        "organization",
        "welfare"
    ],
    "wof:name":"American Red Cross",
    "wof:placetype":"venue"
},
  "geometry": {"coordinates":[-91.134472,40.412737],"type":"Point"}
}