{
  "type": "Feature",
  "properties": {
    "iso:country":"US",
    "sg:address":"630 E Van Buren St",
    "sg:city":"Ottawa",
    "sg:classifiers":[
        {
            "category":"Professional",
            "subcategory":"Business Services",
            "type":"Services"
        }
    ],
    "sg:phone":"+1 815 434 5200",
    "sg:postcode":"61350",
    "sg:province":"IL",
    "wof:name":"Strategic Marketing",
    "wof:placetype":"venue"
},
  "geometry": {"coordinates":[-88.832186,41.339095],"type":"Point"}
}