{
  "type": "Feature",
  "properties": {
    "iso:country":"US",
    "sg:address":"21529 Double Arch Rd",
    "sg:city":"Staunton",
    "sg:classifiers":[
        {
            "category":"Building & Trades",
            "subcategory":"Plumbing",
            "type":"Services"
        }
    ],
    "sg:phone":"+1 217 272 4259",
    "sg:postcode":"62088",
    "sg:province":"IL",
    "sg:tags":[
        "septic"
    ],
    "wof:name":"White Sanitation",
    "wof:placetype":"venue"
},
  "geometry": {"coordinates":[-89.749067,39.008471],"type":"Point"}
}