{
  "type": "Feature",
  "properties": {
    "iso:country":"US",
    "sg:address":"300 W Court St",
    "sg:city":"Jacksonville",
    "sg:classifiers":[
        {
            "category":"Government",
            "subcategory":"Jail",
            "type":"Public Place"
        }
    ],
    "sg:phone":"+1 217 243 6123",
    "sg:postcode":"62650",
    "sg:province":"IL",
    "sg:tags":[
        "county",
        "govt",
        "institution"
    ],
    "wof:name":"Morgan County Jail",
    "wof:placetype":"venue"
},
  "geometry": {"coordinates":[-90.232996,39.734936],"type":"Point"}
}