{
  "type": "Feature",
  "properties": {
    "iso:country":"US",
    "sg:address":"501 N Kedzie Ave",
    "sg:city":"Chicago",
    "sg:classifiers":[
        {
            "category":"Restaurant",
            "type":"Food & Drink"
        }
    ],
    "sg:phone":"+1 773 638 1668",
    "sg:postcode":"60612",
    "sg:province":"IL",
    "sg:tags":[
        "chinese"
    ],
    "wof:name":"Gen Hoe II",
    "wof:placetype":"venue"
},
  "geometry": {"coordinates":[-87.70637499999999,41.890319],"type":"Point"}
}