{
  "type": "Feature",
  "properties": {
    "iso:country":"US",
    "sg:address":"259 Jandus Rd",
    "sg:city":"Cary",
    "sg:classifiers":[
        {
            "category":"Home & Garden",
            "subcategory":"Hardware",
            "type":"Retail Goods"
        }
    ],
    "sg:phone":"+1 847 639 9154",
    "sg:postcode":"60013",
    "sg:province":"IL",
    "wof:name":"AA Door & Hardware Inc",
    "wof:placetype":"venue"
},
  "geometry": {"coordinates":[-88.23231699999999,42.204062],"type":"Point"}
}