{
  "type": "Feature",
  "properties": {
    "iso:country":"US",
    "sg:address":"1507 Rand Rd",
    "sg:city":"Des Plaines",
    "sg:classifiers":[
        {
            "category":"Shopping",
            "subcategory":"Hobbies, Toys, & Games",
            "type":"Retail Goods"
        }
    ],
    "sg:phone":"+1 847 635 7020",
    "sg:postcode":"60016",
    "sg:province":"IL",
    "sg:tags":[
        "craft",
        "supply"
    ],
    "wof:name":"Brudno Art Supply Co",
    "wof:placetype":"venue"
},
  "geometry": {"coordinates":[-87.88701,42.048149],"type":"Point"}
}