{
  "type": "Feature",
  "properties": {
    "iso:country":"US",
    "sg:address":"1605 S Washington St",
    "sg:city":"Lockport",
    "sg:classifiers":[
        {
            "category":"Education",
            "subcategory":"School",
            "type":"Public Place"
        }
    ],
    "sg:phone":"+1 815 838 0408",
    "sg:postcode":"60441",
    "sg:province":"IL",
    "sg:website":"http://www.browncontracting.net",
    "wof:name":"Taft School District 90",
    "wof:placetype":"venue"
},
  "geometry": {"coordinates":[-88.05798799999999,41.58128],"type":"Point"}
}