{
  "type": "Feature",
  "properties": {
    "addr:full":"4435 Adele Ln Oak Forest IL 60452",
    "addr:housenumber":"4435",
    "addr:postcode":"60452",
    "addr:street":"Adele Ln",
    "iso:country":"US",
    "sg:address":"4435 Adele Ln",
    "sg:city":"Oak Forest",
    "sg:classifiers":[
        {
            "category":"Health Services",
            "subcategory":"Doctor",
            "type":"Services"
        }
    ],
    "sg:phone":"+1 708 687 9457",
    "sg:postcode":"60452",
    "sg:province":"IL",
    "sg:tags":[
        "medical"
    ],
    "wof:name":"Shah Dr Kulin",
    "wof:placetype":"venue"
},
  "geometry": {"coordinates":[-87.72880600000001,41.590722],"type":"Point"}
}