{
  "type": "Feature",
  "properties": {
    "iso:country":"US",
    "sg:address":"914 W Bloomington Rd",
    "sg:city":"Champaign",
    "sg:classifiers":[
        {
            "category":"Travel",
            "subcategory":"Hotels & Motels",
            "type":"Entertainment"
        }
    ],
    "sg:phone":"+1 217 356 6000",
    "sg:postcode":"61821",
    "sg:province":"IL",
    "wof:name":"Ameri Inn",
    "wof:placetype":"venue"
},
  "geometry": {"coordinates":[-88.25949900000001,40.1329],"type":"Point"}
}