{
  "type": "Feature",
  "properties": {
    "addr:full":"302 N Henning Rd Danville IL 61832",
    "addr:housenumber":"302",
    "addr:postcode":"61832",
    "addr:street":"N Henning Rd",
    "iso:country":"US",
    "sg:address":"302 N Henning Rd",
    "sg:city":"Danville",
    "sg:classifiers":[
        {
            "category":"Retail",
            "subcategory":"Repair Shop",
            "type":"Services"
        }
    ],
    "sg:phone":"+1 217 446 5009",
    "sg:postcode":"61832",
    "sg:province":"IL",
    "sg:tags":[
        "related"
    ],
    "wof:name":"Marack's Care & Repair",
    "wof:placetype":"venue"
},
  "geometry": {"coordinates":[-87.696764,40.13257],"type":"Point"}
}