{
  "type": "Feature",
  "properties": {
    "iso:country":"US",
    "sg:address":"1308 Rae Ln",
    "sg:city":"Carterville",
    "sg:classifiers":[
        {
            "category":"Real Estate",
            "subcategory":"Real Estate Services",
            "type":"Services"
        }
    ],
    "sg:phone":"+1 618 985 8064",
    "sg:postcode":"62918",
    "sg:province":"IL",
    "sg:tags":[
        "rental"
    ],
    "wof:name":"Clarks Rentals",
    "wof:placetype":"venue"
},
  "geometry": {"coordinates":[-89.048064,37.74935],"type":"Point"}
}