{
  "type": "Feature",
  "properties": {
    "addr:full":"419 John St Apt 111 Rockford IL 61103",
    "addr:housenumber":"419;111",
    "addr:postcode":"61103",
    "addr:street":"John St Apt",
    "iso:country":"US",
    "sg:address":"419 John St Apt 111",
    "sg:city":"Rockford",
    "sg:classifiers":[
        {
            "category":"Real Estate",
            "subcategory":"Real Estate Services",
            "type":"Services"
        },
        {
            "category":"Real Estate",
            "subcategory":"Real Estate Agent",
            "type":"Services"
        }
    ],
    "sg:phone":"+1 815 968 4266",
    "sg:postcode":"61103",
    "sg:province":"IL",
    "sg:tags":[
        "management"
    ],
    "wof:name":"Icon Development Group",
    "wof:placetype":"venue"
},
  "geometry": {"coordinates":[-89.085335,42.282813],"type":"Point"}
}