{
  "type": "Feature",
  "properties": {
    "addr:full":"7447 W Talcott Avenue Suite 422 Chicago IL 60631",
    "addr:housenumber":"7447",
    "addr:postcode":"60631",
    "addr:street":"W Talcott Avenue Suite 422",
    "iso:country":"US",
    "sg:address":"7447 W Talcott Avenue Suite 422",
    "sg:city":"Chicago",
    "sg:classifiers":[
        {
            "category":"Health Services",
            "subcategory":"Doctor",
            "type":"Services"
        }
    ],
    "sg:phone":"+1 773 775 2600",
    "sg:postcode":"60631",
    "sg:province":"IL",
    "wof:name":"Hirani Mona MD",
    "wof:placetype":"venue"
},
  "geometry": {"coordinates":[-87.808083,41.999451],"type":"Point"}
}