{
  "type": "Feature",
  "properties": {
    "iso:country":"US",
    "sg:address":"1000 Oakland Ave",
    "sg:city":"Joliet",
    "sg:classifiers":[
        {
            "category":"Organizations",
            "subcategory":"Religious Organization",
            "type":"Services"
        }
    ],
    "sg:phone":"+1 815 727 4326",
    "sg:postcode":"60435",
    "sg:province":"IL",
    "wof:name":"Gospel Of Peace",
    "wof:placetype":"venue"
},
  "geometry": {"coordinates":[-88.09787300000001,41.543281],"type":"Point"}
}