{
  "type": "Feature",
  "properties": {
    "addr:full":"201 S Quincy Ave Bradley IL 60915",
    "addr:housenumber":"201",
    "addr:postcode":"60915",
    "addr:street":"S Quincy Ave",
    "iso:country":"US",
    "sg:address":"201 S Quincy Ave",
    "sg:city":"Bradley",
    "sg:classifiers":[
        {
            "category":"Manufacturing",
            "subcategory":"Printing",
            "type":"Manufacturing & Wholesale Goods"
        }
    ],
    "sg:phone":"+1 815 937 9032",
    "sg:postcode":"60915",
    "sg:province":"IL",
    "sg:tags":[
        "print",
        "lithographic",
        "merchandise",
        "mfg"
    ],
    "wof:name":"Crown Press Printers",
    "wof:placetype":"venue"
},
  "geometry": {"coordinates":[-87.84952199999999,41.140845],"type":"Point"}
}