{
  "type": "Feature",
  "properties": {
    "iso:country":"US",
    "sg:address":"1146 Lehnertz Cir",
    "sg:city":"Aurora",
    "sg:classifiers":[
        {
            "category":"Building & Trades",
            "subcategory":"Construction",
            "type":"Services"
        }
    ],
    "sg:phone":"+1 630 898 8125",
    "sg:postcode":"60505",
    "sg:province":"IL",
    "sg:tags":[
        "home",
        "builder"
    ],
    "wof:name":"Crestwood Builders",
    "wof:placetype":"venue"
},
  "geometry": {"coordinates":[-88.288158,41.773238],"type":"Point"}
}