{
  "type": "Feature",
  "properties": {
    "iso:country":"US",
    "sg:address":"Siuc Student Ctr",
    "sg:city":"Carbondale",
    "sg:classifiers":[
        {
            "category":"Shopping",
            "subcategory":"Books",
            "type":"Retail Goods"
        }
    ],
    "sg:phone":"+1 618 536 3321",
    "sg:postcode":"62901",
    "sg:province":"IL",
    "sg:tags":[
        "bookstore"
    ],
    "wof:name":"University Bookstore",
    "wof:placetype":"venue"
},
  "geometry": {"coordinates":[-89.215897,37.7253],"type":"Point"}
}