{
  "type": "Feature",
  "properties": {
    "addr:full":"1700 E Higgins Rd Des Plaines IL 60018",
    "addr:housenumber":"1700",
    "addr:postcode":"60018",
    "addr:street":"E Higgins Rd Des",
    "iso:country":"US",
    "sg:address":"1700 E Higgins Rd",
    "sg:city":"Des Plaines",
    "sg:classifiers":[
        {
            "category":"Manufacturing",
            "subcategory":"Printing",
            "type":"Manufacturing & Wholesale Goods"
        }
    ],
    "sg:phone":"+1 847 375 5000",
    "sg:postcode":"60018",
    "sg:province":"IL",
    "sg:tags":[
        "directory",
        "publisher",
        "medium"
    ],
    "wof:name":"Srds",
    "wof:placetype":"venue"
},
  "geometry": {"coordinates":[-87.881221,41.997447],"type":"Point"}
}