{
  "type": "Feature",
  "properties": {
    "addr:full":"6519 Cermak Rd Berwyn IL 60402",
    "addr:housenumber":"6519",
    "addr:postcode":"60402",
    "addr:street":"Cermak Rd",
    "iso:country":"US",
    "sg:address":"6519 Cermak Rd",
    "sg:city":"Berwyn",
    "sg:classifiers":[
        {
            "category":"Fast Food",
            "type":"Food & Drink"
        }
    ],
    "sg:phone":"+1 708 484 4012",
    "sg:postcode":"60402",
    "sg:province":"IL",
    "sg:website":"www.kfc.com",
    "wof:name":"KFC",
    "wof:placetype":"venue"
},
  "geometry": {"coordinates":[-87.78730899999999,41.850545],"type":"Point"}
}