{
  "type": "Feature",
  "properties": {
    "iso:country":"US",
    "sg:address":"5302 N 2nd St",
    "sg:city":"Loves Park",
    "sg:classifiers":[
        {
            "category":"Autos & Motor Vehicles",
            "subcategory":"Auto Supplies",
            "type":"Retail Goods"
        }
    ],
    "sg:phone":"+1   ",
    "sg:postcode":"61111",
    "sg:province":"IL",
    "sg:tags":[
        "parts"
    ],
    "wof:name":"Automotive Repair",
    "wof:placetype":"venue"
},
  "geometry": {"coordinates":[-89.057891,42.307457],"type":"Point"}
}