{
  "type": "Feature",
  "properties": {
    "iso:country":"US",
    "sg:address":"21 W 107th St",
    "sg:city":"Chicago",
    "sg:classifiers":[
        {
            "category":"Utilities",
            "subcategory":"Refuse",
            "type":"Services"
        }
    ],
    "sg:phone":"+1 773 468 5865",
    "sg:postcode":"60628",
    "sg:province":"IL",
    "sg:tags":[
        "container",
        "garbage",
        "collection",
        "removal",
        "rubbish"
    ],
    "wof:name":"Clean Up Clean Out",
    "wof:placetype":"venue"
},
  "geometry": {"coordinates":[-87.624292,41.699863],"type":"Point"}
}