{
  "type": "Feature",
  "properties": {
    "addr:full":"126 Feece Dr Batavia IL 60510",
    "addr:housenumber":"126",
    "addr:postcode":"60510",
    "addr:street":"Feece Dr",
    "iso:country":"US",
    "sg:address":"126 Feece Dr",
    "sg:city":"Batavia",
    "sg:classifiers":[
        {
            "category":"Building & Trades",
            "subcategory":"Electrical",
            "type":"Services"
        }
    ],
    "sg:phone":"+1 630 406 1007",
    "sg:postcode":"60510",
    "sg:province":"IL",
    "sg:tags":[
        "electrical",
        "contractor"
    ],
    "wof:name":"Tri Cities",
    "wof:placetype":"venue"
},
  "geometry": {"coordinates":[-88.336388,41.848688],"type":"Point"}
}