{
  "type": "Feature",
  "properties": {
    "iso:country":"US",
    "sg:address":"7399 159th St",
    "sg:city":"Tinley Park",
    "sg:classifiers":[
        {
            "category":"Organizations",
            "subcategory":"Religious Organization",
            "type":"Services"
        }
    ],
    "sg:phone":"+1 708 429 6767",
    "sg:postcode":"60477",
    "sg:province":"IL",
    "wof:name":"St Julie Billiart Parish",
    "wof:placetype":"venue"
},
  "geometry": {"coordinates":[-87.798448,41.602219],"type":"Point"}
}