{
  "type": "Feature",
  "properties": {
    "iso:country":"US",
    "sg:address":"540 Duane St",
    "sg:city":"Glen Ellyn",
    "sg:classifiers":[
        {
            "category":"Professional",
            "subcategory":"Engineering",
            "type":"Services"
        }
    ],
    "sg:phone":"+1 630 545 9200",
    "sg:postcode":"60137",
    "sg:province":"IL",
    "wof:name":"Andersen",
    "wof:placetype":"venue"
},
  "geometry": {"coordinates":[-88.06566599999999,41.875534],"type":"Point"}
}