{
  "type": "Feature",
  "properties": {
    "addr:full":"330 May Mart Dr Rochelle IL 61068",
    "addr:housenumber":"330",
    "addr:postcode":"61068",
    "addr:street":"May Mart Dr",
    "iso:country":"US",
    "sg:address":"330 May Mart Dr",
    "sg:city":"Rochelle",
    "sg:classifiers":[
        {
            "category":"Insurance",
            "subcategory":"Hazard Insurance",
            "type":"Services"
        }
    ],
    "sg:phone":"+1 815 562 4152",
    "sg:postcode":"61068",
    "sg:province":"IL",
    "sg:tags":[
        "commercial",
        "business"
    ],
    "sg:website":"http://www.queryinsurance.com",
    "wof:name":"Query Insurance Agency Inc",
    "wof:placetype":"venue"
},
  "geometry": {"coordinates":[-89.06359500000001,41.932973],"type":"Point"}
}