{
  "type": "Feature",
  "properties": {
    "addr:full":"2341 Willow Rd Glenview IL 60025",
    "addr:housenumber":"2341",
    "addr:postcode":"60025",
    "addr:street":"Willow Rd",
    "iso:country":"US",
    "sg:address":"2341 Willow Rd",
    "sg:city":"Glenview",
    "sg:classifiers":[
        {
            "category":"Restaurant",
            "type":"Food & Drink"
        }
    ],
    "sg:menulink":"http://www.allmenus.com/il/northfield/221780-chipotle/menu/",
    "sg:phone":"+1 847 724 8580",
    "sg:postcode":"60025",
    "sg:province":"IL",
    "sg:tags":[
        "mexican"
    ],
    "wof:name":"Chipotle",
    "wof:placetype":"venue"
},
  "geometry": {"coordinates":[-87.80910900000001,42.105385],"type":"Point"}
}