{
  "type": "Feature",
  "properties": {
    "addr:full":"300 N Ottawa St Joliet IL 60432",
    "addr:housenumber":"300",
    "addr:postcode":"60432",
    "addr:street":"N Ottawa St",
    "iso:country":"US",
    "sg:address":"300 N Ottawa St",
    "sg:city":"Joliet",
    "sg:classifiers":[
        {
            "category":"Shopping",
            "subcategory":"Pharmacy",
            "type":"Retail Goods"
        }
    ],
    "sg:phone":"+1   ",
    "sg:postcode":"60432",
    "sg:province":"IL",
    "sg:tags":[
        "drug",
        "store"
    ],
    "wof:name":"Basinger Pharmacy Inc",
    "wof:placetype":"venue"
},
  "geometry": {"coordinates":[-88.08314300000001,41.530657],"type":"Point"}
}