{
  "type": "Feature",
  "properties": {
    "addr:full":"1700 New Era Rd Carbondale IL 62901",
    "addr:housenumber":"1700",
    "addr:postcode":"62901",
    "addr:street":"New Era Rd",
    "iso:country":"US",
    "sg:address":"1700 New Era Rd",
    "sg:city":"Carbondale",
    "sg:classifiers":[
        {
            "category":"Insurance",
            "subcategory":"Insurance Agent",
            "type":"Services"
        }
    ],
    "sg:phone":"+1 618 529 2261",
    "sg:postcode":"62901",
    "sg:province":"IL",
    "sg:website":"www.gearhartonline.com",
    "wof:name":"Gearhart & Assoc",
    "wof:placetype":"venue"
},
  "geometry": {"coordinates":[-89.246055,37.747892],"type":"Point"}
}