{
  "type": "Feature",
  "properties": {
    "addr:full":"976 State Rte 59 Aurora IL 60504",
    "addr:housenumber":"976",
    "addr:postcode":"60504",
    "addr:street":"State Rte 59",
    "iso:country":"US",
    "sg:address":"976 State Rte 59",
    "sg:city":"Aurora",
    "sg:classifiers":[
        {
            "category":"Shopping",
            "type":"Retail Goods"
        }
    ],
    "sg:phone":"+1 630 851 1310",
    "sg:postcode":"60504",
    "sg:province":"IL",
    "sg:tags":[
        "pet",
        "shop"
    ],
    "wof:name":"Petsmart",
    "wof:placetype":"venue"
},
  "geometry": {"coordinates":[-88.205748,41.783548],"type":"Point"}
}