{
  "type": "Feature",
  "properties": {
    "addr:full":"2010 N Main St Canton IL 61520",
    "addr:housenumber":"2010",
    "addr:postcode":"61520",
    "addr:street":"N Main St",
    "iso:country":"US",
    "sg:address":"2010 N Main St",
    "sg:city":"Canton",
    "sg:classifiers":[
        {
            "category":"Insurance",
            "subcategory":"Hazard Insurance",
            "type":"Services"
        }
    ],
    "sg:phone":"+1 309 647 7711",
    "sg:postcode":"61520",
    "sg:province":"IL",
    "sg:website":"http://statefarm.mqgroup.com/url.asp?usr=133756",
    "wof:name":"State Farm Insurance Agent-Dee Clark",
    "wof:placetype":"venue"
},
  "geometry": {"coordinates":[-90.036041,40.589611],"type":"Point"}
}