{
  "type": "Feature",
  "properties": {
    "iso:country":"US",
    "sg:address":"805 N Burning Bush Ln",
    "sg:city":"Mount Prospect",
    "sg:classifiers":[
        {
            "category":"Social Services",
            "subcategory":"Child Care",
            "type":"Services"
        }
    ],
    "sg:phone":"+1 847 296 3044",
    "sg:postcode":"60056",
    "sg:province":"IL",
    "sg:tags":[
        "elementary",
        "school",
        "preschool"
    ],
    "wof:name":"Park View Montessori School",
    "wof:placetype":"venue"
},
  "geometry": {"coordinates":[-87.897918,42.080947],"type":"Point"}
}