{
  "type": "Feature",
  "properties": {
    "iso:country":"US",
    "sg:address":"1270 N Lake St",
    "sg:city":"Aurora",
    "sg:classifiers":[
        {
            "category":"Food & Beverages",
            "subcategory":"Groceries & Convenience Stores",
            "type":"Retail Goods"
        }
    ],
    "sg:phone":"+1   ",
    "sg:postcode":"60506",
    "sg:province":"IL",
    "wof:name":"Jewel-Osco 3270",
    "wof:placetype":"venue"
},
  "geometry": {"coordinates":[-88.318815,41.783446],"type":"Point"}
}