{
  "type": "Feature",
  "properties": {
    "iso:country":"US",
    "sg:address":"809 E 4000S Rd",
    "sg:city":"Kankakee",
    "sg:classifiers":[
        {
            "category":"Education",
            "subcategory":"Special Training",
            "type":"Public Place"
        }
    ],
    "sg:phone":"+1 815 939 3575",
    "sg:postcode":"60901",
    "sg:province":"IL",
    "sg:tags":[
        "school",
        "aircraft",
        "pilot"
    ],
    "wof:name":"K 3 Aeronautics II Inc",
    "wof:placetype":"venue"
},
  "geometry": {"coordinates":[-87.84083200000001,41.062582],"type":"Point"}
}