{
  "type": "Feature",
  "properties": {
    "addr:full":"12570 N Davis Rd Davis IL 61019",
    "addr:housenumber":"12570",
    "addr:postcode":"61019",
    "addr:street":"N Davis Rd",
    "iso:country":"US",
    "sg:address":"12570 N Davis Rd",
    "sg:city":"Davis",
    "sg:classifiers":[
        {
            "category":"Manufacturing",
            "subcategory":"Pet Food",
            "type":"Manufacturing & Wholesale Goods"
        },
        {
            "category":"Farming",
            "subcategory":"Farm",
            "type":"Manufacturing & Wholesale Goods"
        }
    ],
    "sg:phone":"+1 815 865 5225",
    "sg:postcode":"61019",
    "sg:province":"IL",
    "sg:tags":[
        "hay"
    ],
    "wof:name":"Faulkner, Stanly",
    "wof:placetype":"venue"
},
  "geometry": {"coordinates":[-89.42054,42.49046],"type":"Point"}
}