{
  "type": "Feature",
  "properties": {
    "iso:country":"US",
    "sg:address":"1709 Winery Rd",
    "sg:city":"West Frankfort",
    "sg:classifiers":[
        {
            "category":"Building & Trades",
            "subcategory":"Construction",
            "type":"Services"
        }
    ],
    "sg:phone":"+1 618 932 6473",
    "sg:postcode":"62896",
    "sg:province":"IL",
    "sg:tags":[
        "excavation",
        "contractor"
    ],
    "wof:name":"Denise Sloan",
    "wof:placetype":"venue"
},
  "geometry": {"coordinates":[-88.956178,37.889679],"type":"Point"}
}