{
  "type": "Feature",
  "properties": {
    "iso:country":"US",
    "sg:address":"940 Roosevelt Rd",
    "sg:city":"Glen Ellyn",
    "sg:classifiers":[
        {
            "category":"Bars & Pubs",
            "subcategory":"Sports Bar",
            "type":"Food & Drink"
        },
        {
            "category":"Restaurant",
            "type":"Food & Drink"
        }
    ],
    "sg:phone":"+1 630 942 0940",
    "sg:postcode":"60137",
    "sg:province":"IL",
    "sg:tags":[
        "new",
        "american"
    ],
    "sg:website":"www.ellyns.com",
    "wof:name":"Ellyn's Tap and Grill",
    "wof:placetype":"venue"
},
  "geometry": {"coordinates":[-88.04010700000001,41.859634],"type":"Point"}
}