{
  "type": "Feature",
  "properties": {
    "iso:country":"US",
    "sg:address":"4029 Aberdeen Ave",
    "sg:city":"Alton",
    "sg:classifiers":[
        {
            "category":"Health Services",
            "subcategory":"Nursing And Care Facility",
            "type":"Services"
        }
    ],
    "sg:phone":"+1 618 462 1515",
    "sg:postcode":"62002",
    "sg:province":"IL",
    "wof:name":"Aberdeen Terrace",
    "wof:placetype":"venue"
},
  "geometry": {"coordinates":[-90.121872,38.893159],"type":"Point"}
}