{
  "type": "Feature",
  "properties": {
    "addr:full":"315 Railroad St Algonquin IL 60102",
    "addr:housenumber":"315",
    "addr:postcode":"60102",
    "addr:street":"Railroad St",
    "iso:country":"US",
    "sg:address":"315 Railroad St",
    "sg:city":"Algonquin",
    "sg:classifiers":[
        {
            "category":"Shopping",
            "subcategory":"Bicycles & Sporting Goods",
            "type":"Retail Goods"
        },
        {
            "category":"Sports & Exercise",
            "subcategory":"Bicycle Rental",
            "type":"Entertainment"
        }
    ],
    "sg:phone":"+1 847 658 1154",
    "sg:postcode":"60102",
    "sg:province":"IL",
    "sg:tags":[
        "bike"
    ],
    "wof:name":"Prairie Trail Bike Shop",
    "wof:placetype":"venue"
},
  "geometry": {"coordinates":[-88.29409800000001,42.165699],"type":"Point"}
}