{
  "type": "Feature",
  "properties": {
    "iso:country":"US",
    "sg:address":"360 W Illinois St Ofc",
    "sg:city":"Chicago",
    "sg:classifiers":[
        {
            "category":"Retail",
            "subcategory":"Funeral Services",
            "type":"Services"
        }
    ],
    "sg:phone":"+1 312 644 8769",
    "sg:postcode":"60610",
    "sg:province":"IL",
    "sg:tags":[
        "cemetery"
    ],
    "wof:name":"Thompson and Kuenster Funeral Home",
    "wof:placetype":"venue"
},
  "geometry": {"coordinates":[-87.636803,41.8908],"type":"Point"}
}