{
  "type": "Feature",
  "properties": {
    "iso:country":"US",
    "sg:address":"11584 Saladino Ct",
    "sg:city":"Roscoe",
    "sg:classifiers":[
        {
            "category":"Building & Trades",
            "subcategory":"Construction",
            "type":"Services"
        }
    ],
    "sg:phone":"+1 815 623 6021",
    "sg:postcode":"61073",
    "sg:province":"IL",
    "sg:tags":[
        "general",
        "house",
        "industrial",
        "co",
        "contractor"
    ],
    "wof:name":"Buddy Lake Builders",
    "wof:placetype":"venue"
},
  "geometry": {"coordinates":[-88.984104,42.42981],"type":"Point"}
}