{
  "type": "Feature",
  "properties": {
    "iso:country":"US",
    "sg:address":"850 36th Ave",
    "sg:city":"Moline",
    "sg:classifiers":[
        {
            "category":"Health Services",
            "subcategory":"Doctor",
            "type":"Services"
        }
    ],
    "sg:phone":"+1 309 764 7631",
    "sg:postcode":"61265",
    "sg:province":"IL",
    "sg:tags":[
        "clinic",
        "dentist"
    ],
    "wof:name":"Rhonda Van Speybroeck DDS",
    "wof:placetype":"venue"
},
  "geometry": {"coordinates":[-90.526358,41.47178],"type":"Point"}
}