{
  "type": "Feature",
  "properties": {
    "addr:full":"123 E Washington St Oswego IL 60543",
    "addr:housenumber":"123",
    "addr:postcode":"60543",
    "addr:street":"E Washington St",
    "iso:country":"US",
    "sg:address":"123 E Washington St",
    "sg:city":"Oswego",
    "sg:classifiers":[
        {
            "category":"Insurance",
            "subcategory":"Insurance Agent",
            "type":"Services"
        },
        {
            "category":"Insurance",
            "subcategory":"Hazard Insurance",
            "type":"Services"
        },
        {
            "category":"Insurance",
            "subcategory":"Title Insurance",
            "type":"Services"
        }
    ],
    "sg:phone":"+1 630 551 1784",
    "sg:postcode":"60543",
    "sg:province":"IL",
    "sg:tags":[
        "auto",
        "homeowner"
    ],
    "sg:website":"http://apps.amfam.com/agentlocator/CREYNOLD?sourceid=yp3",
    "wof:name":"American Family Insurance- Christina Reynolds",
    "wof:placetype":"venue"
},
  "geometry": {"coordinates":[-88.349726,41.680487],"type":"Point"}
}