{
  "type": "Feature",
  "properties": {
    "addr:full":"1438 W Belmont Ave Chicago IL 60657",
    "addr:housenumber":"1438",
    "addr:postcode":"60657",
    "addr:street":"W Belmont Ave",
    "iso:country":"US",
    "sg:address":"1438 W Belmont Ave",
    "sg:city":"Chicago",
    "sg:classifiers":[
        {
            "category":"Real Estate",
            "subcategory":"Real Estate Services",
            "type":"Services"
        },
        {
            "category":"Real Estate",
            "subcategory":"Real Estate Operator",
            "type":"Services"
        }
    ],
    "sg:phone":"+1 773 549 5443",
    "sg:postcode":"60657",
    "sg:province":"IL",
    "sg:tags":[
        "apartment",
        "property",
        "management"
    ],
    "sg:website":"www.icmproperties.com",
    "wof:name":"ICM Properties, Inc.",
    "wof:placetype":"venue"
},
  "geometry": {"coordinates":[-87.66535399999999,41.940008],"type":"Point"}
}