{
  "type": "Feature",
  "properties": {
    "addr:full":"1101 W Taylor St Chicago IL 60607",
    "addr:housenumber":"1101",
    "addr:postcode":"60607",
    "addr:street":"W Taylor St",
    "iso:country":"US",
    "sg:address":"1101 W Taylor St",
    "sg:city":"Chicago",
    "sg:classifiers":[
        {
            "category":"Education",
            "subcategory":"Library",
            "type":"Public Place"
        }
    ],
    "sg:phone":"+1 312 746 5656",
    "sg:postcode":"60607",
    "sg:province":"IL",
    "sg:website":"www.chipublib.org/branch/details...",
    "wof:name":"Chicago Public Library - Roosevelt Branch",
    "wof:placetype":"venue"
},
  "geometry": {"coordinates":[-87.654437,41.869226],"type":"Point"}
}