{
  "type": "Feature",
  "properties": {
    "iso:country":"US",
    "sg:address":"5808 66th Pl",
    "sg:city":"Kenosha",
    "sg:classifiers":[
        {
            "category":"Retail",
            "subcategory":"Portrait Studio",
            "type":"Services"
        },
        {
            "category":"Retail",
            "subcategory":"Photofinishing",
            "type":"Services"
        }
    ],
    "sg:phone":"+1 262 652 6462",
    "sg:postcode":"53142",
    "sg:province":"IL",
    "sg:tags":[
        "laboratory",
        "photographer"
    ],
    "wof:name":"Memories Forever Photograph",
    "wof:placetype":"venue"
},
  "geometry": {"coordinates":[-87.87649500000001,42.574636],"type":"Point"}
}