{
  "type": "Feature",
  "properties": {
    "addr:full":"800 E Roosevelt Rd Glen Ellyn IL 60137",
    "addr:housenumber":"800",
    "addr:postcode":"60137",
    "addr:street":"E Roosevelt Rd",
    "iso:country":"US",
    "sg:address":"800 E Roosevelt Rd",
    "sg:city":"Glen Ellyn",
    "sg:classifiers":[
        {
            "category":"Banks & Credit Unions",
            "subcategory":"Bank",
            "type":"Services"
        }
    ],
    "sg:phone":"+1 630 469 5596",
    "sg:postcode":"60137",
    "sg:province":"IL",
    "sg:tags":[
        "loan",
        "mortgage",
        "real estate"
    ],
    "wof:name":"First Centennial Mortgage Corp",
    "wof:placetype":"venue"
},
  "geometry": {"coordinates":[-88.052144,41.859466],"type":"Point"}
}