{
  "type": "Feature",
  "properties": {
    "iso:country":"US",
    "sg:address":"667 Maple Trl",
    "sg:city":"Bolingbrook",
    "sg:classifiers":[
        {
            "category":"Professional",
            "subcategory":"Computer Services",
            "type":"Services"
        }
    ],
    "sg:phone":"+1 630 771 0539",
    "sg:postcode":"60490",
    "sg:province":"IL",
    "sg:tags":[
        "consultant",
        "designer"
    ],
    "wof:name":"Computer System Solutions",
    "wof:placetype":"venue"
},
  "geometry": {"coordinates":[-88.132645,41.677958],"type":"Point"}
}