{
  "type": "Feature",
  "properties": {
    "addr:full":"2 E Main St Danville IL 61832",
    "addr:housenumber":"2",
    "addr:postcode":"61832",
    "addr:street":"E Main St",
    "iso:country":"US",
    "sg:address":"2 E Main St",
    "sg:city":"Danville",
    "sg:classifiers":[
        {
            "category":"Banks & Credit Unions",
            "subcategory":"Bank",
            "type":"Services"
        }
    ],
    "sg:phone":"+1 217 443 0503",
    "sg:postcode":"61832",
    "sg:province":"IL",
    "sg:tags":[
        "financing"
    ],
    "wof:name":"Personal Finance Co",
    "wof:placetype":"venue"
},
  "geometry": {"coordinates":[-87.628556,40.12452],"type":"Point"}
}