{
  "type": "Feature",
  "properties": {
    "iso:country":"US",
    "sg:address":"903 W Rock Falls Rd",
    "sg:city":"Rock Falls",
    "sg:classifiers":[
        {
            "category":"Real Estate",
            "subcategory":"Real Estate Agent",
            "type":"Services"
        }
    ],
    "sg:phone":"+1 815 625 7183",
    "sg:postcode":"61071",
    "sg:province":"IL",
    "wof:name":"Leonard Real Estate",
    "wof:placetype":"venue"
},
  "geometry": {"coordinates":[-89.702052,41.769542],"type":"Point"}
}