{
  "type": "Feature",
  "properties": {
    "addr:full":"702 W Cumberland Rd Altamont IL 62411",
    "addr:housenumber":"702",
    "addr:postcode":"62411",
    "addr:street":"W Cumberland Rd",
    "iso:country":"US",
    "sg:address":"702 W Cumberland Rd",
    "sg:city":"Altamont",
    "sg:classifiers":[
        {
            "category":"Social Services",
            "subcategory":"Child Care",
            "type":"Services"
        }
    ],
    "sg:phone":"+1 618 483 6136",
    "sg:postcode":"62411",
    "sg:province":"IL",
    "sg:tags":[
        "skilled",
        "nursing",
        "day",
        "facility"
    ],
    "wof:name":"Lutheran Care Center",
    "wof:placetype":"venue"
},
  "geometry": {"coordinates":[-88.75469099999999,39.053109],"type":"Point"}
}