{
  "type": "Feature",
  "properties": {
    "addr:full":"504 W Jackson St Marion IL 62959",
    "addr:housenumber":"504",
    "addr:postcode":"62959",
    "addr:street":"W Jackson St",
    "iso:country":"US",
    "sg:address":"504 W Jackson St",
    "sg:city":"Marion",
    "sg:classifiers":[
        {
            "category":"Banks & Credit Unions",
            "subcategory":"Investment Brokerage",
            "type":"Services"
        },
        {
            "category":"Insurance",
            "subcategory":"Hazard Insurance",
            "type":"Services"
        }
    ],
    "sg:phone":"+1 618 993 2177",
    "sg:postcode":"62959",
    "sg:province":"IL",
    "sg:tags":[
        "commercial",
        "agent",
        "business",
        "resume"
    ],
    "wof:name":"Glodjo & Associates Insurance Agency",
    "wof:placetype":"venue"
},
  "geometry": {"coordinates":[-88.93102399999999,37.732812],"type":"Point"}
}