{
  "type": "Feature",
  "properties": {
    "iso:country":"US",
    "sg:address":"18677 Dixie Hwy",
    "sg:city":"Homewood",
    "sg:classifiers":[
        {
            "category":"Retail",
            "subcategory":"Animal Services",
            "type":"Services"
        }
    ],
    "sg:phone":"+1 708 798 5102",
    "sg:postcode":"60430",
    "sg:province":"IL",
    "sg:tags":[
        "pet",
        "grooming",
        "washing"
    ],
    "wof:name":"Cathy's Creature Comfort",
    "wof:placetype":"venue"
},
  "geometry": {"coordinates":[-87.665145,41.550268],"type":"Point"}
}