{
  "type": "Feature",
  "properties": {
    "addr:full":"1332 E Empire St Bloomington IL 61701",
    "addr:housenumber":"1332",
    "addr:postcode":"61701",
    "addr:street":"E Empire St",
    "iso:country":"US",
    "sg:address":"1332 E Empire St",
    "sg:city":"Bloomington",
    "sg:classifiers":[
        {
            "category":"Banks & Credit Unions",
            "subcategory":"Bank",
            "type":"Services"
        }
    ],
    "sg:phone":"+1 309 823 3281",
    "sg:postcode":"61701",
    "sg:province":"IL",
    "sg:website":"http://nationalcity.com",
    "wof:name":"PNC",
    "wof:placetype":"venue"
},
  "geometry": {"coordinates":[-88.967381,40.488635],"type":"Point"}
}