{
  "type": "Feature",
  "properties": {
    "iso:country":"US",
    "sg:address":"1811 Washington St",
    "sg:city":"Carlyle",
    "sg:classifiers":[
        {
            "category":"Government",
            "subcategory":"Office",
            "type":"Public Place"
        }
    ],
    "sg:phone":"+1 618 594 5211",
    "sg:postcode":"62231",
    "sg:province":"IL",
    "sg:tags":[
        "village"
    ],
    "wof:name":"Carlyle Street & Alley Dept",
    "wof:placetype":"venue"
},
  "geometry": {"coordinates":[-89.380775,38.609269],"type":"Point"}
}