{
  "type": "Feature",
  "properties": {
    "iso:country":"US",
    "sg:address":"5520 159th St",
    "sg:city":"Oak Forest",
    "sg:classifiers":[
        {
            "category":"Restaurant",
            "type":"Food & Drink"
        }
    ],
    "sg:phone":"+1   ",
    "sg:postcode":"60452",
    "sg:province":"IL",
    "sg:tags":[
        "fast"
    ],
    "wof:name":"Burger King",
    "wof:placetype":"venue"
},
  "geometry": {"coordinates":[-87.754513,41.603006],"type":"Point"}
}