{
  "type": "Feature",
  "properties": {
    "addr:full":"400 Skokie Blvd Northbrook IL 60062",
    "addr:housenumber":"400",
    "addr:postcode":"60062",
    "addr:street":"Skokie Blvd",
    "iso:country":"US",
    "sg:address":"400 Skokie Blvd",
    "sg:city":"Northbrook",
    "sg:classifiers":[
        {
            "category":"Banks & Credit Unions",
            "subcategory":"Bank",
            "type":"Services"
        }
    ],
    "sg:phone":"+1 847 559 1226",
    "sg:postcode":"60062",
    "sg:province":"IL",
    "sg:tags":[
        "state",
        "commercial"
    ],
    "wof:name":"Bank of America",
    "wof:placetype":"venue"
},
  "geometry": {"coordinates":[-87.795126,42.143285],"type":"Point"}
}