{
  "type": "Feature",
  "properties": {
    "addr:full":"207 Amherst Dr Bartlett IL 60103",
    "addr:housenumber":"207",
    "addr:postcode":"60103",
    "addr:street":"Amherst Dr",
    "iso:country":"US",
    "sg:address":"207 Amherst Dr",
    "sg:city":"Bartlett",
    "sg:classifiers":[
        {
            "category":"Government",
            "subcategory":"Fire Station",
            "type":"Public Place"
        }
    ],
    "sg:phone":"+1 630 830 6082",
    "sg:postcode":"60103",
    "sg:province":"IL",
    "sg:tags":[
        "consultant",
        "protection"
    ],
    "wof:name":"Titan Fire Protection & Inspec",
    "wof:placetype":"venue"
},
  "geometry": {"coordinates":[-88.177207,41.983893],"type":"Point"}
}