{
  "type": "Feature",
  "properties": {
    "addr:full":"148 Leigh Ave Anna IL 62906",
    "addr:housenumber":"148",
    "addr:postcode":"62906",
    "addr:street":"Leigh Ave",
    "iso:country":"US",
    "sg:address":"148 Leigh Ave",
    "sg:city":"Anna",
    "sg:classifiers":[
        {
            "category":"Food & Beverages",
            "subcategory":"Groceries & Convenience Stores",
            "type":"Retail Goods"
        }
    ],
    "sg:phone":"+1   ",
    "sg:postcode":"62906",
    "sg:province":"IL",
    "wof:name":"Eastside Express",
    "wof:placetype":"venue"
},
  "geometry": {"coordinates":[-89.223224,37.463141],"type":"Point"}
}