{
  "type": "Feature",
  "properties": {
    "iso:country":"US",
    "sg:address":"227 James St",
    "sg:city":"Bensenville",
    "sg:classifiers":[
        {
            "category":"Utilities",
            "subcategory":"Water",
            "type":"Services"
        },
        {
            "category":"Building & Trades",
            "subcategory":"Cleaning & Sanitation",
            "type":"Services"
        }
    ],
    "sg:phone":"+1 630 477 9120",
    "sg:postcode":"60106",
    "sg:province":"IL",
    "sg:tags":[
        "remediation",
        "mold",
        "damage",
        "emergency"
    ],
    "sg:website":"http://www.PuroCleanPros.com",
    "wof:name":"PuroClean",
    "wof:placetype":"venue"
},
  "geometry": {"coordinates":[-87.94913099999999,41.932826],"type":"Point"}
}