{
  "type": "Feature",
  "properties": {
    "iso:country":"US",
    "sg:address":"88 Holly Dr",
    "sg:city":"Crystal Lake",
    "sg:classifiers":[
        {
            "category":"Retail",
            "subcategory":"Auto Repair",
            "type":"Services"
        }
    ],
    "sg:phone":"+1 815 479 9331",
    "sg:postcode":"60014",
    "sg:province":"IL",
    "sg:tags":[
        "truck",
        "general"
    ],
    "wof:name":"Midwest Mobile Truck Svc Inc",
    "wof:placetype":"venue"
},
  "geometry": {"coordinates":[-88.36900199999999,42.238481],"type":"Point"}
}