{
  "type": "Feature",
  "properties": {
    "iso:country":"US",
    "sg:address":"2001 Landmeier Rd",
    "sg:city":"Elk Grove Vlg",
    "sg:classifiers":[
        {
            "category":"Manufacturing",
            "subcategory":"Electronics",
            "type":"Manufacturing & Wholesale Goods"
        }
    ],
    "sg:phone":"+1 847 290 9800",
    "sg:postcode":"60007",
    "sg:province":"IL",
    "sg:tags":[
        "printed",
        "circuit",
        "etched"
    ],
    "sg:website":"www.amitroncorp.com",
    "wof:name":"Amitron Corp",
    "wof:placetype":"venue"
},
  "geometry": {"coordinates":[-87.952078,42.010176],"type":"Point"}
}