{
  "type": "Feature",
  "properties": {
    "iso:country":"US",
    "sg:address":"1200 W State St",
    "sg:city":"Rockford",
    "sg:classifiers":[
        {
            "category":"Health Services",
            "subcategory":"Clinic",
            "type":"Services"
        }
    ],
    "sg:phone":"+1 815 964 0450",
    "sg:postcode":"61102",
    "sg:province":"IL",
    "wof:name":"Black Health Care Initiat",
    "wof:placetype":"venue"
},
  "geometry": {"coordinates":[-89.106515,42.27559],"type":"Point"}
}