{
  "type": "Feature",
  "properties": {
    "iso:country":"US",
    "sg:address":"1440 Lourdes Rd",
    "sg:city":"Metamora",
    "sg:classifiers":[
        {
            "category":"Building & Trades",
            "subcategory":"Construction",
            "type":"Services"
        }
    ],
    "sg:phone":"+1 309 383 2486",
    "sg:postcode":"61548",
    "sg:province":"IL",
    "sg:tags":[
        "industrial",
        "contractors-commercial"
    ],
    "wof:name":"King & Associates",
    "wof:placetype":"venue"
},
  "geometry": {"coordinates":[-89.46669,40.823013],"type":"Point"}
}