{
  "type": "Feature",
  "properties": {
    "addr:full":"931 Green Bay Rd Winnetka IL 60093",
    "addr:housenumber":"931",
    "addr:postcode":"60093",
    "addr:street":"Green Bay Rd",
    "iso:country":"US",
    "sg:address":"931 Green Bay Rd",
    "sg:city":"Winnetka",
    "sg:classifiers":[
        {
            "category":"Shopping",
            "subcategory":"Clothing, Apparel, & Fashions",
            "type":"Retail Goods"
        },
        {
            "category":"Shopping",
            "subcategory":"Shoes",
            "type":"Retail Goods"
        }
    ],
    "sg:phone":"+1 847 446 2005",
    "sg:postcode":"60093",
    "sg:province":"IL",
    "sg:tags":[
        "clothing",
        "sportswear",
        "store"
    ],
    "sg:website":"http://www.discountdance.com",
    "wof:name":"Body & Sole",
    "wof:placetype":"venue"
},
  "geometry": {"coordinates":[-87.74364,42.116716],"type":"Point"}
}