{
  "type": "Feature",
  "properties": {
    "iso:country":"US",
    "sg:address":"8745 W Higgins Rd",
    "sg:city":"Chicago",
    "sg:classifiers":[
        {
            "category":"Personal",
            "subcategory":"Beauty Salon",
            "type":"Services"
        }
    ],
    "sg:phone":"+1 847 384 5000",
    "sg:postcode":"60631",
    "sg:province":"IL",
    "sg:website":"http://www.cablecomcast.com",
    "wof:name":"Authentify Inc",
    "wof:placetype":"venue"
},
  "geometry": {"coordinates":[-87.845073,41.987638],"type":"Point"}
}