{
  "type": "Feature",
  "properties": {
    "addr:full":"901 N Gilbert St Danville IL 61832",
    "addr:housenumber":"901",
    "addr:postcode":"61832",
    "addr:street":"N Gilbert St",
    "iso:country":"US",
    "sg:address":"901 N Gilbert St",
    "sg:city":"Danville",
    "sg:classifiers":[
        {
            "category":"Banks & Credit Unions",
            "subcategory":"Bank",
            "type":"Services"
        }
    ],
    "sg:phone":"+1 217 442 0362",
    "sg:postcode":"61832",
    "sg:province":"IL",
    "wof:name":"First National Bank",
    "wof:placetype":"venue"
},
  "geometry": {"coordinates":[-87.63553,40.13912],"type":"Point"}
}