{
  "type": "Feature",
  "properties": {
    "iso:country":"US",
    "sg:address":"1200 S 14th St",
    "sg:city":"Herrin",
    "sg:classifiers":[
        {
            "category":"Communications",
            "subcategory":"Television Station",
            "type":"Services"
        }
    ],
    "sg:phone":"+1 618 942 2567",
    "sg:postcode":"62948",
    "sg:province":"IL",
    "sg:tags":[
        "satellite",
        "antenna",
        "cable",
        "tv",
        "system",
        "equipment"
    ],
    "wof:name":"Satelite Jacks",
    "wof:placetype":"venue"
},
  "geometry": {"coordinates":[-89.026703,37.792358],"type":"Point"}
}