{
  "type": "Feature",
  "properties": {
    "iso:country":"US",
    "sg:address":"820 Waterview Cir",
    "sg:city":"Vernon Hills",
    "sg:classifiers":[
        {
            "category":"Shopping",
            "subcategory":"Florist",
            "type":"Retail Goods"
        }
    ],
    "sg:phone":"+1 847 549 8587",
    "sg:postcode":"60061",
    "sg:province":"IL",
    "wof:name":"Flowers For All Seasons",
    "wof:placetype":"venue"
},
  "geometry": {"coordinates":[-87.98507600000001,42.22116],"type":"Point"}
}