{
  "type": "Feature",
  "properties": {
    "iso:country":"US",
    "sg:address":"819 N Ashland Ave 1st Fl",
    "sg:city":"Chicago",
    "sg:classifiers":[
        {
            "category":"Shopping",
            "subcategory":"Optical Goods",
            "type":"Retail Goods"
        },
        {
            "category":"Health Services",
            "subcategory":"Optometrist",
            "type":"Services"
        },
        {
            "category":"Shopping",
            "subcategory":"Optician",
            "type":"Retail Goods"
        }
    ],
    "sg:phone":"+1 312 942 0407",
    "sg:postcode":"60622",
    "sg:province":"IL",
    "sg:tags":[
        "lens",
        "eyeglass",
        "contact",
        "eyewear"
    ],
    "sg:website":"www.pearlevision.com",
    "wof:name":"Pearl Vision",
    "wof:placetype":"venue"
},
  "geometry": {"coordinates":[-87.66691299999999,41.896714],"type":"Point"}
}