{
  "type": "Feature",
  "properties": {
    "iso:country":"US",
    "sg:address":"8217 9th St W",
    "sg:city":"Rock Island",
    "sg:classifiers":[
        {
            "category":"Recreation",
            "type":"Entertainment"
        }
    ],
    "sg:phone":"+1 309 787 0107",
    "sg:postcode":"61201",
    "sg:province":"IL",
    "wof:name":"P I Ball Balloons",
    "wof:placetype":"venue"
},
  "geometry": {"coordinates":[-90.579833,41.437337],"type":"Point"}
}