{
  "type": "Feature",
  "properties": {
    "iso:country":"US",
    "sg:address":"21200 Co Rd 1",
    "sg:city":"Omaha",
    "sg:classifiers":[
        {
            "category":"Wholesale",
            "subcategory":"Machinery & Supplies",
            "type":"Manufacturing & Wholesale Goods"
        }
    ],
    "sg:phone":"+1 618 962 3479",
    "sg:postcode":"62871",
    "sg:province":"IL",
    "sg:tags":[
        "aircraft",
        "avionics"
    ],
    "wof:name":"Doyle Fabrications",
    "wof:placetype":"venue"
},
  "geometry": {"coordinates":[-88.342074,37.885608],"type":"Point"}
}