{
  "type": "Feature",
  "properties": {
    "iso:country":"US",
    "sg:address":"387 Plum St",
    "sg:city":"Aurora",
    "sg:classifiers":[
        {
            "category":"Building & Trades",
            "subcategory":"Cleaning & Sanitation",
            "type":"Services"
        }
    ],
    "sg:phone":"+1 630 896 4972",
    "sg:postcode":"60506",
    "sg:province":"IL",
    "sg:tags":[
        "janitor"
    ],
    "wof:name":"S & L Janitorial Svc",
    "wof:placetype":"venue"
},
  "geometry": {"coordinates":[-88.321261,41.767075],"type":"Point"}
}