{
  "type": "Feature",
  "properties": {
    "iso:country":"US",
    "sg:address":"1330 N Illinois Ave",
    "sg:city":"Carbondale",
    "sg:classifiers":[
        {
            "category":"Building & Trades",
            "subcategory":"Construction",
            "type":"Services"
        },
        {
            "category":"Home & Garden",
            "subcategory":"Carpets & Floor Coverings",
            "type":"Retail Goods"
        }
    ],
    "sg:phone":"+1 618 457 5255",
    "sg:postcode":"62901",
    "sg:province":"IL",
    "sg:tags":[
        "material",
        "contractor"
    ],
    "wof:name":"Modern Tile & Carpet Inc",
    "wof:placetype":"venue"
},
  "geometry": {"coordinates":[-89.218834,37.740737],"type":"Point"}
}