{
  "type": "Feature",
  "properties": {
    "iso:country":"US",
    "sg:address":"639 N Entrance Ave",
    "sg:city":"Kankakee",
    "sg:classifiers":[
        {
            "category":"Home & Garden",
            "subcategory":"Building Materials",
            "type":"Retail Goods"
        }
    ],
    "sg:phone":"+1 815 935 5396",
    "sg:postcode":"60901",
    "sg:province":"IL",
    "sg:tags":[
        "windows"
    ],
    "wof:name":"Glazelock Shims",
    "wof:placetype":"venue"
},
  "geometry": {"coordinates":[-87.869054,41.128618],"type":"Point"}
}