{
  "type": "Feature",
  "properties": {
    "iso:country":"US",
    "sg:address":"4797 Bluestem Rd",
    "sg:city":"Roscoe",
    "sg:classifiers":[
        {
            "category":"Restaurant",
            "type":"Food & Drink"
        }
    ],
    "sg:menulink":"http://www.allmenus.com/il/roscoe/73805-pizza-ranch/menu/",
    "sg:phone":"+1 815 623 3800",
    "sg:postcode":"61073",
    "sg:province":"IL",
    "sg:tags":[
        "american",
        "pizza"
    ],
    "wof:name":"Pizza Ranch",
    "wof:placetype":"venue"
},
  "geometry": {"coordinates":[-89.023218,42.433653],"type":"Point"}
}