{
  "type": "Feature",
  "properties": {
    "iso:country":"US",
    "sg:address":"305 S 2nd St",
    "sg:city":"Greenville",
    "sg:classifiers":[
        {
            "category":"Professional",
            "subcategory":"Advertising",
            "type":"Services"
        }
    ],
    "sg:phone":"+1 618 664 3144",
    "sg:postcode":"62246",
    "sg:province":"IL",
    "sg:website":"www.advocategreenville.com",
    "wof:name":"Advocate",
    "wof:placetype":"venue"
},
  "geometry": {"coordinates":[-89.412541,38.890528],"type":"Point"}
}