{
  "type": "Feature",
  "properties": {
    "addr:full":"6000 S Loomis Blvd Chicago IL 60636",
    "addr:housenumber":"6000",
    "addr:postcode":"60636",
    "addr:street":"S Loomis Blvd",
    "iso:country":"US",
    "sg:address":"6000 S Loomis Blvd",
    "sg:city":"Chicago",
    "sg:classifiers":[
        {
            "category":"Food & Beverages",
            "subcategory":"Groceries & Convenience Stores",
            "type":"Retail Goods"
        }
    ],
    "sg:phone":"+1 773 434 2920",
    "sg:postcode":"60636",
    "sg:province":"IL",
    "wof:name":"Loomis Groceries",
    "wof:placetype":"venue"
},
  "geometry": {"coordinates":[-87.659694,41.785005],"type":"Point"}
}