{
  "type": "Feature",
  "properties": {
    "iso:country":"US",
    "sg:address":"1360 N Lake Shore Dr # 514",
    "sg:city":"Chicago",
    "sg:classifiers":[
        {
            "category":"Health Services",
            "subcategory":"Clinic",
            "type":"Services"
        }
    ],
    "sg:phone":"+1 312 515 0183",
    "sg:postcode":"60610",
    "sg:province":"IL",
    "sg:tags":[
        "therapist",
        "biofeedback"
    ],
    "wof:name":"Eli Alson, Phd, P.C.",
    "wof:placetype":"venue"
},
  "geometry": {"coordinates":[-87.62561599999999,41.907274],"type":"Point"}
}