{
  "type": "Feature",
  "properties": {
    "iso:country":"US",
    "sg:address":"1400 Old Indian Town Rd",
    "sg:city":"Henry",
    "sg:classifiers":[
        {
            "category":"Organizations",
            "subcategory":"Religious Organization",
            "type":"Services"
        }
    ],
    "sg:phone":"+1 309 364 2138",
    "sg:postcode":"61537",
    "sg:province":"IL",
    "sg:tags":[
        "church"
    ],
    "wof:name":"New Life Community Church",
    "wof:placetype":"venue"
},
  "geometry": {"coordinates":[-89.364851,41.122673],"type":"Point"}
}