{
  "type": "Feature",
  "properties": {
    "addr:full":"70 W Madison St Chicago IL 60602",
    "addr:housenumber":"70",
    "addr:postcode":"60602",
    "addr:street":"W Madison St",
    "iso:country":"US",
    "sg:address":"70 W Madison St",
    "sg:city":"Chicago",
    "sg:classifiers":[
        {
            "category":"Banks & Credit Unions",
            "subcategory":"Investment Brokerage",
            "type":"Services"
        },
        {
            "category":"Banks & Credit Unions",
            "subcategory":"Financial Services",
            "type":"Services"
        }
    ],
    "sg:phone":"+1 312 346 2700",
    "sg:postcode":"60602",
    "sg:province":"IL",
    "sg:tags":[
        "security",
        "management"
    ],
    "wof:name":"Korshak Kracoff Koing & Sugano",
    "wof:placetype":"venue"
},
  "geometry": {"coordinates":[-87.630028,41.881992],"type":"Point"}
}