{
  "type": "Feature",
  "properties": {
    "iso:country":"US",
    "sg:address":"106 W Main St",
    "sg:city":"Rockton",
    "sg:classifiers":[
        {
            "category":"Shopping",
            "subcategory":"Used Merchandise",
            "type":"Retail Goods"
        },
        {
            "category":"Shopping",
            "subcategory":"Books",
            "type":"Retail Goods"
        }
    ],
    "sg:phone":"+1 815 624 6366",
    "sg:postcode":"61072",
    "sg:province":"IL",
    "sg:tags":[
        "rare",
        "dealer"
    ],
    "wof:name":"Books On Main",
    "wof:placetype":"venue"
},
  "geometry": {"coordinates":[-89.072516,42.452433],"type":"Point"}
}