{
  "type": "Feature",
  "properties": {
    "addr:full":"7481 S Sayre Ave Ste A Chicago IL 60638",
    "addr:housenumber":"7481",
    "addr:postcode":"60638",
    "addr:street":"S Sayre Ave Ste A",
    "iso:country":"US",
    "sg:address":"7481 S Sayre Ave Ste A",
    "sg:city":"Chicago",
    "sg:classifiers":[
        {
            "category":"Manufacturing",
            "subcategory":"Electronics",
            "type":"Manufacturing & Wholesale Goods"
        },
        {
            "category":"Building & Trades",
            "subcategory":"Electrical",
            "type":"Services"
        }
    ],
    "sg:phone":"+1 708 496 3080",
    "sg:postcode":"60638",
    "sg:province":"IL",
    "sg:tags":[
        "control",
        "system",
        "controls",
        "regulator",
        "regulators-control",
        "panel"
    ],
    "wof:name":"Panatrol Corporation",
    "wof:placetype":"venue"
},
  "geometry": {"coordinates":[-87.79483999999999,41.755395],"type":"Point"}
}