{
  "type": "Feature",
  "properties": {
    "iso:country":"US",
    "sg:address":"9118 S 54th Ave",
    "sg:city":"Oak Lawn",
    "sg:classifiers":[
        {
            "category":"Insurance",
            "subcategory":"Insurance Agent",
            "type":"Services"
        }
    ],
    "sg:phone":"+1 708 422 5800",
    "sg:postcode":"60453",
    "sg:province":"IL",
    "sg:tags":[
        "personal"
    ],
    "wof:name":"Stanton & Associates",
    "wof:placetype":"venue"
},
  "geometry": {"coordinates":[-87.755705,41.725619],"type":"Point"}
}