{
  "type": "Feature",
  "properties": {
    "iso:country":"US",
    "sg:address":"21251 N Middleton Dr",
    "sg:city":"Kildeer",
    "sg:classifiers":[
        {
            "category":"Banks & Credit Unions",
            "subcategory":"Investment Brokerage",
            "type":"Services"
        }
    ],
    "sg:phone":"+1 847 438 7383",
    "sg:postcode":"60047",
    "sg:province":"IL",
    "sg:tags":[
        "transfer",
        "security",
        "stock",
        "agent",
        "bond"
    ],
    "wof:name":"Stephen R Cournoyer Profi",
    "wof:placetype":"venue"
},
  "geometry": {"coordinates":[-88.039879,42.17273],"type":"Point"}
}