{
  "type": "Feature",
  "properties": {
    "iso:country":"US",
    "sg:address":"500 John Deere Rd",
    "sg:city":"Moline",
    "sg:classifiers":[
        {
            "category":"Health Services",
            "subcategory":"Doctor",
            "type":"Services"
        }
    ],
    "sg:phone":"+1 309 779 5090",
    "sg:postcode":"61265",
    "sg:province":"IL",
    "sg:tags":[
        "medical"
    ],
    "wof:name":"Antonio P Vigliotti MD",
    "wof:placetype":"venue"
},
  "geometry": {"coordinates":[-90.418118,41.472447],"type":"Point"}
}