{
  "type": "Feature",
  "properties": {
    "addr:full":"112 Frank Scott Pkwy E Belleville IL 62226",
    "addr:housenumber":"112",
    "addr:postcode":"62226",
    "addr:street":"Frank Scott Pkwy E",
    "iso:country":"US",
    "sg:address":"112 Frank Scott Pkwy E",
    "sg:city":"Belleville",
    "sg:classifiers":[
        {
            "category":"Building & Trades",
            "subcategory":"Construction",
            "type":"Services"
        }
    ],
    "sg:phone":"+1 618 235 0539",
    "sg:postcode":"62226",
    "sg:province":"IL",
    "sg:tags":[
        "contractor"
    ],
    "wof:name":"James Fournie",
    "wof:placetype":"venue"
},
  "geometry": {"coordinates":[-89.979545,38.570918],"type":"Point"}
}