{
  "type": "Feature",
  "properties": {
    "iso:country":"US",
    "sg:address":"754 W Annoreno Dr",
    "sg:city":"Addison",
    "sg:phone":"+1 630 458 1200",
    "sg:postcode":"60101",
    "sg:province":"IL",
    "sg:website":"http://Luckymotors.com",
    "wof:name":"Lucky Motors Com",
    "wof:placetype":"venue"
},
  "geometry": {"coordinates":[-88.006314,41.916608],"type":"Point"}
}