{
  "type": "Feature",
  "properties": {
    "addr:full":"1828 N Lincoln Park W Chicago IL 60614",
    "addr:housenumber":"1828",
    "addr:postcode":"60614",
    "addr:street":"N Lincoln Park W",
    "iso:country":"US",
    "sg:address":"1828 N Lincoln Park W",
    "sg:city":"Chicago",
    "sg:classifiers":[
        {
            "category":"Health Services",
            "subcategory":"Clinic",
            "type":"Services"
        }
    ],
    "sg:phone":"+1 312 867 3880",
    "sg:postcode":"60614",
    "sg:province":"IL",
    "sg:tags":[
        "welfare"
    ],
    "wof:name":"Hyer Medical",
    "wof:placetype":"venue"
},
  "geometry": {"coordinates":[-87.635246,41.915791],"type":"Point"}
}