{
  "type": "Feature",
  "properties": {
    "iso:country":"US",
    "sg:address":"489 Spring Rd",
    "sg:city":"Elmhurst",
    "sg:classifiers":[
        {
            "category":"Professional",
            "subcategory":"Management & Consulting",
            "type":"Services"
        }
    ],
    "sg:phone":"+1 630 516 0606",
    "sg:postcode":"60126",
    "sg:province":"IL",
    "sg:tags":[
        "public",
        "relations"
    ],
    "wof:name":"Walsh Communications",
    "wof:placetype":"venue"
},
  "geometry": {"coordinates":[-87.949595,41.886041],"type":"Point"}
}