{
  "type": "Feature",
  "properties": {
    "addr:full":"3043 Rose St Franklin Park IL 60131",
    "addr:housenumber":"3043",
    "addr:postcode":"60131",
    "addr:street":"Rose St",
    "iso:country":"US",
    "sg:address":"3043 Rose St",
    "sg:city":"Franklin Park",
    "sg:classifiers":[
        {
            "category":"Professional",
            "subcategory":"Advertising",
            "type":"Services"
        }
    ],
    "sg:phone":"+1 847 451 2246",
    "sg:postcode":"60131",
    "sg:province":"IL",
    "sg:tags":[
        "agency"
    ],
    "wof:name":"Phil Sasso Mktg Communications",
    "wof:placetype":"venue"
},
  "geometry": {"coordinates":[-87.86535600000001,41.934583],"type":"Point"}
}