{
  "type": "Feature",
  "properties": {
    "iso:country":"US",
    "sg:address":"358 W Ontario St",
    "sg:city":"Chicago",
    "sg:classifiers":[
        {
            "category":"Restaurant",
            "type":"Food & Drink"
        }
    ],
    "sg:menulink":"http://www.allmenus.com/il/chicago/23188-zocalo/menu/",
    "sg:phone":"+1 312 302 9977",
    "sg:postcode":"60610",
    "sg:province":"IL",
    "sg:tags":[
        "mexican"
    ],
    "wof:name":"Zocalo",
    "wof:placetype":"venue"
},
  "geometry": {"coordinates":[-87.63772299999999,41.893134],"type":"Point"}
}