{
  "type": "Feature",
  "properties": {
    "addr:full":"4786 N Milwaukee Avenue Chicago IL 60630",
    "addr:housenumber":"4786",
    "addr:postcode":"60630",
    "addr:street":"N Milwaukee Avenue",
    "iso:country":"US",
    "sg:address":"4786 N Milwaukee Avenue",
    "sg:city":"Chicago",
    "sg:classifiers":[
        {
            "category":"Banks & Credit Unions",
            "subcategory":"Bank",
            "type":"Services"
        },
        {
            "category":"Banks & Credit Unions",
            "subcategory":"Financial Services",
            "type":"Services"
        }
    ],
    "sg:phone":"+1 773 283 4100",
    "sg:postcode":"60630",
    "sg:province":"IL",
    "sg:tags":[
        "broker",
        "mortgage"
    ],
    "wof:name":"Hoyne Safe Deposit Company",
    "wof:placetype":"venue"
},
  "geometry": {"coordinates":[-87.76043799999999,41.967725],"type":"Point"}
}