{
  "type": "Feature",
  "properties": {
    "iso:country":"US",
    "sg:address":"205 W North St",
    "sg:city":"Galesburg",
    "sg:classifiers":[
        {
            "category":"Retail",
            "subcategory":"Laundry & Dry Cleaning",
            "type":"Services"
        }
    ],
    "sg:phone":"+1 309 342 7967",
    "sg:postcode":"61401",
    "sg:province":"IL",
    "sg:tags":[
        "cleaner",
        "rug",
        "carpet"
    ],
    "wof:name":"Rainbow International Carpet Cleaning & Dry Cleaning",
    "wof:placetype":"venue"
},
  "geometry": {"coordinates":[-90.374222,40.951092],"type":"Point"}
}