{
  "type": "Feature",
  "properties": {
    "addr:full":"120 N Green St Chicago IL 60607",
    "addr:housenumber":"120",
    "addr:postcode":"60607",
    "addr:street":"N Green St",
    "iso:country":"US",
    "sg:address":"120 N Green St",
    "sg:city":"Chicago",
    "sg:classifiers":[
        {
            "category":"Professional",
            "subcategory":"Employment Agencies",
            "type":"Services"
        },
        {
            "category":"Organizations",
            "subcategory":"Professional Association",
            "type":"Services"
        }
    ],
    "sg:phone":"+1 312 455 1467",
    "sg:postcode":"60607",
    "sg:province":"IL",
    "sg:tags":[
        "modeling",
        "bureau",
        "entertainment"
    ],
    "wof:name":"Hop Model & Talent Agency",
    "wof:placetype":"venue"
},
  "geometry": {"coordinates":[-87.648556,41.883711],"type":"Point"}
}