{
  "type": "Feature",
  "properties": {
    "iso:country":"US",
    "sg:address":"104 W 1st Ave",
    "sg:city":"Coal Valley",
    "sg:classifiers":[
        {
            "category":"Retail",
            "subcategory":"Veterinary Services",
            "type":"Services"
        }
    ],
    "sg:phone":"+1 309 799 7206",
    "sg:postcode":"61240",
    "sg:province":"IL",
    "sg:tags":[
        "veterinarian"
    ],
    "wof:name":"Valley Veterinary Serv",
    "wof:placetype":"venue"
},
  "geometry": {"coordinates":[-90.461197,41.452702],"type":"Point"}
}