{
  "type": "Feature",
  "properties": {
    "addr:full":"2102 Margaret Dr Loves Park IL 61111",
    "addr:housenumber":"2102",
    "addr:postcode":"61111",
    "addr:street":"Margaret Dr",
    "iso:country":"US",
    "sg:address":"2102 Margaret Dr",
    "sg:city":"Loves Park",
    "sg:classifiers":[
        {
            "category":"Manufacturing",
            "subcategory":"Tools & Machinery",
            "type":"Manufacturing & Wholesale Goods"
        }
    ],
    "sg:phone":"+1 815 654 0035",
    "sg:postcode":"61111",
    "sg:province":"IL",
    "sg:tags":[
        "machine",
        "shop"
    ],
    "wof:name":"Tool Form Inc",
    "wof:placetype":"venue"
},
  "geometry": {"coordinates":[-89.025657,42.328193],"type":"Point"}
}