{
  "type": "Feature",
  "properties": {
    "iso:country":"US",
    "sg:address":"207 W Galena Blvd",
    "sg:city":"Aurora",
    "sg:classifiers":[
        {
            "category":"Professional",
            "subcategory":"Employment Agencies",
            "type":"Services"
        }
    ],
    "sg:phone":"+1 630 801 4800",
    "sg:postcode":"60506",
    "sg:province":"IL",
    "sg:tags":[
        "opportunity"
    ],
    "wof:name":"Staff Force",
    "wof:placetype":"venue"
},
  "geometry": {"coordinates":[-88.320084,41.760566],"type":"Point"}
}