{
  "type": "Feature",
  "properties": {
    "iso:country":"US",
    "sg:address":"1030 Busse Hwy",
    "sg:city":"Park Ridge",
    "sg:classifiers":[
        {
            "category":"Manufacturing",
            "subcategory":"Printing",
            "type":"Manufacturing & Wholesale Goods"
        }
    ],
    "sg:phone":"+1 847 696 1501",
    "sg:postcode":"60068",
    "sg:province":"IL",
    "sg:tags":[
        "album",
        "scrapbook",
        "diary",
        "mfg"
    ],
    "wof:name":"Bound + D/Termined Inc",
    "wof:placetype":"venue"
},
  "geometry": {"coordinates":[-87.857161,42.025228],"type":"Point"}
}