{
  "type": "Feature",
  "properties": {
    "addr:full":"2942 W North Ave Chicago IL 60647",
    "addr:housenumber":"2942",
    "addr:postcode":"60647",
    "addr:street":"W North Ave",
    "iso:country":"US",
    "sg:address":"2942 W North Ave",
    "sg:city":"Chicago",
    "sg:classifiers":[
        {
            "category":"Manufacturing",
            "subcategory":"Chemicals & Compounds",
            "type":"Manufacturing & Wholesale Goods"
        },
        {
            "category":"Home & Garden",
            "subcategory":"Building Materials",
            "type":"Retail Goods"
        }
    ],
    "sg:phone":"+1 773 278 7177",
    "sg:postcode":"60647",
    "sg:province":"IL",
    "sg:tags":[
        "enamel",
        "mfg",
        "wallpaper",
        "coating",
        "paint",
        "wallcoverings"
    ],
    "sg:website":"http://www.carbit.com",
    "wof:name":"The Carbit Paint Company",
    "wof:placetype":"venue"
},
  "geometry": {"coordinates":[-87.700508,41.910207],"type":"Point"}
}