{
  "type": "Feature",
  "properties": {
    "iso:country":"US",
    "sg:address":"4860 Rocky Branch Rd",
    "sg:city":"Bethalto",
    "sg:classifiers":[
        {
            "category":"Social Services",
            "subcategory":"Child Care",
            "type":"Services"
        }
    ],
    "sg:phone":"+1 618 377 4451",
    "sg:postcode":"62010",
    "sg:province":"IL",
    "wof:name":"Kathy Crews",
    "wof:placetype":"venue"
},
  "geometry": {"coordinates":[-90.033713,38.95266],"type":"Point"}
}