{
  "type": "Feature",
  "properties": {
    "addr:full":"17767 N Clear Ln Mount Vernon IL 62864",
    "addr:housenumber":"17767",
    "addr:postcode":"62864",
    "addr:street":"N Clear Ln",
    "iso:country":"US",
    "sg:address":"17767 N Clear Ln",
    "sg:city":"Mount Vernon",
    "sg:classifiers":[
        {
            "category":"Personal",
            "type":"Services"
        }
    ],
    "sg:phone":"+1 618 755 9733",
    "sg:postcode":"62864",
    "sg:province":"IL",
    "wof:name":"Bahama Mamas Tanning Salon",
    "wof:placetype":"venue"
},
  "geometry": {"coordinates":[-88.80895099999999,38.381014],"type":"Point"}
}