{
  "type": "Feature",
  "properties": {
    "iso:country":"US",
    "sg:address":"1104 Elmwood Rd",
    "sg:city":"Bloomington",
    "sg:classifiers":[
        {
            "category":"Professional",
            "subcategory":"Business Services",
            "type":"Services"
        }
    ],
    "sg:phone":"+1 309 827 7035",
    "sg:postcode":"61701",
    "sg:province":"IL",
    "sg:tags":[
        "consultant",
        "coach"
    ],
    "wof:name":"Acorn Tree Consulting",
    "wof:placetype":"venue"
},
  "geometry": {"coordinates":[-88.977625,40.482843],"type":"Point"}
}