{
  "type": "Feature",
  "properties": {
    "iso:country":"US",
    "sg:address":"21920 W Grass Lake Rd",
    "sg:city":"Antioch",
    "sg:classifiers":[
        {
            "category":"Building & Trades",
            "subcategory":"Construction",
            "type":"Services"
        }
    ],
    "sg:phone":"+1 847 838 0733",
    "sg:postcode":"60002",
    "sg:province":"IL",
    "sg:tags":[
        "general",
        "contractor"
    ],
    "wof:name":"Seater Construction",
    "wof:placetype":"venue"
},
  "geometry": {"coordinates":[-88.06070200000001,42.441919],"type":"Point"}
}