{
  "type": "Feature",
  "properties": {
    "iso:country":"US",
    "sg:address":"2057 W North Ave",
    "sg:city":"Chicago",
    "sg:classifiers":[
        {
            "category":"Restaurant",
            "type":"Food & Drink"
        },
        {
            "category":"Food & Beverages",
            "subcategory":"Groceries & Convenience Stores",
            "type":"Retail Goods"
        }
    ],
    "sg:menulink":"http://www.allmenus.com/il/chicago/200650-sultans-market/menu/",
    "sg:phone":"+1 773 235 3072",
    "sg:postcode":"60647",
    "sg:province":"IL",
    "sg:tags":[
        "mediterranean"
    ],
    "wof:name":"Sultan's Market",
    "wof:placetype":"venue"
},
  "geometry": {"coordinates":[-87.679087,41.910446],"type":"Point"}
}