{
  "type": "Feature",
  "properties": {
    "addr:full":"25520 S Governors Hwy Monee IL 60449",
    "addr:housenumber":"25520",
    "addr:postcode":"60449",
    "addr:street":"S Governors Hwy",
    "iso:country":"US",
    "sg:address":"25520 S Governors Hwy",
    "sg:city":"Monee",
    "sg:classifiers":[
        {
            "category":"Bars & Pubs",
            "type":"Food & Drink"
        }
    ],
    "sg:phone":"+1   ",
    "sg:postcode":"60449",
    "sg:province":"IL",
    "wof:name":"Over Edge",
    "wof:placetype":"venue"
},
  "geometry": {"coordinates":[-87.74112100000001,41.426714],"type":"Point"}
}