{
  "type": "Feature",
  "properties": {
    "iso:country":"US",
    "sg:address":"800 N Westmoreland Rd",
    "sg:city":"Lake Forest",
    "sg:classifiers":[
        {
            "category":"Health Services",
            "subcategory":"Doctor",
            "type":"Services"
        }
    ],
    "sg:phone":"+1 847 615 2227",
    "sg:postcode":"60045",
    "sg:province":"IL",
    "sg:tags":[
        "medical"
    ],
    "wof:name":"Vigder & Tanna",
    "wof:placetype":"venue"
},
  "geometry": {"coordinates":[-87.863005,42.255388],"type":"Point"}
}