{
  "type": "Feature",
  "properties": {
    "iso:country":"US",
    "sg:address":"255 S 36th St",
    "sg:city":"Quincy",
    "sg:classifiers":[
        {
            "category":"Wholesale",
            "subcategory":"Machinery & Supplies",
            "type":"Manufacturing & Wholesale Goods"
        }
    ],
    "sg:phone":"+1 217 223 4117",
    "sg:postcode":"62301",
    "sg:province":"IL",
    "sg:tags":[
        "industrial",
        "suppl",
        "threaded",
        "equipment",
        "fastener",
        "construction"
    ],
    "sg:website":"http://www.fastenal.com",
    "wof:name":"Fastenal Company",
    "wof:placetype":"venue"
},
  "geometry": {"coordinates":[-91.35838200000001,39.929352],"type":"Point"}
}