{
  "type": "Feature",
  "properties": {
    "iso:country":"US",
    "sg:address":"2923 Lincoln St",
    "sg:city":"Evanston",
    "sg:classifiers":[
        {
            "category":"Professional",
            "subcategory":"Management & Consulting",
            "type":"Services"
        }
    ],
    "sg:phone":"+1   ",
    "sg:postcode":"60201",
    "sg:province":"IL",
    "sg:tags":[
        "retail",
        "direct",
        "sales"
    ],
    "wof:name":"Cebar Communications Inc",
    "wof:placetype":"venue"
},
  "geometry": {"coordinates":[-87.713378,42.062138],"type":"Point"}
}