{
  "type": "Feature",
  "properties": {
    "iso:country":"US",
    "sg:address":"2020 7th St",
    "sg:city":"Rockford",
    "sg:classifiers":[
        {
            "category":"Manufacturing",
            "subcategory":"Metals",
            "type":"Manufacturing & Wholesale Goods"
        }
    ],
    "sg:phone":"+1 815 966 2000",
    "sg:postcode":"61104",
    "sg:province":"IL",
    "sg:tags":[
        "hardware",
        "product",
        "mfg",
        "institutional",
        "hinge",
        "tubular"
    ],
    "sg:website":"www.rockfordprocess.com",
    "wof:name":"Rockford Process Control Inc",
    "wof:placetype":"venue"
},
  "geometry": {"coordinates":[-89.080871,42.24697],"type":"Point"}
}