{
  "type": "Feature",
  "properties": {
    "iso:country":"US",
    "sg:address":"4497 S Park Rd",
    "sg:city":"Freeport",
    "sg:classifiers":[
        {
            "category":"Building & Trades",
            "subcategory":"Construction",
            "type":"Services"
        }
    ],
    "sg:phone":"+1 815 235 9606",
    "sg:postcode":"61032",
    "sg:province":"IL",
    "sg:tags":[
        "fire",
        "restoration",
        "inspection",
        "damage"
    ],
    "sg:website":"http://www.lossreduction.com",
    "wof:name":"RESTORx Northern Illinois",
    "wof:placetype":"venue"
},
  "geometry": {"coordinates":[-89.649941,42.229283],"type":"Point"}
}