{
  "type": "Feature",
  "properties": {
    "iso:country":"US",
    "sg:address":"2400 Highwood Rd",
    "sg:city":"Mc Henry",
    "sg:classifiers":[
        {
            "category":"Shopping",
            "subcategory":"Used Merchandise",
            "type":"Retail Goods"
        }
    ],
    "sg:phone":"+1   ",
    "sg:postcode":"60051",
    "sg:province":"IL",
    "wof:name":"Moons Madness",
    "wof:placetype":"venue"
},
  "geometry": {"coordinates":[-88.205979,42.301831],"type":"Point"}
}