{
  "type": "Feature",
  "properties": {
    "addr:full":"1308 Mercantile Dr Highland IL 62249",
    "addr:housenumber":"1308",
    "addr:postcode":"62249",
    "addr:street":"Mercantile Dr",
    "iso:country":"US",
    "sg:address":"1308 Mercantile Dr",
    "sg:city":"Highland",
    "sg:classifiers":[
        {
            "category":"Shopping",
            "subcategory":"Hobbies, Toys, & Games",
            "type":"Retail Goods"
        }
    ],
    "sg:phone":"+1 618 654 8183",
    "sg:postcode":"62249",
    "sg:province":"IL",
    "sg:tags":[
        "supply"
    ],
    "wof:name":"Dogs Of War Cards & Games",
    "wof:placetype":"venue"
},
  "geometry": {"coordinates":[-89.675797,38.74897],"type":"Point"}
}