{
  "type": "Feature",
  "properties": {
    "addr:full":"2641 Kirchoff Rd Rolling Meadows IL 60008",
    "addr:housenumber":"2641",
    "addr:postcode":"60008",
    "addr:street":"Kirchoff Rd",
    "iso:country":"US",
    "sg:address":"2641 Kirchoff Rd",
    "sg:city":"Rolling Meadows",
    "sg:classifiers":[
        {
            "category":"Restaurant",
            "type":"Food & Drink"
        }
    ],
    "sg:phone":"+1   ",
    "sg:postcode":"60008",
    "sg:province":"IL",
    "sg:tags":[
        "eating"
    ],
    "wof:name":"Wa-Pa-Ghettis Pizza",
    "wof:placetype":"venue"
},
  "geometry": {"coordinates":[-88.014899,42.077365],"type":"Point"}
}