{
  "type": "Feature",
  "properties": {
    "iso:country":"US",
    "sg:address":"352 E Roosevelt Rd",
    "sg:city":"Glen Ellyn",
    "sg:classifiers":[
        {
            "category":"Wholesale",
            "subcategory":"Electrical",
            "type":"Manufacturing & Wholesale Goods"
        }
    ],
    "sg:phone":"+1 630 469 7510",
    "sg:postcode":"60137",
    "sg:province":"IL",
    "sg:tags":[
        "repair",
        "electric",
        "motor"
    ],
    "sg:website":"www.dreisilker.com",
    "wof:name":"Dreisilker Electric Motors Inc",
    "wof:placetype":"venue"
},
  "geometry": {"coordinates":[-88.074408,41.859357],"type":"Point"}
}