{
  "type": "Feature",
  "properties": {
    "addr:full":"117 N 7th St Quincy IL 62301",
    "addr:housenumber":"117",
    "addr:postcode":"62301",
    "addr:street":"N 7Th St",
    "iso:country":"US",
    "sg:address":"117 N 7th St",
    "sg:city":"Quincy",
    "sg:classifiers":[
        {
            "category":"Organizations",
            "subcategory":"Religious Organization",
            "type":"Services"
        }
    ],
    "sg:phone":"+1 217 222 3000",
    "sg:postcode":"62301",
    "sg:province":"IL",
    "wof:name":"Saint Boniface Church",
    "wof:placetype":"venue"
},
  "geometry": {"coordinates":[-91.404779,39.933137],"type":"Point"}
}