{
  "type": "Feature",
  "properties": {
    "iso:country":"US",
    "sg:address":"438 Park Ln",
    "sg:city":"Lake Bluff",
    "sg:classifiers":[
        {
            "category":"Wholesale",
            "subcategory":"Durable Goods & Equipment",
            "type":"Manufacturing & Wholesale Goods"
        }
    ],
    "sg:phone":"+1 847 234 2406",
    "sg:postcode":"60044",
    "sg:province":"IL",
    "sg:tags":[
        "representative",
        "manufacturer"
    ],
    "wof:name":"Vanburen Co",
    "wof:placetype":"venue"
},
  "geometry": {"coordinates":[-87.855802,42.275037],"type":"Point"}
}