{
  "type": "Feature",
  "properties": {
    "iso:country":"US",
    "sg:address":"1710 W Golf Rd",
    "sg:city":"Mount Prospect",
    "sg:classifiers":[
        {
            "category":"Personal",
            "type":"Services"
        }
    ],
    "sg:phone":"+1 847 956 8267",
    "sg:postcode":"60056",
    "sg:province":"IL",
    "wof:name":"Southbeach Tan",
    "wof:placetype":"venue"
},
  "geometry": {"coordinates":[-87.963297,42.048738],"type":"Point"}
}