{
  "type": "Feature",
  "properties": {
    "iso:country":"US",
    "sg:address":"5005 W Orchard Dr",
    "sg:city":"Mc Henry",
    "sg:classifiers":[
        {
            "category":"Shopping",
            "subcategory":"Computers & Home Electronics",
            "type":"Retail Goods"
        },
        {
            "category":"Professional",
            "subcategory":"Secretarial Services",
            "type":"Services"
        }
    ],
    "sg:phone":"+1 815 385 4510",
    "sg:postcode":"60050",
    "sg:province":"IL",
    "sg:tags":[
        "reporting",
        "software"
    ],
    "wof:name":"All In One Computer",
    "wof:placetype":"venue"
},
  "geometry": {"coordinates":[-88.295481,42.366284],"type":"Point"}
}