{
  "type": "Feature",
  "properties": {
    "iso:country":"US",
    "sg:address":"6 Kingsbury Dr",
    "sg:city":"Bethalto",
    "sg:classifiers":[
        {
            "category":"Home & Garden",
            "subcategory":"Building Materials",
            "type":"Retail Goods"
        }
    ],
    "sg:phone":"+1   ",
    "sg:postcode":"62010",
    "sg:province":"IL",
    "wof:name":"Reflections",
    "wof:placetype":"venue"
},
  "geometry": {"coordinates":[-90.01442400000001,38.895023],"type":"Point"}
}