{
  "type": "Feature",
  "properties": {
    "iso:country":"US",
    "sg:address":"1940 E Devon Ave",
    "sg:city":"Elk Grove Village",
    "sg:classifiers":[
        {
            "category":"Professional",
            "subcategory":"Management & Consulting",
            "type":"Services"
        }
    ],
    "sg:phone":"+1 847 427 8024",
    "sg:postcode":"60007",
    "sg:province":"IL",
    "sg:tags":[
        "marketing",
        "consultant"
    ],
    "wof:name":"F K Suzuki International",
    "wof:placetype":"venue"
},
  "geometry": {"coordinates":[-87.952378,41.993364],"type":"Point"}
}