{
  "type": "Feature",
  "properties": {
    "iso:country":"US",
    "sg:address":"1557 N 20th Rd",
    "sg:city":"Grand Ridge",
    "sg:phone":"+1 815 249 5024",
    "sg:postcode":"61325",
    "sg:province":"IL",
    "sg:tags":[
        "farm",
        "corn",
        "soybean"
    ],
    "wof:name":"Rinker Verlyn",
    "wof:placetype":"venue"
},
  "geometry": {"coordinates":[-88.874763,41.22231],"type":"Point"}
}