{
  "type": "Feature",
  "properties": {
    "addr:full":"400 E Main St Barrington IL 60010",
    "addr:housenumber":"400",
    "addr:postcode":"60010",
    "addr:street":"E Main St",
    "iso:country":"US",
    "sg:address":"400 E Main St",
    "sg:city":"Barrington",
    "sg:classifiers":[
        {
            "category":"Professional",
            "subcategory":"Lawyer & Legal Services",
            "type":"Services"
        }
    ],
    "sg:phone":"+1 847 381 9370",
    "sg:postcode":"60010",
    "sg:province":"IL",
    "wof:name":"Terrence M Johnson",
    "wof:placetype":"venue"
},
  "geometry": {"coordinates":[-88.128305,42.154191],"type":"Point"}
}