{
  "type": "Feature",
  "properties": {
    "addr:full":"3549 Merchandise Dr Rockford IL 61109",
    "addr:housenumber":"3549",
    "addr:postcode":"61109",
    "addr:street":"Merchandise Dr",
    "iso:country":"US",
    "sg:address":"3549 Merchandise Dr",
    "sg:city":"Rockford",
    "sg:classifiers":[
        {
            "category":"Banks & Credit Unions",
            "subcategory":"Atm",
            "type":"Services"
        },
        {
            "category":"Professional",
            "subcategory":"Detective & Security Services",
            "type":"Services"
        },
        {
            "category":"Professional",
            "subcategory":"Business Services",
            "type":"Services"
        },
        {
            "category":"Shopping",
            "type":"Retail Goods"
        }
    ],
    "sg:phone":"+1 815 873 6792",
    "sg:postcode":"61109",
    "sg:province":"IL",
    "sg:tags":[
        "control",
        "monitoring",
        "supply",
        "fire",
        "alarm",
        "safe",
        "system",
        "access",
        "equipment",
        "location",
        "vault"
    ],
    "sg:website":"http://www.rockfordts.com/",
    "wof:name":"Rockford Tech Systems Inc",
    "wof:placetype":"venue"
},
  "geometry": {"coordinates":[-89.03091999999999,42.221077],"type":"Point"}
}