{
  "type": "Feature",
  "properties": {
    "iso:country":"US",
    "sg:address":"9812 Massasoit Ave",
    "sg:city":"Oak Lawn",
    "sg:classifiers":[
        {
            "category":"Freight",
            "type":"Transportation"
        }
    ],
    "sg:phone":"+1 708 424 1102",
    "sg:postcode":"60453",
    "sg:province":"IL",
    "sg:tags":[
        "operator",
        "trucking"
    ],
    "wof:name":"FTW Inc",
    "wof:placetype":"venue"
},
  "geometry": {"coordinates":[-87.763862,41.71403],"type":"Point"}
}