{
  "type": "Feature",
  "properties": {
    "addr:full":"1208 Poplar St Ottawa IL 61350",
    "addr:housenumber":"1208",
    "addr:postcode":"61350",
    "addr:street":"Poplar St",
    "iso:country":"US",
    "sg:address":"1208 Poplar St",
    "sg:city":"Ottawa",
    "sg:classifiers":[
        {
            "category":"Building & Trades",
            "subcategory":"Construction",
            "type":"Services"
        }
    ],
    "sg:phone":"+1 815 434 4877",
    "sg:postcode":"61350",
    "sg:province":"IL",
    "sg:tags":[
        "home",
        "improvement"
    ],
    "wof:name":"Detes Construction",
    "wof:placetype":"venue"
},
  "geometry": {"coordinates":[-88.854562,41.352413],"type":"Point"}
}