{
  "type": "Feature",
  "properties": {
    "iso:country":"US",
    "sg:address":"222 E Main St",
    "sg:city":"Genoa",
    "sg:classifiers":[
        {
            "category":"Building & Trades",
            "subcategory":"Plumbing",
            "type":"Services"
        }
    ],
    "sg:phone":"+1 815 784 4576",
    "sg:postcode":"60135",
    "sg:province":"IL",
    "sg:tags":[
        "plumbing",
        "contractor"
    ],
    "wof:name":"Affordable Plumbing & Sewer",
    "wof:placetype":"venue"
},
  "geometry": {"coordinates":[-88.69071,42.096818],"type":"Point"}
}