{
  "type": "Feature",
  "properties": {
    "addr:full":"5532 S Dorchester Ave Chicago IL 60637",
    "addr:housenumber":"5532",
    "addr:postcode":"60637",
    "addr:street":"S Dorchester Ave",
    "iso:country":"US",
    "sg:address":"5532 S Dorchester Ave",
    "sg:city":"Chicago",
    "sg:classifiers":[
        {
            "category":"Shopping",
            "subcategory":"Hobbies, Toys, & Games",
            "type":"Retail Goods"
        },
        {
            "category":"Shopping",
            "subcategory":"Crafts & Fabrics",
            "type":"Retail Goods"
        }
    ],
    "sg:phone":"+1 773 643 1664",
    "sg:postcode":"60637",
    "sg:province":"IL",
    "sg:tags":[
        "shop",
        "model",
        "hobby",
        "supply"
    ],
    "wof:name":"Web Craft Team",
    "wof:placetype":"venue"
},
  "geometry": {"coordinates":[-87.591651,41.794445],"type":"Point"}
}