{
  "type": "Feature",
  "properties": {
    "iso:country":"US",
    "sg:address":"7546 S Peoria St",
    "sg:city":"Chicago",
    "sg:classifiers":[
        {
            "category":"Building & Trades",
            "subcategory":"Construction",
            "type":"Services"
        }
    ],
    "sg:phone":"+1 773 873 1900",
    "sg:postcode":"60620",
    "sg:province":"IL",
    "sg:tags":[
        "contractor"
    ],
    "wof:name":"Washington Construction Co",
    "wof:placetype":"venue"
},
  "geometry": {"coordinates":[-87.646698,41.756199],"type":"Point"}
}