{
  "type": "Feature",
  "properties": {
    "iso:country":"US",
    "sg:address":"1249 W Boughton Rd",
    "sg:city":"Bolingbrook",
    "sg:classifiers":[
        {
            "category":"Shopping",
            "type":"Retail Goods"
        }
    ],
    "sg:phone":"+1   ",
    "sg:postcode":"60440",
    "sg:province":"IL",
    "sg:tags":[
        "pet",
        "supply"
    ],
    "sg:website":"www.petco.com",
    "wof:name":"PETCO",
    "wof:placetype":"venue"
},
  "geometry": {"coordinates":[-88.12544200000001,41.702966],"type":"Point"}
}