{
  "type": "Feature",
  "properties": {
    "iso:country":"US",
    "sg:address":"1106 Sunset Dr",
    "sg:city":"Viola",
    "sg:classifiers":[
        {
            "category":"Freight",
            "type":"Transportation"
        }
    ],
    "sg:phone":"+1 309 596 2723",
    "sg:postcode":"61486",
    "sg:province":"IL",
    "sg:tags":[
        "special"
    ],
    "wof:name":"Route 17 Storage",
    "wof:placetype":"venue"
},
  "geometry": {"coordinates":[-90.58825299999999,41.205227],"type":"Point"}
}