{
  "type": "Feature",
  "properties": {
    "addr:full":"13006 Friends Creek Park Rd Cisco IL 61830",
    "addr:housenumber":"13006",
    "addr:postcode":"61830",
    "addr:street":"Friends Creek Park Rd",
    "iso:country":"US",
    "sg:address":"13006 Friends Creek Park Rd",
    "sg:city":"Cisco",
    "sg:phone":"+1 217 795 2141",
    "sg:postcode":"61830",
    "sg:province":"IL",
    "sg:tags":[
        "farm",
        "corn",
        "soybean"
    ],
    "wof:name":"Greg Briggs",
    "wof:placetype":"venue"
},
  "geometry": {"coordinates":[-88.783484,40.017105],"type":"Point"}
}