{
  "type": "Feature",
  "properties": {
    "addr:full":"2435 Curtiss St Downers Grove IL 60515",
    "addr:housenumber":"2435",
    "addr:postcode":"60515",
    "addr:street":"Curtiss St",
    "iso:country":"US",
    "sg:address":"2435 Curtiss St",
    "sg:city":"Downers Grove",
    "sg:classifiers":[
        {
            "category":"Education",
            "subcategory":"Special Training",
            "type":"Public Place"
        }
    ],
    "sg:phone":"+1 630 969 0900",
    "sg:postcode":"60515",
    "sg:province":"IL",
    "wof:name":"Premier Gymnastics Academy",
    "wof:placetype":"venue"
},
  "geometry": {"coordinates":[-88.04294299999999,41.79251],"type":"Point"}
}