{
  "type": "Feature",
  "properties": {
    "iso:country":"US",
    "sg:address":"610 Concord St",
    "sg:city":"Aurora",
    "sg:classifiers":[
        {
            "category":"Shopping",
            "subcategory":"Bicycles & Sporting Goods",
            "type":"Retail Goods"
        }
    ],
    "sg:phone":"+1   ",
    "sg:postcode":"60505",
    "sg:province":"IL",
    "wof:name":"L L O Bro Bait & Tackle",
    "wof:placetype":"venue"
},
  "geometry": {"coordinates":[-88.32074,41.743327],"type":"Point"}
}