{
  "type": "Feature",
  "properties": {
    "addr:full":"5400 W Cermak Rd Cicero IL 60804",
    "addr:housenumber":"5400",
    "addr:postcode":"60804",
    "addr:street":"W Cermak Rd",
    "iso:country":"US",
    "sg:address":"5400 W Cermak Rd",
    "sg:city":"Cicero",
    "sg:classifiers":[
        {
            "category":"Restaurant",
            "type":"Food & Drink"
        }
    ],
    "sg:phone":"+1   ",
    "sg:postcode":"60804",
    "sg:province":"IL",
    "sg:tags":[
        "eating"
    ],
    "wof:name":"Churchs Chicken",
    "wof:placetype":"venue"
},
  "geometry": {"coordinates":[-87.761449,41.851085],"type":"Point"}
}