{
  "type": "Feature",
  "properties": {
    "addr:full":"11740 Hayloft Ln Roscoe IL 61073",
    "addr:housenumber":"11740",
    "addr:postcode":"61073",
    "addr:street":"Hayloft Ln",
    "iso:country":"US",
    "sg:address":"11740 Hayloft Ln",
    "sg:city":"Roscoe",
    "sg:classifiers":[
        {
            "category":"Manufacturing",
            "subcategory":"Metals",
            "type":"Manufacturing & Wholesale Goods"
        }
    ],
    "sg:phone":"+1 815 623 3617",
    "sg:postcode":"61073",
    "sg:province":"IL",
    "wof:name":"C & S Blacking Company Inc",
    "wof:placetype":"venue"
},
  "geometry": {"coordinates":[-89.03510199999999,42.431025],"type":"Point"}
}