{
  "type": "Feature",
  "properties": {
    "addr:full":"1338 S Halsted St Chicago IL 60607",
    "addr:housenumber":"1338",
    "addr:postcode":"60607",
    "addr:street":"S Halsted St",
    "iso:country":"US",
    "sg:address":"1338 S Halsted St",
    "sg:city":"Chicago",
    "sg:classifiers":[
        {
            "category":"Shopping",
            "subcategory":"Mobile Phones",
            "type":"Retail Goods"
        }
    ],
    "sg:phone":"+1 312 421 1515",
    "sg:postcode":"60607",
    "sg:province":"IL",
    "wof:name":"Cingular Wireless",
    "wof:placetype":"venue"
},
  "geometry": {"coordinates":[-87.647003,41.865101],"type":"Point"}
}