{
  "type": "Feature",
  "properties": {
    "addr:full":"825 E Roosevelt Rd Lombard IL 60148",
    "addr:housenumber":"825",
    "addr:postcode":"60148",
    "addr:street":"E Roosevelt Rd",
    "iso:country":"US",
    "sg:address":"825 E Roosevelt Rd",
    "sg:city":"Lombard",
    "sg:classifiers":[
        {
            "category":"Shopping",
            "subcategory":"Party Supplies",
            "type":"Retail Goods"
        }
    ],
    "sg:phone":"+1 630 953 2866",
    "sg:postcode":"60148",
    "sg:province":"IL",
    "sg:tags":[
        "decoration",
        "rental"
    ],
    "sg:website":"http://www.awesomeamusements.com",
    "wof:name":"Awesome Amusements",
    "wof:placetype":"venue"
},
  "geometry": {"coordinates":[-87.997606,41.860626],"type":"Point"}
}