{
  "type": "Feature",
  "properties": {
    "addr:full":"220 W 3rd St Byron IL 61010",
    "addr:housenumber":"220",
    "addr:postcode":"61010",
    "addr:street":"W 3Rd St",
    "iso:country":"US",
    "sg:address":"220 W 3rd St",
    "sg:city":"Byron",
    "sg:classifiers":[
        {
            "category":"Professional",
            "type":"Services"
        }
    ],
    "sg:phone":"+1 815 234 2860",
    "sg:postcode":"61010",
    "sg:province":"IL",
    "sg:tags":[
        "establishment"
    ],
    "wof:name":"Byron Cultural Ctr",
    "wof:placetype":"venue"
},
  "geometry": {"coordinates":[-89.25794,42.127715],"type":"Point"}
}