{
  "type": "Feature",
  "properties": {
    "iso:country":"US",
    "sg:address":"3000 Lakeside Dr",
    "sg:city":"Bannockburn",
    "sg:classifiers":[
        {
            "category":"Recreation",
            "type":"Entertainment"
        }
    ],
    "sg:phone":"+1 847 482 1222",
    "sg:postcode":"60015",
    "sg:province":"IL",
    "sg:tags":[
        "ticket"
    ],
    "wof:name":"Ticket Reserve",
    "wof:placetype":"venue"
},
  "geometry": {"coordinates":[-87.884867,42.202664],"type":"Point"}
}