{
  "type": "Feature",
  "properties": {
    "iso:country":"US",
    "sg:address":"1101 W Pines Rd",
    "sg:city":"Oregon",
    "sg:classifiers":[
        {
            "category":"Banks & Credit Unions",
            "subcategory":"Bank",
            "type":"Services"
        }
    ],
    "sg:phone":"+1 815 732 6211",
    "sg:postcode":"61061",
    "sg:province":"IL",
    "sg:tags":[
        "loan"
    ],
    "wof:name":"First Farm Credit Svc",
    "wof:placetype":"venue"
},
  "geometry": {"coordinates":[-89.358707,42.003439],"type":"Point"}
}