{
  "type": "Feature",
  "properties": {
    "iso:country":"US",
    "sg:address":"737 Millersburg Rd",
    "sg:city":"Greenville",
    "sg:classifiers":[
        {
            "category":"Wholesale",
            "subcategory":"Farm Supplies",
            "type":"Manufacturing & Wholesale Goods"
        },
        {
            "category":"Farming",
            "subcategory":"Farm",
            "type":"Manufacturing & Wholesale Goods"
        }
    ],
    "sg:phone":"+1 618 664 3569",
    "sg:postcode":"62246",
    "sg:province":"IL",
    "sg:tags":[
        "grain"
    ],
    "wof:name":"Marvin Stoecklin",
    "wof:placetype":"venue"
},
  "geometry": {"coordinates":[-89.451061,38.845758],"type":"Point"}
}