{
  "type": "Feature",
  "properties": {
    "addr:full":"2696 Timber Trl Rockford IL 61107",
    "addr:housenumber":"2696",
    "addr:postcode":"61107",
    "addr:street":"Timber Trl",
    "iso:country":"US",
    "sg:address":"2696 Timber Trl",
    "sg:city":"Rockford",
    "sg:classifiers":[
        {
            "category":"Building & Trades",
            "subcategory":"Construction",
            "type":"Services"
        }
    ],
    "sg:phone":"+1 815 398 4115",
    "sg:postcode":"61107",
    "sg:province":"IL",
    "sg:tags":[
        "carpentry",
        "contractor"
    ],
    "wof:name":"Glen Bergquist Carpentry",
    "wof:placetype":"venue"
},
  "geometry": {"coordinates":[-88.96361899999999,42.298629],"type":"Point"}
}