{
  "type": "Feature",
  "properties": {
    "addr:full":"419 S West St Gibson City IL 60936",
    "addr:housenumber":"419",
    "addr:postcode":"west;60936",
    "addr:street":"S;St",
    "iso:country":"US",
    "sg:address":"419 S West St",
    "sg:city":"Gibson City",
    "sg:classifiers":[
        {
            "category":"Real Estate",
            "subcategory":"Developer",
            "type":"Services"
        }
    ],
    "sg:phone":"+1 217 784 5941",
    "sg:postcode":"60936",
    "sg:province":"IL",
    "sg:tags":[
        "cemetery"
    ],
    "wof:name":"Drummer Township Cemetery",
    "wof:placetype":"venue"
},
  "geometry": {"coordinates":[-88.38006,40.461083],"type":"Point"}
}