{
  "type": "Feature",
  "properties": {
    "addr:full":"6200 W Belmont Ave Chicago IL 60634",
    "addr:housenumber":"6200",
    "addr:postcode":"60634",
    "addr:street":"W Belmont Ave",
    "iso:country":"US",
    "sg:address":"6200 W Belmont Ave",
    "sg:city":"Chicago",
    "sg:classifiers":[
        {
            "category":"Bakery",
            "type":"Food & Drink"
        },
        {
            "category":"Coffee & Tea",
            "type":"Food & Drink"
        },
        {
            "category":"Bagels",
            "type":"Food & Drink"
        },
        {
            "category":"Donuts",
            "type":"Food & Drink"
        }
    ],
    "sg:menulink":"http://www.allmenus.com/il/chicago/135099-dunkin-donuts/menu/",
    "sg:phone":"+1 773 202 8799",
    "sg:postcode":"60634",
    "sg:province":"IL",
    "sg:tags":[
        "american",
        "pastry"
    ],
    "wof:name":"Dunkin' Donuts",
    "wof:placetype":"venue"
},
  "geometry": {"coordinates":[-87.78139,41.938551],"type":"Point"}
}