{
  "type": "Feature",
  "properties": {
    "iso:country":"US",
    "sg:address":"300 SE 3rd St",
    "sg:city":"Aledo",
    "sg:classifiers":[
        {
            "category":"Restaurant",
            "type":"Food & Drink"
        }
    ],
    "sg:phone":"+1 309 582 7516",
    "sg:postcode":"61231",
    "sg:province":"IL",
    "sg:tags":[
        "parlor",
        "ice",
        "cream"
    ],
    "sg:website":"http://www.tasteefreez.com",
    "wof:name":"Tastee Freez",
    "wof:placetype":"venue"
},
  "geometry": {"coordinates":[-90.74694100000001,41.199909],"type":"Point"}
}