{
  "type": "Feature",
  "properties": {
    "iso:country":"US",
    "sg:address":"6539 Ogden Ave",
    "sg:city":"Berwyn",
    "sg:classifiers":[
        {
            "category":"Autos & Motor Vehicles",
            "subcategory":"Automobile Sales",
            "type":"Retail Goods"
        }
    ],
    "sg:phone":"+1 708 795 7900",
    "sg:postcode":"60402",
    "sg:province":"IL",
    "sg:tags":[
        "car"
    ],
    "wof:name":"Anderson Wayne H Insurance Agcy",
    "wof:placetype":"venue"
},
  "geometry": {"coordinates":[-87.78679700000001,41.829201],"type":"Point"}
}