{
  "type": "Feature",
  "properties": {
    "iso:country":"US",
    "sg:address":"500 Ave C",
    "sg:city":"Danville",
    "sg:classifiers":[
        {
            "category":"Retail",
            "subcategory":"Repair Shop",
            "type":"Services"
        }
    ],
    "sg:phone":"+1 217 442 4441",
    "sg:postcode":"61832",
    "sg:province":"IL",
    "sg:tags":[
        "equipment",
        "electronic",
        "supply"
    ],
    "wof:name":"Burgoyne Electronics",
    "wof:placetype":"venue"
},
  "geometry": {"coordinates":[-87.649694,40.119941],"type":"Point"}
}