{
  "type": "Feature",
  "properties": {
    "iso:country":"US",
    "sg:address":"131 Rutgers Ct",
    "sg:city":"Glenview",
    "sg:classifiers":[
        {
            "category":"Professional",
            "subcategory":"Management & Consulting",
            "type":"Services"
        }
    ],
    "sg:phone":"+1 847 562 8933",
    "sg:postcode":"60026",
    "sg:province":"IL",
    "sg:tags":[
        "counselor",
        "relation",
        "public"
    ],
    "sg:website":"http://www.soarwithme.com",
    "wof:name":"Soar With Me",
    "wof:placetype":"venue"
},
  "geometry": {"coordinates":[-87.833444,42.102377],"type":"Point"}
}