{
  "type": "Feature",
  "properties": {
    "iso:country":"US",
    "sg:address":"736 W 35th Street",
    "sg:city":"Chicago",
    "sg:classifiers":[
        {
            "category":"Health Services",
            "subcategory":"Doctor",
            "type":"Services"
        }
    ],
    "sg:phone":"+1 773 247 2131",
    "sg:postcode":"60616",
    "sg:province":"IL",
    "wof:name":"Rx Pain Management",
    "wof:placetype":"venue"
},
  "geometry": {"coordinates":[-87.644953,41.830758],"type":"Point"}
}