{
  "type": "Feature",
  "properties": {
    "iso:country":"US",
    "sg:address":"2901 State St",
    "sg:city":"Granite City",
    "sg:classifiers":[
        {
            "category":"Education",
            "subcategory":"School",
            "type":"Public Place"
        }
    ],
    "sg:phone":"+1 618 451 5813",
    "sg:postcode":"62040",
    "sg:province":"IL",
    "wof:name":"Schools Public",
    "wof:placetype":"venue"
},
  "geometry": {"coordinates":[-90.129499,38.715828],"type":"Point"}
}