{
  "type": "Feature",
  "properties": {
    "iso:country":"US",
    "sg:address":"1448 W Grand Avenue",
    "sg:city":"Chicago",
    "sg:classifiers":[
        {
            "category":"Education",
            "subcategory":"School",
            "type":"Public Place"
        }
    ],
    "sg:phone":"+1 773 534 7724",
    "sg:postcode":"60622",
    "sg:province":"IL",
    "wof:name":"Schools Public",
    "wof:placetype":"venue"
},
  "geometry": {"coordinates":[-87.663697,41.890895],"type":"Point"}
}