{
  "type": "Feature",
  "properties": {
    "iso:country":"US",
    "sg:address":"7231 W 24th Street",
    "sg:city":"Riverside",
    "sg:classifiers":[
        {
            "category":"Shopping",
            "subcategory":"Crafts & Fabrics",
            "type":"Retail Goods"
        }
    ],
    "sg:phone":"+1 708 442 5787",
    "sg:postcode":"60546",
    "sg:province":"IL",
    "sg:tags":[
        "art",
        "supply"
    ],
    "sg:website":"www.michaels.com",
    "wof:name":"Michaels",
    "wof:placetype":"venue"
},
  "geometry": {"coordinates":[-87.80395799999999,41.846021],"type":"Point"}
}