{
  "type": "Feature",
  "properties": {
    "addr:full":"451 Gainsborough Dr Romeoville IL 60446",
    "addr:housenumber":"451",
    "addr:postcode":"60446",
    "addr:street":"Gainsborough Dr",
    "iso:country":"US",
    "sg:address":"451 Gainsborough Dr",
    "sg:city":"Romeoville",
    "sg:classifiers":[
        {
            "category":"Professional",
            "subcategory":"Computer Services",
            "type":"Services"
        }
    ],
    "sg:phone":"+1 815 293 0236",
    "sg:postcode":"60446",
    "sg:province":"IL",
    "sg:tags":[
        "consulting"
    ],
    "wof:name":"Information Systems Cons",
    "wof:placetype":"venue"
},
  "geometry": {"coordinates":[-88.09057300000001,41.627327],"type":"Point"}
}