{
  "type": "Feature",
  "properties": {
    "iso:country":"US",
    "sg:address":"1203 3rd St",
    "sg:city":"Galena",
    "sg:classifiers":[
        {
            "category":"Travel",
            "subcategory":"Hotels & Motels",
            "type":"Entertainment"
        }
    ],
    "sg:phone":"+1 815 777 1020",
    "sg:postcode":"61036",
    "sg:province":"IL",
    "sg:tags":[
        "breakfast",
        "accommodation",
        "bed"
    ],
    "wof:name":"De Zoya House Bed & Breakfast",
    "wof:placetype":"venue"
},
  "geometry": {"coordinates":[-90.427958,42.408247],"type":"Point"}
}