{
  "type": "Feature",
  "properties": {
    "addr:full":"111 N State St Chicago IL 60602",
    "addr:housenumber":"111",
    "addr:postcode":"60602",
    "addr:street":"N State St",
    "iso:country":"US",
    "sg:address":"111 N State St",
    "sg:city":"Chicago",
    "sg:classifiers":[
        {
            "category":"Shopping",
            "subcategory":"Shoes",
            "type":"Retail Goods"
        }
    ],
    "sg:phone":"+1 312 578 0046",
    "sg:postcode":"60602",
    "sg:province":"IL",
    "sg:tags":[
        "store"
    ],
    "wof:name":"Stride Rite",
    "wof:placetype":"venue"
},
  "geometry": {"coordinates":[-87.627583,41.883521],"type":"Point"}
}