{
  "type": "Feature",
  "properties": {
    "addr:full":"1930 Twin Oaks Ct Buffalo Grove IL 60089",
    "addr:housenumber":"1930",
    "addr:postcode":"60089",
    "addr:street":"Twin Oaks Ct",
    "iso:country":"US",
    "sg:address":"1930 Twin Oaks Ct",
    "sg:city":"Buffalo Grove",
    "sg:classifiers":[
        {
            "category":"Wholesale",
            "subcategory":"Vending Machines",
            "type":"Manufacturing & Wholesale Goods"
        }
    ],
    "sg:phone":"+1   ",
    "sg:postcode":"60089",
    "sg:province":"IL",
    "sg:tags":[
        "operator"
    ],
    "wof:name":"Mj Vending",
    "wof:placetype":"venue"
},
  "geometry": {"coordinates":[-87.97371099999999,42.185039],"type":"Point"}
}