{
  "type": "Feature",
  "properties": {
    "addr:full":"6620 111th St Palos Park IL 60482",
    "addr:housenumber":"6620",
    "addr:postcode":"60482",
    "addr:street":"111Th St",
    "iso:country":"US",
    "sg:address":"6620 111th St",
    "sg:city":"Palos Park",
    "sg:classifiers":[
        {
            "category":"Food & Beverages",
            "subcategory":"Groceries & Convenience Stores",
            "type":"Retail Goods"
        }
    ],
    "sg:phone":"+1 708 448 6338",
    "sg:postcode":"60482",
    "sg:province":"IL",
    "wof:name":"Fairplay",
    "wof:placetype":"venue"
},
  "geometry": {"coordinates":[-87.78500200000001,41.69031],"type":"Point"}
}