{
  "type": "Feature",
  "properties": {
    "addr:full":"300 20th Ave W Milan IL 61264",
    "addr:housenumber":"300",
    "addr:postcode":"61264",
    "addr:street":"20Th Ave W",
    "iso:country":"US",
    "sg:address":"300 20th Ave W",
    "sg:city":"Milan",
    "sg:classifiers":[
        {
            "category":"Real Estate",
            "subcategory":"Real Estate Operator",
            "type":"Services"
        }
    ],
    "sg:phone":"+1 309 787 7368",
    "sg:postcode":"61264",
    "sg:province":"IL",
    "sg:tags":[
        "apartment"
    ],
    "wof:name":"Village Woods Apartments",
    "wof:placetype":"venue"
},
  "geometry": {"coordinates":[-90.570412,41.431961],"type":"Point"}
}