{
  "type": "Feature",
  "properties": {
    "iso:country":"US",
    "sg:address":"108 Kothe Ct",
    "sg:city":"Rockton",
    "sg:classifiers":[
        {
            "category":"Bars & Pubs",
            "type":"Food & Drink"
        }
    ],
    "sg:phone":"+1 815 623 5900",
    "sg:postcode":"61072",
    "sg:province":"IL",
    "sg:tags":[
        "tavern"
    ],
    "wof:name":"Jim Shell",
    "wof:placetype":"venue"
},
  "geometry": {"coordinates":[-89.07210000000001,42.462358],"type":"Point"}
}