{
  "type": "Feature",
  "properties": {
    "iso:country":"US",
    "sg:address":"14102 White School Rd",
    "sg:city":"South Beloit",
    "sg:classifiers":[
        {
            "category":"Farming",
            "subcategory":"Livestock Farm",
            "type":"Manufacturing & Wholesale Goods"
        }
    ],
    "sg:phone":"+1 815 389 4371",
    "sg:postcode":"61080",
    "sg:province":"WI",
    "sg:tags":[
        "hog",
        "or",
        "feedlot"
    ],
    "wof:name":"A M Farms",
    "wof:placetype":"venue"
},
  "geometry": {"coordinates":[-88.960403,42.465858],"type":"Point"}
}