{
  "type": "Feature",
  "properties": {
    "iso:country":"US",
    "sg:address":"600 Lincoln Ave",
    "sg:city":"Charleston",
    "sg:classifiers":[
        {
            "category":"Communications",
            "subcategory":"Radio Station",
            "type":"Services"
        }
    ],
    "sg:phone":"+1 217 581 6116",
    "sg:postcode":"61920",
    "sg:province":"IL",
    "sg:tags":[
        "broadcast"
    ],
    "wof:name":"Weiu FM 889",
    "wof:placetype":"venue"
},
  "geometry": {"coordinates":[-88.175135,39.484382],"type":"Point"}
}