{
  "type": "Feature",
  "properties": {
    "iso:country":"US",
    "sg:address":"1901 S 9th Ave",
    "sg:city":"Maywood",
    "sg:classifiers":[
        {
            "category":"Social Services",
            "subcategory":"Child Care",
            "type":"Services"
        },
        {
            "category":"Education",
            "subcategory":"Preschool",
            "type":"Public Place"
        },
        {
            "category":"Education",
            "subcategory":"School",
            "type":"Public Place"
        }
    ],
    "sg:phone":"+1 708 450 9013",
    "sg:postcode":"60153",
    "sg:province":"IL",
    "sg:tags":[
        "elementary",
        "day"
    ],
    "wof:name":"Tender Care Early Learning Center",
    "wof:placetype":"venue"
},
  "geometry": {"coordinates":[-87.84339900000001,41.869701],"type":"Point"}
}