{
  "type": "Feature",
  "properties": {
    "addr:full":"1740 Sherman Ave Evanston IL 60201",
    "addr:housenumber":"1740",
    "addr:postcode":"60201",
    "addr:street":"Sherman Ave",
    "iso:country":"US",
    "sg:address":"1740 Sherman Ave",
    "sg:city":"Evanston",
    "sg:classifiers":[
        {
            "category":"Restaurant",
            "type":"Food & Drink"
        }
    ],
    "sg:phone":"+1   ",
    "sg:postcode":"60201",
    "sg:province":"IL",
    "wof:name":"Sherman Restaurant",
    "wof:placetype":"venue"
},
  "geometry": {"coordinates":[-87.681887,42.049398],"type":"Point"}
}