{
  "type": "Feature",
  "properties": {
    "addr:full":"1725 Washington St Waukegan IL 60085",
    "addr:housenumber":"1725",
    "addr:postcode":"60085",
    "addr:street":"Washington St",
    "iso:country":"US",
    "sg:address":"1725 Washington St",
    "sg:city":"Waukegan",
    "sg:classifiers":[
        {
            "category":"Personal",
            "subcategory":"Beauty Salon",
            "type":"Services"
        }
    ],
    "sg:phone":"+1 847 249 5422",
    "sg:postcode":"60085",
    "sg:province":"IL",
    "wof:name":"Terla Beauty Salon",
    "wof:placetype":"venue"
},
  "geometry": {"coordinates":[-87.853252,42.359608],"type":"Point"}
}