{
  "type": "Feature",
  "properties": {
    "addr:full":"108 N Jackson St Belleville IL 62220",
    "addr:housenumber":"108",
    "addr:postcode":"62220",
    "addr:street":"N Jackson St",
    "iso:country":"US",
    "sg:address":"108 N Jackson St",
    "sg:city":"Belleville",
    "sg:classifiers":[
        {
            "category":"Professional",
            "subcategory":"Accounting & Tax Preparation",
            "type":"Services"
        }
    ],
    "sg:phone":"+1 618 235 4250",
    "sg:postcode":"62220",
    "sg:province":"IL",
    "wof:name":"Trapp Accounting Service",
    "wof:placetype":"venue"
},
  "geometry": {"coordinates":[-89.981498,38.514646],"type":"Point"}
}