{
  "type": "Feature",
  "properties": {
    "addr:full":"4655 137th St Crestwood IL 60445",
    "addr:housenumber":"4655",
    "addr:postcode":"60445",
    "addr:street":"137Th St",
    "iso:country":"US",
    "sg:address":"4655 137th St",
    "sg:city":"Crestwood",
    "sg:classifiers":[
        {
            "category":"Wholesale",
            "subcategory":"Machinery & Supplies",
            "type":"Manufacturing & Wholesale Goods"
        }
    ],
    "sg:phone":"+1 708 239 7940",
    "sg:postcode":"60445",
    "sg:province":"IL",
    "sg:tags":[
        "contractor"
    ],
    "wof:name":"Central Contractors Svc Inc",
    "wof:placetype":"venue"
},
  "geometry": {"coordinates":[-87.73430999999999,41.643549],"type":"Point"}
}