{
  "type": "Feature",
  "properties": {
    "iso:country":"US",
    "sg:address":"120 E 23rd Ave",
    "sg:city":"Coal Valley",
    "sg:classifiers":[
        {
            "category":"Shopping",
            "subcategory":"Computers & Home Electronics",
            "type":"Retail Goods"
        }
    ],
    "sg:phone":"+1 309 799 5833",
    "sg:postcode":"61240",
    "sg:province":"IL",
    "sg:tags":[
        "television",
        "radio"
    ],
    "wof:name":"Valley TV Svc Ctr",
    "wof:placetype":"venue"
},
  "geometry": {"coordinates":[-90.459812,41.428543],"type":"Point"}
}