{
  "type": "Feature",
  "properties": {
    "iso:country":"US",
    "sg:address":"15 W Delaware Place",
    "sg:city":"Chicago",
    "sg:classifiers":[
        {
            "category":"Place Of Worship",
            "subcategory":"Synagogue",
            "type":"Public Place"
        }
    ],
    "sg:phone":"+1 312 867 7000",
    "sg:postcode":"60610",
    "sg:province":"IL",
    "wof:name":"Chicago Sinai Congregation",
    "wof:placetype":"venue"
},
  "geometry": {"coordinates":[-87.629081,41.899002],"type":"Point"}
}