{
  "type": "Feature",
  "properties": {
    "addr:full":"212 E Ohio St Ste 200 Chicago IL 60611",
    "addr:housenumber":"212",
    "addr:postcode":"60611",
    "addr:street":"E Ohio St Ste 200",
    "iso:country":"US",
    "sg:address":"212 E Ohio St Ste 200",
    "sg:city":"Chicago",
    "sg:classifiers":[
        {
            "category":"Real Estate",
            "subcategory":"Real Estate Services",
            "type":"Services"
        }
    ],
    "sg:phone":"+1 312 506 0200",
    "sg:postcode":"60611",
    "sg:province":"IL",
    "sg:website":"www.atproperties.com/agent-offic...",
    "wof:name":"Mike Paonessa",
    "wof:placetype":"venue"
},
  "geometry": {"coordinates":[-87.622024,41.8924],"type":"Point"}
}