{
  "type": "Feature",
  "properties": {
    "addr:full":"1316 N Clybourn Ave Chicago IL 60610",
    "addr:housenumber":"1316",
    "addr:postcode":"60610",
    "addr:street":"N Clybourn Ave",
    "iso:country":"US",
    "sg:address":"1316 N Clybourn Ave",
    "sg:city":"Chicago",
    "sg:classifiers":[
        {
            "category":"Communications",
            "subcategory":"Film & Video Production",
            "type":"Services"
        },
        {
            "category":"Communications",
            "type":"Services"
        }
    ],
    "sg:phone":"+1 312 664 5353",
    "sg:postcode":"60610",
    "sg:province":"IL",
    "sg:tags":[
        "recording",
        "rehearsal",
        "studio",
        "service-sound"
    ],
    "sg:website":"http://www.grrrrecords.com",
    "wof:name":"Tone Zone Recording",
    "wof:placetype":"venue"
},
  "geometry": {"coordinates":[-87.642899,41.906399],"type":"Point"}
}