{
  "type": "Feature",
  "properties": {
    "iso:country":"US",
    "sg:address":"4918 W 95th St",
    "sg:city":"Oak Lawn",
    "sg:classifiers":[
        {
            "category":"Local Transit",
            "type":"Transportation"
        }
    ],
    "sg:phone":"+1 708 424 8038",
    "sg:postcode":"60453",
    "sg:province":"IL",
    "sg:tags":[
        "ambulance"
    ],
    "wof:name":"EMSI",
    "wof:placetype":"venue"
},
  "geometry": {"coordinates":[-87.744258,41.720089],"type":"Point"}
}