{
  "type": "Feature",
  "properties": {
    "iso:country":"US",
    "sg:address":"1215 Welles Ct",
    "sg:city":"O Fallon",
    "sg:classifiers":[
        {
            "category":"Professional",
            "subcategory":"Employment Agencies",
            "type":"Services"
        }
    ],
    "sg:phone":"+1 618 622 3000",
    "sg:postcode":"62269",
    "sg:province":"IL",
    "wof:name":"Technical Recruiting Services",
    "wof:placetype":"venue"
},
  "geometry": {"coordinates":[-89.925301,38.611301],"type":"Point"}
}