{
  "type": "Feature",
  "properties": {
    "addr:full":"1602 S River Rd Des Plaines IL 60018",
    "addr:housenumber":"1602",
    "addr:postcode":"60018",
    "addr:street":"S River Rd Des",
    "iso:country":"US",
    "sg:address":"1602 S River Rd",
    "sg:city":"Des Plaines",
    "sg:classifiers":[
        {
            "category":"Food & Beverages",
            "subcategory":"Groceries & Convenience Stores",
            "type":"Retail Goods"
        }
    ],
    "sg:phone":"+1   ",
    "sg:postcode":"60018",
    "sg:province":"IL",
    "wof:name":"River Oak Mobile Mart",
    "wof:placetype":"venue"
},
  "geometry": {"coordinates":[-87.87651099999999,42.023522],"type":"Point"}
}