{
  "type": "Feature",
  "properties": {
    "iso:country":"US",
    "sg:address":"5181 Pontiac Ln",
    "sg:city":"Evansville",
    "sg:classifiers":[
        {
            "category":"Building & Trades",
            "subcategory":"Electrical",
            "type":"Services"
        }
    ],
    "sg:phone":"+1 618 282 8399",
    "sg:postcode":"62242",
    "sg:province":"IL",
    "wof:name":"Cable Equites Colorado LTD",
    "wof:placetype":"venue"
},
  "geometry": {"coordinates":[-89.985206,38.119003],"type":"Point"}
}