{
  "type": "Feature",
  "properties": {
    "addr:full":"22147 W Cuba Rd Kildeer IL 60047",
    "addr:housenumber":"22147",
    "addr:postcode":"60047",
    "addr:street":"W Cuba Rd",
    "iso:country":"US",
    "sg:address":"22147 W Cuba Rd",
    "sg:city":"Kildeer",
    "sg:classifiers":[
        {
            "category":"Building & Trades",
            "subcategory":"Construction",
            "type":"Services"
        }
    ],
    "sg:phone":"+1 847 438 1666",
    "sg:postcode":"60047",
    "sg:province":"IL",
    "sg:tags":[
        "general",
        "contractor"
    ],
    "wof:name":"Design Tech Inc",
    "wof:placetype":"venue"
},
  "geometry": {"coordinates":[-88.065578,42.176395],"type":"Point"}
}