{
  "type": "Feature",
  "properties": {
    "iso:country":"US",
    "sg:address":"23 W Ferguson Ave",
    "sg:city":"Wood River",
    "sg:classifiers":[
        {
            "category":"Freight",
            "type":"Transportation"
        }
    ],
    "sg:phone":"+1 618 254 3630",
    "sg:postcode":"62095",
    "sg:province":"IL",
    "sg:tags":[
        "trucking"
    ],
    "wof:name":"Dot's Trucking",
    "wof:placetype":"venue"
},
  "geometry": {"coordinates":[-90.099632,38.861008],"type":"Point"}
}