{
  "type": "Feature",
  "properties": {
    "addr:full":"17519 80th Ave Tinley Park IL 60477",
    "addr:housenumber":"17519",
    "addr:postcode":"60477",
    "addr:street":"80Th Ave",
    "iso:country":"US",
    "sg:address":"17519 80th Ave",
    "sg:city":"Tinley Park",
    "sg:classifiers":[
        {
            "category":"Health Services",
            "subcategory":"Doctor",
            "type":"Services"
        }
    ],
    "sg:phone":"+1 708 429 2111",
    "sg:postcode":"60477",
    "sg:province":"IL",
    "wof:name":"Mc Gonigle Edward P DDS",
    "wof:placetype":"venue"
},
  "geometry": {"coordinates":[-87.812567,41.57105],"type":"Point"}
}