{
  "type": "Feature",
  "properties": {
    "iso:country":"US",
    "sg:address":"5603 W 79th St Ste 2",
    "sg:city":"Burbank",
    "sg:classifiers":[
        {
            "category":"Shopping",
            "subcategory":"Computers & Home Electronics",
            "type":"Retail Goods"
        }
    ],
    "sg:phone":"+1 708 229 2455",
    "sg:postcode":"60459",
    "sg:province":"IL",
    "wof:name":"Polexport Inc",
    "wof:placetype":"venue"
},
  "geometry": {"coordinates":[-87.761397,41.748655],"type":"Point"}
}