{
  "type": "Feature",
  "properties": {
    "iso:country":"US",
    "sg:address":"179 Appleby Dr",
    "sg:city":"Glendale Heights",
    "sg:classifiers":[
        {
            "category":"Communications",
            "subcategory":"Film & Video Production",
            "type":"Services"
        }
    ],
    "sg:phone":"+1 630 668 3301",
    "sg:postcode":"60139",
    "sg:province":"IL",
    "sg:tags":[
        "motion"
    ],
    "wof:name":"Video Weddings",
    "wof:placetype":"venue"
},
  "geometry": {"coordinates":[-88.099902,41.929984],"type":"Point"}
}