{
  "type": "Feature",
  "properties": {
    "iso:country":"US",
    "sg:address":"5757 W 65th St",
    "sg:city":"Chicago",
    "sg:classifiers":[
        {
            "category":"Manufacturing",
            "subcategory":"Metals",
            "type":"Manufacturing & Wholesale Goods"
        }
    ],
    "sg:phone":"+1 708 458 1220",
    "sg:postcode":"60638",
    "sg:province":"IL",
    "sg:tags":[
        "forging"
    ],
    "sg:website":"http://www.wozniakindustries.com",
    "wof:name":"Commercial Forged Products Div",
    "wof:placetype":"venue"
},
  "geometry": {"coordinates":[-87.765215,41.774329],"type":"Point"}
}