{
  "type": "Feature",
  "properties": {
    "addr:full":"1079 Bucks Pond Rd Monticello IL 61856",
    "addr:housenumber":"1079",
    "addr:postcode":"61856",
    "addr:street":"Bucks Pond Rd",
    "iso:country":"US",
    "sg:address":"1079 Bucks Pond Rd",
    "sg:city":"Monticello",
    "sg:classifiers":[
        {
            "category":"Home & Garden",
            "subcategory":"Home Furnishings",
            "type":"Retail Goods"
        },
        {
            "category":"Building & Trades",
            "subcategory":"Construction",
            "type":"Services"
        },
        {
            "category":"Manufacturing",
            "subcategory":"Building Materials",
            "type":"Manufacturing & Wholesale Goods"
        }
    ],
    "sg:phone":"+1 217 762 7996",
    "sg:postcode":"61856",
    "sg:province":"IL",
    "sg:tags":[
        "industrial",
        "cabinetmakers-commercial",
        "carpenter",
        "cabinet",
        "refacing",
        "resurfacing",
        "maker",
        "cabinets-refinishing",
        "kitchen"
    ],
    "wof:name":"Madden Creek",
    "wof:placetype":"venue"
},
  "geometry": {"coordinates":[-88.544639,40.092551],"type":"Point"}
}