{
  "type": "Feature",
  "properties": {
    "iso:country":"US",
    "sg:address":"500 Hermitage Ave",
    "sg:city":"Deerfield",
    "sg:classifiers":[
        {
            "category":"Professional",
            "subcategory":"Computer Services",
            "type":"Services"
        }
    ],
    "sg:phone":"+1 847 948 8340",
    "sg:postcode":"60015",
    "sg:province":"IL",
    "sg:tags":[
        "programing",
        "custom"
    ],
    "wof:name":"UCE Inc",
    "wof:placetype":"venue"
},
  "geometry": {"coordinates":[-87.843064,42.165085],"type":"Point"}
}