{
  "type": "Feature",
  "properties": {
    "addr:full":"4957 S California Avenue Chicago IL 60632",
    "addr:housenumber":"4957",
    "addr:postcode":"60632",
    "addr:street":"S California Avenue",
    "iso:country":"US",
    "sg:address":"4957 S California Avenue",
    "sg:city":"Chicago",
    "sg:classifiers":[
        {
            "category":"Retail",
            "subcategory":"Auto Repair",
            "type":"Services"
        }
    ],
    "sg:phone":"+1 773 778 0007",
    "sg:postcode":"60632",
    "sg:province":"IL",
    "wof:name":"Herman's Auto Repair",
    "wof:placetype":"venue"
},
  "geometry": {"coordinates":[-87.693861,41.802969],"type":"Point"}
}