{
  "type": "Feature",
  "properties": {
    "iso:country":"US",
    "sg:address":"509 Fitch Rd",
    "sg:city":"Rockford",
    "sg:classifiers":[
        {
            "category":"Building & Trades",
            "subcategory":"Construction",
            "type":"Services"
        }
    ],
    "sg:phone":"+1 815 399 9174",
    "sg:postcode":"61109",
    "sg:province":"IL",
    "sg:tags":[
        "roofing",
        "contractor"
    ],
    "wof:name":"M & B Enterprises Of Rockford",
    "wof:placetype":"venue"
},
  "geometry": {"coordinates":[-89.089083,42.229207],"type":"Point"}
}