{
  "type": "Feature",
  "properties": {
    "addr:full":"131 W Pine St Oneida IL 61467",
    "addr:housenumber":"131",
    "addr:postcode":"61467",
    "addr:street":"W Pine St",
    "iso:country":"US",
    "sg:address":"131 W Pine St",
    "sg:city":"Oneida",
    "sg:classifiers":[
        {
            "category":"Organizations",
            "subcategory":"Community Association",
            "type":"Services"
        }
    ],
    "sg:phone":"+1 309 483 6219",
    "sg:postcode":"61467",
    "sg:province":"IL",
    "sg:tags":[
        "military"
    ],
    "wof:name":"American Legion",
    "wof:placetype":"venue"
},
  "geometry": {"coordinates":[-90.225977,41.076098],"type":"Point"}
}