{
  "type": "Feature",
  "properties": {
    "addr:full":"31679 E 2800 N Rd Dwight IL 60420",
    "addr:housenumber":"31679",
    "addr:postcode":"60420",
    "addr:street":"E 2800 N Rd",
    "iso:country":"US",
    "sg:address":"31679 E 2800 N Rd",
    "sg:city":"Dwight",
    "sg:phone":"+1 815 567 3305",
    "sg:postcode":"60420",
    "sg:province":"IL",
    "sg:tags":[
        "corn",
        "soybean",
        "farmer"
    ],
    "wof:name":"Brady Farm Account",
    "wof:placetype":"venue"
},
  "geometry": {"coordinates":[-88.326212,41.037372],"type":"Point"}
}