{
  "type": "Feature",
  "properties": {
    "iso:country":"US",
    "sg:address":"10338 S Cicero Ave",
    "sg:city":"Oak Lawn",
    "sg:classifiers":[
        {
            "category":"Shopping",
            "subcategory":"Pets & Pet Supplies",
            "type":"Retail Goods"
        }
    ],
    "sg:phone":"+1 708 857 9900",
    "sg:postcode":"60453",
    "sg:province":"IL",
    "sg:tags":[
        "store"
    ],
    "wof:name":"Happiness Is Pets of Oaklawn",
    "wof:placetype":"venue"
},
  "geometry": {"coordinates":[-87.740506,41.704677],"type":"Point"}
}