{
  "type": "Feature",
  "properties": {
    "iso:country":"US",
    "sg:address":"1305 Theodore Dr",
    "sg:city":"Champaign",
    "sg:classifiers":[
        {
            "category":"Shopping",
            "subcategory":"Computers & Home Electronics",
            "type":"Retail Goods"
        }
    ],
    "sg:phone":"+1 217 355 0524",
    "sg:postcode":"61821",
    "sg:province":"IL",
    "sg:tags":[
        "software"
    ],
    "sg:website":"www.abj-inc.com",
    "wof:name":"ABJ Assoc Inc",
    "wof:placetype":"venue"
},
  "geometry": {"coordinates":[-88.269,40.091257],"type":"Point"}
}