{
  "type": "Feature",
  "properties": {
    "addr:full":"113 W Van Alstyne St Cullom IL 60929",
    "addr:housenumber":"113",
    "addr:postcode":"60929",
    "addr:street":"W Van Alstyne St",
    "iso:country":"US",
    "sg:address":"113 W Van Alstyne St",
    "sg:city":"Cullom",
    "sg:classifiers":[
        {
            "category":"Organizations",
            "subcategory":"Religious Organization",
            "type":"Services"
        }
    ],
    "sg:phone":"+1 815 689 2367",
    "sg:postcode":"60929",
    "sg:province":"IL",
    "sg:tags":[
        "church"
    ],
    "wof:name":"St John Catholic Church",
    "wof:placetype":"venue"
},
  "geometry": {"coordinates":[-88.26799699999999,40.881335],"type":"Point"}
}