{
  "type": "Feature",
  "properties": {
    "addr:full":"1516 N Lake Shore Dr Fl 3 Chicago IL 60610",
    "addr:housenumber":"1516;3",
    "addr:postcode":"60610",
    "addr:street":"N Lake Shore Dr",
    "iso:country":"US",
    "sg:address":"1516 N Lake Shore Dr Fl 3",
    "sg:city":"Chicago",
    "sg:classifiers":[
        {
            "category":"Education",
            "subcategory":"School",
            "type":"Public Place"
        },
        {
            "category":"Education",
            "subcategory":"University",
            "type":"Public Place"
        }
    ],
    "sg:phone":"+1 312 642 3557",
    "sg:postcode":"60610",
    "sg:province":"IL",
    "sg:tags":[
        "high",
        "middle",
        "college",
        "elementary"
    ],
    "wof:name":"International College of Surgeons",
    "wof:placetype":"venue"
},
  "geometry": {"coordinates":[-87.626362,41.90996],"type":"Point"}
}