{
  "type": "Feature",
  "properties": {
    "addr:full":"165 N Canal St Apt 1218 Chicago IL 60606",
    "addr:housenumber":"165;1218",
    "addr:postcode":"60606",
    "addr:street":"N Canal St Apt",
    "iso:country":"US",
    "sg:address":"165 N Canal St Apt 1218",
    "sg:city":"Chicago",
    "sg:classifiers":[
        {
            "category":"Education",
            "subcategory":"Vocational School",
            "type":"Public Place"
        },
        {
            "category":"Professional",
            "subcategory":"Computer Services",
            "type":"Services"
        }
    ],
    "sg:phone":"+1 312 970 0205",
    "sg:postcode":"60606",
    "sg:province":"IL",
    "sg:tags":[
        "consultant",
        "designer",
        "system",
        "business"
    ],
    "wof:name":"Vetta Solutions, Incorporated",
    "wof:placetype":"venue"
},
  "geometry": {"coordinates":[-87.639803,41.884828],"type":"Point"}
}