{
  "type": "Feature",
  "properties": {
    "addr:full":"6012 Golfview Dr Gurnee IL 60031",
    "addr:housenumber":"6012",
    "addr:postcode":"60031",
    "addr:street":"Golfview Dr",
    "iso:country":"US",
    "sg:address":"6012 Golfview Dr",
    "sg:city":"Gurnee",
    "sg:classifiers":[
        {
            "category":"Wholesale",
            "subcategory":"Painting Supplies",
            "type":"Manufacturing & Wholesale Goods"
        },
        {
            "category":"Autos & Motor Vehicles",
            "subcategory":"Fuel & Gas Station",
            "type":"Retail Goods"
        }
    ],
    "sg:phone":"+1 847 573 1845",
    "sg:postcode":"60031",
    "sg:province":"IL",
    "sg:tags":[
        "paint-wholesale",
        "color",
        "pigment",
        "manufacturer"
    ],
    "wof:name":"Roads & Leads Inc",
    "wof:placetype":"venue"
},
  "geometry": {"coordinates":[-87.956435,42.349189],"type":"Point"}
}