{
  "type": "Feature",
  "properties": {
    "addr:full":"28775 Malta Rd Kirkland IL 60146",
    "addr:postcode":"28775;60146",
    "addr:street":"Malta Rd",
    "iso:country":"US",
    "sg:address":"28775 Malta Rd",
    "sg:city":"Kirkland",
    "sg:classifiers":[
        {
            "category":"Farming",
            "subcategory":"Farm",
            "type":"Manufacturing & Wholesale Goods"
        }
    ],
    "sg:phone":"+1 815 522 4448",
    "sg:postcode":"60146",
    "sg:province":"IL",
    "sg:tags":[
        "crop",
        "general"
    ],
    "wof:name":"Richard Tindall",
    "wof:placetype":"venue"
},
  "geometry": {"coordinates":[-88.863861,42.053943],"type":"Point"}
}