{
  "type": "Feature",
  "properties": {
    "iso:country":"US",
    "sg:address":"15 S 15th St",
    "sg:city":"East St Louis",
    "sg:classifiers":[
        {
            "category":"Personal",
            "subcategory":"Beauty Salon",
            "type":"Services"
        }
    ],
    "sg:phone":"+1 618 271 2564",
    "sg:postcode":"62207",
    "sg:province":"IL",
    "wof:name":"Studio Fifteen Salon Of Hair",
    "wof:placetype":"venue"
},
  "geometry": {"coordinates":[-90.150802,38.614576],"type":"Point"}
}