{
  "type": "Feature",
  "properties": {
    "iso:country":"US",
    "sg:address":"560 S Waukegan Rd",
    "sg:city":"Deerfield",
    "sg:classifiers":[
        {
            "category":"Restaurant",
            "type":"Food & Drink"
        }
    ],
    "sg:phone":"+1   ",
    "sg:postcode":"60015",
    "sg:province":"IL",
    "sg:tags":[
        "family"
    ],
    "wof:name":"Bakers Square 020186",
    "wof:placetype":"venue"
},
  "geometry": {"coordinates":[-87.840006,42.159422],"type":"Point"}
}