{
  "type": "Feature",
  "properties": {
    "iso:country":"US",
    "sg:address":"734 Ridge Rd",
    "sg:city":"Homewood",
    "sg:classifiers":[
        {
            "category":"Real Estate",
            "subcategory":"Real Estate Agent",
            "type":"Services"
        }
    ],
    "sg:phone":"+1 708 249 7800",
    "sg:postcode":"60430",
    "sg:province":"IL",
    "sg:website":"www.centurionrealty.com",
    "wof:name":"Centurion Realty & Estates",
    "wof:placetype":"venue"
},
  "geometry": {"coordinates":[-87.63654200000001,41.562794],"type":"Point"}
}