{
  "type": "Feature",
  "properties": {
    "iso:country":"US",
    "sg:address":"3353 Dempster St",
    "sg:city":"Skokie",
    "sg:classifiers":[
        {
            "category":"Deli",
            "type":"Food & Drink"
        }
    ],
    "sg:menulink":"http://www.allmenus.com/il/niles/237467-kens-diner--grille/menu/",
    "sg:phone":"+1 847 679 2850",
    "sg:postcode":"60076",
    "sg:province":"IL",
    "sg:tags":[
        "american"
    ],
    "wof:name":"Ken's Diner & Grille",
    "wof:placetype":"venue"
},
  "geometry": {"coordinates":[-87.71306300000001,42.040827],"type":"Point"}
}