{
  "type": "Feature",
  "properties": {
    "iso:country":"US",
    "sg:address":"1410 S Banker St",
    "sg:city":"Effingham",
    "sg:classifiers":[
        {
            "category":"Shopping",
            "subcategory":"Tobacco",
            "type":"Retail Goods"
        }
    ],
    "sg:phone":"+1 217 342 3808",
    "sg:postcode":"62401",
    "sg:province":"IL",
    "sg:tags":[
        "cigarette",
        "cigar",
        "dealer"
    ],
    "wof:name":"Discount Tobacco Inc",
    "wof:placetype":"venue"
},
  "geometry": {"coordinates":[-88.546862,39.110041],"type":"Point"}
}