{
  "type": "Feature",
  "properties": {
    "addr:full":"2704 Downing Ct Aurora IL 60502",
    "addr:housenumber":"2704",
    "addr:postcode":"60502",
    "addr:street":"Downing Ct",
    "iso:country":"US",
    "sg:address":"2704 Downing Ct",
    "sg:city":"Aurora",
    "sg:classifiers":[
        {
            "category":"Education",
            "subcategory":"School",
            "type":"Public Place"
        }
    ],
    "sg:phone":"+1 630 236 8544",
    "sg:postcode":"60502",
    "sg:province":"IL",
    "wof:name":"Allinea Systems",
    "wof:placetype":"venue"
},
  "geometry": {"coordinates":[-88.250347,41.785821],"type":"Point"}
}