{
  "type": "Feature",
  "properties": {
    "iso:country":"US",
    "sg:address":"715 N Independence Blvd",
    "sg:city":"Romeoville",
    "sg:classifiers":[
        {
            "category":"Building & Trades",
            "subcategory":"Landscaping Services",
            "type":"Services"
        }
    ],
    "sg:phone":"+1 630 759 8100",
    "sg:postcode":"60446",
    "sg:province":"IL",
    "sg:tags":[
        "landscape",
        "contractor"
    ],
    "wof:name":"Wingren's Landscape Mntnc Inc",
    "wof:placetype":"venue"
},
  "geometry": {"coordinates":[-88.08044200000001,41.652212],"type":"Point"}
}