{
  "type": "Feature",
  "properties": {
    "iso:country":"US",
    "sg:address":"1911 W Chicago Ave",
    "sg:city":"Chicago",
    "sg:classifiers":[
        {
            "category":"Home & Garden",
            "subcategory":"Furniture",
            "type":"Retail Goods"
        }
    ],
    "sg:phone":"+1 312 666 1017",
    "sg:postcode":"60622",
    "sg:province":"IL",
    "sg:tags":[
        "store"
    ],
    "wof:name":"Beltran Furniture",
    "wof:placetype":"venue"
},
  "geometry": {"coordinates":[-87.675003,41.895802],"type":"Point"}
}