{
  "type": "Feature",
  "properties": {
    "iso:country":"US",
    "sg:address":"723 Station Xing",
    "sg:city":"Waterloo",
    "sg:classifiers":[
        {
            "category":"Health Services",
            "subcategory":"Clinic",
            "type":"Services"
        }
    ],
    "sg:phone":"+1 618 939 1546",
    "sg:postcode":"62298",
    "sg:province":"IL",
    "sg:tags":[
        "welfare"
    ],
    "wof:name":"Red Bud Regional Family Health Center",
    "wof:placetype":"venue"
},
  "geometry": {"coordinates":[-90.161616,38.340702],"type":"Point"}
}