{
  "type": "Feature",
  "properties": {
    "addr:full":"5555 S Woodlawn Avenue Chicago IL 60637",
    "addr:housenumber":"5555",
    "addr:postcode":"60637",
    "addr:street":"S Woodlawn Avenue",
    "iso:country":"US",
    "sg:address":"5555 S Woodlawn Avenue",
    "sg:city":"Chicago",
    "sg:classifiers":[
        {
            "category":"Education",
            "subcategory":"University",
            "type":"Public Place"
        }
    ],
    "sg:phone":"+1 773 702 2150",
    "sg:postcode":"60637",
    "sg:province":"IL",
    "sg:tags":[
        "college"
    ],
    "sg:website":"www.uchicago.edu",
    "wof:name":"University of Chicago",
    "wof:placetype":"venue"
},
  "geometry": {"coordinates":[-87.596177,41.79327],"type":"Point"}
}