{
  "type": "Feature",
  "properties": {
    "iso:country":"US",
    "sg:address":"950 Northbrook Ave",
    "sg:city":"Northbrook",
    "sg:classifiers":[
        {
            "category":"Education",
            "subcategory":"Special Training",
            "type":"Public Place"
        }
    ],
    "sg:phone":"+1 847 714 9002",
    "sg:postcode":"60062",
    "sg:province":"IL",
    "sg:tags":[
        "educational"
    ],
    "wof:name":"Karis Larson",
    "wof:placetype":"venue"
},
  "geometry": {"coordinates":[-87.797456,42.135826],"type":"Point"}
}