{
  "type": "Feature",
  "properties": {
    "iso:country":"US",
    "sg:address":"349 Brentwood Pl",
    "sg:city":"Downers Grove",
    "sg:classifiers":[
        {
            "category":"Real Estate",
            "subcategory":"Real Estate Operator",
            "type":"Services"
        }
    ],
    "sg:phone":"+1 630 852 4024",
    "sg:postcode":"60515",
    "sg:province":"IL",
    "sg:tags":[
        "building",
        "nonresidential"
    ],
    "wof:name":"Franmar Properties Inc",
    "wof:placetype":"venue"
},
  "geometry": {"coordinates":[-87.994893,41.81569],"type":"Point"}
}