{
  "type": "Feature",
  "properties": {
    "addr:full":"18250 Harwood Ave Homewood IL 60430",
    "addr:housenumber":"18250",
    "addr:postcode":"60430",
    "addr:street":"Harwood Ave",
    "iso:country":"US",
    "sg:address":"18250 Harwood Ave",
    "sg:city":"Homewood",
    "sg:classifiers":[
        {
            "category":"Professional",
            "subcategory":"Business Services",
            "type":"Services"
        }
    ],
    "sg:phone":"+1 708 798 4221",
    "sg:postcode":"60430",
    "sg:province":"IL",
    "wof:name":"IDM Enterprises LLC",
    "wof:placetype":"venue"
},
  "geometry": {"coordinates":[-87.668848,41.558679],"type":"Point"}
}