{
  "type": "Feature",
  "properties": {
    "addr:full":"12255 S 80th Ave Ste 202 Palos Heights IL 60463",
    "addr:housenumber":"12255",
    "addr:postcode":"60463",
    "addr:street":"S 80Th Ave Ste 202",
    "iso:country":"US",
    "sg:address":"12255 S 80th Ave Ste 202",
    "sg:city":"Palos Heights",
    "sg:classifiers":[
        {
            "category":"Health Services",
            "subcategory":"Doctor",
            "type":"Services"
        }
    ],
    "sg:phone":"+1 708 361 8120",
    "sg:postcode":"60463",
    "sg:province":"IL",
    "wof:name":"Professional Health Association Ltd",
    "wof:placetype":"venue"
},
  "geometry": {"coordinates":[-87.815766,41.668448],"type":"Point"}
}