{
  "type": "Feature",
  "properties": {
    "iso:country":"US",
    "sg:address":"1028 Donna Dr",
    "sg:city":"Belvidere",
    "sg:classifiers":[
        {
            "category":"Building & Trades",
            "subcategory":"Construction",
            "type":"Services"
        }
    ],
    "sg:phone":"+1 815 885 3854",
    "sg:postcode":"61008",
    "sg:province":"IL",
    "sg:tags":[
        "house"
    ],
    "wof:name":"JG Home Repair & Remodel",
    "wof:placetype":"venue"
},
  "geometry": {"coordinates":[-88.91589,42.322568],"type":"Point"}
}