{
  "type": "Feature",
  "properties": {
    "iso:country":"US",
    "sg:address":"1146 E Cambria Ln S",
    "sg:city":"Lombard",
    "sg:classifiers":[
        {
            "category":"Professional",
            "subcategory":"Art Services",
            "type":"Services"
        }
    ],
    "sg:phone":"+1 630 519 3681",
    "sg:postcode":"60148",
    "sg:province":"IL",
    "sg:tags":[
        "interior",
        "designer",
        "decorator"
    ],
    "wof:name":"Naina Interiors",
    "wof:placetype":"venue"
},
  "geometry": {"coordinates":[-87.98902699999999,41.870071],"type":"Point"}
}