{
  "type": "Feature",
  "properties": {
    "iso:country":"US",
    "sg:address":"493 Red Rock Pt",
    "sg:city":"Lakemoor",
    "sg:classifiers":[
        {
            "category":"Building & Trades",
            "subcategory":"Landscaping Services",
            "type":"Services"
        }
    ],
    "sg:phone":"+1 815 344 8989",
    "sg:postcode":"60051",
    "sg:province":"IL",
    "sg:tags":[
        "landscape",
        "contractor"
    ],
    "wof:name":"Windhauser Landscaping Inc",
    "wof:placetype":"venue"
},
  "geometry": {"coordinates":[-88.20054500000001,42.335556],"type":"Point"}
}