{
  "type": "Feature",
  "properties": {
    "iso:country":"US",
    "sg:address":"9032 N 2nd St",
    "sg:city":"Machesney Park",
    "sg:classifiers":[
        {
            "category":"Restaurant",
            "type":"Food & Drink"
        }
    ],
    "sg:phone":"+1   ",
    "sg:postcode":"61115",
    "sg:province":"IL",
    "sg:tags":[
        "eating"
    ],
    "wof:name":"Curly S",
    "wof:placetype":"venue"
},
  "geometry": {"coordinates":[-89.046592,42.353176],"type":"Point"}
}