{
  "type": "Feature",
  "properties": {
    "addr:full":"70 N 4th St Breese IL 62230",
    "addr:housenumber":"70",
    "addr:postcode":"62230",
    "addr:street":"N 4Th St",
    "iso:country":"US",
    "sg:address":"70 N 4th St",
    "sg:city":"Breese",
    "sg:classifiers":[
        {
            "category":"Retail",
            "subcategory":"Auto Rental",
            "type":"Services"
        }
    ],
    "sg:phone":"+1 618 526 8410",
    "sg:postcode":"62230",
    "sg:province":"IL",
    "sg:tags":[
        "renting",
        "truck",
        "leasing"
    ],
    "wof:name":"U-Haul Co",
    "wof:placetype":"venue"
},
  "geometry": {"coordinates":[-89.534736,38.610918],"type":"Point"}
}