{
  "type": "Feature",
  "properties": {
    "iso:country":"US",
    "sg:address":"1655 Eastwood Dr",
    "sg:city":"Aurora",
    "sg:classifiers":[
        {
            "category":"Manufacturing",
            "subcategory":"Chemicals & Compounds",
            "type":"Manufacturing & Wholesale Goods"
        },
        {
            "category":"Shopping",
            "subcategory":"Department Store",
            "type":"Retail Goods"
        },
        {
            "category":"Building & Trades",
            "subcategory":"Cleaning & Sanitation",
            "type":"Services"
        }
    ],
    "sg:phone":"+1 630 264 6001",
    "sg:postcode":"60506",
    "sg:province":"IL",
    "sg:tags":[
        "cleaner",
        "supply",
        "house",
        "equipment",
        "chemicals-wholesale",
        "manufacturer"
    ],
    "sg:website":"http://www.deltamedical.net",
    "wof:name":"Delta Products Group Inc",
    "wof:placetype":"venue"
},
  "geometry": {"coordinates":[-88.336731,41.790605],"type":"Point"}
}