{
  "type": "Feature",
  "properties": {
    "addr:full":"130 E Main St Moweaqua IL 62550",
    "addr:housenumber":"130",
    "addr:postcode":"62550",
    "addr:street":"E Main St",
    "iso:country":"US",
    "sg:address":"130 E Main St",
    "sg:city":"Moweaqua",
    "sg:classifiers":[
        {
            "category":"Health Services",
            "subcategory":"Dentist",
            "type":"Services"
        }
    ],
    "sg:phone":"+1 217 768 3898",
    "sg:postcode":"62550",
    "sg:province":"IL",
    "sg:tags":[
        "dental",
        "clinic"
    ],
    "wof:name":"Moweaqua Dental Office",
    "wof:placetype":"venue"
},
  "geometry": {"coordinates":[-89.020366,39.624977],"type":"Point"}
}