{
  "type": "Feature",
  "properties": {
    "addr:full":"1930 N Linden St Normal IL 61761",
    "addr:housenumber":"1930",
    "addr:postcode":"61761",
    "addr:street":"N Linden St",
    "iso:country":"US",
    "sg:address":"1930 N Linden St",
    "sg:city":"Normal",
    "sg:classifiers":[
        {
            "category":"Restaurant",
            "type":"Food & Drink"
        }
    ],
    "sg:menulink":"http://www.allmenus.com/il/normal/226364-caseys-general-store/menu/",
    "sg:phone":"+1 309 451 8256",
    "sg:postcode":"61761",
    "sg:province":"IL",
    "sg:tags":[
        "american",
        "pizza"
    ],
    "wof:name":"Casey's General Store",
    "wof:placetype":"venue"
},
  "geometry": {"coordinates":[-88.983541,40.539758],"type":"Point"}
}