{
  "type": "Feature",
  "properties": {
    "iso:country":"US",
    "sg:address":"496 W Saint Charles Rd",
    "sg:city":"Elmhurst",
    "sg:classifiers":[
        {
            "category":"Shopping",
            "subcategory":"Catalog Store",
            "type":"Retail Goods"
        }
    ],
    "sg:phone":"+1   ",
    "sg:postcode":"60126",
    "sg:province":"IL",
    "sg:tags":[
        "mail",
        "house"
    ],
    "wof:name":"Harris Foods",
    "wof:placetype":"venue"
},
  "geometry": {"coordinates":[-87.959008,41.890178],"type":"Point"}
}