{
  "type": "Feature",
  "properties": {
    "iso:country":"US",
    "sg:address":"811 Clary St",
    "sg:city":"Beloit",
    "sg:classifiers":[
        {
            "category":"Organizations",
            "subcategory":"Religious Organization",
            "type":"Services"
        }
    ],
    "sg:phone":"+1 608 365 5858",
    "sg:postcode":"53511",
    "sg:province":"IL",
    "wof:name":"Quaker Meeting Of Beloit",
    "wof:placetype":"venue"
},
  "geometry": {"coordinates":[-89.0269,42.506435],"type":"Point"}
}