{
  "type": "Feature",
  "properties": {
    "iso:country":"US",
    "sg:address":"9011 S Ashland Ave",
    "sg:city":"Chicago",
    "sg:classifiers":[
        {
            "category":"Home & Garden",
            "subcategory":"Furniture",
            "type":"Retail Goods"
        }
    ],
    "sg:phone":"+1 773 840 4600",
    "sg:postcode":"60620",
    "sg:province":"IL",
    "sg:tags":[
        "store"
    ],
    "wof:name":"Super Furniture",
    "wof:placetype":"venue"
},
  "geometry": {"coordinates":[-87.66266,41.730131],"type":"Point"}
}