{
  "type": "Feature",
  "properties": {
    "iso:country":"US",
    "sg:address":"6 Country Ln",
    "sg:city":"Columbia",
    "sg:classifiers":[
        {
            "category":"Building & Trades",
            "subcategory":"Construction",
            "type":"Services"
        }
    ],
    "sg:phone":"+1 618 939 5094",
    "sg:postcode":"62236",
    "sg:province":"IL",
    "sg:tags":[
        "carpenter"
    ],
    "wof:name":"Fauss Custom Carpentry Inc",
    "wof:placetype":"venue"
},
  "geometry": {"coordinates":[-90.229208,38.402235],"type":"Point"}
}