{
  "type": "Feature",
  "properties": {
    "iso:country":"US",
    "sg:address":"46 Sterling Cir",
    "sg:city":"Wheaton",
    "sg:classifiers":[
        {
            "category":"Professional",
            "type":"Services"
        }
    ],
    "sg:phone":"+1 630 260 9496",
    "sg:postcode":"60187",
    "sg:province":"IL",
    "wof:name":"Photo Albums On Dvd",
    "wof:placetype":"venue"
},
  "geometry": {"coordinates":[-88.098209,41.834865],"type":"Point"}
}