{
  "type": "Feature",
  "properties": {
    "iso:country":"US",
    "sg:address":"130 May Mart Dr",
    "sg:city":"Rochelle",
    "sg:classifiers":[
        {
            "category":"Home & Garden",
            "subcategory":"Building Materials",
            "type":"Retail Goods"
        }
    ],
    "sg:phone":"+1 815 562 7150",
    "sg:postcode":"61068",
    "sg:province":"IL",
    "sg:tags":[
        "wallpaper"
    ],
    "wof:name":"Floor To Ceiling Store",
    "wof:placetype":"venue"
},
  "geometry": {"coordinates":[-89.06144399999999,41.934023],"type":"Point"}
}