{
  "type": "Feature",
  "properties": {
    "addr:full":"10513 S Western Avenue Chicago IL 60643",
    "addr:housenumber":"10513",
    "addr:postcode":"60643",
    "addr:street":"S Western Avenue",
    "iso:country":"US",
    "sg:address":"10513 S Western Avenue",
    "sg:city":"Chicago",
    "sg:classifiers":[
        {
            "category":"Shopping",
            "subcategory":"Tobacco",
            "type":"Retail Goods"
        }
    ],
    "sg:phone":"+1 773 239 3264",
    "sg:postcode":"60643",
    "sg:province":"IL",
    "sg:tags":[
        "shop"
    ],
    "wof:name":"Beverly Cigar Company",
    "wof:placetype":"venue"
},
  "geometry": {"coordinates":[-87.68121499999999,41.70201],"type":"Point"}
}