{
  "type": "Feature",
  "properties": {
    "addr:full":"3931 N Elston Ave New Rock Theater Chicago IL 60618",
    "addr:housenumber":"3931",
    "addr:postcode":"60618",
    "addr:street":"N Elston Ave",
    "iso:country":"US",
    "sg:address":"3931 N Elston Ave New Rock Theater",
    "sg:city":"Chicago",
    "sg:classifiers":[
        {
            "category":"Arts & Performance",
            "subcategory":"Comedy Club",
            "type":"Entertainment"
        }
    ],
    "sg:postcode":"60618",
    "sg:province":"IL",
    "sg:website":"www.pointbreaklive.com/pointbrea...",
    "wof:name":"Point Break: Live",
    "wof:placetype":"venue"
},
  "geometry": {"coordinates":[-87.717294,41.952768],"type":"Point"}
}