{
  "type": "Feature",
  "properties": {
    "iso:country":"US",
    "sg:address":"1755 Marketview Dr",
    "sg:city":"Yorkville",
    "sg:classifiers":[
        {
            "category":"Real Estate",
            "subcategory":"Real Estate Agent",
            "type":"Services"
        }
    ],
    "sg:phone":"+1 888 553 0777",
    "sg:postcode":"60560",
    "sg:province":"IL",
    "wof:name":"Remax Great American",
    "wof:placetype":"venue"
},
  "geometry": {"coordinates":[-88.440178,41.66285],"type":"Point"}
}