{
  "type": "Feature",
  "properties": {
    "iso:country":"US",
    "sg:address":"2615 Washington St",
    "sg:city":"Waukegan",
    "sg:classifiers":[
        {
            "category":"Social Services",
            "subcategory":"Child Care",
            "type":"Services"
        },
        {
            "category":"Education",
            "subcategory":"School",
            "type":"Public Place"
        }
    ],
    "sg:phone":"+1 847 625 6130",
    "sg:postcode":"60085",
    "sg:province":"IL",
    "sg:tags":[
        "day"
    ],
    "wof:name":"Connections Day School Inc",
    "wof:placetype":"venue"
},
  "geometry": {"coordinates":[-87.866378,42.359277],"type":"Point"}
}