{
  "type": "Feature",
  "properties": {
    "iso:country":"US",
    "sg:address":"17 E Taylor St",
    "sg:city":"Champaign",
    "sg:classifiers":[
        {
            "category":"Real Estate",
            "subcategory":"Architect",
            "type":"Services"
        }
    ],
    "sg:phone":"+1 217 356 9606",
    "sg:postcode":"61820",
    "sg:province":"IL",
    "sg:website":"www.bldd.com",
    "wof:name":"Bldd Architects Inc",
    "wof:placetype":"venue"
},
  "geometry": {"coordinates":[-88.242864,40.117111],"type":"Point"}
}