{
  "type": "Feature",
  "properties": {
    "iso:country":"US",
    "sg:address":"1351 S Main St",
    "sg:city":"Altamont",
    "sg:classifiers":[
        {
            "category":"Place Of Worship",
            "subcategory":"Church",
            "type":"Public Place"
        },
        {
            "category":"Place Of Worship",
            "type":"Public Place"
        }
    ],
    "sg:phone":"+1 618 483 6018",
    "sg:postcode":"62411",
    "sg:province":"IL",
    "sg:tags":[
        "churches-interdenominational",
        "churches-various",
        "denomination",
        "churches-reformed",
        "churches-christian-reformed"
    ],
    "wof:name":"Christian Altamont Church",
    "wof:placetype":"venue"
},
  "geometry": {"coordinates":[-88.747995,39.048666],"type":"Point"}
}