{
  "type": "Feature",
  "properties": {
    "iso:country":"US",
    "sg:address":"15507 S Route 59",
    "sg:city":"Plainfield",
    "sg:classifiers":[
        {
            "category":"Personal",
            "subcategory":"Beauty Salon",
            "type":"Services"
        },
        {
            "category":"Personal",
            "subcategory":"Nail Salon",
            "type":"Services"
        }
    ],
    "sg:phone":"+1 815 439 9350",
    "sg:postcode":"60544",
    "sg:province":"IL",
    "sg:tags":[
        "wig",
        "hair",
        "piece"
    ],
    "wof:name":"A'Colsha Hair Salon",
    "wof:placetype":"venue"
},
  "geometry": {"coordinates":[-88.201628,41.594825],"type":"Point"}
}