{
  "type": "Feature",
  "properties": {
    "iso:country":"US",
    "sg:address":"123 N 3rd St",
    "sg:city":"Hanna City",
    "sg:classifiers":[
        {
            "category":"Building & Trades",
            "subcategory":"Construction",
            "type":"Services"
        }
    ],
    "sg:phone":"+1 309 565 7101",
    "sg:postcode":"61536",
    "sg:province":"IL",
    "sg:tags":[
        "general",
        "contractor"
    ],
    "wof:name":"Cutting Edge Construction",
    "wof:placetype":"venue"
},
  "geometry": {"coordinates":[-89.798775,40.69224],"type":"Point"}
}