{
  "type": "Feature",
  "properties": {
    "addr:full":"123 N 3rd St Hanna City IL 61536",
    "addr:housenumber":"123",
    "addr:postcode":"61536",
    "addr:street":"N 3Rd St",
    "iso:country":"US",
    "sg:address":"123 N 3rd St",
    "sg:city":"Hanna City",
    "sg:classifiers":[
        {
            "category":"Building & Trades",
            "subcategory":"Construction",
            "type":"Services"
        }
    ],
    "sg:phone":"+1 309 565 7101",
    "sg:postcode":"61536",
    "sg:province":"IL",
    "sg:tags":[
        "general",
        "contractor"
    ],
    "wof:name":"Cutting Edge Construction",
    "wof:placetype":"venue"
},
  "geometry": {"coordinates":[-89.79877500000001,40.69224],"type":"Point"}
}