{
  "type": "Feature",
  "properties": {
    "iso:country":"US",
    "sg:address":"2090 Pearl St",
    "sg:city":"Belvidere",
    "sg:classifiers":[
        {
            "category":"Government",
            "subcategory":"Office",
            "type":"Public Place"
        }
    ],
    "sg:phone":"+1 815 544 3484",
    "sg:postcode":"61008",
    "sg:province":"IL",
    "sg:tags":[
        "state",
        "resource"
    ],
    "wof:name":"Boone County Public Aid",
    "wof:placetype":"venue"
},
  "geometry": {"coordinates":[-88.841668,42.237127],"type":"Point"}
}