{
  "type": "Feature",
  "properties": {
    "addr:full":"10206 Clow Creek Dr Plainfield IL 60585",
    "addr:housenumber":"10206",
    "addr:postcode":"60585",
    "addr:street":"Clow Creek Dr",
    "iso:country":"US",
    "sg:address":"10206 Clow Creek Dr",
    "sg:city":"Plainfield",
    "sg:classifiers":[
        {
            "category":"Building & Trades",
            "subcategory":"Construction",
            "type":"Services"
        }
    ],
    "sg:phone":"+1 630 922 9714",
    "sg:postcode":"60585",
    "sg:province":"IL",
    "sg:tags":[
        "bathroom",
        "painting",
        "contractor",
        "planning",
        "remodeling",
        "kitchen"
    ],
    "wof:name":"Artisan Kitchen Cabinet Refinishers",
    "wof:placetype":"venue"
},
  "geometry": {"coordinates":[-88.237272,41.696568],"type":"Point"}
}