{
  "type": "Feature",
  "properties": {
    "addr:full":"1857 N Harlem Ave Chicago IL 60707",
    "addr:housenumber":"1857",
    "addr:postcode":"60707",
    "addr:street":"N Harlem Ave",
    "iso:country":"US",
    "sg:address":"1857 N Harlem Ave",
    "sg:city":"Chicago",
    "sg:classifiers":[
        {
            "category":"Retail",
            "subcategory":"Funeral Services",
            "type":"Services"
        }
    ],
    "sg:phone":"+1 773 889 1700",
    "sg:postcode":"60707",
    "sg:province":"IL",
    "sg:tags":[
        "cemetery"
    ],
    "wof:name":"Salerno's Funeral Home",
    "wof:placetype":"venue"
},
  "geometry": {"coordinates":[-87.80590100000001,41.913799],"type":"Point"}
}