{
  "type": "Feature",
  "properties": {
    "addr:full":"1500 N Mason Avenue Chicago IL 60651",
    "addr:housenumber":"1500",
    "addr:postcode":"60651",
    "addr:street":"N Mason Avenue",
    "iso:country":"US",
    "sg:address":"1500 N Mason Avenue",
    "sg:city":"Chicago",
    "sg:classifiers":[
        {
            "category":"Education",
            "subcategory":"School",
            "type":"Public Place"
        }
    ],
    "sg:phone":"+1 773 237 1930",
    "sg:postcode":"60651",
    "sg:province":"IL",
    "sg:website":"www.lssi.org",
    "wof:name":"Lutheran Social Services of Illinois",
    "wof:placetype":"venue"
},
  "geometry": {"coordinates":[-87.77416700000001,41.907701],"type":"Point"}
}