{
  "type": "Feature",
  "properties": {
    "iso:country":"US",
    "sg:address":"1247 Lakeside Dr",
    "sg:city":"Romeoville",
    "sg:classifiers":[
        {
            "category":"Transit Center",
            "subcategory":"Freight",
            "type":"Transportation"
        },
        {
            "category":"Freight",
            "type":"Transportation"
        }
    ],
    "sg:phone":"+1 630 633 5222",
    "sg:postcode":"60446",
    "sg:province":"IL",
    "sg:tags":[
        "local",
        "trucking-motor",
        "trucking"
    ],
    "wof:name":"Mc Dowell Truck Company",
    "wof:placetype":"venue"
},
  "geometry": {"coordinates":[-88.07272,41.665048],"type":"Point"}
}