{
  "type": "Feature",
  "properties": {
    "addr:full":"250 W Lake St Barrington IL 60010",
    "addr:housenumber":"250",
    "addr:postcode":"60010",
    "addr:street":"W Lake St",
    "iso:country":"US",
    "sg:address":"250 W Lake St",
    "sg:city":"Barrington",
    "sg:classifiers":[
        {
            "category":"Professional",
            "subcategory":"Employment Agencies",
            "type":"Services"
        }
    ],
    "sg:phone":"+1 847 381 3387",
    "sg:postcode":"60010",
    "sg:province":"IL",
    "sg:tags":[
        "help",
        "supply"
    ],
    "wof:name":"Staffing Funding Consultants",
    "wof:placetype":"venue"
},
  "geometry": {"coordinates":[-88.137929,42.152477],"type":"Point"}
}