{
  "type": "Feature",
  "properties": {
    "addr:full":"9447 W Lincoln Hwy Frankfort IL 60423",
    "addr:housenumber":"9447",
    "addr:postcode":"60423",
    "addr:street":"W Lincoln Hwy",
    "iso:country":"US",
    "sg:address":"9447 W Lincoln Hwy",
    "sg:city":"Frankfort",
    "sg:classifiers":[
        {
            "category":"Autos & Motor Vehicles",
            "subcategory":"Automobile Sales",
            "type":"Retail Goods"
        }
    ],
    "sg:phone":"+1 815 469 6530",
    "sg:postcode":"60423",
    "sg:province":"IL",
    "sg:tags":[
        "car",
        "dealer"
    ],
    "wof:name":"Frankfort Auto Haus",
    "wof:placetype":"venue"
},
  "geometry": {"coordinates":[-87.843746,41.506525],"type":"Point"}
}