{
  "type": "Feature",
  "properties": {
    "iso:country":"US",
    "sg:address":"188 S Clinton Ave",
    "sg:city":"Bradley",
    "sg:classifiers":[
        {
            "category":"Social Services",
            "subcategory":"Child Care",
            "type":"Services"
        }
    ],
    "sg:phone":"+1 815 939 9744",
    "sg:postcode":"60915",
    "sg:province":"IL",
    "sg:tags":[
        "kindergarten",
        "academic",
        "school"
    ],
    "wof:name":"Children's Corner",
    "wof:placetype":"venue"
},
  "geometry": {"coordinates":[-87.855008,41.1442],"type":"Point"}
}