{
  "type": "Feature",
  "properties": {
    "iso:country":"US",
    "sg:address":"496 Fox Valley Ctr",
    "sg:city":"Aurora",
    "sg:classifiers":[
        {
            "category":"Shopping",
            "subcategory":"Pets & Pet Supplies",
            "type":"Retail Goods"
        },
        {
            "category":"Retail",
            "subcategory":"Veterinary Services",
            "type":"Services"
        }
    ],
    "sg:phone":"+1 630 499 8914",
    "sg:postcode":"60504",
    "sg:province":"IL",
    "sg:tags":[
        "specialty"
    ],
    "wof:name":"Just Dogs Gourmet",
    "wof:placetype":"venue"
},
  "geometry": {"coordinates":[-88.209261,41.759662],"type":"Point"}
}