{
  "type": "Feature",
  "properties": {
    "iso:country":"US",
    "sg:address":"123 Green Park Dr",
    "sg:city":"Collinsville",
    "sg:classifiers":[
        {
            "category":"Building & Trades",
            "subcategory":"Construction",
            "type":"Services"
        }
    ],
    "sg:phone":"+1 618 344 6353",
    "sg:postcode":"62234",
    "sg:province":"IL",
    "sg:tags":[
        "heavy",
        "excavation",
        "excavating",
        "cont",
        "contractor"
    ],
    "wof:name":"L W Contractors Inc",
    "wof:placetype":"venue"
},
  "geometry": {"coordinates":[-90.001841,38.684264],"type":"Point"}
}