{
  "type": "Feature",
  "properties": {
    "addr:full":"5303 W 25th Pl Cicero IL 60804",
    "addr:housenumber":"5303",
    "addr:postcode":"60804",
    "addr:street":"W 25Th Pl",
    "iso:country":"US",
    "sg:address":"5303 W 25th Pl",
    "sg:city":"Cicero",
    "sg:classifiers":[
        {
            "category":"Government",
            "subcategory":"Fire Station",
            "type":"Public Place"
        }
    ],
    "sg:phone":"+1 708 652 2121",
    "sg:postcode":"60804",
    "sg:province":"IL",
    "sg:tags":[
        "department"
    ],
    "wof:name":"Cicero Fire Dept",
    "wof:placetype":"venue"
},
  "geometry": {"coordinates":[-87.75877199999999,41.844608],"type":"Point"}
}