{
  "type": "Feature",
  "properties": {
    "iso:country":"US",
    "sg:address":"5303 W 25th Pl",
    "sg:city":"Cicero",
    "sg:classifiers":[
        {
            "category":"Government",
            "subcategory":"Fire Station",
            "type":"Public Place"
        }
    ],
    "sg:phone":"+1 708 652 2121",
    "sg:postcode":"60804",
    "sg:province":"IL",
    "sg:tags":[
        "department"
    ],
    "wof:name":"Cicero Fire Dept",
    "wof:placetype":"venue"
},
  "geometry": {"coordinates":[-87.758772,41.844608],"type":"Point"}
}