{
  "type": "Feature",
  "properties": {
    "iso:country":"US",
    "sg:address":"1102 S Gables Blvd",
    "sg:city":"Wheaton",
    "sg:classifiers":[
        {
            "category":"Shopping",
            "type":"Retail Goods"
        },
        {
            "category":"Organizations",
            "subcategory":"Non-profit Organization",
            "type":"Services"
        }
    ],
    "sg:phone":"+1 630 690 5139",
    "sg:postcode":"60189",
    "sg:province":"IL",
    "sg:tags":[
        "fund",
        "games",
        "raising",
        "merchandise",
        "supply"
    ],
    "wof:name":"Joyful Heart Fund",
    "wof:placetype":"venue"
},
  "geometry": {"coordinates":[-88.12397900000001,41.853273],"type":"Point"}
}