{
  "type": "Feature",
  "properties": {
    "iso:country":"US",
    "sg:address":"17355 Torrence Ave",
    "sg:city":"Lansing",
    "sg:classifiers":[
        {
            "category":"Shopping",
            "subcategory":"Shoes",
            "type":"Retail Goods"
        }
    ],
    "sg:phone":"+1   ",
    "sg:postcode":"60438",
    "sg:province":"IL",
    "wof:name":"Meldisco 17355 Torrence Ave",
    "wof:placetype":"venue"
},
  "geometry": {"coordinates":[-87.558784,41.580801],"type":"Point"}
}