{
  "type": "Feature",
  "properties": {
    "addr:full":"1 E Wise Rd Schaumburg IL 60193",
    "addr:housenumber":"1",
    "addr:postcode":"60193",
    "addr:street":"E Wise Rd",
    "iso:country":"US",
    "sg:address":"1 E Wise Rd",
    "sg:city":"Schaumburg",
    "sg:classifiers":[
        {
            "category":"Shopping",
            "subcategory":"Computers & Home Electronics",
            "type":"Retail Goods"
        }
    ],
    "sg:phone":"+1   ",
    "sg:postcode":"60193",
    "sg:province":"IL",
    "sg:tags":[
        "consulting",
        "software"
    ],
    "wof:name":"Net Systems Inc",
    "wof:placetype":"venue"
},
  "geometry": {"coordinates":[-88.078282,42.005388],"type":"Point"}
}