{
  "type": "Feature",
  "properties": {
    "iso:country":"US",
    "sg:address":"3567 W Jefferson St",
    "sg:city":"Joliet",
    "sg:classifiers":[
        {
            "category":"Restaurant",
            "type":"Food & Drink"
        }
    ],
    "sg:phone":"+1 815 744 9740",
    "sg:postcode":"60431",
    "sg:province":"IL",
    "sg:tags":[
        "caterer"
    ],
    "wof:name":"Pita Patio",
    "wof:placetype":"venue"
},
  "geometry": {"coordinates":[-88.164399,41.521849],"type":"Point"}
}