{
  "type": "Feature",
  "properties": {
    "addr:full":"102 Stratford Square Mall Bloomingdale IL 60108",
    "addr:housenumber":"102",
    "addr:postcode":"60108",
    "addr:street":"Stratford Square Mall",
    "iso:country":"US",
    "sg:address":"102 Stratford Square Mall",
    "sg:city":"Bloomingdale",
    "sg:classifiers":[
        {
            "category":"Health Services",
            "subcategory":"Optometrist",
            "type":"Services"
        },
        {
            "category":"Shopping",
            "subcategory":"Optical Goods",
            "type":"Retail Goods"
        },
        {
            "category":"Shopping",
            "subcategory":"Optician",
            "type":"Retail Goods"
        }
    ],
    "sg:phone":"+1 630 893 7608",
    "sg:postcode":"60108",
    "sg:province":"IL",
    "sg:tags":[
        "eyeglass"
    ],
    "sg:website":"http://www.lenscrafters.com",
    "wof:name":"Lenscrafters",
    "wof:placetype":"venue"
},
  "geometry": {"coordinates":[-88.114216,41.951456],"type":"Point"}
}