{
  "type": "Feature",
  "properties": {
    "addr:full":"9301 Collinsville Rd Collinsville IL 62234",
    "addr:housenumber":"9301",
    "addr:postcode":"62234",
    "addr:street":"Collinsville Rd",
    "iso:country":"US",
    "sg:address":"9301 Collinsville Rd",
    "sg:city":"Collinsville",
    "sg:classifiers":[
        {
            "category":"Sports & Exercise",
            "subcategory":"Race Track",
            "type":"Entertainment"
        }
    ],
    "sg:phone":"+1 618 345 4414",
    "sg:postcode":"62234",
    "sg:province":"IL",
    "sg:tags":[
        "equipment",
        "supply"
    ],
    "wof:name":"Amer Totalisator",
    "wof:placetype":"venue"
},
  "geometry": {"coordinates":[-90.03420199999999,38.659686],"type":"Point"}
}