{
  "type": "Feature",
  "properties": {
    "iso:country":"US",
    "sg:address":"509 S Park Ave",
    "sg:city":"Herrin",
    "sg:classifiers":[
        {
            "category":"Restaurant",
            "type":"Food & Drink"
        }
    ],
    "sg:phone":"+1 618 942 2742",
    "sg:postcode":"62948",
    "sg:province":"IL",
    "wof:name":"Mary's Restaurant",
    "wof:placetype":"venue"
},
  "geometry": {"coordinates":[-89.02739699999999,37.800201],"type":"Point"}
}