{
  "type": "Feature",
  "properties": {
    "iso:country":"US",
    "sg:address":"4809 W 77th St",
    "sg:city":"Burbank",
    "sg:classifiers":[
        {
            "category":"Restaurant",
            "type":"Food & Drink"
        }
    ],
    "sg:phone":"+1 708 423 7744",
    "sg:postcode":"60459",
    "sg:province":"IL",
    "wof:name":"Popeye's",
    "wof:placetype":"venue"
},
  "geometry": {"coordinates":[-87.746002,41.752499],"type":"Point"}
}