{
  "type": "Feature",
  "properties": {
    "addr:full":"1623 Sandy Hollow Rd Rockford IL 61109",
    "addr:housenumber":"1623",
    "addr:postcode":"61109",
    "addr:street":"Sandy Hollow Rd",
    "iso:country":"US",
    "sg:address":"1623 Sandy Hollow Rd",
    "sg:city":"Rockford",
    "sg:classifiers":[
        {
            "category":"Personal",
            "subcategory":"Massage",
            "type":"Services"
        },
        {
            "category":"Personal",
            "subcategory":"Beauty Salon",
            "type":"Services"
        }
    ],
    "sg:phone":"+1 815 399 9636",
    "sg:postcode":"61109",
    "sg:province":"IL",
    "sg:tags":[
        "therapist"
    ],
    "wof:name":"Trina & Co Salon & Spa",
    "wof:placetype":"venue"
},
  "geometry": {"coordinates":[-89.07127800000001,42.223413],"type":"Point"}
}