{
  "type": "Feature",
  "properties": {
    "addr:full":"302 Allen Ave West Chicago IL 60185",
    "addr:housenumber":"302",
    "addr:postcode":"60185",
    "addr:street":"Allen Ave West",
    "iso:country":"US",
    "sg:address":"302 Allen Ave",
    "sg:city":"West Chicago",
    "sg:classifiers":[
        {
            "category":"Shopping",
            "type":"Retail Goods"
        }
    ],
    "sg:phone":"+1 630 293 3637",
    "sg:postcode":"60185",
    "sg:province":"IL",
    "sg:tags":[
        "craft",
        "gallery",
        "dealer"
    ],
    "wof:name":"Craft Show Promotions",
    "wof:placetype":"venue"
},
  "geometry": {"coordinates":[-88.20338,41.879213],"type":"Point"}
}