{
  "type": "Feature",
  "properties": {
    "iso:country":"US",
    "sg:address":"100 W Higgins Rd Unit E20",
    "sg:city":"South Barrington",
    "sg:classifiers":[
        {
            "category":"Shopping",
            "subcategory":"Jewelry",
            "type":"Retail Goods"
        }
    ],
    "sg:phone":"+1 847 551 9394",
    "sg:postcode":"60010",
    "sg:province":"IL",
    "wof:name":"Azar Jewelers",
    "wof:placetype":"venue"
},
  "geometry": {"coordinates":[-88.18418,42.073571],"type":"Point"}
}