{
  "type": "Feature",
  "properties": {
    "iso:country":"US",
    "sg:address":"1001 East 53rd Street",
    "sg:city":"Chicago",
    "sg:classifiers":[
        {
            "category":"Food & Beverages",
            "subcategory":"Candy",
            "type":"Retail Goods"
        },
        {
            "category":"Restaurant",
            "type":"Food & Drink"
        }
    ],
    "sg:phone":"+1 708 381 9668",
    "sg:postcode":"60615",
    "sg:province":"IL",
    "sg:tags":[
        "dessert",
        "vegetarian",
        "vegan"
    ],
    "sg:website":"veganbloom.com/cafebloom.html",
    "wof:name":"Cafe Bloom",
    "wof:placetype":"venue"
},
  "geometry": {"coordinates":[-87.60126700000001,41.799387],"type":"Point"}
}