{
  "type": "Feature",
  "properties": {
    "iso:country":"US",
    "sg:address":"8367 Unionville Rd",
    "sg:city":"Brookport",
    "sg:phone":"+1 618 564 2774",
    "sg:postcode":"62910",
    "sg:province":"IL",
    "sg:tags":[
        "farm",
        "corn",
        "soybean"
    ],
    "wof:name":"Bryants Farm",
    "wof:placetype":"venue"
},
  "geometry": {"coordinates":[-88.56319999999999,37.122415],"type":"Point"}
}