{
  "type": "Feature",
  "properties": {
    "iso:country":"US",
    "sg:address":"21617 Schmule Rd",
    "sg:city":"New Lenox",
    "sg:classifiers":[
        {
            "category":"Manufacturing",
            "subcategory":"Glass & Minerals",
            "type":"Manufacturing & Wholesale Goods"
        }
    ],
    "sg:phone":"+1 815 462 3408",
    "sg:postcode":"60451",
    "sg:province":"IL",
    "sg:tags":[
        "concrete",
        "brick",
        "prod",
        "block"
    ],
    "wof:name":"Classical Statuary & Decor Inc",
    "wof:placetype":"venue"
},
  "geometry": {"coordinates":[-87.926774,41.498103],"type":"Point"}
}