{
  "type": "Feature",
  "properties": {
    "addr:full":"2246 N Clark St Chicago IL 60614",
    "addr:housenumber":"2246",
    "addr:postcode":"60614",
    "addr:street":"N Clark St",
    "iso:country":"US",
    "sg:address":"2246 N Clark St",
    "sg:city":"Chicago",
    "sg:classifiers":[
        {
            "category":"Real Estate",
            "subcategory":"Real Estate Operator",
            "type":"Services"
        }
    ],
    "sg:phone":"+1 773 857 3008",
    "sg:postcode":"60614",
    "sg:province":"IL",
    "sg:tags":[
        "apartment"
    ],
    "wof:name":"Chicago Apartment Hunters",
    "wof:placetype":"venue"
},
  "geometry": {"coordinates":[-87.63905699999999,41.923011],"type":"Point"}
}