{
  "type": "Feature",
  "properties": {
    "addr:full":"3972 W Columbus Ave Chicago IL 60652",
    "addr:housenumber":"3972",
    "addr:postcode":"60652",
    "addr:street":"W Columbus Ave",
    "iso:country":"US",
    "sg:address":"3972 W Columbus Ave",
    "sg:city":"Chicago",
    "sg:classifiers":[
        {
            "category":"Food & Beverages",
            "subcategory":"Groceries & Convenience Stores",
            "type":"Retail Goods"
        }
    ],
    "sg:phone":"+1 773 585 6725",
    "sg:postcode":"60652",
    "sg:province":"IL",
    "wof:name":"City Food Mart",
    "wof:placetype":"venue"
},
  "geometry": {"coordinates":[-87.721001,41.736],"type":"Point"}
}