{
  "type": "Feature",
  "properties": {
    "iso:country":"US",
    "sg:address":"954 Bend Rd",
    "sg:city":"Dixon",
    "sg:classifiers":[
        {
            "category":"Freight",
            "type":"Transportation"
        }
    ],
    "sg:phone":"+1 815 288 2828",
    "sg:postcode":"61021",
    "sg:province":"IL",
    "sg:tags":[
        "operator",
        "local",
        "trucking"
    ],
    "wof:name":"Kristis Trucking Inc",
    "wof:placetype":"venue"
},
  "geometry": {"coordinates":[-89.443219,41.903117],"type":"Point"}
}