{
  "type": "Feature",
  "properties": {
    "iso:country":"US",
    "sg:address":"3739 S Halsted St",
    "sg:city":"Chicago",
    "sg:classifiers":[
        {
            "category":"Food & Beverages",
            "subcategory":"Meat & Fish",
            "type":"Retail Goods"
        }
    ],
    "sg:phone":"+1 773 376 8555",
    "sg:postcode":"60609",
    "sg:province":"IL",
    "sg:tags":[
        "shop",
        "market"
    ],
    "wof:name":"Steaktopia",
    "wof:placetype":"venue"
},
  "geometry": {"coordinates":[-87.645798,41.826199],"type":"Point"}
}