{
  "type": "Feature",
  "properties": {
    "addr:full":"935 W 87th St Chicago IL 60620",
    "addr:housenumber":"935",
    "addr:postcode":"60620",
    "addr:street":"W 87Th St",
    "iso:country":"US",
    "sg:address":"935 W 87th St",
    "sg:city":"Chicago",
    "sg:classifiers":[
        {
            "category":"Food & Beverages",
            "subcategory":"Groceries & Convenience Stores",
            "type":"Retail Goods"
        }
    ],
    "sg:phone":"+1 773 224 2557",
    "sg:postcode":"60620",
    "sg:province":"IL",
    "wof:name":"Five Star Certified Inc",
    "wof:placetype":"venue"
},
  "geometry": {"coordinates":[-87.6474,41.735901],"type":"Point"}
}