{
  "type": "Feature",
  "properties": {
    "iso:country":"US",
    "sg:address":"1071 Waveland Ave",
    "sg:city":"Franklin Park",
    "sg:classifiers":[
        {
            "category":"Retail",
            "subcategory":"Repair Shop",
            "type":"Services"
        }
    ],
    "sg:phone":"+1 630 616 1100",
    "sg:postcode":"60131",
    "sg:province":"IL",
    "sg:tags":[
        "heat",
        "welding",
        "metal",
        "mfg"
    ],
    "wof:name":"Howell Welding Corporation",
    "wof:placetype":"venue"
},
  "geometry": {"coordinates":[-87.919141,41.945715],"type":"Point"}
}