{
  "type": "Feature",
  "properties": {
    "iso:country":"US",
    "sg:address":"114 Bradford Rd",
    "sg:city":"Joliet",
    "sg:classifiers":[
        {
            "category":"Insurance",
            "subcategory":"Insurance Agent",
            "type":"Services"
        }
    ],
    "sg:phone":"+1 815 740 6433",
    "sg:postcode":"60433",
    "sg:province":"IL",
    "sg:tags":[
        "process",
        "claim"
    ],
    "wof:name":"T Dukes Elctronic Billing Ctr",
    "wof:placetype":"venue"
},
  "geometry": {"coordinates":[-88.077549,41.489803],"type":"Point"}
}