{
  "type": "Feature",
  "properties": {
    "addr:full":"634 E Galena Blvd Aurora IL 60505",
    "addr:housenumber":"634",
    "addr:postcode":"60505",
    "addr:street":"E Galena Blvd",
    "iso:country":"US",
    "sg:address":"634 E Galena Blvd",
    "sg:city":"Aurora",
    "sg:classifiers":[
        {
            "category":"Autos & Motor Vehicles",
            "subcategory":"Automobile Sales",
            "type":"Retail Goods"
        }
    ],
    "sg:phone":"+1 630 851 0800",
    "sg:postcode":"60505",
    "sg:province":"IL",
    "sg:tags":[
        "car",
        "dealer"
    ],
    "wof:name":"Betel Autoplex LTD",
    "wof:placetype":"venue"
},
  "geometry": {"coordinates":[-88.30170099999999,41.753112],"type":"Point"}
}