{
  "type": "Feature",
  "properties": {
    "iso:country":"US",
    "sg:address":"123 E Chippewa St",
    "sg:city":"Dwight",
    "sg:phone":"+1 312 873 7578",
    "sg:postcode":"60420",
    "sg:province":"IL",
    "wof:name":"Standstrong Services",
    "wof:placetype":"venue"
},
  "geometry": {"coordinates":[-88.428093,41.091869],"type":"Point"}
}