{
  "type": "Feature",
  "properties": {
    "addr:full":"26729 S Ridge Rd Elwood IL 60421",
    "addr:housenumber":"26729",
    "addr:postcode":"60421",
    "addr:street":"S Ridge Rd",
    "iso:country":"US",
    "sg:address":"26729 S Ridge Rd",
    "sg:city":"Elwood",
    "sg:classifiers":[
        {
            "category":"Farming",
            "subcategory":"Livestock Farm",
            "type":"Manufacturing & Wholesale Goods"
        }
    ],
    "sg:phone":"+1 815 478 3623",
    "sg:postcode":"60421",
    "sg:province":"IL",
    "sg:tags":[
        "hog",
        "or",
        "feedlot"
    ],
    "wof:name":"Gary Bernhard",
    "wof:placetype":"venue"
},
  "geometry": {"coordinates":[-88.039124,41.409478],"type":"Point"}
}