{
  "type": "Feature",
  "properties": {
    "addr:full":"201 N 3rd St Quincy IL 62301",
    "addr:housenumber":"201",
    "addr:postcode":"62301",
    "addr:street":"N 3Rd St",
    "iso:country":"US",
    "sg:address":"201 N 3rd St",
    "sg:city":"Quincy",
    "sg:classifiers":[
        {
            "category":"Social Services",
            "type":"Services"
        }
    ],
    "sg:phone":"+1 217 224 1277",
    "sg:postcode":"62301",
    "sg:province":"IL",
    "sg:tags":[
        "organization",
        "welfare"
    ],
    "wof:name":"Birthright Of Quincy",
    "wof:placetype":"venue"
},
  "geometry": {"coordinates":[-91.411692,39.934529],"type":"Point"}
}