{
  "type": "Feature",
  "properties": {
    "addr:full":"555 Elm St Alhambra IL 62001",
    "addr:housenumber":"555",
    "addr:postcode":"62001",
    "addr:street":"Elm St",
    "iso:country":"US",
    "sg:address":"555 Elm St",
    "sg:city":"Alhambra",
    "sg:classifiers":[
        {
            "category":"Personal",
            "subcategory":"Beauty Salon",
            "type":"Services"
        }
    ],
    "sg:phone":"+1 618 488 2701",
    "sg:postcode":"62001",
    "sg:province":"IL",
    "wof:name":"Hair & Co",
    "wof:placetype":"venue"
},
  "geometry": {"coordinates":[-89.7283,38.890118],"type":"Point"}
}