{
  "type": "Feature",
  "properties": {
    "addr:full":"2300 Lehigh Ave Glenview IL 60026",
    "addr:housenumber":"2300",
    "addr:postcode":"60026",
    "addr:street":"Lehigh Ave",
    "iso:country":"US",
    "sg:address":"2300 Lehigh Ave",
    "sg:city":"Glenview",
    "sg:classifiers":[
        {
            "category":"Real Estate",
            "subcategory":"Real Estate Services",
            "type":"Services"
        },
        {
            "category":"Real Estate",
            "subcategory":"Real Estate Agent",
            "type":"Services"
        }
    ],
    "sg:phone":"+1 847 724 5100",
    "sg:postcode":"60026",
    "sg:province":"IL",
    "sg:tags":[
        "buyer",
        "broker"
    ],
    "wof:name":"Prime Invesco",
    "wof:placetype":"venue"
},
  "geometry": {"coordinates":[-87.816101,42.096378],"type":"Point"}
}