{
  "type": "Feature",
  "properties": {
    "addr:full":"75 E Wacker Dr Chicago IL 60601",
    "addr:housenumber":"75",
    "addr:postcode":"60601",
    "addr:street":"E Wacker Dr",
    "iso:country":"US",
    "sg:address":"75 E Wacker Dr",
    "sg:city":"Chicago",
    "sg:classifiers":[
        {
            "category":"Travel",
            "subcategory":"Hotels & Motels",
            "type":"Entertainment"
        }
    ],
    "sg:phone":"+1 312 857 0800",
    "sg:postcode":"60601",
    "sg:province":"IL",
    "wof:name":"Heritage Bed & Breakfast Registry",
    "wof:placetype":"venue"
},
  "geometry": {"coordinates":[-87.62509900000001,41.8881],"type":"Point"}
}