{
  "type": "Feature",
  "properties": {
    "iso:country":"US",
    "sg:address":"110 E Market St",
    "sg:city":"Colchester",
    "sg:classifiers":[
        {
            "category":"Banks & Credit Unions",
            "subcategory":"Investment Brokerage",
            "type":"Services"
        },
        {
            "category":"Insurance",
            "subcategory":"Hazard Insurance",
            "type":"Services"
        },
        {
            "category":"Banks & Credit Unions",
            "subcategory":"Financial Services",
            "type":"Services"
        }
    ],
    "sg:phone":"+1 309 776 5217",
    "sg:postcode":"62326",
    "sg:province":"IL",
    "sg:tags":[
        "security",
        "commercial",
        "business"
    ],
    "wof:name":"Ramsey Financial Services",
    "wof:placetype":"venue"
},
  "geometry": {"coordinates":[-90.792461,40.424751],"type":"Point"}
}