{
  "type": "Feature",
  "properties": {
    "iso:country":"US",
    "sg:address":"212 W 23rd St",
    "sg:city":"Chicago",
    "sg:classifiers":[
        {
            "category":"Restaurant",
            "type":"Food & Drink"
        }
    ],
    "sg:phone":"+1 312 842 8688",
    "sg:postcode":"60616",
    "sg:province":"IL",
    "sg:tags":[
        "seafood",
        "chinese"
    ],
    "sg:website":"www.go4foodusa.com",
    "wof:name":"Go 4 Food",
    "wof:placetype":"venue"
},
  "geometry": {"coordinates":[-87.63255100000001,41.851147],"type":"Point"}
}