{
  "type": "Feature",
  "properties": {
    "iso:country":"US",
    "sg:address":"54 Danada Sq W",
    "sg:city":"Wheaton",
    "sg:classifiers":[
        {
            "category":"Shopping",
            "subcategory":"Gifts & Souvenirs",
            "type":"Retail Goods"
        }
    ],
    "sg:phone":"+1   ",
    "sg:postcode":"60187",
    "sg:province":"IL",
    "wof:name":"Kirlins Hallmark 143",
    "wof:placetype":"venue"
},
  "geometry": {"coordinates":[-88.104458,41.833749],"type":"Point"}
}