{
  "type": "Feature",
  "properties": {
    "iso:country":"US",
    "sg:address":"5801 Heidi Dr",
    "sg:city":"Rockford",
    "sg:classifiers":[
        {
            "category":"Professional",
            "type":"Services"
        }
    ],
    "sg:phone":"+1 815 226 2355",
    "sg:postcode":"61109",
    "sg:province":"IL",
    "sg:tags":[
        "establishment"
    ],
    "wof:name":"Bradley Courter",
    "wof:placetype":"venue"
},
  "geometry": {"coordinates":[-89.000645,42.23275],"type":"Point"}
}