{
  "type": "Feature",
  "properties": {
    "iso:country":"US",
    "sg:address":"842 E 300 North Rd",
    "sg:city":"Cissna Park",
    "sg:classifiers":[
        {
            "category":"Home & Garden",
            "subcategory":"Carpets & Floor Coverings",
            "type":"Retail Goods"
        }
    ],
    "sg:phone":"+1   ",
    "sg:postcode":"60924",
    "sg:province":"IL",
    "sg:tags":[
        "construction",
        "carpenter"
    ],
    "wof:name":"Delbert Bruens",
    "wof:placetype":"venue"
},
  "geometry": {"coordinates":[-87.959585,40.528844],"type":"Point"}
}