{
  "type": "Feature",
  "properties": {
    "addr:full":"923 N Plum Grove Rd Schaumburg IL 60173",
    "addr:housenumber":"923",
    "addr:postcode":"60173",
    "addr:street":"N Plum Grove Rd",
    "iso:country":"US",
    "sg:address":"923 N Plum Grove Rd",
    "sg:city":"Schaumburg",
    "sg:classifiers":[
        {
            "category":"Insurance",
            "subcategory":"Hazard Insurance",
            "type":"Services"
        }
    ],
    "sg:phone":"+1 847 605 8560",
    "sg:postcode":"60173",
    "sg:province":"IL",
    "sg:website":"http://www.cbcco.com",
    "wof:name":"Coorinated Benefits Company",
    "wof:placetype":"venue"
},
  "geometry": {"coordinates":[-88.06004299999999,42.045735],"type":"Point"}
}