{
  "type": "Feature",
  "properties": {
    "iso:country":"US",
    "sg:address":"5770 Spring Creek Rd",
    "sg:city":"Rockford",
    "sg:classifiers":[
        {
            "category":"Organizations",
            "subcategory":"Religious Organization",
            "type":"Services"
        }
    ],
    "sg:phone":"+1 815 877 8331",
    "sg:postcode":"61114",
    "sg:province":"IL",
    "wof:name":"Hope Reformed Church",
    "wof:placetype":"venue"
},
  "geometry": {"coordinates":[-89.002983,42.296814],"type":"Point"}
}