{
  "type": "Feature",
  "properties": {
    "iso:country":"US",
    "sg:address":"14445 Maple Dr",
    "sg:city":"Breese",
    "sg:classifiers":[
        {
            "category":"Retail",
            "subcategory":"Auto Repair",
            "type":"Services"
        }
    ],
    "sg:phone":"+1 618 526 0329",
    "sg:postcode":"62230",
    "sg:province":"IL",
    "sg:tags":[
        "general"
    ],
    "wof:name":"Korte Auto Body",
    "wof:placetype":"venue"
},
  "geometry": {"coordinates":[-89.555244,38.63115],"type":"Point"}
}