{
  "type": "Feature",
  "properties": {
    "iso:country":"US",
    "sg:address":"7212 W Foster Ave",
    "sg:city":"Chicago",
    "sg:classifiers":[
        {
            "category":"Professional",
            "subcategory":"Accounting & Tax Preparation",
            "type":"Services"
        },
        {
            "category":"Banks & Credit Unions",
            "subcategory":"Financial Services",
            "type":"Services"
        }
    ],
    "sg:phone":"+1 773 594 0155",
    "sg:postcode":"60656",
    "sg:province":"IL",
    "sg:tags":[
        "accountant",
        "advising"
    ],
    "wof:name":"H & R Block",
    "wof:placetype":"venue"
},
  "geometry": {"coordinates":[-87.807208,41.974552],"type":"Point"}
}