{
  "type": "Feature",
  "properties": {
    "iso:country":"US",
    "sg:address":"1040 W 95th St",
    "sg:city":"Chicago",
    "sg:classifiers":[
        {
            "category":"Utilities",
            "subcategory":"Water",
            "type":"Services"
        },
        {
            "category":"Government",
            "subcategory":"Office",
            "type":"Public Place"
        }
    ],
    "sg:phone":"+1 312 747 0196",
    "sg:postcode":"60643",
    "sg:province":"IL",
    "sg:tags":[
        "control",
        "conservation",
        "pollution"
    ],
    "sg:website":"http://www.ci.chi.il.us",
    "wof:name":"Water Management, Dept Of",
    "wof:placetype":"venue"
},
  "geometry": {"coordinates":[-87.649417,41.721438],"type":"Point"}
}