{
  "type": "Feature",
  "properties": {
    "addr:full":"20 Chester St Galva IL 61434",
    "addr:housenumber":"20",
    "addr:postcode":"61434",
    "addr:street":"Chester St",
    "iso:country":"US",
    "sg:address":"20 Chester St",
    "sg:city":"Galva",
    "sg:classifiers":[
        {
            "category":"Coffee & Tea",
            "type":"Food & Drink"
        },
        {
            "category":"Restaurant",
            "type":"Food & Drink"
        }
    ],
    "sg:phone":"+1 309 932 3039",
    "sg:postcode":"61434",
    "sg:province":"IL",
    "sg:tags":[
        "style",
        "espresso",
        "family"
    ],
    "wof:name":"Corner Table Cafe",
    "wof:placetype":"venue"
},
  "geometry": {"coordinates":[-90.041254,41.166283],"type":"Point"}
}