{
  "type": "Feature",
  "properties": {
    "iso:country":"US",
    "sg:address":"114 E 5th St",
    "sg:city":"Bowen",
    "sg:classifiers":[
        {
            "category":"Government",
            "subcategory":"Post Office",
            "type":"Public Place"
        }
    ],
    "sg:phone":"+1 217 842 5215",
    "sg:postcode":"62316",
    "sg:province":"IL",
    "sg:tags":[
        "postal",
        "us"
    ],
    "wof:name":"Bowen Post Office",
    "wof:placetype":"venue"
},
  "geometry": {"coordinates":[-91.064518,40.231506],"type":"Point"}
}