{
  "type": "Feature",
  "properties": {
    "addr:full":"27110 W Highland Rd Barrington IL 60010",
    "addr:housenumber":"27110",
    "addr:postcode":"60010",
    "addr:street":"W Highland Rd",
    "iso:country":"US",
    "sg:address":"27110 W Highland Rd",
    "sg:city":"Barrington",
    "sg:classifiers":[
        {
            "category":"Freight",
            "type":"Transportation"
        }
    ],
    "sg:phone":"+1 847 381 3941",
    "sg:postcode":"60010",
    "sg:province":"IL",
    "sg:tags":[
        "distance",
        "long",
        "trucking"
    ],
    "wof:name":"D & K Trucking",
    "wof:placetype":"venue"
},
  "geometry": {"coordinates":[-88.163256,42.170736],"type":"Point"}
}