{
  "type": "Feature",
  "properties": {
    "iso:country":"US",
    "sg:address":"1515 Sheridan Rd",
    "sg:city":"Wilmette",
    "sg:phone":"+1 847 251 7535",
    "sg:postcode":"60091",
    "sg:province":"IL",
    "wof:name":"La Colonna",
    "wof:placetype":"venue"
},
  "geometry": {"coordinates":[-87.69980099999999,42.086598],"type":"Point"}
}