{
  "type": "Feature",
  "properties": {
    "iso:country":"US",
    "sg:address":"4142 W 167th St",
    "sg:city":"Oak Forest",
    "sg:classifiers":[
        {
            "category":"Food & Beverages",
            "subcategory":"Liquor & Beverages",
            "type":"Retail Goods"
        }
    ],
    "sg:phone":"+1 708 596 4064",
    "sg:postcode":"60452",
    "sg:province":"IL",
    "sg:tags":[
        "beer",
        "spirit",
        "wine"
    ],
    "wof:name":"Rose Liquor",
    "wof:placetype":"venue"
},
  "geometry": {"coordinates":[-87.718953,41.586367],"type":"Point"}
}