{
  "type": "Feature",
  "properties": {
    "addr:full":"387 S Main St Bourbonnais IL 60914",
    "addr:housenumber":"387",
    "addr:postcode":"60914",
    "addr:street":"S Main St",
    "iso:country":"US",
    "sg:address":"387 S Main St",
    "sg:city":"Bourbonnais",
    "sg:classifiers":[
        {
            "category":"Professional",
            "subcategory":"Management & Consulting",
            "type":"Services"
        }
    ],
    "sg:phone":"+1 815 939 2800",
    "sg:postcode":"60914",
    "sg:province":"IL",
    "wof:name":"Retirement Planners Inc",
    "wof:placetype":"venue"
},
  "geometry": {"coordinates":[-87.877666,41.15388],"type":"Point"}
}