{
  "type": "Feature",
  "properties": {
    "addr:full":"1080 E Cedarville Rd Freeport IL 61032",
    "addr:housenumber":"1080",
    "addr:postcode":"61032",
    "addr:street":"E Cedarville Rd",
    "iso:country":"US",
    "sg:address":"1080 E Cedarville Rd",
    "sg:city":"Freeport",
    "sg:phone":"+1 815 563 4262",
    "sg:postcode":"61032",
    "sg:province":"IL",
    "sg:tags":[
        "farm",
        "corn"
    ],
    "wof:name":"Russell Cashmore",
    "wof:placetype":"venue"
},
  "geometry": {"coordinates":[-89.57536399999999,42.374352],"type":"Point"}
}