{
  "type": "Feature",
  "properties": {
    "iso:country":"US",
    "sg:address":"2739 W Devon Ave",
    "sg:city":"Chicago",
    "sg:classifiers":[
        {
            "category":"Restaurant",
            "type":"Food & Drink"
        }
    ],
    "sg:menulink":"http://www.allmenus.com/il/chicago/209960-fazal-e-rabi/menu/",
    "sg:phone":"+1 773 338 5577",
    "sg:postcode":"60659",
    "sg:province":"IL",
    "sg:tags":[
        "indian",
        "asian"
    ],
    "wof:name":"Fazal-e-rabi",
    "wof:placetype":"venue"
},
  "geometry": {"coordinates":[-87.69848,41.99749],"type":"Point"}
}