{
  "type": "Feature",
  "properties": {
    "iso:country":"US",
    "sg:address":"6327 N Fairfield Ave",
    "sg:city":"Chicago",
    "sg:classifiers":[
        {
            "category":"Autos & Motor Vehicles",
            "subcategory":"Automobile Sales",
            "type":"Retail Goods"
        }
    ],
    "sg:phone":"+1 773 764 9000",
    "sg:postcode":"60659",
    "sg:province":"IL",
    "sg:tags":[
        "limo"
    ],
    "wof:name":"Above and Beyond Limousine Service",
    "wof:placetype":"venue"
},
  "geometry": {"coordinates":[-87.698198,41.996275],"type":"Point"}
}