{
  "type": "Feature",
  "properties": {
    "addr:full":"2741 S Western Avenue Chicago IL 60608",
    "addr:housenumber":"2741",
    "addr:postcode":"60608",
    "addr:street":"S Western Avenue",
    "iso:country":"US",
    "sg:address":"2741 S Western Avenue",
    "sg:city":"Chicago",
    "sg:classifiers":[
        {
            "category":"Education",
            "subcategory":"School",
            "type":"Public Place"
        }
    ],
    "sg:phone":"+1 773 535 5850",
    "sg:postcode":"60608",
    "sg:province":"IL",
    "sg:tags":[
        "high",
        "middle",
        "elementary"
    ],
    "wof:name":"City of Chicago School District 299",
    "wof:placetype":"venue"
},
  "geometry": {"coordinates":[-87.68516200000001,41.842682],"type":"Point"}
}