{
  "type": "Feature",
  "properties": {
    "addr:full":"21401 S 79th Ave Frankfort IL 60423",
    "addr:housenumber":"21401",
    "addr:postcode":"60423",
    "addr:street":"S 79Th Ave",
    "iso:country":"US",
    "sg:address":"21401 S 79th Ave",
    "sg:city":"Frankfort",
    "sg:classifiers":[
        {
            "category":"Arts & Performance",
            "subcategory":"Theater",
            "type":"Entertainment"
        }
    ],
    "sg:phone":"+1 815 469 2071",
    "sg:postcode":"60423",
    "sg:province":"IL",
    "sg:tags":[
        "bureau"
    ],
    "wof:name":"In-House Productions",
    "wof:placetype":"venue"
},
  "geometry": {"coordinates":[-87.807106,41.5009],"type":"Point"}
}