{
  "type": "Feature",
  "properties": {
    "addr:full":"115 Arlington Heights Rd Arlington Heights IL 60005",
    "addr:housenumber":"115",
    "addr:postcode":"60005",
    "addr:street":"Arlington Heights Rd",
    "iso:country":"US",
    "sg:address":"115 Arlington Heights Rd",
    "sg:city":"Arlington Heights",
    "sg:classifiers":[
        {
            "category":"Manufacturing",
            "subcategory":"Paper Products",
            "type":"Manufacturing & Wholesale Goods"
        }
    ],
    "sg:phone":"+1 847 253 6100",
    "sg:postcode":"60005",
    "sg:province":"IL",
    "sg:tags":[
        "converted",
        "mfg"
    ],
    "wof:name":"Atlas Tag & Label Inc",
    "wof:placetype":"venue"
},
  "geometry": {"coordinates":[-87.980435,42.079794],"type":"Point"}
}