{
  "type": "Feature",
  "properties": {
    "addr:full":"50 W Washington St Chicago IL 60602",
    "addr:housenumber":"50",
    "addr:postcode":"60602",
    "addr:street":"W Washington St",
    "iso:country":"US",
    "sg:address":"50 W Washington St",
    "sg:city":"Chicago",
    "sg:classifiers":[
        {
            "category":"Food & Beverages",
            "subcategory":"Farmers Market",
            "type":"Retail Goods"
        }
    ],
    "sg:postcode":"60602",
    "sg:province":"IL",
    "wof:name":"Daley Plaza Farmers Market",
    "wof:placetype":"venue"
},
  "geometry": {"coordinates":[-87.630236,41.883325],"type":"Point"}
}