{
  "type": "Feature",
  "properties": {
    "iso:country":"US",
    "sg:address":"13 Pickford Rd",
    "sg:city":"Montgomery",
    "sg:classifiers":[
        {
            "category":"Retail",
            "subcategory":"Laundry & Dry Cleaning",
            "type":"Services"
        }
    ],
    "sg:phone":"+1 630 897 2354",
    "sg:postcode":"60538",
    "sg:province":"IL",
    "wof:name":"Rug Doctor Rentals Northern IL",
    "wof:placetype":"venue"
},
  "geometry": {"coordinates":[-88.339057,41.701977],"type":"Point"}
}