{
  "type": "Feature",
  "properties": {
    "iso:country":"US",
    "sg:address":"10331 Werch Dr",
    "sg:city":"Woodridge",
    "sg:classifiers":[
        {
            "category":"Wholesale",
            "subcategory":"Computers",
            "type":"Manufacturing & Wholesale Goods"
        }
    ],
    "sg:phone":"+1 630 343 2600",
    "sg:postcode":"60517",
    "sg:province":"IL",
    "sg:tags":[
        "equipment"
    ],
    "sg:website":"http://www.numinagroup.com",
    "wof:name":"Numina Systems",
    "wof:placetype":"venue"
},
  "geometry": {"coordinates":[-88.02502800000001,41.69695],"type":"Point"}
}