{
  "type": "Feature",
  "properties": {
    "iso:country":"US",
    "sg:address":"97 Juniper Way",
    "sg:city":"Lake Villa",
    "sg:classifiers":[
        {
            "category":"Professional",
            "type":"Services"
        }
    ],
    "sg:phone":"+1 847 265 8444",
    "sg:postcode":"60046",
    "sg:province":"IL",
    "sg:tags":[
        "establishment"
    ],
    "wof:name":"Scardina Enterprises Inc",
    "wof:placetype":"venue"
},
  "geometry": {"coordinates":[-88.080658,42.406597],"type":"Point"}
}