{
  "type": "Feature",
  "properties": {
    "addr:full":"499 Pennsylvania Ave Glen Ellyn IL 60137",
    "addr:housenumber":"499",
    "addr:postcode":"60137",
    "addr:street":"Pennsylvania Ave",
    "iso:country":"US",
    "sg:address":"499 Pennsylvania Ave",
    "sg:city":"Glen Ellyn",
    "sg:classifiers":[
        {
            "category":"Personal",
            "subcategory":"Beauty Salon",
            "type":"Services"
        }
    ],
    "sg:phone":"+1 630 469 2244",
    "sg:postcode":"60137",
    "sg:province":"IL",
    "wof:name":"499 West Salon",
    "wof:placetype":"venue"
},
  "geometry": {"coordinates":[-88.068412,41.877238],"type":"Point"}
}