{
  "type": "Feature",
  "properties": {
    "iso:country":"US",
    "sg:address":"10244 S Saint Lawrence Ave",
    "sg:city":"Chicago",
    "sg:classifiers":[
        {
            "category":"Banks & Credit Unions",
            "subcategory":"Investment Brokerage",
            "type":"Services"
        }
    ],
    "sg:phone":"+1 773 821 9645",
    "sg:postcode":"60628",
    "sg:province":"IL",
    "sg:tags":[
        "investing"
    ],
    "wof:name":"B & G Investmments 2 Corp",
    "wof:placetype":"venue"
},
  "geometry": {"coordinates":[-87.609111,41.708145],"type":"Point"}
}