{
  "type": "Feature",
  "properties": {
    "addr:full":"9788 W 151st St Orland Park IL 60462",
    "addr:housenumber":"9788",
    "addr:postcode":"60462",
    "addr:street":"W 151St St",
    "iso:country":"US",
    "sg:address":"9788 W 151st St",
    "sg:city":"Orland Park",
    "sg:classifiers":[
        {
            "category":"Government",
            "subcategory":"Fire Station",
            "type":"Public Place"
        }
    ],
    "sg:phone":"+1   ",
    "sg:postcode":"60462",
    "sg:province":"IL",
    "sg:tags":[
        "protection"
    ],
    "wof:name":"Combined Agency Response Team",
    "wof:placetype":"venue"
},
  "geometry": {"coordinates":[-87.85827999999999,41.615937],"type":"Point"}
}