{
  "type": "Feature",
  "properties": {
    "iso:country":"US",
    "sg:address":"1627 E 74th Pl",
    "sg:city":"Chicago",
    "sg:classifiers":[
        {
            "category":"Professional",
            "subcategory":"Business Services",
            "type":"Services"
        }
    ],
    "sg:phone":"+1 773 231 2587",
    "sg:postcode":"60649",
    "sg:province":"IL",
    "sg:tags":[
        "recording",
        "studio"
    ],
    "wof:name":"Imec Records Inc",
    "wof:placetype":"venue"
},
  "geometry": {"coordinates":[-87.585331,41.75961],"type":"Point"}
}