{
  "type": "Feature",
  "properties": {
    "iso:country":"US",
    "sg:address":"933 W. Liberty Dr",
    "sg:city":"Wheaton",
    "sg:classifiers":[
        {
            "category":"Building & Trades",
            "subcategory":"Construction",
            "type":"Services"
        }
    ],
    "sg:phone":"+1 888 917 4897",
    "sg:postcode":"60187",
    "sg:province":"IL",
    "sg:tags":[
        "painting",
        "painter",
        "contractor"
    ],
    "sg:website":"www.thosepaintingguys.com/",
    "wof:name":"Those Painting Guys",
    "wof:placetype":"venue"
},
  "geometry": {"coordinates":[-88.120794,41.864055],"type":"Point"}
}