{
  "type": "Feature",
  "properties": {
    "iso:country":"US",
    "sg:address":"328 N Market St",
    "sg:city":"Mount Carmel",
    "sg:classifiers":[
        {
            "category":"Professional",
            "subcategory":"Accounting & Tax Preparation",
            "type":"Services"
        }
    ],
    "sg:phone":"+1 618 262 5446",
    "sg:postcode":"62863",
    "sg:province":"IL",
    "wof:name":"Wilcox McCoekole & Co",
    "wof:placetype":"venue"
},
  "geometry": {"coordinates":[-87.760534,38.408606],"type":"Point"}
}