{
  "type": "Feature",
  "properties": {
    "iso:country":"US",
    "sg:address":"2 W Erie St",
    "sg:city":"Chicago",
    "sg:classifiers":[
        {
            "category":"Bars & Pubs",
            "type":"Food & Drink"
        },
        {
            "category":"Bars & Pubs",
            "subcategory":"Lounge",
            "type":"Food & Drink"
        }
    ],
    "sg:phone":"+1 312 202 6060",
    "sg:postcode":"60654",
    "sg:province":"IL",
    "sg:tags":[
        "cocktail"
    ],
    "sg:website":"www.danahotelandspa.com/rooftop-...",
    "wof:name":"Vertigo Sky Lounge",
    "wof:placetype":"venue"
},
  "geometry": {"coordinates":[-87.628361,41.894336],"type":"Point"}
}