{
  "type": "Feature",
  "properties": {
    "iso:country":"US",
    "sg:address":"300 N Highland Ave",
    "sg:city":"Aurora",
    "sg:classifiers":[
        {
            "category":"Sports & Exercise",
            "subcategory":"Gym",
            "type":"Entertainment"
        }
    ],
    "sg:phone":"+1 630 264 1571",
    "sg:postcode":"60506",
    "sg:province":"IL",
    "sg:tags":[
        "facility",
        "club",
        "gymnasium",
        "health",
        "fitness",
        "studio",
        "physical"
    ],
    "wof:name":"Gold's Gym",
    "wof:placetype":"venue"
},
  "geometry": {"coordinates":[-88.3291,41.765148],"type":"Point"}
}