{
  "type": "Feature",
  "properties": {
    "addr:full":"6520 S Cicero Ave Bedford Park IL 60638",
    "addr:housenumber":"6520",
    "addr:postcode":"60638",
    "addr:street":"S Cicero Ave",
    "iso:country":"US",
    "sg:address":"6520 S Cicero Ave",
    "sg:city":"Bedford Park",
    "sg:classifiers":[
        {
            "category":"Restaurant",
            "type":"Food & Drink"
        }
    ],
    "sg:phone":"+1 708 594 9500",
    "sg:postcode":"60638",
    "sg:province":"IL",
    "sg:website":"www.midwayhotelcenter.com",
    "wof:name":"Dempsey's Irish-American Grill",
    "wof:placetype":"venue"
},
  "geometry": {"coordinates":[-87.744401,41.77392],"type":"Point"}
}