{
  "type": "Feature",
  "properties": {
    "addr:full":"129 Phelps Ave Rockford IL 61108",
    "addr:housenumber":"129",
    "addr:postcode":"61108",
    "addr:street":"Phelps Ave",
    "iso:country":"US",
    "sg:address":"129 Phelps Ave",
    "sg:city":"Rockford",
    "sg:classifiers":[
        {
            "category":"Shopping",
            "type":"Retail Goods"
        }
    ],
    "sg:phone":"+1 815 395 6720",
    "sg:postcode":"61108",
    "sg:province":"IL",
    "sg:tags":[
        "equipment",
        "telephone",
        "supply"
    ],
    "wof:name":"Lexxon Network Inc",
    "wof:placetype":"venue"
},
  "geometry": {"coordinates":[-89.004654,42.26272],"type":"Point"}
}