{
  "type": "Feature",
  "properties": {
    "iso:country":"US",
    "sg:address":"12106 Hoyt Monken Rd",
    "sg:city":"Highland",
    "sg:classifiers":[
        {
            "category":"Organizations",
            "subcategory":"Labor Organization",
            "type":"Services"
        }
    ],
    "sg:phone":"+1 618 654 6881",
    "sg:postcode":"62249",
    "sg:province":"IL",
    "wof:name":"Paschal Enterprises Lc",
    "wof:placetype":"venue"
},
  "geometry": {"coordinates":[-89.702185,38.676756],"type":"Point"}
}