{
  "type": "Feature",
  "properties": {
    "iso:country":"US",
    "sg:address":"117 W Main St",
    "sg:city":"Cary",
    "sg:classifiers":[
        {
            "category":"Food & Beverages",
            "subcategory":"Bakery",
            "type":"Retail Goods"
        }
    ],
    "sg:phone":"+1 847 639 2266",
    "sg:postcode":"60013",
    "sg:province":"IL",
    "sg:tags":[
        "baker"
    ],
    "wof:name":"Peter's Bakery",
    "wof:placetype":"venue"
},
  "geometry": {"coordinates":[-88.241502,42.208607],"type":"Point"}
}