{
  "type": "Feature",
  "properties": {
    "addr:full":"24462 N Kelsey Rd Barrington IL 60010",
    "addr:housenumber":"24462",
    "addr:postcode":"60010",
    "addr:street":"N Kelsey Rd",
    "iso:country":"US",
    "sg:address":"24462 N Kelsey Rd",
    "sg:city":"Barrington",
    "sg:classifiers":[
        {
            "category":"Wholesale",
            "subcategory":"Medical Equipment & Supplies",
            "type":"Manufacturing & Wholesale Goods"
        }
    ],
    "sg:phone":"+1 847 381 5580",
    "sg:postcode":"60010",
    "sg:province":"IL",
    "sg:tags":[
        "product",
        "optical"
    ],
    "wof:name":"Vision Agency Ltd",
    "wof:placetype":"venue"
},
  "geometry": {"coordinates":[-88.161208,42.219609],"type":"Point"}
}