{
  "type": "Feature",
  "properties": {
    "iso:country":"US",
    "sg:address":"5025 W 63rd St",
    "sg:city":"Chicago",
    "sg:classifiers":[
        {
            "category":"Transit Center",
            "subcategory":"Freight",
            "type":"Transportation"
        }
    ],
    "sg:phone":"+1 773 767 5463",
    "sg:postcode":"60638",
    "sg:province":"IL",
    "sg:tags":[
        "cargo",
        "air",
        "express",
        "package"
    ],
    "wof:name":"Southwest Airlines Cargo",
    "wof:placetype":"venue"
},
  "geometry": {"coordinates":[-87.747753,41.778324],"type":"Point"}
}