{
  "type": "Feature",
  "properties": {
    "addr:full":"2139 N Milwaukee Ave Chicago IL 60647",
    "addr:housenumber":"2139",
    "addr:postcode":"60647",
    "addr:street":"N Milwaukee Ave",
    "iso:country":"US",
    "sg:address":"2139 N Milwaukee Ave",
    "sg:city":"Chicago",
    "sg:classifiers":[
        {
            "category":"Coffee & Tea",
            "type":"Food & Drink"
        }
    ],
    "sg:phone":"+1 312 233 2677",
    "sg:postcode":"60647",
    "sg:province":"IL",
    "sg:website":"www.earthandwatercafe.com",
    "wof:name":"Earth and Water Organic Cafe and Bistro",
    "wof:placetype":"venue"
},
  "geometry": {"coordinates":[-87.692667,41.920051],"type":"Point"}
}