{
  "type": "Feature",
  "properties": {
    "addr:full":"46 S Clark St Chicago IL 60603",
    "addr:housenumber":"46",
    "addr:postcode":"60603",
    "addr:street":"S Clark St",
    "iso:country":"US",
    "sg:address":"46 S Clark St",
    "sg:city":"Chicago",
    "sg:classifiers":[
        {
            "category":"Professional",
            "subcategory":"Accounting & Tax Preparation",
            "type":"Services"
        },
        {
            "category":"Banks & Credit Unions",
            "subcategory":"Financial Services",
            "type":"Services"
        }
    ],
    "sg:phone":"+1 312 263 0843",
    "sg:postcode":"60603",
    "sg:province":"IL",
    "sg:tags":[
        "return",
        "preparation-business",
        "taxes-consultants",
        "loan",
        "reporting",
        "representative",
        "alternative",
        "bookkeeping"
    ],
    "sg:website":"http://www.hrblock.com",
    "wof:name":"H&R Block",
    "wof:placetype":"venue"
},
  "geometry": {"coordinates":[-87.63085100000001,41.881273],"type":"Point"}
}