{
  "type": "Feature",
  "properties": {
    "iso:country":"US",
    "sg:address":"4200 W Lawrence Avenue",
    "sg:city":"Chicago",
    "sg:classifiers":[
        {
            "category":"Education",
            "subcategory":"Music School",
            "type":"Public Place"
        }
    ],
    "sg:phone":"+1 773 725 7700",
    "sg:postcode":"60630",
    "sg:province":"IL",
    "sg:tags":[
        "instrument",
        "teacher",
        "musical"
    ],
    "wof:name":"Kims International Music",
    "wof:placetype":"venue"
},
  "geometry": {"coordinates":[-87.733028,41.968182],"type":"Point"}
}