{
  "type": "Feature",
  "properties": {
    "iso:country":"US",
    "sg:address":"6254 Valley Knoll Dr",
    "sg:city":"Rockford",
    "sg:classifiers":[
        {
            "category":"Organizations",
            "subcategory":"Religious Organization",
            "type":"Services"
        }
    ],
    "sg:phone":"+1 815 398 0853",
    "sg:postcode":"61109",
    "sg:province":"IL",
    "sg:tags":[
        "school",
        "church"
    ],
    "sg:website":"www.stritarockford.org",
    "wof:name":"Saint Rita Church",
    "wof:placetype":"venue"
},
  "geometry": {"coordinates":[-88.993991,42.23526],"type":"Point"}
}