{
  "type": "Feature",
  "properties": {
    "addr:full":"13975 W Polo Trail Dr Lake Forest IL 60045",
    "addr:housenumber":"13975",
    "addr:postcode":"60045",
    "addr:street":"W Polo Trail Dr",
    "iso:country":"US",
    "sg:address":"13975 W Polo Trail Dr",
    "sg:city":"Lake Forest",
    "sg:classifiers":[
        {
            "category":"Manufacturing",
            "subcategory":"Apparel",
            "type":"Manufacturing & Wholesale Goods"
        }
    ],
    "sg:phone":"+1 847 247 0380",
    "sg:postcode":"60045",
    "sg:province":"IL",
    "sg:tags":[
        "hospital",
        "mfg"
    ],
    "wof:name":"Dowling Textile Company",
    "wof:placetype":"venue"
},
  "geometry": {"coordinates":[-87.90463,42.267911],"type":"Point"}
}