{
  "type": "Feature",
  "properties": {
    "iso:country":"US",
    "sg:address":"113 Orange St",
    "sg:city":"Anna",
    "sg:classifiers":[
        {
            "category":"Organizations",
            "subcategory":"Religious Organization",
            "type":"Services"
        }
    ],
    "sg:phone":"+1 618 833 3100",
    "sg:postcode":"62906",
    "sg:province":"IL",
    "sg:tags":[
        "clergy"
    ],
    "wof:name":"Hertenstein Richard Rev",
    "wof:placetype":"venue"
},
  "geometry": {"coordinates":[-89.256849,37.460742],"type":"Point"}
}