{
  "type": "Feature",
  "properties": {
    "iso:country":"US",
    "sg:address":"5743 Country Ct",
    "sg:city":"Roscoe",
    "sg:classifiers":[
        {
            "category":"Building & Trades",
            "subcategory":"Electrical",
            "type":"Services"
        }
    ],
    "sg:phone":"+1 815 877 7265",
    "sg:postcode":"61073",
    "sg:province":"IL",
    "sg:tags":[
        "electrical",
        "contractor"
    ],
    "wof:name":"Salmon Electric",
    "wof:placetype":"venue"
},
  "geometry": {"coordinates":[-89.010412,42.400482],"type":"Point"}
}