{
  "type": "Feature",
  "properties": {
    "iso:country":"US",
    "sg:address":"15534 Cicero Ave",
    "sg:city":"Oak Forest",
    "sg:classifiers":[
        {
            "category":"Shopping",
            "type":"Retail Goods"
        }
    ],
    "sg:phone":"+1   ",
    "sg:postcode":"60452",
    "sg:province":"IL",
    "sg:tags":[
        "merchandise"
    ],
    "wof:name":"Timberwick Candle Factory Outl",
    "wof:placetype":"venue"
},
  "geometry": {"coordinates":[-87.73679,41.609375],"type":"Point"}
}