{
  "type": "Feature",
  "properties": {
    "addr:full":"7840 Ogden Ave Ste 3 Lyons IL 60534",
    "addr:housenumber":"7840",
    "addr:postcode":"60534",
    "addr:street":"Ogden Ave Ste 3",
    "iso:country":"US",
    "sg:address":"7840 Ogden Ave Ste 3",
    "sg:city":"Lyons",
    "sg:classifiers":[
        {
            "category":"Personal",
            "subcategory":"Tanning Parlor",
            "type":"Services"
        }
    ],
    "sg:phone":"+1 708 442 1099",
    "sg:postcode":"60534",
    "sg:province":"IL",
    "wof:name":"Ultramax Tan",
    "wof:placetype":"venue"
},
  "geometry": {"coordinates":[-87.82240299999999,41.813599],"type":"Point"}
}