{
  "type": "Feature",
  "properties": {
    "iso:country":"US",
    "sg:address":"15 E Golf Rd",
    "sg:city":"Arlington Hts",
    "sg:classifiers":[
        {
            "category":"Personal",
            "subcategory":"Beauty Salon",
            "type":"Services"
        }
    ],
    "sg:phone":"+1 847 956 1660",
    "sg:postcode":"60005",
    "sg:province":"IL",
    "wof:name":"Dimari Hair & Spa Inc",
    "wof:placetype":"venue"
},
  "geometry": {"coordinates":[-87.97506,42.051372],"type":"Point"}
}