{
  "type": "Feature",
  "properties": {
    "addr:full":"2804 Hidden Valley Ct Carpentersville IL 60110",
    "addr:housenumber":"2804",
    "addr:postcode":"60110",
    "addr:street":"Hidden Valley Ct",
    "iso:country":"US",
    "sg:address":"2804 Hidden Valley Ct",
    "sg:city":"Carpentersville",
    "sg:classifiers":[
        {
            "category":"Freight",
            "type":"Transportation"
        },
        {
            "category":"Travel",
            "subcategory":"Travel Agent",
            "type":"Entertainment"
        },
        {
            "category":"Local Transit",
            "type":"Transportation"
        }
    ],
    "sg:phone":"+1 847 844 7558",
    "sg:postcode":"60110",
    "sg:province":"IL",
    "sg:tags":[
        "consultant",
        "provider",
        "broker",
        "trucking"
    ],
    "wof:name":"Blizzard Express Inc",
    "wof:placetype":"venue"
},
  "geometry": {"coordinates":[-88.317047,42.122047],"type":"Point"}
}