{
  "type": "Feature",
  "properties": {
    "iso:country":"US",
    "sg:address":"2710 E 79th St",
    "sg:city":"Chicago",
    "sg:classifiers":[
        {
            "category":"Building & Trades",
            "subcategory":"Plumbing",
            "type":"Services"
        }
    ],
    "sg:phone":"+1 773 375 4600",
    "sg:postcode":"60649",
    "sg:province":"IL",
    "sg:tags":[
        "heating",
        "contractor",
        "furnaces-repairing",
        "cleaning",
        "air conditioning"
    ],
    "sg:website":"http://www.ralphsheating.net",
    "wof:name":"Ralph's Heating Service Inc.",
    "wof:placetype":"venue"
},
  "geometry": {"coordinates":[-87.558689,41.751839],"type":"Point"}
}