{
  "type": "Feature",
  "properties": {
    "addr:full":"1807 US Hwy 45 Gilman IL 60938",
    "addr:housenumber":"1807",
    "addr:postcode":"60938",
    "addr:street":"Us Hwy 45",
    "iso:country":"US",
    "sg:address":"1807 US Hwy 45",
    "sg:city":"Gilman",
    "sg:classifiers":[
        {
            "category":"Freight",
            "type":"Transportation"
        }
    ],
    "sg:phone":"+1 815 265 8236",
    "sg:postcode":"60938",
    "sg:province":"IL",
    "sg:tags":[
        "warehouse",
        "self",
        "storage"
    ],
    "wof:name":"F S Heritage Inc",
    "wof:placetype":"venue"
},
  "geometry": {"coordinates":[-87.977796,40.768593],"type":"Point"}
}