{
  "type": "Feature",
  "properties": {
    "addr:full":"8733 Indian Trail Rd Ashley IL 62808",
    "addr:housenumber":"8733",
    "addr:postcode":"62808",
    "addr:street":"Indian Trail Rd",
    "iso:country":"US",
    "sg:address":"8733 Indian Trail Rd",
    "sg:city":"Ashley",
    "sg:classifiers":[
        {
            "category":"Farming",
            "subcategory":"Livestock Farm",
            "type":"Manufacturing & Wholesale Goods"
        }
    ],
    "sg:phone":"+1 618 327 3809",
    "sg:postcode":"62808",
    "sg:province":"IL",
    "sg:tags":[
        "beef",
        "feedlot",
        "cattle"
    ],
    "wof:name":"Glenn Fehrman",
    "wof:placetype":"venue"
},
  "geometry": {"coordinates":[-89.29917500000001,38.34387],"type":"Point"}
}