{
  "type": "Feature",
  "properties": {
    "iso:country":"US",
    "sg:address":"2620 Madison Ave",
    "sg:city":"Granite City",
    "sg:classifiers":[
        {
            "category":"Personal",
            "subcategory":"Barber",
            "type":"Services"
        }
    ],
    "sg:phone":"+1 618 451 7453",
    "sg:postcode":"62040",
    "sg:province":"IL",
    "wof:name":"Linda's Ole Fashion Barber Shop",
    "wof:placetype":"venue"
},
  "geometry": {"coordinates":[-90.13310199999999,38.709999],"type":"Point"}
}