{
  "type": "Feature",
  "properties": {
    "addr:full":"554 N Convent St Bourbonnais IL 60914",
    "addr:housenumber":"554",
    "addr:postcode":"60914",
    "addr:street":"N Convent St",
    "iso:country":"US",
    "sg:address":"554 N Convent St",
    "sg:city":"Bourbonnais",
    "sg:classifiers":[
        {
            "category":"Retail",
            "subcategory":"Auto Repair",
            "type":"Services"
        }
    ],
    "sg:phone":"+1 815 932 0145",
    "sg:postcode":"60914",
    "sg:province":"IL",
    "sg:tags":[
        "repairing",
        "automotive",
        "automobile",
        "general"
    ],
    "wof:name":"Levi's Garage",
    "wof:placetype":"venue"
},
  "geometry": {"coordinates":[-87.875237,41.16272],"type":"Point"}
}