{
  "type": "Feature",
  "properties": {
    "addr:full":"16329 W 159th St Lockport IL 60441",
    "addr:housenumber":"16329",
    "addr:postcode":"60441",
    "addr:street":"W 159Th St",
    "iso:country":"US",
    "sg:address":"16329 W 159th St",
    "sg:city":"Lockport",
    "sg:classifiers":[
        {
            "category":"Organizations",
            "subcategory":"Religious Organization",
            "type":"Services"
        }
    ],
    "sg:phone":"+1 815 838 9105",
    "sg:postcode":"60441",
    "sg:province":"IL",
    "sg:tags":[
        "church"
    ],
    "wof:name":"First Assembly Of God",
    "wof:placetype":"venue"
},
  "geometry": {"coordinates":[-88.01505899999999,41.598051],"type":"Point"}
}