{
  "type": "Feature",
  "properties": {
    "addr:full":"428 Main St Marseilles IL 61341",
    "addr:housenumber":"428",
    "addr:postcode":"61341",
    "addr:street":"Main St",
    "iso:country":"US",
    "sg:address":"428 Main St",
    "sg:city":"Marseilles",
    "sg:classifiers":[
        {
            "category":"Shopping",
            "subcategory":"Used Merchandise",
            "type":"Retail Goods"
        }
    ],
    "sg:phone":"+1   ",
    "sg:postcode":"61341",
    "sg:province":"IL",
    "sg:tags":[
        "new",
        "furniture"
    ],
    "wof:name":"Callas Antique & Used Furn",
    "wof:placetype":"venue"
},
  "geometry": {"coordinates":[-88.708366,41.329845],"type":"Point"}
}