{
  "type": "Feature",
  "properties": {
    "addr:full":"488 Orchard St Antioch IL 60002",
    "addr:housenumber":"488",
    "addr:postcode":"60002",
    "addr:street":"Orchard St",
    "iso:country":"US",
    "sg:address":"488 Orchard St",
    "sg:city":"Antioch",
    "sg:classifiers":[
        {
            "category":"Home & Garden",
            "subcategory":"Hardware",
            "type":"Retail Goods"
        }
    ],
    "sg:phone":"+1 847 395 4200",
    "sg:postcode":"60002",
    "sg:province":"IL",
    "sg:tags":[
        "store"
    ],
    "sg:website":"www.truevalue.com",
    "wof:name":"Antioch True Value Hardware Inc",
    "wof:placetype":"venue"
},
  "geometry": {"coordinates":[-88.10019699999999,42.479301],"type":"Point"}
}