{
  "type": "Feature",
  "properties": {
    "iso:country":"US",
    "sg:address":"4239 Venture Dr",
    "sg:city":"Peru",
    "sg:classifiers":[
        {
            "category":"Retail",
            "subcategory":"Auto Repair",
            "type":"Services"
        }
    ],
    "sg:phone":"+1 815 223 6984",
    "sg:postcode":"61354",
    "sg:province":"IL",
    "sg:tags":[
        "automotive"
    ],
    "wof:name":"Penzoil 10 Mnute Oil Chnge Ctr",
    "wof:placetype":"venue"
},
  "geometry": {"coordinates":[-89.127252,41.36149],"type":"Point"}
}