{
  "type": "Feature",
  "properties": {
    "iso:country":"US",
    "sg:address":"15229 Ashland Ave",
    "sg:city":"Harvey",
    "sg:classifiers":[
        {
            "category":"Personal",
            "type":"Services"
        }
    ],
    "sg:phone":"+1 708 331 6645",
    "sg:postcode":"60426",
    "sg:province":"IL",
    "sg:tags":[
        "towing"
    ],
    "wof:name":"A & K Towing",
    "wof:placetype":"venue"
},
  "geometry": {"coordinates":[-87.65547100000001,41.612491],"type":"Point"}
}