{
  "type": "Feature",
  "properties": {
    "iso:country":"US",
    "sg:address":"114 W 3rd St",
    "sg:city":"Elmhurst",
    "sg:classifiers":[
        {
            "category":"Shopping",
            "subcategory":"Used Merchandise",
            "type":"Retail Goods"
        }
    ],
    "sg:phone":"+1   ",
    "sg:postcode":"60126",
    "sg:province":"IL",
    "wof:name":"Elm Classic Consignment Shop",
    "wof:placetype":"venue"
},
  "geometry": {"coordinates":[-87.940921,41.903892],"type":"Point"}
}