{
  "type": "Feature",
  "properties": {
    "iso:country":"US",
    "sg:address":"374 Maple Dr",
    "sg:city":"Bethalto",
    "sg:classifiers":[
        {
            "category":"Insurance",
            "subcategory":"Hazard Insurance",
            "type":"Services"
        }
    ],
    "sg:phone":"+1 618 377 3852",
    "sg:postcode":"62010",
    "sg:province":"IL",
    "wof:name":"James D Luebbert",
    "wof:placetype":"venue"
},
  "geometry": {"coordinates":[-90.007377,38.89452],"type":"Point"}
}