{
  "type": "Feature",
  "properties": {
    "iso:country":"US",
    "sg:address":"160 Biesterfield Rd",
    "sg:city":"Elk Grove Village",
    "sg:classifiers":[
        {
            "category":"Health Services",
            "subcategory":"Doctor",
            "type":"Services"
        }
    ],
    "sg:phone":"+1 847 437 1200",
    "sg:postcode":"60007",
    "sg:province":"IL",
    "sg:tags":[
        "medical"
    ],
    "wof:name":"Rabinowitz Richard R",
    "wof:placetype":"venue"
},
  "geometry": {"coordinates":[-88.007947,42.003606],"type":"Point"}
}