{
  "type": "Feature",
  "properties": {
    "iso:country":"US",
    "sg:address":"11 W Paddock St",
    "sg:city":"Crystal Lake",
    "sg:classifiers":[
        {
            "category":"Professional",
            "subcategory":"Lawyer & Legal Services",
            "type":"Services"
        }
    ],
    "sg:phone":"+1 815 455 6180",
    "sg:postcode":"60014",
    "sg:province":"IL",
    "wof:name":"James Rosenberg",
    "wof:placetype":"venue"
},
  "geometry": {"coordinates":[-88.321285,42.239239],"type":"Point"}
}