{
  "type": "Feature",
  "properties": {
    "addr:full":"103 W 112th St Chicago IL 60628",
    "addr:housenumber":"103",
    "addr:postcode":"60628",
    "addr:street":"W 112Th St",
    "iso:country":"US",
    "sg:address":"103 W 112th St",
    "sg:city":"Chicago",
    "sg:classifiers":[
        {
            "category":"Social Services",
            "type":"Services"
        },
        {
            "category":"Building & Trades",
            "subcategory":"Landscaping Services",
            "type":"Services"
        },
        {
            "category":"Health Services",
            "subcategory":"Nursing And Care Facility",
            "type":"Services"
        }
    ],
    "sg:phone":"+1 773 821 8608",
    "sg:postcode":"60628",
    "sg:province":"IL",
    "sg:tags":[
        "personal",
        "home",
        "aged",
        "homes-institutional"
    ],
    "wof:name":"Cornerstone Recovering Community",
    "wof:placetype":"venue"
},
  "geometry": {"coordinates":[-87.625806,41.690719],"type":"Point"}
}