{
  "type": "Feature",
  "properties": {
    "addr:full":"5205 N Nagle Ave Chicago IL 60630",
    "addr:housenumber":"5205",
    "addr:postcode":"60630",
    "addr:street":"N Nagle Ave",
    "iso:country":"US",
    "sg:address":"5205 N Nagle Ave",
    "sg:city":"Chicago",
    "sg:classifiers":[
        {
            "category":"Bakery",
            "type":"Food & Drink"
        },
        {
            "category":"Coffee & Tea",
            "type":"Food & Drink"
        },
        {
            "category":"Bagels",
            "type":"Food & Drink"
        },
        {
            "category":"Donuts",
            "type":"Food & Drink"
        }
    ],
    "sg:menulink":"http://www.allmenus.com/il/chicago/135084-dunkin-donuts/menu/",
    "sg:phone":"+1 773 763 7160",
    "sg:postcode":"60630",
    "sg:province":"IL",
    "sg:tags":[
        "american",
        "pastry"
    ],
    "wof:name":"Dunkin' Donuts",
    "wof:placetype":"venue"
},
  "geometry": {"coordinates":[-87.787764,41.975915],"type":"Point"}
}