{
  "type": "Feature",
  "properties": {
    "iso:country":"US",
    "sg:address":"1901 N Eastern Ave",
    "sg:city":"Mc Henry",
    "sg:classifiers":[
        {
            "category":"Organizations",
            "subcategory":"Religious Organization",
            "type":"Services"
        }
    ],
    "sg:phone":"+1 815 578 0548",
    "sg:postcode":"60050",
    "sg:province":"IL",
    "wof:name":"Assembly Solutions",
    "wof:placetype":"venue"
},
  "geometry": {"coordinates":[-88.28675,42.353968],"type":"Point"}
}