{
  "type": "Feature",
  "properties": {
    "iso:country":"US",
    "sg:address":"1460 Golf Rd",
    "sg:city":"Rolling Meadows",
    "sg:classifiers":[
        {
            "category":"Shopping",
            "type":"Retail Goods"
        }
    ],
    "sg:phone":"+1   ",
    "sg:postcode":"60008",
    "sg:province":"IL",
    "sg:tags":[
        "merchandise"
    ],
    "wof:name":"C & A Unisource",
    "wof:placetype":"venue"
},
  "geometry": {"coordinates":[-87.996751,42.05148],"type":"Point"}
}