{
  "type": "Feature",
  "properties": {
    "addr:full":"230 Carroll St Colona IL 61241",
    "addr:housenumber":"230",
    "addr:postcode":"61241",
    "addr:street":"Carroll St",
    "iso:country":"US",
    "sg:address":"230 Carroll St",
    "sg:city":"Colona",
    "sg:phone":"+1 309 949 2484",
    "sg:postcode":"61241",
    "sg:province":"IL",
    "sg:tags":[
        "farm",
        "corn",
        "soybean"
    ],
    "wof:name":"Gladys Carroll",
    "wof:placetype":"venue"
},
  "geometry": {"coordinates":[-90.34171600000001,41.469557],"type":"Point"}
}