{
  "type": "Feature",
  "properties": {
    "iso:country":"US",
    "sg:address":"3248 Harlem Ave",
    "sg:city":"Riverside",
    "sg:classifiers":[
        {
            "category":"Shopping",
            "subcategory":"Clothing, Apparel, & Fashions",
            "type":"Retail Goods"
        }
    ],
    "sg:phone":"+1 708 447 5400",
    "sg:postcode":"60546",
    "sg:province":"IL",
    "sg:tags":[
        "accessory",
        "clothing",
        "women's"
    ],
    "wof:name":"Equilibrium Your Body",
    "wof:placetype":"venue"
},
  "geometry": {"coordinates":[-87.803169,41.833405],"type":"Point"}
}