{
  "type": "Feature",
  "properties": {
    "addr:full":"5332 35th St Rockford IL 61109",
    "addr:housenumber":"5332",
    "addr:postcode":"61109",
    "addr:street":"35Th St",
    "iso:country":"US",
    "sg:address":"5332 35th St",
    "sg:city":"Rockford",
    "sg:phone":"+1 815 874 2737",
    "sg:postcode":"61109",
    "sg:province":"IL",
    "sg:tags":[
        "farm",
        "corn",
        "soybean"
    ],
    "wof:name":"Thomas Dorn",
    "wof:placetype":"venue"
},
  "geometry": {"coordinates":[-89.033349,42.204117],"type":"Point"}
}