{
  "type": "Feature",
  "properties": {
    "addr:full":"395 Lakeside Dr Roselle IL 60172",
    "addr:housenumber":"395",
    "addr:postcode":"60172",
    "addr:street":"Lakeside Dr",
    "iso:country":"US",
    "sg:address":"395 Lakeside Dr",
    "sg:city":"Roselle",
    "sg:classifiers":[
        {
            "category":"Restaurant",
            "type":"Food & Drink"
        }
    ],
    "sg:phone":"+1 630 894 1166",
    "sg:postcode":"60172",
    "sg:province":"IL",
    "sg:tags":[
        "pizza"
    ],
    "wof:name":"Nancy's Pizzeria",
    "wof:placetype":"venue"
},
  "geometry": {"coordinates":[-88.075177,41.990746],"type":"Point"}
}