{
  "type": "Feature",
  "properties": {
    "addr:full":"1300 N Milwaukee Ave Chicago IL 60622",
    "addr:housenumber":"1300",
    "addr:postcode":"60622",
    "addr:street":"N Milwaukee Ave",
    "iso:country":"US",
    "sg:address":"1300 N Milwaukee Ave",
    "sg:city":"Chicago",
    "sg:classifiers":[
        {
            "category":"Food & Beverages",
            "subcategory":"Specialty",
            "type":"Retail Goods"
        }
    ],
    "sg:phone":"+1 773 418 0567",
    "sg:postcode":"60622",
    "sg:province":"IL",
    "sg:tags":[
        "product",
        "health",
        "diet"
    ],
    "wof:name":"Garden Of Health Inc",
    "wof:placetype":"venue"
},
  "geometry": {"coordinates":[-87.66944100000001,41.90527],"type":"Point"}
}