{
  "type": "Feature",
  "properties": {
    "iso:country":"US",
    "sg:address":"815 N Delaware Ave",
    "sg:city":"Belleville",
    "sg:classifiers":[
        {
            "category":"Autos & Motor Vehicles",
            "subcategory":"Auto Supplies",
            "type":"Retail Goods"
        }
    ],
    "sg:phone":"+1   ",
    "sg:postcode":"62221",
    "sg:province":"IL",
    "sg:tags":[
        "repair",
        "general"
    ],
    "wof:name":"Patterson Automotive",
    "wof:placetype":"venue"
},
  "geometry": {"coordinates":[-89.969537,38.527643],"type":"Point"}
}