{
  "type": "Feature",
  "properties": {
    "addr:full":"230 N Evergreen Ave Elmhurst IL 60126",
    "addr:housenumber":"230",
    "addr:postcode":"60126",
    "addr:street":"N Evergreen Ave",
    "iso:country":"US",
    "sg:address":"230 N Evergreen Ave",
    "sg:city":"Elmhurst",
    "sg:classifiers":[
        {
            "category":"Professional",
            "subcategory":"Art Services",
            "type":"Services"
        }
    ],
    "sg:phone":"+1 630 834 2871",
    "sg:postcode":"60126",
    "sg:province":"IL",
    "sg:tags":[
        "designer",
        "display",
        "producer"
    ],
    "wof:name":"Rj Peters Design & Marketing",
    "wof:placetype":"venue"
},
  "geometry": {"coordinates":[-87.947405,41.904427],"type":"Point"}
}