{
  "type": "Feature",
  "properties": {
    "iso:country":"US",
    "sg:address":"4 Forestdale Park",
    "sg:city":"Calumet City",
    "sg:classifiers":[
        {
            "category":"Professional",
            "subcategory":"Management & Consulting",
            "type":"Services"
        }
    ],
    "sg:phone":"+1 708 891 6760",
    "sg:postcode":"60409",
    "sg:province":"IL",
    "sg:tags":[
        "construction"
    ],
    "wof:name":"Beautiful House",
    "wof:placetype":"venue"
},
  "geometry": {"coordinates":[-87.525229,41.60209],"type":"Point"}
}