{
  "type": "Feature",
  "properties": {
    "iso:country":"US",
    "sg:address":"387 Gregory M Sears Dr",
    "sg:city":"Gilberts",
    "sg:classifiers":[
        {
            "category":"Building & Trades",
            "subcategory":"Equipment Rental",
            "type":"Services"
        }
    ],
    "sg:phone":"+1 847 695 6841",
    "sg:postcode":"60136",
    "sg:province":"IL",
    "wof:name":"Jump To The Moon Inc",
    "wof:placetype":"venue"
},
  "geometry": {"coordinates":[-88.361688,42.079319],"type":"Point"}
}