{
  "type": "Feature",
  "properties": {
    "iso:country":"US",
    "sg:address":"10 S La Salle St Ste 1130",
    "sg:city":"Chicago",
    "sg:classifiers":[
        {
            "category":"Professional",
            "subcategory":"Lawyer & Legal Services",
            "type":"Services"
        }
    ],
    "sg:phone":"+1 312 372 8506",
    "sg:postcode":"60603",
    "sg:province":"IL",
    "sg:tags":[
        "attorney",
        "accident",
        "personal",
        "damage",
        "injury",
        "property",
        "insurance",
        "law",
        "bankruptcy"
    ],
    "sg:website":"concannoninjurylaw.com",
    "wof:name":"Concannon Michael P Ltd",
    "wof:placetype":"venue"
},
  "geometry": {"coordinates":[-87.632527,41.881782],"type":"Point"}
}