{
  "type": "Feature",
  "properties": {
    "addr:full":"1924 N Paulina St Chicago IL 60622",
    "addr:housenumber":"1924",
    "addr:postcode":"60622",
    "addr:street":"N Paulina St",
    "iso:country":"US",
    "sg:address":"1924 N Paulina St",
    "sg:city":"Chicago",
    "sg:classifiers":[
        {
            "category":"Autos & Motor Vehicles",
            "subcategory":"Automobile Sales",
            "type":"Retail Goods"
        },
        {
            "category":"Retail",
            "subcategory":"Auto Repair",
            "type":"Services"
        }
    ],
    "sg:phone":"+1 773 227 3200",
    "sg:postcode":"60622",
    "sg:province":"IL",
    "sg:tags":[
        "car",
        "new",
        "automotive"
    ],
    "sg:website":"www.orloff.com",
    "wof:name":"Howard Orloff Imports, Inc",
    "wof:placetype":"venue"
},
  "geometry": {"coordinates":[-87.670276,41.916729],"type":"Point"}
}