{
  "type": "Feature",
  "properties": {
    "iso:country":"US",
    "sg:address":"7975 W Barbara Ln",
    "sg:city":"Frankfort",
    "sg:classifiers":[
        {
            "category":"Professional",
            "type":"Services"
        }
    ],
    "sg:phone":"+1 815 469 8151",
    "sg:postcode":"60423",
    "sg:province":"IL",
    "sg:tags":[
        "establishment"
    ],
    "wof:name":"Commonwealth Metals",
    "wof:placetype":"venue"
},
  "geometry": {"coordinates":[-87.810857,41.526455],"type":"Point"}
}