{
  "type": "Feature",
  "properties": {
    "iso:country":"US",
    "sg:address":"2650 Ridge Ave",
    "sg:city":"Evanston",
    "sg:classifiers":[
        {
            "category":"Health Services",
            "subcategory":"Doctor",
            "type":"Services"
        }
    ],
    "sg:phone":"+1 847 570 2565",
    "sg:postcode":"60201",
    "sg:province":"IL",
    "sg:tags":[
        "physician",
        "surgeon"
    ],
    "wof:name":"John F Golan MD",
    "wof:placetype":"venue"
},
  "geometry": {"coordinates":[-87.683174,42.06577],"type":"Point"}
}