{
  "type": "Feature",
  "properties": {
    "iso:country":"US",
    "sg:address":"3143 N Hamlin Ave",
    "sg:city":"Chicago",
    "sg:classifiers":[
        {
            "category":"Shopping",
            "subcategory":"Jewelry",
            "type":"Retail Goods"
        }
    ],
    "sg:phone":"+1 773 583 0194",
    "sg:postcode":"60618",
    "sg:province":"IL",
    "wof:name":"Jewelry Gifts & Tools",
    "wof:placetype":"venue"
},
  "geometry": {"coordinates":[-87.721901,41.938702],"type":"Point"}
}