{
  "type": "Feature",
  "properties": {
    "iso:country":"US",
    "sg:address":"2016 E Woodview Dr",
    "sg:city":"Mount Prospect",
    "sg:classifiers":[
        {
            "category":"Professional",
            "type":"Services"
        }
    ],
    "sg:phone":"+1 847 827 9212",
    "sg:postcode":"60056",
    "sg:province":"IL",
    "wof:name":"Wordplay & Associates",
    "wof:placetype":"venue"
},
  "geometry": {"coordinates":[-87.891671,42.098622],"type":"Point"}
}