{
  "type": "Feature",
  "properties": {
    "addr:full":"9 March Ct Columbia IL 62236",
    "addr:housenumber":"9",
    "addr:postcode":"62236",
    "addr:street":"March Ct",
    "iso:country":"US",
    "sg:address":"9 March Ct",
    "sg:city":"Columbia",
    "sg:classifiers":[
        {
            "category":"Building & Trades",
            "subcategory":"Cleaning & Sanitation",
            "type":"Services"
        }
    ],
    "sg:phone":"+1 618 281 8262",
    "sg:postcode":"62236",
    "sg:province":"IL",
    "sg:tags":[
        "janitor"
    ],
    "wof:name":"Nelson's Commercial Cleaning",
    "wof:placetype":"venue"
},
  "geometry": {"coordinates":[-90.197501,38.456482],"type":"Point"}
}