{
  "type": "Feature",
  "properties": {
    "iso:country":"US",
    "sg:address":"907 Main St",
    "sg:city":"Highland",
    "sg:classifiers":[
        {
            "category":"Organizations",
            "subcategory":"Professional Association",
            "type":"Services"
        }
    ],
    "sg:phone":"+1 618 654 3721",
    "sg:postcode":"62249",
    "sg:province":"IL",
    "sg:tags":[
        "chambers",
        "commerce"
    ],
    "wof:name":"Highland Chamber Of Commerce",
    "wof:placetype":"venue"
},
  "geometry": {"coordinates":[-89.679091,38.740523],"type":"Point"}
}