{
  "type": "Feature",
  "properties": {
    "iso:country":"US",
    "sg:address":"10314 Lincoln Trl",
    "sg:city":"Fairview Heights",
    "sg:classifiers":[
        {
            "category":"Manufacturing",
            "subcategory":"Printing",
            "type":"Manufacturing & Wholesale Goods"
        }
    ],
    "sg:phone":"+1 618 398 6639",
    "sg:postcode":"62208",
    "sg:province":"IL",
    "sg:tags":[
        "publisher"
    ],
    "wof:name":"KMH Printing & Publishing",
    "wof:placetype":"venue"
},
  "geometry": {"coordinates":[-90.002017,38.59287],"type":"Point"}
}