{
  "type": "Feature",
  "properties": {
    "addr:full":"4419 W 95th St Oak Lawn IL 60453",
    "addr:housenumber":"4419",
    "addr:postcode":"60453",
    "addr:street":"W 95Th St",
    "iso:country":"US",
    "sg:address":"4419 W 95th St",
    "sg:city":"Oak Lawn",
    "sg:classifiers":[
        {
            "category":"Real Estate",
            "subcategory":"Real Estate Services",
            "type":"Services"
        }
    ],
    "sg:phone":"+1 708 424 8600",
    "sg:postcode":"60453",
    "sg:province":"IL",
    "sg:tags":[
        "abstract",
        "title"
    ],
    "wof:name":"Greater Illinois Title Co 4",
    "wof:placetype":"venue"
},
  "geometry": {"coordinates":[-87.731691,41.720182],"type":"Point"}
}