{
  "type": "Feature",
  "properties": {
    "addr:full":"55 W Monroe St Ste 690 Chicago IL 60603",
    "addr:housenumber":"55",
    "addr:postcode":"60603",
    "addr:street":"W Monroe St Ste 690",
    "iso:country":"US",
    "sg:address":"55 W Monroe St Ste 690",
    "sg:city":"Chicago",
    "sg:classifiers":[
        {
            "category":"Professional",
            "subcategory":"Employment Agencies",
            "type":"Services"
        }
    ],
    "sg:phone":"+1 312 853 3434",
    "sg:postcode":"60603",
    "sg:province":"IL",
    "sg:tags":[
        "opportunity",
        "contractor"
    ],
    "sg:website":"http://www.kellyservices.com",
    "wof:name":"Kelly Servicez",
    "wof:placetype":"venue"
},
  "geometry": {"coordinates":[-87.629768,41.88069],"type":"Point"}
}