{
  "type": "Feature",
  "properties": {
    "iso:country":"US",
    "sg:address":"809 E 63rd St",
    "sg:city":"Chicago",
    "sg:classifiers":[
        {
            "category":"Restaurant",
            "type":"Food & Drink"
        },
        {
            "category":"Food & Beverages",
            "subcategory":"Ethnic Foods",
            "type":"Retail Goods"
        }
    ],
    "sg:phone":"+1 773 643 6670",
    "sg:postcode":"60637",
    "sg:province":"IL",
    "sg:tags":[
        "diner",
        "soul"
    ],
    "sg:website":"daleysrestaurant.com",
    "wof:name":"Daley's Restaurant",
    "wof:placetype":"venue"
},
  "geometry": {"coordinates":[-87.605445,41.780016],"type":"Point"}
}