{
  "type": "Feature",
  "properties": {
    "addr:full":"5104 N Broadway St Chicago IL 60640",
    "addr:housenumber":"5104",
    "addr:postcode":"60640",
    "addr:street":"N Broadway St",
    "iso:country":"US",
    "sg:address":"5104 N Broadway St",
    "sg:city":"Chicago",
    "sg:classifiers":[
        {
            "category":"Professional",
            "subcategory":"Accounting & Tax Preparation",
            "type":"Services"
        }
    ],
    "sg:phone":"+1 773 989 8809",
    "sg:postcode":"60640",
    "sg:province":"IL",
    "sg:tags":[
        "return"
    ],
    "wof:name":"TTT Proexpert",
    "wof:placetype":"venue"
},
  "geometry": {"coordinates":[-87.65991,41.975114],"type":"Point"}
}