{
  "type": "Feature",
  "properties": {
    "iso:country":"US",
    "sg:address":"931 E Oakton St",
    "sg:city":"Des Plaines",
    "sg:classifiers":[
        {
            "category":"Retail",
            "subcategory":"Laundry & Dry Cleaning",
            "type":"Services"
        }
    ],
    "sg:phone":"+1 847 298 4240",
    "sg:postcode":"60018",
    "sg:province":"IL",
    "sg:tags":[
        "drycleaning",
        "plant",
        "coin"
    ],
    "wof:name":"Norgetown S S & Prof Clr",
    "wof:placetype":"venue"
},
  "geometry": {"coordinates":[-87.899336,42.023682],"type":"Point"}
}