{
  "type": "Feature",
  "properties": {
    "addr:full":"27W024 Jewell Rd Winfield IL 60190",
    "addr:housenumber":"27w024",
    "addr:postcode":"60190",
    "addr:street":"Jewell Rd",
    "iso:country":"US",
    "sg:address":"27W024 Jewell Rd",
    "sg:city":"Winfield",
    "sg:classifiers":[
        {
            "category":"Real Estate",
            "subcategory":"Architect",
            "type":"Services"
        }
    ],
    "sg:phone":"+1 630 260 9559",
    "sg:postcode":"60190",
    "sg:province":"IL",
    "wof:name":"Lsk Consultants Inc",
    "wof:placetype":"venue"
},
  "geometry": {"coordinates":[-88.146726,41.873842],"type":"Point"}
}