{
  "type": "Feature",
  "properties": {
    "iso:country":"US",
    "sg:address":"140 S Poplar St",
    "sg:city":"Centralia",
    "sg:classifiers":[
        {
            "category":"Professional",
            "subcategory":"Lawyer & Legal Services",
            "type":"Services"
        }
    ],
    "sg:phone":"+1 618 532 7353",
    "sg:postcode":"62801",
    "sg:province":"IL",
    "sg:tags":[
        "attorney"
    ],
    "wof:name":"Hodson Jones & Pennock LTD",
    "wof:placetype":"venue"
},
  "geometry": {"coordinates":[-89.133036,38.526888],"type":"Point"}
}