{
  "type": "Feature",
  "properties": {
    "addr:full":"6205 N Sheridan Rd Chicago IL 60660",
    "addr:housenumber":"6205",
    "addr:postcode":"60660",
    "addr:street":"N Sheridan Rd",
    "iso:country":"US",
    "sg:address":"6205 N Sheridan Rd",
    "sg:city":"Chicago",
    "sg:classifiers":[
        {
            "category":"Park",
            "type":"Public Place"
        },
        {
            "category":"Recreation",
            "subcategory":"Playground",
            "type":"Entertainment"
        }
    ],
    "sg:phone":"+1 773 761 0376",
    "sg:postcode":"60660",
    "sg:province":"IL",
    "sg:website":"www.chicagoparkdistrict.com/inde...",
    "wof:name":"Berger Park",
    "wof:placetype":"venue"
},
  "geometry": {"coordinates":[-87.65554400000001,41.994731],"type":"Point"}
}