{
  "type": "Feature",
  "properties": {
    "iso:country":"US",
    "sg:address":"750 Almar Pkwy",
    "sg:city":"Bourbonnais",
    "sg:classifiers":[
        {
            "category":"Professional",
            "subcategory":"Employment Agencies",
            "type":"Services"
        }
    ],
    "sg:phone":"+1 815 929 1900",
    "sg:postcode":"60914",
    "sg:province":"IL",
    "sg:tags":[
        "opportunity"
    ],
    "wof:name":"Myers Group Inc",
    "wof:placetype":"venue"
},
  "geometry": {"coordinates":[-87.88864700000001,41.162982],"type":"Point"}
}