{
  "type": "Feature",
  "properties": {
    "addr:full":"228 Will Scarlett Ln Elgin IL 60120",
    "addr:housenumber":"228",
    "addr:postcode":"60120",
    "addr:street":"Will Scarlett Ln",
    "iso:country":"US",
    "sg:address":"228 Will Scarlett Ln",
    "sg:city":"Elgin",
    "sg:classifiers":[
        {
            "category":"Professional",
            "subcategory":"Testing Lab",
            "type":"Services"
        }
    ],
    "sg:phone":"+1 847 608 6788",
    "sg:postcode":"60120",
    "sg:province":"IL",
    "sg:tags":[
        "equipment",
        "electrical",
        "apparatus"
    ],
    "wof:name":"Fortier Testing and Sales",
    "wof:placetype":"venue"
},
  "geometry": {"coordinates":[-88.22416699999999,42.017604],"type":"Point"}
}