{
  "type": "Feature",
  "properties": {
    "iso:country":"US",
    "sg:address":"1929 S. Archer",
    "sg:city":"Chicago",
    "sg:classifiers":[
        {
            "category":"Social Services",
            "subcategory":"Child Care",
            "type":"Services"
        }
    ],
    "sg:phone":"+1 312 808 1929",
    "sg:postcode":"60616",
    "sg:province":"IL",
    "sg:tags":[
        "day"
    ],
    "sg:website":"www.summaelc.com/",
    "wof:name":"Summa Cum Laude - Early Learning Center",
    "wof:placetype":"venue"
},
  "geometry": {"coordinates":[-87.628252,41.856049],"type":"Point"}
}