{
  "type": "Feature",
  "properties": {
    "addr:full":"806 Fairoaks Dr Champaign IL 61821",
    "addr:housenumber":"806",
    "addr:postcode":"61821",
    "addr:street":"Fairoaks Dr",
    "iso:country":"US",
    "sg:address":"806 Fairoaks Dr",
    "sg:city":"Champaign",
    "sg:classifiers":[
        {
            "category":"Social Services",
            "subcategory":"Child Care",
            "type":"Services"
        }
    ],
    "sg:phone":"+1 217 351 7821",
    "sg:postcode":"61821",
    "sg:province":"IL",
    "wof:name":"Roxanne Heaton",
    "wof:placetype":"venue"
},
  "geometry": {"coordinates":[-88.296234,40.1062],"type":"Point"}
}