{
  "type": "Feature",
  "properties": {
    "iso:country":"US",
    "sg:address":"1866 S Browns Mill Rd",
    "sg:city":"Freeport",
    "sg:classifiers":[
        {
            "category":"Building & Trades",
            "subcategory":"Construction",
            "type":"Services"
        }
    ],
    "sg:phone":"+1 815 235 7663",
    "sg:postcode":"61032",
    "sg:province":"IL",
    "sg:tags":[
        "pond",
        "lake",
        "maintenance"
    ],
    "sg:website":"www.nwgponds.com",
    "wof:name":"Natural Water Gardens",
    "wof:placetype":"venue"
},
  "geometry": {"coordinates":[-89.52297,42.275223],"type":"Point"}
}