{
  "type": "Feature",
  "properties": {
    "addr:full":"2105 Ogden Ave Downers Grove IL 60515",
    "addr:housenumber":"2105",
    "addr:postcode":"60515",
    "addr:street":"Ogden Ave",
    "iso:country":"US",
    "sg:address":"2105 Ogden Ave",
    "sg:city":"Downers Grove",
    "sg:classifiers":[
        {
            "category":"Autos & Motor Vehicles",
            "subcategory":"Automobile Sales",
            "type":"Retail Goods"
        }
    ],
    "sg:phone":"+1   ",
    "sg:postcode":"60515",
    "sg:province":"IL",
    "sg:tags":[
        "used"
    ],
    "wof:name":"Debuonos Auto Sales",
    "wof:placetype":"venue"
},
  "geometry": {"coordinates":[-88.03842299999999,41.806712],"type":"Point"}
}