{
  "type": "Feature",
  "properties": {
    "iso:country":"US",
    "sg:address":"952 Lake St",
    "sg:city":"Oak Park",
    "sg:classifiers":[
        {
            "category":"Health Services",
            "subcategory":"Podiatrist",
            "type":"Services"
        }
    ],
    "sg:phone":"+1 708 383 5554",
    "sg:postcode":"60301",
    "sg:province":"IL",
    "wof:name":"Mary M Disomma DPM",
    "wof:placetype":"venue"
},
  "geometry": {"coordinates":[-87.799705,41.888753],"type":"Point"}
}