{
  "type": "Feature",
  "properties": {
    "iso:country":"US",
    "sg:address":"12200 N Brentfield Dr",
    "sg:city":"Dunlap",
    "sg:classifiers":[
        {
            "category":"Personal",
            "subcategory":"Beauty Salon",
            "type":"Services"
        }
    ],
    "sg:phone":"+1 309 243 5171",
    "sg:postcode":"61525",
    "sg:province":"IL",
    "wof:name":"L A Styles",
    "wof:placetype":"venue"
},
  "geometry": {"coordinates":[-89.618371,40.837059],"type":"Point"}
}