{
  "type": "Feature",
  "properties": {
    "iso:country":"US",
    "sg:address":"1460 W 78th Street",
    "sg:city":"Chicago",
    "sg:classifiers":[
        {
            "category":"Organizations",
            "subcategory":"Religious Organization",
            "type":"Services"
        }
    ],
    "sg:phone":"+1 773 651 2622",
    "sg:postcode":"60620",
    "sg:province":"IL",
    "wof:name":"Zion Hill Mb Church",
    "wof:placetype":"venue"
},
  "geometry": {"coordinates":[-87.661232,41.752207],"type":"Point"}
}