{
  "type": "Feature",
  "properties": {
    "iso:country":"US",
    "sg:address":"1431 E Co Rd 2100",
    "sg:city":"Carthage",
    "sg:phone":"+1 217 746 5061",
    "sg:postcode":"62321",
    "sg:province":"IL",
    "sg:tags":[
        "farm",
        "grain",
        "cash"
    ],
    "wof:name":"Elmer Hamman",
    "wof:placetype":"venue"
},
  "geometry": {"coordinates":[-91.23141200000001,40.506013],"type":"Point"}
}