{
  "type": "Feature",
  "properties": {
    "addr:full":"6565 S Yale Ave Chicago IL 60621",
    "addr:housenumber":"6565",
    "addr:postcode":"60621",
    "addr:street":"S Yale Ave",
    "iso:country":"US",
    "sg:address":"6565 S Yale Ave",
    "sg:city":"Chicago",
    "sg:classifiers":[
        {
            "category":"Structure",
            "subcategory":"Office Building",
            "type":"Public Place"
        }
    ],
    "sg:phone":"+1 773 224 7669",
    "sg:postcode":"60621",
    "sg:province":"IL",
    "sg:tags":[
        "park"
    ],
    "wof:name":"Yale Building Limited Partnership",
    "wof:placetype":"venue"
},
  "geometry": {"coordinates":[-87.631687,41.775217],"type":"Point"}
}