{
  "type": "Feature",
  "properties": {
    "iso:country":"US",
    "sg:address":"2415 Gardner Rd",
    "sg:city":"Broadview",
    "sg:classifiers":[
        {
            "category":"Manufacturing",
            "subcategory":"Chemicals & Compounds",
            "type":"Manufacturing & Wholesale Goods"
        }
    ],
    "sg:phone":"+1 708 345 6880",
    "sg:postcode":"60155",
    "sg:province":"IL",
    "sg:tags":[
        "chemicals-wholesale",
        "manufacturer"
    ],
    "wof:name":"Technical Products",
    "wof:placetype":"venue"
},
  "geometry": {"coordinates":[-87.867586,41.859742],"type":"Point"}
}