{
  "type": "Feature",
  "properties": {
    "addr:full":"4500 N Clarendon Ave Chicago IL 60640",
    "addr:housenumber":"4500",
    "addr:postcode":"60640",
    "addr:street":"N Clarendon Ave",
    "iso:country":"US",
    "sg:address":"4500 N Clarendon Ave",
    "sg:city":"Chicago",
    "sg:classifiers":[
        {
            "category":"Real Estate",
            "subcategory":"Real Estate Operator",
            "type":"Services"
        }
    ],
    "sg:phone":"+1 773 728 0795",
    "sg:postcode":"60640",
    "sg:province":"IL",
    "sg:tags":[
        "high",
        "senior",
        "apartment",
        "facility",
        "citizen"
    ],
    "wof:name":"Clarendon Court Apts",
    "wof:placetype":"venue"
},
  "geometry": {"coordinates":[-87.64980300000001,41.963699],"type":"Point"}
}