{
  "type": "Feature",
  "properties": {
    "iso:country":"US",
    "sg:address":"4700 W Irving Park Rd",
    "sg:city":"Chicago",
    "sg:classifiers":[
        {
            "category":"Personal",
            "subcategory":"Nail Salon",
            "type":"Services"
        }
    ],
    "sg:phone":"+1 773 736 3870",
    "sg:postcode":"60641",
    "sg:province":"IL",
    "wof:name":"Lee Nails",
    "wof:placetype":"venue"
},
  "geometry": {"coordinates":[-87.745796,41.953499],"type":"Point"}
}