{
  "type": "Feature",
  "properties": {
    "iso:country":"US",
    "sg:address":"13821 116th Ave",
    "sg:city":"Orland Park",
    "sg:classifiers":[
        {
            "category":"Professional",
            "subcategory":"Computer Services",
            "type":"Services"
        }
    ],
    "sg:phone":"+1 708 460 4638",
    "sg:postcode":"60467",
    "sg:province":"IL",
    "sg:tags":[
        "aided",
        "design"
    ],
    "wof:name":"Jet Engineering & Design",
    "wof:placetype":"venue"
},
  "geometry": {"coordinates":[-87.901275,41.607763],"type":"Point"}
}