{
  "type": "Feature",
  "properties": {
    "iso:country":"US",
    "sg:address":"209 N 2nd St",
    "sg:city":"Nason",
    "sg:classifiers":[
        {
            "category":"Bars & Pubs",
            "type":"Food & Drink"
        }
    ],
    "sg:phone":"+1 618 279 7220",
    "sg:postcode":"62876",
    "sg:province":"IL",
    "wof:name":"Bubba's Place",
    "wof:placetype":"venue"
},
  "geometry": {"coordinates":[-89.197913,38.282797],"type":"Point"}
}