{
  "type": "Feature",
  "properties": {
    "iso:country":"US",
    "sg:address":"330 S Giant City Rd",
    "sg:city":"Carbondale",
    "sg:classifiers":[
        {
            "category":"Education",
            "subcategory":"School",
            "type":"Public Place"
        }
    ],
    "sg:phone":"+1 618 457 4722",
    "sg:postcode":"62902",
    "sg:province":"IL",
    "sg:tags":[
        "high",
        "middle"
    ],
    "wof:name":"Carbondale Community High School District No 165",
    "wof:placetype":"venue"
},
  "geometry": {"coordinates":[-89.185204,37.7244],"type":"Point"}
}