{
  "type": "Feature",
  "properties": {
    "addr:full":"245 Life Science II Carbondale IL 62901",
    "addr:housenumber":"245",
    "addr:postcode":"62901",
    "iso:country":"US",
    "sg:address":"245 Life Science II",
    "sg:city":"Carbondale",
    "sg:classifiers":[
        {
            "category":"Education",
            "subcategory":"University",
            "type":"Public Place"
        }
    ],
    "sg:phone":"+1 618 453 1544",
    "sg:postcode":"62901",
    "sg:province":"IL",
    "sg:tags":[
        "college"
    ],
    "sg:website":"www.siuc.edu",
    "wof:name":"Southern Illinois University Carbondale",
    "wof:placetype":"venue"
},
  "geometry": {"coordinates":[-89.222724,37.715319],"type":"Point"}
}