{
  "type": "Feature",
  "properties": {
    "addr:full":"302 N 5th Ave Maywood IL 60153",
    "addr:housenumber":"302",
    "addr:postcode":"60153",
    "addr:street":"N 5Th Ave",
    "iso:country":"US",
    "sg:address":"302 N 5th Ave",
    "sg:city":"Maywood",
    "sg:classifiers":[
        {
            "category":"Food & Beverages",
            "subcategory":"Candy",
            "type":"Retail Goods"
        }
    ],
    "sg:phone":"+1 708 343 8448",
    "sg:postcode":"60153",
    "sg:province":"IL",
    "sg:tags":[
        "store"
    ],
    "wof:name":"Candyman Wholesale",
    "wof:placetype":"venue"
},
  "geometry": {"coordinates":[-87.83910400000001,41.890301],"type":"Point"}
}