{
  "type": "Feature",
  "properties": {
    "iso:country":"US",
    "sg:address":"9105 Medill Ave",
    "sg:city":"Franklin Park",
    "sg:classifiers":[
        {
            "category":"Shopping",
            "type":"Retail Goods"
        }
    ],
    "sg:phone":"+1   ",
    "sg:postcode":"60131",
    "sg:province":"IL",
    "sg:tags":[
        "medical",
        "supply"
    ],
    "wof:name":"Health Medical Products Inc",
    "wof:placetype":"venue"
},
  "geometry": {"coordinates":[-87.855402,41.920389],"type":"Point"}
}