{
  "type": "Feature",
  "properties": {
    "addr:full":"904 State St Eldorado IL 62930",
    "addr:housenumber":"904",
    "addr:postcode":"62930",
    "addr:street":"State St",
    "iso:country":"US",
    "sg:address":"904 State St",
    "sg:city":"Eldorado",
    "sg:classifiers":[
        {
            "category":"Shopping",
            "subcategory":"Florist",
            "type":"Retail Goods"
        },
        {
            "category":"Shopping",
            "subcategory":"Gifts & Souvenirs",
            "type":"Retail Goods"
        }
    ],
    "sg:phone":"+1 618 273 6166",
    "sg:postcode":"62930",
    "sg:province":"IL",
    "sg:tags":[
        "shop"
    ],
    "wof:name":"Cottage Florist & Gift",
    "wof:placetype":"venue"
},
  "geometry": {"coordinates":[-88.44309,37.811571],"type":"Point"}
}