{
  "type": "Feature",
  "properties": {
    "addr:full":"385 Sauk Trl Park Forest IL 60466",
    "addr:housenumber":"385",
    "addr:postcode":"60466",
    "addr:street":"Sauk Trl",
    "iso:country":"US",
    "sg:address":"385 Sauk Trl",
    "sg:city":"Park Forest",
    "sg:classifiers":[
        {
            "category":"Autos & Motor Vehicles",
            "subcategory":"Fuel & Gas Station",
            "type":"Retail Goods"
        }
    ],
    "sg:phone":"+1   ",
    "sg:postcode":"60466",
    "sg:province":"IL",
    "sg:tags":[
        "station",
        "gasoline"
    ],
    "wof:name":"Landas Inc",
    "wof:placetype":"venue"
},
  "geometry": {"coordinates":[-87.700022,41.483904],"type":"Point"}
}