{
  "type": "Feature",
  "properties": {
    "addr:full":"2923 117th Ave W Milan IL 61264",
    "addr:housenumber":"2923",
    "addr:postcode":"61264",
    "addr:street":"117Th Ave W",
    "iso:country":"US",
    "sg:address":"2923 117th Ave W",
    "sg:city":"Milan",
    "sg:classifiers":[
        {
            "category":"Health Services",
            "subcategory":"Doctor",
            "type":"Services"
        }
    ],
    "sg:phone":"+1 309 787 2319",
    "sg:postcode":"61264",
    "sg:province":"IL",
    "sg:tags":[
        "physician",
        "surgeon"
    ],
    "wof:name":"William Vipond",
    "wof:placetype":"venue"
},
  "geometry": {"coordinates":[-90.60776799999999,41.403534],"type":"Point"}
}