{
  "type": "Feature",
  "properties": {
    "iso:country":"US",
    "sg:address":"130 N State St 23",
    "sg:city":"Genoa",
    "sg:classifiers":[
        {
            "category":"Social Services",
            "type":"Services"
        },
        {
            "category":"Professional",
            "subcategory":"Employment Agencies",
            "type":"Services"
        }
    ],
    "sg:phone":"+1 815 784 6604",
    "sg:postcode":"60135",
    "sg:province":"IL",
    "sg:tags":[
        "workers'",
        "placement",
        "volunteer"
    ],
    "wof:name":"Temple Masonic",
    "wof:placetype":"venue"
},
  "geometry": {"coordinates":[-88.698018,42.099036],"type":"Point"}
}