{
  "type": "Feature",
  "properties": {
    "addr:full":"2737 W Peterson Ave Chicago IL 60659",
    "addr:housenumber":"2737",
    "addr:postcode":"60659",
    "addr:street":"W Peterson Ave",
    "iso:country":"US",
    "sg:address":"2737 W Peterson Ave",
    "sg:city":"Chicago",
    "sg:classifiers":[
        {
            "category":"Education",
            "subcategory":"School",
            "type":"Public Place"
        }
    ],
    "sg:phone":"+1 312 738 8200",
    "sg:postcode":"60659",
    "sg:province":"IL",
    "wof:name":"Cook Co Juvenile Det C-Bartelm",
    "wof:placetype":"venue"
},
  "geometry": {"coordinates":[-87.699347,41.990368],"type":"Point"}
}