{
  "type": "Feature",
  "properties": {
    "iso:country":"US",
    "sg:address":"3942 Mississippi Ave",
    "sg:city":"Cahokia",
    "sg:classifiers":[
        {
            "category":"Retail",
            "subcategory":"Auto Repair",
            "type":"Services"
        }
    ],
    "sg:phone":"+1 618 337 5600",
    "sg:postcode":"62206",
    "sg:province":"IL",
    "sg:tags":[
        "transmission"
    ],
    "wof:name":"Quality Transmission Svc",
    "wof:placetype":"venue"
},
  "geometry": {"coordinates":[-90.18364,38.577273],"type":"Point"}
}