{
  "type": "Feature",
  "properties": {
    "addr:full":"404 N Wabash Ave Chicago IL 60611",
    "addr:housenumber":"404",
    "addr:postcode":"60611",
    "addr:street":"N Wabash Ave",
    "iso:country":"US",
    "sg:address":"404 N Wabash Ave",
    "sg:city":"Chicago",
    "sg:classifiers":[
        {
            "category":"Coffee & Tea",
            "type":"Food & Drink"
        },
        {
            "category":"Donuts",
            "subcategory":"None",
            "type":"Food & Drink"
        }
    ],
    "sg:phone":"+1 312 786 9750",
    "sg:postcode":"60611",
    "sg:province":"IL",
    "sg:website":"www.dunkindonuts.com",
    "wof:name":"Dunkin Donuts",
    "wof:placetype":"venue"
},
  "geometry": {"coordinates":[-87.626715,41.88961],"type":"Point"}
}