{
  "type": "Feature",
  "properties": {
    "addr:full":"338 S California Ave Chicago IL 60612",
    "addr:housenumber":"338",
    "addr:postcode":"60612",
    "addr:street":"S California Ave",
    "iso:country":"US",
    "sg:address":"338 S California Ave",
    "sg:city":"Chicago",
    "sg:classifiers":[
        {
            "category":"Fast Food",
            "type":"Food & Drink"
        },
        {
            "category":"Restaurant",
            "type":"Food & Drink"
        }
    ],
    "sg:phone":"+1 773 722 9940",
    "sg:postcode":"60612",
    "sg:province":"IL",
    "sg:tags":[
        "seafood",
        "chicken",
        "wing"
    ],
    "wof:name":"Shark's Fish and Chicken",
    "wof:placetype":"venue"
},
  "geometry": {"coordinates":[-87.69616000000001,41.876306],"type":"Point"}
}