{
  "type": "Feature",
  "properties": {
    "addr:full":"14 Winterberry Ct Bolingbrook IL 60440",
    "addr:housenumber":"14",
    "addr:postcode":"60440",
    "addr:street":"Winterberry Ct",
    "iso:country":"US",
    "sg:address":"14 Winterberry Ct",
    "sg:city":"Bolingbrook",
    "sg:classifiers":[
        {
            "category":"Professional",
            "subcategory":"Management & Consulting",
            "type":"Services"
        }
    ],
    "sg:phone":"+1 630 739 0299",
    "sg:postcode":"60440",
    "sg:province":"IL",
    "sg:tags":[
        "consultant"
    ],
    "wof:name":"Strategic Business Solutions",
    "wof:placetype":"venue"
},
  "geometry": {"coordinates":[-88.04781,41.726819],"type":"Point"}
}