{
  "type": "Feature",
  "properties": {
    "addr:full":"5248 S Cicero Ave Chicago IL 60638",
    "addr:housenumber":"5248",
    "addr:postcode":"60638",
    "addr:street":"S Cicero Ave",
    "iso:country":"US",
    "sg:address":"5248 S Cicero Ave",
    "sg:city":"Chicago",
    "sg:classifiers":[
        {
            "category":"Shopping",
            "subcategory":"Party Supplies",
            "type":"Retail Goods"
        }
    ],
    "sg:phone":"+1 773 767 2237",
    "sg:postcode":"60638",
    "sg:province":"IL",
    "sg:tags":[
        "decorating",
        "convention"
    ],
    "sg:website":"http://www.ges.com",
    "wof:name":"Ges Exhibition Services",
    "wof:placetype":"venue"
},
  "geometry": {"coordinates":[-87.742986,41.797912],"type":"Point"}
}