{
  "type": "Feature",
  "properties": {
    "iso:country":"US",
    "sg:address":"4043 S Drexel Blvd",
    "sg:city":"Chicago",
    "sg:classifiers":[
        {
            "category":"Manufacturing",
            "subcategory":"Aerospace",
            "type":"Manufacturing & Wholesale Goods"
        }
    ],
    "sg:phone":"+1 773 891 4602",
    "sg:postcode":"60653",
    "sg:province":"IL",
    "sg:tags":[
        "supply",
        "equipment",
        "aircraft",
        "part",
        "supplies-wholesale",
        "manufacturer"
    ],
    "wof:name":"Avtek Industrials",
    "wof:placetype":"venue"
},
  "geometry": {"coordinates":[-87.60459299999999,41.820236],"type":"Point"}
}