{
  "type": "Feature",
  "properties": {
    "addr:full":"7200 N Ridge Blvd Chicago IL 60645",
    "addr:housenumber":"7200",
    "addr:postcode":"60645",
    "addr:street":"N Ridge Blvd",
    "iso:country":"US",
    "sg:address":"7200 N Ridge Blvd",
    "sg:city":"Chicago",
    "sg:classifiers":[
        {
            "category":"Professional",
            "subcategory":"Business Services",
            "type":"Services"
        }
    ],
    "sg:phone":"+1 773 761 7246",
    "sg:postcode":"60645",
    "sg:province":"IL",
    "sg:tags":[
        "recording",
        "studio"
    ],
    "wof:name":"C R RAINBOW Studio LLC",
    "wof:placetype":"venue"
},
  "geometry": {"coordinates":[-87.68368700000001,42.014034],"type":"Point"}
}