{
  "type": "Feature",
  "properties": {
    "iso:country":"US",
    "sg:address":"2285 Arbeleda Ln",
    "sg:city":"Northbrook",
    "sg:classifiers":[
        {
            "category":"Wholesale",
            "subcategory":"Hardware",
            "type":"Manufacturing & Wholesale Goods"
        }
    ],
    "sg:phone":"+1 847 564 5864",
    "sg:postcode":"60062",
    "sg:province":"IL",
    "sg:tags":[
        "purifier",
        "air"
    ],
    "wof:name":"Negativeionproductscom",
    "wof:placetype":"venue"
},
  "geometry": {"coordinates":[-87.837204,42.102485],"type":"Point"}
}