{
  "type": "Feature",
  "properties": {
    "iso:country":"US",
    "sg:address":"18 W Spring St",
    "sg:city":"Freeport",
    "sg:classifiers":[
        {
            "category":"Retail",
            "subcategory":"Car Wash",
            "type":"Services"
        }
    ],
    "sg:phone":"+1 815 233 6315",
    "sg:postcode":"61032",
    "sg:province":"IL",
    "sg:tags":[
        "polishing",
        "washing"
    ],
    "wof:name":"Car Wash",
    "wof:placetype":"venue"
},
  "geometry": {"coordinates":[-89.619056,42.296854],"type":"Point"}
}