{
  "type": "Feature",
  "properties": {
    "addr:full":"5943 W Irving Park Rd Chicago IL 60634",
    "addr:housenumber":"5943",
    "addr:postcode":"60634",
    "addr:street":"W Irving Park Rd",
    "iso:country":"US",
    "sg:address":"5943 W Irving Park Rd",
    "sg:city":"Chicago",
    "sg:classifiers":[
        {
            "category":"Health Services",
            "subcategory":"Doctor",
            "type":"Services"
        }
    ],
    "sg:phone":"+1 773 282 6111",
    "sg:postcode":"60634",
    "sg:province":"IL",
    "sg:tags":[
        "podiatrist"
    ],
    "sg:website":"www.portagefootandankle.com",
    "wof:name":"Portage Foot & Ankle Clinic",
    "wof:placetype":"venue"
},
  "geometry": {"coordinates":[-87.77619900000001,41.952801],"type":"Point"}
}