{
  "type": "Feature",
  "properties": {
    "iso:country":"US",
    "sg:address":"140 W Commercial St",
    "sg:city":"Wood Dale",
    "sg:classifiers":[
        {
            "category":"Retail",
            "subcategory":"Auto Repair",
            "type":"Services"
        }
    ],
    "sg:phone":"+1 630 350 1952",
    "sg:postcode":"60191",
    "sg:province":"IL",
    "sg:tags":[
        "automotive",
        "wrecker"
    ],
    "wof:name":"American Towing & Recovery",
    "wof:placetype":"venue"
},
  "geometry": {"coordinates":[-87.982056,41.965235],"type":"Point"}
}