{
  "type": "Feature",
  "properties": {
    "iso:country":"US",
    "sg:address":"7056 Roosevelt Rd",
    "sg:city":"Oak Park",
    "sg:classifiers":[
        {
            "category":"Building & Trades",
            "subcategory":"Plumbing",
            "type":"Services"
        }
    ],
    "sg:phone":"+1 708 848 6749",
    "sg:postcode":"60304",
    "sg:province":"IL",
    "wof:name":"Callahan D W & Sons Plumbers",
    "wof:placetype":"venue"
},
  "geometry": {"coordinates":[-87.80090300000001,41.865101],"type":"Point"}
}