{
  "type": "Feature",
  "properties": {
    "iso:country":"US",
    "sg:address":"157 W Kinzie St",
    "sg:city":"Chicago",
    "sg:classifiers":[
        {
            "category":"Recreation",
            "type":"Entertainment"
        }
    ],
    "sg:phone":"+1 312 527 4449",
    "sg:postcode":"60654",
    "sg:province":"IL",
    "sg:tags":[
        "valves-repairing"
    ],
    "wof:name":"Samco Enterprises",
    "wof:placetype":"venue"
},
  "geometry": {"coordinates":[-87.633324,41.889172],"type":"Point"}
}