{
  "type": "Feature",
  "properties": {
    "addr:full":"25 Robinwood Dr Rushville IL 62681",
    "addr:housenumber":"25",
    "addr:postcode":"62681",
    "addr:street":"Robinwood Dr",
    "iso:country":"US",
    "sg:address":"25 Robinwood Dr",
    "sg:city":"Rushville",
    "sg:classifiers":[
        {
            "category":"Retail",
            "subcategory":"Veterinary Services",
            "type":"Services"
        }
    ],
    "sg:phone":"+1 217 322 4901",
    "sg:postcode":"62681",
    "sg:province":"IL",
    "sg:tags":[
        "clinic",
        "hospital",
        "veterinarian",
        "specialty"
    ],
    "wof:name":"Wilson Veterinary Clinic PC",
    "wof:placetype":"venue"
},
  "geometry": {"coordinates":[-90.574941,40.115669],"type":"Point"}
}