{
  "type": "Feature",
  "properties": {
    "addr:full":"712 N Victoria Dr Palatine IL 60074",
    "addr:housenumber":"712",
    "addr:postcode":"60074",
    "addr:street":"N Victoria Dr",
    "iso:country":"US",
    "sg:address":"712 N Victoria Dr",
    "sg:city":"Palatine",
    "sg:classifiers":[
        {
            "category":"Professional",
            "subcategory":"Management & Consulting",
            "type":"Services"
        }
    ],
    "sg:phone":"+1 847 818 8499",
    "sg:postcode":"60074",
    "sg:province":"IL",
    "sg:tags":[
        "business"
    ],
    "wof:name":"Object Consulting Inc",
    "wof:placetype":"venue"
},
  "geometry": {"coordinates":[-88.00747800000001,42.12193],"type":"Point"}
}