{
  "type": "Feature",
  "properties": {
    "addr:full":"521 W Main St Ottawa IL 61350",
    "addr:housenumber":"521",
    "addr:postcode":"61350",
    "addr:street":"W Main St",
    "iso:country":"US",
    "sg:address":"521 W Main St",
    "sg:city":"Ottawa",
    "sg:classifiers":[
        {
            "category":"Restaurant",
            "type":"Food & Drink"
        }
    ],
    "sg:phone":"+1   ",
    "sg:postcode":"61350",
    "sg:province":"IL",
    "sg:tags":[
        "eating"
    ],
    "wof:name":"Tones Doghouse",
    "wof:placetype":"venue"
},
  "geometry": {"coordinates":[-88.847981,41.34564],"type":"Point"}
}