{
  "type": "Feature",
  "properties": {
    "addr:full":"4200 W Peterson Ave Chicago IL 60646",
    "addr:housenumber":"4200",
    "addr:postcode":"60646",
    "addr:street":"W Peterson Ave",
    "iso:country":"US",
    "sg:address":"4200 W Peterson Ave",
    "sg:city":"Chicago",
    "sg:classifiers":[
        {
            "category":"Health Services",
            "subcategory":"Doctor",
            "type":"Services"
        }
    ],
    "sg:phone":"+1 773 561 1750",
    "sg:postcode":"60646",
    "sg:province":"IL",
    "wof:name":"Timothy Bashford DDS PC",
    "wof:placetype":"venue"
},
  "geometry": {"coordinates":[-87.733996,41.990145],"type":"Point"}
}