{
  "type": "Feature",
  "properties": {
    "addr:full":"303 W Erie St Ste 600 Chicago IL 60654",
    "addr:housenumber":"303",
    "addr:postcode":"60654",
    "addr:street":"W Erie St Ste 600",
    "iso:country":"US",
    "sg:address":"303 W Erie St Ste 600",
    "sg:city":"Chicago",
    "sg:classifiers":[
        {
            "category":"Restaurant",
            "type":"Food & Drink"
        }
    ],
    "sg:phone":"+1 312 284 6500",
    "sg:postcode":"60654",
    "sg:province":"IL",
    "sg:tags":[
        "fusion",
        "asian"
    ],
    "sg:website":"www.stircrazy.com",
    "wof:name":"Stir Crazy Inc",
    "wof:placetype":"venue"
},
  "geometry": {"coordinates":[-87.635778,41.893843],"type":"Point"}
}