{
  "type": "Feature",
  "properties": {
    "iso:country":"US",
    "sg:address":"21 W. 240 Nordic Road",
    "sg:city":"Itasca",
    "sg:classifiers":[
        {
            "category":"Travel",
            "subcategory":"Hotels & Motels",
            "type":"Entertainment"
        }
    ],
    "sg:phone":"+1 630 773 2750",
    "sg:postcode":"60143",
    "sg:province":"IL",
    "wof:name":"Nordic Hills",
    "wof:placetype":"venue"
},
  "geometry": {"coordinates":[-88.03994899999999,41.956999],"type":"Point"}
}