{
  "type": "Feature",
  "properties": {
    "addr:full":"300 Washington Ave Cairo IL 62914",
    "addr:housenumber":"300",
    "addr:postcode":"62914",
    "addr:street":"Washington Ave",
    "iso:country":"US",
    "sg:address":"300 Washington Ave",
    "sg:city":"Cairo",
    "sg:classifiers":[
        {
            "category":"Restaurant",
            "type":"Food & Drink"
        }
    ],
    "sg:phone":"+1   ",
    "sg:postcode":"62914",
    "sg:province":"IL",
    "sg:tags":[
        "eating"
    ],
    "wof:name":"Nu Diner",
    "wof:placetype":"venue"
},
  "geometry": {"coordinates":[-89.16467799999999,36.998152],"type":"Point"}
}