{
  "type": "Feature",
  "properties": {
    "iso:country":"US",
    "sg:address":"396 Remington Blvd",
    "sg:city":"Bolingbrook",
    "sg:classifiers":[
        {
            "category":"Health Services",
            "subcategory":"Optometrist",
            "type":"Services"
        },
        {
            "category":"Shopping",
            "subcategory":"Optician",
            "type":"Retail Goods"
        },
        {
            "category":"Health Services",
            "subcategory":"Health Practitioner",
            "type":"Services"
        },
        {
            "category":"Personal",
            "subcategory":"Skin Care",
            "type":"Services"
        }
    ],
    "sg:phone":"+1 630 517 2608",
    "sg:postcode":"60440",
    "sg:province":"IL",
    "sg:tags":[
        "physician",
        "ophthalmology",
        "surgeons"
    ],
    "sg:website":"http://www.wsecmd.com",
    "wof:name":"West Suburban Eye Center",
    "wof:placetype":"venue"
},
  "geometry": {"coordinates":[-88.08110499999999,41.682763],"type":"Point"}
}