{
  "type": "Feature",
  "properties": {
    "iso:country":"US",
    "sg:address":"2701 Spruce St",
    "sg:city":"Quincy",
    "sg:classifiers":[
        {
            "category":"Manufacturing",
            "subcategory":"Metals",
            "type":"Manufacturing & Wholesale Goods"
        }
    ],
    "sg:phone":"+1 217 221 4498",
    "sg:postcode":"62301",
    "sg:province":"IL",
    "sg:tags":[
        "blast",
        "furnace",
        "works"
    ],
    "wof:name":"Titan International Inc",
    "wof:placetype":"venue"
},
  "geometry": {"coordinates":[-91.372451,39.946548],"type":"Point"}
}