{
  "type": "Feature",
  "properties": {
    "addr:full":"302 Park Ave Grayslake IL 60030",
    "addr:housenumber":"302",
    "addr:postcode":"60030",
    "addr:street":"Park Ave",
    "iso:country":"US",
    "sg:address":"302 Park Ave",
    "sg:city":"Grayslake",
    "sg:classifiers":[
        {
            "category":"Real Estate",
            "subcategory":"Real Estate Agent",
            "type":"Services"
        }
    ],
    "sg:phone":"+1 847 548 8272",
    "sg:postcode":"60030",
    "sg:province":"IL",
    "wof:name":"Century 21 Kreuser Seiler",
    "wof:placetype":"venue"
},
  "geometry": {"coordinates":[-88.03890800000001,42.342388],"type":"Point"}
}