{
  "type": "Feature",
  "properties": {
    "addr:full":"25259 S Reed St Channahon IL 60410",
    "addr:housenumber":"25259",
    "addr:postcode":"60410",
    "addr:street":"S Reed St",
    "iso:country":"US",
    "sg:address":"25259 S Reed St",
    "sg:city":"Channahon",
    "sg:classifiers":[
        {
            "category":"Health Services",
            "subcategory":"Doctor",
            "type":"Services"
        }
    ],
    "sg:phone":"+1 815 467 0901",
    "sg:postcode":"60410",
    "sg:province":"IL",
    "wof:name":"Smith Brent DO",
    "wof:placetype":"venue"
},
  "geometry": {"coordinates":[-88.2257,41.432301],"type":"Point"}
}