{
  "type": "Feature",
  "properties": {
    "iso:country":"US",
    "sg:address":"1320 W 9th St",
    "sg:city":"Mount Carmel",
    "sg:classifiers":[
        {
            "category":"Health Services",
            "subcategory":"Nursing And Care Facility",
            "type":"Services"
        }
    ],
    "sg:phone":"+1 618 263 4337",
    "sg:postcode":"62863",
    "sg:province":"IL",
    "sg:tags":[
        "skilled"
    ],
    "wof:name":"Oak View Heights",
    "wof:placetype":"venue"
},
  "geometry": {"coordinates":[-87.78216399999999,38.409929],"type":"Point"}
}