{
  "type": "Feature",
  "properties": {
    "iso:country":"US",
    "sg:address":"630 Essex Ct",
    "sg:city":"Deerfield",
    "sg:classifiers":[
        {
            "category":"Education",
            "subcategory":"School",
            "type":"Public Place"
        }
    ],
    "sg:phone":"+1 847 945 9660",
    "sg:postcode":"60015",
    "sg:province":"IL",
    "sg:tags":[
        "elementary"
    ],
    "wof:name":"Walden Elementary School",
    "wof:placetype":"venue"
},
  "geometry": {"coordinates":[-87.84241,42.176781],"type":"Point"}
}