{
  "type": "Feature",
  "properties": {
    "iso:country":"US",
    "sg:address":"4870 183rd St",
    "sg:city":"Country Club Hills",
    "sg:classifiers":[
        {
            "category":"Restaurant",
            "type":"Food & Drink"
        }
    ],
    "sg:phone":"+1   ",
    "sg:postcode":"60478",
    "sg:province":"IL",
    "sg:tags":[
        "eating"
    ],
    "wof:name":"Mg Chop Suey",
    "wof:placetype":"venue"
},
  "geometry": {"coordinates":[-87.734296,41.557162],"type":"Point"}
}