{
  "type": "Feature",
  "properties": {
    "iso:country":"US",
    "sg:address":"901 Smith St",
    "sg:city":"Carmi",
    "sg:classifiers":[
        {
            "category":"Government",
            "subcategory":"City Hall",
            "type":"Public Place"
        },
        {
            "category":"Government",
            "subcategory":"Office",
            "type":"Public Place"
        }
    ],
    "sg:phone":"+1 618 382 7048",
    "sg:postcode":"62821",
    "sg:province":"IL",
    "sg:tags":[
        "town",
        "township",
        "planner",
        "government-city",
        "village"
    ],
    "wof:name":"Emmitt Township",
    "wof:placetype":"venue"
},
  "geometry": {"coordinates":[-88.173897,38.09166],"type":"Point"}
}