{
  "type": "Feature",
  "properties": {
    "iso:country":"US",
    "sg:address":"65 S Lake St",
    "sg:city":"Aurora",
    "sg:classifiers":[
        {
            "category":"Professional",
            "subcategory":"Business Services",
            "type":"Services"
        }
    ],
    "sg:phone":"+1 630 896 0434",
    "sg:postcode":"60506",
    "sg:province":"IL",
    "sg:tags":[
        "automotive",
        "repair"
    ],
    "wof:name":"Lake Auto Rebuilders",
    "wof:placetype":"venue"
},
  "geometry": {"coordinates":[-88.320097,41.758524],"type":"Point"}
}