{
  "type": "Feature",
  "properties": {
    "iso:country":"US",
    "sg:address":"222 Madison Ave",
    "sg:city":"Charleston",
    "sg:classifiers":[
        {
            "category":"Manufacturing",
            "subcategory":"Printing",
            "type":"Manufacturing & Wholesale Goods"
        }
    ],
    "sg:phone":"+1 217 345 7518",
    "sg:postcode":"61920",
    "sg:province":"IL",
    "sg:tags":[
        "commercial",
        "b",
        "lithographic",
        "printer",
        "typesetting"
    ],
    "wof:name":"Print Co Printing",
    "wof:placetype":"venue"
},
  "geometry": {"coordinates":[-88.180574,39.495416],"type":"Point"}
}