{
  "type": "Feature",
  "properties": {
    "iso:country":"US",
    "sg:address":"700 W Main St",
    "sg:city":"West Frankfort",
    "sg:classifiers":[
        {
            "category":"Personal",
            "type":"Services"
        }
    ],
    "sg:phone":"+1 618 727 0523",
    "sg:postcode":"62896",
    "sg:province":"IL",
    "sg:tags":[
        "control",
        "weight"
    ],
    "wof:name":"Brian Carroll",
    "wof:placetype":"venue"
},
  "geometry": {"coordinates":[-88.937642,37.89795],"type":"Point"}
}