{
  "type": "Feature",
  "properties": {
    "addr:full":"903 S Clay Ave Jacksonville IL 62650",
    "addr:housenumber":"903",
    "addr:postcode":"62650",
    "addr:street":"S Clay Ave",
    "iso:country":"US",
    "sg:address":"903 S Clay Ave",
    "sg:city":"Jacksonville",
    "sg:classifiers":[
        {
            "category":"Building & Trades",
            "subcategory":"Construction",
            "type":"Services"
        }
    ],
    "sg:phone":"+1 217 243 6068",
    "sg:postcode":"62650",
    "sg:province":"IL",
    "sg:tags":[
        "contractor"
    ],
    "wof:name":"Suttles Concrete Contractors",
    "wof:placetype":"venue"
},
  "geometry": {"coordinates":[-90.224553,39.724759],"type":"Point"}
}