{
  "type": "Feature",
  "properties": {
    "iso:country":"US",
    "sg:address":"7238 Niles Center Rd",
    "sg:city":"Skokie",
    "sg:classifiers":[
        {
            "category":"Retail",
            "subcategory":"Laundry & Dry Cleaning",
            "type":"Services"
        }
    ],
    "sg:phone":"+1 708 484 6964",
    "sg:postcode":"60077",
    "sg:province":"IL",
    "sg:tags":[
        "drycleaning",
        "plant"
    ],
    "wof:name":"Garden Cleaners",
    "wof:placetype":"venue"
},
  "geometry": {"coordinates":[-87.761673,42.012626],"type":"Point"}
}