{
  "type": "Feature",
  "properties": {
    "iso:country":"US",
    "sg:address":"750 E. Bunker Court Suite 900",
    "sg:city":"Vernon Hills",
    "sg:classifiers":[
        {
            "category":"Professional",
            "subcategory":"Research",
            "type":"Services"
        }
    ],
    "sg:phone":"+1 847 996 1500",
    "sg:postcode":"60061",
    "sg:province":"IL",
    "sg:website":"http://www.sorbentrx.com/",
    "wof:name":"Sorbent Therapeutics",
    "wof:placetype":"venue"
},
  "geometry": {"coordinates":[-87.946668,42.233538],"type":"Point"}
}