{
  "type": "Feature",
  "properties": {
    "iso:country":"US",
    "sg:address":"7114 S Yates Boulevard",
    "sg:city":"Chicago",
    "sg:classifiers":[
        {
            "category":"Restaurant",
            "type":"Food & Drink"
        }
    ],
    "sg:phone":"+1 773 752 6588",
    "sg:postcode":"60649",
    "sg:province":"IL",
    "wof:name":"Ming Chop Suey",
    "wof:placetype":"venue"
},
  "geometry": {"coordinates":[-87.566591,41.765487],"type":"Point"}
}