{
  "type": "Feature",
  "properties": {
    "addr:full":"322 Moen Ave Rockdale IL 60436",
    "addr:housenumber":"322",
    "addr:postcode":"60436",
    "addr:street":"Moen Ave",
    "iso:country":"US",
    "sg:address":"322 Moen Ave",
    "sg:city":"Rockdale",
    "sg:classifiers":[
        {
            "category":"Retail",
            "subcategory":"Repair Shop",
            "type":"Services"
        }
    ],
    "sg:phone":"+1 815 725 5668",
    "sg:postcode":"60436",
    "sg:province":"IL",
    "sg:tags":[
        "commercial",
        "welding"
    ],
    "sg:website":"www.anzelcwelding.com",
    "wof:name":"Anzelc Welding",
    "wof:placetype":"venue"
},
  "geometry": {"coordinates":[-88.111845,41.505154],"type":"Point"}
}