{
  "type": "Feature",
  "properties": {
    "addr:full":"70 W Burton Pl Chicago IL 60610",
    "addr:housenumber":"70",
    "addr:postcode":"60610",
    "addr:street":"W Burton Pl",
    "iso:country":"US",
    "sg:address":"70 W Burton Pl",
    "sg:city":"Chicago",
    "sg:classifiers":[
        {
            "category":"Organizations",
            "subcategory":"Community Association",
            "type":"Services"
        }
    ],
    "sg:phone":"+1 312 440 8000",
    "sg:postcode":"60610",
    "sg:province":"IL",
    "wof:name":"Faulkner House",
    "wof:placetype":"venue"
},
  "geometry": {"coordinates":[-87.63097500000001,41.909459],"type":"Point"}
}