{
  "type": "Feature",
  "properties": {
    "iso:country":"US",
    "sg:address":"107 S Delphia Ave",
    "sg:city":"Park Ridge",
    "sg:classifiers":[
        {
            "category":"Professional",
            "subcategory":"Business Services",
            "type":"Services"
        }
    ],
    "sg:phone":"+1 847 685 1286",
    "sg:postcode":"60068",
    "sg:province":"IL",
    "wof:name":"Gorniak Enterprises Inc",
    "wof:placetype":"venue"
},
  "geometry": {"coordinates":[-87.841871,42.007692],"type":"Point"}
}