{
  "type": "Feature",
  "properties": {
    "iso:country":"US",
    "sg:address":"20 Maple Ave",
    "sg:city":"Lake Zurich",
    "sg:classifiers":[
        {
            "category":"Professional",
            "type":"Services"
        },
        {
            "category":"Professional",
            "subcategory":"Management & Consulting",
            "type":"Services"
        }
    ],
    "sg:phone":"+1 847 540 6089",
    "sg:postcode":"60047",
    "sg:province":"IL",
    "sg:tags":[
        "editorial"
    ],
    "wof:name":"Louden Health Communications",
    "wof:placetype":"venue"
},
  "geometry": {"coordinates":[-88.098314,42.189842],"type":"Point"}
}