{
  "type": "Feature",
  "properties": {
    "iso:country":"US",
    "sg:address":"6173 E 1950 North Rd",
    "sg:city":"Fithian",
    "sg:phone":"+1 217 548 2287",
    "sg:postcode":"61844",
    "sg:province":"IL",
    "sg:tags":[
        "farm",
        "corn",
        "soybean"
    ],
    "wof:name":"Mark Shepherd Farm Inc",
    "wof:placetype":"venue"
},
  "geometry": {"coordinates":[-87.82548300000001,40.151492],"type":"Point"}
}