{
  "type": "Feature",
  "properties": {
    "addr:full":"6255 S Archer Rd Summit Argo IL 60501",
    "addr:housenumber":"6255",
    "addr:postcode":"60501",
    "addr:street":"S Archer Rd",
    "iso:country":"US",
    "sg:address":"6255 S Archer Rd",
    "sg:city":"Summit Argo",
    "sg:classifiers":[
        {
            "category":"Bars & Pubs",
            "type":"Food & Drink"
        }
    ],
    "sg:phone":"+1   ",
    "sg:postcode":"60501",
    "sg:province":"IL",
    "sg:tags":[
        "drinking",
        "eating"
    ],
    "wof:name":"Chesters Tavern",
    "wof:placetype":"venue"
},
  "geometry": {"coordinates":[-87.813858,41.777279],"type":"Point"}
}