{
  "type": "Feature",
  "properties": {
    "addr:full":"8423 Monticello Ave Skokie IL 60076",
    "addr:housenumber":"8423",
    "addr:postcode":"60076",
    "addr:street":"Monticello Ave",
    "iso:country":"US",
    "sg:address":"8423 Monticello Ave",
    "sg:city":"Skokie",
    "sg:classifiers":[
        {
            "category":"Professional",
            "subcategory":"Research",
            "type":"Services"
        }
    ],
    "sg:phone":"+1 847 673 3505",
    "sg:postcode":"60076",
    "sg:province":"IL",
    "sg:tags":[
        "organization",
        "noncommercial"
    ],
    "wof:name":"Social Policy Research Ins",
    "wof:placetype":"venue"
},
  "geometry": {"coordinates":[-87.71944999999999,42.033633],"type":"Point"}
}