{
  "type": "Feature",
  "properties": {
    "iso:country":"US",
    "sg:address":"13258 S Houston Avenue",
    "sg:city":"Chicago",
    "sg:classifiers":[
        {
            "category":"Shopping",
            "subcategory":"Florist",
            "type":"Retail Goods"
        }
    ],
    "sg:phone":"+1 773 646 1187",
    "sg:postcode":"60633",
    "sg:province":"IL",
    "wof:name":"Lenart Florist",
    "wof:placetype":"venue"
},
  "geometry": {"coordinates":[-87.548519,41.653879],"type":"Point"}
}