{
  "type": "Feature",
  "properties": {
    "addr:full":"2877 Falling Waters Dr Lindenhurst IL 60046",
    "addr:housenumber":"2877",
    "addr:postcode":"60046",
    "addr:street":"Falling Waters Dr",
    "iso:country":"US",
    "sg:address":"2877 Falling Waters Dr",
    "sg:city":"Lindenhurst",
    "sg:classifiers":[
        {
            "category":"Health Services",
            "subcategory":"Dentist",
            "type":"Services"
        }
    ],
    "sg:phone":"+1 847 356 1557",
    "sg:postcode":"60046",
    "sg:province":"IL",
    "sg:tags":[
        "dental",
        "hygienist"
    ],
    "wof:name":"Sarah Pump",
    "wof:placetype":"venue"
},
  "geometry": {"coordinates":[-88.008274,42.404046],"type":"Point"}
}