{
  "type": "Feature",
  "properties": {
    "addr:full":"2401 W Roosevelt Rd Chicago IL 60608",
    "addr:housenumber":"2401",
    "addr:postcode":"60608",
    "addr:street":"W Roosevelt Rd",
    "iso:country":"US",
    "sg:address":"2401 W Roosevelt Rd",
    "sg:city":"Chicago",
    "sg:classifiers":[
        {
            "category":"Autos & Motor Vehicles",
            "subcategory":"Fuel & Gas Station",
            "type":"Retail Goods"
        }
    ],
    "sg:phone":"+1 312 421 0343",
    "sg:postcode":"60608",
    "sg:province":"IL",
    "wof:name":"Roosevelt & Western Shell",
    "wof:placetype":"venue"
},
  "geometry": {"coordinates":[-87.6866,41.866501],"type":"Point"}
}