{
  "type": "Feature",
  "properties": {
    "iso:country":"US",
    "sg:address":"421 E Stevenson Rd",
    "sg:city":"Ottawa",
    "sg:classifiers":[
        {
            "category":"Professional",
            "type":"Services"
        }
    ],
    "sg:phone":"+1 815 433 7300",
    "sg:postcode":"61350",
    "sg:province":"IL",
    "sg:tags":[
        "establishment"
    ],
    "wof:name":"Reliable Corp",
    "wof:placetype":"venue"
},
  "geometry": {"coordinates":[-88.833783,41.379277],"type":"Point"}
}