{
  "type": "Feature",
  "properties": {
    "iso:country":"US",
    "sg:address":"1500 Mc Daniel Ave",
    "sg:city":"Evanston",
    "sg:classifiers":[
        {
            "category":"Professional",
            "type":"Services"
        }
    ],
    "sg:phone":"+1 847 328 6067",
    "sg:postcode":"60201",
    "sg:province":"IL",
    "sg:tags":[
        "establishment"
    ],
    "wof:name":"F H Paschen",
    "wof:placetype":"venue"
},
  "geometry": {"coordinates":[-87.708336,42.046403],"type":"Point"}
}