{
  "type": "Feature",
  "properties": {
    "iso:country":"US",
    "sg:address":"1920 S Randall Rd",
    "sg:city":"Algonquin",
    "sg:classifiers":[
        {
            "category":"Shopping",
            "subcategory":"Jewelry",
            "type":"Retail Goods"
        }
    ],
    "sg:phone":"+1 847 658 5273",
    "sg:postcode":"60102",
    "sg:province":"IL",
    "sg:website":"www.zales.com",
    "wof:name":"Zales Jewelers",
    "wof:placetype":"venue"
},
  "geometry": {"coordinates":[-88.335954,42.150525],"type":"Point"}
}