{
  "type": "Feature",
  "properties": {
    "addr:full":"1437 Oakton St Park Ridge IL 60068",
    "addr:housenumber":"1437",
    "addr:postcode":"60068",
    "addr:street":"Oakton St",
    "iso:country":"US",
    "sg:address":"1437 Oakton St",
    "sg:city":"Park Ridge",
    "sg:classifiers":[
        {
            "category":"Organizations",
            "subcategory":"Religious Organization",
            "type":"Services"
        }
    ],
    "sg:phone":"+1 847 292 1254",
    "sg:postcode":"60068",
    "sg:province":"IL",
    "wof:name":"Midwest Presbyterian Church",
    "wof:placetype":"venue"
},
  "geometry": {"coordinates":[-87.845269,42.025265],"type":"Point"}
}