{
  "type": "Feature",
  "properties": {
    "iso:country":"US",
    "sg:address":"1601 N Lewis Ave",
    "sg:city":"Waukegan",
    "sg:classifiers":[
        {
            "category":"Banks & Credit Unions",
            "subcategory":"Bank",
            "type":"Services"
        }
    ],
    "sg:phone":"+1 847 244 6000",
    "sg:postcode":"60085",
    "sg:province":"IL",
    "sg:tags":[
        "saving",
        "commercial"
    ],
    "wof:name":"Northern States Financial Corporation",
    "wof:placetype":"venue"
},
  "geometry": {"coordinates":[-87.85543800000001,42.382408],"type":"Point"}
}