{
  "type": "Feature",
  "properties": {
    "addr:full":"3361 Fehling Rd Granite City IL 62040",
    "addr:housenumber":"3361",
    "addr:postcode":"62040",
    "addr:street":"Fehling Rd",
    "iso:country":"US",
    "sg:address":"3361 Fehling Rd",
    "sg:city":"Granite City",
    "sg:classifiers":[
        {
            "category":"Banks & Credit Unions",
            "subcategory":"Financial Services",
            "type":"Services"
        }
    ],
    "sg:phone":"+1 618 877 2100",
    "sg:postcode":"62040",
    "sg:province":"IL",
    "sg:tags":[
        "broker",
        "mortgage"
    ],
    "sg:website":"www.agfinance.com",
    "wof:name":"American General Financial Services",
    "wof:placetype":"venue"
},
  "geometry": {"coordinates":[-90.12509900000001,38.723],"type":"Point"}
}