{
  "type": "Feature",
  "properties": {
    "addr:full":"200 E Keely St Creal Springs IL 62922",
    "addr:housenumber":"200",
    "addr:postcode":"62922",
    "addr:street":"E Keely St",
    "iso:country":"US",
    "sg:address":"200 E Keely St",
    "sg:city":"Creal Springs",
    "sg:classifiers":[
        {
            "category":"Insurance",
            "subcategory":"Insurance Agent",
            "type":"Services"
        }
    ],
    "sg:phone":"+1 618 996 3627",
    "sg:postcode":"62922",
    "sg:province":"IL",
    "wof:name":"Stroh Insurance",
    "wof:placetype":"venue"
},
  "geometry": {"coordinates":[-88.835081,37.619858],"type":"Point"}
}