{
  "type": "Feature",
  "properties": {
    "iso:country":"US",
    "sg:address":"182 W Lake St",
    "sg:city":"Chicago",
    "sg:classifiers":[
        {
            "category":"Arena",
            "subcategory":"Sports Club",
            "type":"Entertainment"
        }
    ],
    "sg:phone":"+1 224 622 8369",
    "sg:postcode":"60601",
    "sg:province":"IL",
    "sg:tags":[
        "martial art"
    ],
    "sg:website":"www.defenseinhome.com",
    "wof:name":"Chicago In Home Self Defense",
    "wof:placetype":"venue"
},
  "geometry": {"coordinates":[-87.633437,41.885756],"type":"Point"}
}