{
  "type": "Feature",
  "properties": {
    "iso:country":"US",
    "sg:address":"2850 W 95th St",
    "sg:city":"Evergreen Park",
    "sg:classifiers":[
        {
            "category":"Health Services",
            "subcategory":"Doctor",
            "type":"Services"
        }
    ],
    "sg:phone":"+1 708 423 1130",
    "sg:postcode":"60805",
    "sg:province":"IL",
    "wof:name":"Del Busto Dr Paul",
    "wof:placetype":"venue"
},
  "geometry": {"coordinates":[-87.69360399999999,41.720798],"type":"Point"}
}