{
  "type": "Feature",
  "properties": {
    "iso:country":"US",
    "sg:address":"120 W 1st St",
    "sg:city":"Dixon",
    "sg:classifiers":[
        {
            "category":"Shopping",
            "subcategory":"Pharmacy",
            "type":"Retail Goods"
        }
    ],
    "sg:phone":"+1   ",
    "sg:postcode":"61021",
    "sg:province":"IL",
    "wof:name":"Dixon Pharmacy Inc",
    "wof:placetype":"venue"
},
  "geometry": {"coordinates":[-89.482891,41.8436],"type":"Point"}
}