{
  "type": "Feature",
  "properties": {
    "addr:full":"129 W Main St Urbana IL 61801",
    "addr:housenumber":"129",
    "addr:postcode":"61801",
    "addr:street":"W Main St",
    "iso:country":"US",
    "sg:address":"129 W Main St",
    "sg:city":"Urbana",
    "sg:classifiers":[
        {
            "category":"Professional",
            "subcategory":"Lawyer & Legal Services",
            "type":"Services"
        }
    ],
    "sg:phone":"+1 217 367 9092",
    "sg:postcode":"61801",
    "sg:province":"IL",
    "sg:tags":[
        "attorney",
        "accident",
        "worker",
        "damage",
        "benefit",
        "employee",
        "property",
        "compensation"
    ],
    "sg:website":"http://www.frederickandhagle.com",
    "wof:name":"Frederick & Hagle Attorneys At Law",
    "wof:placetype":"venue"
},
  "geometry": {"coordinates":[-88.207802,40.112099],"type":"Point"}
}