{
  "type": "Feature",
  "properties": {
    "iso:country":"US",
    "sg:address":"1940 W Galena Blvd",
    "sg:city":"Aurora",
    "sg:classifiers":[
        {
            "category":"Health Services",
            "subcategory":"Medical Lab",
            "type":"Services"
        }
    ],
    "sg:phone":"+1 630 859 1959",
    "sg:postcode":"60506",
    "sg:province":"IL",
    "sg:tags":[
        "laboratory",
        "dental"
    ],
    "wof:name":"Sterling Dental Laboratory",
    "wof:placetype":"venue"
},
  "geometry": {"coordinates":[-88.364959,41.764313],"type":"Point"}
}