{
  "type": "Feature",
  "properties": {
    "iso:country":"US",
    "sg:address":"3224 Ridge Rd",
    "sg:city":"Lansing",
    "sg:classifiers":[
        {
            "category":"Health Services",
            "subcategory":"Optometrist",
            "type":"Services"
        }
    ],
    "sg:phone":"+1 708 895 4422",
    "sg:postcode":"60438",
    "sg:province":"IL",
    "wof:name":"Carmine Vision Care PC",
    "wof:placetype":"venue"
},
  "geometry": {"coordinates":[-87.538749,41.564902],"type":"Point"}
}