{
  "type": "Feature",
  "properties": {
    "iso:country":"US",
    "sg:address":"12525 Irving Ave",
    "sg:city":"Blue Island",
    "sg:classifiers":[
        {
            "category":"Building & Trades",
            "subcategory":"Construction",
            "type":"Services"
        }
    ],
    "sg:phone":"+1 708 388 5066",
    "sg:postcode":"60406",
    "sg:province":"IL",
    "sg:tags":[
        "maker",
        "cabinet"
    ],
    "sg:website":"www.cvcustom.com",
    "wof:name":"C-V Custom Counter Tops Inc",
    "wof:placetype":"venue"
},
  "geometry": {"coordinates":[-87.676022,41.665031],"type":"Point"}
}