{
  "type": "Feature",
  "properties": {
    "addr:full":"7105 S Racine Ave Chicago IL 60636",
    "addr:housenumber":"7105",
    "addr:postcode":"60636",
    "addr:street":"S Racine Ave",
    "iso:country":"US",
    "sg:address":"7105 S Racine Ave",
    "sg:city":"Chicago",
    "sg:classifiers":[
        {
            "category":"Food & Beverages",
            "subcategory":"Groceries & Convenience Stores",
            "type":"Retail Goods"
        }
    ],
    "sg:phone":"+1 773 994 7556",
    "sg:postcode":"60636",
    "sg:province":"IL",
    "wof:name":"Safah Food and Liquor",
    "wof:placetype":"venue"
},
  "geometry": {"coordinates":[-87.65389999999999,41.764702],"type":"Point"}
}