{
  "type": "Feature",
  "properties": {
    "iso:country":"US",
    "sg:address":"300 S Central Ave",
    "sg:city":"Wood River",
    "sg:classifiers":[
        {
            "category":"Insurance",
            "subcategory":"Insurance Agent",
            "type":"Services"
        }
    ],
    "sg:phone":"+1 618 254 9314",
    "sg:postcode":"62095",
    "sg:province":"IL",
    "wof:name":"Ron Wisnasky Insurance Inc",
    "wof:placetype":"venue"
},
  "geometry": {"coordinates":[-90.079121,38.854617],"type":"Point"}
}