{
  "type": "Feature",
  "properties": {
    "iso:country":"US",
    "sg:address":"9022 31st St",
    "sg:city":"Brookfield",
    "sg:classifiers":[
        {
            "category":"Restaurant",
            "type":"Food & Drink"
        }
    ],
    "sg:phone":"+1 708 485 4500",
    "sg:postcode":"60513",
    "sg:province":"IL",
    "sg:tags":[
        "steakhouse",
        "italian"
    ],
    "wof:name":"Bellavia Steakhouse",
    "wof:placetype":"venue"
},
  "geometry": {"coordinates":[-87.848078,41.834936],"type":"Point"}
}