{
  "type": "Feature",
  "properties": {
    "iso:country":"US",
    "sg:address":"7740 Banks St",
    "sg:city":"Bedford Park",
    "sg:classifiers":[
        {
            "category":"Building & Trades",
            "subcategory":"Construction",
            "type":"Services"
        }
    ],
    "sg:phone":"+1 773 905 4371",
    "sg:postcode":"60458",
    "sg:province":"IL",
    "sg:tags":[
        "house"
    ],
    "wof:name":"J & Gal Consultant",
    "wof:placetype":"venue"
},
  "geometry": {"coordinates":[-87.842748,41.749606],"type":"Point"}
}