{
  "type": "Feature",
  "properties": {
    "addr:full":"2501 Wabash Ave Springfield IL 62704",
    "addr:housenumber":"2501",
    "addr:postcode":"62704",
    "addr:street":"Wabash Ave",
    "iso:country":"US",
    "sg:address":"2501 Wabash Ave",
    "sg:city":"Springfield",
    "sg:classifiers":[
        {
            "category":"Ice Cream",
            "type":"Food & Drink"
        }
    ],
    "sg:menulink":"http://www.allmenus.com/il/capital/227600-dippin-dots/menu/",
    "sg:phone":"0",
    "sg:postcode":"62704",
    "sg:province":"IL",
    "sg:tags":[
        "american"
    ],
    "wof:name":"Dippin' Dots",
    "wof:placetype":"venue"
},
  "geometry": {"coordinates":[-89.704691,39.764279],"type":"Point"}
}