{
  "type": "Feature",
  "properties": {
    "addr:full":"520 N Michigan Ave Chicago IL 60611",
    "addr:housenumber":"520",
    "addr:postcode":"60611",
    "addr:street":"N Michigan Ave",
    "iso:country":"US",
    "sg:address":"520 N Michigan Ave",
    "sg:city":"Chicago",
    "sg:classifiers":[
        {
            "category":"Shopping",
            "subcategory":"Department Store",
            "type":"Retail Goods"
        }
    ],
    "sg:phone":"+1 312 644 9783",
    "sg:postcode":"60611",
    "sg:province":"IL",
    "sg:website":"www.twitter.com/SanrioNBridge",
    "wof:name":"Sanrio",
    "wof:placetype":"venue"
},
  "geometry": {"coordinates":[-87.624298,41.891602],"type":"Point"}
}