{
  "type": "Feature",
  "properties": {
    "iso:country":"US",
    "sg:address":"22 S Main St",
    "sg:city":"Caseyville",
    "sg:classifiers":[
        {
            "category":"Retail",
            "subcategory":"Repair Shop",
            "type":"Services"
        }
    ],
    "sg:phone":"+1 618 345 5325",
    "sg:postcode":"62232",
    "sg:province":"IL",
    "sg:tags":[
        "pipe",
        "leak",
        "locating"
    ],
    "wof:name":"Leak Detection Svc",
    "wof:placetype":"venue"
},
  "geometry": {"coordinates":[-90.024253,38.637704],"type":"Point"}
}