{
  "type": "Feature",
  "properties": {
    "addr:full":"4418 N Mason Ave Chicago IL 60630",
    "addr:housenumber":"4418",
    "addr:postcode":"60630",
    "addr:street":"N Mason Ave",
    "iso:country":"US",
    "sg:address":"4418 N Mason Ave",
    "sg:city":"Chicago",
    "sg:classifiers":[
        {
            "category":"Real Estate",
            "subcategory":"Real Estate Services",
            "type":"Services"
        },
        {
            "category":"Banks & Credit Unions",
            "subcategory":"Financial Services",
            "type":"Services"
        }
    ],
    "sg:phone":"+1 773 612 7946",
    "sg:postcode":"60630",
    "sg:province":"IL",
    "sg:tags":[
        "loan",
        "processing"
    ],
    "wof:name":"Krk Mortgage Bancorp",
    "wof:placetype":"venue"
},
  "geometry": {"coordinates":[-87.775795,41.960705],"type":"Point"}
}