{
  "type": "Feature",
  "properties": {
    "addr:full":"9575 W Higgins Rd Rosemont IL 60018",
    "addr:housenumber":"9575",
    "addr:postcode":"60018",
    "addr:street":"W Higgins Rd",
    "iso:country":"US",
    "sg:address":"9575 W Higgins Rd",
    "sg:city":"Rosemont",
    "sg:classifiers":[
        {
            "category":"Building & Trades",
            "subcategory":"Construction",
            "type":"Services"
        }
    ],
    "sg:phone":"+1 847 823 5888",
    "sg:postcode":"60018",
    "sg:province":"IL",
    "sg:tags":[
        "mason",
        "masonry",
        "industrial",
        "contractors-commercial",
        "contractor"
    ],
    "sg:website":"http://www.rosemontmasonry.com",
    "wof:name":"Rosemont Masonry",
    "wof:placetype":"venue"
},
  "geometry": {"coordinates":[-87.86457799999999,41.992939],"type":"Point"}
}