{
  "type": "Feature",
  "properties": {
    "addr:full":"3600 Pacific Ave Gurnee IL 60031",
    "addr:housenumber":"3600",
    "addr:postcode":"60031",
    "addr:street":"Pacific Ave",
    "iso:country":"US",
    "sg:address":"3600 Pacific Ave",
    "sg:city":"Gurnee",
    "sg:classifiers":[
        {
            "category":"Utilities",
            "subcategory":"Recycling",
            "type":"Services"
        }
    ],
    "sg:phone":"+1 847 623 9110",
    "sg:postcode":"60031",
    "sg:province":"IL",
    "sg:tags":[
        "rubbish",
        "removal"
    ],
    "wof:name":"Ideal Rolloff Services Inc",
    "wof:placetype":"venue"
},
  "geometry": {"coordinates":[-87.889732,42.381271],"type":"Point"}
}