{
  "type": "Feature",
  "properties": {
    "iso:country":"US",
    "sg:address":"1 N Dearborn St",
    "sg:city":"Chicago",
    "sg:classifiers":[
        {
            "category":"Coffee & Tea",
            "type":"Food & Drink"
        }
    ],
    "sg:phone":"+1 312 212 8032",
    "sg:postcode":"60686",
    "sg:province":"IL",
    "sg:website":"www.argotea.com",
    "wof:name":"Argo Tea",
    "wof:placetype":"venue"
},
  "geometry": {"coordinates":[-87.62939299999999,41.882015],"type":"Point"}
}