{
  "type": "Feature",
  "properties": {
    "addr:full":"210 S 4th St Vandalia IL 62471",
    "addr:housenumber":"210",
    "addr:postcode":"62471",
    "addr:street":"S 4Th St",
    "iso:country":"US",
    "sg:address":"210 S 4th St",
    "sg:city":"Vandalia",
    "sg:classifiers":[
        {
            "category":"Cinema",
            "subcategory":"Movie Theater",
            "type":"Entertainment"
        }
    ],
    "sg:phone":"+1 618 283 1953",
    "sg:postcode":"62471",
    "sg:province":"IL",
    "wof:name":"Liberty Theater",
    "wof:placetype":"venue"
},
  "geometry": {"coordinates":[-89.094635,38.960577],"type":"Point"}
}