{
  "type": "Feature",
  "properties": {
    "addr:full":"507 S Chestnut St Kewanee IL 61443",
    "addr:housenumber":"507",
    "addr:postcode":"61443",
    "addr:street":"S Chestnut St",
    "iso:country":"US",
    "sg:address":"507 S Chestnut St",
    "sg:city":"Kewanee",
    "sg:classifiers":[
        {
            "category":"Retail",
            "subcategory":"Funeral Services",
            "type":"Services"
        }
    ],
    "sg:phone":"+1 309 853 4100",
    "sg:postcode":"61443",
    "sg:province":"IL",
    "sg:tags":[
        "director",
        "crematory"
    ],
    "wof:name":"Rux Funeral Home  Ltd",
    "wof:placetype":"venue"
},
  "geometry": {"coordinates":[-89.92795599999999,41.238099],"type":"Point"}
}