{
  "type": "Feature",
  "properties": {
    "iso:country":"US",
    "sg:address":"5116 W Penn Corner Rd",
    "sg:city":"Oregon",
    "sg:classifiers":[
        {
            "category":"Building & Trades",
            "subcategory":"Landscaping Services",
            "type":"Services"
        }
    ],
    "sg:phone":"+1 815 946 9100",
    "sg:postcode":"61061",
    "sg:province":"IL",
    "sg:tags":[
        "landscape",
        "contractor"
    ],
    "wof:name":"Holden Construction",
    "wof:placetype":"venue"
},
  "geometry": {"coordinates":[-89.43953,41.94146],"type":"Point"}
}