{
  "type": "Feature",
  "properties": {
    "iso:country":"US",
    "sg:address":"100 E Old Mill Rd",
    "sg:city":"Lake Forest",
    "sg:classifiers":[
        {
            "category":"Social Services",
            "type":"Services"
        }
    ],
    "sg:phone":"+1   ",
    "sg:postcode":"60045",
    "sg:province":"IL",
    "sg:tags":[
        "executive"
    ],
    "wof:name":"Lake Frest Lk Bluff Senior Ctr",
    "wof:placetype":"venue"
},
  "geometry": {"coordinates":[-87.845071,42.210887],"type":"Point"}
}