{
  "type": "Feature",
  "properties": {
    "iso:country":"US",
    "sg:address":"23 E. Madison St.",
    "sg:city":"Chicago",
    "sg:classifiers":[
        {
            "category":"Autos & Motor Vehicles",
            "subcategory":"Automobile Sales",
            "type":"Retail Goods"
        },
        {
            "category":"Airline",
            "type":"Transportation"
        }
    ],
    "sg:phone":"+1 312 626 2238",
    "sg:postcode":"60602",
    "sg:province":"IL",
    "sg:tags":[
        "shuttle",
        "airport",
        "limo"
    ],
    "sg:website":"www.chicago-hummer-limo-rental.com",
    "wof:name":"Chicago Hummer Limo Rental",
    "wof:placetype":"venue"
},
  "geometry": {"coordinates":[-87.626885,41.882041],"type":"Point"}
}