{
  "type": "Feature",
  "properties": {
    "iso:country":"US",
    "sg:address":"231 E 75th St",
    "sg:city":"Chicago",
    "sg:classifiers":[
        {
            "category":"Health Services",
            "subcategory":"Doctor",
            "type":"Services"
        }
    ],
    "sg:phone":"+1 773 651 3660",
    "sg:postcode":"60619",
    "sg:province":"IL",
    "wof:name":"Eulien Harold B MD",
    "wof:placetype":"venue"
},
  "geometry": {"coordinates":[-87.6194,41.758202],"type":"Point"}
}