{
  "type": "Feature",
  "properties": {
    "iso:country":"US",
    "sg:address":"400 Main St",
    "sg:city":"Lemont",
    "sg:classifiers":[
        {
            "category":"Retail",
            "subcategory":"Photofinishing",
            "type":"Services"
        }
    ],
    "sg:phone":"+1 630 257 6224",
    "sg:postcode":"60439",
    "sg:province":"IL",
    "sg:tags":[
        "photo",
        "finishing"
    ],
    "wof:name":"Budnik Pharmacy",
    "wof:placetype":"venue"
},
  "geometry": {"coordinates":[-87.99739700000001,41.67496],"type":"Point"}
}