{
  "type": "Feature",
  "properties": {
    "addr:full":"14065 Hansberry Rd Rockton IL 61072",
    "addr:housenumber":"14065",
    "addr:postcode":"61072",
    "addr:street":"Hansberry Rd",
    "iso:country":"US",
    "sg:address":"14065 Hansberry Rd",
    "sg:city":"Rockton",
    "sg:classifiers":[
        {
            "category":"Shopping",
            "type":"Retail Goods"
        },
        {
            "category":"Shopping",
            "subcategory":"Beauty & Cosmetics",
            "type":"Retail Goods"
        }
    ],
    "sg:phone":"+1 815 624 6246",
    "sg:postcode":"61072",
    "sg:province":"IL",
    "sg:tags":[
        "merchandise",
        "perfume"
    ],
    "wof:name":"Scott Cal Cosmetics",
    "wof:placetype":"venue"
},
  "geometry": {"coordinates":[-89.113452,42.473839],"type":"Point"}
}