{
  "type": "Feature",
  "properties": {
    "iso:country":"US",
    "sg:address":"1809 E Main St",
    "sg:city":"Danville",
    "sg:classifiers":[
        {
            "category":"Shopping",
            "type":"Retail Goods"
        }
    ],
    "sg:phone":"+1 217 442 1987",
    "sg:postcode":"61832",
    "sg:province":"IL",
    "sg:tags":[
        "durable",
        "merchandise"
    ],
    "wof:name":"Leverenz Memorials",
    "wof:placetype":"venue"
},
  "geometry": {"coordinates":[-87.594914,40.131789],"type":"Point"}
}