{
  "type": "Feature",
  "properties": {
    "addr:full":"109 Fairfield Way Ste 106 Bloomingdale IL 60108",
    "addr:housenumber":"109",
    "addr:postcode":"60108",
    "addr:street":"Fairfield Way Ste 106",
    "iso:country":"US",
    "sg:address":"109 Fairfield Way Ste 106",
    "sg:city":"Bloomingdale",
    "sg:classifiers":[
        {
            "category":"Taxi",
            "type":"Transportation"
        }
    ],
    "sg:phone":"+1 630 671 0168",
    "sg:postcode":"60108",
    "sg:province":"IL",
    "wof:name":"AAA USA Taxi",
    "wof:placetype":"venue"
},
  "geometry": {"coordinates":[-88.08760100000001,41.951698],"type":"Point"}
}