{
  "type": "Feature",
  "properties": {
    "addr:full":"303 Moen Ave Joliet IL 60436",
    "addr:housenumber":"303",
    "addr:postcode":"60436",
    "addr:street":"Moen Ave",
    "iso:country":"US",
    "sg:address":"303 Moen Ave",
    "sg:city":"Joliet",
    "sg:classifiers":[
        {
            "category":"Building & Trades",
            "subcategory":"Electrical",
            "type":"Services"
        }
    ],
    "sg:phone":"+1 815 725 8921",
    "sg:postcode":"60436",
    "sg:province":"IL",
    "sg:tags":[
        "electrical",
        "contractor"
    ],
    "wof:name":"Cardinal Electric Inc",
    "wof:placetype":"venue"
},
  "geometry": {"coordinates":[-88.112089,41.505298],"type":"Point"}
}