{
  "type": "Feature",
  "properties": {
    "iso:country":"US",
    "sg:address":"210 E Fayette Ave",
    "sg:city":"Effingham",
    "sg:classifiers":[
        {
            "category":"Banks & Credit Unions",
            "subcategory":"Bank",
            "type":"Services"
        }
    ],
    "sg:phone":"+1 217 342 3200",
    "sg:postcode":"62401",
    "sg:province":"IL",
    "sg:tags":[
        "national",
        "commercial"
    ],
    "wof:name":"Effingham National Bank",
    "wof:placetype":"venue"
},
  "geometry": {"coordinates":[-88.540738,39.119986],"type":"Point"}
}