{
  "type": "Feature",
  "properties": {
    "iso:country":"US",
    "sg:address":"850 E Pershing Rd",
    "sg:city":"Decatur",
    "sg:classifiers":[
        {
            "category":"Home & Garden",
            "subcategory":"Hardware",
            "type":"Retail Goods"
        },
        {
            "category":"Manufacturing",
            "subcategory":"Lumber",
            "type":"Manufacturing & Wholesale Goods"
        }
    ],
    "sg:phone":"+1 217 875 7227",
    "sg:postcode":"62526",
    "sg:province":"IL",
    "sg:tags":[
        "lumber-wholesale",
        "store"
    ],
    "wof:name":"Negwer Materials, Inc.",
    "wof:placetype":"venue"
},
  "geometry": {"coordinates":[-88.919033,39.87789],"type":"Point"}
}