{
  "type": "Feature",
  "properties": {
    "iso:country":"US",
    "sg:address":"500 S Western Ave",
    "sg:city":"Peoria",
    "sg:classifiers":[
        {
            "category":"Restaurant",
            "type":"Food & Drink"
        }
    ],
    "sg:menulink":"http://www.allmenus.com/il/peoria-city/13182-churchs-chicken/menu/",
    "sg:phone":"+1 309 637 7570",
    "sg:postcode":"61605",
    "sg:province":"IL",
    "sg:tags":[
        "chicken",
        "wing"
    ],
    "wof:name":"Church's Chicken",
    "wof:placetype":"venue"
},
  "geometry": {"coordinates":[-89.62267,40.682868],"type":"Point"}
}