{
  "type": "Feature",
  "properties": {
    "addr:full":"714 S Highland Ave Oak Park IL 60304",
    "addr:housenumber":"714",
    "addr:postcode":"60304",
    "addr:street":"S Highland Ave",
    "iso:country":"US",
    "sg:address":"714 S Highland Ave",
    "sg:city":"Oak Park",
    "sg:classifiers":[
        {
            "category":"Professional",
            "subcategory":"Management & Consulting",
            "type":"Services"
        }
    ],
    "sg:phone":"+1 708 704 8359",
    "sg:postcode":"60304",
    "sg:province":"IL",
    "wof:name":"Wisdom Link",
    "wof:placetype":"venue"
},
  "geometry": {"coordinates":[-87.781779,41.875675],"type":"Point"}
}