{
  "type": "Feature",
  "properties": {
    "addr:full":"725 Pekin St Lincoln IL 62656",
    "addr:housenumber":"725",
    "addr:postcode":"62656",
    "addr:street":"Pekin St",
    "iso:country":"US",
    "sg:address":"725 Pekin St",
    "sg:city":"Lincoln",
    "sg:classifiers":[
        {
            "category":"Education",
            "subcategory":"Library",
            "type":"Public Place"
        }
    ],
    "sg:phone":"+1 217 732 8878",
    "sg:postcode":"62656",
    "sg:province":"IL",
    "sg:website":"www.lincolnpubliclibrary.org",
    "wof:name":"Lincoln Public Library",
    "wof:placetype":"venue"
},
  "geometry": {"coordinates":[-89.36146599999999,40.147379],"type":"Point"}
}