{
  "type": "Feature",
  "properties": {
    "iso:country":"US",
    "sg:address":"825 Walnut Ave",
    "sg:city":"Elgin",
    "sg:classifiers":[
        {
            "category":"Real Estate",
            "subcategory":"Real Estate Agent",
            "type":"Services"
        }
    ],
    "sg:phone":"+1 847 695 4468",
    "sg:postcode":"60123",
    "sg:province":"IL",
    "wof:name":"Ray Ellett Real Estate",
    "wof:placetype":"venue"
},
  "geometry": {"coordinates":[-88.299704,42.028475],"type":"Point"}
}