{
  "type": "Feature",
  "properties": {
    "addr:full":"16924 Sandy Ln Tinley Park IL 60477",
    "addr:housenumber":"16924",
    "addr:postcode":"60477",
    "addr:street":"Sandy Ln",
    "iso:country":"US",
    "sg:address":"16924 Sandy Ln",
    "sg:city":"Tinley Park",
    "sg:classifiers":[
        {
            "category":"Food & Beverages",
            "subcategory":"Groceries & Convenience Stores",
            "type":"Retail Goods"
        }
    ],
    "sg:phone":"+1   ",
    "sg:postcode":"60477",
    "sg:province":"IL",
    "wof:name":"Three Patels Inc",
    "wof:placetype":"venue"
},
  "geometry": {"coordinates":[-87.79495199999999,41.583765],"type":"Point"}
}