{
  "type": "Feature",
  "properties": {
    "iso:country":"US",
    "sg:address":"1131 Tennyson Ln",
    "sg:city":"Naperville",
    "sg:classifiers":[
        {
            "category":"Social Services",
            "subcategory":"Job Training",
            "type":"Services"
        }
    ],
    "sg:phone":"+1 630 357 6299",
    "sg:postcode":"60540",
    "sg:province":"IL",
    "sg:tags":[
        "nursing",
        "homes-skilled",
        "facility"
    ],
    "wof:name":"Best Care, Inc.",
    "wof:placetype":"venue"
},
  "geometry": {"coordinates":[-88.167225,41.751449],"type":"Point"}
}