{
  "type": "Feature",
  "properties": {
    "iso:country":"US",
    "sg:address":"550 Main St",
    "sg:city":"Antioch",
    "sg:classifiers":[
        {
            "category":"Social Services",
            "type":"Services"
        }
    ],
    "sg:phone":"+1 847 838 9904",
    "sg:postcode":"60002",
    "sg:province":"IL",
    "sg:tags":[
        "counseling"
    ],
    "wof:name":"Blending Families",
    "wof:placetype":"venue"
},
  "geometry": {"coordinates":[-88.09555,42.488238],"type":"Point"}
}