{
  "type": "Feature",
  "properties": {
    "addr:full":"2126 N Bloomington St Streator IL 61364",
    "addr:housenumber":"2126",
    "addr:postcode":"61364",
    "addr:street":"N Bloomington St",
    "iso:country":"US",
    "sg:address":"2126 N Bloomington St",
    "sg:city":"Streator",
    "sg:classifiers":[
        {
            "category":"Utilities",
            "subcategory":"Electric",
            "type":"Services"
        }
    ],
    "sg:phone":"+1 815 672 5041",
    "sg:postcode":"61364",
    "sg:province":"IL",
    "sg:tags":[
        "equipment",
        "supplies-repair",
        "electronic",
        "equipment-repair"
    ],
    "wof:name":"Linson Appliance Parts & Repai",
    "wof:placetype":"venue"
},
  "geometry": {"coordinates":[-88.83580000000001,41.143769],"type":"Point"}
}