{
  "type": "Feature",
  "properties": {
    "iso:country":"US",
    "sg:address":"1947 Cleveland Blvd",
    "sg:city":"Granite City",
    "sg:classifiers":[
        {
            "category":"Real Estate",
            "subcategory":"Real Estate Operator",
            "type":"Services"
        }
    ],
    "sg:phone":"+1 618 452 0925",
    "sg:postcode":"62040",
    "sg:province":"IL",
    "sg:tags":[
        "apartment"
    ],
    "wof:name":"SIR John Court Apartments",
    "wof:placetype":"venue"
},
  "geometry": {"coordinates":[-90.150803,38.702702],"type":"Point"}
}