{
  "type": "Feature",
  "properties": {
    "iso:country":"US",
    "sg:address":"39 Lake Breeze Ct",
    "sg:city":"Lake Zurich",
    "sg:classifiers":[
        {
            "category":"Building & Trades",
            "subcategory":"Equipment Rental",
            "type":"Services"
        }
    ],
    "sg:phone":"+1 847 438 8535",
    "sg:postcode":"60047",
    "sg:province":"IL",
    "sg:tags":[
        "camping"
    ],
    "wof:name":"Wilderness Trails",
    "wof:placetype":"venue"
},
  "geometry": {"coordinates":[-88.110361,42.204007],"type":"Point"}
}