{
  "type": "Feature",
  "properties": {
    "addr:full":"428 N Oak Park Ave Oak Park IL 60302",
    "addr:housenumber":"428",
    "addr:postcode":"60302",
    "addr:street":"N Oak Park Ave",
    "iso:country":"US",
    "sg:address":"428 N Oak Park Ave",
    "sg:city":"Oak Park",
    "sg:classifiers":[
        {
            "category":"Wholesale",
            "subcategory":"Computers",
            "type":"Manufacturing & Wholesale Goods"
        }
    ],
    "sg:phone":"+1 708 445 8544",
    "sg:postcode":"60302",
    "sg:province":"IL",
    "sg:tags":[
        "consultant"
    ],
    "wof:name":"Management Systems Intl",
    "wof:placetype":"venue"
},
  "geometry": {"coordinates":[-87.79458,41.893979],"type":"Point"}
}