{
  "type": "Feature",
  "properties": {
    "iso:country":"US",
    "sg:address":"1242 N Eola Rd",
    "sg:city":"Aurora",
    "sg:classifiers":[
        {
            "category":"Real Estate",
            "subcategory":"Real Estate Services",
            "type":"Services"
        },
        {
            "category":"Real Estate",
            "subcategory":"Real Estate Agent",
            "type":"Services"
        }
    ],
    "sg:phone":"+1 630 269 1793",
    "sg:postcode":"60502",
    "sg:province":"IL",
    "sg:tags":[
        "buyer",
        "broker"
    ],
    "wof:name":"Greg M Wroblewski",
    "wof:placetype":"venue"
},
  "geometry": {"coordinates":[-88.240807,41.782631],"type":"Point"}
}