{
  "type": "Feature",
  "properties": {
    "iso:country":"US",
    "sg:address":"3731 Fults Rd",
    "sg:city":"Fults",
    "sg:phone":"+1 618 458 6636",
    "sg:postcode":"62244",
    "sg:province":"IL",
    "sg:tags":[
        "farm",
        "corn",
        "wheat",
        "soybean"
    ],
    "wof:name":"Randall Esker",
    "wof:placetype":"venue"
},
  "geometry": {"coordinates":[-90.198052,38.168823],"type":"Point"}
}