{
  "type": "Feature",
  "properties": {
    "addr:full":"3202 W Montrose Ave Chicago IL 60618",
    "addr:housenumber":"3202",
    "addr:postcode":"60618",
    "addr:street":"W Montrose Ave",
    "iso:country":"US",
    "sg:address":"3202 W Montrose Ave",
    "sg:city":"Chicago",
    "sg:classifiers":[
        {
            "category":"Arena",
            "subcategory":"Sports Club",
            "type":"Entertainment"
        }
    ],
    "sg:phone":"+1 773 463 0051",
    "sg:postcode":"60618",
    "sg:province":"IL",
    "sg:tags":[
        "martial art"
    ],
    "wof:name":"Jungdo and Hapkido School",
    "wof:placetype":"venue"
},
  "geometry": {"coordinates":[-87.70839700000001,41.9613],"type":"Point"}
}