{
  "type": "Feature",
  "properties": {
    "addr:full":"2313 Glenoak Dr Champaign IL 61821",
    "addr:housenumber":"2313",
    "addr:postcode":"61821",
    "addr:street":"Glenoak Dr",
    "iso:country":"US",
    "sg:address":"2313 Glenoak Dr",
    "sg:city":"Champaign",
    "sg:classifiers":[
        {
            "category":"Wholesale",
            "subcategory":"Chemicals & Plastics",
            "type":"Manufacturing & Wholesale Goods"
        }
    ],
    "sg:phone":"+1 217 359 9299",
    "sg:postcode":"61821",
    "sg:province":"IL",
    "wof:name":"Berg Essex",
    "wof:placetype":"venue"
},
  "geometry": {"coordinates":[-88.283266,40.090526],"type":"Point"}
}