{
  "type": "Feature",
  "properties": {
    "iso:country":"US",
    "sg:address":"2743 Girard Ave",
    "sg:city":"Evanston",
    "sg:classifiers":[
        {
            "category":"Communications",
            "subcategory":"Radio Station",
            "type":"Services"
        }
    ],
    "sg:phone":"+1 847 491 7163",
    "sg:postcode":"60201",
    "sg:province":"IL",
    "sg:tags":[
        "educational"
    ],
    "wof:name":"Donna Jurdy",
    "wof:placetype":"venue"
},
  "geometry": {"coordinates":[-87.685453,42.064691],"type":"Point"}
}