{
  "type": "Feature",
  "properties": {
    "addr:full":"10404 Kings Ct Roscoe IL 61073",
    "addr:housenumber":"10404",
    "addr:postcode":"61073",
    "addr:street":"Kings Ct",
    "iso:country":"US",
    "sg:address":"10404 Kings Ct",
    "sg:city":"Roscoe",
    "sg:classifiers":[
        {
            "category":"Professional",
            "subcategory":"Computer Services",
            "type":"Services"
        }
    ],
    "sg:phone":"+1 815 623 8002",
    "sg:postcode":"61073",
    "sg:province":"IL",
    "sg:tags":[
        "operating",
        "design",
        "system"
    ],
    "wof:name":"Bsdngorg",
    "wof:placetype":"venue"
},
  "geometry": {"coordinates":[-88.958618,42.412206],"type":"Point"}
}