{
  "type": "Feature",
  "properties": {
    "iso:country":"US",
    "sg:address":"20620 Burl Ct",
    "sg:city":"Joliet",
    "sg:classifiers":[
        {
            "category":"Freight",
            "type":"Transportation"
        }
    ],
    "sg:phone":"+1 815 723 4300",
    "sg:postcode":"60433",
    "sg:province":"IL",
    "sg:tags":[
        "distance",
        "local",
        "long",
        "trucking"
    ],
    "wof:name":"Intell Transportation",
    "wof:placetype":"venue"
},
  "geometry": {"coordinates":[-88.022354,41.511448],"type":"Point"}
}