{
  "type": "Feature",
  "properties": {
    "addr:full":"8109 Rosebury Ave Woodridge IL 60517",
    "addr:postcode":"8109;60517",
    "addr:street":"Rosebury Ave",
    "iso:country":"US",
    "sg:address":"8109 Rosebury Ave",
    "sg:city":"Woodridge",
    "sg:classifiers":[
        {
            "category":"Manufacturing",
            "subcategory":"Tools & Machinery",
            "type":"Manufacturing & Wholesale Goods"
        }
    ],
    "sg:phone":"+1 630 910 8835",
    "sg:postcode":"60517",
    "sg:province":"IL",
    "sg:tags":[
        "electric",
        "supply"
    ],
    "wof:name":"Erico-Caddy",
    "wof:placetype":"venue"
},
  "geometry": {"coordinates":[-88.020263,41.741934],"type":"Point"}
}