{
  "type": "Feature",
  "properties": {
    "addr:full":"686 W Boughton Rd Bolingbrook IL 60440",
    "addr:housenumber":"686",
    "addr:postcode":"60440",
    "addr:street":"W Boughton Rd",
    "iso:country":"US",
    "sg:address":"686 W Boughton Rd",
    "sg:city":"Bolingbrook",
    "sg:classifiers":[
        {
            "category":"Manufacturing",
            "subcategory":"Printing",
            "type":"Manufacturing & Wholesale Goods"
        }
    ],
    "sg:phone":"+1 630 378 4021",
    "sg:postcode":"60440",
    "sg:province":"IL",
    "sg:tags":[
        "multimedia"
    ],
    "wof:name":"Ontarget Media",
    "wof:placetype":"venue"
},
  "geometry": {"coordinates":[-88.091559,41.707162],"type":"Point"}
}