{
  "type": "Feature",
  "properties": {
    "addr:full":"106 W 5th St Tilton IL 61833",
    "addr:housenumber":"106",
    "addr:postcode":"61833",
    "addr:street":"W 5Th St",
    "iso:country":"US",
    "sg:address":"106 W 5th St",
    "sg:city":"Tilton",
    "sg:classifiers":[
        {
            "category":"Personal",
            "subcategory":"Beauty Salon",
            "type":"Services"
        }
    ],
    "sg:phone":"+1 217 443 3210",
    "sg:postcode":"61833",
    "sg:province":"IL",
    "wof:name":"Quick Cuts",
    "wof:placetype":"venue"
},
  "geometry": {"coordinates":[-87.650114,40.101548],"type":"Point"}
}