{
  "type": "Feature",
  "properties": {
    "addr:full":"1935 N Kedzie Ave Chicago IL 60647",
    "addr:housenumber":"1935",
    "addr:postcode":"60647",
    "addr:street":"N Kedzie Ave",
    "iso:country":"US",
    "sg:address":"1935 N Kedzie Ave",
    "sg:city":"Chicago",
    "sg:classifiers":[
        {
            "category":"Insurance",
            "subcategory":"Hazard Insurance",
            "type":"Services"
        }
    ],
    "sg:phone":"+1 773 384 4401",
    "sg:postcode":"60647",
    "sg:province":"IL",
    "sg:tags":[
        "commercial",
        "business"
    ],
    "wof:name":"Douglas Raul Williams Farmers Insurance Agency",
    "wof:placetype":"venue"
},
  "geometry": {"coordinates":[-87.706934,41.916572],"type":"Point"}
}