{
  "type": "Feature",
  "properties": {
    "iso:country":"US",
    "sg:address":"1207 Hagan St",
    "sg:city":"Champaign",
    "sg:classifiers":[
        {
            "category":"Organizations",
            "subcategory":"Labor Organization",
            "type":"Services"
        }
    ],
    "sg:phone":"+1 217 359 0887",
    "sg:postcode":"61820",
    "sg:province":"IL",
    "wof:name":"Champaign Firefighters",
    "wof:placetype":"venue"
},
  "geometry": {"coordinates":[-88.254943,40.128308],"type":"Point"}
}