{
  "type": "Feature",
  "properties": {
    "iso:country":"US",
    "sg:address":"522 Clark St",
    "sg:city":"Utica",
    "sg:classifiers":[
        {
            "category":"Manufacturing",
            "subcategory":"Apparel",
            "type":"Manufacturing & Wholesale Goods"
        },
        {
            "category":"Shopping",
            "subcategory":"Clothing, Apparel, & Fashions",
            "type":"Retail Goods"
        }
    ],
    "sg:phone":"+1 815 667 3299",
    "sg:postcode":"61348",
    "sg:province":"IL",
    "sg:tags":[
        "sewing",
        "contractor"
    ],
    "wof:name":"Connie's Needle N Thread",
    "wof:placetype":"venue"
},
  "geometry": {"coordinates":[-89.067919,41.300863],"type":"Point"}
}