{
  "type": "Feature",
  "properties": {
    "addr:full":"808 N Timothy Ln Astoria IL 61501",
    "addr:housenumber":"808",
    "addr:postcode":"61501",
    "addr:street":"N Timothy Ln",
    "iso:country":"US",
    "sg:address":"808 N Timothy Ln",
    "sg:city":"Astoria",
    "sg:classifiers":[
        {
            "category":"Farming",
            "subcategory":"Livestock Farm",
            "type":"Manufacturing & Wholesale Goods"
        },
        {
            "category":"Farming",
            "subcategory":"Farm",
            "type":"Manufacturing & Wholesale Goods"
        }
    ],
    "sg:phone":"+1 309 329 2236",
    "sg:postcode":"61501",
    "sg:province":"IL",
    "sg:tags":[
        "ranch"
    ],
    "wof:name":"Tommy Trone",
    "wof:placetype":"venue"
},
  "geometry": {"coordinates":[-90.42600299999999,40.199232],"type":"Point"}
}