{
  "type": "Feature",
  "properties": {
    "addr:full":"4510 N Austin Ave Chicago IL 60630",
    "addr:housenumber":"4510",
    "addr:postcode":"60630",
    "addr:street":"N Austin Ave",
    "iso:country":"US",
    "sg:address":"4510 N Austin Ave",
    "sg:city":"Chicago",
    "sg:classifiers":[
        {
            "category":"Professional",
            "subcategory":"Detective & Security Services",
            "type":"Services"
        },
        {
            "category":"Professional",
            "subcategory":"Computer Services",
            "type":"Services"
        }
    ],
    "sg:phone":"+1 773 315 3100",
    "sg:postcode":"60630",
    "sg:province":"IL",
    "sg:tags":[
        "stereo",
        "installation",
        "system"
    ],
    "sg:website":"www.exclusivegt.com",
    "wof:name":"Exclusive Audio & Security",
    "wof:placetype":"venue"
},
  "geometry": {"coordinates":[-87.77743,41.962547],"type":"Point"}
}