{
  "type": "Feature",
  "properties": {
    "addr:full":"305 N Ottawa St Joliet IL 60432",
    "addr:housenumber":"305",
    "addr:postcode":"60432",
    "addr:street":"N Ottawa St",
    "iso:country":"US",
    "sg:address":"305 N Ottawa St",
    "sg:city":"Joliet",
    "sg:classifiers":[
        {
            "category":"Manufacturing",
            "subcategory":"Metals",
            "type":"Manufacturing & Wholesale Goods"
        }
    ],
    "sg:phone":"+1 815 726 0672",
    "sg:postcode":"60432",
    "sg:province":"IL",
    "wof:name":"South Town Refrigeration Corp",
    "wof:placetype":"venue"
},
  "geometry": {"coordinates":[-88.08321599999999,41.530576],"type":"Point"}
}