{
  "type": "Feature",
  "properties": {
    "addr:full":"2354 N Milwaukee Ave Chicago IL 60647",
    "addr:housenumber":"2354",
    "addr:postcode":"60647",
    "addr:street":"N Milwaukee Ave",
    "iso:country":"US",
    "sg:address":"2354 N Milwaukee Ave",
    "sg:city":"Chicago",
    "sg:classifiers":[
        {
            "category":"Social Services",
            "type":"Services"
        }
    ],
    "sg:phone":"+1 312 744 0993",
    "sg:postcode":"60647",
    "sg:province":"IL",
    "wof:name":"NW Mental Health Inc",
    "wof:placetype":"venue"
},
  "geometry": {"coordinates":[-87.700315,41.924607],"type":"Point"}
}