{
  "type": "Feature",
  "properties": {
    "iso:country":"US",
    "sg:address":"1404 Newton Dr",
    "sg:city":"Champaign",
    "sg:classifiers":[
        {
            "category":"Banks & Credit Unions",
            "subcategory":"Financial Services",
            "type":"Services"
        }
    ],
    "sg:phone":"+1 217 351 5000",
    "sg:postcode":"61822",
    "sg:province":"IL",
    "sg:tags":[
        "company",
        "holding"
    ],
    "wof:name":"Flo Con Holding Inc",
    "wof:placetype":"venue"
},
  "geometry": {"coordinates":[-88.271003,40.152589],"type":"Point"}
}