{
  "type": "Feature",
  "properties": {
    "iso:country":"US",
    "sg:address":"225 Buchanan St",
    "sg:city":"Carthage",
    "sg:classifiers":[
        {
            "category":"Shopping",
            "subcategory":"Computers & Home Electronics",
            "type":"Retail Goods"
        }
    ],
    "sg:phone":"+1   ",
    "sg:postcode":"62321",
    "sg:province":"IL",
    "sg:website":"www.cmestore.com",
    "wof:name":"Computing Made Easy",
    "wof:placetype":"venue"
},
  "geometry": {"coordinates":[-91.142609,40.416027],"type":"Point"}
}