{
  "type": "Feature",
  "properties": {
    "iso:country":"US",
    "sg:address":"1547 Warren Ave",
    "sg:city":"Downers Grove",
    "sg:classifiers":[
        {
            "category":"Professional",
            "subcategory":"Lawyer & Legal Services",
            "type":"Services"
        }
    ],
    "sg:phone":"+1 630 435 6340",
    "sg:postcode":"60515",
    "sg:province":"IL",
    "sg:tags":[
        "attorney"
    ],
    "wof:name":"Brian J Krajewski Law Office",
    "wof:placetype":"venue"
},
  "geometry": {"coordinates":[-88.024536,41.796106],"type":"Point"}
}