{
  "type": "Feature",
  "properties": {
    "iso:country":"US",
    "sg:address":"27W285 Devon Ave",
    "sg:city":"Hanover Park",
    "sg:classifiers":[
        {
            "category":"Arts & Performance",
            "subcategory":"Art Gallery",
            "type":"Entertainment"
        }
    ],
    "sg:phone":"+1 630 213 0438",
    "sg:postcode":"60133",
    "sg:province":"IL",
    "sg:website":"www.ontariovilleart.com",
    "wof:name":"Ontarioville Gallery of Fine Art",
    "wof:placetype":"venue"
},
  "geometry": {"coordinates":[-88.152477,41.987867],"type":"Point"}
}