{
  "type": "Feature",
  "properties": {
    "addr:full":"7531 S Stony Island Avenue Chicago IL 60649",
    "addr:housenumber":"7531",
    "addr:postcode":"60649",
    "addr:street":"S Stony Island Avenue",
    "iso:country":"US",
    "sg:address":"7531 S Stony Island Avenue",
    "sg:city":"Chicago",
    "sg:classifiers":[
        {
            "category":"Health Services",
            "subcategory":"Doctor",
            "type":"Services"
        }
    ],
    "sg:phone":"+1 773 324 2765",
    "sg:postcode":"60649",
    "sg:province":"IL",
    "sg:website":"www.fmc-ag.com",
    "wof:name":"Fresenius Medical Care",
    "wof:placetype":"venue"
},
  "geometry": {"coordinates":[-87.585514,41.757567],"type":"Point"}
}