{
  "type": "Feature",
  "properties": {
    "iso:country":"US",
    "sg:address":"25668 Jersey Rd",
    "sg:city":"Tampico",
    "sg:classifiers":[
        {
            "category":"Building & Trades",
            "subcategory":"Construction",
            "type":"Services"
        }
    ],
    "sg:phone":"+1 815 438 2246",
    "sg:postcode":"61283",
    "sg:province":"IL",
    "sg:tags":[
        "excavating",
        "contractor"
    ],
    "wof:name":"Burke Excavating Inc",
    "wof:placetype":"venue"
},
  "geometry": {"coordinates":[-89.75845,41.613373],"type":"Point"}
}