{
  "type": "Feature",
  "properties": {
    "iso:country":"US",
    "sg:address":"670 S Lake Ridge Ave",
    "sg:city":"Decatur",
    "sg:classifiers":[
        {
            "category":"Retail",
            "subcategory":"Repair Shop",
            "type":"Services"
        }
    ],
    "sg:phone":"+1 217 422 2256",
    "sg:postcode":"62521",
    "sg:province":"IL",
    "sg:tags":[
        "freezers-repair",
        "refrigerator"
    ],
    "wof:name":"Franks Refrigeration",
    "wof:placetype":"venue"
},
  "geometry": {"coordinates":[-88.892864,39.837206],"type":"Point"}
}