{
  "type": "Feature",
  "properties": {
    "iso:country":"US",
    "sg:address":"1901 N Roselle Rd",
    "sg:city":"Schaumburg",
    "sg:classifiers":[
        {
            "category":"Professional",
            "subcategory":"Business Services",
            "type":"Services"
        }
    ],
    "sg:phone":"+1 847 517 1400",
    "sg:postcode":"60195",
    "sg:province":"IL",
    "sg:tags":[
        "paging",
        "answering"
    ],
    "wof:name":"Executive Message & Mail Ctr",
    "wof:placetype":"venue"
},
  "geometry": {"coordinates":[-88.079512,42.063098],"type":"Point"}
}