{
  "type": "Feature",
  "properties": {
    "addr:full":"8198 N Co Rd 1880 E Charleston IL 61920",
    "addr:housenumber":"8198;1880 e",
    "addr:postcode":"61920",
    "addr:street":"N Co Rd",
    "iso:country":"US",
    "sg:address":"8198 N Co Rd 1880 E",
    "sg:city":"Charleston",
    "sg:classifiers":[
        {
            "category":"Building & Trades",
            "subcategory":"Construction",
            "type":"Services"
        }
    ],
    "sg:phone":"+1 217 345 9607",
    "sg:postcode":"61920",
    "sg:province":"IL",
    "sg:tags":[
        "home",
        "general",
        "remodeling",
        "contractor"
    ],
    "wof:name":"Miller & Etnire Construction",
    "wof:placetype":"venue"
},
  "geometry": {"coordinates":[-88.123893,39.494225],"type":"Point"}
}