{
  "type": "Feature",
  "properties": {
    "iso:country":"US",
    "sg:address":"720 Parras St",
    "sg:city":"Danville",
    "sg:classifiers":[
        {
            "category":"Retail",
            "subcategory":"Auto Repair",
            "type":"Services"
        }
    ],
    "sg:phone":"+1 217 443 5128",
    "sg:postcode":"61832",
    "sg:province":"IL",
    "sg:tags":[
        "wrecker"
    ],
    "wof:name":"Jasper O Mc Queen Towing Svc",
    "wof:placetype":"venue"
},
  "geometry": {"coordinates":[-87.651936,40.13564],"type":"Point"}
}