{
  "type": "Feature",
  "properties": {
    "addr:full":"111 E Center St Le Roy IL 61752",
    "addr:housenumber":"111",
    "addr:postcode":"61752",
    "addr:street":"E Center St",
    "iso:country":"US",
    "sg:address":"111 E Center St",
    "sg:city":"Le Roy",
    "sg:classifiers":[
        {
            "category":"Government",
            "subcategory":"Office",
            "type":"Public Place"
        }
    ],
    "sg:phone":"+1 309 962 9311",
    "sg:postcode":"61752",
    "sg:province":"IL",
    "sg:tags":[
        "civil",
        "defense",
        "agency"
    ],
    "wof:name":"Le Roy Civil Defense Emergency",
    "wof:placetype":"venue"
},
  "geometry": {"coordinates":[-88.761121,40.347061],"type":"Point"}
}