{
  "type": "Feature",
  "properties": {
    "addr:full":"428 N Alfred Ave Elgin IL 60123",
    "addr:housenumber":"428",
    "addr:postcode":"60123",
    "addr:street":"N Alfred Ave",
    "iso:country":"US",
    "sg:address":"428 N Alfred Ave",
    "sg:city":"Elgin",
    "sg:classifiers":[
        {
            "category":"Manufacturing",
            "subcategory":"Printing",
            "type":"Manufacturing & Wholesale Goods"
        }
    ],
    "sg:phone":"+1 847 697 6456",
    "sg:postcode":"60123",
    "sg:province":"IL",
    "sg:tags":[
        "lithographic",
        "commercial"
    ],
    "wof:name":"George Kramer",
    "wof:placetype":"venue"
},
  "geometry": {"coordinates":[-88.305814,42.044681],"type":"Point"}
}