{
  "type": "Feature",
  "properties": {
    "iso:country":"US",
    "sg:address":"45 Ridgewood Rd",
    "sg:city":"Elk Grove Village",
    "sg:classifiers":[
        {
            "category":"Utilities",
            "subcategory":"Telephone",
            "type":"Services"
        }
    ],
    "sg:phone":"+1 847 417 5430",
    "sg:postcode":"60007",
    "sg:province":"IL",
    "sg:tags":[
        "communications"
    ],
    "wof:name":"Rodcom",
    "wof:placetype":"venue"
},
  "geometry": {"coordinates":[-87.98612,42.022095],"type":"Point"}
}