{
  "type": "Feature",
  "properties": {
    "iso:country":"US",
    "sg:address":"311 Moeller Rd",
    "sg:city":"Jacksonville",
    "sg:classifiers":[
        {
            "category":"Building & Trades",
            "subcategory":"Construction",
            "type":"Services"
        }
    ],
    "sg:phone":"+1 217 245 9617",
    "sg:postcode":"62650",
    "sg:province":"IL",
    "sg:tags":[
        "paving",
        "contractor"
    ],
    "wof:name":"K E Vas Co",
    "wof:placetype":"venue"
},
  "geometry": {"coordinates":[-90.229091,39.689129],"type":"Point"}
}