{
  "type": "Feature",
  "properties": {
    "iso:country":"US",
    "sg:address":"743 W Locust St",
    "sg:city":"Canton",
    "sg:classifiers":[
        {
            "category":"Building & Trades",
            "subcategory":"Construction",
            "type":"Services"
        }
    ],
    "sg:phone":"+1 309 647 7199",
    "sg:postcode":"61520",
    "sg:province":"IL",
    "sg:tags":[
        "house"
    ],
    "wof:name":"Source Renovation Co",
    "wof:placetype":"venue"
},
  "geometry": {"coordinates":[-90.054521,40.558679],"type":"Point"}
}