{
  "type": "Feature",
  "properties": {
    "addr:full":"616 N 4th St Chillicothe IL 61523",
    "addr:housenumber":"616",
    "addr:postcode":"61523",
    "addr:street":"N 4Th St",
    "iso:country":"US",
    "sg:address":"616 N 4th St",
    "sg:city":"Chillicothe",
    "sg:classifiers":[
        {
            "category":"Autos & Motor Vehicles",
            "subcategory":"Automobile Sales",
            "type":"Retail Goods"
        }
    ],
    "sg:phone":"+1 309 274 4716",
    "sg:postcode":"61523",
    "sg:province":"IL",
    "sg:tags":[
        "car",
        "used",
        "dealer"
    ],
    "wof:name":"Jerry's Auto Sales",
    "wof:placetype":"venue"
},
  "geometry": {"coordinates":[-89.489514,40.914578],"type":"Point"}
}