{
  "type": "Feature",
  "properties": {
    "addr:full":"5430 W Montrose Ave Chicago IL 60641",
    "addr:housenumber":"5430",
    "addr:postcode":"60641",
    "addr:street":"W Montrose Ave",
    "iso:country":"US",
    "sg:address":"5430 W Montrose Ave",
    "sg:city":"Chicago",
    "sg:classifiers":[
        {
            "category":"Retail",
            "subcategory":"Auto Repair",
            "type":"Services"
        }
    ],
    "sg:phone":"+1 773 282 4848",
    "sg:postcode":"60641",
    "sg:province":"IL",
    "sg:tags":[
        "body",
        "shop"
    ],
    "wof:name":"Accurate Auto Carstar",
    "wof:placetype":"venue"
},
  "geometry": {"coordinates":[-87.764297,41.960499],"type":"Point"}
}