{
  "type": "Feature",
  "properties": {
    "addr:full":"5411 E State St Rockford IL 61108",
    "addr:housenumber":"5411",
    "addr:postcode":"61108",
    "addr:street":"E State St",
    "iso:country":"US",
    "sg:address":"5411 E State St",
    "sg:city":"Rockford",
    "sg:classifiers":[
        {
            "category":"Wholesale",
            "subcategory":"Durable Goods & Equipment",
            "type":"Manufacturing & Wholesale Goods"
        }
    ],
    "sg:phone":"+1 815 398 2500",
    "sg:postcode":"61108",
    "sg:province":"IL",
    "sg:tags":[
        "representative",
        "manufacturer"
    ],
    "sg:website":"www.wpi66.com",
    "wof:name":"Warranty Processing Inc",
    "wof:placetype":"venue"
},
  "geometry": {"coordinates":[-89.00981,42.265211],"type":"Point"}
}