{
  "type": "Feature",
  "properties": {
    "iso:country":"US",
    "sg:address":"605 S Hillside Ave",
    "sg:city":"Elmhurst",
    "sg:classifiers":[
        {
            "category":"Organizations",
            "subcategory":"Religious Organization",
            "type":"Services"
        }
    ],
    "sg:phone":"+1 630 834 5206",
    "sg:postcode":"60126",
    "sg:province":"IL",
    "wof:name":"Realization Advisors, Inc.",
    "wof:placetype":"venue"
},
  "geometry": {"coordinates":[-87.950822,41.882409],"type":"Point"}
}