{
  "type": "Feature",
  "properties": {
    "iso:country":"US",
    "sg:address":"329 S Franklin St",
    "sg:city":"Chicago",
    "sg:classifiers":[
        {
            "category":"Food & Beverages",
            "subcategory":"Bakery",
            "type":"Retail Goods"
        }
    ],
    "sg:phone":"+1 312 922 9255",
    "sg:postcode":"60606",
    "sg:province":"IL",
    "sg:tags":[
        "sandwich"
    ],
    "sg:website":"www.pocketsonline.com",
    "wof:name":"Pockets",
    "wof:placetype":"venue"
},
  "geometry": {"coordinates":[-87.635002,41.877499],"type":"Point"}
}