{
  "type": "Feature",
  "properties": {
    "addr:full":"1201 S State St Jerseyville IL 62052",
    "addr:housenumber":"1201",
    "addr:postcode":"62052",
    "addr:street":"S State St",
    "iso:country":"US",
    "sg:address":"1201 S State St",
    "sg:city":"Jerseyville",
    "sg:classifiers":[
        {
            "category":"Retail",
            "subcategory":"Veterinary Services",
            "type":"Services"
        }
    ],
    "sg:phone":"+1 618 498 6024",
    "sg:postcode":"62052",
    "sg:province":"IL",
    "sg:tags":[
        "veterinarian",
        "emergency"
    ],
    "wof:name":"Donald M Van Walleghen Dv",
    "wof:placetype":"venue"
},
  "geometry": {"coordinates":[-90.317268,39.10725],"type":"Point"}
}