{
  "type": "Feature",
  "properties": {
    "addr:full":"450 Mildred Ave Cahokia IL 62206",
    "addr:housenumber":"450",
    "addr:postcode":"62206",
    "addr:street":"Mildred Ave",
    "iso:country":"US",
    "sg:address":"450 Mildred Ave",
    "sg:city":"Cahokia",
    "sg:classifiers":[
        {
            "category":"Building & Trades",
            "subcategory":"Electrical",
            "type":"Services"
        }
    ],
    "sg:phone":"+1 618 337 2778",
    "sg:postcode":"62206",
    "sg:province":"IL",
    "sg:tags":[
        "electric",
        "contractor"
    ],
    "wof:name":"Integrity",
    "wof:placetype":"venue"
},
  "geometry": {"coordinates":[-90.17592399999999,38.571099],"type":"Point"}
}