{
  "type": "Feature",
  "properties": {
    "addr:full":"2325 4th St Peru IL 61354",
    "addr:housenumber":"2325",
    "addr:postcode":"61354",
    "addr:street":"4Th St",
    "iso:country":"US",
    "sg:address":"2325 4th St",
    "sg:city":"Peru",
    "sg:classifiers":[
        {
            "category":"Home & Garden",
            "subcategory":"Furniture",
            "type":"Retail Goods"
        }
    ],
    "sg:phone":"+1   ",
    "sg:postcode":"61354",
    "sg:province":"IL",
    "sg:tags":[
        "mfg",
        "custom",
        "cabinet"
    ],
    "wof:name":"H B Cabinet Inc",
    "wof:placetype":"venue"
},
  "geometry": {"coordinates":[-89.13672200000001,41.327618],"type":"Point"}
}