{
  "type": "Feature",
  "properties": {
    "iso:country":"US",
    "sg:address":"2057 de Cook Ave",
    "sg:city":"Park Ridge",
    "sg:classifiers":[
        {
            "category":"Building & Trades",
            "subcategory":"Landscaping Services",
            "type":"Services"
        }
    ],
    "sg:phone":"+1 847 518 0268",
    "sg:postcode":"60068",
    "sg:province":"IL",
    "sg:tags":[
        "lawn",
        "garden"
    ],
    "wof:name":"Vito & Bros Landscaping",
    "wof:placetype":"venue"
},
  "geometry": {"coordinates":[-87.85447000000001,42.033172],"type":"Point"}
}