{
  "type": "Feature",
  "properties": {
    "iso:country":"US",
    "sg:address":"1208 Larraway Dr",
    "sg:city":"Buffalo Grove",
    "sg:classifiers":[
        {
            "category":"Taxi",
            "type":"Transportation"
        }
    ],
    "sg:phone":"+1 847 478 0101",
    "sg:postcode":"60089",
    "sg:province":"IL",
    "sg:tags":[
        "taxicab"
    ],
    "wof:name":"One Zero One Express Taxi",
    "wof:placetype":"venue"
},
  "geometry": {"coordinates":[-87.966212,42.175227],"type":"Point"}
}