{
  "type": "Feature",
  "properties": {
    "iso:country":"US",
    "sg:address":"14 Woodcrest Dr",
    "sg:city":"Geneseo",
    "sg:classifiers":[
        {
            "category":"Manufacturing",
            "subcategory":"Tools & Machinery",
            "type":"Manufacturing & Wholesale Goods"
        }
    ],
    "sg:phone":"+1 309 441 6228",
    "sg:postcode":"61254",
    "sg:province":"IL",
    "sg:tags":[
        "equipment",
        "mfg"
    ],
    "wof:name":"Cnh Global",
    "wof:placetype":"venue"
},
  "geometry": {"coordinates":[-90.254567,41.495318],"type":"Point"}
}