{
  "type": "Feature",
  "properties": {
    "iso:country":"US",
    "sg:address":"219 S 3rd St",
    "sg:city":"Geneva",
    "sg:classifiers":[
        {
            "category":"Professional",
            "subcategory":"Lawyer & Legal Services",
            "type":"Services"
        }
    ],
    "sg:phone":"+1 630 845 0054",
    "sg:postcode":"60134",
    "sg:province":"IL",
    "sg:tags":[
        "attorney"
    ],
    "wof:name":"Lonergan Law LTD",
    "wof:placetype":"venue"
},
  "geometry": {"coordinates":[-88.308489,41.884972],"type":"Point"}
}