{
  "type": "Feature",
  "properties": {
    "addr:full":"325 Harrison St Oak Park IL 60304",
    "addr:housenumber":"325",
    "addr:postcode":"60304",
    "addr:street":"Harrison St",
    "iso:country":"US",
    "sg:address":"325 Harrison St",
    "sg:city":"Oak Park",
    "sg:classifiers":[
        {
            "category":"Shopping",
            "subcategory":"Gifts & Souvenirs",
            "type":"Retail Goods"
        }
    ],
    "sg:phone":"+1   ",
    "sg:postcode":"60304",
    "sg:province":"IL",
    "wof:name":"Akatombo",
    "wof:placetype":"venue"
},
  "geometry": {"coordinates":[-87.782365,41.872654],"type":"Point"}
}