{
  "type": "Feature",
  "properties": {
    "iso:country":"US",
    "sg:address":"396 Prospect Ave",
    "sg:city":"Glen Ellyn",
    "sg:classifiers":[
        {
            "category":"Professional",
            "subcategory":"Management & Consulting",
            "type":"Services"
        }
    ],
    "sg:phone":"+1 630 469 5137",
    "sg:postcode":"60137",
    "sg:province":"IL",
    "wof:name":"Daedalus Systems International",
    "wof:placetype":"venue"
},
  "geometry": {"coordinates":[-88.070123,41.873178],"type":"Point"}
}