{
  "type": "Feature",
  "properties": {
    "addr:full":"615 W Front St Ste #202 Wheaton IL 60187",
    "addr:housenumber":"615;202",
    "addr:postcode":"60187",
    "addr:street":"W Front St Ste #",
    "iso:country":"US",
    "sg:address":"615 W Front St Ste #202",
    "sg:city":"Wheaton",
    "sg:classifiers":[
        {
            "category":"Building & Trades",
            "subcategory":"Construction",
            "type":"Services"
        }
    ],
    "sg:phone":"+1 630 632 7685",
    "sg:postcode":"60187",
    "sg:province":"IL",
    "sg:tags":[
        "contractor"
    ],
    "sg:website":"www.avaloft.com",
    "wof:name":"Avaloft Designers & Builders",
    "wof:placetype":"venue"
},
  "geometry": {"coordinates":[-88.11557500000001,41.865414],"type":"Point"}
}