{
  "type": "Feature",
  "properties": {
    "iso:country":"US",
    "sg:address":"112 E Ryder St",
    "sg:city":"Litchfield",
    "sg:classifiers":[
        {
            "category":"Communications",
            "subcategory":"Newspaper",
            "type":"Services"
        },
        {
            "category":"Wholesale",
            "subcategory":"Books, Periodicals, & Newspapers",
            "type":"Manufacturing & Wholesale Goods"
        }
    ],
    "sg:phone":"+1 217 324 2121",
    "sg:postcode":"62056",
    "sg:province":"IL",
    "sg:tags":[
        "dealers-wholesale",
        "news"
    ],
    "wof:name":"News Herald",
    "wof:placetype":"venue"
},
  "geometry": {"coordinates":[-89.65526800000001,39.176376],"type":"Point"}
}