{
  "type": "Feature",
  "properties": {
    "iso:country":"US",
    "sg:address":"930 W 31st Street",
    "sg:city":"Chicago",
    "sg:classifiers":[
        {
            "category":"Autos & Motor Vehicles",
            "subcategory":"Fuel & Gas Station",
            "type":"Retail Goods"
        },
        {
            "category":"Retail",
            "subcategory":"Auto Repair",
            "type":"Services"
        }
    ],
    "sg:phone":"+1 312 842 1887",
    "sg:postcode":"60608",
    "sg:province":"IL",
    "wof:name":"Bridgeport Transmissions",
    "wof:placetype":"venue"
},
  "geometry": {"coordinates":[-87.650026,41.838105],"type":"Point"}
}