{
  "type": "Feature",
  "properties": {
    "iso:country":"US",
    "sg:address":"623 Henry St",
    "sg:city":"Alton",
    "sg:classifiers":[
        {
            "category":"Personal",
            "subcategory":"Beauty Salon",
            "type":"Services"
        }
    ],
    "sg:phone":"+1 618 465 6842",
    "sg:postcode":"62002",
    "sg:province":"IL",
    "sg:tags":[
        "shop",
        "care",
        "skin"
    ],
    "wof:name":"Henry Street Hair Salon",
    "wof:placetype":"venue"
},
  "geometry": {"coordinates":[-90.176665,38.89309],"type":"Point"}
}