{
  "type": "Feature",
  "properties": {
    "addr:full":"39 W 117 Bartelt Rd. Geneva IL 60134",
    "addr:housenumber":"39",
    "addr:postcode":"60134",
    "addr:street":"W 117 Bartelt Rd.",
    "iso:country":"US",
    "sg:address":"39 W 117 Bartelt Rd.",
    "sg:city":"Geneva",
    "sg:classifiers":[
        {
            "category":"Recreation",
            "subcategory":"Dog Park",
            "type":"Entertainment"
        },
        {
            "category":"Shopping",
            "subcategory":"Pets & Pet Supplies",
            "type":"Retail Goods"
        }
    ],
    "sg:phone":"+1 630 845 4898",
    "sg:postcode":"60134",
    "sg:province":"IL",
    "sg:tags":[
        "training"
    ],
    "wof:name":"Bark Busters",
    "wof:placetype":"venue"
},
  "geometry": {"coordinates":[-88.3351,41.8811],"type":"Point"}
}