{
  "type": "Feature",
  "properties": {
    "iso:country":"US",
    "sg:address":"23406 W 135th St",
    "sg:city":"Plainfield",
    "sg:classifiers":[
        {
            "category":"Real Estate",
            "subcategory":"Real Estate Services",
            "type":"Services"
        },
        {
            "category":"Real Estate",
            "subcategory":"Real Estate Agent",
            "type":"Services"
        }
    ],
    "sg:phone":"+1 815 577 3215",
    "sg:postcode":"60544",
    "sg:province":"IL",
    "sg:tags":[
        "buyer",
        "broker"
    ],
    "wof:name":"Jensen Realty Inc",
    "wof:placetype":"venue"
},
  "geometry": {"coordinates":[-88.188984,41.637378],"type":"Point"}
}