{
  "type": "Feature",
  "properties": {
    "iso:country":"US",
    "sg:address":"1830 W Irving Park Rd",
    "sg:city":"Chicago",
    "sg:classifiers":[
        {
            "category":"Building & Trades",
            "subcategory":"Plumbing",
            "type":"Services"
        }
    ],
    "sg:phone":"+1 773 868 4100",
    "sg:postcode":"60613",
    "sg:province":"IL",
    "sg:tags":[
        "plumber",
        "industrial",
        "contractors-commercial"
    ],
    "wof:name":"Public Plumbing & Heating Inc",
    "wof:placetype":"venue"
},
  "geometry": {"coordinates":[-87.67495099999999,41.954182],"type":"Point"}
}