{
  "type": "Feature",
  "properties": {
    "iso:country":"US",
    "sg:address":"519 Main St",
    "sg:city":"Pecatonica",
    "sg:classifiers":[
        {
            "category":"Sports & Exercise",
            "subcategory":"Gym",
            "type":"Entertainment"
        }
    ],
    "sg:phone":"+1 815 239 9150",
    "sg:postcode":"61063",
    "sg:province":"IL",
    "sg:tags":[
        "club",
        "health",
        "studio",
        "gymnasium"
    ],
    "wof:name":"Curves For Women",
    "wof:placetype":"venue"
},
  "geometry": {"coordinates":[-89.359475,42.312624],"type":"Point"}
}