{
  "type": "Feature",
  "properties": {
    "iso:country":"US",
    "sg:address":"200 Lincoln Hwy",
    "sg:city":"Fairview Heights",
    "sg:classifiers":[
        {
            "category":"Restaurant",
            "type":"Food & Drink"
        }
    ],
    "sg:menulink":"http://www.allmenus.com/il/caseyville/185111-show-mes/menu/",
    "sg:phone":"+1 618 628 1625",
    "sg:postcode":"62208",
    "sg:province":"IL",
    "sg:tags":[
        "american"
    ],
    "wof:name":"Show-me's",
    "wof:placetype":"venue"
},
  "geometry": {"coordinates":[-89.981307,38.592728],"type":"Point"}
}