{
  "type": "Feature",
  "properties": {
    "addr:full":"2679 W Forest Rd Freeport IL 61032",
    "addr:housenumber":"2679",
    "addr:postcode":"61032",
    "addr:street":"W Forest Rd",
    "iso:country":"US",
    "sg:address":"2679 W Forest Rd",
    "sg:city":"Freeport",
    "sg:classifiers":[
        {
            "category":"Professional",
            "subcategory":"Business Services",
            "type":"Services"
        }
    ],
    "sg:phone":"+1 815 297 9147",
    "sg:postcode":"61032",
    "sg:province":"IL",
    "wof:name":"Changing Seasons Interiors",
    "wof:placetype":"venue"
},
  "geometry": {"coordinates":[-89.663766,42.272059],"type":"Point"}
}