{
  "type": "Feature",
  "properties": {
    "iso:country":"US",
    "sg:address":"3225 S Racine Avenue",
    "sg:city":"Chicago",
    "sg:classifiers":[
        {
            "category":"Park",
            "type":"Public Place"
        }
    ],
    "sg:phone":"+1 312 747 7001",
    "sg:postcode":"60608",
    "sg:province":"IL",
    "wof:name":"Chicago Park District",
    "wof:placetype":"venue"
},
  "geometry": {"coordinates":[-87.655796,41.835491],"type":"Point"}
}