{
  "type": "Feature",
  "properties": {
    "addr:full":"407 N Elizabeth St Apt 208 Chicago IL 60642",
    "addr:housenumber":"407;208",
    "addr:postcode":"60642",
    "addr:street":"N Elizabeth St Apt",
    "iso:country":"US",
    "sg:address":"407 N Elizabeth St Apt 208",
    "sg:city":"Chicago",
    "sg:classifiers":[
        {
            "category":"Retail",
            "subcategory":"Portrait Studio",
            "type":"Services"
        },
        {
            "category":"Professional",
            "subcategory":"Art Services",
            "type":"Services"
        }
    ],
    "sg:phone":"+1 312 491 1133",
    "sg:postcode":"60642",
    "sg:province":"IL",
    "sg:tags":[
        "photographer",
        "photography",
        "store"
    ],
    "wof:name":"Lindsay Gallup Photo",
    "wof:placetype":"venue"
},
  "geometry": {"coordinates":[-87.658699,41.889014],"type":"Point"}
}