{
  "type": "Feature",
  "properties": {
    "addr:full":"6501 S Promontory Dr Chicago IL 60649",
    "addr:housenumber":"6501",
    "addr:postcode":"60649",
    "addr:street":"S Promontory Dr",
    "iso:country":"US",
    "sg:address":"6501 S Promontory Dr",
    "sg:city":"Chicago",
    "sg:classifiers":[
        {
            "category":"Health Services",
            "subcategory":"Doctor",
            "type":"Services"
        },
        {
            "category":"Health Services",
            "subcategory":"Hospital",
            "type":"Services"
        }
    ],
    "sg:phone":"+1 773 363 6700",
    "sg:postcode":"60649",
    "sg:province":"IL",
    "sg:tags":[
        "physician",
        "pediatrics",
        "surgeons"
    ],
    "sg:website":"http://www.larabida.org",
    "wof:name":"Larabida Children's Hospital",
    "wof:placetype":"venue"
},
  "geometry": {"coordinates":[-87.571158,41.77678],"type":"Point"}
}