{
  "type": "Feature",
  "properties": {
    "iso:country":"US",
    "sg:address":"562 Dover Cir",
    "sg:city":"Frankfort",
    "sg:classifiers":[
        {
            "category":"Professional",
            "subcategory":"Lawyer & Legal Services",
            "type":"Services"
        }
    ],
    "sg:phone":"+1 815 806 8730",
    "sg:postcode":"60423",
    "sg:province":"IL",
    "sg:tags":[
        "attorney"
    ],
    "wof:name":"Marjorie Fortner",
    "wof:placetype":"venue"
},
  "geometry": {"coordinates":[-87.80656999999999,41.492964],"type":"Point"}
}