{
  "type": "Feature",
  "properties": {
    "addr:full":"9414 Rambouillet Rdg Roscoe IL 61073",
    "addr:postcode":"9414;61073",
    "iso:country":"US",
    "sg:address":"9414 Rambouillet Rdg",
    "sg:city":"Roscoe",
    "sg:classifiers":[
        {
            "category":"Building & Trades",
            "subcategory":"Landscaping Services",
            "type":"Services"
        }
    ],
    "sg:phone":"+1 815 623 3905",
    "sg:postcode":"61073",
    "sg:province":"IL",
    "sg:tags":[
        "landscape",
        "contractor"
    ],
    "wof:name":"Al's Tree Planting",
    "wof:placetype":"venue"
},
  "geometry": {"coordinates":[-89.00393699999999,42.397002],"type":"Point"}
}