{
  "type": "Feature",
  "properties": {
    "addr:full":"2153 N Southport Ave Chicago IL 60614",
    "addr:housenumber":"2153",
    "addr:postcode":"60614",
    "addr:street":"N Southport Ave",
    "iso:country":"US",
    "sg:address":"2153 N Southport Ave",
    "sg:city":"Chicago",
    "sg:classifiers":[
        {
            "category":"Retail",
            "subcategory":"Laundry & Dry Cleaning",
            "type":"Services"
        }
    ],
    "sg:phone":"+1 847 869 8820",
    "sg:postcode":"60614",
    "sg:province":"IL",
    "wof:name":"Park Evanstons Cleaners",
    "wof:placetype":"venue"
},
  "geometry": {"coordinates":[-87.66330000000001,41.921501],"type":"Point"}
}