{
  "type": "Feature",
  "properties": {
    "addr:full":"421 Stevens St Geneva IL 60134",
    "addr:housenumber":"421",
    "addr:postcode":"60134",
    "addr:street":"Stevens St",
    "iso:country":"US",
    "sg:address":"421 Stevens St",
    "sg:city":"Geneva",
    "sg:classifiers":[
        {
            "category":"Manufacturing",
            "subcategory":"Rubber & Plastics",
            "type":"Manufacturing & Wholesale Goods"
        }
    ],
    "sg:phone":"+1 630 232 8800",
    "sg:postcode":"60134",
    "sg:province":"IL",
    "sg:website":"www.tri-par.net",
    "wof:name":"Tri PAR Die Corp",
    "wof:placetype":"venue"
},
  "geometry": {"coordinates":[-88.30940099999999,41.892457],"type":"Point"}
}