{
  "type": "Feature",
  "properties": {
    "iso:country":"US",
    "sg:address":"1032 W Northwest Hwy",
    "sg:city":"Barrington",
    "sg:classifiers":[
        {
            "category":"Wholesale",
            "subcategory":"Metals & Minerals",
            "type":"Manufacturing & Wholesale Goods"
        }
    ],
    "sg:phone":"+1 847 381 7713",
    "sg:postcode":"60010",
    "sg:province":"IL",
    "sg:tags":[
        "rod"
    ],
    "wof:name":"Tuttle Manufacturing",
    "wof:placetype":"venue"
},
  "geometry": {"coordinates":[-88.167234,42.171744],"type":"Point"}
}