{
  "type": "Feature",
  "properties": {
    "addr:full":"1695 Larkin Ave Elgin IL 60123",
    "addr:housenumber":"1695",
    "addr:postcode":"60123",
    "addr:street":"Larkin Ave",
    "iso:country":"US",
    "sg:address":"1695 Larkin Ave",
    "sg:city":"Elgin",
    "sg:classifiers":[
        {
            "category":"Banks & Credit Unions",
            "subcategory":"Bank",
            "type":"Services"
        }
    ],
    "sg:phone":"+1 847 214 8323",
    "sg:postcode":"60123",
    "sg:province":"IL",
    "wof:name":"National City",
    "wof:placetype":"venue"
},
  "geometry": {"coordinates":[-88.320165,42.033597],"type":"Point"}
}