{
  "type": "Feature",
  "properties": {
    "addr:full":"1745 W Chicago Ave Chicago IL 60622",
    "addr:housenumber":"1745",
    "addr:postcode":"60622",
    "addr:street":"W Chicago Ave",
    "iso:country":"US",
    "sg:address":"1745 W Chicago Ave",
    "sg:city":"Chicago",
    "sg:phone":"+1 312 738 0363",
    "sg:postcode":"60622",
    "sg:province":"IL",
    "wof:name":"El Taco Veloz Taqueria",
    "wof:placetype":"venue"
},
  "geometry": {"coordinates":[-87.67118600000001,41.896024],"type":"Point"}
}