{
  "type": "Feature",
  "properties": {
    "iso:country":"US",
    "sg:address":"235 W College Ave",
    "sg:city":"Jacksonville",
    "sg:classifiers":[
        {
            "category":"Real Estate",
            "subcategory":"Real Estate Operator",
            "type":"Services"
        }
    ],
    "sg:phone":"+1 217 245 7191",
    "sg:postcode":"62650",
    "sg:province":"IL",
    "sg:tags":[
        "apartment"
    ],
    "wof:name":"Wesara Apartments",
    "wof:placetype":"venue"
},
  "geometry": {"coordinates":[-90.231284,39.732412],"type":"Point"}
}