{
  "type": "Feature",
  "properties": {
    "iso:country":"US",
    "sg:address":"7015 Edgewood Ct",
    "sg:city":"Spring Grove",
    "sg:classifiers":[
        {
            "category":"Building & Trades",
            "subcategory":"Electrical",
            "type":"Services"
        }
    ],
    "sg:phone":"+1 815 675 9540",
    "sg:postcode":"60081",
    "sg:province":"IL",
    "sg:tags":[
        "electrical",
        "contractor"
    ],
    "wof:name":"Village Electric",
    "wof:placetype":"venue"
},
  "geometry": {"coordinates":[-88.2691,42.430637],"type":"Point"}
}