{
  "type": "Feature",
  "properties": {
    "iso:country":"US",
    "sg:address":"1 Lincoln Center",
    "sg:city":"Villa Park",
    "sg:classifiers":[
        {
            "category":"Insurance",
            "subcategory":"Health Insurance",
            "type":"Services"
        }
    ],
    "sg:phone":"+1 630 916 2900",
    "sg:postcode":"60181",
    "sg:province":"IL",
    "sg:tags":[
        "carrier"
    ],
    "wof:name":"Principal Life Insurance Co",
    "wof:placetype":"venue"
},
  "geometry": {"coordinates":[-87.981954,41.847803],"type":"Point"}
}