{
  "type": "Feature",
  "properties": {
    "iso:country":"US",
    "sg:address":"1336 E Dorothy Dr",
    "sg:city":"Palatine",
    "sg:classifiers":[
        {
            "category":"Retail",
            "subcategory":"Portrait Studio",
            "type":"Services"
        }
    ],
    "sg:phone":"+1 847 991 8131",
    "sg:postcode":"60074",
    "sg:province":"IL",
    "sg:tags":[
        "photo"
    ],
    "wof:name":"Malley Imaging & Photography L",
    "wof:placetype":"venue"
},
  "geometry": {"coordinates":[-88.008553,42.111918],"type":"Point"}
}