{
  "type": "Feature",
  "properties": {
    "iso:country":"US",
    "sg:address":"1N712 Bob O Link Dr",
    "sg:city":"Winfield",
    "sg:classifiers":[
        {
            "category":"Building & Trades",
            "subcategory":"Construction",
            "type":"Services"
        }
    ],
    "sg:phone":"+1 630 871 1998",
    "sg:postcode":"60190",
    "sg:province":"IL",
    "sg:tags":[
        "contractor"
    ],
    "wof:name":"Murphy Patrick J Builders",
    "wof:placetype":"venue"
},
  "geometry": {"coordinates":[-88.143764,41.899452],"type":"Point"}
}