{
  "type": "Feature",
  "properties": {
    "iso:country":"US",
    "sg:address":"53 W Jackson Blvd",
    "sg:city":"Chicago",
    "sg:classifiers":[
        {
            "category":"Professional",
            "subcategory":"Lawyer & Legal Services",
            "type":"Services"
        }
    ],
    "sg:phone":"+1 312 427 1696",
    "sg:postcode":"60661",
    "sg:province":"IL",
    "wof:name":"James W Malloy & Associates",
    "wof:placetype":"venue"
},
  "geometry": {"coordinates":[-87.629505,41.878088],"type":"Point"}
}