{
  "type": "Feature",
  "properties": {
    "iso:country":"US",
    "sg:address":"11707 Mark Ln",
    "sg:city":"Orland Park",
    "sg:classifiers":[
        {
            "category":"Professional",
            "subcategory":"Management & Consulting",
            "type":"Services"
        }
    ],
    "sg:phone":"+1 708 403 4385",
    "sg:postcode":"60467",
    "sg:province":"IL",
    "wof:name":"P S Q Consulting Inc",
    "wof:placetype":"venue"
},
  "geometry": {"coordinates":[-87.904092,41.639902],"type":"Point"}
}