{
  "type": "Feature",
  "properties": {
    "iso:country":"US",
    "sg:address":"531 State Rte 3",
    "sg:city":"East Saint Louis",
    "sg:classifiers":[
        {
            "category":"Building & Trades",
            "subcategory":"Plumbing",
            "type":"Services"
        }
    ],
    "sg:phone":"+1 618 337 4505",
    "sg:postcode":"62206",
    "sg:province":"IL",
    "sg:tags":[
        "contractor"
    ],
    "wof:name":"AC Environmental Inc",
    "wof:placetype":"venue"
},
  "geometry": {"coordinates":[-90.191304,38.565023],"type":"Point"}
}