{
  "type": "Feature",
  "properties": {
    "addr:full":"118 E 51st St Chicago IL 60615",
    "addr:housenumber":"118",
    "addr:postcode":"60615",
    "addr:street":"E 51St St",
    "iso:country":"US",
    "sg:address":"118 E 51st St",
    "sg:city":"Chicago",
    "sg:classifiers":[
        {
            "category":"Social Services",
            "subcategory":"Child Care",
            "type":"Services"
        }
    ],
    "sg:phone":"+1 773 536 2223",
    "sg:postcode":"60615",
    "sg:province":"IL",
    "sg:tags":[
        "day"
    ],
    "wof:name":"Brite New Mind Daycare Center No 2",
    "wof:placetype":"venue"
},
  "geometry": {"coordinates":[-87.622325,41.802181],"type":"Point"}
}