{
  "type": "Feature",
  "properties": {
    "iso:country":"US",
    "sg:address":"10 W 35th St",
    "sg:city":"Chicago",
    "sg:classifiers":[
        {
            "category":"Government",
            "subcategory":"Fire Station",
            "type":"Public Place"
        }
    ],
    "sg:phone":"+1 312 745 4210",
    "sg:postcode":"60616",
    "sg:province":"IL",
    "sg:tags":[
        "department"
    ],
    "sg:website":"http://www.ci.chi.il.us",
    "wof:name":"Chicago Fire Department",
    "wof:placetype":"venue"
},
  "geometry": {"coordinates":[-87.626999,41.831005],"type":"Point"}
}