{
  "type": "Feature",
  "properties": {
    "iso:country":"US",
    "sg:address":"106 W Lafayette St",
    "sg:city":"Ottawa",
    "sg:classifiers":[
        {
            "category":"Social Services",
            "type":"Services"
        }
    ],
    "sg:phone":"+1 815 434 9650",
    "sg:postcode":"61350",
    "sg:province":"IL",
    "wof:name":"Adv & Sas",
    "wof:placetype":"venue"
},
  "geometry": {"coordinates":[-88.84260399999999,41.350045],"type":"Point"}
}