{
  "type": "Feature",
  "properties": {
    "addr:full":"2460 State Rte 161 Belleville IL 62226",
    "addr:housenumber":"2460",
    "addr:postcode":"62226",
    "addr:street":"State Rte 161",
    "iso:country":"US",
    "sg:address":"2460 State Rte 161",
    "sg:city":"Belleville",
    "sg:classifiers":[
        {
            "category":"Retail",
            "subcategory":"Auto Repair",
            "type":"Services"
        }
    ],
    "sg:phone":"+1 618 233 6806",
    "sg:postcode":"62226",
    "sg:province":"IL",
    "sg:tags":[
        "towing",
        "wrecker"
    ],
    "wof:name":"Johnston Towing",
    "wof:placetype":"venue"
},
  "geometry": {"coordinates":[-90.004504,38.547611],"type":"Point"}
}