{
  "type": "Feature",
  "properties": {
    "iso:country":"US",
    "sg:address":"20394 W Union Rd",
    "sg:city":"Danville",
    "sg:classifiers":[
        {
            "category":"Wholesale",
            "subcategory":"Machinery & Supplies",
            "type":"Manufacturing & Wholesale Goods"
        }
    ],
    "sg:phone":"+1 217 443 3081",
    "sg:postcode":"61834",
    "sg:province":"IL",
    "sg:tags":[
        "farm",
        "equipment"
    ],
    "wof:name":"Larry T Ellis Equipment",
    "wof:placetype":"venue"
},
  "geometry": {"coordinates":[-87.555931,40.076196],"type":"Point"}
}