{
  "type": "Feature",
  "properties": {
    "addr:full":"2397 E 1251st Rd Ottawa IL 61350",
    "addr:housenumber":"2397",
    "addr:postcode":"61350",
    "addr:street":"E 1251St Rd",
    "iso:country":"US",
    "sg:address":"2397 E 1251st Rd",
    "sg:city":"Ottawa",
    "sg:classifiers":[
        {
            "category":"Manufacturing",
            "subcategory":"Buildings",
            "type":"Manufacturing & Wholesale Goods"
        },
        {
            "category":"Building & Trades",
            "subcategory":"Construction",
            "type":"Services"
        }
    ],
    "sg:phone":"+1 815 433 1262",
    "sg:postcode":"61350",
    "sg:province":"IL",
    "sg:tags":[
        "industrial",
        "system",
        "specialty",
        "builder",
        "heating",
        "contractor",
        "contractors-commercial",
        "home",
        "air conditioning"
    ],
    "wof:name":"H & B Contractors",
    "wof:placetype":"venue"
},
  "geometry": {"coordinates":[-88.93253199999999,41.298172],"type":"Point"}
}