{
  "type": "Feature",
  "properties": {
    "iso:country":"US",
    "sg:address":"504 Sunset Dr",
    "sg:city":"Eureka",
    "sg:classifiers":[
        {
            "category":"Retail",
            "subcategory":"Repair Shop",
            "type":"Services"
        }
    ],
    "sg:phone":"+1 309 467 2429",
    "sg:postcode":"61530",
    "sg:province":"IL",
    "sg:tags":[
        "clocks",
        "parts"
    ],
    "wof:name":"Ken's Clock Shop",
    "wof:placetype":"venue"
},
  "geometry": {"coordinates":[-89.280152,40.724001],"type":"Point"}
}