{
  "type": "Feature",
  "properties": {
    "iso:country":"US",
    "sg:address":"135 S Sycamore St",
    "sg:city":"Centralia",
    "sg:classifiers":[
        {
            "category":"Health Services",
            "subcategory":"Doctor",
            "type":"Services"
        }
    ],
    "sg:phone":"+1 618 532 1411",
    "sg:postcode":"62801",
    "sg:province":"IL",
    "wof:name":"Lindenberg Dental Clinic",
    "wof:placetype":"venue"
},
  "geometry": {"coordinates":[-89.128487,38.526105],"type":"Point"}
}