{
  "type": "Feature",
  "properties": {
    "iso:country":"US",
    "sg:address":"6125 N 2nd St",
    "sg:city":"Loves Park",
    "sg:classifiers":[
        {
            "category":"Home & Garden",
            "subcategory":"Carpets & Floor Coverings",
            "type":"Retail Goods"
        }
    ],
    "sg:phone":"+1   ",
    "sg:postcode":"61111",
    "sg:province":"IL",
    "wof:name":"Carpet Remnant & Rug World",
    "wof:placetype":"venue"
},
  "geometry": {"coordinates":[-89.057878,42.318086],"type":"Point"}
}