{
  "type": "Feature",
  "properties": {
    "addr:full":"1819 W Glen Flora Ave Waukegan IL 60085",
    "addr:housenumber":"1819",
    "addr:postcode":"60085",
    "addr:street":"W Glen Flora Ave",
    "iso:country":"US",
    "sg:address":"1819 W Glen Flora Ave",
    "sg:city":"Waukegan",
    "sg:classifiers":[
        {
            "category":"Personal",
            "subcategory":"Beauty Salon",
            "type":"Services"
        }
    ],
    "sg:phone":"+1 847 244 9517",
    "sg:postcode":"60085",
    "sg:province":"IL",
    "sg:tags":[
        "shop"
    ],
    "wof:name":"T & N Salon De Coiffure",
    "wof:placetype":"venue"
},
  "geometry": {"coordinates":[-87.855312,42.377448],"type":"Point"}
}