{
  "type": "Feature",
  "properties": {
    "addr:full":"8 S Lincoln St Batavia IL 60510",
    "addr:housenumber":"8",
    "addr:postcode":"60510",
    "addr:street":"S Lincoln St",
    "iso:country":"US",
    "sg:address":"8 S Lincoln St",
    "sg:city":"Batavia",
    "sg:classifiers":[
        {
            "category":"Professional",
            "subcategory":"Management & Consulting",
            "type":"Services"
        }
    ],
    "sg:phone":"+1 630 761 8650",
    "sg:postcode":"60510",
    "sg:province":"IL",
    "sg:tags":[
        "business"
    ],
    "wof:name":"M I F Building Consultant",
    "wof:placetype":"venue"
},
  "geometry": {"coordinates":[-88.314273,41.848406],"type":"Point"}
}