{
  "type": "Feature",
  "properties": {
    "iso:country":"US",
    "sg:address":"10912 S Western Ave",
    "sg:city":"Chicago",
    "sg:classifiers":[
        {
            "category":"Personal",
            "subcategory":"Beauty Salon",
            "type":"Services"
        }
    ],
    "sg:phone":"+1 773 239 0505",
    "sg:postcode":"60643",
    "sg:province":"IL",
    "sg:tags":[
        "hair",
        "stylist"
    ],
    "wof:name":"Hair Can Dance",
    "wof:placetype":"venue"
},
  "geometry": {"coordinates":[-87.68125999999999,41.69519],"type":"Point"}
}