{
  "type": "Feature",
  "properties": {
    "iso:country":"US",
    "sg:address":"10302 S Seeley Ave",
    "sg:city":"Chicago",
    "sg:classifiers":[
        {
            "category":"Real Estate",
            "subcategory":"Architect",
            "type":"Services"
        }
    ],
    "sg:phone":"+1 773 233 1000",
    "sg:postcode":"60643",
    "sg:province":"IL",
    "wof:name":"Care Fare",
    "wof:placetype":"venue"
},
  "geometry": {"coordinates":[-87.673422,41.706339],"type":"Point"}
}