{
  "type": "Feature",
  "properties": {
    "addr:full":"2041 16th St Moline IL 61265",
    "addr:housenumber":"2041",
    "addr:postcode":"61265",
    "addr:street":"16Th St",
    "iso:country":"US",
    "sg:address":"2041 16th St",
    "sg:city":"Moline",
    "sg:classifiers":[
        {
            "category":"Ice Cream",
            "type":"Food & Drink"
        }
    ],
    "sg:menulink":"http://www.allmenus.com/il/moline/74353-happy-joes/menu/",
    "sg:phone":"+1 309 764 3388",
    "sg:postcode":"61265",
    "sg:province":"IL",
    "sg:tags":[
        "american",
        "pizza"
    ],
    "wof:name":"Happy Joe's",
    "wof:placetype":"venue"
},
  "geometry": {"coordinates":[-90.51359100000001,41.491653],"type":"Point"}
}