{
  "type": "Feature",
  "properties": {
    "addr:full":"1831 N Santa Fe Ave Chillicothe IL 61523",
    "addr:housenumber":"1831",
    "addr:postcode":"61523",
    "addr:street":"N Santa Fe Ave",
    "iso:country":"US",
    "sg:address":"1831 N Santa Fe Ave",
    "sg:city":"Chillicothe",
    "sg:classifiers":[
        {
            "category":"Local Transit",
            "type":"Transportation"
        }
    ],
    "sg:phone":"+1 309 274 4242",
    "sg:postcode":"61523",
    "sg:province":"IL",
    "wof:name":"Burlington Northern",
    "wof:placetype":"venue"
},
  "geometry": {"coordinates":[-89.49440800000001,40.929368],"type":"Point"}
}