{
  "type": "Feature",
  "properties": {
    "iso:country":"US",
    "sg:address":"3108 N Rockton Ave",
    "sg:city":"Rockford",
    "sg:classifiers":[
        {
            "category":"Retail",
            "subcategory":"Laundry & Dry Cleaning",
            "type":"Services"
        }
    ],
    "sg:phone":"+1 815 964 1395",
    "sg:postcode":"61103",
    "sg:province":"IL",
    "sg:tags":[
        "drycleaning",
        "plant",
        "power"
    ],
    "wof:name":"R & H Laundromat & Dry Clng",
    "wof:placetype":"venue"
},
  "geometry": {"coordinates":[-89.096906,42.305892],"type":"Point"}
}