{
  "type": "Feature",
  "properties": {
    "addr:full":"1007 W 123rd St Calumet Park IL 60827",
    "addr:housenumber":"1007",
    "addr:postcode":"60827",
    "addr:street":"W 123Rd St",
    "iso:country":"US",
    "sg:address":"1007 W 123rd St",
    "sg:city":"Calumet Park",
    "sg:classifiers":[
        {
            "category":"Professional",
            "subcategory":"Computer Services",
            "type":"Services"
        }
    ],
    "sg:phone":"+1 708 396 8516",
    "sg:postcode":"60827",
    "sg:province":"IL",
    "sg:tags":[
        "processing",
        "datum"
    ],
    "wof:name":"Anon Data Resource",
    "wof:placetype":"venue"
},
  "geometry": {"coordinates":[-87.646914,41.670387],"type":"Point"}
}