{
  "type": "Feature",
  "properties": {
    "addr:full":"618 Pierce Ave Bradley IL 60915",
    "addr:housenumber":"618",
    "addr:postcode":"60915",
    "addr:street":"Pierce Ave",
    "iso:country":"US",
    "sg:address":"618 Pierce Ave",
    "sg:city":"Bradley",
    "sg:classifiers":[
        {
            "category":"Building & Trades",
            "subcategory":"Cleaning & Sanitation",
            "type":"Services"
        }
    ],
    "sg:phone":"+1 815 935 5844",
    "sg:postcode":"60915",
    "sg:province":"IL",
    "sg:tags":[
        "window"
    ],
    "wof:name":"Gene's Window Cleaning",
    "wof:placetype":"venue"
},
  "geometry": {"coordinates":[-87.840654,41.15194],"type":"Point"}
}