{
  "type": "Feature",
  "properties": {
    "iso:country":"US",
    "sg:address":"160 E Marquette Rd",
    "sg:city":"Chicago",
    "sg:classifiers":[
        {
            "category":"Wholesale",
            "subcategory":"Non-durable Goods",
            "type":"Manufacturing & Wholesale Goods"
        },
        {
            "category":"Shopping",
            "subcategory":"Gifts & Souvenirs",
            "type":"Retail Goods"
        },
        {
            "category":"Professional",
            "subcategory":"Business Services",
            "type":"Services"
        }
    ],
    "sg:phone":"+1 773 224 1231",
    "sg:postcode":"60637",
    "sg:province":"IL",
    "sg:tags":[
        "shop",
        "broker",
        "merchandise",
        "merchandise-wholesale"
    ],
    "wof:name":"Noah's Ark",
    "wof:placetype":"venue"
},
  "geometry": {"coordinates":[-87.621236,41.772865],"type":"Point"}
}