{
  "type": "Feature",
  "properties": {
    "iso:country":"US",
    "sg:address":"1533 S River Rd",
    "sg:city":"Des Plaines",
    "sg:classifiers":[
        {
            "category":"Autos & Motor Vehicles",
            "subcategory":"Automobile Sales",
            "type":"Retail Goods"
        }
    ],
    "sg:phone":"+1   ",
    "sg:postcode":"60018",
    "sg:province":"IL",
    "sg:tags":[
        "new",
        "used"
    ],
    "wof:name":"OHare Pontiac",
    "wof:placetype":"venue"
},
  "geometry": {"coordinates":[-87.877694,42.025896],"type":"Point"}
}