{
  "type": "Feature",
  "properties": {
    "iso:country":"US",
    "sg:address":"3219 S Riverside Dr",
    "sg:city":"Beloit",
    "sg:classifiers":[
        {
            "category":"Wholesale",
            "subcategory":"Electrical",
            "type":"Manufacturing & Wholesale Goods"
        },
        {
            "category":"Retail",
            "subcategory":"Auto Repair",
            "type":"Services"
        }
    ],
    "sg:phone":"+1 608 365 5201",
    "sg:postcode":"53511",
    "sg:province":"IL",
    "sg:tags":[
        "alternator",
        "automotive",
        "generator",
        "equipment"
    ],
    "wof:name":"Superior Automotive Electrics",
    "wof:placetype":"venue"
},
  "geometry": {"coordinates":[-89.037936,42.559315],"type":"Point"}
}