{
  "type": "Feature",
  "properties": {
    "addr:full":"1510 S. Torrence Ave Calumet City IL 60409",
    "addr:housenumber":"1510",
    "addr:postcode":"60409",
    "addr:street":"S. Torrence Ave",
    "iso:country":"US",
    "sg:address":"1510 S. Torrence Ave",
    "sg:city":"Calumet City",
    "sg:classifiers":[
        {
            "category":"Shopping",
            "subcategory":"Bicycles & Sporting Goods",
            "type":"Retail Goods"
        }
    ],
    "sg:phone":"+1 708 895 0901",
    "sg:postcode":"60409",
    "sg:province":"IL",
    "sg:website":"www.sportsauthority.com",
    "wof:name":"Sports Authority",
    "wof:placetype":"venue"
},
  "geometry": {"coordinates":[-87.558791,41.590339],"type":"Point"}
}