{
  "type": "Feature",
  "properties": {
    "addr:full":"106 N Schmale Rd Carol Stream IL 60188",
    "addr:housenumber":"106",
    "addr:postcode":"60188",
    "addr:street":"N Schmale Rd",
    "iso:country":"US",
    "sg:address":"106 N Schmale Rd",
    "sg:city":"Carol Stream",
    "sg:classifiers":[
        {
            "category":"Autos & Motor Vehicles",
            "subcategory":"Motorcycle Sales",
            "type":"Retail Goods"
        }
    ],
    "sg:phone":"+1 630 690 3333",
    "sg:postcode":"60188",
    "sg:province":"IL",
    "sg:website":"www.suzuki.com",
    "wof:name":"Suzuki of Carolstream",
    "wof:placetype":"venue"
},
  "geometry": {"coordinates":[-88.10195400000001,41.903811],"type":"Point"}
}