{
  "type": "Feature",
  "properties": {
    "addr:full":"9400 S Western Ave Evergreen Park IL 60805",
    "addr:housenumber":"9400",
    "addr:postcode":"60805",
    "addr:street":"S Western Ave",
    "iso:country":"US",
    "sg:address":"9400 S Western Ave",
    "sg:city":"Evergreen Park",
    "sg:classifiers":[
        {
            "category":"Shopping",
            "subcategory":"Discount & Variety Stores",
            "type":"Retail Goods"
        }
    ],
    "sg:phone":"+1   ",
    "sg:postcode":"60805",
    "sg:province":"IL",
    "sg:tags":[
        "merchandise",
        "general"
    ],
    "wof:name":"Wal-Mart",
    "wof:placetype":"venue"
},
  "geometry": {"coordinates":[-87.68208199999999,41.721401],"type":"Point"}
}