{
  "type": "Feature",
  "properties": {
    "iso:country":"US",
    "sg:address":"2850 Devon Avenue",
    "sg:city":"Chicago",
    "sg:classifiers":[
        {
            "category":"Deli",
            "type":"Food & Drink"
        },
        {
            "category":"Bakery",
            "type":"Food & Drink"
        }
    ],
    "sg:phone":"+1 773 338 8770",
    "sg:postcode":"60657",
    "sg:province":"IL",
    "wof:name":"A & T Bakery & Deli",
    "wof:placetype":"venue"
},
  "geometry": {"coordinates":[-87.701302,41.997601],"type":"Point"}
}