{
  "type": "Feature",
  "properties": {
    "addr:full":"122 N Van Buren Ave Freeport IL 61032",
    "addr:housenumber":"122",
    "addr:postcode":"61032",
    "addr:street":"N Van Buren Ave",
    "iso:country":"US",
    "sg:address":"122 N Van Buren Ave",
    "sg:city":"Freeport",
    "sg:classifiers":[
        {
            "category":"Manufacturing",
            "subcategory":"Printing",
            "type":"Manufacturing & Wholesale Goods"
        }
    ],
    "sg:phone":"+1 815 235 3700",
    "sg:postcode":"61032",
    "sg:province":"IL",
    "sg:tags":[
        "lithographic",
        "commercial",
        "typesetting"
    ],
    "wof:name":"Inky Printers",
    "wof:placetype":"venue"
},
  "geometry": {"coordinates":[-89.622128,42.299048],"type":"Point"}
}