{
  "type": "Feature",
  "properties": {
    "iso:country":"US",
    "sg:address":"1545 Clinton Pl",
    "sg:city":"River Forest",
    "sg:classifiers":[
        {
            "category":"Building & Trades",
            "subcategory":"Construction",
            "type":"Services"
        }
    ],
    "sg:phone":"+1 708 488 1722",
    "sg:postcode":"60305",
    "sg:province":"IL",
    "sg:tags":[
        "contractor"
    ],
    "sg:website":"www.astorbuilders.com",
    "wof:name":"Astor Builders",
    "wof:placetype":"venue"
},
  "geometry": {"coordinates":[-87.80878800000001,41.907762],"type":"Point"}
}