{
  "type": "Feature",
  "properties": {
    "addr:full":"300 E Baltimore St Wilmington IL 60481",
    "addr:housenumber":"300",
    "addr:postcode":"60481",
    "addr:street":"E Baltimore St",
    "iso:country":"US",
    "sg:address":"300 E Baltimore St",
    "sg:city":"Wilmington",
    "sg:classifiers":[
        {
            "category":"Health Services",
            "subcategory":"Chiropractor",
            "type":"Services"
        }
    ],
    "sg:phone":"+1 815 476 3700",
    "sg:postcode":"60481",
    "sg:province":"IL",
    "wof:name":"Fitzsimmons Chiropractic",
    "wof:placetype":"venue"
},
  "geometry": {"coordinates":[-88.14354899999999,41.308862],"type":"Point"}
}