{
  "type": "Feature",
  "properties": {
    "addr:full":"6302 N Cicero Avenue Chicago IL 60646",
    "addr:housenumber":"6302",
    "addr:postcode":"60646",
    "addr:street":"N Cicero Avenue",
    "iso:country":"US",
    "sg:address":"6302 N Cicero Avenue",
    "sg:city":"Chicago",
    "sg:classifiers":[
        {
            "category":"Professional",
            "subcategory":"Accounting & Tax Preparation",
            "type":"Services"
        }
    ],
    "sg:phone":"+1 773 282 4181",
    "sg:postcode":"60646",
    "sg:province":"IL",
    "sg:tags":[
        "accountant"
    ],
    "wof:name":"Ross G & Associates",
    "wof:placetype":"venue"
},
  "geometry": {"coordinates":[-87.748125,41.995796],"type":"Point"}
}