{
  "type": "Feature",
  "properties": {
    "iso:country":"US",
    "sg:address":"4638 W 63rd St",
    "sg:city":"Chicago",
    "sg:classifiers":[
        {
            "category":"Personal",
            "subcategory":"Barber",
            "type":"Services"
        }
    ],
    "sg:phone":"+1 773 735 3765",
    "sg:postcode":"60629",
    "sg:province":"IL",
    "wof:name":"Len's Barber Shop",
    "wof:placetype":"venue"
},
  "geometry": {"coordinates":[-87.73893,41.778503],"type":"Point"}
}