{
  "type": "Feature",
  "properties": {
    "iso:country":"US",
    "sg:address":"4834 W Cermak Rd",
    "sg:city":"Cicero",
    "sg:classifiers":[
        {
            "category":"Shopping",
            "subcategory":"Clothing, Apparel, & Fashions",
            "type":"Retail Goods"
        }
    ],
    "sg:phone":"+1 708 222 8014",
    "sg:postcode":"60804",
    "sg:province":"IL",
    "sg:tags":[
        "children's",
        "infant",
        "clothing",
        "wear"
    ],
    "wof:name":"Chiquilladas",
    "wof:placetype":"venue"
},
  "geometry": {"coordinates":[-87.74520099999999,41.851398],"type":"Point"}
}