{
  "type": "Feature",
  "properties": {
    "iso:country":"US",
    "sg:address":"1703 2nd Ave",
    "sg:city":"Rock Island",
    "sg:classifiers":[
        {
            "category":"Real Estate",
            "subcategory":"Real Estate Services",
            "type":"Services"
        }
    ],
    "sg:phone":"+1 309 794 0518",
    "sg:postcode":"61201",
    "sg:province":"IL",
    "sg:tags":[
        "company",
        "abstract",
        "title"
    ],
    "wof:name":"H B Wilkinson Title Co Inc",
    "wof:placetype":"venue"
},
  "geometry": {"coordinates":[-90.575208,41.511133],"type":"Point"}
}