{
  "type": "Feature",
  "properties": {
    "addr:full":"1125 Emerson St Evanston IL 60201",
    "addr:housenumber":"1125",
    "addr:postcode":"60201",
    "addr:street":"Emerson St",
    "iso:country":"US",
    "sg:address":"1125 Emerson St",
    "sg:city":"Evanston",
    "sg:classifiers":[
        {
            "category":"Restaurant",
            "type":"Food & Drink"
        }
    ],
    "sg:menulink":"http://www.allmenus.com/il/evanston/237383-ruby-of-siam/menu/",
    "sg:phone":"+1 847 492 1008",
    "sg:postcode":"60201",
    "sg:province":"IL",
    "sg:tags":[
        "thai",
        "asian"
    ],
    "wof:name":"Ruby Of Siam",
    "wof:placetype":"venue"
},
  "geometry": {"coordinates":[-87.687507,42.052111],"type":"Point"}
}