{
  "type": "Feature",
  "properties": {
    "iso:country":"US",
    "sg:address":"3685 Friendship School Rd",
    "sg:city":"Anna",
    "sg:classifiers":[
        {
            "category":"Real Estate",
            "subcategory":"Real Estate Agent",
            "type":"Services"
        }
    ],
    "sg:phone":"+1 618 833 4784",
    "sg:postcode":"62906",
    "sg:province":"IL",
    "wof:name":"Sequoia Western Corp Illino",
    "wof:placetype":"venue"
},
  "geometry": {"coordinates":[-89.153205,37.433924],"type":"Point"}
}