{
  "type": "Feature",
  "properties": {
    "iso:country":"US",
    "sg:address":"3605 Woodhead Dr",
    "sg:city":"Northbrook",
    "sg:classifiers":[
        {
            "category":"Professional",
            "subcategory":"Management & Consulting",
            "type":"Services"
        }
    ],
    "sg:phone":"+1 847 272 6111",
    "sg:postcode":"60062",
    "sg:province":"IL",
    "sg:tags":[
        "public",
        "relations"
    ],
    "wof:name":"Martin Jay Sales Co Inc",
    "wof:placetype":"venue"
},
  "geometry": {"coordinates":[-87.870744,42.148214],"type":"Point"}
}