{
  "type": "Feature",
  "properties": {
    "iso:country":"US",
    "sg:address":"53 W Jackson Blvd Ste 357",
    "sg:city":"Chicago",
    "sg:classifiers":[
        {
            "category":"Personal",
            "subcategory":"Massage",
            "type":"Services"
        }
    ],
    "sg:phone":"+1 773 822 3504",
    "sg:postcode":"60604",
    "sg:province":"IL",
    "wof:name":"Salvitore Castellano, PFT",
    "wof:placetype":"venue"
},
  "geometry": {"coordinates":[-87.62952799999999,41.878049],"type":"Point"}
}