{
  "type": "Feature",
  "properties": {
    "addr:full":"13248 S Houston Ave Chicago IL 60633",
    "addr:housenumber":"13248",
    "addr:postcode":"60633",
    "addr:street":"S Houston Ave",
    "iso:country":"US",
    "sg:address":"13248 S Houston Ave",
    "sg:city":"Chicago",
    "sg:classifiers":[
        {
            "category":"Personal",
            "subcategory":"Barber",
            "type":"Services"
        }
    ],
    "sg:phone":"+1 773 646 2727",
    "sg:postcode":"60633",
    "sg:province":"IL",
    "wof:name":"Robert L Ray's Hair Salon",
    "wof:placetype":"venue"
},
  "geometry": {"coordinates":[-87.5485,41.654202],"type":"Point"}
}