{
  "type": "Feature",
  "properties": {
    "iso:country":"US",
    "sg:address":"4558 Burningtree Dr",
    "sg:city":"Rockford",
    "sg:classifiers":[
        {
            "category":"Professional",
            "subcategory":"Management & Consulting",
            "type":"Services"
        },
        {
            "category":"Professional",
            "subcategory":"Engineering",
            "type":"Services"
        }
    ],
    "sg:phone":"+1 815 621 2398",
    "sg:postcode":"61114",
    "sg:province":"IL",
    "sg:tags":[
        "environmental",
        "ecological",
        "engineer",
        "consultant"
    ],
    "wof:name":"Focus Environmental Management Group",
    "wof:placetype":"venue"
},
  "geometry": {"coordinates":[-89.02842,42.304266],"type":"Point"}
}