{
  "type": "Feature",
  "properties": {
    "addr:full":"11041 Front St Mokena IL 60448",
    "addr:housenumber":"11041",
    "addr:postcode":"60448",
    "addr:street":"Front St",
    "iso:country":"US",
    "sg:address":"11041 Front St",
    "sg:city":"Mokena",
    "sg:classifiers":[
        {
            "category":"Insurance",
            "subcategory":"Insurance Agent",
            "type":"Services"
        },
        {
            "category":"Insurance",
            "subcategory":"Hazard Insurance",
            "type":"Services"
        },
        {
            "category":"Insurance",
            "subcategory":"Title Insurance",
            "type":"Services"
        },
        {
            "category":"Insurance",
            "subcategory":"Life Insurance",
            "type":"Services"
        }
    ],
    "sg:phone":"+1 708 478 0008",
    "sg:postcode":"60448",
    "sg:province":"IL",
    "sg:tags":[
        "business",
        "auto",
        "commercial",
        "homeowner",
        "motorcycle",
        "renter"
    ],
    "wof:name":"Allstate Insurance Company - Dale Gordy",
    "wof:placetype":"venue"
},
  "geometry": {"coordinates":[-87.88519599999999,41.532074],"type":"Point"}
}