{
  "type": "Feature",
  "properties": {
    "iso:country":"US",
    "sg:address":"15718 Kenwood Ave",
    "sg:city":"South Holland",
    "sg:classifiers":[
        {
            "category":"Real Estate",
            "subcategory":"Architect",
            "type":"Services"
        }
    ],
    "sg:phone":"+1 708 333 3654",
    "sg:postcode":"60473",
    "sg:province":"IL",
    "wof:name":"Schraut Russell W Jr Arch",
    "wof:placetype":"venue"
},
  "geometry": {"coordinates":[-87.5849,41.609402],"type":"Point"}
}