{
  "type": "Feature",
  "properties": {
    "iso:country":"US",
    "sg:address":"1 Burcham Dr",
    "sg:city":"Fairview Heights",
    "sg:classifiers":[
        {
            "category":"Personal",
            "subcategory":"Massage",
            "type":"Services"
        },
        {
            "category":"Insurance",
            "subcategory":"Health Insurance",
            "type":"Services"
        }
    ],
    "sg:phone":"+1 618 398 9136",
    "sg:postcode":"62208",
    "sg:province":"IL",
    "sg:tags":[
        "market"
    ],
    "wof:name":"Advance Therapy",
    "wof:placetype":"venue"
},
  "geometry": {"coordinates":[-90.02691299999999,38.621807],"type":"Point"}
}