{
  "type": "Feature",
  "properties": {
    "addr:full":"2854 W Armitage Ave Chicago IL 60647",
    "addr:housenumber":"2854",
    "addr:postcode":"60647",
    "addr:street":"W Armitage Ave",
    "iso:country":"US",
    "sg:address":"2854 W Armitage Ave",
    "sg:city":"Chicago",
    "sg:classifiers":[
        {
            "category":"Retail",
            "subcategory":"Portrait Studio",
            "type":"Services"
        }
    ],
    "sg:phone":"+1 773 384 4330",
    "sg:postcode":"60647",
    "sg:province":"IL",
    "sg:tags":[
        "photographer"
    ],
    "wof:name":"Augustine Marron Photographer",
    "wof:placetype":"venue"
},
  "geometry": {"coordinates":[-87.699134,41.917546],"type":"Point"}
}