{
  "type": "Feature",
  "properties": {
    "iso:country":"US",
    "sg:address":"304 N Benton St",
    "sg:city":"Tampico",
    "sg:classifiers":[
        {
            "category":"Organizations",
            "subcategory":"Religious Organization",
            "type":"Services"
        }
    ],
    "sg:phone":"+1 815 438 5025",
    "sg:postcode":"61283",
    "sg:province":"IL",
    "sg:tags":[
        "church"
    ],
    "wof:name":"Tampico Baptist Church",
    "wof:placetype":"venue"
},
  "geometry": {"coordinates":[-89.784655,41.633636],"type":"Point"}
}