{
  "type": "Feature",
  "properties": {
    "addr:full":"8 Devon Ave Park Ridge IL 60068",
    "addr:housenumber":"8",
    "addr:postcode":"60068",
    "addr:street":"Devon Ave",
    "iso:country":"US",
    "sg:address":"8 Devon Ave",
    "sg:city":"Park Ridge",
    "sg:classifiers":[
        {
            "category":"Professional",
            "subcategory":"Lawyer & Legal Services",
            "type":"Services"
        }
    ],
    "sg:phone":"+1 630 325 2960",
    "sg:postcode":"60068",
    "sg:province":"IL",
    "wof:name":"Palmisano Nancy A Atty",
    "wof:placetype":"venue"
},
  "geometry": {"coordinates":[-87.821404,41.996799],"type":"Point"}
}