{
  "type": "Feature",
  "properties": {
    "addr:full":"210 W Wesley St Wheaton IL 60187",
    "addr:housenumber":"210",
    "addr:postcode":"60187",
    "addr:street":"W Wesley St",
    "iso:country":"US",
    "sg:address":"210 W Wesley St",
    "sg:city":"Wheaton",
    "sg:classifiers":[
        {
            "category":"Shopping",
            "subcategory":"Baby Store",
            "type":"Retail Goods"
        }
    ],
    "sg:phone":"+1 630 752 1584",
    "sg:postcode":"60187",
    "sg:province":"IL",
    "sg:tags":[
        "gear",
        "furniture"
    ],
    "sg:website":"www.thestorkscradle.com",
    "wof:name":"The Stork's Cradle",
    "wof:placetype":"venue"
},
  "geometry": {"coordinates":[-88.109301,41.866076],"type":"Point"}
}