{
  "type": "Feature",
  "properties": {
    "iso:country":"US",
    "sg:address":"3435 Auburn St",
    "sg:city":"Rockford",
    "sg:classifiers":[
        {
            "category":"Wholesale",
            "subcategory":"Farm Supplies",
            "type":"Manufacturing & Wholesale Goods"
        }
    ],
    "sg:phone":"+1 815 963 7678",
    "sg:postcode":"61101",
    "sg:province":"IL",
    "sg:tags":[
        "feed"
    ],
    "wof:name":"Wayne's Feed Store",
    "wof:placetype":"venue"
},
  "geometry": {"coordinates":[-89.111392,42.288287],"type":"Point"}
}