{
  "type": "Feature",
  "properties": {
    "iso:country":"US",
    "sg:address":"15056 Parnell Cir",
    "sg:city":"Homer Glen",
    "sg:classifiers":[
        {
            "category":"Shopping",
            "type":"Retail Goods"
        }
    ],
    "sg:phone":"+1 815 838 4900",
    "sg:postcode":"60491",
    "sg:province":"IL",
    "sg:tags":[
        "craft",
        "gallery",
        "dealer"
    ],
    "wof:name":"Christmas Crossroads",
    "wof:placetype":"venue"
},
  "geometry": {"coordinates":[-87.984414,41.566712],"type":"Point"}
}