{
  "type": "Feature",
  "properties": {
    "addr:full":"115 Robsart Rd Kenilworth IL 60043",
    "addr:housenumber":"115",
    "addr:postcode":"60043",
    "addr:street":"Robsart Rd",
    "iso:country":"US",
    "sg:address":"115 Robsart Rd",
    "sg:city":"Kenilworth",
    "sg:classifiers":[
        {
            "category":"Shopping",
            "subcategory":"Gifts & Souvenirs",
            "type":"Retail Goods"
        }
    ],
    "sg:phone":"+1   ",
    "sg:postcode":"60043",
    "sg:province":"IL",
    "wof:name":"Kay Jolivette Gifts",
    "wof:placetype":"venue"
},
  "geometry": {"coordinates":[-87.70675,42.087051],"type":"Point"}
}