{
  "type": "Feature",
  "properties": {
    "iso:country":"US",
    "sg:address":"108 E 2nd St",
    "sg:city":"Byron",
    "sg:classifiers":[
        {
            "category":"Retail",
            "subcategory":"Auto Repair",
            "type":"Services"
        }
    ],
    "sg:phone":"+1 815 234 7169",
    "sg:postcode":"61010",
    "sg:province":"IL",
    "sg:tags":[
        "repairing",
        "automobile"
    ],
    "wof:name":"Hanlin Automotive",
    "wof:placetype":"venue"
},
  "geometry": {"coordinates":[-89.255313,42.126572],"type":"Point"}
}