{
  "type": "Feature",
  "properties": {
    "addr:full":"5409 Tam O Shanter Dr Rockford IL 61107",
    "addr:housenumber":"5409",
    "addr:postcode":"61107",
    "addr:street":"Tam O Shanter Dr",
    "iso:country":"US",
    "sg:address":"5409 Tam O Shanter Dr",
    "sg:city":"Rockford",
    "sg:classifiers":[
        {
            "category":"Wholesale",
            "subcategory":"Machinery & Supplies",
            "type":"Manufacturing & Wholesale Goods"
        }
    ],
    "sg:phone":"+1 815 399 5222",
    "sg:postcode":"61107",
    "sg:province":"IL",
    "sg:tags":[
        "machine",
        "tool"
    ],
    "wof:name":"Trumpf Inc",
    "wof:placetype":"venue"
},
  "geometry": {"coordinates":[-89.00898599999999,42.277964],"type":"Point"}
}