{
  "type": "Feature",
  "properties": {
    "iso:country":"US",
    "sg:address":"404 Cowles Ave",
    "sg:city":"Joliet",
    "sg:classifiers":[
        {
            "category":"Social Services",
            "subcategory":"Child Care",
            "type":"Services"
        }
    ],
    "sg:phone":"+1 815 722 2867",
    "sg:postcode":"60435",
    "sg:province":"IL",
    "sg:tags":[
        "day"
    ],
    "wof:name":"Carmens Day Care",
    "wof:placetype":"venue"
},
  "geometry": {"coordinates":[-88.10589299999999,41.532141],"type":"Point"}
}