{
  "type": "Feature",
  "properties": {
    "addr:full":"1509 Hadley Dr Batavia IL 60510",
    "addr:housenumber":"1509",
    "addr:postcode":"60510",
    "addr:street":"Hadley Dr",
    "iso:country":"US",
    "sg:address":"1509 Hadley Dr",
    "sg:city":"Batavia",
    "sg:classifiers":[
        {
            "category":"Professional",
            "subcategory":"Computer Services",
            "type":"Services"
        }
    ],
    "sg:phone":"+1 630 761 9794",
    "sg:postcode":"60510",
    "sg:province":"IL",
    "sg:tags":[
        "datum"
    ],
    "wof:name":"Northern Sky Designs LLC",
    "wof:placetype":"venue"
},
  "geometry": {"coordinates":[-88.33248500000001,41.852781],"type":"Point"}
}