{
  "type": "Feature",
  "properties": {
    "addr:full":"3729 N Trainer Rd Rockford IL 61114",
    "addr:housenumber":"3729",
    "addr:postcode":"61114",
    "addr:street":"N Trainer Rd",
    "iso:country":"US",
    "sg:address":"3729 N Trainer Rd",
    "sg:city":"Rockford",
    "sg:classifiers":[
        {
            "category":"Insurance",
            "subcategory":"Insurance Agent",
            "type":"Services"
        }
    ],
    "sg:phone":"+1 815 877 8332",
    "sg:postcode":"61114",
    "sg:province":"IL",
    "wof:name":"Liberty Mutual",
    "wof:placetype":"venue"
},
  "geometry": {"coordinates":[-88.98556499999999,42.315151],"type":"Point"}
}