{
  "type": "Feature",
  "properties": {
    "iso:country":"US",
    "sg:address":"4115 W 90th Pl",
    "sg:city":"Hometown",
    "sg:classifiers":[
        {
            "category":"Building & Trades",
            "subcategory":"Construction",
            "type":"Services"
        }
    ],
    "sg:phone":"+1 708 499 3884",
    "sg:postcode":"60456",
    "sg:province":"IL",
    "sg:tags":[
        "contractor"
    ],
    "wof:name":"K O Z National Sign Contractor",
    "wof:placetype":"venue"
},
  "geometry": {"coordinates":[-87.724661,41.727966],"type":"Point"}
}