{
  "type": "Feature",
  "properties": {
    "iso:country":"US",
    "sg:address":"209 E 103rd St",
    "sg:city":"Chicago",
    "sg:classifiers":[
        {
            "category":"Food & Beverages",
            "subcategory":"Groceries & Convenience Stores",
            "type":"Retail Goods"
        }
    ],
    "sg:phone":"+1 773 928 2600",
    "sg:postcode":"60628",
    "sg:province":"IL",
    "wof:name":"Buy N Save",
    "wof:placetype":"venue"
},
  "geometry": {"coordinates":[-87.61799600000001,41.707401],"type":"Point"}
}