{
  "type": "Feature",
  "properties": {
    "addr:full":"8724 S Cicero Ave Oak Lawn IL 60453",
    "addr:housenumber":"8724",
    "addr:postcode":"60453",
    "addr:street":"S Cicero Ave",
    "iso:country":"US",
    "sg:address":"8724 S Cicero Ave",
    "sg:city":"Oak Lawn",
    "sg:classifiers":[
        {
            "category":"Shopping",
            "subcategory":"Clothing, Apparel, & Fashions",
            "type":"Retail Goods"
        }
    ],
    "sg:phone":"+1 708 636 4252",
    "sg:postcode":"60453",
    "sg:province":"IL",
    "sg:tags":[
        "clothing",
        "women's"
    ],
    "wof:name":"Dress Barn the",
    "wof:placetype":"venue"
},
  "geometry": {"coordinates":[-87.741203,41.7332],"type":"Point"}
}