{
  "type": "Feature",
  "properties": {
    "iso:country":"US",
    "sg:address":"1201 9th St",
    "sg:city":"Lawrenceville",
    "sg:classifiers":[
        {
            "category":"Home & Garden",
            "subcategory":"Furniture",
            "type":"Retail Goods"
        }
    ],
    "sg:phone":"+1   ",
    "sg:postcode":"62439",
    "sg:province":"IL",
    "wof:name":"S Cannon Furniture",
    "wof:placetype":"venue"
},
  "geometry": {"coordinates":[-87.680025,38.725398],"type":"Point"}
}