{
  "type": "Feature",
  "properties": {
    "iso:country":"US",
    "sg:address":"810 N Wright St",
    "sg:city":"Urbana",
    "sg:classifiers":[
        {
            "category":"Education",
            "subcategory":"Library",
            "type":"Public Place"
        }
    ],
    "sg:phone":"+1 217 333 2216",
    "sg:postcode":"61801",
    "sg:province":"IL",
    "wof:name":"Communications Library",
    "wof:placetype":"venue"
},
  "geometry": {"coordinates":[-88.228728,40.119687],"type":"Point"}
}