{
  "type": "Feature",
  "properties": {
    "iso:country":"US",
    "sg:address":"360 Walnut Cir",
    "sg:city":"Bolingbrook",
    "sg:classifiers":[
        {
            "category":"Freight",
            "type":"Transportation"
        }
    ],
    "sg:phone":"+1 630 364 8515",
    "sg:postcode":"60440",
    "sg:province":"IL",
    "wof:name":"Amoak International",
    "wof:placetype":"venue"
},
  "geometry": {"coordinates":[-88.074244,41.706508],"type":"Point"}
}