{
  "type": "Feature",
  "properties": {
    "iso:country":"US",
    "sg:address":"118 N Randall Rd",
    "sg:city":"Aurora",
    "sg:classifiers":[
        {
            "category":"Autos & Motor Vehicles",
            "subcategory":"Fuel & Gas Station",
            "type":"Retail Goods"
        }
    ],
    "sg:phone":"+1   ",
    "sg:postcode":"60506",
    "sg:province":"IL",
    "sg:tags":[
        "grocery",
        "station",
        "gasoline"
    ],
    "wof:name":"Bejoys Marathon",
    "wof:placetype":"venue"
},
  "geometry": {"coordinates":[-88.349762,41.764059],"type":"Point"}
}