{
  "type": "Feature",
  "properties": {
    "addr:full":"550 Lake Cook Rd Deerfield IL 60015",
    "addr:housenumber":"550",
    "addr:postcode":"60015",
    "addr:street":"Lake Cook Rd",
    "iso:country":"US",
    "sg:address":"550 Lake Cook Rd",
    "sg:city":"Deerfield",
    "sg:classifiers":[
        {
            "category":"Sports & Exercise",
            "subcategory":"Gym",
            "type":"Entertainment"
        }
    ],
    "sg:phone":"+1 847 444 8725",
    "sg:postcode":"60015",
    "sg:province":"IL",
    "sg:tags":[
        "club",
        "health",
        "studio",
        "gymnasium"
    ],
    "wof:name":"Vermeil's Sports & Fitness Inc",
    "wof:placetype":"venue"
},
  "geometry": {"coordinates":[-87.84083200000001,42.152846],"type":"Point"}
}