{
  "type": "Feature",
  "properties": {
    "addr:full":"14751 Pulaski Rd Midlothian IL 60445",
    "addr:housenumber":"14751",
    "addr:postcode":"60445",
    "addr:street":"Pulaski Rd",
    "iso:country":"US",
    "sg:address":"14751 Pulaski Rd",
    "sg:city":"Midlothian",
    "sg:classifiers":[
        {
            "category":"Shopping",
            "subcategory":"Computers & Home Electronics",
            "type":"Retail Goods"
        }
    ],
    "sg:phone":"+1   ",
    "sg:postcode":"60445",
    "sg:province":"IL",
    "sg:tags":[
        "household",
        "appliance"
    ],
    "wof:name":"Radays Inc",
    "wof:placetype":"venue"
},
  "geometry": {"coordinates":[-87.717572,41.624021],"type":"Point"}
}