{
  "type": "Feature",
  "properties": {
    "iso:country":"US",
    "sg:address":"5750 N California Ave",
    "sg:city":"Chicago",
    "sg:classifiers":[
        {
            "category":"Food & Beverages",
            "subcategory":"Groceries & Convenience Stores",
            "type":"Retail Goods"
        }
    ],
    "sg:phone":"+1   ",
    "sg:postcode":"60659",
    "sg:province":"IL",
    "wof:name":"Phillipine Grocery Inc",
    "wof:placetype":"venue"
},
  "geometry": {"coordinates":[-87.699339,41.98627],"type":"Point"}
}