{
  "type": "Feature",
  "properties": {
    "iso:country":"US",
    "sg:address":"600 S Halsted St",
    "sg:city":"Chicago Heights",
    "sg:classifiers":[
        {
            "category":"Deli",
            "type":"Food & Drink"
        }
    ],
    "sg:menulink":"http://www.allmenus.com/il/bloom/233477-browns-chicken--pasta/menu/",
    "sg:phone":"+1 708 754 7400",
    "sg:postcode":"60411",
    "sg:province":"IL",
    "sg:tags":[
        "american"
    ],
    "wof:name":"Brown's Chicken & Pasta",
    "wof:placetype":"venue"
},
  "geometry": {"coordinates":[-87.635744,41.520601],"type":"Point"}
}