{
  "type": "Feature",
  "properties": {
    "iso:country":"US",
    "sg:address":"446 E 75th St",
    "sg:city":"Chicago",
    "sg:classifiers":[
        {
            "category":"Shopping",
            "subcategory":"Clothing, Apparel, & Fashions",
            "type":"Retail Goods"
        },
        {
            "category":"Retail",
            "subcategory":"Laundry & Dry Cleaning",
            "type":"Services"
        }
    ],
    "sg:phone":"+1 773 488 2962",
    "sg:postcode":"60619",
    "sg:province":"IL",
    "sg:tags":[
        "cleaner",
        "tailor",
        "alterations-clothing"
    ],
    "wof:name":"2 Sistahs Cleaners",
    "wof:placetype":"venue"
},
  "geometry": {"coordinates":[-87.613606,41.758435],"type":"Point"}
}