{
  "type": "Feature",
  "properties": {
    "iso:country":"US",
    "sg:address":"3223 Saint Charles Rd",
    "sg:city":"Bellwood",
    "sg:classifiers":[
        {
            "category":"Restaurant",
            "type":"Food & Drink"
        }
    ],
    "sg:phone":"+1 708 547 8177",
    "sg:postcode":"60104",
    "sg:province":"IL",
    "sg:tags":[
        "asian",
        "chinese",
        "pan"
    ],
    "wof:name":"B Fried Rice",
    "wof:placetype":"venue"
},
  "geometry": {"coordinates":[-87.87264,41.886884],"type":"Point"}
}