{
  "type": "Feature",
  "properties": {
    "iso:country":"US",
    "sg:address":"601 Chaffer Ave",
    "sg:city":"Roxana",
    "sg:classifiers":[
        {
            "category":"Education",
            "subcategory":"School",
            "type":"Public Place"
        }
    ],
    "sg:phone":"+1 618 254 7594",
    "sg:postcode":"62084",
    "sg:province":"IL",
    "wof:name":"Central Elementary School",
    "wof:placetype":"venue"
},
  "geometry": {"coordinates":[-90.076686,38.85094],"type":"Point"}
}