{
  "type": "Feature",
  "properties": {
    "iso:country":"US",
    "sg:address":"5 Enterprise Dr",
    "sg:city":"Hanover",
    "sg:classifiers":[
        {
            "category":"Autos & Motor Vehicles",
            "subcategory":"Auto Supplies",
            "type":"Retail Goods"
        },
        {
            "category":"Retail",
            "subcategory":"Auto Repair",
            "type":"Services"
        }
    ],
    "sg:phone":"+1 815 591 2800",
    "sg:postcode":"61041",
    "sg:province":"IL",
    "sg:tags":[
        "body",
        "automobile",
        "truck",
        "painting",
        "repairing"
    ],
    "wof:name":"K & P Auto Body",
    "wof:placetype":"venue"
},
  "geometry": {"coordinates":[-90.27157200000001,42.247229],"type":"Point"}
}