{
  "type": "Feature",
  "properties": {
    "iso:country":"US",
    "sg:address":"1431 Country Aire Dr",
    "sg:city":"Carterville",
    "sg:classifiers":[
        {
            "category":"Health Services",
            "subcategory":"Hospital",
            "type":"Services"
        }
    ],
    "sg:phone":"+1 618 985 2170",
    "sg:postcode":"62918",
    "sg:province":"IL",
    "wof:name":"Alsac St Jude Research Hosp",
    "wof:placetype":"venue"
},
  "geometry": {"coordinates":[-89.053966,37.747109],"type":"Point"}
}