{
  "type": "Feature",
  "properties": {
    "iso:country":"US",
    "sg:address":"2850 W Devon Ave",
    "sg:city":"Chicago",
    "sg:classifiers":[
        {
            "category":"Food & Beverages",
            "subcategory":"Meat & Fish",
            "type":"Retail Goods"
        }
    ],
    "sg:phone":"+1 773 338 0690",
    "sg:postcode":"60659",
    "sg:province":"IL",
    "sg:tags":[
        "grocery"
    ],
    "wof:name":"Nineveh Grocery and Meat",
    "wof:placetype":"venue"
},
  "geometry": {"coordinates":[-87.701401,41.997501],"type":"Point"}
}