{
  "type": "Feature",
  "properties": {
    "iso:country":"US",
    "sg:address":"222 Otto Dr",
    "sg:city":"New Lenox",
    "sg:classifiers":[
        {
            "category":"Manufacturing",
            "subcategory":"Signs",
            "type":"Manufacturing & Wholesale Goods"
        }
    ],
    "sg:phone":"+1 815 462 4564",
    "sg:postcode":"60451",
    "sg:province":"IL",
    "wof:name":"Signtech Visual Communications",
    "wof:placetype":"venue"
},
  "geometry": {"coordinates":[-87.963818,41.494561],"type":"Point"}
}