{
  "type": "Feature",
  "properties": {
    "addr:full":"6374 N Lincoln Ave Ste 301 Chicago IL 60659",
    "addr:housenumber":"6374",
    "addr:postcode":"60659",
    "addr:street":"N Lincoln Ave Ste 301",
    "iso:country":"US",
    "sg:address":"6374 N Lincoln Ave Ste 301",
    "sg:city":"Chicago",
    "sg:classifiers":[
        {
            "category":"Health Services",
            "subcategory":"Doctor",
            "type":"Services"
        },
        {
            "category":"Health Services",
            "subcategory":"Health Practitioner",
            "type":"Services"
        }
    ],
    "sg:phone":"+1 773 478 7100",
    "sg:postcode":"60659",
    "sg:province":"IL",
    "sg:tags":[
        "medicine",
        "sport",
        "therapy",
        "physical"
    ],
    "wof:name":"Pro Sports & Spine Rehabilitation Sc",
    "wof:placetype":"venue"
},
  "geometry": {"coordinates":[-87.71829099999999,41.996811],"type":"Point"}
}