{
  "type": "Feature",
  "properties": {
    "addr:full":"809 W Higgins Rd Schaumburg IL 60195",
    "addr:housenumber":"809",
    "addr:postcode":"60195",
    "addr:street":"W Higgins Rd",
    "iso:country":"US",
    "sg:address":"809 W Higgins Rd",
    "sg:city":"Schaumburg",
    "sg:classifiers":[
        {
            "category":"Retail",
            "subcategory":"Auto Rental",
            "type":"Services"
        }
    ],
    "sg:phone":"+1 847 310 3400",
    "sg:postcode":"60195",
    "sg:province":"IL",
    "sg:tags":[
        "renting",
        "automobile"
    ],
    "wof:name":"Enterprise Rent-A-Car",
    "wof:placetype":"venue"
},
  "geometry": {"coordinates":[-88.098641,42.049554],"type":"Point"}
}