{
  "type": "Feature",
  "properties": {
    "iso:country":"US",
    "sg:address":"9665 W 55th St",
    "sg:city":"La Grange",
    "sg:classifiers":[
        {
            "category":"Retail",
            "subcategory":"Auto Repair",
            "type":"Services"
        }
    ],
    "sg:phone":"+1 708 352 7420",
    "sg:postcode":"60525",
    "sg:province":"IL",
    "wof:name":"Sonomatic",
    "wof:placetype":"venue"
},
  "geometry": {"coordinates":[-87.861362,41.790577],"type":"Point"}
}