{
  "type": "Feature",
  "properties": {
    "iso:country":"US",
    "sg:address":"101 S Division St",
    "sg:city":"Stronghurst",
    "sg:classifiers":[
        {
            "category":"Health Services",
            "subcategory":"Doctor",
            "type":"Services"
        }
    ],
    "sg:phone":"+1 309 924 1381",
    "sg:postcode":"61480",
    "sg:province":"IL",
    "sg:tags":[
        "physician",
        "surgeon"
    ],
    "wof:name":"Stronghurst Medical Clinic",
    "wof:placetype":"venue"
},
  "geometry": {"coordinates":[-90.909676,40.744809],"type":"Point"}
}