{
  "type": "Feature",
  "properties": {
    "iso:country":"US",
    "sg:address":"2395 Cobden School Rd",
    "sg:city":"Cobden",
    "sg:classifiers":[
        {
            "category":"Organizations",
            "subcategory":"Religious Organization",
            "type":"Services"
        }
    ],
    "sg:phone":"+1 618 893 2902",
    "sg:postcode":"62920",
    "sg:province":"IL",
    "wof:name":"Eagles Nest Watch Ministries",
    "wof:placetype":"venue"
},
  "geometry": {"coordinates":[-89.24393499999999,37.564445],"type":"Point"}
}