{
  "type": "Feature",
  "properties": {
    "iso:country":"US",
    "sg:address":"1600 N State Rte 50",
    "sg:city":"Bourbonnais",
    "sg:classifiers":[
        {
            "category":"Shopping",
            "subcategory":"Jewelry",
            "type":"Retail Goods"
        }
    ],
    "sg:phone":"+1 815 937 8400",
    "sg:postcode":"60914",
    "sg:province":"IL",
    "sg:tags":[
        "jeweler"
    ],
    "wof:name":"Rogers & Hollands Jewelers 46",
    "wof:placetype":"venue"
},
  "geometry": {"coordinates":[-87.85099200000001,41.165184],"type":"Point"}
}