{
  "type": "Feature",
  "properties": {
    "iso:country":"US",
    "sg:address":"11457 Melrose Ave",
    "sg:city":"Franklin Park",
    "sg:classifiers":[
        {
            "category":"Wholesale",
            "subcategory":"Dairy",
            "type":"Manufacturing & Wholesale Goods"
        }
    ],
    "sg:phone":"+1 847 288 9183",
    "sg:postcode":"60131",
    "sg:province":"IL",
    "sg:tags":[
        "product"
    ],
    "wof:name":"Hot Mamas",
    "wof:placetype":"venue"
},
  "geometry": {"coordinates":[-87.907964,41.936689],"type":"Point"}
}