{
  "type": "Feature",
  "properties": {
    "iso:country":"US",
    "sg:address":"1513 State St",
    "sg:city":"Alton",
    "sg:classifiers":[
        {
            "category":"Education",
            "subcategory":"School",
            "type":"Public Place"
        }
    ],
    "sg:phone":"+1 618 463 2134",
    "sg:postcode":"62002",
    "sg:province":"IL",
    "sg:website":"www.alton.madison.k12.il.us",
    "wof:name":"West Elementary School",
    "wof:placetype":"venue"
},
  "geometry": {"coordinates":[-90.19461099999999,38.90578],"type":"Point"}
}