{
  "type": "Feature",
  "properties": {
    "addr:full":"11221 S Cherry Ct Palos Hills IL 60465",
    "addr:housenumber":"11221",
    "addr:postcode":"60465",
    "addr:street":"S Cherry Ct",
    "iso:country":"US",
    "sg:address":"11221 S Cherry Ct",
    "sg:city":"Palos Hills",
    "sg:classifiers":[
        {
            "category":"Health Services",
            "subcategory":"Clinic",
            "type":"Services"
        }
    ],
    "sg:phone":"+1 708 974 3282",
    "sg:postcode":"60465",
    "sg:province":"IL",
    "sg:tags":[
        "consulting",
        "care"
    ],
    "wof:name":"Financial Health Care Assoc",
    "wof:placetype":"venue"
},
  "geometry": {"coordinates":[-87.821532,41.686082],"type":"Point"}
}