{
  "type": "Feature",
  "properties": {
    "addr:full":"2022 W Cermak Road Chicago IL 60608",
    "addr:housenumber":"2022",
    "addr:postcode":"60608",
    "addr:street":"W Cermak Road",
    "iso:country":"US",
    "sg:address":"2022 W Cermak Road",
    "sg:city":"Chicago",
    "sg:classifiers":[
        {
            "category":"Park",
            "type":"Public Place"
        }
    ],
    "sg:phone":"+1 312 747 6016",
    "sg:postcode":"60608",
    "sg:province":"IL",
    "sg:website":"www.chicagoparkdistrict.com",
    "wof:name":"Chicago Park District",
    "wof:placetype":"venue"
},
  "geometry": {"coordinates":[-87.676665,41.852269],"type":"Point"}
}