{
  "type": "Feature",
  "properties": {
    "iso:country":"US",
    "sg:address":"221 W Etna Rd",
    "sg:city":"Ottawa",
    "sg:classifiers":[
        {
            "category":"Personal",
            "subcategory":"Barber",
            "type":"Services"
        }
    ],
    "sg:phone":"+1 815 431 1330",
    "sg:postcode":"61350",
    "sg:province":"IL",
    "sg:tags":[
        "shop"
    ],
    "wof:name":"Jon Marc Studio",
    "wof:placetype":"venue"
},
  "geometry": {"coordinates":[-88.837986,41.375036],"type":"Point"}
}