{
  "type": "Feature",
  "properties": {
    "addr:full":"625 Wham Dr Carbondale IL 62901",
    "addr:housenumber":"625",
    "addr:postcode":"62901",
    "addr:street":"Wham Dr",
    "iso:country":"US",
    "sg:address":"625 Wham Dr",
    "sg:city":"Carbondale",
    "sg:classifiers":[
        {
            "category":"Education",
            "subcategory":"University",
            "type":"Public Place"
        }
    ],
    "sg:phone":"+1 618 536 2441",
    "sg:postcode":"62901",
    "sg:province":"IL",
    "sg:tags":[
        "college"
    ],
    "sg:website":"www.siuc.edu",
    "wof:name":"Southern Illinois University Carbondale",
    "wof:placetype":"venue"
},
  "geometry": {"coordinates":[-89.223536,37.717537],"type":"Point"}
}