{
  "type": "Feature",
  "properties": {
    "addr:full":"7438 W 58th Pl Summit Argo IL 60501",
    "addr:housenumber":"7438",
    "addr:postcode":"60501",
    "addr:street":"W 58Th Pl",
    "iso:country":"US",
    "sg:address":"7438 W 58th Pl",
    "sg:city":"Summit Argo",
    "sg:classifiers":[
        {
            "category":"Shopping",
            "subcategory":"Gifts & Souvenirs",
            "type":"Retail Goods"
        }
    ],
    "sg:phone":"+1   ",
    "sg:postcode":"60501",
    "sg:province":"IL",
    "wof:name":"Chicago Phone Cards",
    "wof:placetype":"venue"
},
  "geometry": {"coordinates":[-87.807675,41.785441],"type":"Point"}
}