{
  "type": "Feature",
  "properties": {
    "addr:full":"5029 W Henderson St Chicago IL 60641",
    "addr:housenumber":"5029",
    "addr:postcode":"60641",
    "addr:street":"W Henderson St",
    "iso:country":"US",
    "sg:address":"5029 W Henderson St",
    "sg:city":"Chicago",
    "sg:classifiers":[
        {
            "category":"Building & Trades",
            "subcategory":"Construction",
            "type":"Services"
        }
    ],
    "sg:phone":"+1 773 725 7663",
    "sg:postcode":"60641",
    "sg:province":"IL",
    "sg:tags":[
        "roofing",
        "contractor"
    ],
    "wof:name":"All Ways Roofing",
    "wof:placetype":"venue"
},
  "geometry": {"coordinates":[-87.75367799999999,41.941403],"type":"Point"}
}