{
  "type": "Feature",
  "properties": {
    "iso:country":"US",
    "sg:address":"23957 N 2100th St",
    "sg:city":"Chrisman",
    "sg:classifiers":[
        {
            "category":"Farming",
            "subcategory":"Farm",
            "type":"Manufacturing & Wholesale Goods"
        }
    ],
    "sg:phone":"+1 217 269 3245",
    "sg:postcode":"61924",
    "sg:province":"IL",
    "sg:tags":[
        "farmer"
    ],
    "wof:name":"John W Phipps",
    "wof:placetype":"venue"
},
  "geometry": {"coordinates":[-87.57827399999999,39.819378],"type":"Point"}
}