{
  "type": "Feature",
  "properties": {
    "iso:country":"US",
    "sg:address":"1100 N Lake St",
    "sg:city":"Aurora",
    "sg:classifiers":[
        {
            "category":"Retail",
            "subcategory":"Auto Repair",
            "type":"Services"
        }
    ],
    "sg:phone":"+1 630 896 0730",
    "sg:postcode":"60506",
    "sg:province":"IL",
    "sg:tags":[
        "repairing",
        "automobile"
    ],
    "wof:name":"Merlin's Muffler & Brake",
    "wof:placetype":"venue"
},
  "geometry": {"coordinates":[-88.316766,41.780664],"type":"Point"}
}