{
  "type": "Feature",
  "properties": {
    "iso:country":"US",
    "sg:address":"415 W Kenilworth Ave",
    "sg:city":"Palatine",
    "sg:classifiers":[
        {
            "category":"Building & Trades",
            "subcategory":"Cleaning & Sanitation",
            "type":"Services"
        }
    ],
    "sg:phone":"+1 847 963 0341",
    "sg:postcode":"60067",
    "sg:province":"IL",
    "sg:tags":[
        "maintenance"
    ],
    "wof:name":"Sparkle Cleaning Service",
    "wof:placetype":"venue"
},
  "geometry": {"coordinates":[-88.0545,42.106675],"type":"Point"}
}