{
  "type": "Feature",
  "properties": {
    "iso:country":"US",
    "sg:address":"397 Fulton St",
    "sg:city":"Elgin",
    "sg:classifiers":[
        {
            "category":"Organizations",
            "subcategory":"Religious Organization",
            "type":"Services"
        }
    ],
    "sg:phone":"+1 847 888 2718",
    "sg:postcode":"60120",
    "sg:province":"IL",
    "sg:tags":[
        "church"
    ],
    "wof:name":"St Mary's Religious Education",
    "wof:placetype":"venue"
},
  "geometry": {"coordinates":[-88.276646,42.035321],"type":"Point"}
}