{
  "type": "Feature",
  "properties": {
    "addr:full":"901 Arlington Heights Rd Arlington Heights IL 60005",
    "addr:housenumber":"901",
    "addr:postcode":"60005",
    "addr:street":"Arlington Heights Rd",
    "iso:country":"US",
    "sg:address":"901 Arlington Heights Rd",
    "sg:city":"Arlington Heights",
    "sg:classifiers":[
        {
            "category":"Health Services",
            "subcategory":"Nursing And Care Facility",
            "type":"Services"
        }
    ],
    "sg:phone":"+1 847 255 0585",
    "sg:postcode":"60005",
    "sg:province":"IL",
    "sg:tags":[
        "home",
        "skilled"
    ],
    "wof:name":"Kindred Healthcare Inc",
    "wof:placetype":"venue"
},
  "geometry": {"coordinates":[-87.979981,42.066514],"type":"Point"}
}