{
  "type": "Feature",
  "properties": {
    "addr:full":"1660 N la Salle Dr # 4104 Chicago IL 60614",
    "addr:housenumber":"1660",
    "addr:postcode":"60614",
    "addr:street":"N La Salle Dr # 4104",
    "iso:country":"US",
    "sg:address":"1660 N la Salle Dr # 4104",
    "sg:city":"Chicago",
    "sg:classifiers":[
        {
            "category":"Professional",
            "subcategory":"Advertising",
            "type":"Services"
        }
    ],
    "sg:phone":"+1 312 266 7343",
    "sg:postcode":"60614",
    "sg:province":"IL",
    "sg:tags":[
        "promotion",
        "sale"
    ],
    "wof:name":"Zig Zag Marketing",
    "wof:placetype":"venue"
},
  "geometry": {"coordinates":[-87.633208,41.912783],"type":"Point"}
}