{
  "type": "Feature",
  "properties": {
    "iso:country":"US",
    "sg:address":"804 Timber Trail Dr",
    "sg:city":"Dixon",
    "sg:classifiers":[
        {
            "category":"Wholesale",
            "subcategory":"Machinery & Supplies",
            "type":"Manufacturing & Wholesale Goods"
        }
    ],
    "sg:phone":"+1 815 652 8699",
    "sg:postcode":"61021",
    "sg:province":"IL",
    "sg:tags":[
        "machine",
        "tool"
    ],
    "wof:name":"Machinery Source LLC",
    "wof:placetype":"venue"
},
  "geometry": {"coordinates":[-89.356012,41.916613],"type":"Point"}
}