{
  "type": "Feature",
  "properties": {
    "iso:country":"US",
    "sg:address":"228 Jefferson St",
    "sg:city":"Hopedale",
    "sg:classifiers":[
        {
            "category":"Building & Trades",
            "subcategory":"Landscaping Services",
            "type":"Services"
        }
    ],
    "sg:phone":"+1 309 449 6078",
    "sg:postcode":"61747",
    "sg:province":"IL",
    "wof:name":"Larry Weaver Mowing",
    "wof:placetype":"venue"
},
  "geometry": {"coordinates":[-89.412213,40.423781],"type":"Point"}
}