{
  "type": "Feature",
  "properties": {
    "addr:full":"1725 S West Ave Freeport IL 61032",
    "addr:housenumber":"1725",
    "addr:postcode":"61032",
    "addr:street":"S West Ave",
    "iso:country":"US",
    "sg:address":"1725 S West Ave",
    "sg:city":"Freeport",
    "sg:classifiers":[
        {
            "category":"Banks & Credit Unions",
            "subcategory":"Bank",
            "type":"Services"
        }
    ],
    "sg:phone":"+1 815 235 6137",
    "sg:postcode":"61032",
    "sg:province":"IL",
    "sg:website":"www.mwbonline.com",
    "wof:name":"Midwest Community Bank",
    "wof:placetype":"venue"
},
  "geometry": {"coordinates":[-89.631541,42.27959],"type":"Point"}
}