{
  "type": "Feature",
  "properties": {
    "addr:full":"1110 Curtis Ave Joliet IL 60435",
    "addr:housenumber":"1110",
    "addr:postcode":"60435",
    "addr:street":"Curtis Ave",
    "iso:country":"US",
    "sg:address":"1110 Curtis Ave",
    "sg:city":"Joliet",
    "sg:classifiers":[
        {
            "category":"Education",
            "subcategory":"School",
            "type":"Public Place"
        }
    ],
    "sg:phone":"+1 815 726 8208",
    "sg:postcode":"60435",
    "sg:province":"IL",
    "wof:name":"Genesis School",
    "wof:placetype":"venue"
},
  "geometry": {"coordinates":[-88.10959699999999,41.546557],"type":"Point"}
}