{
  "type": "Feature",
  "properties": {
    "iso:country":"US",
    "sg:address":"60 Akenside Rd",
    "sg:city":"Riverside",
    "sg:classifiers":[
        {
            "category":"Education",
            "subcategory":"Preschool",
            "type":"Public Place"
        },
        {
            "category":"Education",
            "subcategory":"School",
            "type":"Public Place"
        }
    ],
    "sg:phone":"+1 708 447 3373",
    "sg:postcode":"60546",
    "sg:province":"IL",
    "sg:tags":[
        "elementary"
    ],
    "wof:name":"St Pauls Building Blocks Preschool",
    "wof:placetype":"venue"
},
  "geometry": {"coordinates":[-87.81999999999999,41.8307],"type":"Point"}
}