{
  "type": "Feature",
  "properties": {
    "addr:full":"5003 W Addison St Chicago IL 60641",
    "addr:housenumber":"5003",
    "addr:postcode":"60641",
    "addr:street":"W Addison St",
    "iso:country":"US",
    "sg:address":"5003 W Addison St",
    "sg:city":"Chicago",
    "sg:classifiers":[
        {
            "category":"Retail",
            "subcategory":"Laundry & Dry Cleaning",
            "type":"Services"
        }
    ],
    "sg:phone":"+1 773 685 0117",
    "sg:postcode":"60641",
    "sg:province":"IL",
    "wof:name":"Bestyette Laundromat",
    "wof:placetype":"venue"
},
  "geometry": {"coordinates":[-87.75445000000001,41.945955],"type":"Point"}
}