{
  "type": "Feature",
  "properties": {
    "iso:country":"US",
    "sg:address":"10 North Martingale Road Suite 500",
    "sg:city":"Schaumburg",
    "sg:classifiers":[
        {
            "category":"Professional",
            "subcategory":"Computer Services",
            "type":"Services"
        }
    ],
    "sg:phone":"+1 847 273 4141",
    "sg:postcode":"60173",
    "sg:province":"IL",
    "sg:website":"http://www.hitachi-hitec.com",
    "wof:name":"Hitachi High-Technologies",
    "wof:placetype":"venue"
},
  "geometry": {"coordinates":[-88.034758,42.034285],"type":"Point"}
}