{
  "type": "Feature",
  "properties": {
    "addr:full":"6870 Rote Rd Rockford IL 61107",
    "addr:postcode":"6870;61107",
    "addr:street":"Rote Rd",
    "iso:country":"US",
    "sg:address":"6870 Rote Rd",
    "sg:city":"Rockford",
    "sg:classifiers":[
        {
            "category":"Banks & Credit Unions",
            "subcategory":"Bank",
            "type":"Services"
        }
    ],
    "sg:phone":"+1 815 637 1900",
    "sg:postcode":"61107",
    "sg:province":"IL",
    "sg:website":"http://www.thebankcentre.com",
    "wof:name":"The BankCentre",
    "wof:placetype":"venue"
},
  "geometry": {"coordinates":[-88.98110800000001,42.290401],"type":"Point"}
}