{
  "type": "Feature",
  "properties": {
    "iso:country":"US",
    "sg:address":"504 Case Ct",
    "sg:city":"Schaumburg",
    "sg:classifiers":[
        {
            "category":"Home & Garden",
            "subcategory":"Building Materials",
            "type":"Retail Goods"
        }
    ],
    "sg:phone":"+1 847 895 3981",
    "sg:postcode":"60193",
    "sg:province":"IL",
    "sg:tags":[
        "equipment",
        "electric",
        "supply"
    ],
    "wof:name":"Ask Enterprises",
    "wof:placetype":"venue"
},
  "geometry": {"coordinates":[-88.125929,42.016146],"type":"Point"}
}