{
  "type": "Feature",
  "properties": {
    "iso:country":"US",
    "sg:address":"5740 S Archer Ave",
    "sg:city":"Chicago",
    "sg:classifiers":[
        {
            "category":"Insurance",
            "subcategory":"Insurance Agent",
            "type":"Services"
        },
        {
            "category":"Insurance",
            "subcategory":"Hazard Insurance",
            "type":"Services"
        },
        {
            "category":"Insurance",
            "subcategory":"Title Insurance",
            "type":"Services"
        }
    ],
    "sg:phone":"+1 773 581 2800",
    "sg:postcode":"60638",
    "sg:province":"IL",
    "sg:tags":[
        "auto",
        "homeowner"
    ],
    "sg:website":"http://apps.amfam.com/agentlocator/?sourceid=yp3",
    "wof:name":"American Family Insurance- Yolanda Rivera",
    "wof:placetype":"venue"
},
  "geometry": {"coordinates":[-87.75591799999999,41.796709],"type":"Point"}
}