{
  "type": "Feature",
  "properties": {
    "addr:full":"933 W Grace St Chicago IL 60613",
    "addr:housenumber":"933",
    "addr:postcode":"60613",
    "addr:street":"W Grace St",
    "iso:country":"US",
    "sg:address":"933 W Grace St",
    "sg:city":"Chicago",
    "sg:classifiers":[
        {
            "category":"Retail",
            "subcategory":"Laundry & Dry Cleaning",
            "type":"Services"
        }
    ],
    "sg:phone":"+1 773 281 2004",
    "sg:postcode":"60613",
    "sg:province":"IL",
    "wof:name":"Green Cleaners",
    "wof:placetype":"venue"
},
  "geometry": {"coordinates":[-87.653198,41.950993],"type":"Point"}
}