{
  "type": "Feature",
  "properties": {
    "addr:full":"1610 Scottdale Cir Wheaton IL 60187",
    "addr:housenumber":"1610",
    "addr:postcode":"60187",
    "addr:street":"Scottdale Cir",
    "iso:country":"US",
    "sg:address":"1610 Scottdale Cir",
    "sg:city":"Wheaton",
    "sg:classifiers":[
        {
            "category":"Building & Trades",
            "subcategory":"Construction",
            "type":"Services"
        }
    ],
    "sg:phone":"+1 630 682 8022",
    "sg:postcode":"60187",
    "sg:province":"IL",
    "sg:tags":[
        "house"
    ],
    "wof:name":"Self Improvement Through Aware",
    "wof:placetype":"venue"
},
  "geometry": {"coordinates":[-88.08465,41.826852],"type":"Point"}
}