{
  "type": "Feature",
  "properties": {
    "addr:full":"618 N Cicero Ave Chicago IL 60644",
    "addr:housenumber":"618",
    "addr:postcode":"60644",
    "addr:street":"N Cicero Ave",
    "iso:country":"US",
    "sg:address":"618 N Cicero Ave",
    "sg:city":"Chicago",
    "sg:classifiers":[
        {
            "category":"Autos & Motor Vehicles",
            "subcategory":"Automobile Sales",
            "type":"Retail Goods"
        }
    ],
    "sg:phone":"+1 773 921 8529",
    "sg:postcode":"60644",
    "sg:province":"IL",
    "sg:tags":[
        "car",
        "dealer"
    ],
    "wof:name":"A J Auto Sales",
    "wof:placetype":"venue"
},
  "geometry": {"coordinates":[-87.745777,41.891947],"type":"Point"}
}