{
  "type": "Feature",
  "properties": {
    "addr:full":"1144 W Washington Boulevard Chicago IL 60607",
    "addr:housenumber":"1144",
    "addr:postcode":"60607",
    "addr:street":"W Washington Boulevard",
    "iso:country":"US",
    "sg:address":"1144 W Washington Boulevard",
    "sg:city":"Chicago",
    "sg:classifiers":[
        {
            "category":"Building & Trades",
            "subcategory":"Construction",
            "type":"Services"
        }
    ],
    "sg:phone":"+1 312 226 4003",
    "sg:postcode":"60607",
    "sg:province":"IL",
    "sg:tags":[
        "contractor"
    ],
    "wof:name":"Fisher Development",
    "wof:placetype":"venue"
},
  "geometry": {"coordinates":[-87.664548,41.883188],"type":"Point"}
}