{
  "type": "Feature",
  "properties": {
    "iso:country":"US",
    "sg:address":"6621 W Cornelia Ave Fl 2",
    "sg:city":"Chicago",
    "sg:classifiers":[
        {
            "category":"Wholesale",
            "subcategory":"Computers",
            "type":"Manufacturing & Wholesale Goods"
        }
    ],
    "sg:phone":"+1 773 545 9303",
    "sg:postcode":"60634",
    "sg:province":"IL",
    "sg:tags":[
        "equipment"
    ],
    "sg:website":"http://www.afableacs.com",
    "wof:name":"Jda Systems Inc",
    "wof:placetype":"venue"
},
  "geometry": {"coordinates":[-87.792473,41.943689],"type":"Point"}
}