{
  "type": "Feature",
  "properties": {
    "iso:country":"US",
    "sg:address":"8547 State Rte 3",
    "sg:city":"Evansville",
    "sg:phone":"+1 618 282 3386",
    "sg:postcode":"62242",
    "sg:province":"IL",
    "sg:tags":[
        "farm",
        "corn",
        "soybean"
    ],
    "wof:name":"Ruez Farm",
    "wof:placetype":"venue"
},
  "geometry": {"coordinates":[-89.99324799999999,38.127033],"type":"Point"}
}