{
  "type": "Feature",
  "properties": {
    "iso:country":"US",
    "sg:address":"1000 W Beach St",
    "sg:city":"Freeport",
    "sg:classifiers":[
        {
            "category":"Wholesale",
            "subcategory":"Vending Machines",
            "type":"Manufacturing & Wholesale Goods"
        }
    ],
    "sg:phone":"+1 815 233 1117",
    "sg:postcode":"61032",
    "sg:province":"IL",
    "sg:tags":[
        "operator",
        "equipment"
    ],
    "wof:name":"Automatic Vending Co",
    "wof:placetype":"venue"
},
  "geometry": {"coordinates":[-89.639299,42.305358],"type":"Point"}
}