{
  "type": "Feature",
  "properties": {
    "addr:full":"3999 Northwest Hwy Crystal Lake IL 60014",
    "addr:housenumber":"3999",
    "addr:postcode":"60014",
    "addr:street":"Northwest Hwy",
    "iso:country":"US",
    "sg:address":"3999 Northwest Hwy",
    "sg:city":"Crystal Lake",
    "sg:classifiers":[
        {
            "category":"Building & Trades",
            "subcategory":"Equipment Rental",
            "type":"Services"
        }
    ],
    "sg:phone":"+1 847 639 1400",
    "sg:postcode":"60014",
    "sg:province":"IL",
    "sg:tags":[
        "yard"
    ],
    "wof:name":"Route 14 Rental & Svc Inc",
    "wof:placetype":"venue"
},
  "geometry": {"coordinates":[-88.276723,42.226023],"type":"Point"}
}