{
  "type": "Feature",
  "properties": {
    "iso:country":"US",
    "sg:address":"2929 N Clark St",
    "sg:city":"Chicago",
    "sg:classifiers":[
        {
            "category":"Personal",
            "subcategory":"Barber",
            "type":"Services"
        }
    ],
    "sg:phone":"+1 773 404 3705",
    "sg:postcode":"60657",
    "sg:province":"IL",
    "sg:website":"www.cornerbarbershopchicago.com",
    "wof:name":"The Corner Barber Shop",
    "wof:placetype":"venue"
},
  "geometry": {"coordinates":[-87.646905,41.935686],"type":"Point"}
}