{
  "type": "Feature",
  "properties": {
    "iso:country":"US",
    "sg:address":"137 N Oak Park Ave Ste 129",
    "sg:city":"Oak Park",
    "sg:classifiers":[
        {
            "category":"Personal",
            "subcategory":"Beauty Salon",
            "type":"Services"
        }
    ],
    "sg:phone":"+1 708 524 4569",
    "sg:postcode":"60301",
    "sg:province":"IL",
    "sg:tags":[
        "spa"
    ],
    "sg:website":"www.alluremedicaspa.com",
    "wof:name":"Allure Medica Spa",
    "wof:placetype":"venue"
},
  "geometry": {"coordinates":[-87.79436,41.8883],"type":"Point"}
}