{
  "type": "Feature",
  "properties": {
    "addr:full":"1 N Chestnut Ave Arlington Hts IL 60005",
    "addr:housenumber":"1",
    "addr:postcode":"60005",
    "addr:street":"N Chestnut Ave",
    "iso:country":"US",
    "sg:address":"1 N Chestnut Ave",
    "sg:city":"Arlington Hts",
    "sg:classifiers":[
        {
            "category":"Real Estate",
            "subcategory":"Real Estate Operator",
            "type":"Services"
        }
    ],
    "sg:phone":"+1 847 392 8222",
    "sg:postcode":"60005",
    "sg:province":"IL",
    "sg:tags":[
        "apartment"
    ],
    "wof:name":"Chestnut Management",
    "wof:placetype":"venue"
},
  "geometry": {"coordinates":[-87.98649899999999,42.083769],"type":"Point"}
}