{
  "type": "Feature",
  "properties": {
    "iso:country":"US",
    "sg:address":"404 N President St",
    "sg:city":"Wheaton",
    "sg:classifiers":[
        {
            "category":"Organizations",
            "subcategory":"Religious Organization",
            "type":"Services"
        }
    ],
    "sg:phone":"+1 630 653 5285",
    "sg:postcode":"60187",
    "sg:province":"IL",
    "sg:tags":[
        "church"
    ],
    "sg:website":"www.bethanywheaton.com",
    "wof:name":"Bethany Chapel",
    "wof:placetype":"venue"
},
  "geometry": {"coordinates":[-88.092071,41.870082],"type":"Point"}
}