{
  "type": "Feature",
  "properties": {
    "addr:full":"51 S Grove Ave Elgin IL 60120",
    "addr:housenumber":"51",
    "addr:postcode":"60120",
    "addr:street":"S Grove Ave",
    "iso:country":"US",
    "sg:address":"51 S Grove Ave",
    "sg:city":"Elgin",
    "sg:classifiers":[
        {
            "category":"Manufacturing",
            "subcategory":"Metals",
            "type":"Manufacturing & Wholesale Goods"
        }
    ],
    "sg:phone":"+1 847 697 7400",
    "sg:postcode":"60120",
    "sg:province":"IL",
    "sg:tags":[
        "distributor",
        "steel",
        "mills",
        "for"
    ],
    "wof:name":"Severstal Inc",
    "wof:placetype":"venue"
},
  "geometry": {"coordinates":[-88.283148,42.036067],"type":"Point"}
}