{
  "type": "Feature",
  "properties": {
    "addr:full":"954 Marshall Dr Des Plaines IL 60016",
    "addr:housenumber":"954",
    "addr:postcode":"60016",
    "addr:street":"Marshall Dr",
    "iso:country":"US",
    "sg:address":"954 Marshall Dr",
    "sg:city":"Des Plaines",
    "sg:classifiers":[
        {
            "category":"Professional",
            "subcategory":"Computer Services",
            "type":"Services"
        }
    ],
    "sg:phone":"+1 847 437 7692",
    "sg:postcode":"60016",
    "sg:province":"IL",
    "sg:tags":[
        "prepackaged",
        "consulting",
        "management",
        "software"
    ],
    "wof:name":"J Gibbs & Associates Inc",
    "wof:placetype":"venue"
},
  "geometry": {"coordinates":[-87.930891,42.034547],"type":"Point"}
}