{
  "type": "Feature",
  "properties": {
    "iso:country":"US",
    "sg:address":"1250 W Augusta Blvd",
    "sg:city":"Chicago",
    "sg:classifiers":[
        {
            "category":"Banks & Credit Unions",
            "subcategory":"Bank",
            "type":"Services"
        }
    ],
    "sg:phone":"+1 773 278 0208",
    "sg:postcode":"60642",
    "sg:province":"IL",
    "wof:name":"Homestar Bank",
    "wof:placetype":"venue"
},
  "geometry": {"coordinates":[-87.658574,41.900006],"type":"Point"}
}