{
  "type": "Feature",
  "properties": {
    "iso:country":"US",
    "sg:address":"195 E Elk Trl",
    "sg:city":"Carol Stream",
    "sg:classifiers":[
        {
            "category":"Home & Garden",
            "subcategory":"Furniture",
            "type":"Retail Goods"
        }
    ],
    "sg:phone":"+1   ",
    "sg:postcode":"60188",
    "sg:province":"IL",
    "wof:name":"Homemakers",
    "wof:placetype":"venue"
},
  "geometry": {"coordinates":[-88.11998800000001,41.924689],"type":"Point"}
}