{
  "type": "Feature",
  "properties": {
    "iso:country":"US",
    "sg:address":"1105 E Main St",
    "sg:city":"Casey",
    "sg:classifiers":[
        {
            "category":"Mining & Drilling",
            "type":"Manufacturing & Wholesale Goods"
        }
    ],
    "sg:phone":"+1 217 932 4513",
    "sg:postcode":"62420",
    "sg:province":"IL",
    "sg:tags":[
        "crude",
        "production",
        "gas"
    ],
    "wof:name":"Dove Inc",
    "wof:placetype":"venue"
},
  "geometry": {"coordinates":[-87.97887,39.303547],"type":"Point"}
}