{
  "type": "Feature",
  "properties": {
    "iso:country":"US",
    "sg:address":"1320 N Seminary Ave",
    "sg:city":"Woodstock",
    "sg:classifiers":[
        {
            "category":"Professional",
            "subcategory":"Business Services",
            "type":"Services"
        }
    ],
    "sg:phone":"+1 815 337 3422",
    "sg:postcode":"60098",
    "sg:province":"IL",
    "sg:tags":[
        "mail",
        "shipping"
    ],
    "wof:name":"A Mzo Zip Mailing Services",
    "wof:placetype":"venue"
},
  "geometry": {"coordinates":[-88.443129,42.32832],"type":"Point"}
}