{
  "type": "Feature",
  "properties": {
    "addr:full":"506 Monroe Ave Ingleside IL 60041",
    "addr:housenumber":"506",
    "addr:postcode":"60041",
    "addr:street":"Monroe Ave",
    "iso:country":"US",
    "sg:address":"506 Monroe Ave",
    "sg:city":"Ingleside",
    "sg:classifiers":[
        {
            "category":"Retail",
            "subcategory":"Repair Shop",
            "type":"Services"
        }
    ],
    "sg:phone":"+1 847 587 5748",
    "sg:postcode":"60041",
    "sg:province":"IL",
    "sg:tags":[
        "upholsterer"
    ],
    "wof:name":"S & B Upholstery",
    "wof:placetype":"venue"
},
  "geometry": {"coordinates":[-88.15348400000001,42.384967],"type":"Point"}
}