{
  "type": "Feature",
  "properties": {
    "iso:country":"US",
    "sg:address":"1801 W 47th Street",
    "sg:city":"Chicago",
    "sg:classifiers":[
        {
            "category":"Shopping",
            "subcategory":"Jewelry",
            "type":"Retail Goods"
        }
    ],
    "sg:phone":"+1 773 523 7040",
    "sg:postcode":"60609",
    "sg:province":"IL",
    "wof:name":"Latina Jewelry",
    "wof:placetype":"venue"
},
  "geometry": {"coordinates":[-87.660449,41.806725],"type":"Point"}
}