{
  "type": "Feature",
  "properties": {
    "addr:full":"224 E 4th St Lockport IL 60441",
    "addr:housenumber":"224",
    "addr:postcode":"60441",
    "addr:street":"E 4Th St",
    "iso:country":"US",
    "sg:address":"224 E 4th St",
    "sg:city":"Lockport",
    "sg:classifiers":[
        {
            "category":"Retail",
            "subcategory":"Laundry & Dry Cleaning",
            "type":"Services"
        }
    ],
    "sg:phone":"+1 815 838 7636",
    "sg:postcode":"60441",
    "sg:province":"IL",
    "sg:tags":[
        "cleaners",
        "rug",
        "carpet"
    ],
    "wof:name":"Ultimate Carpet & Upholstery",
    "wof:placetype":"venue"
},
  "geometry": {"coordinates":[-88.05241700000001,41.593936],"type":"Point"}
}