{
  "type": "Feature",
  "properties": {
    "addr:full":"901 W Morton Ave Jacksonville IL 62650",
    "addr:housenumber":"901",
    "addr:postcode":"62650",
    "addr:street":"W Morton Ave",
    "iso:country":"US",
    "sg:address":"901 W Morton Ave",
    "sg:city":"Jacksonville",
    "sg:classifiers":[
        {
            "category":"Restaurant",
            "type":"Food & Drink"
        }
    ],
    "sg:phone":"+1   ",
    "sg:postcode":"62650",
    "sg:province":"IL",
    "sg:tags":[
        "eating"
    ],
    "wof:name":"Perkins Family Restaurant",
    "wof:placetype":"venue"
},
  "geometry": {"coordinates":[-90.240039,39.723153],"type":"Point"}
}