{
  "type": "Feature",
  "properties": {
    "iso:country":"US",
    "sg:address":"3614-16 W 26th St",
    "sg:city":"Chicago",
    "sg:classifiers":[
        {
            "category":"Restaurant",
            "type":"Food & Drink"
        }
    ],
    "sg:phone":"+1 773 521 4444",
    "sg:postcode":"60623",
    "sg:province":"IL",
    "sg:tags":[
        "mexican"
    ],
    "sg:website":"www.davilasrestaurant.com",
    "wof:name":"Davila's Restaurant",
    "wof:placetype":"venue"
},
  "geometry": {"coordinates":[-87.715535,41.8445],"type":"Point"}
}