{
  "type": "Feature",
  "properties": {
    "iso:country":"US",
    "sg:address":"2430 W Wadsworth Rd",
    "sg:city":"Waukegan",
    "sg:classifiers":[
        {
            "category":"Building & Trades",
            "subcategory":"Construction",
            "type":"Services"
        }
    ],
    "sg:phone":"+1 847 731 7200",
    "sg:postcode":"60087",
    "sg:province":"IL",
    "sg:tags":[
        "roofing",
        "contractor",
        "industrial",
        "contractors-commercial",
        "consultant"
    ],
    "wof:name":"Great Lakes Roofing Corp",
    "wof:placetype":"venue"
},
  "geometry": {"coordinates":[-87.86224900000001,42.428314],"type":"Point"}
}