{
  "type": "Feature",
  "properties": {
    "iso:country":"US",
    "sg:address":"195 Remington Blvd",
    "sg:city":"Bolingbrook",
    "sg:classifiers":[
        {
            "category":"Restaurant",
            "type":"Food & Drink"
        }
    ],
    "sg:phone":"+1 630 679 0029",
    "sg:postcode":"60440",
    "sg:province":"IL",
    "sg:tags":[
        "mexican"
    ],
    "wof:name":"Rancho Santa Fe",
    "wof:placetype":"venue"
},
  "geometry": {"coordinates":[-88.072625,41.684854],"type":"Point"}
}