{
  "type": "Feature",
  "properties": {
    "iso:country":"US",
    "sg:address":"3640 N Halsted St",
    "sg:city":"Chicago",
    "sg:classifiers":[
        {
            "category":"Food & Beverages",
            "subcategory":"Specialty",
            "type":"Retail Goods"
        },
        {
            "category":"Food & Beverages",
            "subcategory":"Supermarket",
            "type":"Retail Goods"
        }
    ],
    "sg:phone":"+1 773 472 0400",
    "sg:postcode":"60613",
    "sg:province":"IL",
    "sg:tags":[
        "product",
        "diet",
        "health",
        "super",
        "store"
    ],
    "sg:website":"http://www.wholefoods.com",
    "wof:name":"Whole Foods Market, Inc.",
    "wof:placetype":"venue"
},
  "geometry": {"coordinates":[-87.64945299999999,41.948467],"type":"Point"}
}