{
  "type": "Feature",
  "properties": {
    "addr:full":"299 Republic Ave Joliet IL 60435",
    "addr:housenumber":"299",
    "addr:postcode":"60435",
    "addr:street":"Republic Ave",
    "iso:country":"US",
    "sg:address":"299 Republic Ave",
    "sg:city":"Joliet",
    "sg:classifiers":[
        {
            "category":"Wholesale",
            "subcategory":"Hardware",
            "type":"Manufacturing & Wholesale Goods"
        }
    ],
    "sg:phone":"+1 815 729 0502",
    "sg:postcode":"60435",
    "sg:province":"IL",
    "sg:tags":[
        "plumbing"
    ],
    "wof:name":"Lakeside Distributing Inc",
    "wof:placetype":"venue"
},
  "geometry": {"coordinates":[-88.139141,41.524094],"type":"Point"}
}