{
  "type": "Feature",
  "properties": {
    "iso:country":"US",
    "sg:address":"221 W Main St",
    "sg:city":"Staunton",
    "sg:classifiers":[
        {
            "category":"Shopping",
            "subcategory":"Florist",
            "type":"Retail Goods"
        }
    ],
    "sg:phone":"+1 618 635 2288",
    "sg:postcode":"62088",
    "sg:province":"IL",
    "sg:tags":[
        "basket",
        "gift"
    ],
    "sg:website":"http://www.firnhaberflorist.com",
    "wof:name":"Firnhaber Florist",
    "wof:placetype":"venue"
},
  "geometry": {"coordinates":[-89.78793,39.012104],"type":"Point"}
}