{
  "type": "Feature",
  "properties": {
    "addr:full":"31668 N River Rd Libertyville IL 60048",
    "addr:housenumber":"31668",
    "addr:postcode":"60048",
    "addr:street":"N River Rd",
    "iso:country":"US",
    "sg:address":"31668 N River Rd",
    "sg:city":"Libertyville",
    "sg:classifiers":[
        {
            "category":"Recreation",
            "type":"Entertainment"
        }
    ],
    "sg:phone":"+1 847 247 0057",
    "sg:postcode":"60048",
    "sg:province":"IL",
    "sg:tags":[
        "stable"
    ],
    "wof:name":"Equidream School-Horsemanship",
    "wof:placetype":"venue"
},
  "geometry": {"coordinates":[-87.944029,42.323696],"type":"Point"}
}