{
  "type": "Feature",
  "properties": {
    "addr:full":"7056 171st St Tinley Park IL 60477",
    "addr:housenumber":"7056",
    "addr:postcode":"60477",
    "addr:street":"171St St",
    "iso:country":"US",
    "sg:address":"7056 171st St",
    "sg:city":"Tinley Park",
    "sg:classifiers":[
        {
            "category":"Professional",
            "subcategory":"Accounting & Tax Preparation",
            "type":"Services"
        }
    ],
    "sg:phone":"+1 708 429 9968",
    "sg:postcode":"60477",
    "sg:province":"IL",
    "wof:name":"Stapleton Robert G & Co",
    "wof:placetype":"venue"
},
  "geometry": {"coordinates":[-87.792608,41.580543],"type":"Point"}
}