{
  "type": "Feature",
  "properties": {
    "iso:country":"US",
    "sg:address":"1020 W Locust St",
    "sg:city":"Canton",
    "sg:classifiers":[
        {
            "category":"Wholesale",
            "subcategory":"Sporting Goods",
            "type":"Manufacturing & Wholesale Goods"
        }
    ],
    "sg:phone":"+1 309 647 4113",
    "sg:postcode":"61520",
    "sg:province":"IL",
    "sg:tags":[
        "equipment",
        "pool",
        "swimming"
    ],
    "wof:name":"Moshier's Pool & Auction Svc",
    "wof:placetype":"venue"
},
  "geometry": {"coordinates":[-90.06004900000001,40.560201],"type":"Point"}
}