{
  "type": "Feature",
  "properties": {
    "iso:country":"US",
    "sg:address":"4300 Bunkum Rd",
    "sg:city":"Washington Park",
    "sg:classifiers":[
        {
            "category":"Food & Beverages",
            "subcategory":"Liquor & Beverages",
            "type":"Retail Goods"
        }
    ],
    "sg:phone":"+1 618 875 7357",
    "sg:postcode":"62204",
    "sg:province":"IL",
    "wof:name":"Taylor's Package Liquors",
    "wof:placetype":"venue"
},
  "geometry": {"coordinates":[-90.103332,38.623337],"type":"Point"}
}