{
  "type": "Feature",
  "properties": {
    "addr:full":"15638 S 70th Ct Orland Park IL 60462",
    "addr:housenumber":"15638",
    "addr:postcode":"60462",
    "addr:street":"S 70Th Ct",
    "iso:country":"US",
    "sg:address":"15638 S 70th Ct",
    "sg:city":"Orland Park",
    "sg:classifiers":[
        {
            "category":"Manufacturing",
            "subcategory":"Tools & Machinery",
            "type":"Manufacturing & Wholesale Goods"
        }
    ],
    "sg:phone":"+1 708 429 5977",
    "sg:postcode":"60462",
    "sg:province":"IL",
    "sg:tags":[
        "process",
        "control",
        "mfg",
        "instrument"
    ],
    "wof:name":"Promation Inc",
    "wof:placetype":"venue"
},
  "geometry": {"coordinates":[-87.79107399999999,41.608321],"type":"Point"}
}