{
  "type": "Feature",
  "properties": {
    "iso:country":"US",
    "sg:address":"5067 Business 20 W",
    "sg:city":"Freeport",
    "sg:classifiers":[
        {
            "category":"Wholesale",
            "subcategory":"Hardware",
            "type":"Manufacturing & Wholesale Goods"
        },
        {
            "category":"Home & Garden",
            "subcategory":"Garden Supply",
            "type":"Retail Goods"
        },
        {
            "category":"Retail",
            "subcategory":"Repair Shop",
            "type":"Services"
        }
    ],
    "sg:phone":"+1 815 235 8062",
    "sg:postcode":"61032",
    "sg:province":"IL",
    "sg:tags":[
        "renting",
        "lawn",
        "outdoor",
        "power",
        "landscaping",
        "equipment-sales",
        "equipment",
        "saw"
    ],
    "sg:website":"http://www.stihlusa.com/",
    "wof:name":"Stee's Saw & Lawn Equipment",
    "wof:placetype":"venue"
},
  "geometry": {"coordinates":[-89.71189699999999,42.32783],"type":"Point"}
}