{
  "type": "Feature",
  "properties": {
    "addr:full":"2135 W Division St Chicago IL 60622",
    "addr:housenumber":"2135",
    "addr:postcode":"60622",
    "addr:street":"W Division St",
    "iso:country":"US",
    "sg:address":"2135 W Division St",
    "sg:city":"Chicago",
    "sg:classifiers":[
        {
            "category":"Wholesale",
            "subcategory":"Electrical",
            "type":"Manufacturing & Wholesale Goods"
        }
    ],
    "sg:phone":"+1 773 489 1534",
    "sg:postcode":"60622",
    "sg:province":"IL",
    "sg:tags":[
        "equipment",
        "electric",
        "supply"
    ],
    "wof:name":"Aion Antiquities",
    "wof:placetype":"venue"
},
  "geometry": {"coordinates":[-87.680547,41.90312],"type":"Point"}
}