{
  "type": "Feature",
  "properties": {
    "addr:full":"3107 W Fullerton Ave Chicago IL 60647",
    "addr:housenumber":"3107",
    "addr:postcode":"60647",
    "addr:street":"W Fullerton Ave",
    "iso:country":"US",
    "sg:address":"3107 W Fullerton Ave",
    "sg:city":"Chicago",
    "sg:classifiers":[
        {
            "category":"Organizations",
            "subcategory":"Religious Organization",
            "type":"Services"
        }
    ],
    "sg:phone":"+1 773 342 7373",
    "sg:postcode":"60647",
    "sg:province":"IL",
    "wof:name":"Christ Rdmer Byzntine Blrusian",
    "wof:placetype":"venue"
},
  "geometry": {"coordinates":[-87.704745,41.924665],"type":"Point"}
}