{
  "type": "Feature",
  "properties": {
    "addr:full":"212 N 6th St Quincy IL 62301",
    "addr:housenumber":"212",
    "addr:postcode":"62301",
    "addr:street":"N 6Th St",
    "iso:country":"US",
    "sg:address":"212 N 6th St",
    "sg:city":"Quincy",
    "sg:classifiers":[
        {
            "category":"Professional",
            "subcategory":"Business Services",
            "type":"Services"
        }
    ],
    "sg:phone":"+1 217 222 0605",
    "sg:postcode":"62301",
    "sg:province":"IL",
    "sg:tags":[
        "consultant",
        "coach"
    ],
    "wof:name":"I Remember That",
    "wof:placetype":"venue"
},
  "geometry": {"coordinates":[-91.40676000000001,39.933423],"type":"Point"}
}