{
  "type": "Feature",
  "properties": {
    "iso:country":"US",
    "sg:address":"6118 Scott Ln",
    "sg:city":"Crystal Lake",
    "sg:classifiers":[
        {
            "category":"Manufacturing",
            "subcategory":"Metals",
            "type":"Manufacturing & Wholesale Goods"
        }
    ],
    "sg:phone":"+1 815 455 9649",
    "sg:postcode":"60014",
    "sg:province":"IL",
    "sg:tags":[
        "mfg"
    ],
    "wof:name":"Doors Are US Storm Door Spec",
    "wof:placetype":"venue"
},
  "geometry": {"coordinates":[-88.283583,42.239219],"type":"Point"}
}