{
  "type": "Feature",
  "properties": {
    "addr:full":"555 Plate Dr East Dundee IL 60118",
    "addr:housenumber":"555",
    "addr:postcode":"60118",
    "addr:street":"Plate Dr",
    "iso:country":"US",
    "sg:address":"555 Plate Dr",
    "sg:city":"East Dundee",
    "sg:classifiers":[
        {
            "category":"Real Estate",
            "subcategory":"Real Estate Services",
            "type":"Services"
        }
    ],
    "sg:phone":"+1 847 551 9960",
    "sg:postcode":"60118",
    "sg:province":"IL",
    "sg:tags":[
        "management",
        "property"
    ],
    "wof:name":"Rental Systems",
    "wof:placetype":"venue"
},
  "geometry": {"coordinates":[-88.247376,42.091586],"type":"Point"}
}