{
  "type": "Feature",
  "properties": {
    "addr:full":"115 7th St Rockford IL 61104",
    "addr:housenumber":"115",
    "addr:postcode":"61104",
    "addr:street":"7Th St",
    "iso:country":"US",
    "sg:address":"115 7th St",
    "sg:city":"Rockford",
    "sg:classifiers":[
        {
            "category":"Utilities",
            "subcategory":"Water",
            "type":"Services"
        }
    ],
    "sg:phone":"+1 815 968 6277",
    "sg:postcode":"61104",
    "sg:province":"IL",
    "sg:tags":[
        "company",
        "sewage"
    ],
    "wof:name":"Wildwood Utility Co",
    "wof:placetype":"venue"
},
  "geometry": {"coordinates":[-89.08085800000001,42.265875],"type":"Point"}
}