{
  "type": "Feature",
  "properties": {
    "iso:country":"US",
    "sg:address":"2617 Sherman Ave",
    "sg:city":"Rockford",
    "sg:classifiers":[
        {
            "category":"Home & Garden",
            "subcategory":"Hardware",
            "type":"Retail Goods"
        }
    ],
    "sg:phone":"+1 815 965 2059",
    "sg:postcode":"61101",
    "sg:province":"IL",
    "sg:tags":[
        "store"
    ],
    "sg:website":"http://www.expresssteel.com",
    "wof:name":"Express Steel Inc",
    "wof:placetype":"venue"
},
  "geometry": {"coordinates":[-89.127353,42.285083],"type":"Point"}
}