{
  "type": "Feature",
  "properties": {
    "addr:full":"4923 Colt Rd Rockford IL 61109",
    "addr:housenumber":"4923",
    "addr:postcode":"61109",
    "addr:street":"Colt Rd",
    "iso:country":"US",
    "sg:address":"4923 Colt Rd",
    "sg:city":"Rockford",
    "sg:classifiers":[
        {
            "category":"Shopping",
            "type":"Retail Goods"
        },
        {
            "category":"Wholesale",
            "subcategory":"Electrical",
            "type":"Manufacturing & Wholesale Goods"
        }
    ],
    "sg:phone":"+1 815 874 8811",
    "sg:postcode":"61109",
    "sg:province":"IL",
    "sg:tags":[
        "merchandise",
        "electric",
        "motor"
    ],
    "wof:name":"Rockford Armature & Electric M",
    "wof:placetype":"venue"
},
  "geometry": {"coordinates":[-89.021107,42.225713],"type":"Point"}
}