{
  "type": "Feature",
  "properties": {
    "addr:full":"6447 North Albany Avenue Chicago IL 60645",
    "addr:housenumber":"6447",
    "addr:postcode":"60645",
    "addr:street":"North Albany Avenue",
    "iso:country":"US",
    "sg:address":"6447 North Albany Avenue",
    "sg:city":"Chicago",
    "sg:classifiers":[
        {
            "category":"Place Of Worship",
            "subcategory":"Church",
            "type":"Public Place"
        }
    ],
    "sg:phone":"+1 773 465 5406",
    "sg:postcode":"60645",
    "sg:province":"IL",
    "sg:website":"www.konkofaith.org",
    "wof:name":"Konko Church of Chicago",
    "wof:placetype":"venue"
},
  "geometry": {"coordinates":[-87.70657300000001,41.998694],"type":"Point"}
}