{
  "type": "Feature",
  "properties": {
    "iso:country":"US",
    "sg:address":"4210 N Lincoln",
    "sg:city":"Chicago",
    "sg:classifiers":[
        {
            "category":"Arts & Performance",
            "subcategory":"Arts Center",
            "type":"Entertainment"
        },
        {
            "category":"Arts & Performance",
            "subcategory":"Comedy Club",
            "type":"Entertainment"
        }
    ],
    "sg:phone":"+1 773 865 7731",
    "sg:postcode":"60640",
    "sg:province":"IL",
    "sg:tags":[
        "performing"
    ],
    "sg:website":"www.snubfest.com",
    "wof:name":"Snubfest",
    "wof:placetype":"venue"
},
  "geometry": {"coordinates":[-87.681664,41.958046],"type":"Point"}
}