{
  "type": "Feature",
  "properties": {
    "addr:full":"295 Main St NW Bourbonnais IL 60914",
    "addr:housenumber":"295",
    "addr:postcode":"bourbonnais il 60914",
    "addr:street":"Main St Nw",
    "iso:country":"US",
    "sg:address":"295 Main St NW",
    "sg:city":"Bourbonnais",
    "sg:classifiers":[
        {
            "category":"Retail",
            "subcategory":"Funeral Services",
            "type":"Services"
        }
    ],
    "sg:phone":"+1 815 932 1214",
    "sg:postcode":"60914",
    "sg:province":"IL",
    "sg:tags":[
        "crematory"
    ],
    "sg:website":"www.clancygernon.com",
    "wof:name":"Clancy-Gernon Funeral Homes",
    "wof:placetype":"venue"
},
  "geometry": {"coordinates":[-87.88119,41.156229],"type":"Point"}
}