{
  "type": "Feature",
  "properties": {
    "iso:country":"US",
    "sg:address":"3469 S King Dr",
    "sg:city":"Chicago",
    "sg:classifiers":[
        {
            "category":"Personal",
            "subcategory":"Nail Salon",
            "type":"Services"
        }
    ],
    "sg:phone":"+1 312 791 9066",
    "sg:postcode":"60616",
    "sg:province":"IL",
    "wof:name":"Maxim Nails",
    "wof:placetype":"venue"
},
  "geometry": {"coordinates":[-87.616798,41.831699],"type":"Point"}
}