{
  "type": "Feature",
  "properties": {
    "iso:country":"US",
    "sg:address":"3033 W 147th St",
    "sg:city":"Posen",
    "sg:classifiers":[
        {
            "category":"Autos & Motor Vehicles",
            "subcategory":"Fuel & Gas Station",
            "type":"Retail Goods"
        }
    ],
    "sg:phone":"+1 708 385 0940",
    "sg:postcode":"60469",
    "sg:province":"IL",
    "wof:name":"Petro Kanisa",
    "wof:placetype":"venue"
},
  "geometry": {"coordinates":[-87.69499999999999,41.625801],"type":"Point"}
}