{
  "type": "Feature",
  "properties": {
    "addr:full":"321 N Central Ave Chicago IL 60644",
    "addr:housenumber":"321",
    "addr:postcode":"60644",
    "addr:street":"N Central Ave",
    "iso:country":"US",
    "sg:address":"321 N Central Ave",
    "sg:city":"Chicago",
    "sg:classifiers":[
        {
            "category":"Health Services",
            "subcategory":"Nursing And Care Facility",
            "type":"Services"
        },
        {
            "category":"Social Services",
            "subcategory":"Adult Care",
            "type":"Services"
        }
    ],
    "sg:phone":"+1 773 626 2300",
    "sg:postcode":"60644",
    "sg:province":"IL",
    "sg:tags":[
        "home",
        "center",
        "convalescent",
        "rehabilitation",
        "residential"
    ],
    "wof:name":"Central Plaza Residential Home",
    "wof:placetype":"venue"
},
  "geometry": {"coordinates":[-87.765068,41.886051],"type":"Point"}
}