{
  "type": "Feature",
  "properties": {
    "addr:full":"1743 W Division St Chicago IL 60622",
    "addr:housenumber":"1743",
    "addr:postcode":"60622",
    "addr:street":"W Division St",
    "iso:country":"US",
    "sg:address":"1743 W Division St",
    "sg:city":"Chicago",
    "sg:classifiers":[
        {
            "category":"Insurance",
            "subcategory":"Health Insurance",
            "type":"Services"
        }
    ],
    "sg:phone":"+1 773 235 1000",
    "sg:postcode":"60622",
    "sg:province":"IL",
    "sg:tags":[
        "employee",
        "benefit"
    ],
    "sg:website":"http://www.fultonmatthews.com",
    "wof:name":"Fulton Matthews Inc",
    "wof:placetype":"venue"
},
  "geometry": {"coordinates":[-87.67137200000001,41.903267],"type":"Point"}
}