{
  "type": "Feature",
  "properties": {
    "iso:country":"US",
    "sg:address":"315 E Walnut St",
    "sg:city":"Carbondale",
    "sg:classifiers":[
        {
            "category":"Food & Beverages",
            "subcategory":"Groceries & Convenience Stores",
            "type":"Retail Goods"
        }
    ],
    "sg:phone":"+1 618 457 5429",
    "sg:postcode":"62901",
    "sg:province":"IL",
    "wof:name":"Convenient Food Mart",
    "wof:placetype":"venue"
},
  "geometry": {"coordinates":[-89.211237,37.725637],"type":"Point"}
}