{
  "type": "Feature",
  "properties": {
    "iso:country":"US",
    "sg:address":"401 Main St",
    "sg:city":"Savanna",
    "sg:classifiers":[
        {
            "category":"Health Services",
            "subcategory":"Dentist",
            "type":"Services"
        }
    ],
    "sg:phone":"+1 815 273 2212",
    "sg:postcode":"61074",
    "sg:province":"IL",
    "sg:tags":[
        "dental",
        "clinic"
    ],
    "sg:website":"http://www.riversidedentalpc.com",
    "wof:name":"Riverside Dental, P.C.",
    "wof:placetype":"venue"
},
  "geometry": {"coordinates":[-90.156723,42.09433],"type":"Point"}
}