{
  "type": "Feature",
  "properties": {
    "addr:full":"1524 Broadway Rockford IL 61104",
    "addr:housenumber":"1524",
    "addr:postcode":"61104",
    "addr:street":"Broadway",
    "iso:country":"US",
    "sg:address":"1524 Broadway",
    "sg:city":"Rockford",
    "sg:classifiers":[
        {
            "category":"Bars & Pubs",
            "type":"Food & Drink"
        }
    ],
    "sg:phone":"+1 815 964 1544",
    "sg:postcode":"61104",
    "sg:province":"IL",
    "wof:name":"Barb's Broadway Inn Inc",
    "wof:placetype":"venue"
},
  "geometry": {"coordinates":[-89.073133,42.252487],"type":"Point"}
}