{
  "type": "Feature",
  "properties": {
    "addr:full":"1357 W Fullerton Chicago IL 60614",
    "addr:housenumber":"1357",
    "addr:postcode":"60614",
    "addr:street":"W Fullerton",
    "iso:country":"US",
    "sg:address":"1357 W Fullerton",
    "sg:city":"Chicago",
    "sg:classifiers":[
        {
            "category":"Building & Trades",
            "subcategory":"Construction",
            "type":"Services"
        }
    ],
    "sg:phone":"+1 773 818 7608",
    "sg:postcode":"60614",
    "sg:province":"IL",
    "sg:tags":[
        "contractor"
    ],
    "sg:website":"generalcontractoril.com/",
    "wof:name":"Dara Construction Group",
    "wof:placetype":"venue"
},
  "geometry": {"coordinates":[-87.66271,41.925074],"type":"Point"}
}