{
  "type": "Feature",
  "properties": {
    "addr:full":"720 Sycamore St Quincy IL 62301",
    "addr:housenumber":"720",
    "addr:postcode":"62301",
    "addr:street":"Sycamore St",
    "iso:country":"US",
    "sg:address":"720 Sycamore St",
    "sg:city":"Quincy",
    "sg:classifiers":[
        {
            "category":"Professional",
            "type":"Services"
        }
    ],
    "sg:phone":"+1 217 224 8961",
    "sg:postcode":"62301",
    "sg:province":"IL",
    "sg:tags":[
        "establishment"
    ],
    "wof:name":"Contract Therapy",
    "wof:placetype":"venue"
},
  "geometry": {"coordinates":[-91.404572,39.94809],"type":"Point"}
}