{
  "type": "Feature",
  "properties": {
    "iso:country":"US",
    "sg:address":"125 N Main St",
    "sg:city":"Ladd",
    "sg:classifiers":[
        {
            "category":"Education",
            "subcategory":"Library",
            "type":"Public Place"
        }
    ],
    "sg:phone":"+1 815 894 3254",
    "sg:postcode":"61329",
    "sg:province":"IL",
    "wof:name":"Ladd Public Library",
    "wof:placetype":"venue"
},
  "geometry": {"coordinates":[-89.21907,41.382357],"type":"Point"}
}