{
  "type": "Feature",
  "properties": {
    "iso:country":"US",
    "sg:address":"7525 State Rte 154",
    "sg:city":"Baldwin",
    "sg:classifiers":[
        {
            "category":"Wholesale",
            "subcategory":"Sporting Goods",
            "type":"Manufacturing & Wholesale Goods"
        }
    ],
    "sg:phone":"+1 618 785 2235",
    "sg:postcode":"62217",
    "sg:province":"IL",
    "wof:name":"Glenn Zanders Sporting Goods",
    "wof:placetype":"venue"
},
  "geometry": {"coordinates":[-89.874575,38.184805],"type":"Point"}
}