{
  "type": "Feature",
  "properties": {
    "addr:full":"743 Bedford Rd Morris IL 60450",
    "addr:housenumber":"743",
    "addr:postcode":"60450",
    "addr:street":"Bedford Rd",
    "iso:country":"US",
    "sg:address":"743 Bedford Rd",
    "sg:city":"Morris",
    "sg:classifiers":[
        {
            "category":"Restaurant",
            "type":"Food & Drink"
        }
    ],
    "sg:menulink":"http://www.allmenus.com/il/morris/226349-caseys-general-store/menu/",
    "sg:phone":"+1 815 941 2895",
    "sg:postcode":"60450",
    "sg:province":"IL",
    "sg:tags":[
        "american",
        "pizza"
    ],
    "wof:name":"Casey's General Store",
    "wof:placetype":"venue"
},
  "geometry": {"coordinates":[-88.43415400000001,41.371683],"type":"Point"}
}