{
  "type": "Feature",
  "properties": {
    "addr:full":"1743 Sherman Ave Evanston IL 60201",
    "addr:housenumber":"1743",
    "addr:postcode":"60201",
    "addr:street":"Sherman Ave",
    "iso:country":"US",
    "sg:address":"1743 Sherman Ave",
    "sg:city":"Evanston",
    "sg:classifiers":[
        {
            "category":"Fast Food",
            "type":"Food & Drink"
        },
        {
            "category":"Restaurant",
            "type":"Food & Drink"
        }
    ],
    "sg:phone":"+1 847 733 8226",
    "sg:postcode":"60201",
    "sg:province":"IL",
    "sg:tags":[
        "mexican"
    ],
    "sg:website":"http://www.tacobell.com",
    "wof:name":"Taco Bell",
    "wof:placetype":"venue"
},
  "geometry": {"coordinates":[-87.681814,42.049134],"type":"Point"}
}