{
  "type": "Feature",
  "properties": {
    "iso:country":"US",
    "sg:address":"431 Linn Ave",
    "sg:city":"Crystal Lake",
    "sg:classifiers":[
        {
            "category":"Shopping",
            "type":"Retail Goods"
        }
    ],
    "sg:phone":"+1 815 459 2032",
    "sg:postcode":"60014",
    "sg:province":"IL",
    "sg:tags":[
        "miscellaneous",
        "store"
    ],
    "wof:name":"D & D Otte",
    "wof:placetype":"venue"
},
  "geometry": {"coordinates":[-88.334119,42.229167],"type":"Point"}
}