{
  "type": "Feature",
  "properties": {
    "addr:full":"4100 N Elston Ave Chicago IL 60618",
    "addr:housenumber":"4100",
    "addr:postcode":"60618",
    "addr:street":"N Elston Ave",
    "iso:country":"US",
    "sg:address":"4100 N Elston Ave",
    "sg:city":"Chicago",
    "sg:classifiers":[
        {
            "category":"Autos & Motor Vehicles",
            "subcategory":"Auto Supplies",
            "type":"Retail Goods"
        }
    ],
    "sg:phone":"+1 773 866 1720",
    "sg:postcode":"60618",
    "sg:province":"IL",
    "sg:tags":[
        "tire"
    ],
    "wof:name":"Eagle Tire Shop 4",
    "wof:placetype":"venue"
},
  "geometry": {"coordinates":[-87.721397,41.955399],"type":"Point"}
}