{
  "type": "Feature",
  "properties": {
    "iso:country":"US",
    "sg:address":"2744 NW Branch Rd",
    "sg:city":"Polo",
    "sg:classifiers":[
        {
            "category":"Wholesale",
            "subcategory":"Farm Supplies",
            "type":"Manufacturing & Wholesale Goods"
        }
    ],
    "sg:phone":"+1 815 946 2600",
    "sg:postcode":"61064",
    "sg:province":"IL",
    "sg:tags":[
        "grain",
        "elevator"
    ],
    "wof:name":"Bocker Grain Inc",
    "wof:placetype":"venue"
},
  "geometry": {"coordinates":[-89.53904,42.057852],"type":"Point"}
}