{
  "type": "Feature",
  "properties": {
    "iso:country":"US",
    "sg:address":"25 E Dundee Rd",
    "sg:city":"Buffalo Grove",
    "sg:classifiers":[
        {
            "category":"Health Services",
            "subcategory":"Optometrist",
            "type":"Services"
        }
    ],
    "sg:phone":"+1   ",
    "sg:postcode":"60089",
    "sg:province":"IL",
    "sg:tags":[
        "optical",
        "good"
    ],
    "wof:name":"Alan Optical",
    "wof:placetype":"venue"
},
  "geometry": {"coordinates":[-87.957605,42.138817],"type":"Point"}
}