{
  "type": "Feature",
  "properties": {
    "addr:full":"899 N Shady Oaks Dr Elgin IL 60120",
    "addr:housenumber":"899",
    "addr:postcode":"60120",
    "addr:street":"N Shady Oaks Dr",
    "iso:country":"US",
    "sg:address":"899 N Shady Oaks Dr",
    "sg:city":"Elgin",
    "sg:classifiers":[
        {
            "category":"Manufacturing",
            "subcategory":"Printing",
            "type":"Manufacturing & Wholesale Goods"
        }
    ],
    "sg:phone":"+1 847 289 1403",
    "sg:postcode":"60120",
    "sg:province":"IL",
    "sg:tags":[
        "periodical"
    ],
    "wof:name":"Pulp Magazine",
    "wof:placetype":"venue"
},
  "geometry": {"coordinates":[-88.249071,42.048985],"type":"Point"}
}