{
  "type": "Feature",
  "properties": {
    "addr:full":"2635 N Co Rd 900 Niota IL 62358",
    "addr:housenumber":"2635",
    "addr:postcode":"900;62358",
    "addr:street":"N Co Rd",
    "iso:country":"US",
    "sg:address":"2635 N Co Rd 900",
    "sg:city":"Niota",
    "sg:classifiers":[
        {
            "category":"Farming",
            "subcategory":"Farm",
            "type":"Manufacturing & Wholesale Goods"
        }
    ],
    "sg:phone":"+1 217 448 4156",
    "sg:postcode":"62358",
    "sg:province":"IL",
    "wof:name":"Ferguson Farms LTD",
    "wof:placetype":"venue"
},
  "geometry": {"coordinates":[-91.326454,40.575312],"type":"Point"}
}