{
  "type": "Feature",
  "properties": {
    "iso:country":"US",
    "sg:address":"200 N Park St",
    "sg:city":"Galatia",
    "sg:classifiers":[
        {
            "category":"Organizations",
            "subcategory":"Religious Organization",
            "type":"Services"
        }
    ],
    "sg:phone":"+1 618 268 6200",
    "sg:postcode":"62935",
    "sg:province":"IL",
    "wof:name":"James M Baldwin Dr",
    "wof:placetype":"venue"
},
  "geometry": {"coordinates":[-88.614538,37.842805],"type":"Point"}
}