{
  "type": "Feature",
  "properties": {
    "addr:full":"25 Adams St Jacksonville IL 62650",
    "addr:housenumber":"25",
    "addr:postcode":"62650",
    "addr:street":"Adams St",
    "iso:country":"US",
    "sg:address":"25 Adams St",
    "sg:city":"Jacksonville",
    "sg:classifiers":[
        {
            "category":"Retail",
            "subcategory":"Auto Repair",
            "type":"Services"
        }
    ],
    "sg:phone":"+1 217 245 5014",
    "sg:postcode":"62650",
    "sg:province":"IL",
    "sg:tags":[
        "general",
        "supply"
    ],
    "wof:name":"E & D Repair",
    "wof:placetype":"venue"
},
  "geometry": {"coordinates":[-90.346,39.686956],"type":"Point"}
}