{
  "type": "Feature",
  "properties": {
    "iso:country":"US",
    "sg:address":"3207 S Cherry Ave",
    "sg:city":"Mc Henry",
    "sg:classifiers":[
        {
            "category":"Banks & Credit Unions",
            "subcategory":"Investment Brokerage",
            "type":"Services"
        }
    ],
    "sg:phone":"+1 815 759 1727",
    "sg:postcode":"60051",
    "sg:province":"IL",
    "sg:tags":[
        "advisory"
    ],
    "wof:name":"Mountain Capital Financial Svc",
    "wof:placetype":"venue"
},
  "geometry": {"coordinates":[-88.214821,42.282224],"type":"Point"}
}