{
  "type": "Feature",
  "properties": {
    "addr:full":"1 River Oaks Center Dr Calumet City IL 60409",
    "addr:housenumber":"1",
    "addr:postcode":"60409",
    "addr:street":"River Oaks Center Dr",
    "iso:country":"US",
    "sg:address":"1 River Oaks Center Dr",
    "sg:city":"Calumet City",
    "sg:classifiers":[
        {
            "category":"Shopping",
            "subcategory":"Music",
            "type":"Retail Goods"
        }
    ],
    "sg:phone":"+1 708 862 4522",
    "sg:postcode":"60409",
    "sg:province":"IL",
    "sg:tags":[
        "dvd's"
    ],
    "wof:name":"Fye",
    "wof:placetype":"venue"
},
  "geometry": {"coordinates":[-87.530537,41.596413],"type":"Point"}
}