{
  "type": "Feature",
  "properties": {
    "iso:country":"US",
    "sg:address":"34278 W Bluestem Rd",
    "sg:city":"Round Lake Hts",
    "sg:classifiers":[
        {
            "category":"Mining & Drilling",
            "type":"Manufacturing & Wholesale Goods"
        }
    ],
    "sg:phone":"+1 847 740 1148",
    "sg:postcode":"60073",
    "sg:province":"IL",
    "sg:tags":[
        "jacking",
        "mud",
        "contractor"
    ],
    "wof:name":"Judge Concrete Industries",
    "wof:placetype":"venue"
},
  "geometry": {"coordinates":[-88.13199899999999,42.359007],"type":"Point"}
}