{
  "type": "Feature",
  "properties": {
    "iso:country":"US",
    "sg:address":"129 W National St",
    "sg:city":"West Chicago",
    "sg:classifiers":[
        {
            "category":"Park",
            "type":"Public Place"
        }
    ],
    "sg:postcode":"60185",
    "sg:province":"IL",
    "sg:website":"www.we-goparks.org/reed-keppler-...",
    "wof:name":"Reed-Keppler Park",
    "wof:placetype":"venue"
},
  "geometry": {"coordinates":[-88.20599300000001,41.892854],"type":"Point"}
}