{
  "type": "Feature",
  "properties": {
    "iso:country":"US",
    "sg:address":"1909 Aster Ct",
    "sg:city":"Johnsburg",
    "sg:phone":"+1 847 497 9005",
    "sg:postcode":"60051",
    "sg:province":"IL",
    "wof:name":"Budget Blinds Of Mc Henry",
    "wof:placetype":"venue"
},
  "geometry": {"coordinates":[-88.237596,42.404162],"type":"Point"}
}