{
  "type": "Feature",
  "properties": {
    "addr:full":"665 Pasquinelli Dr Unit 203 Westmont IL 60559",
    "addr:housenumber":"665;203",
    "addr:postcode":"60559",
    "addr:street":"Pasquinelli Dr Unit",
    "iso:country":"US",
    "sg:address":"665 Pasquinelli Dr Unit 203",
    "sg:city":"Westmont",
    "sg:classifiers":[
        {
            "category":"Personal",
            "subcategory":"Massage",
            "type":"Services"
        },
        {
            "category":"Food & Beverages",
            "subcategory":"Specialty",
            "type":"Retail Goods"
        },
        {
            "category":"Health Services",
            "subcategory":"Health Practitioner",
            "type":"Services"
        },
        {
            "category":"Food & Beverages",
            "subcategory":"Fruits & Vegetables",
            "type":"Retail Goods"
        }
    ],
    "sg:phone":"+1 630 789 2350",
    "sg:postcode":"60559",
    "sg:province":"IL",
    "sg:tags":[
        "herb",
        "medicine",
        "therapist",
        "acupuncture",
        "alternative",
        "spice"
    ],
    "sg:website":"http://www.liferising.com",
    "wof:name":"Ton Shen Health Westmont",
    "wof:placetype":"venue"
},
  "geometry": {"coordinates":[-87.951212,41.81381],"type":"Point"}
}