{
  "type": "Feature",
  "properties": {
    "addr:full":"17108 S Park Ave South Holland IL 60473",
    "addr:housenumber":"17108",
    "addr:postcode":"60473",
    "addr:street":"S Park Ave",
    "iso:country":"US",
    "sg:address":"17108 S Park Ave",
    "sg:city":"South Holland",
    "sg:classifiers":[
        {
            "category":"Personal",
            "subcategory":"Nail Salon",
            "type":"Services"
        }
    ],
    "sg:phone":"+1 708 210 9505",
    "sg:postcode":"60473",
    "sg:province":"IL",
    "wof:name":"Classy Nails",
    "wof:placetype":"venue"
},
  "geometry": {"coordinates":[-87.60749,41.584398],"type":"Point"}
}