{
  "type": "Feature",
  "properties": {
    "iso:country":"US",
    "sg:address":"11958 S Paulina St",
    "sg:city":"Calumet Park",
    "sg:classifiers":[
        {
            "category":"Communications",
            "subcategory":"News Services",
            "type":"Services"
        }
    ],
    "sg:phone":"+1 708 385 1568",
    "sg:postcode":"60827",
    "sg:province":"IL",
    "wof:name":"Brown News Svc E",
    "wof:placetype":"venue"
},
  "geometry": {"coordinates":[-87.663859,41.676808],"type":"Point"}
}