{
  "type": "Feature",
  "properties": {
    "iso:country":"US",
    "sg:address":"510 Martin Luther King Dr",
    "sg:city":"East Saint Louis",
    "sg:classifiers":[
        {
            "category":"Food & Beverages",
            "subcategory":"Meat & Fish",
            "type":"Retail Goods"
        }
    ],
    "sg:phone":"+1 618 482 4444",
    "sg:postcode":"62201",
    "sg:province":"IL",
    "sg:tags":[
        "shop"
    ],
    "wof:name":"East Side Meat Company",
    "wof:placetype":"venue"
},
  "geometry": {"coordinates":[-90.15478400000001,38.627463],"type":"Point"}
}