{
  "type": "Feature",
  "properties": {
    "addr:full":"16456 Horseshoe Dr Tinley Park IL 60487",
    "addr:housenumber":"16456",
    "addr:postcode":"60487",
    "addr:street":"Horseshoe Dr",
    "iso:country":"US",
    "sg:address":"16456 Horseshoe Dr",
    "sg:city":"Tinley Park",
    "sg:classifiers":[
        {
            "category":"Organizations",
            "subcategory":"Religious Organization",
            "type":"Services"
        }
    ],
    "sg:phone":"+1 708 532 1669",
    "sg:postcode":"60487",
    "sg:province":"IL",
    "wof:name":"John Ouwinga Rev",
    "wof:placetype":"venue"
},
  "geometry": {"coordinates":[-87.82414799999999,41.592352],"type":"Point"}
}