{
  "type": "Feature",
  "properties": {
    "iso:country":"US",
    "sg:address":"205 W Main St",
    "sg:city":"Collinsville",
    "sg:classifiers":[
        {
            "category":"Communications",
            "subcategory":"Newspaper",
            "type":"Services"
        }
    ],
    "sg:phone":"+1 618 345 7822",
    "sg:postcode":"62234",
    "sg:province":"IL",
    "sg:tags":[
        "print",
        "medium"
    ],
    "wof:name":"News-Democrat",
    "wof:placetype":"venue"
},
  "geometry": {"coordinates":[-89.987801,38.669399],"type":"Point"}
}