{
  "type": "Feature",
  "properties": {
    "addr:full":"20559 N Clarice Ave Lincolnshire IL 60069",
    "addr:housenumber":"20559",
    "addr:postcode":"60069",
    "addr:street":"N Clarice Ave",
    "iso:country":"US",
    "sg:address":"20559 N Clarice Ave",
    "sg:city":"Lincolnshire",
    "sg:classifiers":[
        {
            "category":"Mining & Drilling",
            "type":"Manufacturing & Wholesale Goods"
        }
    ],
    "sg:phone":"+1 847 537 7038",
    "sg:postcode":"60069",
    "sg:province":"IL",
    "sg:tags":[
        "field",
        "oil"
    ],
    "wof:name":"Pro-Technics Intl Inc",
    "wof:placetype":"venue"
},
  "geometry": {"coordinates":[-87.946968,42.161962],"type":"Point"}
}