{
  "type": "Feature",
  "properties": {
    "addr:full":"207 E Westminster Ave Lake Forest IL 60045",
    "addr:housenumber":"207",
    "addr:postcode":"60045",
    "addr:street":"E Westminster Ave",
    "iso:country":"US",
    "sg:address":"207 E Westminster Ave",
    "sg:city":"Lake Forest",
    "sg:classifiers":[
        {
            "category":"Shopping",
            "subcategory":"Used Merchandise",
            "type":"Retail Goods"
        }
    ],
    "sg:phone":"+1 847 295 6071",
    "sg:postcode":"60045",
    "sg:province":"IL",
    "sg:tags":[
        "antique"
    ],
    "wof:name":"Samlesbury Hall",
    "wof:placetype":"venue"
},
  "geometry": {"coordinates":[-87.842646,42.2529],"type":"Point"}
}