{
  "type": "Feature",
  "properties": {
    "iso:country":"US",
    "sg:address":"2405 Clarence Ave",
    "sg:city":"Berwyn",
    "sg:classifiers":[
        {
            "category":"Social Services",
            "subcategory":"Child Care",
            "type":"Services"
        }
    ],
    "sg:phone":"+1 708 484 1137",
    "sg:postcode":"60402",
    "sg:province":"IL",
    "sg:tags":[
        "day"
    ],
    "wof:name":"Tinas Daycare",
    "wof:placetype":"venue"
},
  "geometry": {"coordinates":[-87.789441,41.845217],"type":"Point"}
}