{
  "type": "Feature",
  "properties": {
    "iso:country":"US",
    "sg:address":"602 W University Ave",
    "sg:city":"Urbana",
    "sg:classifiers":[
        {
            "category":"Health Services",
            "subcategory":"Doctor",
            "type":"Services"
        },
        {
            "category":"Health Services",
            "subcategory":"Hospital",
            "type":"Services"
        }
    ],
    "sg:phone":"+1 217 383 3313",
    "sg:postcode":"61801",
    "sg:province":"IL",
    "wof:name":"Thomas James H MD",
    "wof:placetype":"venue"
},
  "geometry": {"coordinates":[-88.214699,40.116199],"type":"Point"}
}