{
  "type": "Feature",
  "properties": {
    "iso:country":"US",
    "sg:address":"1440 W 34th St",
    "sg:city":"Chicago",
    "sg:classifiers":[
        {
            "category":"Place Of Worship",
            "subcategory":"Church",
            "type":"Public Place"
        },
        {
            "category":"Place Of Worship",
            "type":"Public Place"
        }
    ],
    "sg:phone":"+1 773 376 7620",
    "sg:postcode":"60608",
    "sg:province":"IL",
    "sg:tags":[
        "churches-methodist"
    ],
    "wof:name":"ACME Refining",
    "wof:placetype":"venue"
},
  "geometry": {"coordinates":[-87.660853,41.83239],"type":"Point"}
}