{
  "type": "Feature",
  "properties": {
    "iso:country":"US",
    "sg:address":"201 N Goodwin Ave",
    "sg:city":"Urbana",
    "sg:classifiers":[
        {
            "category":"Coffee & Tea",
            "type":"Food & Drink"
        }
    ],
    "sg:phone":"+1 217 344 3296",
    "sg:postcode":"61801",
    "sg:province":"IL",
    "wof:name":"Bevande Coffee",
    "wof:placetype":"venue"
},
  "geometry": {"coordinates":[-88.223992,40.113548],"type":"Point"}
}