{
  "type": "Feature",
  "properties": {
    "iso:country":"US",
    "sg:address":"740 Northwest Hwy",
    "sg:city":"Cary",
    "sg:classifiers":[
        {
            "category":"Restaurant",
            "type":"Food & Drink"
        }
    ],
    "sg:menulink":"http://www.allmenus.com/il/algonquin/180960-wendys/menu/",
    "sg:phone":"+1 847 639 4543",
    "sg:postcode":"60013",
    "sg:province":"IL",
    "sg:tags":[
        "burger",
        "american",
        "soup"
    ],
    "wof:name":"Wendy's",
    "wof:placetype":"venue"
},
  "geometry": {"coordinates":[-88.256998,42.21744],"type":"Point"}
}