{
  "type": "Feature",
  "properties": {
    "addr:full":"9618 Holdener Pl Fairview Heights IL 62208",
    "addr:housenumber":"9618",
    "addr:postcode":"62208",
    "addr:street":"Holdener Pl",
    "iso:country":"US",
    "sg:address":"9618 Holdener Pl",
    "sg:city":"Fairview Heights",
    "sg:classifiers":[
        {
            "category":"Freight",
            "type":"Transportation"
        }
    ],
    "sg:phone":"+1 618 397 4192",
    "sg:postcode":"62208",
    "sg:province":"IL",
    "sg:tags":[
        "operator",
        "local",
        "trucking"
    ],
    "wof:name":"Deisner",
    "wof:placetype":"venue"
},
  "geometry": {"coordinates":[-90.037431,38.583864],"type":"Point"}
}