{
  "type": "Feature",
  "properties": {
    "iso:country":"US",
    "sg:address":"11524 N Co Rd 2040 E",
    "sg:city":"Ashmore",
    "sg:phone":"+1 217 345 3081",
    "sg:postcode":"61912",
    "sg:province":"IL",
    "sg:tags":[
        "farm",
        "corn",
        "soybean"
    ],
    "wof:name":"Paul Board",
    "wof:placetype":"venue"
},
  "geometry": {"coordinates":[-88.094747,39.532846],"type":"Point"}
}