{
  "type": "Feature",
  "properties": {
    "addr:full":"800 N Prairie St Batavia IL 60510",
    "addr:housenumber":"800",
    "addr:postcode":"60510",
    "addr:street":"N Prairie St",
    "iso:country":"US",
    "sg:address":"800 N Prairie St",
    "sg:city":"Batavia",
    "sg:classifiers":[
        {
            "category":"Education",
            "subcategory":"School",
            "type":"Public Place"
        }
    ],
    "sg:phone":"+1 630 879 4641",
    "sg:postcode":"60510",
    "sg:province":"IL",
    "wof:name":"Louise White Elementary School",
    "wof:placetype":"venue"
},
  "geometry": {"coordinates":[-88.30157,41.86069],"type":"Point"}
}