{
  "type": "Feature",
  "properties": {
    "iso:country":"US",
    "sg:address":"28 Marsh Ln",
    "sg:city":"Batavia",
    "sg:classifiers":[
        {
            "category":"Professional",
            "subcategory":"Business Services",
            "type":"Services"
        }
    ],
    "sg:phone":"+1 630 879 6131",
    "sg:postcode":"60510",
    "sg:province":"IL",
    "sg:tags":[
        "interior",
        "consultant",
        "design",
        "decorator"
    ],
    "wof:name":"R E Design Consultant",
    "wof:placetype":"venue"
},
  "geometry": {"coordinates":[-88.348468,41.851177],"type":"Point"}
}