{
  "type": "Feature",
  "properties": {
    "iso:country":"US",
    "sg:address":"301 Oak St Ste 2-27",
    "sg:city":"Quincy",
    "sg:classifiers":[
        {
            "category":"Professional",
            "subcategory":"Business Services",
            "type":"Services"
        }
    ],
    "sg:phone":"+1 217 223 5636",
    "sg:postcode":"62301",
    "sg:province":"IL",
    "sg:tags":[
        "consultant",
        "coach"
    ],
    "wof:name":"M R Turner",
    "wof:placetype":"venue"
},
  "geometry": {"coordinates":[-91.411659,39.938301],"type":"Point"}
}