{
  "type": "Feature",
  "properties": {
    "iso:country":"US",
    "sg:address":"4230 Harrison Ave",
    "sg:city":"Rockford",
    "sg:classifiers":[
        {
            "category":"Shopping",
            "subcategory":"Beauty & Cosmetics",
            "type":"Retail Goods"
        }
    ],
    "sg:phone":"+1   ",
    "sg:postcode":"61108",
    "sg:province":"IL",
    "sg:tags":[
        "merchandise"
    ],
    "wof:name":"Heavenly Healing Bath & Body",
    "wof:placetype":"venue"
},
  "geometry": {"coordinates":[-89.029257,42.238373],"type":"Point"}
}