{
  "type": "Feature",
  "properties": {
    "iso:country":"US",
    "sg:address":"6679 N Avondale Ave",
    "sg:city":"Chicago",
    "sg:classifiers":[
        {
            "category":"Recreation",
            "subcategory":"Playground",
            "type":"Entertainment"
        }
    ],
    "sg:postcode":"60631",
    "sg:province":"IL",
    "sg:website":"www.chicagoparkdistrict.com/inde...",
    "wof:name":"Monument Park",
    "wof:placetype":"venue"
},
  "geometry": {"coordinates":[-87.81801,42.001438],"type":"Point"}
}