{
  "type": "Feature",
  "properties": {
    "iso:country":"US",
    "sg:address":"156 N Jefferson St Ste 301",
    "sg:city":"Chicago",
    "sg:classifiers":[
        {
            "category":"Communications",
            "type":"Services"
        }
    ],
    "sg:phone":"+1 312 267 0066",
    "sg:postcode":"60661",
    "sg:province":"IL",
    "sg:tags":[
        "web",
        "design"
    ],
    "sg:website":"www.walkersands.com",
    "wof:name":"Walker Sands Communications",
    "wof:placetype":"venue"
},
  "geometry": {"coordinates":[-87.643754,41.885004],"type":"Point"}
}