{
  "type": "Feature",
  "properties": {
    "addr:full":"2637 W 95th St Evergreen Park IL 60805",
    "addr:housenumber":"2637",
    "addr:postcode":"60805",
    "addr:street":"W 95Th St",
    "iso:country":"US",
    "sg:address":"2637 W 95th St",
    "sg:city":"Evergreen Park",
    "sg:classifiers":[
        {
            "category":"Shopping",
            "subcategory":"Clothing, Apparel, & Fashions",
            "type":"Retail Goods"
        }
    ],
    "sg:phone":"+1 708 425 8783",
    "sg:postcode":"60805",
    "sg:province":"IL",
    "sg:tags":[
        "furnishing"
    ],
    "wof:name":"Casual Male Big & Tall",
    "wof:placetype":"venue"
},
  "geometry": {"coordinates":[-87.69026700000001,41.720783],"type":"Point"}
}