{
  "type": "Feature",
  "properties": {
    "iso:country":"US",
    "sg:address":"610 Robert York Ave",
    "sg:city":"Deerfield",
    "sg:classifiers":[
        {
            "category":"Insurance",
            "subcategory":"Insurance Agent",
            "type":"Services"
        }
    ],
    "sg:phone":"+1 847 267 0088",
    "sg:postcode":"60015",
    "sg:province":"IL",
    "sg:tags":[
        "consultant"
    ],
    "wof:name":"Stern Insurance Consultants",
    "wof:placetype":"venue"
},
  "geometry": {"coordinates":[-87.84683800000001,42.163716],"type":"Point"}
}