{
  "type": "Feature",
  "properties": {
    "addr:full":"606 W le Fevre Rd Sterling IL 61081",
    "addr:housenumber":"606",
    "addr:postcode":"61081",
    "addr:street":"W Le Fevre Rd",
    "iso:country":"US",
    "sg:address":"606 W le Fevre Rd",
    "sg:city":"Sterling",
    "sg:classifiers":[
        {
            "category":"Real Estate",
            "subcategory":"Real Estate Services",
            "type":"Services"
        },
        {
            "category":"Real Estate",
            "subcategory":"Real Estate Operator",
            "type":"Services"
        }
    ],
    "sg:phone":"+1 815 626 1431",
    "sg:postcode":"61081",
    "sg:province":"IL",
    "sg:tags":[
        "vacancy",
        "apartment",
        "rental",
        "finder",
        "listing"
    ],
    "wof:name":"Sterling Manor Apartments",
    "wof:placetype":"venue"
},
  "geometry": {"coordinates":[-89.70364499999999,41.80154],"type":"Point"}
}