{
  "type": "Feature",
  "properties": {
    "addr:full":"13832 S Magnolia Dr Plainfield IL 60544",
    "addr:housenumber":"13832",
    "addr:postcode":"60544",
    "addr:street":"S Magnolia Dr",
    "iso:country":"US",
    "sg:address":"13832 S Magnolia Dr",
    "sg:city":"Plainfield",
    "sg:classifiers":[
        {
            "category":"Real Estate",
            "subcategory":"Real Estate Services",
            "type":"Services"
        },
        {
            "category":"Real Estate",
            "subcategory":"Real Estate Agent",
            "type":"Services"
        }
    ],
    "sg:phone":"+1 815 886 2422",
    "sg:postcode":"60544",
    "sg:province":"IL",
    "sg:tags":[
        "buyer",
        "management",
        "broker"
    ],
    "wof:name":"A S A P Realty",
    "wof:placetype":"venue"
},
  "geometry": {"coordinates":[-88.126751,41.632392],"type":"Point"}
}