{
  "type": "Feature",
  "properties": {
    "iso:country":"US",
    "sg:address":"286 Villa St",
    "sg:city":"Elgin",
    "sg:classifiers":[
        {
            "category":"Wholesale",
            "subcategory":"Groceries",
            "type":"Manufacturing & Wholesale Goods"
        }
    ],
    "sg:phone":"+1 787 868 8252",
    "sg:postcode":"60120",
    "sg:province":"IL",
    "sg:tags":[
        "trade"
    ],
    "wof:name":"World Exportors",
    "wof:placetype":"venue"
},
  "geometry": {"coordinates":[-88.274914,42.032642],"type":"Point"}
}