{
  "type": "Feature",
  "properties": {
    "iso:country":"US",
    "sg:address":"1099 W Wood St Ste A",
    "sg:city":"Decatur",
    "sg:phone":"+1 217 429 7000",
    "sg:postcode":"62522",
    "sg:province":"IL",
    "sg:website":"http://www.tuscanysteakandpasta.com",
    "wof:name":"Tuscany Steak Pasta House",
    "wof:placetype":"venue"
},
  "geometry": {"coordinates":[-88.972702,39.840111],"type":"Point"}
}