{
  "type": "Feature",
  "properties": {
    "addr:full":"8958 S Euclid Ave Chicago IL 60617",
    "addr:housenumber":"8958",
    "addr:postcode":"60617",
    "addr:street":"S Euclid Ave",
    "iso:country":"US",
    "sg:address":"8958 S Euclid Ave",
    "sg:city":"Chicago",
    "sg:classifiers":[
        {
            "category":"Communications",
            "type":"Services"
        }
    ],
    "sg:phone":"+1 773 721 6350",
    "sg:postcode":"60617",
    "sg:province":"IL",
    "sg:tags":[
        "consultant"
    ],
    "wof:name":"Telstar Communications Consultants",
    "wof:placetype":"venue"
},
  "geometry": {"coordinates":[-87.576798,41.732288],"type":"Point"}
}