{
  "type": "Feature",
  "properties": {
    "addr:full":"150 E Brookmont Blvd Kankakee IL 60901",
    "addr:housenumber":"150",
    "addr:postcode":"60901",
    "addr:street":"E Brookmont Blvd",
    "iso:country":"US",
    "sg:address":"150 E Brookmont Blvd",
    "sg:city":"Kankakee",
    "sg:classifiers":[
        {
            "category":"Restaurant",
            "type":"Food & Drink"
        }
    ],
    "sg:phone":"+1 815 932 3849",
    "sg:postcode":"60901",
    "sg:province":"IL",
    "sg:tags":[
        "banquet",
        "rooms"
    ],
    "wof:name":"Martinez Convention Ctr",
    "wof:placetype":"venue"
},
  "geometry": {"coordinates":[-87.86177600000001,41.135346],"type":"Point"}
}