{
  "type": "Feature",
  "properties": {
    "iso:country":"US",
    "sg:address":"8421 Mc Vicker Ave",
    "sg:city":"Morton Grove",
    "sg:classifiers":[
        {
            "category":"Professional",
            "subcategory":"Computer Services",
            "type":"Services"
        }
    ],
    "sg:phone":"+1 773 882 6577",
    "sg:postcode":"60053",
    "sg:province":"IL",
    "sg:tags":[
        "related"
    ],
    "wof:name":"Jenny Pathieu",
    "wof:placetype":"venue"
},
  "geometry": {"coordinates":[-87.777407,42.035359],"type":"Point"}
}