{
  "type": "Feature",
  "properties": {
    "iso:country":"US",
    "sg:address":"8504 S 77th Ave",
    "sg:city":"Bridgeview",
    "sg:classifiers":[
        {
            "category":"Building & Trades",
            "subcategory":"Electrical",
            "type":"Services"
        }
    ],
    "sg:phone":"+1 773 734 1716",
    "sg:postcode":"60455",
    "sg:province":"IL",
    "sg:tags":[
        "electric",
        "contractor"
    ],
    "wof:name":"Electrical Trenching",
    "wof:placetype":"venue"
},
  "geometry": {"coordinates":[-87.811426,41.735146],"type":"Point"}
}