{
  "type": "Feature",
  "properties": {
    "addr:full":"733 S Wells St Chicago IL 60607",
    "addr:housenumber":"733",
    "addr:postcode":"60607",
    "addr:street":"S Wells St",
    "iso:country":"US",
    "sg:address":"733 S Wells St",
    "sg:city":"Chicago",
    "sg:classifiers":[
        {
            "category":"Personal",
            "subcategory":"Massage",
            "type":"Services"
        },
        {
            "category":"Health Services",
            "subcategory":"Clinic",
            "type":"Services"
        },
        {
            "category":"Health Services",
            "subcategory":"Chiropractor",
            "type":"Services"
        }
    ],
    "sg:phone":"+1 312 765 0411",
    "sg:postcode":"60607",
    "sg:province":"IL",
    "sg:tags":[
        "loss",
        "weight"
    ],
    "sg:website":"www.properbalancehealthcare.com",
    "wof:name":"Proper Balance Healthcare",
    "wof:placetype":"venue"
},
  "geometry": {"coordinates":[-87.63360900000001,41.874426],"type":"Point"}
}