{
  "type": "Feature",
  "properties": {
    "addr:full":"909 N 6th St Chillicothe IL 61523",
    "addr:housenumber":"909",
    "addr:postcode":"61523",
    "addr:street":"N 6Th St",
    "iso:country":"US",
    "sg:address":"909 N 6th St",
    "sg:city":"Chillicothe",
    "sg:classifiers":[
        {
            "category":"Professional",
            "subcategory":"Business Services",
            "type":"Services"
        }
    ],
    "sg:phone":"+1 309 274 5777",
    "sg:postcode":"61523",
    "sg:province":"IL",
    "wof:name":"Owens Design Group Ltd",
    "wof:placetype":"venue"
},
  "geometry": {"coordinates":[-89.49091300000001,40.918472],"type":"Point"}
}