{
  "type": "Feature",
  "properties": {
    "addr:full":"8200 Christiana Ave Skokie IL 60076",
    "addr:housenumber":"8200",
    "addr:postcode":"60076",
    "addr:street":"Christiana Ave",
    "iso:country":"US",
    "sg:address":"8200 Christiana Ave",
    "sg:city":"Skokie",
    "sg:classifiers":[
        {
            "category":"Building & Trades",
            "subcategory":"Construction",
            "type":"Services"
        }
    ],
    "sg:phone":"+1 847 568 1420",
    "sg:postcode":"60076",
    "sg:province":"IL",
    "sg:tags":[
        "house"
    ],
    "wof:name":"Meyer & Meyer Inc",
    "wof:placetype":"venue"
},
  "geometry": {"coordinates":[-87.71232500000001,42.031841],"type":"Point"}
}