{
  "type": "Feature",
  "properties": {
    "addr:full":"500 W Anthony Dr Urbana IL 61802",
    "addr:housenumber":"500",
    "addr:postcode":"61802",
    "addr:street":"W Anthony Dr",
    "iso:country":"US",
    "sg:address":"500 W Anthony Dr",
    "sg:city":"Urbana",
    "sg:classifiers":[
        {
            "category":"Building & Trades",
            "subcategory":"Equipment Rental",
            "type":"Services"
        }
    ],
    "sg:phone":"+1 217 328 2000",
    "sg:postcode":"61802",
    "sg:province":"IL",
    "sg:tags":[
        "leasing"
    ],
    "wof:name":"Safety-Kleen",
    "wof:placetype":"venue"
},
  "geometry": {"coordinates":[-88.21416000000001,40.135418],"type":"Point"}
}