{
  "type": "Feature",
  "properties": {
    "iso:country":"US",
    "sg:address":"3100 S Riverside Dr",
    "sg:city":"Beloit",
    "sg:classifiers":[
        {
            "category":"Home & Garden",
            "subcategory":"Household Appliances",
            "type":"Retail Goods"
        }
    ],
    "sg:phone":"+1 608 365 4920",
    "sg:postcode":"53511",
    "sg:province":"IL",
    "sg:tags":[
        "used",
        "merchandise"
    ],
    "wof:name":"Wahl's Appliance Inc",
    "wof:placetype":"venue"
},
  "geometry": {"coordinates":[-89.038668,42.557394],"type":"Point"}
}