{
  "type": "Feature",
  "properties": {
    "addr:full":"2400 S Wallace St Chicago IL 60616",
    "addr:housenumber":"2400",
    "addr:postcode":"60616",
    "addr:street":"S Wallace St",
    "iso:country":"US",
    "sg:address":"2400 S Wallace St",
    "sg:city":"Chicago",
    "sg:classifiers":[
        {
            "category":"Manufacturing",
            "subcategory":"Metals",
            "type":"Manufacturing & Wholesale Goods"
        }
    ],
    "sg:phone":"+1 312 225 5988",
    "sg:postcode":"60616",
    "sg:province":"IL",
    "sg:tags":[
        "work",
        "iron"
    ],
    "wof:name":"Ping's Iron Work",
    "wof:placetype":"venue"
},
  "geometry": {"coordinates":[-87.642242,41.848919],"type":"Point"}
}