{
  "type": "Feature",
  "properties": {
    "addr:full":"1004 E 9th St Lockport IL 60441",
    "addr:housenumber":"1004",
    "addr:postcode":"60441",
    "addr:street":"E 9Th St",
    "iso:country":"US",
    "sg:address":"1004 E 9th St",
    "sg:city":"Lockport",
    "sg:classifiers":[
        {
            "category":"Autos & Motor Vehicles",
            "subcategory":"Fuel & Gas Station",
            "type":"Retail Goods"
        }
    ],
    "sg:phone":"+1 815 838 2019",
    "sg:postcode":"60441",
    "sg:province":"IL",
    "sg:tags":[
        "oil"
    ],
    "sg:website":"www.speedway.com",
    "wof:name":"Speedway",
    "wof:placetype":"venue"
},
  "geometry": {"coordinates":[-88.038318,41.594604],"type":"Point"}
}