{
  "type": "Feature",
  "properties": {
    "addr:full":"598 Massey Ln Jacksonville IL 62650",
    "addr:housenumber":"598",
    "addr:postcode":"62650",
    "addr:street":"Massey Ln",
    "iso:country":"US",
    "sg:address":"598 Massey Ln",
    "sg:city":"Jacksonville",
    "sg:classifiers":[
        {
            "category":"Personal",
            "subcategory":"Beauty Salon",
            "type":"Services"
        }
    ],
    "sg:phone":"+1 217 245 0700",
    "sg:postcode":"62650",
    "sg:province":"IL",
    "sg:tags":[
        "shop",
        "business"
    ],
    "wof:name":"Makin Waves Pool Co",
    "wof:placetype":"venue"
},
  "geometry": {"coordinates":[-90.26673099999999,39.721782],"type":"Point"}
}