{
  "type": "Feature",
  "properties": {
    "iso:country":"US",
    "sg:address":"1500 Broadway",
    "sg:city":"Rockford",
    "sg:classifiers":[
        {
            "category":"Autos & Motor Vehicles",
            "subcategory":"Automobile Sales",
            "type":"Retail Goods"
        }
    ],
    "sg:phone":"+1   ",
    "sg:postcode":"61104",
    "sg:province":"IL",
    "sg:tags":[
        "used"
    ],
    "wof:name":"D & M Auto",
    "wof:placetype":"venue"
},
  "geometry": {"coordinates":[-89.07276,42.252416],"type":"Point"}
}