{
  "type": "Feature",
  "properties": {
    "iso:country":"US",
    "sg:address":"750 Fountains Pkwy",
    "sg:city":"Fairview Heights",
    "sg:classifiers":[
        {
            "category":"Social Services",
            "subcategory":"Child Care",
            "type":"Services"
        },
        {
            "category":"Education",
            "subcategory":"Preschool",
            "type":"Public Place"
        },
        {
            "category":"Education",
            "subcategory":"School",
            "type":"Public Place"
        }
    ],
    "sg:phone":"+1 618 624 5624",
    "sg:postcode":"62208",
    "sg:province":"IL",
    "sg:tags":[
        "elementary",
        "day"
    ],
    "sg:website":"www.theearlyyearsinc.com",
    "wof:name":"Early Years Inc the",
    "wof:placetype":"venue"
},
  "geometry": {"coordinates":[-89.96835,38.601973],"type":"Point"}
}