{
  "type": "Feature",
  "properties": {
    "addr:full":"3545 Mccormick Ave Brookfield IL 60513",
    "addr:housenumber":"3545",
    "addr:postcode":"60513",
    "addr:street":"Mccormick Ave",
    "iso:country":"US",
    "sg:address":"3545 Mccormick Ave",
    "sg:city":"Brookfield",
    "sg:classifiers":[
        {
            "category":"Place Of Worship",
            "type":"Public Place"
        }
    ],
    "sg:phone":"+1 708 485 5210",
    "sg:postcode":"60513",
    "sg:province":"IL",
    "sg:tags":[
        "church"
    ],
    "wof:name":"First Presbyterian Church of Brookfield",
    "wof:placetype":"venue"
},
  "geometry": {"coordinates":[-87.836872,41.827068],"type":"Point"}
}