{
  "type": "Feature",
  "properties": {
    "addr:full":"16335 N Co Rd 1800E Havana IL 62644",
    "addr:housenumber":"16335",
    "addr:postcode":"62644",
    "addr:street":"N Co Rd",
    "iso:country":"US",
    "sg:address":"16335 N Co Rd 1800E",
    "sg:city":"Havana",
    "sg:classifiers":[
        {
            "category":"Building & Trades",
            "subcategory":"Construction",
            "type":"Services"
        }
    ],
    "sg:phone":"+1 309 543 3640",
    "sg:postcode":"62644",
    "sg:province":"IL",
    "sg:tags":[
        "carpentry",
        "contractor"
    ],
    "wof:name":"Handcrafted Toys & Casework",
    "wof:placetype":"venue"
},
  "geometry": {"coordinates":[-90.01801500000001,40.296218],"type":"Point"}
}