{
  "type": "Feature",
  "properties": {
    "iso:country":"US",
    "sg:address":"16091 N 850th St",
    "sg:city":"Shumway",
    "sg:classifiers":[
        {
            "category":"Social Services",
            "subcategory":"Child Care",
            "type":"Services"
        }
    ],
    "sg:phone":"+1 217 868 5263",
    "sg:postcode":"62461",
    "sg:province":"IL",
    "sg:tags":[
        "day"
    ],
    "wof:name":"Lisa L Holste",
    "wof:placetype":"venue"
},
  "geometry": {"coordinates":[-88.642256,39.151742],"type":"Point"}
}