{
  "type": "Feature",
  "properties": {
    "addr:full":"328 S Green Bay Rd Waukegan IL 60085",
    "addr:housenumber":"328",
    "addr:postcode":"60085",
    "addr:street":"S Green Bay Rd",
    "iso:country":"US",
    "sg:address":"328 S Green Bay Rd",
    "sg:city":"Waukegan",
    "sg:classifiers":[
        {
            "category":"Insurance",
            "subcategory":"Insurance Agent",
            "type":"Services"
        }
    ],
    "sg:phone":"+1 847 263 0600",
    "sg:postcode":"60085",
    "sg:province":"IL",
    "wof:name":"Northwest Insurance Network Inc",
    "wof:placetype":"venue"
},
  "geometry": {"coordinates":[-87.873772,42.353889],"type":"Point"}
}