{
  "type": "Feature",
  "properties": {
    "addr:full":"139 N Vermilion St Danville IL 61832",
    "addr:housenumber":"139",
    "addr:postcode":"61832",
    "addr:street":"N Vermilion St",
    "iso:country":"US",
    "sg:address":"139 N Vermilion St",
    "sg:city":"Danville",
    "sg:classifiers":[
        {
            "category":"Health Services",
            "subcategory":"Doctor",
            "type":"Services"
        }
    ],
    "sg:phone":"+1 217 446 7438",
    "sg:postcode":"61832",
    "sg:province":"IL",
    "sg:tags":[
        "dentist"
    ],
    "wof:name":"Mary Ellen Grilly",
    "wof:placetype":"venue"
},
  "geometry": {"coordinates":[-87.62996699999999,40.127068],"type":"Point"}
}