{
  "type": "Feature",
  "properties": {
    "addr:full":"1626 E Myrtle St Canton IL 61520",
    "addr:housenumber":"1626",
    "addr:postcode":"61520",
    "addr:street":"E Myrtle St",
    "iso:country":"US",
    "sg:address":"1626 E Myrtle St",
    "sg:city":"Canton",
    "sg:classifiers":[
        {
            "category":"Real Estate",
            "subcategory":"Real Estate Operator",
            "type":"Services"
        }
    ],
    "sg:phone":"+1 309 647 3211",
    "sg:postcode":"61520",
    "sg:province":"IL",
    "sg:tags":[
        "building",
        "apartment"
    ],
    "wof:name":"Village Square Apartments",
    "wof:placetype":"venue"
},
  "geometry": {"coordinates":[-90.007773,40.564436],"type":"Point"}
}