{
  "type": "Feature",
  "properties": {
    "addr:full":"17883 E Manito Rd Havana IL 62644",
    "addr:housenumber":"17883",
    "addr:postcode":"62644",
    "addr:street":"E Manito Rd",
    "iso:country":"US",
    "sg:address":"17883 E Manito Rd",
    "sg:city":"Havana",
    "sg:phone":"+1 309 543 2798",
    "sg:postcode":"62644",
    "sg:province":"IL",
    "sg:tags":[
        "farm",
        "corn",
        "wheat",
        "soybean"
    ],
    "wof:name":"Roat John",
    "wof:placetype":"venue"
},
  "geometry": {"coordinates":[-90.039895,40.319978],"type":"Point"}
}