{
  "type": "Feature",
  "properties": {
    "iso:country":"US",
    "sg:address":"8854 N Milwaukee Ave",
    "sg:city":"Niles",
    "sg:classifiers":[
        {
            "category":"Personal",
            "subcategory":"Nail Salon",
            "type":"Services"
        }
    ],
    "sg:phone":"+1 847 827 6880",
    "sg:postcode":"60714",
    "sg:province":"IL",
    "wof:name":"Nails By Lana",
    "wof:placetype":"venue"
},
  "geometry": {"coordinates":[-87.827663,42.041663],"type":"Point"}
}