{
  "type": "Feature",
  "properties": {
    "iso:country":"US",
    "sg:address":"3100 Dundee Rd",
    "sg:city":"Northbrook",
    "sg:classifiers":[
        {
            "category":"Real Estate",
            "subcategory":"Real Estate Services",
            "type":"Services"
        },
        {
            "category":"Real Estate",
            "subcategory":"Real Estate Agent",
            "type":"Services"
        }
    ],
    "sg:phone":"+1 847 205 4488",
    "sg:postcode":"60062",
    "sg:province":"IL",
    "sg:tags":[
        "management"
    ],
    "wof:name":"Barry J. Bass Real Estate",
    "wof:placetype":"venue"
},
  "geometry": {"coordinates":[-87.856347,42.138353],"type":"Point"}
}