{
  "type": "Feature",
  "properties": {
    "iso:country":"US",
    "sg:address":"2520 Veterans Pkwy",
    "sg:city":"Vandalia",
    "sg:classifiers":[
        {
            "category":"Retail",
            "subcategory":"Auto Repair",
            "type":"Services"
        }
    ],
    "sg:phone":"+1 618 283 0949",
    "sg:postcode":"62471",
    "sg:province":"IL",
    "sg:tags":[
        "repairing",
        "automobile"
    ],
    "wof:name":"Mc Dowell's Svc",
    "wof:placetype":"venue"
},
  "geometry": {"coordinates":[-89.12389,38.973223],"type":"Point"}
}