{
  "type": "Feature",
  "properties": {
    "iso:country":"US",
    "sg:address":"1270 E Walnut St",
    "sg:city":"Carbondale",
    "sg:phone":"+1 618 457 8779",
    "sg:postcode":"62901",
    "sg:province":"IL",
    "sg:tags":[
        "farm",
        "corn",
        "soybean"
    ],
    "wof:name":"Rendleman John",
    "wof:placetype":"venue"
},
  "geometry": {"coordinates":[-89.193201,37.726995],"type":"Point"}
}