{
  "type": "Feature",
  "properties": {
    "iso:country":"US",
    "sg:address":"670 W 5th Ave",
    "sg:city":"Naperville",
    "sg:classifiers":[
        {
            "category":"Retail",
            "subcategory":"Auto Repair",
            "type":"Services"
        }
    ],
    "sg:phone":"+1 630 708 2704",
    "sg:postcode":"60563",
    "sg:province":"IL",
    "sg:website":"http://www.nelsonsautorepair.com/",
    "wof:name":"Nelson's Services Inc",
    "wof:placetype":"venue"
},
  "geometry": {"coordinates":[-88.160061,41.780843],"type":"Point"}
}