{
  "type": "Feature",
  "properties": {
    "addr:full":"901 Peoria St Washington IL 61536",
    "addr:housenumber":"901",
    "addr:postcode":"61536",
    "addr:street":"Peoria St",
    "iso:country":"US",
    "sg:address":"901 Peoria St",
    "sg:city":"Washington",
    "sg:classifiers":[
        {
            "category":"Personal",
            "subcategory":"Beauty Salon",
            "type":"Services"
        }
    ],
    "sg:phone":"+1 309 444 2875",
    "sg:postcode":"61536",
    "sg:province":"IL",
    "sg:tags":[
        "shop"
    ],
    "wof:name":"Colonial Beauty Salon",
    "wof:placetype":"venue"
},
  "geometry": {"coordinates":[-89.79570699999999,40.694141],"type":"Point"}
}