{
  "type": "Feature",
  "properties": {
    "iso:country":"US",
    "sg:address":"215 W Washington St",
    "sg:city":"Oregon",
    "sg:classifiers":[
        {
            "category":"Community Center",
            "subcategory":"Senior",
            "type":"Public Place"
        },
        {
            "category":"Social Services",
            "subcategory":"Adult Care",
            "type":"Services"
        }
    ],
    "sg:phone":"+1 815 732 3252",
    "sg:postcode":"61061",
    "sg:province":"IL",
    "sg:tags":[
        "counseling",
        "citizen"
    ],
    "wof:name":"Rockriver Center",
    "wof:placetype":"venue"
},
  "geometry": {"coordinates":[-89.330178,42.014545],"type":"Point"}
}