{
  "type": "Feature",
  "properties": {
    "iso:country":"US",
    "sg:address":"4320 Lawndale Ave",
    "sg:city":"Lyons",
    "sg:classifiers":[
        {
            "category":"Food & Beverages",
            "subcategory":"Ethnic Foods",
            "type":"Retail Goods"
        }
    ],
    "sg:phone":"+1 708 442 6388",
    "sg:postcode":"60534",
    "sg:province":"IL",
    "sg:website":"www.smilgadumplings.com",
    "wof:name":"Smilga Dumplings",
    "wof:placetype":"venue"
},
  "geometry": {"coordinates":[-87.825971,41.81248],"type":"Point"}
}