{
  "type": "Feature",
  "properties": {
    "iso:country":"US",
    "sg:address":"226 W Hubbard St",
    "sg:city":"Chicago",
    "sg:classifiers":[
        {
            "category":"Parking",
            "subcategory":"Garage",
            "type":"Transportation"
        }
    ],
    "sg:phone":"+1 312 440 3800",
    "sg:postcode":"60654",
    "sg:province":"IL",
    "sg:tags":[
        "lot"
    ],
    "wof:name":"M C P Partners",
    "wof:placetype":"venue"
},
  "geometry": {"coordinates":[-87.635015,41.88998],"type":"Point"}
}