{
  "type": "Feature",
  "properties": {
    "iso:country":"US",
    "sg:address":"2344 W Fullerton Ave",
    "sg:city":"Chicago",
    "sg:classifiers":[
        {
            "category":"Professional",
            "subcategory":"Computer Services",
            "type":"Services"
        }
    ],
    "sg:phone":"+1 773 276 9600",
    "sg:postcode":"60647",
    "sg:province":"IL",
    "sg:tags":[
        "repair",
        "datum"
    ],
    "sg:website":"bluewavenet.com",
    "wof:name":"Blue Wave Networks",
    "wof:placetype":"venue"
},
  "geometry": {"coordinates":[-87.68628699999999,41.925037],"type":"Point"}
}