{
  "type": "Feature",
  "properties": {
    "iso:country":"US",
    "sg:address":"1163 S Milwaukee Ave",
    "sg:city":"Libertyville",
    "sg:phone":"+1 847 680 9000",
    "sg:postcode":"60048",
    "sg:province":"IL",
    "wof:name":"Xsport Fitness",
    "wof:placetype":"venue"
},
  "geometry": {"coordinates":[-87.949876,42.266223],"type":"Point"}
}