{
  "type": "Feature",
  "properties": {
    "iso:country":"US",
    "sg:address":"117 N Saint Paul St",
    "sg:city":"Spring Valley",
    "sg:classifiers":[
        {
            "category":"Shopping",
            "subcategory":"Clothing, Apparel, & Fashions",
            "type":"Retail Goods"
        }
    ],
    "sg:phone":"+1 815 664 5236",
    "sg:postcode":"61340",
    "sg:province":"IL",
    "wof:name":"Something Different",
    "wof:placetype":"venue"
},
  "geometry": {"coordinates":[-89.251458,41.264872],"type":"Point"}
}