{
  "type": "Feature",
  "properties": {
    "iso:country":"US",
    "sg:address":"908 N Morris Ave",
    "sg:city":"Bloomington",
    "sg:classifiers":[
        {
            "category":"Organizations",
            "subcategory":"Religious Organization",
            "type":"Services"
        }
    ],
    "sg:phone":"+1 309 828 4602",
    "sg:postcode":"61701",
    "sg:province":"IL",
    "wof:name":"Shiloh Missionary Baptist Church",
    "wof:placetype":"venue"
},
  "geometry": {"coordinates":[-89.00682399999999,40.486524],"type":"Point"}
}