{
  "type": "Feature",
  "properties": {
    "addr:full":"205 W 87th St Apt E Chicago IL 60620",
    "addr:housenumber":"205",
    "addr:postcode":"60620",
    "addr:street":"W 87Th St Apt E",
    "iso:country":"US",
    "sg:address":"205 W 87th St Apt E",
    "sg:city":"Chicago",
    "sg:classifiers":[
        {
            "category":"Shopping",
            "subcategory":"Clothing, Apparel, & Fashions",
            "type":"Retail Goods"
        }
    ],
    "sg:phone":"+1 773 783 5196",
    "sg:postcode":"60620",
    "sg:province":"IL",
    "sg:tags":[
        "accessory",
        "clothing",
        "women's"
    ],
    "sg:website":"www.ashleystewart.com",
    "wof:name":"Ashley Stewart",
    "wof:placetype":"venue"
},
  "geometry": {"coordinates":[-87.629119,41.735978],"type":"Point"}
}