{
  "type": "Feature",
  "properties": {
    "addr:full":"175 W North Ave Carol Stream IL 60188",
    "addr:housenumber":"175",
    "addr:postcode":"60188",
    "addr:street":"W North Ave",
    "iso:country":"US",
    "sg:address":"175 W North Ave",
    "sg:city":"Carol Stream",
    "sg:classifiers":[
        {
            "category":"Autos & Motor Vehicles",
            "subcategory":"Automobile Sales",
            "type":"Retail Goods"
        }
    ],
    "sg:phone":"+1 630 682 9200",
    "sg:postcode":"60188",
    "sg:province":"IL",
    "sg:tags":[
        "car"
    ],
    "sg:website":"www.joecottonford.com/site/",
    "wof:name":"Joe Cotton Ford",
    "wof:placetype":"venue"
},
  "geometry": {"coordinates":[-88.123848,41.90543],"type":"Point"}
}