{
  "type": "Feature",
  "properties": {
    "iso:country":"US",
    "sg:address":"7212 88th Ave",
    "sg:city":"Kenosha",
    "sg:classifiers":[
        {
            "category":"Professional",
            "subcategory":"Art Services",
            "type":"Services"
        }
    ],
    "sg:phone":"+1 262 697 9882",
    "sg:postcode":"53142",
    "sg:province":"IL",
    "sg:tags":[
        "photography",
        "commercial"
    ],
    "wof:name":"Fietz & Assoc",
    "wof:placetype":"venue"
},
  "geometry": {"coordinates":[-87.91431300000001,42.568778],"type":"Point"}
}