{
  "type": "Feature",
  "properties": {
    "addr:full":"3033 S Park Ave Herrin IL 62948",
    "addr:housenumber":"3033",
    "addr:postcode":"62948",
    "addr:street":"S Park Ave",
    "iso:country":"US",
    "sg:address":"3033 S Park Ave",
    "sg:city":"Herrin",
    "sg:classifiers":[
        {
            "category":"Shopping",
            "subcategory":"Clothing, Apparel, & Fashions",
            "type":"Retail Goods"
        },
        {
            "category":"Shopping",
            "subcategory":"Party Supplies",
            "type":"Retail Goods"
        }
    ],
    "sg:phone":"+1 618 942 4431",
    "sg:postcode":"62948",
    "sg:province":"IL",
    "sg:tags":[
        "costume"
    ],
    "wof:name":"Party Shop the",
    "wof:placetype":"venue"
},
  "geometry": {"coordinates":[-89.027,37.786301],"type":"Point"}
}