{
  "type": "Feature",
  "properties": {
    "addr:full":"600 Glendale Ave Glendale Heights IL 60137",
    "addr:housenumber":"600",
    "addr:postcode":"60137",
    "addr:street":"Glendale Ave",
    "iso:country":"US",
    "sg:address":"600 Glendale Ave",
    "sg:city":"Glendale Heights",
    "sg:classifiers":[
        {
            "category":"Retail",
            "subcategory":"Auto Repair",
            "type":"Services"
        }
    ],
    "sg:phone":"+1 630 469 9776",
    "sg:postcode":"60137",
    "sg:province":"IL",
    "sg:tags":[
        "exhaust"
    ],
    "wof:name":"Merlins Muffler & Brake",
    "wof:placetype":"venue"
},
  "geometry": {"coordinates":[-88.082781,41.871298],"type":"Point"}
}