{
  "type": "Feature",
  "properties": {
    "iso:country":"US",
    "sg:address":"1000 Orland Park Pl",
    "sg:city":"Orland Park",
    "sg:classifiers":[
        {
            "category":"Shopping",
            "type":"Retail Goods"
        }
    ],
    "sg:phone":"+1 708 873 9673",
    "sg:postcode":"60462",
    "sg:province":"IL",
    "sg:tags":[
        "pet",
        "shop"
    ],
    "sg:website":"www.crabhut.com",
    "wof:name":"Crab Hut",
    "wof:placetype":"venue"
},
  "geometry": {"coordinates":[-87.85210600000001,41.613803],"type":"Point"}
}