{
  "type": "Feature",
  "properties": {
    "addr:full":"3470 N Lake Shore Dr Chicago IL 60657",
    "addr:housenumber":"3470",
    "addr:postcode":"60657",
    "addr:street":"N Lake Shore Dr",
    "iso:country":"US",
    "sg:address":"3470 N Lake Shore Dr",
    "sg:city":"Chicago",
    "sg:classifiers":[
        {
            "category":"Real Estate",
            "subcategory":"Real Estate Agent",
            "type":"Services"
        }
    ],
    "sg:phone":"+1 773 549 9561",
    "sg:postcode":"60657",
    "sg:province":"IL",
    "wof:name":"3470 N Lake Shore Drive Condo",
    "wof:placetype":"venue"
},
  "geometry": {"coordinates":[-87.642107,41.946942],"type":"Point"}
}