{
  "type": "Feature",
  "properties": {
    "iso:country":"US",
    "sg:address":"320 W Oakdale Ave Apt 1602",
    "sg:city":"Chicago",
    "sg:classifiers":[
        {
            "category":"Professional",
            "type":"Services"
        }
    ],
    "sg:phone":"+1 773 296 9202",
    "sg:postcode":"60657",
    "sg:province":"IL",
    "sg:tags":[
        "relocation"
    ],
    "sg:website":"http://www.chicagolandrelocation.com",
    "wof:name":"Access Network Inc",
    "wof:placetype":"venue"
},
  "geometry": {"coordinates":[-87.637242,41.935584],"type":"Point"}
}