{
  "type": "Feature",
  "properties": {
    "iso:country":"US",
    "sg:address":"1280 Parkview Dr",
    "sg:city":"Elgin",
    "sg:classifiers":[
        {
            "category":"Professional",
            "subcategory":"Management & Consulting",
            "type":"Services"
        }
    ],
    "sg:phone":"+1 847 931 7077",
    "sg:postcode":"60123",
    "sg:province":"IL",
    "sg:tags":[
        "consultant",
        "contract",
        "government"
    ],
    "wof:name":"David Joseph & Assiciates",
    "wof:placetype":"venue"
},
  "geometry": {"coordinates":[-88.306031,42.064272],"type":"Point"}
}