{
  "type": "Feature",
  "properties": {
    "iso:country":"US",
    "sg:address":"6101 N Sheridan Rd",
    "sg:city":"Chicago",
    "sg:classifiers":[
        {
            "category":"Wholesale",
            "subcategory":"Groceries",
            "type":"Manufacturing & Wholesale Goods"
        }
    ],
    "sg:phone":"+1 773 761 1480",
    "sg:postcode":"60660",
    "sg:province":"IL",
    "sg:tags":[
        "general"
    ],
    "wof:name":"Criom Corp",
    "wof:placetype":"venue"
},
  "geometry": {"coordinates":[-87.655512,41.994164],"type":"Point"}
}