{
  "type": "Feature",
  "properties": {
    "addr:full":"799 E Roosevelt Rd Glen Ellyn IL 60137",
    "addr:housenumber":"799",
    "addr:postcode":"60137",
    "addr:street":"E Roosevelt Rd",
    "iso:country":"US",
    "sg:address":"799 E Roosevelt Rd",
    "sg:city":"Glen Ellyn",
    "sg:classifiers":[
        {
            "category":"Professional",
            "subcategory":"Management & Consulting",
            "type":"Services"
        }
    ],
    "sg:phone":"+1 630 942 0828",
    "sg:postcode":"60137",
    "sg:province":"IL",
    "sg:tags":[
        "business"
    ],
    "wof:name":"Hayner John Midwest Dev",
    "wof:placetype":"venue"
},
  "geometry": {"coordinates":[-88.05363699999999,41.859412],"type":"Point"}
}