{
  "type": "Feature",
  "properties": {
    "addr:full":"40838 N State Rte 83 Antioch IL 60002",
    "addr:housenumber":"40838",
    "addr:postcode":"60002",
    "addr:street":"N State Rte 83",
    "iso:country":"US",
    "sg:address":"40838 N State Rte 83",
    "sg:city":"Antioch",
    "sg:classifiers":[
        {
            "category":"Retail",
            "subcategory":"Auto Repair",
            "type":"Services"
        }
    ],
    "sg:phone":"+1 847 838 6030",
    "sg:postcode":"60002",
    "sg:province":"IL",
    "sg:tags":[
        "muffler",
        "exhaust",
        "system"
    ],
    "wof:name":"Antioch Mufflers & Brakes",
    "wof:placetype":"venue"
},
  "geometry": {"coordinates":[-88.091756,42.456859],"type":"Point"}
}