{
  "type": "Feature",
  "properties": {
    "iso:country":"US",
    "sg:address":"30W310 Butterfield Rd",
    "sg:city":"Warrenville",
    "sg:classifiers":[
        {
            "category":"Building & Trades",
            "subcategory":"Electrical",
            "type":"Services"
        }
    ],
    "sg:phone":"+1 630 393 9400",
    "sg:postcode":"60555",
    "sg:province":"IL",
    "sg:tags":[
        "industrial",
        "electrician",
        "contractors-commercial",
        "electric"
    ],
    "wof:name":"Amp Rite Electric Company, Inc.",
    "wof:placetype":"venue"
},
  "geometry": {"coordinates":[-88.204437,41.820709],"type":"Point"}
}