{
  "type": "Feature",
  "properties": {
    "addr:full":"921 E Main St Danville IL 61832",
    "addr:housenumber":"921",
    "addr:postcode":"61832",
    "addr:street":"E Main St",
    "iso:country":"US",
    "sg:address":"921 E Main St",
    "sg:city":"Danville",
    "sg:classifiers":[
        {
            "category":"Home & Garden",
            "subcategory":"Household Appliances",
            "type":"Retail Goods"
        }
    ],
    "sg:phone":"+1 217 443 3628",
    "sg:postcode":"61832",
    "sg:province":"IL",
    "sg:tags":[
        "cleaners",
        "vacuum"
    ],
    "wof:name":"Bob Warren's Sweeper Sales",
    "wof:placetype":"venue"
},
  "geometry": {"coordinates":[-87.61031,40.1269],"type":"Point"}
}