{
  "type": "Feature",
  "properties": {
    "iso:country":"US",
    "sg:address":"535 N Evergreen Ave",
    "sg:city":"Elmhurst",
    "sg:classifiers":[
        {
            "category":"Wholesale",
            "subcategory":"Medical Equipment & Supplies",
            "type":"Manufacturing & Wholesale Goods"
        }
    ],
    "sg:phone":"+1 630 530 4011",
    "sg:postcode":"60126",
    "sg:province":"IL",
    "sg:tags":[
        "consul",
        "diagnostic",
        "sales",
        "telecommunication"
    ],
    "wof:name":"Dcsl Group The",
    "wof:placetype":"venue"
},
  "geometry": {"coordinates":[-87.94728499999999,41.913997],"type":"Point"}
}