{
  "type": "Feature",
  "properties": {
    "addr:full":"333 W Taft Dr South Holland IL 60473",
    "addr:housenumber":"333",
    "addr:postcode":"60473",
    "addr:street":"W Taft Dr",
    "iso:country":"US",
    "sg:address":"333 W Taft Dr",
    "sg:city":"South Holland",
    "sg:classifiers":[
        {
            "category":"Manufacturing",
            "subcategory":"Tools & Machinery",
            "type":"Manufacturing & Wholesale Goods"
        }
    ],
    "sg:phone":"+1 708 596 7914",
    "sg:postcode":"60473",
    "sg:province":"IL",
    "sg:tags":[
        "filing"
    ],
    "wof:name":"Archive America",
    "wof:placetype":"venue"
},
  "geometry": {"coordinates":[-87.61825,41.593574],"type":"Point"}
}