{
  "type": "Feature",
  "properties": {
    "iso:country":"US",
    "sg:address":"243 N Highview Ave",
    "sg:city":"Elmhurst",
    "sg:classifiers":[
        {
            "category":"Professional",
            "subcategory":"Computer Services",
            "type":"Services"
        }
    ],
    "sg:phone":"+1 630 279 1417",
    "sg:postcode":"60126",
    "sg:province":"IL",
    "sg:tags":[
        "datum"
    ],
    "wof:name":"Armaritz Business Service",
    "wof:placetype":"venue"
},
  "geometry": {"coordinates":[-87.956077,41.905554],"type":"Point"}
}