{
  "type": "Feature",
  "properties": {
    "iso:country":"US",
    "sg:address":"2024 2nd Ave",
    "sg:city":"Rapids City",
    "sg:classifiers":[
        {
            "category":"Restaurant",
            "type":"Food & Drink"
        }
    ],
    "sg:phone":"+1 309 496 9000",
    "sg:postcode":"61275",
    "sg:province":"IL",
    "wof:name":"Paul Revere's Pizza",
    "wof:placetype":"venue"
},
  "geometry": {"coordinates":[-90.35389000000001,41.578505],"type":"Point"}
}