{
  "type": "Feature",
  "properties": {
    "iso:country":"US",
    "sg:address":"845 Chicago Ave",
    "sg:city":"Evanston",
    "sg:classifiers":[
        {
            "category":"Health Services",
            "subcategory":"Clinic",
            "type":"Services"
        }
    ],
    "sg:phone":"+1 847 475 9662",
    "sg:postcode":"60202",
    "sg:province":"IL",
    "sg:tags":[
        "specialty",
        "outpatient"
    ],
    "wof:name":"Jiang Jing Institute",
    "wof:placetype":"venue"
},
  "geometry": {"coordinates":[-87.679233,42.033573],"type":"Point"}
}