{
  "type": "Feature",
  "properties": {
    "iso:country":"US",
    "sg:address":"807 W State St",
    "sg:city":"O Fallon",
    "sg:classifiers":[
        {
            "category":"Retail",
            "subcategory":"Veterinary Services",
            "type":"Services"
        }
    ],
    "sg:phone":"+1 618 628 1560",
    "sg:postcode":"62269",
    "sg:province":"IL",
    "sg:tags":[
        "veterinarian"
    ],
    "sg:website":"www.ofallonvet.com",
    "wof:name":"All About Pets Veterinary Hospital",
    "wof:placetype":"venue"
},
  "geometry": {"coordinates":[-89.92965,38.592078],"type":"Point"}
}