{
  "type": "Feature",
  "properties": {
    "iso:country":"US",
    "sg:address":"1300 Lawrence Ave",
    "sg:city":"Elgin",
    "sg:phone":"+1 847 495 9135",
    "sg:postcode":"60123",
    "sg:province":"IL",
    "wof:name":"Paul's Family Restaurant",
    "wof:placetype":"venue"
},
  "geometry": {"coordinates":[-88.31073000000001,42.041531],"type":"Point"}
}