{
  "type": "Feature",
  "properties": {
    "addr:full":"4309 S Archer Ave Chicago IL 60632",
    "addr:housenumber":"4309",
    "addr:postcode":"60632",
    "addr:street":"S Archer Ave",
    "iso:country":"US",
    "sg:address":"4309 S Archer Ave",
    "sg:city":"Chicago",
    "sg:classifiers":[
        {
            "category":"Wholesale",
            "subcategory":"Computers",
            "type":"Manufacturing & Wholesale Goods"
        }
    ],
    "sg:phone":"+1 773 317 8278",
    "sg:postcode":"60632",
    "sg:province":"IL",
    "sg:website":"samiliprocomputers.com",
    "wof:name":"Samilipro Computers Inc",
    "wof:placetype":"venue"
},
  "geometry": {"coordinates":[-87.702224,41.815187],"type":"Point"}
}