{
  "type": "Feature",
  "properties": {
    "iso:country":"US",
    "sg:address":"1132 Broadway",
    "sg:city":"Rockford",
    "sg:classifiers":[
        {
            "category":"Shopping",
            "subcategory":"Clothing, Apparel, & Fashions",
            "type":"Retail Goods"
        }
    ],
    "sg:phone":"+1 815 963 1588",
    "sg:postcode":"61104",
    "sg:province":"IL",
    "sg:tags":[
        "lingerie"
    ],
    "wof:name":"LA Coqueta",
    "wof:placetype":"venue"
},
  "geometry": {"coordinates":[-89.07950599999999,42.252439],"type":"Point"}
}