{
  "type": "Feature",
  "properties": {
    "iso:country":"US",
    "sg:address":"507 S Duncan Rd",
    "sg:city":"Champaign",
    "sg:classifiers":[
        {
            "category":"Real Estate",
            "subcategory":"Real Estate Agent",
            "type":"Services"
        }
    ],
    "sg:phone":"+1 217 398 6781",
    "sg:postcode":"61821",
    "sg:province":"IL",
    "wof:name":"Consultant Diversfied",
    "wof:placetype":"venue"
},
  "geometry": {"coordinates":[-88.295523,40.111331],"type":"Point"}
}