{
  "type": "Feature",
  "properties": {
    "addr:full":"2159B S China Pl Chicago IL 60616",
    "addr:housenumber":"2159b",
    "addr:postcode":"60616",
    "addr:street":"S China Pl",
    "iso:country":"US",
    "sg:address":"2159B S China Pl",
    "sg:city":"Chicago",
    "sg:classifiers":[
        {
            "category":"Health Services",
            "subcategory":"Health Practitioner",
            "type":"Services"
        }
    ],
    "sg:phone":"+1 312 674 1988",
    "sg:postcode":"60616",
    "sg:province":"IL",
    "sg:tags":[
        "acupuncture",
        "medicine",
        "alternative"
    ],
    "wof:name":"Sino American Meditech Co",
    "wof:placetype":"venue"
},
  "geometry": {"coordinates":[-87.632937,41.854763],"type":"Point"}
}