{
  "type": "Feature",
  "properties": {
    "addr:full":"7601 S Cicero Ave Chicago IL 60652",
    "addr:housenumber":"7601",
    "addr:postcode":"60652",
    "addr:street":"S Cicero Ave",
    "iso:country":"US",
    "sg:address":"7601 S Cicero Ave",
    "sg:city":"Chicago",
    "sg:classifiers":[
        {
            "category":"Shopping",
            "subcategory":"Department Store",
            "type":"Retail Goods"
        }
    ],
    "sg:phone":"+1 773 284 4200",
    "sg:postcode":"60652",
    "sg:province":"IL",
    "sg:website":"www.sears.com",
    "wof:name":"Sears Roebuck and Co",
    "wof:placetype":"venue"
},
  "geometry": {"coordinates":[-87.74140199999999,41.754299],"type":"Point"}
}