{
  "type": "Feature",
  "properties": {
    "iso:country":"US",
    "sg:address":"3755 W Montrose Ave",
    "sg:city":"Chicago",
    "sg:classifiers":[
        {
            "category":"Food & Beverages",
            "subcategory":"Candy",
            "type":"Retail Goods"
        }
    ],
    "sg:phone":"+1 773 583 1799",
    "sg:postcode":"60618",
    "sg:province":"IL",
    "sg:tags":[
        "store"
    ],
    "wof:name":"Happy Day Food & Candy Store",
    "wof:placetype":"venue"
},
  "geometry": {"coordinates":[-87.722504,41.9608],"type":"Point"}
}