{
  "type": "Feature",
  "properties": {
    "addr:full":"3271 S Harlem Ave Berwyn IL 60402",
    "addr:housenumber":"3271",
    "addr:postcode":"60402",
    "addr:street":"S Harlem Ave",
    "iso:country":"US",
    "sg:address":"3271 S Harlem Ave",
    "sg:city":"Berwyn",
    "sg:classifiers":[
        {
            "category":"Restaurant",
            "type":"Food & Drink"
        }
    ],
    "sg:phone":"+1 708 484 3447",
    "sg:postcode":"60402",
    "sg:province":"IL",
    "sg:website":"conniesberwyn.com/",
    "wof:name":"Connie's Family Restaurant",
    "wof:placetype":"venue"
},
  "geometry": {"coordinates":[-87.802943,41.831533],"type":"Point"}
}