{
  "type": "Feature",
  "properties": {
    "iso:country":"US",
    "sg:address":"459 Spring Cress Ct",
    "sg:city":"West Chicago",
    "sg:classifiers":[
        {
            "category":"Shopping",
            "subcategory":"Hobbies, Toys, & Games",
            "type":"Retail Goods"
        }
    ],
    "sg:phone":"+1 630 876 8697",
    "sg:postcode":"60185",
    "sg:province":"IL",
    "sg:tags":[
        "toy",
        "store"
    ],
    "sg:website":"www.tycs.com",
    "wof:name":"Tycs Enterprises",
    "wof:placetype":"venue"
},
  "geometry": {"coordinates":[-88.196297,41.9048],"type":"Point"}
}