{
  "type": "Feature",
  "properties": {
    "iso:country":"US",
    "sg:address":"4603 Main St",
    "sg:city":"Downers Grove",
    "sg:classifiers":[
        {
            "category":"Social Services",
            "type":"Services"
        }
    ],
    "sg:phone":"+1 630 810 1129",
    "sg:postcode":"60515",
    "sg:province":"IL",
    "wof:name":"Childserv",
    "wof:placetype":"venue"
},
  "geometry": {"coordinates":[-88.010733,41.801933],"type":"Point"}
}