{
  "type": "Feature",
  "properties": {
    "iso:country":"US",
    "sg:address":"2147 Oak Park Ave",
    "sg:city":"Berwyn",
    "sg:classifiers":[
        {
            "category":"Restaurant",
            "type":"Food & Drink"
        }
    ],
    "sg:menulink":"http://www.allmenus.com/il/berwyn/167007-burger-king/menu/",
    "sg:phone":"+1 708 788 3253",
    "sg:postcode":"60402",
    "sg:province":"IL",
    "sg:tags":[
        "burger",
        "american"
    ],
    "wof:name":"Burger King",
    "wof:placetype":"venue"
},
  "geometry": {"coordinates":[-87.79323599999999,41.850909],"type":"Point"}
}