{
  "type": "Feature",
  "properties": {
    "addr:full":"1758 Memorial Dr Calumet City IL 60409",
    "addr:housenumber":"1758",
    "addr:postcode":"60409",
    "addr:street":"Memorial Dr",
    "iso:country":"US",
    "sg:address":"1758 Memorial Dr",
    "sg:city":"Calumet City",
    "sg:classifiers":[
        {
            "category":"Professional",
            "subcategory":"Management & Consulting",
            "type":"Services"
        }
    ],
    "sg:phone":"+1 708 862 3899",
    "sg:postcode":"60409",
    "sg:province":"IL",
    "sg:tags":[
        "construction"
    ],
    "wof:name":"Aubroc Group Inc",
    "wof:placetype":"venue"
},
  "geometry": {"coordinates":[-87.568332,41.619204],"type":"Point"}
}