{
  "type": "Feature",
  "properties": {
    "addr:full":"383 S Lynnville Rd Rochelle IL 61068",
    "addr:housenumber":"383",
    "addr:postcode":"61068",
    "addr:street":"S Lynnville Rd",
    "iso:country":"US",
    "sg:address":"383 S Lynnville Rd",
    "sg:city":"Rochelle",
    "sg:phone":"+1 815 562 5622",
    "sg:postcode":"61068",
    "sg:province":"IL",
    "sg:tags":[
        "farm",
        "corn",
        "soybean"
    ],
    "wof:name":"Huftalin Farms",
    "wof:placetype":"venue"
},
  "geometry": {"coordinates":[-89.02991900000001,42.008892],"type":"Point"}
}