{
  "type": "Feature",
  "properties": {
    "addr:full":"5035 Lincoln Ave Lisle IL 60532",
    "addr:housenumber":"5035",
    "addr:postcode":"60532",
    "addr:street":"Lincoln Ave",
    "iso:country":"US",
    "sg:address":"5035 Lincoln Ave",
    "sg:city":"Lisle",
    "sg:classifiers":[
        {
            "category":"Sports & Exercise",
            "subcategory":"Gym",
            "type":"Entertainment"
        }
    ],
    "sg:phone":"+1 630 810 1049",
    "sg:postcode":"60532",
    "sg:province":"IL",
    "sg:tags":[
        "club",
        "health",
        "studio",
        "gymnasium"
    ],
    "wof:name":"Fitness Experience",
    "wof:placetype":"venue"
},
  "geometry": {"coordinates":[-88.077,41.795456],"type":"Point"}
}