{
  "type": "Feature",
  "properties": {
    "addr:full":"2955 E Division St Coal City IL 60416",
    "addr:housenumber":"2955",
    "addr:postcode":"60416",
    "addr:street":"E Division St",
    "iso:country":"US",
    "sg:address":"2955 E Division St",
    "sg:city":"Coal City",
    "sg:classifiers":[
        {
            "category":"Organizations",
            "subcategory":"Religious Organization",
            "type":"Services"
        }
    ],
    "sg:phone":"+1 815 458 2387",
    "sg:postcode":"60416",
    "sg:province":"IL",
    "wof:name":"Christian Life Assembly God",
    "wof:placetype":"venue"
},
  "geometry": {"coordinates":[-88.24762800000001,41.288499],"type":"Point"}
}