{
  "type": "Feature",
  "properties": {
    "iso:country":"US",
    "sg:address":"2955 E Division St",
    "sg:city":"Coal City",
    "sg:classifiers":[
        {
            "category":"Organizations",
            "subcategory":"Religious Organization",
            "type":"Services"
        }
    ],
    "sg:phone":"+1 815 458 2387",
    "sg:postcode":"60416",
    "sg:province":"IL",
    "wof:name":"Christian Life Assembly God",
    "wof:placetype":"venue"
},
  "geometry": {"coordinates":[-88.247628,41.288499],"type":"Point"}
}