{
  "type": "Feature",
  "properties": {
    "iso:country":"US",
    "sg:address":"3111 Brookview Ln",
    "sg:city":"Palatine",
    "sg:classifiers":[
        {
            "category":"Communications",
            "type":"Services"
        }
    ],
    "sg:phone":"+1 847 303 1112",
    "sg:postcode":"60067",
    "sg:province":"IL",
    "sg:tags":[
        "consultant",
        "engineer"
    ],
    "wof:name":"Telsystems Coomunication, Inc",
    "wof:placetype":"venue"
},
  "geometry": {"coordinates":[-88.052097,42.079546],"type":"Point"}
}