{
  "type": "Feature",
  "properties": {
    "addr:full":"1500 W Hawley St Mundelein IL 60060",
    "addr:housenumber":"1500",
    "addr:postcode":"60060",
    "addr:street":"W Hawley St",
    "iso:country":"US",
    "sg:address":"1500 W Hawley St",
    "sg:city":"Mundelein",
    "sg:classifiers":[
        {
            "category":"Organizations",
            "subcategory":"Religious Organization",
            "type":"Services"
        }
    ],
    "sg:phone":"+1 847 566 8386",
    "sg:postcode":"60060",
    "sg:province":"IL",
    "wof:name":"North Subn Mennonite Church",
    "wof:placetype":"venue"
},
  "geometry": {"coordinates":[-88.022019,42.269888],"type":"Point"}
}