{
  "type": "Feature",
  "properties": {
    "addr:full":"4920 W Irving Park Rd Chicago IL 60641",
    "addr:housenumber":"4920",
    "addr:postcode":"60641",
    "addr:street":"W Irving Park Rd",
    "iso:country":"US",
    "sg:address":"4920 W Irving Park Rd",
    "sg:city":"Chicago",
    "sg:classifiers":[
        {
            "category":"Restaurant",
            "type":"Food & Drink"
        }
    ],
    "sg:phone":"+1 773 202 0999",
    "sg:postcode":"60641",
    "sg:province":"IL",
    "sg:tags":[
        "steakhouse"
    ],
    "sg:website":"www.lastablas.com",
    "wof:name":"Las Tablas Restaurant",
    "wof:placetype":"venue"
},
  "geometry": {"coordinates":[-87.75092100000001,41.953484],"type":"Point"}
}