{
  "type": "Feature",
  "properties": {
    "iso:country":"US",
    "sg:address":"2200 W Jefferson St",
    "sg:city":"Joliet",
    "sg:classifiers":[
        {
            "category":"Autos & Motor Vehicles",
            "subcategory":"Auto Supplies",
            "type":"Retail Goods"
        }
    ],
    "sg:phone":"+1 815 744 1129",
    "sg:postcode":"60435",
    "sg:province":"IL",
    "sg:tags":[
        "automobile",
        "parts"
    ],
    "wof:name":"Murray's Discount Auto Store",
    "wof:placetype":"venue"
},
  "geometry": {"coordinates":[-88.13312,41.52235],"type":"Point"}
}