{
  "type": "Feature",
  "properties": {
    "addr:full":"1254 Ogden Ave Downers Grove IL 60515",
    "addr:housenumber":"1254",
    "addr:postcode":"60515",
    "addr:street":"Ogden Ave",
    "iso:country":"US",
    "sg:address":"1254 Ogden Ave",
    "sg:city":"Downers Grove",
    "sg:classifiers":[
        {
            "category":"Health Services",
            "subcategory":"Doctor",
            "type":"Services"
        }
    ],
    "sg:phone":"+1 630 963 6913",
    "sg:postcode":"60515",
    "sg:province":"IL",
    "sg:tags":[
        "clinic"
    ],
    "wof:name":"Doctors Emergency Medical Ctr",
    "wof:placetype":"venue"
},
  "geometry": {"coordinates":[-88.016982,41.80836],"type":"Point"}
}