{
  "type": "Feature",
  "properties": {
    "iso:country":"US",
    "sg:address":"217 Mcnaughton Park Rd",
    "sg:city":"Pekin",
    "sg:classifiers":[
        {
            "category":"Sports & Exercise",
            "subcategory":"Stables",
            "type":"Entertainment"
        }
    ],
    "sg:phone":"+1 309 382 1268",
    "sg:postcode":"61554",
    "sg:province":"IL",
    "sg:tags":[
        "riding",
        "academy"
    ],
    "sg:website":"http://www.rockinptrails.com",
    "wof:name":"Rockin' P Public Riding Ranch",
    "wof:placetype":"venue"
},
  "geometry": {"coordinates":[-89.59852600000001,40.600765],"type":"Point"}
}