{
  "type": "Feature",
  "properties": {
    "iso:country":"US",
    "sg:address":"108 E Front St",
    "sg:city":"Fisher",
    "sg:classifiers":[
        {
            "category":"Government",
            "subcategory":"Police Station",
            "type":"Public Place"
        }
    ],
    "sg:phone":"+1 217 897 1184",
    "sg:postcode":"61843",
    "sg:province":"IL",
    "sg:tags":[
        "department"
    ],
    "wof:name":"Fisher Police Dept",
    "wof:placetype":"venue"
},
  "geometry": {"coordinates":[-88.348304,40.317822],"type":"Point"}
}