{
  "type": "Feature",
  "properties": {
    "addr:full":"1215 Illinois Ave Jacksonville IL 62650",
    "addr:housenumber":"1215",
    "addr:postcode":"62650",
    "addr:street":"Illinois Ave",
    "iso:country":"US",
    "sg:address":"1215 Illinois Ave",
    "sg:city":"Jacksonville",
    "sg:classifiers":[
        {
            "category":"Freight",
            "type":"Transportation"
        },
        {
            "category":"Building & Trades",
            "subcategory":"Construction",
            "type":"Services"
        }
    ],
    "sg:phone":"+1 217 243 9567",
    "sg:postcode":"62650",
    "sg:province":"IL",
    "sg:tags":[
        "operator",
        "excavating",
        "contractor",
        "local",
        "trucking"
    ],
    "wof:name":"Rouland Construction & Trckng",
    "wof:placetype":"venue"
},
  "geometry": {"coordinates":[-90.219722,39.747832],"type":"Point"}
}