{
  "type": "Feature",
  "properties": {
    "addr:full":"615 N Oakland Ave Carbondale IL 62901",
    "addr:housenumber":"615",
    "addr:postcode":"62901",
    "addr:street":"N Oakland Ave",
    "iso:country":"US",
    "sg:address":"615 N Oakland Ave",
    "sg:city":"Carbondale",
    "sg:classifiers":[
        {
            "category":"Social Services",
            "subcategory":"Child Care",
            "type":"Services"
        }
    ],
    "sg:phone":"+1 618 457 5081",
    "sg:postcode":"62901",
    "sg:province":"IL",
    "wof:name":"Robins Nest",
    "wof:placetype":"venue"
},
  "geometry": {"coordinates":[-89.22765,37.734194],"type":"Point"}
}