{
  "type": "Feature",
  "properties": {
    "addr:full":"2201 Main St Evanston IL 60202",
    "addr:housenumber":"2201",
    "addr:postcode":"60202",
    "addr:street":"Main St",
    "iso:country":"US",
    "sg:address":"2201 Main St",
    "sg:city":"Evanston",
    "sg:classifiers":[
        {
            "category":"Health Services",
            "subcategory":"Nursing And Care Facility",
            "type":"Services"
        }
    ],
    "sg:phone":"+1 847 905 3000",
    "sg:postcode":"60202",
    "sg:province":"IL",
    "sg:tags":[
        "home",
        "convalescent"
    ],
    "wof:name":"Care Centers Inc",
    "wof:placetype":"venue"
},
  "geometry": {"coordinates":[-87.70475399999999,42.03377],"type":"Point"}
}