{
  "type": "Feature",
  "properties": {
    "iso:country":"US",
    "sg:address":"2201 Main St",
    "sg:city":"Evanston",
    "sg:classifiers":[
        {
            "category":"Health Services",
            "subcategory":"Nursing And Care Facility",
            "type":"Services"
        }
    ],
    "sg:phone":"+1 847 905 3000",
    "sg:postcode":"60202",
    "sg:province":"IL",
    "sg:tags":[
        "home",
        "convalescent"
    ],
    "wof:name":"Care Centers Inc",
    "wof:placetype":"venue"
},
  "geometry": {"coordinates":[-87.704754,42.03377],"type":"Point"}
}