{
  "type": "Feature",
  "properties": {
    "iso:country":"US",
    "sg:address":"4211 Wildwood Dr",
    "sg:city":"Crystal Lake",
    "sg:classifiers":[
        {
            "category":"Building & Trades",
            "subcategory":"Construction",
            "type":"Services"
        }
    ],
    "sg:phone":"+1 815 477 9565",
    "sg:postcode":"60014",
    "sg:province":"IL",
    "sg:tags":[
        "drywall"
    ],
    "wof:name":"Drywall Construction Inc",
    "wof:placetype":"venue"
},
  "geometry": {"coordinates":[-88.226889,42.267066],"type":"Point"}
}