{
  "type": "Feature",
  "properties": {
    "addr:full":"312 W Main St Barrington IL 60010",
    "addr:housenumber":"312",
    "addr:postcode":"60010",
    "addr:street":"W Main St",
    "iso:country":"US",
    "sg:address":"312 W Main St",
    "sg:city":"Barrington",
    "sg:classifiers":[
        {
            "category":"Building & Trades",
            "subcategory":"Construction",
            "type":"Services"
        }
    ],
    "sg:phone":"+1 847 304 1600",
    "sg:postcode":"60010",
    "sg:province":"IL",
    "sg:tags":[
        "roofing",
        "contractor"
    ],
    "wof:name":"Crc Inc",
    "wof:placetype":"venue"
},
  "geometry": {"coordinates":[-88.140895,42.1543],"type":"Point"}
}