{
  "type": "Feature",
  "properties": {
    "addr:full":"8578 Springhill Rd Erie IL 61250",
    "addr:housenumber":"8578",
    "addr:postcode":"61250",
    "addr:street":"Springhill Rd",
    "iso:country":"US",
    "sg:address":"8578 Springhill Rd",
    "sg:city":"Erie",
    "sg:phone":"+1 309 659 7776",
    "sg:postcode":"61250",
    "sg:province":"IL",
    "sg:tags":[
        "farm",
        "corn",
        "soybean"
    ],
    "wof:name":"Neil Young",
    "wof:placetype":"venue"
},
  "geometry": {"coordinates":[-90.086122,41.599918],"type":"Point"}
}