{
  "type": "Feature",
  "properties": {
    "iso:country":"US",
    "sg:address":"1453 E Hyde Park Boulevard",
    "sg:city":"Chicago",
    "sg:classifiers":[
        {
            "category":"Personal",
            "subcategory":"Beauty Salon",
            "type":"Services"
        }
    ],
    "sg:phone":"+1 773 288 2255",
    "sg:postcode":"60615",
    "sg:province":"IL",
    "sg:tags":[
        "hair"
    ],
    "wof:name":"Max & Company Hair Design",
    "wof:placetype":"venue"
},
  "geometry": {"coordinates":[-87.59022,41.802477],"type":"Point"}
}