{
  "type": "Feature",
  "properties": {
    "addr:full":"6372 Rocky Rd East Dubuque IL 61025",
    "addr:housenumber":"6372",
    "addr:postcode":"61025",
    "addr:street":"Rocky Rd",
    "iso:country":"US",
    "sg:address":"6372 Rocky Rd",
    "sg:city":"East Dubuque",
    "sg:classifiers":[
        {
            "category":"Retail",
            "subcategory":"Auto Repair",
            "type":"Services"
        }
    ],
    "sg:phone":"+1 815 747 3648",
    "sg:postcode":"61025",
    "sg:province":"IL",
    "sg:tags":[
        "body",
        "automobile",
        "painting"
    ],
    "wof:name":"Puls Auto Body",
    "wof:placetype":"venue"
},
  "geometry": {"coordinates":[-90.540308,42.467593],"type":"Point"}
}