{
  "type": "Feature",
  "properties": {
    "addr:full":"3115 E Poplar Ln Crete IL 60417",
    "addr:housenumber":"3115",
    "addr:postcode":"60417",
    "addr:street":"E Poplar Ln",
    "iso:country":"US",
    "sg:address":"3115 E Poplar Ln",
    "sg:city":"Crete",
    "sg:classifiers":[
        {
            "category":"Professional",
            "subcategory":"Computer Services",
            "type":"Services"
        }
    ],
    "sg:phone":"+1 708 367 0851",
    "sg:postcode":"60417",
    "sg:province":"IL",
    "sg:tags":[
        "consultant",
        "designer"
    ],
    "wof:name":"Leading Edge Provider",
    "wof:placetype":"venue"
},
  "geometry": {"coordinates":[-87.545677,41.445576],"type":"Point"}
}