{
  "type": "Feature",
  "properties": {
    "iso:country":"US",
    "sg:address":"992 E Hay Rd",
    "sg:city":"Oregon",
    "sg:phone":"+1 815 732 2517",
    "sg:postcode":"61061",
    "sg:province":"IL",
    "sg:tags":[
        "farm",
        "corn",
        "soybean"
    ],
    "wof:name":"Harold Hay",
    "wof:placetype":"venue"
},
  "geometry": {"coordinates":[-89.333581,41.931272],"type":"Point"}
}