{
  "type": "Feature",
  "properties": {
    "iso:country":"US",
    "sg:address":"2022 N Kickapoo St",
    "sg:city":"Lincoln",
    "sg:classifiers":[
        {
            "category":"Organizations",
            "subcategory":"Professional Association",
            "type":"Services"
        }
    ],
    "sg:phone":"+1 217 732 7093",
    "sg:postcode":"62656",
    "sg:province":"IL",
    "sg:tags":[
        "business"
    ],
    "wof:name":"Masonic Temple",
    "wof:placetype":"venue"
},
  "geometry": {"coordinates":[-89.343571,40.162881],"type":"Point"}
}