{
  "type": "Feature",
  "properties": {
    "addr:full":"21 Jandus Rd Cary IL 60013",
    "addr:housenumber":"21",
    "addr:postcode":"60013",
    "addr:street":"Jandus Rd",
    "iso:country":"US",
    "sg:address":"21 Jandus Rd",
    "sg:city":"Cary",
    "sg:classifiers":[
        {
            "category":"Education",
            "subcategory":"Dance Studio",
            "type":"Public Place"
        }
    ],
    "sg:phone":"+1 847 639 3800",
    "sg:postcode":"60013",
    "sg:province":"IL",
    "sg:tags":[
        "instruction",
        "dancing"
    ],
    "wof:name":"Cary-Grove Performing Arts Ctr",
    "wof:placetype":"venue"
},
  "geometry": {"coordinates":[-88.24015799999999,42.208125],"type":"Point"}
}