{
  "type": "Feature",
  "properties": {
    "iso:country":"US",
    "sg:address":"415 S Mulford Rd",
    "sg:city":"Rockford",
    "sg:classifiers":[
        {
            "category":"Professional",
            "subcategory":"Lawyer & Legal Services",
            "type":"Services"
        }
    ],
    "sg:phone":"+1 815 226 8912",
    "sg:postcode":"61108",
    "sg:province":"IL",
    "sg:tags":[
        "attorney",
        "trust",
        "corporation",
        "wills",
        "partnership",
        "elder",
        "planning",
        "real estate",
        "law"
    ],
    "wof:name":"Liebovich & Weber PC",
    "wof:placetype":"venue"
},
  "geometry": {"coordinates":[-88.999657,42.264526],"type":"Point"}
}