{
  "type": "Feature",
  "properties": {
    "iso:country":"US",
    "sg:address":"5832 S Archer Avenue",
    "sg:city":"Chicago",
    "sg:classifiers":[
        {
            "category":"Professional",
            "subcategory":"Lawyer & Legal Services",
            "type":"Services"
        }
    ],
    "sg:phone":"+1 773 767 5422",
    "sg:postcode":"60638",
    "sg:province":"IL",
    "wof:name":"Law Office of Christopher Koczwara",
    "wof:placetype":"venue"
},
  "geometry": {"coordinates":[-87.760097,41.796088],"type":"Point"}
}