{
  "type": "Feature",
  "properties": {
    "addr:full":"7601 S Phillips Ave Chicago IL 60649",
    "addr:housenumber":"7601",
    "addr:postcode":"60649",
    "addr:street":"S Phillips Ave",
    "iso:country":"US",
    "sg:address":"7601 S Phillips Ave",
    "sg:city":"Chicago",
    "sg:classifiers":[
        {
            "category":"Social Services",
            "type":"Services"
        }
    ],
    "sg:phone":"+1 773 731 0444",
    "sg:postcode":"60649",
    "sg:province":"IL",
    "sg:tags":[
        "organization",
        "welfare"
    ],
    "sg:website":"www.chicagoyouthcenters.org",
    "wof:name":"Chicago Youth Ctr-Crown",
    "wof:placetype":"venue"
},
  "geometry": {"coordinates":[-87.56509,41.755375],"type":"Point"}
}