{
  "type": "Feature",
  "properties": {
    "addr:full":"5149 N Broadway St Chicago IL 60640",
    "addr:housenumber":"5149",
    "addr:postcode":"60640",
    "addr:street":"N Broadway St",
    "iso:country":"US",
    "sg:address":"5149 N Broadway St",
    "sg:city":"Chicago",
    "sg:classifiers":[
        {
            "category":"Health Services",
            "subcategory":"Doctor",
            "type":"Services"
        }
    ],
    "sg:phone":"+1 773 334 3767",
    "sg:postcode":"60640",
    "sg:province":"IL",
    "sg:tags":[
        "medical"
    ],
    "wof:name":"Lx Health Advocate Center",
    "wof:placetype":"venue"
},
  "geometry": {"coordinates":[-87.659784,41.976108],"type":"Point"}
}