{
  "type": "Feature",
  "properties": {
    "iso:country":"US",
    "sg:address":"810 Indian Spring Ln",
    "sg:city":"Buffalo Grove",
    "sg:classifiers":[
        {
            "category":"Retail",
            "subcategory":"Repair Shop",
            "type":"Services"
        }
    ],
    "sg:phone":"+1 847 465 9966",
    "sg:postcode":"60089",
    "sg:province":"IL",
    "sg:tags":[
        "electrical"
    ],
    "wof:name":"Magic Appliance",
    "wof:placetype":"venue"
},
  "geometry": {"coordinates":[-87.979336,42.168824],"type":"Point"}
}