{
  "type": "Feature",
  "properties": {
    "iso:country":"US",
    "sg:address":"15880 E 1420th Ave",
    "sg:city":"Teutopolis",
    "sg:classifiers":[
        {
            "category":"Building & Trades",
            "subcategory":"Construction",
            "type":"Services"
        }
    ],
    "sg:phone":"+1 217 857 3052",
    "sg:postcode":"62467",
    "sg:province":"IL",
    "sg:tags":[
        "hanging",
        "contractor"
    ],
    "wof:name":"Roepke Wallcovering",
    "wof:placetype":"venue"
},
  "geometry": {"coordinates":[-88.50755599999999,39.12168],"type":"Point"}
}