{
  "type": "Feature",
  "properties": {
    "iso:country":"US",
    "sg:address":"19673 Fiona Ave",
    "sg:city":"Mokena",
    "sg:classifiers":[
        {
            "category":"Home & Garden",
            "subcategory":"Furniture",
            "type":"Retail Goods"
        }
    ],
    "sg:phone":"+1 708 478 6990",
    "sg:postcode":"60448",
    "sg:province":"IL",
    "sg:tags":[
        "store"
    ],
    "wof:name":"Joe Halper Builders",
    "wof:placetype":"venue"
},
  "geometry": {"coordinates":[-87.870408,41.531171],"type":"Point"}
}