{
  "type": "Feature",
  "properties": {
    "iso:country":"US",
    "sg:address":"900 S Oak St",
    "sg:city":"Effingham",
    "sg:classifiers":[
        {
            "category":"Autos & Motor Vehicles",
            "subcategory":"Fuel & Gas Station",
            "type":"Retail Goods"
        }
    ],
    "sg:phone":"+1   ",
    "sg:postcode":"62401",
    "sg:province":"IL",
    "sg:tags":[
        "station",
        "gasoline"
    ],
    "wof:name":"Dust Towing",
    "wof:placetype":"venue"
},
  "geometry": {"coordinates":[-88.554119,39.114394],"type":"Point"}
}