{
  "type": "Feature",
  "properties": {
    "addr:full":"10430 S Hoyne Ave Chicago IL 60643",
    "addr:housenumber":"10430",
    "addr:postcode":"60643",
    "addr:street":"S Hoyne Ave",
    "iso:country":"US",
    "sg:address":"10430 S Hoyne Ave",
    "sg:city":"Chicago",
    "sg:classifiers":[
        {
            "category":"Real Estate",
            "subcategory":"Architect",
            "type":"Services"
        }
    ],
    "sg:phone":"+1 773 238 9686",
    "sg:postcode":"60643",
    "sg:province":"IL",
    "wof:name":"Messerle Architects",
    "wof:placetype":"venue"
},
  "geometry": {"coordinates":[-87.674301,41.703701],"type":"Point"}
}