{
  "type": "Feature",
  "properties": {
    "addr:full":"3727 23rd Ave Moline IL 61265",
    "addr:housenumber":"3727",
    "addr:postcode":"61265",
    "addr:street":"23Rd Ave",
    "iso:country":"US",
    "sg:address":"3727 23rd Ave",
    "sg:city":"Moline",
    "sg:classifiers":[
        {
            "category":"Shopping",
            "subcategory":"Music",
            "type":"Retail Goods"
        }
    ],
    "sg:phone":"+1   ",
    "sg:postcode":"61265",
    "sg:province":"IL",
    "wof:name":"Co-Op Records",
    "wof:placetype":"venue"
},
  "geometry": {"coordinates":[-90.479984,41.490325],"type":"Point"}
}