{
  "type": "Feature",
  "properties": {
    "addr:full":"5926 N Keating Ave Chicago IL 60646",
    "addr:housenumber":"5926",
    "addr:postcode":"60646",
    "addr:street":"N Keating Ave",
    "iso:country":"US",
    "sg:address":"5926 N Keating Ave",
    "sg:city":"Chicago",
    "sg:classifiers":[
        {
            "category":"Taxi",
            "type":"Transportation"
        },
        {
            "category":"Government",
            "subcategory":"Post Office",
            "type":"Public Place"
        }
    ],
    "sg:phone":"+1 773 283 2969",
    "sg:postcode":"60646",
    "sg:province":"IL",
    "sg:tags":[
        "delivery",
        "courier"
    ],
    "wof:name":"Battaglia Distributing Company",
    "wof:placetype":"venue"
},
  "geometry": {"coordinates":[-87.74706999999999,41.988635],"type":"Point"}
}