{
  "type": "Feature",
  "properties": {
    "addr:full":"6722 Cermak Rd Berwyn IL 60402",
    "addr:housenumber":"6722",
    "addr:postcode":"60402",
    "addr:street":"Cermak Rd",
    "iso:country":"US",
    "sg:address":"6722 Cermak Rd",
    "sg:city":"Berwyn",
    "sg:classifiers":[
        {
            "category":"Banks & Credit Unions",
            "subcategory":"Bank",
            "type":"Services"
        }
    ],
    "sg:phone":"+1 708 484 8100",
    "sg:postcode":"60402",
    "sg:province":"IL",
    "sg:tags":[
        "loan",
        "real estate"
    ],
    "wof:name":"Barrister Mortgage",
    "wof:placetype":"venue"
},
  "geometry": {"coordinates":[-87.791031,41.85067],"type":"Point"}
}