{
  "type": "Feature",
  "properties": {
    "iso:country":"US",
    "sg:address":"4878 N Broadway St",
    "sg:city":"Chicago",
    "sg:classifiers":[
        {
            "category":"Banks & Credit Unions",
            "subcategory":"Bank",
            "type":"Services"
        }
    ],
    "sg:phone":"+1 773 769 6868",
    "sg:postcode":"60640",
    "sg:province":"IL",
    "sg:tags":[
        "national",
        "commercial"
    ],
    "wof:name":"American Metro Bank",
    "wof:placetype":"venue"
},
  "geometry": {"coordinates":[-87.65969800000001,41.9711],"type":"Point"}
}