{
  "type": "Feature",
  "properties": {
    "addr:full":"680 N Lake Shore Dr Chicago IL 60611",
    "addr:housenumber":"680",
    "addr:postcode":"60611",
    "addr:street":"N Lake Shore Dr",
    "iso:country":"US",
    "sg:address":"680 N Lake Shore Dr",
    "sg:city":"Chicago",
    "sg:classifiers":[
        {
            "category":"Health Services",
            "subcategory":"Doctor",
            "type":"Services"
        }
    ],
    "sg:phone":"+1 312 654 9100",
    "sg:postcode":"60611",
    "sg:province":"IL",
    "sg:tags":[
        "gynecology",
        "physician",
        "surgeon",
        "surgeons",
        "obstetrics"
    ],
    "wof:name":"Obstetrics & Gynecologic Ultra Sound",
    "wof:placetype":"venue"
},
  "geometry": {"coordinates":[-87.615621,41.894691],"type":"Point"}
}