{
  "type": "Feature",
  "properties": {
    "addr:full":"1332 N Halsted St Ste 404 Chicago IL 60622",
    "addr:housenumber":"1332",
    "addr:postcode":"60622",
    "addr:street":"N Halsted St Ste 404",
    "iso:country":"US",
    "sg:address":"1332 N Halsted St Ste 404",
    "sg:city":"Chicago",
    "sg:classifiers":[
        {
            "category":"Professional",
            "subcategory":"Computer Services",
            "type":"Services"
        }
    ],
    "sg:phone":"+1 877 244 5489",
    "sg:postcode":"60622",
    "sg:province":"IL",
    "sg:tags":[
        "repair"
    ],
    "sg:website":"www.agilitynetworks.com",
    "wof:name":"Agility Computer Network Services",
    "wof:placetype":"venue"
},
  "geometry": {"coordinates":[-87.648168,41.905049],"type":"Point"}
}