{
  "type": "Feature",
  "properties": {
    "iso:country":"US",
    "sg:address":"4640 N Marine Dr",
    "sg:city":"Chicago",
    "sg:classifiers":[
        {
            "category":"Health Services",
            "subcategory":"Doctor",
            "type":"Services"
        }
    ],
    "sg:phone":"+1 773 334 8633",
    "sg:postcode":"60640",
    "sg:province":"IL",
    "sg:tags":[
        "physician",
        "surgeon"
    ],
    "wof:name":"Edelson Sheldon L MD",
    "wof:placetype":"venue"
},
  "geometry": {"coordinates":[-87.648903,41.966702],"type":"Point"}
}