{
  "type": "Feature",
  "properties": {
    "iso:country":"US",
    "sg:address":"19 W Jackson Blvd",
    "sg:city":"Chicago",
    "sg:classifiers":[
        {
            "category":"Professional",
            "subcategory":"Lawyer & Legal Services",
            "type":"Services"
        }
    ],
    "sg:phone":"+1 312 922 0631",
    "sg:postcode":"60604",
    "sg:province":"IL",
    "wof:name":"Ciardelli Victor F Atty",
    "wof:placetype":"venue"
},
  "geometry": {"coordinates":[-87.628372,41.878047],"type":"Point"}
}