{
  "type": "Feature",
  "properties": {
    "addr:full":"1811 Autumn Ridge Dr Urbana IL 61802",
    "addr:housenumber":"1811",
    "addr:postcode":"61802",
    "addr:street":"Autumn Ridge Dr",
    "iso:country":"US",
    "sg:address":"1811 Autumn Ridge Dr",
    "sg:city":"Urbana",
    "sg:classifiers":[
        {
            "category":"Manufacturing",
            "subcategory":"Tools & Machinery",
            "type":"Manufacturing & Wholesale Goods"
        }
    ],
    "sg:phone":"+1 217 344 0271",
    "sg:postcode":"61802",
    "sg:province":"IL",
    "sg:tags":[
        "terminal",
        "computer",
        "mfg"
    ],
    "wof:name":"Albert Harris",
    "wof:placetype":"venue"
},
  "geometry": {"coordinates":[-88.182582,40.077534],"type":"Point"}
}