{
  "type": "Feature",
  "properties": {
    "addr:full":"627 Gentleman Rd Ottawa IL 61350",
    "addr:housenumber":"627",
    "addr:postcode":"61350",
    "addr:street":"Gentleman Rd",
    "iso:country":"US",
    "sg:address":"627 Gentleman Rd",
    "sg:city":"Ottawa",
    "sg:classifiers":[
        {
            "category":"Organizations",
            "subcategory":"Religious Organization",
            "type":"Services"
        }
    ],
    "sg:phone":"+1 815 434 4416",
    "sg:postcode":"61350",
    "sg:province":"IL",
    "sg:tags":[
        "church"
    ],
    "wof:name":"Epworth United Methodist Chrch",
    "wof:placetype":"venue"
},
  "geometry": {"coordinates":[-88.83102100000001,41.331851],"type":"Point"}
}