{
  "type": "Feature",
  "properties": {
    "iso:country":"US",
    "sg:address":"3230 Williams Ave",
    "sg:city":"Rockford",
    "sg:classifiers":[
        {
            "category":"Building & Trades",
            "subcategory":"Construction",
            "type":"Services"
        }
    ],
    "sg:phone":"+1 815 965 6630",
    "sg:postcode":"61101",
    "sg:province":"IL",
    "sg:tags":[
        "general",
        "commercial",
        "contractor"
    ],
    "wof:name":"Cord Construction Co",
    "wof:placetype":"venue"
},
  "geometry": {"coordinates":[-89.108793,42.301372],"type":"Point"}
}