{
  "type": "Feature",
  "properties": {
    "addr:full":"9611 Franklin Ave Franklin Park IL 60131",
    "addr:housenumber":"9611",
    "addr:postcode":"60131",
    "addr:street":"Franklin Ave",
    "iso:country":"US",
    "sg:address":"9611 Franklin Ave",
    "sg:city":"Franklin Park",
    "sg:classifiers":[
        {
            "category":"Manufacturing",
            "subcategory":"Printing",
            "type":"Manufacturing & Wholesale Goods"
        }
    ],
    "sg:phone":"+1 847 455 5760",
    "sg:postcode":"60131",
    "sg:province":"IL",
    "sg:tags":[
        "lithographic",
        "commercial"
    ],
    "sg:website":"www.corpbizcards.com",
    "wof:name":"Corporate Business Cards LTD",
    "wof:placetype":"venue"
},
  "geometry": {"coordinates":[-87.86614899999999,41.935385],"type":"Point"}
}