{
  "type": "Feature",
  "properties": {
    "addr:full":"1229 N Ashland Avenue Chicago IL 60622",
    "addr:housenumber":"1229",
    "addr:postcode":"60622",
    "addr:street":"N Ashland Avenue",
    "iso:country":"US",
    "sg:address":"1229 N Ashland Avenue",
    "sg:city":"Chicago",
    "sg:classifiers":[
        {
            "category":"Health Services",
            "subcategory":"Dentist",
            "type":"Services"
        }
    ],
    "sg:phone":"+1 773 252 5772",
    "sg:postcode":"60622",
    "sg:province":"IL",
    "sg:tags":[
        "dentists-cosmetic",
        "denture",
        "dentists-prosthodontists",
        "dentistry",
        "implant",
        "dentists-implantology"
    ],
    "sg:website":"http://www.westtowndentalgroup.com",
    "wof:name":"West Town Dental Group",
    "wof:placetype":"venue"
},
  "geometry": {"coordinates":[-87.667562,41.903998],"type":"Point"}
}