{
  "type": "Feature",
  "properties": {
    "iso:country":"US",
    "sg:address":"3209 Thomas Hickey Dr",
    "sg:city":"Joliet",
    "sg:classifiers":[
        {
            "category":"Building & Trades",
            "subcategory":"Construction",
            "type":"Services"
        }
    ],
    "sg:phone":"+1 815 436 6361",
    "sg:postcode":"60431",
    "sg:province":"IL",
    "sg:tags":[
        "home",
        "builder"
    ],
    "wof:name":"Leach Homes",
    "wof:placetype":"venue"
},
  "geometry": {"coordinates":[-88.162103,41.555282],"type":"Point"}
}