{
  "type": "Feature",
  "properties": {
    "addr:full":"920 175th St Homewood IL 60430",
    "addr:housenumber":"920",
    "addr:postcode":"60430",
    "addr:street":"175Th St",
    "iso:country":"US",
    "sg:address":"920 175th St",
    "sg:city":"Homewood",
    "sg:classifiers":[
        {
            "category":"Professional",
            "subcategory":"Accounting & Tax Preparation",
            "type":"Services"
        }
    ],
    "sg:phone":"+1 708 798 0234",
    "sg:postcode":"60430",
    "sg:province":"IL",
    "wof:name":"Accu File Inc",
    "wof:placetype":"venue"
},
  "geometry": {"coordinates":[-87.64057699999999,41.571872],"type":"Point"}
}