{
  "type": "Feature",
  "properties": {
    "addr:full":"218 N Foley Ave Freeport IL 61032",
    "addr:housenumber":"218",
    "addr:postcode":"61032",
    "addr:street":"N Foley Ave",
    "iso:country":"US",
    "sg:address":"218 N Foley Ave",
    "sg:city":"Freeport",
    "sg:classifiers":[
        {
            "category":"Retail",
            "subcategory":"Repair Shop",
            "type":"Services"
        }
    ],
    "sg:phone":"+1 815 232 8968",
    "sg:postcode":"61032",
    "sg:province":"IL",
    "sg:tags":[
        "refinishing",
        "furniture"
    ],
    "wof:name":"Chair Caning",
    "wof:placetype":"venue"
},
  "geometry": {"coordinates":[-89.635154,42.299093],"type":"Point"}
}