{
  "type": "Feature",
  "properties": {
    "iso:country":"US",
    "sg:address":"1835 E 2850 North Rd",
    "sg:city":"Blue Mound",
    "sg:phone":"+1 217 676 2206",
    "sg:postcode":"62513",
    "sg:province":"IL",
    "sg:tags":[
        "farm",
        "corn",
        "soybean"
    ],
    "wof:name":"Mark Cochran",
    "wof:placetype":"venue"
},
  "geometry": {"coordinates":[-89.19049,39.765462],"type":"Point"}
}