{
  "type": "Feature",
  "properties": {
    "iso:country":"US",
    "sg:address":"3215 N Main St",
    "sg:city":"Rockford",
    "sg:classifiers":[
        {
            "category":"Professional",
            "subcategory":"Business Services",
            "type":"Services"
        },
        {
            "category":"Personal",
            "type":"Services"
        }
    ],
    "sg:phone":"+1 815 633 6644",
    "sg:postcode":"61103",
    "sg:province":"IL",
    "sg:tags":[
        "license",
        "licensing",
        "related"
    ],
    "wof:name":"Dream's Currency Exchange Inc",
    "wof:placetype":"venue"
},
  "geometry": {"coordinates":[-89.07708700000001,42.308939],"type":"Point"}
}