{
  "type": "Feature",
  "properties": {
    "addr:full":"300 W Grand Ave Chicago IL 60654",
    "addr:housenumber":"300",
    "addr:postcode":"60654",
    "addr:street":"W Grand Ave",
    "iso:country":"US",
    "sg:address":"300 W Grand Ave",
    "sg:city":"Chicago",
    "sg:classifiers":[
        {
            "category":"Home & Garden",
            "subcategory":"Building Materials",
            "type":"Retail Goods"
        },
        {
            "category":"Home & Garden",
            "subcategory":"Carpets & Floor Coverings",
            "type":"Retail Goods"
        }
    ],
    "sg:phone":"+1 773 398 8758",
    "sg:postcode":"60654",
    "sg:province":"IL",
    "sg:tags":[
        "flooring",
        "supply"
    ],
    "sg:website":"www.rodebrothers.com",
    "wof:name":"Rode Bros",
    "wof:placetype":"venue"
},
  "geometry": {"coordinates":[-87.63605699999999,41.891795],"type":"Point"}
}