{
  "type": "Feature",
  "properties": {
    "iso:country":"US",
    "sg:address":"11458 S Cicero Ave",
    "sg:city":"Alsip",
    "sg:classifiers":[
        {
            "category":"Autos & Motor Vehicles",
            "subcategory":"Fuel & Gas Station",
            "type":"Retail Goods"
        }
    ],
    "sg:phone":"+1   ",
    "sg:postcode":"60803",
    "sg:province":"IL",
    "sg:tags":[
        "station",
        "gasoline"
    ],
    "wof:name":"N & S Amoco",
    "wof:placetype":"venue"
},
  "geometry": {"coordinates":[-87.739769,41.690093],"type":"Point"}
}