{
  "type": "Feature",
  "properties": {
    "iso:country":"US",
    "sg:address":"1077 Collinsville Crossing Blvd",
    "sg:city":"Collinsville",
    "sg:classifiers":[
        {
            "category":"Utilities",
            "subcategory":"Mobile Phone",
            "type":"Services"
        },
        {
            "category":"Coffee & Tea",
            "type":"Food & Drink"
        }
    ],
    "sg:phone":"+1 618 343 9062",
    "sg:postcode":"62234",
    "sg:province":"IL",
    "sg:tags":[
        "shop",
        "wi-fi",
        "espresso",
        "hotspot",
        "restaurant"
    ],
    "sg:website":"http://www.starbuckscoffee.com",
    "wof:name":"Starbucks Coffee",
    "wof:placetype":"venue"
},
  "geometry": {"coordinates":[-90.015214,38.676015],"type":"Point"}
}