{
  "type": "Feature",
  "properties": {
    "iso:country":"US",
    "sg:address":"1918 Manor Ln",
    "sg:city":"Mundelein",
    "sg:classifiers":[
        {
            "category":"Professional",
            "subcategory":"Management & Consulting",
            "type":"Services"
        }
    ],
    "sg:phone":"+1 847 566 2850",
    "sg:postcode":"60060",
    "sg:province":"IL",
    "sg:tags":[
        "business"
    ],
    "wof:name":"RP Stone Consulting Inc",
    "wof:placetype":"venue"
},
  "geometry": {"coordinates":[-88.032546,42.273243],"type":"Point"}
}