{
  "type": "Feature",
  "properties": {
    "iso:country":"US",
    "sg:address":"9732 S Troy Ave",
    "sg:city":"Evergreen Park",
    "sg:classifiers":[
        {
            "category":"Building & Trades",
            "subcategory":"Cleaning & Sanitation",
            "type":"Services"
        }
    ],
    "sg:phone":"+1 708 308 9423",
    "sg:postcode":"60805",
    "sg:province":"IL",
    "sg:tags":[
        "maintenance"
    ],
    "wof:name":"Domina Painting & Wallpapering",
    "wof:placetype":"venue"
},
  "geometry": {"coordinates":[-87.700379,41.715069],"type":"Point"}
}