{
  "type": "Feature",
  "properties": {
    "iso:country":"US",
    "sg:address":"906 Vandalia St",
    "sg:city":"Collinsville",
    "sg:classifiers":[
        {
            "category":"Personal",
            "subcategory":"Beauty Salon",
            "type":"Services"
        }
    ],
    "sg:phone":"+1 618 344 7073",
    "sg:postcode":"62234",
    "sg:province":"IL",
    "sg:tags":[
        "tanning",
        "massage"
    ],
    "wof:name":"Mane Tamers",
    "wof:placetype":"venue"
},
  "geometry": {"coordinates":[-89.980003,38.680099],"type":"Point"}
}