{
  "type": "Feature",
  "properties": {
    "addr:full":"7251 S Stony Island Ave Chicago IL 60649",
    "addr:housenumber":"7251",
    "addr:postcode":"60649",
    "addr:street":"S Stony Island Ave",
    "iso:country":"US",
    "sg:address":"7251 S Stony Island Ave",
    "sg:city":"Chicago",
    "sg:classifiers":[
        {
            "category":"Retail",
            "subcategory":"Auto Repair",
            "type":"Services"
        }
    ],
    "sg:phone":"+1 773 643 1610",
    "sg:postcode":"60649",
    "sg:province":"IL",
    "sg:website":"www.midas.com",
    "wof:name":"Midas Auto Service",
    "wof:placetype":"venue"
},
  "geometry": {"coordinates":[-87.585488,41.762647],"type":"Point"}
}