{
  "type": "Feature",
  "properties": {
    "addr:full":"2622 W 84th St Chicago IL 60652",
    "addr:housenumber":"2622",
    "addr:postcode":"60652",
    "addr:street":"W 84Th St",
    "iso:country":"US",
    "sg:address":"2622 W 84th St",
    "sg:city":"Chicago",
    "sg:classifiers":[
        {
            "category":"Professional",
            "subcategory":"Computer Services",
            "type":"Services"
        }
    ],
    "sg:phone":"+1 773 776 8536",
    "sg:postcode":"60652",
    "sg:province":"IL",
    "sg:tags":[
        "internet"
    ],
    "wof:name":"Cetek Solutions Inc",
    "wof:placetype":"venue"
},
  "geometry": {"coordinates":[-87.68944500000001,41.741018],"type":"Point"}
}