{
  "type": "Feature",
  "properties": {
    "iso:country":"US",
    "sg:address":"333 Center St",
    "sg:city":"Naperville",
    "sg:classifiers":[
        {
            "category":"Bars & Pubs",
            "type":"Food & Drink"
        }
    ],
    "sg:menulink":"http://www.allmenus.com/il/lisle/237472-orazio-pub/menu/",
    "sg:phone":"+1 630 357 4350",
    "sg:postcode":"60540",
    "sg:province":"IL",
    "sg:tags":[
        "american"
    ],
    "wof:name":"Orazio Pub",
    "wof:placetype":"venue"
},
  "geometry": {"coordinates":[-88.14621099999999,41.778938],"type":"Point"}
}