{
  "type": "Feature",
  "properties": {
    "iso:country":"US",
    "sg:address":"19731 Cheneys Grove Rd",
    "sg:city":"Bloomington",
    "sg:classifiers":[
        {
            "category":"Professional",
            "subcategory":"Art Services",
            "type":"Services"
        }
    ],
    "sg:phone":"+1 309 378 4604",
    "sg:postcode":"61705",
    "sg:province":"IL",
    "sg:tags":[
        "graphic",
        "commercial",
        "designer",
        "artist"
    ],
    "wof:name":"Wcf",
    "wof:placetype":"venue"
},
  "geometry": {"coordinates":[-88.88712,40.438773],"type":"Point"}
}