{
  "type": "Feature",
  "properties": {
    "addr:full":"1499 Shermer Rd Northbrook IL 60062",
    "addr:housenumber":"1499",
    "addr:postcode":"60062",
    "addr:street":"Shermer Rd",
    "iso:country":"US",
    "sg:address":"1499 Shermer Rd",
    "sg:city":"Northbrook",
    "sg:classifiers":[
        {
            "category":"Banks & Credit Unions",
            "subcategory":"Investment Brokerage",
            "type":"Services"
        }
    ],
    "sg:phone":"+1 847 412 9096",
    "sg:postcode":"60062",
    "sg:province":"IL",
    "sg:tags":[
        "security"
    ],
    "wof:name":"Francis Frain Mgmt",
    "wof:placetype":"venue"
},
  "geometry": {"coordinates":[-87.829234,42.126038],"type":"Point"}
}