{
  "type": "Feature",
  "properties": {
    "addr:full":"12223 W Farmington Rd Hanna City IL 61536",
    "addr:housenumber":"12223",
    "addr:postcode":"61536",
    "addr:street":"W Farmington Rd",
    "iso:country":"US",
    "sg:address":"12223 W Farmington Rd",
    "sg:city":"Hanna City",
    "sg:classifiers":[
        {
            "category":"Banks & Credit Unions",
            "subcategory":"Bank",
            "type":"Services"
        }
    ],
    "sg:phone":"+1 309 565 4261",
    "sg:postcode":"61536",
    "sg:province":"IL",
    "sg:website":"www.heritage-bnk.com",
    "wof:name":"Heritage Bank",
    "wof:placetype":"venue"
},
  "geometry": {"coordinates":[-89.80013099999999,40.69295],"type":"Point"}
}