{
  "type": "Feature",
  "properties": {
    "iso:country":"US",
    "sg:address":"6336 W North Avenue",
    "sg:city":"Chicago",
    "sg:classifiers":[
        {
            "category":"Bakery",
            "type":"Food & Drink"
        }
    ],
    "sg:phone":"+1 773 622 1881",
    "sg:postcode":"60639",
    "sg:province":"IL",
    "sg:website":"www.baskinrobbins.com",
    "wof:name":"Dunkin Donuts-Baskin Robins",
    "wof:placetype":"venue"
},
  "geometry": {"coordinates":[-87.784459,41.909314],"type":"Point"}
}