{
  "type": "Feature",
  "properties": {
    "addr:full":"303 Alschuler Dr Aurora IL 60506",
    "addr:housenumber":"303",
    "addr:postcode":"60506",
    "addr:street":"Alschuler Dr",
    "iso:country":"US",
    "sg:address":"303 Alschuler Dr",
    "sg:city":"Aurora",
    "sg:classifiers":[
        {
            "category":"Wholesale",
            "subcategory":"Chemicals & Plastics",
            "type":"Manufacturing & Wholesale Goods"
        }
    ],
    "sg:phone":"+1 630 896 3596",
    "sg:postcode":"60506",
    "sg:province":"IL",
    "wof:name":"Novotny Asset Management Co",
    "wof:placetype":"venue"
},
  "geometry": {"coordinates":[-88.360457,41.754628],"type":"Point"}
}