{
  "type": "Feature",
  "properties": {
    "addr:full":"1111 S State St Apt 404 Chicago IL 60605",
    "addr:housenumber":"1111;404",
    "addr:postcode":"60605",
    "addr:street":"S State St Apt",
    "iso:country":"US",
    "sg:address":"1111 S State St Apt 404",
    "sg:city":"Chicago",
    "sg:classifiers":[
        {
            "category":"Professional",
            "subcategory":"Art Services",
            "type":"Services"
        }
    ],
    "sg:phone":"+1 312 341 1227",
    "sg:postcode":"60605",
    "sg:province":"IL",
    "sg:tags":[
        "designer",
        "display",
        "producer"
    ],
    "wof:name":"Mchorvat Design",
    "wof:placetype":"venue"
},
  "geometry": {"coordinates":[-87.627399,41.869063],"type":"Point"}
}