{
  "type": "Feature",
  "properties": {
    "iso:country":"US",
    "sg:address":"2590 E Federal Dr",
    "sg:city":"Decatur",
    "sg:classifiers":[
        {
            "category":"Retail",
            "subcategory":"Laundry & Dry Cleaning",
            "type":"Services"
        },
        {
            "category":"Building & Trades",
            "subcategory":"Cleaning & Sanitation",
            "type":"Services"
        }
    ],
    "sg:phone":"+1 217 876 7860",
    "sg:postcode":"62526",
    "sg:province":"IL",
    "sg:tags":[
        "cleaner",
        "house",
        "rug",
        "janitorial",
        "carpet"
    ],
    "sg:website":"http://www.cics.com",
    "wof:name":"C I C S Inc",
    "wof:placetype":"venue"
},
  "geometry": {"coordinates":[-88.92012699999999,39.88857],"type":"Point"}
}