{
  "type": "Feature",
  "properties": {
    "addr:full":"5738 N Merrimac Ave Chicago IL 60646",
    "addr:housenumber":"5738",
    "addr:postcode":"60646",
    "addr:street":"N Merrimac Ave",
    "iso:country":"US",
    "sg:address":"5738 N Merrimac Ave",
    "sg:city":"Chicago",
    "sg:classifiers":[
        {
            "category":"Professional",
            "type":"Services"
        }
    ],
    "sg:phone":"+1 773 467 1885",
    "sg:postcode":"60646",
    "sg:province":"IL",
    "wof:name":"Marcos Dj Service",
    "wof:placetype":"venue"
},
  "geometry": {"coordinates":[-87.784115,41.985818],"type":"Point"}
}