{
  "type": "Feature",
  "properties": {
    "iso:country":"US",
    "sg:address":"16855 Torrence Ave",
    "sg:city":"Lansing",
    "sg:classifiers":[
        {
            "category":"Shopping",
            "subcategory":"Discount & Variety Stores",
            "type":"Retail Goods"
        }
    ],
    "sg:phone":"+1 708 394 0600",
    "sg:postcode":"60438",
    "sg:province":"IL",
    "sg:website":"www.formanmills.com",
    "wof:name":"Forman Mills",
    "wof:placetype":"venue"
},
  "geometry": {"coordinates":[-87.556102,41.588327],"type":"Point"}
}