{
  "type": "Feature",
  "properties": {
    "addr:full":"20505 SE Frontage Rd Joliet IL 60431",
    "addr:postcode":"20505;60431",
    "addr:street":"Se Frontage Rd",
    "iso:country":"US",
    "sg:address":"20505 SE Frontage Rd",
    "sg:city":"Joliet",
    "sg:classifiers":[
        {
            "category":"Manufacturing",
            "subcategory":"Metals",
            "type":"Manufacturing & Wholesale Goods"
        }
    ],
    "sg:phone":"+1 815 744 9090",
    "sg:postcode":"60431",
    "sg:province":"IL",
    "sg:tags":[
        "steel",
        "shape",
        "cold",
        "mfg"
    ],
    "wof:name":"Fox Valley Industries Inc",
    "wof:placetype":"venue"
},
  "geometry": {"coordinates":[-88.19493199999999,41.512007],"type":"Point"}
}