{
  "type": "Feature",
  "properties": {
    "iso:country":"US",
    "sg:address":"8027 W 79th St",
    "sg:city":"Justice",
    "sg:classifiers":[
        {
            "category":"Retail",
            "subcategory":"Laundry & Dry Cleaning",
            "type":"Services"
        }
    ],
    "sg:phone":"+1 708 563 9532",
    "sg:postcode":"60458",
    "sg:province":"IL",
    "sg:tags":[
        "drycleaning",
        "plant"
    ],
    "wof:name":"Justice Village Clnrs",
    "wof:placetype":"venue"
},
  "geometry": {"coordinates":[-87.821404,41.747501],"type":"Point"}
}