{
  "type": "Feature",
  "properties": {
    "addr:full":"4006 11th St Rock Island IL 61201",
    "addr:housenumber":"4006",
    "addr:postcode":"61201",
    "addr:street":"11Th St",
    "iso:country":"US",
    "sg:address":"4006 11th St",
    "sg:city":"Rock Island",
    "sg:classifiers":[
        {
            "category":"Freight",
            "type":"Transportation"
        }
    ],
    "sg:phone":"+1 563 357 1208",
    "sg:postcode":"61201",
    "sg:province":"IL",
    "sg:tags":[
        "general"
    ],
    "wof:name":"Todd Till",
    "wof:placetype":"venue"
},
  "geometry": {"coordinates":[-90.583753,41.471537],"type":"Point"}
}