{
  "type": "Feature",
  "properties": {
    "iso:country":"US",
    "sg:address":"1300 W 35th St",
    "sg:city":"Chicago",
    "sg:classifiers":[
        {
            "category":"Home & Garden",
            "subcategory":"Building Materials",
            "type":"Retail Goods"
        },
        {
            "category":"Manufacturing",
            "subcategory":"Building Materials",
            "type":"Manufacturing & Wholesale Goods"
        }
    ],
    "sg:phone":"+1 773 523 6611",
    "sg:postcode":"60609",
    "sg:province":"IL",
    "sg:tags":[
        "doors-wholesale",
        "accessory",
        "window",
        "doors",
        "frames",
        "manufacturer"
    ],
    "sg:website":"http://www.windowplacecorp.com",
    "wof:name":"Window Place Corp",
    "wof:placetype":"venue"
},
  "geometry": {"coordinates":[-87.657707,41.830589],"type":"Point"}
}