{
  "type": "Feature",
  "properties": {
    "iso:country":"US",
    "sg:address":"6804 S Washtenaw Ave",
    "sg:city":"Chicago",
    "sg:classifiers":[
        {
            "category":"Organizations",
            "subcategory":"Religious Organization",
            "type":"Services"
        }
    ],
    "sg:phone":"+1 773 476 5135",
    "sg:postcode":"60629",
    "sg:province":"IL",
    "wof:name":"Sisters Of St Casimir",
    "wof:placetype":"venue"
},
  "geometry": {"coordinates":[-87.69071700000001,41.769957],"type":"Point"}
}