{
  "type": "Feature",
  "properties": {
    "addr:full":"3612 Lincoln Hwy Olympia Fields IL 60461",
    "addr:housenumber":"3612",
    "addr:postcode":"60461",
    "addr:street":"Lincoln Hwy",
    "iso:country":"US",
    "sg:address":"3612 Lincoln Hwy",
    "sg:city":"Olympia Fields",
    "sg:classifiers":[
        {
            "category":"Real Estate",
            "subcategory":"Real Estate Agent",
            "type":"Services"
        }
    ],
    "sg:phone":"+1 708 283 1556",
    "sg:postcode":"60461",
    "sg:province":"IL",
    "sg:tags":[
        "residential",
        "commercial",
        "realty"
    ],
    "wof:name":"Hughey Realty",
    "wof:placetype":"venue"
},
  "geometry": {"coordinates":[-87.70402300000001,41.506222],"type":"Point"}
}