{
  "type": "Feature",
  "properties": {
    "addr:full":"4545 N Seeley Ave Chicago IL 60625",
    "addr:housenumber":"4545",
    "addr:postcode":"60625",
    "addr:street":"N Seeley Ave",
    "iso:country":"US",
    "sg:address":"4545 N Seeley Ave",
    "sg:city":"Chicago",
    "sg:classifiers":[
        {
            "category":"Health Services",
            "subcategory":"Hospital",
            "type":"Services"
        }
    ],
    "sg:phone":"+1 773 784 1831",
    "sg:postcode":"60625",
    "sg:province":"IL",
    "wof:name":"Childrens Memorial Hospital",
    "wof:placetype":"venue"
},
  "geometry": {"coordinates":[-87.680646,41.964066],"type":"Point"}
}