{
  "type": "Feature",
  "properties": {
    "iso:country":"US",
    "sg:address":"1717 Philo Rd",
    "sg:city":"Urbana",
    "sg:classifiers":[
        {
            "category":"Real Estate",
            "subcategory":"Real Estate Agent",
            "type":"Services"
        }
    ],
    "sg:phone":"+1 217 384 5787",
    "sg:postcode":"61802",
    "sg:province":"IL",
    "wof:name":"Sunnycrest Mall",
    "wof:placetype":"venue"
},
  "geometry": {"coordinates":[-88.190765,40.095087],"type":"Point"}
}