{
  "type": "Feature",
  "properties": {
    "iso:country":"US",
    "sg:address":"2415 Pecan St",
    "sg:city":"Joliet",
    "sg:classifiers":[
        {
            "category":"Autos & Motor Vehicles",
            "subcategory":"Motorcycle Sales",
            "type":"Retail Goods"
        }
    ],
    "sg:phone":"+1 815 436 1403",
    "sg:postcode":"60435",
    "sg:province":"IL",
    "sg:tags":[
        "scooter"
    ],
    "wof:name":"Dragons Performance",
    "wof:placetype":"venue"
},
  "geometry": {"coordinates":[-88.147386,41.575777],"type":"Point"}
}