{
  "type": "Feature",
  "properties": {
    "iso:country":"US",
    "sg:address":"2 American Way",
    "sg:city":"Elgin",
    "sg:classifiers":[
        {
            "category":"Health Services",
            "subcategory":"Health Practitioner",
            "type":"Services"
        }
    ],
    "sg:phone":"+1 847 742 6290",
    "sg:postcode":"60120",
    "sg:province":"IL",
    "sg:tags":[
        "psychologist"
    ],
    "wof:name":"Lee Plasmier & Assoc",
    "wof:placetype":"venue"
},
  "geometry": {"coordinates":[-88.257621,42.045702],"type":"Point"}
}