{
  "type": "Feature",
  "properties": {
    "addr:full":"320 E Main St Barrington IL 60010",
    "addr:housenumber":"320",
    "addr:postcode":"60010",
    "addr:street":"E Main St",
    "iso:country":"US",
    "sg:address":"320 E Main St",
    "sg:city":"Barrington",
    "sg:classifiers":[
        {
            "category":"Professional",
            "subcategory":"Business Services",
            "type":"Services"
        }
    ],
    "sg:phone":"+1 847 382 1001",
    "sg:postcode":"60010",
    "sg:province":"IL",
    "wof:name":"Lampert Adelle L Asid",
    "wof:placetype":"venue"
},
  "geometry": {"coordinates":[-88.13129000000001,42.154199],"type":"Point"}
}