{
  "type": "Feature",
  "properties": {
    "addr:full":"925 S Valley Ln Palatine IL 60067",
    "addr:housenumber":"925",
    "addr:postcode":"60067",
    "addr:street":"S Valley Ln",
    "iso:country":"US",
    "sg:address":"925 S Valley Ln",
    "sg:city":"Palatine",
    "sg:classifiers":[
        {
            "category":"Professional",
            "subcategory":"Business Services",
            "type":"Services"
        }
    ],
    "sg:phone":"+1 847 359 7517",
    "sg:postcode":"60067",
    "sg:province":"IL",
    "wof:name":"Magestic Partners",
    "wof:placetype":"venue"
},
  "geometry": {"coordinates":[-88.061108,42.09368],"type":"Point"}
}