{
  "type": "Feature",
  "properties": {
    "addr:full":"5097 N Elston Avenue Chicago IL 60630",
    "addr:housenumber":"5097",
    "addr:postcode":"60630",
    "addr:street":"N Elston Avenue",
    "iso:country":"US",
    "sg:address":"5097 N Elston Avenue",
    "sg:city":"Chicago",
    "sg:classifiers":[
        {
            "category":"Professional",
            "subcategory":"Accounting & Tax Preparation",
            "type":"Services"
        }
    ],
    "sg:phone":"+1 773 282 4636",
    "sg:postcode":"60630",
    "sg:province":"IL",
    "sg:tags":[
        "accountant"
    ],
    "wof:name":"Karahalios & Pavlatos",
    "wof:placetype":"venue"
},
  "geometry": {"coordinates":[-87.74905099999999,41.973568],"type":"Point"}
}