{
  "type": "Feature",
  "properties": {
    "iso:country":"US",
    "sg:address":"4841 Butterfield Rd",
    "sg:city":"Hillside",
    "sg:classifiers":[
        {
            "category":"Professional",
            "type":"Services"
        },
        {
            "category":"Restaurant",
            "type":"Food & Drink"
        }
    ],
    "sg:phone":"+1 708 449 7488",
    "sg:postcode":"60162",
    "sg:province":"IL",
    "sg:tags":[
        "caterer",
        "pizza"
    ],
    "sg:website":"http://www.qsrestaurant.com",
    "wof:name":"Q's Restaurant & Pizzeria",
    "wof:placetype":"venue"
},
  "geometry": {"coordinates":[-87.904117,41.877242],"type":"Point"}
}