{
  "type": "Feature",
  "properties": {
    "addr:full":"2700 Washington Ave Alton IL 62002",
    "addr:housenumber":"2700",
    "addr:postcode":"62002",
    "addr:street":"Washington Ave",
    "iso:country":"US",
    "sg:address":"2700 Washington Ave",
    "sg:city":"Alton",
    "sg:phone":"+1 618 462 7272",
    "sg:postcode":"62002",
    "sg:province":"IL",
    "sg:website":"http://www.papajohns.com",
    "wof:name":"Papa John's Pizza",
    "wof:placetype":"venue"
},
  "geometry": {"coordinates":[-90.15070299999999,38.914322],"type":"Point"}
}