{
  "type": "Feature",
  "properties": {
    "addr:full":"1044 Western Ave Henry IL 61537",
    "addr:housenumber":"1044",
    "addr:postcode":"61537",
    "addr:street":"Western Ave",
    "iso:country":"US",
    "sg:address":"1044 Western Ave",
    "sg:city":"Henry",
    "sg:classifiers":[
        {
            "category":"Restaurant",
            "type":"Food & Drink"
        }
    ],
    "sg:menulink":"http://www.allmenus.com/il/whitefield/126570-subway/menu/",
    "sg:phone":"+1 309 364 3512",
    "sg:postcode":"61537",
    "sg:province":"IL",
    "sg:tags":[
        "american",
        "sandwich"
    ],
    "wof:name":"Subway",
    "wof:placetype":"venue"
},
  "geometry": {"coordinates":[-89.42940299999999,41.113218],"type":"Point"}
}