{
  "type": "Feature",
  "properties": {
    "iso:country":"US",
    "sg:address":"441 N Weber Rd",
    "sg:city":"Romeoville",
    "sg:classifiers":[
        {
            "category":"Professional",
            "subcategory":"Advertising",
            "type":"Services"
        },
        {
            "category":"Health Services",
            "subcategory":"Dentist",
            "type":"Services"
        }
    ],
    "sg:phone":"+1 815 372 2345",
    "sg:postcode":"60446",
    "sg:province":"IL",
    "sg:tags":[
        "coupon",
        "implant",
        "dentists-implantology",
        "dentists-cosmetic",
        "dentistry"
    ],
    "sg:website":"http://www.vvdental.com",
    "wof:name":"Valley View Dental",
    "wof:placetype":"venue"
},
  "geometry": {"coordinates":[-88.123149,41.606897],"type":"Point"}
}