{
  "type": "Feature",
  "properties": {
    "iso:country":"US",
    "sg:address":"1617 5th St",
    "sg:city":"Peru",
    "sg:classifiers":[
        {
            "category":"Professional",
            "subcategory":"Business Services",
            "type":"Services"
        }
    ],
    "sg:phone":"+1 815 220 1068",
    "sg:postcode":"61354",
    "sg:province":"IL",
    "sg:tags":[
        "process",
        "server"
    ],
    "wof:name":"CAM Inc",
    "wof:placetype":"venue"
},
  "geometry": {"coordinates":[-89.127689,41.328612],"type":"Point"}
}