{
  "type": "Feature",
  "properties": {
    "iso:country":"US",
    "sg:address":"10637 S Pulaski Rd",
    "sg:city":"Chicago",
    "sg:classifiers":[
        {
            "category":"Professional",
            "subcategory":"Lawyer & Legal Services",
            "type":"Services"
        }
    ],
    "sg:phone":"+1 773 233 5510",
    "sg:postcode":"60655",
    "sg:province":"IL",
    "sg:tags":[
        "attorney"
    ],
    "wof:name":"Gerald Bauer Jr Law Offices",
    "wof:placetype":"venue"
},
  "geometry": {"coordinates":[-87.720605,41.700141],"type":"Point"}
}