{
  "type": "Feature",
  "properties": {
    "iso:country":"US",
    "sg:address":"4108 N Sheridan Rd",
    "sg:city":"Chicago",
    "sg:classifiers":[
        {
            "category":"Health Services",
            "subcategory":"Doctor",
            "type":"Services"
        }
    ],
    "sg:phone":"+1 773 529 4913",
    "sg:postcode":"60613",
    "sg:province":"IL",
    "wof:name":"Gesund",
    "wof:placetype":"venue"
},
  "geometry": {"coordinates":[-87.65477,41.957258],"type":"Point"}
}