{
  "type": "Feature",
  "properties": {
    "addr:full":"201 E 71st St Chicago IL 60619",
    "addr:housenumber":"201",
    "addr:postcode":"60619",
    "addr:street":"E 71St St",
    "iso:country":"US",
    "sg:address":"201 E 71st St",
    "sg:city":"Chicago",
    "sg:classifiers":[
        {
            "category":"Banks & Credit Unions",
            "subcategory":"Bureau De Change",
            "type":"Services"
        }
    ],
    "sg:phone":"+1 773 224 4445",
    "sg:postcode":"60619",
    "sg:province":"IL",
    "sg:tags":[
        "currency",
        "exchange",
        "broker",
        "foreign"
    ],
    "wof:name":"71st & Indiana Currency Inc",
    "wof:placetype":"venue"
},
  "geometry": {"coordinates":[-87.62011,41.765621],"type":"Point"}
}