{
  "type": "Feature",
  "properties": {
    "iso:country":"US",
    "sg:address":"110 S Chicago St",
    "sg:city":"Geneseo",
    "sg:classifiers":[
        {
            "category":"Utilities",
            "subcategory":"Fuel Oil & Lpg",
            "type":"Services"
        }
    ],
    "sg:phone":"+1   ",
    "sg:postcode":"61254",
    "sg:province":"IL",
    "sg:tags":[
        "liquefied",
        "gas",
        "dealer",
        "petroleum"
    ],
    "wof:name":"Ferrellgas L P",
    "wof:placetype":"venue"
},
  "geometry": {"coordinates":[-90.143811,41.453177],"type":"Point"}
}