{
  "type": "Feature",
  "properties": {
    "iso:country":"US",
    "sg:address":"77 E Van Buren St",
    "sg:city":"Chicago",
    "sg:classifiers":[
        {
            "category":"Shopping",
            "subcategory":"Books",
            "type":"Retail Goods"
        }
    ],
    "sg:phone":"+1 312 461 1989",
    "sg:postcode":"60605",
    "sg:province":"IL",
    "sg:tags":[
        "bookstore"
    ],
    "wof:name":"Coulsons Music Matters",
    "wof:placetype":"venue"
},
  "geometry": {"coordinates":[-87.625801,41.877102],"type":"Point"}
}