{
  "type": "Feature",
  "properties": {
    "iso:country":"US",
    "sg:address":"419 N Oak St",
    "sg:city":"Williamsfield",
    "sg:classifiers":[
        {
            "category":"Organizations",
            "subcategory":"Religious Organization",
            "type":"Services"
        }
    ],
    "sg:phone":"+1 309 639 4343",
    "sg:postcode":"61489",
    "sg:province":"IL",
    "wof:name":"Methodist Church Parsonage",
    "wof:placetype":"venue"
},
  "geometry": {"coordinates":[-90.018114,40.926857],"type":"Point"}
}