{
  "type": "Feature",
  "properties": {
    "addr:full":"1640 N Wells St Chicago IL 60614",
    "addr:housenumber":"1640",
    "addr:postcode":"60614",
    "addr:street":"N Wells St",
    "iso:country":"US",
    "sg:address":"1640 N Wells St",
    "sg:city":"Chicago",
    "sg:classifiers":[
        {
            "category":"Health Services",
            "subcategory":"Doctor",
            "type":"Services"
        },
        {
            "category":"Health Services",
            "subcategory":"Dentist",
            "type":"Services"
        }
    ],
    "sg:phone":"+1 312 642 4217",
    "sg:postcode":"60614",
    "sg:province":"IL",
    "sg:tags":[
        "surgeon",
        "oral"
    ],
    "wof:name":"Stein James DDS",
    "wof:placetype":"venue"
},
  "geometry": {"coordinates":[-87.634804,41.912102],"type":"Point"}
}