{
  "type": "Feature",
  "properties": {
    "iso:country":"US",
    "sg:address":"1434 E Galena Blvd",
    "sg:city":"Aurora",
    "sg:classifiers":[
        {
            "category":"Food & Beverages",
            "subcategory":"Groceries & Convenience Stores",
            "type":"Retail Goods"
        }
    ],
    "sg:phone":"+1   ",
    "sg:postcode":"60505",
    "sg:province":"IL",
    "wof:name":"Last Chance Grocery Inc",
    "wof:placetype":"venue"
},
  "geometry": {"coordinates":[-88.27931700000001,41.750772],"type":"Point"}
}