{
  "type": "Feature",
  "properties": {
    "iso:country":"US",
    "sg:address":"224 W Stephenson St Ste 4",
    "sg:city":"Freeport",
    "sg:classifiers":[
        {
            "category":"Professional",
            "subcategory":"Lawyer & Legal Services",
            "type":"Services"
        }
    ],
    "sg:phone":"+1 815 232 4533",
    "sg:postcode":"61032",
    "sg:province":"IL",
    "sg:tags":[
        "plan"
    ],
    "wof:name":"Mitchell John F",
    "wof:placetype":"venue"
},
  "geometry": {"coordinates":[-89.622224,42.29753],"type":"Point"}
}