{
  "type": "Feature",
  "properties": {
    "iso:country":"US",
    "sg:address":"1548 E 10000N Rd",
    "sg:city":"Manteno",
    "sg:classifiers":[
        {
            "category":"Home & Garden",
            "subcategory":"Garden Supply",
            "type":"Retail Goods"
        },
        {
            "category":"Farming",
            "subcategory":"Farm",
            "type":"Manufacturing & Wholesale Goods"
        }
    ],
    "sg:phone":"+1 815 468 8511",
    "sg:postcode":"60950",
    "sg:province":"IL",
    "sg:tags":[
        "tree",
        "christmas"
    ],
    "wof:name":"Family Tree Nursery",
    "wof:placetype":"venue"
},
  "geometry": {"coordinates":[-87.847998,41.265013],"type":"Point"}
}