{
  "type": "Feature",
  "properties": {
    "iso:country":"US",
    "sg:address":"205 W Goethe St",
    "sg:city":"Chicago",
    "sg:classifiers":[
        {
            "category":"Personal",
            "type":"Services"
        },
        {
            "category":"Retail",
            "subcategory":"Event Space",
            "type":"Services"
        }
    ],
    "sg:phone":"+1 866 329 7196",
    "sg:postcode":"60610",
    "sg:province":"IL",
    "sg:tags":[
        "party",
        "planning",
        "meeting"
    ],
    "sg:website":"http://www.jamevents.com",
    "wof:name":"JAM Entertainment & Creative Services",
    "wof:placetype":"venue"
},
  "geometry": {"coordinates":[-87.635867,41.905694],"type":"Point"}
}