{
  "type": "Feature",
  "properties": {
    "iso:country":"US",
    "sg:address":"25 E Washington St",
    "sg:city":"Chicago",
    "sg:classifiers":[
        {
            "category":"Professional",
            "subcategory":"Lawyer & Legal Services",
            "type":"Services"
        }
    ],
    "sg:phone":"+1 312 236 7800",
    "sg:postcode":"60602",
    "sg:province":"IL",
    "wof:name":"Mrozowski Gail E Lwyr",
    "wof:placetype":"venue"
},
  "geometry": {"coordinates":[-87.62690000000001,41.883202],"type":"Point"}
}