{
  "type": "Feature",
  "properties": {
    "iso:country":"US",
    "sg:address":"9 W Cass St",
    "sg:city":"Joliet",
    "sg:classifiers":[
        {
            "category":"Organizations",
            "subcategory":"Non-profit Organization",
            "type":"Services"
        }
    ],
    "sg:phone":"+1 815 474 9815",
    "sg:postcode":"60432",
    "sg:province":"IL",
    "wof:name":"Joliet Boxing Team",
    "wof:placetype":"venue"
},
  "geometry": {"coordinates":[-88.082912,41.527863],"type":"Point"}
}