{
  "type": "Feature",
  "properties": {
    "addr:full":"12730 S Pulaski Rd Alsip IL 60803",
    "addr:housenumber":"12730",
    "addr:postcode":"60803",
    "addr:street":"S Pulaski Rd",
    "iso:country":"US",
    "sg:address":"12730 S Pulaski Rd",
    "sg:city":"Alsip",
    "sg:classifiers":[
        {
            "category":"Freight",
            "type":"Transportation"
        }
    ],
    "sg:phone":"+1 708 388 6100",
    "sg:postcode":"60803",
    "sg:province":"IL",
    "sg:tags":[
        "warehouse",
        "mini"
    ],
    "wof:name":"Public Storage Inc",
    "wof:placetype":"venue"
},
  "geometry": {"coordinates":[-87.719229,41.661504],"type":"Point"}
}