{
  "type": "Feature",
  "properties": {
    "iso:country":"US",
    "sg:address":"215 N 1st St",
    "sg:city":"Effingham",
    "sg:classifiers":[
        {
            "category":"Education",
            "subcategory":"School",
            "type":"Public Place"
        }
    ],
    "sg:phone":"+1 217 540 1380",
    "sg:postcode":"62401",
    "sg:province":"IL",
    "wof:name":"East Side Preschool",
    "wof:placetype":"venue"
},
  "geometry": {"coordinates":[-88.538408,39.122997],"type":"Point"}
}