{
  "type": "Feature",
  "properties": {
    "addr:full":"2120 Crystal Lake Rd S Crystal Lake IL 60012",
    "addr:housenumber":"2120",
    "addr:postcode":"60012",
    "addr:street":"Crystal Lake Rd S",
    "iso:country":"US",
    "sg:address":"2120 Crystal Lake Rd S",
    "sg:city":"Crystal Lake",
    "sg:classifiers":[
        {
            "category":"Sports & Exercise",
            "subcategory":"Golf",
            "type":"Entertainment"
        }
    ],
    "sg:phone":"+1 815 479 9361",
    "sg:postcode":"60012",
    "sg:province":"IL",
    "sg:tags":[
        "course"
    ],
    "wof:name":"Old Top Golf Course",
    "wof:placetype":"venue"
},
  "geometry": {"coordinates":[-88.31654,42.295254],"type":"Point"}
}