{
  "type": "Feature",
  "properties": {
    "addr:full":"350 Main St NW Bourbonnais IL 60914",
    "addr:housenumber":"350",
    "addr:postcode":"bourbonnais il 60914",
    "addr:street":"Main St Nw",
    "iso:country":"US",
    "sg:address":"350 Main St NW",
    "sg:city":"Bourbonnais",
    "sg:classifiers":[
        {
            "category":"Personal",
            "subcategory":"Tanning Parlor",
            "type":"Services"
        }
    ],
    "sg:phone":"+1 815 933 1400",
    "sg:postcode":"60914",
    "sg:province":"IL",
    "sg:tags":[
        "salon"
    ],
    "wof:name":"Cardinal Fitness",
    "wof:placetype":"venue"
},
  "geometry": {"coordinates":[-87.88288,41.157358],"type":"Point"}
}