{
  "type": "Feature",
  "properties": {
    "iso:country":"US",
    "sg:address":"145 Virginia Rd",
    "sg:city":"Crystal Lake",
    "sg:classifiers":[
        {
            "category":"Banks & Credit Unions",
            "subcategory":"Investment Brokerage",
            "type":"Services"
        }
    ],
    "sg:phone":"+1 815 459 4110",
    "sg:postcode":"60014",
    "sg:province":"IL",
    "sg:tags":[
        "consultant",
        "planning",
        "financial"
    ],
    "wof:name":"Met Life Financial Svc",
    "wof:placetype":"venue"
},
  "geometry": {"coordinates":[-88.313877,42.214588],"type":"Point"}
}