{
  "type": "Feature",
  "properties": {
    "iso:country":"US",
    "sg:address":"535 N Michigan Ave",
    "sg:city":"Chicago",
    "sg:classifiers":[
        {
            "category":"Restaurant",
            "type":"Food & Drink"
        }
    ],
    "sg:phone":"+1 312 644 3524",
    "sg:postcode":"60611",
    "sg:province":"IL",
    "sg:tags":[
        "traditional",
        "american"
    ],
    "sg:website":"www.hillstone.com/#/restaurants/...",
    "wof:name":"Bandera Restaurant",
    "wof:placetype":"venue"
},
  "geometry": {"coordinates":[-87.62400100000001,41.891701],"type":"Point"}
}