{
  "type": "Feature",
  "properties": {
    "iso:country":"US",
    "sg:address":"5419 N Sheridan Rd",
    "sg:city":"Chicago",
    "sg:classifiers":[
        {
            "category":"Professional",
            "subcategory":"Management & Consulting",
            "type":"Services"
        },
        {
            "category":"Professional",
            "subcategory":"Computer Services",
            "type":"Services"
        }
    ],
    "sg:phone":"+1 773 506 1700",
    "sg:postcode":"60640",
    "sg:province":"IL",
    "sg:tags":[
        "consultant",
        "programming",
        "system",
        "business"
    ],
    "wof:name":"Consolidated Information Svcs",
    "wof:placetype":"venue"
},
  "geometry": {"coordinates":[-87.655018,41.980238],"type":"Point"}
}