{
  "type": "Feature",
  "properties": {
    "iso:country":"US",
    "sg:address":"414 Spruce Ln",
    "sg:city":"Crystal Lake",
    "sg:classifiers":[
        {
            "category":"Professional",
            "subcategory":"Management & Consulting",
            "type":"Services"
        }
    ],
    "sg:phone":"+1 815 455 6535",
    "sg:postcode":"60014",
    "sg:province":"IL",
    "sg:tags":[
        "development",
        "new",
        "product",
        "design",
        "engineering"
    ],
    "wof:name":"Design 4 Plastics Inc",
    "wof:placetype":"venue"
},
  "geometry": {"coordinates":[-88.341241,42.22919],"type":"Point"}
}