{
  "type": "Feature",
  "properties": {
    "addr:full":"1725 Jenks St Evanston IL 60201",
    "addr:housenumber":"1725",
    "addr:postcode":"60201",
    "addr:street":"Jenks St",
    "iso:country":"US",
    "sg:address":"1725 Jenks St",
    "sg:city":"Evanston",
    "sg:classifiers":[
        {
            "category":"Professional",
            "subcategory":"Management & Consulting",
            "type":"Services"
        }
    ],
    "sg:phone":"+1 847 328 7889",
    "sg:postcode":"60201",
    "sg:province":"IL",
    "sg:tags":[
        "marketing"
    ],
    "wof:name":"Strategic Solutions Group",
    "wof:placetype":"venue"
},
  "geometry": {"coordinates":[-87.695961,42.067733],"type":"Point"}
}