{
  "type": "Feature",
  "properties": {
    "addr:full":"4701 W Rice St Chicago IL 60651",
    "addr:housenumber":"4701",
    "addr:postcode":"60651",
    "addr:street":"W Rice St",
    "iso:country":"US",
    "sg:address":"4701 W Rice St",
    "sg:city":"Chicago",
    "sg:classifiers":[
        {
            "category":"Manufacturing",
            "subcategory":"Rubber & Plastics",
            "type":"Manufacturing & Wholesale Goods"
        }
    ],
    "sg:phone":"+1 773 626 8800",
    "sg:postcode":"60651",
    "sg:province":"IL",
    "sg:tags":[
        "gaskets-manufacturers"
    ],
    "sg:website":"http://www.chambersgasket.com",
    "wof:name":"Chambers Gasket & Manufacturing Co",
    "wof:placetype":"venue"
},
  "geometry": {"coordinates":[-87.74355300000001,41.895981],"type":"Point"}
}