{
  "type": "Feature",
  "properties": {
    "iso:country":"US",
    "sg:address":"2075 Sweets Dr",
    "sg:city":"Carbondale",
    "sg:classifiers":[
        {
            "category":"Home & Garden",
            "subcategory":"Furniture",
            "type":"Retail Goods"
        },
        {
            "category":"Home & Garden",
            "subcategory":"Carpets & Floor Coverings",
            "type":"Retail Goods"
        }
    ],
    "sg:phone":"+1 618 549 8332",
    "sg:postcode":"62902",
    "sg:province":"IL",
    "sg:tags":[
        "store",
        "mattress"
    ],
    "wof:name":"Furniture King",
    "wof:placetype":"venue"
},
  "geometry": {"coordinates":[-89.15619700000001,37.733299],"type":"Point"}
}