{
  "type": "Feature",
  "properties": {
    "addr:full":"710 Landwehr Rd Northbrook IL 60062",
    "addr:housenumber":"710",
    "addr:postcode":"60062",
    "addr:street":"Landwehr Rd",
    "iso:country":"US",
    "sg:address":"710 Landwehr Rd",
    "sg:city":"Northbrook",
    "sg:classifiers":[
        {
            "category":"Building & Trades",
            "subcategory":"Construction",
            "type":"Services"
        },
        {
            "category":"Home & Garden",
            "subcategory":"Furniture",
            "type":"Retail Goods"
        }
    ],
    "sg:phone":"+1 847 559 1095",
    "sg:postcode":"60062",
    "sg:province":"IL",
    "sg:tags":[
        "equipment",
        "contractor",
        "material",
        "kitchen",
        "cabinet"
    ],
    "wof:name":"Cabinetpro Inc",
    "wof:placetype":"venue"
},
  "geometry": {"coordinates":[-87.86124100000001,42.141028],"type":"Point"}
}