{
  "type": "Feature",
  "properties": {
    "addr:full":"229 N Church St Rockford IL 61101",
    "addr:housenumber":"229",
    "addr:postcode":"61101",
    "addr:street":"N Church St",
    "iso:country":"US",
    "sg:address":"229 N Church St",
    "sg:city":"Rockford",
    "sg:classifiers":[
        {
            "category":"Organizations",
            "subcategory":"Non-profit Organization",
            "type":"Services"
        }
    ],
    "sg:phone":"+1 815 968 0333",
    "sg:postcode":"61101",
    "sg:province":"IL",
    "sg:tags":[
        "information",
        "alcoholism",
        "treatment"
    ],
    "wof:name":"Alcoholics Anonymous",
    "wof:placetype":"venue"
},
  "geometry": {"coordinates":[-89.09450099999999,42.273372],"type":"Point"}
}