{
  "type": "Feature",
  "properties": {
    "addr:full":"6263 N McCormick Road Lincolnwood IL 60712",
    "addr:housenumber":"6263",
    "addr:postcode":"il 60712",
    "addr:street":"N Mccormick Road",
    "iso:country":"US",
    "sg:address":"6263 N McCormick Road",
    "sg:city":"Lincolnwood",
    "sg:classifiers":[
        {
            "category":"Restaurant",
            "type":"Food & Drink"
        }
    ],
    "sg:phone":"+1 773 866 1601",
    "sg:postcode":"60712",
    "sg:province":"IL",
    "wof:name":"Uncle's Restaurant",
    "wof:placetype":"venue"
},
  "geometry": {"coordinates":[-87.71296700000001,41.995342],"type":"Point"}
}