{
  "type": "Feature",
  "properties": {
    "iso:country":"US",
    "sg:address":"4901 41st St",
    "sg:city":"Moline",
    "sg:classifiers":[
        {
            "category":"Retail",
            "subcategory":"Auto Repair",
            "type":"Services"
        }
    ],
    "sg:phone":"+1 309 764 3981",
    "sg:postcode":"61265",
    "sg:province":"IL",
    "sg:tags":[
        "body",
        "shop"
    ],
    "wof:name":"Speed & Floyd Collision Repair",
    "wof:placetype":"venue"
},
  "geometry": {"coordinates":[-90.47110000000001,41.467899],"type":"Point"}
}