{
  "type": "Feature",
  "properties": {
    "addr:full":"3243 Harlem Ave Berwyn IL 60402",
    "addr:housenumber":"3243",
    "addr:postcode":"60402",
    "addr:street":"Harlem Ave",
    "iso:country":"US",
    "sg:address":"3243 Harlem Ave",
    "sg:city":"Berwyn",
    "sg:classifiers":[
        {
            "category":"Bars & Pubs",
            "subcategory":"Sports Bar",
            "type":"Food & Drink"
        }
    ],
    "sg:phone":"+1 708 484 8895",
    "sg:postcode":"60402",
    "sg:province":"IL",
    "wof:name":"Alfonso Sports Bar",
    "wof:placetype":"venue"
},
  "geometry": {"coordinates":[-87.802757,41.832342],"type":"Point"}
}