{
  "type": "Feature",
  "properties": {
    "addr:full":"416 W 97th St Chicago IL 60628",
    "addr:housenumber":"416",
    "addr:postcode":"60628",
    "addr:street":"W 97Th St",
    "iso:country":"US",
    "sg:address":"416 W 97th St",
    "sg:city":"Chicago",
    "sg:classifiers":[
        {
            "category":"Professional",
            "subcategory":"Detective & Security Services",
            "type":"Services"
        }
    ],
    "sg:phone":"+1 773 269 0074",
    "sg:postcode":"60628",
    "sg:province":"IL",
    "sg:tags":[
        "system"
    ],
    "wof:name":"All Systems Installation",
    "wof:placetype":"venue"
},
  "geometry": {"coordinates":[-87.634568,41.7182],"type":"Point"}
}