{
  "type": "Feature",
  "properties": {
    "addr:full":"2359 Sycamore Rd Dekalb IL 60115",
    "addr:housenumber":"2359",
    "addr:postcode":"60115",
    "addr:street":"Sycamore Rd",
    "iso:country":"US",
    "sg:address":"2359 Sycamore Rd",
    "sg:city":"Dekalb",
    "sg:classifiers":[
        {
            "category":"Shopping",
            "subcategory":"Department Store",
            "type":"Retail Goods"
        },
        {
            "category":"Shopping",
            "subcategory":"Discount & Variety Stores",
            "type":"Retail Goods"
        }
    ],
    "sg:phone":"+1 815 748 4443",
    "sg:postcode":"60115",
    "sg:province":"IL",
    "wof:name":"Deals-Nothing Over A Dollar",
    "wof:placetype":"venue"
},
  "geometry": {"coordinates":[-88.725195,41.952516],"type":"Point"}
}