{
  "type": "Feature",
  "properties": {
    "iso:country":"US",
    "sg:address":"1658 N Milwaukee Ave Ste 424",
    "sg:city":"Chicago",
    "sg:classifiers":[
        {
            "category":"Food & Beverages",
            "subcategory":"Liquor & Beverages",
            "type":"Retail Goods"
        }
    ],
    "sg:postcode":"60647",
    "sg:province":"IL",
    "sg:tags":[
        "beer",
        "spirit",
        "wine"
    ],
    "sg:website":"www.drinkfour.com/",
    "wof:name":"Four Loko",
    "wof:placetype":"venue"
},
  "geometry": {"coordinates":[-87.67968,41.911707],"type":"Point"}
}