{
  "type": "Feature",
  "properties": {
    "addr:full":"645 N Kingsbury St Chicago IL 60610",
    "addr:housenumber":"645",
    "addr:postcode":"60610",
    "addr:street":"N Kingsbury St",
    "iso:country":"US",
    "sg:address":"645 N Kingsbury St",
    "sg:city":"Chicago",
    "sg:classifiers":[
        {
            "category":"Real Estate",
            "subcategory":"Real Estate Services",
            "type":"Services"
        }
    ],
    "sg:phone":"+1 312 943 3143",
    "sg:postcode":"60610",
    "sg:province":"IL",
    "sg:tags":[
        "management",
        "property"
    ],
    "wof:name":"Admirals Pointe",
    "wof:placetype":"venue"
},
  "geometry": {"coordinates":[-87.641403,41.893398],"type":"Point"}
}