{
  "type": "Feature",
  "properties": {
    "iso:country":"US",
    "sg:address":"120 W South Ave",
    "sg:city":"Sumner",
    "sg:classifiers":[
        {
            "category":"Government",
            "subcategory":"Post Office",
            "type":"Public Place"
        }
    ],
    "sg:phone":"+1 618 936 2613",
    "sg:postcode":"62466",
    "sg:province":"IL",
    "sg:tags":[
        "postal",
        "us"
    ],
    "wof:name":"US Post Office",
    "wof:placetype":"venue"
},
  "geometry": {"coordinates":[-87.861913,38.715649],"type":"Point"}
}