{
  "type": "Feature",
  "properties": {
    "addr:full":"114 N Main St Ohio IL 61349",
    "addr:housenumber":"114",
    "addr:postcode":"61349",
    "addr:street":"N Main St",
    "iso:country":"US",
    "sg:address":"114 N Main St",
    "sg:city":"Ohio",
    "sg:classifiers":[
        {
            "category":"Wholesale",
            "subcategory":"Medical Equipment & Supplies",
            "type":"Manufacturing & Wholesale Goods"
        }
    ],
    "sg:phone":"+1 815 376 7005",
    "sg:postcode":"61349",
    "sg:province":"IL",
    "sg:tags":[
        "physician",
        "surgeon"
    ],
    "wof:name":"Whitehall Medical Supply",
    "wof:placetype":"venue"
},
  "geometry": {"coordinates":[-89.46167199999999,41.558901],"type":"Point"}
}