{
  "type": "Feature",
  "properties": {
    "iso:country":"US",
    "sg:address":"1015 W Jefferson St",
    "sg:city":"Rockford",
    "sg:classifiers":[
        {
            "category":"Social Services",
            "type":"Services"
        }
    ],
    "sg:phone":"+1 815 962 7373",
    "sg:postcode":"61101",
    "sg:province":"IL",
    "sg:tags":[
        "organization",
        "welfare"
    ],
    "wof:name":"Camaraderie Arts",
    "wof:placetype":"venue"
},
  "geometry": {"coordinates":[-89.10413800000001,42.277697],"type":"Point"}
}