{
  "type": "Feature",
  "properties": {
    "iso:country":"US",
    "sg:address":"9301 Skokie Blvd",
    "sg:city":"Skokie",
    "sg:classifiers":[
        {
            "category":"Autos & Motor Vehicles",
            "subcategory":"Fuel & Gas Station",
            "type":"Retail Goods"
        }
    ],
    "sg:phone":"+1 847 329 4483",
    "sg:postcode":"60077",
    "sg:province":"IL",
    "sg:tags":[
        "oil"
    ],
    "wof:name":"Cdent LLC Shell",
    "wof:placetype":"venue"
},
  "geometry": {"coordinates":[-87.746888,42.050816],"type":"Point"}
}