{
  "type": "Feature",
  "properties": {
    "addr:full":"1107 N del Mar Dr Palatine IL 60067",
    "addr:housenumber":"1107",
    "addr:postcode":"60067",
    "addr:street":"N Del Mar Dr",
    "iso:country":"US",
    "sg:address":"1107 N del Mar Dr",
    "sg:city":"Palatine",
    "sg:classifiers":[
        {
            "category":"Shopping",
            "type":"Retail Goods"
        }
    ],
    "sg:phone":"+1 847 991 5767",
    "sg:postcode":"60067",
    "sg:province":"IL",
    "sg:tags":[
        "equipment",
        "telephone",
        "supply"
    ],
    "wof:name":"CPT Network Solutions",
    "wof:placetype":"venue"
},
  "geometry": {"coordinates":[-88.040565,42.135396],"type":"Point"}
}