{
  "type": "Feature",
  "properties": {
    "iso:country":"US",
    "sg:address":"2950 Lewallen Pl",
    "sg:city":"Decatur",
    "sg:classifiers":[
        {
            "category":"Sports & Exercise",
            "subcategory":"Sports Center",
            "type":"Entertainment"
        }
    ],
    "sg:phone":"+1 217 422 7317",
    "sg:postcode":"62521",
    "sg:province":"IL",
    "wof:name":"Abe Lincoln Miata Club",
    "wof:placetype":"venue"
},
  "geometry": {"coordinates":[-88.902271,39.805072],"type":"Point"}
}