{
  "type": "Feature",
  "properties": {
    "addr:full":"2500 S Millard Avenue Chicago IL 60623",
    "addr:housenumber":"2500",
    "addr:postcode":"60623",
    "addr:street":"S Millard Avenue",
    "iso:country":"US",
    "sg:address":"2500 S Millard Avenue",
    "sg:city":"Chicago",
    "sg:classifiers":[
        {
            "category":"Shopping",
            "subcategory":"Florist",
            "type":"Retail Goods"
        }
    ],
    "sg:phone":"+1 773 522 0035",
    "sg:postcode":"60623",
    "sg:province":"IL",
    "wof:name":"Tiffany's Flower Shop",
    "wof:placetype":"venue"
},
  "geometry": {"coordinates":[-87.71597800000001,41.846125],"type":"Point"}
}