{
  "type": "Feature",
  "properties": {
    "iso:country":"US",
    "sg:address":"472 S Kenilworth Ave",
    "sg:city":"Elmhurst",
    "sg:classifiers":[
        {
            "category":"Travel",
            "subcategory":"Travel Agent",
            "type":"Entertainment"
        }
    ],
    "sg:phone":"+1 630 532 5050",
    "sg:postcode":"60126",
    "sg:province":"IL",
    "sg:tags":[
        "operator",
        "tour"
    ],
    "wof:name":"Earth Is Yours Walking Tours",
    "wof:placetype":"venue"
},
  "geometry": {"coordinates":[-87.938464,41.885186],"type":"Point"}
}