{
  "type": "Feature",
  "properties": {
    "iso:country":"US",
    "sg:address":"3821 W. Montrose Avenue",
    "sg:city":"Chicago",
    "sg:classifiers":[
        {
            "category":"Arena",
            "subcategory":"Sports Club",
            "type":"Entertainment"
        }
    ],
    "sg:phone":"+1 773 478 8187",
    "sg:postcode":"60618",
    "sg:province":"IL",
    "sg:tags":[
        "martial art"
    ],
    "wof:name":"Acedemia of Kung Fu",
    "wof:placetype":"venue"
},
  "geometry": {"coordinates":[-87.72370100000001,41.960899],"type":"Point"}
}