{
  "type": "Feature",
  "properties": {
    "iso:country":"US",
    "sg:address":"219 S 2nd St",
    "sg:city":"Rockford",
    "sg:classifiers":[
        {
            "category":"Organizations",
            "subcategory":"Religious Organization",
            "type":"Services"
        }
    ],
    "sg:phone":"+1 815 490 9178",
    "sg:postcode":"61104",
    "sg:province":"IL",
    "sg:tags":[
        "church"
    ],
    "wof:name":"Rockford New Hope Inc",
    "wof:placetype":"venue"
},
  "geometry": {"coordinates":[-89.089101,42.266071],"type":"Point"}
}