{
  "type": "Feature",
  "properties": {
    "addr:full":"3217 N Keating Ave Chicago IL 60641",
    "addr:housenumber":"3217",
    "addr:postcode":"60641",
    "addr:street":"N Keating Ave",
    "iso:country":"US",
    "sg:address":"3217 N Keating Ave",
    "sg:city":"Chicago",
    "sg:classifiers":[
        {
            "category":"Manufacturing",
            "subcategory":"Glass & Minerals",
            "type":"Manufacturing & Wholesale Goods"
        }
    ],
    "sg:phone":"+1 847 962 7763",
    "sg:postcode":"60641",
    "sg:province":"IL",
    "sg:tags":[
        "ornamental",
        "shape",
        "carved",
        "glass-beveled",
        "circle",
        "special",
        "etched"
    ],
    "wof:name":"Streamwood Glass",
    "wof:placetype":"venue"
},
  "geometry": {"coordinates":[-87.74518399999999,41.93914],"type":"Point"}
}