{
  "type": "Feature",
  "properties": {
    "iso:country":"US",
    "sg:address":"5423 W Washington Blvd",
    "sg:city":"Chicago",
    "sg:classifiers":[
        {
            "category":"Professional",
            "type":"Services"
        }
    ],
    "sg:phone":"+1 773 626 2453",
    "sg:postcode":"60644",
    "sg:province":"IL",
    "sg:tags":[
        "establishment"
    ],
    "wof:name":"Deanna Harris LLC",
    "wof:placetype":"venue"
},
  "geometry": {"coordinates":[-87.761483,41.882214],"type":"Point"}
}