{
  "type": "Feature",
  "properties": {
    "addr:full":"2273 E 1700th Ave Teutopolis IL 62467",
    "addr:housenumber":"2273",
    "addr:postcode":"62467",
    "addr:street":"E 1700Th Ave",
    "iso:country":"US",
    "sg:address":"2273 E 1700th Ave",
    "sg:city":"Teutopolis",
    "sg:classifiers":[
        {
            "category":"Farming",
            "subcategory":"Farm",
            "type":"Manufacturing & Wholesale Goods"
        }
    ],
    "sg:phone":"+1 217 683 2352",
    "sg:postcode":"62467",
    "sg:province":"IL",
    "sg:tags":[
        "crop",
        "general"
    ],
    "wof:name":"Mammoser Farm Inc",
    "wof:placetype":"venue"
},
  "geometry": {"coordinates":[-88.330546,39.102272],"type":"Point"}
}