{
  "type": "Feature",
  "properties": {
    "addr:full":"634 Countryside Hwy Mundelein IL 60060",
    "addr:housenumber":"634",
    "addr:postcode":"60060",
    "addr:street":"Countryside Hwy",
    "iso:country":"US",
    "sg:address":"634 Countryside Hwy",
    "sg:city":"Mundelein",
    "sg:classifiers":[
        {
            "category":"Education",
            "subcategory":"School",
            "type":"Public Place"
        }
    ],
    "sg:phone":"+1 847 949 0991",
    "sg:postcode":"60060",
    "sg:province":"IL",
    "wof:name":"Fairhaven Elementary School",
    "wof:placetype":"venue"
},
  "geometry": {"coordinates":[-87.994147,42.264097],"type":"Point"}
}