{
  "type": "Feature",
  "properties": {
    "iso:country":"US",
    "sg:address":"1185 N Bridge St",
    "sg:city":"Yorkville",
    "sg:classifiers":[
        {
            "category":"Restaurant",
            "type":"Food & Drink"
        }
    ],
    "sg:menulink":"http://www.allmenus.com/il/bristol/68934-rosatis-pizza/menu/",
    "sg:phone":"+1 630 553 5533",
    "sg:postcode":"60560",
    "sg:province":"IL",
    "sg:tags":[
        "american",
        "pizza"
    ],
    "wof:name":"Rosati's Pizza",
    "wof:placetype":"venue"
},
  "geometry": {"coordinates":[-88.442868,41.655222],"type":"Point"}
}