{
  "type": "Feature",
  "properties": {
    "iso:country":"US",
    "sg:address":"1490 Jasper Dr",
    "sg:city":"Wheaton",
    "sg:classifiers":[
        {
            "category":"Professional",
            "type":"Services"
        },
        {
            "category":"Manufacturing",
            "subcategory":"Tools & Machinery",
            "type":"Manufacturing & Wholesale Goods"
        }
    ],
    "sg:phone":"+1 630 653 0387",
    "sg:postcode":"60187",
    "sg:province":"IL",
    "sg:tags":[
        "consulting",
        "scientist",
        "industry",
        "business",
        "mfg"
    ],
    "wof:name":"Regunathan & Assoc Inc",
    "wof:placetype":"venue"
},
  "geometry": {"coordinates":[-88.084032,41.824276],"type":"Point"}
}