{
  "type": "Feature",
  "properties": {
    "iso:country":"US",
    "sg:address":"206 W Front St",
    "sg:city":"Annawan",
    "sg:classifiers":[
        {
            "category":"Community Center",
            "type":"Public Place"
        },
        {
            "category":"Government",
            "subcategory":"Office",
            "type":"Public Place"
        }
    ],
    "sg:phone":"+1 309 935 6742",
    "sg:postcode":"61234",
    "sg:province":"IL",
    "sg:tags":[
        "recreation",
        "government-city",
        "township",
        "village"
    ],
    "wof:name":"Annawan City Of Community Center",
    "wof:placetype":"venue"
},
  "geometry": {"coordinates":[-89.90637,41.397096],"type":"Point"}
}