{
  "type": "Feature",
  "properties": {
    "iso:country":"US",
    "sg:address":"214 E Lincoln Hwy",
    "sg:city":"Dekalb",
    "sg:classifiers":[
        {
            "category":"Fast Food",
            "type":"Food & Drink"
        },
        {
            "category":"Restaurant",
            "type":"Food & Drink"
        },
        {
            "category":"Bars & Pubs",
            "subcategory":"Lounge",
            "type":"Food & Drink"
        }
    ],
    "sg:phone":"+1 815 758 2677",
    "sg:postcode":"60115",
    "sg:province":"IL",
    "sg:tags":[
        "mexican",
        "take",
        "cocktail"
    ],
    "sg:website":"http://www.eduardosdekalb.com",
    "wof:name":"Eduardo's Mexican Restaurant",
    "wof:placetype":"venue"
},
  "geometry": {"coordinates":[-88.75254200000001,41.930292],"type":"Point"}
}