{
  "type": "Feature",
  "properties": {
    "iso:country":"US",
    "sg:address":"1798 Busse Hwy",
    "sg:city":"Des Plaines",
    "sg:classifiers":[
        {
            "category":"Freight",
            "type":"Transportation"
        }
    ],
    "sg:phone":"+1 847 827 8888",
    "sg:postcode":"60016",
    "sg:province":"IL",
    "sg:tags":[
        "insurance",
        "special"
    ],
    "wof:name":"U-Stor-It",
    "wof:placetype":"venue"
},
  "geometry": {"coordinates":[-87.881368,42.039244],"type":"Point"}
}