{
  "type": "Feature",
  "properties": {
    "addr:full":"167 N Racine Avenue Chicago IL 60607",
    "addr:housenumber":"167",
    "addr:postcode":"60607",
    "addr:street":"N Racine Avenue",
    "iso:country":"US",
    "sg:address":"167 N Racine Avenue",
    "sg:city":"Chicago",
    "sg:classifiers":[
        {
            "category":"Shopping",
            "subcategory":"Antiques",
            "type":"Retail Goods"
        }
    ],
    "sg:phone":"+1 312 850 0071",
    "sg:postcode":"60607",
    "sg:province":"IL",
    "wof:name":"Eurocraft",
    "wof:placetype":"venue"
},
  "geometry": {"coordinates":[-87.656735,41.885071],"type":"Point"}
}