{
  "type": "Feature",
  "properties": {
    "addr:full":"3125 S Ashland Avenue Chicago IL 60608",
    "addr:housenumber":"3125",
    "addr:postcode":"60608",
    "addr:street":"S Ashland Avenue",
    "iso:country":"US",
    "sg:address":"3125 S Ashland Avenue",
    "sg:city":"Chicago",
    "sg:classifiers":[
        {
            "category":"Food & Beverages",
            "subcategory":"Bakery",
            "type":"Retail Goods"
        }
    ],
    "sg:phone":"+1 773 254 4885",
    "sg:postcode":"60608",
    "sg:province":"IL",
    "sg:tags":[
        "sandwich"
    ],
    "sg:website":"www.subway.com",
    "wof:name":"Subway",
    "wof:placetype":"venue"
},
  "geometry": {"coordinates":[-87.665672,41.838215],"type":"Point"}
}