{
  "type": "Feature",
  "properties": {
    "iso:country":"US",
    "sg:address":"7102 Forest Hills Rd",
    "sg:city":"Loves Park",
    "sg:classifiers":[
        {
            "category":"Building & Trades",
            "subcategory":"Cleaning & Sanitation",
            "type":"Services"
        }
    ],
    "sg:phone":"+1 815 395 8635",
    "sg:postcode":"61111",
    "sg:province":"IL",
    "sg:tags":[
        "janitor",
        "maintenance"
    ],
    "wof:name":"Classy Touch Cleaning Service",
    "wof:placetype":"venue"
},
  "geometry": {"coordinates":[-89.02389700000001,42.32536],"type":"Point"}
}