{
  "type": "Feature",
  "properties": {
    "iso:country":"US",
    "sg:address":"425 A St",
    "sg:city":"Charleston",
    "sg:classifiers":[
        {
            "category":"Autos & Motor Vehicles",
            "subcategory":"Automobile Sales",
            "type":"Retail Goods"
        }
    ],
    "sg:phone":"+1 217 345 4106",
    "sg:postcode":"61920",
    "sg:province":"IL",
    "sg:tags":[
        "car",
        "dealer"
    ],
    "wof:name":"Stark's Auto Sales",
    "wof:placetype":"venue"
},
  "geometry": {"coordinates":[-88.183027,39.501556],"type":"Point"}
}