{
  "type": "Feature",
  "properties": {
    "addr:full":"514 Lakehurst Rd Waukegan IL 60085",
    "addr:housenumber":"514",
    "addr:postcode":"60085",
    "addr:street":"Lakehurst Rd",
    "iso:country":"US",
    "sg:address":"514 Lakehurst Rd",
    "sg:city":"Waukegan",
    "sg:classifiers":[
        {
            "category":"Wholesale",
            "subcategory":"Machinery & Supplies",
            "type":"Manufacturing & Wholesale Goods"
        }
    ],
    "sg:phone":"+1 847 912 5584",
    "sg:postcode":"60085",
    "sg:province":"IL",
    "sg:tags":[
        "hardware",
        "marine"
    ],
    "wof:name":"Anz Enterprise Inc",
    "wof:placetype":"venue"
},
  "geometry": {"coordinates":[-87.90057899999999,42.340171],"type":"Point"}
}