{
  "type": "Feature",
  "properties": {
    "iso:country":"US",
    "sg:address":"519 S Consumers Ave",
    "sg:city":"Palatine",
    "sg:classifiers":[
        {
            "category":"Sports & Exercise",
            "subcategory":"Bowling",
            "type":"Entertainment"
        }
    ],
    "sg:phone":"+1 847 392 8290",
    "sg:postcode":"60074",
    "sg:province":"IL",
    "sg:tags":[
        "center"
    ],
    "wof:name":"Brunswick Zone",
    "wof:placetype":"venue"
},
  "geometry": {"coordinates":[-88.011066,42.097104],"type":"Point"}
}