{
  "type": "Feature",
  "properties": {
    "iso:country":"US",
    "sg:address":"907 N 87th St",
    "sg:city":"East Saint Louis",
    "sg:classifiers":[
        {
            "category":"Social Services",
            "subcategory":"Child Care",
            "type":"Services"
        }
    ],
    "sg:phone":"+1 618 398 7390",
    "sg:postcode":"62203",
    "sg:province":"IL",
    "sg:tags":[
        "day"
    ],
    "wof:name":"Terry Clara",
    "wof:placetype":"venue"
},
  "geometry": {"coordinates":[-90.056241,38.598095],"type":"Point"}
}