{
  "type": "Feature",
  "properties": {
    "addr:full":"1460 N Halsted Ste 404 Chicago IL 60657",
    "addr:housenumber":"1460",
    "addr:postcode":"60657",
    "addr:street":"N Halsted Ste 404",
    "iso:country":"US",
    "sg:address":"1460 N Halsted Ste 404",
    "sg:city":"Chicago",
    "sg:classifiers":[
        {
            "category":"Health Services",
            "subcategory":"Doctor",
            "type":"Services"
        }
    ],
    "sg:phone":"+1 773 883 0274",
    "sg:postcode":"60657",
    "sg:province":"IL",
    "sg:website":"www.allergists-asthma.com/index....",
    "wof:name":"Steve Handoyo, MD",
    "wof:placetype":"venue"
},
  "geometry": {"coordinates":[-87.648231,41.90787],"type":"Point"}
}