{
  "type": "Feature",
  "properties": {
    "addr:full":"2513 24th St Rock Island IL 61201",
    "addr:housenumber":"2513",
    "addr:postcode":"61201",
    "addr:street":"24Th St",
    "iso:country":"US",
    "sg:address":"2513 24th St",
    "sg:city":"Rock Island",
    "sg:classifiers":[
        {
            "category":"Health Services",
            "subcategory":"Doctor",
            "type":"Services"
        }
    ],
    "sg:phone":"+1 309 794 9365",
    "sg:postcode":"61201",
    "sg:province":"IL",
    "sg:tags":[
        "dentist"
    ],
    "wof:name":"Michael J Nonnenmann LTD",
    "wof:placetype":"venue"
},
  "geometry": {"coordinates":[-90.567089,41.482048],"type":"Point"}
}