{
  "type": "Feature",
  "properties": {
    "iso:country":"US",
    "sg:address":"214 Linden Ave",
    "sg:city":"Lake Forest",
    "sg:classifiers":[
        {
            "category":"Professional",
            "subcategory":"Accounting & Tax Preparation",
            "type":"Services"
        }
    ],
    "sg:phone":"+1 847 735 0493",
    "sg:postcode":"60045",
    "sg:province":"IL",
    "sg:tags":[
        "billing"
    ],
    "wof:name":"JJB Billing Inc",
    "wof:placetype":"venue"
},
  "geometry": {"coordinates":[-87.844377,42.221371],"type":"Point"}
}