{
  "type": "Feature",
  "properties": {
    "iso:country":"US",
    "sg:address":"2991 E 350th Rd",
    "sg:city":"La Salle",
    "sg:classifiers":[
        {
            "category":"Government",
            "subcategory":"Office",
            "type":"Public Place"
        }
    ],
    "sg:phone":"+1   ",
    "sg:postcode":"61301",
    "sg:province":"IL",
    "sg:tags":[
        "transportation"
    ],
    "wof:name":"Division of Highways",
    "wof:placetype":"venue"
},
  "geometry": {"coordinates":[-89.067709,41.367381],"type":"Point"}
}