{
  "type": "Feature",
  "properties": {
    "addr:full":"5710 N Western Avenue Chicago IL 60659",
    "addr:housenumber":"5710",
    "addr:postcode":"60659",
    "addr:street":"N Western Avenue",
    "iso:country":"US",
    "sg:address":"5710 N Western Avenue",
    "sg:city":"Chicago",
    "sg:classifiers":[
        {
            "category":"Restaurant",
            "type":"Food & Drink"
        }
    ],
    "sg:phone":"+1 773 769 9141",
    "sg:postcode":"60659",
    "sg:province":"IL",
    "wof:name":"East Cafe & Restaurant",
    "wof:placetype":"venue"
},
  "geometry": {"coordinates":[-87.689294,41.985312],"type":"Point"}
}