{
  "type": "Feature",
  "properties": {
    "iso:country":"US",
    "sg:address":"5015 N Marmora Ave",
    "sg:city":"Chicago",
    "sg:classifiers":[
        {
            "category":"Building & Trades",
            "subcategory":"Electrical",
            "type":"Services"
        },
        {
            "category":"Retail",
            "subcategory":"Auto Repair",
            "type":"Services"
        }
    ],
    "sg:phone":"+1 773 685 2430",
    "sg:postcode":"60630",
    "sg:province":"IL",
    "sg:tags":[
        "automobile",
        "electrician",
        "electric"
    ],
    "wof:name":"Ominia Builders & Engineers",
    "wof:placetype":"venue"
},
  "geometry": {"coordinates":[-87.77582700000001,41.97274],"type":"Point"}
}