{
  "type": "Feature",
  "properties": {
    "addr:full":"201 W Harlem Ave Monmouth IL 61462",
    "addr:housenumber":"201",
    "addr:postcode":"61462",
    "addr:street":"W Harlem Ave",
    "iso:country":"US",
    "sg:address":"201 W Harlem Ave",
    "sg:city":"Monmouth",
    "sg:classifiers":[
        {
            "category":"Wholesale",
            "subcategory":"Farm Supplies",
            "type":"Manufacturing & Wholesale Goods"
        },
        {
            "category":"Wholesale",
            "subcategory":"Machinery & Supplies",
            "type":"Manufacturing & Wholesale Goods"
        }
    ],
    "sg:phone":"+1 309 734 3541",
    "sg:postcode":"61462",
    "sg:province":"IL",
    "sg:tags":[
        "baling",
        "equipment"
    ],
    "wof:name":"Painter Farm Equipment",
    "wof:placetype":"venue"
},
  "geometry": {"coordinates":[-90.64924600000001,40.921108],"type":"Point"}
}