{
  "type": "Feature",
  "properties": {
    "addr:full":"104 E Madison St Pontiac IL 61764",
    "addr:housenumber":"104",
    "addr:postcode":"61764",
    "addr:street":"E Madison St",
    "iso:country":"US",
    "sg:address":"104 E Madison St",
    "sg:city":"Pontiac",
    "sg:classifiers":[
        {
            "category":"Professional",
            "subcategory":"Lawyer & Legal Services",
            "type":"Services"
        }
    ],
    "sg:phone":"+1 815 842 0700",
    "sg:postcode":"61764",
    "sg:province":"IL",
    "sg:tags":[
        "attorney",
        "planning",
        "real estate",
        "law",
        "bankruptcy"
    ],
    "sg:website":"http://www.doddlaw.net",
    "wof:name":"Dodd Ludwig Maatuka LLLC",
    "wof:placetype":"venue"
},
  "geometry": {"coordinates":[-88.628593,40.880341],"type":"Point"}
}