{
  "type": "Feature",
  "properties": {
    "iso:country":"US",
    "sg:address":"4777 N Harlem Ave Ste 2",
    "sg:city":"Harwood Heights",
    "sg:classifiers":[
        {
            "category":"Health Services",
            "subcategory":"Doctor",
            "type":"Services"
        }
    ],
    "sg:phone":"+1 708 867 4020",
    "sg:postcode":"60706",
    "sg:province":"IL",
    "wof:name":"Cisneros Alfred MD",
    "wof:placetype":"venue"
},
  "geometry": {"coordinates":[-87.806999,41.967701],"type":"Point"}
}