{
  "type": "Feature",
  "properties": {
    "addr:full":"3020 W 108th Street Chicago IL 60655",
    "addr:housenumber":"3020",
    "addr:postcode":"60655",
    "addr:street":"W 108Th Street",
    "iso:country":"US",
    "sg:address":"3020 W 108th Street",
    "sg:city":"Chicago",
    "sg:classifiers":[
        {
            "category":"Education",
            "subcategory":"School",
            "type":"Public Place"
        }
    ],
    "sg:phone":"+1 773 535 2636",
    "sg:postcode":"60655",
    "sg:province":"IL",
    "sg:tags":[
        "high",
        "middle",
        "elementary"
    ],
    "wof:name":"Schools Public",
    "wof:placetype":"venue"
},
  "geometry": {"coordinates":[-87.696697,41.697197],"type":"Point"}
}