{
  "type": "Feature",
  "properties": {
    "iso:country":"US",
    "sg:address":"20 Grant St",
    "sg:city":"Crystal Lake",
    "sg:classifiers":[
        {
            "category":"Professional",
            "subcategory":"Lawyer & Legal Services",
            "type":"Services"
        }
    ],
    "sg:phone":"+1 815 459 5300",
    "sg:postcode":"60014",
    "sg:province":"IL",
    "sg:tags":[
        "attorney"
    ],
    "wof:name":"Cowlin Currin & Coppedge",
    "wof:placetype":"venue"
},
  "geometry": {"coordinates":[-88.31972399999999,42.242469],"type":"Point"}
}