{
  "type": "Feature",
  "properties": {
    "iso:country":"US",
    "sg:address":"1120 Manhattan Rd",
    "sg:city":"Joliet",
    "sg:classifiers":[
        {
            "category":"Building & Trades",
            "subcategory":"Plumbing",
            "type":"Services"
        }
    ],
    "sg:phone":"+1 815 726 0477",
    "sg:postcode":"60433",
    "sg:province":"IL",
    "sg:tags":[
        "heating",
        "contractor"
    ],
    "wof:name":"Custom Fabricating Htg & Clng",
    "wof:placetype":"venue"
},
  "geometry": {"coordinates":[-88.05111100000001,41.493691],"type":"Point"}
}