{
  "type": "Feature",
  "properties": {
    "addr:full":"7001 S Western Avenue Chicago IL 60636",
    "addr:housenumber":"7001",
    "addr:postcode":"60636",
    "addr:street":"S Western Avenue",
    "iso:country":"US",
    "sg:address":"7001 S Western Avenue",
    "sg:city":"Chicago",
    "sg:classifiers":[
        {
            "category":"Retail",
            "subcategory":"Auto Rental",
            "type":"Services"
        }
    ],
    "sg:phone":"+1 773 778 2000",
    "sg:postcode":"60636",
    "sg:province":"IL",
    "sg:tags":[
        "car"
    ],
    "sg:website":"www.enterprise.com",
    "wof:name":"Enterprise Rent-A-Car",
    "wof:placetype":"venue"
},
  "geometry": {"coordinates":[-87.68305700000001,41.765986],"type":"Point"}
}