{
  "type": "Feature",
  "properties": {
    "addr:full":"401 Country Club Rd Crystal Lake IL 60014",
    "addr:housenumber":"401",
    "addr:postcode":"60014",
    "addr:street":"Country Club Rd",
    "iso:country":"US",
    "sg:address":"401 Country Club Rd",
    "sg:city":"Crystal Lake",
    "sg:classifiers":[
        {
            "category":"Health Services",
            "subcategory":"Health Practitioner",
            "type":"Services"
        }
    ],
    "sg:phone":"+1 815 479 9022",
    "sg:postcode":"60014",
    "sg:province":"IL",
    "wof:name":"Weeden Mary R Rn Lcsw",
    "wof:placetype":"venue"
},
  "geometry": {"coordinates":[-88.344706,42.229856],"type":"Point"}
}