{
  "type": "Feature",
  "properties": {
    "iso:country":"US",
    "sg:address":"53 Summit Ave",
    "sg:city":"Park Ridge",
    "sg:classifiers":[
        {
            "category":"Personal",
            "subcategory":"Shoe Repair & Shine",
            "type":"Services"
        }
    ],
    "sg:phone":"+1 847 698 9524",
    "sg:postcode":"60068",
    "sg:province":"IL",
    "sg:tags":[
        "parlor"
    ],
    "wof:name":"Jims Shoe & Luggage Repair",
    "wof:placetype":"venue"
},
  "geometry": {"coordinates":[-87.831715,42.011768],"type":"Point"}
}