{
  "type": "Feature",
  "properties": {
    "addr:full":"980 Ensell Rd Lake Zurich IL 60047",
    "addr:housenumber":"980",
    "addr:postcode":"60047",
    "addr:street":"Ensell Rd",
    "iso:country":"US",
    "sg:address":"980 Ensell Rd",
    "sg:city":"Lake Zurich",
    "sg:classifiers":[
        {
            "category":"Manufacturing",
            "subcategory":"Tools & Machinery",
            "type":"Manufacturing & Wholesale Goods"
        }
    ],
    "sg:phone":"+1 847 438 0334",
    "sg:postcode":"60047",
    "sg:province":"IL",
    "sg:tags":[
        "control",
        "equipment",
        "air",
        "pollution"
    ],
    "sg:website":"www.cpilink.com",
    "wof:name":"Catalytic Products Intl Inc",
    "wof:placetype":"venue"
},
  "geometry": {"coordinates":[-88.06796900000001,42.204618],"type":"Point"}
}