{
  "type": "Feature",
  "properties": {
    "iso:country":"US",
    "sg:address":"5628 N Keystone Ave",
    "sg:city":"Chicago",
    "sg:classifiers":[
        {
            "category":"Building & Trades",
            "subcategory":"Pest Control",
            "type":"Services"
        }
    ],
    "sg:phone":"+1 847 878 9554",
    "sg:postcode":"60646",
    "sg:province":"IL",
    "wof:name":"Gauntlet Pest Control",
    "wof:placetype":"venue"
},
  "geometry": {"coordinates":[-87.729753,41.983874],"type":"Point"}
}