{
  "type": "Feature",
  "properties": {
    "iso:country":"US",
    "sg:address":"609 S Glover Ave",
    "sg:city":"Urbana",
    "sg:classifiers":[
        {
            "category":"Building & Trades",
            "subcategory":"Construction",
            "type":"Services"
        }
    ],
    "sg:phone":"+1 217 328 0333",
    "sg:postcode":"61802",
    "sg:province":"IL",
    "sg:tags":[
        "painter"
    ],
    "wof:name":"Aesthetic Enterprises",
    "wof:placetype":"venue"
},
  "geometry": {"coordinates":[-88.193416,40.108647],"type":"Point"}
}