{
  "type": "Feature",
  "properties": {
    "addr:full":"401 N Michigan Ave Ste 2500 Chicago IL 60611",
    "addr:housenumber":"401",
    "addr:postcode":"60611",
    "addr:street":"N Michigan Ave Ste 2500",
    "iso:country":"US",
    "sg:address":"401 N Michigan Ave Ste 2500",
    "sg:city":"Chicago",
    "sg:classifiers":[
        {
            "category":"Wholesale",
            "subcategory":"Medical Equipment & Supplies",
            "type":"Manufacturing & Wholesale Goods"
        },
        {
            "category":"Shopping",
            "subcategory":"Pharmacy",
            "type":"Retail Goods"
        },
        {
            "category":"Health Services",
            "subcategory":"Dentist",
            "type":"Services"
        }
    ],
    "sg:phone":"+1 312 644 9388",
    "sg:postcode":"60611",
    "sg:province":"IL",
    "sg:tags":[
        "home",
        "dental",
        "care"
    ],
    "wof:name":"Cosmedent Inc",
    "wof:placetype":"venue"
},
  "geometry": {"coordinates":[-87.624165,41.889414],"type":"Point"}
}