{
  "type": "Feature",
  "properties": {
    "iso:country":"US",
    "sg:address":"110 S Mark Ct",
    "sg:city":"Carbondale",
    "sg:classifiers":[
        {
            "category":"Building & Trades",
            "subcategory":"Landscaping Services",
            "type":"Services"
        }
    ],
    "sg:phone":"+1 618 549 0525",
    "sg:postcode":"62901",
    "sg:province":"IL",
    "wof:name":"Joyce Lees Mowing Service",
    "wof:placetype":"venue"
},
  "geometry": {"coordinates":[-89.258708,37.725482],"type":"Point"}
}