{
  "type": "Feature",
  "properties": {
    "iso:country":"US",
    "sg:address":"8123 S Cottage Grove Ave",
    "sg:city":"Chicago",
    "sg:classifiers":[
        {
            "category":"Personal",
            "subcategory":"Nail Salon",
            "type":"Services"
        }
    ],
    "sg:phone":"+1 773 723 6596",
    "sg:postcode":"60619",
    "sg:province":"IL",
    "wof:name":"Brother Kahniyah Pedicure",
    "wof:placetype":"venue"
},
  "geometry": {"coordinates":[-87.605121,41.747209],"type":"Point"}
}