{
  "type": "Feature",
  "properties": {
    "iso:country":"US",
    "sg:address":"820 State St",
    "sg:city":"Quincy",
    "sg:classifiers":[
        {
            "category":"Professional",
            "subcategory":"Management & Consulting",
            "type":"Services"
        },
        {
            "category":"Insurance",
            "subcategory":"Hazard Insurance",
            "type":"Services"
        },
        {
            "category":"Banks & Credit Unions",
            "subcategory":"Financial Services",
            "type":"Services"
        }
    ],
    "sg:phone":"+1 217 223 0046",
    "sg:postcode":"62301",
    "sg:province":"IL",
    "sg:tags":[
        "consultant",
        "financing",
        "planning",
        "commercial",
        "business"
    ],
    "wof:name":"David Cawthon Insurance Financial Services",
    "wof:placetype":"venue"
},
  "geometry": {"coordinates":[-91.402956,39.926567],"type":"Point"}
}