{
  "type": "Feature",
  "properties": {
    "addr:full":"6055 W 63rd St Chicago IL 60638",
    "addr:housenumber":"6055",
    "addr:postcode":"60638",
    "addr:street":"W 63Rd St",
    "iso:country":"US",
    "sg:address":"6055 W 63rd St",
    "sg:city":"Chicago",
    "sg:classifiers":[
        {
            "category":"Shopping",
            "type":"Retail Goods"
        },
        {
            "category":"Shopping",
            "subcategory":"Comic Books",
            "type":"Retail Goods"
        }
    ],
    "sg:phone":"+1 773 788 0915",
    "sg:postcode":"60638",
    "sg:province":"IL",
    "sg:tags":[
        "collectible"
    ],
    "wof:name":"Record Dug Out Comics",
    "wof:placetype":"venue"
},
  "geometry": {"coordinates":[-87.77310199999999,41.777699],"type":"Point"}
}