{
  "type": "Feature",
  "properties": {
    "iso:country":"US",
    "sg:address":"780 W Army Trail Rd",
    "sg:city":"Carol Stream",
    "sg:classifiers":[
        {
            "category":"Professional",
            "subcategory":"Computer Services",
            "type":"Services"
        }
    ],
    "sg:phone":"+1 630 293 0942",
    "sg:postcode":"60188",
    "sg:province":"IL",
    "sg:tags":[
        "programing",
        "custom"
    ],
    "wof:name":"Deneb Corporation",
    "wof:placetype":"venue"
},
  "geometry": {"coordinates":[-88.145119,41.940269],"type":"Point"}
}