{
  "type": "Feature",
  "properties": {
    "addr:full":"6707 S Racine Ave Chicago IL 60636",
    "addr:housenumber":"6707",
    "addr:postcode":"60636",
    "addr:street":"S Racine Ave",
    "iso:country":"US",
    "sg:address":"6707 S Racine Ave",
    "sg:city":"Chicago",
    "sg:classifiers":[
        {
            "category":"Retail",
            "subcategory":"Auto Repair",
            "type":"Services"
        }
    ],
    "sg:phone":"+1 773 651 3636",
    "sg:postcode":"60636",
    "sg:province":"IL",
    "wof:name":"Leon's Auto",
    "wof:placetype":"venue"
},
  "geometry": {"coordinates":[-87.654099,41.771999],"type":"Point"}
}