{
  "type": "Feature",
  "properties": {
    "iso:country":"US",
    "sg:address":"1509 State St",
    "sg:city":"Calumet City",
    "sg:classifiers":[
        {
            "category":"Real Estate",
            "subcategory":"Real Estate Operator",
            "type":"Services"
        }
    ],
    "sg:phone":"+1 708 862 9473",
    "sg:postcode":"60409",
    "sg:province":"IL",
    "sg:tags":[
        "building",
        "apartment"
    ],
    "wof:name":"L J Realty",
    "wof:placetype":"venue"
},
  "geometry": {"coordinates":[-87.562669,41.629955],"type":"Point"}
}