{
  "type": "Feature",
  "properties": {
    "addr:full":"209 S La Salle Street Chicago IL 60604",
    "addr:housenumber":"209",
    "addr:postcode":"60604",
    "addr:street":"S La Salle Street",
    "iso:country":"US",
    "sg:address":"209 S La Salle Street",
    "sg:city":"Chicago",
    "sg:classifiers":[
        {
            "category":"Shopping",
            "subcategory":"Clothing, Apparel, & Fashions",
            "type":"Retail Goods"
        }
    ],
    "sg:phone":"+1 312 263 0100",
    "sg:postcode":"60604",
    "sg:province":"IL",
    "sg:tags":[
        "men's",
        "clothing",
        "women's"
    ],
    "wof:name":"Brooks Brothers",
    "wof:placetype":"venue"
},
  "geometry": {"coordinates":[-87.63227000000001,41.879297],"type":"Point"}
}