{
  "type": "Feature",
  "properties": {
    "addr:full":"140 E Poplar St Albion IL 62806",
    "addr:housenumber":"140",
    "addr:postcode":"62806",
    "addr:street":"E Poplar St",
    "iso:country":"US",
    "sg:address":"140 E Poplar St",
    "sg:city":"Albion",
    "sg:classifiers":[
        {
            "category":"Education",
            "subcategory":"School",
            "type":"Public Place"
        }
    ],
    "sg:phone":"+1 618 445 2182",
    "sg:postcode":"62806",
    "sg:province":"IL",
    "wof:name":"Edwards County Headstart",
    "wof:placetype":"venue"
},
  "geometry": {"coordinates":[-88.055516,38.380034],"type":"Point"}
}