{
  "type": "Feature",
  "properties": {
    "addr:full":"108 W Vienna St Anna IL 62906",
    "addr:housenumber":"108",
    "addr:postcode":"62906",
    "addr:street":"W Vienna",
    "iso:country":"US",
    "sg:address":"108 W Vienna St",
    "sg:city":"Anna",
    "sg:classifiers":[
        {
            "category":"Manufacturing",
            "subcategory":"Printing",
            "type":"Manufacturing & Wholesale Goods"
        }
    ],
    "sg:phone":"+1 618 833 2525",
    "sg:postcode":"62906",
    "sg:province":"IL",
    "sg:tags":[
        "commercial"
    ],
    "wof:name":"Union County Press",
    "wof:placetype":"venue"
},
  "geometry": {"coordinates":[-89.249396,37.461768],"type":"Point"}
}