{
  "type": "Feature",
  "properties": {
    "iso:country":"US",
    "sg:address":"609 E 75th Street",
    "sg:city":"Chicago",
    "sg:classifiers":[
        {
            "category":"Professional",
            "subcategory":"Lawyer & Legal Services",
            "type":"Services"
        }
    ],
    "sg:phone":"+1 773 846 0011",
    "sg:postcode":"60619",
    "sg:province":"IL",
    "wof:name":"Watkins Steven Atty",
    "wof:placetype":"venue"
},
  "geometry": {"coordinates":[-87.610024,41.758474],"type":"Point"}
}