{
  "type": "Feature",
  "properties": {
    "iso:country":"US",
    "sg:address":"25420 State Rte 161",
    "sg:city":"Centralia",
    "sg:classifiers":[
        {
            "category":"Farming",
            "subcategory":"Dairy Farm",
            "type":"Manufacturing & Wholesale Goods"
        }
    ],
    "sg:phone":"+1 618 532 7007",
    "sg:postcode":"62801",
    "sg:province":"IL",
    "wof:name":"Michael Dairy",
    "wof:placetype":"venue"
},
  "geometry": {"coordinates":[-89.227333,38.536177],"type":"Point"}
}