{
  "type": "Feature",
  "properties": {
    "iso:country":"US",
    "sg:address":"125 S Batavia Ave",
    "sg:city":"Batavia",
    "sg:classifiers":[
        {
            "category":"Real Estate",
            "subcategory":"Real Estate Agent",
            "type":"Services"
        }
    ],
    "sg:phone":"+1 630 879 9555",
    "sg:postcode":"60510",
    "sg:province":"IL",
    "sg:tags":[
        "broker"
    ],
    "sg:website":"www.kettleyhomes.com",
    "wof:name":"Kettley Realtors",
    "wof:placetype":"venue"
},
  "geometry": {"coordinates":[-88.311797,41.847282],"type":"Point"}
}