{
  "type": "Feature",
  "properties": {
    "addr:full":"1845 Brighton Cir Aurora IL 60506",
    "addr:housenumber":"1845",
    "addr:postcode":"60506",
    "addr:street":"Brighton Cir",
    "iso:country":"US",
    "sg:address":"1845 Brighton Cir",
    "sg:city":"Aurora",
    "sg:classifiers":[
        {
            "category":"Professional",
            "subcategory":"Business Services",
            "type":"Services"
        }
    ],
    "sg:phone":"+1 630 859 8363",
    "sg:postcode":"60506",
    "sg:province":"IL",
    "sg:tags":[
        "paper",
        "lamination"
    ],
    "wof:name":"Dura-Fibre",
    "wof:placetype":"venue"
},
  "geometry": {"coordinates":[-88.36077400000001,41.787869],"type":"Point"}
}