{
  "type": "Feature",
  "properties": {
    "iso:country":"US",
    "sg:address":"907 S 1st St",
    "sg:city":"Princeton",
    "sg:classifiers":[
        {
            "category":"Professional",
            "subcategory":"Employment Agencies",
            "type":"Services"
        }
    ],
    "sg:phone":"+1 815 879 4045",
    "sg:postcode":"61356",
    "sg:province":"IL",
    "sg:tags":[
        "help",
        "supply"
    ],
    "wof:name":"McMullen Joey HMS",
    "wof:placetype":"venue"
},
  "geometry": {"coordinates":[-89.467392,41.366202],"type":"Point"}
}