{
  "type": "Feature",
  "properties": {
    "iso:country":"US",
    "sg:address":"18436 de Jong Ln",
    "sg:city":"Lansing",
    "sg:classifiers":[
        {
            "category":"Utilities",
            "subcategory":"Recycling",
            "type":"Services"
        }
    ],
    "sg:phone":"+1 708 474 3539",
    "sg:postcode":"60438",
    "sg:province":"IL",
    "wof:name":"Tu-X-Sel",
    "wof:placetype":"venue"
},
  "geometry": {"coordinates":[-87.569041,41.56018],"type":"Point"}
}