{
  "type": "Feature",
  "properties": {
    "iso:country":"US",
    "sg:address":"726 E Schaumburg Rd",
    "sg:city":"Schaumburg",
    "sg:classifiers":[
        {
            "category":"Home & Garden",
            "subcategory":"Garden Supply",
            "type":"Retail Goods"
        },
        {
            "category":"Shopping",
            "subcategory":"Gifts & Souvenirs",
            "type":"Retail Goods"
        },
        {
            "category":"Shopping",
            "subcategory":"Crafts & Fabrics",
            "type":"Retail Goods"
        },
        {
            "category":"Shopping",
            "subcategory":"Florist",
            "type":"Retail Goods"
        }
    ],
    "sg:phone":"+1 847 885 7564",
    "sg:postcode":"60194",
    "sg:province":"IL",
    "sg:tags":[
        "plant",
        "etc-retail",
        "dried",
        "basket",
        "trees-silk",
        "flowers"
    ],
    "sg:website":"http://www.flowersofschaumburg.com",
    "wof:name":"Flower Show Of Schaumburg",
    "wof:placetype":"venue"
},
  "geometry": {"coordinates":[-88.06291899999999,42.028036],"type":"Point"}
}