{
  "type": "Feature",
  "properties": {
    "addr:full":"1917 W 16th St Chicago IL 60608",
    "addr:housenumber":"1917",
    "addr:postcode":"60608",
    "addr:street":"W 16Th St",
    "iso:country":"US",
    "sg:address":"1917 W 16th St",
    "sg:city":"Chicago",
    "sg:classifiers":[
        {
            "category":"Wholesale",
            "subcategory":"Apparel",
            "type":"Manufacturing & Wholesale Goods"
        }
    ],
    "sg:phone":"+1 224 399 9696",
    "sg:postcode":"60608",
    "sg:province":"IL",
    "sg:tags":[
        "shoes-wholesale",
        "manufacturer"
    ],
    "wof:name":"Il Kickz Shoes & Appearal",
    "wof:placetype":"venue"
},
  "geometry": {"coordinates":[-87.672562,41.859521],"type":"Point"}
}