{
  "type": "Feature",
  "properties": {
    "addr:full":"1214 E Church St Sandwich IL 60548",
    "addr:housenumber":"1214",
    "addr:postcode":"60548",
    "addr:street":"E Church St",
    "iso:country":"US",
    "sg:address":"1214 E Church St",
    "sg:city":"Sandwich",
    "sg:classifiers":[
        {
            "category":"Shopping",
            "subcategory":"Pets & Pet Supplies",
            "type":"Retail Goods"
        },
        {
            "category":"Retail",
            "subcategory":"Veterinary Services",
            "type":"Services"
        },
        {
            "category":"Retail",
            "subcategory":"Animal Services",
            "type":"Services"
        }
    ],
    "sg:phone":"+1 815 570 9973",
    "sg:postcode":"60548",
    "sg:province":"IL",
    "sg:tags":[
        "information",
        "hospital",
        "specialty",
        "dog",
        "clinic",
        "cat",
        "veterinarian",
        "veterinarians'",
        "grooming",
        "referral"
    ],
    "sg:website":"http://www.yext.com/p/superpages/sandwich-veterinary-hospital-sandwich-illinois.html",
    "wof:name":"Sandwich Veterinary Hospital",
    "wof:placetype":"venue"
},
  "geometry": {"coordinates":[-88.604934,41.646296],"type":"Point"}
}