{
  "type": "Feature",
  "properties": {
    "iso:country":"US",
    "sg:address":"36768 200th Ave",
    "sg:city":"Pittsfield",
    "sg:classifiers":[
        {
            "category":"Manufacturing",
            "subcategory":"Food",
            "type":"Manufacturing & Wholesale Goods"
        },
        {
            "category":"Farming",
            "subcategory":"Livestock Farm",
            "type":"Manufacturing & Wholesale Goods"
        },
        {
            "category":"Farming",
            "subcategory":"Farm",
            "type":"Manufacturing & Wholesale Goods"
        }
    ],
    "sg:phone":"+1 217 285 2678",
    "sg:postcode":"62363",
    "sg:province":"IL",
    "sg:tags":[
        "corn",
        "ranch",
        "product"
    ],
    "wof:name":"Highland Farms",
    "wof:placetype":"venue"
},
  "geometry": {"coordinates":[-90.842912,39.545769],"type":"Point"}
}