{
  "type": "Feature",
  "properties": {
    "iso:country":"US",
    "sg:address":"9220 S Luella Ave",
    "sg:city":"Chicago",
    "sg:classifiers":[
        {
            "category":"Professional",
            "subcategory":"Lawyer & Legal Services",
            "type":"Services"
        }
    ],
    "sg:phone":"+1 773 731 2039",
    "sg:postcode":"60617",
    "sg:province":"IL",
    "wof:name":"Ec Williams & Associates Ltd",
    "wof:placetype":"venue"
},
  "geometry": {"coordinates":[-87.56950399999999,41.727699],"type":"Point"}
}