{
  "type": "Feature",
  "properties": {
    "iso:country":"US",
    "sg:address":"218 Washington St",
    "sg:city":"Ingleside",
    "sg:classifiers":[
        {
            "category":"Social Services",
            "subcategory":"Child Care",
            "type":"Services"
        }
    ],
    "sg:phone":"+1 847 587 5437",
    "sg:postcode":"60041",
    "sg:province":"IL",
    "wof:name":"Kidsuccess",
    "wof:placetype":"venue"
},
  "geometry": {"coordinates":[-88.15567,42.393848],"type":"Point"}
}