{
  "type": "Feature",
  "properties": {
    "addr:full":"2109 N 765 East Rd Danforth IL 60930",
    "addr:housenumber":"2109",
    "addr:postcode":"60930",
    "addr:street":"N 765 East Rd",
    "iso:country":"US",
    "sg:address":"2109 N 765 East Rd",
    "sg:city":"Danforth",
    "sg:classifiers":[
        {
            "category":"Airport",
            "type":"Transportation"
        }
    ],
    "sg:phone":"+1 815 269 2552",
    "sg:postcode":"60930",
    "sg:province":"IL",
    "wof:name":"Global Aeronautics",
    "wof:placetype":"venue"
},
  "geometry": {"coordinates":[-87.985601,40.810758],"type":"Point"}
}