{
  "type": "Feature",
  "properties": {
    "addr:full":"55 E Monroe St Chicago IL 60603",
    "addr:housenumber":"55",
    "addr:postcode":"60603",
    "addr:street":"E Monroe St",
    "iso:country":"US",
    "sg:address":"55 E Monroe St",
    "sg:city":"Chicago",
    "sg:classifiers":[
        {
            "category":"Coffee & Tea",
            "type":"Food & Drink"
        }
    ],
    "sg:phone":"+1 312 750 1430",
    "sg:postcode":"60603",
    "sg:province":"IL",
    "sg:website":"www.seattlesbest.com",
    "wof:name":"Seattle's Best Coffee",
    "wof:placetype":"venue"
},
  "geometry": {"coordinates":[-87.625839,41.880653],"type":"Point"}
}