{
  "type": "Feature",
  "properties": {
    "addr:full":"395 N Co Rd 1775 E Hindsboro IL 61930",
    "addr:housenumber":"395;1775 e",
    "addr:postcode":"61930",
    "addr:street":"N Co Rd",
    "iso:country":"US",
    "sg:address":"395 N Co Rd 1775 E",
    "sg:city":"Hindsboro",
    "sg:classifiers":[
        {
            "category":"Building & Trades",
            "subcategory":"Plumbing",
            "type":"Services"
        }
    ],
    "sg:phone":"+1 217 346 3331",
    "sg:postcode":"61930",
    "sg:province":"IL",
    "sg:tags":[
        "septic"
    ],
    "wof:name":"Miller Septic Tank Svc",
    "wof:placetype":"venue"
},
  "geometry": {"coordinates":[-88.138724,39.708068],"type":"Point"}
}