{
  "type": "Feature",
  "properties": {
    "addr:full":"1190 W Station St Kankakee IL 60901",
    "addr:housenumber":"1190",
    "addr:postcode":"60901",
    "addr:street":"W Station St",
    "iso:country":"US",
    "sg:address":"1190 W Station St",
    "sg:city":"Kankakee",
    "sg:classifiers":[
        {
            "category":"Fast Food",
            "type":"Food & Drink"
        },
        {
            "category":"Coffee & Tea",
            "type":"Food & Drink"
        },
        {
            "category":"Restaurant",
            "type":"Food & Drink"
        }
    ],
    "sg:phone":"+1 815 933 5315",
    "sg:postcode":"60901",
    "sg:province":"IL",
    "sg:tags":[
        "style",
        "espresso",
        "take",
        "family"
    ],
    "sg:website":"http://www.bluescafe.com",
    "wof:name":"Blues Cafe",
    "wof:placetype":"venue"
},
  "geometry": {"coordinates":[-87.881496,41.118731],"type":"Point"}
}