{
  "type": "Feature",
  "properties": {
    "addr:full":"902 Maple Ave Downers Grove IL 60515",
    "addr:housenumber":"902",
    "addr:postcode":"60515",
    "addr:street":"Maple Ave",
    "iso:country":"US",
    "sg:address":"902 Maple Ave",
    "sg:city":"Downers Grove",
    "sg:classifiers":[
        {
            "category":"Health Services",
            "subcategory":"Health Practitioner",
            "type":"Services"
        }
    ],
    "sg:phone":"+1 630 663 1214",
    "sg:postcode":"60515",
    "sg:province":"IL",
    "sg:tags":[
        "psychologist"
    ],
    "wof:name":"Julia A Glazko PHD",
    "wof:placetype":"venue"
},
  "geometry": {"coordinates":[-88.006907,41.792633],"type":"Point"}
}