{
  "type": "Feature",
  "properties": {
    "iso:country":"US",
    "sg:address":"636 Deerfield Rd",
    "sg:city":"Deerfield",
    "sg:classifiers":[
        {
            "category":"Home & Garden",
            "subcategory":"Furniture",
            "type":"Retail Goods"
        }
    ],
    "sg:phone":"+1 847 267 1994",
    "sg:postcode":"60015",
    "sg:province":"IL",
    "sg:website":"www.amishfurnitureshoppe.com",
    "wof:name":"Amish Furniture Shoppe Inc",
    "wof:placetype":"venue"
},
  "geometry": {"coordinates":[-87.845501,42.167379],"type":"Point"}
}