{
  "type": "Feature",
  "properties": {
    "iso:country":"US",
    "sg:address":"1531 Acorn Rd",
    "sg:city":"Highland",
    "sg:classifiers":[
        {
            "category":"Farming",
            "subcategory":"Livestock Farm",
            "type":"Manufacturing & Wholesale Goods"
        },
        {
            "category":"Farming",
            "subcategory":"Farm",
            "type":"Manufacturing & Wholesale Goods"
        }
    ],
    "sg:phone":"+1 618 654 4113",
    "sg:postcode":"62249",
    "sg:province":"IL",
    "wof:name":"Craig Ammann",
    "wof:placetype":"venue"
},
  "geometry": {"coordinates":[-89.707702,38.709182],"type":"Point"}
}