{
  "type": "Feature",
  "properties": {
    "addr:full":"806 Jefferson St Mendota IL 61342",
    "addr:housenumber":"806",
    "addr:postcode":"61342",
    "addr:street":"Jefferson St",
    "iso:country":"US",
    "sg:address":"806 Jefferson St",
    "sg:city":"Mendota",
    "sg:classifiers":[
        {
            "category":"Professional",
            "subcategory":"Lawyer & Legal Services",
            "type":"Services"
        }
    ],
    "sg:phone":"+1 815 539 5616",
    "sg:postcode":"61342",
    "sg:province":"IL",
    "wof:name":"Kaleel David M Attorney At Law",
    "wof:placetype":"venue"
},
  "geometry": {"coordinates":[-89.120857,41.549242],"type":"Point"}
}