{
  "type": "Feature",
  "properties": {
    "iso:country":"US",
    "sg:address":"7302 Montague Rd",
    "sg:city":"Rockford",
    "sg:classifiers":[
        {
            "category":"Professional",
            "type":"Services"
        }
    ],
    "sg:phone":"+1 815 968 7578",
    "sg:postcode":"61102",
    "sg:province":"IL",
    "wof:name":"Charles W Meyers",
    "wof:placetype":"venue"
},
  "geometry": {"coordinates":[-89.189907,42.220343],"type":"Point"}
}