{
  "type": "Feature",
  "properties": {
    "iso:country":"US",
    "sg:address":"2226 N Lincoln Avenue",
    "sg:city":"Chicago",
    "sg:classifiers":[
        {
            "category":"Personal",
            "subcategory":"Hair Removal",
            "type":"Services"
        },
        {
            "category":"Personal",
            "subcategory":"Day Spa",
            "type":"Services"
        }
    ],
    "sg:phone":"+1 773 388 2100",
    "sg:postcode":"60614",
    "sg:province":"IL",
    "wof:name":"Advanced Laser Clinics",
    "wof:placetype":"venue"
},
  "geometry": {"coordinates":[-87.644893,41.922394],"type":"Point"}
}