{
  "type": "Feature",
  "properties": {
    "addr:full":"5210 W 95th St Oak Lawn IL 60453",
    "addr:housenumber":"5210",
    "addr:postcode":"60453",
    "addr:street":"W 95Th St",
    "iso:country":"US",
    "sg:address":"5210 W 95th St",
    "sg:city":"Oak Lawn",
    "sg:classifiers":[
        {
            "category":"Professional",
            "subcategory":"Accounting & Tax Preparation",
            "type":"Services"
        }
    ],
    "sg:phone":"+1 708 425 6025",
    "sg:postcode":"60453",
    "sg:province":"IL",
    "sg:tags":[
        "accountant"
    ],
    "wof:name":"McCabe-Tax and Financial Services",
    "wof:placetype":"venue"
},
  "geometry": {"coordinates":[-87.7509,41.719898],"type":"Point"}
}