{
  "type": "Feature",
  "properties": {
    "iso:country":"US",
    "sg:address":"605 Arlington Heights Rd",
    "sg:city":"Arlington Heights",
    "sg:classifiers":[
        {
            "category":"Professional",
            "subcategory":"Computer Services",
            "type":"Services"
        }
    ],
    "sg:phone":"+1 847 690 9698",
    "sg:postcode":"60005",
    "sg:province":"IL",
    "sg:tags":[
        "programing",
        "custom"
    ],
    "wof:name":"Versant Technologies Inc",
    "wof:placetype":"venue"
},
  "geometry": {"coordinates":[-87.980439,42.072004],"type":"Point"}
}