{
  "type": "Feature",
  "properties": {
    "iso:country":"US",
    "sg:address":"1630 Sheffield Dr",
    "sg:city":"Elgin",
    "sg:classifiers":[
        {
            "category":"Professional",
            "subcategory":"Business Services",
            "type":"Services"
        }
    ],
    "sg:phone":"+1 847 741 5470",
    "sg:postcode":"60123",
    "sg:province":"IL",
    "sg:tags":[
        "interior",
        "consultant",
        "design",
        "decorator"
    ],
    "wof:name":"Interior Design With Feng Shui",
    "wof:placetype":"venue"
},
  "geometry": {"coordinates":[-88.318118,42.06497],"type":"Point"}
}