{
  "type": "Feature",
  "properties": {
    "iso:country":"US",
    "sg:address":"1445 S State Rte 127",
    "sg:city":"Greenville",
    "sg:classifiers":[
        {
            "category":"Health Services",
            "subcategory":"Clinic",
            "type":"Services"
        }
    ],
    "sg:phone":"+1 618 664 2333",
    "sg:postcode":"62246",
    "sg:province":"IL",
    "sg:tags":[
        "home",
        "care"
    ],
    "wof:name":"V N A/ Tip",
    "wof:placetype":"venue"
},
  "geometry": {"coordinates":[-89.46618,38.952827],"type":"Point"}
}