{
  "type": "Feature",
  "properties": {
    "iso:country":"US",
    "sg:address":"21007 Mcguire Rd",
    "sg:city":"Harvard",
    "sg:classifiers":[
        {
            "category":"Social Services",
            "subcategory":"Child Care",
            "type":"Services"
        }
    ],
    "sg:phone":"+1 815 943 3499",
    "sg:postcode":"60033",
    "sg:province":"IL",
    "sg:tags":[
        "nursery",
        "day"
    ],
    "wof:name":"Brown Bear Corporation",
    "wof:placetype":"venue"
},
  "geometry": {"coordinates":[-88.60774600000001,42.407372],"type":"Point"}
}