{
  "type": "Feature",
  "properties": {
    "iso:country":"US",
    "sg:address":"7325 W Lakeside Dr",
    "sg:city":"Frankfort",
    "sg:classifiers":[
        {
            "category":"Professional",
            "subcategory":"Advertising",
            "type":"Services"
        }
    ],
    "sg:phone":"+1 815 464 5649",
    "sg:postcode":"60423",
    "sg:province":"IL",
    "sg:tags":[
        "counselor",
        "agency"
    ],
    "sg:website":"www.butlerproductionservices.com",
    "wof:name":"Butler Production Service",
    "wof:placetype":"venue"
},
  "geometry": {"coordinates":[-87.80037,41.535965],"type":"Point"}
}