{
  "type": "Feature",
  "properties": {
    "iso:country":"US",
    "sg:address":"2095 Oak Leaf St",
    "sg:city":"Joliet",
    "sg:classifiers":[
        {
            "category":"Building & Trades",
            "subcategory":"Construction",
            "type":"Services"
        }
    ],
    "sg:phone":"+1 815 730 0336",
    "sg:postcode":"60436",
    "sg:province":"IL",
    "sg:tags":[
        "repair",
        "air conditioning"
    ],
    "wof:name":"Tec",
    "wof:placetype":"venue"
},
  "geometry": {"coordinates":[-88.133443,41.512185],"type":"Point"}
}