{
  "type": "Feature",
  "properties": {
    "iso:country":"US",
    "sg:address":"222 N Plum Grove Rd",
    "sg:city":"Palatine",
    "sg:classifiers":[
        {
            "category":"Health Services",
            "subcategory":"Doctor",
            "type":"Services"
        }
    ],
    "sg:phone":"+1 847 358 9000",
    "sg:postcode":"60067",
    "sg:province":"IL",
    "wof:name":"Aylward Gerry DDS Ms",
    "wof:placetype":"venue"
},
  "geometry": {"coordinates":[-88.04375400000001,42.113974],"type":"Point"}
}