{
  "type": "Feature",
  "properties": {
    "addr:full":"8770 W Bryn Mawr Ave Ste 1300 S Chicago IL 60631",
    "addr:housenumber":"8770",
    "addr:postcode":"60631",
    "addr:street":"W Bryn Mawr Ave Ste 1300 S",
    "iso:country":"US",
    "sg:address":"8770 W Bryn Mawr Ave Ste 1300 S",
    "sg:city":"Chicago",
    "sg:classifiers":[
        {
            "category":"Professional",
            "subcategory":"Computer Services",
            "type":"Services"
        }
    ],
    "sg:phone":"+1 312 878 1270",
    "sg:postcode":"60631",
    "sg:province":"IL",
    "sg:tags":[
        "repair"
    ],
    "sg:website":"www.salvagedata.com",
    "wof:name":"Salvage Data Recovery Services",
    "wof:placetype":"venue"
},
  "geometry": {"coordinates":[-87.84517700000001,41.982976],"type":"Point"}
}