{
  "type": "Feature",
  "properties": {
    "addr:full":"1261 Ridge Ave Elk Grove Vlg IL 60007",
    "addr:housenumber":"1261",
    "addr:postcode":"60007",
    "addr:street":"Ridge Ave",
    "iso:country":"US",
    "sg:address":"1261 Ridge Ave",
    "sg:city":"Elk Grove Vlg",
    "sg:classifiers":[
        {
            "category":"Shopping",
            "subcategory":"Hobbies, Toys, & Games",
            "type":"Retail Goods"
        }
    ],
    "sg:phone":"+1 847 439 1107",
    "sg:postcode":"60007",
    "sg:province":"IL",
    "sg:tags":[
        "equipment",
        "ceramic",
        "supply"
    ],
    "wof:name":"Cherry's Ceramic Creations",
    "wof:placetype":"venue"
},
  "geometry": {"coordinates":[-87.98905600000001,41.995158],"type":"Point"}
}