{
  "type": "Feature",
  "properties": {
    "addr:full":"414 W Jefferson Ave Effingham IL 62401",
    "addr:housenumber":"414",
    "addr:postcode":"62401",
    "addr:street":"W Jefferson Ave",
    "iso:country":"US",
    "sg:address":"414 W Jefferson Ave",
    "sg:city":"Effingham",
    "sg:classifiers":[
        {
            "category":"Health Services",
            "subcategory":"Chiropractor",
            "type":"Services"
        }
    ],
    "sg:phone":"+1 217 347 1050",
    "sg:postcode":"62401",
    "sg:province":"IL",
    "wof:name":"Kelly L Stanfield PC",
    "wof:placetype":"venue"
},
  "geometry": {"coordinates":[-88.54744100000001,39.122031],"type":"Point"}
}