{
  "type": "Feature",
  "properties": {
    "iso:country":"US",
    "sg:address":"1006 Peoria St",
    "sg:city":"Washington",
    "sg:classifiers":[
        {
            "category":"Restaurant",
            "type":"Food & Drink"
        }
    ],
    "sg:phone":"+1 309 444 1985",
    "sg:postcode":"61536",
    "sg:province":"IL",
    "wof:name":"Legondolier & Pasta",
    "wof:placetype":"venue"
},
  "geometry": {"coordinates":[-89.795713,40.694141],"type":"Point"}
}