{
  "type": "Feature",
  "properties": {
    "iso:country":"US",
    "sg:address":"200 Burr Oak Rd",
    "sg:city":"Capron",
    "sg:classifiers":[
        {
            "category":"Manufacturing",
            "subcategory":"Metals",
            "type":"Manufacturing & Wholesale Goods"
        }
    ],
    "sg:phone":"+1 815 569 2301",
    "sg:postcode":"61012",
    "sg:province":"IL",
    "sg:tags":[
        "plating",
        "formed",
        "coating",
        "product",
        "chromium",
        "or"
    ],
    "wof:name":"Capron Manufacturing Company",
    "wof:placetype":"venue"
},
  "geometry": {"coordinates":[-88.730398,42.4141],"type":"Point"}
}