{
  "type": "Feature",
  "properties": {
    "addr:full":"1630 Todd Farm Dr Elgin IL 60123",
    "addr:housenumber":"1630",
    "addr:postcode":"60123",
    "addr:street":"Todd Farm Dr",
    "iso:country":"US",
    "sg:address":"1630 Todd Farm Dr",
    "sg:city":"Elgin",
    "sg:classifiers":[
        {
            "category":"Professional",
            "subcategory":"Business Services",
            "type":"Services"
        }
    ],
    "sg:phone":"+1 847 468 1750",
    "sg:postcode":"60123",
    "sg:province":"IL",
    "wof:name":"United Coating Technologies LL",
    "wof:placetype":"venue"
},
  "geometry": {"coordinates":[-88.320452,42.061107],"type":"Point"}
}