{
  "type": "Feature",
  "properties": {
    "iso:country":"US",
    "sg:address":"28479 N 2700th Ave",
    "sg:city":"Prophetstown",
    "sg:phone":"+1 815 948 7581",
    "sg:postcode":"61277",
    "sg:province":"IL",
    "sg:tags":[
        "farm",
        "corn",
        "soybean"
    ],
    "wof:name":"Paul Hilger",
    "wof:placetype":"venue"
},
  "geometry": {"coordinates":[-89.89636400000001,41.5399],"type":"Point"}
}