{
  "type": "Feature",
  "properties": {
    "addr:full":"Hilton Chicago Indian Lakes Resort 250 W Schick Rd Bloomingdale IL 60108",
    "addr:housenumber":"250",
    "addr:postcode":"60108",
    "addr:street":"W Schick Rd",
    "iso:country":"US",
    "sg:address":"Hilton Chicago Indian Lakes Resort 250 W Schick Rd",
    "sg:city":"Bloomingdale",
    "sg:classifiers":[
        {
            "category":"Restaurant",
            "type":"Food & Drink"
        }
    ],
    "sg:phone":"+1 630 671 5013",
    "sg:postcode":"60108",
    "sg:province":"IL",
    "sg:tags":[
        "new",
        "american"
    ],
    "sg:website":"www.shirazonthewater.com",
    "wof:name":"Shiraz on the Water",
    "wof:placetype":"venue"
},
  "geometry": {"coordinates":[-88.093841,41.953771],"type":"Point"}
}