{
  "type": "Feature",
  "properties": {
    "addr:full":"89 Delo Dr Wauconda IL 60084",
    "addr:housenumber":"89",
    "addr:postcode":"60084",
    "addr:street":"Delo Dr",
    "iso:country":"US",
    "sg:address":"89 Delo Dr",
    "sg:city":"Wauconda",
    "sg:classifiers":[
        {
            "category":"Local Transit",
            "type":"Transportation"
        }
    ],
    "sg:phone":"+1 847 526 3094",
    "sg:postcode":"60084",
    "sg:province":"IL",
    "sg:tags":[
        "limousine"
    ],
    "wof:name":"Scott's Chauffeuring",
    "wof:placetype":"venue"
},
  "geometry": {"coordinates":[-88.140467,42.253267],"type":"Point"}
}