{
  "type": "Feature",
  "properties": {
    "iso:country":"US",
    "sg:address":"165 N Page St",
    "sg:city":"Wheaton",
    "sg:classifiers":[
        {
            "category":"Building & Trades",
            "subcategory":"Plumbing",
            "type":"Services"
        }
    ],
    "sg:phone":"+1 630 668 0960",
    "sg:postcode":"60187",
    "sg:province":"IL",
    "sg:tags":[
        "contractor"
    ],
    "wof:name":"R Cortino Plumbing & Heating",
    "wof:placetype":"venue"
},
  "geometry": {"coordinates":[-88.139873,41.863556],"type":"Point"}
}