{
  "type": "Feature",
  "properties": {
    "addr:full":"180 N La Salle St Chicago IL 60601",
    "addr:housenumber":"180",
    "addr:postcode":"60601",
    "addr:street":"N La Salle St",
    "iso:country":"US",
    "sg:address":"180 N La Salle St",
    "sg:city":"Chicago",
    "sg:classifiers":[
        {
            "category":"Sports & Exercise",
            "subcategory":"Gym",
            "type":"Entertainment"
        }
    ],
    "sg:phone":"+1 312 419 1959",
    "sg:postcode":"60601",
    "sg:province":"IL",
    "sg:tags":[
        "trainer"
    ],
    "wof:name":"Jenny Craig Weight Loss Centres",
    "wof:placetype":"venue"
},
  "geometry": {"coordinates":[-87.632599,41.885399],"type":"Point"}
}