{
  "type": "Feature",
  "properties": {
    "iso:country":"US",
    "sg:address":"231 E 2nd St",
    "sg:city":"Mount Carmel",
    "sg:classifiers":[
        {
            "category":"Organizations",
            "subcategory":"Religious Organization",
            "type":"Services"
        }
    ],
    "sg:phone":"+1 618 262 2505",
    "sg:postcode":"62863",
    "sg:province":"IL",
    "sg:tags":[
        "church"
    ],
    "wof:name":"Jacob's Well",
    "wof:placetype":"venue"
},
  "geometry": {"coordinates":[-87.756738,38.407952],"type":"Point"}
}