{
  "type": "Feature",
  "properties": {
    "iso:country":"US",
    "sg:address":"815 Dunlop Ave",
    "sg:city":"Forest Park",
    "sg:classifiers":[
        {
            "category":"Health Services",
            "subcategory":"Doctor",
            "type":"Services"
        }
    ],
    "sg:phone":"+1 708 771 4594",
    "sg:postcode":"60130",
    "sg:province":"IL",
    "wof:name":"Karbin Jan A Dgn Ins",
    "wof:placetype":"venue"
},
  "geometry": {"coordinates":[-87.815904,41.871573],"type":"Point"}
}