{
  "type": "Feature",
  "properties": {
    "addr:full":"7917 S Vincennes Ave Chicago IL 60620",
    "addr:housenumber":"7917",
    "addr:postcode":"60620",
    "addr:street":"S Vincennes Ave",
    "iso:country":"US",
    "sg:address":"7917 S Vincennes Ave",
    "sg:city":"Chicago",
    "sg:classifiers":[
        {
            "category":"Retail",
            "subcategory":"Auto Repair",
            "type":"Services"
        }
    ],
    "sg:phone":"+1 773 874 9400",
    "sg:postcode":"60620",
    "sg:province":"IL",
    "sg:tags":[
        "body",
        "shop"
    ],
    "wof:name":"Riverdale Body Shop",
    "wof:placetype":"venue"
},
  "geometry": {"coordinates":[-87.634073,41.750361],"type":"Point"}
}