{
  "type": "Feature",
  "properties": {
    "iso:country":"US",
    "sg:address":"5680 E Firehouse Rd",
    "sg:city":"Decatur",
    "sg:classifiers":[
        {
            "category":"Building & Trades",
            "subcategory":"Landscaping Services",
            "type":"Services"
        }
    ],
    "sg:phone":"+1 217 864 2867",
    "sg:postcode":"62521",
    "sg:province":"IL",
    "sg:tags":[
        "lawn",
        "maintenance"
    ],
    "wof:name":"Marcella Stortzum",
    "wof:placetype":"venue"
},
  "geometry": {"coordinates":[-88.865709,39.809321],"type":"Point"}
}