{
  "type": "Feature",
  "properties": {
    "iso:country":"US",
    "sg:address":"1000 S State St Unit A",
    "sg:city":"Hampshire",
    "sg:classifiers":[
        {
            "category":"Health Services",
            "subcategory":"Doctor",
            "type":"Services"
        }
    ],
    "sg:phone":"+1 847 683 7543",
    "sg:postcode":"60140",
    "sg:province":"IL",
    "wof:name":"Mathen Shaun MD",
    "wof:placetype":"venue"
},
  "geometry": {"coordinates":[-88.53028500000001,42.089088],"type":"Point"}
}