{
  "type": "Feature",
  "properties": {
    "iso:country":"US",
    "sg:address":"25055 Virginia Ave",
    "sg:city":"Lake Zurich",
    "sg:classifiers":[
        {
            "category":"Building & Trades",
            "subcategory":"Construction",
            "type":"Services"
        }
    ],
    "sg:phone":"+1 847 438 6640",
    "sg:postcode":"60047",
    "sg:province":"IL",
    "sg:tags":[
        "contractor"
    ],
    "wof:name":"Pjk Taping",
    "wof:placetype":"venue"
},
  "geometry": {"coordinates":[-88.109876,42.227643],"type":"Point"}
}