{
  "type": "Feature",
  "properties": {
    "iso:country":"US",
    "sg:address":"55 W. Wacker Dr., Ste. 1400",
    "sg:city":"Chicago",
    "sg:classifiers":[
        {
            "category":"Professional",
            "subcategory":"Lawyer & Legal Services",
            "type":"Services"
        }
    ],
    "sg:phone":"+1 877 736 4222",
    "sg:postcode":"60601",
    "sg:province":"IL",
    "sg:tags":[
        "litigation",
        "personal",
        "injury"
    ],
    "wof:name":"Truck Accident Lawyer Group - Brad Pistotnik",
    "wof:placetype":"venue"
},
  "geometry": {"coordinates":[-87.629897,41.886683],"type":"Point"}
}