{
  "type": "Feature",
  "properties": {
    "addr:full":"1525 Chicago Ave Evanston IL 60201",
    "addr:housenumber":"1525",
    "addr:postcode":"60201",
    "addr:street":"Chicago Ave",
    "iso:country":"US",
    "sg:address":"1525 Chicago Ave",
    "sg:city":"Evanston",
    "sg:classifiers":[
        {
            "category":"Retail",
            "subcategory":"Laundry & Dry Cleaning",
            "type":"Services"
        },
        {
            "category":"Building & Trades",
            "subcategory":"Cleaning & Sanitation",
            "type":"Services"
        }
    ],
    "sg:phone":"+1 847 328 2321",
    "sg:postcode":"60201",
    "sg:province":"IL",
    "sg:tags":[
        "cleaner",
        "upholstery",
        "rug",
        "curtain",
        "drapery",
        "carpet"
    ],
    "wof:name":"Coit Drapery & Carpet Cleaners",
    "wof:placetype":"venue"
},
  "geometry": {"coordinates":[-87.680083,42.04531],"type":"Point"}
}