{
  "type": "Feature",
  "properties": {
    "iso:country":"US",
    "sg:address":"426 N Vancina Ln",
    "sg:city":"New Lenox",
    "sg:classifiers":[
        {
            "category":"Building & Trades",
            "subcategory":"Landscaping Services",
            "type":"Services"
        }
    ],
    "sg:phone":"+1 815 485 6772",
    "sg:postcode":"60451",
    "sg:province":"IL",
    "sg:tags":[
        "landscape",
        "contractor"
    ],
    "wof:name":"Vancina Landscaping Inc",
    "wof:placetype":"venue"
},
  "geometry": {"coordinates":[-87.919837,41.512157],"type":"Point"}
}