{
  "type": "Feature",
  "properties": {
    "iso:country":"US",
    "sg:address":"1017 W Main St",
    "sg:city":"Collinsville",
    "sg:classifiers":[
        {
            "category":"Building & Trades",
            "subcategory":"Construction",
            "type":"Services"
        }
    ],
    "sg:phone":"+1 618 781 0816",
    "sg:postcode":"62234",
    "sg:province":"IL",
    "sg:tags":[
        "house"
    ],
    "wof:name":"Merwin Construction Inc",
    "wof:placetype":"venue"
},
  "geometry": {"coordinates":[-89.997934,38.666756],"type":"Point"}
}