{
  "type": "Feature",
  "properties": {
    "iso:country":"US",
    "sg:address":"4608 Ave of the Cities",
    "sg:city":"Moline",
    "sg:classifiers":[
        {
            "category":"Shopping",
            "subcategory":"Mobile Phones",
            "type":"Retail Goods"
        }
    ],
    "sg:phone":"+1 309 762 6100",
    "sg:postcode":"61265",
    "sg:province":"IL",
    "sg:website":"vzw.com",
    "wof:name":"Verizon Wireless",
    "wof:placetype":"venue"
},
  "geometry": {"coordinates":[-90.47136399999999,41.489795],"type":"Point"}
}