{
  "type": "Feature",
  "properties": {
    "iso:country":"US",
    "sg:address":"5125 S Greenwood Ave # 200",
    "sg:city":"Chicago",
    "sg:classifiers":[
        {
            "category":"Professional",
            "subcategory":"Computer Services",
            "type":"Services"
        }
    ],
    "sg:phone":"+1 773 493 4116",
    "sg:postcode":"60615",
    "sg:province":"IL",
    "sg:tags":[
        "publisher",
        "designer",
        "consultant",
        "system",
        "software",
        "developer"
    ],
    "wof:name":"Impressions Graphics, Inc.",
    "wof:placetype":"venue"
},
  "geometry": {"coordinates":[-87.59979300000001,41.801989],"type":"Point"}
}