{
  "type": "Feature",
  "properties": {
    "addr:full":"200 W 3rd St Ste 302 Alton IL 62002",
    "addr:housenumber":"200",
    "addr:postcode":"62002",
    "addr:street":"W 3Rd St Ste 302",
    "iso:country":"US",
    "sg:address":"200 W 3rd St Ste 302",
    "sg:city":"Alton",
    "sg:classifiers":[
        {
            "category":"Professional",
            "subcategory":"Lawyer & Legal Services",
            "type":"Services"
        }
    ],
    "sg:phone":"+1 618 465 8825",
    "sg:postcode":"62002",
    "sg:province":"IL",
    "sg:tags":[
        "attorney",
        "practice"
    ],
    "wof:name":"Robert E Ryan",
    "wof:placetype":"venue"
},
  "geometry": {"coordinates":[-90.18759900000001,38.891201],"type":"Point"}
}