{
  "type": "Feature",
  "properties": {
    "iso:country":"US",
    "sg:address":"910 E Oak St",
    "sg:city":"Lake In The Hls",
    "sg:classifiers":[
        {
            "category":"Insurance",
            "subcategory":"Insurance Agent",
            "type":"Services"
        }
    ],
    "sg:phone":"+1 847 658 9251",
    "sg:postcode":"60156",
    "sg:province":"IL",
    "wof:name":"Maryniw Financial",
    "wof:placetype":"venue"
},
  "geometry": {"coordinates":[-88.308834,42.190174],"type":"Point"}
}