{
  "type": "Feature",
  "properties": {
    "addr:full":"3760 N Halsted St Chicago IL 60613",
    "addr:housenumber":"3760",
    "addr:postcode":"60613",
    "addr:street":"N Halsted St",
    "iso:country":"US",
    "sg:address":"3760 N Halsted St",
    "sg:city":"Chicago",
    "sg:classifiers":[
        {
            "category":"Restaurant",
            "type":"Food & Drink"
        }
    ],
    "sg:phone":"+1 773 296 0048",
    "sg:postcode":"60613",
    "sg:province":"IL",
    "sg:tags":[
        "breakfast",
        "brunch"
    ],
    "sg:website":"www.ihop.com",
    "wof:name":"International House of Pancakes",
    "wof:placetype":"venue"
},
  "geometry": {"coordinates":[-87.649399,41.950901],"type":"Point"}
}