{
  "type": "Feature",
  "properties": {
    "iso:country":"US",
    "sg:address":"2233 Charles St",
    "sg:city":"Rockford",
    "sg:classifiers":[
        {
            "category":"Education",
            "subcategory":"Dance Studio",
            "type":"Public Place"
        }
    ],
    "sg:phone":"+1 815 229 0997",
    "sg:postcode":"61104",
    "sg:province":"IL",
    "sg:tags":[
        "instruction",
        "dancing"
    ],
    "wof:name":"Comtemporary Dance Expressions",
    "wof:placetype":"venue"
},
  "geometry": {"coordinates":[-89.06113,42.261151],"type":"Point"}
}