{
  "type": "Feature",
  "properties": {
    "iso:country":"US",
    "sg:address":"1455 Leighton Rd",
    "sg:city":"Mundelein",
    "sg:classifiers":[
        {
            "category":"Autos & Motor Vehicles",
            "subcategory":"Automobile Sales",
            "type":"Retail Goods"
        }
    ],
    "sg:phone":"+1 847 970 9009",
    "sg:postcode":"60060",
    "sg:province":"IL",
    "sg:tags":[
        "car",
        "used"
    ],
    "wof:name":"Wheeler's Auto",
    "wof:placetype":"venue"
},
  "geometry": {"coordinates":[-87.984073,42.242168],"type":"Point"}
}