{
  "type": "Feature",
  "properties": {
    "iso:country":"US",
    "sg:address":"802 W Main St",
    "sg:city":"Carbondale",
    "sg:classifiers":[
        {
            "category":"Professional",
            "subcategory":"Lawyer & Legal Services",
            "type":"Services"
        }
    ],
    "sg:phone":"+1 618 549 4529",
    "sg:postcode":"62901",
    "sg:province":"IL",
    "sg:tags":[
        "attorney"
    ],
    "sg:website":"www.habigerelderlaw.com",
    "wof:name":"Habinger & Assoc Elder Law",
    "wof:placetype":"venue"
},
  "geometry": {"coordinates":[-89.225451,37.726608],"type":"Point"}
}