{
  "type": "Feature",
  "properties": {
    "addr:full":"4164 Shorewood Dr Rockford IL 61101",
    "addr:housenumber":"4164",
    "addr:postcode":"61101",
    "addr:street":"Shorewood Dr",
    "iso:country":"US",
    "sg:address":"4164 Shorewood Dr",
    "sg:city":"Rockford",
    "sg:classifiers":[
        {
            "category":"Building & Trades",
            "subcategory":"Construction",
            "type":"Services"
        }
    ],
    "sg:phone":"+1 815 962 1445",
    "sg:postcode":"61101",
    "sg:province":"IL",
    "sg:tags":[
        "hanging",
        "contractor"
    ],
    "wof:name":"K&M Home Services Inc",
    "wof:placetype":"venue"
},
  "geometry": {"coordinates":[-89.13882,42.316012],"type":"Point"}
}