{
  "type": "Feature",
  "properties": {
    "iso:country":"US",
    "sg:address":"4325 Alby St",
    "sg:city":"Alton",
    "sg:classifiers":[
        {
            "category":"Health Services",
            "subcategory":"Doctor",
            "type":"Services"
        }
    ],
    "sg:phone":"+1 618 462 3888",
    "sg:postcode":"62002",
    "sg:province":"IL",
    "sg:tags":[
        "physician",
        "surgeon"
    ],
    "wof:name":"Foot Health Ctr Inc",
    "wof:placetype":"venue"
},
  "geometry": {"coordinates":[-90.17961200000001,38.921548],"type":"Point"}
}