{
  "type": "Feature",
  "properties": {
    "addr:full":"2209 Howard St Evanston IL 60202",
    "addr:housenumber":"2209",
    "addr:postcode":"60202",
    "addr:street":"Howard St",
    "iso:country":"US",
    "sg:address":"2209 Howard St",
    "sg:city":"Evanston",
    "sg:classifiers":[
        {
            "category":"Coffee & Tea",
            "type":"Food & Drink"
        }
    ],
    "sg:menulink":"http://www.allmenus.com/il/chicago/112479-starbucks-coffee/menu/",
    "sg:phone":"+1 847 733 1144",
    "sg:postcode":"60202",
    "sg:province":"IL",
    "sg:tags":[
        "american"
    ],
    "wof:name":"Starbucks Coffee",
    "wof:placetype":"venue"
},
  "geometry": {"coordinates":[-87.704302,42.019264],"type":"Point"}
}