{
  "type": "Feature",
  "properties": {
    "addr:full":"7 Augusta Ct Lake In The Hills IL 60156",
    "addr:housenumber":"7",
    "addr:postcode":"60156",
    "addr:street":"Augusta Ct",
    "iso:country":"US",
    "sg:address":"7 Augusta Ct",
    "sg:city":"Lake In The Hills",
    "sg:classifiers":[
        {
            "category":"Professional",
            "subcategory":"Business Services",
            "type":"Services"
        }
    ],
    "sg:phone":"+1   ",
    "sg:postcode":"60156",
    "sg:province":"IL",
    "sg:tags":[
        "furniture"
    ],
    "wof:name":"Finishing Touches",
    "wof:placetype":"venue"
},
  "geometry": {"coordinates":[-88.355738,42.179735],"type":"Point"}
}