{
  "type": "Feature",
  "properties": {
    "addr:full":"3201 S Halsted Chicago IL 60608",
    "addr:housenumber":"3201",
    "addr:postcode":"60608",
    "addr:street":"S Halsted",
    "iso:country":"US",
    "sg:address":"3201 S Halsted",
    "sg:city":"Chicago",
    "sg:classifiers":[
        {
            "category":"Shopping",
            "subcategory":"Bicycles & Sporting Goods",
            "type":"Retail Goods"
        }
    ],
    "sg:phone":"+1 312 225 3780",
    "sg:postcode":"60608",
    "sg:province":"IL",
    "sg:tags":[
        "bike"
    ],
    "sg:website":"www.bluecitycycles.com/",
    "wof:name":"Blue City Cycles",
    "wof:placetype":"venue"
},
  "geometry": {"coordinates":[-87.645865,41.835982],"type":"Point"}
}