{
  "type": "Feature",
  "properties": {
    "iso:country":"US",
    "sg:address":"106 Stephen St",
    "sg:city":"Lemont",
    "sg:classifiers":[
        {
            "category":"Professional",
            "subcategory":"Management & Consulting",
            "type":"Services"
        }
    ],
    "sg:phone":"+1 630 243 0145",
    "sg:postcode":"60439",
    "sg:province":"IL",
    "wof:name":"Lifecore",
    "wof:placetype":"venue"
},
  "geometry": {"coordinates":[-87.999117,41.675365],"type":"Point"}
}