{
  "type": "Feature",
  "properties": {
    "iso:country":"US",
    "sg:address":"2777 Black Rd",
    "sg:city":"Joliet",
    "sg:classifiers":[
        {
            "category":"Restaurant",
            "type":"Food & Drink"
        }
    ],
    "sg:phone":"+1 815 744 1060",
    "sg:postcode":"60435",
    "sg:province":"IL",
    "sg:tags":[
        "delicatessen"
    ],
    "wof:name":"Deli Depot",
    "wof:placetype":"venue"
},
  "geometry": {"coordinates":[-88.14977500000001,41.53668],"type":"Point"}
}