{
  "type": "Feature",
  "properties": {
    "addr:full":"3246 N Pulaski Rd Chicago IL 60641",
    "addr:housenumber":"3246",
    "addr:postcode":"60641",
    "addr:street":"N Pulaski Rd",
    "iso:country":"US",
    "sg:address":"3246 N Pulaski Rd",
    "sg:city":"Chicago",
    "sg:classifiers":[
        {
            "category":"Shopping",
            "subcategory":"Bridal",
            "type":"Retail Goods"
        }
    ],
    "sg:phone":"+1 773 685 8494",
    "sg:postcode":"60641",
    "sg:province":"IL",
    "sg:website":"lilysbridalchicago.com",
    "wof:name":"Lily's Bridal & Gifts",
    "wof:placetype":"venue"
},
  "geometry": {"coordinates":[-87.72717400000001,41.940206],"type":"Point"}
}