{
  "type": "Feature",
  "properties": {
    "iso:country":"US",
    "sg:address":"2285 Cedar Point Ct",
    "sg:city":"Elgin",
    "sg:classifiers":[
        {
            "category":"Shopping",
            "subcategory":"Computers & Home Electronics",
            "type":"Retail Goods"
        }
    ],
    "sg:phone":"+1 847 622 1357",
    "sg:postcode":"60123",
    "sg:province":"IL",
    "sg:tags":[
        "equipment"
    ],
    "wof:name":"Productive Computers Inc",
    "wof:placetype":"venue"
},
  "geometry": {"coordinates":[-88.33275399999999,41.998424],"type":"Point"}
}