{
  "type": "Feature",
  "properties": {
    "addr:full":"4720 State Rte 3 Wolf Lake IL 62998",
    "addr:housenumber":"4720",
    "addr:postcode":"62998",
    "addr:street":"State Rte 3 Wolf",
    "iso:country":"US",
    "sg:address":"4720 State Rte 3",
    "sg:city":"Wolf Lake",
    "sg:classifiers":[
        {
            "category":"Education",
            "subcategory":"Library",
            "type":"Public Place"
        }
    ],
    "sg:phone":"+1 618 833 4923",
    "sg:postcode":"62998",
    "sg:province":"IL",
    "wof:name":"Wolfe Lake Branch Library",
    "wof:placetype":"venue"
},
  "geometry": {"coordinates":[-89.442915,37.512155],"type":"Point"}
}