{
  "type": "Feature",
  "properties": {
    "iso:country":"US",
    "sg:address":"291 Trestle Ave",
    "sg:city":"Highland",
    "sg:phone":"+1 618 654 3998",
    "sg:postcode":"62249",
    "sg:province":"IL",
    "sg:tags":[
        "farm",
        "soybean"
    ],
    "wof:name":"Maurice Hartlieb",
    "wof:placetype":"venue"
},
  "geometry": {"coordinates":[-89.577639,38.757352],"type":"Point"}
}