{
  "type": "Feature",
  "properties": {
    "iso:country":"US",
    "sg:address":"708 Brittany Dr",
    "sg:city":"Champaign",
    "sg:classifiers":[
        {
            "category":"Restaurant",
            "type":"Food & Drink"
        }
    ],
    "sg:phone":"+1   ",
    "sg:postcode":"61822",
    "sg:province":"IL",
    "sg:tags":[
        "eating"
    ],
    "wof:name":"Jignesh",
    "wof:placetype":"venue"
},
  "geometry": {"coordinates":[-88.301709,40.123003],"type":"Point"}
}