{
  "type": "Feature",
  "properties": {
    "addr:full":"111 N Main St Crystal Lake IL 60014",
    "addr:housenumber":"111",
    "addr:postcode":"60014",
    "addr:street":"N Main St",
    "iso:country":"US",
    "sg:address":"111 N Main St",
    "sg:city":"Crystal Lake",
    "sg:classifiers":[
        {
            "category":"Restaurant",
            "type":"Food & Drink"
        }
    ],
    "sg:phone":"+1 815 479 1770",
    "sg:postcode":"60014",
    "sg:province":"IL",
    "wof:name":"Christopher's",
    "wof:placetype":"venue"
},
  "geometry": {"coordinates":[-88.31602100000001,42.24447],"type":"Point"}
}