{
  "type": "Feature",
  "properties": {
    "iso:country":"US",
    "sg:address":"1020 Lakehurst Rd",
    "sg:city":"Waukegan",
    "sg:classifiers":[
        {
            "category":"Professional",
            "subcategory":"Computer Services",
            "type":"Services"
        }
    ],
    "sg:phone":"+1 847 473 4653",
    "sg:postcode":"60085",
    "sg:province":"IL",
    "sg:tags":[
        "related"
    ],
    "wof:name":"Rockhopper Media",
    "wof:placetype":"venue"
},
  "geometry": {"coordinates":[-87.90003,42.345785],"type":"Point"}
}