{
  "type": "Feature",
  "properties": {
    "iso:country":"US",
    "sg:address":"12511 S 81st Ave",
    "sg:city":"Palos Park",
    "sg:classifiers":[
        {
            "category":"Building & Trades",
            "subcategory":"Construction",
            "type":"Services"
        }
    ],
    "sg:phone":"+1 708 361 5208",
    "sg:postcode":"60464",
    "sg:province":"IL",
    "sg:tags":[
        "house"
    ],
    "wof:name":"Teds Remodeling",
    "wof:placetype":"venue"
},
  "geometry": {"coordinates":[-87.818058,41.662305],"type":"Point"}
}