{
  "type": "Feature",
  "properties": {
    "iso:country":"US",
    "sg:address":"25296 Toboggan Ave",
    "sg:city":"Hopedale",
    "sg:classifiers":[
        {
            "category":"Building & Trades",
            "subcategory":"Construction",
            "type":"Services"
        }
    ],
    "sg:phone":"+1 309 449 6276",
    "sg:postcode":"61747",
    "sg:province":"IL",
    "sg:tags":[
        "residential"
    ],
    "wof:name":"Canopy Construction",
    "wof:placetype":"venue"
},
  "geometry": {"coordinates":[-89.447865,40.409979],"type":"Point"}
}