{
  "type": "Feature",
  "properties": {
    "addr:full":"740 Winston Dr Elk Grove Village IL 60007",
    "addr:housenumber":"740",
    "addr:postcode":"60007",
    "addr:street":"Winston Dr",
    "iso:country":"US",
    "sg:address":"740 Winston Dr",
    "sg:city":"Elk Grove Village",
    "sg:classifiers":[
        {
            "category":"Real Estate",
            "subcategory":"Real Estate Agent",
            "type":"Services"
        }
    ],
    "sg:phone":"+1 847 439 1705",
    "sg:postcode":"60007",
    "sg:province":"IL",
    "sg:tags":[
        "manager",
        "property"
    ],
    "wof:name":"Lone Mountain Center LLC",
    "wof:placetype":"venue"
},
  "geometry": {"coordinates":[-88.015235,42.010001],"type":"Point"}
}