{
  "type": "Feature",
  "properties": {
    "iso:country":"US",
    "sg:address":"2107 Marquette Rd",
    "sg:city":"Peru",
    "sg:classifiers":[
        {
            "category":"Banks & Credit Unions",
            "subcategory":"Bank",
            "type":"Services"
        }
    ],
    "sg:phone":"+1 815 224 2666",
    "sg:postcode":"61354",
    "sg:province":"IL",
    "sg:website":"www.ivcu.com",
    "wof:name":"Illinois Valley Credit Union",
    "wof:placetype":"venue"
},
  "geometry": {"coordinates":[-89.116957,41.341538],"type":"Point"}
}