{
  "type": "Feature",
  "properties": {
    "addr:full":"206 S Merchant St Effingham IL 62401",
    "addr:housenumber":"206",
    "addr:postcode":"62401",
    "addr:street":"S Merchant St",
    "iso:country":"US",
    "sg:address":"206 S Merchant St",
    "sg:city":"Effingham",
    "sg:classifiers":[
        {
            "category":"Building & Trades",
            "subcategory":"Plumbing",
            "type":"Services"
        }
    ],
    "sg:phone":"+1 217 342 2744",
    "sg:postcode":"62401",
    "sg:province":"IL",
    "sg:tags":[
        "plumbing",
        "contractor"
    ],
    "wof:name":"Boos Plumbing & Heating Co",
    "wof:placetype":"venue"
},
  "geometry": {"coordinates":[-88.54656799999999,39.120456],"type":"Point"}
}