{
  "type": "Feature",
  "properties": {
    "iso:country":"US",
    "sg:address":"602 N 14th St",
    "sg:city":"Murphysboro",
    "sg:classifiers":[
        {
            "category":"Structure",
            "subcategory":"Warehouse",
            "type":"Public Place"
        },
        {
            "category":"Retail",
            "subcategory":"Storage",
            "type":"Services"
        }
    ],
    "sg:phone":"+1 618 687 5547",
    "sg:postcode":"62966",
    "sg:province":"IL",
    "sg:tags":[
        "self",
        "commercial",
        "warehouses-public-commercial",
        "household"
    ],
    "wof:name":"Self Service Storage",
    "wof:placetype":"venue"
},
  "geometry": {"coordinates":[-89.338142,37.770209],"type":"Point"}
}