{
  "type": "Feature",
  "properties": {
    "iso:country":"US",
    "sg:address":"107 Rand Rd",
    "sg:city":"Lakemoor",
    "sg:classifiers":[
        {
            "category":"Personal",
            "subcategory":"Beauty Salon",
            "type":"Services"
        }
    ],
    "sg:phone":"+1 815 344 4448",
    "sg:postcode":"60051",
    "sg:province":"IL",
    "wof:name":"Asymmetric Hair Salon",
    "wof:placetype":"venue"
},
  "geometry": {"coordinates":[-88.198768,42.328546],"type":"Point"}
}