{
  "type": "Feature",
  "properties": {
    "addr:full":"4878 N Broadway St Chicago IL 60640",
    "addr:housenumber":"4878",
    "addr:postcode":"60640",
    "addr:street":"N Broadway St",
    "iso:country":"US",
    "sg:address":"4878 N Broadway St",
    "sg:city":"Chicago",
    "sg:classifiers":[
        {
            "category":"Travel",
            "subcategory":"Travel Agent",
            "type":"Entertainment"
        }
    ],
    "sg:phone":"+1 773 907 0070",
    "sg:postcode":"60640",
    "sg:province":"IL",
    "sg:tags":[
        "agency",
        "bureau"
    ],
    "sg:website":"www.angeltours.com",
    "wof:name":"Angel Tours & Svc",
    "wof:placetype":"venue"
},
  "geometry": {"coordinates":[-87.65979299999999,41.970674],"type":"Point"}
}