{
  "type": "Feature",
  "properties": {
    "addr:full":"1150 Ensell Rd Lake Zurich IL 60047",
    "addr:housenumber":"1150",
    "addr:postcode":"60047",
    "addr:street":"Ensell Rd",
    "iso:country":"US",
    "sg:address":"1150 Ensell Rd",
    "sg:city":"Lake Zurich",
    "sg:classifiers":[
        {
            "category":"Building & Trades",
            "subcategory":"Plumbing",
            "type":"Services"
        }
    ],
    "sg:phone":"+1 847 705 6900",
    "sg:postcode":"60047",
    "sg:province":"IL",
    "sg:tags":[
        "repair",
        "contractor",
        "re"
    ],
    "wof:name":"Sterling Service Group Inc",
    "wof:placetype":"venue"
},
  "geometry": {"coordinates":[-88.068657,42.20462],"type":"Point"}
}