{
  "type": "Feature",
  "properties": {
    "iso:country":"US",
    "sg:address":"3037 N Cicero Ave",
    "sg:city":"Chicago",
    "sg:classifiers":[
        {
            "category":"Wholesale",
            "subcategory":"Auto Parts",
            "type":"Manufacturing & Wholesale Goods"
        }
    ],
    "sg:phone":"+1 773 685 6666",
    "sg:postcode":"60641",
    "sg:province":"IL",
    "wof:name":"Smart Auto Body Inc",
    "wof:placetype":"venue"
},
  "geometry": {"coordinates":[-87.74673799999999,41.936951],"type":"Point"}
}