{
  "type": "Feature",
  "properties": {
    "addr:full":"459 N Bolingbrook Dr Bolingbrook IL 60440",
    "addr:housenumber":"459",
    "addr:postcode":"60440",
    "addr:street":"N Bolingbrook Dr",
    "iso:country":"US",
    "sg:address":"459 N Bolingbrook Dr",
    "sg:city":"Bolingbrook",
    "sg:classifiers":[
        {
            "category":"Restaurant",
            "type":"Food & Drink"
        }
    ],
    "sg:phone":"+1   ",
    "sg:postcode":"60440",
    "sg:province":"IL",
    "sg:tags":[
        "eating"
    ],
    "wof:name":"Taste of The Orient Inc",
    "wof:placetype":"venue"
},
  "geometry": {"coordinates":[-88.068753,41.713148],"type":"Point"}
}