{
  "type": "Feature",
  "properties": {
    "iso:country":"US",
    "sg:address":"512 N Cramer Rd",
    "sg:city":"Elmwood",
    "sg:classifiers":[
        {
            "category":"Insurance",
            "subcategory":"Hazard Insurance",
            "type":"Services"
        }
    ],
    "sg:phone":"+1 309 245 2619",
    "sg:postcode":"61529",
    "sg:province":"IL",
    "wof:name":"Marvin W Johnson",
    "wof:placetype":"venue"
},
  "geometry": {"coordinates":[-89.947489,40.69603],"type":"Point"}
}