{
  "type": "Feature",
  "properties": {
    "addr:full":"1648 Birmingham Ln Crystal Lake IL 60014",
    "addr:housenumber":"1648",
    "addr:postcode":"60014",
    "addr:street":"Birmingham Ln",
    "iso:country":"US",
    "sg:address":"1648 Birmingham Ln",
    "sg:city":"Crystal Lake",
    "sg:classifiers":[
        {
            "category":"Professional",
            "subcategory":"Computer Services",
            "type":"Services"
        }
    ],
    "sg:phone":"+1 815 356 0402",
    "sg:postcode":"60014",
    "sg:province":"IL",
    "sg:tags":[
        "related"
    ],
    "wof:name":"Cdh Consulting Inc",
    "wof:placetype":"venue"
},
  "geometry": {"coordinates":[-88.354041,42.193376],"type":"Point"}
}