{
  "type": "Feature",
  "properties": {
    "addr:full":"129 Phelps Ave Ste 411 Rockford IL 61108",
    "addr:housenumber":"129",
    "addr:postcode":"61108",
    "addr:street":"Phelps Ave Ste 411",
    "iso:country":"US",
    "sg:address":"129 Phelps Ave Ste 411",
    "sg:city":"Rockford",
    "sg:classifiers":[
        {
            "category":"Insurance",
            "subcategory":"Insurance Agent",
            "type":"Services"
        },
        {
            "category":"Insurance",
            "subcategory":"Hazard Insurance",
            "type":"Services"
        },
        {
            "category":"Insurance",
            "subcategory":"Title Insurance",
            "type":"Services"
        },
        {
            "category":"Insurance",
            "subcategory":"Life Insurance",
            "type":"Services"
        }
    ],
    "sg:phone":"+1 815 397 5656",
    "sg:postcode":"61108",
    "sg:province":"IL",
    "sg:tags":[
        "auto",
        "commercial",
        "business",
        "homeowner"
    ],
    "sg:website":"http://www.countryfinancial.com/george.bass",
    "wof:name":"COUNTRY Financial George Bass",
    "wof:placetype":"venue"
},
  "geometry": {"coordinates":[-89.00457400000001,42.265226],"type":"Point"}
}