{
  "type": "Feature",
  "properties": {
    "addr:full":"1125 Hillside Ave Antioch IL 60002",
    "addr:housenumber":"1125",
    "addr:postcode":"60002",
    "addr:street":"Hillside Ave",
    "iso:country":"US",
    "sg:address":"1125 Hillside Ave",
    "sg:city":"Antioch",
    "sg:classifiers":[
        {
            "category":"Insurance",
            "subcategory":"Insurance Agent",
            "type":"Services"
        }
    ],
    "sg:phone":"+1 847 395 6655",
    "sg:postcode":"60002",
    "sg:province":"IL",
    "wof:name":"A-1 Family Insurance Agency",
    "wof:placetype":"venue"
},
  "geometry": {"coordinates":[-88.10453200000001,42.471964],"type":"Point"}
}