{
  "type": "Feature",
  "properties": {
    "addr:full":"1701 W Yorkhouse Rd Waukegan IL 60087",
    "addr:housenumber":"1701",
    "addr:postcode":"60087",
    "addr:street":"W Yorkhouse Rd",
    "iso:country":"US",
    "sg:address":"1701 W Yorkhouse Rd",
    "sg:city":"Waukegan",
    "sg:classifiers":[
        {
            "category":"Building & Trades",
            "subcategory":"Construction",
            "type":"Services"
        }
    ],
    "sg:phone":"+1 224 588 6009",
    "sg:postcode":"60087",
    "sg:province":"IL",
    "sg:tags":[
        "drywall",
        "painting",
        "contractor"
    ],
    "wof:name":"Maldonado's Drywall",
    "wof:placetype":"venue"
},
  "geometry": {"coordinates":[-87.85257,42.410099],"type":"Point"}
}