{
  "type": "Feature",
  "properties": {
    "addr:full":"7358 S Ashland Avenue Chicago IL 60636",
    "addr:housenumber":"7358",
    "addr:postcode":"60636",
    "addr:street":"S Ashland Avenue",
    "iso:country":"US",
    "sg:address":"7358 S Ashland Avenue",
    "sg:city":"Chicago",
    "sg:classifiers":[
        {
            "category":"Restaurant",
            "type":"Food & Drink"
        }
    ],
    "sg:phone":"+1 773 778 5622",
    "sg:postcode":"60636",
    "sg:province":"IL",
    "wof:name":"New Attitude Restaurant & Lounge",
    "wof:placetype":"venue"
},
  "geometry": {"coordinates":[-87.66368,41.759577],"type":"Point"}
}