{
  "type": "Feature",
  "properties": {
    "iso:country":"US",
    "sg:address":"2048 Northbrook Ct",
    "sg:city":"Northbrook",
    "sg:classifiers":[
        {
            "category":"Shopping",
            "subcategory":"Gifts & Souvenirs",
            "type":"Retail Goods"
        }
    ],
    "sg:phone":"+1 847 559 8111",
    "sg:postcode":"60062",
    "sg:province":"IL",
    "sg:tags":[
        "shop"
    ],
    "wof:name":"Row Bottoms And Willoughby",
    "wof:placetype":"venue"
},
  "geometry": {"coordinates":[-87.817125,42.152017],"type":"Point"}
}