{
  "type": "Feature",
  "properties": {
    "addr:full":"50 W Oakton St Des Plaines IL 60018",
    "addr:housenumber":"50",
    "addr:postcode":"60018",
    "addr:street":"W Oakton St",
    "iso:country":"US",
    "sg:address":"50 W Oakton St",
    "sg:city":"Des Plaines",
    "sg:classifiers":[
        {
            "category":"Organizations",
            "subcategory":"Labor Organization",
            "type":"Services"
        }
    ],
    "sg:phone":"+1 773 694 3898",
    "sg:postcode":"60018",
    "sg:province":"IL",
    "wof:name":"Local 1487",
    "wof:placetype":"venue"
},
  "geometry": {"coordinates":[-87.924612,42.022884],"type":"Point"}
}