{
  "type": "Feature",
  "properties": {
    "iso:country":"US",
    "sg:address":"2215 S 17th Ave Lowr",
    "sg:city":"Broadview",
    "sg:classifiers":[
        {
            "category":"Health Services",
            "subcategory":"Doctor",
            "type":"Services"
        }
    ],
    "sg:phone":"+1 708 344 7171",
    "sg:postcode":"60155",
    "sg:province":"IL",
    "wof:name":"Kelley Eric MD",
    "wof:placetype":"venue"
},
  "geometry": {"coordinates":[-87.852997,41.863701],"type":"Point"}
}