{
  "type": "Feature",
  "properties": {
    "iso:country":"US",
    "sg:address":"1269 N 89th St Ste 5",
    "sg:city":"East Saint Louis",
    "sg:classifiers":[
        {
            "category":"Education",
            "subcategory":"School",
            "type":"Public Place"
        },
        {
            "category":"Education",
            "subcategory":"University",
            "type":"Public Place"
        }
    ],
    "sg:phone":"+1 618 397 4973",
    "sg:postcode":"62203",
    "sg:province":"IL",
    "sg:tags":[
        "high",
        "middle",
        "college",
        "elementary"
    ],
    "wof:name":"University of Illinois",
    "wof:placetype":"venue"
},
  "geometry": {"coordinates":[-90.053497,38.5961],"type":"Point"}
}