{
  "type": "Feature",
  "properties": {
    "iso:country":"US",
    "sg:address":"8796 W Penn Corner Rd",
    "sg:city":"Polo",
    "sg:classifiers":[
        {
            "category":"Manufacturing",
            "subcategory":"Food",
            "type":"Manufacturing & Wholesale Goods"
        },
        {
            "category":"Farming",
            "subcategory":"Farm",
            "type":"Manufacturing & Wholesale Goods"
        }
    ],
    "sg:phone":"+1 815 946 3171",
    "sg:postcode":"61064",
    "sg:province":"IL",
    "sg:tags":[
        "corn",
        "product"
    ],
    "wof:name":"Russell Statler",
    "wof:placetype":"venue"
},
  "geometry": {"coordinates":[-89.50653200000001,41.945337],"type":"Point"}
}