{
  "type": "Feature",
  "properties": {
    "addr:full":"1807 W Armitage Ave Chicago IL 60622",
    "addr:housenumber":"1807",
    "addr:postcode":"60622",
    "addr:street":"W Armitage Ave",
    "iso:country":"US",
    "sg:address":"1807 W Armitage Ave",
    "sg:city":"Chicago",
    "sg:classifiers":[
        {
            "category":"Building & Trades",
            "subcategory":"Construction",
            "type":"Services"
        }
    ],
    "sg:phone":"+1 312 520 1500",
    "sg:postcode":"60622",
    "sg:province":"IL",
    "sg:tags":[
        "wallcoverings-installation",
        "wallpaper",
        "painting",
        "contractor"
    ],
    "wof:name":"Planet Earth Painting",
    "wof:placetype":"venue"
},
  "geometry": {"coordinates":[-87.673022,41.917846],"type":"Point"}
}