{
  "type": "Feature",
  "properties": {
    "addr:full":"5125 Elmgate Dr Rockford IL 61101",
    "addr:housenumber":"5125",
    "addr:postcode":"61101",
    "addr:street":"Elmgate Dr",
    "iso:country":"US",
    "sg:address":"5125 Elmgate Dr",
    "sg:city":"Rockford",
    "sg:classifiers":[
        {
            "category":"Personal",
            "subcategory":"Beauty Salon",
            "type":"Services"
        }
    ],
    "sg:phone":"+1 815 987 0456",
    "sg:postcode":"61101",
    "sg:province":"IL",
    "sg:tags":[
        "shop"
    ],
    "wof:name":"Cross Cuts",
    "wof:placetype":"venue"
},
  "geometry": {"coordinates":[-89.110392,42.334433],"type":"Point"}
}