{
  "type": "Feature",
  "properties": {
    "addr:full":"634 Spring Rd Elmhurst IL 60126",
    "addr:housenumber":"634",
    "addr:postcode":"60126",
    "addr:street":"Spring Rd",
    "iso:country":"US",
    "sg:address":"634 Spring Rd",
    "sg:city":"Elmhurst",
    "sg:classifiers":[
        {
            "category":"Building & Trades",
            "subcategory":"Construction",
            "type":"Services"
        }
    ],
    "sg:phone":"+1 630 351 8360",
    "sg:postcode":"60126",
    "sg:province":"IL",
    "sg:tags":[
        "residential"
    ],
    "wof:name":"Gianni Homes Inc",
    "wof:placetype":"venue"
},
  "geometry": {"coordinates":[-87.94962700000001,41.88025],"type":"Point"}
}