{
  "type": "Feature",
  "properties": {
    "addr:full":"6134 N Artesian Ave Chicago IL 60659",
    "addr:housenumber":"6134",
    "addr:postcode":"60659",
    "addr:street":"N Artesian Ave",
    "iso:country":"US",
    "sg:address":"6134 N Artesian Ave",
    "sg:city":"Chicago",
    "sg:classifiers":[
        {
            "category":"Shopping",
            "subcategory":"Stationery & Office Supplies",
            "type":"Retail Goods"
        }
    ],
    "sg:phone":"+1 773 761 9655",
    "sg:postcode":"60659",
    "sg:province":"IL",
    "sg:tags":[
        "equipment"
    ],
    "wof:name":"A Reliable Copy Shop",
    "wof:placetype":"venue"
},
  "geometry": {"coordinates":[-87.691152,41.992864],"type":"Point"}
}