{
  "type": "Feature",
  "properties": {
    "addr:full":"871 E Dundee Rd Palatine IL 60074",
    "addr:housenumber":"871",
    "addr:postcode":"60074",
    "addr:street":"E Dundee Rd",
    "iso:country":"US",
    "sg:address":"871 E Dundee Rd",
    "sg:city":"Palatine",
    "sg:classifiers":[
        {
            "category":"Manufacturing",
            "subcategory":"Rubber & Plastics",
            "type":"Manufacturing & Wholesale Goods"
        },
        {
            "category":"Autos & Motor Vehicles",
            "subcategory":"Auto Supplies",
            "type":"Retail Goods"
        },
        {
            "category":"Retail",
            "subcategory":"Auto Repair",
            "type":"Services"
        }
    ],
    "sg:phone":"+1 847 776 8540",
    "sg:postcode":"60074",
    "sg:province":"IL",
    "sg:tags":[
        "wheel",
        "tires-wholesale",
        "tire",
        "retread",
        "balancing",
        "wheels-aligning",
        "recap",
        "brake",
        "manufacturer"
    ],
    "sg:website":"http://www.ntb.com",
    "wof:name":"NTB - National Tire & Battery",
    "wof:placetype":"venue"
},
  "geometry": {"coordinates":[-88.022414,42.139166],"type":"Point"}
}