{
  "type": "Feature",
  "properties": {
    "iso:country":"US",
    "sg:address":"20420 Rand Rd",
    "sg:city":"Kildeer",
    "sg:classifiers":[
        {
            "category":"Bars & Pubs",
            "type":"Food & Drink"
        },
        {
            "category":"Restaurant",
            "type":"Food & Drink"
        },
        {
            "category":"Bars & Pubs",
            "subcategory":"Lounge",
            "type":"Food & Drink"
        }
    ],
    "sg:phone":"+1 847 550 6411",
    "sg:postcode":"60074",
    "sg:province":"IL",
    "sg:tags":[
        "cocktail"
    ],
    "wof:name":"John's Pub",
    "wof:placetype":"venue"
},
  "geometry": {"coordinates":[-88.049072,42.160247],"type":"Point"}
}