{
  "type": "Feature",
  "properties": {
    "addr:full":"823 Clinton St Ottawa IL 61350",
    "addr:housenumber":"823",
    "addr:postcode":"61350",
    "addr:street":"Clinton St",
    "iso:country":"US",
    "sg:address":"823 Clinton St",
    "sg:city":"Ottawa",
    "sg:classifiers":[
        {
            "category":"Banks & Credit Unions",
            "subcategory":"Investment Brokerage",
            "type":"Services"
        },
        {
            "category":"Insurance",
            "subcategory":"Insurance Agent",
            "type":"Services"
        }
    ],
    "sg:phone":"+1 815 434 9303",
    "sg:postcode":"61350",
    "sg:province":"IL",
    "sg:tags":[
        "advisory",
        "financial"
    ],
    "wof:name":"Killelea Financial Services",
    "wof:placetype":"venue"
},
  "geometry": {"coordinates":[-88.844205,41.348683],"type":"Point"}
}