{
  "type": "Feature",
  "properties": {
    "iso:country":"US",
    "sg:address":"158 Old Dundee Rd",
    "sg:city":"Barrington",
    "sg:classifiers":[
        {
            "category":"Freight",
            "type":"Transportation"
        }
    ],
    "sg:phone":"+1 847 756 4490",
    "sg:postcode":"60010",
    "sg:province":"IL",
    "sg:tags":[
        "local",
        "storage",
        "trucking"
    ],
    "wof:name":"K Line Transit",
    "wof:placetype":"venue"
},
  "geometry": {"coordinates":[-88.181195,42.114253],"type":"Point"}
}