{
  "type": "Feature",
  "properties": {
    "iso:country":"US",
    "sg:address":"1300 W Belmont",
    "sg:city":"Chicago",
    "sg:classifiers":[
        {
            "category":"Health Services",
            "subcategory":"Clinic",
            "type":"Services"
        },
        {
            "category":"Professional",
            "subcategory":"Management & Consulting",
            "type":"Services"
        }
    ],
    "sg:phone":"+1 847 207 2168",
    "sg:postcode":"60657",
    "sg:province":"IL",
    "sg:tags":[
        "counseling",
        "life",
        "coach",
        "mental"
    ],
    "wof:name":"Ruby Slippers Coaching",
    "wof:placetype":"venue"
},
  "geometry": {"coordinates":[-87.66158799999999,41.939871],"type":"Point"}
}