{
  "type": "Feature",
  "properties": {
    "addr:full":"2515 Moss Ln New Lenox IL 60451",
    "addr:housenumber":"2515",
    "addr:postcode":"60451",
    "addr:street":"Moss Ln",
    "iso:country":"US",
    "sg:address":"2515 Moss Ln",
    "sg:city":"New Lenox",
    "sg:classifiers":[
        {
            "category":"Professional",
            "subcategory":"Management & Consulting",
            "type":"Services"
        }
    ],
    "sg:phone":"+1 815 722 0841",
    "sg:postcode":"60451",
    "sg:province":"IL",
    "wof:name":"PSW Consultants",
    "wof:placetype":"venue"
},
  "geometry": {"coordinates":[-88.02174100000001,41.518421],"type":"Point"}
}