{
  "type": "Feature",
  "properties": {
    "iso:country":"US",
    "sg:address":"604 Kenneth",
    "sg:city":"Heyworth",
    "sg:classifiers":[
        {
            "category":"Freight",
            "type":"Transportation"
        }
    ],
    "sg:phone":"+1 309 473 2534",
    "sg:postcode":"61745",
    "sg:province":"IL",
    "sg:tags":[
        "operator",
        "local",
        "trucking"
    ],
    "wof:name":"Ron Cline Trucking",
    "wof:placetype":"venue"
},
  "geometry": {"coordinates":[-88.986108,40.314515],"type":"Point"}
}