{
  "type": "Feature",
  "properties": {
    "addr:full":"110 E 79th Street Chicago IL 60619",
    "addr:housenumber":"110",
    "addr:postcode":"60619",
    "addr:street":"E 79Th Street",
    "iso:country":"US",
    "sg:address":"110 E 79th Street",
    "sg:city":"Chicago",
    "sg:classifiers":[
        {
            "category":"Health Services",
            "subcategory":"Dentist",
            "type":"Services"
        }
    ],
    "sg:phone":"+1 773 488 3579",
    "sg:postcode":"60619",
    "sg:province":"IL",
    "wof:name":"H & W Dental Assoc",
    "wof:placetype":"venue"
},
  "geometry": {"coordinates":[-87.621307,41.750783],"type":"Point"}
}