{
  "type": "Feature",
  "properties": {
    "addr:full":"17 Lakeside Ln North Barrington IL 60010",
    "addr:housenumber":"17",
    "addr:postcode":"60010",
    "addr:street":"Lakeside Ln",
    "iso:country":"US",
    "sg:address":"17 Lakeside Ln",
    "sg:city":"North Barrington",
    "sg:classifiers":[
        {
            "category":"Professional",
            "subcategory":"Management & Consulting",
            "type":"Services"
        }
    ],
    "sg:phone":"+1 847 381 3872",
    "sg:postcode":"60010",
    "sg:province":"IL",
    "sg:tags":[
        "marketing",
        "consultant"
    ],
    "sg:website":"www.wilkesandmclean.com",
    "wof:name":"Wilkes & Mc Lean LTD",
    "wof:placetype":"venue"
},
  "geometry": {"coordinates":[-88.120153,42.232334],"type":"Point"}
}