{
  "type": "Feature",
  "properties": {
    "iso:country":"US",
    "sg:address":"106 N Clinton St",
    "sg:city":"Collinsville",
    "sg:classifiers":[
        {
            "category":"Personal",
            "subcategory":"Beauty Salon",
            "type":"Services"
        }
    ],
    "sg:phone":"+1 618 344 5229",
    "sg:postcode":"62234",
    "sg:province":"IL",
    "wof:name":"Linda's Beauty Spot",
    "wof:placetype":"venue"
},
  "geometry": {"coordinates":[-89.987413,38.669691],"type":"Point"}
}