{
  "type": "Feature",
  "properties": {
    "addr:full":"2748 Wisconsin Ave Downers Grove IL 60515",
    "addr:housenumber":"2748",
    "addr:postcode":"60515",
    "addr:street":"Wisconsin Ave",
    "iso:country":"US",
    "sg:address":"2748 Wisconsin Ave",
    "sg:city":"Downers Grove",
    "sg:classifiers":[
        {
            "category":"Shopping",
            "subcategory":"Gifts & Souvenirs",
            "type":"Retail Goods"
        }
    ],
    "sg:phone":"+1 630 852 7544",
    "sg:postcode":"60515",
    "sg:province":"IL",
    "sg:tags":[
        "shop"
    ],
    "wof:name":"Ashro Life Style",
    "wof:placetype":"venue"
},
  "geometry": {"coordinates":[-88.050387,41.789548],"type":"Point"}
}