{
  "type": "Feature",
  "properties": {
    "addr:full":"103 W Willow Rd Prospect Heights IL 60070",
    "addr:housenumber":"103",
    "addr:postcode":"60070",
    "addr:street":"W Willow Rd",
    "iso:country":"US",
    "sg:address":"103 W Willow Rd",
    "sg:city":"Prospect Heights",
    "sg:classifiers":[
        {
            "category":"Wholesale",
            "subcategory":"Chemicals & Plastics",
            "type":"Manufacturing & Wholesale Goods"
        }
    ],
    "sg:phone":"+1 847 670 0205",
    "sg:postcode":"60070",
    "sg:province":"IL",
    "wof:name":"Parachem",
    "wof:placetype":"venue"
},
  "geometry": {"coordinates":[-87.94157800000001,42.102479],"type":"Point"}
}