{
  "type": "Feature",
  "properties": {
    "iso:country":"US",
    "sg:address":"161 N Edison Ave",
    "sg:city":"Elgin",
    "sg:classifiers":[
        {
            "category":"Shopping",
            "subcategory":"Bicycles & Sporting Goods",
            "type":"Retail Goods"
        }
    ],
    "sg:phone":"+1 847 695 3990",
    "sg:postcode":"60123",
    "sg:province":"IL",
    "wof:name":"Gun Room",
    "wof:placetype":"venue"
},
  "geometry": {"coordinates":[-88.304461,42.03736],"type":"Point"}
}