{
  "type": "Feature",
  "properties": {
    "addr:full":"850 N Galena Ave Dixon IL 61021",
    "addr:housenumber":"850",
    "addr:postcode":"61021",
    "addr:street":"N Galena Ave",
    "iso:country":"US",
    "sg:address":"850 N Galena Ave",
    "sg:city":"Dixon",
    "sg:classifiers":[
        {
            "category":"Personal",
            "subcategory":"Beauty Salon",
            "type":"Services"
        }
    ],
    "sg:phone":"+1 815 284 4424",
    "sg:postcode":"61021",
    "sg:province":"IL",
    "wof:name":"Skin Deep Spa Treatments",
    "wof:placetype":"venue"
},
  "geometry": {"coordinates":[-89.488257,41.854952],"type":"Point"}
}