{
  "type": "Feature",
  "properties": {
    "addr:full":"1 E Wacker Dr Chicago IL 60601",
    "addr:housenumber":"1",
    "addr:postcode":"60601",
    "addr:street":"E;Dr",
    "iso:country":"US",
    "sg:address":"1 E Wacker Dr",
    "sg:city":"Chicago",
    "sg:classifiers":[
        {
            "category":"Professional",
            "subcategory":"Lawyer & Legal Services",
            "type":"Services"
        }
    ],
    "sg:phone":"+1 312 782 5010",
    "sg:postcode":"60601",
    "sg:province":"IL",
    "wof:name":"Gozdecki & Del Giudice",
    "wof:placetype":"venue"
},
  "geometry": {"coordinates":[-87.62795300000001,41.886937],"type":"Point"}
}