{
  "type": "Feature",
  "properties": {
    "iso:country":"US",
    "sg:address":"5301 N Central Ave",
    "sg:city":"Chicago",
    "sg:classifiers":[
        {
            "category":"Real Estate",
            "subcategory":"Real Estate Services",
            "type":"Services"
        },
        {
            "category":"Building & Trades",
            "subcategory":"Plumbing",
            "type":"Services"
        },
        {
            "category":"Building & Trades",
            "subcategory":"Construction",
            "type":"Services"
        }
    ],
    "sg:phone":"+1 773 355 5511",
    "sg:postcode":"60630",
    "sg:province":"IL",
    "sg:tags":[
        "management",
        "property",
        "contractor"
    ],
    "wof:name":"Certified Heating & Cooling",
    "wof:placetype":"venue"
},
  "geometry": {"coordinates":[-87.768427,41.977384],"type":"Point"}
}