{
  "type": "Feature",
  "properties": {
    "iso:country":"US",
    "sg:address":"11321 S Lawler Ave",
    "sg:city":"Alsip",
    "sg:classifiers":[
        {
            "category":"Building & Trades",
            "subcategory":"Construction",
            "type":"Services"
        }
    ],
    "sg:phone":"+1 708 371 9088",
    "sg:postcode":"60803",
    "sg:province":"IL",
    "sg:tags":[
        "contractor"
    ],
    "wof:name":"Champion Construction Co Inc",
    "wof:placetype":"venue"
},
  "geometry": {"coordinates":[-87.74389600000001,41.686401],"type":"Point"}
}