{
  "type": "Feature",
  "properties": {
    "iso:country":"US",
    "sg:address":"8019 Linder Ave",
    "sg:city":"Burbank",
    "sg:classifiers":[
        {
            "category":"Home & Garden",
            "subcategory":"Building Materials",
            "type":"Retail Goods"
        },
        {
            "category":"Professional",
            "subcategory":"Printing & Photocopies",
            "type":"Services"
        }
    ],
    "sg:phone":"+1 708 422 7677",
    "sg:postcode":"60459",
    "sg:province":"IL",
    "sg:tags":[
        "door",
        "garage",
        "opener",
        "door-overhead",
        "type"
    ],
    "wof:name":"S & R Overhead Doors",
    "wof:placetype":"venue"
},
  "geometry": {"coordinates":[-87.758264,41.746128],"type":"Point"}
}