{
  "type": "Feature",
  "properties": {
    "addr:full":"865 Parkway Ave Elgin IL 60120",
    "addr:housenumber":"865",
    "addr:postcode":"60120",
    "addr:street":"Parkway Ave",
    "iso:country":"US",
    "sg:address":"865 Parkway Ave",
    "sg:city":"Elgin",
    "sg:classifiers":[
        {
            "category":"Organizations",
            "subcategory":"Religious Organization",
            "type":"Services"
        }
    ],
    "sg:phone":"+1 847 741 5683",
    "sg:postcode":"60120",
    "sg:province":"IL",
    "wof:name":"New Covenant Fellowship",
    "wof:placetype":"venue"
},
  "geometry": {"coordinates":[-88.25729,42.062008],"type":"Point"}
}