{
  "type": "Feature",
  "properties": {
    "addr:full":"1620 S 9th St Mattoon IL 61938",
    "addr:housenumber":"1620",
    "addr:postcode":"61938",
    "addr:street":"S 9Th St",
    "iso:country":"US",
    "sg:address":"1620 S 9th St",
    "sg:city":"Mattoon",
    "sg:classifiers":[
        {
            "category":"Real Estate",
            "subcategory":"Real Estate Operator",
            "type":"Services"
        }
    ],
    "sg:phone":"+1 217 234 8330",
    "sg:postcode":"61938",
    "sg:province":"IL",
    "sg:tags":[
        "property",
        "lessor"
    ],
    "wof:name":"Dick Scalet",
    "wof:placetype":"venue"
},
  "geometry": {"coordinates":[-88.364205,39.466112],"type":"Point"}
}