{
  "type": "Feature",
  "properties": {
    "iso:country":"US",
    "sg:address":"5019 Highland Ave",
    "sg:city":"Downers Grove",
    "sg:classifiers":[
        {
            "category":"Travel",
            "subcategory":"Travel Agent",
            "type":"Entertainment"
        }
    ],
    "sg:phone":"+1 630 971 1985",
    "sg:postcode":"60515",
    "sg:province":"IL",
    "sg:tags":[
        "agency"
    ],
    "wof:name":"Grove Travel",
    "wof:placetype":"venue"
},
  "geometry": {"coordinates":[-88.009221,41.796011],"type":"Point"}
}