{
  "type": "Feature",
  "properties": {
    "addr:full":"680 N Lake Shore Drive Apt 902 Chicago IL 60611",
    "addr:housenumber":"680;902",
    "addr:postcode":"60611",
    "addr:street":"N Lake Shore Drive Apt",
    "iso:country":"US",
    "sg:address":"680 N Lake Shore Drive Apt 902",
    "sg:city":"Chicago",
    "sg:classifiers":[
        {
            "category":"Shopping",
            "subcategory":"Mobile Phones",
            "type":"Retail Goods"
        }
    ],
    "sg:phone":"+1 312 337 5316",
    "sg:postcode":"60611",
    "sg:province":"IL",
    "wof:name":"Cypress Communications",
    "wof:placetype":"venue"
},
  "geometry": {"coordinates":[-87.615736,41.894755],"type":"Point"}
}