{
  "type": "Feature",
  "properties": {
    "iso:country":"US",
    "sg:address":"2500 Galen Dr Ste 7",
    "sg:city":"Champaign",
    "sg:classifiers":[
        {
            "category":"Professional",
            "subcategory":"Employment Agencies",
            "type":"Services"
        },
        {
            "category":"Professional",
            "subcategory":"Computer Services",
            "type":"Services"
        }
    ],
    "sg:phone":"+1 217 398 9000",
    "sg:postcode":"61821",
    "sg:province":"IL",
    "sg:tags":[
        "repair"
    ],
    "sg:website":"www.williscomputing.com",
    "wof:name":"Willis Computing Specialist",
    "wof:placetype":"venue"
},
  "geometry": {"coordinates":[-88.262079,40.082068],"type":"Point"}
}