{
  "type": "Feature",
  "properties": {
    "iso:country":"US",
    "sg:address":"1133 Arlington Heights Rd",
    "sg:city":"Arlington Heights",
    "sg:classifiers":[
        {
            "category":"Retail",
            "subcategory":"Laundry & Dry Cleaning",
            "type":"Services"
        }
    ],
    "sg:phone":"+1 847 439 5620",
    "sg:postcode":"60005",
    "sg:province":"IL",
    "sg:tags":[
        "drycleaning",
        "plant"
    ],
    "wof:name":"Norgetown Cleaners",
    "wof:placetype":"venue"
},
  "geometry": {"coordinates":[-87.979779,42.063017],"type":"Point"}
}