{
  "type": "Feature",
  "properties": {
    "iso:country":"US",
    "sg:address":"27W751 North Ave",
    "sg:city":"West Chicago",
    "sg:classifiers":[
        {
            "category":"Restaurant",
            "type":"Food & Drink"
        }
    ],
    "sg:phone":"+1 630 293 4774",
    "sg:postcode":"60185",
    "sg:province":"IL",
    "sg:tags":[
        "breakfast",
        "brunch"
    ],
    "wof:name":"Olde North",
    "wof:placetype":"venue"
},
  "geometry": {"coordinates":[-88.15078699999999,41.907905],"type":"Point"}
}