{
  "type": "Feature",
  "properties": {
    "iso:country":"US",
    "sg:address":"7407 Breese Rd",
    "sg:city":"Breese",
    "sg:classifiers":[
        {
            "category":"Farming",
            "subcategory":"Farm",
            "type":"Manufacturing & Wholesale Goods"
        }
    ],
    "sg:phone":"+1 618 526 7396",
    "sg:postcode":"62230",
    "sg:province":"IL",
    "sg:tags":[
        "crop",
        "general"
    ],
    "wof:name":"Duane Richter",
    "wof:placetype":"venue"
},
  "geometry": {"coordinates":[-89.56487199999999,38.597266],"type":"Point"}
}