{
  "type": "Feature",
  "properties": {
    "addr:full":"26 E Main St Round Lake Park IL 60073",
    "addr:housenumber":"26",
    "addr:postcode":"60073",
    "addr:street":"E Main St",
    "iso:country":"US",
    "sg:address":"26 E Main St",
    "sg:city":"Round Lake Park",
    "sg:classifiers":[
        {
            "category":"Building & Trades",
            "subcategory":"Construction",
            "type":"Services"
        }
    ],
    "sg:phone":"+1 847 740 1286",
    "sg:postcode":"60073",
    "sg:province":"IL",
    "sg:tags":[
        "dry wall",
        "contractor"
    ],
    "wof:name":"D H Drywall",
    "wof:placetype":"venue"
},
  "geometry": {"coordinates":[-88.082691,42.349733],"type":"Point"}
}