{
  "type": "Feature",
  "properties": {
    "addr:full":"126 E Wing St Arlington Hts IL 60004",
    "addr:housenumber":"126",
    "addr:postcode":"60004",
    "addr:street":"E Wing St",
    "iso:country":"US",
    "sg:address":"126 E Wing St",
    "sg:city":"Arlington Hts",
    "sg:classifiers":[
        {
            "category":"Personal",
            "type":"Services"
        }
    ],
    "sg:phone":"+1 847 253 2856",
    "sg:postcode":"60004",
    "sg:province":"IL",
    "sg:tags":[
        "consultant",
        "program",
        "health",
        "fitness"
    ],
    "sg:website":"www.arlingtonathletics.com",
    "wof:name":"APRIORIATHLETICS.COM",
    "wof:placetype":"venue"
},
  "geometry": {"coordinates":[-87.980774,42.083819],"type":"Point"}
}