{
  "type": "Feature",
  "properties": {
    "iso:country":"US",
    "sg:address":"500 Maine St",
    "sg:city":"Quincy",
    "sg:classifiers":[
        {
            "category":"Recreation",
            "type":"Entertainment"
        }
    ],
    "sg:phone":"+1 217 223 1406",
    "sg:postcode":"62301",
    "sg:province":"IL",
    "wof:name":"Aqua X",
    "wof:placetype":"venue"
},
  "geometry": {"coordinates":[-91.408446,39.931927],"type":"Point"}
}