{
  "type": "Feature",
  "properties": {
    "iso:country":"US",
    "sg:address":"9697 191st St",
    "sg:city":"Mokena",
    "sg:classifiers":[
        {
            "category":"Professional",
            "subcategory":"Accounting & Tax Preparation",
            "type":"Services"
        }
    ],
    "sg:phone":"+1 708 478 2900",
    "sg:postcode":"60448",
    "sg:province":"IL",
    "sg:tags":[
        "accountant",
        "public",
        "certified"
    ],
    "wof:name":"O'Neill & Gaspardo",
    "wof:placetype":"venue"
},
  "geometry": {"coordinates":[-87.854516,41.542897],"type":"Point"}
}