{
  "type": "Feature",
  "properties": {
    "addr:full":"801 W Deyoung St Ste B Marion IL 62959",
    "addr:housenumber":"801",
    "addr:postcode":"62959",
    "addr:street":"W Deyoung St Ste B",
    "iso:country":"US",
    "sg:address":"801 W Deyoung St Ste B",
    "sg:city":"Marion",
    "sg:classifiers":[
        {
            "category":"Insurance",
            "subcategory":"Hazard Insurance",
            "type":"Services"
        },
        {
            "category":"Insurance",
            "subcategory":"Life Insurance",
            "type":"Services"
        }
    ],
    "sg:phone":"+1 618 997 5551",
    "sg:postcode":"62959",
    "sg:province":"IL",
    "sg:tags":[
        "commercial",
        "group",
        "business"
    ],
    "sg:website":"http://www.woodmen.com",
    "wof:name":"Woodmen Of The World",
    "wof:placetype":"venue"
},
  "geometry": {"coordinates":[-88.933787,37.740872],"type":"Point"}
}