{
  "type": "Feature",
  "properties": {
    "iso:country":"US",
    "sg:address":"561 W Diversey Parkway",
    "sg:city":"Chicago",
    "sg:classifiers":[
        {
            "category":"Arts & Performance",
            "subcategory":"Art Gallery",
            "type":"Entertainment"
        }
    ],
    "sg:phone":"+1 773 281 2500",
    "sg:postcode":"60614",
    "sg:province":"IL",
    "sg:website":"www.plattfineart.com",
    "wof:name":"Platt Fine Art",
    "wof:placetype":"venue"
},
  "geometry": {"coordinates":[-87.64291799999999,41.93281],"type":"Point"}
}