{
  "type": "Feature",
  "properties": {
    "addr:full":"333 N Michigan Ave # 426 Chicago IL 60601",
    "addr:housenumber":"333",
    "addr:postcode":"60601",
    "addr:street":"N Michigan Ave # 426",
    "iso:country":"US",
    "sg:address":"333 N Michigan Ave # 426",
    "sg:city":"Chicago",
    "sg:classifiers":[
        {
            "category":"Shopping",
            "subcategory":"Beauty & Cosmetics",
            "type":"Retail Goods"
        }
    ],
    "sg:phone":"+1 312 422 0445",
    "sg:postcode":"60601",
    "sg:province":"IL",
    "sg:tags":[
        "perfume",
        "salons-equipment",
        "supply"
    ],
    "wof:name":"Renew Hair & Cosmetics Center",
    "wof:placetype":"venue"
},
  "geometry": {"coordinates":[-87.624456,41.887324],"type":"Point"}
}