{
  "type": "Feature",
  "properties": {
    "iso:country":"US",
    "sg:address":"1600 S Main St",
    "sg:city":"Eureka",
    "sg:classifiers":[
        {
            "category":"Restaurant",
            "type":"Food & Drink"
        }
    ],
    "sg:phone":"+1   ",
    "sg:postcode":"61530",
    "sg:province":"IL",
    "sg:tags":[
        "drinking",
        "eating"
    ],
    "wof:name":"Outpost The",
    "wof:placetype":"venue"
},
  "geometry": {"coordinates":[-89.272737,40.708735],"type":"Point"}
}