{
  "type": "Feature",
  "properties": {
    "addr:full":"9016 W 89th St Oak Lawn IL 60457",
    "addr:housenumber":"9016",
    "addr:postcode":"60457",
    "addr:street":"W 89Th St",
    "iso:country":"US",
    "sg:address":"9016 W 89th St",
    "sg:city":"Oak Lawn",
    "sg:classifiers":[
        {
            "category":"Shopping",
            "subcategory":"Crafts & Fabrics",
            "type":"Retail Goods"
        }
    ],
    "sg:phone":"+1   ",
    "sg:postcode":"60457",
    "sg:province":"IL",
    "sg:tags":[
        "sewing"
    ],
    "wof:name":"OH Sew Cute",
    "wof:placetype":"venue"
},
  "geometry": {"coordinates":[-87.84697199999999,41.728648],"type":"Point"}
}