{
  "type": "Feature",
  "properties": {
    "iso:country":"US",
    "sg:address":"1072 Ridge Ave",
    "sg:city":"Elk Grove Village",
    "sg:classifiers":[
        {
            "category":"Organizations",
            "subcategory":"Religious Organization",
            "type":"Services"
        }
    ],
    "sg:phone":"+1 847 439 2067",
    "sg:postcode":"60007",
    "sg:province":"IL",
    "sg:tags":[
        "child",
        "day",
        "care"
    ],
    "wof:name":"Saint Nicholas Epis Church",
    "wof:placetype":"venue"
},
  "geometry": {"coordinates":[-87.988386,42.000266],"type":"Point"}
}