{
  "type": "Feature",
  "properties": {
    "addr:full":"3401 Freedom Dr Springfield IL 62704",
    "addr:housenumber":"3401",
    "addr:postcode":"62704",
    "addr:street":"Freedom Dr",
    "iso:country":"US",
    "sg:address":"3401 Freedom Dr",
    "sg:city":"Springfield",
    "sg:classifiers":[
        {
            "category":"Health Services",
            "subcategory":"Optometrist",
            "type":"Services"
        }
    ],
    "sg:phone":"+1 217 793 2020",
    "sg:postcode":"62704",
    "sg:province":"IL",
    "wof:name":"Irvine, Wm J Jr Od",
    "wof:placetype":"venue"
},
  "geometry": {"coordinates":[-89.707802,39.753151],"type":"Point"}
}