{
  "type": "Feature",
  "properties": {
    "iso:country":"US",
    "sg:address":"1798 US Hwy 136",
    "sg:city":"Carthage",
    "sg:classifiers":[
        {
            "category":"Wholesale",
            "subcategory":"Farm Supplies",
            "type":"Manufacturing & Wholesale Goods"
        }
    ],
    "sg:phone":"+1 217 357 2192",
    "sg:postcode":"62321",
    "sg:province":"IL",
    "sg:tags":[
        "feed",
        "animal"
    ],
    "wof:name":"Nutrition Services Inc",
    "wof:placetype":"venue"
},
  "geometry": {"coordinates":[-91.199707,40.401465],"type":"Point"}
}