{
  "type": "Feature",
  "properties": {
    "addr:full":"2736 Lincolnwood Dr Evanston IL 60201",
    "addr:housenumber":"2736",
    "addr:postcode":"60201",
    "addr:street":"Lincolnwood Dr",
    "iso:country":"US",
    "sg:address":"2736 Lincolnwood Dr",
    "sg:city":"Evanston",
    "sg:classifiers":[
        {
            "category":"Professional",
            "subcategory":"Engineering",
            "type":"Services"
        }
    ],
    "sg:phone":"+1 847 869 4181",
    "sg:postcode":"60201",
    "sg:province":"IL",
    "wof:name":"Wall Engineering",
    "wof:placetype":"venue"
},
  "geometry": {"coordinates":[-87.715262,42.069027],"type":"Point"}
}