{
  "type": "Feature",
  "properties": {
    "iso:country":"US",
    "sg:address":"100 Westhaven Cir",
    "sg:city":"Geneva",
    "sg:classifiers":[
        {
            "category":"Professional",
            "subcategory":"Management & Consulting",
            "type":"Services"
        }
    ],
    "sg:phone":"+1 630 921 0420",
    "sg:postcode":"60134",
    "sg:province":"IL",
    "sg:tags":[
        "business"
    ],
    "wof:name":"Gigavelocity",
    "wof:placetype":"venue"
},
  "geometry": {"coordinates":[-88.355604,41.888353],"type":"Point"}
}