{
  "type": "Feature",
  "properties": {
    "addr:full":"1145 Formosa Rd Collinsville IL 62234",
    "addr:housenumber":"1145",
    "addr:postcode":"62234",
    "addr:street":"Formosa Rd",
    "iso:country":"US",
    "sg:address":"1145 Formosa Rd",
    "sg:city":"Collinsville",
    "sg:classifiers":[
        {
            "category":"Utilities",
            "subcategory":"Telephone",
            "type":"Services"
        }
    ],
    "sg:phone":"+1 618 667 4191",
    "sg:postcode":"62234",
    "sg:province":"IL",
    "sg:tags":[
        "communications",
        "animal"
    ],
    "wof:name":"Pawprint Inc",
    "wof:placetype":"venue"
},
  "geometry": {"coordinates":[-89.913966,38.699705],"type":"Point"}
}