{
  "type": "Feature",
  "properties": {
    "iso:country":"US",
    "sg:address":"711 NW 6th St",
    "sg:city":"Aledo",
    "sg:classifiers":[
        {
            "category":"Personal",
            "subcategory":"Beauty Salon",
            "type":"Services"
        }
    ],
    "sg:phone":"+1 309 582 5051",
    "sg:postcode":"61231",
    "sg:province":"IL",
    "wof:name":"Lyn's Hair Boutique",
    "wof:placetype":"venue"
},
  "geometry": {"coordinates":[-90.757242,41.206247],"type":"Point"}
}