{
  "type": "Feature",
  "properties": {
    "addr:full":"3512 Mc Arthur Blvd Alton IL 62002",
    "addr:housenumber":"3512",
    "addr:postcode":"62002",
    "addr:street":"Mc Arthur Blvd",
    "iso:country":"US",
    "sg:address":"3512 Mc Arthur Blvd",
    "sg:city":"Alton",
    "sg:classifiers":[
        {
            "category":"Social Services",
            "type":"Services"
        }
    ],
    "sg:phone":"+1 618 462 0634",
    "sg:postcode":"62002",
    "sg:province":"IL",
    "sg:tags":[
        "organization",
        "welfare"
    ],
    "sg:website":"www.cc.dio.org",
    "wof:name":"Catholic Charities",
    "wof:placetype":"venue"
},
  "geometry": {"coordinates":[-90.13460600000001,38.914977],"type":"Point"}
}