{
  "type": "Feature",
  "properties": {
    "iso:country":"US",
    "sg:address":"2250 N Lincoln Ave",
    "sg:city":"Chicago",
    "sg:classifiers":[
        {
            "category":"Shopping Center",
            "type":"Public Place"
        }
    ],
    "sg:phone":"+1 773 681 0764",
    "sg:postcode":"60614",
    "sg:province":"IL",
    "sg:tags":[
        "mall"
    ],
    "wof:name":"Chicago Electronic Cigarettes",
    "wof:placetype":"venue"
},
  "geometry": {"coordinates":[-87.646203,41.923619],"type":"Point"}
}