{
  "type": "Feature",
  "properties": {
    "addr:full":"7609 W Irving Park Road Chicago IL 60634",
    "addr:housenumber":"7609",
    "addr:postcode":"60634",
    "addr:street":"W Irving Park Road",
    "iso:country":"US",
    "sg:address":"7609 W Irving Park Road",
    "sg:city":"Chicago",
    "sg:classifiers":[
        {
            "category":"Retail",
            "subcategory":"Laundry & Dry Cleaning",
            "type":"Services"
        }
    ],
    "sg:phone":"+1 773 622 8127",
    "sg:postcode":"60634",
    "sg:province":"IL",
    "wof:name":"Neat Cleaning Services",
    "wof:placetype":"venue"
},
  "geometry": {"coordinates":[-87.81735999999999,41.952304],"type":"Point"}
}