{
  "type": "Feature",
  "properties": {
    "iso:country":"US",
    "sg:address":"3120 Vimy Ridge Dr",
    "sg:city":"Joliet",
    "sg:classifiers":[
        {
            "category":"Freight",
            "type":"Transportation"
        }
    ],
    "sg:phone":"+1 815 254 4449",
    "sg:postcode":"60435",
    "sg:province":"IL",
    "sg:tags":[
        "commercial",
        "storage"
    ],
    "wof:name":"Four Seasons Self Storage",
    "wof:placetype":"venue"
},
  "geometry": {"coordinates":[-88.15926,41.563374],"type":"Point"}
}