{
  "type": "Feature",
  "properties": {
    "iso:country":"US",
    "sg:address":"715 N Milwaukee Ave",
    "sg:city":"Libertyville",
    "sg:classifiers":[
        {
            "category":"Wholesale",
            "subcategory":"Construction Materials",
            "type":"Manufacturing & Wholesale Goods"
        },
        {
            "category":"Home & Garden",
            "subcategory":"Building Materials",
            "type":"Retail Goods"
        }
    ],
    "sg:phone":"+1 847 367 4744",
    "sg:postcode":"60048",
    "sg:province":"IL",
    "sg:tags":[
        "garage",
        "door"
    ],
    "wof:name":"Aero Garage Door Inc",
    "wof:placetype":"venue"
},
  "geometry": {"coordinates":[-87.954863,42.290101],"type":"Point"}
}