{
  "type": "Feature",
  "properties": {
    "addr:full":"307 W University Ave Champaign IL 61820",
    "addr:housenumber":"307",
    "addr:postcode":"61820",
    "addr:street":"W University Ave",
    "iso:country":"US",
    "sg:address":"307 W University Ave",
    "sg:city":"Champaign",
    "sg:classifiers":[
        {
            "category":"Real Estate",
            "subcategory":"Real Estate Operator",
            "type":"Services"
        }
    ],
    "sg:phone":"+1 217 359 1569",
    "sg:postcode":"61820",
    "sg:province":"IL",
    "sg:tags":[
        "apartment"
    ],
    "wof:name":"East View Apartments",
    "wof:placetype":"venue"
},
  "geometry": {"coordinates":[-88.248386,40.11622],"type":"Point"}
}