{
  "type": "Feature",
  "properties": {
    "addr:full":"8356 S Pulaski Rd Chicago IL 60652",
    "addr:housenumber":"8356",
    "addr:postcode":"60652",
    "addr:street":"S Pulaski Rd",
    "iso:country":"US",
    "sg:address":"8356 S Pulaski Rd",
    "sg:city":"Chicago",
    "sg:classifiers":[
        {
            "category":"Personal",
            "type":"Services"
        }
    ],
    "sg:phone":"+1 773 582 5650",
    "sg:postcode":"60652",
    "sg:province":"IL",
    "sg:tags":[
        "piercing"
    ],
    "wof:name":"Etched In Skin",
    "wof:placetype":"venue"
},
  "geometry": {"coordinates":[-87.72161199999999,41.740508],"type":"Point"}
}