{
  "type": "Feature",
  "properties": {
    "iso:country":"US",
    "sg:address":"14995 Waterman Rd",
    "sg:city":"Dekalb",
    "sg:classifiers":[
        {
            "category":"Real Estate",
            "subcategory":"Real Estate Services",
            "type":"Services"
        },
        {
            "category":"Banks & Credit Unions",
            "subcategory":"Financial Services",
            "type":"Services"
        }
    ],
    "sg:phone":"+1 815 756 3535",
    "sg:postcode":"60115",
    "sg:province":"IL",
    "sg:tags":[
        "loan",
        "mortgage"
    ],
    "wof:name":"Pat Herrmann Mortgage Inc",
    "wof:placetype":"venue"
},
  "geometry": {"coordinates":[-88.77332699999999,41.848241],"type":"Point"}
}