{
  "type": "Feature",
  "properties": {
    "addr:full":"1421 W Chicago Ave Chicago IL 60622",
    "addr:housenumber":"1421",
    "addr:postcode":"60622",
    "addr:street":"W Chicago Ave",
    "iso:country":"US",
    "sg:address":"1421 W Chicago Ave",
    "sg:city":"Chicago",
    "sg:classifiers":[
        {
            "category":"Restaurant",
            "type":"Food & Drink"
        }
    ],
    "sg:menulink":"http://www.allmenus.com/il/chicago/214413-demars-/menu/",
    "sg:phone":"+1 312 733 7165",
    "sg:postcode":"60622",
    "sg:province":"IL",
    "sg:tags":[
        "american",
        "diner"
    ],
    "wof:name":"Demars ",
    "wof:placetype":"venue"
},
  "geometry": {"coordinates":[-87.66327,41.896128],"type":"Point"}
}