{
  "type": "Feature",
  "properties": {
    "iso:country":"US",
    "sg:address":"6133 N River Rd Ste 200",
    "sg:city":"Rosemont",
    "sg:classifiers":[
        {
            "category":"Real Estate",
            "subcategory":"Real Estate Services",
            "type":"Services"
        },
        {
            "category":"Real Estate",
            "subcategory":"Real Estate Agent",
            "type":"Services"
        }
    ],
    "sg:phone":"+1 847 232 5400",
    "sg:postcode":"60018",
    "sg:province":"IL",
    "sg:tags":[
        "vacancy",
        "buyer",
        "rental",
        "broker",
        "listing"
    ],
    "sg:website":"http://www.dukerealty.com",
    "wof:name":"Duke Realty Corporation",
    "wof:placetype":"venue"
},
  "geometry": {"coordinates":[-87.86024500000001,41.988698],"type":"Point"}
}