{
  "type": "Feature",
  "properties": {
    "addr:full":"760 W Champaign Ave Rantoul IL 61866",
    "addr:housenumber":"760",
    "addr:postcode":"61866",
    "addr:street":"W Champaign Ave",
    "iso:country":"US",
    "sg:address":"760 W Champaign Ave",
    "sg:city":"Rantoul",
    "sg:classifiers":[
        {
            "category":"Restaurant",
            "type":"Food & Drink"
        }
    ],
    "sg:menulink":"http://www.allmenus.com/il/rantoul/159561-arbys/menu/",
    "sg:phone":"+1 217 892 5144",
    "sg:postcode":"61866",
    "sg:province":"IL",
    "sg:tags":[
        "burger",
        "american"
    ],
    "wof:name":"Arby's",
    "wof:placetype":"venue"
},
  "geometry": {"coordinates":[-88.189504,40.308447],"type":"Point"}
}