{
  "type": "Feature",
  "properties": {
    "iso:country":"US",
    "sg:address":"927 E Lilly Ct",
    "sg:city":"Palatine",
    "sg:classifiers":[
        {
            "category":"Shopping",
            "subcategory":"Bicycles & Sporting Goods",
            "type":"Retail Goods"
        }
    ],
    "sg:phone":"+1   ",
    "sg:postcode":"60074",
    "sg:province":"IL",
    "wof:name":"Real Goods Inc",
    "wof:placetype":"venue"
},
  "geometry": {"coordinates":[-88.021734,42.142361],"type":"Point"}
}