{
  "type": "Feature",
  "properties": {
    "iso:country":"US",
    "sg:address":"9401 N Hamlin Ave",
    "sg:city":"Niles",
    "sg:classifiers":[
        {
            "category":"Education",
            "subcategory":"School",
            "type":"Public Place"
        }
    ],
    "sg:phone":"+1 847 296 5341",
    "sg:postcode":"60714",
    "sg:province":"IL",
    "sg:tags":[
        "elementary"
    ],
    "sg:website":"http://www.emsd63.org",
    "wof:name":"Mark Twain Elementary School",
    "wof:placetype":"venue"
},
  "geometry": {"coordinates":[-87.850182,42.051479],"type":"Point"}
}