{
  "type": "Feature",
  "properties": {
    "addr:full":"944 W 15th Pl Chicago IL 60608",
    "addr:housenumber":"944",
    "addr:postcode":"60608",
    "addr:street":"W 15Th Pl",
    "iso:country":"US",
    "sg:address":"944 W 15th Pl",
    "sg:city":"Chicago",
    "sg:classifiers":[
        {
            "category":"Real Estate",
            "subcategory":"Real Estate Services",
            "type":"Services"
        }
    ],
    "sg:phone":"+1 312 829 0254",
    "sg:postcode":"60608",
    "sg:province":"IL",
    "sg:tags":[
        "management",
        "condominium"
    ],
    "wof:name":"Condo Association",
    "wof:placetype":"venue"
},
  "geometry": {"coordinates":[-87.665836,41.86055],"type":"Point"}
}