{
  "type": "Feature",
  "properties": {
    "iso:country":"US",
    "sg:address":"34438 S Division St",
    "sg:city":"Braidwood",
    "sg:classifiers":[
        {
            "category":"Retail",
            "subcategory":"Repair Shop",
            "type":"Services"
        }
    ],
    "sg:phone":"+1 815 458 3074",
    "sg:postcode":"60408",
    "sg:province":"IL",
    "sg:tags":[
        "refrigeration"
    ],
    "wof:name":"Chanceys Refrigeration Svcs",
    "wof:placetype":"venue"
},
  "geometry": {"coordinates":[-88.226491,41.253275],"type":"Point"}
}