{
  "type": "Feature",
  "properties": {
    "addr:full":"6232 N Pulaski Rd Ste 302 Chicago IL 60646",
    "addr:housenumber":"6232",
    "addr:postcode":"60646",
    "addr:street":"N Pulaski Rd Ste 302",
    "iso:country":"US",
    "sg:address":"6232 N Pulaski Rd Ste 302",
    "sg:city":"Chicago",
    "sg:classifiers":[
        {
            "category":"Professional",
            "subcategory":"Detective & Security Services",
            "type":"Services"
        }
    ],
    "sg:phone":"+1 773 382 9358",
    "sg:postcode":"60646",
    "sg:province":"IL",
    "sg:tags":[
        "information",
        "bureau"
    ],
    "wof:name":"Credit Resources Services Of America",
    "wof:placetype":"venue"
},
  "geometry": {"coordinates":[-87.728887,41.994215],"type":"Point"}
}