{
  "type": "Feature",
  "properties": {
    "addr:full":"1828 Broadway St Quincy IL 62301",
    "addr:housenumber":"1828",
    "addr:postcode":"62301",
    "addr:street":"Broadway St",
    "iso:country":"US",
    "sg:address":"1828 Broadway St",
    "sg:city":"Quincy",
    "sg:classifiers":[
        {
            "category":"Banks & Credit Unions",
            "subcategory":"Financial Services",
            "type":"Services"
        }
    ],
    "sg:phone":"+1 217 228 1200",
    "sg:postcode":"62301",
    "sg:province":"IL",
    "sg:tags":[
        "loan",
        "alternative",
        "payday"
    ],
    "sg:website":"http://www.cashstore.com/IL/Trademark/yp.com",
    "wof:name":"Cash Store",
    "wof:placetype":"venue"
},
  "geometry": {"coordinates":[-91.386719,39.935504],"type":"Point"}
}