{
  "type": "Feature",
  "properties": {
    "iso:country":"US",
    "sg:address":"244 Tenney St",
    "sg:city":"Kewanee",
    "sg:classifiers":[
        {
            "category":"Autos & Motor Vehicles",
            "subcategory":"Auto Supplies",
            "type":"Retail Goods"
        }
    ],
    "sg:phone":"+1 309 854 7043",
    "sg:postcode":"61443",
    "sg:province":"IL",
    "sg:tags":[
        "automobile",
        "parts"
    ],
    "wof:name":"Autozone",
    "wof:placetype":"venue"
},
  "geometry": {"coordinates":[-89.927177,41.231787],"type":"Point"}
}