{
  "type": "Feature",
  "properties": {
    "iso:country":"US",
    "sg:address":"1063 N Salem Dr",
    "sg:city":"Schaumburg",
    "sg:classifiers":[
        {
            "category":"Organizations",
            "subcategory":"Membership Organization",
            "type":"Services"
        }
    ],
    "sg:phone":"+1 847 882 6980",
    "sg:postcode":"60194",
    "sg:province":"IL",
    "sg:tags":[
        "meditation",
        "instruction"
    ],
    "wof:name":"Dahn Center",
    "wof:placetype":"venue"
},
  "geometry": {"coordinates":[-88.10187000000001,42.039326],"type":"Point"}
}