{
  "type": "Feature",
  "properties": {
    "addr:full":"2324 W Polk St Ste 2 Chicago IL 60612",
    "addr:housenumber":"2324",
    "addr:postcode":"60612",
    "addr:street":"W Polk St Ste 2",
    "iso:country":"US",
    "sg:address":"2324 W Polk St Ste 2",
    "sg:city":"Chicago",
    "sg:classifiers":[
        {
            "category":"Government",
            "subcategory":"Office",
            "type":"Public Place"
        }
    ],
    "sg:phone":"+1 773 814 8533",
    "sg:postcode":"60612",
    "sg:province":"IL",
    "sg:tags":[
        "government-united",
        "state"
    ],
    "wof:name":"2711 West Congress Parkw",
    "wof:placetype":"venue"
},
  "geometry": {"coordinates":[-87.684757,41.871343],"type":"Point"}
}