{
  "type": "Feature",
  "properties": {
    "iso:country":"US",
    "sg:address":"2536 N Narragansett Avenue",
    "sg:city":"Chicago",
    "sg:classifiers":[
        {
            "category":"Shopping",
            "subcategory":"Used Merchandise",
            "type":"Retail Goods"
        }
    ],
    "sg:phone":"+1 773 804 1847",
    "sg:postcode":"60639",
    "sg:province":"IL",
    "sg:tags":[
        "vintage",
        "consignment"
    ],
    "sg:website":"www.dressbarn.com",
    "wof:name":"Dress Barn",
    "wof:placetype":"venue"
},
  "geometry": {"coordinates":[-87.785471,41.927239],"type":"Point"}
}