{
  "type": "Feature",
  "properties": {
    "addr:full":"7402 Unionville Rd Brookport IL 62910",
    "addr:housenumber":"7402",
    "addr:postcode":"62910",
    "addr:street":"Unionville Rd",
    "iso:country":"US",
    "sg:address":"7402 Unionville Rd",
    "sg:city":"Brookport",
    "sg:classifiers":[
        {
            "category":"Home & Garden",
            "subcategory":"Garden Supply",
            "type":"Retail Goods"
        }
    ],
    "sg:phone":"+1 618 564 2080",
    "sg:postcode":"62910",
    "sg:province":"IL",
    "sg:tags":[
        "renting",
        "hardware",
        "lawn",
        "equipment"
    ],
    "sg:website":"http://www.stihldealer.net/default-dealer-002682.aspx",
    "wof:name":"Hoyer Outdoor Equipment, Inc.",
    "wof:placetype":"venue"
},
  "geometry": {"coordinates":[-88.593307,37.128154],"type":"Point"}
}