{
  "type": "Feature",
  "properties": {
    "iso:country":"US",
    "sg:address":"6355 N Broadway St",
    "sg:city":"Chicago",
    "sg:classifiers":[
        {
            "category":"Education",
            "subcategory":"School",
            "type":"Public Place"
        }
    ],
    "sg:phone":"+1 773 338 8590",
    "sg:postcode":"60660",
    "sg:province":"IL",
    "wof:name":"B & K Healthcare Consultant",
    "wof:placetype":"venue"
},
  "geometry": {"coordinates":[-87.660434,41.997191],"type":"Point"}
}