{
  "type": "Feature",
  "properties": {
    "iso:country":"US",
    "sg:address":"1 Elm Creek Ct",
    "sg:city":"Elmhurst",
    "sg:classifiers":[
        {
            "category":"Real Estate",
            "subcategory":"Real Estate Operator",
            "type":"Services"
        }
    ],
    "sg:phone":"+1 630 833 0077",
    "sg:postcode":"60126",
    "sg:province":"IL",
    "sg:tags":[
        "complex",
        "apt"
    ],
    "wof:name":"Elm Creek Apartments",
    "wof:placetype":"venue"
},
  "geometry": {"coordinates":[-87.945042,41.864532],"type":"Point"}
}