{
  "type": "Feature",
  "properties": {
    "addr:full":"404 N Hickory St Joliet IL 60435",
    "addr:housenumber":"404",
    "addr:postcode":"60435",
    "addr:street":"N Hickory St",
    "iso:country":"US",
    "sg:address":"404 N Hickory St",
    "sg:city":"Joliet",
    "sg:classifiers":[
        {
            "category":"Professional",
            "type":"Services"
        }
    ],
    "sg:phone":"+1 815 740 1521",
    "sg:postcode":"60435",
    "sg:province":"IL",
    "sg:tags":[
        "establishment"
    ],
    "wof:name":"Friars Franciscan",
    "wof:placetype":"venue"
},
  "geometry": {"coordinates":[-88.088576,41.532543],"type":"Point"}
}