{
  "type": "Feature",
  "properties": {
    "addr:full":"9847 S Avers Ave Evergreen Park IL 60805",
    "addr:housenumber":"9847",
    "addr:postcode":"60805",
    "addr:street":"S Avers Ave",
    "iso:country":"US",
    "sg:address":"9847 S Avers Ave",
    "sg:city":"Evergreen Park",
    "sg:classifiers":[
        {
            "category":"Building & Trades",
            "subcategory":"Electrical",
            "type":"Services"
        }
    ],
    "sg:phone":"+1 708 422 7275",
    "sg:postcode":"60805",
    "sg:province":"IL",
    "sg:tags":[
        "electrical",
        "contractor"
    ],
    "wof:name":"OSullivan Electric",
    "wof:placetype":"venue"
},
  "geometry": {"coordinates":[-87.717411,41.714084],"type":"Point"}
}