{
  "type": "Feature",
  "properties": {
    "addr:full":"3845 S State St Chicago IL 60609",
    "addr:housenumber":"3845",
    "addr:postcode":"60609",
    "addr:street":"S State St",
    "iso:country":"US",
    "sg:address":"3845 S State St",
    "sg:city":"Chicago",
    "sg:classifiers":[
        {
            "category":"Shopping",
            "type":"Retail Goods"
        }
    ],
    "sg:phone":"+1 630 334 2909",
    "sg:postcode":"60609",
    "sg:province":"IL",
    "sg:tags":[
        "merchandise"
    ],
    "wof:name":"Platinum Iridium Company Ltd",
    "wof:placetype":"venue"
},
  "geometry": {"coordinates":[-87.62642200000001,41.824694],"type":"Point"}
}