{
  "type": "Feature",
  "properties": {
    "iso:country":"US",
    "sg:address":"6850 159th St",
    "sg:city":"Tinley Park",
    "sg:classifiers":[
        {
            "category":"Education",
            "subcategory":"School",
            "type":"Public Place"
        }
    ],
    "sg:phone":"+1 708 532 3529",
    "sg:postcode":"60477",
    "sg:province":"IL",
    "sg:tags":[
        "parochial",
        "church"
    ],
    "wof:name":"Trinity Lutheran Church",
    "wof:placetype":"venue"
},
  "geometry": {"coordinates":[-87.78657200000001,41.602451],"type":"Point"}
}