{
  "type": "Feature",
  "properties": {
    "addr:full":"1303 N Pine Ave Arlington Hts IL 60004",
    "addr:housenumber":"1303",
    "addr:postcode":"60004",
    "addr:street":"N Pine Ave",
    "iso:country":"US",
    "sg:address":"1303 N Pine Ave",
    "sg:city":"Arlington Hts",
    "sg:classifiers":[
        {
            "category":"Professional",
            "subcategory":"Management & Consulting",
            "type":"Services"
        },
        {
            "category":"Travel",
            "subcategory":"Travel Agent",
            "type":"Entertainment"
        }
    ],
    "sg:phone":"+1 847 392 7865",
    "sg:postcode":"60004",
    "sg:province":"IL",
    "sg:tags":[
        "agency",
        "bureau"
    ],
    "wof:name":"Destination By Designing Inc",
    "wof:placetype":"venue"
},
  "geometry": {"coordinates":[-87.97911499999999,42.100314],"type":"Point"}
}