{
  "type": "Feature",
  "properties": {
    "iso:country":"US",
    "sg:address":"2601 5th Ave",
    "sg:city":"Moline",
    "sg:classifiers":[
        {
            "category":"Manufacturing",
            "subcategory":"Tools & Machinery",
            "type":"Manufacturing & Wholesale Goods"
        },
        {
            "category":"Home & Garden",
            "subcategory":"Household Appliances",
            "type":"Retail Goods"
        },
        {
            "category":"Wholesale",
            "subcategory":"Electrical",
            "type":"Manufacturing & Wholesale Goods"
        },
        {
            "category":"Shopping",
            "subcategory":"Computers & Home Electronics",
            "type":"Retail Goods"
        }
    ],
    "sg:phone":"+1 309 797 3361",
    "sg:postcode":"61265",
    "sg:province":"IL",
    "sg:tags":[
        "major",
        "electric",
        "supply",
        "consumer",
        "appliances-small",
        "equipment",
        "supplies-wholesale",
        "manufacturer"
    ],
    "sg:website":"http://www.springfieldelectric.com",
    "wof:name":"Springfield Electric Supply Company",
    "wof:placetype":"venue"
},
  "geometry": {"coordinates":[-90.500381,41.510269],"type":"Point"}
}