{
  "type": "Feature",
  "properties": {
    "addr:full":"340 Walnut St Murphysboro IL 62966",
    "addr:housenumber":"340",
    "addr:postcode":"62966",
    "addr:street":"Walnut St",
    "iso:country":"US",
    "sg:address":"340 Walnut St",
    "sg:city":"Murphysboro",
    "sg:classifiers":[
        {
            "category":"Restaurant",
            "type":"Food & Drink"
        }
    ],
    "sg:menulink":"http://www.allmenus.com/il/murphysboro/154602-hardees/menu/",
    "sg:phone":"+1 618 684 2712",
    "sg:postcode":"62966",
    "sg:province":"IL",
    "sg:tags":[
        "burger",
        "american"
    ],
    "wof:name":"Hardee's",
    "wof:placetype":"venue"
},
  "geometry": {"coordinates":[-89.327504,37.764366],"type":"Point"}
}