{
  "type": "Feature",
  "properties": {
    "addr:full":"8253 E Farm School Rd Rock City IL 61070",
    "addr:housenumber":"8253",
    "addr:postcode":"61070",
    "addr:street":"E Farm School Rd",
    "iso:country":"US",
    "sg:address":"8253 E Farm School Rd",
    "sg:city":"Rock City",
    "sg:classifiers":[
        {
            "category":"Building & Trades",
            "subcategory":"Construction",
            "type":"Services"
        }
    ],
    "sg:phone":"+1 815 449 9191",
    "sg:postcode":"61070",
    "sg:province":"IL",
    "sg:tags":[
        "concrete",
        "work"
    ],
    "wof:name":"Johns Concrete",
    "wof:placetype":"venue"
},
  "geometry": {"coordinates":[-89.45272,42.400302],"type":"Point"}
}