{
  "type": "Feature",
  "properties": {
    "addr:full":"3312 183rd St Hazel Crest IL 60429",
    "addr:housenumber":"3312",
    "addr:postcode":"60429",
    "addr:street":"183Rd St",
    "iso:country":"US",
    "sg:address":"3312 183rd St",
    "sg:city":"Hazel Crest",
    "sg:classifiers":[
        {
            "category":"Banks & Credit Unions",
            "subcategory":"Investment Brokerage",
            "type":"Services"
        }
    ],
    "sg:phone":"+1 708 957 7218",
    "sg:postcode":"60429",
    "sg:province":"IL",
    "sg:tags":[
        "advisory",
        "financial"
    ],
    "wof:name":"ETC Inc",
    "wof:placetype":"venue"
},
  "geometry": {"coordinates":[-87.69615,41.557235],"type":"Point"}
}