{
  "type": "Feature",
  "properties": {
    "addr:full":"3003 Wakefield Dr Carpentersville IL 60110",
    "addr:housenumber":"3003",
    "addr:postcode":"60110",
    "addr:street":"Wakefield Dr",
    "iso:country":"US",
    "sg:address":"3003 Wakefield Dr",
    "sg:city":"Carpentersville",
    "sg:classifiers":[
        {
            "category":"Social Services",
            "subcategory":"Child Care",
            "type":"Services"
        }
    ],
    "sg:phone":"+1 847 836 9835",
    "sg:postcode":"60110",
    "sg:province":"IL",
    "sg:tags":[
        "day"
    ],
    "wof:name":"Well Child Center",
    "wof:placetype":"venue"
},
  "geometry": {"coordinates":[-88.246949,42.105612],"type":"Point"}
}