{
  "type": "Feature",
  "properties": {
    "iso:country":"US",
    "sg:address":"640 Executive Dr",
    "sg:city":"Willowbrook",
    "sg:classifiers":[
        {
            "category":"Wholesale",
            "subcategory":"Non-durable Goods",
            "type":"Manufacturing & Wholesale Goods"
        }
    ],
    "sg:phone":"+1 630 908 7345",
    "sg:postcode":"60527",
    "sg:province":"IL",
    "sg:tags":[
        "dry",
        "goods-wholesale"
    ],
    "wof:name":"Nyco Supply Inc",
    "wof:placetype":"venue"
},
  "geometry": {"coordinates":[-87.937889,41.749897],"type":"Point"}
}