{
  "type": "Feature",
  "properties": {
    "iso:country":"US",
    "sg:address":"110 W Gallatin St",
    "sg:city":"Vandalia",
    "sg:classifiers":[
        {
            "category":"Food & Beverages",
            "subcategory":"Liquor & Beverages",
            "type":"Retail Goods"
        }
    ],
    "sg:phone":"+1 618 283 1309",
    "sg:postcode":"62471",
    "sg:province":"IL",
    "sg:tags":[
        "alcoholic"
    ],
    "wof:name":"Rubes Package Liquor",
    "wof:placetype":"venue"
},
  "geometry": {"coordinates":[-89.091783,38.960597],"type":"Point"}
}