{
  "type": "Feature",
  "properties": {
    "addr:full":"3415 Howard St Skokie IL 60076",
    "addr:housenumber":"3415",
    "addr:postcode":"60076",
    "addr:street":"Howard St",
    "iso:country":"US",
    "sg:address":"3415 Howard St",
    "sg:city":"Skokie",
    "sg:classifiers":[
        {
            "category":"Building & Trades",
            "subcategory":"Construction",
            "type":"Services"
        }
    ],
    "sg:phone":"+1 847 362 5111",
    "sg:postcode":"60076",
    "sg:province":"IL",
    "sg:tags":[
        "painting",
        "contractor"
    ],
    "wof:name":"Prime Coat Corp.",
    "wof:placetype":"venue"
},
  "geometry": {"coordinates":[-87.714491,42.019091],"type":"Point"}
}