{
  "type": "Feature",
  "properties": {
    "iso:country":"US",
    "sg:address":"732 N Dryden Ave",
    "sg:city":"Arlington Heights",
    "sg:classifiers":[
        {
            "category":"Manufacturing",
            "subcategory":"Tools & Machinery",
            "type":"Manufacturing & Wholesale Goods"
        }
    ],
    "sg:phone":"+1 847 394 0492",
    "sg:postcode":"60004",
    "sg:province":"IL",
    "sg:tags":[
        "mfg"
    ],
    "wof:name":"Cut Rite Die Co",
    "wof:placetype":"venue"
},
  "geometry": {"coordinates":[-87.970793,42.092899],"type":"Point"}
}