{
  "type": "Feature",
  "properties": {
    "iso:country":"US",
    "sg:address":"144 Wesley Ave",
    "sg:city":"Oak Park",
    "sg:classifiers":[
        {
            "category":"Professional",
            "subcategory":"Management & Consulting",
            "type":"Services"
        }
    ],
    "sg:phone":"+1 708 383 4096",
    "sg:postcode":"60302",
    "sg:province":"IL",
    "wof:name":"Lisa Haas Freelance Marketing",
    "wof:placetype":"venue"
},
  "geometry": {"coordinates":[-87.791066,41.885351],"type":"Point"}
}