{
  "type": "Feature",
  "properties": {
    "addr:full":"676 N Saint Clair St # 1777 Chicago IL 60611",
    "addr:housenumber":"676",
    "addr:postcode":"60611",
    "addr:street":"N Saint Clair St # 1777",
    "iso:country":"US",
    "sg:address":"676 N Saint Clair St # 1777",
    "sg:city":"Chicago",
    "sg:classifiers":[
        {
            "category":"Health Services",
            "subcategory":"Doctor",
            "type":"Services"
        }
    ],
    "sg:phone":"+1 312 787 7463",
    "sg:postcode":"60611",
    "sg:province":"IL",
    "sg:tags":[
        "physician",
        "surgeon",
        "surgeons",
        "surgery-general"
    ],
    "wof:name":"Gary T Gireesan Md",
    "wof:placetype":"venue"
},
  "geometry": {"coordinates":[-87.622736,41.894491],"type":"Point"}
}