{
  "type": "Feature",
  "properties": {
    "iso:country":"US",
    "sg:address":"18 Emerald Ter",
    "sg:city":"Swansea",
    "sg:classifiers":[
        {
            "category":"Health Services",
            "subcategory":"Doctor",
            "type":"Services"
        }
    ],
    "sg:phone":"+1 618 234 4010",
    "sg:postcode":"62226",
    "sg:province":"IL",
    "sg:tags":[
        "physician",
        "surgeon"
    ],
    "wof:name":"Wallace P Berkowitz LTD",
    "wof:placetype":"venue"
},
  "geometry": {"coordinates":[-89.985186,38.547607],"type":"Point"}
}