{
  "type": "Feature",
  "properties": {
    "addr:full":"3267 Court St Pekin IL 61554",
    "addr:housenumber":"3267",
    "addr:postcode":"61554",
    "addr:street":"Court St",
    "iso:country":"US",
    "sg:address":"3267 Court St",
    "sg:city":"Pekin",
    "sg:classifiers":[
        {
            "category":"Insurance",
            "subcategory":"Insurance Agent",
            "type":"Services"
        },
        {
            "category":"Insurance",
            "subcategory":"Hazard Insurance",
            "type":"Services"
        }
    ],
    "sg:phone":"+1 309 928 3501",
    "sg:postcode":"61554",
    "sg:province":"IL",
    "sg:tags":[
        "fire",
        "property",
        "casualty"
    ],
    "sg:website":"http://www.progressinsurance.com",
    "wof:name":"Progressive Insurance",
    "wof:placetype":"venue"
},
  "geometry": {"coordinates":[-89.603973,40.546638],"type":"Point"}
}