{
  "type": "Feature",
  "properties": {
    "addr:full":"1215 Gail Dr Buffalo Grove IL 60089",
    "addr:housenumber":"1215",
    "addr:postcode":"60089",
    "addr:street":"Gail Dr",
    "iso:country":"US",
    "sg:address":"1215 Gail Dr",
    "sg:city":"Buffalo Grove",
    "sg:classifiers":[
        {
            "category":"Building & Trades",
            "subcategory":"Construction",
            "type":"Services"
        }
    ],
    "sg:phone":"+1 847 955 0219",
    "sg:postcode":"60089",
    "sg:province":"IL",
    "sg:tags":[
        "residential"
    ],
    "wof:name":"Loa Construction",
    "wof:placetype":"venue"
},
  "geometry": {"coordinates":[-87.97247,42.172844],"type":"Point"}
}