{
  "type": "Feature",
  "properties": {
    "iso:country":"US",
    "sg:address":"2220 Weber Rd",
    "sg:city":"Crest Hill",
    "sg:classifiers":[
        {
            "category":"Health Services",
            "subcategory":"Doctor",
            "type":"Services"
        }
    ],
    "sg:phone":"+1 815 744 4498",
    "sg:postcode":"60435",
    "sg:province":"IL",
    "sg:tags":[
        "physician",
        "surgeon"
    ],
    "wof:name":"E A Devassy & Assoc",
    "wof:placetype":"venue"
},
  "geometry": {"coordinates":[-88.121342,41.561032],"type":"Point"}
}