{
  "type": "Feature",
  "properties": {
    "iso:country":"US",
    "sg:address":"17221 W Oak Ave",
    "sg:city":"Lockport",
    "sg:classifiers":[
        {
            "category":"Building & Trades",
            "subcategory":"Landscaping Services",
            "type":"Services"
        }
    ],
    "sg:phone":"+1 815 740 0949",
    "sg:postcode":"60441",
    "sg:province":"IL",
    "sg:tags":[
        "designer",
        "landscape"
    ],
    "wof:name":"A & J Landscaping & Design",
    "wof:placetype":"venue"
},
  "geometry": {"coordinates":[-88.035127,41.561272],"type":"Point"}
}