{
  "type": "Feature",
  "properties": {
    "addr:full":"503 E Algonquin Rd Algonquin IL 60102",
    "addr:housenumber":"503",
    "addr:postcode":"60102",
    "addr:street":"E Algonquin Rd",
    "iso:country":"US",
    "sg:address":"503 E Algonquin Rd",
    "sg:city":"Algonquin",
    "sg:classifiers":[
        {
            "category":"Shopping",
            "subcategory":"Florist",
            "type":"Retail Goods"
        }
    ],
    "sg:phone":"+1 866 488 7773",
    "sg:postcode":"60102",
    "sg:province":"IL",
    "sg:website":"www.accentfloralcompany.com",
    "wof:name":"Accent Floral Company Inc",
    "wof:placetype":"venue"
},
  "geometry": {"coordinates":[-88.285124,42.163821],"type":"Point"}
}