{
  "type": "Feature",
  "properties": {
    "iso:country":"US",
    "sg:address":"21 E Hawthorn Pkwy",
    "sg:city":"Vernon Hills",
    "sg:classifiers":[
        {
            "category":"Education",
            "subcategory":"School",
            "type":"Public Place"
        }
    ],
    "sg:phone":"+1 847 247 9071",
    "sg:postcode":"60061",
    "sg:province":"IL",
    "wof:name":"Board of Jewish Education",
    "wof:placetype":"venue"
},
  "geometry": {"coordinates":[-87.96301800000001,42.241624],"type":"Point"}
}