{
  "type": "Feature",
  "properties": {
    "iso:country":"US",
    "sg:address":"2980 S River Rd",
    "sg:city":"Des Plaines",
    "sg:classifiers":[
        {
            "category":"Banks & Credit Unions",
            "subcategory":"Bank",
            "type":"Services"
        }
    ],
    "sg:phone":"+1 847 795 9300",
    "sg:postcode":"60018",
    "sg:province":"IL",
    "sg:tags":[
        "broker",
        "mortgage"
    ],
    "wof:name":"Ivc Mortgage Group Inc",
    "wof:placetype":"venue"
},
  "geometry": {"coordinates":[-87.86431399999999,42.001751],"type":"Point"}
}