{
  "type": "Feature",
  "properties": {
    "iso:country":"US",
    "sg:address":"500 Washington St",
    "sg:city":"South Beloit",
    "sg:classifiers":[
        {
            "category":"Organizations",
            "subcategory":"Religious Organization",
            "type":"Services"
        }
    ],
    "sg:phone":"+1 815 389 8284",
    "sg:postcode":"61080",
    "sg:province":"WI",
    "sg:tags":[
        "church"
    ],
    "wof:name":"International Council",
    "wof:placetype":"venue"
},
  "geometry": {"coordinates":[-89.03420800000001,42.490182],"type":"Point"}
}