{
  "type": "Feature",
  "properties": {
    "addr:full":"308 N Redfield Ct Park Ridge IL 60068",
    "addr:housenumber":"308",
    "addr:postcode":"60068",
    "addr:street":"N Redfield Ct",
    "iso:country":"US",
    "sg:address":"308 N Redfield Ct",
    "sg:city":"Park Ridge",
    "sg:classifiers":[
        {
            "category":"Freight",
            "type":"Transportation"
        }
    ],
    "sg:phone":"+1 847 720 4290",
    "sg:postcode":"60068",
    "sg:province":"IL",
    "sg:tags":[
        "operator",
        "trucking"
    ],
    "wof:name":"Tad Kolcz",
    "wof:placetype":"venue"
},
  "geometry": {"coordinates":[-87.85412700000001,42.015881],"type":"Point"}
}