{
  "type": "Feature",
  "properties": {
    "iso:country":"US",
    "sg:address":"5502 Seven Hills Rd",
    "sg:city":"Odin",
    "sg:classifiers":[
        {
            "category":"Retail",
            "subcategory":"Laundry & Dry Cleaning",
            "type":"Services"
        }
    ],
    "sg:phone":"+1 618 775 8860",
    "sg:postcode":"62870",
    "sg:province":"IL",
    "sg:tags":[
        "drycleaning",
        "plant"
    ],
    "wof:name":"Garner Cleaning Services Inc",
    "wof:placetype":"venue"
},
  "geometry": {"coordinates":[-89.048084,38.675777],"type":"Point"}
}