{
  "type": "Feature",
  "properties": {
    "addr:full":"1237 S Prospect Ave Park Ridge IL 60068",
    "addr:housenumber":"1237",
    "addr:postcode":"60068",
    "addr:street":"S Prospect Ave",
    "iso:country":"US",
    "sg:address":"1237 S Prospect Ave",
    "sg:city":"Park Ridge",
    "sg:classifiers":[
        {
            "category":"Real Estate",
            "subcategory":"Real Estate Services",
            "type":"Services"
        }
    ],
    "sg:phone":"+1 847 292 3622",
    "sg:postcode":"60068",
    "sg:province":"IL",
    "sg:tags":[
        "home",
        "inspector"
    ],
    "wof:name":"Paul C Bias Home Inspections",
    "wof:placetype":"venue"
},
  "geometry": {"coordinates":[-87.832551,41.994983],"type":"Point"}
}