{
  "type": "Feature",
  "properties": {
    "iso:country":"US",
    "sg:address":"5146 W Belmont Ave",
    "sg:city":"Chicago",
    "sg:classifiers":[
        {
            "category":"Professional",
            "subcategory":"Business Services",
            "type":"Services"
        }
    ],
    "sg:phone":"+1 773 286 1217",
    "sg:postcode":"60641",
    "sg:province":"IL",
    "wof:name":"Zgoda",
    "wof:placetype":"venue"
},
  "geometry": {"coordinates":[-87.75571100000001,41.938789],"type":"Point"}
}