{
  "type": "Feature",
  "properties": {
    "iso:country":"US",
    "sg:address":"6858 Old Jacksonville Rd",
    "sg:city":"Springfield",
    "sg:classifiers":[
        {
            "category":"Place Of Worship",
            "subcategory":"Church",
            "type":"Public Place"
        },
        {
            "category":"Place Of Worship",
            "type":"Public Place"
        }
    ],
    "sg:phone":"+1 217 787 4147",
    "sg:postcode":"62711",
    "sg:province":"IL",
    "sg:tags":[
        "churches-methodist"
    ],
    "wof:name":"New Salem United Methodist Chu",
    "wof:placetype":"venue"
},
  "geometry": {"coordinates":[-89.763962,39.786558],"type":"Point"}
}