{
  "type": "Feature",
  "properties": {
    "addr:full":"1300 Internationale Pkwy Woodridge IL 60517",
    "addr:housenumber":"1300",
    "addr:postcode":"60517",
    "addr:street":"Internationale Pkwy",
    "iso:country":"US",
    "sg:address":"1300 Internationale Pkwy",
    "sg:city":"Woodridge",
    "sg:classifiers":[
        {
            "category":"Manufacturing",
            "subcategory":"Food",
            "type":"Manufacturing & Wholesale Goods"
        }
    ],
    "sg:phone":"+1 630 783 9696",
    "sg:postcode":"60517",
    "sg:province":"IL",
    "sg:tags":[
        "frozen",
        "pizza",
        "mfg"
    ],
    "sg:website":"http://www.homeruninn.com",
    "wof:name":"Home Run Inn Frozen Foods",
    "wof:placetype":"venue"
},
  "geometry": {"coordinates":[-88.013321,41.696579],"type":"Point"}
}