{
  "type": "Feature",
  "properties": {
    "addr:full":"3455 N Western Ave Chicago IL 60618",
    "addr:housenumber":"3455",
    "addr:postcode":"60618",
    "addr:street":"N Western Ave",
    "iso:country":"US",
    "sg:address":"3455 N Western Ave",
    "sg:city":"Chicago",
    "sg:classifiers":[
        {
            "category":"Retail",
            "subcategory":"Auto Repair",
            "type":"Services"
        }
    ],
    "sg:phone":"+1 773 665 1500",
    "sg:postcode":"60618",
    "sg:province":"IL",
    "wof:name":"American Lube Plus Inc",
    "wof:placetype":"venue"
},
  "geometry": {"coordinates":[-87.688301,41.944199],"type":"Point"}
}