{
  "type": "Feature",
  "properties": {
    "addr:full":"675 Lake St Oak Park IL 60301",
    "addr:housenumber":"675",
    "addr:postcode":"60301",
    "addr:street":"Lake St",
    "iso:country":"US",
    "sg:address":"675 Lake St",
    "sg:city":"Oak Park",
    "sg:classifiers":[
        {
            "category":"Manufacturing",
            "subcategory":"Metals",
            "type":"Manufacturing & Wholesale Goods"
        }
    ],
    "sg:phone":"+1 708 445 0445",
    "sg:postcode":"60301",
    "sg:province":"IL",
    "sg:tags":[
        "mfg",
        "metalwork",
        "structural"
    ],
    "wof:name":"Eastman Metals",
    "wof:placetype":"venue"
},
  "geometry": {"coordinates":[-87.79104700000001,41.888446],"type":"Point"}
}