{
  "type": "Feature",
  "properties": {
    "addr:full":"5355 W 79th St Burbank IL 60459",
    "addr:housenumber":"5355",
    "addr:postcode":"60459",
    "addr:street":"W 79Th St",
    "iso:country":"US",
    "sg:address":"5355 W 79th St",
    "sg:city":"Burbank",
    "sg:classifiers":[
        {
            "category":"Restaurant",
            "type":"Food & Drink"
        }
    ],
    "sg:menulink":"http://www.allmenus.com/il/stickney/212168-mcdonalds/menu/",
    "sg:postcode":"60459",
    "sg:province":"IL",
    "sg:tags":[
        "burger",
        "american"
    ],
    "wof:name":"McDonald's",
    "wof:placetype":"venue"
},
  "geometry": {"coordinates":[-87.75565400000001,41.748839],"type":"Point"}
}