{
  "type": "Feature",
  "properties": {
    "addr:full":"344 Harrison St Oak Park IL 60304",
    "addr:housenumber":"344",
    "addr:postcode":"60304",
    "addr:street":"Harrison St",
    "iso:country":"US",
    "sg:address":"344 Harrison St",
    "sg:city":"Oak Park",
    "sg:classifiers":[
        {
            "category":"Building & Trades",
            "subcategory":"Construction",
            "type":"Services"
        }
    ],
    "sg:phone":"+1 708 383 5000",
    "sg:postcode":"60304",
    "sg:province":"IL",
    "sg:tags":[
        "contractor"
    ],
    "wof:name":"Suburban Fence Inc",
    "wof:placetype":"venue"
},
  "geometry": {"coordinates":[-87.783699,41.8727],"type":"Point"}
}