{
  "type": "Feature",
  "properties": {
    "iso:country":"US",
    "sg:address":"2301 Plum Grove Rd",
    "sg:city":"Palatine",
    "sg:classifiers":[
        {
            "category":"Professional",
            "subcategory":"Business Services",
            "type":"Services"
        }
    ],
    "sg:phone":"+1 847 303 6606",
    "sg:postcode":"60067",
    "sg:province":"IL",
    "wof:name":"M & M Design Consultants Ltd",
    "wof:placetype":"venue"
},
  "geometry": {"coordinates":[-88.04393,42.085048],"type":"Point"}
}