{
  "type": "Feature",
  "properties": {
    "addr:full":"825 E Dundee Rd Palatine IL 60074",
    "addr:housenumber":"825",
    "addr:postcode":"60074",
    "addr:street":"E Dundee Rd",
    "iso:country":"US",
    "sg:address":"825 E Dundee Rd",
    "sg:city":"Palatine",
    "sg:classifiers":[
        {
            "category":"Home & Garden",
            "subcategory":"Building Materials",
            "type":"Retail Goods"
        }
    ],
    "sg:phone":"+1   ",
    "sg:postcode":"60074",
    "sg:province":"IL",
    "wof:name":"Home Depot",
    "wof:placetype":"venue"
},
  "geometry": {"coordinates":[-88.024888,42.139083],"type":"Point"}
}