{
  "type": "Feature",
  "properties": {
    "addr:full":"9172 South Rd Palos Hills IL 60465",
    "addr:housenumber":"9172",
    "addr:postcode":"60465",
    "addr:street":"South Rd",
    "iso:country":"US",
    "sg:address":"9172 South Rd",
    "sg:city":"Palos Hills",
    "sg:classifiers":[
        {
            "category":"Recreation",
            "type":"Entertainment"
        }
    ],
    "sg:phone":"+1 708 974 9660",
    "sg:postcode":"60465",
    "sg:province":"IL",
    "sg:tags":[
        "charter",
        "boat"
    ],
    "wof:name":"Captain Joe's Charter Boat",
    "wof:placetype":"venue"
},
  "geometry": {"coordinates":[-87.845386,41.686927],"type":"Point"}
}