{
  "type": "Feature",
  "properties": {
    "iso:country":"US",
    "sg:address":"3330 181st Pl Ste 103",
    "sg:city":"Lansing",
    "sg:classifiers":[
        {
            "category":"Professional",
            "subcategory":"Lawyer & Legal Services",
            "type":"Services"
        }
    ],
    "sg:phone":"+1 708 418 3339",
    "sg:postcode":"60438",
    "sg:province":"IL",
    "wof:name":"Law Offices of Julie A Garmon",
    "wof:placetype":"venue"
},
  "geometry": {"coordinates":[-87.536524,41.566002],"type":"Point"}
}