{
  "type": "Feature",
  "properties": {
    "iso:country":"US",
    "sg:address":"28 Rolling Hills Dr",
    "sg:city":"Barrington",
    "sg:classifiers":[
        {
            "category":"Professional",
            "subcategory":"Lawyer & Legal Services",
            "type":"Services"
        }
    ],
    "sg:phone":"+1 847 551 3135",
    "sg:postcode":"60010",
    "sg:province":"IL",
    "wof:name":"Steven A Miner Esq",
    "wof:placetype":"venue"
},
  "geometry": {"coordinates":[-88.229049,42.119058],"type":"Point"}
}