{
  "type": "Feature",
  "properties": {
    "addr:full":"93 Berkshire Dr Crystal Lake IL 60014",
    "addr:housenumber":"93",
    "addr:postcode":"60014",
    "addr:street":"Berkshire Dr",
    "iso:country":"US",
    "sg:address":"93 Berkshire Dr",
    "sg:city":"Crystal Lake",
    "sg:classifiers":[
        {
            "category":"Real Estate",
            "subcategory":"Developer",
            "type":"Services"
        },
        {
            "category":"Building & Trades",
            "subcategory":"Construction",
            "type":"Services"
        }
    ],
    "sg:phone":"+1 815 788 1000",
    "sg:postcode":"60014",
    "sg:province":"IL",
    "sg:tags":[
        "general",
        "contractor"
    ],
    "wof:name":"Marmac Development Corp",
    "wof:placetype":"venue"
},
  "geometry": {"coordinates":[-88.323446,42.219845],"type":"Point"}
}