{
  "type": "Feature",
  "properties": {
    "iso:country":"US",
    "sg:address":"2340 W Fullerton Ave",
    "sg:city":"Chicago",
    "sg:classifiers":[
        {
            "category":"Building & Trades",
            "subcategory":"Construction",
            "type":"Services"
        }
    ],
    "sg:phone":"+1 773 276 4259",
    "sg:postcode":"60647",
    "sg:province":"IL",
    "sg:tags":[
        "remodeling",
        "contractor"
    ],
    "wof:name":"A R Remodeling Inc",
    "wof:placetype":"venue"
},
  "geometry": {"coordinates":[-87.68651699999999,41.924989],"type":"Point"}
}