{
  "type": "Feature",
  "properties": {
    "iso:country":"US",
    "sg:address":"6114 E Riverside Blvd",
    "sg:city":"Loves Park",
    "sg:classifiers":[
        {
            "category":"Shopping",
            "subcategory":"Beauty & Cosmetics",
            "type":"Retail Goods"
        }
    ],
    "sg:phone":"+1   ",
    "sg:postcode":"61111",
    "sg:province":"IL",
    "sg:tags":[
        "merchandise"
    ],
    "wof:name":"Merle Norman Cosmetics",
    "wof:placetype":"venue"
},
  "geometry": {"coordinates":[-88.999489,42.318615],"type":"Point"}
}