{
  "type": "Feature",
  "properties": {
    "iso:country":"US",
    "sg:address":"2732 W Devon Avenue",
    "sg:city":"Chicago",
    "sg:classifiers":[
        {
            "category":"Food & Beverages",
            "subcategory":"Meat & Fish",
            "type":"Retail Goods"
        }
    ],
    "sg:phone":"+1 773 262 0178",
    "sg:postcode":"60659",
    "sg:province":"IL",
    "sg:tags":[
        "shop"
    ],
    "wof:name":"J A Meat Market & Grocery",
    "wof:placetype":"venue"
},
  "geometry": {"coordinates":[-87.698494,41.9976],"type":"Point"}
}