{
  "type": "Feature",
  "properties": {
    "addr:full":"21W415 North Ave Lombard IL 60148",
    "addr:housenumber":"21w415",
    "addr:postcode":"60148",
    "addr:street":"North Ave",
    "iso:country":"US",
    "sg:address":"21W415 North Ave",
    "sg:city":"Lombard",
    "sg:phone":"+1 630 812 0702",
    "sg:postcode":"60148",
    "sg:province":"IL",
    "sg:website":"http://www.a1safetychimney.com",
    "wof:name":"A-1 Safety Chimney Service, Inc.",
    "wof:placetype":"venue"
},
  "geometry": {"coordinates":[-88.040215,41.90399],"type":"Point"}
}