{
  "type": "Feature",
  "properties": {
    "iso:country":"US",
    "sg:address":"1107 Cambridge Ln",
    "sg:city":"Shorewood",
    "sg:classifiers":[
        {
            "category":"Professional",
            "subcategory":"Business Services",
            "type":"Services"
        }
    ],
    "sg:phone":"+1 815 744 4906",
    "sg:postcode":"60404",
    "sg:province":"IL",
    "sg:tags":[
        "consultant",
        "coach"
    ],
    "wof:name":"Anthony Costa Consultant",
    "wof:placetype":"venue"
},
  "geometry": {"coordinates":[-88.214837,41.508367],"type":"Point"}
}