{
  "type": "Feature",
  "properties": {
    "addr:full":"316 W Main St Genoa IL 60135",
    "addr:housenumber":"316",
    "addr:postcode":"60135",
    "addr:street":"W Main St",
    "iso:country":"US",
    "sg:address":"316 W Main St",
    "sg:city":"Genoa",
    "sg:classifiers":[
        {
            "category":"Shopping",
            "subcategory":"Gifts & Souvenirs",
            "type":"Retail Goods"
        }
    ],
    "sg:phone":"+1 815 784 3004",
    "sg:postcode":"60135",
    "sg:province":"IL",
    "sg:tags":[
        "shop"
    ],
    "wof:name":"Crow's Nest",
    "wof:placetype":"venue"
},
  "geometry": {"coordinates":[-88.695483,42.097565],"type":"Point"}
}