{
  "type": "Feature",
  "properties": {
    "addr:full":"1358 Shermer Rd Northbrook IL 60062",
    "addr:housenumber":"1358",
    "addr:postcode":"60062",
    "addr:street":"Shermer Rd",
    "iso:country":"US",
    "sg:address":"1358 Shermer Rd",
    "sg:city":"Northbrook",
    "sg:classifiers":[
        {
            "category":"Restaurant",
            "type":"Food & Drink"
        }
    ],
    "sg:phone":"+1   ",
    "sg:postcode":"60062",
    "sg:province":"IL",
    "sg:tags":[
        "eating"
    ],
    "wof:name":"Trattoria Pizzeria Oliverii",
    "wof:placetype":"venue"
},
  "geometry": {"coordinates":[-87.82797600000001,42.128104],"type":"Point"}
}