{
  "type": "Feature",
  "properties": {
    "addr:full":"2508 N Greenview Ave Chicago IL 60614",
    "addr:housenumber":"2508",
    "addr:postcode":"60614",
    "addr:street":"N Greenview Ave",
    "iso:country":"US",
    "sg:address":"2508 N Greenview Ave",
    "sg:city":"Chicago",
    "sg:classifiers":[
        {
            "category":"Real Estate",
            "subcategory":"Real Estate Services",
            "type":"Services"
        }
    ],
    "sg:phone":"+1 773 549 6422",
    "sg:postcode":"60614",
    "sg:province":"IL",
    "sg:tags":[
        "management",
        "property"
    ],
    "wof:name":"Depaul Properties",
    "wof:placetype":"venue"
},
  "geometry": {"coordinates":[-87.665604,41.927101],"type":"Point"}
}