{
  "type": "Feature",
  "properties": {
    "iso:country":"US",
    "sg:address":"6443 Abernathy Way",
    "sg:city":"Roscoe",
    "sg:classifiers":[
        {
            "category":"Building & Trades",
            "subcategory":"Construction",
            "type":"Services"
        }
    ],
    "sg:phone":"+1 815 623 2007",
    "sg:postcode":"61073",
    "sg:province":"IL",
    "sg:tags":[
        "repairing",
        "remodeling",
        "contractor"
    ],
    "wof:name":"Remodeling By Jon Inc",
    "wof:placetype":"venue"
},
  "geometry": {"coordinates":[-88.989374,42.430084],"type":"Point"}
}