{
  "type": "Feature",
  "properties": {
    "iso:country":"US",
    "sg:address":"1198 Prairie St",
    "sg:city":"Aurora",
    "sg:classifiers":[
        {
            "category":"Retail",
            "subcategory":"Repair Shop",
            "type":"Services"
        }
    ],
    "sg:phone":"+1   ",
    "sg:postcode":"60506",
    "sg:province":"IL",
    "sg:website":"www.westwaves.net",
    "wof:name":"J D Satellite TV",
    "wof:placetype":"venue"
},
  "geometry": {"coordinates":[-88.345254,41.752262],"type":"Point"}
}