{
  "type": "Feature",
  "properties": {
    "addr:full":"1227 Harlem Ave Berwyn IL 60402",
    "addr:housenumber":"1227",
    "addr:postcode":"60402",
    "addr:street":"Harlem Ave",
    "iso:country":"US",
    "sg:address":"1227 Harlem Ave",
    "sg:city":"Berwyn",
    "sg:classifiers":[
        {
            "category":"Real Estate",
            "subcategory":"Real Estate Operator",
            "type":"Services"
        }
    ],
    "sg:phone":"+1 708 484 6170",
    "sg:postcode":"60402",
    "sg:province":"IL",
    "sg:tags":[
        "apartment"
    ],
    "wof:name":"Twelve Twenty Seven Avenue Manor",
    "wof:placetype":"venue"
},
  "geometry": {"coordinates":[-87.804182,41.864351],"type":"Point"}
}