{
  "type": "Feature",
  "properties": {
    "iso:country":"US",
    "sg:address":"1201 S Lake Shore Dr",
    "sg:city":"Chicago",
    "sg:classifiers":[
        {
            "category":"Fast Food",
            "type":"Food & Drink"
        }
    ],
    "sg:phone":"+1 312 588 1229",
    "sg:postcode":"60605",
    "sg:province":"IL",
    "sg:tags":[
        "burger"
    ],
    "sg:website":"www.mcdonalds.com",
    "wof:name":"McDonald's",
    "wof:placetype":"venue"
},
  "geometry": {"coordinates":[-87.618906,41.867569],"type":"Point"}
}