{
  "type": "Feature",
  "properties": {
    "iso:country":"US",
    "sg:address":"1056 Sterling Rd",
    "sg:city":"Dixon",
    "sg:phone":"+1 815 857 2508",
    "sg:postcode":"61021",
    "sg:province":"IL",
    "sg:tags":[
        "hog",
        "farm",
        "corn",
        "soybean",
        "or",
        "feedlot"
    ],
    "wof:name":"Leo McCaffrey",
    "wof:placetype":"venue"
},
  "geometry": {"coordinates":[-89.423074,41.722064],"type":"Point"}
}