{
  "type": "Feature",
  "properties": {
    "iso:country":"US",
    "sg:address":"2515 Central Park Ave",
    "sg:city":"Evanston",
    "sg:classifiers":[
        {
            "category":"Organizations",
            "subcategory":"Religious Organization",
            "type":"Services"
        }
    ],
    "sg:phone":"+1 847 869 9210",
    "sg:postcode":"60201",
    "sg:province":"IL",
    "sg:tags":[
        "church"
    ],
    "wof:name":"Northminster Nursery School",
    "wof:placetype":"venue"
},
  "geometry": {"coordinates":[-87.717713,42.063731],"type":"Point"}
}