{
  "type": "Feature",
  "properties": {
    "addr:full":"152 E Main St Shelbyville IL 62565",
    "addr:housenumber":"152",
    "addr:postcode":"62565",
    "addr:street":"E Main St",
    "iso:country":"US",
    "sg:address":"152 E Main St",
    "sg:city":"Shelbyville",
    "sg:classifiers":[
        {
            "category":"Shopping",
            "subcategory":"Clothing, Apparel, & Fashions",
            "type":"Retail Goods"
        },
        {
            "category":"Shopping",
            "subcategory":"Crafts & Fabrics",
            "type":"Retail Goods"
        },
        {
            "category":"Professional",
            "subcategory":"Printing & Photocopies",
            "type":"Services"
        }
    ],
    "sg:phone":"+1 217 774 2227",
    "sg:postcode":"62565",
    "sg:province":"IL",
    "sg:tags":[
        "shop",
        "made",
        "screen",
        "shirts-custom",
        "clothing",
        "store"
    ],
    "wof:name":"Just A Stitch",
    "wof:placetype":"venue"
},
  "geometry": {"coordinates":[-88.792869,39.406689],"type":"Point"}
}