{
  "type": "Feature",
  "properties": {
    "iso:country":"US",
    "sg:address":"4908 W Hutchinson St",
    "sg:city":"Chicago",
    "sg:classifiers":[
        {
            "category":"Building & Trades",
            "subcategory":"Construction",
            "type":"Services"
        }
    ],
    "sg:phone":"+1 773 283 9002",
    "sg:postcode":"60641",
    "sg:province":"IL",
    "sg:tags":[
        "carpenter"
    ],
    "wof:name":"Vulkan Roofing & Carpentry Inc",
    "wof:placetype":"venue"
},
  "geometry": {"coordinates":[-87.75035099999999,41.95797],"type":"Point"}
}