{
  "type": "Feature",
  "properties": {
    "addr:full":"105 Watters Dr Dwight IL 60420",
    "addr:housenumber":"105",
    "addr:postcode":"60420",
    "addr:street":"Watters Dr",
    "iso:country":"US",
    "sg:address":"105 Watters Dr",
    "sg:city":"Dwight",
    "sg:classifiers":[
        {
            "category":"Retail",
            "subcategory":"Auto Repair",
            "type":"Services"
        }
    ],
    "sg:phone":"+1 815 584 2588",
    "sg:postcode":"60420",
    "sg:province":"IL",
    "sg:tags":[
        "body",
        "automobile",
        "painting"
    ],
    "wof:name":"Tech-In-Kolor Autocrafters",
    "wof:placetype":"venue"
},
  "geometry": {"coordinates":[-88.44287799999999,41.089969],"type":"Point"}
}