{
  "type": "Feature",
  "properties": {
    "iso:country":"US",
    "sg:address":"15635 Perrysville Rd",
    "sg:city":"Danville",
    "sg:classifiers":[
        {
            "category":"Shopping",
            "type":"Retail Goods"
        }
    ],
    "sg:phone":"+1   ",
    "sg:postcode":"61834",
    "sg:province":"IL",
    "sg:tags":[
        "station",
        "gasoline",
        "merchandise"
    ],
    "wof:name":"Calhoun Auctions",
    "wof:placetype":"venue"
},
  "geometry": {"coordinates":[-87.559924,40.102235],"type":"Point"}
}