{
  "type": "Feature",
  "properties": {
    "iso:country":"US",
    "sg:address":"12742 S Spencer St",
    "sg:city":"Alsip",
    "sg:classifiers":[
        {
            "category":"Wholesale",
            "subcategory":"Painting Supplies",
            "type":"Manufacturing & Wholesale Goods"
        },
        {
            "category":"Manufacturing",
            "subcategory":"Buildings",
            "type":"Manufacturing & Wholesale Goods"
        },
        {
            "category":"Building & Trades",
            "subcategory":"Construction",
            "type":"Services"
        }
    ],
    "sg:phone":"+1 708 389 8358",
    "sg:postcode":"60803",
    "sg:province":"IL",
    "sg:tags":[
        "home",
        "paint",
        "builder",
        "contractor"
    ],
    "wof:name":"Adc Painting Interior/Exterior",
    "wof:placetype":"venue"
},
  "geometry": {"coordinates":[-87.737047,41.660691],"type":"Point"}
}