{
  "type": "Feature",
  "properties": {
    "addr:full":"1960 Essington Rd Joliet IL 60435",
    "addr:housenumber":"1960",
    "addr:postcode":"60435",
    "addr:street":"Essington Rd",
    "iso:country":"US",
    "sg:address":"1960 Essington Rd",
    "sg:city":"Joliet",
    "sg:classifiers":[
        {
            "category":"Shopping",
            "subcategory":"Optical Goods",
            "type":"Retail Goods"
        }
    ],
    "sg:phone":"+1 815 436 8605",
    "sg:postcode":"60435",
    "sg:province":"IL",
    "wof:name":"EVERYTHING In Sight",
    "wof:placetype":"venue"
},
  "geometry": {"coordinates":[-88.161286,41.557401],"type":"Point"}
}