{
  "type": "Feature",
  "properties": {
    "iso:country":"US",
    "sg:address":"4285 N Brown Rd",
    "sg:city":"Rock City",
    "sg:classifiers":[
        {
            "category":"Farming",
            "subcategory":"Dairy Farm",
            "type":"Manufacturing & Wholesale Goods"
        }
    ],
    "sg:phone":"+1 815 449 2502",
    "sg:postcode":"61070",
    "sg:province":"IL",
    "wof:name":"Steven De Haven",
    "wof:placetype":"venue"
},
  "geometry": {"coordinates":[-89.495678,42.360407],"type":"Point"}
}