{
  "type": "Feature",
  "properties": {
    "addr:full":"1030 N Austin Blvd Oak Park IL 60302",
    "addr:housenumber":"1030",
    "addr:postcode":"60302",
    "addr:street":"N Austin Blvd",
    "iso:country":"US",
    "sg:address":"1030 N Austin Blvd",
    "sg:city":"Oak Park",
    "sg:classifiers":[
        {
            "category":"Professional",
            "subcategory":"Management & Consulting",
            "type":"Services"
        }
    ],
    "sg:phone":"+1 708 386 6412",
    "sg:postcode":"60302",
    "sg:province":"IL",
    "sg:tags":[
        "small",
        "business"
    ],
    "wof:name":"Taylor Sydney Consultants",
    "wof:placetype":"venue"
},
  "geometry": {"coordinates":[-87.775375,41.900092],"type":"Point"}
}