{
  "type": "Feature",
  "properties": {
    "iso:country":"US",
    "sg:address":"8814 Ridgewood Rd",
    "sg:city":"Rock Island",
    "sg:classifiers":[
        {
            "category":"Wholesale",
            "subcategory":"Hardware",
            "type":"Manufacturing & Wholesale Goods"
        }
    ],
    "sg:phone":"+1 309 787 1945",
    "sg:postcode":"61201",
    "sg:province":"IL",
    "sg:tags":[
        "plumbing"
    ],
    "wof:name":"Art Express",
    "wof:placetype":"venue"
},
  "geometry": {"coordinates":[-90.594454,41.430559],"type":"Point"}
}