{
  "type": "Feature",
  "properties": {
    "iso:country":"US",
    "sg:address":"27035 Robin Rd",
    "sg:city":"Tower Lakes",
    "sg:classifiers":[
        {
            "category":"Professional",
            "type":"Services"
        }
    ],
    "sg:phone":"+1 847 526 0731",
    "sg:postcode":"60010",
    "sg:province":"IL",
    "sg:tags":[
        "establishment"
    ],
    "wof:name":"Dehnert & Dehnert",
    "wof:placetype":"venue"
},
  "geometry": {"coordinates":[-88.158894,42.230781],"type":"Point"}
}