{
  "type": "Feature",
  "properties": {
    "addr:full":"1612 Cranston Rd Beloit IL 53511",
    "addr:housenumber":"1612",
    "addr:postcode":"53511",
    "addr:street":"Cranston Rd",
    "iso:country":"US",
    "sg:address":"1612 Cranston Rd",
    "sg:city":"Beloit",
    "sg:classifiers":[
        {
            "category":"Insurance",
            "subcategory":"Insurance Agent",
            "type":"Services"
        }
    ],
    "sg:phone":"+1 608 362 4510",
    "sg:postcode":"53511",
    "sg:province":"IL",
    "wof:name":"Ronald Moe",
    "wof:placetype":"venue"
},
  "geometry": {"coordinates":[-89.01719900000001,42.53216],"type":"Point"}
}