{
  "type": "Feature",
  "properties": {
    "iso:country":"US",
    "sg:address":"1600 N 24th St",
    "sg:city":"Quincy",
    "sg:classifiers":[
        {
            "category":"Food & Beverages",
            "subcategory":"Groceries & Convenience Stores",
            "type":"Retail Goods"
        }
    ],
    "sg:phone":"+1   ",
    "sg:postcode":"62301",
    "sg:province":"IL",
    "wof:name":"Fastop Convenience Store",
    "wof:placetype":"venue"
},
  "geometry": {"coordinates":[-91.377518,39.951187],"type":"Point"}
}