{
  "type": "Feature",
  "properties": {
    "addr:full":"1600 N 24th St Quincy IL 62301",
    "addr:housenumber":"1600",
    "addr:postcode":"62301",
    "addr:street":"N 24Th St",
    "iso:country":"US",
    "sg:address":"1600 N 24th St",
    "sg:city":"Quincy",
    "sg:classifiers":[
        {
            "category":"Food & Beverages",
            "subcategory":"Groceries & Convenience Stores",
            "type":"Retail Goods"
        }
    ],
    "sg:phone":"+1   ",
    "sg:postcode":"62301",
    "sg:province":"IL",
    "wof:name":"Fastop Convenience Store",
    "wof:placetype":"venue"
},
  "geometry": {"coordinates":[-91.37751799999999,39.951187],"type":"Point"}
}