{
  "type": "Feature",
  "properties": {
    "addr:full":"2435 E Devon Ave Elk Grove Village IL 60007",
    "addr:housenumber":"2435",
    "addr:postcode":"60007",
    "addr:street":"E Devon Ave",
    "iso:country":"US",
    "sg:address":"2435 E Devon Ave",
    "sg:city":"Elk Grove Village",
    "sg:classifiers":[
        {
            "category":"Wholesale",
            "subcategory":"Groceries",
            "type":"Manufacturing & Wholesale Goods"
        }
    ],
    "sg:phone":"+1 847 238 2000",
    "sg:postcode":"60007",
    "sg:province":"IL",
    "wof:name":"United Trading Inc",
    "wof:placetype":"venue"
},
  "geometry": {"coordinates":[-87.94288899999999,41.99353],"type":"Point"}
}