{
  "type": "Feature",
  "properties": {
    "iso:country":"US",
    "sg:address":"2435 E Devon Ave",
    "sg:city":"Elk Grove Village",
    "sg:classifiers":[
        {
            "category":"Wholesale",
            "subcategory":"Groceries",
            "type":"Manufacturing & Wholesale Goods"
        }
    ],
    "sg:phone":"+1 847 238 2000",
    "sg:postcode":"60007",
    "sg:province":"IL",
    "wof:name":"United Trading Inc",
    "wof:placetype":"venue"
},
  "geometry": {"coordinates":[-87.942889,41.99353],"type":"Point"}
}