{
  "type": "Feature",
  "properties": {
    "addr:full":"1100 S Lincoln Ave Park Ridge IL 60068",
    "addr:housenumber":"1100",
    "addr:postcode":"60068",
    "addr:street":"S Lincoln Ave",
    "iso:country":"US",
    "sg:address":"1100 S Lincoln Ave",
    "sg:city":"Park Ridge",
    "sg:classifiers":[
        {
            "category":"Professional",
            "subcategory":"Research",
            "type":"Services"
        }
    ],
    "sg:phone":"+1 847 698 1127",
    "sg:postcode":"60068",
    "sg:province":"IL",
    "sg:tags":[
        "nonphysical",
        "commercial"
    ],
    "wof:name":"Market Research Services",
    "wof:placetype":"venue"
},
  "geometry": {"coordinates":[-87.84332999999999,41.997156],"type":"Point"}
}