{
  "type": "Feature",
  "properties": {
    "iso:country":"US",
    "sg:address":"13145 Illinois Dr",
    "sg:city":"Huntley",
    "sg:classifiers":[
        {
            "category":"Building & Trades",
            "subcategory":"Landscaping Services",
            "type":"Services"
        }
    ],
    "sg:phone":"+1 847 515 1610",
    "sg:postcode":"60142",
    "sg:province":"IL",
    "sg:tags":[
        "lawn"
    ],
    "wof:name":"Jim's Landscaping",
    "wof:placetype":"venue"
},
  "geometry": {"coordinates":[-88.453182,42.137091],"type":"Point"}
}