{
  "type": "Feature",
  "properties": {
    "iso:country":"US",
    "sg:address":"5423 S Hyde Park Blvd",
    "sg:city":"Chicago",
    "sg:classifiers":[
        {
            "category":"Place Of Worship",
            "type":"Public Place"
        },
        {
            "category":"Place Of Worship",
            "subcategory":"Temple",
            "type":"Public Place"
        }
    ],
    "sg:phone":"+1 773 363 0027",
    "sg:postcode":"60615",
    "sg:province":"IL",
    "sg:tags":[
        "churches-hindu",
        "church"
    ],
    "wof:name":"Ramakrishna Mission",
    "wof:placetype":"venue"
},
  "geometry": {"coordinates":[-87.583986,41.797494],"type":"Point"}
}