{
  "type": "Feature",
  "properties": {
    "iso:country":"US",
    "sg:address":"1528 W Adams St 1st Fl",
    "sg:city":"Chicago",
    "sg:classifiers":[
        {
            "category":"Professional",
            "subcategory":"Printing & Photocopies",
            "type":"Services"
        }
    ],
    "sg:phone":"+1 312 243 8304",
    "sg:postcode":"60607",
    "sg:province":"IL",
    "sg:website":"www.culturestudio.net",
    "wof:name":"Culture Studio Custom Screen Print and Embroidery",
    "wof:placetype":"venue"
},
  "geometry": {"coordinates":[-87.66555700000001,41.878937],"type":"Point"}
}