{
  "type": "Feature",
  "properties": {
    "addr:full":"1262 Ticklen Rd Odin IL 62870",
    "addr:housenumber":"1262",
    "addr:postcode":"62870",
    "addr:street":"Ticklen Rd",
    "iso:country":"US",
    "sg:address":"1262 Ticklen Rd",
    "sg:city":"Odin",
    "sg:classifiers":[
        {
            "category":"Building & Trades",
            "subcategory":"Plumbing",
            "type":"Services"
        }
    ],
    "sg:phone":"+1 618 775 6400",
    "sg:postcode":"62870",
    "sg:province":"IL",
    "sg:tags":[
        "contractor"
    ],
    "wof:name":"Ticknor Heating & AC",
    "wof:placetype":"venue"
},
  "geometry": {"coordinates":[-89.079735,38.670406],"type":"Point"}
}