{
  "type": "Feature",
  "properties": {
    "addr:full":"1726 170th Ave Aledo IL 61231",
    "addr:housenumber":"1726",
    "addr:postcode":"61231",
    "addr:street":"170Th Ave",
    "iso:country":"US",
    "sg:address":"1726 170th Ave",
    "sg:city":"Aledo",
    "sg:phone":"+1 309 372 8243",
    "sg:postcode":"61231",
    "sg:province":"IL",
    "sg:tags":[
        "farm",
        "corn",
        "soybean"
    ],
    "wof:name":"Douglas Mc Cleary",
    "wof:placetype":"venue"
},
  "geometry": {"coordinates":[-90.75901399999999,41.314314],"type":"Point"}
}