{
  "type": "Feature",
  "properties": {
    "iso:country":"US",
    "sg:address":"203 Shannon Rd",
    "sg:city":"Murphysboro",
    "sg:classifiers":[
        {
            "category":"Farming",
            "subcategory":"Livestock Farm",
            "type":"Manufacturing & Wholesale Goods"
        },
        {
            "category":"Farming",
            "subcategory":"Farm",
            "type":"Manufacturing & Wholesale Goods"
        }
    ],
    "sg:phone":"+1 618 684 6173",
    "sg:postcode":"62966",
    "sg:province":"IL",
    "wof:name":"Shannon Farm",
    "wof:placetype":"venue"
},
  "geometry": {"coordinates":[-89.399229,37.849152],"type":"Point"}
}