{
  "type": "Feature",
  "properties": {
    "iso:country":"US",
    "sg:address":"630 N Grand Ave E",
    "sg:city":"Springfield",
    "sg:classifiers":[
        {
            "category":"Restaurant",
            "type":"Food & Drink"
        }
    ],
    "sg:menulink":"http://www.allmenus.com/il/capital/127486-subway/menu/",
    "sg:phone":"+1 217 753 4054",
    "sg:postcode":"62702",
    "sg:province":"IL",
    "sg:tags":[
        "american",
        "sandwich"
    ],
    "wof:name":"Subway",
    "wof:placetype":"venue"
},
  "geometry": {"coordinates":[-89.646638,39.816279],"type":"Point"}
}