{
  "type": "Feature",
  "properties": {
    "addr:full":"85 Tefft Ave Elgin IL 60120",
    "addr:housenumber":"85",
    "addr:postcode":"60120",
    "addr:street":"Tefft Ave",
    "iso:country":"US",
    "sg:address":"85 Tefft Ave",
    "sg:city":"Elgin",
    "sg:classifiers":[
        {
            "category":"Building & Trades",
            "subcategory":"Landscaping Services",
            "type":"Services"
        }
    ],
    "sg:phone":"+1 847 695 6804",
    "sg:postcode":"60120",
    "sg:province":"IL",
    "wof:name":"Reds Landscaping Inc",
    "wof:placetype":"venue"
},
  "geometry": {"coordinates":[-88.257959,42.037736],"type":"Point"}
}