{
  "type": "Feature",
  "properties": {
    "addr:full":"3010 Highland Ave Downers Grove IL 60515",
    "addr:housenumber":"3010",
    "addr:postcode":"60515",
    "addr:street":"Highland Ave",
    "iso:country":"US",
    "sg:address":"3010 Highland Ave",
    "sg:city":"Downers Grove",
    "sg:classifiers":[
        {
            "category":"Professional",
            "subcategory":"Management & Consulting",
            "type":"Services"
        }
    ],
    "sg:phone":"+1 630 874 7300",
    "sg:postcode":"60515",
    "sg:province":"IL",
    "sg:website":"www.corvel.com",
    "wof:name":"Cor Vel Corp",
    "wof:placetype":"venue"
},
  "geometry": {"coordinates":[-88.01096800000001,41.833408],"type":"Point"}
}