{
  "type": "Feature",
  "properties": {
    "iso:country":"US",
    "sg:address":"124 N Main St",
    "sg:city":"Rockford",
    "sg:classifiers":[
        {
            "category":"Personal",
            "subcategory":"Beauty Salon",
            "type":"Services"
        }
    ],
    "sg:phone":"+1 815 965 4010",
    "sg:postcode":"61101",
    "sg:province":"IL",
    "sg:tags":[
        "shop"
    ],
    "wof:name":"Fuzz A Salon",
    "wof:placetype":"venue"
},
  "geometry": {"coordinates":[-89.094027,42.272004],"type":"Point"}
}