{
  "type": "Feature",
  "properties": {
    "addr:full":"1 E. Jackson Blvd Chicago IL 60604",
    "addr:housenumber":"1",
    "addr:postcode":"60604",
    "addr:street":"E. Jackson Blvd",
    "iso:country":"US",
    "sg:address":"1 E. Jackson Blvd",
    "sg:city":"Chicago",
    "sg:classifiers":[
        {
            "category":"Shopping",
            "subcategory":"Books",
            "type":"Retail Goods"
        }
    ],
    "sg:phone":"+1 312 362 8795",
    "sg:postcode":"60604",
    "sg:province":"IL",
    "sg:tags":[
        "bookstore"
    ],
    "sg:website":"www.bn.com",
    "wof:name":"Barnes & Noble",
    "wof:placetype":"venue"
},
  "geometry": {"coordinates":[-87.62763699999999,41.878207],"type":"Point"}
}