{
  "type": "Feature",
  "properties": {
    "iso:country":"US",
    "sg:address":"305 W South St",
    "sg:city":"Freeport",
    "sg:classifiers":[
        {
            "category":"Food & Beverages",
            "subcategory":"Groceries & Convenience Stores",
            "type":"Retail Goods"
        }
    ],
    "sg:phone":"+1   ",
    "sg:postcode":"61032",
    "sg:province":"IL",
    "wof:name":"Econofoods",
    "wof:placetype":"venue"
},
  "geometry": {"coordinates":[-89.62112500000001,42.280365],"type":"Point"}
}