{
  "type": "Feature",
  "properties": {
    "iso:country":"US",
    "sg:address":"705 Thomas Dr",
    "sg:city":"Bensenville",
    "sg:classifiers":[
        {
            "category":"Food & Beverages",
            "subcategory":"Meat & Fish",
            "type":"Retail Goods"
        }
    ],
    "sg:phone":"+1 630 766 0113",
    "sg:postcode":"60106",
    "sg:province":"IL",
    "sg:tags":[
        "market"
    ],
    "wof:name":"Malcolm Meats",
    "wof:placetype":"venue"
},
  "geometry": {"coordinates":[-87.945663,41.974801],"type":"Point"}
}