{
  "type": "Feature",
  "properties": {
    "iso:country":"US",
    "sg:address":"520 Jefferson St",
    "sg:city":"Ingleside",
    "sg:classifiers":[
        {
            "category":"Wholesale",
            "subcategory":"Machinery & Supplies",
            "type":"Manufacturing & Wholesale Goods"
        }
    ],
    "sg:phone":"+1 847 587 9427",
    "sg:postcode":"60041",
    "sg:province":"IL",
    "sg:tags":[
        "equipment",
        "welding"
    ],
    "wof:name":"Articulate Specialized Welding",
    "wof:placetype":"venue"
},
  "geometry": {"coordinates":[-88.15586999999999,42.384513],"type":"Point"}
}