{
  "type": "Feature",
  "properties": {
    "iso:country":"US",
    "sg:address":"1205 Karl Ct",
    "sg:city":"Wauconda",
    "sg:classifiers":[
        {
            "category":"Manufacturing",
            "subcategory":"Metals",
            "type":"Manufacturing & Wholesale Goods"
        }
    ],
    "sg:phone":"+1 847 526 6700",
    "sg:postcode":"60084",
    "sg:province":"IL",
    "sg:tags":[
        "cable"
    ],
    "wof:name":"Quality Cable Source Inc",
    "wof:placetype":"venue"
},
  "geometry": {"coordinates":[-88.14177,42.281361],"type":"Point"}
}