{
  "type": "Feature",
  "properties": {
    "iso:country":"US",
    "sg:address":"5599 Meadow Ln",
    "sg:city":"Alton",
    "sg:classifiers":[
        {
            "category":"Retail",
            "subcategory":"Repair Shop",
            "type":"Services"
        }
    ],
    "sg:phone":"+1 618 278 4595",
    "sg:postcode":"62002",
    "sg:province":"IL",
    "sg:tags":[
        "welding"
    ],
    "wof:name":"Mechanical Repair & Welding In",
    "wof:placetype":"venue"
},
  "geometry": {"coordinates":[-90.047648,39.005466],"type":"Point"}
}