{
  "type": "Feature",
  "properties": {
    "addr:full":"1 Sandpiper Ln Hawthorn Woods IL 60047",
    "addr:housenumber":"1",
    "addr:postcode":"60047",
    "addr:street":"Sandpiper Ln",
    "iso:country":"US",
    "sg:address":"1 Sandpiper Ln",
    "sg:city":"Hawthorn Woods",
    "sg:classifiers":[
        {
            "category":"Wholesale",
            "subcategory":"Hardware",
            "type":"Manufacturing & Wholesale Goods"
        },
        {
            "category":"Building & Trades",
            "subcategory":"Plumbing",
            "type":"Services"
        }
    ],
    "sg:phone":"+1 847 394 0440",
    "sg:postcode":"60047",
    "sg:province":"IL",
    "sg:tags":[
        "supply",
        "heating",
        "air",
        "parts",
        "conditioning",
        "contractor"
    ],
    "wof:name":"Paul's Heating & Cooling",
    "wof:placetype":"venue"
},
  "geometry": {"coordinates":[-88.065501,42.244358],"type":"Point"}
}