{
  "type": "Feature",
  "properties": {
    "iso:country":"US",
    "sg:address":"7900 E River Rd",
    "sg:city":"Ridott",
    "sg:classifiers":[
        {
            "category":"Freight",
            "type":"Transportation"
        }
    ],
    "sg:phone":"+1 815 449 2211",
    "sg:postcode":"61067",
    "sg:province":"IL",
    "sg:tags":[
        "operator",
        "hauling",
        "local",
        "livestock",
        "trucking"
    ],
    "wof:name":"Russ Boyer Trucking",
    "wof:placetype":"venue"
},
  "geometry": {"coordinates":[-89.463892,42.32064],"type":"Point"}
}