{
  "type": "Feature",
  "properties": {
    "iso:country":"US",
    "sg:address":"911 N 2nd St",
    "sg:city":"Chillicothe",
    "sg:classifiers":[
        {
            "category":"Personal",
            "subcategory":"Barber",
            "type":"Services"
        }
    ],
    "sg:phone":"+1 309 274 4991",
    "sg:postcode":"61523",
    "sg:province":"IL",
    "wof:name":"Andy's Barber Hairstyling Shop",
    "wof:placetype":"venue"
},
  "geometry": {"coordinates":[-89.485468,40.917098],"type":"Point"}
}