{
  "type": "Feature",
  "properties": {
    "addr:full":"1909 S Kensington Ave Kankakee IL 60901",
    "addr:housenumber":"1909",
    "addr:postcode":"60901",
    "addr:street":"S Kensington Ave",
    "iso:country":"US",
    "sg:address":"1909 S Kensington Ave",
    "sg:city":"Kankakee",
    "sg:classifiers":[
        {
            "category":"Building & Trades",
            "subcategory":"Construction",
            "type":"Services"
        }
    ],
    "sg:phone":"+1 815 936 9990",
    "sg:postcode":"60901",
    "sg:province":"IL",
    "sg:tags":[
        "concrete",
        "contractor"
    ],
    "wof:name":"Einfeldt Construction Inc",
    "wof:placetype":"venue"
},
  "geometry": {"coordinates":[-87.872981,41.097871],"type":"Point"}
}