{
  "type": "Feature",
  "properties": {
    "iso:country":"US",
    "sg:address":"313 Beinoris Dr",
    "sg:city":"Wood Dale",
    "sg:classifiers":[
        {
            "category":"Wholesale",
            "subcategory":"Scrap",
            "type":"Manufacturing & Wholesale Goods"
        }
    ],
    "sg:phone":"+1 630 616 1126",
    "sg:postcode":"60191",
    "sg:province":"IL",
    "sg:tags":[
        "material"
    ],
    "wof:name":"G & M Metal & Parts",
    "wof:placetype":"venue"
},
  "geometry": {"coordinates":[-87.968574,41.976515],"type":"Point"}
}