{
  "type": "Feature",
  "properties": {
    "iso:country":"US",
    "sg:address":"801 S Macarthur Blvd",
    "sg:city":"Springfield",
    "sg:classifiers":[
        {
            "category":"Professional",
            "subcategory":"Lawyer & Legal Services",
            "type":"Services"
        }
    ],
    "sg:phone":"+1 217 726 7540",
    "sg:postcode":"62704",
    "sg:province":"IL",
    "sg:tags":[
        "attorney",
        "accident",
        "family",
        "corporation",
        "wills",
        "partnership",
        "damage",
        "property",
        "planning",
        "real estate",
        "trust",
        "law"
    ],
    "sg:website":"http://www.kopecandwhite-law.com",
    "wof:name":"Kopec & White",
    "wof:placetype":"venue"
},
  "geometry": {"coordinates":[-89.668114,39.794201],"type":"Point"}
}