{
  "type": "Feature",
  "properties": {
    "addr:full":"321 Powell Ave Waukegan IL 60085",
    "addr:housenumber":"321",
    "addr:postcode":"60085",
    "addr:street":"Powell Ave",
    "iso:country":"US",
    "sg:address":"321 Powell Ave",
    "sg:city":"Waukegan",
    "sg:classifiers":[
        {
            "category":"Personal",
            "subcategory":"Beauty Salon",
            "type":"Services"
        }
    ],
    "sg:phone":"+1 847 623 9115",
    "sg:postcode":"60085",
    "sg:province":"IL",
    "sg:tags":[
        "shop"
    ],
    "wof:name":"Hair & Nail Talk & Boutique",
    "wof:placetype":"venue"
},
  "geometry": {"coordinates":[-87.841022,42.354222],"type":"Point"}
}