{
  "type": "Feature",
  "properties": {
    "iso:country":"US",
    "sg:address":"1019 W Stearns Rd",
    "sg:city":"Bartlett",
    "sg:classifiers":[
        {
            "category":"Professional",
            "subcategory":"Employment Agencies",
            "type":"Services"
        }
    ],
    "sg:phone":"+1 630 540 0840",
    "sg:postcode":"60103",
    "sg:province":"IL",
    "sg:website":"www.staffingsolutions.com",
    "wof:name":"Total Staffing Solutions",
    "wof:placetype":"venue"
},
  "geometry": {"coordinates":[-88.200104,41.974499],"type":"Point"}
}