{
  "type": "Feature",
  "properties": {
    "addr:full":"1127 N Dunton Ave Arlington Heights IL 60004",
    "addr:housenumber":"1127",
    "addr:postcode":"60004",
    "addr:street":"N Dunton Ave",
    "iso:country":"US",
    "sg:address":"1127 N Dunton Ave",
    "sg:city":"Arlington Heights",
    "sg:classifiers":[
        {
            "category":"Professional",
            "subcategory":"Computer Services",
            "type":"Services"
        }
    ],
    "sg:phone":"+1 847 398 1727",
    "sg:postcode":"60004",
    "sg:province":"IL",
    "sg:tags":[
        "programing",
        "custom"
    ],
    "wof:name":"Wr Computing Inc",
    "wof:placetype":"venue"
},
  "geometry": {"coordinates":[-87.982804,42.098704],"type":"Point"}
}