{
  "type": "Feature",
  "properties": {
    "addr:full":"1816 Wilmette Ct Wheaton IL 60187",
    "addr:housenumber":"1816",
    "addr:postcode":"60187",
    "addr:street":"Wilmette Ct",
    "iso:country":"US",
    "sg:address":"1816 Wilmette Ct",
    "sg:city":"Wheaton",
    "sg:classifiers":[
        {
            "category":"Manufacturing",
            "subcategory":"Tools & Machinery",
            "type":"Manufacturing & Wholesale Goods"
        }
    ],
    "sg:phone":"+1 630 665 4696",
    "sg:postcode":"60187",
    "sg:province":"IL",
    "sg:tags":[
        "machine",
        "shop"
    ],
    "wof:name":"Glenro Inc",
    "wof:placetype":"venue"
},
  "geometry": {"coordinates":[-88.08478599999999,41.883884],"type":"Point"}
}