{
  "type": "Feature",
  "properties": {
    "iso:country":"US",
    "sg:address":"2001 Lakewood Blvd",
    "sg:city":"Schaumburg",
    "sg:classifiers":[
        {
            "category":"Utilities",
            "subcategory":"Telephone",
            "type":"Services"
        }
    ],
    "sg:phone":"+1 708 705 7899",
    "sg:postcode":"60192",
    "sg:province":"IL",
    "sg:tags":[
        "communications"
    ],
    "wof:name":"BellSouth Mobility LLC",
    "wof:placetype":"venue"
},
  "geometry": {"coordinates":[-88.129847,42.074413],"type":"Point"}
}