{
  "type": "Feature",
  "properties": {
    "iso:country":"US",
    "sg:address":"1180 Belt Line Rd",
    "sg:city":"Collinsville",
    "sg:classifiers":[
        {
            "category":"Wholesale",
            "subcategory":"Medical Equipment & Supplies",
            "type":"Manufacturing & Wholesale Goods"
        },
        {
            "category":"Utilities",
            "subcategory":"Natural Gas",
            "type":"Services"
        }
    ],
    "sg:phone":"+1 318 233 0503",
    "sg:postcode":"62234",
    "sg:province":"IL",
    "sg:tags":[
        "assistive",
        "device",
        "aids-manufacturers",
        "aid",
        "hearing"
    ],
    "wof:name":"Hearing Center, The",
    "wof:placetype":"venue"
},
  "geometry": {"coordinates":[-89.989084,38.691212],"type":"Point"}
}