{
  "type": "Feature",
  "properties": {
    "addr:full":"2318 State St East Saint Louis IL 62205",
    "addr:housenumber":"2318",
    "addr:postcode":"62205",
    "addr:street":"State St East",
    "iso:country":"US",
    "sg:address":"2318 State St",
    "sg:city":"East Saint Louis",
    "sg:classifiers":[
        {
            "category":"Shopping",
            "subcategory":"Department Store",
            "type":"Retail Goods"
        },
        {
            "category":"Shopping",
            "subcategory":"Discount & Variety Stores",
            "type":"Retail Goods"
        }
    ],
    "sg:phone":"+1 618 875 9806",
    "sg:postcode":"62205",
    "sg:province":"IL",
    "sg:tags":[
        "shop"
    ],
    "sg:website":"www.familydollar.com",
    "wof:name":"Family Dollar Stores Inc",
    "wof:placetype":"venue"
},
  "geometry": {"coordinates":[-90.128799,38.6166],"type":"Point"}
}