{
  "type": "Feature",
  "properties": {
    "iso:country":"US",
    "sg:address":"1120 Chicago Ave",
    "sg:city":"Oak Park",
    "sg:classifiers":[
        {
            "category":"Shopping",
            "type":"Retail Goods"
        }
    ],
    "sg:phone":"+1   ",
    "sg:postcode":"60302",
    "sg:province":"IL",
    "sg:tags":[
        "interior",
        "design",
        "framing",
        "custom"
    ],
    "wof:name":"Wallace Gilmours Inc",
    "wof:placetype":"venue"
},
  "geometry": {"coordinates":[-87.80514700000001,41.894295],"type":"Point"}
}