{
  "type": "Feature",
  "properties": {
    "addr:full":"1682 Barclay Blvd Buffalo Grove IL 60089",
    "addr:housenumber":"1682",
    "addr:postcode":"60089",
    "addr:street":"Barclay Blvd",
    "iso:country":"US",
    "sg:address":"1682 Barclay Blvd",
    "sg:city":"Buffalo Grove",
    "sg:classifiers":[
        {
            "category":"Wholesale",
            "subcategory":"Machinery & Supplies",
            "type":"Manufacturing & Wholesale Goods"
        }
    ],
    "sg:phone":"+1 847 459 8040",
    "sg:postcode":"60089",
    "sg:province":"IL",
    "sg:tags":[
        "industrial",
        "com"
    ],
    "wof:name":"Foodservice Solutions Inc",
    "wof:placetype":"venue"
},
  "geometry": {"coordinates":[-87.935621,42.178599],"type":"Point"}
}