{
  "type": "Feature",
  "properties": {
    "addr:full":"12163 E 1580 North Rd Catlin IL 61817",
    "addr:housenumber":"12163",
    "addr:postcode":"61817",
    "addr:street":"E 1580 North Rd",
    "iso:country":"US",
    "sg:address":"12163 E 1580 North Rd",
    "sg:city":"Catlin",
    "sg:classifiers":[
        {
            "category":"Building & Trades",
            "subcategory":"Construction",
            "type":"Services"
        }
    ],
    "sg:phone":"+1 217 427 5624",
    "sg:postcode":"61817",
    "sg:province":"IL",
    "sg:tags":[
        "sandblasting"
    ],
    "wof:name":"C B Ervin & Sons",
    "wof:placetype":"venue"
},
  "geometry": {"coordinates":[-87.709463,40.100731],"type":"Point"}
}