{
  "type": "Feature",
  "properties": {
    "iso:country":"US",
    "sg:address":"940 Patricia Ln",
    "sg:city":"Crete",
    "sg:classifiers":[
        {
            "category":"Professional",
            "subcategory":"Management & Consulting",
            "type":"Services"
        }
    ],
    "sg:phone":"+1 708 672 7935",
    "sg:postcode":"60417",
    "sg:province":"IN",
    "wof:name":"Therrien Industrial Consulting",
    "wof:placetype":"venue"
},
  "geometry": {"coordinates":[-87.589569,41.468284],"type":"Point"}
}