{
  "type": "Feature",
  "properties": {
    "iso:country":"US",
    "sg:address":"2505 Grove Ln",
    "sg:city":"Cary",
    "sg:classifiers":[
        {
            "category":"Shopping",
            "subcategory":"Clothing, Apparel, & Fashions",
            "type":"Retail Goods"
        }
    ],
    "sg:phone":"+1 847 462 0693",
    "sg:postcode":"60013",
    "sg:province":"IL",
    "sg:tags":[
        "sportswear"
    ],
    "sg:website":"www.urbanwarriorsportswear.com",
    "wof:name":"Urban Warrior",
    "wof:placetype":"venue"
},
  "geometry": {"coordinates":[-88.238199,42.195972],"type":"Point"}
}