{
  "type": "Feature",
  "properties": {
    "addr:full":"9227 Lorel Ave Skokie IL 60077",
    "addr:housenumber":"9227",
    "addr:postcode":"60077",
    "addr:street":"Lorel Ave",
    "iso:country":"US",
    "sg:address":"9227 Lorel Ave",
    "sg:city":"Skokie",
    "sg:classifiers":[
        {
            "category":"Professional",
            "subcategory":"Computer Services",
            "type":"Services"
        }
    ],
    "sg:phone":"+1 847 965 3306",
    "sg:postcode":"60077",
    "sg:province":"IL",
    "sg:tags":[
        "aided",
        "design"
    ],
    "wof:name":"B & J Computer Design Services",
    "wof:placetype":"venue"
},
  "geometry": {"coordinates":[-87.760204,42.049527],"type":"Point"}
}