{
  "type": "Feature",
  "properties": {
    "iso:country":"US",
    "sg:address":"2201 W Townline Rd Ste 4",
    "sg:city":"Peoria",
    "sg:classifiers":[
        {
            "category":"Health Services",
            "subcategory":"Nursing And Care Facility",
            "type":"Services"
        },
        {
            "category":"Health Services",
            "subcategory":"Health Practitioner",
            "type":"Services"
        }
    ],
    "sg:phone":"+1 309 691 1839",
    "sg:postcode":"61615",
    "sg:province":"IL",
    "sg:tags":[
        "home",
        "eldercare-home"
    ],
    "wof:name":"Emercengy Resource Staffing",
    "wof:placetype":"venue"
},
  "geometry": {"coordinates":[-89.627083,40.797985],"type":"Point"}
}