{
  "type": "Feature",
  "properties": {
    "addr:full":"117 N Wabash Ave Chicago IL 60602",
    "addr:housenumber":"117",
    "addr:postcode":"60602",
    "addr:street":"N Wabash Ave",
    "iso:country":"US",
    "sg:address":"117 N Wabash Ave",
    "sg:city":"Chicago",
    "sg:classifiers":[
        {
            "category":"Food & Beverages",
            "subcategory":"Candy",
            "type":"Retail Goods"
        }
    ],
    "sg:phone":"+1 312 750 1755",
    "sg:postcode":"60602",
    "sg:province":"IL",
    "sg:tags":[
        "confectionery"
    ],
    "wof:name":"Fannie May",
    "wof:placetype":"venue"
},
  "geometry": {"coordinates":[-87.626223,41.883634],"type":"Point"}
}