{
  "type": "Feature",
  "properties": {
    "addr:full":"469b W Liberty St Wauconda IL 60084",
    "addr:housenumber":"469b",
    "addr:postcode":"60084",
    "addr:street":"W Liberty St",
    "iso:country":"US",
    "sg:address":"469b W Liberty St",
    "sg:city":"Wauconda",
    "sg:classifiers":[
        {
            "category":"Restaurant",
            "type":"Food & Drink"
        }
    ],
    "sg:menulink":"http://www.allmenus.com/il/wauconda/76544-dominos-pizza/menu/",
    "sg:phone":"+1 847 526 0550",
    "sg:postcode":"60084",
    "sg:province":"IL",
    "sg:tags":[
        "american",
        "wing",
        "pizza"
    ],
    "wof:name":"Domino's Pizza",
    "wof:placetype":"venue"
},
  "geometry": {"coordinates":[-88.147848,42.256924],"type":"Point"}
}