{
  "type": "Feature",
  "properties": {
    "iso:country":"US",
    "sg:address":"8700 Collinsville Rd",
    "sg:city":"Collinsville",
    "sg:classifiers":[
        {
            "category":"Food & Beverages",
            "subcategory":"Liquor & Beverages",
            "type":"Retail Goods"
        }
    ],
    "sg:phone":"+1 618 345 7873",
    "sg:postcode":"62234",
    "sg:province":"IL",
    "wof:name":"Stop & Go Liquor Annex",
    "wof:placetype":"venue"
},
  "geometry": {"coordinates":[-90.04564000000001,38.658767],"type":"Point"}
}