{
  "type": "Feature",
  "properties": {
    "iso:country":"US",
    "sg:address":"6118 Barnard Mill Rd",
    "sg:city":"Ringwood",
    "sg:classifiers":[
        {
            "category":"Building & Trades",
            "subcategory":"Plumbing",
            "type":"Services"
        }
    ],
    "sg:phone":"+1 815 653 5530",
    "sg:postcode":"60072",
    "sg:province":"IL",
    "sg:tags":[
        "contractor"
    ],
    "wof:name":"Accura Air",
    "wof:placetype":"venue"
},
  "geometry": {"coordinates":[-88.309471,42.394552],"type":"Point"}
}