{
  "type": "Feature",
  "properties": {
    "iso:country":"US",
    "sg:address":"4353 S Kedzie Ave",
    "sg:city":"Chicago",
    "sg:classifiers":[
        {
            "category":"Health Services",
            "subcategory":"Chiropractor",
            "type":"Services"
        }
    ],
    "sg:phone":"+1 773 927 1885",
    "sg:postcode":"60632",
    "sg:province":"IL",
    "sg:tags":[
        "chiropractic"
    ],
    "wof:name":"A Back To Health Chiropractic",
    "wof:placetype":"venue"
},
  "geometry": {"coordinates":[-87.704015,41.814093],"type":"Point"}
}