{
  "type": "Feature",
  "properties": {
    "iso:country":"US",
    "sg:address":"435 E 75th St",
    "sg:city":"Chicago",
    "sg:classifiers":[
        {
            "category":"Shopping",
            "subcategory":"Beauty & Cosmetics",
            "type":"Retail Goods"
        },
        {
            "category":"Personal",
            "subcategory":"Beauty Salon",
            "type":"Services"
        }
    ],
    "sg:phone":"+1 773 874 0363",
    "sg:postcode":"60619",
    "sg:province":"IL",
    "sg:tags":[
        "perfume",
        "salons-equipment",
        "supply"
    ],
    "wof:name":"Symthony Daffney Hair Salon",
    "wof:placetype":"venue"
},
  "geometry": {"coordinates":[-87.613855,41.758431],"type":"Point"}
}