{
  "type": "Feature",
  "properties": {
    "iso:country":"US",
    "sg:address":"510 W Belmont Ave",
    "sg:city":"Chicago",
    "sg:classifiers":[
        {
            "category":"Education",
            "subcategory":"Special Training",
            "type":"Public Place"
        }
    ],
    "sg:phone":"+1 773 348 3048",
    "sg:postcode":"60657",
    "sg:province":"IL",
    "sg:tags":[
        "learning"
    ],
    "wof:name":"Learntrain",
    "wof:placetype":"venue"
},
  "geometry": {"coordinates":[-87.643128,41.940142],"type":"Point"}
}