{
  "type": "Feature",
  "properties": {
    "addr:full":"105 E Galena Blvd Aurora IL 60505",
    "addr:housenumber":"105",
    "addr:postcode":"60505",
    "addr:street":"E Galena Blvd",
    "iso:country":"US",
    "sg:address":"105 E Galena Blvd",
    "sg:city":"Aurora",
    "sg:classifiers":[
        {
            "category":"Banks & Credit Unions",
            "subcategory":"Bank",
            "type":"Services"
        }
    ],
    "sg:phone":"+1 630 844 6110",
    "sg:postcode":"60505",
    "sg:province":"IL",
    "sg:tags":[
        "company",
        "trust",
        "holding",
        "facility"
    ],
    "wof:name":"Greatbanc Inc",
    "wof:placetype":"venue"
},
  "geometry": {"coordinates":[-88.312178,41.75656],"type":"Point"}
}