{
  "type": "Feature",
  "properties": {
    "addr:full":"1509 N Rand Rd Palatine IL 60074",
    "addr:housenumber":"1509",
    "addr:postcode":"60074",
    "addr:street":"N Rand Rd",
    "iso:country":"US",
    "sg:address":"1509 N Rand Rd",
    "sg:city":"Palatine",
    "sg:classifiers":[
        {
            "category":"Food & Beverages",
            "subcategory":"Groceries & Convenience Stores",
            "type":"Retail Goods"
        }
    ],
    "sg:phone":"+1   ",
    "sg:postcode":"60074",
    "sg:province":"IL",
    "wof:name":"White Hen Pantry",
    "wof:placetype":"venue"
},
  "geometry": {"coordinates":[-88.019165,42.137206],"type":"Point"}
}