{
  "type": "Feature",
  "properties": {
    "iso:country":"US",
    "sg:address":"603 S East St",
    "sg:city":"Jacksonville",
    "sg:classifiers":[
        {
            "category":"Arts & Performance",
            "subcategory":"Theater",
            "type":"Entertainment"
        }
    ],
    "sg:phone":"+1 217 245 6835",
    "sg:postcode":"62650",
    "sg:province":"IL",
    "sg:tags":[
        "group"
    ],
    "wof:name":"Club Dbr Video DJ",
    "wof:placetype":"venue"
},
  "geometry": {"coordinates":[-90.226899,39.726979],"type":"Point"}
}