{
  "type": "Feature",
  "properties": {
    "addr:full":"3422 N Lincoln Avenue Chicago IL 60657",
    "addr:housenumber":"3422",
    "addr:postcode":"60657",
    "addr:street":"N Lincoln Avenue",
    "iso:country":"US",
    "sg:address":"3422 N Lincoln Avenue",
    "sg:city":"Chicago",
    "sg:classifiers":[
        {
            "category":"Shopping",
            "subcategory":"Antiques",
            "type":"Retail Goods"
        }
    ],
    "sg:phone":"+1 773 883 8733",
    "sg:postcode":"60657",
    "sg:province":"IL",
    "wof:name":"Tree Studio Gallery",
    "wof:placetype":"venue"
},
  "geometry": {"coordinates":[-87.671604,41.944139],"type":"Point"}
}