{
  "type": "Feature",
  "properties": {
    "iso:country":"US",
    "sg:address":"581 Beltline Rd",
    "sg:city":"Collinsville",
    "sg:classifiers":[
        {
            "category":"Shopping",
            "subcategory":"Shoes",
            "type":"Retail Goods"
        }
    ],
    "sg:phone":"+1   ",
    "sg:postcode":"62234",
    "sg:province":"IL",
    "sg:tags":[
        "shoe",
        "store"
    ],
    "wof:name":"Famous Footwear 1259",
    "wof:placetype":"venue"
},
  "geometry": {"coordinates":[-89.978745,38.690898],"type":"Point"}
}