{
  "type": "Feature",
  "properties": {
    "addr:full":"1560 Franklin Grove Rd Dixon IL 61021",
    "addr:housenumber":"1560",
    "addr:postcode":"61021",
    "addr:street":"Franklin Grove Rd",
    "iso:country":"US",
    "sg:address":"1560 Franklin Grove Rd",
    "sg:city":"Dixon",
    "sg:classifiers":[
        {
            "category":"Organizations",
            "subcategory":"Community Association",
            "type":"Services"
        }
    ],
    "sg:phone":"+1 815 288 5165",
    "sg:postcode":"61021",
    "sg:province":"IL",
    "sg:tags":[
        "club"
    ],
    "wof:name":"Veterans Of Foreign Wars",
    "wof:placetype":"venue"
},
  "geometry": {"coordinates":[-89.445604,41.837818],"type":"Point"}
}