{
  "type": "Feature",
  "properties": {
    "iso:country":"US",
    "sg:address":"1401 S State St Ste 1314",
    "sg:city":"Chicago",
    "sg:classifiers":[
        {
            "category":"Professional",
            "type":"Services"
        }
    ],
    "sg:phone":"+1 312 550 4800",
    "sg:postcode":"60605",
    "sg:province":"IL",
    "sg:website":"www.escotal.com",
    "wof:name":"Escotal Corporation",
    "wof:placetype":"venue"
},
  "geometry": {"coordinates":[-87.62691100000001,41.863766],"type":"Point"}
}