{
  "type": "Feature",
  "properties": {
    "iso:country":"US",
    "sg:address":"1445 1000th St",
    "sg:city":"Lincoln",
    "sg:phone":"+1 217 735 1474",
    "sg:postcode":"62656",
    "sg:province":"IL",
    "sg:tags":[
        "farm",
        "corn"
    ],
    "wof:name":"Bill Bree",
    "wof:placetype":"venue"
},
  "geometry": {"coordinates":[-89.32420500000001,40.062821],"type":"Point"}
}