{
  "type": "Feature",
  "properties": {
    "iso:country":"US",
    "sg:address":"4320 W Ogden Avenue",
    "sg:city":"Chicago",
    "sg:classifiers":[
        {
            "category":"Food & Beverages",
            "subcategory":"Meat & Fish",
            "type":"Retail Goods"
        }
    ],
    "sg:phone":"+1 773 762 3334",
    "sg:postcode":"60623",
    "sg:province":"IL",
    "sg:tags":[
        "shop"
    ],
    "wof:name":"Sparrer Sausage Company",
    "wof:placetype":"venue"
},
  "geometry": {"coordinates":[-87.731876,41.848558],"type":"Point"}
}