{
  "type": "Feature",
  "properties": {
    "iso:country":"US",
    "sg:address":"527 Warren Ave",
    "sg:city":"Rockford",
    "sg:classifiers":[
        {
            "category":"Retail",
            "subcategory":"Laundry & Dry Cleaning",
            "type":"Services"
        }
    ],
    "sg:phone":"+1 815 398 5124",
    "sg:postcode":"61107",
    "sg:province":"IL",
    "sg:tags":[
        "cleaners",
        "rug",
        "carpet"
    ],
    "wof:name":"State Line Cleaning",
    "wof:placetype":"venue"
},
  "geometry": {"coordinates":[-89.044622,42.27256],"type":"Point"}
}