{
  "type": "Feature",
  "properties": {
    "iso:country":"US",
    "sg:address":"221 N La Salle Ste 1450",
    "sg:city":"Chicago",
    "sg:classifiers":[
        {
            "category":"Professional",
            "subcategory":"Employment Agencies",
            "type":"Services"
        }
    ],
    "sg:phone":"+1 312 346 4292",
    "sg:postcode":"60601",
    "sg:province":"IL",
    "sg:website":"www.jki-inc.com",
    "wof:name":"Jean Kripton, Inc",
    "wof:placetype":"venue"
},
  "geometry": {"coordinates":[-87.632559,41.884811],"type":"Point"}
}