{
  "type": "Feature",
  "properties": {
    "iso:country":"US",
    "sg:address":"1796 Rand Rd",
    "sg:city":"Des Plaines",
    "sg:classifiers":[
        {
            "category":"Building & Trades",
            "subcategory":"Construction",
            "type":"Services"
        }
    ],
    "sg:phone":"+1 847 459 0100",
    "sg:postcode":"60016",
    "sg:province":"IL",
    "sg:tags":[
        "house",
        "contractor",
        "concrete"
    ],
    "wof:name":"Main Beam Construction",
    "wof:placetype":"venue"
},
  "geometry": {"coordinates":[-87.880717,42.045523],"type":"Point"}
}