{
  "type": "Feature",
  "properties": {
    "iso:country":"US",
    "sg:address":"1743 E Co Rd 2200",
    "sg:city":"Dallas City",
    "sg:classifiers":[
        {
            "category":"Wholesale",
            "subcategory":"Farm Supplies",
            "type":"Manufacturing & Wholesale Goods"
        }
    ],
    "sg:phone":"+1 217 746 3111",
    "sg:postcode":"62330",
    "sg:province":"IL",
    "sg:tags":[
        "fertilizer"
    ],
    "wof:name":"Chem Gro Inc",
    "wof:placetype":"venue"
},
  "geometry": {"coordinates":[-91.169119,40.520555],"type":"Point"}
}