{
  "type": "Feature",
  "properties": {
    "iso:country":"US",
    "sg:address":"171 Kenwood St",
    "sg:city":"Argenta",
    "sg:classifiers":[
        {
            "category":"Restaurant",
            "type":"Food & Drink"
        }
    ],
    "sg:phone":"+1 217 795 2444",
    "sg:postcode":"62501",
    "sg:province":"IL",
    "sg:tags":[
        "caterer"
    ],
    "wof:name":"Blue Banana Catering & Event",
    "wof:placetype":"venue"
},
  "geometry": {"coordinates":[-88.8239,39.982731],"type":"Point"}
}