{
  "type": "Feature",
  "properties": {
    "iso:country":"US",
    "sg:address":"711 S Knight Ave",
    "sg:city":"Park Ridge",
    "sg:classifiers":[
        {
            "category":"Building & Trades",
            "subcategory":"Construction",
            "type":"Services"
        }
    ],
    "sg:phone":"+1 847 692 3693",
    "sg:postcode":"60068",
    "sg:province":"IL",
    "sg:tags":[
        "hanging",
        "contractor"
    ],
    "wof:name":"Jacks Decorating",
    "wof:placetype":"venue"
},
  "geometry": {"coordinates":[-87.84433799999999,42.003112],"type":"Point"}
}