{
  "type": "Feature",
  "properties": {
    "iso:country":"US",
    "sg:address":"453 Lincoln Ave",
    "sg:city":"Charleston",
    "sg:classifiers":[
        {
            "category":"Restaurant",
            "type":"Food & Drink"
        }
    ],
    "sg:menulink":"http://www.allmenus.com/il/charleston/276097-boxa-grinders-pizza-wings/menu/",
    "sg:phone":"+1 217 345 2692",
    "sg:postcode":"61920",
    "sg:province":"IL",
    "sg:tags":[
        "american",
        "sandwich",
        "wing",
        "pizza"
    ],
    "wof:name":"Boxa Grinders Pizza Wings",
    "wof:placetype":"venue"
},
  "geometry": {"coordinates":[-88.176467,39.484554],"type":"Point"}
}