{
  "type": "Feature",
  "properties": {
    "addr:full":"505 Devonshire Dr Champaign IL 61820",
    "addr:housenumber":"505",
    "addr:postcode":"61820",
    "addr:street":"Devonshire Dr",
    "iso:country":"US",
    "sg:address":"505 Devonshire Dr",
    "sg:city":"Champaign",
    "sg:classifiers":[
        {
            "category":"Insurance",
            "subcategory":"Hazard Insurance",
            "type":"Services"
        }
    ],
    "sg:phone":"+1 217 356 7263",
    "sg:postcode":"61820",
    "sg:province":"IL",
    "sg:website":"http://www.downeygroup.com",
    "wof:name":"Mcgill, John E Jr Clu",
    "wof:placetype":"venue"
},
  "geometry": {"coordinates":[-88.250529,40.089758],"type":"Point"}
}