{
  "type": "Feature",
  "properties": {
    "addr:full":"2404 Windsor Pl Champaign IL 61820",
    "addr:housenumber":"2404",
    "addr:postcode":"61820",
    "addr:street":"Windsor Pl",
    "iso:country":"US",
    "sg:address":"2404 Windsor Pl",
    "sg:city":"Champaign",
    "sg:classifiers":[
        {
            "category":"Professional",
            "subcategory":"Accounting & Tax Preparation",
            "type":"Services"
        }
    ],
    "sg:phone":"+1 217 351 5010",
    "sg:postcode":"61820",
    "sg:province":"IL",
    "sg:tags":[
        "accountant"
    ],
    "wof:name":"Accredited Business Svc",
    "wof:placetype":"venue"
},
  "geometry": {"coordinates":[-88.248329,40.08266],"type":"Point"}
}