{
  "type": "Feature",
  "properties": {
    "addr:full":"24100 W North Ave Antioch IL 60002",
    "addr:housenumber":"24100",
    "addr:postcode":"60002",
    "addr:street":"W North Ave",
    "iso:country":"US",
    "sg:address":"24100 W North Ave",
    "sg:city":"Antioch",
    "sg:classifiers":[
        {
            "category":"Farming",
            "subcategory":"Farm",
            "type":"Manufacturing & Wholesale Goods"
        }
    ],
    "sg:phone":"+1 847 395 0322",
    "sg:postcode":"60002",
    "sg:province":"IL",
    "sg:tags":[
        "crop",
        "general"
    ],
    "wof:name":"Hermans Farm",
    "wof:placetype":"venue"
},
  "geometry": {"coordinates":[-88.103523,42.488041],"type":"Point"}
}