{
  "type": "Feature",
  "properties": {
    "iso:country":"US",
    "sg:address":"1301 Ashland Ave",
    "sg:city":"Des Plaines",
    "sg:classifiers":[
        {
            "category":"Government",
            "subcategory":"Office",
            "type":"Public Place"
        }
    ],
    "sg:phone":"+1   ",
    "sg:postcode":"60016",
    "sg:province":"IL",
    "sg:tags":[
        "building",
        "program",
        "housing",
        "apartment",
        "operator"
    ],
    "wof:name":"Henrich House",
    "wof:placetype":"venue"
},
  "geometry": {"coordinates":[-87.890925,42.036162],"type":"Point"}
}