{
  "type": "Feature",
  "properties": {
    "iso:country":"US",
    "sg:address":"1812 E Lincoln Hwy",
    "sg:city":"New Lenox",
    "sg:classifiers":[
        {
            "category":"Health Services",
            "subcategory":"Health Practitioner",
            "type":"Services"
        }
    ],
    "sg:phone":"+1 815 485 8495",
    "sg:postcode":"60451",
    "sg:province":"IL",
    "sg:tags":[
        "therapist",
        "physical"
    ],
    "wof:name":"Provena Physical Therapy Svc",
    "wof:placetype":"venue"
},
  "geometry": {"coordinates":[-87.93284,41.51177],"type":"Point"}
}