{
  "type": "Feature",
  "properties": {
    "iso:country":"US",
    "sg:address":"426 N Center St",
    "sg:city":"Durand",
    "sg:classifiers":[
        {
            "category":"Home & Garden",
            "subcategory":"Furniture",
            "type":"Retail Goods"
        }
    ],
    "sg:phone":"+1 815 248 4800",
    "sg:postcode":"61024",
    "sg:province":"IL",
    "wof:name":"Mc Corkle Furniture",
    "wof:placetype":"venue"
},
  "geometry": {"coordinates":[-89.332034,42.436341],"type":"Point"}
}