{
  "type": "Feature",
  "properties": {
    "iso:country":"US",
    "sg:address":"928 Best St",
    "sg:city":"Staunton",
    "sg:classifiers":[
        {
            "category":"Building & Trades",
            "subcategory":"Electrical",
            "type":"Services"
        }
    ],
    "sg:phone":"+1 618 635 6222",
    "sg:postcode":"62088",
    "sg:province":"IL",
    "sg:tags":[
        "electrical",
        "contractor"
    ],
    "wof:name":"Rl Electrical Services Inc",
    "wof:placetype":"venue"
},
  "geometry": {"coordinates":[-89.795573,39.004612],"type":"Point"}
}