{
  "type": "Feature",
  "properties": {
    "iso:country":"US",
    "sg:address":"645 Supreme Dr",
    "sg:city":"Bensenville",
    "sg:classifiers":[
        {
            "category":"Banks & Credit Unions",
            "subcategory":"Investment Brokerage",
            "type":"Services"
        },
        {
            "category":"Banks & Credit Unions",
            "subcategory":"Financial Services",
            "type":"Services"
        }
    ],
    "sg:phone":"+1 630 238 0500",
    "sg:postcode":"60106",
    "sg:province":"IL",
    "sg:tags":[
        "annuity",
        "retirement",
        "insurance",
        "plan"
    ],
    "sg:website":"http://www.usbinc.com",
    "wof:name":"United States Brokerage",
    "wof:placetype":"venue"
},
  "geometry": {"coordinates":[-87.949584,41.98519],"type":"Point"}
}