{
  "type": "Feature",
  "properties": {
    "iso:country":"US",
    "sg:address":"612 Chestnut St",
    "sg:city":"Waukegan",
    "sg:classifiers":[
        {
            "category":"Freight",
            "type":"Transportation"
        }
    ],
    "sg:phone":"+1 847 845 8399",
    "sg:postcode":"60085",
    "sg:province":"IL",
    "sg:tags":[
        "operator",
        "local",
        "trucking"
    ],
    "wof:name":"P/W Light Hauling",
    "wof:placetype":"venue"
},
  "geometry": {"coordinates":[-87.841157,42.370089],"type":"Point"}
}