{
  "type": "Feature",
  "properties": {
    "iso:country":"US",
    "sg:address":"1114 W Hubbard St",
    "sg:city":"Chicago",
    "sg:classifiers":[
        {
            "category":"Manufacturing",
            "subcategory":"Petroleum Products",
            "type":"Manufacturing & Wholesale Goods"
        }
    ],
    "sg:phone":"+1 312 207 4788",
    "sg:postcode":"60642",
    "sg:province":"IL",
    "sg:tags":[
        "candles-wholesale",
        "manufacturer"
    ],
    "wof:name":"M & L Enterprises Inc",
    "wof:placetype":"venue"
},
  "geometry": {"coordinates":[-87.655219,41.889999],"type":"Point"}
}