{
  "type": "Feature",
  "properties": {
    "iso:country":"US",
    "sg:address":"594 N Pinecrest Rd",
    "sg:city":"Bolingbrook",
    "sg:classifiers":[
        {
            "category":"Bars & Pubs",
            "type":"Food & Drink"
        }
    ],
    "sg:phone":"+1   ",
    "sg:postcode":"60440",
    "sg:province":"IL",
    "sg:tags":[
        "bar"
    ],
    "wof:name":"TS",
    "wof:placetype":"venue"
},
  "geometry": {"coordinates":[-88.050568,41.71637],"type":"Point"}
}