{
  "type": "Feature",
  "properties": {
    "addr:full":"1501 Central St Evanston IL 60201",
    "addr:housenumber":"1501",
    "addr:postcode":"60201",
    "addr:street":"Central St",
    "iso:country":"US",
    "sg:address":"1501 Central St",
    "sg:city":"Evanston",
    "sg:classifiers":[
        {
            "category":"Professional",
            "subcategory":"Management & Consulting",
            "type":"Services"
        }
    ],
    "sg:phone":"+1   ",
    "sg:postcode":"60201",
    "sg:province":"IL",
    "sg:tags":[
        "retail",
        "direct",
        "sales"
    ],
    "wof:name":"Sodexho Services Sports Center",
    "wof:placetype":"venue"
},
  "geometry": {"coordinates":[-87.692334,42.064331],"type":"Point"}
}