{
  "type": "Feature",
  "properties": {
    "addr:full":"5106 S Western Ave Chicago IL 60609",
    "addr:housenumber":"5106",
    "addr:postcode":"60609",
    "addr:street":"S Western Ave",
    "iso:country":"US",
    "sg:address":"5106 S Western Ave",
    "sg:city":"Chicago",
    "sg:classifiers":[
        {
            "category":"Health Services",
            "subcategory":"Clinic",
            "type":"Services"
        }
    ],
    "sg:phone":"+1 773 778 3303",
    "sg:postcode":"60609",
    "sg:province":"IL",
    "sg:tags":[
        "counseling",
        "mental"
    ],
    "wof:name":"PHD Healthcare",
    "wof:placetype":"venue"
},
  "geometry": {"coordinates":[-87.684303,41.8008],"type":"Point"}
}