{
  "type": "Feature",
  "properties": {
    "iso:country":"US",
    "sg:address":"2827 18th Ave",
    "sg:city":"Rock Island",
    "sg:classifiers":[
        {
            "category":"Autos & Motor Vehicles",
            "subcategory":"Fuel & Gas Station",
            "type":"Retail Goods"
        }
    ],
    "sg:phone":"+1 309 786 4747",
    "sg:postcode":"61201",
    "sg:province":"IL",
    "sg:tags":[
        "repair",
        "station",
        "oil",
        "gasoline",
        "general"
    ],
    "wof:name":"Walt's Citgo",
    "wof:placetype":"venue"
},
  "geometry": {"coordinates":[-90.559967,41.493494],"type":"Point"}
}