{
  "type": "Feature",
  "properties": {
    "addr:full":"9319 Gulfstream Rd Frankfort IL 60423",
    "addr:housenumber":"9319",
    "addr:postcode":"60423",
    "addr:street":"Gulfstream Rd",
    "iso:country":"US",
    "sg:address":"9319 Gulfstream Rd",
    "sg:city":"Frankfort",
    "sg:classifiers":[
        {
            "category":"Professional",
            "subcategory":"Management & Consulting",
            "type":"Services"
        }
    ],
    "sg:phone":"+1 815 464 0200",
    "sg:postcode":"60423",
    "sg:province":"IL",
    "sg:tags":[
        "consultant",
        "safety"
    ],
    "sg:website":"www.safetymeetingoutlines.com",
    "wof:name":"Safety Meeeting Outlines Inc",
    "wof:placetype":"venue"
},
  "geometry": {"coordinates":[-87.84297599999999,41.474458],"type":"Point"}
}