{
  "type": "Feature",
  "properties": {
    "addr:full":"9834 S Kedzie Ave Evergreen Park IL 60805",
    "addr:housenumber":"9834",
    "addr:postcode":"60805",
    "addr:street":"S Kedzie Ave",
    "iso:country":"US",
    "sg:address":"9834 S Kedzie Ave",
    "sg:city":"Evergreen Park",
    "sg:classifiers":[
        {
            "category":"Shopping",
            "type":"Retail Goods"
        }
    ],
    "sg:phone":"+1 708 425 0073",
    "sg:postcode":"60805",
    "sg:province":"IL",
    "sg:tags":[
        "plastic"
    ],
    "wof:name":"Florida Plastic Intl",
    "wof:placetype":"venue"
},
  "geometry": {"coordinates":[-87.701711,41.714476],"type":"Point"}
}