{
  "type": "Feature",
  "properties": {
    "addr:full":"1241 Jarvis Ave Elk Grove Village IL 60007",
    "addr:housenumber":"1241",
    "addr:postcode":"60007",
    "addr:street":"Jarvis Ave",
    "iso:country":"US",
    "sg:address":"1241 Jarvis Ave",
    "sg:city":"Elk Grove Village",
    "sg:classifiers":[
        {
            "category":"Wholesale",
            "subcategory":"Machinery & Supplies",
            "type":"Manufacturing & Wholesale Goods"
        }
    ],
    "sg:phone":"+1 847 593 5771",
    "sg:postcode":"60007",
    "sg:province":"IL",
    "sg:tags":[
        "warehouse",
        "industrial",
        "clutches",
        "sales",
        "for"
    ],
    "wof:name":"Matrix International Limited",
    "wof:placetype":"venue"
},
  "geometry": {"coordinates":[-87.960081,42.013178],"type":"Point"}
}