{
  "type": "Feature",
  "properties": {
    "iso:country":"US",
    "sg:address":"401 Chaffer Ave",
    "sg:city":"Roxana",
    "sg:classifiers":[
        {
            "category":"Education",
            "subcategory":"School",
            "type":"Public Place"
        }
    ],
    "sg:phone":"+1 618 254 7544",
    "sg:postcode":"62084",
    "sg:province":"IL",
    "sg:tags":[
        "management"
    ],
    "wof:name":"Roxana Cmnty Unit Schl Dst 1",
    "wof:placetype":"venue"
},
  "geometry": {"coordinates":[-90.076728,38.852377],"type":"Point"}
}