{
  "type": "Feature",
  "properties": {
    "iso:country":"US",
    "sg:address":"555 Old Mill Grove Rd",
    "sg:city":"Lake Zurich",
    "sg:classifiers":[
        {
            "category":"Education",
            "subcategory":"School",
            "type":"Public Place"
        }
    ],
    "sg:phone":"+1 847 438 5986",
    "sg:postcode":"60047",
    "sg:province":"IL",
    "wof:name":"Sarah Adams Elementary School",
    "wof:placetype":"venue"
},
  "geometry": {"coordinates":[-88.072606,42.186862],"type":"Point"}
}