{
  "type": "Feature",
  "properties": {
    "addr:full":"555 Old Mill Grove Rd Lake Zurich IL 60047",
    "addr:housenumber":"555",
    "addr:postcode":"60047",
    "addr:street":"Old Mill Grove Rd",
    "iso:country":"US",
    "sg:address":"555 Old Mill Grove Rd",
    "sg:city":"Lake Zurich",
    "sg:classifiers":[
        {
            "category":"Education",
            "subcategory":"School",
            "type":"Public Place"
        }
    ],
    "sg:phone":"+1 847 438 5986",
    "sg:postcode":"60047",
    "sg:province":"IL",
    "wof:name":"Sarah Adams Elementary School",
    "wof:placetype":"venue"
},
  "geometry": {"coordinates":[-88.07260599999999,42.186862],"type":"Point"}
}