{
  "type": "Feature",
  "properties": {
    "iso:country":"US",
    "sg:address":"195 N Harbor Drive",
    "sg:city":"Chicago",
    "sg:classifiers":[
        {
            "category":"Health Services",
            "subcategory":"Doctor",
            "type":"Services"
        }
    ],
    "sg:phone":"+1 312 616 7778",
    "sg:postcode":"60601",
    "sg:province":"IL",
    "sg:tags":[
        "medicine",
        "sport"
    ],
    "wof:name":"Natarajan Balu MD Sc",
    "wof:placetype":"venue"
},
  "geometry": {"coordinates":[-87.61573799999999,41.885759],"type":"Point"}
}