{
  "type": "Feature",
  "properties": {
    "iso:country":"US",
    "sg:address":"8460 S 77th Ave",
    "sg:city":"Bridgeview",
    "sg:classifiers":[
        {
            "category":"Building & Trades",
            "subcategory":"Construction",
            "type":"Services"
        }
    ],
    "sg:phone":"+1 708 599 6994",
    "sg:postcode":"60455",
    "sg:province":"IL",
    "sg:tags":[
        "carpentry",
        "contractor"
    ],
    "wof:name":"Majestic Carpenter Contractors",
    "wof:placetype":"venue"
},
  "geometry": {"coordinates":[-87.811521,41.737494],"type":"Point"}
}