{
  "type": "Feature",
  "properties": {
    "addr:full":"5505 E State St Rockford IL 61108",
    "addr:housenumber":"5505",
    "addr:postcode":"61108",
    "addr:street":"E State St",
    "iso:country":"US",
    "sg:address":"5505 E State St",
    "sg:city":"Rockford",
    "sg:classifiers":[
        {
            "category":"Shopping",
            "subcategory":"Department Store",
            "type":"Retail Goods"
        }
    ],
    "sg:phone":"+1 815 395 0396",
    "sg:postcode":"61108",
    "sg:province":"IL",
    "sg:tags":[
        "shop"
    ],
    "wof:name":"Deals-Nothing Over A Dollar",
    "wof:placetype":"venue"
},
  "geometry": {"coordinates":[-89.008308,42.265496],"type":"Point"}
}