{
  "type": "Feature",
  "properties": {
    "addr:full":"2215 Oak Ln Rolling Meadows IL 60008",
    "addr:housenumber":"2215",
    "addr:postcode":"60008",
    "addr:street":"Oak Ln",
    "iso:country":"US",
    "sg:address":"2215 Oak Ln",
    "sg:city":"Rolling Meadows",
    "sg:classifiers":[
        {
            "category":"Building & Trades",
            "subcategory":"Construction",
            "type":"Services"
        }
    ],
    "sg:phone":"+1 847 815 8747",
    "sg:postcode":"60008",
    "sg:province":"IL",
    "sg:tags":[
        "residential"
    ],
    "wof:name":"Northwest Sliding Inc",
    "wof:placetype":"venue"
},
  "geometry": {"coordinates":[-88.009837,42.063761],"type":"Point"}
}