{
  "type": "Feature",
  "properties": {
    "iso:country":"US",
    "sg:address":"5700 S Cicero Ave",
    "sg:city":"Chicago",
    "sg:classifiers":[
        {
            "category":"Home & Garden",
            "subcategory":"Building Materials",
            "type":"Retail Goods"
        },
        {
            "category":"Building & Trades",
            "subcategory":"Construction",
            "type":"Services"
        }
    ],
    "sg:phone":"+1 773 735 7725",
    "sg:postcode":"60638",
    "sg:province":"IL",
    "sg:tags":[
        "industrial",
        "asphalt",
        "contractors-commercial",
        "contractor",
        "concrete",
        "sealcoating",
        "staining",
        "masonry",
        "road",
        "paving"
    ],
    "wof:name":"Metro Paving",
    "wof:placetype":"venue"
},
  "geometry": {"coordinates":[-87.74141899999999,41.785893],"type":"Point"}
}