{
  "type": "Feature",
  "properties": {
    "iso:country":"US",
    "sg:address":"3565 Dredge Rd",
    "sg:city":"Paw Paw",
    "sg:phone":"+1 815 627 9418",
    "sg:postcode":"61353",
    "sg:province":"IL",
    "sg:tags":[
        "farm",
        "grain",
        "long",
        "trucking"
    ],
    "wof:name":"R R Schoenholz",
    "wof:placetype":"venue"
},
  "geometry": {"coordinates":[-88.980586,41.707273],"type":"Point"}
}