{
  "type": "Feature",
  "properties": {
    "iso:country":"US",
    "sg:address":"120 N East St",
    "sg:city":"Cambridge",
    "sg:classifiers":[
        {
            "category":"Shopping",
            "subcategory":"Hobbies, Toys, & Games",
            "type":"Retail Goods"
        },
        {
            "category":"Shopping",
            "subcategory":"Antiques",
            "type":"Retail Goods"
        },
        {
            "category":"Shopping",
            "subcategory":"Gifts & Souvenirs",
            "type":"Retail Goods"
        }
    ],
    "sg:phone":"+1 309 937 5150",
    "sg:postcode":"61238",
    "sg:province":"IL",
    "sg:tags":[
        "shop",
        "hobby",
        "model",
        "coin",
        "supply"
    ],
    "wof:name":"Midwest Coinarama",
    "wof:placetype":"venue"
},
  "geometry": {"coordinates":[-90.19453900000001,41.302946],"type":"Point"}
}