{
  "type": "Feature",
  "properties": {
    "addr:full":"4629 W Cermak Rd Cicero IL 60804",
    "addr:housenumber":"4629",
    "addr:postcode":"60804",
    "addr:street":"W Cermak Rd",
    "iso:country":"US",
    "sg:address":"4629 W Cermak Rd",
    "sg:city":"Cicero",
    "sg:classifiers":[
        {
            "category":"Shopping",
            "subcategory":"Bicycles & Sporting Goods",
            "type":"Retail Goods"
        }
    ],
    "sg:phone":"+1 708 652 6791",
    "sg:postcode":"60804",
    "sg:province":"IL",
    "wof:name":"Foot Locker",
    "wof:placetype":"venue"
},
  "geometry": {"coordinates":[-87.740601,41.851101],"type":"Point"}
}