{
  "type": "Feature",
  "properties": {
    "iso:country":"US",
    "sg:address":"1907 Central St",
    "sg:city":"Evanston",
    "sg:classifiers":[
        {
            "category":"Home & Garden",
            "subcategory":"Carpets & Floor Coverings",
            "type":"Retail Goods"
        }
    ],
    "sg:phone":"+1   ",
    "sg:postcode":"60201",
    "sg:province":"IL",
    "wof:name":"Rouzati Oriental Rugs Inc",
    "wof:placetype":"venue"
},
  "geometry": {"coordinates":[-87.699553,42.064414],"type":"Point"}
}