{
  "type": "Feature",
  "properties": {
    "addr:full":"Burnham Harbor 1500 SE Lake Shore Dr Chicago IL 60638",
    "addr:housenumber":"1500",
    "addr:postcode":"60638",
    "addr:street":"Se Lake Shore Dr",
    "iso:country":"US",
    "sg:address":"Burnham Harbor 1500 SE Lake Shore Dr",
    "sg:city":"Chicago",
    "sg:classifiers":[
        {
            "category":"Recreation",
            "subcategory":"Boat Charter",
            "type":"Entertainment"
        },
        {
            "category":"Marine",
            "type":"Transportation"
        },
        {
            "category":"Landmark",
            "subcategory":"Tourist Information",
            "type":"Public Place"
        }
    ],
    "sg:phone":"+1 773 788 9494",
    "sg:postcode":"60638",
    "sg:province":"IL",
    "sg:tags":[
        "boating",
        "tour",
        "tours-operators",
        "promoter",
        "watercraft-personal-renting"
    ],
    "sg:website":"www.valara.com",
    "wof:name":"Adventure Sea Tours",
    "wof:placetype":"venue"
},
  "geometry": {"coordinates":[-87.79625799999999,41.786269],"type":"Point"}
}