{
  "type": "Feature",
  "properties": {
    "iso:country":"US",
    "sg:address":"253 W Broadway St",
    "sg:city":"Bradley",
    "sg:classifiers":[
        {
            "category":"Professional",
            "subcategory":"Accounting & Tax Preparation",
            "type":"Services"
        }
    ],
    "sg:phone":"+1 815 939 0016",
    "sg:postcode":"60915",
    "sg:province":"IL",
    "sg:tags":[
        "accountant"
    ],
    "wof:name":"Charles R Burke CPA & Assoc",
    "wof:placetype":"venue"
},
  "geometry": {"coordinates":[-87.864278,41.142374],"type":"Point"}
}