{
  "type": "Feature",
  "properties": {
    "iso:country":"US",
    "sg:address":"172 S Berkley Ave",
    "sg:city":"Elmhurst",
    "sg:classifiers":[
        {
            "category":"Professional",
            "subcategory":"Lawyer & Legal Services",
            "type":"Services"
        }
    ],
    "sg:phone":"+1 630 279 6903",
    "sg:postcode":"60126",
    "sg:province":"IL",
    "sg:tags":[
        "attorney",
        "wills",
        "practice",
        "planning",
        "plan",
        "real estate",
        "trust"
    ],
    "wof:name":"Law Offices Of Ralph Tellefsen Iii",
    "wof:placetype":"venue"
},
  "geometry": {"coordinates":[-87.954459,41.896013],"type":"Point"}
}