{
  "type": "Feature",
  "properties": {
    "addr:full":"3815 N Ventura Dr Arlington Hts IL 60004",
    "addr:housenumber":"3815",
    "addr:postcode":"60004",
    "addr:street":"N Ventura Dr",
    "iso:country":"US",
    "sg:address":"3815 N Ventura Dr",
    "sg:city":"Arlington Hts",
    "sg:classifiers":[
        {
            "category":"Wholesale",
            "subcategory":"Machinery & Supplies",
            "type":"Manufacturing & Wholesale Goods"
        },
        {
            "category":"Manufacturing",
            "subcategory":"Tools & Machinery",
            "type":"Manufacturing & Wholesale Goods"
        }
    ],
    "sg:phone":"+1 847 398 5757",
    "sg:postcode":"60004",
    "sg:province":"IL",
    "sg:tags":[
        "conveying",
        "mfg",
        "conveyor",
        "system",
        "equipment",
        "carrier"
    ],
    "sg:website":"www.dynapace.com",
    "wof:name":"Dynapace Corp",
    "wof:placetype":"venue"
},
  "geometry": {"coordinates":[-88.000658,42.144011],"type":"Point"}
}