{
  "type": "Feature",
  "properties": {
    "addr:full":"5140 N California Ave Chicago IL 60625",
    "addr:housenumber":"5140",
    "addr:postcode":"60625",
    "addr:street":"N California Ave",
    "iso:country":"US",
    "sg:address":"5140 N California Ave",
    "sg:city":"Chicago",
    "sg:classifiers":[
        {
            "category":"Health Services",
            "subcategory":"Doctor",
            "type":"Services"
        }
    ],
    "sg:phone":"+1 847 869 1400",
    "sg:postcode":"60625",
    "sg:province":"IL",
    "wof:name":"Dr. Sylvia Duby",
    "wof:placetype":"venue"
},
  "geometry": {"coordinates":[-87.69889999999999,41.974967],"type":"Point"}
}