{
  "type": "Feature",
  "properties": {
    "addr:full":"415 N Milwaukee Ave Chicago IL 60654",
    "addr:housenumber":"415",
    "addr:postcode":"60654",
    "addr:street":"N Milwaukee Ave",
    "iso:country":"US",
    "sg:address":"415 N Milwaukee Ave",
    "sg:city":"Chicago",
    "sg:classifiers":[
        {
            "category":"Fast Food",
            "type":"Food & Drink"
        },
        {
            "category":"Restaurant",
            "type":"Food & Drink"
        }
    ],
    "sg:phone":"+1 312 829 6300",
    "sg:postcode":"60654",
    "sg:province":"IL",
    "sg:tags":[
        "burger",
        "american",
        "new"
    ],
    "sg:website":"www.paramountroom.com",
    "wof:name":"Paramount Room",
    "wof:placetype":"venue"
},
  "geometry": {"coordinates":[-87.64482099999999,41.889629],"type":"Point"}
}