{
  "type": "Feature",
  "properties": {
    "iso:country":"US",
    "sg:address":"1734 Elmhurst Rd",
    "sg:city":"Elk Grove Vlg",
    "sg:classifiers":[
        {
            "category":"Manufacturing",
            "subcategory":"Electronics",
            "type":"Manufacturing & Wholesale Goods"
        }
    ],
    "sg:phone":"+1 847 437 2299",
    "sg:postcode":"60007",
    "sg:province":"IL",
    "sg:tags":[
        "assembly",
        "boards",
        "supply",
        "equipment",
        "printed",
        "circuit",
        "electronic"
    ],
    "wof:name":"Buildex Electronics Inc",
    "wof:placetype":"venue"
},
  "geometry": {"coordinates":[-87.940177,42.000969],"type":"Point"}
}