{
  "type": "Feature",
  "properties": {
    "iso:country":"US",
    "sg:address":"200 Hughes Ave",
    "sg:city":"Lockport",
    "sg:classifiers":[
        {
            "category":"Retail",
            "subcategory":"Animal Services",
            "type":"Services"
        }
    ],
    "sg:phone":"+1 815 353 4044",
    "sg:postcode":"60441",
    "sg:province":"IL",
    "sg:tags":[
        "pet",
        "exercising",
        "sitting"
    ],
    "wof:name":"A Picture Perfect Pup",
    "wof:placetype":"venue"
},
  "geometry": {"coordinates":[-88.06616200000001,41.570438],"type":"Point"}
}