{
  "type": "Feature",
  "properties": {
    "iso:country":"US",
    "sg:address":"984 N Lake St",
    "sg:city":"Aurora",
    "sg:classifiers":[
        {
            "category":"Building & Trades",
            "subcategory":"Equipment Rental",
            "type":"Services"
        }
    ],
    "sg:phone":"+1 630 966 1100",
    "sg:postcode":"60506",
    "sg:province":"IL",
    "sg:tags":[
        "yard"
    ],
    "wof:name":"Color Tyme",
    "wof:placetype":"venue"
},
  "geometry": {"coordinates":[-88.31569500000001,41.778451],"type":"Point"}
}