{
  "type": "Feature",
  "properties": {
    "iso:country":"US",
    "sg:address":"800 Higgins Rd",
    "sg:city":"Park Ridge",
    "sg:classifiers":[
        {
            "category":"Health Services",
            "subcategory":"Dentist",
            "type":"Services"
        }
    ],
    "sg:phone":"+1 847 318 6358",
    "sg:postcode":"60068",
    "sg:province":"IL",
    "wof:name":"Ridge Dental Care",
    "wof:placetype":"venue"
},
  "geometry": {"coordinates":[-87.841499,41.987202],"type":"Point"}
}