{
  "type": "Feature",
  "properties": {
    "iso:country":"US",
    "sg:address":"103 E Winslow Ave",
    "sg:city":"Danvers",
    "sg:classifiers":[
        {
            "category":"Insurance",
            "subcategory":"Insurance Agent",
            "type":"Services"
        }
    ],
    "sg:phone":"+1 309 963 4764",
    "sg:postcode":"61732",
    "sg:province":"IL",
    "wof:name":"Sparks Miller Insurance",
    "wof:placetype":"venue"
},
  "geometry": {"coordinates":[-89.17646000000001,40.531922],"type":"Point"}
}