{
  "type": "Feature",
  "properties": {
    "addr:full":"14045 S Cleveland Ave Posen IL 60469",
    "addr:housenumber":"14045",
    "addr:postcode":"60469",
    "addr:street":"S Cleveland Ave",
    "iso:country":"US",
    "sg:address":"14045 S Cleveland Ave",
    "sg:city":"Posen",
    "sg:classifiers":[
        {
            "category":"Building & Trades",
            "subcategory":"Construction",
            "type":"Services"
        }
    ],
    "sg:phone":"+1 708 389 3030",
    "sg:postcode":"60469",
    "sg:province":"IL",
    "sg:tags":[
        "contractor"
    ],
    "wof:name":"Roof Right Roofing & Insulating",
    "wof:placetype":"venue"
},
  "geometry": {"coordinates":[-87.686401,41.638302],"type":"Point"}
}