{
  "type": "Feature",
  "properties": {
    "iso:country":"US",
    "sg:address":"525 E Burnett Rd",
    "sg:city":"Island Lake",
    "sg:classifiers":[
        {
            "category":"Professional",
            "type":"Services"
        }
    ],
    "sg:phone":"+1 847 487 8398",
    "sg:postcode":"60042",
    "sg:province":"IL",
    "wof:name":"Krystals Kleaning Service",
    "wof:placetype":"venue"
},
  "geometry": {"coordinates":[-88.190197,42.284887],"type":"Point"}
}