{
  "type": "Feature",
  "properties": {
    "iso:country":"US",
    "sg:address":"921 Adams St",
    "sg:city":"Maywood",
    "sg:classifiers":[
        {
            "category":"Travel",
            "subcategory":"Travel Agent",
            "type":"Entertainment"
        }
    ],
    "sg:phone":"+1 708 345 7953",
    "sg:postcode":"60153",
    "sg:province":"IL",
    "sg:tags":[
        "agency",
        "services-commercial"
    ],
    "wof:name":"Floyds Fun N Travel Inc.",
    "wof:placetype":"venue"
},
  "geometry": {"coordinates":[-87.843902,41.875219],"type":"Point"}
}