{
  "type": "Feature",
  "properties": {
    "iso:country":"US",
    "sg:address":"910 2nd Ave",
    "sg:city":"Rockford",
    "sg:classifiers":[
        {
            "category":"Professional",
            "subcategory":"Lawyer & Legal Services",
            "type":"Services"
        }
    ],
    "sg:phone":"+1 815 968 7200",
    "sg:postcode":"61104",
    "sg:province":"IL",
    "sg:tags":[
        "attorney",
        "law",
        "family",
        "corporation",
        "wills",
        "partnership",
        "planning",
        "real estate",
        "trust"
    ],
    "sg:website":"http://www.canfieldlaw.com",
    "wof:name":"Canfield Robert E & Assocs",
    "wof:placetype":"venue"
},
  "geometry": {"coordinates":[-89.083547,42.26476],"type":"Point"}
}