{
  "type": "Feature",
  "properties": {
    "iso:country":"US",
    "sg:address":"3539 Adler Ct",
    "sg:city":"Belleville",
    "sg:classifiers":[
        {
            "category":"Building & Trades",
            "subcategory":"Plumbing",
            "type":"Services"
        }
    ],
    "sg:phone":"+1 618 416 1430",
    "sg:postcode":"62221",
    "sg:province":"IL",
    "sg:tags":[
        "plumber"
    ],
    "wof:name":"Champion Plumbing Company, Inc.",
    "wof:placetype":"venue"
},
  "geometry": {"coordinates":[-89.921403,38.549933],"type":"Point"}
}