{
  "type": "Feature",
  "properties": {
    "iso:country":"US",
    "sg:address":"3567 Grand Ave Ste B",
    "sg:city":"Gurnee",
    "sg:classifiers":[
        {
            "category":"Home & Garden",
            "subcategory":"Carpets & Floor Coverings",
            "type":"Retail Goods"
        }
    ],
    "sg:phone":"+1 847 838 0278",
    "sg:postcode":"60031",
    "sg:province":"IL",
    "sg:tags":[
        "dyer",
        "rug"
    ],
    "wof:name":"On The Spot Carpet Dyeing Inc",
    "wof:placetype":"venue"
},
  "geometry": {"coordinates":[-87.888442,42.370583],"type":"Point"}
}