{
  "type": "Feature",
  "properties": {
    "addr:full":"146 N Addison Ave Elmhurst IL 60126",
    "addr:housenumber":"146",
    "addr:postcode":"60126",
    "addr:street":"N Addison Ave",
    "iso:country":"US",
    "sg:address":"146 N Addison Ave",
    "sg:city":"Elmhurst",
    "sg:classifiers":[
        {
            "category":"Personal",
            "subcategory":"Beauty Salon",
            "type":"Services"
        }
    ],
    "sg:phone":"+1 630 279 8827",
    "sg:postcode":"60126",
    "sg:province":"IL",
    "sg:tags":[
        "shop"
    ],
    "wof:name":"Touch of Class",
    "wof:placetype":"venue"
},
  "geometry": {"coordinates":[-87.94170699999999,41.900351],"type":"Point"}
}