{
  "type": "Feature",
  "properties": {
    "addr:full":"830 Main St Meredosia IL 62665",
    "addr:housenumber":"830",
    "addr:postcode":"62665",
    "addr:street":"Main St",
    "iso:country":"US",
    "sg:address":"830 Main St",
    "sg:city":"Meredosia",
    "sg:classifiers":[
        {
            "category":"Education",
            "subcategory":"Special Training",
            "type":"Public Place"
        }
    ],
    "sg:phone":"+1 217 584 1741",
    "sg:postcode":"62665",
    "sg:province":"IL",
    "sg:tags":[
        "educational"
    ],
    "wof:name":"Meredosia-Chambersburg Unit Schools Junior & Senior High School Meredosia",
    "wof:placetype":"venue"
},
  "geometry": {"coordinates":[-90.554221,39.830702],"type":"Point"}
}