{
  "type": "Feature",
  "properties": {
    "iso:country":"US",
    "sg:address":"1401 25th Ave",
    "sg:city":"Moline",
    "sg:classifiers":[
        {
            "category":"Autos & Motor Vehicles",
            "subcategory":"Fuel & Gas Station",
            "type":"Retail Goods"
        }
    ],
    "sg:phone":"+1   ",
    "sg:postcode":"61265",
    "sg:province":"IL",
    "sg:tags":[
        "repair",
        "station",
        "gasoline",
        "general"
    ],
    "wof:name":"Forest Hill Service",
    "wof:placetype":"venue"
},
  "geometry": {"coordinates":[-90.515869,41.487424],"type":"Point"}
}