{
  "type": "Feature",
  "properties": {
    "iso:country":"US",
    "sg:address":"517 E Norris Dr",
    "sg:city":"Ottawa",
    "sg:classifiers":[
        {
            "category":"Restaurant",
            "type":"Food & Drink"
        }
    ],
    "sg:phone":"+1 815 433 3388",
    "sg:postcode":"61350",
    "sg:province":"IL",
    "wof:name":"Tai Jiang Restaurant",
    "wof:placetype":"venue"
},
  "geometry": {"coordinates":[-88.834754,41.356176],"type":"Point"}
}