{
  "type": "Feature",
  "properties": {
    "addr:full":"1020 W Riverside Blvd Rockford IL 61103",
    "addr:housenumber":"1020",
    "addr:postcode":"61103",
    "addr:street":"W Riverside Blvd",
    "iso:country":"US",
    "sg:address":"1020 W Riverside Blvd",
    "sg:city":"Rockford",
    "sg:classifiers":[
        {
            "category":"Recreation",
            "type":"Entertainment"
        }
    ],
    "sg:phone":"+1 815 639 9360",
    "sg:postcode":"61103",
    "sg:province":"IL",
    "wof:name":"Excel Academy",
    "wof:placetype":"venue"
},
  "geometry": {"coordinates":[-89.076972,42.315675],"type":"Point"}
}