{
  "type": "Feature",
  "properties": {
    "iso:country":"US",
    "sg:address":"8830 Harvest Hills Trl",
    "sg:city":"Rockford",
    "sg:classifiers":[
        {
            "category":"Professional",
            "subcategory":"Business Services",
            "type":"Services"
        }
    ],
    "sg:phone":"+1 815 914 9553",
    "sg:postcode":"61114",
    "sg:province":"IL",
    "wof:name":"Mile High Solutions",
    "wof:placetype":"venue"
},
  "geometry": {"coordinates":[-88.941627,42.316518],"type":"Point"}
}