{
  "type": "Feature",
  "properties": {
    "iso:country":"US",
    "sg:address":"103 N Prospect St",
    "sg:city":"Cambridge",
    "sg:classifiers":[
        {
            "category":"Personal",
            "subcategory":"Barber",
            "type":"Services"
        }
    ],
    "sg:phone":"+1 309 937 5894",
    "sg:postcode":"61238",
    "sg:province":"IL",
    "wof:name":"Humphrey's Barber Shop",
    "wof:placetype":"venue"
},
  "geometry": {"coordinates":[-90.19279,41.303855],"type":"Point"}
}