{
  "type": "Feature",
  "properties": {
    "iso:country":"US",
    "sg:address":"2307 Union School Rd",
    "sg:city":"Alton",
    "sg:classifiers":[
        {
            "category":"Organizations",
            "subcategory":"Religious Organization",
            "type":"Services"
        }
    ],
    "sg:phone":"+1 618 463 1425",
    "sg:postcode":"62002",
    "sg:province":"IL",
    "sg:tags":[
        "church"
    ],
    "wof:name":"Jehovah's Witnesses",
    "wof:placetype":"venue"
},
  "geometry": {"coordinates":[-90.15231900000001,38.937299],"type":"Point"}
}