{
  "type": "Feature",
  "properties": {
    "addr:full":"2333 N Seeley Ave Chicago IL 60647",
    "addr:housenumber":"2333",
    "addr:postcode":"60647",
    "addr:street":"N Seeley Ave",
    "iso:country":"US",
    "sg:address":"2333 N Seeley Ave",
    "sg:city":"Chicago",
    "sg:classifiers":[
        {
            "category":"Building & Trades",
            "subcategory":"Construction",
            "type":"Services"
        }
    ],
    "sg:phone":"+1 773 486 8844",
    "sg:postcode":"60647",
    "sg:province":"IL",
    "sg:tags":[
        "commercial"
    ],
    "wof:name":"Wilco Construction Spc Ltd",
    "wof:placetype":"venue"
},
  "geometry": {"coordinates":[-87.679017,41.924154],"type":"Point"}
}