{
  "type": "Feature",
  "properties": {
    "addr:full":"Corner of 44th & Maplewood Chicago IL 60632",
    "addr:postcode":"60632",
    "addr:street":"Corner",
    "iso:country":"US",
    "sg:address":"Corner of 44th & Maplewood",
    "sg:city":"Chicago",
    "sg:classifiers":[
        {
            "category":"Food & Beverages",
            "subcategory":"Meat & Fish",
            "type":"Retail Goods"
        }
    ],
    "sg:postcode":"60632",
    "sg:province":"IL",
    "sg:tags":[
        "hot",
        "dog"
    ],
    "wof:name":"John's Hot Dog's",
    "wof:placetype":"venue"
},
  "geometry": {"coordinates":[-87.68822,41.813727],"type":"Point"}
}