{
  "type": "Feature",
  "properties": {
    "addr:full":"700 E Grand Ave Navy Pier Chicago IL 60611",
    "addr:housenumber":"700",
    "addr:postcode":"60611",
    "addr:street":"E Grand Ave Navy Pier",
    "iso:country":"US",
    "sg:address":"700 E Grand Ave Navy Pier",
    "sg:city":"Chicago",
    "sg:classifiers":[
        {
            "category":"Bakery",
            "type":"Food & Drink"
        }
    ],
    "sg:phone":"+1 312 595 7437",
    "sg:postcode":"60611",
    "sg:province":"IL",
    "wof:name":"Ryba's Fudge Shops",
    "wof:placetype":"venue"
},
  "geometry": {"coordinates":[-87.609994,41.892332],"type":"Point"}
}