{
  "type": "Feature",
  "properties": {
    "addr:full":"4216 W Cermak Road Chicago IL 60623",
    "addr:housenumber":"4216",
    "addr:postcode":"60623",
    "addr:street":"W Cermak Road",
    "iso:country":"US",
    "sg:address":"4216 W Cermak Road",
    "sg:city":"Chicago",
    "sg:classifiers":[
        {
            "category":"Restaurant",
            "type":"Food & Drink"
        }
    ],
    "sg:phone":"+1 773 277 9700",
    "sg:postcode":"60623",
    "sg:province":"IL",
    "wof:name":"Dj's Sub #3",
    "wof:placetype":"venue"
},
  "geometry": {"coordinates":[-87.730236,41.851576],"type":"Point"}
}