{
  "type": "Feature",
  "properties": {
    "addr:full":"10208 Smythe Ave Machesney Park IL 61115",
    "addr:housenumber":"10208",
    "addr:postcode":"61115",
    "addr:street":"Smythe Ave",
    "iso:country":"US",
    "sg:address":"10208 Smythe Ave",
    "sg:city":"Machesney Park",
    "sg:classifiers":[
        {
            "category":"Retail",
            "subcategory":"Repair Shop",
            "type":"Services"
        }
    ],
    "sg:phone":"+1 815 633 9868",
    "sg:postcode":"61115",
    "sg:province":"IL",
    "wof:name":"Cantus Upholstery",
    "wof:placetype":"venue"
},
  "geometry": {"coordinates":[-89.039196,42.367281],"type":"Point"}
}