{
  "type": "Feature",
  "properties": {
    "iso:country":"US",
    "sg:address":"8605 Major Ave",
    "sg:city":"Bedford Park",
    "sg:classifiers":[
        {
            "category":"Building & Trades",
            "subcategory":"Construction",
            "type":"Services"
        }
    ],
    "sg:phone":"+1 708 425 1051",
    "sg:postcode":"60459",
    "sg:province":"IL",
    "sg:tags":[
        "house"
    ],
    "wof:name":"S & J Stuculla Construction",
    "wof:placetype":"venue"
},
  "geometry": {"coordinates":[-87.762638,41.734701],"type":"Point"}
}