{
  "type": "Feature",
  "properties": {
    "iso:country":"US",
    "sg:address":"766 N Gary Ave",
    "sg:city":"Carol Stream",
    "sg:classifiers":[
        {
            "category":"Building & Trades",
            "subcategory":"Construction",
            "type":"Services"
        }
    ],
    "sg:phone":"+1 630 440 6741",
    "sg:postcode":"60188",
    "sg:province":"IL",
    "sg:tags":[
        "hanging",
        "contractor"
    ],
    "wof:name":"Zur Tomasz Painting",
    "wof:placetype":"venue"
},
  "geometry": {"coordinates":[-88.120627,41.923323],"type":"Point"}
}