{
  "type": "Feature",
  "properties": {
    "addr:full":"10643 S Fairfield Ave Chicago IL 60655",
    "addr:housenumber":"10643",
    "addr:postcode":"60655",
    "addr:street":"S Fairfield Ave",
    "iso:country":"US",
    "sg:address":"10643 S Fairfield Ave",
    "sg:city":"Chicago",
    "sg:classifiers":[
        {
            "category":"Professional",
            "subcategory":"Business Services",
            "type":"Services"
        }
    ],
    "sg:phone":"+1 773 445 6400",
    "sg:postcode":"60655",
    "sg:province":"IL",
    "wof:name":"Execprotect Inc",
    "wof:placetype":"venue"
},
  "geometry": {"coordinates":[-87.689559,41.700244],"type":"Point"}
}