{
  "type": "Feature",
  "properties": {
    "addr:full":"2 W Harrison St Sullivan IL 61951",
    "addr:housenumber":"2",
    "addr:postcode":"61951",
    "addr:street":"W Harrison St",
    "iso:country":"US",
    "sg:address":"2 W Harrison St",
    "sg:city":"Sullivan",
    "sg:classifiers":[
        {
            "category":"Government",
            "subcategory":"City Hall",
            "type":"Public Place"
        },
        {
            "category":"Government",
            "subcategory":"Office",
            "type":"Public Place"
        }
    ],
    "sg:phone":"+1 217 728 4383",
    "sg:postcode":"61951",
    "sg:province":"IL",
    "sg:tags":[
        "town",
        "township",
        "planner",
        "government-city",
        "village"
    ],
    "wof:name":"Sullivan City Hall",
    "wof:placetype":"venue"
},
  "geometry": {"coordinates":[-88.60745199999999,39.59938],"type":"Point"}
}