{
  "type": "Feature",
  "properties": {
    "iso:country":"US",
    "sg:address":"1435 W 87th St",
    "sg:city":"Chicago",
    "sg:classifiers":[
        {
            "category":"Banks & Credit Unions",
            "subcategory":"Bureau De Change",
            "type":"Services"
        }
    ],
    "sg:phone":"+1 773 779 8282",
    "sg:postcode":"60620",
    "sg:province":"IL",
    "sg:tags":[
        "currency",
        "exchange",
        "broker",
        "foreign"
    ],
    "wof:name":"R Crowe",
    "wof:placetype":"venue"
},
  "geometry": {"coordinates":[-87.659453,41.735839],"type":"Point"}
}