{
  "type": "Feature",
  "properties": {
    "iso:country":"US",
    "sg:address":"5192 Harrison Ave",
    "sg:city":"Rockford",
    "sg:classifiers":[
        {
            "category":"Banks & Credit Unions",
            "subcategory":"Investment Brokerage",
            "type":"Services"
        }
    ],
    "sg:phone":"+1 815 395 6503",
    "sg:postcode":"61108",
    "sg:province":"IL",
    "sg:tags":[
        "consultant",
        "planning",
        "financial"
    ],
    "wof:name":"American Express Financial Adv",
    "wof:placetype":"venue"
},
  "geometry": {"coordinates":[-89.016694,42.238438],"type":"Point"}
}