{
  "type": "Feature",
  "properties": {
    "iso:country":"US",
    "sg:address":"3025 Lick Creek Rd",
    "sg:city":"Buncombe",
    "sg:classifiers":[
        {
            "category":"Retail",
            "subcategory":"Repair Shop",
            "type":"Services"
        }
    ],
    "sg:phone":"+1 618 658 2567",
    "sg:postcode":"62912",
    "sg:province":"IL",
    "sg:tags":[
        "ironwork"
    ],
    "wof:name":"Iron Age",
    "wof:placetype":"venue"
},
  "geometry": {"coordinates":[-88.993864,37.487113],"type":"Point"}
}