{
  "type": "Feature",
  "properties": {
    "addr:full":"922 Brook Forest Ave Shorewood IL 60431",
    "addr:housenumber":"922",
    "addr:postcode":"60431",
    "addr:street":"Brook Forest Ave",
    "iso:country":"US",
    "sg:address":"922 Brook Forest Ave",
    "sg:city":"Shorewood",
    "sg:classifiers":[
        {
            "category":"Utilities",
            "subcategory":"Mobile Phone",
            "type":"Services"
        }
    ],
    "sg:phone":"+1 815 254 6815",
    "sg:postcode":"60431",
    "sg:province":"IL",
    "sg:tags":[
        "telephone",
        "cellular"
    ],
    "wof:name":"Us Cellular Inc",
    "wof:placetype":"venue"
},
  "geometry": {"coordinates":[-88.19922699999999,41.538347],"type":"Point"}
}