{
  "type": "Feature",
  "properties": {
    "iso:country":"US",
    "sg:address":"800 N 24th St",
    "sg:city":"Quincy",
    "sg:classifiers":[
        {
            "category":"Retail",
            "subcategory":"Auto Repair",
            "type":"Services"
        }
    ],
    "sg:phone":"+1 217 224 2200",
    "sg:postcode":"62301",
    "sg:province":"IL",
    "sg:tags":[
        "automotive",
        "general"
    ],
    "wof:name":"Exhaust & Auto Ctr",
    "wof:placetype":"venue"
},
  "geometry": {"coordinates":[-91.377662,39.941598],"type":"Point"}
}