{
  "type": "Feature",
  "properties": {
    "iso:country":"US",
    "sg:address":"4314 W Mclean Ave",
    "sg:city":"Chicago",
    "sg:classifiers":[
        {
            "category":"Manufacturing",
            "subcategory":"Leather Goods",
            "type":"Manufacturing & Wholesale Goods"
        }
    ],
    "sg:phone":"+1 773 486 1552",
    "sg:postcode":"60639",
    "sg:province":"IL",
    "sg:tags":[
        "manufacturer"
    ],
    "wof:name":"Leather Goods",
    "wof:placetype":"venue"
},
  "geometry": {"coordinates":[-87.73425400000001,41.917987],"type":"Point"}
}