{
  "type": "Feature",
  "properties": {
    "iso:country":"US",
    "sg:address":"2727 Lauren Lake Dr",
    "sg:city":"Belleville",
    "sg:classifiers":[
        {
            "category":"Organizations",
            "subcategory":"Religious Organization",
            "type":"Services"
        }
    ],
    "sg:phone":"+1 618 622 4940",
    "sg:postcode":"62221",
    "sg:province":"IL",
    "wof:name":"Harvest Church of Illinois",
    "wof:placetype":"venue"
},
  "geometry": {"coordinates":[-89.933924,38.567735],"type":"Point"}
}