{
  "type": "Feature",
  "properties": {
    "iso:country":"US",
    "sg:address":"1390 Lunt Ave",
    "sg:city":"Elk Grove Village",
    "sg:classifiers":[
        {
            "category":"Manufacturing",
            "subcategory":"Electronics",
            "type":"Manufacturing & Wholesale Goods"
        }
    ],
    "sg:phone":"+1 847 806 7777",
    "sg:postcode":"60007",
    "sg:province":"IL",
    "sg:tags":[
        "boards",
        "circuit",
        "mfg"
    ],
    "wof:name":"Qma Inc",
    "wof:placetype":"venue"
},
  "geometry": {"coordinates":[-87.964628,42.002046],"type":"Point"}
}