{
  "type": "Feature",
  "properties": {
    "addr:full":"4406 N Broadway St Chicago IL 60640",
    "addr:housenumber":"4406",
    "addr:postcode":"60640",
    "addr:street":"N Broadway St",
    "iso:country":"US",
    "sg:address":"4406 N Broadway St",
    "sg:city":"Chicago",
    "sg:classifiers":[
        {
            "category":"Restaurant",
            "type":"Food & Drink"
        }
    ],
    "sg:phone":"+1 773 907 9090",
    "sg:postcode":"60640",
    "sg:province":"IL",
    "wof:name":"A J's Grill",
    "wof:placetype":"venue"
},
  "geometry": {"coordinates":[-87.655714,41.962473],"type":"Point"}
}