{
  "type": "Feature",
  "properties": {
    "addr:full":"4860 Oakton St Skokie IL 60077",
    "addr:housenumber":"4860",
    "addr:postcode":"60077",
    "addr:street":"Oakton St",
    "iso:country":"US",
    "sg:address":"4860 Oakton St",
    "sg:city":"Skokie",
    "sg:classifiers":[
        {
            "category":"Health Services",
            "subcategory":"Doctor",
            "type":"Services"
        }
    ],
    "sg:phone":"+1 847 329 0470",
    "sg:postcode":"60077",
    "sg:province":"IL",
    "sg:tags":[
        "medical"
    ],
    "wof:name":"Oakton Health Center",
    "wof:placetype":"venue"
},
  "geometry": {"coordinates":[-87.748597,42.026337],"type":"Point"}
}