{
  "type": "Feature",
  "properties": {
    "addr:full":"4701 N Illinois Fairview Heights IL 62208",
    "addr:housenumber":"4701",
    "addr:postcode":"62208",
    "addr:street":"N",
    "iso:country":"US",
    "sg:address":"4701 N Illinois",
    "sg:city":"Fairview Heights",
    "sg:classifiers":[
        {
            "category":"Coffee & Tea",
            "type":"Food & Drink"
        }
    ],
    "sg:postcode":"62208",
    "sg:province":"IL",
    "wof:name":"Starbucks",
    "wof:placetype":"venue"
},
  "geometry": {"coordinates":[-89.98516100000001,38.571336],"type":"Point"}
}