{
  "type": "Feature",
  "properties": {
    "addr:full":"5934 N Melvina Ave Chicago IL 60646",
    "addr:housenumber":"5934",
    "addr:postcode":"60646",
    "addr:street":"N Melvina Ave",
    "iso:country":"US",
    "sg:address":"5934 N Melvina Ave",
    "sg:city":"Chicago",
    "sg:classifiers":[
        {
            "category":"Building & Trades",
            "subcategory":"Electrical",
            "type":"Services"
        }
    ],
    "sg:phone":"+1 773 467 9570",
    "sg:postcode":"60646",
    "sg:province":"IL",
    "sg:tags":[
        "electric",
        "contractor"
    ],
    "wof:name":"Alvarez Electric Contr Co",
    "wof:placetype":"venue"
},
  "geometry": {"coordinates":[-87.782849,41.988675],"type":"Point"}
}