{
  "type": "Feature",
  "properties": {
    "addr:full":"3000 N Halsted Street Chicago IL 60657",
    "addr:housenumber":"3000",
    "addr:postcode":"60657",
    "addr:street":"N Halsted Street",
    "iso:country":"US",
    "sg:address":"3000 N Halsted Street",
    "sg:city":"Chicago",
    "sg:classifiers":[
        {
            "category":"Health Services",
            "subcategory":"Doctor",
            "type":"Services"
        }
    ],
    "sg:phone":"+1 773 296 3700",
    "sg:postcode":"60657",
    "sg:province":"IL",
    "wof:name":"Feldman Sidney MD",
    "wof:placetype":"venue"
},
  "geometry": {"coordinates":[-87.649131,41.936925],"type":"Point"}
}