{
  "type": "Feature",
  "properties": {
    "iso:country":"US",
    "sg:address":"817 Maryknoll Dr",
    "sg:city":"Lockport",
    "sg:classifiers":[
        {
            "category":"Retail",
            "subcategory":"Repair Shop",
            "type":"Services"
        }
    ],
    "sg:phone":"+1 815 838 7326",
    "sg:postcode":"60441",
    "sg:province":"IL",
    "sg:tags":[
        "taxidermist"
    ],
    "wof:name":"Richard E Janovsky",
    "wof:placetype":"venue"
},
  "geometry": {"coordinates":[-88.041344,41.608363],"type":"Point"}
}