{
  "type": "Feature",
  "properties": {
    "addr:full":"601 E Oak St Mahomet IL 61853",
    "addr:housenumber":"601",
    "addr:postcode":"61853",
    "addr:street":"E Oak St",
    "iso:country":"US",
    "sg:address":"601 E Oak St",
    "sg:city":"Mahomet",
    "sg:classifiers":[
        {
            "category":"Ice Cream",
            "type":"Food & Drink"
        }
    ],
    "sg:menulink":"http://www.allmenus.com/il/mahomet/161958-dairy-queen/menu/",
    "sg:phone":"+1 217 586 4061",
    "sg:postcode":"61853",
    "sg:province":"IL",
    "sg:tags":[
        "burger",
        "american"
    ],
    "wof:name":"Dairy Queen",
    "wof:placetype":"venue"
},
  "geometry": {"coordinates":[-88.401881,40.191908],"type":"Point"}
}