{
  "type": "Feature",
  "properties": {
    "iso:country":"US",
    "sg:address":"29 S La Salle St",
    "sg:city":"Chicago",
    "sg:classifiers":[
        {
            "category":"Professional",
            "subcategory":"Lawyer & Legal Services",
            "type":"Services"
        }
    ],
    "sg:phone":"+1 312 443 0008",
    "sg:postcode":"60603",
    "sg:province":"IL",
    "wof:name":"Helen R Rogal",
    "wof:placetype":"venue"
},
  "geometry": {"coordinates":[-87.6323,41.881248],"type":"Point"}
}