{
  "type": "Feature",
  "properties": {
    "iso:country":"US",
    "sg:address":"1715 Maple Ave",
    "sg:city":"Evanston",
    "sg:classifiers":[
        {
            "category":"Cinema",
            "subcategory":"Movie Theater",
            "type":"Entertainment"
        }
    ],
    "sg:phone":"+1 847 492 0123",
    "sg:postcode":"60201",
    "sg:province":"IL",
    "wof:name":"Century Theatres",
    "wof:placetype":"venue"
},
  "geometry": {"coordinates":[-87.684701,42.049779],"type":"Point"}
}