{
  "type": "Feature",
  "properties": {
    "addr:full":"4019 Cottonwood Ct Island Lake IL 60042",
    "addr:housenumber":"4019",
    "addr:postcode":"60042",
    "addr:street":"Cottonwood Ct",
    "iso:country":"US",
    "sg:address":"4019 Cottonwood Ct",
    "sg:city":"Island Lake",
    "sg:classifiers":[
        {
            "category":"Professional",
            "subcategory":"Management & Consulting",
            "type":"Services"
        }
    ],
    "sg:phone":"+1 847 526 1164",
    "sg:postcode":"60042",
    "sg:province":"IL",
    "sg:tags":[
        "business"
    ],
    "sg:website":"www.tigroup-usa.com",
    "wof:name":"Technology Integration Group",
    "wof:placetype":"venue"
},
  "geometry": {"coordinates":[-88.189363,42.270897],"type":"Point"}
}