{
  "type": "Feature",
  "properties": {
    "addr:full":"6051 N. Mozart St #4 Chicago IL 60659",
    "addr:housenumber":"6051",
    "addr:postcode":"60659",
    "addr:street":"N. Mozart St # 4",
    "iso:country":"US",
    "sg:address":"6051 N. Mozart St #4",
    "sg:city":"Chicago",
    "sg:classifiers":[
        {
            "category":"Professional",
            "subcategory":"Art Services",
            "type":"Services"
        }
    ],
    "sg:phone":"+1 312 802 6277",
    "sg:postcode":"60659",
    "sg:province":"IL",
    "sg:tags":[
        "photographer"
    ],
    "sg:website":"www.heatherstonephotography.com/",
    "wof:name":"Heather Stone Photography",
    "wof:placetype":"venue"
},
  "geometry": {"coordinates":[-87.700602,41.991837],"type":"Point"}
}