{
  "type": "Feature",
  "properties": {
    "iso:country":"US",
    "sg:address":"1809 4th St",
    "sg:city":"Peru",
    "sg:classifiers":[
        {
            "category":"Shopping",
            "subcategory":"Clothing, Apparel, & Fashions",
            "type":"Retail Goods"
        }
    ],
    "sg:phone":"+1 815 223 0695",
    "sg:postcode":"61354",
    "sg:province":"IL",
    "sg:tags":[
        "furnishing"
    ],
    "wof:name":"Vlastnik's Men's Wear",
    "wof:placetype":"venue"
},
  "geometry": {"coordinates":[-89.13039,41.32768],"type":"Point"}
}