{
  "type": "Feature",
  "properties": {
    "addr:full":"2908 W Peterson Avenue Chicago IL 60659",
    "addr:housenumber":"2908",
    "addr:postcode":"60659",
    "addr:street":"W Peterson Avenue",
    "iso:country":"US",
    "sg:address":"2908 W Peterson Avenue",
    "sg:city":"Chicago",
    "sg:classifiers":[
        {
            "category":"Banks & Credit Unions",
            "subcategory":"Financial Services",
            "type":"Services"
        }
    ],
    "sg:phone":"+1 773 338 9000",
    "sg:postcode":"60659",
    "sg:province":"IL",
    "sg:tags":[
        "broker",
        "mortgage"
    ],
    "wof:name":"Quantum Financial Mortgage",
    "wof:placetype":"venue"
},
  "geometry": {"coordinates":[-87.702155,41.990425],"type":"Point"}
}