{
  "type": "Feature",
  "properties": {
    "iso:country":"US",
    "sg:address":"233 S Wacker Drive",
    "sg:city":"Chicago",
    "sg:classifiers":[
        {
            "category":"Health Services",
            "subcategory":"Dentist",
            "type":"Services"
        }
    ],
    "sg:phone":"+1 312 993 0800",
    "sg:postcode":"60606",
    "sg:province":"IL",
    "wof:name":"Christina Kromkowski, \u00a0DDS",
    "wof:placetype":"venue"
},
  "geometry": {"coordinates":[-87.63671100000001,41.878981],"type":"Point"}
}