{
  "type": "Feature",
  "properties": {
    "iso:country":"US",
    "sg:address":"1880 W Fullerton Ave Ste 5",
    "sg:city":"Chicago",
    "sg:classifiers":[
        {
            "category":"Shopping",
            "subcategory":"Clothing, Apparel, & Fashions",
            "type":"Retail Goods"
        },
        {
            "category":"Shopping",
            "subcategory":"Party Supplies",
            "type":"Retail Goods"
        },
        {
            "category":"Shopping",
            "subcategory":"Discount & Variety Stores",
            "type":"Retail Goods"
        }
    ],
    "sg:phone":"+1 773 342 1500",
    "sg:postcode":"60614",
    "sg:province":"IL",
    "sg:tags":[
        "costume",
        "outlet"
    ],
    "sg:website":"www.cardandpartygiant.com",
    "wof:name":"Card & Party Giant",
    "wof:placetype":"venue"
},
  "geometry": {"coordinates":[-87.676439,41.925217],"type":"Point"}
}