{
  "type": "Feature",
  "properties": {
    "addr:full":"6039 N Bernard St Chicago IL 60659",
    "addr:housenumber":"6039",
    "addr:postcode":"60659",
    "addr:street":"N Bernard St",
    "iso:country":"US",
    "sg:address":"6039 N Bernard St",
    "sg:city":"Chicago",
    "sg:classifiers":[
        {
            "category":"Banks & Credit Unions",
            "subcategory":"Investment Brokerage",
            "type":"Services"
        }
    ],
    "sg:phone":"+1 773 463 0777",
    "sg:postcode":"60659",
    "sg:province":"IL",
    "sg:tags":[
        "trust"
    ],
    "wof:name":"Bassman Family Foundation",
    "wof:placetype":"venue"
},
  "geometry": {"coordinates":[-87.715211,41.990973],"type":"Point"}
}