{
  "type": "Feature",
  "properties": {
    "addr:full":"3502 Thomas Ave Alton IL 62002",
    "addr:housenumber":"3502",
    "addr:postcode":"62002",
    "addr:street":"Thomas Ave",
    "iso:country":"US",
    "sg:address":"3502 Thomas Ave",
    "sg:city":"Alton",
    "sg:classifiers":[
        {
            "category":"Professional",
            "subcategory":"Business Services",
            "type":"Services"
        }
    ],
    "sg:phone":"+1 618 462 6152",
    "sg:postcode":"62002",
    "sg:province":"IL",
    "wof:name":"Waller Tax Service",
    "wof:placetype":"venue"
},
  "geometry": {"coordinates":[-90.130656,38.899357],"type":"Point"}
}