{
  "type": "Feature",
  "properties": {
    "iso:country":"US",
    "sg:address":"1285 Elmhurst Rd",
    "sg:city":"Des Plaines",
    "sg:classifiers":[
        {
            "category":"Cinema",
            "subcategory":"Movie Rental",
            "type":"Entertainment"
        }
    ],
    "sg:phone":"+1 847 952 8323",
    "sg:postcode":"60018",
    "sg:province":"IL",
    "sg:tags":[
        "video",
        "tape"
    ],
    "wof:name":"Barbara S Video 2",
    "wof:placetype":"venue"
},
  "geometry": {"coordinates":[-87.940501,42.029624],"type":"Point"}
}