{
  "type": "Feature",
  "properties": {
    "iso:country":"US",
    "sg:address":"2010 State St",
    "sg:city":"Alton",
    "sg:classifiers":[
        {
            "category":"Health Services",
            "subcategory":"Clinic",
            "type":"Services"
        }
    ],
    "sg:phone":"+1 618 234 9369",
    "sg:postcode":"62002",
    "sg:province":"IL",
    "wof:name":"Health Facilty Staffing",
    "wof:placetype":"venue"
},
  "geometry": {"coordinates":[-90.196302,38.911598],"type":"Point"}
}