{
  "type": "Feature",
  "properties": {
    "addr:full":"510 Maplewood Dr Sycamore IL 60178",
    "addr:housenumber":"510",
    "addr:postcode":"60178",
    "addr:street":"Maplewood Dr",
    "iso:country":"US",
    "sg:address":"510 Maplewood Dr",
    "sg:city":"Sycamore",
    "sg:classifiers":[
        {
            "category":"Building & Trades",
            "subcategory":"Construction",
            "type":"Services"
        }
    ],
    "sg:phone":"+1 815 895 2026",
    "sg:postcode":"60178",
    "sg:province":"IL",
    "sg:tags":[
        "wallcoverings-installation",
        "wallpaper",
        "painting",
        "contractor"
    ],
    "wof:name":"Realistic Painting",
    "wof:placetype":"venue"
},
  "geometry": {"coordinates":[-88.687601,42.002332],"type":"Point"}
}