{
  "type": "Feature",
  "properties": {
    "iso:country":"US",
    "sg:address":"14270 Telegraph Rd",
    "sg:city":"Pecatonica",
    "sg:classifiers":[
        {
            "category":"Professional",
            "subcategory":"Business Services",
            "type":"Services"
        }
    ],
    "sg:phone":"+1 815 239 1823",
    "sg:postcode":"61063",
    "sg:province":"IL",
    "wof:name":"Fye Webb Deborah Designer",
    "wof:placetype":"venue"
},
  "geometry": {"coordinates":[-89.317635,42.330035],"type":"Point"}
}