{
  "type": "Feature",
  "properties": {
    "iso:country":"US",
    "sg:address":"1111 Oxford Ln",
    "sg:city":"Lake Zurich",
    "sg:classifiers":[
        {
            "category":"Real Estate",
            "subcategory":"Architect",
            "type":"Services"
        }
    ],
    "sg:phone":"+1 847 726 1101",
    "sg:postcode":"60047",
    "sg:province":"IL",
    "wof:name":"Schmitt Cibulka Assoc",
    "wof:placetype":"venue"
},
  "geometry": {"coordinates":[-88.061644,42.178984],"type":"Point"}
}