{
  "type": "Feature",
  "properties": {
    "addr:full":"5036 S Ashland Ave Chicago IL 60609",
    "addr:housenumber":"5036",
    "addr:postcode":"60609",
    "addr:street":"S Ashland Ave",
    "iso:country":"US",
    "sg:address":"5036 S Ashland Ave",
    "sg:city":"Chicago",
    "sg:classifiers":[
        {
            "category":"Home & Garden",
            "subcategory":"Furniture",
            "type":"Retail Goods"
        }
    ],
    "sg:phone":"+1 773 424 8843",
    "sg:postcode":"60609",
    "sg:province":"IL",
    "sg:tags":[
        "store"
    ],
    "wof:name":"Store God's House Furniture",
    "wof:placetype":"venue"
},
  "geometry": {"coordinates":[-87.665052,41.802507],"type":"Point"}
}