{
  "type": "Feature",
  "properties": {
    "iso:country":"US",
    "sg:address":"7516 Madison St",
    "sg:city":"Forest Park",
    "sg:classifiers":[
        {
            "category":"Shopping",
            "subcategory":"Used Merchandise",
            "type":"Retail Goods"
        }
    ],
    "sg:phone":"+1   ",
    "sg:postcode":"60130",
    "sg:province":"IL",
    "wof:name":"At Home With Antiques",
    "wof:placetype":"venue"
},
  "geometry": {"coordinates":[-87.812505,41.879422],"type":"Point"}
}