{
  "type": "Feature",
  "properties": {
    "addr:full":"2104 South St Rolling Meadows IL 60008",
    "addr:housenumber":"2104",
    "addr:postcode":"60008",
    "addr:street":"South St",
    "iso:country":"US",
    "sg:address":"2104 South St",
    "sg:city":"Rolling Meadows",
    "sg:classifiers":[
        {
            "category":"Food & Beverages",
            "subcategory":"Specialty",
            "type":"Retail Goods"
        }
    ],
    "sg:phone":"+1   ",
    "sg:postcode":"60008",
    "sg:province":"IL",
    "wof:name":"In The Pink Ink",
    "wof:placetype":"venue"
},
  "geometry": {"coordinates":[-88.008759,42.079383],"type":"Point"}
}