{
  "type": "Feature",
  "properties": {
    "iso:country":"US",
    "sg:address":"3330 S King Dr",
    "sg:city":"Chicago",
    "sg:classifiers":[
        {
            "category":"Place Of Worship",
            "subcategory":"Church",
            "type":"Public Place"
        },
        {
            "category":"Place Of Worship",
            "type":"Public Place"
        },
        {
            "category":"Organizations",
            "subcategory":"Religious Organization",
            "type":"Services"
        }
    ],
    "sg:phone":"+1 312 842 5957",
    "sg:postcode":"60616",
    "sg:province":"IL",
    "sg:tags":[
        "churches-methodist"
    ],
    "wof:name":"Hartzell United Methodist Church",
    "wof:placetype":"venue"
},
  "geometry": {"coordinates":[-87.61736000000001,41.834192],"type":"Point"}
}