{
  "type": "Feature",
  "properties": {
    "iso:country":"US",
    "sg:address":"1314 Devonshire Rd",
    "sg:city":"Buffalo Grove",
    "sg:classifiers":[
        {
            "category":"Organizations",
            "subcategory":"Religious Organization",
            "type":"Services"
        }
    ],
    "sg:phone":"+1 847 634 1908",
    "sg:postcode":"60089",
    "sg:province":"IL",
    "wof:name":"Korean Logos Church",
    "wof:placetype":"venue"
},
  "geometry": {"coordinates":[-87.977495,42.174979],"type":"Point"}
}