{
  "type": "Feature",
  "properties": {
    "iso:country":"US",
    "sg:address":"260 E Belvidere Rd",
    "sg:city":"Hainesville",
    "sg:classifiers":[
        {
            "category":"Professional",
            "subcategory":"Business Services",
            "type":"Services"
        },
        {
            "category":"Professional",
            "subcategory":"Printing & Photocopies",
            "type":"Services"
        },
        {
            "category":"Government",
            "subcategory":"Post Office",
            "type":"Public Place"
        },
        {
            "category":"Organizations",
            "subcategory":"Professional Association",
            "type":"Services"
        }
    ],
    "sg:phone":"+1 847 543 0101",
    "sg:postcode":"60030",
    "sg:province":"IL",
    "sg:tags":[
        "blueprinting",
        "mailbox-rental",
        "shipping",
        "duplicating",
        "fulfillment",
        "copying",
        "mail-order",
        "receiving"
    ],
    "sg:website":"http://www.copyandmail.net",
    "wof:name":"Hainesville Print Copy & Mail Center",
    "wof:placetype":"venue"
},
  "geometry": {"coordinates":[-88.03998799999999,42.337574],"type":"Point"}
}