{
  "type": "Feature",
  "properties": {
    "addr:full":"700 Taft Ave Glen Ellyn IL 60137",
    "addr:housenumber":"700",
    "addr:postcode":"60137",
    "addr:street":"Taft Ave",
    "iso:country":"US",
    "sg:address":"700 Taft Ave",
    "sg:city":"Glen Ellyn",
    "sg:classifiers":[
        {
            "category":"Building & Trades",
            "subcategory":"Landscaping Services",
            "type":"Services"
        }
    ],
    "sg:phone":"+1 847 394 4233",
    "sg:postcode":"60137",
    "sg:province":"IL",
    "sg:tags":[
        "ornamental",
        "surgery",
        "tree"
    ],
    "wof:name":"Hendricksen The Care Trees Inc",
    "wof:placetype":"venue"
},
  "geometry": {"coordinates":[-88.058504,41.858534],"type":"Point"}
}