{
  "type": "Feature",
  "properties": {
    "iso:country":"US",
    "sg:address":"5375 Pocono Dr",
    "sg:city":"Loves Park",
    "sg:classifiers":[
        {
            "category":"Manufacturing",
            "subcategory":"Tools & Machinery",
            "type":"Manufacturing & Wholesale Goods"
        }
    ],
    "sg:phone":"+1 815 282 6758",
    "sg:postcode":"61111",
    "sg:province":"IL",
    "wof:name":"Giggle Stitch Custom EMB",
    "wof:placetype":"venue"
},
  "geometry": {"coordinates":[-89.01257099999999,42.358837],"type":"Point"}
}