{
  "type": "Feature",
  "properties": {
    "addr:full":"330 E Wilson St Batavia IL 60510",
    "addr:housenumber":"330",
    "addr:postcode":"60510",
    "addr:street":"E Wilson St",
    "iso:country":"US",
    "sg:address":"330 E Wilson St",
    "sg:city":"Batavia",
    "sg:classifiers":[
        {
            "category":"Personal",
            "subcategory":"Beauty Salon",
            "type":"Services"
        }
    ],
    "sg:phone":"+1 630 406 1177",
    "sg:postcode":"60510",
    "sg:province":"IL",
    "wof:name":"Fantastic Sam's",
    "wof:placetype":"venue"
},
  "geometry": {"coordinates":[-88.30181399999999,41.849965],"type":"Point"}
}