{
  "type": "Feature",
  "properties": {
    "iso:country":"US",
    "sg:address":"1329 US Hwy 20",
    "sg:city":"Freeport",
    "sg:classifiers":[
        {
            "category":"Insurance",
            "subcategory":"Insurance Agent",
            "type":"Services"
        }
    ],
    "sg:phone":"+1 815 232 4726",
    "sg:postcode":"61032",
    "sg:province":"IL",
    "wof:name":"Bob Grimm Agency",
    "wof:placetype":"venue"
},
  "geometry": {"coordinates":[-89.590193,42.320309],"type":"Point"}
}