{
  "type": "Feature",
  "properties": {
    "iso:country":"US",
    "sg:address":"402 Kent Rd N",
    "sg:city":"Mc Henry",
    "sg:classifiers":[
        {
            "category":"Real Estate",
            "subcategory":"Real Estate Agent",
            "type":"Services"
        }
    ],
    "sg:phone":"+1 815 385 0137",
    "sg:postcode":"60051",
    "sg:province":"IL",
    "wof:name":"L&C Real Estate",
    "wof:placetype":"venue"
},
  "geometry": {"coordinates":[-88.230407,42.333413],"type":"Point"}
}