{
  "type": "Feature",
  "properties": {
    "iso:country":"US",
    "sg:address":"1541 Revere Cir",
    "sg:city":"Schaumburg",
    "sg:classifiers":[
        {
            "category":"Shopping",
            "subcategory":"Computers & Home Electronics",
            "type":"Retail Goods"
        }
    ],
    "sg:phone":"+1   ",
    "sg:postcode":"60193",
    "sg:province":"IL",
    "wof:name":"Surfgiftscom",
    "wof:placetype":"venue"
},
  "geometry": {"coordinates":[-88.118028,42.022635],"type":"Point"}
}