{
  "type": "Feature",
  "properties": {
    "addr:full":"3937 W North Ave Chicago IL 60647",
    "addr:housenumber":"3937",
    "addr:postcode":"60647",
    "addr:street":"W North Ave",
    "iso:country":"US",
    "sg:address":"3937 W North Ave",
    "sg:city":"Chicago",
    "sg:classifiers":[
        {
            "category":"Professional",
            "subcategory":"Accounting & Tax Preparation",
            "type":"Services"
        }
    ],
    "sg:phone":"+1 773 489 9810",
    "sg:postcode":"60647",
    "sg:province":"IL",
    "sg:tags":[
        "bookkeeping",
        "return",
        "representative",
        "preparation-business",
        "taxes-consultants"
    ],
    "sg:website":"http://www.jacksonhewitt.com/",
    "wof:name":"Jackson Hewitt Tax Service",
    "wof:placetype":"venue"
},
  "geometry": {"coordinates":[-87.725376,41.909899],"type":"Point"}
}