{
  "type": "Feature",
  "properties": {
    "iso:country":"US",
    "sg:address":"3020 S Banker St",
    "sg:city":"Effingham",
    "sg:classifiers":[
        {
            "category":"Retail",
            "subcategory":"Repair Shop",
            "type":"Services"
        }
    ],
    "sg:phone":"+1 217 536 5545",
    "sg:postcode":"62401",
    "sg:province":"IL",
    "wof:name":"Mahdurs",
    "wof:placetype":"venue"
},
  "geometry": {"coordinates":[-88.54779000000001,39.090661],"type":"Point"}
}