{
  "type": "Feature",
  "properties": {
    "iso:country":"US",
    "sg:address":"8419 W 50th Pl",
    "sg:city":"Mc Cook",
    "sg:classifiers":[
        {
            "category":"Education",
            "subcategory":"Library",
            "type":"Public Place"
        }
    ],
    "sg:phone":"+1 708 442 1242",
    "sg:postcode":"60525",
    "sg:province":"IL",
    "wof:name":"McCook Library District",
    "wof:placetype":"venue"
},
  "geometry": {"coordinates":[-87.845001,41.791],"type":"Point"}
}