{
  "type": "Feature",
  "properties": {
    "iso:country":"US",
    "sg:address":"1170 E Dundee Rd",
    "sg:city":"Palatine",
    "sg:classifiers":[
        {
            "category":"Shopping",
            "subcategory":"Discount & Variety Stores",
            "type":"Retail Goods"
        }
    ],
    "sg:phone":"+1 847 991 8241",
    "sg:postcode":"60074",
    "sg:province":"IL",
    "wof:name":"Dollar Buster",
    "wof:placetype":"venue"
},
  "geometry": {"coordinates":[-88.01757,42.139144],"type":"Point"}
}