{
  "type": "Feature",
  "properties": {
    "iso:country":"US",
    "sg:address":"7 S Aberdeen St",
    "sg:city":"Chicago",
    "sg:classifiers":[
        {
            "category":"Real Estate",
            "subcategory":"Real Estate Services",
            "type":"Services"
        }
    ],
    "sg:phone":"+1 312 829 1849",
    "sg:postcode":"60607",
    "sg:province":"IL",
    "sg:tags":[
        "management",
        "condominium"
    ],
    "wof:name":"7 S Aberdeen Condo Association",
    "wof:placetype":"venue"
},
  "geometry": {"coordinates":[-87.654709,41.881411],"type":"Point"}
}