{
  "type": "Feature",
  "properties": {
    "iso:country":"US",
    "sg:address":"964 Washington St",
    "sg:city":"South Beloit",
    "sg:classifiers":[
        {
            "category":"Building & Trades",
            "subcategory":"Construction",
            "type":"Services"
        }
    ],
    "sg:phone":"+1 815 389 4455",
    "sg:postcode":"61080",
    "sg:province":"WI",
    "sg:tags":[
        "maker",
        "cabinet"
    ],
    "wof:name":"Custom Designed Cabinetry",
    "wof:placetype":"venue"
},
  "geometry": {"coordinates":[-89.026071,42.490138],"type":"Point"}
}