{
  "type": "Feature",
  "properties": {
    "addr:full":"1026 S State St Lockport IL 60441",
    "addr:housenumber":"1026",
    "addr:postcode":"60441",
    "addr:street":"S State St",
    "iso:country":"US",
    "sg:address":"1026 S State St",
    "sg:city":"Lockport",
    "sg:classifiers":[
        {
            "category":"Restaurant",
            "type":"Food & Drink"
        }
    ],
    "sg:phone":"+1   ",
    "sg:postcode":"60441",
    "sg:province":"IL",
    "sg:tags":[
        "mexican"
    ],
    "wof:name":"Kualla Restaurant",
    "wof:placetype":"venue"
},
  "geometry": {"coordinates":[-88.05824,41.587547],"type":"Point"}
}