{
  "type": "Feature",
  "properties": {
    "iso:country":"US",
    "sg:address":"793 S Elm Ave",
    "sg:city":"Kankakee",
    "sg:classifiers":[
        {
            "category":"Building & Trades",
            "subcategory":"Landscaping Services",
            "type":"Services"
        }
    ],
    "sg:phone":"+1 815 936 9659",
    "sg:postcode":"60901",
    "sg:province":"IL",
    "sg:tags":[
        "landscape",
        "contractor"
    ],
    "wof:name":"Bill's Landscaping",
    "wof:placetype":"venue"
},
  "geometry": {"coordinates":[-87.851693,41.10995],"type":"Point"}
}