{
  "type": "Feature",
  "properties": {
    "addr:full":"283 S Elm St Winchester IL 62694",
    "addr:housenumber":"283",
    "addr:postcode":"62694",
    "addr:street":"S Elm St",
    "iso:country":"US",
    "sg:address":"283 S Elm St",
    "sg:city":"Winchester",
    "sg:classifiers":[
        {
            "category":"Education",
            "subcategory":"School",
            "type":"Public Place"
        }
    ],
    "sg:phone":"+1 217 742 9551",
    "sg:postcode":"62694",
    "sg:province":"IL",
    "wof:name":"Winchester Elementary School",
    "wof:placetype":"venue"
},
  "geometry": {"coordinates":[-90.460616,39.625211],"type":"Point"}
}