{
  "type": "Feature",
  "properties": {
    "addr:full":"4915 N Big Hollow Rd Peoria IL 61615",
    "addr:housenumber":"4915",
    "addr:postcode":"61615",
    "addr:street":"N Big Hollow Rd",
    "iso:country":"US",
    "sg:address":"4915 N Big Hollow Rd",
    "sg:city":"Peoria",
    "sg:classifiers":[
        {
            "category":"Restaurant",
            "type":"Food & Drink"
        }
    ],
    "sg:menulink":"http://www.allmenus.com/il/peoria-city/42058-bob-evans/menu/",
    "sg:phone":"+1 309 692 3600",
    "sg:postcode":"61615",
    "sg:province":"IL",
    "sg:tags":[
        "american"
    ],
    "wof:name":"Bob Evans",
    "wof:placetype":"venue"
},
  "geometry": {"coordinates":[-89.64226499999999,40.753274],"type":"Point"}
}