{
  "type": "Feature",
  "properties": {
    "addr:full":"6400 Woodward Ave Downers Grove IL 60516",
    "addr:housenumber":"6400",
    "addr:postcode":"60516",
    "addr:street":"Woodward Ave",
    "iso:country":"US",
    "sg:address":"6400 Woodward Ave",
    "sg:city":"Downers Grove",
    "sg:classifiers":[
        {
            "category":"Wholesale",
            "subcategory":"Durable Goods & Equipment",
            "type":"Manufacturing & Wholesale Goods"
        }
    ],
    "sg:phone":"+1 630 852 0852",
    "sg:postcode":"60516",
    "sg:province":"IL",
    "wof:name":"America Rectrix Corp",
    "wof:placetype":"venue"
},
  "geometry": {"coordinates":[-88.031831,41.771687],"type":"Point"}
}