{
  "type": "Feature",
  "properties": {
    "addr:full":"70 W Hubbard St Ste 201 Chicago IL 60654",
    "addr:housenumber":"70",
    "addr:postcode":"60654",
    "addr:street":"W Hubbard St Ste 201",
    "iso:country":"US",
    "sg:address":"70 W Hubbard St Ste 201",
    "sg:city":"Chicago",
    "sg:classifiers":[
        {
            "category":"Building & Trades",
            "subcategory":"Landscaping Services",
            "type":"Services"
        }
    ],
    "sg:phone":"+1 312 467 1330",
    "sg:postcode":"60654",
    "sg:province":"IL",
    "sg:tags":[
        "consultant",
        "lawn",
        "designer",
        "landscape"
    ],
    "wof:name":"Prassas Landscape Studio",
    "wof:placetype":"venue"
},
  "geometry": {"coordinates":[-87.630325,41.890045],"type":"Point"}
}