{
  "type": "Feature",
  "properties": {
    "iso:country":"US",
    "sg:address":"8422 W Lawrence Ave",
    "sg:city":"Norridge",
    "sg:classifiers":[
        {
            "category":"Banks & Credit Unions",
            "subcategory":"Bank",
            "type":"Services"
        }
    ],
    "sg:phone":"+1 708 456 2146",
    "sg:postcode":"60706",
    "sg:province":"IL",
    "sg:website":"www.lasallebank.com",
    "wof:name":"Lasalle Bank",
    "wof:placetype":"venue"
},
  "geometry": {"coordinates":[-87.837681,41.96678],"type":"Point"}
}