{
  "type": "Feature",
  "properties": {
    "addr:full":"200 Applebee St Barrington IL 60010",
    "addr:housenumber":"200",
    "addr:postcode":"60010",
    "addr:street":"Applebee St",
    "iso:country":"US",
    "sg:address":"200 Applebee St",
    "sg:city":"Barrington",
    "sg:classifiers":[
        {
            "category":"Professional",
            "subcategory":"Lawyer & Legal Services",
            "type":"Services"
        }
    ],
    "sg:phone":"+1 847 381 6635",
    "sg:postcode":"60010",
    "sg:province":"IL",
    "wof:name":"J Frank Wyatt Jr",
    "wof:placetype":"venue"
},
  "geometry": {"coordinates":[-88.136116,42.154483],"type":"Point"}
}