{
  "type": "Feature",
  "properties": {
    "iso:country":"US",
    "sg:address":"3105 W 111th St",
    "sg:city":"Chicago",
    "sg:classifiers":[
        {
            "category":"Autos & Motor Vehicles",
            "subcategory":"Automobile Sales",
            "type":"Retail Goods"
        }
    ],
    "sg:phone":"+1 773 233 8866",
    "sg:postcode":"60655",
    "sg:province":"IL",
    "sg:tags":[
        "car"
    ],
    "wof:name":"Hallberg-Valek Katherine Ins",
    "wof:placetype":"venue"
},
  "geometry": {"coordinates":[-87.698898,41.691502],"type":"Point"}
}