{
  "type": "Feature",
  "properties": {
    "iso:country":"US",
    "sg:address":"310 12th St",
    "sg:city":"Mendota",
    "sg:classifiers":[
        {
            "category":"Shopping",
            "subcategory":"Bicycles & Sporting Goods",
            "type":"Retail Goods"
        }
    ],
    "sg:phone":"+1   ",
    "sg:postcode":"61342",
    "sg:province":"IL",
    "wof:name":"Freds Fishing & Hunting Sups",
    "wof:placetype":"venue"
},
  "geometry": {"coordinates":[-89.112978,41.555101],"type":"Point"}
}