{
  "type": "Feature",
  "properties": {
    "addr:full":"2439 Glenwood Ave Joliet IL 60435",
    "addr:housenumber":"2439",
    "addr:postcode":"60435",
    "addr:street":"Glenwood Ave",
    "iso:country":"US",
    "sg:address":"2439 Glenwood Ave",
    "sg:city":"Joliet",
    "sg:classifiers":[
        {
            "category":"Insurance",
            "subcategory":"Insurance Agent",
            "type":"Services"
        }
    ],
    "sg:phone":"+1 815 730 3510",
    "sg:postcode":"60435",
    "sg:province":"IL",
    "sg:website":"www.kskjlife.com",
    "wof:name":"Amer Slovenian Catholic Union",
    "wof:placetype":"venue"
},
  "geometry": {"coordinates":[-88.14267,41.529534],"type":"Point"}
}