{
  "type": "Feature",
  "properties": {
    "iso:country":"US",
    "sg:address":"407 Filbert St",
    "sg:city":"Odin",
    "sg:classifiers":[
        {
            "category":"Personal",
            "subcategory":"Beauty Salon",
            "type":"Services"
        }
    ],
    "sg:phone":"+1 618 775 6773",
    "sg:postcode":"62870",
    "sg:province":"IL",
    "wof:name":"Holly's Highlights & Moore",
    "wof:placetype":"venue"
},
  "geometry": {"coordinates":[-89.049768,38.614657],"type":"Point"}
}