{
  "type": "Feature",
  "properties": {
    "addr:full":"4234 S Bunker Hill Rd German Valley IL 61039",
    "addr:housenumber":"4234",
    "addr:postcode":"61039",
    "addr:street":"S Bunker Hill Rd",
    "iso:country":"US",
    "sg:address":"4234 S Bunker Hill Rd",
    "sg:city":"German Valley",
    "sg:phone":"+1 815 362 5711",
    "sg:postcode":"61039",
    "sg:province":"IL",
    "sg:tags":[
        "farm",
        "corn",
        "soybean"
    ],
    "wof:name":"Kenneth Juergens",
    "wof:placetype":"venue"
},
  "geometry": {"coordinates":[-89.493785,42.240746],"type":"Point"}
}