{
  "type": "Feature",
  "properties": {
    "addr:full":"300 N Goodwin Ave Urbana IL 61801",
    "addr:housenumber":"300",
    "addr:postcode":"61801",
    "addr:street":"N Goodwin Ave",
    "iso:country":"US",
    "sg:address":"300 N Goodwin Ave",
    "sg:city":"Urbana",
    "sg:classifiers":[
        {
            "category":"Communications",
            "subcategory":"Radio Station",
            "type":"Services"
        }
    ],
    "sg:phone":"+1 217 333 0850",
    "sg:postcode":"61801",
    "sg:province":"IL",
    "wof:name":"Will Am-Fm Radio",
    "wof:placetype":"venue"
},
  "geometry": {"coordinates":[-88.22380099999999,40.114601],"type":"Point"}
}