{
  "type": "Feature",
  "properties": {
    "iso:country":"US",
    "sg:address":"2623 W Armitage Avenue",
    "sg:city":"Chicago",
    "sg:classifiers":[
        {
            "category":"Banks & Credit Unions",
            "subcategory":"Financial Services",
            "type":"Services"
        }
    ],
    "sg:phone":"+1 773 235 3030",
    "sg:postcode":"60647",
    "sg:province":"IL",
    "sg:tags":[
        "broker",
        "mortgage"
    ],
    "wof:name":"Accelerated Funding",
    "wof:placetype":"venue"
},
  "geometry": {"coordinates":[-87.693191,41.917414],"type":"Point"}
}