{
  "type": "Feature",
  "properties": {
    "iso:country":"US",
    "sg:address":"2022 S Archer Ave Unit North",
    "sg:city":"Chicago",
    "sg:classifiers":[
        {
            "category":"Restaurant",
            "type":"Food & Drink"
        }
    ],
    "sg:phone":"+1 312 225 8282",
    "sg:postcode":"60616",
    "sg:province":"IL",
    "sg:tags":[
        "chinese"
    ],
    "sg:website":"www.chicagotastycity.com",
    "wof:name":"Tasty City",
    "wof:placetype":"venue"
},
  "geometry": {"coordinates":[-87.63224599999999,41.854751],"type":"Point"}
}