{
  "type": "Feature",
  "properties": {
    "addr:full":"340 Fredericksburg Dr Belleville IL 62223",
    "addr:housenumber":"340",
    "addr:postcode":"62223",
    "addr:street":"Fredericksburg Dr",
    "iso:country":"US",
    "sg:address":"340 Fredericksburg Dr",
    "sg:city":"Belleville",
    "sg:classifiers":[
        {
            "category":"Building & Trades",
            "subcategory":"Construction",
            "type":"Services"
        }
    ],
    "sg:phone":"+1 618 277 1011",
    "sg:postcode":"62223",
    "sg:province":"IL",
    "sg:tags":[
        "steel",
        "erectors"
    ],
    "wof:name":"Tri-Star Steel Erectors Inc",
    "wof:placetype":"venue"
},
  "geometry": {"coordinates":[-90.04124299999999,38.533734],"type":"Point"}
}