{
  "type": "Feature",
  "properties": {
    "addr:full":"McCormick Place Convention Center 2301 S Lake Shore Dr Chicago IL 60616",
    "addr:housenumber":"2301",
    "addr:postcode":"60616",
    "addr:street":"S Lake Shore Dr",
    "iso:country":"US",
    "sg:address":"McCormick Place Convention Center 2301 S Lake Shore Dr",
    "sg:city":"Chicago",
    "sg:classifiers":[
        {
            "category":"Arts & Performance",
            "subcategory":"Arts Center",
            "type":"Entertainment"
        },
        {
            "category":"Retail",
            "subcategory":"Event Space",
            "type":"Services"
        }
    ],
    "sg:phone":"+1 312 791 6000",
    "sg:postcode":"60616",
    "sg:province":"IL",
    "sg:tags":[
        "performing",
        "venue"
    ],
    "wof:name":"Arie Crown Theater At McCormick Place",
    "wof:placetype":"venue"
},
  "geometry": {"coordinates":[-87.615476,41.850227],"type":"Point"}
}