{
  "type": "Feature",
  "properties": {
    "addr:full":"5390 Williams Dr Roscoe IL 61073",
    "addr:housenumber":"5390",
    "addr:postcode":"61073",
    "addr:street":"Williams Dr",
    "iso:country":"US",
    "sg:address":"5390 Williams Dr",
    "sg:city":"Roscoe",
    "sg:classifiers":[
        {
            "category":"Banks & Credit Unions",
            "subcategory":"Bank",
            "type":"Services"
        },
        {
            "category":"Banks & Credit Unions",
            "subcategory":"Financial Services",
            "type":"Services"
        }
    ],
    "sg:phone":"+1 815 623 5243",
    "sg:postcode":"61073",
    "sg:province":"IL",
    "sg:tags":[
        "loan"
    ],
    "sg:website":"http://www.gatewaycb.com",
    "wof:name":"Gateway Community Bank",
    "wof:placetype":"venue"
},
  "geometry": {"coordinates":[-89.013603,42.42103],"type":"Point"}
}