{
  "type": "Feature",
  "properties": {
    "iso:country":"US",
    "sg:address":"406 N Center St",
    "sg:city":"Durand",
    "sg:classifiers":[
        {
            "category":"Manufacturing",
            "subcategory":"Printing",
            "type":"Manufacturing & Wholesale Goods"
        }
    ],
    "sg:phone":"+1 815 248 6497",
    "sg:postcode":"61024",
    "sg:province":"IL",
    "sg:tags":[
        "newspaper",
        "publisher"
    ],
    "wof:name":"Rock Valley Publishing Co LLC",
    "wof:placetype":"venue"
},
  "geometry": {"coordinates":[-89.33204,42.436573],"type":"Point"}
}