{
  "type": "Feature",
  "properties": {
    "iso:country":"US",
    "sg:address":"6100 W Main St",
    "sg:city":"Belleville",
    "sg:classifiers":[
        {
            "category":"Banks & Credit Unions",
            "subcategory":"Bank",
            "type":"Services"
        }
    ],
    "sg:phone":"+1 618 233 8073",
    "sg:postcode":"62223",
    "sg:province":"IL",
    "sg:tags":[
        "state"
    ],
    "sg:website":"www.catholicandcommunitycu.com",
    "wof:name":"Catholic & Community Credit",
    "wof:placetype":"venue"
},
  "geometry": {"coordinates":[-90.03772600000001,38.551918],"type":"Point"}
}