{
  "type": "Feature",
  "properties": {
    "iso:country":"US",
    "sg:address":"10144 Highway 127",
    "sg:city":"Murphysboro",
    "sg:classifiers":[
        {
            "category":"Professional",
            "subcategory":"Art Services",
            "type":"Services"
        }
    ],
    "sg:phone":"+1 618 303 3368",
    "sg:postcode":"62966",
    "sg:province":"IL",
    "sg:tags":[
        "designer",
        "display",
        "producer"
    ],
    "wof:name":"Striking Designs",
    "wof:placetype":"venue"
},
  "geometry": {"coordinates":[-89.324188,37.741537],"type":"Point"}
}