{
  "type": "Feature",
  "properties": {
    "iso:country":"US",
    "sg:address":"544 E Benton St",
    "sg:city":"Aurora",
    "sg:classifiers":[
        {
            "category":"Retail",
            "subcategory":"Auto Repair",
            "type":"Services"
        }
    ],
    "sg:phone":"+1 630 236 9649",
    "sg:postcode":"60505",
    "sg:province":"IL",
    "sg:tags":[
        "repairing",
        "automobile"
    ],
    "wof:name":"Jorge's Auto Svc",
    "wof:placetype":"venue"
},
  "geometry": {"coordinates":[-88.307894,41.751705],"type":"Point"}
}