{
  "type": "Feature",
  "properties": {
    "addr:full":"10776 State Rte 153 Coulterville IL 62237",
    "addr:housenumber":"10776",
    "addr:postcode":"62237",
    "addr:street":"State Rte 153",
    "iso:country":"US",
    "sg:address":"10776 State Rte 153",
    "sg:city":"Coulterville",
    "sg:classifiers":[
        {
            "category":"Shopping",
            "subcategory":"Gifts & Souvenirs",
            "type":"Retail Goods"
        }
    ],
    "sg:phone":"+1 618 758 2703",
    "sg:postcode":"62237",
    "sg:province":"IL",
    "sg:tags":[
        "shop",
        "honey",
        "product",
        "beeping",
        "mfg"
    ],
    "wof:name":"D & H Florist and Candle Shop",
    "wof:placetype":"venue"
},
  "geometry": {"coordinates":[-89.610482,38.203937],"type":"Point"}
}