{
  "type": "Feature",
  "properties": {
    "addr:full":"1956 W Cermak Rd Chicago IL 60608",
    "addr:housenumber":"1956",
    "addr:postcode":"60608",
    "addr:street":"W Cermak Rd",
    "iso:country":"US",
    "sg:address":"1956 W Cermak Rd",
    "sg:city":"Chicago",
    "sg:classifiers":[
        {
            "category":"Retail",
            "subcategory":"Photofinishing",
            "type":"Services"
        },
        {
            "category":"Retail",
            "subcategory":"Portrait Studio",
            "type":"Services"
        },
        {
            "category":"Professional",
            "subcategory":"Art Services",
            "type":"Services"
        }
    ],
    "sg:phone":"+1 773 475 7922",
    "sg:postcode":"60608",
    "sg:province":"IL",
    "sg:tags":[
        "rental",
        "photographers-portrait",
        "darkroom",
        "photo",
        "retouching",
        "restoration",
        "photographic"
    ],
    "wof:name":"Foto",
    "wof:placetype":"venue"
},
  "geometry": {"coordinates":[-87.67478300000001,41.852195],"type":"Point"}
}