{
  "type": "Feature",
  "properties": {
    "addr:full":"621 N Shelby Ave Salem IL 62881",
    "addr:housenumber":"621",
    "addr:postcode":"62881",
    "addr:street":"N Shelby Ave",
    "iso:country":"US",
    "sg:address":"621 N Shelby Ave",
    "sg:city":"Salem",
    "sg:classifiers":[
        {
            "category":"Social Services",
            "subcategory":"Child Care",
            "type":"Services"
        }
    ],
    "sg:phone":"+1 618 548 5797",
    "sg:postcode":"62881",
    "sg:province":"IL",
    "wof:name":"Kid Care Inc",
    "wof:placetype":"venue"
},
  "geometry": {"coordinates":[-88.93920799999999,38.632073],"type":"Point"}
}