{
  "type": "Feature",
  "properties": {
    "addr:full":"5746 N Western Ave Chicago IL 60659",
    "addr:housenumber":"5746",
    "addr:postcode":"60659",
    "addr:street":"N Western Ave",
    "iso:country":"US",
    "sg:address":"5746 N Western Ave",
    "sg:city":"Chicago",
    "sg:classifiers":[
        {
            "category":"Manufacturing",
            "subcategory":"Printing",
            "type":"Manufacturing & Wholesale Goods"
        }
    ],
    "sg:phone":"+1 773 561 9815",
    "sg:postcode":"60659",
    "sg:province":"IL",
    "sg:tags":[
        "lithographic",
        "commercial",
        "ty"
    ],
    "wof:name":"Weber Press Inc",
    "wof:placetype":"venue"
},
  "geometry": {"coordinates":[-87.6896,41.985954],"type":"Point"}
}