{
  "type": "Feature",
  "properties": {
    "addr:full":"3716 N. Cicero Ave. Chicago, IL. 60641 Chicago IL 60641",
    "addr:housenumber":"3716",
    "addr:postcode":"60641;60641",
    "addr:street":"N. Cicero Ave.",
    "iso:country":"US",
    "sg:address":"3716 N. Cicero Ave. Chicago, IL. 60641",
    "sg:city":"Chicago",
    "sg:classifiers":[
        {
            "category":"Education",
            "subcategory":"School",
            "type":"Public Place"
        },
        {
            "category":"Arena",
            "subcategory":"Sports Club",
            "type":"Entertainment"
        }
    ],
    "sg:phone":"+1 773 727 0550",
    "sg:postcode":"60641",
    "sg:province":"IL",
    "sg:tags":[
        "martial art"
    ],
    "sg:website":"wwwchicagofutsao.com/",
    "wof:name":"Chicago Fut Sao Wing Chun Association",
    "wof:placetype":"venue"
},
  "geometry": {"coordinates":[-87.747167,41.948515],"type":"Point"}
}