{
  "type": "Feature",
  "properties": {
    "iso:country":"US",
    "sg:address":"2135 11th St",
    "sg:city":"Rockford",
    "sg:classifiers":[
        {
            "category":"Professional",
            "subcategory":"Printing & Photocopies",
            "type":"Services"
        }
    ],
    "sg:phone":"+1 815 968 0208",
    "sg:postcode":"61104",
    "sg:province":"IL",
    "sg:tags":[
        "print",
        "photocopying",
        "lithographic"
    ],
    "sg:website":"www.11thstreetexpress.com",
    "wof:name":"11th Street Express Printing",
    "wof:placetype":"venue"
},
  "geometry": {"coordinates":[-89.072206,42.244845],"type":"Point"}
}