{
  "type": "Feature",
  "properties": {
    "iso:country":"US",
    "sg:address":"15 Laura Ln",
    "sg:city":"Highland",
    "sg:classifiers":[
        {
            "category":"Professional",
            "subcategory":"Management & Consulting",
            "type":"Services"
        }
    ],
    "sg:phone":"+1 618 651 8417",
    "sg:postcode":"62249",
    "sg:province":"IL",
    "sg:tags":[
        "new",
        "car"
    ],
    "wof:name":"Mercedes-Benz",
    "wof:placetype":"venue"
},
  "geometry": {"coordinates":[-89.688717,38.772333],"type":"Point"}
}