{
  "type": "Feature",
  "properties": {
    "iso:country":"US",
    "sg:address":"925 6th Ave",
    "sg:city":"Aurora",
    "sg:classifiers":[
        {
            "category":"Social Services",
            "subcategory":"Adult Care",
            "type":"Services"
        }
    ],
    "sg:phone":"+1 630 898 7844",
    "sg:postcode":"60505",
    "sg:province":"IL",
    "sg:tags":[
        "residential",
        "skilled",
        "nursing",
        "facility"
    ],
    "sg:website":"www.sunnymere.com",
    "wof:name":"Sunnymere",
    "wof:placetype":"venue"
},
  "geometry": {"coordinates":[-88.293563,41.742962],"type":"Point"}
}