{
  "type": "Feature",
  "properties": {
    "addr:full":"120 N Clifton Dr Round Lake IL 60073",
    "addr:housenumber":"120",
    "addr:postcode":"60073",
    "addr:street":"N Clifton Dr",
    "iso:country":"US",
    "sg:address":"120 N Clifton Dr",
    "sg:city":"Round Lake",
    "sg:classifiers":[
        {
            "category":"Professional",
            "subcategory":"Business Services",
            "type":"Services"
        }
    ],
    "sg:phone":"+1 847 546 1111",
    "sg:postcode":"60073",
    "sg:province":"IL",
    "sg:tags":[
        "trade",
        "contractor"
    ],
    "wof:name":"A-1 Quality Pool Service",
    "wof:placetype":"venue"
},
  "geometry": {"coordinates":[-88.07984,42.351209],"type":"Point"}
}