{
  "type": "Feature",
  "properties": {
    "addr:full":"609 NW 9th Ave Aledo IL 61231",
    "addr:housenumber":"609",
    "addr:postcode":"61231",
    "addr:street":"Nw 9Th Ave",
    "iso:country":"US",
    "sg:address":"609 NW 9th Ave",
    "sg:city":"Aledo",
    "sg:classifiers":[
        {
            "category":"Building & Trades",
            "subcategory":"Construction",
            "type":"Services"
        }
    ],
    "sg:phone":"+1 309 582 2939",
    "sg:postcode":"61231",
    "sg:province":"IL",
    "sg:tags":[
        "house",
        "construct",
        "contractor"
    ],
    "wof:name":"Blaser Builders & Remodeling",
    "wof:placetype":"venue"
},
  "geometry": {"coordinates":[-90.758454,41.207325],"type":"Point"}
}