{
  "type": "Feature",
  "properties": {
    "iso:country":"US",
    "sg:address":"486 N Main St",
    "sg:city":"Canton",
    "sg:classifiers":[
        {
            "category":"Professional",
            "subcategory":"Accounting & Tax Preparation",
            "type":"Services"
        }
    ],
    "sg:phone":"+1 309 647 2505",
    "sg:postcode":"61520",
    "sg:province":"IL",
    "sg:tags":[
        "return",
        "filing"
    ],
    "wof:name":"H & R Block Tax Svc",
    "wof:placetype":"venue"
},
  "geometry": {"coordinates":[-90.035158,40.560816],"type":"Point"}
}