{
  "type": "Feature",
  "properties": {
    "addr:full":"3859 W North Ave Chicago IL 60647",
    "addr:housenumber":"3859",
    "addr:postcode":"60647",
    "addr:street":"W North Ave",
    "iso:country":"US",
    "sg:address":"3859 W North Ave",
    "sg:city":"Chicago",
    "sg:classifiers":[
        {
            "category":"Retail",
            "subcategory":"Laundry & Dry Cleaning",
            "type":"Services"
        }
    ],
    "sg:phone":"+1 773 227 5212",
    "sg:postcode":"60647",
    "sg:province":"IL",
    "sg:tags":[
        "cleaners"
    ],
    "wof:name":"Choice Cleaners",
    "wof:placetype":"venue"
},
  "geometry": {"coordinates":[-87.724101,41.909882],"type":"Point"}
}