{
  "type": "Feature",
  "properties": {
    "iso:country":"US",
    "sg:address":"11405 Main St",
    "sg:city":"Roscoe",
    "sg:classifiers":[
        {
            "category":"Real Estate",
            "subcategory":"Real Estate Agent",
            "type":"Services"
        }
    ],
    "sg:phone":"+1 815 623 4025",
    "sg:postcode":"61073",
    "sg:province":"IL",
    "wof:name":"Nancy Newsom",
    "wof:placetype":"venue"
},
  "geometry": {"coordinates":[-89.01215,42.427128],"type":"Point"}
}