{
  "type": "Feature",
  "properties": {
    "iso:country":"US",
    "sg:address":"20121 Crawford Ave",
    "sg:city":"Olympia Fields",
    "sg:classifiers":[
        {
            "category":"Local Transit",
            "type":"Transportation"
        },
        {
            "category":"Wholesale",
            "subcategory":"Motor Vehicles",
            "type":"Manufacturing & Wholesale Goods"
        }
    ],
    "sg:phone":"+1 708 481 1774",
    "sg:postcode":"60443",
    "sg:province":"IL",
    "sg:tags":[
        "passenger",
        "hearse",
        "ambulance"
    ],
    "wof:name":"Alverno Ambulance Service",
    "wof:placetype":"venue"
},
  "geometry": {"coordinates":[-87.713165,41.522853],"type":"Point"}
}