{
  "type": "Feature",
  "properties": {
    "iso:country":"US",
    "sg:address":"8429 88th St W",
    "sg:city":"Taylor Ridge",
    "sg:phone":"+1 309 798 2791",
    "sg:postcode":"61284",
    "sg:province":"IL",
    "sg:tags":[
        "farm",
        "corn",
        "soybean"
    ],
    "wof:name":"James Bohnsack",
    "wof:placetype":"venue"
},
  "geometry": {"coordinates":[-90.69493799999999,41.441061],"type":"Point"}
}