{
  "type": "Feature",
  "properties": {
    "iso:country":"US",
    "sg:address":"535 Thomas Rd",
    "sg:city":"Bolingbrook",
    "sg:classifiers":[
        {
            "category":"Professional",
            "subcategory":"Engineering",
            "type":"Services"
        }
    ],
    "sg:phone":"+1 630 783 9685",
    "sg:postcode":"60440",
    "sg:province":"IL",
    "wof:name":"Sess Midwest LLC",
    "wof:placetype":"venue"
},
  "geometry": {"coordinates":[-88.067868,41.714569],"type":"Point"}
}