{
  "type": "Feature",
  "properties": {
    "addr:full":"17951 Huntleigh Ct Country Club Hills IL 60478",
    "addr:housenumber":"17951",
    "addr:postcode":"60478",
    "addr:street":"Huntleigh Ct",
    "iso:country":"US",
    "sg:address":"17951 Huntleigh Ct",
    "sg:city":"Country Club Hills",
    "sg:classifiers":[
        {
            "category":"Freight",
            "type":"Transportation"
        }
    ],
    "sg:phone":"+1 708 417 2816",
    "sg:postcode":"60478",
    "sg:province":"IL",
    "wof:name":"Lundys Transportation",
    "wof:placetype":"venue"
},
  "geometry": {"coordinates":[-87.717292,41.562924],"type":"Point"}
}