{
  "type": "Feature",
  "properties": {
    "iso:country":"US",
    "sg:address":"6 Meadow Ave",
    "sg:city":"Rockdale",
    "sg:classifiers":[
        {
            "category":"Wholesale",
            "subcategory":"Machinery & Supplies",
            "type":"Manufacturing & Wholesale Goods"
        }
    ],
    "sg:phone":"+1 815 729 3725",
    "sg:postcode":"60436",
    "sg:province":"IL",
    "sg:tags":[
        "equipment",
        "barber"
    ],
    "wof:name":"Borellas Barber Shop",
    "wof:placetype":"venue"
},
  "geometry": {"coordinates":[-88.105958,41.507123],"type":"Point"}
}