{
  "type": "Feature",
  "properties": {
    "addr:full":"176 Co Rd 1800 N Seymour IL 61875",
    "addr:housenumber":"176",
    "addr:postcode":"61875",
    "addr:street":"Co Rd 1800 N",
    "iso:country":"US",
    "sg:address":"176 Co Rd 1800 N",
    "sg:city":"Seymour",
    "sg:classifiers":[
        {
            "category":"Farming",
            "subcategory":"Farm",
            "type":"Manufacturing & Wholesale Goods"
        }
    ],
    "sg:phone":"+1 217 687 2806",
    "sg:postcode":"61875",
    "sg:province":"IL",
    "sg:tags":[
        "crop",
        "general"
    ],
    "wof:name":"Hogan Farms",
    "wof:placetype":"venue"
},
  "geometry": {"coordinates":[-88.450886,40.142332],"type":"Point"}
}