{
  "type": "Feature",
  "properties": {
    "addr:full":"12343 S Latrobe Ave Alsip IL 60803",
    "addr:housenumber":"12343",
    "addr:postcode":"60803",
    "addr:street":"S Latrobe Ave",
    "iso:country":"US",
    "sg:address":"12343 S Latrobe Ave",
    "sg:city":"Alsip",
    "sg:classifiers":[
        {
            "category":"Food & Beverages",
            "subcategory":"Meat & Fish",
            "type":"Retail Goods"
        }
    ],
    "sg:phone":"+1 708 389 3433",
    "sg:postcode":"60803",
    "sg:province":"IL",
    "sg:tags":[
        "shop"
    ],
    "wof:name":"Firehouse Jerky",
    "wof:placetype":"venue"
},
  "geometry": {"coordinates":[-87.751147,41.667295],"type":"Point"}
}