{
  "type": "Feature",
  "properties": {
    "iso:country":"US",
    "sg:address":"214 Lexington",
    "sg:city":"Quincy",
    "sg:classifiers":[
        {
            "category":"Real Estate",
            "subcategory":"Real Estate Agent",
            "type":"Services"
        }
    ],
    "sg:phone":"+1 217 223 9747",
    "sg:postcode":"62305",
    "sg:province":"IL",
    "wof:name":"Farmers National Co",
    "wof:placetype":"venue"
},
  "geometry": {"coordinates":[-91.343554,39.933441],"type":"Point"}
}