{
  "type": "Feature",
  "properties": {
    "iso:country":"US",
    "sg:address":"1140 W Erie St",
    "sg:city":"Chicago",
    "sg:classifiers":[
        {
            "category":"Banks & Credit Unions",
            "subcategory":"Investment Brokerage",
            "type":"Services"
        }
    ],
    "sg:phone":"+1 312 633 9700",
    "sg:postcode":"60642",
    "sg:province":"IL",
    "sg:tags":[
        "trust"
    ],
    "wof:name":"Nib Foundation",
    "wof:placetype":"venue"
},
  "geometry": {"coordinates":[-87.656346,41.89328],"type":"Point"}
}