{
  "type": "Feature",
  "properties": {
    "addr:full":"1713 S West St Jacksonville IL 62650",
    "addr:housenumber":"1713",
    "addr:postcode":"62650",
    "addr:street":"S;St",
    "iso:country":"US",
    "sg:address":"1713 S West St",
    "sg:city":"Jacksonville",
    "sg:classifiers":[
        {
            "category":"Health Services",
            "subcategory":"Doctor",
            "type":"Services"
        }
    ],
    "sg:phone":"+1 217 245 6413",
    "sg:postcode":"62650",
    "sg:province":"IL",
    "sg:tags":[
        "professional",
        "medical",
        "employer"
    ],
    "sg:website":"http://www.iahperd.org",
    "wof:name":"Ill Assoc Hlth Phys Ed Rec &",
    "wof:placetype":"venue"
},
  "geometry": {"coordinates":[-90.231883,39.710349],"type":"Point"}
}