{
  "type": "Feature",
  "properties": {
    "iso:country":"US",
    "sg:address":"4440 W 95th St",
    "sg:city":"Oak Lawn",
    "sg:classifiers":[
        {
            "category":"Health Services",
            "subcategory":"Hospital",
            "type":"Services"
        }
    ],
    "sg:phone":"+1 708 346 1337",
    "sg:postcode":"60453",
    "sg:province":"IL",
    "sg:tags":[
        "specialty"
    ],
    "wof:name":"Advocate Substance Abuse",
    "wof:placetype":"venue"
},
  "geometry": {"coordinates":[-87.733406,41.720296],"type":"Point"}
}