{
  "type": "Feature",
  "properties": {
    "addr:full":"6054 N Broadway St Chicago IL 60660",
    "addr:housenumber":"6054",
    "addr:postcode":"60660",
    "addr:street":"N Broadway St",
    "iso:country":"US",
    "sg:address":"6054 N Broadway St",
    "sg:city":"Chicago",
    "sg:classifiers":[
        {
            "category":"Home & Garden",
            "subcategory":"Home Furnishings",
            "type":"Retail Goods"
        }
    ],
    "sg:phone":"+1 773 622 3402",
    "sg:postcode":"60660",
    "sg:province":"IL",
    "sg:tags":[
        "antique",
        "curtain",
        "made",
        "drapery"
    ],
    "wof:name":"Art of Living",
    "wof:placetype":"venue"
},
  "geometry": {"coordinates":[-87.66041300000001,41.992109],"type":"Point"}
}