{
  "type": "Feature",
  "properties": {
    "iso:country":"US",
    "sg:address":"2162 Acorn Ct",
    "sg:city":"Wheaton",
    "sg:classifiers":[
        {
            "category":"Professional",
            "subcategory":"Management & Consulting",
            "type":"Services"
        }
    ],
    "sg:phone":"+1 630 462 0493",
    "sg:postcode":"60187",
    "sg:province":"IL",
    "sg:tags":[
        "business"
    ],
    "wof:name":"Acorn Holdings",
    "wof:placetype":"venue"
},
  "geometry": {"coordinates":[-88.076514,41.828461],"type":"Point"}
}