{
  "type": "Feature",
  "properties": {
    "addr:full":"33 W Ontario St Chicago IL 60654",
    "addr:housenumber":"33",
    "addr:postcode":"60654",
    "addr:street":"W Ontario St",
    "iso:country":"US",
    "sg:address":"33 W Ontario St",
    "sg:city":"Chicago",
    "sg:classifiers":[
        {
            "category":"Communications",
            "subcategory":"Film & Video Production",
            "type":"Services"
        }
    ],
    "sg:phone":"+1 312 951 8000",
    "sg:postcode":"60654",
    "sg:province":"IL",
    "sg:tags":[
        "services-commercial"
    ],
    "wof:name":"C T B Media",
    "wof:placetype":"venue"
},
  "geometry": {"coordinates":[-87.629456,41.893266],"type":"Point"}
}