{
  "type": "Feature",
  "properties": {
    "addr:full":"1029 Commonwealth Ct Bolingbrook IL 60440",
    "addr:housenumber":"1029",
    "addr:postcode":"60440",
    "addr:street":"Commonwealth Ct",
    "iso:country":"US",
    "sg:address":"1029 Commonwealth Ct",
    "sg:city":"Bolingbrook",
    "sg:classifiers":[
        {
            "category":"Professional",
            "type":"Services"
        }
    ],
    "sg:phone":"+1 630 679 1330",
    "sg:postcode":"60440",
    "sg:province":"IL",
    "sg:tags":[
        "establishment"
    ],
    "wof:name":"C C Intl",
    "wof:placetype":"venue"
},
  "geometry": {"coordinates":[-88.11310899999999,41.700442],"type":"Point"}
}