{
  "type": "Feature",
  "properties": {
    "addr:full":"3941 W Armitage Ave Chicago IL 60647",
    "addr:housenumber":"3941",
    "addr:postcode":"60647",
    "addr:street":"W Armitage Ave",
    "iso:country":"US",
    "sg:address":"3941 W Armitage Ave",
    "sg:city":"Chicago",
    "sg:classifiers":[
        {
            "category":"Real Estate",
            "subcategory":"Real Estate Agent",
            "type":"Services"
        }
    ],
    "sg:phone":"+1 773 278 3881",
    "sg:postcode":"60647",
    "sg:province":"IL",
    "wof:name":"Burgos Real Estate",
    "wof:placetype":"venue"
},
  "geometry": {"coordinates":[-87.72644699999999,41.917092],"type":"Point"}
}