{
  "type": "Feature",
  "properties": {
    "iso:country":"US",
    "sg:address":"216 E Broadway",
    "sg:city":"Alton",
    "sg:classifiers":[
        {
            "category":"Shopping",
            "subcategory":"Used Merchandise",
            "type":"Retail Goods"
        }
    ],
    "sg:phone":"+1 618 462 5696",
    "sg:postcode":"62002",
    "sg:province":"IL",
    "sg:tags":[
        "pawnbroker"
    ],
    "wof:name":"Sam's Loan",
    "wof:placetype":"venue"
},
  "geometry": {"coordinates":[-90.184004,38.890154],"type":"Point"}
}