{
  "type": "Feature",
  "properties": {
    "iso:country":"US",
    "sg:address":"2829 167th St",
    "sg:city":"Hazel Crest",
    "sg:classifiers":[
        {
            "category":"Retail",
            "subcategory":"Auto Repair",
            "type":"Services"
        }
    ],
    "sg:phone":"+1 708 596 0249",
    "sg:postcode":"60429",
    "sg:province":"IL",
    "sg:tags":[
        "general"
    ],
    "wof:name":"Whitlows Auto Repair",
    "wof:placetype":"venue"
},
  "geometry": {"coordinates":[-87.685165,41.586222],"type":"Point"}
}