{
  "type": "Feature",
  "properties": {
    "addr:full":"2698 N 900 East Rd Ashkum IL 60911",
    "addr:housenumber":"2698",
    "addr:postcode":"60911",
    "addr:street":"N 900 East Rd",
    "iso:country":"US",
    "sg:address":"2698 N 900 East Rd",
    "sg:city":"Ashkum",
    "sg:classifiers":[
        {
            "category":"Wholesale",
            "subcategory":"Groceries",
            "type":"Manufacturing & Wholesale Goods"
        }
    ],
    "sg:phone":"+1 815 698 2702",
    "sg:postcode":"60911",
    "sg:province":"IL",
    "sg:tags":[
        "import",
        "spice"
    ],
    "wof:name":"Ecips of Spice Inc",
    "wof:placetype":"venue"
},
  "geometry": {"coordinates":[-87.96210600000001,40.894551],"type":"Point"}
}