{
  "type": "Feature",
  "properties": {
    "iso:country":"US",
    "sg:address":"134 Parkview Dr",
    "sg:city":"Wauconda",
    "sg:classifiers":[
        {
            "category":"Real Estate",
            "subcategory":"Real Estate Agent",
            "type":"Services"
        }
    ],
    "sg:phone":"+1 847 526 6784",
    "sg:postcode":"60084",
    "sg:province":"IL",
    "wof:name":"RS Graybill Inc",
    "wof:placetype":"venue"
},
  "geometry": {"coordinates":[-88.143741,42.273068],"type":"Point"}
}