{
  "type": "Feature",
  "properties": {
    "addr:full":"730 S Buffalo Grove Rd Buffalo Grove IL 60089",
    "addr:housenumber":"730",
    "addr:postcode":"60089",
    "addr:street":"S Buffalo Grove Rd",
    "iso:country":"US",
    "sg:address":"730 S Buffalo Grove Rd",
    "sg:city":"Buffalo Grove",
    "sg:classifiers":[
        {
            "category":"Personal",
            "type":"Services"
        },
        {
            "category":"Personal",
            "subcategory":"Beauty Salon",
            "type":"Services"
        }
    ],
    "sg:phone":"+1 847 520 7719",
    "sg:postcode":"60089",
    "sg:province":"IL",
    "sg:tags":[
        "spa",
        "day"
    ],
    "sg:website":"www.bearjantoniosalonandspa.com",
    "wof:name":"Bearj Antonio Salon & Spa",
    "wof:placetype":"venue"
},
  "geometry": {"coordinates":[-87.958623,42.140951],"type":"Point"}
}