{
  "type": "Feature",
  "properties": {
    "addr:full":"333 E Ontario St Ste A Chicago IL 60611",
    "addr:housenumber":"333",
    "addr:postcode":"60611",
    "addr:street":"E Ontario St Ste A",
    "iso:country":"US",
    "sg:address":"333 E Ontario St Ste A",
    "sg:city":"Chicago",
    "sg:classifiers":[
        {
            "category":"Health Services",
            "subcategory":"Dentist",
            "type":"Services"
        }
    ],
    "sg:phone":"+1 312 664 6616",
    "sg:postcode":"60611",
    "sg:province":"IL",
    "sg:website":"drtilden.com",
    "wof:name":"Jordan J. Tilden, DDS & Associates",
    "wof:placetype":"venue"
},
  "geometry": {"coordinates":[-87.618735,41.893445],"type":"Point"}
}