{
  "type": "Feature",
  "properties": {
    "addr:full":"12704 Western Ave Blue Island IL 60406",
    "addr:housenumber":"12704",
    "addr:postcode":"60406",
    "addr:street":"Western Ave",
    "iso:country":"US",
    "sg:address":"12704 Western Ave",
    "sg:city":"Blue Island",
    "sg:classifiers":[
        {
            "category":"Personal",
            "subcategory":"Barber",
            "type":"Services"
        }
    ],
    "sg:phone":"+1 708 597 2288",
    "sg:postcode":"60406",
    "sg:province":"IL",
    "wof:name":"Famous Cut",
    "wof:placetype":"venue"
},
  "geometry": {"coordinates":[-87.680261,41.662457],"type":"Point"}
}