{
  "type": "Feature",
  "properties": {
    "iso:country":"US",
    "sg:address":"4853 Hydraulic Rd",
    "sg:city":"Rockford",
    "sg:classifiers":[
        {
            "category":"Manufacturing",
            "subcategory":"Metals",
            "type":"Manufacturing & Wholesale Goods"
        }
    ],
    "sg:phone":"+1 815 874 2898",
    "sg:postcode":"61109",
    "sg:province":"IL",
    "sg:tags":[
        "finisher"
    ],
    "wof:name":"Painted Parts Inc",
    "wof:placetype":"venue"
},
  "geometry": {"coordinates":[-89.02222399999999,42.227211],"type":"Point"}
}