{
  "type": "Feature",
  "properties": {
    "iso:country":"US",
    "sg:address":"271 Country Commons Rd",
    "sg:city":"Cary",
    "sg:classifiers":[
        {
            "category":"Banks & Credit Unions",
            "subcategory":"Investment Brokerage",
            "type":"Services"
        }
    ],
    "sg:phone":"+1 847 639 2080",
    "sg:postcode":"60013",
    "sg:province":"IL",
    "sg:tags":[
        "security"
    ],
    "wof:name":"Anico",
    "wof:placetype":"venue"
},
  "geometry": {"coordinates":[-88.25714499999999,42.203352],"type":"Point"}
}