{
  "type": "Feature",
  "properties": {
    "iso:country":"US",
    "sg:address":"150 E Chestnut St",
    "sg:city":"Louisville",
    "sg:classifiers":[
        {
            "category":"Autos & Motor Vehicles",
            "subcategory":"Auto Supplies",
            "type":"Retail Goods"
        }
    ],
    "sg:phone":"+1 618 665 3398",
    "sg:postcode":"62858",
    "sg:province":"IL",
    "sg:tags":[
        "automobile",
        "part",
        "accessory"
    ],
    "wof:name":"Louisville Auto Parts, Inc.",
    "wof:placetype":"venue"
},
  "geometry": {"coordinates":[-88.501206,38.77302],"type":"Point"}
}