{
  "type": "Feature",
  "properties": {
    "iso:country":"US",
    "sg:address":"626 Sheridan Rd",
    "sg:city":"Evanston",
    "sg:classifiers":[
        {
            "category":"Professional",
            "subcategory":"Management & Consulting",
            "type":"Services"
        }
    ],
    "sg:phone":"+1 847 491 9228",
    "sg:postcode":"60202",
    "sg:province":"IL",
    "sg:tags":[
        "employee",
        "assistance",
        "program"
    ],
    "wof:name":"Ayrol Young & Associates Inc",
    "wof:placetype":"venue"
},
  "geometry": {"coordinates":[-87.670709,42.027857],"type":"Point"}
}