{
  "type": "Feature",
  "properties": {
    "iso:country":"US",
    "sg:address":"11415 S Harlem Ave",
    "sg:city":"Worth",
    "sg:phone":"+1 708 923 1730",
    "sg:postcode":"60482",
    "sg:province":"IL",
    "wof:name":"Giovanni's Hair Salon",
    "wof:placetype":"venue"
},
  "geometry": {"coordinates":[-87.797256,41.683723],"type":"Point"}
}