{
  "type": "Feature",
  "properties": {
    "iso:country":"US",
    "sg:address":"701 College Rd",
    "sg:city":"Lebanon",
    "sg:classifiers":[
        {
            "category":"Education",
            "subcategory":"Library",
            "type":"Public Place"
        }
    ],
    "sg:phone":"+1 618 537 6950",
    "sg:postcode":"62254",
    "sg:province":"IL",
    "wof:name":"Holman Library",
    "wof:placetype":"venue"
},
  "geometry": {"coordinates":[-89.816245,38.605198],"type":"Point"}
}