{
  "type": "Feature",
  "properties": {
    "iso:country":"US",
    "sg:address":"1467 E 53rd St",
    "sg:city":"Chicago",
    "sg:classifiers":[
        {
            "category":"Manufacturing",
            "subcategory":"Tobacco Products",
            "type":"Manufacturing & Wholesale Goods"
        },
        {
            "category":"Shopping",
            "subcategory":"Tobacco",
            "type":"Retail Goods"
        },
        {
            "category":"Food & Beverages",
            "subcategory":"Groceries & Convenience Stores",
            "type":"Retail Goods"
        }
    ],
    "sg:phone":"+1 773 955 5159",
    "sg:postcode":"60615",
    "sg:province":"IL",
    "sg:tags":[
        "cigarette",
        "cigar",
        "manufacturer",
        "tobacco-wholesale"
    ],
    "wof:name":"Select Cigars & Fragrance",
    "wof:placetype":"venue"
},
  "geometry": {"coordinates":[-87.58975700000001,41.799423],"type":"Point"}
}