{
  "type": "Feature",
  "properties": {
    "addr:full":"3506 Bankview Dr Joliet IL 60431",
    "addr:housenumber":"3506",
    "addr:postcode":"60431",
    "addr:street":"Bankview Dr",
    "iso:country":"US",
    "sg:address":"3506 Bankview Dr",
    "sg:city":"Joliet",
    "sg:classifiers":[
        {
            "category":"Building & Trades",
            "subcategory":"Landscaping Services",
            "type":"Services"
        }
    ],
    "sg:phone":"+1 815 744 7883",
    "sg:postcode":"60431",
    "sg:province":"IL",
    "sg:tags":[
        "lawn",
        "maintenance",
        "grounds"
    ],
    "wof:name":"Lawn Works",
    "wof:placetype":"venue"
},
  "geometry": {"coordinates":[-88.169521,41.531672],"type":"Point"}
}