{
  "type": "Feature",
  "properties": {
    "iso:country":"US",
    "sg:address":"190 N State St Ste 1100",
    "sg:city":"Chicago",
    "sg:phone":"+1 312 750 7777",
    "sg:postcode":"60601",
    "sg:province":"IL",
    "sg:website":"http://www.abclocal.com",
    "wof:name":"Wls Tv Chicago",
    "wof:placetype":"venue"
},
  "geometry": {"coordinates":[-87.627944,41.885451],"type":"Point"}
}