{
  "type": "Feature",
  "properties": {
    "iso:country":"US",
    "sg:address":"668 E Northwest Hwy",
    "sg:city":"Palatine",
    "sg:classifiers":[
        {
            "category":"Insurance",
            "subcategory":"Insurance Agent",
            "type":"Services"
        }
    ],
    "sg:phone":"+1 847 991 3200",
    "sg:postcode":"60074",
    "sg:province":"IL",
    "wof:name":"Exam One",
    "wof:placetype":"venue"
},
  "geometry": {"coordinates":[-88.027172,42.103866],"type":"Point"}
}