{
  "type": "Feature",
  "properties": {
    "iso:country":"US",
    "sg:address":"321 W State St",
    "sg:city":"Rockford",
    "sg:classifiers":[
        {
            "category":"Social Services",
            "type":"Services"
        }
    ],
    "sg:phone":"+1 815 965 5172",
    "sg:postcode":"61101",
    "sg:province":"IL",
    "sg:tags":[
        "organization",
        "welfare"
    ],
    "wof:name":"Family Advocate Inc",
    "wof:placetype":"venue"
},
  "geometry": {"coordinates":[-89.095368,42.271653],"type":"Point"}
}