{
  "type": "Feature",
  "properties": {
    "iso:country":"US",
    "sg:address":"1690 S Randall Rd",
    "sg:city":"Geneva",
    "sg:classifiers":[
        {
            "category":"Restaurant",
            "type":"Food & Drink"
        }
    ],
    "sg:menulink":"http://www.allmenus.com/il/geneva/23400-applebees/menu/",
    "sg:phone":"+1 630 232 2280",
    "sg:postcode":"60134",
    "sg:province":"IL",
    "sg:tags":[
        "burger",
        "american",
        "sandwich",
        "soup"
    ],
    "wof:name":"Applebee's",
    "wof:placetype":"venue"
},
  "geometry": {"coordinates":[-88.340349,41.868888],"type":"Point"}
}