{
  "type": "Feature",
  "properties": {
    "addr:full":"140 Seabury Rd Bolingbrook IL 60440",
    "addr:housenumber":"140",
    "addr:postcode":"60440",
    "addr:street":"Seabury Rd",
    "iso:country":"US",
    "sg:address":"140 Seabury Rd",
    "sg:city":"Bolingbrook",
    "sg:classifiers":[
        {
            "category":"Building & Trades",
            "subcategory":"Construction",
            "type":"Services"
        }
    ],
    "sg:phone":"+1 630 739 5388",
    "sg:postcode":"60440",
    "sg:province":"IL",
    "sg:tags":[
        "excavating",
        "contractor"
    ],
    "wof:name":"Rogers Excavating Inc",
    "wof:placetype":"venue"
},
  "geometry": {"coordinates":[-88.053291,41.701541],"type":"Point"}
}