{
  "type": "Feature",
  "properties": {
    "addr:full":"642 Anthony Trl Northbrook IL 60062",
    "addr:housenumber":"642",
    "addr:postcode":"60062",
    "addr:street":"Anthony Trl",
    "iso:country":"US",
    "sg:address":"642 Anthony Trl",
    "sg:city":"Northbrook",
    "sg:classifiers":[
        {
            "category":"Professional",
            "subcategory":"Accounting & Tax Preparation",
            "type":"Services"
        }
    ],
    "sg:phone":"+1 847 480 7333",
    "sg:postcode":"60062",
    "sg:province":"IL",
    "sg:tags":[
        "accountant"
    ],
    "wof:name":"Cutler Financial Svc",
    "wof:placetype":"venue"
},
  "geometry": {"coordinates":[-87.853308,42.144879],"type":"Point"}
}