{
  "type": "Feature",
  "properties": {
    "iso:country":"US",
    "sg:address":"1225 Carnegie St",
    "sg:city":"Rolling Meadows",
    "sg:classifiers":[
        {
            "category":"Manufacturing",
            "subcategory":"Chemicals & Compounds",
            "type":"Manufacturing & Wholesale Goods"
        }
    ],
    "sg:phone":"+1 847 454 1070",
    "sg:postcode":"60008",
    "sg:province":"IL",
    "sg:tags":[
        "preparation",
        "disinfectant",
        "sanitation",
        "mfg"
    ],
    "wof:name":"Medivation Industries Inc",
    "wof:placetype":"venue"
},
  "geometry": {"coordinates":[-88.02686,42.09653],"type":"Point"}
}