{
  "type": "Feature",
  "properties": {
    "iso:country":"US",
    "sg:address":"421 N 4th St",
    "sg:city":"Chillicothe",
    "sg:classifiers":[
        {
            "category":"Home & Garden",
            "subcategory":"Furniture",
            "type":"Retail Goods"
        }
    ],
    "sg:phone":"+1 309 274 3449",
    "sg:postcode":"61523",
    "sg:province":"IL",
    "sg:tags":[
        "equipment",
        "kitchen",
        "cabinet"
    ],
    "wof:name":"Lund Kitchen & Bath Co",
    "wof:placetype":"venue"
},
  "geometry": {"coordinates":[-89.49055,40.912536],"type":"Point"}
}