{
  "type": "Feature",
  "properties": {
    "iso:country":"US",
    "sg:address":"427 Iowa Ave",
    "sg:city":"Villa Park",
    "sg:classifiers":[
        {
            "category":"Building & Trades",
            "subcategory":"Construction",
            "type":"Services"
        }
    ],
    "sg:phone":"+1 630 279 4456",
    "sg:postcode":"60181",
    "sg:province":"IL",
    "sg:tags":[
        "house"
    ],
    "wof:name":"Mike France Home Improvements",
    "wof:placetype":"venue"
},
  "geometry": {"coordinates":[-87.987249,41.899546],"type":"Point"}
}