{
  "type": "Feature",
  "properties": {
    "iso:country":"US",
    "sg:address":"3016 Argonne Dr",
    "sg:city":"North Chicago",
    "sg:classifiers":[
        {
            "category":"Building & Trades",
            "subcategory":"Electrical",
            "type":"Services"
        }
    ],
    "sg:phone":"+1 847 887 0909",
    "sg:postcode":"60064",
    "sg:province":"IL",
    "sg:tags":[
        "residential",
        "electrician"
    ],
    "wof:name":"Ohm Electric & Construction",
    "wof:placetype":"venue"
},
  "geometry": {"coordinates":[-87.870868,42.325147],"type":"Point"}
}