{
  "type": "Feature",
  "properties": {
    "iso:country":"US",
    "sg:address":"9085 State Rte 34 N",
    "sg:city":"Galatia",
    "sg:classifiers":[
        {
            "category":"Manufacturing",
            "subcategory":"Petroleum Products",
            "type":"Manufacturing & Wholesale Goods"
        },
        {
            "category":"Mining & Drilling",
            "type":"Manufacturing & Wholesale Goods"
        }
    ],
    "sg:phone":"+1 618 268 6311",
    "sg:postcode":"62935",
    "sg:province":"IL",
    "sg:tags":[
        "coal"
    ],
    "wof:name":"American Coal Company",
    "wof:placetype":"venue"
},
  "geometry": {"coordinates":[-88.583637,37.834788],"type":"Point"}
}