{
  "type": "Feature",
  "properties": {
    "iso:country":"US",
    "sg:address":"7315 W Grand Ave",
    "sg:city":"Elmwood Park",
    "sg:classifiers":[
        {
            "category":"Banks & Credit Unions",
            "subcategory":"Bank",
            "type":"Services"
        }
    ],
    "sg:phone":"+1 773 625 3300",
    "sg:postcode":"60707",
    "sg:province":"IL",
    "wof:name":"First Security Trust & Savings Bank",
    "wof:placetype":"venue"
},
  "geometry": {"coordinates":[-87.80940200000001,41.9244],"type":"Point"}
}