{
  "type": "Feature",
  "properties": {
    "iso:country":"US",
    "sg:address":"303 E Main St",
    "sg:city":"Barrington",
    "sg:classifiers":[
        {
            "category":"Professional",
            "subcategory":"Business Services",
            "type":"Services"
        }
    ],
    "sg:phone":"+1 847 277 9930",
    "sg:postcode":"60010",
    "sg:province":"IL",
    "sg:tags":[
        "property",
        "management"
    ],
    "wof:name":"McHenry Commons Partners LLC",
    "wof:placetype":"venue"
},
  "geometry": {"coordinates":[-88.13237,42.154202],"type":"Point"}
}