{
  "type": "Feature",
  "properties": {
    "iso:country":"US",
    "sg:address":"970 N Shore Dr",
    "sg:city":"Lake Bluff",
    "sg:classifiers":[
        {
            "category":"Retail",
            "subcategory":"Animal Services",
            "type":"Services"
        }
    ],
    "sg:phone":"+1 847 234 6200",
    "sg:postcode":"60044",
    "sg:province":"IL",
    "sg:tags":[
        "pet",
        "boarding",
        "sitting"
    ],
    "wof:name":"A Yuppy Puppy Inc",
    "wof:placetype":"venue"
},
  "geometry": {"coordinates":[-87.870838,42.272789],"type":"Point"}
}