{
  "type": "Feature",
  "properties": {
    "iso:country":"US",
    "sg:address":"2113 W Chicago Ave",
    "sg:city":"Chicago",
    "sg:classifiers":[
        {
            "category":"Personal",
            "subcategory":"Beauty Salon",
            "type":"Services"
        }
    ],
    "sg:phone":"+1 773 342 2996",
    "sg:postcode":"60612",
    "sg:province":"IL",
    "sg:tags":[
        "hair"
    ],
    "wof:name":"Shampoo Salon",
    "wof:placetype":"venue"
},
  "geometry": {"coordinates":[-87.680138,41.895835],"type":"Point"}
}