{
  "type": "Feature",
  "properties": {
    "addr:full":"66 W Ferguson Ave Wood River IL 62095",
    "addr:housenumber":"66",
    "addr:postcode":"62095",
    "addr:street":"W Ferguson Ave",
    "iso:country":"US",
    "sg:address":"66 W Ferguson Ave",
    "sg:city":"Wood River",
    "sg:classifiers":[
        {
            "category":"Personal",
            "subcategory":"Beauty Salon",
            "type":"Services"
        }
    ],
    "sg:phone":"+1 618 254 9711",
    "sg:postcode":"62095",
    "sg:province":"IL",
    "wof:name":"LA Bonita Beauty Salon",
    "wof:placetype":"venue"
},
  "geometry": {"coordinates":[-90.09891,38.860884],"type":"Point"}
}