{
  "type": "Feature",
  "properties": {
    "iso:country":"US",
    "sg:address":"436 Park Ave",
    "sg:city":"Clarendon Hills",
    "sg:classifiers":[
        {
            "category":"Professional",
            "subcategory":"Business Services",
            "type":"Services"
        }
    ],
    "sg:phone":"+1 630 887 1718",
    "sg:postcode":"60514",
    "sg:province":"IL",
    "sg:tags":[
        "packaging"
    ],
    "wof:name":"Arnquist Packaging Corp",
    "wof:placetype":"venue"
},
  "geometry": {"coordinates":[-87.963491,41.794939],"type":"Point"}
}