{
  "type": "Feature",
  "properties": {
    "iso:country":"US",
    "sg:address":"5301 Dempster St",
    "sg:city":"Skokie",
    "sg:classifiers":[
        {
            "category":"Health Services",
            "subcategory":"Clinic",
            "type":"Services"
        }
    ],
    "sg:phone":"+1 847 663 8383",
    "sg:postcode":"60077",
    "sg:province":"IL",
    "sg:tags":[
        "spa",
        "medical"
    ],
    "wof:name":"Lightcare Medical Spa",
    "wof:placetype":"venue"
},
  "geometry": {"coordinates":[-87.757925,42.040858],"type":"Point"}
}