{
  "type": "Feature",
  "properties": {
    "iso:country":"US",
    "sg:address":"2100 Manchester Rd",
    "sg:city":"Wheaton",
    "sg:classifiers":[
        {
            "category":"Manufacturing",
            "subcategory":"Tools & Machinery",
            "type":"Manufacturing & Wholesale Goods"
        }
    ],
    "sg:phone":"+1 630 260 7705",
    "sg:postcode":"60187",
    "sg:province":"IL",
    "sg:tags":[
        "equipment",
        "peripheral",
        "computer",
        "mfg"
    ],
    "wof:name":"Printek Inc",
    "wof:placetype":"venue"
},
  "geometry": {"coordinates":[-88.13596200000001,41.865567],"type":"Point"}
}