{
  "type": "Feature",
  "properties": {
    "iso:country":"US",
    "sg:address":"1901 S 4th St",
    "sg:city":"Effingham",
    "sg:classifiers":[
        {
            "category":"Government",
            "subcategory":"Office",
            "type":"Public Place"
        }
    ],
    "sg:phone":"+1 217 347 7600",
    "sg:postcode":"62401",
    "sg:province":"IL",
    "sg:tags":[
        "federal",
        "affairs",
        "govt",
        "admin"
    ],
    "wof:name":"Dept Of Veterans Affairs Med",
    "wof:placetype":"venue"
},
  "geometry": {"coordinates":[-88.542264,39.105092],"type":"Point"}
}