{
  "type": "Feature",
  "properties": {
    "iso:country":"US",
    "sg:address":"111 E Lake St # 111-1",
    "sg:city":"Bloomingdale",
    "sg:classifiers":[
        {
            "category":"Restaurant",
            "type":"Food & Drink"
        }
    ],
    "sg:phone":"+1 630 924 8400",
    "sg:postcode":"60108",
    "sg:province":"IL",
    "sg:tags":[
        "indian"
    ],
    "wof:name":"Taj Mahal",
    "wof:placetype":"venue"
},
  "geometry": {"coordinates":[-88.07989000000001,41.957786],"type":"Point"}
}