{
  "type": "Feature",
  "properties": {
    "iso:country":"US",
    "sg:address":"3611 Hickory Ln",
    "sg:city":"Rockford",
    "sg:classifiers":[
        {
            "category":"Professional",
            "subcategory":"Accounting & Tax Preparation",
            "type":"Services"
        }
    ],
    "sg:phone":"+1 815 399 7899",
    "sg:postcode":"61107",
    "sg:province":"IL",
    "wof:name":"Albert Triebel Jr",
    "wof:placetype":"venue"
},
  "geometry": {"coordinates":[-89.039473,42.287554],"type":"Point"}
}