{
  "type": "Feature",
  "properties": {
    "iso:country":"US",
    "sg:address":"2807 State St",
    "sg:city":"Chester",
    "sg:classifiers":[
        {
            "category":"Manufacturing",
            "subcategory":"Buildings",
            "type":"Manufacturing & Wholesale Goods"
        },
        {
            "category":"Government",
            "subcategory":"Post Office",
            "type":"Public Place"
        },
        {
            "category":"Building & Trades",
            "subcategory":"Construction",
            "type":"Services"
        },
        {
            "category":"Building & Trades",
            "subcategory":"Landfill",
            "type":"Services"
        }
    ],
    "sg:phone":"+1 877 347 8121",
    "sg:postcode":"62233",
    "sg:province":"IL",
    "sg:tags":[
        "repairing",
        "farm",
        "frame",
        "metal",
        "contractor",
        "buildings-pole",
        "garages-building"
    ],
    "sg:website":"http://www.mortonbuildings.com",
    "wof:name":"Morton Buildings",
    "wof:placetype":"venue"
},
  "geometry": {"coordinates":[-89.796666,37.935543],"type":"Point"}
}