{
  "type": "Feature",
  "properties": {
    "addr:full":"1401 Maybook Dr Maywood IL 60153",
    "addr:housenumber":"1401",
    "addr:postcode":"60153",
    "addr:street":"Maybook Dr",
    "iso:country":"US",
    "sg:address":"1401 Maybook Dr",
    "sg:city":"Maywood",
    "sg:classifiers":[
        {
            "category":"Government",
            "subcategory":"City Hall",
            "type":"Public Place"
        }
    ],
    "sg:phone":"+1 708 865 4700",
    "sg:postcode":"60153",
    "sg:province":"IL",
    "sg:website":"www.ccspd.org",
    "wof:name":"Cook County Sheriff's Police",
    "wof:placetype":"venue"
},
  "geometry": {"coordinates":[-87.828501,41.875247],"type":"Point"}
}