{
  "type": "Feature",
  "properties": {
    "iso:country":"US",
    "sg:address":"216 Industry Ave",
    "sg:city":"Frankfort",
    "sg:classifiers":[
        {
            "category":"Retail",
            "subcategory":"Auto Repair",
            "type":"Services"
        }
    ],
    "sg:phone":"+1 815 464 7250",
    "sg:postcode":"60423",
    "sg:province":"IL",
    "sg:tags":[
        "machine",
        "automobile",
        "shop"
    ],
    "sg:website":"www.bookracing.com",
    "wof:name":"BRE Inc",
    "wof:placetype":"venue"
},
  "geometry": {"coordinates":[-87.839485,41.479732],"type":"Point"}
}