{
  "type": "Feature",
  "properties": {
    "iso:country":"US",
    "sg:address":"4539 N Sheridan Rd",
    "sg:city":"Chicago",
    "sg:classifiers":[
        {
            "category":"Shopping",
            "subcategory":"Department Store",
            "type":"Retail Goods"
        }
    ],
    "sg:phone":"+1   ",
    "sg:postcode":"60640",
    "sg:province":"IL",
    "wof:name":"Double Crowne International",
    "wof:placetype":"venue"
},
  "geometry": {"coordinates":[-87.65471,41.965267],"type":"Point"}
}