{
  "type": "Feature",
  "properties": {
    "addr:full":"1388 Wasdale Ave Elk Grove Vlg IL 60007",
    "addr:housenumber":"1388",
    "addr:postcode":"60007",
    "addr:street":"Wasdale Ave",
    "iso:country":"US",
    "sg:address":"1388 Wasdale Ave",
    "sg:city":"Elk Grove Vlg",
    "sg:classifiers":[
        {
            "category":"Retail",
            "subcategory":"Repair Shop",
            "type":"Services"
        }
    ],
    "sg:phone":"+1 847 956 0707",
    "sg:postcode":"60007",
    "sg:province":"IL",
    "sg:tags":[
        "door"
    ],
    "wof:name":"A-Advance Glass Svc Inc",
    "wof:placetype":"venue"
},
  "geometry": {"coordinates":[-87.999932,41.994177],"type":"Point"}
}