{
  "type": "Feature",
  "properties": {
    "iso:country":"US",
    "sg:address":"9222 Ogden Ave",
    "sg:city":"Brookfield",
    "sg:classifiers":[
        {
            "category":"Shopping",
            "subcategory":"Gifts & Souvenirs",
            "type":"Retail Goods"
        }
    ],
    "sg:phone":"+1 708 485 0008",
    "sg:postcode":"60513",
    "sg:province":"IL",
    "sg:tags":[
        "flower"
    ],
    "wof:name":"Jacobs Ladder",
    "wof:placetype":"venue"
},
  "geometry": {"coordinates":[-87.852501,41.817101],"type":"Point"}
}