{
  "type": "Feature",
  "properties": {
    "iso:country":"US",
    "sg:address":"24606 Co Hwy 22",
    "sg:city":"Atkinson",
    "sg:phone":"+1 309 935 6681",
    "sg:postcode":"61235",
    "sg:province":"IL",
    "sg:tags":[
        "farm",
        "corn"
    ],
    "wof:name":"Gary Pritchard",
    "wof:placetype":"venue"
},
  "geometry": {"coordinates":[-89.957009,41.427818],"type":"Point"}
}