{
  "type": "Feature",
  "properties": {
    "iso:country":"US",
    "sg:address":"1217 N Ridgeland Ave",
    "sg:city":"Oak Park",
    "sg:classifiers":[
        {
            "category":"Manufacturing",
            "subcategory":"Chemicals & Compounds",
            "type":"Manufacturing & Wholesale Goods"
        }
    ],
    "sg:phone":"+1 708 445 1078",
    "sg:postcode":"60302",
    "sg:province":"IL",
    "sg:tags":[
        "preparation",
        "pharmaceutical",
        "mfg"
    ],
    "wof:name":"McKesson Corporation",
    "wof:placetype":"venue"
},
  "geometry": {"coordinates":[-87.783415,41.908351],"type":"Point"}
}