{
  "type": "Feature",
  "properties": {
    "iso:country":"US",
    "sg:address":"204 N Main St",
    "sg:city":"Morton",
    "sg:classifiers":[
        {
            "category":"Professional",
            "subcategory":"Management & Consulting",
            "type":"Services"
        },
        {
            "category":"Banks & Credit Unions",
            "subcategory":"Financial Services",
            "type":"Services"
        }
    ],
    "sg:phone":"+1 309 263 0022",
    "sg:postcode":"61550",
    "sg:province":"IL",
    "sg:tags":[
        "consultant",
        "financing",
        "planning"
    ],
    "sg:website":"http://www.cmfs.net",
    "wof:name":"Craig Miller Financial Services",
    "wof:placetype":"venue"
},
  "geometry": {"coordinates":[-89.460938,40.61137],"type":"Point"}
}