{
  "type": "Feature",
  "properties": {
    "iso:country":"US",
    "sg:address":"2015 Mitchell Blvd",
    "sg:city":"Schaumburg",
    "sg:classifiers":[
        {
            "category":"Wholesale",
            "subcategory":"Electrical",
            "type":"Manufacturing & Wholesale Goods"
        }
    ],
    "sg:phone":"+1 847 524 9995",
    "sg:postcode":"60193",
    "sg:province":"IL",
    "sg:tags":[
        "equipment",
        "industrial"
    ],
    "wof:name":"Toolmex Corporation",
    "wof:placetype":"venue"
},
  "geometry": {"coordinates":[-88.091624,42.000017],"type":"Point"}
}