{
  "type": "Feature",
  "properties": {
    "iso:country":"US",
    "sg:address":"2301 S Shore Dr",
    "sg:city":"Springfield",
    "sg:classifiers":[
        {
            "category":"Recreation",
            "type":"Entertainment"
        }
    ],
    "sg:phone":"+1 217 529 1111",
    "sg:postcode":"61265",
    "sg:province":"IL",
    "sg:tags":[
        "parks"
    ],
    "sg:website":"www.lmgnc.com",
    "wof:name":"Lincoln Memorial Garden Nature",
    "wof:placetype":"venue"
},
  "geometry": {"coordinates":[-90.50761799999999,41.458711],"type":"Point"}
}