{
  "type": "Feature",
  "properties": {
    "iso:country":"US",
    "sg:address":"2443 Warrenville Rd",
    "sg:city":"Lisle",
    "sg:classifiers":[
        {
            "category":"Insurance",
            "subcategory":"Hazard Insurance",
            "type":"Services"
        }
    ],
    "sg:phone":"+1 630 955 1300",
    "sg:postcode":"60532",
    "sg:province":"IL",
    "sg:tags":[
        "carrier"
    ],
    "wof:name":"Amica Mutual Insurance Company",
    "wof:placetype":"venue"
},
  "geometry": {"coordinates":[-88.10181,41.808155],"type":"Point"}
}