{
  "type": "Feature",
  "properties": {
    "addr:full":"1019 Gardner St South Beloit WI 61080",
    "addr:housenumber":"1019",
    "addr:postcode":"61080",
    "addr:street":"Gardner St",
    "iso:country":"US",
    "sg:address":"1019 Gardner St",
    "sg:city":"South Beloit",
    "sg:classifiers":[
        {
            "category":"Shopping",
            "subcategory":"Used Merchandise",
            "type":"Retail Goods"
        }
    ],
    "sg:phone":"+1 815 389 8800",
    "sg:postcode":"61080",
    "sg:province":"WI",
    "sg:tags":[
        "antique"
    ],
    "wof:name":"Roscoe Antique Mall",
    "wof:placetype":"venue"
},
  "geometry": {"coordinates":[-89.024835,42.492185],"type":"Point"}
}