{
  "type": "Feature",
  "properties": {
    "iso:country":"US",
    "sg:address":"13130 Cicero Ave",
    "sg:city":"Crestwood",
    "sg:phone":"+1 708 385 6400",
    "sg:postcode":"60445",
    "sg:province":"IL",
    "sg:website":"http://www.portillos.com",
    "wof:name":"Portillo's Hot Dogs",
    "wof:placetype":"venue"
},
  "geometry": {"coordinates":[-87.738297,41.65266],"type":"Point"}
}