{
  "type": "Feature",
  "properties": {
    "iso:country":"US",
    "sg:address":"1152 Tower Ln",
    "sg:city":"Bensenville",
    "sg:classifiers":[
        {
            "category":"Food & Beverages",
            "subcategory":"Bakery",
            "type":"Retail Goods"
        },
        {
            "category":"Bakery",
            "type":"Food & Drink"
        }
    ],
    "sg:phone":"+1 630 860 1225",
    "sg:postcode":"60106",
    "sg:province":"IL",
    "sg:tags":[
        "bakers-wholesale"
    ],
    "wof:name":"Chicago Specialty Bakers Inc",
    "wof:placetype":"venue"
},
  "geometry": {"coordinates":[-87.96129000000001,41.986749],"type":"Point"}
}