{
  "type": "Feature",
  "properties": {
    "iso:country":"US",
    "sg:address":"303 E State St",
    "sg:city":"Cherry Valley",
    "sg:classifiers":[
        {
            "category":"Autos & Motor Vehicles",
            "subcategory":"Fuel & Gas Station",
            "type":"Retail Goods"
        }
    ],
    "sg:phone":"+1 815 332 3461",
    "sg:postcode":"61016",
    "sg:province":"IL",
    "sg:tags":[
        "oil"
    ],
    "wof:name":"Expresslane Gas & Food Mart",
    "wof:placetype":"venue"
},
  "geometry": {"coordinates":[-88.950642,42.234764],"type":"Point"}
}