{
  "type": "Feature",
  "properties": {
    "iso:country":"US",
    "sg:address":"625 N Michigan Ave",
    "sg:city":"Chicago",
    "sg:classifiers":[
        {
            "category":"Shopping",
            "subcategory":"Clothing, Apparel, & Fashions",
            "type":"Retail Goods"
        },
        {
            "category":"Manufacturing",
            "subcategory":"Leather Goods",
            "type":"Manufacturing & Wholesale Goods"
        }
    ],
    "sg:phone":"+1 877 275 1274",
    "sg:postcode":"60611",
    "sg:province":"IL",
    "sg:tags":[
        "accessory"
    ],
    "sg:website":"www.exotic-elegance-handbags.com",
    "wof:name":"EXOTIC elegance",
    "wof:placetype":"venue"
},
  "geometry": {"coordinates":[-87.623684,41.893137],"type":"Point"}
}