{
  "type": "Feature",
  "properties": {
    "iso:country":"US",
    "sg:address":"10 W Golf Rd",
    "sg:city":"Des Plaines",
    "sg:classifiers":[
        {
            "category":"Autos & Motor Vehicles",
            "subcategory":"Fuel & Gas Station",
            "type":"Retail Goods"
        }
    ],
    "sg:phone":"+1   ",
    "sg:postcode":"60016",
    "sg:province":"IL",
    "sg:tags":[
        "station",
        "gasoline"
    ],
    "wof:name":"Busse Marathon",
    "wof:placetype":"venue"
},
  "geometry": {"coordinates":[-87.922263,42.048718],"type":"Point"}
}