{
  "type": "Feature",
  "properties": {
    "addr:full":"2500 Longest Drive W Chicago IL 60607",
    "addr:housenumber":"2500",
    "addr:postcode":"60607",
    "addr:street":"Longest Drive W",
    "iso:country":"US",
    "sg:address":"2500 Longest Drive W",
    "sg:city":"Chicago",
    "sg:classifiers":[
        {
            "category":"Airline",
            "type":"Transportation"
        }
    ],
    "sg:phone":"+1 630 232 1650",
    "sg:postcode":"60607",
    "sg:province":"IL",
    "sg:tags":[
        "airport"
    ],
    "wof:name":"Dupage Airport Authority",
    "wof:placetype":"venue"
},
  "geometry": {"coordinates":[-87.656932,41.873792],"type":"Point"}
}