{
  "type": "Feature",
  "properties": {
    "iso:country":"US",
    "sg:address":"7010 S Pulaski Rd",
    "sg:city":"Chicago",
    "sg:classifiers":[
        {
            "category":"Restaurant",
            "type":"Food & Drink"
        }
    ],
    "sg:phone":"+1 773 838 1368",
    "sg:postcode":"60629",
    "sg:province":"IL",
    "sg:tags":[
        "chinese",
        "buffet"
    ],
    "wof:name":"Buffet City",
    "wof:placetype":"venue"
},
  "geometry": {"coordinates":[-87.722504,41.765499],"type":"Point"}
}