{
  "type": "Feature",
  "properties": {
    "addr:full":"641 Beau Ct Des Plaines IL 60016",
    "addr:housenumber":"641",
    "addr:postcode":"60016",
    "addr:street":"Beau Ct",
    "iso:country":"US",
    "sg:address":"641 Beau Ct",
    "sg:city":"Des Plaines",
    "sg:classifiers":[
        {
            "category":"Professional",
            "subcategory":"Management & Consulting",
            "type":"Services"
        }
    ],
    "sg:phone":"+1 847 806 4184",
    "sg:postcode":"60016",
    "sg:province":"IL",
    "sg:tags":[
        "business"
    ],
    "wof:name":"Fbn Consulting",
    "wof:placetype":"venue"
},
  "geometry": {"coordinates":[-87.93789200000001,42.035922],"type":"Point"}
}