{
  "type": "Feature",
  "properties": {
    "addr:full":"490 N Main St Breese IL 62230",
    "addr:housenumber":"490",
    "addr:postcode":"62230",
    "addr:street":"N Main St",
    "iso:country":"US",
    "sg:address":"490 N Main St",
    "sg:city":"Breese",
    "sg:classifiers":[
        {
            "category":"Home & Garden",
            "subcategory":"Carpets & Floor Coverings",
            "type":"Retail Goods"
        }
    ],
    "sg:phone":"+1 618 526 0477",
    "sg:postcode":"62230",
    "sg:province":"IL",
    "sg:tags":[
        "company",
        "material",
        "flooring"
    ],
    "wof:name":"Interiors On Main Inc",
    "wof:placetype":"venue"
},
  "geometry": {"coordinates":[-89.52732399999999,38.610863],"type":"Point"}
}