{
  "type": "Feature",
  "properties": {
    "iso:country":"US",
    "sg:address":"17940 Settlers Pond Way",
    "sg:city":"Orland Park",
    "sg:classifiers":[
        {
            "category":"Building & Trades",
            "subcategory":"Construction",
            "type":"Services"
        }
    ],
    "sg:phone":"+1 708 478 4606",
    "sg:postcode":"60467",
    "sg:province":"IL",
    "sg:tags":[
        "home",
        "builder"
    ],
    "wof:name":"Distinctive Homes LTD",
    "wof:placetype":"venue"
},
  "geometry": {"coordinates":[-87.897093,41.562939],"type":"Point"}
}