{
  "type": "Feature",
  "properties": {
    "iso:country":"US",
    "sg:address":"9830 Ridgeland Ave Ste 1",
    "sg:city":"Chicago Ridge",
    "sg:classifiers":[
        {
            "category":"Health Services",
            "subcategory":"Doctor",
            "type":"Services"
        }
    ],
    "sg:phone":"+1 708 425 2332",
    "sg:postcode":"60415",
    "sg:province":"IL",
    "wof:name":"Alawad Medical Center",
    "wof:placetype":"venue"
},
  "geometry": {"coordinates":[-87.779996,41.713566],"type":"Point"}
}