{
  "type": "Feature",
  "properties": {
    "iso:country":"US",
    "sg:address":"659 Russell St",
    "sg:city":"Elgin",
    "sg:classifiers":[
        {
            "category":"Building & Trades",
            "subcategory":"Construction",
            "type":"Services"
        }
    ],
    "sg:phone":"+1 847 697 9055",
    "sg:postcode":"60120",
    "sg:province":"IL",
    "sg:tags":[
        "hanging",
        "contractor"
    ],
    "wof:name":"Old Country Painting",
    "wof:placetype":"venue"
},
  "geometry": {"coordinates":[-88.264714,42.01974],"type":"Point"}
}