{
  "type": "Feature",
  "properties": {
    "iso:country":"US",
    "sg:address":"6651 W 79th St",
    "sg:city":"Burbank",
    "sg:classifiers":[
        {
            "category":"Real Estate",
            "subcategory":"Real Estate Services",
            "type":"Services"
        },
        {
            "category":"Real Estate",
            "subcategory":"Real Estate Agent",
            "type":"Services"
        }
    ],
    "sg:phone":"+1 708 399 4213",
    "sg:postcode":"60459",
    "sg:province":"IL",
    "sg:tags":[
        "buyer",
        "broker"
    ],
    "wof:name":"Total Realty",
    "wof:placetype":"venue"
},
  "geometry": {"coordinates":[-87.786665,41.748343],"type":"Point"}
}