{
  "type": "Feature",
  "properties": {
    "iso:country":"US",
    "sg:address":"125 Randall St",
    "sg:city":"Elk Grove Village",
    "sg:classifiers":[
        {
            "category":"Retail",
            "subcategory":"Auto Repair",
            "type":"Services"
        }
    ],
    "sg:phone":"+1 847 437 6421",
    "sg:postcode":"60007",
    "sg:province":"IL",
    "sg:tags":[
        "body"
    ],
    "wof:name":"Hoskin Chevrolet",
    "wof:placetype":"venue"
},
  "geometry": {"coordinates":[-87.98491799999999,42.029214],"type":"Point"}
}