{
  "type": "Feature",
  "properties": {
    "iso:country":"US",
    "sg:address":"220 Exchange Dr",
    "sg:city":"Crystal Lake",
    "sg:classifiers":[
        {
            "category":"Shopping",
            "subcategory":"Books",
            "type":"Retail Goods"
        }
    ],
    "sg:phone":"+1   ",
    "sg:postcode":"60014",
    "sg:province":"IL",
    "sg:tags":[
        "bookstore"
    ],
    "wof:name":"Follett Corporation",
    "wof:placetype":"venue"
},
  "geometry": {"coordinates":[-88.304658,42.234908],"type":"Point"}
}