{
  "type": "Feature",
  "properties": {
    "iso:country":"US",
    "sg:address":"1471 US Hwy 20",
    "sg:city":"Elizabeth",
    "sg:classifiers":[
        {
            "category":"Wholesale",
            "subcategory":"Machinery & Supplies",
            "type":"Manufacturing & Wholesale Goods"
        }
    ],
    "sg:phone":"+1 815 858 2426",
    "sg:postcode":"61028",
    "sg:province":"IL",
    "sg:tags":[
        "bookbinder",
        "equipment"
    ],
    "wof:name":"Mc Arthur Machinery LTD",
    "wof:placetype":"venue"
},
  "geometry": {"coordinates":[-90.240147,42.313027],"type":"Point"}
}