{
  "type": "Feature",
  "properties": {
    "iso:country":"US",
    "sg:address":"2251 W Devon Ave",
    "sg:city":"Chicago",
    "sg:classifiers":[
        {
            "category":"Bars & Pubs",
            "type":"Food & Drink"
        }
    ],
    "sg:phone":"+1 773 743 5737",
    "sg:postcode":"60659",
    "sg:province":"IL",
    "sg:tags":[
        "drinking",
        "beverage",
        "alcoholic"
    ],
    "wof:name":"Cary's Lounge",
    "wof:placetype":"venue"
},
  "geometry": {"coordinates":[-87.686897,41.997601],"type":"Point"}
}