{
  "type": "Feature",
  "properties": {
    "iso:country":"US",
    "sg:address":"1090 Johnson Dr",
    "sg:city":"Buffalo Grove",
    "sg:classifiers":[
        {
            "category":"Wholesale",
            "subcategory":"Medical Equipment & Supplies",
            "type":"Manufacturing & Wholesale Goods"
        }
    ],
    "sg:phone":"+1 847 947 8005",
    "sg:postcode":"60089",
    "sg:province":"IL",
    "sg:tags":[
        "hypertensive",
        "mail",
        "diabetic",
        "order",
        "asthmatic"
    ],
    "wof:name":"Health Alliance Holdings Inc",
    "wof:placetype":"venue"
},
  "geometry": {"coordinates":[-87.932997,42.153862],"type":"Point"}
}