{
  "type": "Feature",
  "properties": {
    "addr:full":"4715 N Sheridan Rd Chicago IL 60640",
    "addr:housenumber":"4715",
    "addr:postcode":"60640",
    "addr:street":"N Sheridan Rd",
    "iso:country":"US",
    "sg:address":"4715 N Sheridan Rd",
    "sg:city":"Chicago",
    "sg:classifiers":[
        {
            "category":"Cafe",
            "type":"Food & Drink"
        }
    ],
    "sg:menulink":"http://www.allmenus.com/il/chicago/209622-cafe-too/menu/",
    "sg:phone":"+1 773 275 0626",
    "sg:postcode":"60640",
    "sg:province":"IL",
    "sg:tags":[
        "american",
        "diner"
    ],
    "wof:name":"Cafe Too",
    "wof:placetype":"venue"
},
  "geometry": {"coordinates":[-87.654787,41.967947],"type":"Point"}
}