{
  "type": "Feature",
  "properties": {
    "addr:full":"204 Wisconsin Ave Sandoval IL 62882",
    "addr:housenumber":"204",
    "addr:postcode":"62882",
    "addr:street":"Wisconsin Ave",
    "iso:country":"US",
    "sg:address":"204 Wisconsin Ave",
    "sg:city":"Sandoval",
    "sg:classifiers":[
        {
            "category":"Government",
            "subcategory":"Office",
            "type":"Public Place"
        }
    ],
    "sg:phone":"+1 618 247 3813",
    "sg:postcode":"62882",
    "sg:province":"IL",
    "sg:tags":[
        "village"
    ],
    "wof:name":"Sandoval Twnsp General Assist",
    "wof:placetype":"venue"
},
  "geometry": {"coordinates":[-89.12217,38.614792],"type":"Point"}
}