{
  "type": "Feature",
  "properties": {
    "iso:country":"US",
    "sg:address":"217 E Mazon Ave",
    "sg:city":"Dwight",
    "sg:classifiers":[
        {
            "category":"Education",
            "subcategory":"Special Training",
            "type":"Public Place"
        }
    ],
    "sg:phone":"+1 815 584 1738",
    "sg:postcode":"60420",
    "sg:province":"IL",
    "sg:tags":[
        "program"
    ],
    "wof:name":"Services Exchange",
    "wof:placetype":"venue"
},
  "geometry": {"coordinates":[-88.425945,41.094016],"type":"Point"}
}