{
  "type": "Feature",
  "properties": {
    "addr:full":"400 S Garrard St Rantoul IL 61866",
    "addr:housenumber":"400",
    "addr:postcode":"61866",
    "addr:street":"S Garrard St",
    "iso:country":"US",
    "sg:address":"400 S Garrard St",
    "sg:city":"Rantoul",
    "sg:classifiers":[
        {
            "category":"Professional",
            "subcategory":"Management & Consulting",
            "type":"Services"
        }
    ],
    "sg:phone":"+1 217 893 0531",
    "sg:postcode":"61866",
    "sg:province":"IL",
    "sg:tags":[
        "business"
    ],
    "wof:name":"Rudnicke Consulting",
    "wof:placetype":"venue"
},
  "geometry": {"coordinates":[-88.157315,40.305163],"type":"Point"}
}