{
  "type": "Feature",
  "properties": {
    "iso:country":"US",
    "sg:address":"1226 State St",
    "sg:city":"Chester",
    "sg:classifiers":[
        {
            "category":"Restaurant",
            "type":"Food & Drink"
        },
        {
            "category":"Food & Beverages",
            "subcategory":"Groceries & Convenience Stores",
            "type":"Retail Goods"
        }
    ],
    "sg:menulink":"http://www.allmenus.com/il/chester/226208-caseys-general-store/menu/",
    "sg:phone":"+1 618 826 4325",
    "sg:postcode":"62233",
    "sg:province":"IL",
    "sg:tags":[
        "american",
        "pizza"
    ],
    "wof:name":"Casey's General Store",
    "wof:placetype":"venue"
},
  "geometry": {"coordinates":[-89.821563,37.913521],"type":"Point"}
}