{
  "type": "Feature",
  "properties": {
    "iso:country":"US",
    "sg:address":"195 Armstrong Rd",
    "sg:city":"Des Plaines",
    "sg:classifiers":[
        {
            "category":"Professional",
            "subcategory":"Advertising",
            "type":"Services"
        }
    ],
    "sg:phone":"+1 847 795 8100",
    "sg:postcode":"60018",
    "sg:province":"IL",
    "sg:tags":[
        "distribution"
    ],
    "wof:name":"Distribution Specialist Inc",
    "wof:placetype":"venue"
},
  "geometry": {"coordinates":[-87.922117,42.003899],"type":"Point"}
}