{
  "type": "Feature",
  "properties": {
    "iso:country":"US",
    "sg:address":"1445 18th Ave",
    "sg:city":"East Moline",
    "sg:classifiers":[
        {
            "category":"Building & Trades",
            "subcategory":"Plumbing",
            "type":"Services"
        }
    ],
    "sg:phone":"+1 309 755 7040",
    "sg:postcode":"61244",
    "sg:province":"IL",
    "wof:name":"Fiers Plumbing & Heating",
    "wof:placetype":"venue"
},
  "geometry": {"coordinates":[-90.429298,41.5158],"type":"Point"}
}