{
  "type": "Feature",
  "properties": {
    "iso:country":"US",
    "sg:address":"9757 Squire Ln",
    "sg:city":"Belvidere",
    "sg:classifiers":[
        {
            "category":"Organizations",
            "subcategory":"Religious Organization",
            "type":"Services"
        }
    ],
    "sg:phone":"+1 815 547 0765",
    "sg:postcode":"61008",
    "sg:province":"IL",
    "wof:name":"Voice In Wilderness Ministries",
    "wof:placetype":"venue"
},
  "geometry": {"coordinates":[-88.803984,42.295534],"type":"Point"}
}