{
  "type": "Feature",
  "properties": {
    "iso:country":"US",
    "sg:address":"2820 Columbus St",
    "sg:city":"Ottawa",
    "sg:classifiers":[
        {
            "category":"Shopping",
            "subcategory":"Clothing, Apparel, & Fashions",
            "type":"Retail Goods"
        }
    ],
    "sg:phone":"+1 815 433 5648",
    "sg:postcode":"61350",
    "sg:province":"IL",
    "sg:website":"www.maruices.com",
    "wof:name":"Maurice's",
    "wof:placetype":"venue"
},
  "geometry": {"coordinates":[-88.835781,41.369947],"type":"Point"}
}