{
  "type": "Feature",
  "properties": {
    "addr:full":"5017 N Winthrop Ave Chicago IL 60640",
    "addr:housenumber":"5017",
    "addr:postcode":"60640",
    "addr:street":"N Winthrop Ave",
    "iso:country":"US",
    "sg:address":"5017 N Winthrop Ave",
    "sg:city":"Chicago",
    "sg:classifiers":[
        {
            "category":"Professional",
            "type":"Services"
        }
    ],
    "sg:phone":"+1 773 561 8880",
    "sg:postcode":"60640",
    "sg:province":"IL",
    "sg:tags":[
        "establishment"
    ],
    "wof:name":"Asian Village Parking",
    "wof:placetype":"venue"
},
  "geometry": {"coordinates":[-87.657706,41.974919],"type":"Point"}
}