{
  "type": "Feature",
  "properties": {
    "iso:country":"US",
    "sg:address":"2230 S Archer Ave",
    "sg:city":"Chicago",
    "sg:classifiers":[
        {
            "category":"Manufacturing",
            "subcategory":"Electronics",
            "type":"Manufacturing & Wholesale Goods"
        },
        {
            "category":"Professional",
            "subcategory":"Printing & Photocopies",
            "type":"Services"
        }
    ],
    "sg:phone":"+1 312 942 9601",
    "sg:postcode":"60616",
    "sg:province":"IL",
    "sg:tags":[
        "supply",
        "services-commercial",
        "typesetting",
        "lithographer",
        "printers-equipment"
    ],
    "wof:name":"Vgi Press Inc",
    "wof:placetype":"venue"
},
  "geometry": {"coordinates":[-87.63643399999999,41.85205],"type":"Point"}
}