{
  "type": "Feature",
  "properties": {
    "iso:country":"US",
    "sg:address":"5401 S Cornell Ave",
    "sg:city":"Chicago",
    "sg:classifiers":[
        {
            "category":"Organizations",
            "subcategory":"Religious Organization",
            "type":"Services"
        }
    ],
    "sg:phone":"+1 773 493 2306",
    "sg:postcode":"60615",
    "sg:province":"IL",
    "wof:name":"Religious Brothers",
    "wof:placetype":"venue"
},
  "geometry": {"coordinates":[-87.58504600000001,41.797889],"type":"Point"}
}