{
  "type": "Feature",
  "properties": {
    "iso:country":"US",
    "sg:address":"825 N Rutledge St",
    "sg:city":"Springfield",
    "sg:classifiers":[
        {
            "category":"Health Services",
            "subcategory":"Clinic",
            "type":"Services"
        }
    ],
    "sg:phone":"+1 217 782 6562",
    "sg:postcode":"62702",
    "sg:province":"IL",
    "sg:tags":[
        "welfare"
    ],
    "wof:name":"Division Of Laboratories",
    "wof:placetype":"venue"
},
  "geometry": {"coordinates":[-89.65738899999999,39.81003],"type":"Point"}
}