{
  "type": "Feature",
  "properties": {
    "iso:country":"US",
    "sg:address":"399 N Co Rd 1675E",
    "sg:city":"Hindsboro",
    "sg:phone":"+1 217 346 3509",
    "sg:postcode":"61930",
    "sg:province":"IL",
    "sg:tags":[
        "farm",
        "corn"
    ],
    "wof:name":"Duffle Farms",
    "wof:placetype":"venue"
},
  "geometry": {"coordinates":[-88.15825,39.701876],"type":"Point"}
}