{
  "type": "Feature",
  "properties": {
    "addr:full":"18010 WEST ACCESS RD Carlyle IL 62231",
    "addr:housenumber":"18010",
    "addr:postcode":"62231",
    "addr:street":"West Access Rd",
    "iso:country":"US",
    "sg:address":"18010 WEST ACCESS RD",
    "sg:city":"Carlyle",
    "sg:classifiers":[
        {
            "category":"Fast Food",
            "type":"Food & Drink"
        },
        {
            "category":"Restaurant",
            "type":"Food & Drink"
        }
    ],
    "sg:phone":"+1 618 594 4474",
    "sg:postcode":"62231",
    "sg:province":"IL",
    "sg:tags":[
        "hamburger",
        "hot",
        "dog",
        "american",
        "take",
        "chicken"
    ],
    "sg:website":"http://www.mcdonalds.com",
    "wof:name":"McDonald's",
    "wof:placetype":"venue"
},
  "geometry": {"coordinates":[-89.259972,38.657162],"type":"Point"}
}