{
  "type": "Feature",
  "properties": {
    "iso:country":"US",
    "sg:address":"3300 N Halsted St",
    "sg:city":"Chicago",
    "sg:classifiers":[
        {
            "category":"Professional",
            "subcategory":"Advertising",
            "type":"Services"
        },
        {
            "category":"Professional",
            "subcategory":"Art Services",
            "type":"Services"
        },
        {
            "category":"Building & Trades",
            "subcategory":"Locksmith",
            "type":"Services"
        },
        {
            "category":"Government",
            "subcategory":"Post Office",
            "type":"Public Place"
        }
    ],
    "sg:phone":"+1 773 935 0008",
    "sg:postcode":"60657",
    "sg:province":"IL",
    "sg:tags":[
        "antique",
        "repair",
        "coupon",
        "lock",
        "restoration",
        "key",
        "boxes-retail",
        "mail"
    ],
    "wof:name":"Dexter Lock Service",
    "wof:placetype":"venue"
},
  "geometry": {"coordinates":[-87.64958,41.941915],"type":"Point"}
}