{
  "type": "Feature",
  "properties": {
    "iso:country":"US",
    "sg:address":"227 E State St",
    "sg:city":"Jacksonville",
    "sg:classifiers":[
        {
            "category":"Shopping",
            "subcategory":"Gifts & Souvenirs",
            "type":"Retail Goods"
        }
    ],
    "sg:phone":"+1 217 245 1467",
    "sg:postcode":"62650",
    "sg:province":"IL",
    "sg:tags":[
        "shop"
    ],
    "wof:name":"D & D Treasures",
    "wof:placetype":"venue"
},
  "geometry": {"coordinates":[-90.227349,39.734189],"type":"Point"}
}