{
  "type": "Feature",
  "properties": {
    "iso:country":"US",
    "sg:address":"441 Rainmaker Trl",
    "sg:city":"Butler",
    "sg:classifiers":[
        {
            "category":"Shopping",
            "type":"Retail Goods"
        }
    ],
    "sg:phone":"+1 217 532 7858",
    "sg:postcode":"62015",
    "sg:province":"IL",
    "sg:tags":[
        "cosmetic",
        "perfume"
    ],
    "wof:name":"Mary Kay Cosmetics",
    "wof:placetype":"venue"
},
  "geometry": {"coordinates":[-89.58977899999999,39.207055],"type":"Point"}
}