{
  "type": "Feature",
  "properties": {
    "addr:full":"335 5th Ave Moline IL 61265",
    "addr:housenumber":"335",
    "addr:postcode":"61265",
    "addr:street":"5Th Ave",
    "iso:country":"US",
    "sg:address":"335 5th Ave",
    "sg:city":"Moline",
    "sg:classifiers":[
        {
            "category":"Education",
            "subcategory":"School",
            "type":"Public Place"
        }
    ],
    "sg:phone":"+1 309 757 3506",
    "sg:postcode":"61265",
    "sg:province":"IL",
    "wof:name":"Ericsson Elementary School",
    "wof:placetype":"venue"
},
  "geometry": {"coordinates":[-90.533418,41.504827],"type":"Point"}
}