{
  "type": "Feature",
  "properties": {
    "addr:full":"210 N Elm St Breese IL 62230",
    "addr:housenumber":"210",
    "addr:postcode":"62230",
    "addr:street":"N Elm St",
    "iso:country":"US",
    "sg:address":"210 N Elm St",
    "sg:city":"Breese",
    "sg:classifiers":[
        {
            "category":"Shopping",
            "subcategory":"Computers & Home Electronics",
            "type":"Retail Goods"
        }
    ],
    "sg:phone":"+1 618 526 4183",
    "sg:postcode":"62230",
    "sg:province":"IL",
    "sg:tags":[
        "television",
        "radio"
    ],
    "wof:name":"Thien Radio & TV Sales & Svc",
    "wof:placetype":"venue"
},
  "geometry": {"coordinates":[-89.52306299999999,38.609569],"type":"Point"}
}