{
  "type": "Feature",
  "properties": {
    "addr:full":"919 W University Ave Champaign IL 61821",
    "addr:housenumber":"919",
    "addr:postcode":"61821",
    "addr:street":"W University Ave",
    "iso:country":"US",
    "sg:address":"919 W University Ave",
    "sg:city":"Champaign",
    "sg:classifiers":[
        {
            "category":"Professional",
            "subcategory":"Lawyer & Legal Services",
            "type":"Services"
        }
    ],
    "sg:phone":"+1 217 359 2552",
    "sg:postcode":"61821",
    "sg:province":"IL",
    "wof:name":"Sinder Carl J Atty",
    "wof:placetype":"venue"
},
  "geometry": {"coordinates":[-88.259697,40.1161],"type":"Point"}
}