{
  "type": "Feature",
  "properties": {
    "iso:country":"US",
    "sg:address":"717 Belmont Dr",
    "sg:city":"Romeoville",
    "sg:classifiers":[
        {
            "category":"Building & Trades",
            "subcategory":"Plumbing",
            "type":"Services"
        }
    ],
    "sg:phone":"+1 815 886 5300",
    "sg:postcode":"60446",
    "sg:province":"IL",
    "sg:tags":[
        "heating",
        "contractor"
    ],
    "wof:name":"John Johnson Heating & AC SVC",
    "wof:placetype":"venue"
},
  "geometry": {"coordinates":[-88.098558,41.634262],"type":"Point"}
}