{
  "type": "Feature",
  "properties": {
    "iso:country":"US",
    "sg:address":"708 S Main St",
    "sg:city":"Homer",
    "sg:classifiers":[
        {
            "category":"Retail",
            "subcategory":"Funeral Services",
            "type":"Services"
        }
    ],
    "sg:phone":"+1 217 896 2323",
    "sg:postcode":"61849",
    "sg:province":"IL",
    "wof:name":"Kirby Funeral Home",
    "wof:placetype":"venue"
},
  "geometry": {"coordinates":[-87.95807600000001,40.028684],"type":"Point"}
}