{
  "type": "Feature",
  "properties": {
    "addr:full":"722 11th St Lawrenceville IL 62439",
    "addr:housenumber":"722",
    "addr:postcode":"62439",
    "addr:street":"11Th St",
    "iso:country":"US",
    "sg:address":"722 11th St",
    "sg:city":"Lawrenceville",
    "sg:classifiers":[
        {
            "category":"Professional",
            "subcategory":"Computer Services",
            "type":"Services"
        }
    ],
    "sg:phone":"+1 618 943 2083",
    "sg:postcode":"62439",
    "sg:province":"IL",
    "sg:tags":[
        "repair"
    ],
    "wof:name":"Brian's PC Corner",
    "wof:placetype":"venue"
},
  "geometry": {"coordinates":[-87.682,38.729267],"type":"Point"}
}