{
  "type": "Feature",
  "properties": {
    "iso:country":"US",
    "sg:address":"12202 Red Clover Ln",
    "sg:city":"Plainfield",
    "sg:classifiers":[
        {
            "category":"Manufacturing",
            "subcategory":"Wood Products",
            "type":"Manufacturing & Wholesale Goods"
        }
    ],
    "sg:phone":"+1 815 790 7590",
    "sg:postcode":"60585",
    "sg:province":"IL",
    "sg:tags":[
        "millwork-wholesale",
        "millwork",
        "manufacturer"
    ],
    "wof:name":"Jah Woodworking",
    "wof:placetype":"venue"
},
  "geometry": {"coordinates":[-88.22949800000001,41.659954],"type":"Point"}
}