{
  "type": "Feature",
  "properties": {
    "iso:country":"US",
    "sg:address":"1334 Gail Dr",
    "sg:city":"Buffalo Grove",
    "sg:classifiers":[
        {
            "category":"Professional",
            "subcategory":"Management & Consulting",
            "type":"Services"
        }
    ],
    "sg:phone":"+1 847 634 4548",
    "sg:postcode":"60089",
    "sg:province":"IL",
    "sg:tags":[
        "business"
    ],
    "wof:name":"Drew & Turner Cpas",
    "wof:placetype":"venue"
},
  "geometry": {"coordinates":[-87.972646,42.175407],"type":"Point"}
}