{
  "type": "Feature",
  "properties": {
    "iso:country":"US",
    "sg:address":"129 Fairfield Way",
    "sg:city":"Bloomingdale",
    "sg:classifiers":[
        {
            "category":"Banks & Credit Unions",
            "subcategory":"Financial Services",
            "type":"Services"
        }
    ],
    "sg:phone":"+1 630 893 4837",
    "sg:postcode":"60108",
    "sg:province":"IL",
    "sg:tags":[
        "broker",
        "mortgage"
    ],
    "wof:name":"Lighthouse Financial Inc",
    "wof:placetype":"venue"
},
  "geometry": {"coordinates":[-88.07289900000001,41.9547],"type":"Point"}
}