{
  "type": "Feature",
  "properties": {
    "addr:full":"6150 N Wyckles Rd Warrensburg IL 62573",
    "addr:housenumber":"6150",
    "addr:postcode":"62573",
    "addr:street":"N Wyckles Rd",
    "iso:country":"US",
    "sg:address":"6150 N Wyckles Rd",
    "sg:city":"Warrensburg",
    "sg:classifiers":[
        {
            "category":"Real Estate",
            "subcategory":"Real Estate Operator",
            "type":"Services"
        }
    ],
    "sg:phone":"+1 217 672 3725",
    "sg:postcode":"62573",
    "sg:province":"IL",
    "sg:tags":[
        "property",
        "lessor"
    ],
    "wof:name":"Lewis Disbrow",
    "wof:placetype":"venue"
},
  "geometry": {"coordinates":[-89.028914,39.922803],"type":"Point"}
}