{
  "type": "Feature",
  "properties": {
    "addr:full":"8611 W 95th St Hickory Hills IL 60457",
    "addr:housenumber":"8611",
    "addr:postcode":"60457",
    "addr:street":"W 95Th St",
    "iso:country":"US",
    "sg:address":"8611 W 95th St",
    "sg:city":"Hickory Hills",
    "sg:classifiers":[
        {
            "category":"Health Services",
            "subcategory":"Doctor",
            "type":"Services"
        }
    ],
    "sg:phone":"+1 708 598 5858",
    "sg:postcode":"60457",
    "sg:province":"IL",
    "sg:tags":[
        "dentist"
    ],
    "wof:name":"Hickory Hills Dental Center",
    "wof:placetype":"venue"
},
  "geometry": {"coordinates":[-87.832748,41.718244],"type":"Point"}
}