{
  "type": "Feature",
  "properties": {
    "iso:country":"US",
    "sg:address":"1129 S Harlem Ave",
    "sg:city":"Chicago",
    "sg:classifiers":[
        {
            "category":"Health Services",
            "subcategory":"Dentist",
            "type":"Services"
        }
    ],
    "sg:phone":"+1 312 326 5437",
    "sg:postcode":"60130",
    "sg:province":"IL",
    "sg:tags":[
        "pediatric"
    ],
    "sg:website":"www.little-teeth-big-smiles.com",
    "wof:name":"Jerry Udelson, DDS",
    "wof:placetype":"venue"
},
  "geometry": {"coordinates":[-87.80544500000001,41.90053],"type":"Point"}
}