{
  "type": "Feature",
  "properties": {
    "iso:country":"US",
    "sg:address":"2813 W Touhy Ave",
    "sg:city":"Chicago",
    "sg:classifiers":[
        {
            "category":"Arena",
            "subcategory":"Sports Club",
            "type":"Entertainment"
        }
    ],
    "sg:phone":"+1 773 764 5589",
    "sg:postcode":"60645",
    "sg:province":"IL",
    "sg:tags":[
        "martial art",
        "instruction"
    ],
    "wof:name":"Romb's Martial Art Academy",
    "wof:placetype":"venue"
},
  "geometry": {"coordinates":[-87.70000400000001,42.012082],"type":"Point"}
}