{
  "type": "Feature",
  "properties": {
    "addr:full":"1334 15th St Moline IL 61265",
    "addr:housenumber":"1334",
    "addr:postcode":"61265",
    "addr:street":"15Th St",
    "iso:country":"US",
    "sg:address":"1334 15th St",
    "sg:city":"Moline",
    "sg:classifiers":[
        {
            "category":"Personal",
            "subcategory":"Beauty Salon",
            "type":"Services"
        }
    ],
    "sg:phone":"+1 309 764 0333",
    "sg:postcode":"61265",
    "sg:province":"IL",
    "sg:tags":[
        "hair",
        "stylist"
    ],
    "wof:name":"15th Street Hair Designers",
    "wof:placetype":"venue"
},
  "geometry": {"coordinates":[-90.515612,41.498995],"type":"Point"}
}