{
  "type": "Feature",
  "properties": {
    "addr:full":"21 Plaza Dr Beardstown IL 62618",
    "addr:housenumber":"21",
    "addr:postcode":"62618",
    "addr:street":"Plaza Dr",
    "iso:country":"US",
    "sg:address":"21 Plaza Dr",
    "sg:city":"Beardstown",
    "sg:classifiers":[
        {
            "category":"Shopping",
            "subcategory":"Department Store",
            "type":"Retail Goods"
        },
        {
            "category":"Shopping",
            "subcategory":"Discount & Variety Stores",
            "type":"Retail Goods"
        },
        {
            "category":"Shopping",
            "type":"Retail Goods"
        },
        {
            "category":"Food & Beverages",
            "subcategory":"Groceries & Convenience Stores",
            "type":"Retail Goods"
        }
    ],
    "sg:phone":"+1 217 323 3566",
    "sg:postcode":"62618",
    "sg:province":"IL",
    "sg:tags":[
        "merchandise"
    ],
    "sg:website":"http://www.dollargeneral.com",
    "wof:name":"Dollar General",
    "wof:placetype":"venue"
},
  "geometry": {"coordinates":[-90.441294,40.003019],"type":"Point"}
}