{
  "type": "Feature",
  "properties": {
    "addr:full":"15431 Sheffield Ln Orland Park IL 60462",
    "addr:housenumber":"15431",
    "addr:postcode":"60462",
    "addr:street":"Sheffield Ln",
    "iso:country":"US",
    "sg:address":"15431 Sheffield Ln",
    "sg:city":"Orland Park",
    "sg:classifiers":[
        {
            "category":"Manufacturing",
            "subcategory":"Tools & Machinery",
            "type":"Manufacturing & Wholesale Goods"
        }
    ],
    "sg:phone":"+1 708 226 1127",
    "sg:postcode":"60462",
    "sg:province":"IL",
    "sg:tags":[
        "article",
        "electronic",
        "merchandising",
        "mfg"
    ],
    "wof:name":"Checkpoint Systems Inc",
    "wof:placetype":"venue"
},
  "geometry": {"coordinates":[-87.840323,41.611376],"type":"Point"}
}