{
  "type": "Feature",
  "properties": {
    "iso:country":"US",
    "sg:address":"6248 W 95th St",
    "sg:city":"Oak Lawn",
    "sg:classifiers":[
        {
            "category":"Restaurant",
            "type":"Food & Drink"
        }
    ],
    "sg:phone":"+1 708 598 7007",
    "sg:postcode":"60453",
    "sg:province":"IL",
    "sg:tags":[
        "italian"
    ],
    "sg:website":"www.miafrancesca.com/restaurants...",
    "wof:name":"Francesca's at 95th",
    "wof:placetype":"venue"
},
  "geometry": {"coordinates":[-87.7771,41.719567],"type":"Point"}
}