{
  "type": "Feature",
  "properties": {
    "iso:country":"US",
    "sg:address":"3725 Morse Ave",
    "sg:city":"Lincolnwood",
    "sg:classifiers":[
        {
            "category":"Professional",
            "type":"Services"
        }
    ],
    "sg:phone":"+1 847 763 9104",
    "sg:postcode":"60712",
    "sg:province":"IL",
    "sg:tags":[
        "establishment"
    ],
    "wof:name":"APM Worldwide",
    "wof:placetype":"venue"
},
  "geometry": {"coordinates":[-87.72319400000001,42.006072],"type":"Point"}
}