{
  "type": "Feature",
  "properties": {
    "addr:full":"2086 Colony Ct Beloit IL 53511",
    "addr:housenumber":"2086",
    "addr:postcode":"53511",
    "addr:street":"Colony Ct",
    "iso:country":"US",
    "sg:address":"2086 Colony Ct",
    "sg:city":"Beloit",
    "sg:classifiers":[
        {
            "category":"Health Services",
            "subcategory":"Nursing And Care Facility",
            "type":"Services"
        }
    ],
    "sg:phone":"+1 608 365 7470",
    "sg:postcode":"53511",
    "sg:province":"IL",
    "sg:tags":[
        "home",
        "rest"
    ],
    "wof:name":"Encore Senior Villa At Beloit",
    "wof:placetype":"venue"
},
  "geometry": {"coordinates":[-89.010041,42.552619],"type":"Point"}
}