{
  "type": "Feature",
  "properties": {
    "iso:country":"US",
    "sg:address":"342 N Mason Ave",
    "sg:city":"Amboy",
    "sg:classifiers":[
        {
            "category":"Autos & Motor Vehicles",
            "subcategory":"Fuel & Gas Station",
            "type":"Retail Goods"
        }
    ],
    "sg:phone":"+1 815 857 2990",
    "sg:postcode":"61310",
    "sg:province":"IL",
    "sg:tags":[
        "station",
        "gasoline",
        "oil"
    ],
    "wof:name":"Amboy Express Lane",
    "wof:placetype":"venue"
},
  "geometry": {"coordinates":[-89.32935999999999,41.721465],"type":"Point"}
}