{
  "type": "Feature",
  "properties": {
    "iso:country":"US",
    "sg:address":"2521 Gross Point Rd",
    "sg:city":"Evanston",
    "sg:classifiers":[
        {
            "category":"Wholesale",
            "subcategory":"Machinery & Supplies",
            "type":"Manufacturing & Wholesale Goods"
        }
    ],
    "sg:phone":"+1 847 864 9670",
    "sg:postcode":"60201",
    "sg:province":"IL",
    "sg:tags":[
        "industrial"
    ],
    "wof:name":"Kna & Company Inc",
    "wof:placetype":"venue"
},
  "geometry": {"coordinates":[-87.728975,42.063748],"type":"Point"}
}