{
  "type": "Feature",
  "properties": {
    "addr:full":"9363 S Longwood Dr Chicago IL 60643",
    "addr:housenumber":"9363",
    "addr:postcode":"60643",
    "addr:street":"S Longwood Dr",
    "iso:country":"US",
    "sg:address":"9363 S Longwood Dr",
    "sg:city":"Chicago",
    "sg:classifiers":[
        {
            "category":"Building & Trades",
            "subcategory":"Construction",
            "type":"Services"
        }
    ],
    "sg:phone":"+1 773 779 5941",
    "sg:postcode":"60643",
    "sg:province":"IL",
    "sg:tags":[
        "system",
        "contractor",
        "air conditioning"
    ],
    "wof:name":"Longwood Service Inc",
    "wof:placetype":"venue"
},
  "geometry": {"coordinates":[-87.66832700000001,41.721134],"type":"Point"}
}