{
  "type": "Feature",
  "properties": {
    "iso:country":"US",
    "sg:address":"4109 S. Halsted Street",
    "sg:city":"Chicago",
    "sg:classifiers":[
        {
            "category":"Professional",
            "subcategory":"Business Services",
            "type":"Services"
        }
    ],
    "sg:phone":"+1 773 247 6902",
    "sg:postcode":"60609",
    "sg:province":"IL",
    "sg:tags":[
        "delivery",
        "courier"
    ],
    "sg:website":"www.usps.com",
    "wof:name":"USPS-Stockyard Station",
    "wof:placetype":"venue"
},
  "geometry": {"coordinates":[-87.645775,41.820039],"type":"Point"}
}