{
  "type": "Feature",
  "properties": {
    "iso:country":"US",
    "sg:address":"11014 Front St",
    "sg:city":"Mokena",
    "sg:classifiers":[
        {
            "category":"Personal",
            "subcategory":"Beauty Salon",
            "type":"Services"
        },
        {
            "category":"Personal",
            "subcategory":"Barber",
            "type":"Services"
        }
    ],
    "sg:phone":"+1 708 479 6066",
    "sg:postcode":"60448",
    "sg:province":"IL",
    "sg:tags":[
        "hair"
    ],
    "wof:name":"Dina's Barber Shop",
    "wof:placetype":"venue"
},
  "geometry": {"coordinates":[-87.884649,41.532385],"type":"Point"}
}