{
  "type": "Feature",
  "properties": {
    "iso:country":"US",
    "sg:address":"700 E Grand Ave Ste 123",
    "sg:city":"Chicago",
    "sg:classifiers":[
        {
            "category":"Restaurant",
            "type":"Food & Drink"
        }
    ],
    "sg:phone":"+1 312 494 9400",
    "sg:postcode":"60611",
    "sg:province":"IL",
    "wof:name":"Twisted Lizard",
    "wof:placetype":"venue"
},
  "geometry": {"coordinates":[-87.610001,41.892101],"type":"Point"}
}