{
  "type": "Feature",
  "properties": {
    "iso:country":"US",
    "sg:address":"8531 S 83rd Ct",
    "sg:city":"Hickory Hills",
    "sg:classifiers":[
        {
            "category":"Travel",
            "subcategory":"Travel Agent",
            "type":"Entertainment"
        }
    ],
    "sg:phone":"+1 708 793 5500",
    "sg:postcode":"60457",
    "sg:province":"IL",
    "sg:tags":[
        "agency",
        "bureau"
    ],
    "wof:name":"Annie's Cruises & Tours Inc",
    "wof:placetype":"venue"
},
  "geometry": {"coordinates":[-87.827115,41.735139],"type":"Point"}
}