{
  "type": "Feature",
  "properties": {
    "iso:country":"US",
    "sg:address":"550 N McLean Blvd",
    "sg:city":"Elgin",
    "sg:classifiers":[
        {
            "category":"Restaurant",
            "type":"Food & Drink"
        }
    ],
    "sg:phone":"+1 847 697 7311",
    "sg:postcode":"60123",
    "sg:province":"IL",
    "wof:name":"Streets Of Chicago",
    "wof:placetype":"venue"
},
  "geometry": {"coordinates":[-88.313872,42.019058],"type":"Point"}
}