{
  "type": "Feature",
  "properties": {
    "addr:full":"150 N Wacker Drive Chicago IL 60606",
    "addr:housenumber":"150",
    "addr:postcode":"60606",
    "addr:street":"N Wacker Drive",
    "iso:country":"US",
    "sg:address":"150 N Wacker Drive",
    "sg:city":"Chicago",
    "sg:classifiers":[
        {
            "category":"Travel",
            "subcategory":"Travel Agent",
            "type":"Entertainment"
        }
    ],
    "sg:phone":"+1 312 840 8090",
    "sg:postcode":"60606",
    "sg:province":"IL",
    "sg:website":"www.meetpuertorico.com",
    "wof:name":"Puerto Convention Center",
    "wof:placetype":"venue"
},
  "geometry": {"coordinates":[-87.637306,41.885096],"type":"Point"}
}