{
  "type": "Feature",
  "properties": {
    "iso:country":"US",
    "sg:address":"1022 Ridgeview Dr",
    "sg:city":"Barrington",
    "sg:classifiers":[
        {
            "category":"Banks & Credit Unions",
            "subcategory":"Bank",
            "type":"Services"
        }
    ],
    "sg:phone":"+1 847 382 4896",
    "sg:postcode":"60010",
    "sg:province":"IL",
    "sg:tags":[
        "institution",
        "business"
    ],
    "wof:name":"Dnh Ventures Inc",
    "wof:placetype":"venue"
},
  "geometry": {"coordinates":[-88.13609700000001,42.106889],"type":"Point"}
}