{
  "type": "Feature",
  "properties": {
    "addr:full":"6134 S Pulaski Rd Chicago IL 60629",
    "addr:housenumber":"6134",
    "addr:postcode":"60629",
    "addr:street":"S Pulaski Rd",
    "iso:country":"US",
    "sg:address":"6134 S Pulaski Rd",
    "sg:city":"Chicago",
    "sg:classifiers":[
        {
            "category":"Manufacturing",
            "subcategory":"Textiles",
            "type":"Manufacturing & Wholesale Goods"
        }
    ],
    "sg:phone":"+1 773 582 7900",
    "sg:postcode":"60629",
    "sg:province":"IL",
    "sg:tags":[
        "sewing",
        "contractor"
    ],
    "wof:name":"We're In Stitches",
    "wof:placetype":"venue"
},
  "geometry": {"coordinates":[-87.722841,41.781656],"type":"Point"}
}