{
  "type": "Feature",
  "properties": {
    "addr:full":"302 Lathrop Ave River Forest IL 60305",
    "addr:housenumber":"302",
    "addr:postcode":"60305",
    "addr:street":"Lathrop Ave",
    "iso:country":"US",
    "sg:address":"302 Lathrop Ave",
    "sg:city":"River Forest",
    "sg:classifiers":[
        {
            "category":"Home & Garden",
            "subcategory":"Home Furnishings",
            "type":"Retail Goods"
        }
    ],
    "sg:phone":"+1 708 366 1114",
    "sg:postcode":"60305",
    "sg:province":"IL",
    "sg:tags":[
        "bath",
        "kitchen"
    ],
    "wof:name":"Pampered Chef",
    "wof:placetype":"venue"
},
  "geometry": {"coordinates":[-87.81466899999999,41.884714],"type":"Point"}
}