{
  "type": "Feature",
  "properties": {
    "addr:full":"5100 W Harrison St Chicago IL 60644",
    "addr:housenumber":"5100",
    "addr:postcode":"60644",
    "addr:street":"W Harrison St",
    "iso:country":"US",
    "sg:address":"5100 W Harrison St",
    "sg:city":"Chicago",
    "sg:classifiers":[
        {
            "category":"Professional",
            "subcategory":"Art Services",
            "type":"Services"
        }
    ],
    "sg:phone":"+1 312 832 3124",
    "sg:postcode":"60644",
    "sg:province":"IL",
    "sg:tags":[
        "commercial",
        "design"
    ],
    "wof:name":"Studio Air",
    "wof:placetype":"venue"
},
  "geometry": {"coordinates":[-87.754806,41.872946],"type":"Point"}
}