{
  "type": "Feature",
  "properties": {
    "addr:full":"218 Gregory M Sears Dr Gilberts IL 60136",
    "addr:housenumber":"218",
    "addr:postcode":"60136",
    "addr:street":"Gregory M Sears Dr",
    "iso:country":"US",
    "sg:address":"218 Gregory M Sears Dr",
    "sg:city":"Gilberts",
    "sg:classifiers":[
        {
            "category":"Building & Trades",
            "subcategory":"Landscaping Services",
            "type":"Services"
        }
    ],
    "sg:phone":"+1 847 931 0214",
    "sg:postcode":"60136",
    "sg:province":"IL",
    "wof:name":"Dooty Free Lawns",
    "wof:placetype":"venue"
},
  "geometry": {"coordinates":[-88.37014499999999,42.081192],"type":"Point"}
}