{
  "type": "Feature",
  "properties": {
    "iso:country":"US",
    "sg:address":"802 Thunderbird Trl",
    "sg:city":"Carol Stream",
    "sg:classifiers":[
        {
            "category":"Professional",
            "type":"Services"
        }
    ],
    "sg:phone":"+1 630 254 5857",
    "sg:postcode":"60188",
    "sg:province":"IL",
    "wof:name":"Bradleys Handyman Service",
    "wof:placetype":"venue"
},
  "geometry": {"coordinates":[-88.149634,41.911274],"type":"Point"}
}