{
  "type": "Feature",
  "properties": {
    "iso:country":"US",
    "sg:address":"1775 Walters Ave",
    "sg:city":"Northbrook",
    "sg:classifiers":[
        {
            "category":"Health Services",
            "subcategory":"Health Practitioner",
            "type":"Services"
        }
    ],
    "sg:phone":"+1 847 480 0727",
    "sg:postcode":"60062",
    "sg:province":"IL",
    "sg:tags":[
        "psychologist"
    ],
    "wof:name":"Mary F Fisher PHD",
    "wof:placetype":"venue"
},
  "geometry": {"coordinates":[-87.82399,42.127255],"type":"Point"}
}