{
  "type": "Feature",
  "properties": {
    "iso:country":"US",
    "sg:address":"5401 S Lorel Ave",
    "sg:city":"Chicago",
    "sg:classifiers":[
        {
            "category":"Building & Trades",
            "subcategory":"Construction",
            "type":"Services"
        }
    ],
    "sg:phone":"+1 312 806 1983",
    "sg:postcode":"60638",
    "sg:province":"IL",
    "sg:tags":[
        "contractor"
    ],
    "sg:website":"greatexpectationsremodeling.net",
    "wof:name":"Great Expectations Remodeling",
    "wof:placetype":"venue"
},
  "geometry": {"coordinates":[-87.755805,41.794441],"type":"Point"}
}