{
  "type": "Feature",
  "properties": {
    "iso:country":"US",
    "sg:address":"1710 N Wells St",
    "sg:city":"Chicago",
    "sg:classifiers":[
        {
            "category":"Bakery",
            "type":"Food & Drink"
        }
    ],
    "sg:phone":"+1 773 545 7215",
    "sg:postcode":"60614",
    "sg:province":"IL",
    "sg:website":"www.delightfulpastries.com",
    "wof:name":"Delightful Pastries",
    "wof:placetype":"venue"
},
  "geometry": {"coordinates":[-87.63479700000001,41.913216],"type":"Point"}
}