{
  "type": "Feature",
  "properties": {
    "addr:full":"11211 120th Ave Pleasant Prairie IL 53142",
    "addr:housenumber":"11211",
    "addr:postcode":"53142",
    "addr:street":"120Th Ave",
    "iso:country":"US",
    "sg:address":"11211 120th Ave",
    "sg:city":"Pleasant Prairie",
    "sg:classifiers":[
        {
            "category":"Shopping",
            "subcategory":"Clothing, Apparel, & Fashions",
            "type":"Retail Goods"
        }
    ],
    "sg:phone":"+1 262 857 3983",
    "sg:postcode":"53142",
    "sg:province":"IL",
    "sg:tags":[
        "infant",
        "wear"
    ],
    "wof:name":"Limited Too",
    "wof:placetype":"venue"
},
  "geometry": {"coordinates":[-87.954379,42.523679],"type":"Point"}
}