{
  "type": "Feature",
  "properties": {
    "iso:country":"US",
    "sg:address":"120 Manor Ct",
    "sg:city":"Alton",
    "sg:classifiers":[
        {
            "category":"Real Estate",
            "subcategory":"Real Estate Operator",
            "type":"Services"
        }
    ],
    "sg:phone":"+1 618 465 0120",
    "sg:postcode":"62002",
    "sg:province":"IL",
    "sg:tags":[
        "building",
        "apartment"
    ],
    "wof:name":"Hempel Apartments",
    "wof:placetype":"venue"
},
  "geometry": {"coordinates":[-90.157392,38.890484],"type":"Point"}
}