{
  "type": "Feature",
  "properties": {
    "iso:country":"US",
    "sg:address":"3 Barton Ct",
    "sg:city":"Champaign",
    "sg:classifiers":[
        {
            "category":"Social Services",
            "subcategory":"Child Care",
            "type":"Services"
        }
    ],
    "sg:phone":"+1 217 352 2324",
    "sg:postcode":"61821",
    "sg:province":"IL",
    "wof:name":"Stephanie Alumbaugh",
    "wof:placetype":"venue"
},
  "geometry": {"coordinates":[-88.28684,40.095321],"type":"Point"}
}