{
  "type": "Feature",
  "properties": {
    "addr:full":"1307 Main Street Rd Cary IL 60013",
    "addr:housenumber":"1307",
    "addr:postcode":"60013",
    "addr:street":"Main Street Rd",
    "iso:country":"US",
    "sg:address":"1307 Main Street Rd",
    "sg:city":"Cary",
    "sg:classifiers":[
        {
            "category":"Freight",
            "type":"Transportation"
        }
    ],
    "sg:phone":"+1 847 639 4784",
    "sg:postcode":"60013",
    "sg:province":"IL",
    "sg:tags":[
        "trucking"
    ],
    "wof:name":"Tiker Trucking Inc",
    "wof:placetype":"venue"
},
  "geometry": {"coordinates":[-88.207274,42.208729],"type":"Point"}
}