{
  "type": "Feature",
  "properties": {
    "addr:full":"800 Dempster St Evanston IL 60202",
    "addr:housenumber":"800",
    "addr:postcode":"60202",
    "addr:street":"Dempster St",
    "iso:country":"US",
    "sg:address":"800 Dempster St",
    "sg:city":"Evanston",
    "sg:classifiers":[
        {
            "category":"Shopping",
            "subcategory":"Music",
            "type":"Retail Goods"
        }
    ],
    "sg:phone":"+1 847 491 1690",
    "sg:postcode":"60202",
    "sg:province":"IL",
    "sg:tags":[
        "compact",
        "record",
        "disc",
        "tape"
    ],
    "wof:name":"2nd Hand Tunes",
    "wof:placetype":"venue"
},
  "geometry": {"coordinates":[-87.682688,42.041201],"type":"Point"}
}