{
  "type": "Feature",
  "properties": {
    "addr:full":"122 N Main St Pearl City IL 61062",
    "addr:housenumber":"122",
    "addr:postcode":"61062",
    "addr:street":"N Main St",
    "iso:country":"US",
    "sg:address":"122 N Main St",
    "sg:city":"Pearl City",
    "sg:classifiers":[
        {
            "category":"Freight",
            "type":"Transportation"
        }
    ],
    "sg:phone":"+1 815 443 2336",
    "sg:postcode":"61062",
    "sg:province":"IL",
    "sg:tags":[
        "operator",
        "trucking"
    ],
    "wof:name":"Werkheiser Trucking Inc",
    "wof:placetype":"venue"
},
  "geometry": {"coordinates":[-89.826322,42.268549],"type":"Point"}
}