{
  "type": "Feature",
  "properties": {
    "addr:full":"237 E Delmar Ave Alton IL 62002",
    "addr:housenumber":"237",
    "addr:postcode":"62002",
    "addr:street":"E Delmar Ave",
    "iso:country":"US",
    "sg:address":"237 E Delmar Ave",
    "sg:city":"Alton",
    "sg:classifiers":[
        {
            "category":"Recreation",
            "type":"Entertainment"
        }
    ],
    "sg:phone":"+1 618 462 5425",
    "sg:postcode":"62002",
    "sg:province":"IL",
    "sg:tags":[
        "martial",
        "arts",
        "instruction"
    ],
    "wof:name":"American Family Martial Arts",
    "wof:placetype":"venue"
},
  "geometry": {"coordinates":[-90.17376299999999,38.92225],"type":"Point"}
}