{
  "type": "Feature",
  "properties": {
    "addr:full":"257 Kenmore Ave Deerfield IL 60015",
    "addr:housenumber":"257",
    "addr:postcode":"60015",
    "addr:street":"Kenmore Ave",
    "iso:country":"US",
    "sg:address":"257 Kenmore Ave",
    "sg:city":"Deerfield",
    "sg:classifiers":[
        {
            "category":"Professional",
            "subcategory":"Business Services",
            "type":"Services"
        }
    ],
    "sg:phone":"+1 847 940 9490",
    "sg:postcode":"60015",
    "sg:province":"IL",
    "wof:name":"Lorrie Burrows Garden Design",
    "wof:placetype":"venue"
},
  "geometry": {"coordinates":[-87.86479,42.157328],"type":"Point"}
}