{
  "type": "Feature",
  "properties": {
    "iso:country":"US",
    "sg:address":"4140 N Sheridan Rd",
    "sg:city":"Chicago",
    "sg:classifiers":[
        {
            "category":"Shopping",
            "subcategory":"Clothing, Apparel, & Fashions",
            "type":"Retail Goods"
        },
        {
            "category":"Manufacturing",
            "subcategory":"Apparel",
            "type":"Manufacturing & Wholesale Goods"
        }
    ],
    "sg:phone":"+1 773 472 7220",
    "sg:postcode":"60613",
    "sg:province":"IL",
    "sg:tags":[
        "apparel-wholesale",
        "accessory",
        "women's",
        "clothing",
        "manufacturer"
    ],
    "sg:website":"www.blakestandard.com",
    "wof:name":"Blake Standard",
    "wof:placetype":"venue"
},
  "geometry": {"coordinates":[-87.654786,41.957688],"type":"Point"}
}