{
  "type": "Feature",
  "properties": {
    "addr:full":"9700 S Commercial Ave Chicago IL 60617",
    "addr:housenumber":"9700",
    "addr:postcode":"60617",
    "addr:street":"S Commercial Ave",
    "iso:country":"US",
    "sg:address":"9700 S Commercial Ave",
    "sg:city":"Chicago",
    "sg:classifiers":[
        {
            "category":"Food & Beverages",
            "subcategory":"Liquor & Beverages",
            "type":"Retail Goods"
        }
    ],
    "sg:phone":"+1 773 221 3224",
    "sg:postcode":"60617",
    "sg:province":"IL",
    "sg:tags":[
        "beer",
        "spirit",
        "wine"
    ],
    "wof:name":"Lopez Liquors",
    "wof:placetype":"venue"
},
  "geometry": {"coordinates":[-87.551102,41.718899],"type":"Point"}
}