{
  "type": "Feature",
  "properties": {
    "iso:country":"US",
    "sg:address":"26480 W Klondike Ave",
    "sg:city":"Antioch",
    "sg:classifiers":[
        {
            "category":"Freight",
            "type":"Transportation"
        }
    ],
    "sg:phone":"+1 847 838 0842",
    "sg:postcode":"60002",
    "sg:province":"IL",
    "sg:tags":[
        "trucking"
    ],
    "wof:name":"Spirit Enterprises Inc",
    "wof:placetype":"venue"
},
  "geometry": {"coordinates":[-88.152632,42.42833],"type":"Point"}
}