{
  "type": "Feature",
  "properties": {
    "iso:country":"US",
    "sg:address":"8822 S Indiana Ave",
    "sg:city":"Chicago",
    "sg:classifiers":[
        {
            "category":"Education",
            "subcategory":"Special Training",
            "type":"Public Place"
        }
    ],
    "sg:phone":"+1 773 633 2658",
    "sg:postcode":"60619",
    "sg:province":"IL",
    "sg:tags":[
        "educational"
    ],
    "wof:name":"Academy For Digital Media Studies, Inc.",
    "wof:placetype":"venue"
},
  "geometry": {"coordinates":[-87.619328,41.734189],"type":"Point"}
}