{
  "type": "Feature",
  "properties": {
    "iso:country":"US",
    "sg:address":"17306 Kedzie Ave",
    "sg:city":"Hazel Crest",
    "sg:classifiers":[
        {
            "category":"Shopping",
            "subcategory":"Bicycles & Sporting Goods",
            "type":"Retail Goods"
        }
    ],
    "sg:phone":"+1 708 335 2755",
    "sg:postcode":"60429",
    "sg:province":"IL",
    "wof:name":"Bike Doctors",
    "wof:placetype":"venue"
},
  "geometry": {"coordinates":[-87.69445,41.571832],"type":"Point"}
}