{
  "type": "Feature",
  "properties": {
    "addr:full":"2834 W Oregon Trail Rd Oregon IL 61061",
    "addr:housenumber":"2834",
    "addr:postcode":"61061",
    "addr:street":"W Oregon Trail Rd",
    "iso:country":"US",
    "sg:address":"2834 W Oregon Trail Rd",
    "sg:city":"Oregon",
    "sg:classifiers":[
        {
            "category":"Recreation",
            "type":"Entertainment"
        }
    ],
    "sg:phone":"+1 815 732 6074",
    "sg:postcode":"61061",
    "sg:province":"IL",
    "wof:name":"Mark W Mordan",
    "wof:placetype":"venue"
},
  "geometry": {"coordinates":[-89.39049900000001,42.016332],"type":"Point"}
}