{
  "type": "Feature",
  "properties": {
    "addr:full":"2303 N Clybourn Avenue Chicago IL 60614",
    "addr:housenumber":"2303",
    "addr:postcode":"60614",
    "addr:street":"N Clybourn Avenue",
    "iso:country":"US",
    "sg:address":"2303 N Clybourn Avenue",
    "sg:city":"Chicago",
    "sg:classifiers":[
        {
            "category":"Real Estate",
            "subcategory":"Real Estate Services",
            "type":"Services"
        },
        {
            "category":"Real Estate",
            "subcategory":"Real Estate Operator",
            "type":"Services"
        }
    ],
    "sg:phone":"+1 773 871 8505",
    "sg:postcode":"60614",
    "sg:province":"IL",
    "sg:tags":[
        "vacancy",
        "apartment",
        "rental",
        "finder",
        "listing"
    ],
    "wof:name":"Fullerton Court Apts",
    "wof:placetype":"venue"
},
  "geometry": {"coordinates":[-87.66731799999999,41.923748],"type":"Point"}
}