{
  "type": "Feature",
  "properties": {
    "iso:country":"US",
    "sg:address":"2422 W Lincoln Ave",
    "sg:city":"Peoria",
    "sg:classifiers":[
        {
            "category":"Arts & Performance",
            "subcategory":"Arts Center",
            "type":"Entertainment"
        },
        {
            "category":"Shopping",
            "subcategory":"Crafts & Fabrics",
            "type":"Retail Goods"
        },
        {
            "category":"Manufacturing",
            "subcategory":"Paper Products",
            "type":"Manufacturing & Wholesale Goods"
        },
        {
            "category":"Shopping",
            "subcategory":"Florist",
            "type":"Retail Goods"
        }
    ],
    "sg:phone":"+1 309 672 9489",
    "sg:postcode":"61605",
    "sg:province":"IL",
    "sg:tags":[
        "plant",
        "etc-retail",
        "tree",
        "artificial",
        "dried",
        "trees-silk",
        "bamboo",
        "flowers"
    ],
    "wof:name":"Schepke Flower Center",
    "wof:placetype":"venue"
},
  "geometry": {"coordinates":[-89.631508,40.681402],"type":"Point"}
}