{
  "type": "Feature",
  "properties": {
    "iso:country":"US",
    "sg:address":"13747 S 88th Ave",
    "sg:city":"Orland Park",
    "sg:classifiers":[
        {
            "category":"Education",
            "subcategory":"Vocational School",
            "type":"Public Place"
        }
    ],
    "sg:phone":"+1 708 460 6157",
    "sg:postcode":"60462",
    "sg:province":"IL",
    "sg:tags":[
        "processing",
        "datum"
    ],
    "wof:name":"Chyna Computer Tutor",
    "wof:placetype":"venue"
},
  "geometry": {"coordinates":[-87.832723,41.639733],"type":"Point"}
}