{
  "type": "Feature",
  "properties": {
    "iso:country":"US",
    "sg:address":"1015 N Moki Ln",
    "sg:city":"Mount Prospect",
    "sg:classifiers":[
        {
            "category":"Real Estate",
            "subcategory":"Real Estate Agent",
            "type":"Services"
        }
    ],
    "sg:phone":"+1 847 635 0760",
    "sg:postcode":"60056",
    "sg:province":"IL",
    "wof:name":"Spm Inc",
    "wof:placetype":"venue"
},
  "geometry": {"coordinates":[-87.89314400000001,42.084576],"type":"Point"}
}