{
  "type": "Feature",
  "properties": {
    "iso:country":"US",
    "sg:address":"473 State Rte 73 S",
    "sg:city":"Pearl City",
    "sg:phone":"+1 815 443 2520",
    "sg:postcode":"61062",
    "sg:province":"IL",
    "sg:tags":[
        "farm",
        "corn"
    ],
    "wof:name":"Wayne Solt",
    "wof:placetype":"venue"
},
  "geometry": {"coordinates":[-89.826736,42.292997],"type":"Point"}
}