{
  "type": "Feature",
  "properties": {
    "addr:full":"55 Karen Dr Bourbonnais IL 60914",
    "addr:housenumber":"55",
    "addr:postcode":"60914",
    "addr:street":"Karen Dr",
    "iso:country":"US",
    "sg:address":"55 Karen Dr",
    "sg:city":"Bourbonnais",
    "sg:classifiers":[
        {
            "category":"Personal",
            "subcategory":"Beauty Salon",
            "type":"Services"
        }
    ],
    "sg:phone":"+1 815 932 0175",
    "sg:postcode":"60914",
    "sg:province":"IL",
    "wof:name":"Diana's Hair Fashions",
    "wof:placetype":"venue"
},
  "geometry": {"coordinates":[-87.88466099999999,41.177596],"type":"Point"}
}