{
  "type": "Feature",
  "properties": {
    "addr:full":"499 Royal Oaks Dr Wood Dale IL 60191",
    "addr:housenumber":"499",
    "addr:postcode":"60191",
    "addr:street":"Royal Oaks Dr",
    "iso:country":"US",
    "sg:address":"499 Royal Oaks Dr",
    "sg:city":"Wood Dale",
    "sg:classifiers":[
        {
            "category":"Professional",
            "subcategory":"Business Services",
            "type":"Services"
        }
    ],
    "sg:phone":"+1 630 766 2467",
    "sg:postcode":"60191",
    "sg:province":"IL",
    "wof:name":"Hillyn H Sennholtz",
    "wof:placetype":"venue"
},
  "geometry": {"coordinates":[-87.960527,41.952337],"type":"Point"}
}