{
  "type": "Feature",
  "properties": {
    "iso:country":"US",
    "sg:address":"1410 8th St",
    "sg:city":"Highland",
    "sg:classifiers":[
        {
            "category":"Social Services",
            "subcategory":"Child Care",
            "type":"Services"
        }
    ],
    "sg:phone":"+1 618 654 1021",
    "sg:postcode":"62249",
    "sg:province":"IL",
    "sg:tags":[
        "day"
    ],
    "wof:name":"Debbie Mc Neilly",
    "wof:placetype":"venue"
},
  "geometry": {"coordinates":[-89.672815,38.742416],"type":"Point"}
}