{
  "type": "Feature",
  "properties": {
    "addr:full":"2458 S Millard Ave Chicago IL 60623",
    "addr:housenumber":"2458",
    "addr:postcode":"60623",
    "addr:street":"S Millard Ave",
    "iso:country":"US",
    "sg:address":"2458 S Millard Ave",
    "sg:city":"Chicago",
    "sg:classifiers":[
        {
            "category":"Sports & Exercise",
            "subcategory":"Gym",
            "type":"Entertainment"
        }
    ],
    "sg:phone":"+1 773 542 5254",
    "sg:postcode":"60623",
    "sg:province":"IL",
    "sg:tags":[
        "trainer"
    ],
    "sg:website":"www.curves.com",
    "wof:name":"Curves For Women Little Village",
    "wof:placetype":"venue"
},
  "geometry": {"coordinates":[-87.71641200000001,41.84634],"type":"Point"}
}