{
  "type": "Feature",
  "properties": {
    "iso:country":"US",
    "sg:address":"1130 Donegal Ln",
    "sg:city":"Northbrook",
    "sg:classifiers":[
        {
            "category":"Banks & Credit Unions",
            "subcategory":"Investment Brokerage",
            "type":"Services"
        }
    ],
    "sg:phone":"+1 847 498 9173",
    "sg:postcode":"60062",
    "sg:province":"IL",
    "sg:tags":[
        "security"
    ],
    "wof:name":"Kevin P Golden",
    "wof:placetype":"venue"
},
  "geometry": {"coordinates":[-87.853034,42.13092],"type":"Point"}
}