{
  "type": "Feature",
  "properties": {
    "addr:full":"1097 Buckskin Ln Carol Stream IL 60188",
    "addr:housenumber":"1097",
    "addr:postcode":"60188",
    "addr:street":"Buckskin Ln",
    "iso:country":"US",
    "sg:address":"1097 Buckskin Ln",
    "sg:city":"Carol Stream",
    "sg:classifiers":[
        {
            "category":"Shopping",
            "type":"Retail Goods"
        }
    ],
    "sg:phone":"+1   ",
    "sg:postcode":"60188",
    "sg:province":"IL",
    "sg:tags":[
        "merchandise"
    ],
    "wof:name":"Dke Products",
    "wof:placetype":"venue"
},
  "geometry": {"coordinates":[-88.160239,41.920254],"type":"Point"}
}