{
  "type": "Feature",
  "properties": {
    "iso:country":"US",
    "sg:address":"819 S Wabash Ave",
    "sg:city":"Chicago",
    "sg:classifiers":[
        {
            "category":"Real Estate",
            "subcategory":"Architect",
            "type":"Services"
        }
    ],
    "sg:phone":"+1 312 913 1010",
    "sg:postcode":"60605",
    "sg:province":"IL",
    "wof:name":"Wright Architects",
    "wof:placetype":"venue"
},
  "geometry": {"coordinates":[-87.625885,41.871319],"type":"Point"}
}