{
  "type": "Feature",
  "properties": {
    "addr:full":"1560 Sherman Ave Evanston IL 60201",
    "addr:housenumber":"1560",
    "addr:postcode":"60201",
    "addr:street":"Sherman Ave",
    "iso:country":"US",
    "sg:address":"1560 Sherman Ave",
    "sg:city":"Evanston",
    "sg:classifiers":[
        {
            "category":"Shopping",
            "subcategory":"News",
            "type":"Retail Goods"
        }
    ],
    "sg:phone":"+1 847 864 1228",
    "sg:postcode":"60201",
    "sg:province":"IL",
    "sg:tags":[
        "dealer"
    ],
    "wof:name":"Gateway News Stand",
    "wof:placetype":"venue"
},
  "geometry": {"coordinates":[-87.68196,42.045625],"type":"Point"}
}