{
  "type": "Feature",
  "properties": {
    "addr:full":"1122 Hinman Ave Evanston IL 60202",
    "addr:housenumber":"1122",
    "addr:postcode":"60202",
    "addr:street":"Hinman Ave",
    "iso:country":"US",
    "sg:address":"1122 Hinman Ave",
    "sg:city":"Evanston",
    "sg:classifiers":[
        {
            "category":"Professional",
            "subcategory":"Business Services",
            "type":"Services"
        }
    ],
    "sg:phone":"+1 847 864 8662",
    "sg:postcode":"60202",
    "sg:province":"IL",
    "wof:name":"Midwest System Inc Sciences",
    "wof:placetype":"venue"
},
  "geometry": {"coordinates":[-87.678889,42.038865],"type":"Point"}
}