{
  "type": "Feature",
  "properties": {
    "addr:full":"10151 N Hall Ln Waltonville IL 62894",
    "addr:housenumber":"10151",
    "addr:postcode":"62894",
    "addr:street":"N Hall Ln",
    "iso:country":"US",
    "sg:address":"10151 N Hall Ln",
    "sg:city":"Waltonville",
    "sg:classifiers":[
        {
            "category":"Insurance",
            "subcategory":"Hazard Insurance",
            "type":"Services"
        }
    ],
    "sg:phone":"+1 618 735 2443",
    "sg:postcode":"62894",
    "sg:province":"IL",
    "wof:name":"Bruce Pytlinski",
    "wof:placetype":"venue"
},
  "geometry": {"coordinates":[-89.04042099999999,38.265442],"type":"Point"}
}