{
  "type": "Feature",
  "properties": {
    "addr:full":"6201 S la Grange Rd Hodgkins IL 60525",
    "addr:housenumber":"6201",
    "addr:postcode":"60525",
    "addr:street":"S La Grange Rd",
    "iso:country":"US",
    "sg:address":"6201 S la Grange Rd",
    "sg:city":"Hodgkins",
    "sg:classifiers":[
        {
            "category":"Autos & Motor Vehicles",
            "subcategory":"Automobile Sales",
            "type":"Retail Goods"
        }
    ],
    "sg:phone":"+1 877 865 6804",
    "sg:postcode":"60525",
    "sg:province":"IL",
    "sg:tags":[
        "new",
        "car"
    ],
    "sg:website":"http://www.ettleson.com",
    "wof:name":"Ettleson Cadillac Buick GMC",
    "wof:placetype":"venue"
},
  "geometry": {"coordinates":[-87.86814099999999,41.77858],"type":"Point"}
}