{
  "type": "Feature",
  "properties": {
    "iso:country":"US",
    "sg:address":"115 Danada Sq E",
    "sg:city":"Wheaton",
    "sg:classifiers":[
        {
            "category":"Shopping",
            "subcategory":"Optical Goods",
            "type":"Retail Goods"
        },
        {
            "category":"Health Services",
            "subcategory":"Optometrist",
            "type":"Services"
        }
    ],
    "sg:phone":"+1 630 668 0378",
    "sg:postcode":"60187",
    "sg:province":"IL",
    "wof:name":"Danada Vision Center",
    "wof:placetype":"venue"
},
  "geometry": {"coordinates":[-88.09922899999999,41.832869],"type":"Point"}
}