{
  "type": "Feature",
  "properties": {
    "addr:full":"800 Busse Hwy Park Ridge IL 60068",
    "addr:housenumber":"800",
    "addr:postcode":"60068",
    "addr:street":"Busse Hwy",
    "iso:country":"US",
    "sg:address":"800 Busse Hwy",
    "sg:city":"Park Ridge",
    "sg:classifiers":[
        {
            "category":"Professional",
            "subcategory":"Accounting & Tax Preparation",
            "type":"Services"
        }
    ],
    "sg:phone":"+1 847 696 1060",
    "sg:postcode":"60068",
    "sg:province":"IL",
    "sg:tags":[
        "accountant",
        "public",
        "certified"
    ],
    "wof:name":"John Seybold & Company Ltd",
    "wof:placetype":"venue"
},
  "geometry": {"coordinates":[-87.850768,42.021572],"type":"Point"}
}