{
  "type": "Feature",
  "properties": {
    "iso:country":"US",
    "sg:address":"601 E Fairchild St",
    "sg:city":"Danville",
    "sg:classifiers":[
        {
            "category":"Retail",
            "subcategory":"Auto Repair",
            "type":"Services"
        }
    ],
    "sg:phone":"+1 217 431 0813",
    "sg:postcode":"61832",
    "sg:province":"IL",
    "sg:tags":[
        "repairing",
        "automobile"
    ],
    "wof:name":"Martins Auto Repair",
    "wof:placetype":"venue"
},
  "geometry": {"coordinates":[-87.62129,40.13885],"type":"Point"}
}