{
  "type": "Feature",
  "properties": {
    "iso:country":"US",
    "sg:address":"2249 Bernice Rd",
    "sg:city":"Lansing",
    "sg:classifiers":[
        {
            "category":"Restaurant",
            "type":"Food & Drink"
        }
    ],
    "sg:phone":"+1 708 474 6300",
    "sg:postcode":"60438",
    "sg:province":"IL",
    "wof:name":"Holiday Inn",
    "wof:placetype":"venue"
},
  "geometry": {"coordinates":[-87.564796,41.5793],"type":"Point"}
}