{
  "type": "Feature",
  "properties": {
    "iso:country":"US",
    "sg:address":"502 S Franklin St",
    "sg:city":"Clayton",
    "sg:classifiers":[
        {
            "category":"Manufacturing",
            "subcategory":"Furniture",
            "type":"Manufacturing & Wholesale Goods"
        }
    ],
    "sg:phone":"+1 217 894 6313",
    "sg:postcode":"62324",
    "sg:province":"IL",
    "sg:tags":[
        "household",
        "wood",
        "mfg"
    ],
    "wof:name":"Wren Hollow Woodworking",
    "wof:placetype":"venue"
},
  "geometry": {"coordinates":[-90.960447,40.025845],"type":"Point"}
}