{
  "type": "Feature",
  "properties": {
    "addr:full":"108 N State St Chicago IL 60602",
    "addr:housenumber":"108",
    "addr:postcode":"60602",
    "addr:street":"N State St",
    "iso:country":"US",
    "sg:address":"108 N State St",
    "sg:city":"Chicago",
    "sg:classifiers":[
        {
            "category":"Shopping Center",
            "type":"Public Place"
        }
    ],
    "sg:phone":"+1 312 220 0037",
    "sg:postcode":"60602",
    "sg:province":"IL",
    "sg:website":"www.block37.com",
    "wof:name":"Block 37",
    "wof:placetype":"venue"
},
  "geometry": {"coordinates":[-87.628176,41.883397],"type":"Point"}
}