{
  "type": "Feature",
  "properties": {
    "addr:full":"2088 Ogden Ave Aurora IL 60504",
    "addr:housenumber":"2088",
    "addr:postcode":"60504",
    "addr:street":"Ogden Ave",
    "iso:country":"US",
    "sg:address":"2088 Ogden Ave",
    "sg:city":"Aurora",
    "sg:classifiers":[
        {
            "category":"Health Services",
            "subcategory":"Doctor",
            "type":"Services"
        }
    ],
    "sg:phone":"+1 630 851 6440",
    "sg:postcode":"60504",
    "sg:province":"IL",
    "sg:tags":[
        "physician",
        "cardiology",
        "thoracic",
        "surgeons",
        "surgery",
        "surgeon",
        "cardiovascular"
    ],
    "sg:website":"http://www.foxvalleycardio.com",
    "wof:name":"Fox Valley Cardiovascular Consultants",
    "wof:placetype":"venue"
},
  "geometry": {"coordinates":[-88.26544800000001,41.729743],"type":"Point"}
}