{
  "type": "Feature",
  "properties": {
    "iso:country":"US",
    "sg:address":"2613 Little Bluestem Rd",
    "sg:city":"Morris",
    "sg:classifiers":[
        {
            "category":"Utilities",
            "subcategory":"Refuse",
            "type":"Services"
        }
    ],
    "sg:phone":"+1 815 942 6100",
    "sg:postcode":"60450",
    "sg:province":"IL",
    "sg:tags":[
        "collection",
        "garbage"
    ],
    "wof:name":"Three Rivers Disposal & R",
    "wof:placetype":"venue"
},
  "geometry": {"coordinates":[-88.441864,41.383584],"type":"Point"}
}