{
  "type": "Feature",
  "properties": {
    "iso:country":"US",
    "sg:address":"5493 S Cornell Ave",
    "sg:city":"Chicago",
    "sg:classifiers":[
        {
            "category":"Banks & Credit Unions",
            "subcategory":"Bank",
            "type":"Services"
        }
    ],
    "sg:phone":"+1 773 241 5100",
    "sg:postcode":"60637",
    "sg:province":"IL",
    "sg:website":"www.harrisbank.com",
    "wof:name":"Harris Bank",
    "wof:placetype":"venue"
},
  "geometry": {"coordinates":[-87.585403,41.795412],"type":"Point"}
}