{
  "type": "Feature",
  "properties": {
    "iso:country":"US",
    "sg:address":"2821 Central St",
    "sg:city":"Evanston",
    "sg:classifiers":[
        {
            "category":"Health Services",
            "subcategory":"Clinic",
            "type":"Services"
        }
    ],
    "sg:phone":"+1 847 467 7423",
    "sg:postcode":"60201",
    "sg:province":"IL",
    "sg:tags":[
        "home",
        "care"
    ],
    "wof:name":"Palliatize Care Ctr & Hospice",
    "wof:placetype":"venue"
},
  "geometry": {"coordinates":[-87.71334400000001,42.064528],"type":"Point"}
}