{
  "type": "Feature",
  "properties": {
    "addr:full":"79 Woodcrest Ln Elk Grove Village IL 60007",
    "addr:housenumber":"79",
    "addr:postcode":"60007",
    "addr:street":"Woodcrest Ln",
    "iso:country":"US",
    "sg:address":"79 Woodcrest Ln",
    "sg:city":"Elk Grove Village",
    "sg:classifiers":[
        {
            "category":"Freight",
            "type":"Transportation"
        }
    ],
    "sg:phone":"+1 847 867 1281",
    "sg:postcode":"60007",
    "sg:province":"IL",
    "sg:tags":[
        "operator",
        "trucking"
    ],
    "wof:name":"Yeti Inc",
    "wof:placetype":"venue"
},
  "geometry": {"coordinates":[-87.983498,42.024415],"type":"Point"}
}