{
  "type": "Feature",
  "properties": {
    "iso:country":"US",
    "sg:address":"6292 N 100 East Rd",
    "sg:city":"Allerton",
    "sg:phone":"+1 217 288 9360",
    "sg:postcode":"61810",
    "sg:province":"IL",
    "sg:tags":[
        "farm",
        "corn"
    ],
    "wof:name":"Dean Warters",
    "wof:placetype":"venue"
},
  "geometry": {"coordinates":[-87.919785,39.967328],"type":"Point"}
}