{
  "type": "Feature",
  "properties": {
    "iso:country":"US",
    "sg:address":"7245 Westfield Plaza Dr",
    "sg:city":"Belleville",
    "sg:classifiers":[
        {
            "category":"Real Estate",
            "subcategory":"Real Estate Operator",
            "type":"Services"
        },
        {
            "category":"Organizations",
            "subcategory":"Professional Association",
            "type":"Services"
        }
    ],
    "sg:phone":"+1 618 233 5506",
    "sg:postcode":"62223",
    "sg:province":"IL",
    "sg:tags":[
        "building",
        "apartment"
    ],
    "wof:name":"Westfield Manor Assn",
    "wof:placetype":"venue"
},
  "geometry": {"coordinates":[-90.05211799999999,38.544967],"type":"Point"}
}