{
  "type": "Feature",
  "properties": {
    "addr:full":"1750 Cumberland Pkwy Ste 14 Algonquin IL 60102",
    "addr:housenumber":"1750",
    "addr:postcode":"60102",
    "addr:street":"Cumberland Pkwy Ste 14",
    "iso:country":"US",
    "sg:address":"1750 Cumberland Pkwy Ste 14",
    "sg:city":"Algonquin",
    "sg:classifiers":[
        {
            "category":"Building & Trades",
            "subcategory":"Locksmith",
            "type":"Services"
        }
    ],
    "sg:phone":"+1 815 455 1842",
    "sg:postcode":"60102",
    "sg:province":"IL",
    "sg:tags":[
        "key"
    ],
    "wof:name":"Omni Locks",
    "wof:placetype":"venue"
},
  "geometry": {"coordinates":[-88.26709700000001,42.1591],"type":"Point"}
}