{
  "type": "Feature",
  "properties": {
    "iso:country":"US",
    "sg:address":"103 E North St",
    "sg:city":"Colchester",
    "sg:classifiers":[
        {
            "category":"Restaurant",
            "type":"Food & Drink"
        }
    ],
    "sg:phone":"+1   ",
    "sg:postcode":"62326",
    "sg:province":"IL",
    "sg:tags":[
        "eating"
    ],
    "wof:name":"Seldos",
    "wof:placetype":"venue"
},
  "geometry": {"coordinates":[-90.792245,40.426589],"type":"Point"}
}