{
  "type": "Feature",
  "properties": {
    "iso:country":"US",
    "sg:address":"302 Chestnut St",
    "sg:city":"Dalzell",
    "sg:classifiers":[
        {
            "category":"Organizations",
            "subcategory":"Religious Organization",
            "type":"Services"
        }
    ],
    "sg:phone":"+1 815 663 6201",
    "sg:postcode":"61320",
    "sg:province":"IL",
    "sg:tags":[
        "church"
    ],
    "wof:name":"St Thomas Moore Church",
    "wof:placetype":"venue"
},
  "geometry": {"coordinates":[-89.17476,41.357734],"type":"Point"}
}