{
  "type": "Feature",
  "properties": {
    "iso:country":"US",
    "sg:address":"105 W Adams St",
    "sg:city":"Chicago",
    "sg:classifiers":[
        {
            "category":"Real Estate",
            "subcategory":"Real Estate Services",
            "type":"Services"
        }
    ],
    "sg:phone":"+1 312 782 0300",
    "sg:postcode":"60603",
    "sg:province":"IL",
    "sg:tags":[
        "management",
        "property"
    ],
    "wof:name":"First Merit Realty Services",
    "wof:placetype":"venue"
},
  "geometry": {"coordinates":[-87.630898,41.879398],"type":"Point"}
}