{
  "type": "Feature",
  "properties": {
    "addr:full":"2341 N Milwaukee Ave Chicago IL 60647",
    "addr:housenumber":"2341",
    "addr:postcode":"60647",
    "addr:street":"N Milwaukee Ave",
    "iso:country":"US",
    "sg:address":"2341 N Milwaukee Ave",
    "sg:city":"Chicago",
    "sg:classifiers":[
        {
            "category":"Manufacturing",
            "subcategory":"Chemicals & Compounds",
            "type":"Manufacturing & Wholesale Goods"
        }
    ],
    "sg:phone":"+1 773 235 5225",
    "sg:postcode":"60647",
    "sg:province":"IL",
    "sg:tags":[
        "preparation",
        "toilet",
        "mfg"
    ],
    "wof:name":"Maynard Inc",
    "wof:placetype":"venue"
},
  "geometry": {"coordinates":[-87.69829,41.923496],"type":"Point"}
}