{
  "type": "Feature",
  "properties": {
    "addr:full":"610 S Maple Ave Ste 3300 Oak Park IL 60304",
    "addr:housenumber":"610",
    "addr:postcode":"60304",
    "addr:street":"S Maple Ave Ste 3300",
    "iso:country":"US",
    "sg:address":"610 S Maple Ave Ste 3300",
    "sg:city":"Oak Park",
    "sg:classifiers":[
        {
            "category":"Health Services",
            "subcategory":"Doctor",
            "type":"Services"
        }
    ],
    "sg:phone":"+1 708 386 0954",
    "sg:postcode":"60304",
    "sg:province":"IL",
    "sg:tags":[
        "medicine",
        "internal"
    ],
    "wof:name":"Emelita C Co MD Sc",
    "wof:placetype":"venue"
},
  "geometry": {"coordinates":[-87.80358,41.878016],"type":"Point"}
}