{
  "type": "Feature",
  "properties": {
    "addr:full":"2139 N Hoyne Ave Chicago IL 60647",
    "addr:housenumber":"2139",
    "addr:postcode":"60647",
    "addr:street":"N Hoyne Ave",
    "iso:country":"US",
    "sg:address":"2139 N Hoyne Ave",
    "sg:city":"Chicago",
    "sg:classifiers":[
        {
            "category":"Mining & Drilling",
            "type":"Manufacturing & Wholesale Goods"
        }
    ],
    "sg:phone":"+1 312 525 9865",
    "sg:postcode":"60647",
    "sg:province":"IL",
    "wof:name":"Stone Chicago, Inc.",
    "wof:placetype":"venue"
},
  "geometry": {"coordinates":[-87.680196,41.920851],"type":"Point"}
}