{
  "type": "Feature",
  "properties": {
    "addr:full":"110 S Scott St Oakwood IL 61858",
    "addr:housenumber":"110",
    "addr:postcode":"61858",
    "addr:street":"S Scott St",
    "iso:country":"US",
    "sg:address":"110 S Scott St",
    "sg:city":"Oakwood",
    "sg:classifiers":[
        {
            "category":"Government",
            "subcategory":"Post Office",
            "type":"Public Place"
        }
    ],
    "sg:phone":"+1 217 354 2100",
    "sg:postcode":"61858",
    "sg:province":"IL",
    "wof:name":"US Post Office",
    "wof:placetype":"venue"
},
  "geometry": {"coordinates":[-87.77678299999999,40.115526],"type":"Point"}
}