{
  "type": "Feature",
  "properties": {
    "iso:country":"US",
    "sg:address":"916 W Terrace Dr",
    "sg:city":"Glenwood",
    "sg:classifiers":[
        {
            "category":"Autos & Motor Vehicles",
            "subcategory":"Automobile Sales",
            "type":"Retail Goods"
        }
    ],
    "sg:phone":"+1 708 204 3690",
    "sg:postcode":"60425",
    "sg:province":"IL",
    "sg:tags":[
        "new",
        "car"
    ],
    "wof:name":"Terrance L Threatt",
    "wof:placetype":"venue"
},
  "geometry": {"coordinates":[-87.632259,41.550968],"type":"Point"}
}