{
  "type": "Feature",
  "properties": {
    "iso:country":"US",
    "sg:address":"117 Tanglewood Dr",
    "sg:city":"Freeport",
    "sg:classifiers":[
        {
            "category":"Professional",
            "subcategory":"Management & Consulting",
            "type":"Services"
        }
    ],
    "sg:phone":"+1 815 235 9898",
    "sg:postcode":"61032",
    "sg:province":"IL",
    "sg:tags":[
        "communications",
        "consultant"
    ],
    "wof:name":"Lehman Communications",
    "wof:placetype":"venue"
},
  "geometry": {"coordinates":[-89.615423,42.274641],"type":"Point"}
}