{
  "type": "Feature",
  "properties": {
    "iso:country":"US",
    "sg:address":"333 Park Dr",
    "sg:city":"Glenwood",
    "sg:classifiers":[
        {
            "category":"Building & Trades",
            "subcategory":"Construction",
            "type":"Services"
        }
    ],
    "sg:phone":"+1 708 754 4935",
    "sg:postcode":"60425",
    "sg:province":"IL",
    "sg:tags":[
        "house"
    ],
    "wof:name":"M & G Construction",
    "wof:placetype":"venue"
},
  "geometry": {"coordinates":[-87.62867199999999,41.55056],"type":"Point"}
}