{
  "type": "Feature",
  "properties": {
    "iso:country":"US",
    "sg:address":"1125 Aurora Ave",
    "sg:city":"Aurora",
    "sg:classifiers":[
        {
            "category":"Autos & Motor Vehicles",
            "subcategory":"Fuel & Gas Station",
            "type":"Retail Goods"
        }
    ],
    "sg:phone":"+1 630 844 0450",
    "sg:postcode":"60504",
    "sg:province":"IL",
    "sg:tags":[
        "oil"
    ],
    "wof:name":"Go-Tane Service Station",
    "wof:placetype":"venue"
},
  "geometry": {"coordinates":[-88.309333,41.779818],"type":"Point"}
}