{
  "type": "Feature",
  "properties": {
    "iso:country":"US",
    "sg:address":"6030 N Northwest Hwy",
    "sg:city":"Chicago",
    "sg:classifiers":[
        {
            "category":"Building & Trades",
            "subcategory":"Construction",
            "type":"Services"
        }
    ],
    "sg:phone":"+1 773 763 5511",
    "sg:postcode":"60631",
    "sg:province":"IL",
    "sg:tags":[
        "contractor"
    ],
    "sg:website":"www.dapratorigali.com",
    "wof:name":"Daprato Rigali",
    "wof:placetype":"venue"
},
  "geometry": {"coordinates":[-87.79572400000001,41.990583],"type":"Point"}
}