{
  "type": "Feature",
  "properties": {
    "addr:full":"117 S Madison St Carthage IL 62321",
    "addr:housenumber":"117",
    "addr:postcode":"62321",
    "addr:street":"S Madison St",
    "iso:country":"US",
    "sg:address":"117 S Madison St",
    "sg:city":"Carthage",
    "sg:classifiers":[
        {
            "category":"Retail",
            "subcategory":"Repair Shop",
            "type":"Services"
        }
    ],
    "sg:phone":"+1 217 357 3312",
    "sg:postcode":"62321",
    "sg:province":"IL",
    "sg:tags":[
        "contractor",
        "welder",
        "welding",
        "trade"
    ],
    "wof:name":"Cokel Welding Shop",
    "wof:placetype":"venue"
},
  "geometry": {"coordinates":[-91.136335,40.411492],"type":"Point"}
}