{
  "type": "Feature",
  "properties": {
    "iso:country":"US",
    "sg:address":"2840 Adlai Stevenson Dr",
    "sg:city":"Springfield",
    "sg:classifiers":[
        {
            "category":"Autos & Motor Vehicles",
            "subcategory":"Automobile Sales",
            "type":"Retail Goods"
        },
        {
            "category":"Personal",
            "type":"Services"
        },
        {
            "category":"Professional",
            "subcategory":"Advertising",
            "type":"Services"
        },
        {
            "category":"Autos & Motor Vehicles",
            "subcategory":"Auto Supplies",
            "type":"Retail Goods"
        },
        {
            "category":"Retail",
            "subcategory":"Auto Repair",
            "type":"Services"
        }
    ],
    "sg:phone":"+1 217 529 0292",
    "sg:postcode":"62703",
    "sg:province":"IL",
    "sg:tags":[
        "tire",
        "coupon",
        "equipment",
        "towing",
        "brake",
        "air conditioning",
        "batteries-storage"
    ],
    "sg:website":"http://www.napaautocare.com/",
    "wof:name":"Wilkerson's Service Center",
    "wof:placetype":"venue"
},
  "geometry": {"coordinates":[-89.613281,39.758148],"type":"Point"}
}