{
  "type": "Feature",
  "properties": {
    "iso:country":"US",
    "sg:address":"1631 Lind St",
    "sg:city":"Quincy",
    "sg:classifiers":[
        {
            "category":"Building & Trades",
            "subcategory":"Construction",
            "type":"Services"
        }
    ],
    "sg:phone":"+1 217 224 7420",
    "sg:postcode":"62301",
    "sg:province":"IL",
    "sg:tags":[
        "contractor"
    ],
    "wof:name":"Holzgrafe & Son Masonry",
    "wof:placetype":"venue"
},
  "geometry": {"coordinates":[-91.38915900000001,39.941785],"type":"Point"}
}