{
  "type": "Feature",
  "properties": {
    "addr:full":"701 E State St Bridgeport IL 62417",
    "addr:housenumber":"701",
    "addr:postcode":"62417",
    "addr:street":"E State St",
    "iso:country":"US",
    "sg:address":"701 E State St",
    "sg:city":"Bridgeport",
    "sg:classifiers":[
        {
            "category":"Food & Beverages",
            "subcategory":"Groceries & Convenience Stores",
            "type":"Retail Goods"
        }
    ],
    "sg:phone":"+1 618 945 7451",
    "sg:postcode":"62417",
    "sg:province":"IL",
    "sg:tags":[
        "grocer"
    ],
    "wof:name":"Mc Kim Valumart",
    "wof:placetype":"venue"
},
  "geometry": {"coordinates":[-87.75443,38.716516],"type":"Point"}
}