{
  "type": "Feature",
  "properties": {
    "iso:country":"US",
    "sg:address":"700 N Michigan Ave",
    "sg:city":"Chicago",
    "sg:classifiers":[
        {
            "category":"Shopping",
            "subcategory":"Beauty & Cosmetics",
            "type":"Retail Goods"
        }
    ],
    "sg:phone":"+1 312 482 8301",
    "sg:postcode":"60611",
    "sg:province":"IL",
    "sg:tags":[
        "supply"
    ],
    "wof:name":"Body Shop the",
    "wof:placetype":"venue"
},
  "geometry": {"coordinates":[-87.624397,41.894901],"type":"Point"}
}