{
  "type": "Feature",
  "properties": {
    "iso:country":"US",
    "sg:address":"1025 W Kentucky Rd",
    "sg:city":"Beecher",
    "sg:classifiers":[
        {
            "category":"Building & Trades",
            "subcategory":"Construction",
            "type":"Services"
        }
    ],
    "sg:phone":"+1 708 946 6402",
    "sg:postcode":"60401",
    "sg:province":"IL",
    "sg:tags":[
        "excavating",
        "contractor"
    ],
    "wof:name":"Butch Burdick Inc",
    "wof:placetype":"venue"
},
  "geometry": {"coordinates":[-87.635693,41.311513],"type":"Point"}
}