{
  "type": "Feature",
  "properties": {
    "iso:country":"US",
    "sg:address":"324 W 1st St",
    "sg:city":"Dixon",
    "sg:classifiers":[
        {
            "category":"Insurance",
            "subcategory":"Insurance Agent",
            "type":"Services"
        }
    ],
    "sg:phone":"+1 815 288 2541",
    "sg:postcode":"61021",
    "sg:province":"IL",
    "sg:website":"www.saukvalleyinsurance.com",
    "wof:name":"Sauk Valley Insurance Svc Inc",
    "wof:placetype":"venue"
},
  "geometry": {"coordinates":[-89.48554,41.842809],"type":"Point"}
}