{
  "type": "Feature",
  "properties": {
    "iso:country":"US",
    "sg:address":"1951 W 19th St",
    "sg:city":"Chicago",
    "sg:classifiers":[
        {
            "category":"Social Services",
            "subcategory":"Child Care",
            "type":"Services"
        }
    ],
    "sg:phone":"+1 312 997 2021",
    "sg:postcode":"60608",
    "sg:province":"IL",
    "sg:tags":[
        "nursery",
        "day"
    ],
    "wof:name":"The Guadalupe Reyes Children & Family Center",
    "wof:placetype":"venue"
},
  "geometry": {"coordinates":[-87.674723,41.85585],"type":"Point"}
}