{
  "type": "Feature",
  "properties": {
    "addr:full":"491 Naber Ave Antioch IL 60002",
    "addr:housenumber":"491",
    "addr:postcode":"60002",
    "addr:street":"Naber Ave",
    "iso:country":"US",
    "sg:address":"491 Naber Ave",
    "sg:city":"Antioch",
    "sg:classifiers":[
        {
            "category":"Building & Trades",
            "subcategory":"Construction",
            "type":"Services"
        }
    ],
    "sg:phone":"+1 847 838 2627",
    "sg:postcode":"60002",
    "sg:province":"IL",
    "sg:tags":[
        "contractor"
    ],
    "wof:name":"Roma Construction Inc",
    "wof:placetype":"venue"
},
  "geometry": {"coordinates":[-88.10056,42.476177],"type":"Point"}
}