{
  "type": "Feature",
  "properties": {
    "iso:country":"US",
    "sg:address":"1430 Holland Pl",
    "sg:city":"Downers Grove",
    "sg:classifiers":[
        {
            "category":"Professional",
            "subcategory":"Secretarial Services",
            "type":"Services"
        }
    ],
    "sg:phone":"+1 630 969 7550",
    "sg:postcode":"60515",
    "sg:province":"IL",
    "sg:tags":[
        "reporting"
    ],
    "wof:name":"Bassi Communications Inc",
    "wof:placetype":"venue"
},
  "geometry": {"coordinates":[-88.019379,41.827938],"type":"Point"}
}