{
  "type": "Feature",
  "properties": {
    "iso:country":"US",
    "sg:address":"1645 W Jackson Blvd Ste 215",
    "sg:city":"Chicago",
    "sg:classifiers":[
        {
            "category":"Health Services",
            "subcategory":"Doctor",
            "type":"Services"
        }
    ],
    "sg:phone":"+1 312 942 8000",
    "sg:postcode":"60612",
    "sg:province":"IL",
    "wof:name":"Rush Lifetime Medical Associates",
    "wof:placetype":"venue"
},
  "geometry": {"coordinates":[-87.668503,41.877264],"type":"Point"}
}