{
  "type": "Feature",
  "properties": {
    "iso:country":"US",
    "sg:address":"8837 S Cornell Avenue",
    "sg:city":"Chicago",
    "sg:classifiers":[
        {
            "category":"Personal",
            "subcategory":"Day Spa",
            "type":"Services"
        }
    ],
    "sg:phone":"+1 773 734 2288",
    "sg:postcode":"60617",
    "sg:province":"IL",
    "wof:name":"The Aah Spa",
    "wof:placetype":"venue"
},
  "geometry": {"coordinates":[-87.583808,41.733953],"type":"Point"}
}