{
  "type": "Feature",
  "properties": {
    "addr:full":"25 Arrowhead Dr Algonquin IL 60102",
    "addr:housenumber":"25",
    "addr:postcode":"60102",
    "addr:street":"Arrowhead Dr",
    "iso:country":"US",
    "sg:address":"25 Arrowhead Dr",
    "sg:city":"Algonquin",
    "sg:classifiers":[
        {
            "category":"Real Estate",
            "subcategory":"Real Estate Operator",
            "type":"Services"
        }
    ],
    "sg:phone":"+1 847 658 8463",
    "sg:postcode":"60102",
    "sg:province":"IL",
    "sg:tags":[
        "apartment"
    ],
    "wof:name":"Malibu Apartments",
    "wof:placetype":"venue"
},
  "geometry": {"coordinates":[-88.286405,42.174691],"type":"Point"}
}