{
  "type": "Feature",
  "properties": {
    "iso:country":"US",
    "sg:address":"948 Clemson Ave",
    "sg:city":"Fairview Heights",
    "sg:classifiers":[
        {
            "category":"Building & Trades",
            "subcategory":"Plumbing",
            "type":"Services"
        }
    ],
    "sg:phone":"+1 618 624 8990",
    "sg:postcode":"62208",
    "sg:province":"IL",
    "sg:tags":[
        "contractor"
    ],
    "wof:name":"Action Sewer Services Inc",
    "wof:placetype":"venue"
},
  "geometry": {"coordinates":[-89.968378,38.573163],"type":"Point"}
}