{
  "type": "Feature",
  "properties": {
    "addr:full":"12015 Western Ave Blue Island IL 60406",
    "addr:housenumber":"12015",
    "addr:postcode":"60406",
    "addr:street":"Western Ave",
    "iso:country":"US",
    "sg:address":"12015 Western Ave",
    "sg:city":"Blue Island",
    "sg:classifiers":[
        {
            "category":"Banks & Credit Unions",
            "subcategory":"Bank",
            "type":"Services"
        }
    ],
    "sg:phone":"+1 708 385 2900",
    "sg:postcode":"60406",
    "sg:province":"IL",
    "sg:tags":[
        "commercial"
    ],
    "sg:website":"www.firstmidwest.com",
    "wof:name":"First Midwest Bank",
    "wof:placetype":"venue"
},
  "geometry": {"coordinates":[-87.680397,41.675098],"type":"Point"}
}