{
  "type": "Feature",
  "properties": {
    "addr:full":"170 E John Casey Rd Bourbonnais IL 60914",
    "addr:housenumber":"170",
    "addr:postcode":"60914",
    "addr:street":"E John Casey Rd",
    "iso:country":"US",
    "sg:address":"170 E John Casey Rd",
    "sg:city":"Bourbonnais",
    "sg:classifiers":[
        {
            "category":"Organizations",
            "subcategory":"Religious Organization",
            "type":"Services"
        }
    ],
    "sg:phone":"+1 815 933 4117",
    "sg:postcode":"60914",
    "sg:province":"IL",
    "sg:tags":[
        "church"
    ],
    "wof:name":"Jehovah's Witnesses Kingdom",
    "wof:placetype":"venue"
},
  "geometry": {"coordinates":[-87.87232400000001,41.164989],"type":"Point"}
}