{
  "type": "Feature",
  "properties": {
    "iso:country":"US",
    "sg:address":"1730 W Wrightwood Ave",
    "sg:city":"Chicago",
    "sg:classifiers":[
        {
            "category":"Home & Garden",
            "subcategory":"Home Furnishings",
            "type":"Retail Goods"
        }
    ],
    "sg:phone":"+1 773 871 4331",
    "sg:postcode":"60614",
    "sg:province":"IL",
    "sg:tags":[
        "bath",
        "kitchen"
    ],
    "sg:website":"www.1730outlet.com",
    "wof:name":"1730 Outlet Company",
    "wof:placetype":"venue"
},
  "geometry": {"coordinates":[-87.671725,41.928759],"type":"Point"}
}