{
  "type": "Feature",
  "properties": {
    "iso:country":"US",
    "sg:address":"1250 E Rexford St",
    "sg:city":"Centralia",
    "sg:classifiers":[
        {
            "category":"Organizations",
            "subcategory":"Community Association",
            "type":"Services"
        }
    ],
    "sg:phone":"+1 618 532 2951",
    "sg:postcode":"62801",
    "sg:province":"IL",
    "sg:tags":[
        "club"
    ],
    "wof:name":"Centralia Cultural Ctr",
    "wof:placetype":"venue"
},
  "geometry": {"coordinates":[-89.117629,38.532632],"type":"Point"}
}