{
  "type": "Feature",
  "properties": {
    "iso:country":"US",
    "sg:address":"5120 N Kilbourn Ave",
    "sg:city":"Chicago",
    "sg:classifiers":[
        {
            "category":"Banks & Credit Unions",
            "subcategory":"Investment Brokerage",
            "type":"Services"
        },
        {
            "category":"Professional",
            "subcategory":"Business Services",
            "type":"Services"
        }
    ],
    "sg:phone":"+1 312 377 9050",
    "sg:postcode":"60630",
    "sg:province":"IL",
    "sg:tags":[
        "broker",
        "commodity"
    ],
    "wof:name":"Piton Holdings",
    "wof:placetype":"venue"
},
  "geometry": {"coordinates":[-87.74061,41.973953],"type":"Point"}
}