{
  "type": "Feature",
  "properties": {
    "iso:country":"US",
    "sg:address":"708 Kimela Dr",
    "sg:city":"Mahomet",
    "sg:classifiers":[
        {
            "category":"Professional",
            "subcategory":"Management & Consulting",
            "type":"Services"
        }
    ],
    "sg:phone":"+1 217 586 7036",
    "sg:postcode":"61853",
    "sg:province":"IL",
    "sg:tags":[
        "financial"
    ],
    "wof:name":"Paragon Consulting Assoc Inc",
    "wof:placetype":"venue"
},
  "geometry": {"coordinates":[-88.385735,40.19009],"type":"Point"}
}