{
  "type": "Feature",
  "properties": {
    "iso:country":"US",
    "sg:address":"2404 S Wolcott Ave",
    "sg:city":"Chicago",
    "sg:classifiers":[
        {
            "category":"Wholesale",
            "subcategory":"Fruits & Vegetables",
            "type":"Manufacturing & Wholesale Goods"
        }
    ],
    "sg:phone":"+1 312 226 6888",
    "sg:postcode":"60608",
    "sg:province":"IL",
    "sg:tags":[
        "vegetables-wholesale"
    ],
    "sg:website":"http://www.strube.com",
    "wof:name":"Strobe Celery And Vegetable Co",
    "wof:placetype":"venue"
},
  "geometry": {"coordinates":[-87.67327899999999,41.848939],"type":"Point"}
}