{
  "type": "Feature",
  "properties": {
    "iso:country":"US",
    "sg:address":"2259 N Lorel Avenue",
    "sg:city":"Chicago",
    "sg:classifiers":[
        {
            "category":"Food & Beverages",
            "subcategory":"Groceries & Convenience Stores",
            "type":"Retail Goods"
        }
    ],
    "sg:phone":"+1 773 622 0889",
    "sg:postcode":"60639",
    "sg:province":"IL",
    "wof:name":"Elaugila",
    "wof:placetype":"venue"
},
  "geometry": {"coordinates":[-87.75985300000001,41.922074],"type":"Point"}
}