{
  "type": "Feature",
  "properties": {
    "addr:full":"1814 Washington Ave Cairo IL 62914",
    "addr:housenumber":"1814",
    "addr:postcode":"62914",
    "addr:street":"Washington Ave",
    "iso:country":"US",
    "sg:address":"1814 Washington Ave",
    "sg:city":"Cairo",
    "sg:classifiers":[
        {
            "category":"Restaurant",
            "type":"Food & Drink"
        }
    ],
    "sg:phone":"+1 618 734 1266",
    "sg:postcode":"62914",
    "sg:province":"IL",
    "sg:tags":[
        "parlor",
        "ice",
        "cream"
    ],
    "wof:name":"Dairy Hut",
    "wof:placetype":"venue"
},
  "geometry": {"coordinates":[-89.175101,37.004434],"type":"Point"}
}