{
  "type": "Feature",
  "properties": {
    "iso:country":"US",
    "sg:address":"339 N Front St",
    "sg:city":"Mounds",
    "sg:classifiers":[
        {
            "category":"Place Of Worship",
            "subcategory":"Church",
            "type":"Public Place"
        },
        {
            "category":"Place Of Worship",
            "type":"Public Place"
        },
        {
            "category":"Organizations",
            "subcategory":"Religious Organization",
            "type":"Services"
        }
    ],
    "sg:phone":"+1 618 742 8191",
    "sg:postcode":"62964",
    "sg:province":"IL",
    "sg:tags":[
        "god",
        "churches-church",
        "churches-pentecostal"
    ],
    "wof:name":"Johnsons Temple Church Of God",
    "wof:placetype":"venue"
},
  "geometry": {"coordinates":[-89.201771,37.117375],"type":"Point"}
}