{
  "type": "Feature",
  "properties": {
    "addr:full":"960 Victoria St Antioch IL 60002",
    "addr:housenumber":"960",
    "addr:postcode":"60002",
    "addr:street":"Victoria St",
    "iso:country":"US",
    "sg:address":"960 Victoria St",
    "sg:city":"Antioch",
    "sg:classifiers":[
        {
            "category":"Health Services",
            "subcategory":"Chiropractor",
            "type":"Services"
        }
    ],
    "sg:phone":"+1 847 838 0688",
    "sg:postcode":"60002",
    "sg:province":"IL",
    "wof:name":"Antioch Family Chiropractic",
    "wof:placetype":"venue"
},
  "geometry": {"coordinates":[-88.096901,42.476898],"type":"Point"}
}