{
  "type": "Feature",
  "properties": {
    "addr:full":"2277 E Devon Ave Elk Grove Village IL 60007",
    "addr:housenumber":"2277",
    "addr:postcode":"60007",
    "addr:street":"E Devon Ave",
    "iso:country":"US",
    "sg:address":"2277 E Devon Ave",
    "sg:city":"Elk Grove Village",
    "sg:classifiers":[
        {
            "category":"Wholesale",
            "subcategory":"Construction Materials",
            "type":"Manufacturing & Wholesale Goods"
        }
    ],
    "sg:phone":"+1 847 787 0154",
    "sg:postcode":"60007",
    "sg:province":"IL",
    "wof:name":"Inno Dekor",
    "wof:placetype":"venue"
},
  "geometry": {"coordinates":[-87.944091,41.993512],"type":"Point"}
}