{
  "type": "Feature",
  "properties": {
    "iso:country":"US",
    "sg:address":"5467 Bridge St",
    "sg:city":"Roscoe",
    "sg:classifiers":[
        {
            "category":"Restaurant",
            "type":"Food & Drink"
        }
    ],
    "sg:phone":"+1 815 623 5903",
    "sg:postcode":"61073",
    "sg:province":"IL",
    "wof:name":"Sophia's Restaurant",
    "wof:placetype":"venue"
},
  "geometry": {"coordinates":[-89.010289,42.412959],"type":"Point"}
}