{
  "type": "Feature",
  "properties": {
    "addr:full":"17121 Odell Ave Tinley Park IL 60477",
    "addr:housenumber":"17121",
    "addr:postcode":"60477",
    "addr:street":"Odell Ave",
    "iso:country":"US",
    "sg:address":"17121 Odell Ave",
    "sg:city":"Tinley Park",
    "sg:classifiers":[
        {
            "category":"Insurance",
            "subcategory":"Insurance Agent",
            "type":"Services"
        }
    ],
    "sg:phone":"+1 708 429 0656",
    "sg:postcode":"60477",
    "sg:province":"IL",
    "wof:name":"Jh Deornellas Financial Svcs",
    "wof:placetype":"venue"
},
  "geometry": {"coordinates":[-87.79656799999999,41.577171],"type":"Point"}
}