{
  "type": "Feature",
  "properties": {
    "iso:country":"US",
    "sg:address":"1675 E Walnut St",
    "sg:city":"Canton",
    "sg:classifiers":[
        {
            "category":"Retail",
            "subcategory":"Auto Repair",
            "type":"Services"
        }
    ],
    "sg:phone":"+1 309 647 1539",
    "sg:postcode":"61520",
    "sg:province":"IL",
    "sg:tags":[
        "truck"
    ],
    "wof:name":"Wheeler's Truck Garage",
    "wof:placetype":"venue"
},
  "geometry": {"coordinates":[-90.00784299999999,40.553602],"type":"Point"}
}