{
  "type": "Feature",
  "properties": {
    "iso:country":"US",
    "sg:address":"215 S Swift St",
    "sg:city":"Winnebago",
    "sg:classifiers":[
        {
            "category":"Home & Garden",
            "subcategory":"Building Materials",
            "type":"Retail Goods"
        }
    ],
    "sg:phone":"+1 815 335 2046",
    "sg:postcode":"61088",
    "sg:province":"IL",
    "sg:tags":[
        "top",
        "counter"
    ],
    "wof:name":"Granite Graphix",
    "wof:placetype":"venue"
},
  "geometry": {"coordinates":[-89.246234,42.264839],"type":"Point"}
}