{
  "type": "Feature",
  "properties": {
    "iso:country":"US",
    "sg:address":"18811 Dixie Hwy",
    "sg:city":"Homewood",
    "sg:classifiers":[
        {
            "category":"Health Services",
            "subcategory":"Doctor",
            "type":"Services"
        }
    ],
    "sg:phone":"+1 708 335 3693",
    "sg:postcode":"60430",
    "sg:province":"IL",
    "sg:tags":[
        "medical"
    ],
    "wof:name":"Homewood Pediatrics Associates",
    "wof:placetype":"venue"
},
  "geometry": {"coordinates":[-87.664949,41.546794],"type":"Point"}
}