{
  "type": "Feature",
  "properties": {
    "addr:full":"1120 S 27th St Mattoon IL 61938",
    "addr:housenumber":"1120",
    "addr:postcode":"61938",
    "addr:street":"S 27Th St",
    "iso:country":"US",
    "sg:address":"1120 S 27th St",
    "sg:city":"Mattoon",
    "sg:classifiers":[
        {
            "category":"Professional",
            "subcategory":"Accounting & Tax Preparation",
            "type":"Services"
        }
    ],
    "sg:phone":"+1 217 235 6233",
    "sg:postcode":"61938",
    "sg:province":"IL",
    "sg:tags":[
        "public",
        "accountants-certified"
    ],
    "wof:name":"Katherine L Shaffer Cpa",
    "wof:placetype":"venue"
},
  "geometry": {"coordinates":[-88.38843199999999,39.471747],"type":"Point"}
}