{
  "type": "Feature",
  "properties": {
    "addr:full":"6000 S Ashland Ave Chicago IL 60636",
    "addr:housenumber":"6000",
    "addr:postcode":"60636",
    "addr:street":"S Ashland Ave",
    "iso:country":"US",
    "sg:address":"6000 S Ashland Ave",
    "sg:city":"Chicago",
    "sg:classifiers":[
        {
            "category":"Place Of Worship",
            "subcategory":"Church",
            "type":"Public Place"
        },
        {
            "category":"Place Of Worship",
            "type":"Public Place"
        }
    ],
    "sg:phone":"+1 773 737 1009",
    "sg:postcode":"60636",
    "sg:province":"IL",
    "sg:tags":[
        "churches-non-denominational"
    ],
    "wof:name":"Believe In Thine Heart Ministry",
    "wof:placetype":"venue"
},
  "geometry": {"coordinates":[-87.66435199999999,41.784931],"type":"Point"}
}