{
  "type": "Feature",
  "properties": {
    "addr:full":"108 S Grove St Lexington IL 61753",
    "addr:housenumber":"108",
    "addr:postcode":"61753",
    "addr:street":"S Grove St",
    "iso:country":"US",
    "sg:address":"108 S Grove St",
    "sg:city":"Lexington",
    "sg:classifiers":[
        {
            "category":"Building & Trades",
            "subcategory":"Construction",
            "type":"Services"
        }
    ],
    "sg:phone":"+1 309 365 8787",
    "sg:postcode":"61753",
    "sg:province":"IL",
    "sg:tags":[
        "general",
        "contractor"
    ],
    "wof:name":"George Construction",
    "wof:placetype":"venue"
},
  "geometry": {"coordinates":[-88.790543,40.641402],"type":"Point"}
}