{
  "type": "Feature",
  "properties": {
    "iso:country":"US",
    "sg:address":"410 E Grant St",
    "sg:city":"Coulterville",
    "sg:classifiers":[
        {
            "category":"Professional",
            "subcategory":"Business Services",
            "type":"Services"
        }
    ],
    "sg:phone":"+1 618 758 2388",
    "sg:postcode":"62237",
    "sg:province":"IL",
    "sg:tags":[
        "auctioneer"
    ],
    "wof:name":"Penny Pincher Auction Barn",
    "wof:placetype":"venue"
},
  "geometry": {"coordinates":[-89.602654,38.186228],"type":"Point"}
}