{
  "type": "Feature",
  "properties": {
    "iso:country":"US",
    "sg:address":"117 E Morgan St",
    "sg:city":"Dixon",
    "sg:classifiers":[
        {
            "category":"Wholesale",
            "subcategory":"Toys & Hobbies",
            "type":"Manufacturing & Wholesale Goods"
        }
    ],
    "sg:phone":"+1 815 284 1647",
    "sg:postcode":"61021",
    "sg:province":"IL",
    "sg:tags":[
        "puppet",
        "marionette"
    ],
    "wof:name":"Son Shine Puppet Co",
    "wof:placetype":"venue"
},
  "geometry": {"coordinates":[-89.48489499999999,41.851576],"type":"Point"}
}