{
  "type": "Feature",
  "properties": {
    "iso:country":"US",
    "sg:address":"85 Revere Dr",
    "sg:city":"Northbrook",
    "sg:classifiers":[
        {
            "category":"Banks & Credit Unions",
            "subcategory":"Bank",
            "type":"Services"
        }
    ],
    "sg:phone":"+1 847 849 8800",
    "sg:postcode":"60062",
    "sg:province":"IL",
    "sg:tags":[
        "broker",
        "mortgage"
    ],
    "wof:name":"Third Coast Mortgage LLC",
    "wof:placetype":"venue"
},
  "geometry": {"coordinates":[-87.80602500000001,42.151694],"type":"Point"}
}