{
  "type": "Feature",
  "properties": {
    "iso:country":"US",
    "sg:address":"55 E Washington St",
    "sg:city":"Chicago",
    "sg:classifiers":[
        {
            "category":"Social Services",
            "type":"Services"
        },
        {
            "category":"Personal",
            "type":"Services"
        }
    ],
    "sg:phone":"+1 312 332 0349",
    "sg:postcode":"60602",
    "sg:province":"IL",
    "sg:tags":[
        "counseling",
        "worker"
    ],
    "wof:name":"Yolanda R Scheunemann",
    "wof:placetype":"venue"
},
  "geometry": {"coordinates":[-87.62605600000001,41.883221],"type":"Point"}
}