{
  "type": "Feature",
  "properties": {
    "iso:country":"US",
    "sg:address":"6340 N Western Ave",
    "sg:city":"Chicago",
    "sg:phone":"+1 773 761 7700",
    "sg:postcode":"60659",
    "sg:province":"IL",
    "wof:name":"Italian Express Family Restaurant",
    "wof:placetype":"venue"
},
  "geometry": {"coordinates":[-87.689842,41.997197],"type":"Point"}
}