{
  "type": "Feature",
  "properties": {
    "iso:country":"US",
    "sg:address":"28401 Ballard Dr",
    "sg:city":"Lake Forest",
    "sg:classifiers":[
        {
            "category":"Wholesale",
            "subcategory":"Machinery & Supplies",
            "type":"Manufacturing & Wholesale Goods"
        }
    ],
    "sg:phone":"+1 847 549 8695",
    "sg:postcode":"60045",
    "sg:province":"IL",
    "sg:tags":[
        "equipment",
        "industrial"
    ],
    "wof:name":"Warco Industrial Equipment Inc",
    "wof:placetype":"venue"
},
  "geometry": {"coordinates":[-87.899582,42.275314],"type":"Point"}
}