{
  "type": "Feature",
  "properties": {
    "iso:country":"US",
    "sg:address":"3000 Grand Ave",
    "sg:city":"Waukegan",
    "sg:classifiers":[
        {
            "category":"Social Services",
            "type":"Services"
        }
    ],
    "sg:phone":"+1 847 244 9944",
    "sg:postcode":"60085",
    "sg:province":"IL",
    "sg:tags":[
        "shelter",
        "homeless"
    ],
    "wof:name":"Staben House",
    "wof:placetype":"venue"
},
  "geometry": {"coordinates":[-87.877028,42.370388],"type":"Point"}
}