{
  "type": "Feature",
  "properties": {
    "addr:full":"100 N Oak Park Ave Oak Park IL 60301",
    "addr:housenumber":"100",
    "addr:postcode":"60301",
    "addr:street":"N Oak Park Ave",
    "iso:country":"US",
    "sg:address":"100 N Oak Park Ave",
    "sg:city":"Oak Park",
    "sg:classifiers":[
        {
            "category":"Organizations",
            "subcategory":"Professional Association",
            "type":"Services"
        }
    ],
    "sg:phone":"+1 708 763 8451",
    "sg:postcode":"60301",
    "sg:province":"IL",
    "wof:name":"Avenue Association",
    "wof:placetype":"venue"
},
  "geometry": {"coordinates":[-87.794496,41.887921],"type":"Point"}
}