{
  "type": "Feature",
  "properties": {
    "iso:country":"US",
    "sg:address":"105 Pieper Cir",
    "sg:city":"Delavan",
    "sg:classifiers":[
        {
            "category":"Farming",
            "subcategory":"Farm",
            "type":"Manufacturing & Wholesale Goods"
        }
    ],
    "sg:phone":"+1 309 244 7843",
    "sg:postcode":"61734",
    "sg:province":"IL",
    "sg:tags":[
        "crop",
        "general"
    ],
    "wof:name":"Dwight Kurtz",
    "wof:placetype":"venue"
},
  "geometry": {"coordinates":[-89.537967,40.376867],"type":"Point"}
}