{
  "type": "Feature",
  "properties": {
    "addr:full":"459 Busse Rd Elk Grove Village IL 60007",
    "addr:housenumber":"459",
    "addr:postcode":"60007",
    "addr:street":"Busse Rd",
    "iso:country":"US",
    "sg:address":"459 Busse Rd",
    "sg:city":"Elk Grove Village",
    "sg:classifiers":[
        {
            "category":"Manufacturing",
            "subcategory":"Chemicals & Compounds",
            "type":"Manufacturing & Wholesale Goods"
        }
    ],
    "sg:phone":"+1 847 593 2100",
    "sg:postcode":"60007",
    "sg:province":"IL",
    "sg:tags":[
        "personal",
        "preparation",
        "filler",
        "cosmetic",
        "mfg"
    ],
    "wof:name":"Labtec Cosmetics By Marzena",
    "wof:placetype":"venue"
},
  "geometry": {"coordinates":[-87.95980299999999,42.022345],"type":"Point"}
}