{
  "type": "Feature",
  "properties": {
    "addr:full":"2525 Amy Ln Aurora IL 60506",
    "addr:housenumber":"2525",
    "addr:postcode":"60506",
    "addr:street":"Amy Ln",
    "iso:country":"US",
    "sg:address":"2525 Amy Ln",
    "sg:city":"Aurora",
    "sg:classifiers":[
        {
            "category":"Manufacturing",
            "subcategory":"Paper Products",
            "type":"Manufacturing & Wholesale Goods"
        }
    ],
    "sg:phone":"+1 630 896 6262",
    "sg:postcode":"60506",
    "sg:province":"IL",
    "sg:tags":[
        "packaging",
        "material"
    ],
    "wof:name":"Clipper Packaging Co",
    "wof:placetype":"venue"
},
  "geometry": {"coordinates":[-88.382446,41.759459],"type":"Point"}
}