{
  "type": "Feature",
  "properties": {
    "iso:country":"US",
    "sg:address":"327 Village Dr",
    "sg:city":"Carol Stream",
    "sg:classifiers":[
        {
            "category":"Professional",
            "subcategory":"Advertising",
            "type":"Services"
        },
        {
            "category":"Professional",
            "subcategory":"Printing & Photocopies",
            "type":"Services"
        }
    ],
    "sg:phone":"+1 630 456 4172",
    "sg:postcode":"60188",
    "sg:province":"IL",
    "sg:tags":[
        "marketing"
    ],
    "sg:website":"aaalasermarking.com",
    "wof:name":"AAA Laser Marking",
    "wof:placetype":"venue"
},
  "geometry": {"coordinates":[-88.11838400000001,41.910772],"type":"Point"}
}