{
  "type": "Feature",
  "properties": {
    "addr:full":"3375 Commercial Ave Northbrook IL 60062",
    "addr:housenumber":"3375",
    "addr:postcode":"60062",
    "addr:street":"Commercial Ave",
    "iso:country":"US",
    "sg:address":"3375 Commercial Ave",
    "sg:city":"Northbrook",
    "sg:classifiers":[
        {
            "category":"Education",
            "subcategory":"Library",
            "type":"Public Place"
        }
    ],
    "sg:phone":"+1 847 480 2200",
    "sg:postcode":"60062",
    "sg:province":"IL",
    "sg:tags":[
        "research"
    ],
    "wof:name":"National Deed Service",
    "wof:placetype":"venue"
},
  "geometry": {"coordinates":[-87.862296,42.146511],"type":"Point"}
}