{
  "type": "Feature",
  "properties": {
    "iso:country":"US",
    "sg:address":"712 Ashton Ln N",
    "sg:city":"Champaign",
    "sg:classifiers":[
        {
            "category":"Shopping",
            "subcategory":"Antiques",
            "type":"Retail Goods"
        }
    ],
    "sg:phone":"+1 217 398 3973",
    "sg:postcode":"61820",
    "sg:province":"IL",
    "wof:name":"Hillside Gifts And Collectibles",
    "wof:placetype":"venue"
},
  "geometry": {"coordinates":[-88.25274,40.090621],"type":"Point"}
}