{
  "type": "Feature",
  "properties": {
    "addr:full":"1616 Larkin Ave Crest Hill IL 60435",
    "addr:housenumber":"1616",
    "addr:postcode":"60435",
    "addr:street":"Larkin Ave",
    "iso:country":"US",
    "sg:address":"1616 Larkin Ave",
    "sg:city":"Crest Hill",
    "sg:classifiers":[
        {
            "category":"Restaurant",
            "type":"Food & Drink"
        }
    ],
    "sg:phone":"+1 815 741 3110",
    "sg:postcode":"60435",
    "sg:province":"IL",
    "wof:name":"Burger King",
    "wof:placetype":"venue"
},
  "geometry": {"coordinates":[-88.125693,41.554819],"type":"Point"}
}