{
  "type": "Feature",
  "properties": {
    "iso:country":"US",
    "sg:address":"815 Kimberly Dr",
    "sg:city":"Carol Stream",
    "sg:classifiers":[
        {
            "category":"Professional",
            "subcategory":"Business Services",
            "type":"Services"
        }
    ],
    "sg:phone":"+1 630 653 1150",
    "sg:postcode":"60188",
    "sg:province":"IL",
    "sg:tags":[
        "trade",
        "exposition",
        "fair",
        "show"
    ],
    "wof:name":"Expo Project Consolidation Ctr",
    "wof:placetype":"venue"
},
  "geometry": {"coordinates":[-88.111857,41.924621],"type":"Point"}
}