{
  "type": "Feature",
  "properties": {
    "iso:country":"US",
    "sg:address":"1163 E Ogden Ave",
    "sg:city":"Naperville",
    "sg:classifiers":[
        {
            "category":"Airline",
            "type":"Transportation"
        },
        {
            "category":"Travel",
            "subcategory":"Travel Agent",
            "type":"Entertainment"
        },
        {
            "category":"Marine",
            "type":"Transportation"
        }
    ],
    "sg:phone":"+1 630 614 1628",
    "sg:postcode":"60563",
    "sg:province":"IL",
    "sg:tags":[
        "agency",
        "cruise"
    ],
    "sg:website":"http://www.travelleaders.com/napervilleil",
    "wof:name":"Travel Leaders of Naperville",
    "wof:placetype":"venue"
},
  "geometry": {"coordinates":[-88.12587000000001,41.794289],"type":"Point"}
}