{
  "type": "Feature",
  "properties": {
    "addr:full":"105 W Madison Ste 115 Chicago IL 60602",
    "addr:housenumber":"105",
    "addr:postcode":"60602",
    "addr:street":"W Madison Ste 115",
    "iso:country":"US",
    "sg:address":"105 W Madison Ste 115",
    "sg:city":"Chicago",
    "sg:classifiers":[
        {
            "category":"Shopping",
            "subcategory":"Gifts & Souvenirs",
            "type":"Retail Goods"
        }
    ],
    "sg:phone":"+1 877 237 7905",
    "sg:postcode":"60602",
    "sg:province":"IL",
    "sg:tags":[
        "flower"
    ],
    "sg:website":"www.fruitflowers.com",
    "wof:name":"Fruit Flowers",
    "wof:placetype":"venue"
},
  "geometry": {"coordinates":[-87.63102000000001,41.88197],"type":"Point"}
}