{
  "type": "Feature",
  "properties": {
    "addr:full":"109 W Rockland Rd Libertyville IL 60048",
    "addr:housenumber":"109",
    "addr:postcode":"60048",
    "addr:street":"W Rockland Rd",
    "iso:country":"US",
    "sg:address":"109 W Rockland Rd",
    "sg:city":"Libertyville",
    "sg:classifiers":[
        {
            "category":"Manufacturing",
            "subcategory":"Signs",
            "type":"Manufacturing & Wholesale Goods"
        }
    ],
    "sg:phone":"+1 847 680 0004",
    "sg:postcode":"60048",
    "sg:province":"IL",
    "wof:name":"Sign-A-Rama",
    "wof:placetype":"venue"
},
  "geometry": {"coordinates":[-87.952476,42.277981],"type":"Point"}
}