{
  "type": "Feature",
  "properties": {
    "iso:country":"US",
    "sg:address":"6776 Prairie Flower",
    "sg:city":"Roscoe",
    "sg:classifiers":[
        {
            "category":"Building & Trades",
            "subcategory":"Construction",
            "type":"Services"
        }
    ],
    "sg:phone":"+1 815 623 3732",
    "sg:postcode":"61073",
    "sg:province":"IL",
    "sg:tags":[
        "fence",
        "contractor"
    ],
    "wof:name":"Wayne's Fencing",
    "wof:placetype":"venue"
},
  "geometry": {"coordinates":[-88.985902,42.395455],"type":"Point"}
}