{
  "type": "Feature",
  "properties": {
    "iso:country":"US",
    "sg:address":"505 W Elms Court Ln",
    "sg:city":"Crete",
    "sg:classifiers":[
        {
            "category":"Building & Trades",
            "subcategory":"Plumbing",
            "type":"Services"
        }
    ],
    "sg:phone":"+1 708 672 8642",
    "sg:postcode":"60417",
    "sg:province":"IL",
    "sg:tags":[
        "contractor"
    ],
    "wof:name":"AC Control & Heating",
    "wof:placetype":"venue"
},
  "geometry": {"coordinates":[-87.622108,41.406087],"type":"Point"}
}