{
  "type": "Feature",
  "properties": {
    "addr:full":"660 N Wells St Chicago IL 60654",
    "addr:housenumber":"660",
    "addr:postcode":"60654",
    "addr:street":"N Wells St",
    "iso:country":"US",
    "sg:address":"660 N Wells St",
    "sg:city":"Chicago",
    "sg:classifiers":[
        {
            "category":"Fast Food",
            "type":"Food & Drink"
        },
        {
            "category":"Restaurant",
            "type":"Food & Drink"
        }
    ],
    "sg:phone":"+1 312 944 8800",
    "sg:postcode":"60654",
    "sg:province":"IL",
    "sg:tags":[
        "traditional",
        "american",
        "chicken",
        "wing"
    ],
    "sg:website":"www.hooters.com",
    "wof:name":"Hooters",
    "wof:placetype":"venue"
},
  "geometry": {"coordinates":[-87.634153,41.894236],"type":"Point"}
}