{
  "type": "Feature",
  "properties": {
    "addr:full":"604 S Country Fair Dr Champaign IL 61821",
    "addr:housenumber":"604",
    "addr:postcode":"61821",
    "addr:street":"S Country Fair Dr",
    "iso:country":"US",
    "sg:address":"604 S Country Fair Dr",
    "sg:city":"Champaign",
    "sg:classifiers":[
        {
            "category":"Restaurant",
            "type":"Food & Drink"
        }
    ],
    "sg:phone":"+1 217 356 0888",
    "sg:postcode":"61821",
    "sg:province":"IL",
    "sg:tags":[
        "lounge",
        "bar",
        "cocktail"
    ],
    "sg:website":"http://www.drdiggers.com",
    "wof:name":"Dr Digger's",
    "wof:placetype":"venue"
},
  "geometry": {"coordinates":[-88.282799,40.110252],"type":"Point"}
}