{
  "type": "Feature",
  "properties": {
    "iso:country":"US",
    "sg:address":"204 N Water St",
    "sg:city":"Wilmington",
    "sg:classifiers":[
        {
            "category":"Shopping",
            "subcategory":"Florist",
            "type":"Retail Goods"
        }
    ],
    "sg:phone":"+1   ",
    "sg:postcode":"60481",
    "sg:province":"IL",
    "wof:name":"Flower Loft Inc",
    "wof:placetype":"venue"
},
  "geometry": {"coordinates":[-88.147827,41.309447],"type":"Point"}
}