{
  "type": "Feature",
  "properties": {
    "iso:country":"US",
    "sg:address":"1507 Cherry St",
    "sg:city":"Quincy",
    "sg:classifiers":[
        {
            "category":"Social Services",
            "subcategory":"Child Care",
            "type":"Services"
        }
    ],
    "sg:phone":"+1 217 228 1929",
    "sg:postcode":"62301",
    "sg:province":"IL",
    "sg:tags":[
        "day"
    ],
    "wof:name":"Jeannie F Tyson",
    "wof:placetype":"venue"
},
  "geometry": {"coordinates":[-91.391978,39.944292],"type":"Point"}
}