{
  "type": "Feature",
  "properties": {
    "iso:country":"US",
    "sg:address":"1515 E Court St",
    "sg:city":"Kankakee",
    "sg:classifiers":[
        {
            "category":"Retail",
            "subcategory":"Auto Repair",
            "type":"Services"
        }
    ],
    "sg:phone":"+1 815 932 9898",
    "sg:postcode":"60901",
    "sg:province":"IL",
    "sg:tags":[
        "muffler",
        "exhaust",
        "system"
    ],
    "wof:name":"Best Muffler & Brakes",
    "wof:placetype":"venue"
},
  "geometry": {"coordinates":[-87.844544,41.118998],"type":"Point"}
}