{
  "type": "Feature",
  "properties": {
    "addr:full":"230 N Michigan Ave Chicago IL 60601",
    "addr:housenumber":"230",
    "addr:postcode":"60601",
    "addr:street":"N Michigan Ave",
    "iso:country":"US",
    "sg:address":"230 N Michigan Ave",
    "sg:city":"Chicago",
    "sg:phone":"+1 312 334 6700",
    "sg:postcode":"60601",
    "sg:province":"IL",
    "wof:name":"China Grill",
    "wof:placetype":"venue"
},
  "geometry": {"coordinates":[-87.62458700000001,41.886039],"type":"Point"}
}