{
  "type": "Feature",
  "properties": {
    "iso:country":"US",
    "sg:address":"3912 W John St",
    "sg:city":"Mchenry",
    "sg:classifiers":[
        {
            "category":"Utilities",
            "subcategory":"Natural Gas",
            "type":"Services"
        }
    ],
    "sg:phone":"+1 815 385 4200",
    "sg:postcode":"60050",
    "sg:province":"IL",
    "wof:name":"Northern Propane Gas Co.",
    "wof:placetype":"venue"
},
  "geometry": {"coordinates":[-88.27421099999999,42.342608],"type":"Point"}
}