{
  "type": "Feature",
  "properties": {
    "iso:country":"US",
    "sg:address":"359 Merrill Ct",
    "sg:city":"Libertyville",
    "sg:classifiers":[
        {
            "category":"Government",
            "subcategory":"Office",
            "type":"Public Place"
        }
    ],
    "sg:phone":"+1 847 816 6872",
    "sg:postcode":"60048",
    "sg:province":"IL",
    "sg:tags":[
        "village"
    ],
    "wof:name":"Libertyville Clerk's Office",
    "wof:placetype":"venue"
},
  "geometry": {"coordinates":[-87.957975,42.292954],"type":"Point"}
}