{
  "type": "Feature",
  "properties": {
    "iso:country":"US",
    "sg:address":"150 E Huron Street",
    "sg:city":"Chicago",
    "sg:classifiers":[
        {
            "category":"Health Services",
            "subcategory":"Doctor",
            "type":"Services"
        }
    ],
    "sg:phone":"+1 312 337 6888",
    "sg:postcode":"60611",
    "sg:province":"IL",
    "wof:name":"Dresner Bruce L MD",
    "wof:placetype":"venue"
},
  "geometry": {"coordinates":[-87.623773,41.894854],"type":"Point"}
}