{
  "type": "Feature",
  "properties": {
    "addr:full":"1625 Chicago Ave Evanston IL 60201",
    "addr:housenumber":"1625",
    "addr:postcode":"60201",
    "addr:street":"Chicago Ave",
    "iso:country":"US",
    "sg:address":"1625 Chicago Ave",
    "sg:city":"Evanston",
    "sg:phone":"+1 847 869 9453",
    "sg:postcode":"60201",
    "sg:province":"IL",
    "wof:name":"Wild Dogz",
    "wof:placetype":"venue"
},
  "geometry": {"coordinates":[-87.67947599999999,42.046574],"type":"Point"}
}