{
  "type": "Feature",
  "properties": {
    "iso:country":"US",
    "sg:address":"3116 7th Ave",
    "sg:city":"Rock Island",
    "sg:classifiers":[
        {
            "category":"Building & Trades",
            "subcategory":"Landscaping Services",
            "type":"Services"
        }
    ],
    "sg:phone":"+1 309 794 9195",
    "sg:postcode":"61201",
    "sg:province":"IL",
    "sg:tags":[
        "tree"
    ],
    "wof:name":"Tony's Tree Svc",
    "wof:placetype":"venue"
},
  "geometry": {"coordinates":[-90.554414,41.504912],"type":"Point"}
}