{
  "type": "Feature",
  "properties": {
    "iso:country":"US",
    "sg:address":"17838 Chappel Ave",
    "sg:city":"Lansing",
    "sg:classifiers":[
        {
            "category":"Shopping",
            "type":"Retail Goods"
        }
    ],
    "sg:phone":"+1 708 895 2770",
    "sg:postcode":"60438",
    "sg:province":"IL",
    "sg:website":"www.LifetimeCreationsOnline.com",
    "wof:name":"Lifetime Creations",
    "wof:placetype":"venue"
},
  "geometry": {"coordinates":[-87.572497,41.571305],"type":"Point"}
}