{
  "type": "Feature",
  "properties": {
    "addr:full":"363 S Schmale Rd Carol Stream IL 60188",
    "addr:housenumber":"363",
    "addr:postcode":"60188",
    "addr:street":"S Schmale Rd",
    "iso:country":"US",
    "sg:address":"363 S Schmale Rd",
    "sg:city":"Carol Stream",
    "sg:classifiers":[
        {
            "category":"Restaurant",
            "type":"Food & Drink"
        }
    ],
    "sg:menulink":"http://www.allmenus.com/il/milton/8044-dennys/menu/",
    "sg:phone":"+1 630 653 8996",
    "sg:postcode":"60188",
    "sg:province":"IL",
    "sg:tags":[
        "american",
        "diner"
    ],
    "wof:name":"Denny's",
    "wof:placetype":"venue"
},
  "geometry": {"coordinates":[-88.10361,41.893566],"type":"Point"}
}