{
  "type": "Feature",
  "properties": {
    "addr:full":"403 N Howard Ave Elmhurst IL 60126",
    "addr:housenumber":"403",
    "addr:postcode":"60126",
    "addr:street":"N Howard Ave",
    "iso:country":"US",
    "sg:address":"403 N Howard Ave",
    "sg:city":"Elmhurst",
    "sg:classifiers":[
        {
            "category":"Building & Trades",
            "subcategory":"Construction",
            "type":"Services"
        }
    ],
    "sg:phone":"+1 312 656 8839",
    "sg:postcode":"60126",
    "sg:province":"IL",
    "sg:tags":[
        "house"
    ],
    "wof:name":"Lahman John Cnstr & Rmdlg",
    "wof:placetype":"venue"
},
  "geometry": {"coordinates":[-87.932457,41.909288],"type":"Point"}
}