{
  "type": "Feature",
  "properties": {
    "addr:full":"1208 Lisle Pl Lisle IL 60532",
    "addr:housenumber":"1208",
    "addr:postcode":"60532",
    "addr:street":"Lisle Pl",
    "iso:country":"US",
    "sg:address":"1208 Lisle Pl",
    "sg:city":"Lisle",
    "sg:classifiers":[
        {
            "category":"Professional",
            "subcategory":"Business Services",
            "type":"Services"
        }
    ],
    "sg:phone":"+1 630 515 1160",
    "sg:postcode":"60532",
    "sg:province":"IL",
    "wof:name":"Kennedy Productions Inc",
    "wof:placetype":"venue"
},
  "geometry": {"coordinates":[-88.077054,41.796432],"type":"Point"}
}