{
  "type": "Feature",
  "properties": {
    "addr:full":"132 Essex Rd Elk Grove Village IL 60007",
    "addr:housenumber":"132",
    "addr:postcode":"60007",
    "addr:street":"Essex Rd",
    "iso:country":"US",
    "sg:address":"132 Essex Rd",
    "sg:city":"Elk Grove Village",
    "sg:classifiers":[
        {
            "category":"Professional",
            "subcategory":"Business Services",
            "type":"Services"
        }
    ],
    "sg:phone":"+1 847 640 7757",
    "sg:postcode":"60007",
    "sg:province":"IL",
    "wof:name":"OConnell and Associates",
    "wof:placetype":"venue"
},
  "geometry": {"coordinates":[-87.996645,41.99486],"type":"Point"}
}