{
  "type": "Feature",
  "properties": {
    "iso:country":"US",
    "sg:address":"305 Linn St",
    "sg:city":"Olney",
    "sg:classifiers":[
        {
            "category":"Building & Trades",
            "subcategory":"Equipment Rental",
            "type":"Services"
        }
    ],
    "sg:phone":"+1 618 392 6130",
    "sg:postcode":"62450",
    "sg:province":"IL",
    "sg:tags":[
        "yard",
        "leasing",
        "store"
    ],
    "wof:name":"Rehmel Mcnabb Rentals",
    "wof:placetype":"venue"
},
  "geometry": {"coordinates":[-88.103355,38.727519],"type":"Point"}
}