{
  "type": "Feature",
  "properties": {
    "iso:country":"US",
    "sg:address":"I 90 & Rt 20",
    "sg:city":"Hampshire",
    "sg:classifiers":[
        {
            "category":"Restaurant",
            "type":"Food & Drink"
        }
    ],
    "sg:phone":"+1 847 683 3531",
    "sg:postcode":"60140",
    "sg:province":"IL",
    "wof:name":"Arrowhead Restaurant the",
    "wof:placetype":"venue"
},
  "geometry": {"coordinates":[-88.53119700000001,42.0942],"type":"Point"}
}