{
  "type": "Feature",
  "properties": {
    "addr:full":"318 High St Aurora IL 60505",
    "addr:housenumber":"318",
    "addr:postcode":"60505",
    "addr:street":"High St",
    "iso:country":"US",
    "sg:address":"318 High St",
    "sg:city":"Aurora",
    "sg:classifiers":[
        {
            "category":"Sports & Exercise",
            "subcategory":"Bowling",
            "type":"Entertainment"
        }
    ],
    "sg:phone":"+1   ",
    "sg:postcode":"60505",
    "sg:province":"IL",
    "sg:tags":[
        "lounge",
        "alley"
    ],
    "wof:name":"Highway Lanes",
    "wof:placetype":"venue"
},
  "geometry": {"coordinates":[-88.302847,41.761805],"type":"Point"}
}