{
  "type": "Feature",
  "properties": {
    "addr:full":"501 W Church St Champaign IL 61820",
    "addr:housenumber":"501",
    "addr:postcode":"61820",
    "addr:street":"W Church St",
    "iso:country":"US",
    "sg:address":"501 W Church St",
    "sg:city":"Champaign",
    "sg:classifiers":[
        {
            "category":"Professional",
            "subcategory":"Lawyer & Legal Services",
            "type":"Services"
        }
    ],
    "sg:phone":"+1 217 352 7661",
    "sg:postcode":"61820",
    "sg:province":"IL",
    "wof:name":"Jefferson Timothy S Atty",
    "wof:placetype":"venue"
},
  "geometry": {"coordinates":[-88.24990099999999,40.118198],"type":"Point"}
}