{
  "type": "Feature",
  "properties": {
    "iso:country":"US",
    "sg:address":"12400 S 81st Ave",
    "sg:city":"Palos Park",
    "sg:classifiers":[
        {
            "category":"Building & Trades",
            "subcategory":"Construction",
            "type":"Services"
        }
    ],
    "sg:phone":"+1 708 448 3461",
    "sg:postcode":"60464",
    "sg:province":"IL",
    "sg:tags":[
        "plastering",
        "contractor"
    ],
    "wof:name":"Lasota Plastering Co  Inc",
    "wof:placetype":"venue"
},
  "geometry": {"coordinates":[-87.818186,41.663935],"type":"Point"}
}