{
  "type": "Feature",
  "properties": {
    "iso:country":"US",
    "sg:address":"901 W Oak St",
    "sg:city":"Mahomet",
    "sg:classifiers":[
        {
            "category":"Organizations",
            "subcategory":"Labor Organization",
            "type":"Services"
        }
    ],
    "sg:phone":"+1 217 586 2529",
    "sg:postcode":"61853",
    "sg:province":"IL",
    "wof:name":"Union of Utility Workers",
    "wof:placetype":"venue"
},
  "geometry": {"coordinates":[-88.42027899999999,40.194115],"type":"Point"}
}