{
  "type": "Feature",
  "properties": {
    "addr:full":"27901 W Concrete Dr Ingleside IL 60041",
    "addr:housenumber":"27901",
    "addr:postcode":"60041",
    "addr:street":"W Concrete Dr",
    "iso:country":"US",
    "sg:address":"27901 W Concrete Dr",
    "sg:city":"Ingleside",
    "sg:classifiers":[
        {
            "category":"Building & Trades",
            "subcategory":"Construction",
            "type":"Services"
        }
    ],
    "sg:phone":"+1 815 759 9140",
    "sg:postcode":"60041",
    "sg:province":"IL",
    "sg:tags":[
        "drywall",
        "contractor"
    ],
    "sg:website":"www.dritexinc.com",
    "wof:name":"Dritex Inc",
    "wof:placetype":"venue"
},
  "geometry": {"coordinates":[-88.173068,42.334845],"type":"Point"}
}