{
  "type": "Feature",
  "properties": {
    "addr:full":"1960 N Clybourn Avenue Rear Building Chicago IL 60614",
    "addr:housenumber":"1960",
    "addr:postcode":"60614",
    "addr:street":"N Clybourn Avenue Rear Building",
    "iso:country":"US",
    "sg:address":"1960 N Clybourn Avenue Rear Building",
    "sg:city":"Chicago",
    "sg:classifiers":[
        {
            "category":"Professional",
            "type":"Services"
        }
    ],
    "sg:phone":"+1 773 868 3010",
    "sg:postcode":"60614",
    "sg:province":"IL",
    "sg:tags":[
        "planning",
        "event"
    ],
    "sg:website":"www.chicagoevents.com/",
    "wof:name":"Special Events Management",
    "wof:placetype":"venue"
},
  "geometry": {"coordinates":[-87.657554,41.91669],"type":"Point"}
}