{
  "type": "Feature",
  "properties": {
    "addr:full":"9449 1/2 S Ashland Ave Chicago IL 60620",
    "addr:housenumber":"9449 1 / 2",
    "addr:postcode":"60620",
    "addr:street":"Ashland Ave",
    "iso:country":"US",
    "sg:address":"9449 1/2 S Ashland Ave",
    "sg:city":"Chicago",
    "sg:classifiers":[
        {
            "category":"Shopping",
            "subcategory":"Clothing, Apparel, & Fashions",
            "type":"Retail Goods"
        }
    ],
    "sg:phone":"+1 773 881 0555",
    "sg:postcode":"60620",
    "sg:province":"IL",
    "sg:tags":[
        "accessory",
        "clothing",
        "women's"
    ],
    "wof:name":"D & A Unlimited",
    "wof:placetype":"venue"
},
  "geometry": {"coordinates":[-87.666906,41.881449],"type":"Point"}
}