{
  "type": "Feature",
  "properties": {
    "iso:country":"US",
    "sg:address":"407 Lincoln Ave",
    "sg:city":"Charleston",
    "sg:classifiers":[
        {
            "category":"Professional",
            "subcategory":"Business Services",
            "type":"Services"
        }
    ],
    "sg:phone":"+1 217 345 3364",
    "sg:postcode":"61920",
    "sg:province":"IL",
    "sg:tags":[
        "transportation",
        "freight",
        "arrangement"
    ],
    "wof:name":"Mail Boxes Etc",
    "wof:placetype":"venue"
},
  "geometry": {"coordinates":[-88.17697800000001,39.484459],"type":"Point"}
}