{
  "type": "Feature",
  "properties": {
    "iso:country":"US",
    "sg:address":"4342 Oak Ave",
    "sg:city":"Lyons",
    "sg:classifiers":[
        {
            "category":"Shopping",
            "subcategory":"Computers & Home Electronics",
            "type":"Retail Goods"
        }
    ],
    "sg:phone":"+1   ",
    "sg:postcode":"60534",
    "sg:province":"IL",
    "wof:name":"Virgin Satellites",
    "wof:placetype":"venue"
},
  "geometry": {"coordinates":[-87.81128699999999,41.812532],"type":"Point"}
}