{
  "type": "Feature",
  "properties": {
    "iso:country":"US",
    "sg:address":"12818 Western Ave",
    "sg:city":"Blue Island",
    "sg:classifiers":[
        {
            "category":"Professional",
            "subcategory":"Accounting & Tax Preparation",
            "type":"Services"
        }
    ],
    "sg:phone":"+1 708 389 5596",
    "sg:postcode":"60406",
    "sg:province":"IL",
    "sg:tags":[
        "accountant"
    ],
    "wof:name":"Anthony J Lenart & Associates",
    "wof:placetype":"venue"
},
  "geometry": {"coordinates":[-87.680173,41.660517],"type":"Point"}
}