{
  "type": "Feature",
  "properties": {
    "addr:full":"4496 N 250 East Rd Allerton IL 61810",
    "addr:housenumber":"4496",
    "addr:postcode":"61810",
    "addr:street":"N 250 East Rd",
    "iso:country":"US",
    "sg:address":"4496 N 250 East Rd",
    "sg:city":"Allerton",
    "sg:phone":"+1 217 288 9264",
    "sg:postcode":"61810",
    "sg:province":"IL",
    "sg:tags":[
        "farm",
        "corn",
        "soybean"
    ],
    "wof:name":"Elmore Farms",
    "wof:placetype":"venue"
},
  "geometry": {"coordinates":[-87.890975,39.930989],"type":"Point"}
}