{
  "type": "Feature",
  "properties": {
    "addr:full":"122 W Madison St Chicago IL 60686",
    "addr:housenumber":"122",
    "addr:postcode":"60686",
    "addr:street":"W Madison St",
    "iso:country":"US",
    "sg:address":"122 W Madison St",
    "sg:city":"Chicago",
    "sg:classifiers":[
        {
            "category":"Restaurant",
            "type":"Food & Drink"
        }
    ],
    "sg:phone":"+1 312 338 0080",
    "sg:postcode":"60686",
    "sg:province":"IL",
    "sg:tags":[
        "mexican"
    ],
    "sg:website":"www.labambaburritos.com",
    "wof:name":"La Bamba",
    "wof:placetype":"venue"
},
  "geometry": {"coordinates":[-87.63154299999999,41.881957],"type":"Point"}
}