{
  "type": "Feature",
  "properties": {
    "iso:country":"US",
    "sg:address":"1105 Presley Ln",
    "sg:city":"West Frankfort",
    "sg:classifiers":[
        {
            "category":"Shopping",
            "subcategory":"Gifts & Souvenirs",
            "type":"Retail Goods"
        }
    ],
    "sg:phone":"+1   ",
    "sg:postcode":"62896",
    "sg:province":"IL",
    "wof:name":"Anna Ceramics & Gift Shops",
    "wof:placetype":"venue"
},
  "geometry": {"coordinates":[-88.974644,37.876662],"type":"Point"}
}