{
  "type": "Feature",
  "properties": {
    "iso:country":"US",
    "sg:address":"315 W Main St",
    "sg:city":"West Frankfort",
    "sg:classifiers":[
        {
            "category":"Home & Garden",
            "subcategory":"Building Materials",
            "type":"Retail Goods"
        }
    ],
    "sg:phone":"+1   ",
    "sg:postcode":"62896",
    "sg:province":"IL",
    "wof:name":"Kathalynas Construction",
    "wof:placetype":"venue"
},
  "geometry": {"coordinates":[-88.93285400000001,37.898009],"type":"Point"}
}