{
  "type": "Feature",
  "properties": {
    "iso:country":"US",
    "sg:address":"25082 423rd Ln",
    "sg:city":"Pittsfield",
    "sg:classifiers":[
        {
            "category":"Farming",
            "subcategory":"Farm",
            "type":"Manufacturing & Wholesale Goods"
        }
    ],
    "sg:phone":"+1 217 285 6070",
    "sg:postcode":"62363",
    "sg:province":"IL",
    "wof:name":"Schlieper Farms Carroll",
    "wof:placetype":"venue"
},
  "geometry": {"coordinates":[-90.736651,39.619673],"type":"Point"}
}