{
  "type": "Feature",
  "properties": {
    "addr:full":"217 W Chestnut St Chillicothe IL 61523",
    "addr:housenumber":"217",
    "addr:postcode":"61523",
    "addr:street":"W Chestnut St",
    "iso:country":"US",
    "sg:address":"217 W Chestnut St",
    "sg:city":"Chillicothe",
    "sg:classifiers":[
        {
            "category":"Government",
            "subcategory":"Office",
            "type":"Public Place"
        }
    ],
    "sg:phone":"+1 309 274 2172",
    "sg:postcode":"61523",
    "sg:province":"IL",
    "sg:tags":[
        "village"
    ],
    "wof:name":"Chillicothe City Office",
    "wof:placetype":"venue"
},
  "geometry": {"coordinates":[-89.48593200000001,40.918543],"type":"Point"}
}