{
  "type": "Feature",
  "properties": {
    "iso:country":"US",
    "sg:address":"1301 17th St",
    "sg:city":"Fulton",
    "sg:classifiers":[
        {
            "category":"Building & Trades",
            "subcategory":"Construction",
            "type":"Services"
        }
    ],
    "sg:phone":"+1 815 589 2330",
    "sg:postcode":"61252",
    "sg:province":"IL",
    "sg:tags":[
        "general",
        "contractor"
    ],
    "wof:name":"Goldridge Construction",
    "wof:placetype":"venue"
},
  "geometry": {"coordinates":[-90.147687,41.869233],"type":"Point"}
}