{
  "type": "Feature",
  "properties": {
    "iso:country":"US",
    "sg:address":"1350 N Wells Street Ofc",
    "sg:city":"Chicago",
    "sg:classifiers":[
        {
            "category":"Banks & Credit Unions",
            "subcategory":"Bank",
            "type":"Services"
        }
    ],
    "sg:phone":"+1 312 440 1296",
    "sg:postcode":"60610",
    "sg:province":"IL",
    "sg:website":"www.chase.com",
    "wof:name":"Chase",
    "wof:placetype":"venue"
},
  "geometry": {"coordinates":[-87.634602,41.906909],"type":"Point"}
}