{
  "type": "Feature",
  "properties": {
    "iso:country":"US",
    "sg:address":"218 W Washington St",
    "sg:city":"Chicago",
    "sg:classifiers":[
        {
            "category":"Personal",
            "type":"Services"
        },
        {
            "category":"Shopping",
            "subcategory":"Florist",
            "type":"Retail Goods"
        }
    ],
    "sg:phone":"+1 312 357 6040",
    "sg:postcode":"60606",
    "sg:province":"IL",
    "sg:tags":[
        "planning",
        "wedding"
    ],
    "sg:website":"www.cityenchantedgardens.com",
    "wof:name":"City Enchanted Gardens",
    "wof:placetype":"venue"
},
  "geometry": {"coordinates":[-87.634457,41.883211],"type":"Point"}
}