{
  "type": "Feature",
  "properties": {
    "iso:country":"US",
    "sg:address":"15 Newell Ave",
    "sg:city":"Danville",
    "sg:classifiers":[
        {
            "category":"Building & Trades",
            "subcategory":"Landscaping Services",
            "type":"Services"
        }
    ],
    "sg:phone":"+1 217 446 2115",
    "sg:postcode":"61832",
    "sg:province":"IL",
    "sg:tags":[
        "landscape",
        "contractor"
    ],
    "wof:name":"Sod A Lot Lawn Care & Snow",
    "wof:placetype":"venue"
},
  "geometry": {"coordinates":[-87.62986,40.166153],"type":"Point"}
}