{
  "type": "Feature",
  "properties": {
    "iso:country":"US",
    "sg:address":"1058 W Bryn Mawr Ave",
    "sg:city":"Chicago",
    "sg:classifiers":[
        {
            "category":"Banks & Credit Unions",
            "subcategory":"Bank",
            "type":"Services"
        }
    ],
    "sg:phone":"+1 773 989 2060",
    "sg:postcode":"60660",
    "sg:province":"IL",
    "wof:name":"Uptown Natl Bank of Chgo",
    "wof:placetype":"venue"
},
  "geometry": {"coordinates":[-87.65770000000001,41.9837],"type":"Point"}
}