{
  "type": "Feature",
  "properties": {
    "iso:country":"US",
    "sg:address":"3703 N Kildare Ave",
    "sg:city":"Chicago",
    "sg:classifiers":[
        {
            "category":"Building & Trades",
            "subcategory":"Construction",
            "type":"Services"
        }
    ],
    "sg:phone":"+1 773 583 6339",
    "sg:postcode":"60641",
    "sg:province":"IL",
    "sg:tags":[
        "home",
        "general",
        "remodeling",
        "contractor"
    ],
    "wof:name":"M D Olson & Co",
    "wof:placetype":"venue"
},
  "geometry": {"coordinates":[-87.735253,41.9499],"type":"Point"}
}