{
  "type": "Feature",
  "properties": {
    "iso:country":"US",
    "sg:address":"801 Meacham Rd",
    "sg:city":"Elk Grove Village",
    "sg:classifiers":[
        {
            "category":"Restaurant",
            "type":"Food & Drink"
        }
    ],
    "sg:phone":"+1   ",
    "sg:postcode":"60007",
    "sg:province":"IL",
    "sg:tags":[
        "eating"
    ],
    "wof:name":"Taco Bell",
    "wof:placetype":"venue"
},
  "geometry": {"coordinates":[-88.045946,42.000225],"type":"Point"}
}