{
  "type": "Feature",
  "properties": {
    "iso:country":"US",
    "sg:address":"1900 N Roselle Rd Ste 408",
    "sg:city":"Schaumburg",
    "sg:classifiers":[
        {
            "category":"Banks & Credit Unions",
            "subcategory":"Financial Services",
            "type":"Services"
        },
        {
            "category":"Professional",
            "subcategory":"Business Services",
            "type":"Services"
        }
    ],
    "sg:phone":"+1 847 230 1199",
    "sg:postcode":"60195",
    "sg:province":"IL",
    "sg:tags":[
        "management"
    ],
    "wof:name":"Tcf Asset Management",
    "wof:placetype":"venue"
},
  "geometry": {"coordinates":[-88.07953500000001,42.060284],"type":"Point"}
}