{
  "type": "Feature",
  "properties": {
    "iso:country":"US",
    "sg:address":"2614 Chapel Hill Dr",
    "sg:city":"Elgin",
    "sg:classifiers":[
        {
            "category":"Home & Garden",
            "subcategory":"Hardware",
            "type":"Retail Goods"
        }
    ],
    "sg:phone":"+1   ",
    "sg:postcode":"60120",
    "sg:province":"IL",
    "wof:name":"Clark Tools Inc",
    "wof:placetype":"venue"
},
  "geometry": {"coordinates":[-88.229113,42.035489],"type":"Point"}
}