{
  "type": "Feature",
  "properties": {
    "addr:full":"1455 S Michigan Ave Ste 230 Chicago IL 60605",
    "addr:housenumber":"1455",
    "addr:postcode":"60605",
    "addr:street":"S Michigan Ave Ste 230",
    "iso:country":"US",
    "sg:address":"1455 S Michigan Ave Ste 230",
    "sg:city":"Chicago",
    "sg:classifiers":[
        {
            "category":"Health Services",
            "subcategory":"Health Practitioner",
            "type":"Services"
        }
    ],
    "sg:phone":"+1 312 513 2554",
    "sg:postcode":"60605",
    "sg:province":"IL",
    "sg:tags":[
        "acupuncture"
    ],
    "sg:website":"ancienthealingchicago.com",
    "wof:name":"Ancient Healing Chicago",
    "wof:placetype":"venue"
},
  "geometry": {"coordinates":[-87.62357799999999,41.862553],"type":"Point"}
}