{
  "type": "Feature",
  "properties": {
    "iso:country":"US",
    "sg:address":"404 E Plaza Dr",
    "sg:city":"Carterville",
    "sg:classifiers":[
        {
            "category":"Health Services",
            "subcategory":"Optometrist",
            "type":"Services"
        }
    ],
    "sg:phone":"+1 618 985 9983",
    "sg:postcode":"62918",
    "sg:province":"IL",
    "sg:tags":[
        "ophthalmologist"
    ],
    "wof:name":"Marion Eye Center",
    "wof:placetype":"venue"
},
  "geometry": {"coordinates":[-89.072701,37.745201],"type":"Point"}
}