{
  "type": "Feature",
  "properties": {
    "iso:country":"US",
    "sg:address":"226 Marquette St",
    "sg:city":"La Salle",
    "sg:classifiers":[
        {
            "category":"Health Services",
            "subcategory":"Podiatrist",
            "type":"Services"
        }
    ],
    "sg:phone":"+1 815 224 3535",
    "sg:postcode":"61301",
    "sg:province":"IL",
    "wof:name":"Tabor Podiatry Center",
    "wof:placetype":"venue"
},
  "geometry": {"coordinates":[-89.095653,41.33003],"type":"Point"}
}