{
  "type": "Feature",
  "properties": {
    "iso:country":"US",
    "sg:address":"322 S Plaza Park",
    "sg:city":"Chillicothe",
    "sg:classifiers":[
        {
            "category":"Restaurant",
            "type":"Food & Drink"
        }
    ],
    "sg:menulink":"http://www.allmenus.com/il/chillicothe/88354-monicals-pizza/menu/",
    "sg:phone":"+1 309 274 6721",
    "sg:postcode":"61523",
    "sg:province":"IL",
    "sg:tags":[
        "american",
        "pizza"
    ],
    "wof:name":"Monicals Pizza",
    "wof:placetype":"venue"
},
  "geometry": {"coordinates":[-89.494913,40.90481],"type":"Point"}
}