{
  "type": "Feature",
  "properties": {
    "iso:country":"US",
    "sg:address":"320 E Dearborn St",
    "sg:city":"Havana",
    "sg:classifiers":[
        {
            "category":"Shopping",
            "subcategory":"Pharmacy",
            "type":"Retail Goods"
        }
    ],
    "sg:phone":"+1 309 543 6603",
    "sg:postcode":"62644",
    "sg:province":"IL",
    "wof:name":"CVS Pharmacy",
    "wof:placetype":"venue"
},
  "geometry": {"coordinates":[-90.05650199999999,40.294257],"type":"Point"}
}