{
  "type": "Feature",
  "properties": {
    "iso:country":"US",
    "sg:address":"301 S Main St",
    "sg:city":"Columbia",
    "sg:classifiers":[
        {
            "category":"Wholesale",
            "subcategory":"Computers",
            "type":"Manufacturing & Wholesale Goods"
        }
    ],
    "sg:phone":"+1 618 977 8666",
    "sg:postcode":"62236",
    "sg:province":"IL",
    "sg:tags":[
        "equipment"
    ],
    "wof:name":"Rl Custom Computers",
    "wof:placetype":"venue"
},
  "geometry": {"coordinates":[-90.19715100000001,38.441841],"type":"Point"}
}