{
  "type": "Feature",
  "properties": {
    "addr:full":"3837 W 127th St Alsip IL 60803",
    "addr:housenumber":"3837",
    "addr:postcode":"60803",
    "addr:street":"W 127Th St",
    "iso:country":"US",
    "sg:address":"3837 W 127th St",
    "sg:city":"Alsip",
    "sg:classifiers":[
        {
            "category":"Communications",
            "type":"Services"
        }
    ],
    "sg:phone":"+1 708 388 4150",
    "sg:postcode":"60803",
    "sg:province":"IL",
    "sg:tags":[
        "recording",
        "rehearsal",
        "studio"
    ],
    "wof:name":"U B Jammin' Productions",
    "wof:placetype":"venue"
},
  "geometry": {"coordinates":[-87.714983,41.661962],"type":"Point"}
}