{
  "type": "Feature",
  "properties": {
    "iso:country":"US",
    "sg:address":"1410 Bradley Ct",
    "sg:city":"Downers Grove",
    "sg:classifiers":[
        {
            "category":"Professional",
            "subcategory":"Lawyer & Legal Services",
            "type":"Services"
        }
    ],
    "sg:phone":"+1 630 964 6425",
    "sg:postcode":"60516",
    "sg:province":"IL",
    "wof:name":"Drews John Law Office",
    "wof:placetype":"venue"
},
  "geometry": {"coordinates":[-88.0194,41.764254],"type":"Point"}
}