{
  "type": "Feature",
  "properties": {
    "iso:country":"US",
    "sg:address":"5958 W Diversey Avenue",
    "sg:city":"Chicago",
    "sg:classifiers":[
        {
            "category":"Restaurant",
            "type":"Food & Drink"
        }
    ],
    "sg:phone":"+1 773 745 7199",
    "sg:postcode":"60639",
    "sg:province":"IL",
    "sg:tags":[
        "mexican"
    ],
    "wof:name":"Super Taqueria Vallarta",
    "wof:placetype":"venue"
},
  "geometry": {"coordinates":[-87.77584400000001,41.931178],"type":"Point"}
}