{
  "type": "Feature",
  "properties": {
    "iso:country":"US",
    "sg:address":"1357 W 103rd Street",
    "sg:city":"Chicago",
    "sg:classifiers":[
        {
            "category":"Banks & Credit Unions",
            "subcategory":"Bank",
            "type":"Services"
        },
        {
            "category":"Banks & Credit Unions",
            "subcategory":"Financial Services",
            "type":"Services"
        }
    ],
    "sg:phone":"+1 773 881 2200",
    "sg:postcode":"60643",
    "sg:province":"IL",
    "sg:tags":[
        "broker",
        "mortgage"
    ],
    "wof:name":"Charter One Bank",
    "wof:placetype":"venue"
},
  "geometry": {"coordinates":[-87.65611699999999,41.706757],"type":"Point"}
}