{
  "type": "Feature",
  "properties": {
    "addr:full":"5936 S King Dr Ste 2 Chicago IL 60637",
    "addr:housenumber":"5936",
    "addr:postcode":"60637",
    "addr:street":"S King Dr Ste 2",
    "iso:country":"US",
    "sg:address":"5936 S King Dr Ste 2",
    "sg:city":"Chicago",
    "sg:classifiers":[
        {
            "category":"Building & Trades",
            "subcategory":"Cleaning & Sanitation",
            "type":"Services"
        }
    ],
    "sg:phone":"+1 773 608 9235",
    "sg:postcode":"60637",
    "sg:province":"IL",
    "sg:tags":[
        "carpet"
    ],
    "sg:website":"www.ddfkproperties.com",
    "wof:name":"DDFK Properties",
    "wof:placetype":"venue"
},
  "geometry": {"coordinates":[-87.616089,41.786148],"type":"Point"}
}