{
  "type": "Feature",
  "properties": {
    "addr:full":"8260 Co Hwy 12 Addieville IL 62214",
    "addr:housenumber":"8260",
    "addr:postcode":"62214",
    "addr:street":"Co Hwy 12",
    "iso:country":"US",
    "sg:address":"8260 Co Hwy 12",
    "sg:city":"Addieville",
    "sg:classifiers":[
        {
            "category":"Farming",
            "subcategory":"Livestock Farm",
            "type":"Manufacturing & Wholesale Goods"
        }
    ],
    "sg:phone":"+1 618 824 6397",
    "sg:postcode":"62214",
    "sg:province":"IL",
    "sg:tags":[
        "hog",
        "beef",
        "far",
        "corn",
        "cattle",
        "or",
        "feedlot"
    ],
    "wof:name":"Jeff Heckert",
    "wof:placetype":"venue"
},
  "geometry": {"coordinates":[-89.648703,38.339344],"type":"Point"}
}