{
  "type": "Feature",
  "properties": {
    "addr:full":"2924 E 92nd Street Chicago IL 60617",
    "addr:housenumber":"2924",
    "addr:postcode":"60617",
    "addr:street":"E 92Nd Street",
    "iso:country":"US",
    "sg:address":"2924 E 92nd Street",
    "sg:city":"Chicago",
    "sg:classifiers":[
        {
            "category":"Shopping",
            "subcategory":"Pharmacy",
            "type":"Retail Goods"
        }
    ],
    "sg:phone":"+1 773 721 6603",
    "sg:postcode":"60617",
    "sg:province":"IL",
    "sg:tags":[
        "drugstore"
    ],
    "sg:website":"www.walgreens.com",
    "wof:name":"Walgreen Drug Stores",
    "wof:placetype":"venue"
},
  "geometry": {"coordinates":[-87.552947,41.728124],"type":"Point"}
}