{
  "type": "Feature",
  "properties": {
    "iso:country":"US",
    "sg:address":"150 E Huron St",
    "sg:city":"Chicago",
    "sg:classifiers":[
        {
            "category":"Health Services",
            "subcategory":"Doctor",
            "type":"Services"
        }
    ],
    "sg:phone":"+1 312 649 6565",
    "sg:postcode":"60611",
    "sg:province":"IL",
    "wof:name":"Jacks Barabra MD",
    "wof:placetype":"venue"
},
  "geometry": {"coordinates":[-87.623802,41.894901],"type":"Point"}
}