{
  "type": "Feature",
  "properties": {
    "addr:full":"10 S Riverside Plaza Ste 130 Chicago IL 60601",
    "addr:housenumber":"10",
    "addr:postcode":"60601",
    "addr:street":"S Riverside Plaza Ste 130",
    "iso:country":"US",
    "sg:address":"10 S Riverside Plaza Ste 130",
    "sg:city":"Chicago",
    "sg:classifiers":[
        {
            "category":"Coffee & Tea",
            "type":"Food & Drink"
        }
    ],
    "sg:phone":"+1 312 441 1919",
    "sg:postcode":"60601",
    "sg:province":"IL",
    "sg:website":"www.starbucks.com",
    "wof:name":"Starbucks",
    "wof:placetype":"venue"
},
  "geometry": {"coordinates":[-87.63884899999999,41.881237],"type":"Point"}
}