{
  "type": "Feature",
  "properties": {
    "addr:full":"728 Florsheim Dr Ste 10 Libertyville IL 60048",
    "addr:housenumber":"728",
    "addr:postcode":"60048",
    "addr:street":"Florsheim Dr Ste 10",
    "iso:country":"US",
    "sg:address":"728 Florsheim Dr Ste 10",
    "sg:city":"Libertyville",
    "sg:classifiers":[
        {
            "category":"Professional",
            "subcategory":"Lawyer & Legal Services",
            "type":"Services"
        }
    ],
    "sg:phone":"+1 847 680 7070",
    "sg:postcode":"60048",
    "sg:province":"IL",
    "sg:tags":[
        "attorney",
        "practice"
    ],
    "sg:website":"http://www.beermannfamilylaw.com",
    "wof:name":"Beerman, Jon L & Associates Limited Inc",
    "wof:placetype":"venue"
},
  "geometry": {"coordinates":[-87.94578300000001,42.258215],"type":"Point"}
}