{
  "type": "Feature",
  "properties": {
    "addr:full":"116 W Grand Ave Carterville IL 62918",
    "addr:housenumber":"116",
    "addr:postcode":"62918",
    "addr:street":"W Grand Ave",
    "iso:country":"US",
    "sg:address":"116 W Grand Ave",
    "sg:city":"Carterville",
    "sg:classifiers":[
        {
            "category":"Organizations",
            "subcategory":"Religious Organization",
            "type":"Services"
        }
    ],
    "sg:phone":"+1 618 985 2751",
    "sg:postcode":"62918",
    "sg:province":"IL",
    "sg:tags":[
        "church"
    ],
    "wof:name":"Grand Avenue Baptist Church",
    "wof:placetype":"venue"
},
  "geometry": {"coordinates":[-89.07732900000001,37.760238],"type":"Point"}
}