{
  "type": "Feature",
  "properties": {
    "addr:full":"560 N Ardmore Ave Villa Park IL 60181",
    "addr:housenumber":"560",
    "addr:postcode":"60181",
    "addr:street":"N Ardmore Ave",
    "iso:country":"US",
    "sg:address":"560 N Ardmore Ave",
    "sg:city":"Villa Park",
    "sg:classifiers":[
        {
            "category":"Building & Trades",
            "subcategory":"Construction",
            "type":"Services"
        }
    ],
    "sg:phone":"+1 630 530 4645",
    "sg:postcode":"60181",
    "sg:province":"IL",
    "sg:tags":[
        "house"
    ],
    "wof:name":"D Jones Construction",
    "wof:placetype":"venue"
},
  "geometry": {"coordinates":[-87.97896799999999,41.899613],"type":"Point"}
}