{
  "type": "Feature",
  "properties": {
    "iso:country":"US",
    "sg:address":"2082 N 2900th Ave",
    "sg:city":"Loraine",
    "sg:classifiers":[
        {
            "category":"Farming",
            "subcategory":"Livestock Farm",
            "type":"Manufacturing & Wholesale Goods"
        }
    ],
    "sg:phone":"+1 217 842 5531",
    "sg:postcode":"62349",
    "sg:province":"IL",
    "sg:tags":[
        "hog",
        "wheat",
        "corn",
        "soybean",
        "or",
        "feedlot"
    ],
    "wof:name":"Waner Farms",
    "wof:placetype":"venue"
},
  "geometry": {"coordinates":[-91.107433,40.180418],"type":"Point"}
}