{
  "type": "Feature",
  "properties": {
    "iso:country":"US",
    "sg:address":"18 Inverness Dr",
    "sg:city":"Bloomington",
    "sg:classifiers":[
        {
            "category":"Insurance",
            "subcategory":"Hazard Insurance",
            "type":"Services"
        }
    ],
    "sg:phone":"+1 309 827 7493",
    "sg:postcode":"61701",
    "sg:province":"IL",
    "wof:name":"Cindy L Myers",
    "wof:placetype":"venue"
},
  "geometry": {"coordinates":[-88.972802,40.491816],"type":"Point"}
}