{
  "type": "Feature",
  "properties": {
    "addr:full":"1909 S Mount Zion Rd Decatur IL 62521",
    "addr:housenumber":"1909",
    "addr:postcode":"62521",
    "addr:street":"S Mount Zion Rd",
    "iso:country":"US",
    "sg:address":"1909 S Mount Zion Rd",
    "sg:city":"Decatur",
    "sg:classifiers":[
        {
            "category":"Restaurant",
            "type":"Food & Drink"
        }
    ],
    "sg:menulink":"http://www.allmenus.com/il/long-creek/212307-mcdonalds/menu/",
    "sg:postcode":"62521",
    "sg:province":"IL",
    "sg:tags":[
        "burger",
        "american"
    ],
    "wof:name":"McDonald's",
    "wof:placetype":"venue"
},
  "geometry": {"coordinates":[-88.878468,39.820556],"type":"Point"}
}