{
  "type": "Feature",
  "properties": {
    "addr:full":"222 W Main St Staunton IL 62088",
    "addr:housenumber":"222",
    "addr:postcode":"62088",
    "addr:street":"W Main St",
    "iso:country":"US",
    "sg:address":"222 W Main St",
    "sg:city":"Staunton",
    "sg:classifiers":[
        {
            "category":"Home & Garden",
            "subcategory":"Furniture",
            "type":"Retail Goods"
        }
    ],
    "sg:phone":"+1   ",
    "sg:postcode":"62088",
    "sg:province":"IL",
    "sg:tags":[
        "floor",
        "covering"
    ],
    "wof:name":"RUSSELL FURNITURE & FLOOR COVE",
    "wof:placetype":"venue"
},
  "geometry": {"coordinates":[-89.78802899999999,39.012046],"type":"Point"}
}