{
  "type": "Feature",
  "properties": {
    "addr:full":"2150 W Carroll Ave Chicago IL 60612",
    "addr:housenumber":"2150",
    "addr:postcode":"60612",
    "addr:street":"W Carroll Ave",
    "iso:country":"US",
    "sg:address":"2150 W Carroll Ave",
    "sg:city":"Chicago",
    "sg:classifiers":[
        {
            "category":"Food & Beverages",
            "subcategory":"Groceries & Convenience Stores",
            "type":"Retail Goods"
        }
    ],
    "sg:phone":"+1 312 421 6500",
    "sg:postcode":"60612",
    "sg:province":"IL",
    "wof:name":"Anmar Foods",
    "wof:placetype":"venue"
},
  "geometry": {"coordinates":[-87.679497,41.887699],"type":"Point"}
}