{
  "type": "Feature",
  "properties": {
    "iso:country":"US",
    "sg:address":"1001 Warrenville Rd",
    "sg:city":"Lisle",
    "sg:classifiers":[
        {
            "category":"Professional",
            "subcategory":"Computer Services",
            "type":"Services"
        }
    ],
    "sg:phone":"+1 630 515 0780",
    "sg:postcode":"60532",
    "sg:province":"IL",
    "sg:tags":[
        "develops",
        "consults",
        "software"
    ],
    "wof:name":"Rti",
    "wof:placetype":"venue"
},
  "geometry": {"coordinates":[-88.07082699999999,41.808552],"type":"Point"}
}