{
  "type": "Feature",
  "properties": {
    "addr:full":"3336 W Bryn Mawr Ave Chicago IL 60659",
    "addr:housenumber":"3336",
    "addr:postcode":"60659",
    "addr:street":"W Bryn Mawr Ave",
    "iso:country":"US",
    "sg:address":"3336 W Bryn Mawr Ave",
    "sg:city":"Chicago",
    "sg:classifiers":[
        {
            "category":"Real Estate",
            "subcategory":"Real Estate Operator",
            "type":"Services"
        }
    ],
    "sg:phone":"+1 773 267 8133",
    "sg:postcode":"60659",
    "sg:province":"IL",
    "sg:tags":[
        "building",
        "nonresidential"
    ],
    "wof:name":"Travel Shopping Center",
    "wof:placetype":"venue"
},
  "geometry": {"coordinates":[-87.713688,41.983084],"type":"Point"}
}