{
  "type": "Feature",
  "properties": {
    "addr:full":"951 S 7th St Rochelle IL 61068",
    "addr:housenumber":"951",
    "addr:postcode":"61068",
    "addr:street":"S 7Th St",
    "iso:country":"US",
    "sg:address":"951 S 7th St",
    "sg:city":"Rochelle",
    "sg:classifiers":[
        {
            "category":"Building & Trades",
            "subcategory":"Construction",
            "type":"Services"
        }
    ],
    "sg:phone":"+1 815 561 0440",
    "sg:postcode":"61068",
    "sg:province":"IL",
    "sg:tags":[
        "general",
        "contractor"
    ],
    "wof:name":"Diamond Petroleum Systems",
    "wof:placetype":"venue"
},
  "geometry": {"coordinates":[-89.068422,41.910138],"type":"Point"}
}