{
  "type": "Feature",
  "properties": {
    "iso:country":"US",
    "sg:address":"3561 W Armitage Ave",
    "sg:city":"Chicago",
    "sg:classifiers":[
        {
            "category":"Restaurant",
            "type":"Food & Drink"
        }
    ],
    "sg:phone":"+1   ",
    "sg:postcode":"60647",
    "sg:province":"IL",
    "sg:tags":[
        "eating"
    ],
    "wof:name":"Steves Gyros Inc",
    "wof:placetype":"venue"
},
  "geometry": {"coordinates":[-87.716271,41.917214],"type":"Point"}
}