{
  "type": "Feature",
  "properties": {
    "addr:full":"1506 6th Ave Moline IL 61265",
    "addr:housenumber":"1506",
    "addr:postcode":"61265",
    "addr:street":"6Th Ave",
    "iso:country":"US",
    "sg:address":"1506 6th Ave",
    "sg:city":"Moline",
    "sg:classifiers":[
        {
            "category":"Education",
            "subcategory":"Dance Studio",
            "type":"Public Place"
        },
        {
            "category":"Arts & Performance",
            "subcategory":"Theater",
            "type":"Entertainment"
        }
    ],
    "sg:phone":"+1 309 757 0071",
    "sg:postcode":"61265",
    "sg:province":"IL",
    "sg:tags":[
        "theatrical",
        "instruction",
        "dancing"
    ],
    "wof:name":"Academy For The Performing Art",
    "wof:placetype":"venue"
},
  "geometry": {"coordinates":[-90.514387,41.505662],"type":"Point"}
}