{
  "type": "Feature",
  "properties": {
    "addr:full":"27267 E 900 N Rd Le Roy IL 61741",
    "addr:housenumber":"27267",
    "addr:postcode":"61741",
    "addr:street":"E 900 N Rd",
    "iso:country":"US",
    "sg:address":"27267 E 900 N Rd",
    "sg:city":"Le Roy",
    "sg:classifiers":[
        {
            "category":"Recreation",
            "type":"Entertainment"
        }
    ],
    "sg:phone":"+1 309 724 8043",
    "sg:postcode":"61741",
    "sg:province":"IL",
    "sg:tags":[
        "stable"
    ],
    "wof:name":"Outlaw Outfitters Riding Stbl",
    "wof:placetype":"venue"
},
  "geometry": {"coordinates":[-88.40680999999999,40.759956],"type":"Point"}
}