{
  "type": "Feature",
  "properties": {
    "addr:full":"5316 N Milwaukee Ave Chicago IL 60630",
    "addr:housenumber":"5316",
    "addr:postcode":"60630",
    "addr:street":"N Milwaukee Ave",
    "iso:country":"US",
    "sg:address":"5316 N Milwaukee Ave",
    "sg:city":"Chicago",
    "sg:classifiers":[
        {
            "category":"Wholesale",
            "subcategory":"Medical Equipment & Supplies",
            "type":"Manufacturing & Wholesale Goods"
        },
        {
            "category":"Shopping",
            "subcategory":"Hobbies, Toys, & Games",
            "type":"Retail Goods"
        },
        {
            "category":"Retail",
            "subcategory":"Photofinishing",
            "type":"Services"
        },
        {
            "category":"Shopping",
            "subcategory":"Discount & Variety Stores",
            "type":"Retail Goods"
        },
        {
            "category":"Communications",
            "subcategory":"Television Station",
            "type":"Services"
        }
    ],
    "sg:phone":"+1 773 763 0313",
    "sg:postcode":"60630",
    "sg:province":"IL",
    "sg:tags":[
        "shop",
        "toy",
        "telescope",
        "microscope",
        "laboratory",
        "hobby",
        "model",
        "salvage",
        "merchandise",
        "surplus"
    ],
    "sg:website":"http://Sciplus.com",
    "wof:name":"American Science & Surplus",
    "wof:placetype":"venue"
},
  "geometry": {"coordinates":[-87.768829,41.976871],"type":"Point"}
}