{
  "type": "Feature",
  "properties": {
    "iso:country":"US",
    "sg:address":"946 S Oak Park Ave",
    "sg:city":"Oak Park",
    "sg:classifiers":[
        {
            "category":"Professional",
            "subcategory":"Lawyer & Legal Services",
            "type":"Services"
        }
    ],
    "sg:phone":"+1 708 848 4566",
    "sg:postcode":"60304",
    "sg:province":"IL",
    "wof:name":"Stephen H Dixon",
    "wof:placetype":"venue"
},
  "geometry": {"coordinates":[-87.79386599999999,41.870803],"type":"Point"}
}