{
  "type": "Feature",
  "properties": {
    "addr:full":"2755 W Adams St Chicago IL 60612",
    "addr:housenumber":"2755",
    "addr:postcode":"60612",
    "addr:street":"W Adams St",
    "iso:country":"US",
    "sg:address":"2755 W Adams St",
    "sg:city":"Chicago",
    "sg:classifiers":[
        {
            "category":"Place Of Worship",
            "subcategory":"Church",
            "type":"Public Place"
        },
        {
            "category":"Place Of Worship",
            "type":"Public Place"
        }
    ],
    "sg:phone":"+1 773 915 1279",
    "sg:postcode":"60612",
    "sg:province":"IL",
    "sg:tags":[
        "churches-non-denominational"
    ],
    "wof:name":"Living Word Ministries Intl",
    "wof:placetype":"venue"
},
  "geometry": {"coordinates":[-87.695104,41.878349],"type":"Point"}
}