{
  "type": "Feature",
  "properties": {
    "addr:full":"1200 Ravinia Pl Orland Park IL 60462",
    "addr:housenumber":"1200",
    "addr:postcode":"60462",
    "addr:street":"Ravinia Pl",
    "iso:country":"US",
    "sg:address":"1200 Ravinia Pl",
    "sg:city":"Orland Park",
    "sg:classifiers":[
        {
            "category":"Insurance",
            "subcategory":"Insurance Agent",
            "type":"Services"
        }
    ],
    "sg:phone":"+1 708 460 9556",
    "sg:postcode":"60462",
    "sg:province":"IL",
    "wof:name":"American Builders Insurance",
    "wof:placetype":"venue"
},
  "geometry": {"coordinates":[-87.853454,41.615342],"type":"Point"}
}