{
  "type": "Feature",
  "properties": {
    "iso:country":"US",
    "sg:address":"1940 Connie Dr",
    "sg:city":"Crest Hill",
    "sg:classifiers":[
        {
            "category":"Professional",
            "subcategory":"Accounting & Tax Preparation",
            "type":"Services"
        }
    ],
    "sg:phone":"+1 815 744 0557",
    "sg:postcode":"60403",
    "sg:province":"IL",
    "sg:tags":[
        "bookkeeping",
        "general"
    ],
    "wof:name":"Alex & Assoc Administrative",
    "wof:placetype":"venue"
},
  "geometry": {"coordinates":[-88.135957,41.557388],"type":"Point"}
}