{
  "type": "Feature",
  "properties": {
    "addr:full":"2550 Golf Rd Rolling Meadows IL 60008",
    "addr:housenumber":"2550",
    "addr:postcode":"60008",
    "addr:street":"Golf Rd",
    "iso:country":"US",
    "sg:address":"2550 Golf Rd",
    "sg:city":"Rolling Meadows",
    "sg:classifiers":[
        {
            "category":"Real Estate",
            "subcategory":"Developer",
            "type":"Services"
        }
    ],
    "sg:phone":"+1 847 640 1440",
    "sg:postcode":"60008",
    "sg:province":"IL",
    "sg:website":"www.goco.com",
    "wof:name":"Golub & Co",
    "wof:placetype":"venue"
},
  "geometry": {"coordinates":[-88.01191,42.051275],"type":"Point"}
}