{
  "type": "Feature",
  "properties": {
    "addr:full":"29092 Blue Heron Rd Rock Falls IL 61071",
    "addr:housenumber":"29092",
    "addr:postcode":"61071",
    "addr:street":"Blue Heron Rd",
    "iso:country":"US",
    "sg:address":"29092 Blue Heron Rd",
    "sg:city":"Rock Falls",
    "sg:classifiers":[
        {
            "category":"Building & Trades",
            "subcategory":"Plumbing",
            "type":"Services"
        }
    ],
    "sg:phone":"+1 815 626 4744",
    "sg:postcode":"61071",
    "sg:province":"IL",
    "sg:tags":[
        "contractor"
    ],
    "wof:name":"Tom Cushman Plumbing",
    "wof:placetype":"venue"
},
  "geometry": {"coordinates":[-89.68957399999999,41.712191],"type":"Point"}
}