{
  "type": "Feature",
  "properties": {
    "addr:full":"12854 S Ashland Ave Calumet Park IL 60827",
    "addr:housenumber":"12854",
    "addr:postcode":"60827",
    "addr:street":"S Ashland Ave",
    "iso:country":"US",
    "sg:address":"12854 S Ashland Ave",
    "sg:city":"Calumet Park",
    "sg:classifiers":[
        {
            "category":"Retail",
            "subcategory":"Portrait Studio",
            "type":"Services"
        },
        {
            "category":"Shopping",
            "subcategory":"Pharmacy",
            "type":"Retail Goods"
        }
    ],
    "sg:phone":"+1 708 239 1136",
    "sg:postcode":"60827",
    "sg:province":"IL",
    "sg:tags":[
        "photography",
        "drugstore",
        "store"
    ],
    "sg:website":"www.walgreens.com",
    "wof:name":"Walgreen Drug Stores",
    "wof:placetype":"venue"
},
  "geometry": {"coordinates":[-87.66101999999999,41.659725],"type":"Point"}
}