{
  "type": "Feature",
  "properties": {
    "addr:full":"810 W 59th Street Chicago IL 60621",
    "addr:housenumber":"810",
    "addr:postcode":"60621",
    "addr:street":"W 59Th Street",
    "iso:country":"US",
    "sg:address":"810 W 59th Street",
    "sg:city":"Chicago",
    "sg:classifiers":[
        {
            "category":"Restaurant",
            "type":"Food & Drink"
        }
    ],
    "sg:phone":"+1 773 602 1988",
    "sg:postcode":"60621",
    "sg:province":"IL",
    "wof:name":"Hook Fish & Chicken",
    "wof:placetype":"venue"
},
  "geometry": {"coordinates":[-87.645636,41.786787],"type":"Point"}
}