{
  "type": "Feature",
  "properties": {
    "iso:country":"US",
    "sg:address":"270 Cumberland Ln",
    "sg:city":"Crystal Lake",
    "sg:classifiers":[
        {
            "category":"Professional",
            "type":"Services"
        }
    ],
    "sg:phone":"+1 815 455 5211",
    "sg:postcode":"60014",
    "sg:province":"IL",
    "wof:name":"Byer Editorial Services",
    "wof:placetype":"venue"
},
  "geometry": {"coordinates":[-88.351489,42.231155],"type":"Point"}
}