{
  "type": "Feature",
  "properties": {
    "iso:country":"US",
    "sg:address":"10834 S Wabash Ave",
    "sg:city":"Chicago",
    "sg:classifiers":[
        {
            "category":"Organizations",
            "subcategory":"Community Association",
            "type":"Services"
        }
    ],
    "sg:phone":"+1 347 285 3909",
    "sg:postcode":"60628",
    "sg:province":"IL",
    "wof:name":"American People United",
    "wof:placetype":"venue"
},
  "geometry": {"coordinates":[-87.622052,41.697435],"type":"Point"}
}