{
  "type": "Feature",
  "properties": {
    "addr:full":"542 W Colfax St Palatine IL 60067",
    "addr:housenumber":"542",
    "addr:postcode":"60067",
    "addr:street":"W Colfax St",
    "iso:country":"US",
    "sg:address":"542 W Colfax St",
    "sg:city":"Palatine",
    "sg:classifiers":[
        {
            "category":"Retail",
            "subcategory":"Auto Repair",
            "type":"Services"
        }
    ],
    "sg:phone":"+1 847 359 0910",
    "sg:postcode":"60067",
    "sg:province":"IL",
    "sg:tags":[
        "shop",
        "automotive",
        "general"
    ],
    "wof:name":"Colfax Auto Repair Inc",
    "wof:placetype":"venue"
},
  "geometry": {"coordinates":[-88.054946,42.116398],"type":"Point"}
}