{
  "type": "Feature",
  "properties": {
    "iso:country":"US",
    "sg:address":"4721 Cromwell Ln",
    "sg:city":"Loves Park",
    "sg:classifiers":[
        {
            "category":"Retail",
            "subcategory":"Repair Shop",
            "type":"Services"
        }
    ],
    "sg:phone":"+1 815 654 1084",
    "sg:postcode":"61111",
    "sg:province":"IL",
    "sg:tags":[
        "taxidermist"
    ],
    "wof:name":"Bland's Taxidermy Studio",
    "wof:placetype":"venue"
},
  "geometry": {"coordinates":[-89.010065,42.326917],"type":"Point"}
}