{
  "type": "Feature",
  "properties": {
    "iso:country":"US",
    "sg:address":"18 East Ave",
    "sg:city":"Riverside",
    "sg:classifiers":[
        {
            "category":"Autos & Motor Vehicles",
            "subcategory":"Auto Supplies",
            "type":"Retail Goods"
        },
        {
            "category":"Retail",
            "subcategory":"Auto Repair",
            "type":"Services"
        }
    ],
    "sg:phone":"+1 708 447 7221",
    "sg:postcode":"60546",
    "sg:province":"IL",
    "sg:tags":[
        "automobile",
        "part",
        "truck"
    ],
    "sg:website":"http://clickserve.dartsearch.net/link/click?lid=43000000313869905&ds_s_kwgid=58000000006820725&ds_e_matchtype={MatchType}&ds_e_kwdid={OrderItemId}&ds_e_adid={AdId}&ds_url_v=2",
    "wof:name":"Riverside Garage",
    "wof:placetype":"venue"
},
  "geometry": {"coordinates":[-87.820691,41.827421],"type":"Point"}
}