{
  "type": "Feature",
  "properties": {
    "addr:full":"123 N Wacker Drive Chicago IL 60606",
    "addr:housenumber":"123",
    "addr:postcode":"60606",
    "addr:street":"N Wacker Drive",
    "iso:country":"US",
    "sg:address":"123 N Wacker Drive",
    "sg:city":"Chicago",
    "sg:classifiers":[
        {
            "category":"Professional",
            "subcategory":"Lawyer & Legal Services",
            "type":"Services"
        }
    ],
    "sg:phone":"+1 312 474 7140",
    "sg:postcode":"60606",
    "sg:province":"IL",
    "wof:name":"Naccasha Ziyad",
    "wof:placetype":"venue"
},
  "geometry": {"coordinates":[-87.636724,41.883807],"type":"Point"}
}