{
  "type": "Feature",
  "properties": {
    "addr:full":"110 S Waukegan Rd Deerfield IL 60015",
    "addr:housenumber":"110",
    "addr:postcode":"60015",
    "addr:street":"S Waukegan Rd",
    "iso:country":"US",
    "sg:address":"110 S Waukegan Rd",
    "sg:city":"Deerfield",
    "sg:classifiers":[
        {
            "category":"Utilities",
            "subcategory":"Mobile Phone",
            "type":"Services"
        }
    ],
    "sg:phone":"+1 847 509 0219",
    "sg:postcode":"60015",
    "sg:province":"IL",
    "sg:tags":[
        "telephone",
        "cellular"
    ],
    "wof:name":"T-Mobile",
    "wof:placetype":"venue"
},
  "geometry": {"coordinates":[-87.833468,42.149648],"type":"Point"}
}