{
  "type": "Feature",
  "properties": {
    "addr:full":"9515 Holy Cross Ln Breese IL 62230",
    "addr:postcode":"9515;62230",
    "addr:street":"Holy Cross Ln",
    "iso:country":"US",
    "sg:address":"9515 Holy Cross Ln",
    "sg:city":"Breese",
    "sg:classifiers":[
        {
            "category":"Health Services",
            "subcategory":"Hospital",
            "type":"Services"
        },
        {
            "category":"Health Services",
            "subcategory":"Clinic",
            "type":"Services"
        }
    ],
    "sg:phone":"+1 618 526 4511",
    "sg:postcode":"62230",
    "sg:province":"IL",
    "sg:tags":[
        "treatment",
        "cancer"
    ],
    "wof:name":"Oncology Therapy Services, Lp",
    "wof:placetype":"venue"
},
  "geometry": {"coordinates":[-89.524292,38.625149],"type":"Point"}
}