{
  "type": "Feature",
  "properties": {
    "iso:country":"US",
    "sg:address":"297 E Glenwood Lansing Rd",
    "sg:city":"Glenwood",
    "sg:classifiers":[
        {
            "category":"Insurance",
            "subcategory":"Insurance Agent",
            "type":"Services"
        },
        {
            "category":"Insurance",
            "subcategory":"Hazard Insurance",
            "type":"Services"
        },
        {
            "category":"Insurance",
            "subcategory":"Title Insurance",
            "type":"Services"
        },
        {
            "category":"Insurance",
            "subcategory":"Life Insurance",
            "type":"Services"
        }
    ],
    "sg:phone":"+1 708 758 3300",
    "sg:postcode":"60425",
    "sg:province":"IL",
    "sg:tags":[
        "business",
        "auto",
        "commercial",
        "homeowner",
        "motorcycle",
        "renter"
    ],
    "wof:name":"Allstate Insurance Company - Paula Kelly",
    "wof:placetype":"venue"
},
  "geometry": {"coordinates":[-87.60372099999999,41.542631],"type":"Point"}
}