{
  "type": "Feature",
  "properties": {
    "iso:country":"US",
    "sg:address":"3 Lincoln Center",
    "sg:city":"Villa Park",
    "sg:classifiers":[
        {
            "category":"Restaurant",
            "type":"Food & Drink"
        }
    ],
    "sg:phone":"+1   ",
    "sg:postcode":"60181",
    "sg:province":"IL",
    "sg:tags":[
        "eating"
    ],
    "wof:name":"Lincoln Center Cafe",
    "wof:placetype":"venue"
},
  "geometry": {"coordinates":[-87.982007,41.847876],"type":"Point"}
}