{
  "type": "Feature",
  "properties": {
    "iso:country":"US",
    "sg:address":"330 N 4th St",
    "sg:city":"Vandalia",
    "sg:classifiers":[
        {
            "category":"Retail",
            "subcategory":"Auto Repair",
            "type":"Services"
        }
    ],
    "sg:phone":"+1 618 283 2016",
    "sg:postcode":"62471",
    "sg:province":"IL",
    "sg:tags":[
        "muffler",
        "exhaust",
        "system"
    ],
    "wof:name":"Eastwood Muffler",
    "wof:placetype":"venue"
},
  "geometry": {"coordinates":[-89.094588,38.964352],"type":"Point"}
}