{
  "type": "Feature",
  "properties": {
    "iso:country":"US",
    "sg:address":"409 N 1st St",
    "sg:city":"Cary",
    "sg:classifiers":[
        {
            "category":"Education",
            "subcategory":"School",
            "type":"Public Place"
        }
    ],
    "sg:phone":"+1 847 462 5971",
    "sg:postcode":"60013",
    "sg:province":"IL",
    "wof:name":"Trinity Christian Academy",
    "wof:placetype":"venue"
},
  "geometry": {"coordinates":[-88.238176,42.213662],"type":"Point"}
}