{
  "type": "Feature",
  "properties": {
    "iso:country":"US",
    "sg:address":"1801 State St",
    "sg:city":"Alton",
    "sg:classifiers":[
        {
            "category":"Retail",
            "subcategory":"Repair Shop",
            "type":"Services"
        }
    ],
    "sg:phone":"+1 618 465 4374",
    "sg:postcode":"62002",
    "sg:province":"IL",
    "sg:tags":[
        "repairing",
        "lawn",
        "mower"
    ],
    "wof:name":"Velloff's Power Equipment",
    "wof:placetype":"venue"
},
  "geometry": {"coordinates":[-90.19619299999999,38.910028],"type":"Point"}
}