{
  "type": "Feature",
  "properties": {
    "iso:country":"US",
    "sg:address":"7437 W Diversey Ave",
    "sg:city":"Elmwood Park",
    "sg:classifiers":[
        {
            "category":"Food & Beverages",
            "subcategory":"Groceries & Convenience Stores",
            "type":"Retail Goods"
        }
    ],
    "sg:phone":"+1 708 453 6400",
    "sg:postcode":"60707",
    "sg:province":"IL",
    "wof:name":"G & R Grocery",
    "wof:placetype":"venue"
},
  "geometry": {"coordinates":[-87.81289700000001,41.9305],"type":"Point"}
}