{
  "type": "Feature",
  "properties": {
    "iso:country":"US",
    "sg:address":"1635 Glen Ellyn Rd",
    "sg:city":"Glendale Heights",
    "sg:classifiers":[
        {
            "category":"Government",
            "subcategory":"Office",
            "type":"Public Place"
        }
    ],
    "sg:phone":"+1 630 260 6007",
    "sg:postcode":"60139",
    "sg:province":"IL",
    "sg:tags":[
        "govt",
        "city"
    ],
    "wof:name":"Glendale Hts Water Dept",
    "wof:placetype":"venue"
},
  "geometry": {"coordinates":[-88.061729,41.919603],"type":"Point"}
}