{
  "type": "Feature",
  "properties": {
    "addr:full":"10342 S Kedzie Ave Chicago IL 60655",
    "addr:housenumber":"10342",
    "addr:postcode":"60655",
    "addr:street":"S Kedzie Ave",
    "iso:country":"US",
    "sg:address":"10342 S Kedzie Ave",
    "sg:city":"Chicago",
    "sg:classifiers":[
        {
            "category":"Health Services",
            "subcategory":"Dentist",
            "type":"Services"
        }
    ],
    "sg:phone":"+1 773 779 1983",
    "sg:postcode":"60655",
    "sg:province":"IL",
    "wof:name":"Mc Nicholas Robert DDS",
    "wof:placetype":"venue"
},
  "geometry": {"coordinates":[-87.701494,41.705379],"type":"Point"}
}