{
  "type": "Feature",
  "properties": {
    "addr:full":"1374 E Ash St Canton IL 61520",
    "addr:housenumber":"1374",
    "addr:postcode":"61520",
    "addr:street":"E Ash St",
    "iso:country":"US",
    "sg:address":"1374 E Ash St",
    "sg:city":"Canton",
    "sg:classifiers":[
        {
            "category":"Personal",
            "subcategory":"Beauty Salon",
            "type":"Services"
        }
    ],
    "sg:phone":"+1 309 647 3944",
    "sg:postcode":"61520",
    "sg:province":"IL",
    "wof:name":"KLIP & KURL Beauty Salon",
    "wof:placetype":"venue"
},
  "geometry": {"coordinates":[-90.01453600000001,40.560696],"type":"Point"}
}