{
  "type": "Feature",
  "properties": {
    "iso:country":"US",
    "sg:address":"5509 W 85th St",
    "sg:city":"Bedford Park",
    "sg:classifiers":[
        {
            "category":"Building & Trades",
            "subcategory":"Construction",
            "type":"Services"
        }
    ],
    "sg:phone":"+1 708 636 3390",
    "sg:postcode":"60459",
    "sg:province":"IL",
    "sg:tags":[
        "contractor"
    ],
    "wof:name":"M W Roofing & Aluminum",
    "wof:placetype":"venue"
},
  "geometry": {"coordinates":[-87.760258,41.737769],"type":"Point"}
}