{
  "type": "Feature",
  "properties": {
    "iso:country":"US",
    "sg:address":"455 Brighton Dr",
    "sg:city":"Bloomingdale",
    "sg:classifiers":[
        {
            "category":"Home & Garden",
            "subcategory":"Hardware",
            "type":"Retail Goods"
        }
    ],
    "sg:phone":"+1 630 351 9500",
    "sg:postcode":"60108",
    "sg:province":"IL",
    "sg:tags":[
        "store"
    ],
    "wof:name":"Tech Syn Corporation",
    "wof:placetype":"venue"
},
  "geometry": {"coordinates":[-88.12460299999999,41.941399],"type":"Point"}
}