{
  "type": "Feature",
  "properties": {
    "iso:country":"US",
    "sg:address":"40 E Railroad St",
    "sg:city":"Sandwich",
    "sg:classifiers":[
        {
            "category":"Personal",
            "subcategory":"Beauty Salon",
            "type":"Services"
        }
    ],
    "sg:phone":"+1 815 786 6959",
    "sg:postcode":"60548",
    "sg:province":"IL",
    "wof:name":"Bella Luciana Salon & Spa",
    "wof:placetype":"venue"
},
  "geometry": {"coordinates":[-88.621258,41.64506],"type":"Point"}
}