{
  "type": "Feature",
  "properties": {
    "addr:full":"15 N Washington Ave Batavia IL 60510",
    "addr:housenumber":"15",
    "addr:postcode":"60510",
    "addr:street":"N Washington Ave",
    "iso:country":"US",
    "sg:address":"15 N Washington Ave",
    "sg:city":"Batavia",
    "sg:classifiers":[
        {
            "category":"Organizations",
            "subcategory":"Religious Organization",
            "type":"Services"
        }
    ],
    "sg:phone":"+1 630 879 1467",
    "sg:postcode":"60510",
    "sg:province":"IL",
    "sg:tags":[
        "church"
    ],
    "wof:name":"First Baptist Church",
    "wof:placetype":"venue"
},
  "geometry": {"coordinates":[-88.304637,41.850981],"type":"Point"}
}