{
  "type": "Feature",
  "properties": {
    "iso:country":"US",
    "sg:address":"132 W Phillips Ferry Rd",
    "sg:city":"Bluffs",
    "sg:classifiers":[
        {
            "category":"Wholesale",
            "subcategory":"Farm Supplies",
            "type":"Manufacturing & Wholesale Goods"
        },
        {
            "category":"Farming",
            "subcategory":"Farm",
            "type":"Manufacturing & Wholesale Goods"
        }
    ],
    "sg:phone":"+1 217 754 3995",
    "sg:postcode":"62621",
    "sg:province":"IL",
    "sg:tags":[
        "grain"
    ],
    "wof:name":"Crusa Farm",
    "wof:placetype":"venue"
},
  "geometry": {"coordinates":[-90.560867,39.705074],"type":"Point"}
}