{
  "type": "Feature",
  "properties": {
    "iso:country":"US",
    "sg:address":"4400 W Springfield Ave",
    "sg:city":"Champaign",
    "sg:classifiers":[
        {
            "category":"Building & Trades",
            "subcategory":"Electrical",
            "type":"Services"
        }
    ],
    "sg:phone":"+1 217 359 2700",
    "sg:postcode":"61822",
    "sg:province":"IL",
    "sg:tags":[
        "electrician"
    ],
    "wof:name":"Bud Allens Electric Inc",
    "wof:placetype":"venue"
},
  "geometry": {"coordinates":[-88.318668,40.113731],"type":"Point"}
}