{
  "type": "Feature",
  "properties": {
    "iso:country":"US",
    "sg:address":"805 E Division St",
    "sg:city":"Coal City",
    "sg:classifiers":[
        {
            "category":"Autos & Motor Vehicles",
            "subcategory":"Automobile Sales",
            "type":"Retail Goods"
        }
    ],
    "sg:phone":"+1 815 634 0680",
    "sg:postcode":"60416",
    "sg:province":"IL",
    "sg:tags":[
        "car",
        "dealer"
    ],
    "wof:name":"Auto Tek Specialities",
    "wof:placetype":"venue"
},
  "geometry": {"coordinates":[-88.27356899999999,41.287935],"type":"Point"}
}