{
  "type": "Feature",
  "properties": {
    "iso:country":"US",
    "sg:address":"3417 Oak Park Ave",
    "sg:city":"Berwyn",
    "sg:classifiers":[
        {
            "category":"Professional",
            "subcategory":"Computer Services",
            "type":"Services"
        }
    ],
    "sg:phone":"+1 708 788 0191",
    "sg:postcode":"60402",
    "sg:province":"IL",
    "sg:tags":[
        "isp",
        "provider",
        "internet"
    ],
    "wof:name":"Hb Internet",
    "wof:placetype":"venue"
},
  "geometry": {"coordinates":[-87.79270200000001,41.829845],"type":"Point"}
}