{
  "type": "Feature",
  "properties": {
    "iso:country":"US",
    "sg:address":"1150 Spring Hill Mall",
    "sg:city":"West Dundee",
    "sg:classifiers":[
        {
            "category":"Health Services",
            "subcategory":"Dentist",
            "type":"Services"
        }
    ],
    "sg:phone":"+1 847 836 8400",
    "sg:postcode":"60118",
    "sg:province":"IL",
    "sg:website":"www.prodentalcare.com",
    "wof:name":"Shah Ketki DDS",
    "wof:placetype":"venue"
},
  "geometry": {"coordinates":[-88.289574,42.098632],"type":"Point"}
}