{
  "type": "Feature",
  "properties": {
    "iso:country":"US",
    "sg:address":"1578 Barclay Blvd",
    "sg:city":"Buffalo Grove",
    "sg:classifiers":[
        {
            "category":"Wholesale",
            "subcategory":"Chemicals & Plastics",
            "type":"Manufacturing & Wholesale Goods"
        }
    ],
    "sg:phone":"+1 847 243 2500",
    "sg:postcode":"60089",
    "sg:province":"IL",
    "sg:tags":[
        "import",
        "printing",
        "dye"
    ],
    "wof:name":"Mingzu Chemical USA Ltd",
    "wof:placetype":"venue"
},
  "geometry": {"coordinates":[-87.935494,42.180168],"type":"Point"}
}