{
  "type": "Feature",
  "properties": {
    "iso:country":"US",
    "sg:address":"201 N Constitution Dr",
    "sg:city":"Aurora",
    "sg:classifiers":[
        {
            "category":"Insurance",
            "subcategory":"Insurance Agent",
            "type":"Services"
        }
    ],
    "sg:phone":"+1 630 844 0099",
    "sg:postcode":"60506",
    "sg:province":"IL",
    "wof:name":"Dennis Kellen Insurance",
    "wof:placetype":"venue"
},
  "geometry": {"coordinates":[-88.37020699999999,41.76546],"type":"Point"}
}