{
  "type": "Feature",
  "properties": {
    "iso:country":"US",
    "sg:address":"169 Co Rd 1225 E",
    "sg:city":"Jewett",
    "sg:classifiers":[
        {
            "category":"Building & Trades",
            "subcategory":"Construction",
            "type":"Services"
        }
    ],
    "sg:phone":"+1 217 348 5365",
    "sg:postcode":"62436",
    "sg:province":"IL",
    "sg:tags":[
        "excavating",
        "contractor"
    ],
    "wof:name":"Doug Fidler Excavting",
    "wof:placetype":"venue"
},
  "geometry": {"coordinates":[-88.242428,39.196692],"type":"Point"}
}