{
  "type": "Feature",
  "properties": {
    "addr:full":"3601 W Devon Avenue Chicago IL 60659",
    "addr:housenumber":"3601",
    "addr:postcode":"60659",
    "addr:street":"W Devon Avenue",
    "iso:country":"US",
    "sg:address":"3601 W Devon Avenue",
    "sg:city":"Chicago",
    "sg:classifiers":[
        {
            "category":"Real Estate",
            "subcategory":"Real Estate Services",
            "type":"Services"
        }
    ],
    "sg:phone":"+1 773 279 9000",
    "sg:postcode":"60659",
    "sg:province":"IL",
    "wof:name":"Vranas & Chioros Realty Group",
    "wof:placetype":"venue"
},
  "geometry": {"coordinates":[-87.71900100000001,41.997126],"type":"Point"}
}