{
  "type": "Feature",
  "properties": {
    "addr:full":"3312 W Foster Chicago IL 60625",
    "addr:housenumber":"3312",
    "addr:postcode":"60625",
    "addr:street":"W Foster",
    "iso:country":"US",
    "sg:address":"3312 W Foster",
    "sg:city":"Chicago",
    "sg:classifiers":[
        {
            "category":"Restaurant",
            "type":"Food & Drink"
        }
    ],
    "sg:phone":"+1 773 267 6808",
    "sg:postcode":"60625",
    "sg:province":"IL",
    "sg:tags":[
        "thai",
        "japanese",
        "chinese"
    ],
    "sg:website":"bit.ly/dythmi",
    "wof:name":"Rice N Roll",
    "wof:placetype":"venue"
},
  "geometry": {"coordinates":[-87.711737,41.975975],"type":"Point"}
}