{
  "type": "Feature",
  "properties": {
    "iso:country":"US",
    "sg:address":"7260 W 159th St",
    "sg:city":"Orland Park",
    "sg:classifiers":[
        {
            "category":"Home & Garden",
            "subcategory":"Carpets & Floor Coverings",
            "type":"Retail Goods"
        }
    ],
    "sg:phone":"+1 708 263 2500",
    "sg:postcode":"60462",
    "sg:province":"IL",
    "sg:tags":[
        "dealer",
        "rug"
    ],
    "wof:name":"Carpetland USA Color Til",
    "wof:placetype":"venue"
},
  "geometry": {"coordinates":[-87.797151,41.602311],"type":"Point"}
}