{
  "type": "Feature",
  "properties": {
    "iso:country":"US",
    "sg:address":"13290 Wine Hill Rd",
    "sg:city":"Campbell Hill",
    "sg:classifiers":[
        {
            "category":"Farming",
            "subcategory":"Dairy Farm",
            "type":"Manufacturing & Wholesale Goods"
        }
    ],
    "sg:phone":"+1 618 965 9618",
    "sg:postcode":"62916",
    "sg:province":"IL",
    "wof:name":"Cedar Lane Farm",
    "wof:placetype":"venue"
},
  "geometry": {"coordinates":[-89.614119,37.934056],"type":"Point"}
}