{
  "type": "Feature",
  "properties": {
    "iso:country":"US",
    "sg:address":"2321 Westbrook Dr",
    "sg:city":"Rockford",
    "sg:classifiers":[
        {
            "category":"Utilities",
            "type":"Services"
        }
    ],
    "sg:phone":"+1 815 877 0158",
    "sg:postcode":"61107",
    "sg:province":"IL",
    "sg:tags":[
        "sanitary"
    ],
    "wof:name":"Rex A Sommer",
    "wof:placetype":"venue"
},
  "geometry": {"coordinates":[-89.04376600000001,42.292569],"type":"Point"}
}