{
  "type": "Feature",
  "properties": {
    "addr:full":"2005 N Western Ave Chicago IL 60647",
    "addr:housenumber":"2005",
    "addr:postcode":"60647",
    "addr:street":"N Western Ave",
    "iso:country":"US",
    "sg:address":"2005 N Western Ave",
    "sg:city":"Chicago",
    "sg:classifiers":[
        {
            "category":"Restaurant",
            "type":"Food & Drink"
        }
    ],
    "sg:phone":"+1   ",
    "sg:postcode":"60647",
    "sg:province":"IL",
    "sg:tags":[
        "eating"
    ],
    "wof:name":"Lazos Tacos",
    "wof:placetype":"venue"
},
  "geometry": {"coordinates":[-87.68735700000001,41.918223],"type":"Point"}
}