{
  "type": "Feature",
  "properties": {
    "iso:country":"US",
    "sg:address":"4517 W Ogden Ave",
    "sg:city":"Chicago",
    "sg:classifiers":[
        {
            "category":"Personal",
            "type":"Services"
        }
    ],
    "sg:phone":"+1 773 762 4249",
    "sg:postcode":"60623",
    "sg:province":"IL",
    "sg:tags":[
        "towing"
    ],
    "wof:name":"J C Towing",
    "wof:placetype":"venue"
},
  "geometry": {"coordinates":[-87.73768099999999,41.846525],"type":"Point"}
}