{
  "type": "Feature",
  "properties": {
    "iso:country":"US",
    "sg:address":"112 S Sangamon St",
    "sg:city":"Chicago",
    "sg:classifiers":[
        {
            "category":"Professional",
            "subcategory":"Lawyer & Legal Services",
            "type":"Services"
        }
    ],
    "sg:phone":"+1 312 432 0400",
    "sg:postcode":"60607",
    "sg:province":"IL",
    "wof:name":"Baranyk James Atty",
    "wof:placetype":"venue"
},
  "geometry": {"coordinates":[-87.650999,41.8803],"type":"Point"}
}