{
  "type": "Feature",
  "properties": {
    "addr:full":"250 W State Rte 173 Antioch IL 60002",
    "addr:housenumber":"250",
    "addr:postcode":"60002",
    "addr:street":"W State Rte 173",
    "iso:country":"US",
    "sg:address":"250 W State Rte 173",
    "sg:city":"Antioch",
    "sg:classifiers":[
        {
            "category":"Autos & Motor Vehicles",
            "subcategory":"Auto Supplies",
            "type":"Retail Goods"
        }
    ],
    "sg:phone":"+1 847 395 3660",
    "sg:postcode":"60002",
    "sg:province":"IL",
    "sg:tags":[
        "automobile",
        "parts"
    ],
    "wof:name":"NAPA Antioch Auto Parts",
    "wof:placetype":"venue"
},
  "geometry": {"coordinates":[-88.090993,42.470597],"type":"Point"}
}