{
  "type": "Feature",
  "properties": {
    "addr:full":"217 Division St Elgin IL 60120",
    "addr:housenumber":"217",
    "addr:postcode":"60120",
    "addr:street":"Division St",
    "iso:country":"US",
    "sg:address":"217 Division St",
    "sg:city":"Elgin",
    "sg:classifiers":[
        {
            "category":"Organizations",
            "subcategory":"Religious Organization",
            "type":"Services"
        }
    ],
    "sg:phone":"+1 847 931 0710",
    "sg:postcode":"60120",
    "sg:province":"IL",
    "sg:tags":[
        "church"
    ],
    "wof:name":"Elgin District Office",
    "wof:placetype":"venue"
},
  "geometry": {"coordinates":[-88.281408,42.038592],"type":"Point"}
}