{
  "type": "Feature",
  "properties": {
    "iso:country":"US",
    "sg:address":"115 E 600 North Rd",
    "sg:city":"Buckley",
    "sg:phone":"+1 217 394 2073",
    "sg:postcode":"60918",
    "sg:province":"IL",
    "sg:tags":[
        "farm",
        "corn",
        "soybean"
    ],
    "wof:name":"Mark R Maulding",
    "wof:placetype":"venue"
},
  "geometry": {"coordinates":[-88.088429,40.575247],"type":"Point"}
}