{
  "type": "Feature",
  "properties": {
    "addr:full":"1712 Seiler Rd Alton IL 62002",
    "addr:housenumber":"1712",
    "addr:postcode":"62002",
    "addr:street":"Seiler Rd",
    "iso:country":"US",
    "sg:address":"1712 Seiler Rd",
    "sg:city":"Alton",
    "sg:classifiers":[
        {
            "category":"Freight",
            "type":"Transportation"
        }
    ],
    "sg:phone":"+1 618 466 2816",
    "sg:postcode":"62002",
    "sg:province":"IL",
    "sg:tags":[
        "operator",
        "local",
        "trucking"
    ],
    "wof:name":"Bommershine Trucking",
    "wof:placetype":"venue"
},
  "geometry": {"coordinates":[-90.13899600000001,38.966672],"type":"Point"}
}