{
  "type": "Feature",
  "properties": {
    "addr:full":"3036 W. Chicago Chicago IL 60686",
    "addr:housenumber":"3036",
    "addr:postcode":"60686",
    "addr:street":"W. Chicago",
    "iso:country":"US",
    "sg:address":"3036 W. Chicago",
    "sg:city":"Chicago",
    "sg:classifiers":[
        {
            "category":"Arts & Performance",
            "subcategory":"Arts Center",
            "type":"Entertainment"
        }
    ],
    "sg:postcode":"60686",
    "sg:province":"IL",
    "sg:tags":[
        "performing"
    ],
    "wof:name":"Elsewhere Theater",
    "wof:placetype":"venue"
},
  "geometry": {"coordinates":[-87.702877,41.895799],"type":"Point"}
}