{
  "type": "Feature",
  "properties": {
    "iso:country":"US",
    "sg:address":"3163 Partridge Ln",
    "sg:city":"Belvidere",
    "sg:classifiers":[
        {
            "category":"Shopping",
            "subcategory":"Bicycles & Sporting Goods",
            "type":"Retail Goods"
        }
    ],
    "sg:phone":"+1   ",
    "sg:postcode":"61008",
    "sg:province":"IL",
    "wof:name":"Hunters Edge Gun Shop",
    "wof:placetype":"venue"
},
  "geometry": {"coordinates":[-88.87710199999999,42.313418],"type":"Point"}
}