{
  "type": "Feature",
  "properties": {
    "iso:country":"US",
    "sg:address":"156 N Jefferson St # 300",
    "sg:city":"Chicago",
    "sg:classifiers":[
        {
            "category":"Home & Garden",
            "subcategory":"Kitchen Supply",
            "type":"Retail Goods"
        }
    ],
    "sg:phone":"+1 312 432 6200",
    "sg:postcode":"60661",
    "sg:province":"IL",
    "sg:tags":[
        "utensil",
        "cookware"
    ],
    "wof:name":"Global Contract Manufacturing",
    "wof:placetype":"venue"
},
  "geometry": {"coordinates":[-87.642725,41.884589],"type":"Point"}
}