{
  "type": "Feature",
  "properties": {
    "iso:country":"US",
    "sg:address":"273 N Park Blvd",
    "sg:city":"Glen Ellyn",
    "sg:classifiers":[
        {
            "category":"Professional",
            "subcategory":"Management & Consulting",
            "type":"Services"
        }
    ],
    "sg:phone":"+1 630 469 3180",
    "sg:postcode":"60137",
    "sg:province":"IL",
    "sg:tags":[
        "business"
    ],
    "wof:name":"Liberty Consulting",
    "wof:placetype":"venue"
},
  "geometry": {"coordinates":[-88.060819,41.869411],"type":"Point"}
}