{
  "type": "Feature",
  "properties": {
    "iso:country":"US",
    "sg:address":"15027 Woodlawn Ave",
    "sg:city":"Dolton",
    "sg:classifiers":[
        {
            "category":"Restaurant",
            "type":"Food & Drink"
        }
    ],
    "sg:phone":"+1 708 841 7278",
    "sg:postcode":"60419",
    "sg:province":"IL",
    "sg:tags":[
        "asian",
        "chinese",
        "pan"
    ],
    "wof:name":"New Star Chop Suey",
    "wof:placetype":"venue"
},
  "geometry": {"coordinates":[-87.587898,41.621899],"type":"Point"}
}