{
  "type": "Feature",
  "properties": {
    "addr:full":"26 Co Rd 1300 E Pesotum IL 61863",
    "addr:housenumber":"26;1300 e",
    "addr:postcode":"61863",
    "addr:street":"Co Rd",
    "iso:country":"US",
    "sg:address":"26 Co Rd 1300 E",
    "sg:city":"Pesotum",
    "sg:phone":"+1 217 867 2277",
    "sg:postcode":"61863",
    "sg:province":"IL",
    "sg:tags":[
        "farm",
        "corn",
        "soybean"
    ],
    "wof:name":"Dennis Reifsteck",
    "wof:placetype":"venue"
},
  "geometry": {"coordinates":[-88.21721100000001,39.885493],"type":"Point"}
}