{
  "type": "Feature",
  "properties": {
    "addr:full":"163 E Chicago St Elgin IL 60120",
    "addr:housenumber":"163",
    "addr:postcode":"60120",
    "addr:street":"E Chicago St",
    "iso:country":"US",
    "sg:address":"163 E Chicago St",
    "sg:city":"Elgin",
    "sg:classifiers":[
        {
            "category":"Wholesale",
            "subcategory":"Furniture",
            "type":"Manufacturing & Wholesale Goods"
        }
    ],
    "sg:phone":"+1 847 697 6664",
    "sg:postcode":"60120",
    "sg:province":"IL",
    "wof:name":"Mattresses & Furn Unlimited",
    "wof:placetype":"venue"
},
  "geometry": {"coordinates":[-88.283451,42.03715],"type":"Point"}
}