{
  "type": "Feature",
  "properties": {
    "iso:country":"US",
    "sg:address":"1211 Griffith Rd",
    "sg:city":"Lake Forest",
    "sg:classifiers":[
        {
            "category":"Wholesale",
            "subcategory":"Hardware",
            "type":"Manufacturing & Wholesale Goods"
        }
    ],
    "sg:phone":"+1 847 482 1323",
    "sg:postcode":"60045",
    "sg:province":"IL",
    "sg:tags":[
        "beer",
        "cooling",
        "dispensing"
    ],
    "wof:name":"William Schilling & Assoc LTD",
    "wof:placetype":"venue"
},
  "geometry": {"coordinates":[-87.840594,42.261385],"type":"Point"}
}