{
  "type": "Feature",
  "properties": {
    "iso:country":"US",
    "sg:address":"5257 Swanson Rd",
    "sg:city":"Roscoe",
    "sg:classifiers":[
        {
            "category":"Health Services",
            "subcategory":"Chiropractor",
            "type":"Services"
        }
    ],
    "sg:phone":"+1 815 654 8600",
    "sg:postcode":"61073",
    "sg:province":"IL",
    "wof:name":"Intergrative Rehabilitation",
    "wof:placetype":"venue"
},
  "geometry": {"coordinates":[-89.012934,42.391802],"type":"Point"}
}