{
  "type": "Feature",
  "properties": {
    "iso:country":"US",
    "sg:address":"4019 N Mozart St",
    "sg:city":"Chicago",
    "sg:classifiers":[
        {
            "category":"Building & Trades",
            "subcategory":"Plumbing",
            "type":"Services"
        }
    ],
    "sg:phone":"+1 773 583 5468",
    "sg:postcode":"60618",
    "sg:province":"IL",
    "sg:tags":[
        "plumber",
        "industrial",
        "contractors-commercial"
    ],
    "wof:name":"Boehm Plumbing",
    "wof:placetype":"venue"
},
  "geometry": {"coordinates":[-87.699433,41.954295],"type":"Point"}
}