{
  "type": "Feature",
  "properties": {
    "addr:full":"7446 S Kingston Ave Chicago IL 60649",
    "addr:housenumber":"7446",
    "addr:postcode":"60649",
    "addr:street":"S Kingston Ave",
    "iso:country":"US",
    "sg:address":"7446 S Kingston Ave",
    "sg:city":"Chicago",
    "sg:classifiers":[
        {
            "category":"Banks & Credit Unions",
            "subcategory":"Investment Brokerage",
            "type":"Services"
        }
    ],
    "sg:phone":"+1 773 978 4406",
    "sg:postcode":"60649",
    "sg:province":"IL",
    "wof:name":"Steel Investments Inc",
    "wof:placetype":"venue"
},
  "geometry": {"coordinates":[-87.563227,41.759588],"type":"Point"}
}