{
  "type": "Feature",
  "properties": {
    "iso:country":"US",
    "sg:address":"1000 Pelican St",
    "sg:city":"Effingham",
    "sg:classifiers":[
        {
            "category":"Professional",
            "subcategory":"Business Services",
            "type":"Services"
        }
    ],
    "sg:phone":"+1 217 342 6458",
    "sg:postcode":"62401",
    "sg:province":"IL",
    "sg:tags":[
        "custom",
        "monogramming"
    ],
    "wof:name":"Moonlight Monogram",
    "wof:placetype":"venue"
},
  "geometry": {"coordinates":[-88.547889,39.132282],"type":"Point"}
}