{
  "type": "Feature",
  "properties": {
    "addr:full":"37W080 Hopps Rd Elgin IL 60124",
    "addr:housenumber":"37w080",
    "addr:postcode":"60124",
    "addr:street":"Hopps Rd",
    "iso:country":"US",
    "sg:address":"37W080 Hopps Rd",
    "sg:city":"Elgin",
    "sg:classifiers":[
        {
            "category":"Education",
            "subcategory":"Preschool",
            "type":"Public Place"
        },
        {
            "category":"Education",
            "subcategory":"School",
            "type":"Public Place"
        }
    ],
    "sg:phone":"+1 847 841 7532",
    "sg:postcode":"60124",
    "sg:province":"IL",
    "sg:tags":[
        "kindergarten"
    ],
    "sg:website":"http://www.dvacademy.org",
    "wof:name":"Da Vinci Academy",
    "wof:placetype":"venue"
},
  "geometry": {"coordinates":[-88.34348300000001,41.995762],"type":"Point"}
}