{
  "type": "Feature",
  "properties": {
    "addr:full":"10495 E 125th St Colchester IL 62326",
    "addr:housenumber":"10495",
    "addr:postcode":"62326",
    "addr:street":"E 125Th St",
    "iso:country":"US",
    "sg:address":"10495 E 125th St",
    "sg:city":"Colchester",
    "sg:phone":"+1 309 776 4276",
    "sg:postcode":"62326",
    "sg:province":"IL",
    "sg:tags":[
        "farm",
        "corn",
        "soybean"
    ],
    "wof:name":"Mark Beckner",
    "wof:placetype":"venue"
},
  "geometry": {"coordinates":[-90.88296699999999,40.439687],"type":"Point"}
}