{
  "type": "Feature",
  "properties": {
    "iso:country":"US",
    "sg:address":"1100 1st Ave",
    "sg:city":"Silvis",
    "sg:classifiers":[
        {
            "category":"Banks & Credit Unions",
            "subcategory":"Bank",
            "type":"Services"
        },
        {
            "category":"Banks & Credit Unions",
            "subcategory":"Financial Services",
            "type":"Services"
        }
    ],
    "sg:phone":"+1 309 752 1200",
    "sg:postcode":"61282",
    "sg:province":"IL",
    "sg:tags":[
        "broker",
        "mortgage"
    ],
    "wof:name":"Blackhawk State Bank",
    "wof:placetype":"venue"
},
  "geometry": {"coordinates":[-90.413101,41.5117],"type":"Point"}
}