{
  "type": "Feature",
  "properties": {
    "iso:country":"US",
    "sg:address":"506 G H Baker Dr",
    "sg:city":"Urbana",
    "sg:classifiers":[
        {
            "category":"Building & Trades",
            "subcategory":"Cleaning & Sanitation",
            "type":"Services"
        }
    ],
    "sg:phone":"+1 217 344 9074",
    "sg:postcode":"61801",
    "sg:province":"IL",
    "sg:tags":[
        "home",
        "carpet"
    ],
    "wof:name":"Campbell & Associates",
    "wof:placetype":"venue"
},
  "geometry": {"coordinates":[-88.202522,40.132402],"type":"Point"}
}