{
  "type": "Feature",
  "properties": {
    "iso:country":"US",
    "sg:address":"6969 Ogden Ave Ste 4",
    "sg:city":"Berwyn",
    "sg:classifiers":[
        {
            "category":"Restaurant",
            "type":"Food & Drink"
        }
    ],
    "sg:phone":"+1 708 788 1100",
    "sg:postcode":"60402",
    "sg:province":"IL",
    "sg:tags":[
        "pizza"
    ],
    "wof:name":"Nonno's Pizza",
    "wof:placetype":"venue"
},
  "geometry": {"coordinates":[-87.796997,41.8256],"type":"Point"}
}