{
  "type": "Feature",
  "properties": {
    "iso:country":"US",
    "sg:address":"24112 N Rand Rd",
    "sg:city":"Lake Zurich",
    "sg:classifiers":[
        {
            "category":"Autos & Motor Vehicles",
            "subcategory":"Fuel & Gas Station",
            "type":"Retail Goods"
        }
    ],
    "sg:phone":"+1   ",
    "sg:postcode":"60047",
    "sg:province":"IL",
    "sg:tags":[
        "station",
        "gasoline"
    ],
    "wof:name":"Sweeney Food Works",
    "wof:placetype":"venue"
},
  "geometry": {"coordinates":[-88.11718999999999,42.241532],"type":"Point"}
}