{
  "type": "Feature",
  "properties": {
    "iso:country":"US",
    "sg:address":"101 E Main St",
    "sg:city":"Rockton",
    "sg:classifiers":[
        {
            "category":"Education",
            "subcategory":"Library",
            "type":"Public Place"
        }
    ],
    "sg:phone":"+1 815 624 7511",
    "sg:postcode":"61072",
    "sg:province":"IL",
    "sg:website":"www.talcottfreelibrary.com",
    "wof:name":"Talcott Free Library",
    "wof:placetype":"venue"
},
  "geometry": {"coordinates":[-89.071124,42.452512],"type":"Point"}
}