{
  "type": "Feature",
  "properties": {
    "addr:full":"1000 W 35th St Chicago IL 60609",
    "addr:housenumber":"1000",
    "addr:postcode":"60609",
    "addr:street":"W 35Th St",
    "iso:country":"US",
    "sg:address":"1000 W 35th St",
    "sg:city":"Chicago",
    "sg:classifiers":[
        {
            "category":"Food & Beverages",
            "subcategory":"Bakery",
            "type":"Retail Goods"
        }
    ],
    "sg:phone":"+1 773 579 1995",
    "sg:postcode":"60609",
    "sg:province":"IL",
    "sg:tags":[
        "sandwich"
    ],
    "wof:name":"Mr. Submarine",
    "wof:placetype":"venue"
},
  "geometry": {"coordinates":[-87.650972,41.830847],"type":"Point"}
}