{
  "type": "Feature",
  "properties": {
    "addr:full":"2355 S Arlington Heights Rd Arlington Hts IL 60005",
    "addr:housenumber":"2355",
    "addr:postcode":"60005",
    "addr:street":"S Arlington Heights Rd",
    "iso:country":"US",
    "sg:address":"2355 S Arlington Heights Rd",
    "sg:city":"Arlington Hts",
    "sg:classifiers":[
        {
            "category":"Insurance",
            "subcategory":"Insurance Agent",
            "type":"Services"
        }
    ],
    "sg:phone":"+1 847 437 9966",
    "sg:postcode":"60005",
    "sg:province":"IL",
    "wof:name":"Allstate Insurance",
    "wof:placetype":"venue"
},
  "geometry": {"coordinates":[-87.983463,42.04225],"type":"Point"}
}