{
  "type": "Feature",
  "properties": {
    "addr:full":"424 S High St Belleville IL 62220",
    "addr:housenumber":"424",
    "addr:postcode":"62220",
    "addr:street":"S High St",
    "iso:country":"US",
    "sg:address":"424 S High St",
    "sg:city":"Belleville",
    "sg:classifiers":[
        {
            "category":"Restaurant",
            "type":"Food & Drink"
        }
    ],
    "sg:phone":"+1   ",
    "sg:postcode":"62220",
    "sg:province":"IL",
    "sg:tags":[
        "eating"
    ],
    "wof:name":"American Eagle Pizza Inc",
    "wof:placetype":"venue"
},
  "geometry": {"coordinates":[-89.98278000000001,38.509038],"type":"Point"}
}