{
  "type": "Feature",
  "properties": {
    "addr:full":"225 S Harvard Ave Villa Park IL 60181",
    "addr:housenumber":"225",
    "addr:postcode":"60181",
    "addr:street":"S Harvard Ave",
    "iso:country":"US",
    "sg:address":"225 S Harvard Ave",
    "sg:city":"Villa Park",
    "sg:classifiers":[
        {
            "category":"Education",
            "subcategory":"School",
            "type":"Public Place"
        }
    ],
    "sg:phone":"+1 630 530 6255",
    "sg:postcode":"60181",
    "sg:province":"IL",
    "sg:tags":[
        "elementary"
    ],
    "wof:name":"Ardmore Elementary School",
    "wof:placetype":"venue"
},
  "geometry": {"coordinates":[-87.98386499999999,41.886972],"type":"Point"}
}