{
  "type": "Feature",
  "properties": {
    "addr:full":"12 W Schaumburg Rd Schaumburg IL 60194",
    "addr:housenumber":"12",
    "addr:postcode":"60194",
    "addr:street":"W Schaumburg Rd",
    "iso:country":"US",
    "sg:address":"12 W Schaumburg Rd",
    "sg:city":"Schaumburg",
    "sg:classifiers":[
        {
            "category":"Health Services",
            "subcategory":"Doctor",
            "type":"Services"
        }
    ],
    "sg:phone":"+1 847 519 1711",
    "sg:postcode":"60194",
    "sg:province":"IL",
    "wof:name":"Schoolhouse Square Dntl Off PC",
    "wof:placetype":"venue"
},
  "geometry": {"coordinates":[-88.082437,42.027282],"type":"Point"}
}