{
  "type": "Feature",
  "properties": {
    "iso:country":"US",
    "sg:address":"2126 Pine Rd",
    "sg:city":"Homewood",
    "sg:classifiers":[
        {
            "category":"Real Estate",
            "subcategory":"Developer",
            "type":"Services"
        }
    ],
    "sg:phone":"+1 708 957 8518",
    "sg:postcode":"60430",
    "sg:province":"IL",
    "wof:name":"Jlg Development Inc",
    "wof:placetype":"venue"
},
  "geometry": {"coordinates":[-87.66846,41.56462],"type":"Point"}
}