{
  "type": "Feature",
  "properties": {
    "iso:country":"US",
    "sg:address":"202 Oscar St",
    "sg:city":"Lincoln",
    "sg:classifiers":[
        {
            "category":"Shopping",
            "subcategory":"Hobbies, Toys, & Games",
            "type":"Retail Goods"
        }
    ],
    "sg:phone":"+1 217 735 2766",
    "sg:postcode":"62656",
    "sg:province":"IL",
    "sg:tags":[
        "craft"
    ],
    "wof:name":"Harvest Moon",
    "wof:placetype":"venue"
},
  "geometry": {"coordinates":[-89.373625,40.142913],"type":"Point"}
}