{
  "type": "Feature",
  "properties": {
    "iso:country":"US",
    "sg:address":"1530 Landmeier Rd",
    "sg:city":"Elk Grove Vlg",
    "sg:classifiers":[
        {
            "category":"Manufacturing",
            "subcategory":"Glass & Minerals",
            "type":"Manufacturing & Wholesale Goods"
        }
    ],
    "sg:phone":"+1 847 593 0109",
    "sg:postcode":"60007",
    "sg:province":"IL",
    "sg:tags":[
        "plate",
        "window",
        "automobile"
    ],
    "wof:name":"Active Glass Inc",
    "wof:placetype":"venue"
},
  "geometry": {"coordinates":[-87.966248,42.011446],"type":"Point"}
}