{
  "type": "Feature",
  "properties": {
    "addr:full":"1530 Landmeier Rd Elk Grove Vlg IL 60007",
    "addr:housenumber":"1530",
    "addr:postcode":"60007",
    "addr:street":"Landmeier Rd",
    "iso:country":"US",
    "sg:address":"1530 Landmeier Rd",
    "sg:city":"Elk Grove Vlg",
    "sg:classifiers":[
        {
            "category":"Manufacturing",
            "subcategory":"Glass & Minerals",
            "type":"Manufacturing & Wholesale Goods"
        }
    ],
    "sg:phone":"+1 847 593 0109",
    "sg:postcode":"60007",
    "sg:province":"IL",
    "sg:tags":[
        "plate",
        "window",
        "automobile"
    ],
    "wof:name":"Active Glass Inc",
    "wof:placetype":"venue"
},
  "geometry": {"coordinates":[-87.96624799999999,42.011446],"type":"Point"}
}