{
  "type": "Feature",
  "properties": {
    "addr:full":"6703 N Olmsted Avenue Chicago IL 60631",
    "addr:housenumber":"6703",
    "addr:postcode":"60631",
    "addr:street":"N Olmsted Avenue",
    "iso:country":"US",
    "sg:address":"6703 N Olmsted Avenue",
    "sg:city":"Chicago",
    "sg:classifiers":[
        {
            "category":"Retail",
            "subcategory":"Laundry & Dry Cleaning",
            "type":"Services"
        }
    ],
    "sg:phone":"+1 773 763 5083",
    "sg:postcode":"60631",
    "sg:province":"IL",
    "wof:name":"Burmans Cleaners",
    "wof:placetype":"venue"
},
  "geometry": {"coordinates":[-87.817206,42.002026],"type":"Point"}
}