{
  "type": "Feature",
  "properties": {
    "addr:full":"3019 N Clark St Chicago IL 60657",
    "addr:housenumber":"3019",
    "addr:postcode":"60657",
    "addr:street":"N Clark St",
    "iso:country":"US",
    "sg:address":"3019 N Clark St",
    "sg:city":"Chicago",
    "sg:classifiers":[
        {
            "category":"Utilities",
            "subcategory":"Telephone",
            "type":"Services"
        }
    ],
    "sg:phone":"+1 773 525 0381",
    "sg:postcode":"60657",
    "sg:province":"IL",
    "sg:tags":[
        "company"
    ],
    "wof:name":"Cingular Wireless",
    "wof:placetype":"venue"
},
  "geometry": {"coordinates":[-87.64896299999999,41.937837],"type":"Point"}
}