{
  "type": "Feature",
  "properties": {
    "iso:country":"US",
    "sg:address":"1130 S Wabash Ste 404",
    "sg:city":"Chicago",
    "sg:classifiers":[
        {
            "category":"Personal",
            "subcategory":"Beauty Salon",
            "type":"Services"
        },
        {
            "category":"Personal",
            "subcategory":"Day Spa",
            "type":"Services"
        }
    ],
    "sg:phone":"+1 312 446 0588",
    "sg:postcode":"60605",
    "sg:province":"IL",
    "sg:tags":[
        "hair"
    ],
    "wof:name":"All Tangled Up Salon and Spa",
    "wof:placetype":"venue"
},
  "geometry": {"coordinates":[-87.62635400000001,41.868383],"type":"Point"}
}