{
  "type": "Feature",
  "properties": {
    "iso:country":"US",
    "sg:address":"204 W Gallatin St",
    "sg:city":"Vandalia",
    "sg:classifiers":[
        {
            "category":"Bars & Pubs",
            "type":"Food & Drink"
        }
    ],
    "sg:phone":"+1   ",
    "sg:postcode":"62471",
    "sg:province":"IL",
    "sg:tags":[
        "drinking"
    ],
    "wof:name":"Johns Red Wood Inn",
    "wof:placetype":"venue"
},
  "geometry": {"coordinates":[-89.093245,38.960592],"type":"Point"}
}