{
  "type": "Feature",
  "properties": {
    "addr:full":"1719 13th Ave Rockford IL 61104",
    "addr:housenumber":"1719",
    "addr:postcode":"61104",
    "addr:street":"13Th Ave",
    "iso:country":"US",
    "sg:address":"1719 13th Ave",
    "sg:city":"Rockford",
    "sg:classifiers":[
        {
            "category":"Retail",
            "subcategory":"Repair Shop",
            "type":"Services"
        }
    ],
    "sg:phone":"+1 815 226 9588",
    "sg:postcode":"61104",
    "sg:province":"IL",
    "wof:name":"Hansons Mtro Piano Tuning Repr",
    "wof:placetype":"venue"
},
  "geometry": {"coordinates":[-89.068575,42.253373],"type":"Point"}
}