{
  "type": "Feature",
  "properties": {
    "iso:country":"US",
    "sg:address":"716 S Bench St",
    "sg:city":"Galena",
    "sg:classifiers":[
        {
            "category":"Communications",
            "subcategory":"Newspaper",
            "type":"Services"
        },
        {
            "category":"Wholesale",
            "subcategory":"Books, Periodicals, & Newspapers",
            "type":"Manufacturing & Wholesale Goods"
        }
    ],
    "sg:phone":"+1 815 777 0019",
    "sg:postcode":"61036",
    "sg:province":"IL",
    "sg:tags":[
        "news",
        "publishers-periodical",
        "dealers-wholesale"
    ],
    "wof:name":"Gazette",
    "wof:placetype":"venue"
},
  "geometry": {"coordinates":[-90.432266,42.409565],"type":"Point"}
}