{
  "type": "Feature",
  "properties": {
    "iso:country":"US",
    "sg:address":"202 W North Ave",
    "sg:city":"Lombard",
    "sg:classifiers":[
        {
            "category":"Manufacturing",
            "subcategory":"Tools & Machinery",
            "type":"Manufacturing & Wholesale Goods"
        },
        {
            "category":"Wholesale",
            "subcategory":"Machinery & Supplies",
            "type":"Manufacturing & Wholesale Goods"
        },
        {
            "category":"Home & Garden",
            "subcategory":"Building Materials",
            "type":"Retail Goods"
        }
    ],
    "sg:phone":"+1 630 495 2200",
    "sg:postcode":"60148",
    "sg:province":"IL",
    "sg:tags":[
        "equipment",
        "fasteners-industrial",
        "industrial"
    ],
    "sg:website":"http://www.fastenal.com",
    "wof:name":"Fastenal Company",
    "wof:placetype":"venue"
},
  "geometry": {"coordinates":[-88.022453,41.904726],"type":"Point"}
}