{
  "type": "Feature",
  "properties": {
    "iso:country":"US",
    "sg:address":"16678 W Aptakisic Rd",
    "sg:city":"Lincolnshire",
    "sg:phone":"+1 847 634 3291",
    "sg:postcode":"60069",
    "sg:province":"IL",
    "sg:tags":[
        "farm",
        "florist",
        "corn",
        "soybean"
    ],
    "wof:name":"Didier Vegetable Farm Inc",
    "wof:placetype":"venue"
},
  "geometry": {"coordinates":[-87.95795,42.182733],"type":"Point"}
}