{
  "type": "Feature",
  "properties": {
    "iso:country":"US",
    "sg:address":"1929 Sherman Ave",
    "sg:city":"Evanston",
    "sg:classifiers":[
        {
            "category":"Real Estate",
            "subcategory":"Real Estate Operator",
            "type":"Services"
        }
    ],
    "sg:phone":"+1 847 328 6083",
    "sg:postcode":"60201",
    "sg:province":"IL",
    "sg:tags":[
        "property",
        "lessor"
    ],
    "wof:name":"Eleanor Firstenberger",
    "wof:placetype":"venue"
},
  "geometry": {"coordinates":[-87.681645,42.053369],"type":"Point"}
}