{
  "type": "Feature",
  "properties": {
    "addr:full":"5705 N Lincoln Ave Chicago IL 60659",
    "addr:housenumber":"5705",
    "addr:postcode":"60659",
    "addr:street":"N Lincoln Ave",
    "iso:country":"US",
    "sg:address":"5705 N Lincoln Ave",
    "sg:city":"Chicago",
    "sg:classifiers":[
        {
            "category":"Organizations",
            "subcategory":"Non-profit Organization",
            "type":"Services"
        }
    ],
    "sg:phone":"+1 773 271 1212",
    "sg:postcode":"60659",
    "sg:province":"IL",
    "sg:tags":[
        "service/non-profit",
        "community"
    ],
    "wof:name":"Goldie's Place",
    "wof:placetype":"venue"
},
  "geometry": {"coordinates":[-87.698469,41.985127],"type":"Point"}
}