{
  "type": "Feature",
  "properties": {
    "addr:full":"111 N Northampton Dr Geneva IL 60134",
    "addr:housenumber":"111",
    "addr:postcode":"60134",
    "addr:street":"N Northampton Dr",
    "iso:country":"US",
    "sg:address":"111 N Northampton Dr",
    "sg:city":"Geneva",
    "sg:classifiers":[
        {
            "category":"Professional",
            "subcategory":"Business Services",
            "type":"Services"
        }
    ],
    "sg:phone":"+1 630 208 5964",
    "sg:postcode":"60134",
    "sg:province":"IL",
    "wof:name":"Great Lakes Indus Solution",
    "wof:placetype":"venue"
},
  "geometry": {"coordinates":[-88.330202,41.888423],"type":"Point"}
}