{
  "type": "Feature",
  "properties": {
    "addr:full":"129 Welty Ave Rockford IL 61107",
    "addr:housenumber":"129",
    "addr:postcode":"61107",
    "addr:street":"Welty Ave",
    "iso:country":"US",
    "sg:address":"129 Welty Ave",
    "sg:city":"Rockford",
    "sg:classifiers":[
        {
            "category":"Shopping",
            "type":"Retail Goods"
        }
    ],
    "sg:phone":"+1   ",
    "sg:postcode":"61107",
    "sg:province":"IL",
    "sg:tags":[
        "merchandise"
    ],
    "wof:name":"Thou Art",
    "wof:placetype":"venue"
},
  "geometry": {"coordinates":[-89.056915,42.267222],"type":"Point"}
}