{
  "type": "Feature",
  "properties": {
    "iso:country":"US",
    "sg:address":"225 S Eden Rd",
    "sg:city":"Hanna City",
    "sg:phone":"+1 309 565 4526",
    "sg:postcode":"61536",
    "sg:province":"IL",
    "sg:tags":[
        "farm",
        "grain",
        "cash"
    ],
    "wof:name":"Eden Farm",
    "wof:placetype":"venue"
},
  "geometry": {"coordinates":[-89.83323900000001,40.688901],"type":"Point"}
}