{
  "type": "Feature",
  "properties": {
    "iso:country":"US",
    "sg:address":"1800 South St",
    "sg:city":"Geneva",
    "sg:classifiers":[
        {
            "category":"Government",
            "subcategory":"Fire Station",
            "type":"Public Place"
        }
    ],
    "sg:phone":"+1 630 232 9555",
    "sg:postcode":"60134",
    "sg:province":"IL",
    "sg:tags":[
        "relief",
        "disaster",
        "recovery"
    ],
    "wof:name":"Genva Emg Service And Disaster Agency",
    "wof:placetype":"venue"
},
  "geometry": {"coordinates":[-88.32740800000001,41.883389],"type":"Point"}
}