{
  "type": "Feature",
  "properties": {
    "iso:country":"US",
    "sg:address":"9836 S Western Ave",
    "sg:city":"Evergreen Park",
    "sg:classifiers":[
        {
            "category":"Food & Beverages",
            "subcategory":"Bakery",
            "type":"Retail Goods"
        }
    ],
    "sg:phone":"+1   ",
    "sg:postcode":"60805",
    "sg:province":"IL",
    "wof:name":"Great American Bagel Inc",
    "wof:placetype":"venue"
},
  "geometry": {"coordinates":[-87.68195,41.714808],"type":"Point"}
}