{
  "type": "Feature",
  "properties": {
    "iso:country":"US",
    "sg:address":"1906 S State St",
    "sg:city":"Chicago",
    "sg:phone":"+1 312 567 9898",
    "sg:postcode":"60616",
    "sg:province":"IL",
    "sg:website":"http://www.opartthai.com",
    "wof:name":"Opart Thai House",
    "wof:placetype":"venue"
},
  "geometry": {"coordinates":[-87.62716500000001,41.856485],"type":"Point"}
}