{
  "type": "Feature",
  "properties": {
    "iso:country":"US",
    "sg:address":"1484 W Farragut Ave",
    "sg:city":"Chicago",
    "sg:classifiers":[
        {
            "category":"Professional",
            "subcategory":"Employment Agencies",
            "type":"Services"
        }
    ],
    "sg:phone":"+1 773 506 0607",
    "sg:postcode":"60640",
    "sg:province":"IL",
    "sg:tags":[
        "help",
        "supply"
    ],
    "sg:website":"www.birthwaysinc.com",
    "wof:name":"Birthways Inc",
    "wof:placetype":"venue"
},
  "geometry": {"coordinates":[-87.668333,41.97718],"type":"Point"}
}