{
  "type": "Feature",
  "properties": {
    "iso:country":"US",
    "sg:address":"4848 N Winthrop Ave",
    "sg:city":"Chicago",
    "sg:classifiers":[
        {
            "category":"Taxi",
            "type":"Transportation"
        }
    ],
    "sg:phone":"+1 773 989 7855",
    "sg:postcode":"60640",
    "sg:province":"IL",
    "sg:tags":[
        "taxicab"
    ],
    "wof:name":"908 Corp",
    "wof:placetype":"venue"
},
  "geometry": {"coordinates":[-87.657732,41.970318],"type":"Point"}
}