{
  "type": "Feature",
  "properties": {
    "iso:country":"US",
    "sg:address":"3691 Blackhawk Rd",
    "sg:city":"Rockford",
    "sg:classifiers":[
        {
            "category":"Building & Trades",
            "subcategory":"Electrical",
            "type":"Services"
        }
    ],
    "sg:phone":"+1 815 874 2999",
    "sg:postcode":"61109",
    "sg:province":"IL",
    "sg:tags":[
        "electric",
        "contractor"
    ],
    "wof:name":"David Waldner Electric Co",
    "wof:placetype":"venue"
},
  "geometry": {"coordinates":[-89.04333200000001,42.194557],"type":"Point"}
}