{
  "type": "Feature",
  "properties": {
    "iso:country":"US",
    "sg:address":"4108 W Lillian St",
    "sg:city":"Mc Henry",
    "sg:classifiers":[
        {
            "category":"Real Estate",
            "subcategory":"Real Estate Operator",
            "type":"Services"
        }
    ],
    "sg:phone":"+1 815 385 7368",
    "sg:postcode":"60050",
    "sg:province":"IL",
    "sg:tags":[
        "building",
        "apartment"
    ],
    "wof:name":"Cunat Inc",
    "wof:placetype":"venue"
},
  "geometry": {"coordinates":[-88.278499,42.33607],"type":"Point"}
}