{
  "type": "Feature",
  "properties": {
    "iso:country":"US",
    "sg:address":"4849 W Fullerton Ave",
    "sg:city":"Chicago",
    "sg:classifiers":[
        {
            "category":"Health Services",
            "subcategory":"Doctor",
            "type":"Services"
        },
        {
            "category":"Health Services",
            "subcategory":"Hospital",
            "type":"Services"
        }
    ],
    "sg:phone":"+1 773 237 8000",
    "sg:postcode":"60639",
    "sg:province":"IL",
    "wof:name":"Resurrection Medical Center",
    "wof:placetype":"venue"
},
  "geometry": {"coordinates":[-87.74839799999999,41.924],"type":"Point"}
}