{
  "type": "Feature",
  "properties": {
    "iso:country":"US",
    "sg:address":"2451 Landmeier Rd",
    "sg:city":"Elk Grove Village",
    "sg:classifiers":[
        {
            "category":"Autos & Motor Vehicles",
            "subcategory":"Auto Supplies",
            "type":"Retail Goods"
        }
    ],
    "sg:phone":"+1   ",
    "sg:postcode":"60007",
    "sg:province":"IL",
    "wof:name":"Wingfoot Coml Tire Systems LLC",
    "wof:placetype":"venue"
},
  "geometry": {"coordinates":[-87.943085,42.011302],"type":"Point"}
}