{
  "type": "Feature",
  "properties": {
    "addr:full":"5 Meadowview Center Kankakee IL 60901",
    "addr:housenumber":"5",
    "addr:postcode":"60901",
    "addr:street":"Meadowview Center",
    "iso:country":"US",
    "sg:address":"5 Meadowview Center",
    "sg:city":"Kankakee",
    "sg:classifiers":[
        {
            "category":"Insurance",
            "subcategory":"Insurance Agent",
            "type":"Services"
        }
    ],
    "sg:phone":"+1 815 933 7100",
    "sg:postcode":"60901",
    "sg:province":"IL",
    "wof:name":"Acceptance Insurance Co",
    "wof:placetype":"venue"
},
  "geometry": {"coordinates":[-87.875648,41.135406],"type":"Point"}
}