{
  "type": "Feature",
  "properties": {
    "addr:full":"1017 W Washington Blvd Chicago IL 60607",
    "addr:housenumber":"1017",
    "addr:postcode":"60607",
    "addr:street":"W Washington Blvd",
    "iso:country":"US",
    "sg:address":"1017 W Washington Blvd",
    "sg:city":"Chicago",
    "sg:classifiers":[
        {
            "category":"Shopping",
            "subcategory":"Clothing, Apparel, & Fashions",
            "type":"Retail Goods"
        }
    ],
    "sg:phone":"+1 312 666 7549",
    "sg:postcode":"60607",
    "sg:province":"IL",
    "sg:tags":[
        "accessory",
        "clothing",
        "women's"
    ],
    "wof:name":"Harpo Boutique",
    "wof:placetype":"venue"
},
  "geometry": {"coordinates":[-87.65273500000001,41.882941],"type":"Point"}
}