{
  "type": "Feature",
  "properties": {
    "addr:full":"116 Alton Sq Alton IL 62002",
    "addr:housenumber":"116",
    "addr:postcode":"62002",
    "addr:street":"Alton Sq",
    "iso:country":"US",
    "sg:address":"116 Alton Sq",
    "sg:city":"Alton",
    "sg:classifiers":[
        {
            "category":"Shopping",
            "subcategory":"Clothing, Apparel, & Fashions",
            "type":"Retail Goods"
        }
    ],
    "sg:phone":"+1 618 463 2350",
    "sg:postcode":"62002",
    "sg:province":"IL",
    "wof:name":"Christopher & Banks Inc",
    "wof:placetype":"venue"
},
  "geometry": {"coordinates":[-90.176873,38.924441],"type":"Point"}
}