{
  "type": "Feature",
  "properties": {
    "iso:country":"US",
    "sg:address":"27W115 Geneva Rd",
    "sg:city":"Winfield",
    "sg:classifiers":[
        {
            "category":"Health Services",
            "subcategory":"Doctor",
            "type":"Services"
        }
    ],
    "sg:phone":"+1 630 588 9915",
    "sg:postcode":"60190",
    "sg:province":"IL",
    "sg:tags":[
        "surgeon",
        "oral"
    ],
    "wof:name":"Oliver Daniel A III DDS",
    "wof:placetype":"venue"
},
  "geometry": {"coordinates":[-88.147903,41.887901],"type":"Point"}
}