{
  "type": "Feature",
  "properties": {
    "addr:full":"5840 W 63rd St Chicago IL 60638",
    "addr:housenumber":"5840",
    "addr:postcode":"60638",
    "addr:street":"W 63Rd St",
    "iso:country":"US",
    "sg:address":"5840 W 63rd St",
    "sg:city":"Chicago",
    "sg:classifiers":[
        {
            "category":"Real Estate",
            "subcategory":"Real Estate Services",
            "type":"Services"
        },
        {
            "category":"Real Estate",
            "subcategory":"Real Estate Agent",
            "type":"Services"
        }
    ],
    "sg:phone":"+1 773 585 5385",
    "sg:postcode":"60638",
    "sg:province":"IL",
    "sg:tags":[
        "buyer",
        "management",
        "broker"
    ],
    "sg:website":"http://www.americorpre.com",
    "wof:name":"Americorp Real Estate Ltd",
    "wof:placetype":"venue"
},
  "geometry": {"coordinates":[-87.767822,41.77795],"type":"Point"}
}