{
  "type": "Feature",
  "properties": {
    "iso:country":"US",
    "sg:address":"2801 Civic Circle Blvd Ste 7",
    "sg:city":"Marion",
    "sg:classifiers":[
        {
            "category":"Health Services",
            "subcategory":"Dentist",
            "type":"Services"
        }
    ],
    "sg:phone":"+1 618 998 9868",
    "sg:postcode":"62959",
    "sg:province":"IL",
    "sg:tags":[
        "pediatric"
    ],
    "sg:website":"www.mariondentalcareforkids.com",
    "wof:name":"Dental Care For Kids",
    "wof:placetype":"venue"
},
  "geometry": {"coordinates":[-88.975694,37.74964],"type":"Point"}
}