{
  "type": "Feature",
  "properties": {
    "iso:country":"US",
    "sg:address":"1110 Gore Rd",
    "sg:city":"Morris",
    "sg:classifiers":[
        {
            "category":"Manufacturing",
            "subcategory":"Food",
            "type":"Manufacturing & Wholesale Goods"
        },
        {
            "category":"Farming",
            "subcategory":"Farm",
            "type":"Manufacturing & Wholesale Goods"
        }
    ],
    "sg:phone":"+1 815 942 3450",
    "sg:postcode":"60450",
    "sg:province":"IL",
    "sg:tags":[
        "corn",
        "product"
    ],
    "wof:name":"Jerald Thompson",
    "wof:placetype":"venue"
},
  "geometry": {"coordinates":[-88.44295700000001,41.386131],"type":"Point"}
}