{
  "type": "Feature",
  "properties": {
    "iso:country":"US",
    "sg:address":"28 Fernwood Dr",
    "sg:city":"Bolingbrook",
    "sg:classifiers":[
        {
            "category":"Shopping",
            "type":"Retail Goods"
        },
        {
            "category":"Home & Garden",
            "subcategory":"Carpets & Floor Coverings",
            "type":"Retail Goods"
        }
    ],
    "sg:phone":"+1 630 759 0966",
    "sg:postcode":"60440",
    "sg:province":"IL",
    "sg:tags":[
        "repair",
        "art",
        "gallery",
        "dealer"
    ],
    "wof:name":"Artbeats",
    "wof:placetype":"venue"
},
  "geometry": {"coordinates":[-88.074026,41.69223],"type":"Point"}
}