{
  "type": "Feature",
  "properties": {
    "iso:country":"US",
    "sg:address":"1030 W North Ave Ste 300",
    "sg:city":"Chicago",
    "sg:classifiers":[
        {
            "category":"Personal",
            "subcategory":"Massage",
            "type":"Services"
        }
    ],
    "sg:phone":"+1 312 493 9008",
    "sg:postcode":"60622",
    "sg:province":"IL",
    "wof:name":"Drew Bales, Massage Therapist",
    "wof:placetype":"venue"
},
  "geometry": {"coordinates":[-87.653976,41.910884],"type":"Point"}
}