{
  "type": "Feature",
  "properties": {
    "iso:country":"US",
    "sg:address":"6130 Old US Hwy 50",
    "sg:city":"Breese",
    "sg:classifiers":[
        {
            "category":"Travel",
            "subcategory":"Hotels & Motels",
            "type":"Entertainment"
        }
    ],
    "sg:phone":"+1 618 228 7068",
    "sg:postcode":"62230",
    "sg:province":"IL",
    "sg:tags":[
        "breakfast",
        "accommodation",
        "bed"
    ],
    "wof:name":"Timmermann House",
    "wof:placetype":"venue"
},
  "geometry": {"coordinates":[-89.591468,38.612093],"type":"Point"}
}