{
  "type": "Feature",
  "properties": {
    "iso:country":"US",
    "sg:address":"114 N Vine St",
    "sg:city":"Urbana",
    "sg:classifiers":[
        {
            "category":"Personal",
            "subcategory":"Tanning Parlor",
            "type":"Services"
        }
    ],
    "sg:phone":"+1 217 367 3707",
    "sg:postcode":"61802",
    "sg:province":"IL",
    "wof:name":"Classic Tan",
    "wof:placetype":"venue"
},
  "geometry": {"coordinates":[-88.204803,40.112598],"type":"Point"}
}