{
  "type": "Feature",
  "properties": {
    "iso:country":"US",
    "sg:address":"220 Otto Dr",
    "sg:city":"New Lenox",
    "sg:classifiers":[
        {
            "category":"Building & Trades",
            "subcategory":"Construction",
            "type":"Services"
        }
    ],
    "sg:phone":"+1 815 485 4846",
    "sg:postcode":"60451",
    "sg:province":"IL",
    "sg:tags":[
        "foundation"
    ],
    "wof:name":"B & B Concrete Inc",
    "wof:placetype":"venue"
},
  "geometry": {"coordinates":[-87.96375999999999,41.494571],"type":"Point"}
}