{
  "type": "Feature",
  "properties": {
    "addr:full":"15 E Stephenson St Freeport IL 61032",
    "addr:housenumber":"15",
    "addr:postcode":"61032",
    "addr:street":"E Stephenson St",
    "iso:country":"US",
    "sg:address":"15 E Stephenson St",
    "sg:city":"Freeport",
    "sg:classifiers":[
        {
            "category":"Shopping",
            "subcategory":"Clothing, Apparel, & Fashions",
            "type":"Retail Goods"
        }
    ],
    "sg:phone":"+1 815 232 7509",
    "sg:postcode":"61032",
    "sg:province":"IL",
    "wof:name":"Karen's Fashions & Gifts",
    "wof:placetype":"venue"
},
  "geometry": {"coordinates":[-89.61985799999999,42.298424],"type":"Point"}
}