{
  "type": "Feature",
  "properties": {
    "iso:country":"US",
    "sg:address":"100 South St",
    "sg:city":"Peoria",
    "sg:classifiers":[
        {
            "category":"Manufacturing",
            "subcategory":"Electronics",
            "type":"Manufacturing & Wholesale Goods"
        }
    ],
    "sg:phone":"+1 309 696 2632",
    "sg:postcode":"61602",
    "sg:province":"IL",
    "sg:tags":[
        "control",
        "equipment-wholesale",
        "security",
        "manufacturer"
    ],
    "wof:name":"J & L Dock Facilities Inc",
    "wof:placetype":"venue"
},
  "geometry": {"coordinates":[-89.61224,40.67477],"type":"Point"}
}