{
  "type": "Feature",
  "properties": {
    "addr:full":"711 Madison St Oak Park IL 60302",
    "addr:housenumber":"711",
    "addr:postcode":"60302",
    "addr:street":"Madison St",
    "iso:country":"US",
    "sg:address":"711 Madison St",
    "sg:city":"Oak Park",
    "sg:classifiers":[
        {
            "category":"Retail",
            "subcategory":"Auto Rental",
            "type":"Services"
        }
    ],
    "sg:phone":"+1 708 386 0048",
    "sg:postcode":"60302",
    "sg:province":"IL",
    "sg:tags":[
        "renting",
        "automobile"
    ],
    "wof:name":"Enterprise Rent-A-Car",
    "wof:placetype":"venue"
},
  "geometry": {"coordinates":[-87.791804,41.879799],"type":"Point"}
}