{
  "type": "Feature",
  "properties": {
    "iso:country":"US",
    "sg:address":"260 W Locust Ave",
    "sg:city":"Charleston",
    "sg:classifiers":[
        {
            "category":"Organizations",
            "subcategory":"Non-profit Organization",
            "type":"Services"
        }
    ],
    "sg:phone":"+1 217 345 5000",
    "sg:postcode":"61920",
    "sg:province":"IL",
    "sg:tags":[
        "alternative",
        "abortion"
    ],
    "wof:name":"Crisis Pregnancy Ctr Of E Il",
    "wof:placetype":"venue"
},
  "geometry": {"coordinates":[-88.184625,39.49986],"type":"Point"}
}