{
  "type": "Feature",
  "properties": {
    "addr:full":"50 E Harrison Street Chicago IL 60605",
    "addr:housenumber":"50",
    "addr:postcode":"60605",
    "addr:street":"E Harrison Street",
    "iso:country":"US",
    "sg:address":"50 E Harrison Street",
    "sg:city":"Chicago",
    "sg:classifiers":[
        {
            "category":"Parking",
            "type":"Transportation"
        }
    ],
    "sg:phone":"+1 312 922 8051",
    "sg:postcode":"60605",
    "sg:province":"IL",
    "wof:name":"Park One",
    "wof:placetype":"venue"
},
  "geometry": {"coordinates":[-87.62521099999999,41.874413],"type":"Point"}
}