{
  "type": "Feature",
  "properties": {
    "iso:country":"US",
    "sg:address":"208 S La Salle Street",
    "sg:city":"Chicago",
    "sg:classifiers":[
        {
            "category":"Shopping",
            "subcategory":"Stationery & Office Supplies",
            "type":"Retail Goods"
        }
    ],
    "sg:phone":"+1 312 357 5601",
    "sg:postcode":"60604",
    "sg:province":"IL",
    "sg:tags":[
        "equipment"
    ],
    "wof:name":"Taylor Resources Chicago",
    "wof:placetype":"venue"
},
  "geometry": {"coordinates":[-87.632448,41.879256],"type":"Point"}
}