{
  "type": "Feature",
  "properties": {
    "iso:country":"US",
    "sg:address":"460 N Finis St",
    "sg:city":"Virden",
    "sg:classifiers":[
        {
            "category":"Building & Trades",
            "subcategory":"Construction",
            "type":"Services"
        }
    ],
    "sg:phone":"+1 217 899 9968",
    "sg:postcode":"62690",
    "sg:province":"IL",
    "sg:tags":[
        "concrete",
        "contractor"
    ],
    "wof:name":"Beechler Concrete",
    "wof:placetype":"venue"
},
  "geometry": {"coordinates":[-89.771569,39.505355],"type":"Point"}
}