{
  "type": "Feature",
  "properties": {
    "addr:full":"46 E Oak Street Chicago IL 60611",
    "addr:housenumber":"46",
    "addr:postcode":"60611",
    "addr:street":"E Oak Street",
    "iso:country":"US",
    "sg:address":"46 E Oak Street",
    "sg:city":"Chicago",
    "sg:classifiers":[
        {
            "category":"Personal",
            "subcategory":"Hair Removal",
            "type":"Services"
        }
    ],
    "sg:phone":"+1 312 943 4190",
    "sg:postcode":"60611",
    "sg:province":"IL",
    "wof:name":"M G Institute Ltd",
    "wof:placetype":"venue"
},
  "geometry": {"coordinates":[-87.626893,41.900783],"type":"Point"}
}