{
  "type": "Feature",
  "properties": {
    "iso:country":"US",
    "sg:address":"1325 Harvard Dr",
    "sg:city":"Kankakee",
    "sg:classifiers":[
        {
            "category":"Wholesale",
            "subcategory":"Painting Supplies",
            "type":"Manufacturing & Wholesale Goods"
        },
        {
            "category":"Manufacturing",
            "subcategory":"Chemicals & Compounds",
            "type":"Manufacturing & Wholesale Goods"
        }
    ],
    "sg:phone":"+1 815 933 3742",
    "sg:postcode":"60901",
    "sg:province":"IL",
    "sg:tags":[
        "wholesaler",
        "equipment",
        "painter",
        "roller",
        "paint"
    ],
    "sg:website":"www.jrbrush.com",
    "wof:name":"J R Edwards Brush & Roller Inc",
    "wof:placetype":"venue"
},
  "geometry": {"coordinates":[-87.843433,41.135902],"type":"Point"}
}