{
  "type": "Feature",
  "properties": {
    "iso:country":"US",
    "sg:address":"3000 Columbus St",
    "sg:city":"Ottawa",
    "sg:classifiers":[
        {
            "category":"Real Estate",
            "subcategory":"Real Estate Agent",
            "type":"Services"
        }
    ],
    "sg:phone":"+1 815 433 0900",
    "sg:postcode":"61350",
    "sg:province":"IL",
    "wof:name":"First Illinois Realty",
    "wof:placetype":"venue"
},
  "geometry": {"coordinates":[-88.83604099999999,41.374199],"type":"Point"}
}