{
  "type": "Feature",
  "properties": {
    "iso:country":"US",
    "sg:address":"2812 Northwind Dr",
    "sg:city":"New Lenox",
    "sg:classifiers":[
        {
            "category":"Professional",
            "type":"Services"
        }
    ],
    "sg:phone":"+1 815 462 4035",
    "sg:postcode":"60451",
    "sg:province":"IL",
    "sg:tags":[
        "establishment"
    ],
    "wof:name":"Cachey Buliders Inc",
    "wof:placetype":"venue"
},
  "geometry": {"coordinates":[-87.91158900000001,41.50559],"type":"Point"}
}