{
  "type": "Feature",
  "properties": {
    "addr:full":"4236 Elm St Downers Grove IL 60515",
    "addr:housenumber":"4236",
    "addr:postcode":"60515",
    "addr:street":"Elm St",
    "iso:country":"US",
    "sg:address":"4236 Elm St",
    "sg:city":"Downers Grove",
    "sg:classifiers":[
        {
            "category":"Professional",
            "subcategory":"Computer Services",
            "type":"Services"
        }
    ],
    "sg:phone":"+1 630 852 2442",
    "sg:postcode":"60515",
    "sg:province":"IL",
    "sg:tags":[
        "internet"
    ],
    "sg:website":"www.dougkershaw.com",
    "wof:name":"Celebrity Promotions",
    "wof:placetype":"venue"
},
  "geometry": {"coordinates":[-88.005555,41.809863],"type":"Point"}
}