{
  "type": "Feature",
  "properties": {
    "addr:full":"510 Raven Grv Belleville IL 62221",
    "addr:housenumber":"510",
    "addr:postcode":"62221",
    "addr:street":"Raven Grv",
    "iso:country":"US",
    "sg:address":"510 Raven Grv",
    "sg:city":"Belleville",
    "sg:classifiers":[
        {
            "category":"Building & Trades",
            "subcategory":"Equipment Rental",
            "type":"Services"
        }
    ],
    "sg:phone":"+1 618 234 2977",
    "sg:postcode":"62221",
    "sg:province":"IL",
    "sg:tags":[
        "yard",
        "leasing",
        "store"
    ],
    "wof:name":"H A H Rentals",
    "wof:placetype":"venue"
},
  "geometry": {"coordinates":[-89.94755600000001,38.556468],"type":"Point"}
}