{
  "type": "Feature",
  "properties": {
    "iso:country":"US",
    "sg:address":"6321 N Avondale Ave",
    "sg:city":"Chicago",
    "sg:classifiers":[
        {
            "category":"Building & Trades",
            "subcategory":"Construction",
            "type":"Services"
        }
    ],
    "sg:phone":"+1 773 792 3162",
    "sg:postcode":"60631",
    "sg:province":"IL",
    "sg:tags":[
        "contractor"
    ],
    "wof:name":"Construction All Concrete Inc",
    "wof:placetype":"venue"
},
  "geometry": {"coordinates":[-87.80789900000001,41.995701],"type":"Point"}
}