{
  "type": "Feature",
  "properties": {
    "addr:full":"1500 Skokie Blvd Northbrook IL 60062",
    "addr:housenumber":"1500",
    "addr:postcode":"60062",
    "addr:street":"Skokie Blvd",
    "iso:country":"US",
    "sg:address":"1500 Skokie Blvd",
    "sg:city":"Northbrook",
    "sg:classifiers":[
        {
            "category":"Insurance",
            "subcategory":"Insurance Agent",
            "type":"Services"
        }
    ],
    "sg:phone":"+1 847 559 9488",
    "sg:postcode":"60062",
    "sg:province":"IL",
    "wof:name":"National Benefit Brokers Inc",
    "wof:placetype":"venue"
},
  "geometry": {"coordinates":[-87.783163,42.124394],"type":"Point"}
}