{
  "type": "Feature",
  "properties": {
    "addr:full":"1605 Dundee Ave Elgin IL 60120",
    "addr:housenumber":"1605",
    "addr:postcode":"60120",
    "addr:street":"Dundee Ave",
    "iso:country":"US",
    "sg:address":"1605 Dundee Ave",
    "sg:city":"Elgin",
    "sg:classifiers":[
        {
            "category":"Wholesale",
            "subcategory":"Machinery & Supplies",
            "type":"Manufacturing & Wholesale Goods"
        }
    ],
    "sg:phone":"+1 847 931 4100",
    "sg:postcode":"60120",
    "sg:province":"IL",
    "sg:tags":[
        "equipment",
        "material",
        "handling"
    ],
    "wof:name":"Mooney Material Handling Inc",
    "wof:placetype":"venue"
},
  "geometry": {"coordinates":[-88.26445699999999,42.064615],"type":"Point"}
}