{
  "type": "Feature",
  "properties": {
    "addr:full":"600 Academy Dr Northbrook IL 60062",
    "addr:housenumber":"600",
    "addr:postcode":"60062",
    "addr:street":"Academy Dr",
    "iso:country":"US",
    "sg:address":"600 Academy Dr",
    "sg:city":"Northbrook",
    "sg:classifiers":[
        {
            "category":"Professional",
            "subcategory":"Management & Consulting",
            "type":"Services"
        }
    ],
    "sg:phone":"+1 847 559 2945",
    "sg:postcode":"60062",
    "sg:province":"IL",
    "sg:tags":[
        "consultant",
        "publishing"
    ],
    "wof:name":"Dowden Health Media",
    "wof:placetype":"venue"
},
  "geometry": {"coordinates":[-87.85686800000001,42.141711],"type":"Point"}
}