{
  "type": "Feature",
  "properties": {
    "iso:country":"US",
    "sg:address":"1 Dearborn Sq",
    "sg:city":"Kankakee",
    "sg:classifiers":[
        {
            "category":"Health Services",
            "subcategory":"Doctor",
            "type":"Services"
        }
    ],
    "sg:phone":"+1 815 933 2227",
    "sg:postcode":"60901",
    "sg:province":"IL",
    "sg:tags":[
        "medical"
    ],
    "wof:name":"James Pinski Mdsc",
    "wof:placetype":"venue"
},
  "geometry": {"coordinates":[-87.862635,41.11962],"type":"Point"}
}