{
  "type": "Feature",
  "properties": {
    "addr:full":"75 Vista Ln Lake Barrington IL 60010",
    "addr:housenumber":"75",
    "addr:postcode":"60010",
    "addr:street":"Vista Ln",
    "iso:country":"US",
    "sg:address":"75 Vista Ln",
    "sg:city":"Lake Barrington",
    "sg:classifiers":[
        {
            "category":"Health Services",
            "subcategory":"Chiropractor",
            "type":"Services"
        }
    ],
    "sg:phone":"+1 847 382 3011",
    "sg:postcode":"60010",
    "sg:province":"IL",
    "wof:name":"Victoria Vonbergen DC",
    "wof:placetype":"venue"
},
  "geometry": {"coordinates":[-88.171631,42.202833],"type":"Point"}
}