{
  "type": "Feature",
  "properties": {
    "addr:full":"14605 W Edison Dr New Lenox IL 60451",
    "addr:housenumber":"14605",
    "addr:postcode":"60451",
    "addr:street":"W Edison Dr",
    "iso:country":"US",
    "sg:address":"14605 W Edison Dr",
    "sg:city":"New Lenox",
    "sg:classifiers":[
        {
            "category":"Building & Trades",
            "subcategory":"Construction",
            "type":"Services"
        }
    ],
    "sg:phone":"+1 815 462 9431",
    "sg:postcode":"60451",
    "sg:province":"IL",
    "sg:tags":[
        "contractor"
    ],
    "wof:name":"Alltight Masonry Inc",
    "wof:placetype":"venue"
},
  "geometry": {"coordinates":[-87.96508900000001,41.49123],"type":"Point"}
}