{
  "type": "Feature",
  "properties": {
    "addr:city":"Batavia",
    "addr:full":"155 Houston St Batavia, Il 60510",
    "addr:house_number":"155",
    "addr:housenumber":"155",
    "addr:phone":"+1 630-406-5274",
    "addr:postcode":"60510",
    "addr:road":"Houston St",
    "addr:state":"IL",
    "addr:street":"Houston St",
    "iso:country":"US",
    "sg:address":"155 Houston St",
    "sg:city":"Batavia",
    "sg:classifiers":[
        {
            "category":"Museum",
            "type":"Entertainment"
        }
    ],
    "sg:phone":"+1 630 406 5274",
    "sg:postcode":"60510",
    "sg:province":"IL",
    "sg:tags":[
        "gallery"
    ],
    "wof:airports":[
        102529559,
        102528701
    ],
    "wof:name":"Batavia Depot Museum",
    "wof:placetype":"venue"
},
  "geometry": {"coordinates":[-88.31104999999999,41.84873],"type":"Point"}
}