{
  "type": "Feature",
  "properties": {
    "addr:full":"155 Houston St Batavia IL 60510",
    "addr:housenumber":"155",
    "addr:postcode":"60510",
    "addr:street":"Houston St",
    "iso:country":"US",
    "sg:address":"155 Houston St",
    "sg:city":"Batavia",
    "sg:classifiers":[
        {
            "category":"Museum",
            "type":"Entertainment"
        }
    ],
    "sg:phone":"+1 630 406 5274",
    "sg:postcode":"60510",
    "sg:province":"IL",
    "sg:tags":[
        "gallery"
    ],
    "wof:name":"Batavia Depot Museum",
    "wof:placetype":"venue"
},
  "geometry": {"coordinates":[-88.309639,41.851346],"type":"Point"}
}