{
  "type": "Feature",
  "properties": {
    "iso:country":"US",
    "sg:address":"1300 W South 3rd St",
    "sg:city":"Shelbyville",
    "sg:classifiers":[
        {
            "category":"Place Of Worship",
            "subcategory":"Church",
            "type":"Public Place"
        },
        {
            "category":"Place Of Worship",
            "type":"Public Place"
        }
    ],
    "sg:phone":"+1 217 774 2015",
    "sg:postcode":"62565",
    "sg:province":"IL",
    "sg:tags":[
        "lutheran",
        "america",
        "churches-lutheran",
        "churches-lutheran-evangelical"
    ],
    "wof:name":"Lutheran Church St Pauls Elca",
    "wof:placetype":"venue"
},
  "geometry": {"coordinates":[-88.80838,39.403931],"type":"Point"}
}