{
  "type": "Feature",
  "properties": {
    "iso:country":"US",
    "sg:address":"806 E Belvidere Rd",
    "sg:city":"Grayslake",
    "sg:classifiers":[
        {
            "category":"Home & Garden",
            "subcategory":"Hardware",
            "type":"Retail Goods"
        },
        {
            "category":"Home & Garden",
            "subcategory":"Furniture",
            "type":"Retail Goods"
        }
    ],
    "sg:phone":"+1 847 548 5949",
    "sg:postcode":"60030",
    "sg:province":"IL",
    "sg:tags":[
        "outdoor",
        "fountain",
        "display",
        "patio"
    ],
    "wof:name":"Garden Of Eatin Etc",
    "wof:placetype":"venue"
},
  "geometry": {"coordinates":[-88.028369,42.336639],"type":"Point"}
}