{
  "type": "Feature",
  "properties": {
    "iso:country":"US",
    "sg:address":"2470 W Schaumburg Rd",
    "sg:city":"Schaumburg",
    "sg:classifiers":[
        {
            "category":"Retail",
            "subcategory":"Laundry & Dry Cleaning",
            "type":"Services"
        }
    ],
    "sg:phone":"+1 847 882 9194",
    "sg:postcode":"60194",
    "sg:province":"IL",
    "sg:tags":[
        "drycleaning",
        "plant"
    ],
    "wof:name":"Signature Cleaners",
    "wof:placetype":"venue"
},
  "geometry": {"coordinates":[-88.153911,42.029751],"type":"Point"}
}