{
  "type": "Feature",
  "properties": {
    "iso:country":"US",
    "sg:address":"1506 W Division St",
    "sg:city":"Kewanee",
    "sg:classifiers":[
        {
            "category":"Wholesale",
            "subcategory":"Machinery & Supplies",
            "type":"Manufacturing & Wholesale Goods"
        }
    ],
    "sg:phone":"+1 309 853 5441",
    "sg:postcode":"61443",
    "sg:province":"IL",
    "sg:tags":[
        "equipment",
        "foundry"
    ],
    "wof:name":"Demmler Products Co",
    "wof:placetype":"venue"
},
  "geometry": {"coordinates":[-89.948172,41.234595],"type":"Point"}
}