{
  "type": "Feature",
  "properties": {
    "addr:full":"3315 Dora St Franklin Park IL 60131",
    "addr:housenumber":"3315",
    "addr:postcode":"60131",
    "addr:street":"Dora St",
    "iso:country":"US",
    "sg:address":"3315 Dora St",
    "sg:city":"Franklin Park",
    "sg:classifiers":[
        {
            "category":"Manufacturing",
            "subcategory":"Metals",
            "type":"Manufacturing & Wholesale Goods"
        }
    ],
    "sg:phone":"+1 847 678 3188",
    "sg:postcode":"60131",
    "sg:province":"IL",
    "sg:tags":[
        "machine",
        "screw",
        "product",
        "mfg"
    ],
    "wof:name":"Yarnel Manufacturing",
    "wof:placetype":"venue"
},
  "geometry": {"coordinates":[-87.880128,41.938918],"type":"Point"}
}