{
  "type": "Feature",
  "properties": {
    "addr:full":"1619 N Main St Princeton IL 61356",
    "addr:housenumber":"1619",
    "addr:postcode":"61356",
    "addr:street":"N Main St",
    "iso:country":"US",
    "sg:address":"1619 N Main St",
    "sg:city":"Princeton",
    "sg:classifiers":[
        {
            "category":"Home & Garden",
            "subcategory":"Furniture",
            "type":"Retail Goods"
        }
    ],
    "sg:phone":"+1 815 879 0604",
    "sg:postcode":"61356",
    "sg:province":"IL",
    "sg:tags":[
        "equipment",
        "kitchen",
        "cabinet"
    ],
    "sg:website":"www.someonesinthekitchen.org",
    "wof:name":"Someone's In The Kitchen",
    "wof:placetype":"venue"
},
  "geometry": {"coordinates":[-89.465433,41.389843],"type":"Point"}
}