{
  "type": "Feature",
  "properties": {
    "addr:full":"118 Lake St Libertyville IL 60048",
    "addr:housenumber":"118",
    "addr:postcode":"60048",
    "addr:street":"Lake St",
    "iso:country":"US",
    "sg:address":"118 Lake St",
    "sg:city":"Libertyville",
    "sg:classifiers":[
        {
            "category":"Insurance",
            "subcategory":"Insurance Agent",
            "type":"Services"
        },
        {
            "category":"Insurance",
            "subcategory":"Hazard Insurance",
            "type":"Services"
        },
        {
            "category":"Insurance",
            "subcategory":"Title Insurance",
            "type":"Services"
        },
        {
            "category":"Insurance",
            "subcategory":"Life Insurance",
            "type":"Services"
        }
    ],
    "sg:phone":"+1 847 362 0099",
    "sg:postcode":"60048",
    "sg:province":"IL",
    "sg:tags":[
        "business",
        "auto",
        "commercial",
        "homeowner",
        "motorcycle",
        "renter"
    ],
    "wof:name":"Allstate Insurance Company - Rose Sheldon",
    "wof:placetype":"venue"
},
  "geometry": {"coordinates":[-87.954779,42.289446],"type":"Point"}
}