{
  "type": "Feature",
  "properties": {
    "iso:country":"US",
    "sg:address":"205 E Center St",
    "sg:city":"Le Roy",
    "sg:classifiers":[
        {
            "category":"Banks & Credit Unions",
            "subcategory":"Bank",
            "type":"Services"
        }
    ],
    "sg:phone":"+1 309 722 3291",
    "sg:postcode":"61752",
    "sg:province":"IL",
    "wof:name":"Farmer City State Bank",
    "wof:placetype":"venue"
},
  "geometry": {"coordinates":[-88.760492,40.34706],"type":"Point"}
}