{
  "type": "Feature",
  "properties": {
    "addr:full":"1816 W Magnolia Ln Mount Prospect IL 60056",
    "addr:housenumber":"1816",
    "addr:postcode":"60056",
    "addr:street":"W Magnolia Ln",
    "iso:country":"US",
    "sg:address":"1816 W Magnolia Ln",
    "sg:city":"Mount Prospect",
    "sg:classifiers":[
        {
            "category":"Personal",
            "type":"Services"
        }
    ],
    "sg:phone":"+1 847 437 6375",
    "sg:postcode":"60056",
    "sg:province":"IL",
    "wof:name":"Johnnys Screaming",
    "wof:placetype":"venue"
},
  "geometry": {"coordinates":[-87.96797599999999,42.042656],"type":"Point"}
}