{
  "type": "Feature",
  "properties": {
    "iso:country":"US",
    "sg:address":"812 Lyster Rd",
    "sg:city":"Highwood",
    "sg:classifiers":[
        {
            "category":"Professional",
            "subcategory":"Engineering",
            "type":"Services"
        },
        {
            "category":"Organizations",
            "subcategory":"Professional Association",
            "type":"Services"
        }
    ],
    "sg:phone":"+1 847 266 7833",
    "sg:postcode":"60040",
    "sg:province":"IL",
    "sg:tags":[
        "engineer"
    ],
    "wof:name":"Innovative Medical Services",
    "wof:placetype":"venue"
},
  "geometry": {"coordinates":[-87.813972,42.212666],"type":"Point"}
}