{
  "type": "Feature",
  "properties": {
    "iso:country":"US",
    "sg:address":"969 Pine Tree Cir S",
    "sg:city":"Buffalo Grove",
    "sg:classifiers":[
        {
            "category":"Manufacturing",
            "subcategory":"Chemicals & Compounds",
            "type":"Manufacturing & Wholesale Goods"
        }
    ],
    "sg:phone":"+1 847 808 1785",
    "sg:postcode":"60089",
    "sg:province":"IL",
    "sg:tags":[
        "preparation",
        "mfg"
    ],
    "wof:name":"Martys Core Company",
    "wof:placetype":"venue"
},
  "geometry": {"coordinates":[-87.964082,42.169698],"type":"Point"}
}