{
  "type": "Feature",
  "properties": {
    "iso:country":"US",
    "sg:address":"633 Skokie Blvd Ste 200",
    "sg:city":"Northbrook",
    "sg:classifiers":[
        {
            "category":"Food & Beverages",
            "subcategory":"Liquor & Beverages",
            "type":"Retail Goods"
        }
    ],
    "sg:phone":"+1 847 559 2703",
    "sg:postcode":"60062",
    "sg:province":"IL",
    "sg:tags":[
        "bottler",
        "beverages-distributors"
    ],
    "wof:name":"Jeff's Soda",
    "wof:placetype":"venue"
},
  "geometry": {"coordinates":[-87.7931,42.140138],"type":"Point"}
}