{
  "type": "Feature",
  "properties": {
    "addr:full":"1220 Central Ave Bartlett IL 60133",
    "addr:housenumber":"1220",
    "addr:postcode":"60133",
    "addr:street":"Central Ave",
    "iso:country":"US",
    "sg:address":"1220 Central Ave",
    "sg:city":"Bartlett",
    "sg:classifiers":[
        {
            "category":"Manufacturing",
            "subcategory":"Metals",
            "type":"Manufacturing & Wholesale Goods"
        }
    ],
    "sg:phone":"+1 630 671 1220",
    "sg:postcode":"60133",
    "sg:province":"IL",
    "sg:tags":[
        "fabricator",
        "parts",
        "sheet",
        "precision"
    ],
    "wof:name":"PMF",
    "wof:placetype":"venue"
},
  "geometry": {"coordinates":[-88.12778299999999,41.982099],"type":"Point"}
}