{
  "type": "Feature",
  "properties": {
    "addr:full":"504 Hannah Ave Forest Park IL 60130",
    "addr:housenumber":"504",
    "addr:postcode":"60130",
    "addr:street":"Hannah Ave",
    "iso:country":"US",
    "sg:address":"504 Hannah Ave",
    "sg:city":"Forest Park",
    "sg:classifiers":[
        {
            "category":"Building & Trades",
            "subcategory":"Landscaping Services",
            "type":"Services"
        }
    ],
    "sg:phone":"+1 708 366 9426",
    "sg:postcode":"60130",
    "sg:province":"IL",
    "sg:tags":[
        "landscape"
    ],
    "wof:name":"Pats Landscaping",
    "wof:placetype":"venue"
},
  "geometry": {"coordinates":[-87.80941900000001,41.876924],"type":"Point"}
}