{
  "type": "Feature",
  "properties": {
    "addr:full":"1401 1/2 Morningside Dr Freeport IL 61032",
    "addr:housenumber":"1401 1 / 2",
    "addr:postcode":"61032",
    "addr:street":"Morningside Dr",
    "iso:country":"US",
    "sg:address":"1401 1/2 Morningside Dr",
    "sg:city":"Freeport",
    "sg:classifiers":[
        {
            "category":"Building & Trades",
            "subcategory":"Landscaping Services",
            "type":"Services"
        }
    ],
    "sg:phone":"+1 815 235 7582",
    "sg:postcode":"61032",
    "sg:province":"IL",
    "sg:tags":[
        "lawn"
    ],
    "wof:name":"Extreme Hardscapes Landscapes",
    "wof:placetype":"venue"
},
  "geometry": {"coordinates":[-89.59605000000001,42.285797],"type":"Point"}
}