{
  "type": "Feature",
  "properties": {
    "addr:full":"1595 Burr Oak Cir Aurora IL 60506",
    "addr:housenumber":"1595",
    "addr:postcode":"60506",
    "addr:street":"Burr Oak Cir",
    "iso:country":"US",
    "sg:address":"1595 Burr Oak Cir",
    "sg:city":"Aurora",
    "sg:classifiers":[
        {
            "category":"Professional",
            "subcategory":"Management & Consulting",
            "type":"Services"
        }
    ],
    "sg:phone":"+1 630 896 7682",
    "sg:postcode":"60506",
    "sg:province":"IL",
    "wof:name":"Clasique Elegance Corp",
    "wof:placetype":"venue"
},
  "geometry": {"coordinates":[-88.347453,41.785435],"type":"Point"}
}