{
  "type": "Feature",
  "properties": {
    "addr:full":"1010 Hickory Nut Grove Ln Cary IL 60013",
    "addr:housenumber":"1010",
    "addr:postcode":"60013",
    "addr:street":"Hickory Nut Grove Ln",
    "iso:country":"US",
    "sg:address":"1010 Hickory Nut Grove Ln",
    "sg:city":"Cary",
    "sg:classifiers":[
        {
            "category":"Building & Trades",
            "subcategory":"Construction",
            "type":"Services"
        }
    ],
    "sg:phone":"+1 847 639 8176",
    "sg:postcode":"60013",
    "sg:province":"IL",
    "sg:tags":[
        "roofing",
        "contractor"
    ],
    "wof:name":"Lakewood Roofing",
    "wof:placetype":"venue"
},
  "geometry": {"coordinates":[-88.21578100000001,42.234356],"type":"Point"}
}