{
  "type": "Feature",
  "properties": {
    "addr:full":"810 Waukegan Rd Deerfield IL 60015",
    "addr:housenumber":"810",
    "addr:postcode":"60015",
    "addr:street":"Waukegan Rd",
    "iso:country":"US",
    "sg:address":"810 Waukegan Rd",
    "sg:city":"Deerfield",
    "sg:classifiers":[
        {
            "category":"Travel",
            "subcategory":"Travel Agent",
            "type":"Entertainment"
        }
    ],
    "sg:phone":"+1 847 948 7770",
    "sg:postcode":"60015",
    "sg:province":"IL",
    "sg:tags":[
        "agency"
    ],
    "wof:name":"Gould-Kelly World Travel Inc",
    "wof:placetype":"venue"
},
  "geometry": {"coordinates":[-87.846115,42.168235],"type":"Point"}
}