{
  "type": "Feature",
  "properties": {
    "addr:full":"3811 W 63rd St Chicago IL 60629",
    "addr:housenumber":"3811",
    "addr:postcode":"60629",
    "addr:street":"W 63Rd St",
    "iso:country":"US",
    "sg:address":"3811 W 63rd St",
    "sg:city":"Chicago",
    "sg:classifiers":[
        {
            "category":"Deli",
            "type":"Food & Drink"
        }
    ],
    "sg:menulink":"http://www.allmenus.com/il/chicago/223562-lady-bs-pizzeria/menu/",
    "sg:phone":"+1 773 585 6344",
    "sg:postcode":"60629",
    "sg:province":"IL",
    "sg:tags":[
        "american"
    ],
    "wof:name":"Lady B's Pizzeria",
    "wof:placetype":"venue"
},
  "geometry": {"coordinates":[-87.718036,41.778634],"type":"Point"}
}