{
  "type": "Feature",
  "properties": {
    "addr:full":"201 Timberview Dr La Harpe IL 61450",
    "addr:housenumber":"201",
    "addr:postcode":"61450",
    "addr:street":"Timberview Dr",
    "iso:country":"US",
    "sg:address":"201 Timberview Dr",
    "sg:city":"La Harpe",
    "sg:classifiers":[
        {
            "category":"Health Services",
            "subcategory":"Nursing And Care Facility",
            "type":"Services"
        }
    ],
    "sg:phone":"+1 217 659 3729",
    "sg:postcode":"61450",
    "sg:province":"IL",
    "sg:tags":[
        "home",
        "convalescent"
    ],
    "wof:name":"Alternative Assisted Living",
    "wof:placetype":"venue"
},
  "geometry": {"coordinates":[-90.96108099999999,40.589112],"type":"Point"}
}