{
  "type": "Feature",
  "properties": {
    "addr:full":"33 N La Salle St Ste 2700 Chicago IL 60602",
    "addr:housenumber":"33",
    "addr:postcode":"60602",
    "addr:street":"N La Salle St Ste 2700",
    "iso:country":"US",
    "sg:address":"33 N La Salle St Ste 2700",
    "sg:city":"Chicago",
    "sg:classifiers":[
        {
            "category":"Professional",
            "subcategory":"Lawyer & Legal Services",
            "type":"Services"
        }
    ],
    "sg:phone":"+1 312 332 4042",
    "sg:postcode":"60602",
    "sg:province":"IL",
    "wof:name":"Law Offices of Martin Fertel",
    "wof:placetype":"venue"
},
  "geometry": {"coordinates":[-87.632356,41.882606],"type":"Point"}
}