{
  "type": "Feature",
  "properties": {
    "iso:country":"US",
    "sg:address":"1211 Royal Rd",
    "sg:city":"Quincy",
    "sg:classifiers":[
        {
            "category":"Wholesale",
            "subcategory":"Machinery & Supplies",
            "type":"Manufacturing & Wholesale Goods"
        }
    ],
    "sg:phone":"+1 217 224 4783",
    "sg:postcode":"62301",
    "sg:province":"IL",
    "sg:tags":[
        "rubber",
        "product"
    ],
    "wof:name":"BRC Rubber & Plastics Inc",
    "wof:placetype":"venue"
},
  "geometry": {"coordinates":[-91.376499,39.916408],"type":"Point"}
}