{
  "type": "Feature",
  "properties": {
    "iso:country":"US",
    "sg:address":"2619 E 74th St",
    "sg:city":"Chicago",
    "sg:classifiers":[
        {
            "category":"Building & Trades",
            "subcategory":"Pest Control",
            "type":"Services"
        }
    ],
    "sg:phone":"+1 773 978 1880",
    "sg:postcode":"60649",
    "sg:province":"IL",
    "wof:name":"Four Seasons Pest Control",
    "wof:placetype":"venue"
},
  "geometry": {"coordinates":[-87.56076,41.761254],"type":"Point"}
}