{
  "type": "Feature",
  "properties": {
    "iso:country":"US",
    "sg:address":"1201 W Roosevelt Rd",
    "sg:city":"Maywood",
    "sg:classifiers":[
        {
            "category":"Health Services",
            "subcategory":"Hospital",
            "type":"Services"
        }
    ],
    "sg:phone":"+1 708 531 7050",
    "sg:postcode":"60153",
    "sg:province":"IL",
    "sg:tags":[
        "dialysis"
    ],
    "sg:website":"http://www.luc.edu",
    "wof:name":"Loyola Dialysis",
    "wof:placetype":"venue"
},
  "geometry": {"coordinates":[-87.846901,41.864208],"type":"Point"}
}