{
  "type": "Feature",
  "properties": {
    "addr:full":"1923 Larkin Ave Elgin IL 60123",
    "addr:housenumber":"1923",
    "addr:postcode":"60123",
    "addr:street":"Larkin Ave",
    "iso:country":"US",
    "sg:address":"1923 Larkin Ave",
    "sg:city":"Elgin",
    "sg:classifiers":[
        {
            "category":"Retail",
            "subcategory":"Car Wash",
            "type":"Services"
        }
    ],
    "sg:phone":"+1 847 695 2770",
    "sg:postcode":"60123",
    "sg:province":"IL",
    "sg:tags":[
        "carwash"
    ],
    "wof:name":"Larkin Super Wash",
    "wof:placetype":"venue"
},
  "geometry": {"coordinates":[-88.32606,42.032506],"type":"Point"}
}