{
  "type": "Feature",
  "properties": {
    "addr:full":"9645 N Milwaukee Ave Niles IL 60714",
    "addr:housenumber":"9645",
    "addr:postcode":"60714",
    "addr:street":"N Milwaukee Ave",
    "iso:country":"US",
    "sg:address":"9645 N Milwaukee Ave",
    "sg:city":"Niles",
    "sg:classifiers":[
        {
            "category":"Deli",
            "type":"Food & Drink"
        }
    ],
    "sg:menulink":"http://www.allmenus.com/il/maine/224245-goodis-/menu/",
    "sg:phone":"+1 847 583 9500",
    "sg:postcode":"60714",
    "sg:province":"IL",
    "sg:tags":[
        "american"
    ],
    "wof:name":"Goodi's ",
    "wof:placetype":"venue"
},
  "geometry": {"coordinates":[-87.839043,42.055633],"type":"Point"}
}