{
  "type": "Feature",
  "properties": {
    "iso:country":"US",
    "sg:address":"1260 N Green Bay Rd",
    "sg:city":"Lake Forest",
    "sg:classifiers":[
        {
            "category":"Professional",
            "type":"Services"
        }
    ],
    "sg:phone":"+1 847 234 1063",
    "sg:postcode":"60045",
    "sg:province":"IL",
    "wof:name":"Ragdale Foundation",
    "wof:placetype":"venue"
},
  "geometry": {"coordinates":[-87.849945,42.263128],"type":"Point"}
}