{
  "type": "Feature",
  "properties": {
    "iso:country":"US",
    "sg:address":"609 N Douglas Ave",
    "sg:city":"Belleville",
    "sg:classifiers":[
        {
            "category":"Personal",
            "subcategory":"Beauty Salon",
            "type":"Services"
        }
    ],
    "sg:phone":"+1 618 233 6371",
    "sg:postcode":"62220",
    "sg:province":"IL",
    "sg:tags":[
        "shop"
    ],
    "wof:name":"Whatever Cuts",
    "wof:placetype":"venue"
},
  "geometry": {"coordinates":[-89.977813,38.520124],"type":"Point"}
}