{
  "type": "Feature",
  "properties": {
    "addr:full":"811 Waukegan Rd Deerfield IL 60015",
    "addr:housenumber":"811",
    "addr:postcode":"60015",
    "addr:street":"Waukegan Rd",
    "iso:country":"US",
    "sg:address":"811 Waukegan Rd",
    "sg:city":"Deerfield",
    "sg:classifiers":[
        {
            "category":"Shopping",
            "subcategory":"Musical Instruments",
            "type":"Retail Goods"
        }
    ],
    "sg:phone":"+1 847 945 1322",
    "sg:postcode":"60015",
    "sg:province":"IL",
    "sg:website":"www.deerfieldmusic.com",
    "wof:name":"Music Center Of Deerfield",
    "wof:placetype":"venue"
},
  "geometry": {"coordinates":[-87.845968,42.168265],"type":"Point"}
}