{
  "type": "Feature",
  "properties": {
    "iso:country":"US",
    "sg:address":"1118 Cranston Rd",
    "sg:city":"Beloit",
    "sg:classifiers":[
        {
            "category":"Recreation",
            "type":"Entertainment"
        }
    ],
    "sg:phone":"+1 608 364 1188",
    "sg:postcode":"53511",
    "sg:province":"IL",
    "sg:tags":[
        "club",
        "baseball"
    ],
    "wof:name":"Midwest Professional Baseball",
    "wof:placetype":"venue"
},
  "geometry": {"coordinates":[-89.023281,42.532191],"type":"Point"}
}