{
  "type": "Feature",
  "properties": {
    "iso:country":"US",
    "sg:address":"13936 S Clark St",
    "sg:city":"Riverdale",
    "sg:classifiers":[
        {
            "category":"Social Services",
            "type":"Services"
        }
    ],
    "sg:phone":"+1 708 841 8033",
    "sg:postcode":"60827",
    "sg:province":"IL",
    "sg:tags":[
        "shelter",
        "woman"
    ],
    "wof:name":"Hagars Center For Women",
    "wof:placetype":"venue"
},
  "geometry": {"coordinates":[-87.624799,41.641738],"type":"Point"}
}