{
  "type": "Feature",
  "properties": {
    "iso:country":"US",
    "sg:address":"1570 Girard Ave",
    "sg:city":"Bourbonnais",
    "sg:classifiers":[
        {
            "category":"Professional",
            "type":"Services"
        }
    ],
    "sg:phone":"+1 815 937 5626",
    "sg:postcode":"60914",
    "sg:province":"IL",
    "sg:tags":[
        "establishment"
    ],
    "wof:name":"J & J Creative Colors",
    "wof:placetype":"venue"
},
  "geometry": {"coordinates":[-87.837669,41.16909],"type":"Point"}
}