{
  "type": "Feature",
  "properties": {
    "addr:full":"3935 W North Ave Chicago IL 60647",
    "addr:housenumber":"3935",
    "addr:postcode":"60647",
    "addr:street":"W North Ave",
    "iso:country":"US",
    "sg:address":"3935 W North Ave",
    "sg:city":"Chicago",
    "sg:classifiers":[
        {
            "category":"Insurance",
            "subcategory":"Insurance Agent",
            "type":"Services"
        }
    ],
    "sg:phone":"+1 773 395 9676",
    "sg:postcode":"60647",
    "sg:province":"IL",
    "wof:name":"Allstate",
    "wof:placetype":"venue"
},
  "geometry": {"coordinates":[-87.72613800000001,41.90986],"type":"Point"}
}