{
  "type": "Feature",
  "properties": {
    "addr:full":"107 W North St Danville IL 61832",
    "addr:housenumber":"107",
    "addr:postcode":"61832",
    "addr:street":"W North St",
    "iso:country":"US",
    "sg:address":"107 W North St",
    "sg:city":"Danville",
    "sg:classifiers":[
        {
            "category":"Professional",
            "subcategory":"Business Services",
            "type":"Services"
        }
    ],
    "sg:phone":"+1 217 442 8054",
    "sg:postcode":"61832",
    "sg:province":"IL",
    "sg:tags":[
        "license"
    ],
    "wof:name":"Shannon's License Shop",
    "wof:placetype":"venue"
},
  "geometry": {"coordinates":[-87.63256800000001,40.126404],"type":"Point"}
}