{
  "type": "Feature",
  "properties": {
    "addr:full":"225 N First St Wilmington IL 60481",
    "addr:housenumber":"225",
    "addr:postcode":"60481",
    "addr:street":"N First St",
    "iso:country":"US",
    "sg:address":"225 N First St",
    "sg:city":"Wilmington",
    "sg:classifiers":[
        {
            "category":"Shopping",
            "subcategory":"Crafts & Fabrics",
            "type":"Retail Goods"
        },
        {
            "category":"Professional",
            "subcategory":"Art Services",
            "type":"Services"
        }
    ],
    "sg:phone":"+1 815 237 2099",
    "sg:postcode":"60481",
    "sg:province":"IL",
    "sg:tags":[
        "punching",
        "design",
        "embroidery"
    ],
    "wof:name":"Custom Sewing & Embroidery By",
    "wof:placetype":"venue"
},
  "geometry": {"coordinates":[-88.15432699999999,41.307232],"type":"Point"}
}