{
  "type": "Feature",
  "properties": {
    "addr:full":"5432 W Van Buren St Chicago IL 60644",
    "addr:housenumber":"5432",
    "addr:postcode":"60644",
    "addr:street":"W Van Buren St",
    "iso:country":"US",
    "sg:address":"5432 W Van Buren St",
    "sg:city":"Chicago",
    "sg:classifiers":[
        {
            "category":"Communications",
            "subcategory":"Film & Video Production",
            "type":"Services"
        }
    ],
    "sg:phone":"+1 773 287 6661",
    "sg:postcode":"60644",
    "sg:province":"IL",
    "sg:tags":[
        "company"
    ],
    "wof:name":"Studio Desiree",
    "wof:placetype":"venue"
},
  "geometry": {"coordinates":[-87.759044,41.874874],"type":"Point"}
}