{
  "type": "Feature",
  "properties": {
    "iso:country":"US",
    "sg:address":"8536 S Ashland Ave",
    "sg:city":"Chicago",
    "sg:classifiers":[
        {
            "category":"Restaurant",
            "type":"Food & Drink"
        }
    ],
    "sg:phone":"+1 773 881 1180",
    "sg:postcode":"60620",
    "sg:province":"IL",
    "wof:name":"D & L and Family",
    "wof:placetype":"venue"
},
  "geometry": {"coordinates":[-87.6632,41.738899],"type":"Point"}
}