{
  "type": "Feature",
  "properties": {
    "iso:country":"US",
    "sg:address":"16 Baker St",
    "sg:city":"Kankakee",
    "sg:classifiers":[
        {
            "category":"Home & Garden",
            "subcategory":"Building Materials",
            "type":"Retail Goods"
        }
    ],
    "sg:phone":"+1   ",
    "sg:postcode":"60901",
    "sg:province":"IL",
    "wof:name":"K & K Marketing",
    "wof:placetype":"venue"
},
  "geometry": {"coordinates":[-87.812255,41.082032],"type":"Point"}
}