{
  "type": "Feature",
  "properties": {
    "addr:full":"10 N Hugh St Plano IL 60545",
    "addr:housenumber":"10",
    "addr:postcode":"60545",
    "addr:street":"N Hugh St",
    "iso:country":"US",
    "sg:address":"10 N Hugh St",
    "sg:city":"Plano",
    "sg:classifiers":[
        {
            "category":"Communications",
            "subcategory":"Film & Video Production",
            "type":"Services"
        },
        {
            "category":"Personal",
            "type":"Services"
        }
    ],
    "sg:phone":"+1 630 552 8815",
    "sg:postcode":"60545",
    "sg:province":"IL",
    "sg:tags":[
        "videography",
        "dvd",
        "photography",
        "services-commercial",
        "duplicating",
        "cd",
        "cassette",
        "wedding"
    ],
    "wof:name":"Reel Pro Video",
    "wof:placetype":"venue"
},
  "geometry": {"coordinates":[-88.53830499999999,41.662501],"type":"Point"}
}