{
  "type": "Feature",
  "properties": {
    "addr:full":"990 Grove St Evanston IL 60201",
    "addr:housenumber":"990",
    "addr:postcode":"60201",
    "addr:street":"Grove St",
    "iso:country":"US",
    "sg:address":"990 Grove St",
    "sg:city":"Evanston",
    "sg:classifiers":[
        {
            "category":"Manufacturing",
            "subcategory":"Printing",
            "type":"Manufacturing & Wholesale Goods"
        }
    ],
    "sg:phone":"+1 847 491 6440",
    "sg:postcode":"60201",
    "sg:province":"IL",
    "sg:tags":[
        "publisher"
    ],
    "sg:website":"www.cruisetravelmag.com",
    "wof:name":"Century Publishing",
    "wof:placetype":"venue"
},
  "geometry": {"coordinates":[-87.683708,42.045496],"type":"Point"}
}