{
  "type": "Feature",
  "properties": {
    "addr:full":"2400 Arlington Heights Rd Arlington Heights IL 60005",
    "addr:housenumber":"2400",
    "addr:postcode":"60005",
    "addr:street":"Arlington Heights Rd",
    "iso:country":"US",
    "sg:address":"2400 Arlington Heights Rd",
    "sg:city":"Arlington Heights",
    "sg:classifiers":[
        {
            "category":"Freight",
            "type":"Transportation"
        }
    ],
    "sg:phone":"+1 847 806 1747",
    "sg:postcode":"60005",
    "sg:province":"IL",
    "sg:tags":[
        "operator",
        "trucking"
    ],
    "wof:name":"Ng Express Inc",
    "wof:placetype":"venue"
},
  "geometry": {"coordinates":[-87.98355599999999,42.0427],"type":"Point"}
}