{
  "type": "Feature",
  "properties": {
    "iso:country":"US",
    "sg:address":"5875 N Rogers Ave",
    "sg:city":"Chicago",
    "sg:classifiers":[
        {
            "category":"Personal",
            "type":"Services"
        },
        {
            "category":"Retail",
            "subcategory":"Auto Rental",
            "type":"Services"
        }
    ],
    "sg:phone":"+1 773 685 6790",
    "sg:postcode":"60646",
    "sg:province":"IL",
    "sg:tags":[
        "car",
        "mover"
    ],
    "wof:name":"New World Van Lines Inc",
    "wof:placetype":"venue"
},
  "geometry": {"coordinates":[-87.736397,41.987202],"type":"Point"}
}