{
  "type": "Feature",
  "properties": {
    "addr:full":"5927 N Milwaukee Ave Chicago IL 60646",
    "addr:housenumber":"5927",
    "addr:postcode":"60646",
    "addr:street":"N Milwaukee Ave",
    "iso:country":"US",
    "sg:address":"5927 N Milwaukee Ave",
    "sg:city":"Chicago",
    "sg:classifiers":[
        {
            "category":"Personal",
            "subcategory":"Day Spa",
            "type":"Services"
        }
    ],
    "sg:phone":"+1 773 631 4658",
    "sg:postcode":"60646",
    "sg:province":"IL",
    "sg:website":"www.theeeuropeanspa.com",
    "wof:name":"Thee European Spa",
    "wof:placetype":"venue"
},
  "geometry": {"coordinates":[-87.779901,41.989432],"type":"Point"}
}