{
  "type": "Feature",
  "properties": {
    "iso:country":"US",
    "sg:address":"2109 W Middlebury Rd",
    "sg:city":"Freeport",
    "sg:classifiers":[
        {
            "category":"Building & Trades",
            "subcategory":"Construction",
            "type":"Services"
        }
    ],
    "sg:phone":"+1 815 232 8387",
    "sg:postcode":"61032",
    "sg:province":"IL",
    "sg:tags":[
        "house",
        "general",
        "contractor"
    ],
    "wof:name":"Mockridge Construction & Rmdlg",
    "wof:placetype":"venue"
},
  "geometry": {"coordinates":[-89.662679,42.297358],"type":"Point"}
}