{
  "type": "Feature",
  "properties": {
    "iso:country":"US",
    "sg:address":"3092 Homer M Adams Pkwy",
    "sg:city":"Alton",
    "sg:classifiers":[
        {
            "category":"Personal",
            "subcategory":"Tanning Parlor",
            "type":"Services"
        }
    ],
    "sg:phone":"+1 618 465 2910",
    "sg:postcode":"62002",
    "sg:province":"IL",
    "sg:tags":[
        "salon"
    ],
    "wof:name":"Pacific Beach",
    "wof:placetype":"venue"
},
  "geometry": {"coordinates":[-90.143729,38.915447],"type":"Point"}
}