{
  "type": "Feature",
  "properties": {
    "iso:country":"US",
    "sg:address":"6004 W Main St",
    "sg:city":"Belleville",
    "sg:classifiers":[
        {
            "category":"Shopping",
            "subcategory":"Jewelry",
            "type":"Retail Goods"
        }
    ],
    "sg:phone":"+1 618 222 9533",
    "sg:postcode":"62223",
    "sg:province":"IL",
    "sg:tags":[
        "jeweler"
    ],
    "wof:name":"Gems & Jewels Jewlry Svc",
    "wof:placetype":"venue"
},
  "geometry": {"coordinates":[-90.036262,38.550517],"type":"Point"}
}