{
  "type": "Feature",
  "properties": {
    "iso:country":"US",
    "sg:address":"6120 S Racine Ave",
    "sg:city":"Chicago",
    "sg:classifiers":[
        {
            "category":"Government",
            "subcategory":"Police Station",
            "type":"Public Place"
        },
        {
            "category":"Government",
            "subcategory":"Office",
            "type":"Public Place"
        }
    ],
    "sg:phone":"+1 312 747 8220",
    "sg:postcode":"60636",
    "sg:province":"IL",
    "sg:tags":[
        "department",
        "township",
        "government-city",
        "village"
    ],
    "sg:website":"https://portal.chicagopolice.org/portal/page/portal/ClearPath/Communities/Districts/District7",
    "wof:name":"Chicago Police Department - 7th District - Englewood",
    "wof:placetype":"venue"
},
  "geometry": {"coordinates":[-87.65459,41.782852],"type":"Point"}
}