{
  "type": "Feature",
  "properties": {
    "iso:country":"US",
    "sg:address":"2321 Concord Arenzville Rd",
    "sg:city":"Arenzville",
    "sg:classifiers":[
        {
            "category":"Transit Center",
            "subcategory":"Freight",
            "type":"Transportation"
        },
        {
            "category":"Freight",
            "type":"Transportation"
        }
    ],
    "sg:phone":"+1 217 997 5575",
    "sg:postcode":"62611",
    "sg:province":"IL",
    "sg:tags":[
        "local",
        "trucking-motor",
        "trucking"
    ],
    "wof:name":"Schnitker Truck Lines",
    "wof:placetype":"venue"
},
  "geometry": {"coordinates":[-90.372147,39.861092],"type":"Point"}
}