{
  "type": "Feature",
  "properties": {
    "addr:full":"1311 297th St Viola IL 61486",
    "addr:housenumber":"1311",
    "addr:postcode":"61486",
    "addr:street":"297Th St",
    "iso:country":"US",
    "sg:address":"1311 297th St",
    "sg:city":"Viola",
    "sg:phone":"+1 309 667 2209",
    "sg:postcode":"61486",
    "sg:province":"IL",
    "sg:tags":[
        "farm",
        "corn"
    ],
    "wof:name":"Ray Zurcher",
    "wof:placetype":"venue"
},
  "geometry": {"coordinates":[-90.517882,41.253983],"type":"Point"}
}