{
  "type": "Feature",
  "properties": {
    "iso:country":"US",
    "sg:address":"1334 Old Ripley Rd",
    "sg:city":"Sorento",
    "sg:classifiers":[
        {
            "category":"Professional",
            "subcategory":"Accounting & Tax Preparation",
            "type":"Services"
        }
    ],
    "sg:phone":"+1 217 272 4346",
    "sg:postcode":"62086",
    "sg:province":"IL",
    "sg:tags":[
        "return"
    ],
    "wof:name":"Ua Inc",
    "wof:placetype":"venue"
},
  "geometry": {"coordinates":[-89.570306,38.934233],"type":"Point"}
}