{
  "type": "Feature",
  "properties": {
    "iso:country":"US",
    "sg:address":"735 Green Garden Pl",
    "sg:city":"Lockport",
    "sg:classifiers":[
        {
            "category":"Education",
            "subcategory":"School",
            "type":"Public Place"
        }
    ],
    "sg:phone":"+1 815 726 6156",
    "sg:postcode":"60441",
    "sg:province":"IL",
    "wof:name":"Fairmont Elementary School",
    "wof:placetype":"venue"
},
  "geometry": {"coordinates":[-88.063487,41.564228],"type":"Point"}
}