{
  "type": "Feature",
  "properties": {
    "iso:country":"US",
    "sg:address":"2513 Lundgren Rd",
    "sg:city":"Pecatonica",
    "sg:classifiers":[
        {
            "category":"Professional",
            "subcategory":"Art Services",
            "type":"Services"
        }
    ],
    "sg:phone":"+1 815 239 1164",
    "sg:postcode":"61063",
    "sg:province":"IL",
    "sg:tags":[
        "commercial",
        "design"
    ],
    "wof:name":"Art Design",
    "wof:placetype":"venue"
},
  "geometry": {"coordinates":[-89.339668,42.300088],"type":"Point"}
}