{
  "type": "Feature",
  "properties": {
    "iso:country":"US",
    "sg:address":"855 W Belmont Ave",
    "sg:city":"Chicago",
    "sg:classifiers":[
        {
            "category":"Shopping",
            "subcategory":"Shoes",
            "type":"Retail Goods"
        },
        {
            "category":"Shopping",
            "subcategory":"Used Merchandise",
            "type":"Retail Goods"
        }
    ],
    "sg:phone":"+1 773 549 1038",
    "sg:postcode":"60657",
    "sg:province":"IL",
    "sg:tags":[
        "vintage",
        "consignment",
        "store"
    ],
    "sg:website":"www.belmontarmy.com/",
    "wof:name":"Belmont Army",
    "wof:placetype":"venue"
},
  "geometry": {"coordinates":[-87.651492,41.939667],"type":"Point"}
}