{
  "type": "Feature",
  "properties": {
    "iso:country":"US",
    "sg:address":"1834 S Ashland Ave",
    "sg:city":"Chicago",
    "sg:classifiers":[
        {
            "category":"Personal",
            "subcategory":"Day Spa",
            "type":"Services"
        }
    ],
    "sg:phone":"+1 312 624 8396",
    "sg:postcode":"60608",
    "sg:province":"IL",
    "sg:website":"www.studio18spatique.com",
    "wof:name":"Rockstar Hair Boutique & Day Spa",
    "wof:placetype":"venue"
},
  "geometry": {"coordinates":[-87.666493,41.856742],"type":"Point"}
}