{
  "type": "Feature",
  "properties": {
    "addr:full":"2400 N Ashland Avenue Chicago IL 60614",
    "addr:housenumber":"2400",
    "addr:postcode":"60614",
    "addr:street":"N Ashland Avenue",
    "iso:country":"US",
    "sg:address":"2400 N Ashland Avenue",
    "sg:city":"Chicago",
    "sg:classifiers":[
        {
            "category":"Health Services",
            "subcategory":"Doctor",
            "type":"Services"
        }
    ],
    "sg:phone":"+1 773 348 2500",
    "sg:postcode":"60614",
    "sg:province":"IL",
    "sg:tags":[
        "practice",
        "family"
    ],
    "wof:name":"Occupational Health Services",
    "wof:placetype":"venue"
},
  "geometry": {"coordinates":[-87.66806099999999,41.925301],"type":"Point"}
}