{
  "type": "Feature",
  "properties": {
    "addr:full":"1100 N Cicero Ave Chicago IL 60651",
    "addr:housenumber":"1100",
    "addr:postcode":"60651",
    "addr:street":"N Cicero Ave",
    "iso:country":"US",
    "sg:address":"1100 N Cicero Ave",
    "sg:city":"Chicago",
    "sg:classifiers":[
        {
            "category":"Shopping",
            "subcategory":"Gifts & Souvenirs",
            "type":"Retail Goods"
        }
    ],
    "sg:phone":"+1 773 379 7878",
    "sg:postcode":"60651",
    "sg:province":"IL",
    "sg:tags":[
        "material",
        "wrapping"
    ],
    "wof:name":"Flex-O-Glass Inc.",
    "wof:placetype":"venue"
},
  "geometry": {"coordinates":[-87.745918,41.90049],"type":"Point"}
}