{
  "type": "Feature",
  "properties": {
    "iso:country":"US",
    "sg:address":"5105 34th Ave",
    "sg:city":"Moline",
    "sg:classifiers":[
        {
            "category":"Building & Trades",
            "subcategory":"Construction",
            "type":"Services"
        }
    ],
    "sg:phone":"+1 309 764 2961",
    "sg:postcode":"61265",
    "sg:province":"IL",
    "sg:tags":[
        "contractor"
    ],
    "wof:name":"Mattecheck Roger G & Son Construction Co",
    "wof:placetype":"venue"
},
  "geometry": {"coordinates":[-90.46669799999999,41.4786],"type":"Point"}
}