{
  "type": "Feature",
  "properties": {
    "addr:full":"2122 Marshall Ave Mattoon IL 61938",
    "addr:housenumber":"2122",
    "addr:postcode":"61938",
    "addr:street":"Marshall Ave",
    "iso:country":"US",
    "sg:address":"2122 Marshall Ave",
    "sg:city":"Mattoon",
    "sg:classifiers":[
        {
            "category":"Retail",
            "subcategory":"Auto Repair",
            "type":"Services"
        }
    ],
    "sg:phone":"+1 217 234 3939",
    "sg:postcode":"61938",
    "sg:province":"IL",
    "sg:tags":[
        "general"
    ],
    "wof:name":"Rich's Garage",
    "wof:placetype":"venue"
},
  "geometry": {"coordinates":[-88.38139200000001,39.477927],"type":"Point"}
}