{
  "type": "Feature",
  "properties": {
    "addr:full":"301 N Main St Sandoval IL 62882",
    "addr:housenumber":"301",
    "addr:postcode":"62882",
    "addr:street":"N Main St",
    "iso:country":"US",
    "sg:address":"301 N Main St",
    "sg:city":"Sandoval",
    "sg:classifiers":[
        {
            "category":"Bars & Pubs",
            "type":"Food & Drink"
        }
    ],
    "sg:phone":"+1 618 247 3423",
    "sg:postcode":"62882",
    "sg:province":"IL",
    "wof:name":"Bub's Pub Inc",
    "wof:placetype":"venue"
},
  "geometry": {"coordinates":[-89.12067399999999,38.616051],"type":"Point"}
}