{
  "type": "Feature",
  "properties": {
    "iso:country":"US",
    "sg:address":"14503 S Union Ave",
    "sg:city":"Riverdale",
    "sg:classifiers":[
        {
            "category":"Social Services",
            "subcategory":"Adult Care",
            "type":"Services"
        }
    ],
    "sg:phone":"+1 708 606 9928",
    "sg:postcode":"60827",
    "sg:province":"IL",
    "sg:tags":[
        "residential"
    ],
    "wof:name":"Lucy Love Senior Care",
    "wof:placetype":"venue"
},
  "geometry": {"coordinates":[-87.638953,41.629886],"type":"Point"}
}