{
  "type": "Feature",
  "properties": {
    "iso:country":"US",
    "sg:address":"628 Palestine Rd",
    "sg:city":"Chester",
    "sg:classifiers":[
        {
            "category":"Manufacturing",
            "subcategory":"Buildings",
            "type":"Manufacturing & Wholesale Goods"
        },
        {
            "category":"Building & Trades",
            "subcategory":"Construction",
            "type":"Services"
        }
    ],
    "sg:phone":"+1 618 826 5013",
    "sg:postcode":"62233",
    "sg:province":"IL",
    "sg:tags":[
        "industrial",
        "system",
        "specialty",
        "builder",
        "heating",
        "contractor",
        "contractors-commercial",
        "home",
        "air conditioning"
    ],
    "wof:name":"G R E Construction",
    "wof:placetype":"venue"
},
  "geometry": {"coordinates":[-89.822028,37.920747],"type":"Point"}
}