{
  "type": "Feature",
  "properties": {
    "addr:full":"15344 129th St Lemont IL 60439",
    "addr:housenumber":"15344",
    "addr:postcode":"60439",
    "addr:street":"129Th St",
    "iso:country":"US",
    "sg:address":"15344 129th St",
    "sg:city":"Lemont",
    "sg:classifiers":[
        {
            "category":"Real Estate",
            "subcategory":"Architect",
            "type":"Services"
        }
    ],
    "sg:phone":"+1 630 243 1192",
    "sg:postcode":"60439",
    "sg:province":"IL",
    "sg:tags":[
        "estimate",
        "construction"
    ],
    "wof:name":"Derek's Construction",
    "wof:placetype":"venue"
},
  "geometry": {"coordinates":[-87.993819,41.652969],"type":"Point"}
}