{
  "type": "Feature",
  "properties": {
    "iso:country":"US",
    "sg:address":"290 S North St",
    "sg:city":"Argenta",
    "sg:classifiers":[
        {
            "category":"Restaurant",
            "type":"Food & Drink"
        },
        {
            "category":"Food & Beverages",
            "subcategory":"Groceries & Convenience Stores",
            "type":"Retail Goods"
        }
    ],
    "sg:menulink":"http://www.allmenus.com/il/friends-creek/226155-caseys-general-store/menu/",
    "sg:phone":"+1 217 795 2051",
    "sg:postcode":"62501",
    "sg:province":"IL",
    "sg:tags":[
        "american",
        "pizza"
    ],
    "wof:name":"Casey's General Store",
    "wof:placetype":"venue"
},
  "geometry": {"coordinates":[-88.822452,39.979106],"type":"Point"}
}