{
  "type": "Feature",
  "properties": {
    "iso:country":"US",
    "sg:address":"319 S Rohlwing Rd",
    "sg:city":"Palatine",
    "sg:classifiers":[
        {
            "category":"Restaurant",
            "type":"Food & Drink"
        }
    ],
    "sg:phone":"+1   ",
    "sg:postcode":"60074",
    "sg:province":"IL",
    "sg:tags":[
        "eating"
    ],
    "wof:name":"Mr Beefys",
    "wof:placetype":"venue"
},
  "geometry": {"coordinates":[-88.024127,42.103574],"type":"Point"}
}