{
  "type": "Feature",
  "properties": {
    "iso:country":"US",
    "sg:address":"4304 W Shamrock Ln",
    "sg:city":"Mc Henry",
    "sg:classifiers":[
        {
            "category":"Professional",
            "subcategory":"Business Services",
            "type":"Services"
        }
    ],
    "sg:phone":"+1 815 790 9410",
    "sg:postcode":"60050",
    "sg:province":"IL",
    "wof:name":"Allay Home Care Agency Inc",
    "wof:placetype":"venue"
},
  "geometry": {"coordinates":[-88.281824,42.314686],"type":"Point"}
}