{
  "type": "Feature",
  "properties": {
    "addr:full":"23153 W Miller Rd Lake Zurich IL 60047",
    "addr:housenumber":"23153",
    "addr:postcode":"60047",
    "addr:street":"W Miller Rd",
    "iso:country":"US",
    "sg:address":"23153 W Miller Rd",
    "sg:city":"Lake Zurich",
    "sg:classifiers":[
        {
            "category":"Organizations",
            "subcategory":"Religious Organization",
            "type":"Services"
        }
    ],
    "sg:phone":"+1 847 540 8289",
    "sg:postcode":"60047",
    "sg:province":"IL",
    "wof:name":"Alpine Chapel",
    "wof:placetype":"venue"
},
  "geometry": {"coordinates":[-88.08981799999999,42.214944],"type":"Point"}
}