{
  "type": "Feature",
  "properties": {
    "iso:country":"US",
    "sg:address":"14378 N 100th St",
    "sg:city":"Brocton",
    "sg:classifiers":[
        {
            "category":"Farming",
            "subcategory":"Farm",
            "type":"Manufacturing & Wholesale Goods"
        }
    ],
    "sg:phone":"+1 217 346 2107",
    "sg:postcode":"61917",
    "sg:province":"IL",
    "wof:name":"Richard Wright Tenant Farm",
    "wof:placetype":"venue"
},
  "geometry": {"coordinates":[-87.946882,39.677812],"type":"Point"}
}