{
  "type": "Feature",
  "properties": {
    "addr:full":"65 N River Ln Ste 210 Geneva IL 60134",
    "addr:housenumber":"65",
    "addr:postcode":"60134",
    "addr:street":"N River Ln Ste 210",
    "iso:country":"US",
    "sg:address":"65 N River Ln Ste 210",
    "sg:city":"Geneva",
    "sg:classifiers":[
        {
            "category":"Banks & Credit Unions",
            "subcategory":"Investment Brokerage",
            "type":"Services"
        },
        {
            "category":"Banks & Credit Unions",
            "subcategory":"Financial Services",
            "type":"Services"
        }
    ],
    "sg:phone":"+1 630 845 0820",
    "sg:postcode":"60134",
    "sg:province":"IL",
    "sg:tags":[
        "advisory",
        "security",
        "management",
        "planner"
    ],
    "wof:name":"John Locke Investments Inc",
    "wof:placetype":"venue"
},
  "geometry": {"coordinates":[-88.303569,41.888095],"type":"Point"}
}