{
  "type": "Feature",
  "properties": {
    "iso:country":"US",
    "sg:address":"303 Amphitheater Dr",
    "sg:city":"Rockford",
    "sg:classifiers":[
        {
            "category":"Health Services",
            "subcategory":"Health Practitioner",
            "type":"Services"
        }
    ],
    "sg:phone":"+1 815 963 7272",
    "sg:postcode":"61107",
    "sg:province":"IL",
    "wof:name":"Teresa Roden",
    "wof:placetype":"venue"
},
  "geometry": {"coordinates":[-88.973167,42.271472],"type":"Point"}
}