{
  "type": "Feature",
  "properties": {
    "iso:country":"US",
    "sg:address":"535 Aptakisic Rd",
    "sg:city":"Lincolnshire",
    "sg:classifiers":[
        {
            "category":"Building & Trades",
            "subcategory":"Landscaping Services",
            "type":"Services"
        }
    ],
    "sg:phone":"+1 847 256 8733",
    "sg:postcode":"60069",
    "sg:province":"IL",
    "sg:tags":[
        "tree"
    ],
    "sg:website":"www.sunrisetree.com",
    "wof:name":"Sunrise Tree & Mulch Svc",
    "wof:placetype":"venue"
},
  "geometry": {"coordinates":[-87.93040499999999,42.181279],"type":"Point"}
}