{
  "type": "Feature",
  "properties": {
    "iso:country":"US",
    "sg:address":"4590 N 11000W Rd",
    "sg:city":"Bonfield",
    "sg:classifiers":[
        {
            "category":"Wholesale",
            "subcategory":"Machinery & Supplies",
            "type":"Manufacturing & Wholesale Goods"
        }
    ],
    "sg:phone":"+1 815 421 0064",
    "sg:postcode":"60913",
    "sg:province":"IL",
    "sg:tags":[
        "farm",
        "equipment"
    ],
    "sg:website":"www.shoupparts.com",
    "wof:name":"Little Co",
    "wof:placetype":"venue"
},
  "geometry": {"coordinates":[-88.088957,41.17609],"type":"Point"}
}