{
  "type": "Feature",
  "properties": {
    "addr:full":"6349 S Cottage Grove Ave Chicago IL 60637",
    "addr:housenumber":"6349",
    "addr:postcode":"60637",
    "addr:street":"S Cottage Grove Ave",
    "iso:country":"US",
    "sg:address":"6349 S Cottage Grove Ave",
    "sg:city":"Chicago",
    "sg:classifiers":[
        {
            "category":"Social Services",
            "type":"Services"
        }
    ],
    "sg:phone":"+1 773 772 1213",
    "sg:postcode":"60637",
    "sg:province":"IL",
    "sg:tags":[
        "consultant",
        "security",
        "representative"
    ],
    "sg:website":"http://www.ssa.gov",
    "wof:name":"Social Security Administration",
    "wof:placetype":"venue"
},
  "geometry": {"coordinates":[-87.605896,41.779508],"type":"Point"}
}