{
  "type": "Feature",
  "properties": {
    "iso:country":"US",
    "sg:address":"621 S 8th St",
    "sg:city":"West Dundee",
    "sg:classifiers":[
        {
            "category":"Food & Beverages",
            "subcategory":"Groceries & Convenience Stores",
            "type":"Retail Goods"
        }
    ],
    "sg:phone":"+1 847 426 0225",
    "sg:postcode":"60118",
    "sg:province":"IL",
    "sg:website":"www.7-eleven.com",
    "wof:name":"7-Eleven",
    "wof:placetype":"venue"
},
  "geometry": {"coordinates":[-88.288567,42.090846],"type":"Point"}
}