{
  "type": "Feature",
  "properties": {
    "addr:full":"7337 N 1100th St Watson IL 62473",
    "addr:housenumber":"7337",
    "addr:postcode":"62473",
    "addr:street":"N 1100Th St",
    "iso:country":"US",
    "sg:address":"7337 N 1100th St",
    "sg:city":"Watson",
    "sg:classifiers":[
        {
            "category":"Farming",
            "subcategory":"Farm",
            "type":"Manufacturing & Wholesale Goods"
        }
    ],
    "sg:phone":"+1 217 536 5823",
    "sg:postcode":"62473",
    "sg:province":"IL",
    "sg:tags":[
        "crop",
        "general"
    ],
    "wof:name":"Lyle Westfall",
    "wof:placetype":"venue"
},
  "geometry": {"coordinates":[-88.596599,39.028852],"type":"Point"}
}