{
  "type": "Feature",
  "properties": {
    "addr:full":"289 S Bolingbrook Dr Bolingbrook IL 60440",
    "addr:housenumber":"289",
    "addr:postcode":"60440",
    "addr:street":"S Bolingbrook Dr",
    "iso:country":"US",
    "sg:address":"289 S Bolingbrook Dr",
    "sg:city":"Bolingbrook",
    "sg:classifiers":[
        {
            "category":"Restaurant",
            "type":"Food & Drink"
        }
    ],
    "sg:phone":"+1 630 759 6667",
    "sg:postcode":"60440",
    "sg:province":"IL",
    "wof:name":"Doggie Diner 2",
    "wof:placetype":"venue"
},
  "geometry": {"coordinates":[-88.068316,41.69353],"type":"Point"}
}