{
  "type": "Feature",
  "properties": {
    "iso:country":"US",
    "sg:address":"155 W 115th St",
    "sg:city":"Chicago",
    "sg:classifiers":[
        {
            "category":"Food & Beverages",
            "subcategory":"Bakery",
            "type":"Retail Goods"
        },
        {
            "category":"Wholesale",
            "subcategory":"Groceries",
            "type":"Manufacturing & Wholesale Goods"
        }
    ],
    "sg:phone":"+1 773 785 2731",
    "sg:postcode":"60628",
    "sg:province":"IL",
    "sg:tags":[
        "cooky",
        "crackers-wholesale",
        "bakers-wholesale",
        "manufacturer"
    ],
    "wof:name":"Cookies House Of Care",
    "wof:placetype":"venue"
},
  "geometry": {"coordinates":[-87.626925,41.685284],"type":"Point"}
}