{
  "type": "Feature",
  "properties": {
    "iso:country":"US",
    "sg:address":"1401 E State St",
    "sg:city":"Rockford",
    "sg:classifiers":[
        {
            "category":"Social Services",
            "type":"Services"
        }
    ],
    "sg:phone":"+1 815 966 2696",
    "sg:postcode":"61104",
    "sg:province":"IL",
    "wof:name":"Children First Program",
    "wof:placetype":"venue"
},
  "geometry": {"coordinates":[-89.072006,42.267033],"type":"Point"}
}