{
  "type": "Feature",
  "properties": {
    "iso:country":"US",
    "sg:address":"21W580 Lynn Rd",
    "sg:city":"Lombard",
    "sg:classifiers":[
        {
            "category":"Building & Trades",
            "subcategory":"Cleaning & Sanitation",
            "type":"Services"
        }
    ],
    "sg:phone":"+1 630 827 1414",
    "sg:postcode":"60148",
    "sg:province":"IL",
    "sg:tags":[
        "home"
    ],
    "wof:name":"Lorrie's Cleaning Service",
    "wof:placetype":"venue"
},
  "geometry": {"coordinates":[-88.045502,41.898998],"type":"Point"}
}