{
  "type": "Feature",
  "properties": {
    "iso:country":"US",
    "sg:address":"6415 S State Street",
    "sg:city":"Chicago",
    "sg:classifiers":[
        {
            "category":"Building & Trades",
            "subcategory":"Construction",
            "type":"Services"
        }
    ],
    "sg:phone":"+1 773 496 5140",
    "sg:postcode":"60637",
    "sg:province":"IL",
    "sg:tags":[
        "contractor"
    ],
    "wof:name":"G & M Roofing",
    "wof:placetype":"venue"
},
  "geometry": {"coordinates":[-87.624983,41.776136],"type":"Point"}
}