{
  "type": "Feature",
  "properties": {
    "addr:full":"110 Schiller St Elmhurst IL 60126",
    "addr:housenumber":"110",
    "addr:postcode":"60126",
    "addr:street":"Schiller St",
    "iso:country":"US",
    "sg:address":"110 Schiller St",
    "sg:city":"Elmhurst",
    "sg:classifiers":[
        {
            "category":"Insurance",
            "subcategory":"Insurance Agent",
            "type":"Services"
        }
    ],
    "sg:phone":"+1 630 530 0344",
    "sg:postcode":"60126",
    "sg:province":"IL",
    "wof:name":"Centaurus Financial Inc",
    "wof:placetype":"venue"
},
  "geometry": {"coordinates":[-87.938553,41.901047],"type":"Point"}
}