{
  "type": "Feature",
  "properties": {
    "addr:full":"5614 W Higgins Ave Chicago IL 60630",
    "addr:housenumber":"5614",
    "addr:postcode":"60630",
    "addr:street":"W Higgins Ave",
    "iso:country":"US",
    "sg:address":"5614 W Higgins Ave",
    "sg:city":"Chicago",
    "sg:classifiers":[
        {
            "category":"Building & Trades",
            "subcategory":"Construction",
            "type":"Services"
        }
    ],
    "sg:phone":"+1 312 601 9963",
    "sg:postcode":"60630",
    "sg:province":"IL",
    "sg:tags":[
        "system",
        "specialty",
        "heating",
        "contractor",
        "air conditioning"
    ],
    "wof:name":"Comfort Air Heating & Air Conditioning",
    "wof:placetype":"venue"
},
  "geometry": {"coordinates":[-87.768044,41.970462],"type":"Point"}
}