{
  "type": "Feature",
  "properties": {
    "addr:full":"5790 N Lincoln Avenue Chicago IL 60659",
    "addr:housenumber":"5790",
    "addr:postcode":"60659",
    "addr:street":"N Lincoln Avenue",
    "iso:country":"US",
    "sg:address":"5790 N Lincoln Avenue",
    "sg:city":"Chicago",
    "sg:classifiers":[
        {
            "category":"Real Estate",
            "subcategory":"Architect",
            "type":"Services"
        }
    ],
    "sg:phone":"+1 773 878 2286",
    "sg:postcode":"60659",
    "sg:province":"IL",
    "wof:name":"Ebenbrook",
    "wof:placetype":"venue"
},
  "geometry": {"coordinates":[-87.701066,41.986646],"type":"Point"}
}