{
  "type": "Feature",
  "properties": {
    "addr:full":"5089 Herrin Rd Carterville IL 62918",
    "addr:postcode":"5089;62918",
    "addr:street":"Herrin Rd",
    "iso:country":"US",
    "sg:address":"5089 Herrin Rd",
    "sg:city":"Carterville",
    "sg:classifiers":[
        {
            "category":"Retail",
            "subcategory":"Animal Services",
            "type":"Services"
        }
    ],
    "sg:phone":"+1 618 942 2466",
    "sg:postcode":"62918",
    "sg:province":"IL",
    "wof:name":"McBee Peggy",
    "wof:placetype":"venue"
},
  "geometry": {"coordinates":[-89.06267,37.81115],"type":"Point"}
}