{
  "type": "Feature",
  "properties": {
    "iso:country":"US",
    "sg:address":"5123 W Hutchinson St",
    "sg:city":"Chicago",
    "sg:classifiers":[
        {
            "category":"Building & Trades",
            "subcategory":"Construction",
            "type":"Services"
        }
    ],
    "sg:phone":"+1 773 286 2270",
    "sg:postcode":"60641",
    "sg:province":"IL",
    "sg:tags":[
        "house"
    ],
    "wof:name":"Mike Travers Construction",
    "wof:placetype":"venue"
},
  "geometry": {"coordinates":[-87.756758,41.957793],"type":"Point"}
}