{
  "type": "Feature",
  "properties": {
    "addr:full":"225 S Canal St Chicago IL 60606",
    "addr:housenumber":"225",
    "addr:postcode":"60606",
    "addr:street":"S Canal St",
    "iso:country":"US",
    "sg:address":"225 S Canal St",
    "sg:city":"Chicago",
    "sg:classifiers":[
        {
            "category":"Juice Bar",
            "subcategory":"None",
            "type":"Food & Drink"
        }
    ],
    "sg:phone":"+1 312 382 9904",
    "sg:postcode":"60606",
    "sg:province":"IL",
    "sg:tags":[
        "smoothy"
    ],
    "sg:website":"www.jambajuice.com",
    "wof:name":"Jamba Juice",
    "wof:placetype":"venue"
},
  "geometry": {"coordinates":[-87.637001,41.882301],"type":"Point"}
}