{
  "type": "Feature",
  "properties": {
    "addr:full":"750 Missouri Ave East Saint Louis IL 62201",
    "addr:housenumber":"750",
    "addr:postcode":"62201",
    "addr:street":"Missouri Ave East",
    "iso:country":"US",
    "sg:address":"750 Missouri Ave",
    "sg:city":"East Saint Louis",
    "sg:classifiers":[
        {
            "category":"Professional",
            "subcategory":"Secretarial Services",
            "type":"Services"
        }
    ],
    "sg:phone":"+1 618 482 9124",
    "sg:postcode":"62201",
    "sg:province":"IL",
    "sg:tags":[
        "federal",
        "official",
        "court",
        "reporter"
    ],
    "wof:name":"US District Court",
    "wof:placetype":"venue"
},
  "geometry": {"coordinates":[-90.15618600000001,38.623927],"type":"Point"}
}