{
  "type": "Feature",
  "properties": {
    "addr:full":"7247 S Peoria St Chicago IL 60621",
    "addr:housenumber":"7247",
    "addr:postcode":"60621",
    "addr:street":"S Peoria St",
    "iso:country":"US",
    "sg:address":"7247 S Peoria St",
    "sg:city":"Chicago",
    "sg:classifiers":[
        {
            "category":"Building & Trades",
            "subcategory":"Plumbing",
            "type":"Services"
        }
    ],
    "sg:phone":"+1 773 224 9726",
    "sg:postcode":"60621",
    "sg:province":"IL",
    "sg:tags":[
        "plumber",
        "industrial",
        "contractors-commercial"
    ],
    "wof:name":"Toms Maint Plumbing",
    "wof:placetype":"venue"
},
  "geometry": {"coordinates":[-87.64676799999999,41.762481],"type":"Point"}
}