{
  "type": "Feature",
  "properties": {
    "iso:country":"US",
    "sg:address":"769 N Virn Allen Ct",
    "sg:city":"Palatine",
    "sg:classifiers":[
        {
            "category":"Manufacturing",
            "subcategory":"Printing",
            "type":"Manufacturing & Wholesale Goods"
        }
    ],
    "sg:phone":"+1 847 359 8639",
    "sg:postcode":"60067",
    "sg:province":"IL",
    "sg:tags":[
        "commercial"
    ],
    "wof:name":"JC Sales",
    "wof:placetype":"venue"
},
  "geometry": {"coordinates":[-88.062388,42.124595],"type":"Point"}
}