{
  "type": "Feature",
  "properties": {
    "iso:country":"US",
    "sg:address":"1555 Sherman Ave",
    "sg:city":"Evanston",
    "sg:classifiers":[
        {
            "category":"Retail",
            "subcategory":"Laundry & Dry Cleaning",
            "type":"Services"
        }
    ],
    "sg:phone":"+1 847 328 2321",
    "sg:postcode":"60201",
    "sg:province":"IL",
    "sg:tags":[
        "cleaners",
        "rug",
        "carpet"
    ],
    "wof:name":"Coit Drapery & Carpet Cleaners",
    "wof:placetype":"venue"
},
  "geometry": {"coordinates":[-87.68181,42.045629],"type":"Point"}
}