{
  "type": "Feature",
  "properties": {
    "iso:country":"US",
    "sg:address":"3325 W Belmont Avenue",
    "sg:city":"Chicago",
    "sg:classifiers":[
        {
            "category":"Real Estate",
            "subcategory":"Real Estate Services",
            "type":"Services"
        }
    ],
    "sg:phone":"+1 773 267 4040",
    "sg:postcode":"60618",
    "sg:province":"IL",
    "sg:tags":[
        "management",
        "property"
    ],
    "wof:name":"Felmar Realty",
    "wof:placetype":"venue"
},
  "geometry": {"coordinates":[-87.710533,41.939192],"type":"Point"}
}