{
  "type": "Feature",
  "properties": {
    "iso:country":"US",
    "sg:address":"112 W 87th St #M5",
    "sg:city":"Chicago",
    "sg:classifiers":[
        {
            "category":"Utilities",
            "subcategory":"Mobile Phone",
            "type":"Services"
        },
        {
            "category":"Shopping",
            "subcategory":"Mobile Phones",
            "type":"Retail Goods"
        }
    ],
    "sg:phone":"+1 847 315 9754",
    "sg:postcode":"60620",
    "sg:province":"IL",
    "sg:tags":[
        "supply",
        "communication",
        "telephone",
        "wireless",
        "equipment",
        "cellular"
    ],
    "sg:website":"http://www.mycricket.com",
    "wof:name":"Cricket Wireless - Chatham Ridge Shopping Center",
    "wof:placetype":"venue"
},
  "geometry": {"coordinates":[-87.626825,41.736286],"type":"Point"}
}