{
  "type": "Feature",
  "properties": {
    "addr:full":"5901 S Morgan Street Chicago IL 60621",
    "addr:housenumber":"5901",
    "addr:postcode":"60621",
    "addr:street":"S Morgan Street",
    "iso:country":"US",
    "sg:address":"5901 S Morgan Street",
    "sg:city":"Chicago",
    "sg:classifiers":[
        {
            "category":"Food & Beverages",
            "subcategory":"Groceries & Convenience Stores",
            "type":"Retail Goods"
        }
    ],
    "sg:phone":"+1 773 434 6239",
    "sg:postcode":"60621",
    "sg:province":"IL",
    "wof:name":"Morgan Mobil Fuel and Mini Mar",
    "wof:placetype":"venue"
},
  "geometry": {"coordinates":[-87.649619,41.786618],"type":"Point"}
}