{
  "type": "Feature",
  "properties": {
    "iso:country":"US",
    "sg:address":"4161 N Lincoln Ave",
    "sg:city":"Chicago",
    "sg:classifiers":[
        {
            "category":"Shopping",
            "subcategory":"Clothing, Apparel, & Fashions",
            "type":"Retail Goods"
        },
        {
            "category":"Shopping",
            "subcategory":"Jewelry",
            "type":"Retail Goods"
        }
    ],
    "sg:phone":"+1 773 525 4400",
    "sg:postcode":"60618",
    "sg:province":"IL",
    "sg:tags":[
        "accessory"
    ],
    "sg:website":"www.embellishchicago.com",
    "wof:name":"Embellish Chicago",
    "wof:placetype":"venue"
},
  "geometry": {"coordinates":[-87.68111399999999,41.957476],"type":"Point"}
}