{
  "type": "Feature",
  "properties": {
    "addr:full":"1700 E Washington St Joliet IL 60433",
    "addr:housenumber":"1700",
    "addr:postcode":"60433",
    "addr:street":"E Washington St",
    "iso:country":"US",
    "sg:address":"1700 E Washington St",
    "sg:city":"Joliet",
    "sg:classifiers":[
        {
            "category":"Restaurant",
            "type":"Food & Drink"
        }
    ],
    "sg:phone":"+1 815 726 5461",
    "sg:postcode":"60433",
    "sg:province":"IL",
    "wof:name":"Gyros Shack",
    "wof:placetype":"venue"
},
  "geometry": {"coordinates":[-88.039492,41.522628],"type":"Point"}
}