{
  "type": "Feature",
  "properties": {
    "addr:full":"27560 Ebenezer Rd Geneseo IL 61254",
    "addr:housenumber":"27560",
    "addr:postcode":"61254",
    "addr:street":"Ebenezer Rd",
    "iso:country":"US",
    "sg:address":"27560 Ebenezer Rd",
    "sg:city":"Geneseo",
    "sg:classifiers":[
        {
            "category":"Professional",
            "subcategory":"Testing Lab",
            "type":"Services"
        }
    ],
    "sg:phone":"+1 309 945 9090",
    "sg:postcode":"61254",
    "sg:province":"IL",
    "sg:tags":[
        "soil"
    ],
    "wof:name":"A & E Soil Consultants",
    "wof:placetype":"venue"
},
  "geometry": {"coordinates":[-90.123424,41.548256],"type":"Point"}
}