{
  "type": "Feature",
  "properties": {
    "addr:full":"5931 W North Ave Chicago IL 60639",
    "addr:housenumber":"5931",
    "addr:postcode":"60639",
    "addr:street":"W North Ave",
    "iso:country":"US",
    "sg:address":"5931 W North Ave",
    "sg:city":"Chicago",
    "sg:classifiers":[
        {
            "category":"Restaurant",
            "type":"Food & Drink"
        }
    ],
    "sg:postcode":"60639",
    "sg:province":"IL",
    "sg:tags":[
        "barbeque"
    ],
    "wof:name":"Joe's BBQ",
    "wof:placetype":"venue"
},
  "geometry": {"coordinates":[-87.774417,41.909207],"type":"Point"}
}