{
  "type": "Feature",
  "properties": {
    "iso:country":"US",
    "sg:address":"259 S Bolingbrook Dr",
    "sg:city":"Bolingbrook",
    "sg:classifiers":[
        {
            "category":"Shopping",
            "subcategory":"Beauty & Cosmetics",
            "type":"Retail Goods"
        }
    ],
    "sg:phone":"+1 630 378 5207",
    "sg:postcode":"60440",
    "sg:province":"IL",
    "sg:tags":[
        "equipment",
        "supply"
    ],
    "wof:name":"Sally Beauty Supply",
    "wof:placetype":"venue"
},
  "geometry": {"coordinates":[-88.06831,41.692679],"type":"Point"}
}