{
  "type": "Feature",
  "properties": {
    "iso:country":"US",
    "sg:address":"1617 W Jefferson St",
    "sg:city":"Joliet",
    "sg:classifiers":[
        {
            "category":"Government",
            "subcategory":"Office",
            "type":"Public Place"
        }
    ],
    "sg:phone":"+1 815 730 4200",
    "sg:postcode":"60435",
    "sg:province":"IL",
    "sg:tags":[
        "state",
        "resource"
    ],
    "wof:name":"Human Services Dept",
    "wof:placetype":"venue"
},
  "geometry": {"coordinates":[-88.12174899999999,41.522781],"type":"Point"}
}