{
  "type": "Feature",
  "properties": {
    "addr:full":"317 W 25th Pl Ste 3W Chicago IL 60616",
    "addr:housenumber":"317",
    "addr:postcode":"60616",
    "addr:street":"W 25Th Pl Ste 3W",
    "iso:country":"US",
    "sg:address":"317 W 25th Pl Ste 3W",
    "sg:city":"Chicago",
    "sg:classifiers":[
        {
            "category":"Professional",
            "subcategory":"Business Services",
            "type":"Services"
        }
    ],
    "sg:phone":"+1 312 473 4809",
    "sg:postcode":"60616",
    "sg:province":"IL",
    "sg:tags":[
        "consultant",
        "coach"
    ],
    "wof:name":"Resources Unlimited And Associates",
    "wof:placetype":"venue"
},
  "geometry": {"coordinates":[-87.634933,41.846397],"type":"Point"}
}