{
  "type": "Feature",
  "properties": {
    "addr:full":"444 N Bolingbrook Dr Bolingbrook IL 60440",
    "addr:housenumber":"444",
    "addr:postcode":"60440",
    "addr:street":"N Bolingbrook Dr",
    "iso:country":"US",
    "sg:address":"444 N Bolingbrook Dr",
    "sg:city":"Bolingbrook",
    "sg:classifiers":[
        {
            "category":"Restaurant",
            "type":"Food & Drink"
        }
    ],
    "sg:menulink":"http://www.allmenus.com/il/du-page/196170-taco-bell/menu/",
    "sg:postcode":"60440",
    "sg:province":"IL",
    "sg:tags":[
        "mexican"
    ],
    "wof:name":"Taco Bell",
    "wof:placetype":"venue"
},
  "geometry": {"coordinates":[-88.068601,41.709512],"type":"Point"}
}