{
  "type": "Feature",
  "properties": {
    "iso:country":"US",
    "sg:address":"12 SW 2nd St",
    "sg:city":"Galva",
    "sg:classifiers":[
        {
            "category":"Autos & Motor Vehicles",
            "subcategory":"Fuel & Gas Station",
            "type":"Retail Goods"
        },
        {
            "category":"Food & Beverages",
            "subcategory":"Groceries & Convenience Stores",
            "type":"Retail Goods"
        }
    ],
    "sg:phone":"+1 309 932 8935",
    "sg:postcode":"61434",
    "sg:province":"IL",
    "wof:name":"Gateway Express",
    "wof:placetype":"venue"
},
  "geometry": {"coordinates":[-90.042216,41.16419],"type":"Point"}
}