{
  "type": "Feature",
  "properties": {
    "addr:full":"453 S Main St White Hall IL 62092",
    "addr:housenumber":"453",
    "addr:postcode":"62092",
    "addr:street":"S Main St",
    "iso:country":"US",
    "sg:address":"453 S Main St",
    "sg:city":"White Hall",
    "sg:classifiers":[
        {
            "category":"Building & Trades",
            "subcategory":"Cleaning & Sanitation",
            "type":"Services"
        }
    ],
    "sg:phone":"+1 217 374 2974",
    "sg:postcode":"62092",
    "sg:province":"IL",
    "sg:tags":[
        "maintenance"
    ],
    "wof:name":"Coad Window Cleaning Service",
    "wof:placetype":"venue"
},
  "geometry": {"coordinates":[-90.40375899999999,39.431147],"type":"Point"}
}