{
  "type": "Feature",
  "properties": {
    "iso:country":"US",
    "sg:address":"410 N Maple St",
    "sg:city":"Effingham",
    "sg:classifiers":[
        {
            "category":"Shopping",
            "type":"Retail Goods"
        }
    ],
    "sg:phone":"+1 217 342 4636",
    "sg:postcode":"62401",
    "sg:province":"IL",
    "sg:tags":[
        "hearing",
        "equipment",
        "supply",
        "impaired"
    ],
    "wof:name":"Clark's Hearing Aid Svc",
    "wof:placetype":"venue"
},
  "geometry": {"coordinates":[-88.549178,39.124574],"type":"Point"}
}