{
  "type": "Feature",
  "properties": {
    "iso:country":"US",
    "sg:address":"225 N 10th St",
    "sg:city":"Mount Vernon",
    "sg:classifiers":[
        {
            "category":"Health Services",
            "subcategory":"Nursing And Care Facility",
            "type":"Services"
        }
    ],
    "sg:phone":"+1 618 244 2540",
    "sg:postcode":"62864",
    "sg:province":"IL",
    "wof:name":"Begley-Harrison Business ADM",
    "wof:placetype":"venue"
},
  "geometry": {"coordinates":[-88.904031,38.319799],"type":"Point"}
}