{
  "type": "Feature",
  "properties": {
    "addr:full":"895 Schomer Rd Aurora IL 60505",
    "addr:housenumber":"895",
    "addr:postcode":"60505",
    "addr:street":"Schomer Rd",
    "iso:country":"US",
    "sg:address":"895 Schomer Rd",
    "sg:city":"Aurora",
    "sg:classifiers":[
        {
            "category":"Professional",
            "type":"Services"
        }
    ],
    "sg:phone":"+1 630 820 0353",
    "sg:postcode":"60505",
    "sg:province":"IL",
    "wof:name":"Just In Time Services",
    "wof:placetype":"venue"
},
  "geometry": {"coordinates":[-88.294392,41.793726],"type":"Point"}
}