{
  "type": "Feature",
  "properties": {
    "addr:full":"1641 US Rte 52 Dixon IL 61021",
    "addr:housenumber":"1641",
    "addr:postcode":"61021",
    "addr:street":"Us Rte 52",
    "iso:country":"US",
    "sg:address":"1641 US Rte 52",
    "sg:city":"Dixon",
    "sg:classifiers":[
        {
            "category":"Organizations",
            "subcategory":"Community Association",
            "type":"Services"
        }
    ],
    "sg:phone":"+1 815 288 0984",
    "sg:postcode":"61021",
    "sg:province":"IL",
    "wof:name":"Sterling Noon Lions Club",
    "wof:placetype":"venue"
},
  "geometry": {"coordinates":[-89.43527899999999,41.815816],"type":"Point"}
}