{
  "type": "Feature",
  "properties": {
    "addr:full":"2515 S Wabash Ave Chicago IL 60616",
    "addr:housenumber":"2515",
    "addr:postcode":"60616",
    "addr:street":"S Wabash Ave",
    "iso:country":"US",
    "sg:address":"2515 S Wabash Ave",
    "sg:city":"Chicago",
    "sg:classifiers":[
        {
            "category":"Building & Trades",
            "subcategory":"Plumbing",
            "type":"Services"
        },
        {
            "category":"Building & Trades",
            "subcategory":"Construction",
            "type":"Services"
        }
    ],
    "sg:phone":"+1 312 326 4100",
    "sg:postcode":"60616",
    "sg:province":"IL",
    "sg:tags":[
        "plumber",
        "industrial",
        "contractor",
        "contractors-commercial",
        "mechanical"
    ],
    "sg:website":"http://www.gf.org",
    "wof:name":"G. F. Connelly Mechanical Contractors, Inc.",
    "wof:placetype":"venue"
},
  "geometry": {"coordinates":[-87.625343,41.846982],"type":"Point"}
}