{
  "type": "Feature",
  "properties": {
    "addr:full":"2600 Humbert St Alton IL 62002",
    "addr:postcode":"2600;62002",
    "addr:street":"Humbert St",
    "iso:country":"US",
    "sg:address":"2600 Humbert St",
    "sg:city":"Alton",
    "sg:classifiers":[
        {
            "category":"Education",
            "subcategory":"Special Training",
            "type":"Public Place"
        }
    ],
    "sg:phone":"+1 314 341 1553",
    "sg:postcode":"62002",
    "sg:province":"IL",
    "sg:tags":[
        "educational"
    ],
    "wof:name":"Seed Of Success",
    "wof:placetype":"venue"
},
  "geometry": {"coordinates":[-90.152199,38.913261],"type":"Point"}
}