{
  "type": "Feature",
  "properties": {
    "iso:country":"US",
    "sg:address":"116 N York St",
    "sg:city":"Elmhurst",
    "sg:classifiers":[
        {
            "category":"Restaurant",
            "type":"Food & Drink"
        }
    ],
    "sg:phone":"+1 630 530 7777",
    "sg:postcode":"60126",
    "sg:province":"IL",
    "wof:name":"Fuego Loco York Inc",
    "wof:placetype":"venue"
},
  "geometry": {"coordinates":[-87.940045,41.900557],"type":"Point"}
}