{
  "type": "Feature",
  "properties": {
    "addr:full":"1079 Collinsville Crossing Blvd Collinsville IL 62234",
    "addr:housenumber":"1079",
    "addr:postcode":"62234",
    "addr:street":"Collinsville Crossing Blvd",
    "iso:country":"US",
    "sg:address":"1079 Collinsville Crossing Blvd",
    "sg:city":"Collinsville",
    "sg:classifiers":[
        {
            "category":"Restaurant",
            "type":"Food & Drink"
        }
    ],
    "sg:phone":"+1 618 343 0309",
    "sg:postcode":"62234",
    "sg:province":"IL",
    "sg:tags":[
        "style",
        "family",
        "buffet",
        "lunch",
        "american",
        "brunch",
        "breakfast"
    ],
    "sg:website":"http://www.goldencorral.com",
    "wof:name":"Golden Corral Restaurants",
    "wof:placetype":"venue"
},
  "geometry": {"coordinates":[-90.015209,38.676022],"type":"Point"}
}