{
  "type": "Feature",
  "properties": {
    "addr:full":"9624 S Cicero Ave Oak Lawn IL 60453",
    "addr:housenumber":"9624",
    "addr:postcode":"60453",
    "addr:street":"S Cicero Ave",
    "iso:country":"US",
    "sg:address":"9624 S Cicero Ave",
    "sg:city":"Oak Lawn",
    "sg:classifiers":[
        {
            "category":"Personal",
            "type":"Services"
        },
        {
            "category":"Professional",
            "subcategory":"Printing & Photocopies",
            "type":"Services"
        }
    ],
    "sg:phone":"+1 708 423 0059",
    "sg:postcode":"60453",
    "sg:province":"IL",
    "sg:tags":[
        "mover"
    ],
    "sg:website":"www.theupsstore.com",
    "wof:name":"Ups Store the",
    "wof:placetype":"venue"
},
  "geometry": {"coordinates":[-87.740803,41.717778],"type":"Point"}
}