{
  "type": "Feature",
  "properties": {
    "addr:full":"628 Michigan Dr Romeoville IL 60446",
    "addr:housenumber":"628",
    "addr:postcode":"60446",
    "addr:street":"Michigan Dr",
    "iso:country":"US",
    "sg:address":"628 Michigan Dr",
    "sg:city":"Romeoville",
    "sg:classifiers":[
        {
            "category":"Professional",
            "subcategory":"Management & Consulting",
            "type":"Services"
        }
    ],
    "sg:phone":"+1 815 886 6846",
    "sg:postcode":"60446",
    "sg:province":"IL",
    "sg:tags":[
        "fuel"
    ],
    "wof:name":"Wellspring Practice Management",
    "wof:placetype":"venue"
},
  "geometry": {"coordinates":[-88.10477,41.651656],"type":"Point"}
}