{
  "type": "Feature",
  "properties": {
    "addr:full":"880 S Main St Jacksonville IL 62650",
    "addr:housenumber":"880",
    "addr:postcode":"62650",
    "addr:street":"S Main St",
    "iso:country":"US",
    "sg:address":"880 S Main St",
    "sg:city":"Jacksonville",
    "sg:classifiers":[
        {
            "category":"Wholesale",
            "subcategory":"Groceries",
            "type":"Manufacturing & Wholesale Goods"
        }
    ],
    "sg:phone":"+1 217 243 8261",
    "sg:postcode":"62650",
    "sg:province":"IL",
    "sg:tags":[
        "baker"
    ],
    "wof:name":"Butternut Bread",
    "wof:placetype":"venue"
},
  "geometry": {"coordinates":[-90.22908099999999,39.724655],"type":"Point"}
}