{
  "type": "Feature",
  "properties": {
    "iso:country":"US",
    "sg:address":"1011 W Poplar St",
    "sg:city":"Harrisburg",
    "sg:classifiers":[
        {
            "category":"Food & Beverages",
            "subcategory":"Groceries & Convenience Stores",
            "type":"Retail Goods"
        }
    ],
    "sg:phone":"+1 618 252 6034",
    "sg:postcode":"62946",
    "sg:province":"IL",
    "wof:name":"Granny's Kitchen And Fuel",
    "wof:placetype":"venue"
},
  "geometry": {"coordinates":[-88.55577700000001,37.738838],"type":"Point"}
}