{
  "type": "Feature",
  "properties": {
    "iso:country":"US",
    "sg:address":"100 W Charles St",
    "sg:city":"Kankakee",
    "sg:classifiers":[
        {
            "category":"Manufacturing",
            "subcategory":"Metals",
            "type":"Manufacturing & Wholesale Goods"
        }
    ],
    "sg:phone":"+1 815 935 5445",
    "sg:postcode":"60901",
    "sg:province":"IL",
    "sg:tags":[
        "restoration",
        "rifle"
    ],
    "wof:name":"Acevedo Restoration",
    "wof:placetype":"venue"
},
  "geometry": {"coordinates":[-87.868805,41.110489],"type":"Point"}
}