{
  "type": "Feature",
  "properties": {
    "iso:country":"US",
    "sg:address":"7740 Old US Highway 50",
    "sg:city":"Breese",
    "sg:classifiers":[
        {
            "category":"Education",
            "subcategory":"Special Training",
            "type":"Public Place"
        },
        {
            "category":"Education",
            "subcategory":"School",
            "type":"Public Place"
        },
        {
            "category":"Government",
            "subcategory":"Office",
            "type":"Public Place"
        }
    ],
    "sg:phone":"+1 618 526 4578",
    "sg:postcode":"62230",
    "sg:province":"IL",
    "sg:tags":[
        "high",
        "parish",
        "educational",
        "government-county"
    ],
    "sg:website":"http://www.centralcougars.org/",
    "wof:name":"Central Charter High School District 71",
    "wof:placetype":"venue"
},
  "geometry": {"coordinates":[-89.559342,38.611653],"type":"Point"}
}