{
  "type": "Feature",
  "properties": {
    "iso:country":"US",
    "sg:address":"236 W Cherry St",
    "sg:city":"Winchester",
    "sg:classifiers":[
        {
            "category":"Insurance",
            "subcategory":"Hazard Insurance",
            "type":"Services"
        }
    ],
    "sg:phone":"+1 217 742 9511",
    "sg:postcode":"62694",
    "sg:province":"IL",
    "sg:website":"http://statefarm.mqgroup.com/url.asp?usr=132881",
    "wof:name":"State Farm Insurance Agent-Dick Coon",
    "wof:placetype":"venue"
},
  "geometry": {"coordinates":[-90.46162,39.629814],"type":"Point"}
}