{
  "type": "Feature",
  "properties": {
    "iso:country":"US",
    "sg:address":"1601 Tanglewood Ave",
    "sg:city":"Bartlett",
    "sg:classifiers":[
        {
            "category":"Health Services",
            "subcategory":"Doctor",
            "type":"Services"
        }
    ],
    "sg:phone":"+1 630 830 7300",
    "sg:postcode":"60133",
    "sg:province":"IL",
    "sg:tags":[
        "clinic",
        "dentist"
    ],
    "wof:name":"Rao Shyam V N",
    "wof:placetype":"venue"
},
  "geometry": {"coordinates":[-88.146633,42.004743],"type":"Point"}
}