{
  "type": "Feature",
  "properties": {
    "iso:country":"US",
    "sg:address":"106 N Roman Dr",
    "sg:city":"Dieterich",
    "sg:classifiers":[
        {
            "category":"Personal",
            "subcategory":"Beauty Salon",
            "type":"Services"
        }
    ],
    "sg:phone":"+1 217 925 5117",
    "sg:postcode":"62424",
    "sg:province":"IL",
    "wof:name":"Hair Care Unlimited",
    "wof:placetype":"venue"
},
  "geometry": {"coordinates":[-88.386737,39.06046],"type":"Point"}
}