{
  "type": "Feature",
  "properties": {
    "addr:full":"15122 Gebke Rd Bartelso IL 62218",
    "addr:postcode":"15122;62218",
    "addr:street":"Gebke Rd",
    "iso:country":"US",
    "sg:address":"15122 Gebke Rd",
    "sg:city":"Bartelso",
    "sg:classifiers":[
        {
            "category":"Professional",
            "subcategory":"Computer Services",
            "type":"Services"
        }
    ],
    "sg:phone":"+1 618 765 2807",
    "sg:postcode":"62218",
    "sg:province":"IL",
    "sg:tags":[
        "datum"
    ],
    "wof:name":"Affordable Data Services",
    "wof:placetype":"venue"
},
  "geometry": {"coordinates":[-89.414754,38.543758],"type":"Point"}
}