{
  "type": "Feature",
  "properties": {
    "iso:country":"US",
    "sg:address":"501 S Commercial St",
    "sg:city":"Harrisburg",
    "sg:classifiers":[
        {
            "category":"Restaurant",
            "type":"Food & Drink"
        }
    ],
    "sg:phone":"+1 618 253 3535",
    "sg:postcode":"62946",
    "sg:province":"IL",
    "sg:tags":[
        "house",
        "steak",
        "barbecue"
    ],
    "wof:name":"Three Pigs Bbq",
    "wof:placetype":"venue"
},
  "geometry": {"coordinates":[-88.533241,37.735741],"type":"Point"}
}