{
  "type": "Feature",
  "properties": {
    "addr:full":"601 W Adams St Chicago IL 60661",
    "addr:housenumber":"601",
    "addr:postcode":"60661",
    "addr:street":"W Adams St",
    "iso:country":"US",
    "sg:address":"601 W Adams St",
    "sg:city":"Chicago",
    "sg:classifiers":[
        {
            "category":"Restaurant",
            "type":"Food & Drink"
        },
        {
            "category":"Food & Beverages",
            "subcategory":"Meat & Fish",
            "type":"Retail Goods"
        }
    ],
    "sg:phone":"+1 312 993 0222",
    "sg:postcode":"60661",
    "sg:province":"IL",
    "sg:tags":[
        "hot",
        "dog"
    ],
    "sg:website":"www.americasdog.com",
    "wof:name":"America's Dog",
    "wof:placetype":"venue"
},
  "geometry": {"coordinates":[-87.642977,41.878865],"type":"Point"}
}