{
  "type": "Feature",
  "properties": {
    "iso:country":"US",
    "sg:address":"7350 W Montrose Ave",
    "sg:city":"Norridge",
    "sg:classifiers":[
        {
            "category":"Manufacturing",
            "subcategory":"Building Materials",
            "type":"Manufacturing & Wholesale Goods"
        }
    ],
    "sg:phone":"+1 708 452 0250",
    "sg:postcode":"60706",
    "sg:province":"IL",
    "sg:tags":[
        "concrete",
        "construction",
        "form",
        "accessory"
    ],
    "sg:website":"http://www.deeconcrete.com",
    "wof:name":"Dee Concrete Acces",
    "wof:placetype":"venue"
},
  "geometry": {"coordinates":[-87.81093,41.959954],"type":"Point"}
}