{
  "type": "Feature",
  "properties": {
    "iso:country":"US",
    "sg:address":"1840 Oak Ave",
    "sg:city":"Evanston",
    "sg:classifiers":[
        {
            "category":"Professional",
            "subcategory":"Management & Consulting",
            "type":"Services"
        }
    ],
    "sg:phone":"+1 312 933 8745",
    "sg:postcode":"60201",
    "sg:province":"IL",
    "wof:name":"Netgambit",
    "wof:placetype":"venue"
},
  "geometry": {"coordinates":[-87.686624,42.05151],"type":"Point"}
}