{
  "type": "Feature",
  "properties": {
    "iso:country":"US",
    "sg:address":"1250 E Diehl Rd",
    "sg:city":"Naperville",
    "sg:classifiers":[
        {
            "category":"Wholesale",
            "subcategory":"Computers",
            "type":"Manufacturing & Wholesale Goods"
        }
    ],
    "sg:phone":"+1 630 577 6553",
    "sg:postcode":"60563",
    "sg:province":"IL",
    "sg:tags":[
        "equipment"
    ],
    "wof:name":"Tibco",
    "wof:placetype":"venue"
},
  "geometry": {"coordinates":[-88.12284099999999,41.802319],"type":"Point"}
}