{
  "type": "Feature",
  "properties": {
    "iso:country":"US",
    "sg:address":"995 N Ellsworth Ave",
    "sg:city":"Villa Park",
    "sg:classifiers":[
        {
            "category":"Manufacturing",
            "subcategory":"Metals",
            "type":"Manufacturing & Wholesale Goods"
        }
    ],
    "sg:phone":"+1 630 279 1550",
    "sg:postcode":"60181",
    "sg:province":"IL",
    "sg:tags":[
        "fitting",
        "fluid",
        "power",
        "mfg"
    ],
    "wof:name":"Kepner Products Company",
    "wof:placetype":"venue"
},
  "geometry": {"coordinates":[-87.973591,41.909179],"type":"Point"}
}