{
  "type": "Feature",
  "properties": {
    "iso:country":"US",
    "sg:address":"2701 State Rte 17",
    "sg:city":"Kankakee",
    "sg:classifiers":[
        {
            "category":"Education",
            "subcategory":"Library",
            "type":"Public Place"
        }
    ],
    "sg:phone":"+1 815 939 1696",
    "sg:postcode":"60901",
    "sg:province":"IL",
    "wof:name":"Limestone Township Library",
    "wof:placetype":"venue"
},
  "geometry": {"coordinates":[-87.826921,41.119113],"type":"Point"}
}