{
  "type": "Feature",
  "properties": {
    "addr:full":"6601 171st St Tinley Park IL 60477",
    "addr:housenumber":"6601",
    "addr:postcode":"60477",
    "addr:street":"171St St",
    "iso:country":"US",
    "sg:address":"6601 171st St",
    "sg:city":"Tinley Park",
    "sg:classifiers":[
        {
            "category":"Education",
            "subcategory":"School",
            "type":"Public Place"
        }
    ],
    "sg:phone":"+1 708 614 4525",
    "sg:postcode":"60477",
    "sg:province":"IL",
    "wof:name":"Fulton School",
    "wof:placetype":"venue"
},
  "geometry": {"coordinates":[-87.780745,41.580567],"type":"Point"}
}