{
  "type": "Feature",
  "properties": {
    "addr:full":"7734 W North Ave Elmwood Park IL 60707",
    "addr:housenumber":"7734",
    "addr:postcode":"60707",
    "addr:street":"W North Ave",
    "iso:country":"US",
    "sg:address":"7734 W North Ave",
    "sg:city":"Elmwood Park",
    "sg:classifiers":[
        {
            "category":"Health Services",
            "subcategory":"Doctor",
            "type":"Services"
        }
    ],
    "sg:phone":"+1 708 456 6611",
    "sg:postcode":"60707",
    "sg:province":"IL",
    "sg:tags":[
        "medicine",
        "practice",
        "internal",
        "family"
    ],
    "wof:name":"Gigante Joseph D MD",
    "wof:placetype":"venue"
},
  "geometry": {"coordinates":[-87.81992,41.908949],"type":"Point"}
}