{
  "type": "Feature",
  "properties": {
    "iso:country":"US",
    "sg:address":"1166 W Morton Ave",
    "sg:city":"Jacksonville",
    "sg:classifiers":[
        {
            "category":"Banks & Credit Unions",
            "subcategory":"Bank",
            "type":"Services"
        }
    ],
    "sg:phone":"+1 217 479 0033",
    "sg:postcode":"62650",
    "sg:province":"IL",
    "sg:tags":[
        "loan"
    ],
    "wof:name":"Dollars Today",
    "wof:placetype":"venue"
},
  "geometry": {"coordinates":[-90.24375499999999,39.723299],"type":"Point"}
}