{
  "type": "Feature",
  "properties": {
    "iso:country":"US",
    "sg:address":"1629 W Grand Ave",
    "sg:city":"Chicago",
    "sg:classifiers":[
        {
            "category":"Professional",
            "type":"Services"
        },
        {
            "category":"Professional",
            "subcategory":"Business Services",
            "type":"Services"
        }
    ],
    "sg:phone":"+1 312 491 1870",
    "sg:postcode":"60622",
    "sg:province":"IL",
    "sg:tags":[
        "food",
        "delivery",
        "caterer"
    ],
    "sg:website":"www.chicagocafecaterers.com",
    "wof:name":"Chicago Cafe Caterers",
    "wof:placetype":"venue"
},
  "geometry": {"coordinates":[-87.65726100000001,41.89243],"type":"Point"}
}