{
  "type": "Feature",
  "properties": {
    "iso:country":"US",
    "sg:address":"12403 85th Ave",
    "sg:city":"Pleasant Prairie",
    "sg:classifiers":[
        {
            "category":"Building & Trades",
            "subcategory":"Construction",
            "type":"Services"
        }
    ],
    "sg:phone":"+1 262 694 7612",
    "sg:postcode":"53158",
    "sg:province":"IL",
    "sg:tags":[
        "masonry",
        "work"
    ],
    "wof:name":"C N Masonry Inc",
    "wof:placetype":"venue"
},
  "geometry": {"coordinates":[-87.908755,42.500325],"type":"Point"}
}