{
  "type": "Feature",
  "properties": {
    "addr:full":"6701 S Emerald Ave Chicago IL 60621",
    "addr:housenumber":"6701",
    "addr:postcode":"60621",
    "addr:street":"S Emerald Ave",
    "iso:country":"US",
    "sg:address":"6701 S Emerald Ave",
    "sg:city":"Chicago",
    "sg:classifiers":[
        {
            "category":"Place Of Worship",
            "subcategory":"Church",
            "type":"Public Place"
        },
        {
            "category":"Place Of Worship",
            "type":"Public Place"
        }
    ],
    "sg:phone":"+1 773 723 5500",
    "sg:postcode":"60621",
    "sg:province":"IL",
    "sg:tags":[
        "churches-baptist-general",
        "churches-baptist"
    ],
    "sg:website":"http://www.atmbc.org",
    "wof:name":"Alpha Temple Baptist Church",
    "wof:placetype":"venue"
},
  "geometry": {"coordinates":[-87.643242,41.77248],"type":"Point"}
}