{
  "type": "Feature",
  "properties": {
    "iso:country":"US",
    "sg:address":"559 High St",
    "sg:city":"Aurora",
    "sg:classifiers":[
        {
            "category":"Personal",
            "subcategory":"Beauty Salon",
            "type":"Services"
        }
    ],
    "sg:phone":"+1 630 264 1416",
    "sg:postcode":"60505",
    "sg:province":"IL",
    "wof:name":"M D Hair Salon",
    "wof:placetype":"venue"
},
  "geometry": {"coordinates":[-88.30164600000001,41.767558],"type":"Point"}
}