{
  "type": "Feature",
  "properties": {
    "iso:country":"US",
    "sg:address":"913 W Lake St",
    "sg:city":"Aurora",
    "sg:classifiers":[
        {
            "category":"Retail",
            "subcategory":"Car Wash",
            "type":"Services"
        }
    ],
    "sg:phone":"+1 630 897 2583",
    "sg:postcode":"60506",
    "sg:province":"IL",
    "sg:tags":[
        "carwash"
    ],
    "wof:name":"Pro Finish",
    "wof:placetype":"venue"
},
  "geometry": {"coordinates":[-88.33890599999999,41.744628],"type":"Point"}
}