{
  "type": "Feature",
  "properties": {
    "iso:country":"US",
    "sg:address":"153 W Austin Ave",
    "sg:city":"Libertyville",
    "sg:classifiers":[
        {
            "category":"Building & Trades",
            "subcategory":"Construction",
            "type":"Services"
        }
    ],
    "sg:phone":"+1 847 247 1308",
    "sg:postcode":"60048",
    "sg:province":"IL",
    "sg:tags":[
        "handyman"
    ],
    "wof:name":"Kruegers Service Repair",
    "wof:placetype":"venue"
},
  "geometry": {"coordinates":[-87.95352,42.276932],"type":"Point"}
}