{
  "type": "Feature",
  "properties": {
    "addr:full":"6418 Vermont Trl Crystal Lake IL 60012",
    "addr:housenumber":"6418",
    "addr:postcode":"60012",
    "addr:street":"Vermont Trl",
    "iso:country":"US",
    "sg:address":"6418 Vermont Trl",
    "sg:city":"Crystal Lake",
    "sg:classifiers":[
        {
            "category":"Building & Trades",
            "subcategory":"Landscaping Services",
            "type":"Services"
        }
    ],
    "sg:phone":"+1 815 459 2274",
    "sg:postcode":"60012",
    "sg:province":"IL",
    "sg:tags":[
        "landscape",
        "contractor"
    ],
    "wof:name":"Campobellos Landscaping Co",
    "wof:placetype":"venue"
},
  "geometry": {"coordinates":[-88.321477,42.265608],"type":"Point"}
}