{
  "type": "Feature",
  "properties": {
    "iso:country":"US",
    "sg:address":"8529 S Kolin Ave",
    "sg:city":"Chicago",
    "sg:classifiers":[
        {
            "category":"Personal",
            "subcategory":"Beauty Salon",
            "type":"Services"
        }
    ],
    "sg:phone":"+1 773 912 4567",
    "sg:postcode":"60652",
    "sg:province":"IL",
    "wof:name":"Josie's Day Spa",
    "wof:placetype":"venue"
},
  "geometry": {"coordinates":[-87.73003199999999,41.737847],"type":"Point"}
}