{
  "type": "Feature",
  "properties": {
    "addr:full":"39 S State St Chicago IL 60603",
    "addr:housenumber":"39",
    "addr:postcode":"60603",
    "addr:street":"S State St",
    "iso:country":"US",
    "sg:address":"39 S State St",
    "sg:city":"Chicago",
    "sg:classifiers":[
        {
            "category":"Shopping",
            "subcategory":"Clothing, Apparel, & Fashions",
            "type":"Retail Goods"
        }
    ],
    "sg:phone":"+1 312 332 9111",
    "sg:postcode":"60603",
    "sg:province":"IL",
    "sg:tags":[
        "children's",
        "clothing"
    ],
    "wof:name":"Children's Place the",
    "wof:placetype":"venue"
},
  "geometry": {"coordinates":[-87.627602,41.881599],"type":"Point"}
}