{
  "type": "Feature",
  "properties": {
    "addr:full":"2850 Roslyn Ln Buffalo Grove IL 60089",
    "addr:housenumber":"2850",
    "addr:postcode":"60089",
    "addr:street":"Roslyn Ln",
    "iso:country":"US",
    "sg:address":"2850 Roslyn Ln",
    "sg:city":"Buffalo Grove",
    "sg:classifiers":[
        {
            "category":"Professional",
            "subcategory":"Business Services",
            "type":"Services"
        }
    ],
    "sg:phone":"+1 847 634 8404",
    "sg:postcode":"60089",
    "sg:province":"IL",
    "sg:tags":[
        "appraiser"
    ],
    "wof:name":"Traci D Jacobs",
    "wof:placetype":"venue"
},
  "geometry": {"coordinates":[-87.956282,42.200456],"type":"Point"}
}