{
  "type": "Feature",
  "properties": {
    "iso:country":"US",
    "sg:address":"1492 S Randall Rd",
    "sg:city":"Geneva",
    "sg:classifiers":[
        {
            "category":"Bakery",
            "type":"Food & Drink"
        }
    ],
    "sg:menulink":"http://www.allmenus.com/il/geneva/103365-panera-bread/menu/",
    "sg:phone":"+1 630 262 9800",
    "sg:postcode":"60134",
    "sg:province":"IL",
    "sg:tags":[
        "american",
        "sandwich",
        "pastry"
    ],
    "wof:name":"Panera Bread",
    "wof:placetype":"venue"
},
  "geometry": {"coordinates":[-88.34048199999999,41.873802],"type":"Point"}
}