{
  "type": "Feature",
  "properties": {
    "iso:country":"US",
    "sg:address":"2 Territorial Ct",
    "sg:city":"Bolingbrook",
    "sg:classifiers":[
        {
            "category":"Banks & Credit Unions",
            "subcategory":"Bank",
            "type":"Services"
        }
    ],
    "sg:phone":"+1 630 679 1420",
    "sg:postcode":"60440",
    "sg:province":"IL",
    "wof:name":"Globe Union America Corp.",
    "wof:placetype":"venue"
},
  "geometry": {"coordinates":[-88.097881,41.674545],"type":"Point"}
}