{
  "type": "Feature",
  "properties": {
    "addr:full":"5118 W Irving Park Rd Chicago IL 60641",
    "addr:housenumber":"5118",
    "addr:postcode":"60641",
    "addr:street":"W Irving Park Rd",
    "iso:country":"US",
    "sg:address":"5118 W Irving Park Rd",
    "sg:city":"Chicago",
    "sg:classifiers":[
        {
            "category":"Wholesale",
            "subcategory":"Office Equipment",
            "type":"Manufacturing & Wholesale Goods"
        },
        {
            "category":"Shopping",
            "subcategory":"Stationery & Office Supplies",
            "type":"Retail Goods"
        }
    ],
    "sg:phone":"+1 773 282 8000",
    "sg:postcode":"60641",
    "sg:province":"IL",
    "sg:tags":[
        "refinish",
        "machine",
        "equipment-repair",
        "copy",
        "furniture"
    ],
    "wof:name":"J&J Electronics & Office Machines Inc",
    "wof:placetype":"venue"
},
  "geometry": {"coordinates":[-87.755424,41.953324],"type":"Point"}
}