{
  "type": "Feature",
  "properties": {
    "iso:country":"US",
    "sg:address":"509 Walnut Aly",
    "sg:city":"Quincy",
    "sg:classifiers":[
        {
            "category":"Professional",
            "subcategory":"Accounting & Tax Preparation",
            "type":"Services"
        }
    ],
    "sg:phone":"+1 217 231 9953",
    "sg:postcode":"62301",
    "sg:province":"IL",
    "sg:tags":[
        "accountant"
    ],
    "wof:name":"Bowles Accounting & Taxing Svc",
    "wof:placetype":"venue"
},
  "geometry": {"coordinates":[-91.407861,39.937723],"type":"Point"}
}