{
  "type": "Feature",
  "properties": {
    "addr:full":"53 W Jackson Blvd Ste 1442 Chicago IL 60604",
    "addr:housenumber":"53",
    "addr:postcode":"60604",
    "addr:street":"W Jackson Blvd Ste 1442",
    "iso:country":"US",
    "sg:address":"53 W Jackson Blvd Ste 1442",
    "sg:city":"Chicago",
    "sg:classifiers":[
        {
            "category":"Banks & Credit Unions",
            "subcategory":"Atm",
            "type":"Services"
        }
    ],
    "sg:phone":"+1 312 427 1558",
    "sg:postcode":"60604",
    "sg:province":"IL",
    "sg:tags":[
        "bankruptcy"
    ],
    "wof:name":"Monica O'brien",
    "wof:placetype":"venue"
},
  "geometry": {"coordinates":[-87.629402,41.878201],"type":"Point"}
}