{
  "type": "Feature",
  "properties": {
    "addr:full":"9335 Landings Ln Des Plaines IL 60016",
    "addr:housenumber":"9335",
    "addr:postcode":"60016",
    "addr:street":"Landings Ln",
    "iso:country":"US",
    "sg:address":"9335 Landings Ln",
    "sg:city":"Des Plaines",
    "sg:classifiers":[
        {
            "category":"Retail",
            "subcategory":"Laundry & Dry Cleaning",
            "type":"Services"
        }
    ],
    "sg:phone":"+1 847 370 5259",
    "sg:postcode":"60016",
    "sg:province":"IL",
    "sg:tags":[
        "drycleaning",
        "plant"
    ],
    "wof:name":"Vega Cleaning Services Inc",
    "wof:placetype":"venue"
},
  "geometry": {"coordinates":[-87.859128,42.042107],"type":"Point"}
}