{
  "type": "Feature",
  "properties": {
    "iso:country":"US",
    "sg:address":"203 New Douglas Ave",
    "sg:city":"Sorento",
    "sg:classifiers":[
        {
            "category":"Building & Trades",
            "subcategory":"Landscaping Services",
            "type":"Services"
        }
    ],
    "sg:phone":"+1 217 272 4001",
    "sg:postcode":"62086",
    "sg:province":"IL",
    "sg:tags":[
        "landscape"
    ],
    "wof:name":"Irrisys Land Designs",
    "wof:placetype":"venue"
},
  "geometry": {"coordinates":[-89.598067,38.977821],"type":"Point"}
}