{
  "type": "Feature",
  "properties": {
    "addr:full":"1017 S Western Ave Unit 4 Chicago IL 60612",
    "addr:housenumber":"1017",
    "addr:postcode":"60612",
    "addr:street":"S Western Ave Unit",
    "iso:country":"US",
    "sg:address":"1017 S Western Ave Unit 4",
    "sg:city":"Chicago",
    "sg:classifiers":[
        {
            "category":"Professional",
            "subcategory":"Art Services",
            "type":"Services"
        }
    ],
    "sg:phone":"+1 773 354 8505",
    "sg:postcode":"60612",
    "sg:province":"IL",
    "sg:tags":[
        "photographer"
    ],
    "sg:website":"dare2dreamphotography.shutterfly...",
    "wof:name":"Dare2Dream Photography",
    "wof:placetype":"venue"
},
  "geometry": {"coordinates":[-87.685984,41.868691],"type":"Point"}
}