{
  "type": "Feature",
  "properties": {
    "iso:country":"US",
    "sg:address":"2723 Shellingham Dr",
    "sg:city":"Lisle",
    "sg:classifiers":[
        {
            "category":"Manufacturing",
            "subcategory":"Tools & Machinery",
            "type":"Manufacturing & Wholesale Goods"
        }
    ],
    "sg:phone":"+1 630 305 9068",
    "sg:postcode":"60532",
    "sg:province":"IL",
    "sg:tags":[
        "gear",
        "man"
    ],
    "wof:name":"LI Gear Inc",
    "wof:placetype":"venue"
},
  "geometry": {"coordinates":[-88.107309,41.773123],"type":"Point"}
}