{
  "type": "Feature",
  "properties": {
    "addr:full":"2825 W Grandville Ave Waukegan IL 60085",
    "addr:housenumber":"2825",
    "addr:postcode":"60085",
    "addr:street":"W Grandville Ave",
    "iso:country":"US",
    "sg:address":"2825 W Grandville Ave",
    "sg:city":"Waukegan",
    "sg:classifiers":[
        {
            "category":"Building & Trades",
            "subcategory":"Construction",
            "type":"Services"
        }
    ],
    "sg:phone":"+1 847 336 2335",
    "sg:postcode":"60085",
    "sg:province":"IL",
    "sg:tags":[
        "contractor"
    ],
    "wof:name":"Juan Carlos Vega Tile",
    "wof:placetype":"venue"
},
  "geometry": {"coordinates":[-87.871093,42.3739],"type":"Point"}
}