{
  "type": "Feature",
  "properties": {
    "iso:country":"US",
    "sg:address":"5521 S Rock City Rd",
    "sg:city":"German Valley",
    "sg:classifiers":[
        {
            "category":"Retail",
            "subcategory":"Veterinary Services",
            "type":"Services"
        }
    ],
    "sg:phone":"+1 815 362 3151",
    "sg:postcode":"61039",
    "sg:province":"IL",
    "sg:tags":[
        "clinic"
    ],
    "wof:name":"New Hope Veterinary Clinic",
    "wof:placetype":"venue"
},
  "geometry": {"coordinates":[-89.47387,42.224068],"type":"Point"}
}