{
  "type": "Feature",
  "properties": {
    "iso:country":"US",
    "sg:address":"1821 Heather Ln",
    "sg:city":"Northbrook",
    "sg:classifiers":[
        {
            "category":"Professional",
            "subcategory":"Management & Consulting",
            "type":"Services"
        }
    ],
    "sg:phone":"+1 847 559 1602",
    "sg:postcode":"60062",
    "sg:province":"IL",
    "wof:name":"J Levine & Associates",
    "wof:placetype":"venue"
},
  "geometry": {"coordinates":[-87.850395,42.118991],"type":"Point"}
}