{
  "type": "Feature",
  "properties": {
    "iso:country":"US",
    "sg:address":"1818 Pebble Beach Cir",
    "sg:city":"Elk Grove Village",
    "sg:classifiers":[
        {
            "category":"Building & Trades",
            "subcategory":"Construction",
            "type":"Services"
        }
    ],
    "sg:phone":"+1 847 534 6196",
    "sg:postcode":"60007",
    "sg:province":"IL",
    "sg:tags":[
        "hanging",
        "contractor"
    ],
    "wof:name":"Chester Decorating",
    "wof:placetype":"venue"
},
  "geometry": {"coordinates":[-88.059503,42.017397],"type":"Point"}
}