{
  "type": "Feature",
  "properties": {
    "addr:full":"2401 W Ohio St Chicago IL 60612",
    "addr:housenumber":"2401",
    "addr:postcode":"60612",
    "addr:street":"W Ohio St",
    "iso:country":"US",
    "sg:address":"2401 W Ohio St",
    "sg:city":"Chicago",
    "sg:classifiers":[
        {
            "category":"Building & Trades",
            "subcategory":"Construction",
            "type":"Services"
        }
    ],
    "sg:phone":"+1 312 738 7300",
    "sg:postcode":"60612",
    "sg:province":"IL",
    "sg:tags":[
        "interior",
        "design"
    ],
    "wof:name":"Jamesthomas Llc",
    "wof:placetype":"venue"
},
  "geometry": {"coordinates":[-87.686699,41.892101],"type":"Point"}
}