{
  "type": "Feature",
  "properties": {
    "addr:full":"3915 Sage Dr Rockford IL 61114",
    "addr:housenumber":"3915",
    "addr:postcode":"61114",
    "addr:street":"Sage Dr",
    "iso:country":"US",
    "sg:address":"3915 Sage Dr",
    "sg:city":"Rockford",
    "sg:classifiers":[
        {
            "category":"Building & Trades",
            "subcategory":"Construction",
            "type":"Services"
        }
    ],
    "sg:phone":"+1 815 885 4244",
    "sg:postcode":"61114",
    "sg:province":"IL",
    "sg:tags":[
        "painter"
    ],
    "wof:name":"Lou's Painting & Wallpapering",
    "wof:placetype":"venue"
},
  "geometry": {"coordinates":[-89.022699,42.317083],"type":"Point"}
}