{
  "type": "Feature",
  "properties": {
    "addr:full":"1205 Woburn Rd Greenville IL 62246",
    "addr:housenumber":"1205",
    "addr:postcode":"62246",
    "addr:street":"Woburn Rd",
    "iso:country":"US",
    "sg:address":"1205 Woburn Rd",
    "sg:city":"Greenville",
    "sg:classifiers":[
        {
            "category":"Professional",
            "subcategory":"Business Services",
            "type":"Services"
        }
    ],
    "sg:phone":"+1 618 664 6089",
    "sg:postcode":"62246",
    "sg:province":"IL",
    "wof:name":"Southern Hoof Service",
    "wof:placetype":"venue"
},
  "geometry": {"coordinates":[-89.372793,38.917001],"type":"Point"}
}