{
  "type": "Feature",
  "properties": {
    "addr:full":"5835 E Riverside Blvd Rockford IL 61114",
    "addr:housenumber":"5835",
    "addr:postcode":"61114",
    "addr:street":"E Riverside Blvd",
    "iso:country":"US",
    "sg:address":"5835 E Riverside Blvd",
    "sg:city":"Rockford",
    "sg:classifiers":[
        {
            "category":"Shopping",
            "subcategory":"Computers & Home Electronics",
            "type":"Retail Goods"
        }
    ],
    "sg:phone":"+1   ",
    "sg:postcode":"61114",
    "sg:province":"IL",
    "wof:name":"Radio Shack",
    "wof:placetype":"venue"
},
  "geometry": {"coordinates":[-89.006467,42.318563],"type":"Point"}
}