{
  "type": "Feature",
  "properties": {
    "iso:country":"US",
    "sg:address":"1341 N 1363rd Ln",
    "sg:city":"Fowler",
    "sg:classifiers":[
        {
            "category":"Farming",
            "subcategory":"Livestock Farm",
            "type":"Manufacturing & Wholesale Goods"
        }
    ],
    "sg:phone":"+1 217 434 8673",
    "sg:postcode":"62338",
    "sg:province":"IL",
    "sg:tags":[
        "hog",
        "beef",
        "corn",
        "cattle",
        "or",
        "feedlot"
    ],
    "wof:name":"Bobby Neisen",
    "wof:placetype":"venue"
},
  "geometry": {"coordinates":[-91.25774699999999,39.957707],"type":"Point"}
}