{
  "type": "Feature",
  "properties": {
    "addr:full":"15098 Short Rd Danville IL 61834",
    "addr:housenumber":"15098",
    "addr:postcode":"61834",
    "addr:street":"Short Rd",
    "iso:country":"US",
    "sg:address":"15098 Short Rd",
    "sg:city":"Danville",
    "sg:classifiers":[
        {
            "category":"Restaurant",
            "type":"Food & Drink"
        }
    ],
    "sg:phone":"+1   ",
    "sg:postcode":"61834",
    "sg:province":"IL",
    "sg:tags":[
        "eating"
    ],
    "wof:name":"Quiznos Subs",
    "wof:placetype":"venue"
},
  "geometry": {"coordinates":[-87.65754200000001,40.196079],"type":"Point"}
}