{
  "type": "Feature",
  "properties": {
    "iso:country":"US",
    "sg:address":"15098 Short Rd",
    "sg:city":"Danville",
    "sg:classifiers":[
        {
            "category":"Restaurant",
            "type":"Food & Drink"
        }
    ],
    "sg:phone":"+1   ",
    "sg:postcode":"61834",
    "sg:province":"IL",
    "sg:tags":[
        "eating"
    ],
    "wof:name":"Quiznos Subs",
    "wof:placetype":"venue"
},
  "geometry": {"coordinates":[-87.657542,40.196079],"type":"Point"}
}