{
  "type": "Feature",
  "properties": {
    "iso:country":"US",
    "sg:address":"1810 S 4th St",
    "sg:city":"Rockford",
    "sg:classifiers":[
        {
            "category":"Professional",
            "subcategory":"Art Services",
            "type":"Services"
        }
    ],
    "sg:phone":"+1 815 965 6422",
    "sg:postcode":"61104",
    "sg:province":"IL",
    "sg:tags":[
        "photographer"
    ],
    "wof:name":"Jon Mc Ginty Photography",
    "wof:placetype":"venue"
},
  "geometry": {"coordinates":[-89.085268,42.247903],"type":"Point"}
}