{
  "type": "Feature",
  "properties": {
    "iso:country":"US",
    "sg:address":"4108 N Cicero Avenue",
    "sg:city":"Chicago",
    "sg:classifiers":[
        {
            "category":"Professional",
            "subcategory":"Lawyer & Legal Services",
            "type":"Services"
        }
    ],
    "sg:phone":"+1 773 777 9559",
    "sg:postcode":"60641",
    "sg:province":"IL",
    "wof:name":"Dulski Warren C",
    "wof:placetype":"venue"
},
  "geometry": {"coordinates":[-87.747294,41.955436],"type":"Point"}
}