{
  "type": "Feature",
  "properties": {
    "iso:country":"US",
    "sg:address":"5450 N Sayre Avenue",
    "sg:city":"Chicago",
    "sg:classifiers":[
        {
            "category":"Professional",
            "subcategory":"Lawyer & Legal Services",
            "type":"Services"
        }
    ],
    "sg:phone":"+1 773 792 0383",
    "sg:postcode":"60656",
    "sg:province":"IL",
    "wof:name":"Roberts Don",
    "wof:placetype":"venue"
},
  "geometry": {"coordinates":[-87.801091,41.97994],"type":"Point"}
}