{
  "type": "Feature",
  "properties": {
    "iso:country":"US",
    "sg:address":"14 Pine Dr",
    "sg:city":"Sherman",
    "sg:classifiers":[
        {
            "category":"Building & Trades",
            "subcategory":"Construction",
            "type":"Services"
        }
    ],
    "sg:phone":"+1 217 496 3044",
    "sg:postcode":"62684",
    "sg:province":"IL",
    "sg:tags":[
        "house"
    ],
    "wof:name":"Georgetown Oaks",
    "wof:placetype":"venue"
},
  "geometry": {"coordinates":[-89.594831,39.892928],"type":"Point"}
}