{
  "type": "Feature",
  "properties": {
    "iso:country":"US",
    "sg:address":"566 W Adams St Ste 600",
    "sg:city":"Chicago",
    "sg:classifiers":[
        {
            "category":"Real Estate",
            "subcategory":"Real Estate Services",
            "type":"Services"
        }
    ],
    "sg:phone":"+1 312 707 8503",
    "sg:postcode":"60661",
    "sg:province":"IL",
    "sg:tags":[
        "management",
        "property"
    ],
    "wof:name":"Jefferson Adams Co",
    "wof:placetype":"venue"
},
  "geometry": {"coordinates":[-87.64160200000001,41.879299],"type":"Point"}
}