{
  "type": "Feature",
  "properties": {
    "iso:country":"US",
    "sg:address":"122 S Chicago St",
    "sg:city":"Lincoln",
    "sg:classifiers":[
        {
            "category":"Bars & Pubs",
            "type":"Food & Drink"
        }
    ],
    "sg:phone":"+1 217 735 1095",
    "sg:postcode":"62656",
    "sg:province":"IL",
    "wof:name":"Jackie & Charlie's Pour House",
    "wof:placetype":"venue"
},
  "geometry": {"coordinates":[-89.363665,40.147245],"type":"Point"}
}