{
  "type": "Feature",
  "properties": {
    "addr:full":"71 S Wacker Dr Chicago IL 60606",
    "addr:housenumber":"71",
    "addr:postcode":"60606",
    "addr:street":"S Wacker Dr",
    "iso:country":"US",
    "sg:address":"71 S Wacker Dr",
    "sg:city":"Chicago",
    "sg:classifiers":[
        {
            "category":"Professional",
            "subcategory":"Lawyer & Legal Services",
            "type":"Services"
        }
    ],
    "sg:phone":"+1 312 782 0600",
    "sg:postcode":"60606",
    "sg:province":"IL",
    "sg:tags":[
        "litigation",
        "tort",
        "attorney"
    ],
    "wof:name":"Cypers, Michael L. - Mayer, Brown, Rowe & Maw LLP",
    "wof:placetype":"venue"
},
  "geometry": {"coordinates":[-87.636731,41.881373],"type":"Point"}
}