{
  "type": "Feature",
  "properties": {
    "iso:country":"US",
    "sg:address":"175 W Des Plaines St",
    "sg:city":"Coal City",
    "sg:classifiers":[
        {
            "category":"Building & Trades",
            "subcategory":"Construction",
            "type":"Services"
        }
    ],
    "sg:phone":"+1 815 634 3232",
    "sg:postcode":"60416",
    "sg:province":"IL",
    "sg:tags":[
        "restoration",
        "cleaning",
        "patio",
        "deck"
    ],
    "wof:name":"Blast Off Power Washing",
    "wof:placetype":"venue"
},
  "geometry": {"coordinates":[-88.287786,41.276192],"type":"Point"}
}