{
  "type": "Feature",
  "properties": {
    "iso:country":"US",
    "sg:address":"1330 S Alpine Rd",
    "sg:city":"Rockford",
    "sg:classifiers":[
        {
            "category":"Shopping",
            "subcategory":"Musical Instruments",
            "type":"Retail Goods"
        }
    ],
    "sg:phone":"+1 815 398 7529",
    "sg:postcode":"61108",
    "sg:province":"IL",
    "sg:tags":[
        "piano"
    ],
    "wof:name":"Karnes Music",
    "wof:placetype":"venue"
},
  "geometry": {"coordinates":[-89.029011,42.252961],"type":"Point"}
}