{
  "type": "Feature",
  "properties": {
    "addr:full":"11500 S Western Ave Chicago IL 60643",
    "addr:housenumber":"11500",
    "addr:postcode":"60643",
    "addr:street":"S Western Ave",
    "iso:country":"US",
    "sg:address":"11500 S Western Ave",
    "sg:city":"Chicago",
    "sg:classifiers":[
        {
            "category":"Restaurant",
            "type":"Food & Drink"
        }
    ],
    "sg:phone":"+1   ",
    "sg:postcode":"60643",
    "sg:province":"IL",
    "sg:tags":[
        "eating"
    ],
    "wof:name":"Mickeys",
    "wof:placetype":"venue"
},
  "geometry": {"coordinates":[-87.680875,41.682729],"type":"Point"}
}