{
  "type": "Feature",
  "properties": {
    "addr:full":"423 W Touhy Ave Des Plaines IL 60018",
    "addr:housenumber":"423",
    "addr:postcode":"60018",
    "addr:street":"W Touhy Ave",
    "iso:country":"US",
    "sg:address":"423 W Touhy Ave",
    "sg:city":"Des Plaines",
    "sg:classifiers":[
        {
            "category":"Cinema",
            "subcategory":"Movie Rental",
            "type":"Entertainment"
        }
    ],
    "sg:phone":"+1 773 694 0090",
    "sg:postcode":"60018",
    "sg:province":"IL",
    "sg:tags":[
        "leasing",
        "video",
        "disc",
        "tape"
    ],
    "wof:name":"Adult World",
    "wof:placetype":"venue"
},
  "geometry": {"coordinates":[-87.932832,42.008264],"type":"Point"}
}