{
  "type": "Feature",
  "properties": {
    "addr:full":"22340 Governors Hwy Richton Park IL 60471",
    "addr:housenumber":"22340",
    "addr:postcode":"60471",
    "addr:street":"Governors Hwy;Park",
    "iso:country":"US",
    "sg:address":"22340 Governors Hwy",
    "sg:city":"Richton Park",
    "sg:classifiers":[
        {
            "category":"Retail",
            "subcategory":"Laundry & Dry Cleaning",
            "type":"Services"
        }
    ],
    "sg:phone":"+1 708 481 6690",
    "sg:postcode":"60471",
    "sg:province":"IL",
    "sg:tags":[
        "cleaners"
    ],
    "wof:name":"Poplar Cleaners",
    "wof:placetype":"venue"
},
  "geometry": {"coordinates":[-87.71305,41.4798],"type":"Point"}
}