{
  "type": "Feature",
  "properties": {
    "addr:full":"2003 W Monroe St Springfield IL 62704",
    "addr:housenumber":"2003",
    "addr:postcode":"62704",
    "addr:street":"W Monroe St",
    "iso:country":"US",
    "sg:address":"2003 W Monroe St",
    "sg:city":"Springfield",
    "sg:classifiers":[
        {
            "category":"Coffee & Tea",
            "type":"Food & Drink"
        }
    ],
    "sg:menulink":"http://www.allmenus.com/il/capital/112625-starbucks-coffee/menu/",
    "sg:phone":"+1 217 793 2193",
    "sg:postcode":"62704",
    "sg:province":"IL",
    "sg:tags":[
        "american"
    ],
    "wof:name":"Starbucks Coffee",
    "wof:placetype":"venue"
},
  "geometry": {"coordinates":[-89.68711,39.799559],"type":"Point"}
}