{
  "type": "Feature",
  "properties": {
    "addr:full":"102 N 1st St San Jose IL 62682",
    "addr:housenumber":"102",
    "addr:postcode":"62682",
    "addr:street":"N 1St St",
    "iso:country":"US",
    "sg:address":"102 N 1st St",
    "sg:city":"San Jose",
    "sg:classifiers":[
        {
            "category":"Restaurant",
            "type":"Food & Drink"
        }
    ],
    "sg:phone":"+1 309 247 3663",
    "sg:postcode":"62682",
    "sg:province":"IL",
    "wof:name":"Jo's Express Inc",
    "wof:placetype":"venue"
},
  "geometry": {"coordinates":[-89.602604,40.306038],"type":"Point"}
}