{
  "type": "Feature",
  "properties": {
    "iso:country":"US",
    "sg:address":"1250 E 75th St",
    "sg:city":"Chicago",
    "sg:classifiers":[
        {
            "category":"Place Of Worship",
            "subcategory":"Church",
            "type":"Public Place"
        },
        {
            "category":"Place Of Worship",
            "type":"Public Place"
        }
    ],
    "sg:phone":"+1 773 493 1111",
    "sg:postcode":"60619",
    "sg:province":"IL",
    "sg:tags":[
        "churches-baptist-general",
        "churches-baptist-missionary",
        "churches-baptist"
    ],
    "wof:name":"Lord's Way Baptist Church The",
    "wof:placetype":"venue"
},
  "geometry": {"coordinates":[-87.594294,41.758705],"type":"Point"}
}