{
  "type": "Feature",
  "properties": {
    "iso:country":"US",
    "sg:address":"30 N La Salle St",
    "sg:city":"Chicago",
    "sg:classifiers":[
        {
            "category":"Professional",
            "subcategory":"Lawyer & Legal Services",
            "type":"Services"
        }
    ],
    "sg:phone":"+1 312 759 2500",
    "sg:postcode":"60602",
    "sg:province":"IL",
    "sg:tags":[
        "personal",
        "injury"
    ],
    "wof:name":"Potter Robin Atty",
    "wof:placetype":"venue"
},
  "geometry": {"coordinates":[-87.632401,41.882599],"type":"Point"}
}