{
  "type": "Feature",
  "properties": {
    "iso:country":"US",
    "sg:address":"1220 Douglas Dr",
    "sg:city":"Carbondale",
    "sg:classifiers":[
        {
            "category":"Health Services",
            "subcategory":"Clinic",
            "type":"Services"
        }
    ],
    "sg:phone":"+1 618 453 3311",
    "sg:postcode":"62901",
    "sg:province":"IL",
    "wof:name":"Appts Health Svc",
    "wof:placetype":"venue"
},
  "geometry": {"coordinates":[-89.230838,37.711982],"type":"Point"}
}