{
  "type": "Feature",
  "properties": {
    "iso:country":"US",
    "sg:address":"63 N Chicago St",
    "sg:city":"Joliet",
    "sg:classifiers":[
        {
            "category":"Organizations",
            "subcategory":"Professional Association",
            "type":"Services"
        }
    ],
    "sg:phone":"+1 815 727 5371",
    "sg:postcode":"60432",
    "sg:province":"IL",
    "sg:tags":[
        "chambers",
        "commerce"
    ],
    "wof:name":"Joliet Region Chamber-Commerce",
    "wof:placetype":"venue"
},
  "geometry": {"coordinates":[-88.08162299999999,41.52464],"type":"Point"}
}