{
  "type": "Feature",
  "properties": {
    "iso:country":"US",
    "sg:address":"101 S Charlotte St",
    "sg:city":"Havana",
    "sg:classifiers":[
        {
            "category":"Organizations",
            "subcategory":"Religious Organization",
            "type":"Services"
        }
    ],
    "sg:phone":"+1 309 543 3115",
    "sg:postcode":"62644",
    "sg:province":"IL",
    "sg:tags":[
        "church"
    ],
    "wof:name":"First Baptist Church",
    "wof:placetype":"venue"
},
  "geometry": {"coordinates":[-90.050223,40.30008],"type":"Point"}
}