{
  "type": "Feature",
  "properties": {
    "iso:country":"US",
    "sg:address":"55 River Oaks Center Dr",
    "sg:city":"Calumet City",
    "sg:classifiers":[
        {
            "category":"Shopping",
            "subcategory":"Clothing, Apparel, & Fashions",
            "type":"Retail Goods"
        }
    ],
    "sg:phone":"+1   ",
    "sg:postcode":"60409",
    "sg:province":"IL",
    "wof:name":"Ashley Stewart Ltd",
    "wof:placetype":"venue"
},
  "geometry": {"coordinates":[-87.532268,41.596881],"type":"Point"}
}