{
  "type": "Feature",
  "properties": {
    "iso:country":"US",
    "sg:address":"17665 Torrence Ave",
    "sg:city":"Lansing",
    "sg:classifiers":[
        {
            "category":"Professional",
            "subcategory":"Employment Agencies",
            "type":"Services"
        }
    ],
    "sg:phone":"+1 708 895 9200",
    "sg:postcode":"60438",
    "sg:province":"IL",
    "sg:tags":[
        "personnel"
    ],
    "wof:name":"Staffmark",
    "wof:placetype":"venue"
},
  "geometry": {"coordinates":[-87.55876000000001,41.574262],"type":"Point"}
}