{
  "type": "Feature",
  "properties": {
    "iso:country":"US",
    "sg:address":"9 Kensington",
    "sg:city":"Collinsville",
    "sg:classifiers":[
        {
            "category":"Building & Trades",
            "subcategory":"Construction",
            "type":"Services"
        }
    ],
    "sg:phone":"+1 618 344 8570",
    "sg:postcode":"62234",
    "sg:province":"IL",
    "sg:tags":[
        "house"
    ],
    "wof:name":"Mallard Builders",
    "wof:placetype":"venue"
},
  "geometry": {"coordinates":[-89.971235,38.700532],"type":"Point"}
}