{
  "type": "Feature",
  "properties": {
    "addr:full":"504 12th St Lawrenceville IL 62439",
    "addr:housenumber":"504",
    "addr:postcode":"62439",
    "addr:street":"12Th St",
    "iso:country":"US",
    "sg:address":"504 12th St",
    "sg:city":"Lawrenceville",
    "sg:classifiers":[
        {
            "category":"Health Services",
            "subcategory":"Doctor",
            "type":"Services"
        }
    ],
    "sg:phone":"+1 618 943 4213",
    "sg:postcode":"62439",
    "sg:province":"IL",
    "sg:tags":[
        "dentist"
    ],
    "wof:name":"D W Luckett DDS",
    "wof:placetype":"venue"
},
  "geometry": {"coordinates":[-87.683099,38.730689],"type":"Point"}
}