{
  "type": "Feature",
  "properties": {
    "addr:full":"575 Thornhill Dr Carol Stream IL 60188",
    "addr:housenumber":"575",
    "addr:postcode":"60188",
    "addr:street":"Thornhill Dr",
    "iso:country":"US",
    "sg:address":"575 Thornhill Dr",
    "sg:city":"Carol Stream",
    "sg:classifiers":[
        {
            "category":"Shopping",
            "subcategory":"Gifts & Souvenirs",
            "type":"Retail Goods"
        }
    ],
    "sg:phone":"+1   ",
    "sg:postcode":"60188",
    "sg:province":"IL",
    "wof:name":"Anytime Gifts",
    "wof:placetype":"venue"
},
  "geometry": {"coordinates":[-88.09693300000001,41.891295],"type":"Point"}
}