{
  "type": "Feature",
  "properties": {
    "addr:full":"18525 Torrence Ave Ste D1 Lansing IL 60438",
    "addr:housenumber":"18525",
    "addr:postcode":"60438",
    "addr:street":"Torrence Ave Ste D1",
    "iso:country":"US",
    "sg:address":"18525 Torrence Ave Ste D1",
    "sg:city":"Lansing",
    "sg:classifiers":[
        {
            "category":"Insurance",
            "subcategory":"Insurance Agent",
            "type":"Services"
        },
        {
            "category":"Insurance",
            "subcategory":"Hazard Insurance",
            "type":"Services"
        },
        {
            "category":"Insurance",
            "subcategory":"Title Insurance",
            "type":"Services"
        },
        {
            "category":"Insurance",
            "subcategory":"Life Insurance",
            "type":"Services"
        }
    ],
    "sg:phone":"+1 708 474 5600",
    "sg:postcode":"60438",
    "sg:province":"IL",
    "sg:tags":[
        "auto",
        "commercial",
        "business",
        "homeowner"
    ],
    "sg:website":"http://www.countryfinancial.com/john.tameling",
    "wof:name":"COUNTRY Financial John Tameling",
    "wof:placetype":"venue"
},
  "geometry": {"coordinates":[-87.558688,41.558596],"type":"Point"}
}