{
  "type": "Feature",
  "properties": {
    "addr:full":"4 Golf Center Schaumburg IL 60195",
    "addr:housenumber":"4",
    "addr:postcode":"60195",
    "addr:street":"Golf",
    "iso:country":"US",
    "sg:address":"4 Golf Center",
    "sg:city":"Schaumburg",
    "sg:classifiers":[
        {
            "category":"Freight",
            "type":"Transportation"
        }
    ],
    "sg:phone":"+1 847 519 1980",
    "sg:postcode":"60195",
    "sg:province":"IL",
    "sg:tags":[
        "operator",
        "trucking"
    ],
    "wof:name":"Oasis Transportation Inc",
    "wof:placetype":"venue"
},
  "geometry": {"coordinates":[-88.082177,42.048605],"type":"Point"}
}