{
  "type": "Feature",
  "properties": {
    "iso:country":"US",
    "sg:address":"201 E Huron St Ste 200",
    "sg:city":"Chicago",
    "sg:classifiers":[
        {
            "category":"Health Services",
            "subcategory":"Doctor",
            "type":"Services"
        }
    ],
    "sg:phone":"+1 312 642 9844",
    "sg:postcode":"60607",
    "sg:province":"IL",
    "sg:tags":[
        "obstetrician",
        "gynecologist"
    ],
    "wof:name":"University Gynecologic Consultants, SC",
    "wof:placetype":"venue"
},
  "geometry": {"coordinates":[-87.62273,41.894953],"type":"Point"}
}