{
  "type": "Feature",
  "properties": {
    "iso:country":"US",
    "sg:address":"5555 S Brainard Ave",
    "sg:city":"Countryside",
    "sg:classifiers":[
        {
            "category":"Shopping",
            "subcategory":"Department Store",
            "type":"Retail Goods"
        }
    ],
    "sg:phone":"+1 708 354 5113",
    "sg:postcode":"60525",
    "sg:province":"IL",
    "wof:name":"Homegoods",
    "wof:placetype":"venue"
},
  "geometry": {"coordinates":[-87.878198,41.787999],"type":"Point"}
}