{
  "type": "Feature",
  "properties": {
    "addr:full":"301 W Main St Heyworth IL 61745",
    "addr:housenumber":"301",
    "addr:postcode":"61745",
    "addr:street":"W Main St",
    "iso:country":"US",
    "sg:address":"301 W Main St",
    "sg:city":"Heyworth",
    "sg:classifiers":[
        {
            "category":"Personal",
            "subcategory":"Beauty Salon",
            "type":"Services"
        }
    ],
    "sg:phone":"+1 309 473 2969",
    "sg:postcode":"61745",
    "sg:province":"IL",
    "sg:tags":[
        "shop"
    ],
    "wof:name":"Christines Full Service Salon",
    "wof:placetype":"venue"
},
  "geometry": {"coordinates":[-88.980059,40.314077],"type":"Point"}
}