{
  "type": "Feature",
  "properties": {
    "iso:country":"US",
    "sg:address":"152 S Pinecrest Rd",
    "sg:city":"Bolingbrook",
    "sg:classifiers":[
        {
            "category":"Travel",
            "subcategory":"Travel Agent",
            "type":"Entertainment"
        }
    ],
    "sg:phone":"+1 708 493 2885",
    "sg:postcode":"60440",
    "sg:province":"IL",
    "sg:tags":[
        "agency",
        "bureau"
    ],
    "wof:name":"A & A World Travel",
    "wof:placetype":"venue"
},
  "geometry": {"coordinates":[-88.04767,41.69876],"type":"Point"}
}