{
  "type": "Feature",
  "properties": {
    "iso:country":"US",
    "sg:address":"1100 Foran Ln",
    "sg:city":"Aurora",
    "sg:classifiers":[
        {
            "category":"Retail",
            "subcategory":"Repair Shop",
            "type":"Services"
        }
    ],
    "sg:phone":"+1 630 844 2688",
    "sg:postcode":"60506",
    "sg:province":"IL",
    "sg:tags":[
        "upholsterer"
    ],
    "wof:name":"Cathy's Upholstery",
    "wof:placetype":"venue"
},
  "geometry": {"coordinates":[-88.337723,41.779356],"type":"Point"}
}