{
  "type": "Feature",
  "properties": {
    "addr:full":"2122 Grand Ave Waukegan IL 60085",
    "addr:housenumber":"2122",
    "addr:postcode":"60085",
    "addr:street":"Grand Ave",
    "iso:country":"US",
    "sg:address":"2122 Grand Ave",
    "sg:city":"Waukegan",
    "sg:classifiers":[
        {
            "category":"Restaurant",
            "type":"Food & Drink"
        }
    ],
    "sg:menulink":"http://www.allmenus.com/il/waukegan/196340-taco-bell/menu/",
    "sg:postcode":"60085",
    "sg:province":"IL",
    "sg:tags":[
        "mexican"
    ],
    "wof:name":"Taco Bell",
    "wof:placetype":"venue"
},
  "geometry": {"coordinates":[-87.85924799999999,42.370587],"type":"Point"}
}