{
  "type": "Feature",
  "properties": {
    "iso:country":"US",
    "sg:address":"204 E Elm St",
    "sg:city":"Wheaton",
    "sg:classifiers":[
        {
            "category":"Professional",
            "subcategory":"Management & Consulting",
            "type":"Services"
        }
    ],
    "sg:phone":"+1 630 933 9336",
    "sg:postcode":"60187",
    "sg:province":"IL",
    "wof:name":"Ed Knowledge",
    "wof:placetype":"venue"
},
  "geometry": {"coordinates":[-88.103916,41.855075],"type":"Point"}
}