{
  "type": "Feature",
  "properties": {
    "addr:full":"310 N Cedar Ave Wood Dale IL 60191",
    "addr:housenumber":"310",
    "addr:postcode":"60191",
    "addr:street":"N Cedar Ave",
    "iso:country":"US",
    "sg:address":"310 N Cedar Ave",
    "sg:city":"Wood Dale",
    "sg:classifiers":[
        {
            "category":"Building & Trades",
            "subcategory":"Construction",
            "type":"Services"
        }
    ],
    "sg:phone":"+1 630 595 0629",
    "sg:postcode":"60191",
    "sg:province":"IL",
    "sg:tags":[
        "hanging",
        "contractor"
    ],
    "wof:name":"Brush Away Painting & STA",
    "wof:placetype":"venue"
},
  "geometry": {"coordinates":[-87.974093,41.97156],"type":"Point"}
}