{
  "type": "Feature",
  "properties": {
    "iso:country":"US",
    "sg:address":"25686 Stoney Kirk Ct",
    "sg:city":"Lake Zurich",
    "sg:classifiers":[
        {
            "category":"Building & Trades",
            "subcategory":"Construction",
            "type":"Services"
        }
    ],
    "sg:phone":"+1 847 438 7888",
    "sg:postcode":"60047",
    "sg:province":"IL",
    "sg:tags":[
        "carpentry",
        "contractor"
    ],
    "wof:name":"Thomas C Carlberg Cnstr Co",
    "wof:placetype":"venue"
},
  "geometry": {"coordinates":[-88.08284999999999,42.236293],"type":"Point"}
}