{
  "type": "Feature",
  "properties": {
    "addr:full":"27 Old Barn Rd Lake Zurich IL 60047",
    "addr:housenumber":"27",
    "addr:postcode":"60047",
    "addr:street":"Old Barn Rd",
    "iso:country":"US",
    "sg:address":"27 Old Barn Rd",
    "sg:city":"Lake Zurich",
    "sg:classifiers":[
        {
            "category":"Wholesale",
            "subcategory":"Medical Equipment & Supplies",
            "type":"Manufacturing & Wholesale Goods"
        }
    ],
    "sg:phone":"+1 847 540 6011",
    "sg:postcode":"60047",
    "sg:province":"IL",
    "wof:name":"Detail Jennings Sales",
    "wof:placetype":"venue"
},
  "geometry": {"coordinates":[-88.021169,42.211064],"type":"Point"}
}