{
  "type": "Feature",
  "properties": {
    "iso:country":"US",
    "sg:address":"1936 S Randall Rd",
    "sg:city":"Algonquin",
    "sg:classifiers":[
        {
            "category":"Shopping",
            "subcategory":"Clothing, Apparel, & Fashions",
            "type":"Retail Goods"
        }
    ],
    "sg:phone":"+1 847 458 2510",
    "sg:postcode":"60102",
    "sg:province":"IL",
    "sg:tags":[
        "children's",
        "clothing"
    ],
    "wof:name":"Limited Too",
    "wof:placetype":"venue"
},
  "geometry": {"coordinates":[-88.33595699999999,42.150333],"type":"Point"}
}