{
  "type": "Feature",
  "properties": {
    "iso:country":"US",
    "sg:address":"1520 Forest Ave",
    "sg:city":"Calumet City",
    "sg:classifiers":[
        {
            "category":"Organizations",
            "subcategory":"Non-profit Organization",
            "type":"Services"
        }
    ],
    "sg:phone":"+1 708 832 0048",
    "sg:postcode":"60409",
    "sg:province":"IL",
    "sg:tags":[
        "social"
    ],
    "wof:name":"Local 621",
    "wof:placetype":"venue"
},
  "geometry": {"coordinates":[-87.531102,41.588711],"type":"Point"}
}