{
  "type": "Feature",
  "properties": {
    "addr:full":"5706 N Northwest Hwy Chicago IL 60646",
    "addr:housenumber":"5706",
    "addr:postcode":"60646",
    "addr:street":"N Northwest Hwy",
    "iso:country":"US",
    "sg:address":"5706 N Northwest Hwy",
    "sg:city":"Chicago",
    "sg:classifiers":[
        {
            "category":"Manufacturing",
            "subcategory":"Tools & Machinery",
            "type":"Manufacturing & Wholesale Goods"
        }
    ],
    "sg:phone":"+1 773 631 2339",
    "sg:postcode":"60646",
    "sg:province":"IL",
    "sg:tags":[
        "instrument",
        "dental",
        "mfg"
    ],
    "wof:name":"Pru-Dent Manufacturing Inc",
    "wof:placetype":"venue"
},
  "geometry": {"coordinates":[-87.787648,41.985832],"type":"Point"}
}