{
  "type": "Feature",
  "properties": {
    "iso:country":"US",
    "sg:address":"2210 N Willow Rd",
    "sg:city":"Urbana",
    "sg:classifiers":[
        {
            "category":"Shopping",
            "subcategory":"Bridal",
            "type":"Retail Goods"
        }
    ],
    "sg:phone":"+1 217 337 7766",
    "sg:postcode":"61802",
    "sg:province":"IL",
    "sg:website":"www.michellesbridalshoppe.com",
    "wof:name":"M 2",
    "wof:placetype":"venue"
},
  "geometry": {"coordinates":[-88.20034200000001,40.135436],"type":"Point"}
}