{
  "type": "Feature",
  "properties": {
    "iso:country":"US",
    "sg:address":"1175 Joseph Cir",
    "sg:city":"Des Plaines",
    "sg:classifiers":[
        {
            "category":"Utilities",
            "subcategory":"Mobile Phone",
            "type":"Services"
        }
    ],
    "sg:phone":"+1 847 296 1353",
    "sg:postcode":"60051",
    "sg:province":"IL",
    "sg:tags":[
        "telephone",
        "cellular"
    ],
    "wof:name":"Cingular Wireless",
    "wof:placetype":"venue"
},
  "geometry": {"coordinates":[-88.219351,42.403911],"type":"Point"}
}