{
  "type": "Feature",
  "properties": {
    "iso:country":"US",
    "sg:address":"160 Louis St",
    "sg:city":"Beckemeyer",
    "sg:classifiers":[
        {
            "category":"Banks & Credit Unions",
            "subcategory":"Bank",
            "type":"Services"
        }
    ],
    "sg:phone":"+1 618 227 8584",
    "sg:postcode":"62219",
    "sg:province":"IL",
    "wof:name":"Germantown Trust & Savings",
    "wof:placetype":"venue"
},
  "geometry": {"coordinates":[-89.435832,38.607376],"type":"Point"}
}