{
  "type": "Feature",
  "properties": {
    "iso:country":"US",
    "sg:address":"2140 W 52nd Pl",
    "sg:city":"Chicago",
    "sg:phone":"+1 708 952 4804",
    "sg:postcode":"60609",
    "sg:province":"IL",
    "wof:name":"Mike Richmond",
    "wof:placetype":"venue"
},
  "geometry": {"coordinates":[-87.677572,41.797986],"type":"Point"}
}