{
  "type": "Feature",
  "properties": {
    "addr:full":"8223 114th Ave W Taylor Ridge IL 61284",
    "addr:housenumber":"8223",
    "addr:postcode":"61284",
    "addr:street":"114Th Ave W Taylor",
    "iso:country":"US",
    "sg:address":"8223 114th Ave W",
    "sg:city":"Taylor Ridge",
    "sg:phone":"+1 309 798 2437",
    "sg:postcode":"61284",
    "sg:province":"IL",
    "sg:tags":[
        "feed",
        "beef",
        "farm",
        "corn",
        "crop",
        "field",
        "soybean",
        "cattle"
    ],
    "wof:name":"Thomas Moseley",
    "wof:placetype":"venue"
},
  "geometry": {"coordinates":[-90.687471,41.411458],"type":"Point"}
}