{
  "type": "Feature",
  "properties": {
    "addr:full":"6615 N Caldwell Ave Chicago IL 60646",
    "addr:housenumber":"6615",
    "addr:postcode":"60646",
    "addr:street":"N Caldwell Ave",
    "iso:country":"US",
    "sg:address":"6615 N Caldwell Ave",
    "sg:city":"Chicago",
    "sg:classifiers":[
        {
            "category":"Banks & Credit Unions",
            "subcategory":"Investment Brokerage",
            "type":"Services"
        }
    ],
    "sg:phone":"+1 773 467 1574",
    "sg:postcode":"60646",
    "sg:province":"IL",
    "sg:tags":[
        "broker",
        "commodity"
    ],
    "wof:name":"Bcl International Trading",
    "wof:placetype":"venue"
},
  "geometry": {"coordinates":[-87.77462300000001,42.001015],"type":"Point"}
}