{
  "type": "Feature",
  "properties": {
    "iso:country":"US",
    "sg:address":"301 Obernuefemann Rd",
    "sg:city":"O'Fallon",
    "sg:classifiers":[
        {
            "category":"Park",
            "type":"Public Place"
        }
    ],
    "sg:phone":"+1 618 624 4500",
    "sg:postcode":"62269",
    "sg:province":"IL",
    "sg:website":"www.ofallon.org/Public_Documents...",
    "wof:name":"O'Fallon Sports Park",
    "wof:placetype":"venue"
},
  "geometry": {"coordinates":[-89.93163199999999,38.595742],"type":"Point"}
}