{
  "type": "Feature",
  "properties": {
    "iso:country":"US",
    "sg:address":"1736 N Campbell Ave",
    "sg:city":"Chicago",
    "sg:classifiers":[
        {
            "category":"Insurance",
            "subcategory":"Hazard Insurance",
            "type":"Services"
        }
    ],
    "sg:phone":"+1 773 343 4635",
    "sg:postcode":"60647",
    "sg:province":"IL",
    "sg:tags":[
        "carrier"
    ],
    "wof:name":"Edda M Zafiro",
    "wof:placetype":"venue"
},
  "geometry": {"coordinates":[-87.689791,41.912372],"type":"Point"}
}