{
  "type": "Feature",
  "properties": {
    "addr:full":"205 W Wacker Dr Ste 730 Chicago IL 60606",
    "addr:housenumber":"205",
    "addr:postcode":"60606",
    "addr:street":"W;Dr Ste 730",
    "iso:country":"US",
    "sg:address":"205 W Wacker Dr Ste 730",
    "sg:city":"Chicago",
    "sg:classifiers":[
        {
            "category":"Real Estate",
            "subcategory":"Architect",
            "type":"Services"
        }
    ],
    "sg:phone":"+1 312 419 0009",
    "sg:postcode":"60606",
    "sg:province":"IL",
    "wof:name":"Ilekis Assoc",
    "wof:placetype":"venue"
},
  "geometry": {"coordinates":[-87.634201,41.886799],"type":"Point"}
}