{
  "type": "Feature",
  "properties": {
    "iso:country":"US",
    "sg:address":"309 N Eastern Ave",
    "sg:city":"Joliet",
    "sg:classifiers":[
        {
            "category":"Professional",
            "subcategory":"Lawyer & Legal Services",
            "type":"Services"
        }
    ],
    "sg:phone":"+1 815 727 6343",
    "sg:postcode":"60432",
    "sg:province":"IL",
    "sg:tags":[
        "naturalization",
        "immigration"
    ],
    "wof:name":"Spanish Center Daycare",
    "wof:placetype":"venue"
},
  "geometry": {"coordinates":[-88.074951,41.531403],"type":"Point"}
}