{
  "type": "Feature",
  "properties": {
    "iso:country":"US",
    "sg:address":"10 Deerfield Rd",
    "sg:city":"Deerfield",
    "sg:classifiers":[
        {
            "category":"Organizations",
            "subcategory":"Religious Organization",
            "type":"Services"
        }
    ],
    "sg:phone":"+1 847 945 2009",
    "sg:postcode":"60015",
    "sg:province":"IL",
    "sg:tags":[
        "church"
    ],
    "wof:name":"Zion Evangelical Lutheran Chr",
    "wof:placetype":"venue"
},
  "geometry": {"coordinates":[-87.828829,42.167728],"type":"Point"}
}