{
  "type": "Feature",
  "properties": {
    "iso:country":"US",
    "sg:address":"577 Lee St",
    "sg:city":"Glen Ellyn",
    "sg:classifiers":[
        {
            "category":"Organizations",
            "subcategory":"Community Association",
            "type":"Services"
        }
    ],
    "sg:phone":"+1 630 469 4649",
    "sg:postcode":"60137",
    "sg:province":"IL",
    "wof:name":"National Assoc of Miniature",
    "wof:placetype":"venue"
},
  "geometry": {"coordinates":[-88.056146,41.880875],"type":"Point"}
}