{
  "type": "Feature",
  "properties": {
    "iso:country":"US",
    "sg:address":"4929 W Elm St",
    "sg:city":"Mc Henry",
    "sg:classifiers":[
        {
            "category":"Personal",
            "subcategory":"Beauty Salon",
            "type":"Services"
        }
    ],
    "sg:phone":"+1 815 385 2233",
    "sg:postcode":"60050",
    "sg:province":"IL",
    "sg:tags":[
        "shop"
    ],
    "wof:name":"Joanne's Hair Care",
    "wof:placetype":"venue"
},
  "geometry": {"coordinates":[-88.2941,42.349106],"type":"Point"}
}