{
  "type": "Feature",
  "properties": {
    "addr:full":"1550 Frontage Rd O Fallon IL 62269",
    "addr:housenumber":"1550",
    "addr:postcode":"62269",
    "addr:street":"Frontage Rd",
    "iso:country":"US",
    "sg:address":"1550 Frontage Rd",
    "sg:city":"O Fallon",
    "sg:classifiers":[
        {
            "category":"Building & Trades",
            "subcategory":"Construction",
            "type":"Services"
        }
    ],
    "sg:phone":"+1 618 628 0400",
    "sg:postcode":"62269",
    "sg:province":"IL",
    "sg:tags":[
        "painter"
    ],
    "wof:name":"Diversified Coatings",
    "wof:placetype":"venue"
},
  "geometry": {"coordinates":[-89.955803,38.5975],"type":"Point"}
}