{
  "type": "Feature",
  "properties": {
    "addr:full":"301 E South St Freeport IL 61032",
    "addr:housenumber":"301 e",
    "addr:postcode":"61032",
    "addr:street":"South St",
    "iso:country":"US",
    "sg:address":"301 E South St",
    "sg:city":"Freeport",
    "sg:classifiers":[
        {
            "category":"Building & Trades",
            "subcategory":"Plumbing",
            "type":"Services"
        }
    ],
    "sg:phone":"+1 815 233 3073",
    "sg:postcode":"61032",
    "sg:province":"IL",
    "sg:tags":[
        "plumbing",
        "contractor"
    ],
    "wof:name":"Steve Kuhlemeier Plumbing",
    "wof:placetype":"venue"
},
  "geometry": {"coordinates":[-89.61258100000001,42.280422],"type":"Point"}
}