{
  "type": "Feature",
  "properties": {
    "addr:full":"1775 Grinnell Rd Kankakee IL 60901",
    "addr:housenumber":"1775",
    "addr:postcode":"60901",
    "addr:street":"Grinnell Rd",
    "iso:country":"US",
    "sg:address":"1775 Grinnell Rd",
    "sg:city":"Kankakee",
    "sg:classifiers":[
        {
            "category":"Home & Garden",
            "subcategory":"Building Materials",
            "type":"Retail Goods"
        }
    ],
    "sg:phone":"+1 815 932 5400",
    "sg:postcode":"60901",
    "sg:province":"IL",
    "sg:tags":[
        "roofing"
    ],
    "wof:name":"Richards Building Supply",
    "wof:placetype":"venue"
},
  "geometry": {"coordinates":[-87.842979,41.133432],"type":"Point"}
}