{
  "type": "Feature",
  "properties": {
    "addr:full":"6017 Dempster St Lake Forest IL 60053",
    "addr:housenumber":"6017",
    "addr:postcode":"60053",
    "addr:street":"Dempster St",
    "iso:country":"US",
    "sg:address":"6017 Dempster St",
    "sg:city":"Lake Forest",
    "sg:classifiers":[
        {
            "category":"Home & Garden",
            "subcategory":"Carpets & Floor Coverings",
            "type":"Retail Goods"
        }
    ],
    "sg:phone":"+1 847 676 8160",
    "sg:postcode":"60053",
    "sg:province":"IL",
    "sg:tags":[
        "dealer",
        "rug"
    ],
    "wof:name":"Sunshine Carpet Cleaning",
    "wof:placetype":"venue"
},
  "geometry": {"coordinates":[-87.77701999999999,42.040846],"type":"Point"}
}