{
  "type": "Feature",
  "properties": {
    "iso:country":"US",
    "sg:address":"2651 N Milwaukee Ave",
    "sg:city":"Chicago",
    "sg:classifiers":[
        {
            "category":"Professional",
            "subcategory":"Lawyer & Legal Services",
            "type":"Services"
        }
    ],
    "sg:phone":"+1 773 278 7777",
    "sg:postcode":"60647",
    "sg:province":"IL",
    "wof:name":"Guillermo Martinez",
    "wof:placetype":"venue"
},
  "geometry": {"coordinates":[-87.7089,41.929798],"type":"Point"}
}