{
  "type": "Feature",
  "properties": {
    "addr:full":"29 E Madison St Ste 601 Chicago IL 60602",
    "addr:housenumber":"29",
    "addr:postcode":"60602",
    "addr:street":"E Madison St Ste 601",
    "iso:country":"US",
    "sg:address":"29 E Madison St Ste 601",
    "sg:city":"Chicago",
    "sg:classifiers":[
        {
            "category":"Wholesale",
            "subcategory":"Jewelry",
            "type":"Manufacturing & Wholesale Goods"
        },
        {
            "category":"Shopping",
            "subcategory":"Jewelry",
            "type":"Retail Goods"
        }
    ],
    "sg:phone":"+1 312 558 9060",
    "sg:postcode":"60602",
    "sg:province":"IL",
    "sg:tags":[
        "diamonds-wholesale"
    ],
    "wof:name":"Ofer Mizrahi Diamonds Inc",
    "wof:placetype":"venue"
},
  "geometry": {"coordinates":[-87.6267,41.881943],"type":"Point"}
}