{
  "type": "Feature",
  "properties": {
    "iso:country":"US",
    "sg:address":"220 W Huron Street",
    "sg:city":"Chicago",
    "sg:classifiers":[
        {
            "category":"Building & Trades",
            "subcategory":"Construction",
            "type":"Services"
        }
    ],
    "sg:phone":"+1 312 255 8800",
    "sg:postcode":"60610",
    "sg:province":"IL",
    "sg:tags":[
        "interior",
        "design"
    ],
    "wof:name":"Eva Quateman Interiors Ltd",
    "wof:placetype":"venue"
},
  "geometry": {"coordinates":[-87.635107,41.894874],"type":"Point"}
}