{
  "type": "Feature",
  "properties": {
    "addr:full":"401 N Michigan Ave Suite 1200 Chicago IL 60611",
    "addr:housenumber":"401",
    "addr:postcode":"60611",
    "addr:street":"N Michigan Ave Suite 1200",
    "iso:country":"US",
    "sg:address":"401 N Michigan Ave Suite 1200",
    "sg:city":"Chicago",
    "sg:classifiers":[
        {
            "category":"Professional",
            "type":"Services"
        },
        {
            "category":"Travel",
            "subcategory":"Travel Agent",
            "type":"Entertainment"
        }
    ],
    "sg:phone":"+1 312 730 0204",
    "sg:postcode":"60611",
    "sg:province":"IL",
    "sg:website":"www.samedaypassport-visa.com",
    "wof:name":"Sameday Passport & Visa Expedite Services Inc",
    "wof:placetype":"venue"
},
  "geometry": {"coordinates":[-87.62296000000001,41.889596],"type":"Point"}
}