{
  "type": "Feature",
  "properties": {
    "iso:country":"US",
    "sg:address":"2326 W Lyndale St",
    "sg:city":"Chicago",
    "sg:classifiers":[
        {
            "category":"Professional",
            "subcategory":"Management & Consulting",
            "type":"Services"
        }
    ],
    "sg:phone":"+1 312 310 0013",
    "sg:postcode":"60647",
    "sg:province":"IL",
    "wof:name":"Marc Goldenberg",
    "wof:placetype":"venue"
},
  "geometry": {"coordinates":[-87.686806,41.922703],"type":"Point"}
}