{
  "type": "Feature",
  "properties": {
    "addr:full":"200 Howard Ave Des Plaines IL 60018",
    "addr:housenumber":"200",
    "addr:postcode":"60018",
    "addr:street":"Howard Ave",
    "iso:country":"US",
    "sg:address":"200 Howard Ave",
    "sg:city":"Des Plaines",
    "sg:classifiers":[
        {
            "category":"Freight",
            "type":"Transportation"
        }
    ],
    "sg:phone":"+1 847 699 8220",
    "sg:postcode":"60018",
    "sg:province":"IL",
    "sg:tags":[
        "arrangement"
    ],
    "wof:name":"J F Moran Co",
    "wof:placetype":"venue"
},
  "geometry": {"coordinates":[-87.917241,42.015889],"type":"Point"}
}