{
  "type": "Feature",
  "properties": {
    "iso:country":"US",
    "sg:address":"859 W Armitage",
    "sg:city":"Chicago",
    "sg:classifiers":[
        {
            "category":"Shopping",
            "subcategory":"Beauty & Cosmetics",
            "type":"Retail Goods"
        }
    ],
    "sg:phone":"+1 773 281 5874",
    "sg:postcode":"60614",
    "sg:province":"IL",
    "sg:tags":[
        "supply"
    ],
    "sg:website":"www.lush.com",
    "wof:name":"LUSH",
    "wof:placetype":"venue"
},
  "geometry": {"coordinates":[-87.650233,41.918152],"type":"Point"}
}