{
  "type": "Feature",
  "properties": {
    "iso:country":"US",
    "sg:address":"834 Windsor Rd",
    "sg:city":"Glenview",
    "sg:classifiers":[
        {
            "category":"Professional",
            "subcategory":"Management & Consulting",
            "type":"Services"
        }
    ],
    "sg:phone":"+1 847 657 8026",
    "sg:postcode":"60025",
    "sg:province":"IL",
    "sg:tags":[
        "consultant"
    ],
    "wof:name":"Cheryl J Kalman Consulting",
    "wof:placetype":"venue"
},
  "geometry": {"coordinates":[-87.782651,42.069654],"type":"Point"}
}