{
  "type": "Feature",
  "properties": {
    "addr:full":"1515 Elmwood Rd Rockford IL 61103",
    "addr:housenumber":"1515",
    "addr:postcode":"61103",
    "addr:street":"Elmwood Rd",
    "iso:country":"US",
    "sg:address":"1515 Elmwood Rd",
    "sg:city":"Rockford",
    "sg:classifiers":[
        {
            "category":"Building & Trades",
            "subcategory":"Construction",
            "type":"Services"
        }
    ],
    "sg:phone":"+1 815 633 7619",
    "sg:postcode":"61103",
    "sg:province":"IL",
    "sg:tags":[
        "c",
        "multiple",
        "family",
        "general",
        "dwelling",
        "contractor"
    ],
    "wof:name":"Three Hammer Construction Inc",
    "wof:placetype":"venue"
},
  "geometry": {"coordinates":[-89.062933,42.332235],"type":"Point"}
}