{
  "type": "Feature",
  "properties": {
    "iso:country":"US",
    "sg:address":"14927 W Brimfield-Jubilee Rd",
    "sg:city":"Brimfield",
    "sg:classifiers":[
        {
            "category":"Professional",
            "type":"Services"
        }
    ],
    "sg:phone":"+1 309 446 3585",
    "sg:postcode":"61517",
    "sg:province":"IL",
    "sg:tags":[
        "establishment"
    ],
    "wof:name":"Scotland Prairie Corp",
    "wof:placetype":"venue"
},
  "geometry": {"coordinates":[-89.831874,40.843314],"type":"Point"}
}