{
  "type": "Feature",
  "properties": {
    "addr:full":"5419 Harvey Rd Fulton IL 61252",
    "addr:housenumber":"5419",
    "addr:postcode":"61252",
    "addr:street":"Harvey Rd",
    "iso:country":"US",
    "sg:address":"5419 Harvey Rd",
    "sg:city":"Fulton",
    "sg:classifiers":[
        {
            "category":"Organizations",
            "subcategory":"Religious Organization",
            "type":"Services"
        }
    ],
    "sg:phone":"+1 309 887 5134",
    "sg:postcode":"61252",
    "sg:province":"IL",
    "wof:name":"Donald Temple",
    "wof:placetype":"venue"
},
  "geometry": {"coordinates":[-90.142458,41.786545],"type":"Point"}
}