{
  "type": "Feature",
  "properties": {
    "iso:country":"US",
    "sg:address":"801 Charleston Ave",
    "sg:city":"Mattoon",
    "sg:classifiers":[
        {
            "category":"Restaurant",
            "type":"Food & Drink"
        }
    ],
    "sg:phone":"+1   ",
    "sg:postcode":"61938",
    "sg:province":"IL",
    "sg:tags":[
        "eating"
    ],
    "wof:name":"Mc Hughs",
    "wof:placetype":"venue"
},
  "geometry": {"coordinates":[-88.364285,39.481521],"type":"Point"}
}