{
  "type": "Feature",
  "properties": {
    "iso:country":"US",
    "sg:address":"1230 Woodlawn Rd",
    "sg:city":"Lincoln",
    "sg:classifiers":[
        {
            "category":"Banks & Credit Unions",
            "subcategory":"Bank",
            "type":"Services"
        }
    ],
    "sg:phone":"+1 217 732 5626",
    "sg:postcode":"62656",
    "sg:province":"IL",
    "sg:tags":[
        "personal",
        "loan",
        "institution"
    ],
    "wof:name":"Heights Finance Corporation",
    "wof:placetype":"venue"
},
  "geometry": {"coordinates":[-89.388782,40.157893],"type":"Point"}
}