{
  "type": "Feature",
  "properties": {
    "addr:full":"4629 W Erie St Chicago IL 60644",
    "addr:housenumber":"4629",
    "addr:postcode":"60644",
    "addr:street":"W Erie St",
    "iso:country":"US",
    "sg:address":"4629 W Erie St",
    "sg:city":"Chicago",
    "sg:classifiers":[
        {
            "category":"Building & Trades",
            "subcategory":"Cleaning & Sanitation",
            "type":"Services"
        }
    ],
    "sg:phone":"+1 773 261 1036",
    "sg:postcode":"60644",
    "sg:province":"IL",
    "sg:tags":[
        "janitorial",
        "carpet"
    ],
    "wof:name":"Magazine Professional Services",
    "wof:placetype":"venue"
},
  "geometry": {"coordinates":[-87.742841,41.892243],"type":"Point"}
}