{
  "type": "Feature",
  "properties": {
    "addr:full":"1108 Eastern Dr Urbana IL 61801",
    "addr:housenumber":"1108",
    "addr:postcode":"61801",
    "addr:street":"Eastern Dr",
    "iso:country":"US",
    "sg:address":"1108 Eastern Dr",
    "sg:city":"Urbana",
    "sg:classifiers":[
        {
            "category":"Building & Trades",
            "subcategory":"Construction",
            "type":"Services"
        }
    ],
    "sg:phone":"+1 217 328 1804",
    "sg:postcode":"61801",
    "sg:province":"IL",
    "sg:tags":[
        "carpentry",
        "contractor"
    ],
    "wof:name":"Walker Carpentry Inc",
    "wof:placetype":"venue"
},
  "geometry": {"coordinates":[-88.19473499999999,40.104348],"type":"Point"}
}