{
  "type": "Feature",
  "properties": {
    "iso:country":"US",
    "sg:address":"3725 W 49th St",
    "sg:city":"Chicago",
    "sg:classifiers":[
        {
            "category":"Retail",
            "subcategory":"Repair Shop",
            "type":"Services"
        }
    ],
    "sg:phone":"+1 773 523 2944",
    "sg:postcode":"60632",
    "sg:province":"IL",
    "sg:tags":[
        "machine"
    ],
    "sg:website":"http://www.enrmachine.com",
    "wof:name":"E.N.R. General Machining Co.",
    "wof:placetype":"venue"
},
  "geometry": {"coordinates":[-87.717158,41.804289],"type":"Point"}
}