{
  "type": "Feature",
  "properties": {
    "addr:full":"5 Eastgate Ct Woodridge IL 60517",
    "addr:housenumber":"5",
    "addr:postcode":"60517",
    "addr:street":"Eastgate Ct",
    "iso:country":"US",
    "sg:address":"5 Eastgate Ct",
    "sg:city":"Woodridge",
    "sg:classifiers":[
        {
            "category":"Health Services",
            "subcategory":"Doctor",
            "type":"Services"
        }
    ],
    "sg:phone":"+1 630 960 4438",
    "sg:postcode":"60517",
    "sg:province":"IL",
    "sg:tags":[
        "medical"
    ],
    "wof:name":"Supermarket Search Grp",
    "wof:placetype":"venue"
},
  "geometry": {"coordinates":[-88.044388,41.776367],"type":"Point"}
}