{
  "type": "Feature",
  "properties": {
    "addr:full":"9606 W Higgins Rd Rosemont IL 60018",
    "addr:housenumber":"9606",
    "addr:postcode":"60018",
    "addr:street":"W Higgins Rd",
    "iso:country":"US",
    "sg:address":"9606 W Higgins Rd",
    "sg:city":"Rosemont",
    "sg:classifiers":[
        {
            "category":"Real Estate",
            "subcategory":"Real Estate Operator",
            "type":"Services"
        }
    ],
    "sg:phone":"+1 847 696 9740",
    "sg:postcode":"60018",
    "sg:province":"IL",
    "sg:tags":[
        "condominium"
    ],
    "wof:name":"Executive Estates Condos",
    "wof:placetype":"venue"
},
  "geometry": {"coordinates":[-87.87088900000001,41.994726],"type":"Point"}
}