{
  "type": "Feature",
  "properties": {
    "iso:country":"US",
    "sg:address":"1281 W 71st St",
    "sg:city":"Chicago",
    "sg:classifiers":[
        {
            "category":"Food & Beverages",
            "subcategory":"Groceries & Convenience Stores",
            "type":"Retail Goods"
        }
    ],
    "sg:phone":"+1 773 487 0680",
    "sg:postcode":"60636",
    "sg:province":"IL",
    "wof:name":"Ada Foods",
    "wof:placetype":"venue"
},
  "geometry": {"coordinates":[-87.65709699999999,41.764801],"type":"Point"}
}