{
  "type": "Feature",
  "properties": {
    "iso:country":"US",
    "sg:address":"109 W Walnut St",
    "sg:city":"Fairbury",
    "sg:classifiers":[
        {
            "category":"Health Services",
            "subcategory":"Chiropractor",
            "type":"Services"
        }
    ],
    "sg:phone":"+1 815 692 4618",
    "sg:postcode":"61739",
    "sg:province":"IL",
    "sg:tags":[
        "chiropractic"
    ],
    "wof:name":"Accident & Sports Clinic, S. C.",
    "wof:placetype":"venue"
},
  "geometry": {"coordinates":[-88.513383,40.745891],"type":"Point"}
}