{
  "type": "Feature",
  "properties": {
    "addr:full":"9337 Plum Creek Rd Sparta IL 62286",
    "addr:housenumber":"9337",
    "addr:postcode":"62286",
    "addr:street":"Plum Creek Rd",
    "iso:country":"US",
    "sg:address":"9337 Plum Creek Rd",
    "sg:city":"Sparta",
    "sg:classifiers":[
        {
            "category":"Retail",
            "subcategory":"Repair Shop",
            "type":"Services"
        }
    ],
    "sg:phone":"+1 618 443 2720",
    "sg:postcode":"62286",
    "sg:province":"IL",
    "sg:tags":[
        "major",
        "appliance",
        "refinishing"
    ],
    "wof:name":"Innovative Machine And Welding",
    "wof:placetype":"venue"
},
  "geometry": {"coordinates":[-89.743397,38.14789],"type":"Point"}
}