{
  "type": "Feature",
  "properties": {
    "iso:country":"US",
    "sg:address":"1460 Gilmoor Dr",
    "sg:city":"Fowler",
    "sg:classifiers":[
        {
            "category":"Shopping",
            "subcategory":"Gifts & Souvenirs",
            "type":"Retail Goods"
        }
    ],
    "sg:phone":"+1   ",
    "sg:postcode":"62338",
    "sg:province":"IL",
    "wof:name":"Scents N Things",
    "wof:placetype":"venue"
},
  "geometry": {"coordinates":[-91.233137,39.944166],"type":"Point"}
}