{
  "type": "Feature",
  "properties": {
    "addr:full":"18320 Kedzie Ave Homewood IL 60430",
    "addr:housenumber":"18320",
    "addr:postcode":"60430",
    "addr:street":"Kedzie Ave",
    "iso:country":"US",
    "sg:address":"18320 Kedzie Ave",
    "sg:city":"Homewood",
    "sg:classifiers":[
        {
            "category":"Recreation",
            "type":"Entertainment"
        }
    ],
    "sg:phone":"+1 708 957 0050",
    "sg:postcode":"60430",
    "sg:province":"IL",
    "wof:name":"Masters Sporex 4",
    "wof:placetype":"venue"
},
  "geometry": {"coordinates":[-87.69422,41.556643],"type":"Point"}
}