{
  "type": "Feature",
  "properties": {
    "addr:full":"4954 Main St Skokie IL 60077",
    "addr:housenumber":"4954",
    "addr:postcode":"60077",
    "addr:street":"Main St",
    "iso:country":"US",
    "sg:address":"4954 Main St",
    "sg:city":"Skokie",
    "sg:classifiers":[
        {
            "category":"Building & Trades",
            "subcategory":"Plumbing",
            "type":"Services"
        }
    ],
    "sg:phone":"+1 847 763 9042",
    "sg:postcode":"60077",
    "sg:province":"IL",
    "sg:tags":[
        "plumber",
        "sewer",
        "contractor"
    ],
    "sg:website":"http://www.billsplumbingandsewer.com",
    "wof:name":"Bill's Plumbing & Sewer Inc",
    "wof:placetype":"venue"
},
  "geometry": {"coordinates":[-87.751583,42.033585],"type":"Point"}
}