{
  "type": "Feature",
  "properties": {
    "addr:full":"188 Bernard St Bourbonnais IL 60914",
    "addr:housenumber":"188",
    "addr:postcode":"60914",
    "addr:street":"Bernard St",
    "iso:country":"US",
    "sg:address":"188 Bernard St",
    "sg:city":"Bourbonnais",
    "sg:classifiers":[
        {
            "category":"Organizations",
            "subcategory":"Religious Organization",
            "type":"Services"
        }
    ],
    "sg:phone":"+1 815 939 0888",
    "sg:postcode":"60914",
    "sg:province":"IL",
    "wof:name":"W W Dean Rev",
    "wof:placetype":"venue"
},
  "geometry": {"coordinates":[-87.878225,41.156051],"type":"Point"}
}