{
  "type": "Feature",
  "properties": {
    "iso:country":"US",
    "sg:address":"309 N Logan Ave",
    "sg:city":"Danville",
    "sg:classifiers":[
        {
            "category":"Social Services",
            "type":"Services"
        }
    ],
    "sg:phone":"+1 217 442 8097",
    "sg:postcode":"61832",
    "sg:province":"IL",
    "sg:tags":[
        "organization",
        "welfare"
    ],
    "wof:name":"Children & Family Connections",
    "wof:placetype":"venue"
},
  "geometry": {"coordinates":[-87.640214,40.129301],"type":"Point"}
}