{
  "type": "Feature",
  "properties": {
    "iso:country":"US",
    "sg:address":"12127 W Farmington Rd",
    "sg:city":"Hanna City",
    "sg:classifiers":[
        {
            "category":"Utilities",
            "subcategory":"Mobile Phone",
            "type":"Services"
        }
    ],
    "sg:phone":"+1 309 565 4979",
    "sg:postcode":"61536",
    "sg:province":"IL",
    "sg:tags":[
        "telephone",
        "cellular"
    ],
    "wof:name":"Quality Wireless",
    "wof:placetype":"venue"
},
  "geometry": {"coordinates":[-89.78433200000001,40.691831],"type":"Point"}
}