{
  "type": "Feature",
  "properties": {
    "iso:country":"US",
    "sg:address":"29 Whidden Ave",
    "sg:city":"Waukegan",
    "sg:classifiers":[
        {
            "category":"Shopping",
            "subcategory":"Music",
            "type":"Retail Goods"
        }
    ],
    "sg:phone":"+1 847 623 8673",
    "sg:postcode":"60085",
    "sg:province":"IL",
    "sg:tags":[
        "compact",
        "record",
        "disc",
        "tape"
    ],
    "wof:name":"Xenolith Records",
    "wof:placetype":"venue"
},
  "geometry": {"coordinates":[-87.862905,42.357743],"type":"Point"}
}