{
  "type": "Feature",
  "properties": {
    "addr:full":"10021 S Western Ave Chicago IL 60643",
    "addr:housenumber":"10021",
    "addr:postcode":"60643",
    "addr:street":"S Western Ave",
    "iso:country":"US",
    "sg:address":"10021 S Western Ave",
    "sg:city":"Chicago",
    "sg:classifiers":[
        {
            "category":"Banks & Credit Unions",
            "subcategory":"Bank",
            "type":"Services"
        }
    ],
    "sg:phone":"+1 773 779 3007",
    "sg:postcode":"60643",
    "sg:province":"IL",
    "sg:tags":[
        "loan",
        "real estate"
    ],
    "wof:name":"All Funds Mortgage Co",
    "wof:placetype":"venue"
},
  "geometry": {"coordinates":[-87.68166600000001,41.7104],"type":"Point"}
}