{
  "type": "Feature",
  "properties": {
    "addr:full":"6417 Blaine Pl Spring Grove IL 60081",
    "addr:housenumber":"6417",
    "addr:postcode":"60081",
    "addr:street":"Blaine Pl",
    "iso:country":"US",
    "sg:address":"6417 Blaine Pl",
    "sg:city":"Spring Grove",
    "sg:classifiers":[
        {
            "category":"Building & Trades",
            "subcategory":"Construction",
            "type":"Services"
        }
    ],
    "sg:phone":"+1 847 587 0960",
    "sg:postcode":"60081",
    "sg:province":"IL",
    "sg:tags":[
        "excavation",
        "contractor"
    ],
    "wof:name":"Peck Excavating",
    "wof:placetype":"venue"
},
  "geometry": {"coordinates":[-88.202207,42.420564],"type":"Point"}
}