{
  "type": "Feature",
  "properties": {
    "iso:country":"US",
    "sg:address":"476 Co Rd 1700 N",
    "sg:city":"Champaign",
    "sg:classifiers":[
        {
            "category":"Retail",
            "subcategory":"Auto Repair",
            "type":"Services"
        }
    ],
    "sg:phone":"+1 217 863 2003",
    "sg:postcode":"61822",
    "sg:province":"IL",
    "sg:tags":[
        "general"
    ],
    "wof:name":"P D B Truck Shop",
    "wof:placetype":"venue"
},
  "geometry": {"coordinates":[-88.374512,40.127698],"type":"Point"}
}