{
  "type": "Feature",
  "properties": {
    "iso:country":"US",
    "sg:address":"29 E Roosevelt St",
    "sg:city":"Freeport",
    "sg:classifiers":[
        {
            "category":"Arts & Performance",
            "subcategory":"Theater",
            "type":"Entertainment"
        }
    ],
    "sg:phone":"+1 815 233 2376",
    "sg:postcode":"61032",
    "sg:province":"IL",
    "sg:tags":[
        "live",
        "music"
    ],
    "wof:name":"Tobin's DJ Svc",
    "wof:placetype":"venue"
},
  "geometry": {"coordinates":[-89.616223,42.281834],"type":"Point"}
}