{
  "type": "Feature",
  "properties": {
    "iso:country":"US",
    "sg:address":"854 Pembrook Ct",
    "sg:city":"Carol Stream",
    "sg:classifiers":[
        {
            "category":"Utilities",
            "subcategory":"Telephone",
            "type":"Services"
        }
    ],
    "sg:phone":"+1 630 334 8331",
    "sg:postcode":"60188",
    "sg:province":"IL",
    "sg:tags":[
        "communications"
    ],
    "wof:name":"Info Trak",
    "wof:placetype":"venue"
},
  "geometry": {"coordinates":[-88.092645,41.900167],"type":"Point"}
}