{
  "type": "Feature",
  "properties": {
    "iso:country":"US",
    "sg:address":"101 W University Ave",
    "sg:city":"Champaign",
    "sg:classifiers":[
        {
            "category":"Health Services",
            "subcategory":"Doctor",
            "type":"Services"
        }
    ],
    "sg:phone":"+1 217 366 1255",
    "sg:postcode":"61820",
    "sg:province":"IL",
    "sg:website":"www.christieclinic.com",
    "wof:name":"Nelson Mildred S MD",
    "wof:placetype":"venue"
},
  "geometry": {"coordinates":[-88.24389600000001,40.116199],"type":"Point"}
}