{
  "type": "Feature",
  "properties": {
    "iso:country":"US",
    "sg:address":"960 N Mulford Rd",
    "sg:city":"Rockford",
    "sg:classifiers":[
        {
            "category":"Building & Trades",
            "subcategory":"Construction",
            "type":"Services"
        }
    ],
    "sg:phone":"+1 815 394 0928",
    "sg:postcode":"61107",
    "sg:province":"IL",
    "sg:tags":[
        "contractor"
    ],
    "wof:name":"Ebco Construction Group",
    "wof:placetype":"venue"
},
  "geometry": {"coordinates":[-88.999644,42.279065],"type":"Point"}
}