{
  "type": "Feature",
  "properties": {
    "iso:country":"US",
    "sg:address":"1600 Downs Dr",
    "sg:city":"West Chicago",
    "sg:classifiers":[
        {
            "category":"Freight",
            "type":"Transportation"
        }
    ],
    "sg:phone":"+1 630 876 0600",
    "sg:postcode":"60185",
    "sg:province":"IL",
    "sg:tags":[
        "trucking"
    ],
    "wof:name":"Bulk Commodities Transport Inc",
    "wof:placetype":"venue"
},
  "geometry": {"coordinates":[-88.235275,41.886107],"type":"Point"}
}