{
  "type": "Feature",
  "properties": {
    "iso:country":"US",
    "sg:address":"233 S Wacker Dr Ste 5150",
    "sg:city":"Chicago",
    "sg:classifiers":[
        {
            "category":"Professional",
            "subcategory":"Lawyer & Legal Services",
            "type":"Services"
        }
    ],
    "sg:phone":"+1 312 467 0004",
    "sg:postcode":"60610",
    "sg:province":"IL",
    "wof:name":"Legal Helpers",
    "wof:placetype":"venue"
},
  "geometry": {"coordinates":[-87.638559,41.896528],"type":"Point"}
}