{
  "type": "Feature",
  "properties": {
    "iso:country":"US",
    "sg:address":"877 S Poplar Camp Rd",
    "sg:city":"Makanda",
    "sg:classifiers":[
        {
            "category":"Building & Trades",
            "subcategory":"Construction",
            "type":"Services"
        }
    ],
    "sg:phone":"+1 618 549 0659",
    "sg:postcode":"62958",
    "sg:province":"IL",
    "sg:tags":[
        "excavation",
        "contractor"
    ],
    "wof:name":"Dd Williams Construction Inc",
    "wof:placetype":"venue"
},
  "geometry": {"coordinates":[-89.263475,37.635845],"type":"Point"}
}