{
  "type": "Feature",
  "properties": {
    "addr:full":"300 Louise Dr Collinsville IL 62234",
    "addr:housenumber":"300",
    "addr:postcode":"62234",
    "addr:street":"Louise Dr",
    "iso:country":"US",
    "sg:address":"300 Louise Dr",
    "sg:city":"Collinsville",
    "sg:classifiers":[
        {
            "category":"Food & Beverages",
            "subcategory":"Bakery",
            "type":"Retail Goods"
        }
    ],
    "sg:phone":"+1   ",
    "sg:postcode":"62234",
    "sg:province":"IL",
    "wof:name":"Kruta Collinsville Bakery",
    "wof:placetype":"venue"
},
  "geometry": {"coordinates":[-89.953138,38.715902],"type":"Point"}
}