{
  "type": "Feature",
  "properties": {
    "addr:full":"226 N 4th St Ste F Chillicothe IL 61523",
    "addr:housenumber":"226",
    "addr:postcode":"61523",
    "addr:street":"N 4Th St Ste F",
    "iso:country":"US",
    "sg:address":"226 N 4th St Ste F",
    "sg:city":"Chillicothe",
    "sg:classifiers":[
        {
            "category":"Real Estate",
            "subcategory":"Real Estate Services",
            "type":"Services"
        },
        {
            "category":"Real Estate",
            "subcategory":"Real Estate Agent",
            "type":"Services"
        }
    ],
    "sg:phone":"+1 309 274 3248",
    "sg:postcode":"61523",
    "sg:province":"IL",
    "sg:tags":[
        "buyer",
        "management",
        "broker"
    ],
    "wof:name":"River Valley Real Estate",
    "wof:placetype":"venue"
},
  "geometry": {"coordinates":[-89.49145900000001,40.91021],"type":"Point"}
}