{
  "type": "Feature",
  "properties": {
    "iso:country":"US",
    "sg:address":"1836 S Ashland Ave",
    "sg:city":"Chicago",
    "sg:classifiers":[
        {
            "category":"Home & Garden",
            "subcategory":"Hardware",
            "type":"Retail Goods"
        }
    ],
    "sg:phone":"+1 312 243 2393",
    "sg:postcode":"60608",
    "sg:province":"IL",
    "sg:tags":[
        "store"
    ],
    "wof:name":"Torres Hardware #2",
    "wof:placetype":"venue"
},
  "geometry": {"coordinates":[-87.666312,41.85672],"type":"Point"}
}