{
  "type": "Feature",
  "properties": {
    "addr:full":"6700 Broadway St Quincy IL 62305",
    "addr:housenumber":"6700",
    "addr:postcode":"62305",
    "addr:street":"Broadway St",
    "iso:country":"US",
    "sg:address":"6700 Broadway St",
    "sg:city":"Quincy",
    "sg:classifiers":[
        {
            "category":"Home & Garden",
            "subcategory":"Building Materials",
            "type":"Retail Goods"
        }
    ],
    "sg:phone":"+1 217 224 2400",
    "sg:postcode":"62305",
    "sg:province":"IL",
    "wof:name":"American Builders Supply Inc",
    "wof:placetype":"venue"
},
  "geometry": {"coordinates":[-91.310244,39.934716],"type":"Point"}
}