{
  "type": "Feature",
  "properties": {
    "iso:country":"US",
    "sg:address":"614 210th Ave",
    "sg:city":"Monmouth",
    "sg:classifiers":[
        {
            "category":"Personal",
            "type":"Services"
        }
    ],
    "sg:phone":"+1 309 734 9409",
    "sg:postcode":"61462",
    "sg:province":"IL",
    "wof:name":"Critsers Fast Lcense Title Svc",
    "wof:placetype":"venue"
},
  "geometry": {"coordinates":[-90.667948,40.936297],"type":"Point"}
}