{
  "type": "Feature",
  "properties": {
    "iso:country":"US",
    "sg:address":"507 S Williams St",
    "sg:city":"Colchester",
    "sg:classifiers":[
        {
            "category":"Personal",
            "subcategory":"Beauty Salon",
            "type":"Services"
        }
    ],
    "sg:phone":"+1 309 776 3646",
    "sg:postcode":"62326",
    "sg:province":"IL",
    "sg:tags":[
        "shop"
    ],
    "wof:name":"Pam's Place",
    "wof:placetype":"venue"
},
  "geometry": {"coordinates":[-90.79291499999999,40.420577],"type":"Point"}
}