{
  "type": "Feature",
  "properties": {
    "addr:full":"216 E State St Cherry Valley IL 61016",
    "addr:housenumber":"216",
    "addr:postcode":"61016",
    "addr:street":"E State St",
    "iso:country":"US",
    "sg:address":"216 E State St",
    "sg:city":"Cherry Valley",
    "sg:classifiers":[
        {
            "category":"Restaurant",
            "type":"Food & Drink"
        }
    ],
    "sg:phone":"+1 815 332 3449",
    "sg:postcode":"61016",
    "sg:province":"IL",
    "wof:name":"Country Skillet",
    "wof:placetype":"venue"
},
  "geometry": {"coordinates":[-88.951982,42.2353],"type":"Point"}
}