{
  "type": "Feature",
  "properties": {
    "addr:full":"3143 N Lincoln Ave Chicago IL 60657",
    "addr:housenumber":"3143",
    "addr:postcode":"60657",
    "addr:street":"N Lincoln Ave",
    "iso:country":"US",
    "sg:address":"3143 N Lincoln Ave",
    "sg:city":"Chicago",
    "sg:classifiers":[
        {
            "category":"Personal",
            "subcategory":"Beauty Salon",
            "type":"Services"
        }
    ],
    "sg:phone":"+1 773 549 0800",
    "sg:postcode":"60657",
    "sg:province":"IL",
    "sg:tags":[
        "hair"
    ],
    "sg:website":"www.sirensalon.com",
    "wof:name":"Siren Salon",
    "wof:placetype":"venue"
},
  "geometry": {"coordinates":[-87.66739699999999,41.938599],"type":"Point"}
}