{
  "type": "Feature",
  "properties": {
    "iso:country":"US",
    "sg:address":"1674 Wright Blvd",
    "sg:city":"Schaumburg",
    "sg:classifiers":[
        {
            "category":"Freight",
            "type":"Transportation"
        }
    ],
    "sg:phone":"+1 847 895 3970",
    "sg:postcode":"60193",
    "sg:province":"IL",
    "sg:tags":[
        "operator",
        "local",
        "trucking"
    ],
    "wof:name":"Wkr Trucking",
    "wof:placetype":"venue"
},
  "geometry": {"coordinates":[-88.10184099999999,41.996038],"type":"Point"}
}