{
  "type": "Feature",
  "properties": {
    "addr:full":"2450 N Milwaukee Ave Chicago IL 60647",
    "addr:housenumber":"2450",
    "addr:postcode":"60647",
    "addr:street":"N Milwaukee Ave",
    "iso:country":"US",
    "sg:address":"2450 N Milwaukee Ave",
    "sg:city":"Chicago",
    "sg:classifiers":[
        {
            "category":"Personal",
            "subcategory":"Tattoo Parlor",
            "type":"Services"
        },
        {
            "category":"Personal",
            "subcategory":"Piercing",
            "type":"Services"
        }
    ],
    "sg:phone":"+1 773 697 4663",
    "sg:postcode":"60647",
    "sg:province":"IL",
    "sg:website":"www.reaperstattoo.com",
    "wof:name":"Reaper Tattoo & Body Piercing Inc",
    "wof:placetype":"venue"
},
  "geometry": {"coordinates":[-87.70217599999999,41.925727],"type":"Point"}
}