{
  "type": "Feature",
  "properties": {
    "iso:country":"US",
    "sg:address":"7453 State Rte 403",
    "sg:city":"Dilltown",
    "sg:classifiers":[
        {
            "category":"Travel",
            "subcategory":"Hotels & Motels",
            "type":"Entertainment"
        }
    ],
    "sg:phone":"+1 814 446 6465",
    "sg:postcode":"99999",
    "sg:province":"IL",
    "sg:tags":[
        "breakfast",
        "accommodation",
        "bed"
    ],
    "wof:name":"Dillweed Bread & Breakfast",
    "wof:placetype":"venue"
},
  "geometry": {"coordinates":[-87.622028,41.628074],"type":"Point"}
}