{
  "type": "Feature",
  "properties": {
    "iso:country":"US",
    "sg:address":"6340 Fremont Dr",
    "sg:city":"Bartlett",
    "sg:classifiers":[
        {
            "category":"Recreation",
            "type":"Entertainment"
        }
    ],
    "sg:phone":"+1 847 840 5902",
    "sg:postcode":"60133",
    "sg:province":"IL",
    "wof:name":"Art of Touch",
    "wof:placetype":"venue"
},
  "geometry": {"coordinates":[-88.143647,41.988087],"type":"Point"}
}