{
  "type": "Feature",
  "properties": {
    "iso:country":"US",
    "sg:address":"420 W 79th St",
    "sg:city":"Chicago",
    "sg:classifiers":[
        {
            "category":"Shopping",
            "subcategory":"Beauty & Cosmetics",
            "type":"Retail Goods"
        }
    ],
    "sg:phone":"+1 708 743 7273",
    "sg:postcode":"60620",
    "sg:province":"IL",
    "sg:tags":[
        "supply"
    ],
    "wof:name":"Star Trek Beauty Supply",
    "wof:placetype":"venue"
},
  "geometry": {"coordinates":[-87.635124,41.750683],"type":"Point"}
}