{
  "type": "Feature",
  "properties": {
    "addr:full":"452 Georgetown Sq Wood Dale IL 60191",
    "addr:housenumber":"452",
    "addr:postcode":"60191",
    "addr:street":"Georgetown Sq",
    "iso:country":"US",
    "sg:address":"452 Georgetown Sq",
    "sg:city":"Wood Dale",
    "sg:classifiers":[
        {
            "category":"Real Estate",
            "subcategory":"Real Estate Agent",
            "type":"Services"
        }
    ],
    "sg:phone":"+1 630 616 9600",
    "sg:postcode":"60191",
    "sg:province":"IL",
    "wof:name":"Mathisen Realty Inc",
    "wof:placetype":"venue"
},
  "geometry": {"coordinates":[-87.99669299999999,41.965208],"type":"Point"}
}