{
  "type": "Feature",
  "properties": {
    "addr:full":"444 N Michigan Ave Chicago IL 60611",
    "addr:housenumber":"444",
    "addr:postcode":"60611",
    "addr:street":"N Michigan Ave",
    "iso:country":"US",
    "sg:address":"444 N Michigan Ave",
    "sg:city":"Chicago",
    "sg:classifiers":[
        {
            "category":"Communications",
            "subcategory":"Newspaper",
            "type":"Services"
        }
    ],
    "sg:phone":"+1 312 396 8000",
    "sg:postcode":"60611",
    "sg:province":"IL",
    "sg:tags":[
        "print",
        "medium"
    ],
    "wof:name":"Shape Magazine",
    "wof:placetype":"venue"
},
  "geometry": {"coordinates":[-87.624188,41.89035],"type":"Point"}
}