{
  "type": "Feature",
  "properties": {
    "iso:country":"US",
    "sg:address":"480 19th St",
    "sg:city":"East Moline",
    "sg:classifiers":[
        {
            "category":"Retail",
            "subcategory":"Car Wash",
            "type":"Services"
        }
    ],
    "sg:phone":"+1 309 752 1233",
    "sg:postcode":"61244",
    "sg:province":"IL",
    "sg:tags":[
        "carwash"
    ],
    "wof:name":"East Moline Super Wash",
    "wof:placetype":"venue"
},
  "geometry": {"coordinates":[-90.425697,41.526501],"type":"Point"}
}