{
  "type": "Feature",
  "properties": {
    "iso:country":"US",
    "sg:address":"2015 N Main St",
    "sg:city":"Wheaton",
    "sg:classifiers":[
        {
            "category":"Health Services",
            "subcategory":"Doctor",
            "type":"Services"
        }
    ],
    "sg:phone":"+1 630 668 8250",
    "sg:postcode":"60187",
    "sg:province":"IL",
    "sg:tags":[
        "medical"
    ],
    "wof:name":"Daily Mark J MD",
    "wof:placetype":"venue"
},
  "geometry": {"coordinates":[-88.106719,41.88405],"type":"Point"}
}