{
  "type": "Feature",
  "properties": {
    "iso:country":"US",
    "sg:address":"1401 15th St",
    "sg:city":"Moline",
    "sg:classifiers":[
        {
            "category":"Professional",
            "subcategory":"Accounting & Tax Preparation",
            "type":"Services"
        }
    ],
    "sg:phone":"+1 309 764 4558",
    "sg:postcode":"61265",
    "sg:province":"IL",
    "wof:name":"Claseman Ed Accounting Tax Svc",
    "wof:placetype":"venue"
},
  "geometry": {"coordinates":[-90.515605,41.49754],"type":"Point"}
}