{
  "type": "Feature",
  "properties": {
    "iso:country":"US",
    "sg:address":"4213 Main St",
    "sg:city":"Downers Grove",
    "sg:classifiers":[
        {
            "category":"Restaurant",
            "type":"Food & Drink"
        }
    ],
    "sg:phone":"+1   ",
    "sg:postcode":"60515",
    "sg:province":"IL",
    "sg:tags":[
        "eating"
    ],
    "wof:name":"A Thyme For Taste",
    "wof:placetype":"venue"
},
  "geometry": {"coordinates":[-88.011062,41.810283],"type":"Point"}
}