{
  "type": "Feature",
  "properties": {
    "iso:country":"US",
    "sg:address":"1216 Arlington Heights Rd",
    "sg:city":"Arlington Heights",
    "sg:classifiers":[
        {
            "category":"Real Estate",
            "subcategory":"Architect",
            "type":"Services"
        }
    ],
    "sg:phone":"+1 847 253 0002",
    "sg:postcode":"60005",
    "sg:province":"IL",
    "sg:tags":[
        "architectural"
    ],
    "wof:name":"Tinaglia Architects Inc",
    "wof:placetype":"venue"
},
  "geometry": {"coordinates":[-87.979972,42.060877],"type":"Point"}
}