{
  "type": "Feature",
  "properties": {
    "addr:full":"2300 Ridge Dr Glenview IL 60025",
    "addr:housenumber":"2300",
    "addr:postcode":"60025",
    "addr:street":"Ridge Dr",
    "iso:country":"US",
    "sg:address":"2300 Ridge Dr",
    "sg:city":"Glenview",
    "sg:classifiers":[
        {
            "category":"Home & Garden",
            "subcategory":"Building Materials",
            "type":"Retail Goods"
        },
        {
            "category":"Building & Trades",
            "subcategory":"Construction",
            "type":"Services"
        },
        {
            "category":"Manufacturing",
            "subcategory":"Building Materials",
            "type":"Manufacturing & Wholesale Goods"
        }
    ],
    "sg:phone":"+1 800 630 5838",
    "sg:postcode":"60025",
    "sg:province":"IL",
    "sg:tags":[
        "installation",
        "windows-repair",
        "doors-vinyl",
        "window",
        "doors",
        "frames",
        "accessory",
        "replacement"
    ],
    "sg:website":"http://www.renewalbyandersen.com/default.aspx?engName=PdSchYPOrganic",
    "wof:name":"Renewal by Andersen",
    "wof:placetype":"venue"
},
  "geometry": {"coordinates":[-87.812943,42.099947],"type":"Point"}
}