{
  "type": "Feature",
  "properties": {
    "iso:country":"US",
    "sg:address":"1317 3rd Ave",
    "sg:city":"Rock Island",
    "sg:classifiers":[
        {
            "category":"Government",
            "subcategory":"Jail",
            "type":"Public Place"
        }
    ],
    "sg:phone":"+1 309 794 1234",
    "sg:postcode":"61201",
    "sg:province":"IL",
    "sg:tags":[
        "county",
        "govt",
        "institution"
    ],
    "wof:name":"County Jail",
    "wof:placetype":"venue"
},
  "geometry": {"coordinates":[-90.58037400000001,41.508977],"type":"Point"}
}