{
  "type": "Feature",
  "properties": {
    "iso:country":"US",
    "sg:address":"1041 S Mayfield Ave",
    "sg:city":"Chicago",
    "sg:classifiers":[
        {
            "category":"Building & Trades",
            "subcategory":"Construction",
            "type":"Services"
        }
    ],
    "sg:phone":"+1 773 378 1279",
    "sg:postcode":"60644",
    "sg:province":"IL",
    "sg:tags":[
        "contractor"
    ],
    "wof:name":"Hodges Tuck Pointing",
    "wof:placetype":"venue"
},
  "geometry": {"coordinates":[-87.771686,41.868071],"type":"Point"}
}