{
  "type": "Feature",
  "properties": {
    "addr:full":"900 Broadway St Quincy IL 62301",
    "addr:housenumber":"900",
    "addr:postcode":"62301",
    "addr:street":"Broadway St",
    "iso:country":"US",
    "sg:address":"900 Broadway St",
    "sg:city":"Quincy",
    "sg:classifiers":[
        {
            "category":"Food & Beverages",
            "subcategory":"Bakery",
            "type":"Retail Goods"
        }
    ],
    "sg:phone":"+1   ",
    "sg:postcode":"62301",
    "sg:province":"IL",
    "wof:name":"Purity Baking Co",
    "wof:placetype":"venue"
},
  "geometry": {"coordinates":[-91.40002200000001,39.935604],"type":"Point"}
}