{
  "type": "Feature",
  "properties": {
    "iso:country":"US",
    "sg:address":"3061 Wolf Rd",
    "sg:city":"Westchester",
    "sg:classifiers":[
        {
            "category":"Education",
            "subcategory":"Special Training",
            "type":"Public Place"
        }
    ],
    "sg:phone":"+1 708 562 2006",
    "sg:postcode":"60154",
    "sg:province":"IL",
    "sg:tags":[
        "educational"
    ],
    "wof:name":"Sylvan Learning Centers",
    "wof:placetype":"venue"
},
  "geometry": {"coordinates":[-87.900642,41.836082],"type":"Point"}
}