{
  "type": "Feature",
  "properties": {
    "iso:country":"US",
    "sg:address":"3930 44th Avenue Dr",
    "sg:city":"Moline",
    "sg:classifiers":[
        {
            "category":"Personal",
            "subcategory":"Nail Salon",
            "type":"Services"
        }
    ],
    "sg:phone":"+1 309 764 6245",
    "sg:postcode":"61265",
    "sg:province":"IL",
    "wof:name":"Davi Nails",
    "wof:placetype":"venue"
},
  "geometry": {"coordinates":[-90.48375299999999,41.470347],"type":"Point"}
}