{
  "type": "Feature",
  "properties": {
    "iso:country":"US",
    "sg:address":"1646 Trafalgar Ln",
    "sg:city":"Aurora",
    "sg:classifiers":[
        {
            "category":"Building & Trades",
            "subcategory":"Construction",
            "type":"Services"
        }
    ],
    "sg:phone":"+1 630 375 6067",
    "sg:postcode":"60504",
    "sg:province":"IL",
    "sg:tags":[
        "painter"
    ],
    "wof:name":"Decorators Etc Inc",
    "wof:placetype":"venue"
},
  "geometry": {"coordinates":[-88.25783,41.727871],"type":"Point"}
}