{
  "type": "Feature",
  "properties": {
    "iso:country":"US",
    "sg:address":"17 E Fort St",
    "sg:city":"Farmington",
    "sg:classifiers":[
        {
            "category":"Restaurant",
            "type":"Food & Drink"
        }
    ],
    "sg:phone":"+1 309 245 4116",
    "sg:postcode":"61531",
    "sg:province":"IL",
    "wof:name":"Subway Sandwiches & Salads",
    "wof:placetype":"venue"
},
  "geometry": {"coordinates":[-90.005646,40.698291],"type":"Point"}
}