{
  "type": "Feature",
  "properties": {
    "iso:country":"US",
    "sg:address":"2312 W Roscoe St",
    "sg:city":"Chicago",
    "sg:classifiers":[
        {
            "category":"Arts & Performance",
            "subcategory":"Arts Center",
            "type":"Entertainment"
        }
    ],
    "sg:phone":"+1 773 348 9474",
    "sg:postcode":"60618",
    "sg:province":"IL",
    "sg:website":"www.wishcraftworkshop.com",
    "wof:name":"Wishcraft",
    "wof:placetype":"venue"
},
  "geometry": {"coordinates":[-87.686328,41.943409],"type":"Point"}
}