{
  "type": "Feature",
  "properties": {
    "addr:full":"3845 N Hamilton Ave Chicago IL 60618",
    "addr:housenumber":"3845",
    "addr:postcode":"60618",
    "addr:street":"N Hamilton Ave",
    "iso:country":"US",
    "sg:address":"3845 N Hamilton Ave",
    "sg:city":"Chicago",
    "sg:classifiers":[
        {
            "category":"Real Estate",
            "subcategory":"Real Estate Services",
            "type":"Services"
        },
        {
            "category":"Real Estate",
            "subcategory":"Surveying",
            "type":"Services"
        }
    ],
    "sg:phone":"+1 773 871 2425",
    "sg:postcode":"60618",
    "sg:province":"IL",
    "sg:tags":[
        "industrial",
        "appraisers-commercial",
        "appraiser"
    ],
    "wof:name":"C M Appraisal Services",
    "wof:placetype":"venue"
},
  "geometry": {"coordinates":[-87.682329,41.951268],"type":"Point"}
}