{
  "type": "Feature",
  "properties": {
    "addr:full":"118 W Main St Elmwood IL 61529",
    "addr:housenumber":"118",
    "addr:postcode":"61529",
    "addr:street":"W Main St",
    "iso:country":"US",
    "sg:address":"118 W Main St",
    "sg:city":"Elmwood",
    "sg:classifiers":[
        {
            "category":"Professional",
            "subcategory":"Lawyer & Legal Services",
            "type":"Services"
        }
    ],
    "sg:phone":"+1 309 742 3611",
    "sg:postcode":"61529",
    "sg:province":"IL",
    "sg:tags":[
        "attorney"
    ],
    "wof:name":"Whitney & Potts LTD",
    "wof:placetype":"venue"
},
  "geometry": {"coordinates":[-89.966341,40.77792],"type":"Point"}
}