{
  "type": "Feature",
  "properties": {
    "iso:country":"US",
    "sg:address":"40 W Acorn Ln",
    "sg:city":"Lake In the Hills",
    "sg:classifiers":[
        {
            "category":"Social Services",
            "subcategory":"Child Care",
            "type":"Services"
        },
        {
            "category":"Education",
            "subcategory":"Preschool",
            "type":"Public Place"
        },
        {
            "category":"Education",
            "subcategory":"School",
            "type":"Public Place"
        }
    ],
    "sg:phone":"+1 847 854 1699",
    "sg:postcode":"60156",
    "sg:province":"IL",
    "sg:tags":[
        "elementary",
        "day"
    ],
    "sg:website":"www.kindercare.com/Our-Centers/C...",
    "wof:name":"Lake In the Hills Kindercare",
    "wof:placetype":"venue"
},
  "geometry": {"coordinates":[-88.33393,42.181593],"type":"Point"}
}