{
  "type": "Feature",
  "properties": {
    "iso:country":"US",
    "sg:address":"2914 Cardinal Dr",
    "sg:city":"Rolling Meadows",
    "sg:classifiers":[
        {
            "category":"Building & Trades",
            "subcategory":"Construction",
            "type":"Services"
        }
    ],
    "sg:phone":"+1 847 259 4978",
    "sg:postcode":"60008",
    "sg:province":"IL",
    "sg:tags":[
        "residential"
    ],
    "wof:name":"K&L Qaulity",
    "wof:placetype":"venue"
},
  "geometry": {"coordinates":[-88.021448,42.081446],"type":"Point"}
}