{
  "type": "Feature",
  "properties": {
    "addr:full":"330 W North St Dwight IL 60420",
    "addr:housenumber":"330",
    "addr:postcode":"60420",
    "addr:street":"W North St",
    "iso:country":"US",
    "sg:address":"330 W North St",
    "sg:city":"Dwight",
    "sg:phone":"+1 815 584 2849",
    "sg:postcode":"60420",
    "sg:province":"IL",
    "sg:tags":[
        "farm",
        "corn"
    ],
    "wof:name":"Larry Zabel",
    "wof:placetype":"venue"
},
  "geometry": {"coordinates":[-88.433835,41.097545],"type":"Point"}
}