{
  "type": "Feature",
  "properties": {
    "iso:country":"US",
    "sg:address":"5209 N Clark St",
    "sg:city":"Chicago",
    "sg:classifiers":[
        {
            "category":"Banks & Credit Unions",
            "subcategory":"Bank",
            "type":"Services"
        }
    ],
    "sg:phone":"+1 773 275 3353",
    "sg:postcode":"60640",
    "sg:province":"IL",
    "sg:tags":[
        "personal",
        "institution"
    ],
    "wof:name":"Itf Inc",
    "wof:placetype":"venue"
},
  "geometry": {"coordinates":[-87.668322,41.97684],"type":"Point"}
}