{
  "type": "Feature",
  "properties": {
    "iso:country":"US",
    "sg:address":"1549 Sycamore Rd",
    "sg:city":"Yorkville",
    "sg:classifiers":[
        {
            "category":"Home & Garden",
            "subcategory":"Home Furnishings",
            "type":"Retail Goods"
        },
        {
            "category":"Home & Garden",
            "subcategory":"Carpets & Floor Coverings",
            "type":"Retail Goods"
        }
    ],
    "sg:phone":"+1 630 552 9988",
    "sg:postcode":"60560",
    "sg:province":"IL",
    "sg:tags":[
        "set",
        "bedding",
        "bed",
        "mattress",
        "linen",
        "bedroom"
    ],
    "wof:name":"Beds Beds Beds",
    "wof:placetype":"venue"
},
  "geometry": {"coordinates":[-88.47426299999999,41.660055],"type":"Point"}
}