{
  "type": "Feature",
  "properties": {
    "addr:full":"825 S County Line Rd Maple Park IL 60151",
    "addr:housenumber":"825",
    "addr:postcode":"60151",
    "addr:street":"S County Line Rd",
    "iso:country":"US",
    "sg:address":"825 S County Line Rd",
    "sg:city":"Maple Park",
    "sg:classifiers":[
        {
            "category":"Restaurant",
            "type":"Food & Drink"
        }
    ],
    "sg:menulink":"http://www.allmenus.com/il/cortland/226330-caseys-general-store/menu/",
    "sg:phone":"+1 815 827 4314",
    "sg:postcode":"60151",
    "sg:province":"IL",
    "sg:tags":[
        "american",
        "pizza"
    ],
    "wof:name":"Casey's General Store",
    "wof:placetype":"venue"
},
  "geometry": {"coordinates":[-88.60140699999999,41.901539],"type":"Point"}
}