{
  "type": "Feature",
  "properties": {
    "iso:country":"US",
    "sg:address":"3244 W Ainslie St",
    "sg:city":"Chicago",
    "sg:classifiers":[
        {
            "category":"Education",
            "subcategory":"School",
            "type":"Public Place"
        }
    ],
    "sg:phone":"+1 773 534 5191",
    "sg:postcode":"60625",
    "sg:province":"IL",
    "sg:tags":[
        "elementary"
    ],
    "sg:website":"www.hibbard.cps.k12.il.us",
    "wof:name":"Hibbard William G",
    "wof:placetype":"venue"
},
  "geometry": {"coordinates":[-87.710016,41.970243],"type":"Point"}
}