{
  "type": "Feature",
  "properties": {
    "addr:full":"4419 N Beacon St Chicago IL 60640",
    "addr:housenumber":"4419",
    "addr:postcode":"60640",
    "addr:street":"N Beacon",
    "iso:country":"US",
    "sg:address":"4419 N Beacon St",
    "sg:city":"Chicago",
    "sg:classifiers":[
        {
            "category":"Shopping",
            "subcategory":"Beauty & Cosmetics",
            "type":"Retail Goods"
        }
    ],
    "sg:phone":"+1   ",
    "sg:postcode":"60640",
    "sg:province":"IL",
    "sg:tags":[
        "merchandise"
    ],
    "wof:name":"Bodegas Merle Group LLC",
    "wof:placetype":"venue"
},
  "geometry": {"coordinates":[-87.66367700000001,41.963151],"type":"Point"}
}