{
  "type": "Feature",
  "properties": {
    "addr:full":"3808 Hitt Rd Tamaroa IL 62888",
    "addr:housenumber":"3808",
    "addr:postcode":"62888",
    "addr:street":"Hitt Rd",
    "iso:country":"US",
    "sg:address":"3808 Hitt Rd",
    "sg:city":"Tamaroa",
    "sg:classifiers":[
        {
            "category":"Insurance",
            "subcategory":"Hazard Insurance",
            "type":"Services"
        }
    ],
    "sg:phone":"+1 618 496 3268",
    "sg:postcode":"62888",
    "sg:province":"IL",
    "sg:tags":[
        "commercial",
        "business"
    ],
    "wof:name":"Hitt Insurance Agency",
    "wof:placetype":"venue"
},
  "geometry": {"coordinates":[-89.18654600000001,38.087753],"type":"Point"}
}