{
  "type": "Feature",
  "properties": {
    "iso:country":"US",
    "sg:address":"14416 High Rd",
    "sg:city":"Lockport",
    "sg:classifiers":[
        {
            "category":"Building & Trades",
            "subcategory":"Cleaning & Sanitation",
            "type":"Services"
        }
    ],
    "sg:phone":"+1 815 834 9900",
    "sg:postcode":"60441",
    "sg:province":"IL",
    "sg:tags":[
        "janitor"
    ],
    "wof:name":"Lourdes Cleaning Svc Inc",
    "wof:placetype":"venue"
},
  "geometry": {"coordinates":[-88.046235,41.623823],"type":"Point"}
}