{
  "type": "Feature",
  "properties": {
    "iso:country":"US",
    "sg:address":"6230 W 95th St",
    "sg:city":"Oak Lawn",
    "sg:classifiers":[
        {
            "category":"Home & Garden",
            "subcategory":"Household Appliances",
            "type":"Retail Goods"
        }
    ],
    "sg:phone":"+1 708 430 7157",
    "sg:postcode":"60453",
    "sg:province":"IL",
    "sg:tags":[
        "repair"
    ],
    "sg:website":"www.plassappliance.com",
    "wof:name":"Plass Appliance & Electronics",
    "wof:placetype":"venue"
},
  "geometry": {"coordinates":[-87.776398,41.7197],"type":"Point"}
}