{
  "type": "Feature",
  "properties": {
    "iso:country":"US",
    "sg:address":"17607 Frogtown Rd",
    "sg:city":"Carlyle",
    "sg:classifiers":[
        {
            "category":"Wholesale",
            "subcategory":"Farm Supplies",
            "type":"Manufacturing & Wholesale Goods"
        }
    ],
    "sg:phone":"+1 618 526 4671",
    "sg:postcode":"62231",
    "sg:province":"IL",
    "sg:tags":[
        "equipment"
    ],
    "wof:name":"Randy Kuhl",
    "wof:placetype":"venue"
},
  "geometry": {"coordinates":[-89.476585,38.674969],"type":"Point"}
}