{
  "type": "Feature",
  "properties": {
    "iso:country":"US",
    "sg:address":"117 N Stanton St",
    "sg:city":"Shannon",
    "sg:classifiers":[
        {
            "category":"Retail",
            "subcategory":"Repair Shop",
            "type":"Services"
        }
    ],
    "sg:phone":"+1 815 864 2497",
    "sg:postcode":"61078",
    "sg:province":"IL",
    "sg:tags":[
        "tractor"
    ],
    "wof:name":"Bryan's Repair",
    "wof:placetype":"venue"
},
  "geometry": {"coordinates":[-89.736008,42.156302],"type":"Point"}
}