{
  "type": "Feature",
  "properties": {
    "iso:country":"US",
    "sg:address":"15337 Cicero Ave",
    "sg:city":"Oak Forest",
    "sg:classifiers":[
        {
            "category":"Health Services",
            "subcategory":"Clinic",
            "type":"Services"
        }
    ],
    "sg:phone":"+1 708 535 4200",
    "sg:postcode":"60452",
    "sg:province":"IL",
    "sg:tags":[
        "home",
        "care"
    ],
    "wof:name":"Help At Home Inc",
    "wof:placetype":"venue"
},
  "geometry": {"coordinates":[-87.73677499999999,41.613078],"type":"Point"}
}