{
  "type": "Feature",
  "properties": {
    "iso:country":"US",
    "sg:address":"421 E Elm St",
    "sg:city":"Albion",
    "sg:classifiers":[
        {
            "category":"Autos & Motor Vehicles",
            "subcategory":"Auto Supplies",
            "type":"Retail Goods"
        }
    ],
    "sg:phone":"+1 618 445 3265",
    "sg:postcode":"62806",
    "sg:province":"IL",
    "sg:tags":[
        "tire"
    ],
    "wof:name":"Edwards County Tire",
    "wof:placetype":"venue"
},
  "geometry": {"coordinates":[-88.049718,38.378337],"type":"Point"}
}