{
  "type": "Feature",
  "properties": {
    "addr:full":"1030 N Dearborn St Chicago IL 60610",
    "addr:housenumber":"1030",
    "addr:postcode":"60610",
    "addr:street":"N Dearborn St",
    "iso:country":"US",
    "sg:address":"1030 N Dearborn St",
    "sg:city":"Chicago",
    "sg:classifiers":[
        {
            "category":"Real Estate",
            "subcategory":"Real Estate Operator",
            "type":"Services"
        }
    ],
    "sg:phone":"+1 312 397 0777",
    "sg:postcode":"60610",
    "sg:province":"IL",
    "sg:tags":[
        "apartment"
    ],
    "sg:website":"halapts.com/",
    "wof:name":"1030 North Dearborn Plaza Apartments",
    "wof:placetype":"venue"
},
  "geometry": {"coordinates":[-87.629898,41.901001],"type":"Point"}
}