{
  "type": "Feature",
  "properties": {
    "addr:full":"2137 W Belmont Ave Chicago IL 60618",
    "addr:housenumber":"2137",
    "addr:postcode":"60618",
    "addr:street":"W Belmont Ave",
    "iso:country":"US",
    "sg:address":"2137 W Belmont Ave",
    "sg:city":"Chicago",
    "sg:classifiers":[
        {
            "category":"Personal",
            "subcategory":"Barber",
            "type":"Services"
        }
    ],
    "sg:phone":"+1 773 829 4184",
    "sg:postcode":"60618",
    "sg:province":"IL",
    "sg:website":"http://chicago.citysearch.com/profile/36764517/chicago_il/emmett_hodge_hair_stylist_make_up_artist.html?publisher=yellowpages&reference_id=1&placement=ypwebsitemip",
    "wof:name":"Emmett Hodge - Hair Stylist & Make-up Artist",
    "wof:placetype":"venue"
},
  "geometry": {"coordinates":[-87.681682,41.939534],"type":"Point"}
}