{
  "type": "Feature",
  "properties": {
    "iso:country":"US",
    "sg:address":"2365 Lakeshore Ct",
    "sg:city":"Aurora",
    "sg:classifiers":[
        {
            "category":"Shopping",
            "subcategory":"Clothing, Apparel, & Fashions",
            "type":"Retail Goods"
        }
    ],
    "sg:phone":"+1   ",
    "sg:postcode":"60504",
    "sg:province":"IL",
    "wof:name":"Honn Enterprises Inc",
    "wof:placetype":"venue"
},
  "geometry": {"coordinates":[-88.258775,41.737688],"type":"Point"}
}