{
  "type": "Feature",
  "properties": {
    "iso:country":"US",
    "sg:address":"402 N 3rd St",
    "sg:city":"Girard",
    "sg:classifiers":[
        {
            "category":"Banks & Credit Unions",
            "subcategory":"Bank",
            "type":"Services"
        }
    ],
    "sg:phone":"+1 217 627 2186",
    "sg:postcode":"62640",
    "sg:province":"IL",
    "sg:tags":[
        "saving",
        "commercial"
    ],
    "sg:website":"http://www.fmstatebank.com",
    "wof:name":"Farmers Insurance",
    "wof:placetype":"venue"
},
  "geometry": {"coordinates":[-89.780579,39.449214],"type":"Point"}
}