{
  "type": "Feature",
  "properties": {
    "iso:country":"US",
    "sg:address":"207 E McAllister St",
    "sg:city":"Lebanon",
    "sg:classifiers":[
        {
            "category":"Recreation",
            "type":"Entertainment"
        }
    ],
    "sg:phone":"+1 618 537 4340",
    "sg:postcode":"62254",
    "sg:province":"IL",
    "sg:tags":[
        "psychic",
        "medium"
    ],
    "wof:name":"Astrology Bar",
    "wof:placetype":"venue"
},
  "geometry": {"coordinates":[-89.804935,38.595051],"type":"Point"}
}