{
  "type": "Feature",
  "properties": {
    "iso:country":"US",
    "sg:address":"2920 N Commonwealth Ave",
    "sg:city":"Chicago",
    "sg:classifiers":[
        {
            "category":"Travel",
            "subcategory":"Travel Agent",
            "type":"Entertainment"
        }
    ],
    "sg:phone":"+1 773 525 4669",
    "sg:postcode":"60657",
    "sg:province":"IL",
    "sg:tags":[
        "agency",
        "bureau"
    ],
    "wof:name":"Ftt-Harold Travel Service",
    "wof:placetype":"venue"
},
  "geometry": {"coordinates":[-87.63823600000001,41.93512],"type":"Point"}
}