{
  "type": "Feature",
  "properties": {
    "iso:country":"US",
    "sg:address":"217 Schoen Ave",
    "sg:city":"Sorento",
    "sg:classifiers":[
        {
            "category":"Farming",
            "subcategory":"Farm",
            "type":"Manufacturing & Wholesale Goods"
        }
    ],
    "sg:phone":"+1 618 488 7777",
    "sg:postcode":"62086",
    "sg:province":"IL",
    "sg:tags":[
        "crop",
        "general"
    ],
    "wof:name":"Jeff A Schoen",
    "wof:placetype":"venue"
},
  "geometry": {"coordinates":[-89.596126,38.896472],"type":"Point"}
}