{
  "type": "Feature",
  "properties": {
    "addr:full":"6271 W Hyacinth St Chicago IL 60646",
    "addr:housenumber":"6271",
    "addr:postcode":"60646",
    "addr:street":"W Hyacinth St",
    "iso:country":"US",
    "sg:address":"6271 W Hyacinth St",
    "sg:city":"Chicago",
    "sg:classifiers":[
        {
            "category":"Professional",
            "subcategory":"Business Services",
            "type":"Services"
        }
    ],
    "sg:phone":"+1 773 792 8479",
    "sg:postcode":"60646",
    "sg:province":"IL",
    "wof:name":"Jej Design Ltd",
    "wof:placetype":"venue"
},
  "geometry": {"coordinates":[-87.78542,41.992117],"type":"Point"}
}