{
  "type": "Feature",
  "properties": {
    "addr:full":"5615 Northwest Hwy Crystal Lake IL 60014",
    "addr:housenumber":"5615",
    "addr:postcode":"60014",
    "addr:street":"Northwest Hwy",
    "iso:country":"US",
    "sg:address":"5615 Northwest Hwy",
    "sg:city":"Crystal Lake",
    "sg:classifiers":[
        {
            "category":"Banks & Credit Unions",
            "subcategory":"Bank",
            "type":"Services"
        }
    ],
    "sg:phone":"+1 815 788 0114",
    "sg:postcode":"60014",
    "sg:province":"IL",
    "sg:tags":[
        "financing"
    ],
    "wof:name":"Wells Fargo Financial",
    "wof:placetype":"venue"
},
  "geometry": {"coordinates":[-88.29878600000001,42.226175],"type":"Point"}
}