{
  "type": "Feature",
  "properties": {
    "addr:full":"49 W 111th Pl Chicago IL 60628",
    "addr:housenumber":"49",
    "addr:postcode":"60628",
    "addr:street":"W 111Th Pl",
    "iso:country":"US",
    "sg:address":"49 W 111th Pl",
    "sg:city":"Chicago",
    "sg:classifiers":[
        {
            "category":"Social Services",
            "subcategory":"Child Care",
            "type":"Services"
        }
    ],
    "sg:phone":"+1 773 821 5500",
    "sg:postcode":"60628",
    "sg:province":"IL",
    "sg:tags":[
        "day"
    ],
    "wof:name":"Intelligent Minds",
    "wof:placetype":"venue"
},
  "geometry": {"coordinates":[-87.624363,41.691534],"type":"Point"}
}