{
  "type": "Feature",
  "properties": {
    "iso:country":"US",
    "sg:address":"956 E 58th St",
    "sg:city":"Chicago",
    "sg:classifiers":[
        {
            "category":"Government",
            "subcategory":"Post Office",
            "type":"Public Place"
        }
    ],
    "sg:postcode":"60615",
    "sg:province":"IL",
    "sg:website":"www.usps.com",
    "wof:name":"United States Post Office - Finance Station U",
    "wof:placetype":"venue"
},
  "geometry": {"coordinates":[-87.60262299999999,41.789465],"type":"Point"}
}