{
  "type": "Feature",
  "properties": {
    "iso:country":"US",
    "sg:address":"S Harlem Ave",
    "sg:city":"Chicago",
    "sg:classifiers":[
        {
            "category":"Restaurant",
            "type":"Food & Drink"
        }
    ],
    "sg:menulink":"http://www.allmenus.com/il/chicago/219599-el-gallo-de-oro-restaurant/menu/",
    "sg:phone":"+1 708 448 5449",
    "sg:postcode":"60638",
    "sg:province":"IL",
    "sg:tags":[
        "mexican"
    ],
    "wof:name":"El Gallo De Oro Restaurant",
    "wof:placetype":"venue"
},
  "geometry": {"coordinates":[-87.800878,41.776491],"type":"Point"}
}