{
  "type": "Feature",
  "properties": {
    "iso:country":"US",
    "sg:address":"1820 Lockwood Dr",
    "sg:city":"Libertyville",
    "sg:classifiers":[
        {
            "category":"Manufacturing",
            "subcategory":"Buildings",
            "type":"Manufacturing & Wholesale Goods"
        },
        {
            "category":"Home & Garden",
            "subcategory":"Building Materials",
            "type":"Retail Goods"
        },
        {
            "category":"Building & Trades",
            "subcategory":"Construction",
            "type":"Services"
        }
    ],
    "sg:phone":"+1 847 816 0853",
    "sg:postcode":"60048",
    "sg:province":"IL",
    "sg:tags":[
        "industrial",
        "specialty",
        "builder",
        "heating",
        "system",
        "contractors-commercial",
        "contractor",
        "gazebo",
        "air conditioning",
        "patio"
    ],
    "wof:name":"Top Deck Builders, Incorporated.",
    "wof:placetype":"venue"
},
  "geometry": {"coordinates":[-87.91103,42.305898],"type":"Point"}
}