{
  "type": "Feature",
  "properties": {
    "addr:full":"328 Antelope Trl Carol Stream IL 60188",
    "addr:housenumber":"328",
    "addr:postcode":"60188",
    "addr:street":"Antelope Trl",
    "iso:country":"US",
    "sg:address":"328 Antelope Trl",
    "sg:city":"Carol Stream",
    "sg:classifiers":[
        {
            "category":"Professional",
            "subcategory":"Business Services",
            "type":"Services"
        }
    ],
    "sg:phone":"+1 630 690 4435",
    "sg:postcode":"60188",
    "sg:province":"IL",
    "sg:tags":[
        "interior",
        "consultant",
        "design",
        "decorator"
    ],
    "wof:name":"Barbara Tabor Designs LTD",
    "wof:placetype":"venue"
},
  "geometry": {"coordinates":[-88.130709,41.92948],"type":"Point"}
}