{
  "type": "Feature",
  "properties": {
    "iso:country":"US",
    "sg:address":"1656 Gardner Rd",
    "sg:city":"Westchester",
    "sg:classifiers":[
        {
            "category":"Professional",
            "subcategory":"Management & Consulting",
            "type":"Services"
        }
    ],
    "sg:phone":"+1   ",
    "sg:postcode":"60154",
    "sg:province":"IL",
    "sg:tags":[
        "retail",
        "direct",
        "sales"
    ],
    "wof:name":"Lady Remington",
    "wof:placetype":"venue"
},
  "geometry": {"coordinates":[-87.867428,41.855046],"type":"Point"}
}