{
  "type": "Feature",
  "properties": {
    "iso:country":"US",
    "sg:address":"931 N Lombard Ave",
    "sg:city":"Oak Park",
    "sg:classifiers":[
        {
            "category":"Home & Garden",
            "subcategory":"Home Furnishings",
            "type":"Retail Goods"
        }
    ],
    "sg:phone":"+1   ",
    "sg:postcode":"60302",
    "sg:province":"IL",
    "wof:name":"Custom Interiors",
    "wof:placetype":"venue"
},
  "geometry": {"coordinates":[-87.78036400000001,41.903257],"type":"Point"}
}