{
  "type": "Feature",
  "properties": {
    "iso:country":"US",
    "sg:address":"6851 N Kilpatrick Ave",
    "sg:city":"Lincolnwood",
    "sg:classifiers":[
        {
            "category":"Professional",
            "subcategory":"Management & Consulting",
            "type":"Services"
        }
    ],
    "sg:phone":"+1 847 676 9598",
    "sg:postcode":"60712",
    "sg:province":"IL",
    "sg:tags":[
        "counselor",
        "relation",
        "public"
    ],
    "sg:website":"http://www.lehrercommunications.com",
    "wof:name":"Jonathan Lehrer Communica",
    "wof:placetype":"venue"
},
  "geometry": {"coordinates":[-87.74601,42.00536],"type":"Point"}
}