{
  "type": "Feature",
  "properties": {
    "addr:full":"214 N Main St Galena IL 61036",
    "addr:housenumber":"214",
    "addr:postcode":"61036",
    "addr:street":"N Main St",
    "iso:country":"US",
    "sg:address":"214 N Main St",
    "sg:city":"Galena",
    "sg:classifiers":[
        {
            "category":"Shopping",
            "subcategory":"Crafts & Fabrics",
            "type":"Retail Goods"
        }
    ],
    "sg:phone":"+1 815 777 3550",
    "sg:postcode":"61036",
    "sg:province":"IL",
    "sg:tags":[
        "yarn"
    ],
    "wof:name":"Fiber Wild",
    "wof:placetype":"venue"
},
  "geometry": {"coordinates":[-90.427239,42.416595],"type":"Point"}
}