{
  "type": "Feature",
  "properties": {
    "addr:full":"354 Boulder Dr Glendale Heights IL 60139",
    "addr:housenumber":"354",
    "addr:postcode":"60139",
    "addr:street":"Boulder Dr",
    "iso:country":"US",
    "sg:address":"354 Boulder Dr",
    "sg:city":"Glendale Heights",
    "sg:classifiers":[
        {
            "category":"Education",
            "subcategory":"Special Training",
            "type":"Public Place"
        }
    ],
    "sg:phone":"+1 630 980 1938",
    "sg:postcode":"60139",
    "sg:province":"IL",
    "wof:name":"Qasim Darul",
    "wof:placetype":"venue"
},
  "geometry": {"coordinates":[-88.072682,41.931154],"type":"Point"}
}