{
  "type": "Feature",
  "properties": {
    "addr:full":"943 W Superior St Chicago IL 60642",
    "addr:housenumber":"943",
    "addr:postcode":"60642",
    "addr:street":"W Superior St",
    "iso:country":"US",
    "sg:address":"943 W Superior St",
    "sg:city":"Chicago",
    "sg:classifiers":[
        {
            "category":"Professional",
            "subcategory":"Art Services",
            "type":"Services"
        },
        {
            "category":"Building & Trades",
            "subcategory":"Construction",
            "type":"Services"
        }
    ],
    "sg:phone":"+1 312 563 0000",
    "sg:postcode":"60642",
    "sg:province":"IL",
    "sg:tags":[
        "interior",
        "designer",
        "design",
        "decorator"
    ],
    "wof:name":"Marshall Morgan Erb Design",
    "wof:placetype":"venue"
},
  "geometry": {"coordinates":[-87.65136800000001,41.895356],"type":"Point"}
}