{
  "type": "Feature",
  "properties": {
    "addr:full":"15774 S LaGrange Rd #240 Orland Park IL 60462",
    "addr:housenumber":"15774",
    "addr:postcode":"60462",
    "addr:street":"S Lagrange Rd # 240",
    "iso:country":"US",
    "sg:address":"15774 S LaGrange Rd #240",
    "sg:city":"Orland Park",
    "sg:classifiers":[
        {
            "category":"Building & Trades",
            "subcategory":"Construction",
            "type":"Services"
        }
    ],
    "sg:phone":"+1 708 349 9551",
    "sg:postcode":"60462",
    "sg:province":"IL",
    "sg:tags":[
        "air",
        "heating",
        "conditioning/hvac"
    ],
    "sg:website":"www.mrductcleaning.com",
    "wof:name":"Mr. Duct Air Duct Cleaning",
    "wof:placetype":"venue"
},
  "geometry": {"coordinates":[-87.70004,41.694149],"type":"Point"}
}