{
  "type": "Feature",
  "properties": {
    "iso:country":"US",
    "sg:address":"64 130th Ave",
    "sg:city":"Kirkwood",
    "sg:phone":"+1 309 768 2507",
    "sg:postcode":"61447",
    "sg:province":"IL",
    "sg:tags":[
        "farm",
        "corn",
        "soybean"
    ],
    "wof:name":"Jim Missavage",
    "wof:placetype":"venue"
},
  "geometry": {"coordinates":[-90.782894,40.821136],"type":"Point"}
}