{
  "type": "Feature",
  "properties": {
    "iso:country":"US",
    "sg:address":"5855 W 75th Pl",
    "sg:city":"Burbank",
    "sg:classifiers":[
        {
            "category":"Health Services",
            "subcategory":"Doctor",
            "type":"Services"
        }
    ],
    "sg:phone":"+1 708 458 7197",
    "sg:postcode":"60459",
    "sg:province":"IL",
    "sg:tags":[
        "physician",
        "surgeon"
    ],
    "wof:name":"Jozef A Zuwala",
    "wof:placetype":"venue"
},
  "geometry": {"coordinates":[-87.765396,41.755561],"type":"Point"}
}