{
  "type": "Feature",
  "properties": {
    "iso:country":"US",
    "sg:address":"114 S Oak St",
    "sg:city":"De Soto",
    "sg:classifiers":[
        {
            "category":"Organizations",
            "subcategory":"Religious Organization",
            "type":"Services"
        }
    ],
    "sg:phone":"+1 618 867 2418",
    "sg:postcode":"62924",
    "sg:province":"IL",
    "sg:tags":[
        "church"
    ],
    "wof:name":"Mt Calvary Lutheran Church",
    "wof:placetype":"venue"
},
  "geometry": {"coordinates":[-89.226725,37.816065],"type":"Point"}
}