{
  "type": "Feature",
  "properties": {
    "addr:full":"5915 W Grand Avenue Chicago IL 60639",
    "addr:housenumber":"5915",
    "addr:postcode":"60639",
    "addr:street":"W Grand Avenue",
    "iso:country":"US",
    "sg:address":"5915 W Grand Avenue",
    "sg:city":"Chicago",
    "sg:classifiers":[
        {
            "category":"Retail",
            "subcategory":"Auto Repair",
            "type":"Services"
        }
    ],
    "sg:phone":"+1 773 637 6001",
    "sg:postcode":"60639",
    "sg:province":"IL",
    "wof:name":"Compact Cars",
    "wof:placetype":"venue"
},
  "geometry": {"coordinates":[-87.773403,41.919983],"type":"Point"}
}