{
  "type": "Feature",
  "properties": {
    "iso:country":"US",
    "sg:address":"900 S Frontage Rd",
    "sg:city":"Woodridge",
    "sg:classifiers":[
        {
            "category":"Health Services",
            "subcategory":"Doctor",
            "type":"Services"
        }
    ],
    "sg:phone":"+1 630 324 7900",
    "sg:postcode":"60517",
    "sg:province":"IL",
    "sg:tags":[
        "physician",
        "surgeon"
    ],
    "wof:name":"Cardiac Surgery Assoc",
    "wof:placetype":"venue"
},
  "geometry": {"coordinates":[-88.004464,41.715666],"type":"Point"}
}