{
  "type": "Feature",
  "properties": {
    "iso:country":"US",
    "sg:address":"511 N Broadway St",
    "sg:city":"Joliet",
    "sg:classifiers":[
        {
            "category":"Wholesale",
            "subcategory":"Vending Machines",
            "type":"Manufacturing & Wholesale Goods"
        }
    ],
    "sg:phone":"+1   ",
    "sg:postcode":"60435",
    "sg:province":"IL",
    "sg:tags":[
        "operator"
    ],
    "wof:name":"AM Vending",
    "wof:placetype":"venue"
},
  "geometry": {"coordinates":[-88.087001,41.533474],"type":"Point"}
}