{
  "type": "Feature",
  "properties": {
    "addr:full":"400 Lake Cook Rd Deerfield IL 60015",
    "addr:housenumber":"400",
    "addr:postcode":"60015",
    "addr:street":"Lake Cook Rd",
    "iso:country":"US",
    "sg:address":"400 Lake Cook Rd",
    "sg:city":"Deerfield",
    "sg:classifiers":[
        {
            "category":"Insurance",
            "subcategory":"Insurance Agent",
            "type":"Services"
        },
        {
            "category":"Insurance",
            "subcategory":"Hazard Insurance",
            "type":"Services"
        },
        {
            "category":"Insurance",
            "subcategory":"Title Insurance",
            "type":"Services"
        },
        {
            "category":"Insurance",
            "subcategory":"Life Insurance",
            "type":"Services"
        }
    ],
    "sg:phone":"+1 847 236 9000",
    "sg:postcode":"60015",
    "sg:province":"IL",
    "sg:tags":[
        "business",
        "auto",
        "commercial",
        "homeowner",
        "motorcycle",
        "renter"
    ],
    "wof:name":"Allstate Insurance Company - Marc Turim",
    "wof:placetype":"venue"
},
  "geometry": {"coordinates":[-87.837965,42.152757],"type":"Point"}
}