{
  "type": "Feature",
  "properties": {
    "addr:full":"653 Carlyle Ave Belleville IL 62221",
    "addr:housenumber":"653",
    "addr:postcode":"62221",
    "addr:street":"Carlyle Ave",
    "iso:country":"US",
    "sg:address":"653 Carlyle Ave",
    "sg:city":"Belleville",
    "sg:classifiers":[
        {
            "category":"Restaurant",
            "type":"Food & Drink"
        }
    ],
    "sg:phone":"+1 618 257 1888",
    "sg:postcode":"62221",
    "sg:province":"IL",
    "sg:tags":[
        "eating"
    ],
    "wof:name":"Bamboo Valley Buffet",
    "wof:placetype":"venue"
},
  "geometry": {"coordinates":[-89.95427599999999,38.516999],"type":"Point"}
}