{
  "type": "Feature",
  "properties": {
    "addr:full":"110 N High St Belleville IL 62220",
    "addr:housenumber":"110",
    "addr:postcode":"62220",
    "addr:street":"N High St",
    "iso:country":"US",
    "sg:address":"110 N High St",
    "sg:city":"Belleville",
    "sg:classifiers":[
        {
            "category":"Organizations",
            "subcategory":"Labor Organization",
            "type":"Services"
        }
    ],
    "sg:phone":"+1 618 233 0766",
    "sg:postcode":"62220",
    "sg:province":"IL",
    "wof:name":"Communications Wkrs Amer Local",
    "wof:placetype":"venue"
},
  "geometry": {"coordinates":[-89.982759,38.51543],"type":"Point"}
}