{
  "type": "Feature",
  "properties": {
    "addr:full":"3458 N Halsted St Chicago IL 60657",
    "addr:housenumber":"3458",
    "addr:postcode":"60657",
    "addr:street":"N Halsted St",
    "iso:country":"US",
    "sg:address":"3458 N Halsted St",
    "sg:city":"Chicago",
    "sg:classifiers":[
        {
            "category":"Bars & Pubs",
            "type":"Food & Drink"
        }
    ],
    "sg:phone":"+1 773 975 9244",
    "sg:postcode":"60657",
    "sg:province":"IL",
    "sg:tags":[
        "dance",
        "club",
        "drinking"
    ],
    "sg:website":"www.hydratechicago.com",
    "wof:name":"Hydrate",
    "wof:placetype":"venue"
},
  "geometry": {"coordinates":[-87.649451,41.945063],"type":"Point"}
}