{
  "type": "Feature",
  "properties": {
    "iso:country":"US",
    "sg:address":"17130 Torrence Ave",
    "sg:city":"Lansing",
    "sg:classifiers":[
        {
            "category":"Insurance",
            "subcategory":"Hazard Insurance",
            "type":"Services"
        },
        {
            "category":"Banks & Credit Unions",
            "subcategory":"Bank",
            "type":"Services"
        },
        {
            "category":"Banks & Credit Unions",
            "subcategory":"Financial Services",
            "type":"Services"
        }
    ],
    "sg:phone":"+1 708 895 6442",
    "sg:postcode":"60438",
    "sg:province":"IL",
    "sg:tags":[
        "commercial",
        "loan",
        "saving",
        "business"
    ],
    "wof:name":"Royal Savings Bank",
    "wof:placetype":"venue"
},
  "geometry": {"coordinates":[-87.558864,41.583864],"type":"Point"}
}