{
  "type": "Feature",
  "properties": {
    "addr:full":"5125 Sherwin Ave Skokie IL 60077",
    "addr:housenumber":"5125",
    "addr:postcode":"60077",
    "addr:street":"Sherwin Ave",
    "iso:country":"US",
    "sg:address":"5125 Sherwin Ave",
    "sg:city":"Skokie",
    "sg:classifiers":[
        {
            "category":"Manufacturing",
            "subcategory":"Printing",
            "type":"Manufacturing & Wholesale Goods"
        }
    ],
    "sg:phone":"+1 847 674 9662",
    "sg:postcode":"60077",
    "sg:province":"IL",
    "sg:tags":[
        "printer"
    ],
    "wof:name":"Express Printing Ctr",
    "wof:placetype":"venue"
},
  "geometry": {"coordinates":[-87.756201,42.014487],"type":"Point"}
}