{
  "type": "Feature",
  "properties": {
    "iso:country":"US",
    "sg:address":"7349 Hamlin Ave",
    "sg:city":"Skokie",
    "sg:classifiers":[
        {
            "category":"Manufacturing",
            "subcategory":"Tools & Machinery",
            "type":"Manufacturing & Wholesale Goods"
        }
    ],
    "sg:phone":"+1 847 679 8770",
    "sg:postcode":"60076",
    "sg:province":"IL",
    "sg:tags":[
        "machine",
        "shop",
        "industrial",
        "mfg"
    ],
    "wof:name":"G S Machine & Tool Inc",
    "wof:placetype":"venue"
},
  "geometry": {"coordinates":[-87.723683,42.013577],"type":"Point"}
}