{
  "type": "Feature",
  "properties": {
    "addr:full":"6 Victory Ln Fairfield IL 62837",
    "addr:housenumber":"6",
    "addr:postcode":"62837",
    "addr:street":"Victory Ln",
    "iso:country":"US",
    "sg:address":"6 Victory Ln",
    "sg:city":"Fairfield",
    "sg:classifiers":[
        {
            "category":"Organizations",
            "subcategory":"Religious Organization",
            "type":"Services"
        }
    ],
    "sg:phone":"+1 618 842 5371",
    "sg:postcode":"62837",
    "sg:province":"IL",
    "sg:tags":[
        "clergy"
    ],
    "wof:name":"Trent Philip Pastor",
    "wof:placetype":"venue"
},
  "geometry": {"coordinates":[-88.37712500000001,38.375991],"type":"Point"}
}