{
  "type": "Feature",
  "properties": {
    "iso:country":"US",
    "sg:address":"2255 S Throop 1st Fl",
    "sg:city":"Chicago",
    "sg:classifiers":[
        {
            "category":"Autos & Motor Vehicles",
            "subcategory":"Automobile Sales",
            "type":"Retail Goods"
        }
    ],
    "sg:phone":"+1 312 808 9700",
    "sg:postcode":"60608",
    "sg:province":"IL",
    "sg:tags":[
        "limo"
    ],
    "sg:website":"www.masterstrans.com",
    "wof:name":"Masters Transportation",
    "wof:placetype":"venue"
},
  "geometry": {"coordinates":[-87.658647,41.851347],"type":"Point"}
}