{
  "type": "Feature",
  "properties": {
    "iso:country":"US",
    "sg:address":"6400 Shafer Ct",
    "sg:city":"Des Plaines",
    "sg:classifiers":[
        {
            "category":"Manufacturing",
            "subcategory":"Chemicals & Compounds",
            "type":"Manufacturing & Wholesale Goods"
        }
    ],
    "sg:phone":"+1 847 696 0800",
    "sg:postcode":"60018",
    "sg:province":"IL",
    "sg:tags":[
        "flavor",
        "sales",
        "fragrance",
        "for"
    ],
    "wof:name":"I F F",
    "wof:placetype":"venue"
},
  "geometry": {"coordinates":[-87.86515,41.995696],"type":"Point"}
}