{
  "type": "Feature",
  "properties": {
    "iso:country":"US",
    "sg:address":"450 Norwood Square Dr",
    "sg:city":"Park Forest",
    "sg:classifiers":[
        {
            "category":"Shopping",
            "subcategory":"Discount & Variety Stores",
            "type":"Retail Goods"
        },
        {
            "category":"Shopping",
            "subcategory":"Department Store",
            "type":"Retail Goods"
        }
    ],
    "sg:phone":"+1 708 503 4147",
    "sg:postcode":"60466",
    "sg:province":"IL",
    "sg:tags":[
        "shop"
    ],
    "wof:name":"Family Dollar Stores",
    "wof:placetype":"venue"
},
  "geometry": {"coordinates":[-87.67655000000001,41.492024],"type":"Point"}
}