{
  "type": "Feature",
  "properties": {
    "addr:full":"803 E Kettering Park Dr Urbana IL 61801",
    "addr:housenumber":"803",
    "addr:postcode":"61801",
    "addr:street":"E Kettering Park Dr",
    "iso:country":"US",
    "sg:address":"803 E Kettering Park Dr",
    "sg:city":"Urbana",
    "sg:classifiers":[
        {
            "category":"Organizations",
            "subcategory":"Religious Organization",
            "type":"Services"
        }
    ],
    "sg:phone":"+1 217 344 4636",
    "sg:postcode":"61801",
    "sg:province":"IL",
    "wof:name":"Nehemiah Ministries",
    "wof:placetype":"venue"
},
  "geometry": {"coordinates":[-88.219002,40.129902],"type":"Point"}
}