{
  "type": "Feature",
  "properties": {
    "addr:full":"2805 S 25th Ave Broadview IL 60155",
    "addr:housenumber":"2805",
    "addr:postcode":"60155",
    "addr:street":"S 25Th Ave",
    "iso:country":"US",
    "sg:address":"2805 S 25th Ave",
    "sg:city":"Broadview",
    "sg:classifiers":[
        {
            "category":"Manufacturing",
            "subcategory":"Textiles",
            "type":"Manufacturing & Wholesale Goods"
        },
        {
            "category":"Professional",
            "subcategory":"Advertising",
            "type":"Services"
        },
        {
            "category":"School Buses",
            "type":"Transportation"
        },
        {
            "category":"Wholesale",
            "subcategory":"Home Furnishings",
            "type":"Manufacturing & Wholesale Goods"
        }
    ],
    "sg:phone":"+1 708 343 6555",
    "sg:postcode":"60155",
    "sg:province":"IL",
    "sg:tags":[
        "product",
        "upholstery",
        "fabrics-wholesale",
        "specialty",
        "identification",
        "advertising-promotional",
        "card",
        "manufacturer"
    ],
    "sg:website":"http://www.compusystems.com",
    "wof:name":"Adcraft Manufacturing",
    "wof:placetype":"venue"
},
  "geometry": {"coordinates":[-87.862346,41.852725],"type":"Point"}
}