{
  "type": "Feature",
  "properties": {
    "iso:country":"US",
    "sg:address":"10030 S Western Ave",
    "sg:city":"Chicago",
    "sg:classifiers":[
        {
            "category":"Banks & Credit Unions",
            "subcategory":"Bank",
            "type":"Services"
        }
    ],
    "sg:phone":"+1 773 445 7170",
    "sg:postcode":"60643",
    "sg:province":"IL",
    "sg:tags":[
        "loan",
        "real estate"
    ],
    "wof:name":"Blue Line Mortgage Group",
    "wof:placetype":"venue"
},
  "geometry": {"coordinates":[-87.68182,41.710585],"type":"Point"}
}