{
  "type": "Feature",
  "properties": {
    "iso:country":"US",
    "sg:address":"122 Lincoln Place Ct",
    "sg:city":"Belleville",
    "sg:classifiers":[
        {
            "category":"Professional",
            "subcategory":"Engineering",
            "type":"Services"
        }
    ],
    "sg:phone":"+1 618 233 1010",
    "sg:postcode":"62221",
    "sg:province":"IL",
    "wof:name":"Schweitzer Engineering Labs",
    "wof:placetype":"venue"
},
  "geometry": {"coordinates":[-89.937123,38.518199],"type":"Point"}
}