{
  "type": "Feature",
  "properties": {
    "iso:country":"US",
    "sg:address":"50 N Martingale Rd",
    "sg:city":"Schaumburg",
    "sg:classifiers":[
        {
            "category":"Travel",
            "subcategory":"Hotels & Motels",
            "type":"Entertainment"
        }
    ],
    "sg:phone":"+1 847 240 0100",
    "sg:postcode":"60173",
    "sg:province":"IL",
    "sg:tags":[
        "lodging"
    ],
    "sg:website":"http://ad.doubleclick.net/clk;227431036;51131009;n?http://www.marriott.com/hotels/travel/CHISB",
    "wof:name":"Chicago Marriott Schaumburg",
    "wof:placetype":"venue"
},
  "geometry": {"coordinates":[-88.03182,42.026577],"type":"Point"}
}