{
  "type": "Feature",
  "properties": {
    "iso:country":"US",
    "sg:address":"4444 W Sunnyside Ave",
    "sg:city":"Chicago",
    "sg:phone":"+1 773 852 6974",
    "sg:postcode":"60630",
    "sg:province":"IL",
    "wof:name":"Bogan Kowalski",
    "wof:placetype":"venue"
},
  "geometry": {"coordinates":[-87.740021,41.962636],"type":"Point"}
}