{
  "type": "Feature",
  "properties": {
    "addr:full":"272 Apollo Ct Wood Dale IL 60191",
    "addr:housenumber":"272",
    "addr:postcode":"60191",
    "addr:street":"Apollo Ct",
    "iso:country":"US",
    "sg:address":"272 Apollo Ct",
    "sg:city":"Wood Dale",
    "sg:classifiers":[
        {
            "category":"Shopping",
            "subcategory":"Beauty & Cosmetics",
            "type":"Retail Goods"
        }
    ],
    "sg:phone":"+1   ",
    "sg:postcode":"60191",
    "sg:province":"IL",
    "sg:tags":[
        "food",
        "merchandise"
    ],
    "wof:name":"Shaklee",
    "wof:placetype":"venue"
},
  "geometry": {"coordinates":[-88.00142200000001,41.961164],"type":"Point"}
}