{
  "type": "Feature",
  "properties": {
    "iso:country":"US",
    "sg:address":"1483 Co Rd 1900 E",
    "sg:city":"Urbana",
    "sg:phone":"+1 217 469 2626",
    "sg:postcode":"61802",
    "sg:province":"IL",
    "sg:tags":[
        "farm",
        "corn",
        "soybean"
    ],
    "wof:name":"Francis Osterbur",
    "wof:placetype":"venue"
},
  "geometry": {"coordinates":[-88.10477299999999,40.096397],"type":"Point"}
}