{
  "type": "Feature",
  "properties": {
    "iso:country":"US",
    "sg:address":"5102 Baker Rd",
    "sg:city":"Salem",
    "sg:classifiers":[
        {
            "category":"Retail",
            "subcategory":"Auto Repair",
            "type":"Services"
        }
    ],
    "sg:phone":"+1 618 548 4129",
    "sg:postcode":"62881",
    "sg:province":"IL",
    "sg:tags":[
        "body",
        "painting",
        "repairing",
        "automobile"
    ],
    "wof:name":"Woods Body Shop",
    "wof:placetype":"venue"
},
  "geometry": {"coordinates":[-88.901586,38.63905],"type":"Point"}
}