{
  "type": "Feature",
  "properties": {
    "addr:full":"1404 1/2 W Belmont Ave Chicago IL 60657",
    "addr:housenumber":"1404 1 / 2",
    "addr:postcode":"60657",
    "addr:street":"W Belmont Ave",
    "iso:country":"US",
    "sg:address":"1404 1/2 W Belmont Ave",
    "sg:city":"Chicago",
    "sg:classifiers":[
        {
            "category":"Personal",
            "subcategory":"Beauty Salon",
            "type":"Services"
        }
    ],
    "sg:phone":"+1 773 665 9035",
    "sg:postcode":"60657",
    "sg:province":"IL",
    "sg:tags":[
        "hair"
    ],
    "wof:name":"Head First Hair Studio",
    "wof:placetype":"venue"
},
  "geometry": {"coordinates":[-87.663928,41.939763],"type":"Point"}
}