{
  "type": "Feature",
  "properties": {
    "addr:full":"118 S Clinton St Chicago IL 60661",
    "addr:housenumber":"118",
    "addr:postcode":"60661",
    "addr:street":"S Clinton St",
    "iso:country":"US",
    "sg:address":"118 S Clinton St",
    "sg:city":"Chicago",
    "sg:classifiers":[
        {
            "category":"Restaurant",
            "type":"Food & Drink"
        }
    ],
    "sg:phone":"+1   ",
    "sg:postcode":"60661",
    "sg:province":"IL",
    "sg:tags":[
        "eating"
    ],
    "wof:name":"Bacinos On Clinton Inc",
    "wof:placetype":"venue"
},
  "geometry": {"coordinates":[-87.641189,41.879515],"type":"Point"}
}