{
  "type": "Feature",
  "properties": {
    "iso:country":"US",
    "sg:address":"18 Mulberry Dr",
    "sg:city":"Hawthorn Woods",
    "sg:classifiers":[
        {
            "category":"Wholesale",
            "subcategory":"Machinery & Supplies",
            "type":"Manufacturing & Wholesale Goods"
        }
    ],
    "sg:phone":"+1 847 719 2655",
    "sg:postcode":"60047",
    "sg:province":"IL",
    "sg:tags":[
        "equipment",
        "railroad"
    ],
    "wof:name":"Helm Financial Corp",
    "wof:placetype":"venue"
},
  "geometry": {"coordinates":[-88.076487,42.223634],"type":"Point"}
}