{
  "type": "Feature",
  "properties": {
    "iso:country":"US",
    "sg:address":"8118 S Stony Island Ave",
    "sg:city":"Chicago",
    "sg:classifiers":[
        {
            "category":"Recreation",
            "subcategory":"Fishing",
            "type":"Entertainment"
        }
    ],
    "sg:phone":"+1 773 375 5500",
    "sg:postcode":"60617",
    "sg:province":"IL",
    "sg:tags":[
        "tackle",
        "bait"
    ],
    "wof:name":"Ace Bait Shop",
    "wof:placetype":"venue"
},
  "geometry": {"coordinates":[-87.58586200000001,41.747502],"type":"Point"}
}