{
  "type": "Feature",
  "properties": {
    "iso:country":"US",
    "sg:address":"3424 Constance Dr",
    "sg:city":"Rockford",
    "sg:classifiers":[
        {
            "category":"Insurance",
            "subcategory":"Insurance Agent",
            "type":"Services"
        }
    ],
    "sg:phone":"+1 815 399 0858",
    "sg:postcode":"61108",
    "sg:province":"IL",
    "wof:name":"Frazer Life & Health Agency",
    "wof:placetype":"venue"
},
  "geometry": {"coordinates":[-89.039648,42.240033],"type":"Point"}
}