{
  "type": "Feature",
  "properties": {
    "iso:country":"US",
    "sg:address":"4256 N Ravenswood Ave",
    "sg:city":"Chicago",
    "sg:classifiers":[
        {
            "category":"Personal",
            "subcategory":"Massage",
            "type":"Services"
        },
        {
            "category":"Health Services",
            "subcategory":"Health Practitioner",
            "type":"Services"
        },
        {
            "category":"Health Services",
            "subcategory":"Chiropractor",
            "type":"Services"
        }
    ],
    "sg:phone":"+1 773 904 2588",
    "sg:postcode":"60613",
    "sg:province":"IL",
    "sg:tags":[
        "traditional",
        "medicine",
        "chinese"
    ],
    "sg:website":"chicagochiropractornow.com/",
    "wof:name":"Ravenswood Health Center",
    "wof:placetype":"venue"
},
  "geometry": {"coordinates":[-87.674353,41.959841],"type":"Point"}
}