{
  "type": "Feature",
  "properties": {
    "iso:country":"US",
    "sg:address":"8907 S Prairie Rd",
    "sg:city":"Evansville",
    "sg:classifiers":[
        {
            "category":"Building & Trades",
            "subcategory":"Construction",
            "type":"Services"
        }
    ],
    "sg:phone":"+1 618 282 6052",
    "sg:postcode":"62242",
    "sg:province":"IL",
    "sg:tags":[
        "water",
        "well",
        "drilling"
    ],
    "wof:name":"K Diamond Services",
    "wof:placetype":"venue"
},
  "geometry": {"coordinates":[-89.944779,38.134645],"type":"Point"}
}