{
  "type": "Feature",
  "properties": {
    "iso:country":"US",
    "sg:address":"2639 N Monticello Ave",
    "sg:city":"Chicago",
    "sg:classifiers":[
        {
            "category":"Place Of Worship",
            "subcategory":"Temple",
            "type":"Public Place"
        }
    ],
    "sg:phone":"+1 773 255 6483",
    "sg:postcode":"60647",
    "sg:province":"IL",
    "sg:tags":[
        "buddhist"
    ],
    "sg:website":"logansquarezen.org/",
    "wof:name":"Logan Square Zendo",
    "wof:placetype":"venue"
},
  "geometry": {"coordinates":[-87.71799300000001,41.929411],"type":"Point"}
}