{
  "type": "Feature",
  "properties": {
    "addr:full":"1339 N Wells St Chicago IL 60614",
    "addr:housenumber":"1339",
    "addr:postcode":"60614",
    "addr:street":"N Wells St",
    "iso:country":"US",
    "sg:address":"1339 N Wells St",
    "sg:city":"Chicago",
    "sg:classifiers":[
        {
            "category":"Restaurant",
            "type":"Food & Drink"
        },
        {
            "category":"Bars & Pubs",
            "subcategory":"Nightclub",
            "type":"Food & Drink"
        }
    ],
    "sg:phone":"+1 312 266 6789",
    "sg:postcode":"60614",
    "sg:province":"IL",
    "sg:tags":[
        "nightlife",
        "pizza"
    ],
    "sg:website":"www.otpchicago.com",
    "wof:name":"Old Town Pub",
    "wof:placetype":"venue"
},
  "geometry": {"coordinates":[-87.634141,41.906907],"type":"Point"}
}