{
  "type": "Feature",
  "properties": {
    "iso:country":"US",
    "sg:address":"325 Cottonwood Ln",
    "sg:city":"Naperville",
    "sg:classifiers":[
        {
            "category":"Real Estate",
            "subcategory":"Real Estate Services",
            "type":"Services"
        },
        {
            "category":"Professional",
            "subcategory":"Business Services",
            "type":"Services"
        },
        {
            "category":"Real Estate",
            "subcategory":"Surveying",
            "type":"Services"
        }
    ],
    "sg:phone":"+1 630 420 2720",
    "sg:postcode":"60540",
    "sg:province":"IL",
    "sg:tags":[
        "appraisers-business",
        "industrial",
        "appraisers-commercial",
        "commercial",
        "broker",
        "buyer",
        "appraiser"
    ],
    "wof:name":"Dixon Appraisal",
    "wof:placetype":"venue"
},
  "geometry": {"coordinates":[-88.176311,41.770462],"type":"Point"}
}