{
  "type": "Feature",
  "properties": {
    "addr:full":"4594 Brighton Bunker Hill Rd Brighton IL 62012",
    "addr:housenumber":"4594",
    "addr:postcode":"62012",
    "addr:street":"Brighton Bunker Hill Rd",
    "iso:country":"US",
    "sg:address":"4594 Brighton Bunker Hill Rd",
    "sg:city":"Brighton",
    "sg:classifiers":[
        {
            "category":"Building & Trades",
            "subcategory":"Construction",
            "type":"Services"
        }
    ],
    "sg:phone":"+1 618 372 7062",
    "sg:postcode":"62012",
    "sg:province":"IL",
    "sg:tags":[
        "masonry",
        "contractor"
    ],
    "wof:name":"Tri-County Masonry Inc",
    "wof:placetype":"venue"
},
  "geometry": {"coordinates":[-90.062642,39.049388],"type":"Point"}
}