{
  "type": "Feature",
  "properties": {
    "iso:country":"US",
    "sg:address":"1130 N Lincoln Ave",
    "sg:city":"Park Ridge",
    "sg:classifiers":[
        {
            "category":"Professional",
            "type":"Services"
        }
    ],
    "sg:phone":"+1 847 823 1500",
    "sg:postcode":"60068",
    "sg:province":"IL",
    "sg:tags":[
        "establishment"
    ],
    "wof:name":"Ginco Interprise Inc",
    "wof:placetype":"venue"
},
  "geometry": {"coordinates":[-87.84315700000001,42.028954],"type":"Point"}
}