{
  "type": "Feature",
  "properties": {
    "addr:full":"311 N Union St Dwight IL 60420",
    "addr:housenumber":"311",
    "addr:postcode":"60420",
    "addr:street":"N Union St",
    "iso:country":"US",
    "sg:address":"311 N Union St",
    "sg:city":"Dwight",
    "sg:classifiers":[
        {
            "category":"Restaurant",
            "type":"Food & Drink"
        },
        {
            "category":"Food & Beverages",
            "subcategory":"Groceries & Convenience Stores",
            "type":"Retail Goods"
        }
    ],
    "sg:menulink":"http://www.allmenus.com/il/dwight/226242-caseys-general-store/menu/",
    "sg:phone":"+1 815 584 3000",
    "sg:postcode":"60420",
    "sg:province":"IL",
    "sg:tags":[
        "american",
        "pizza"
    ],
    "wof:name":"Casey's General Store",
    "wof:placetype":"venue"
},
  "geometry": {"coordinates":[-88.42062,41.096581],"type":"Point"}
}