{
  "type": "Feature",
  "properties": {
    "addr:full":"3550 W Peterson Ave Chicago IL 60659",
    "addr:housenumber":"3550",
    "addr:postcode":"60659",
    "addr:street":"W Peterson Ave",
    "iso:country":"US",
    "sg:address":"3550 W Peterson Ave",
    "sg:city":"Chicago",
    "sg:classifiers":[
        {
            "category":"Organizations",
            "subcategory":"Professional Association",
            "type":"Services"
        }
    ],
    "sg:phone":"+1 773 478 6613",
    "sg:postcode":"60659",
    "sg:province":"IL",
    "sg:tags":[
        "home",
        "nursing",
        "for",
        "trade"
    ],
    "wof:name":"Illinois Council On Long Tem",
    "wof:placetype":"venue"
},
  "geometry": {"coordinates":[-87.71851599999999,41.990342],"type":"Point"}
}