{
  "type": "Feature",
  "properties": {
    "iso:country":"US",
    "sg:address":"306 E 2nd St",
    "sg:city":"Gridley",
    "sg:classifiers":[
        {
            "category":"Government",
            "subcategory":"Office",
            "type":"Public Place"
        }
    ],
    "sg:phone":"+1 309 747 2395",
    "sg:postcode":"61744",
    "sg:province":"IL",
    "sg:tags":[
        "village"
    ],
    "wof:name":"Gridley Twp Highway Comm",
    "wof:placetype":"venue"
},
  "geometry": {"coordinates":[-88.877461,40.74128],"type":"Point"}
}