{
  "type": "Feature",
  "properties": {
    "iso:country":"US",
    "sg:address":"734 Union Ave",
    "sg:city":"Romeoville",
    "sg:classifiers":[
        {
            "category":"Professional",
            "subcategory":"Management & Consulting",
            "type":"Services"
        }
    ],
    "sg:phone":"+1 815 886 6115",
    "sg:postcode":"60446",
    "sg:province":"IL",
    "sg:tags":[
        "business"
    ],
    "wof:name":"Blazek Consultants",
    "wof:placetype":"venue"
},
  "geometry": {"coordinates":[-88.10252699999999,41.642091],"type":"Point"}
}