{
  "type": "Feature",
  "properties": {
    "addr:full":"9 Sandhurst Ct Streamwood IL 60107",
    "addr:housenumber":"9",
    "addr:postcode":"60107",
    "addr:street":"Sandhurst Ct",
    "iso:country":"US",
    "sg:address":"9 Sandhurst Ct",
    "sg:city":"Streamwood",
    "sg:classifiers":[
        {
            "category":"Restaurant",
            "type":"Food & Drink"
        }
    ],
    "sg:phone":"+1 630 872 8208",
    "sg:postcode":"60107",
    "sg:province":"IL",
    "wof:name":"Charkies Restaurant",
    "wof:placetype":"venue"
},
  "geometry": {"coordinates":[-88.139274,42.037001],"type":"Point"}
}