{
  "type": "Feature",
  "properties": {
    "iso:country":"US",
    "sg:address":"943 E New York St",
    "sg:city":"Aurora",
    "sg:classifiers":[
        {
            "category":"Professional",
            "subcategory":"Engineering",
            "type":"Services"
        },
        {
            "category":"Building & Trades",
            "subcategory":"Construction",
            "type":"Services"
        }
    ],
    "sg:phone":"+1 630 898 7799",
    "sg:postcode":"60505",
    "sg:province":"IL",
    "sg:tags":[
        "system",
        "specialty",
        "heating",
        "equipment",
        "contractor",
        "air conditioning"
    ],
    "wof:name":"A Aabco Air Conditioning",
    "wof:placetype":"venue"
},
  "geometry": {"coordinates":[-88.29289199999999,41.753639],"type":"Point"}
}