{
  "type": "Feature",
  "properties": {
    "addr:full":"160 W Wendell St Chicago IL 60610",
    "addr:housenumber":"160",
    "addr:postcode":"60610",
    "addr:street":"W Wendell St",
    "iso:country":"US",
    "sg:address":"160 W Wendell St",
    "sg:city":"Chicago",
    "sg:classifiers":[
        {
            "category":"Education",
            "subcategory":"School",
            "type":"Public Place"
        }
    ],
    "sg:phone":"+1 773 534 8310",
    "sg:postcode":"60610",
    "sg:province":"IL",
    "sg:tags":[
        "high",
        "middle",
        "elementary"
    ],
    "wof:name":"Schools Public",
    "wof:placetype":"venue"
},
  "geometry": {"coordinates":[-87.636805,41.901306],"type":"Point"}
}