{
  "type": "Feature",
  "properties": {
    "iso:country":"US",
    "sg:address":"914 N Ironwood Pl",
    "sg:city":"Mount Prospect",
    "sg:classifiers":[
        {
            "category":"Professional",
            "subcategory":"Secretarial Services",
            "type":"Services"
        }
    ],
    "sg:phone":"+1 847 259 0682",
    "sg:postcode":"60056",
    "sg:province":"IL",
    "sg:tags":[
        "reporting"
    ],
    "wof:name":"Ironwood Secretarial",
    "wof:placetype":"venue"
},
  "geometry": {"coordinates":[-87.918251,42.081924],"type":"Point"}
}