{
  "type": "Feature",
  "properties": {
    "iso:country":"US",
    "sg:address":"7743 S Paxton Ave",
    "sg:city":"Chicago",
    "sg:classifiers":[
        {
            "category":"Retail",
            "subcategory":"Laundry & Dry Cleaning",
            "type":"Services"
        },
        {
            "category":"Building & Trades",
            "subcategory":"Cleaning & Sanitation",
            "type":"Services"
        }
    ],
    "sg:phone":"+1 773 374 1786",
    "sg:postcode":"60649",
    "sg:province":"IL",
    "sg:tags":[
        "house",
        "cleaner"
    ],
    "wof:name":"Clean Coat",
    "wof:placetype":"venue"
},
  "geometry": {"coordinates":[-87.571163,41.754511],"type":"Point"}
}