{
  "type": "Feature",
  "properties": {
    "addr:full":"102 S Main St White Hall IL 62092",
    "addr:housenumber":"102",
    "addr:postcode":"62092",
    "addr:street":"S Main St",
    "iso:country":"US",
    "sg:address":"102 S Main St",
    "sg:city":"White Hall",
    "sg:classifiers":[
        {
            "category":"Banks & Credit Unions",
            "subcategory":"Bank",
            "type":"Services"
        }
    ],
    "sg:phone":"+1 217 374 2181",
    "sg:postcode":"62092",
    "sg:province":"IL",
    "wof:name":"White Hall National Bank",
    "wof:placetype":"venue"
},
  "geometry": {"coordinates":[-90.403577,39.436816],"type":"Point"}
}