{
  "type": "Feature",
  "properties": {
    "iso:country":"US",
    "sg:address":"127 Chicago St",
    "sg:city":"West Chicago",
    "sg:classifiers":[
        {
            "category":"Food & Beverages",
            "subcategory":"Dairy",
            "type":"Retail Goods"
        }
    ],
    "sg:phone":"+1   ",
    "sg:postcode":"60185",
    "sg:province":"IL",
    "sg:tags":[
        "product"
    ],
    "wof:name":"Irmas Delight Ice Cream",
    "wof:placetype":"venue"
},
  "geometry": {"coordinates":[-88.20128699999999,41.882639],"type":"Point"}
}