{
  "type": "Feature",
  "properties": {
    "addr:full":"7443 S Cottage Grove Avenue Chicago IL 60619",
    "addr:housenumber":"7443",
    "addr:postcode":"60619",
    "addr:street":"S Cottage Grove Avenue",
    "iso:country":"US",
    "sg:address":"7443 S Cottage Grove Avenue",
    "sg:city":"Chicago",
    "sg:classifiers":[
        {
            "category":"Shopping",
            "subcategory":"Beauty & Cosmetics",
            "type":"Retail Goods"
        }
    ],
    "sg:phone":"+1 773 487 8282",
    "sg:postcode":"60619",
    "sg:province":"IL",
    "sg:tags":[
        "supply"
    ],
    "wof:name":"Q Beauty Supply",
    "wof:placetype":"venue"
},
  "geometry": {"coordinates":[-87.605228,41.759513],"type":"Point"}
}