{
  "type": "Feature",
  "properties": {
    "addr:full":"5934 W Diversey Avenue Chicago IL 60639",
    "addr:housenumber":"5934",
    "addr:postcode":"60639",
    "addr:street":"W Diversey Avenue",
    "iso:country":"US",
    "sg:address":"5934 W Diversey Avenue",
    "sg:city":"Chicago",
    "sg:classifiers":[
        {
            "category":"Social Services",
            "subcategory":"Child Care",
            "type":"Services"
        }
    ],
    "sg:phone":"+1 773 804 1271",
    "sg:postcode":"60639",
    "sg:province":"IL",
    "sg:tags":[
        "day"
    ],
    "wof:name":"Toddler Town Daycare Two",
    "wof:placetype":"venue"
},
  "geometry": {"coordinates":[-87.77489300000001,41.931188],"type":"Point"}
}