{
  "type": "Feature",
  "properties": {
    "addr:full":"1100 Perrysville Ave Georgetown IL 61846",
    "addr:housenumber":"1100",
    "addr:postcode":"61846",
    "addr:street":"Perrysville Ave",
    "iso:country":"US",
    "sg:address":"1100 Perrysville Ave",
    "sg:city":"Georgetown",
    "sg:classifiers":[
        {
            "category":"Organizations",
            "subcategory":"Religious Organization",
            "type":"Services"
        }
    ],
    "sg:phone":"+1 217 662 8110",
    "sg:postcode":"61846",
    "sg:province":"IL",
    "sg:tags":[
        "church"
    ],
    "wof:name":"Jehovah's Witnesses",
    "wof:placetype":"venue"
},
  "geometry": {"coordinates":[-87.62857,39.984529],"type":"Point"}
}