{
  "type": "Feature",
  "properties": {
    "iso:country":"US",
    "sg:address":"8467 W Wilson Ave",
    "sg:city":"Chicago",
    "sg:classifiers":[
        {
            "category":"Restaurant",
            "type":"Food & Drink"
        }
    ],
    "sg:phone":"+1   ",
    "sg:postcode":"60656",
    "sg:province":"IL",
    "sg:tags":[
        "eating"
    ],
    "wof:name":"Midland Snow & Ice Management",
    "wof:placetype":"venue"
},
  "geometry": {"coordinates":[-87.838919,41.963656],"type":"Point"}
}