{
  "type": "Feature",
  "properties": {
    "addr:full":"203 N Michigan Ave Chicago IL 60601",
    "addr:housenumber":"203",
    "addr:postcode":"60601",
    "addr:street":"N Michigan Ave",
    "iso:country":"US",
    "sg:address":"203 N Michigan Ave",
    "sg:city":"Chicago",
    "sg:classifiers":[
        {
            "category":"Retail",
            "subcategory":"Auto Repair",
            "type":"Services"
        }
    ],
    "sg:postcode":"60601",
    "sg:province":"IL",
    "sg:website":"www.paintlessdentrepairillinois.com",
    "wof:name":"Paintless Dent Repair Illinois",
    "wof:placetype":"venue"
},
  "geometry": {"coordinates":[-87.624379,41.885788],"type":"Point"}
}