{
  "type": "Feature",
  "properties": {
    "addr:full":"940 Ripple Brook Ln Elgin IL 60120",
    "addr:housenumber":"940",
    "addr:postcode":"60120",
    "addr:street":"Ripple Brook Ln",
    "iso:country":"US",
    "sg:address":"940 Ripple Brook Ln",
    "sg:city":"Elgin",
    "sg:classifiers":[
        {
            "category":"Insurance",
            "subcategory":"Insurance Agent",
            "type":"Services"
        }
    ],
    "sg:phone":"+1 847 742 7105",
    "sg:postcode":"60120",
    "sg:province":"IL",
    "wof:name":"Thrivent Financial-Lutherans",
    "wof:placetype":"venue"
},
  "geometry": {"coordinates":[-88.252527,42.051321],"type":"Point"}
}