{
  "type": "Feature",
  "properties": {
    "iso:country":"US",
    "sg:address":"4758 S Wood St",
    "sg:city":"Chicago",
    "sg:classifiers":[
        {
            "category":"Food & Beverages",
            "subcategory":"Farmers Market",
            "type":"Retail Goods"
        }
    ],
    "sg:phone":"+1 773 847 6559",
    "sg:postcode":"60609",
    "sg:province":"IL",
    "sg:tags":[
        "vegetable",
        "fruit"
    ],
    "wof:name":"Los Tres Armons",
    "wof:placetype":"venue"
},
  "geometry": {"coordinates":[-87.669809,41.807468],"type":"Point"}
}