{
  "type": "Feature",
  "properties": {
    "addr:full":"260 Schott Dr Essex IL 60935",
    "addr:housenumber":"260",
    "addr:postcode":"60935",
    "addr:street":"Schott Dr",
    "iso:country":"US",
    "sg:address":"260 Schott Dr",
    "sg:city":"Essex",
    "sg:classifiers":[
        {
            "category":"Freight",
            "type":"Transportation"
        }
    ],
    "sg:phone":"+1 815 365 2968",
    "sg:postcode":"60935",
    "sg:province":"IL",
    "sg:tags":[
        "operator",
        "local",
        "trucking"
    ],
    "wof:name":"K J Cartage",
    "wof:placetype":"venue"
},
  "geometry": {"coordinates":[-88.18605599999999,41.186751],"type":"Point"}
}