{
  "type": "Feature",
  "properties": {
    "addr:full":"1900 W Taylor Street Chicago IL 60612",
    "addr:housenumber":"1900",
    "addr:postcode":"60612",
    "addr:street":"W Taylor Street",
    "iso:country":"US",
    "sg:address":"1900 W Taylor Street",
    "sg:city":"Chicago",
    "sg:classifiers":[
        {
            "category":"Education",
            "subcategory":"School",
            "type":"Public Place"
        },
        {
            "category":"Organizations",
            "subcategory":"Religious Organization",
            "type":"Services"
        }
    ],
    "sg:phone":"+1 312 243 8186",
    "sg:postcode":"60612",
    "sg:province":"IL",
    "sg:tags":[
        "high",
        "middle",
        "elementary",
        "k-",
        "private"
    ],
    "sg:website":"http://www.rochesterstjude.com",
    "wof:name":"Children of Peace School",
    "wof:placetype":"venue"
},
  "geometry": {"coordinates":[-87.673709,41.869166],"type":"Point"}
}