{
  "type": "Feature",
  "properties": {
    "addr:full":"2565 W 79th St Chicago IL 60652",
    "addr:housenumber":"2565",
    "addr:postcode":"60652",
    "addr:street":"W 79Th St",
    "iso:country":"US",
    "sg:address":"2565 W 79th St",
    "sg:city":"Chicago",
    "sg:classifiers":[
        {
            "category":"Sports & Exercise",
            "subcategory":"Gym",
            "type":"Entertainment"
        }
    ],
    "sg:phone":"+1 773 434 9500",
    "sg:postcode":"60652",
    "sg:province":"IL",
    "sg:tags":[
        "club",
        "health",
        "studio",
        "gymnasium"
    ],
    "wof:name":"Essential Element Martial Arts",
    "wof:placetype":"venue"
},
  "geometry": {"coordinates":[-87.68819999999999,41.749947],"type":"Point"}
}