{
  "type": "Feature",
  "properties": {
    "addr:full":"600 Industrial Dr Cary IL 60013",
    "addr:housenumber":"600",
    "addr:postcode":"60013",
    "addr:street":"Industrial Dr",
    "iso:country":"US",
    "sg:address":"600 Industrial Dr",
    "sg:city":"Cary",
    "sg:classifiers":[
        {
            "category":"Building & Trades",
            "subcategory":"Landscaping Services",
            "type":"Services"
        }
    ],
    "sg:phone":"+1 847 462 9760",
    "sg:postcode":"60013",
    "sg:province":"IL",
    "sg:tags":[
        "lawn",
        "maintenance",
        "grounds"
    ],
    "wof:name":"Scotts Lawn Svc",
    "wof:placetype":"venue"
},
  "geometry": {"coordinates":[-88.25266499999999,42.213288],"type":"Point"}
}