{
  "type": "Feature",
  "properties": {
    "iso:country":"US",
    "sg:address":"201 W Romeo Rd",
    "sg:city":"Romeoville",
    "sg:classifiers":[
        {
            "category":"Personal",
            "subcategory":"Barber",
            "type":"Services"
        }
    ],
    "sg:phone":"+1 815 886 9816",
    "sg:postcode":"60446",
    "sg:province":"IL",
    "wof:name":"Jodi's Hair FX",
    "wof:placetype":"venue"
},
  "geometry": {"coordinates":[-88.084319,41.639915],"type":"Point"}
}