{
  "type": "Feature",
  "properties": {
    "addr:full":"25 W Iroquois St Freeport IL 61032",
    "addr:housenumber":"25",
    "addr:postcode":"61032",
    "addr:street":"W Iroquois St",
    "iso:country":"US",
    "sg:address":"25 W Iroquois St",
    "sg:city":"Freeport",
    "sg:classifiers":[
        {
            "category":"Shopping",
            "subcategory":"Clothing, Apparel, & Fashions",
            "type":"Retail Goods"
        }
    ],
    "sg:phone":"+1 815 233 3012",
    "sg:postcode":"61032",
    "sg:province":"IL",
    "sg:tags":[
        "tailor"
    ],
    "wof:name":"Fashions 4 Today",
    "wof:placetype":"venue"
},
  "geometry": {"coordinates":[-89.616657,42.294082],"type":"Point"}
}