{
  "type": "Feature",
  "properties": {
    "iso:country":"US",
    "sg:address":"4958 Seminary Rd",
    "sg:city":"Alton",
    "sg:classifiers":[
        {
            "category":"Real Estate",
            "subcategory":"Real Estate Agent",
            "type":"Services"
        }
    ],
    "sg:phone":"+1 618 467 7085",
    "sg:postcode":"62002",
    "sg:province":"IL",
    "sg:tags":[
        "inspection"
    ],
    "wof:name":"River Bend Home Inspection",
    "wof:placetype":"venue"
},
  "geometry": {"coordinates":[-90.142387,38.961193],"type":"Point"}
}