{
  "type": "Feature",
  "properties": {
    "iso:country":"US",
    "sg:address":"87 Axline Rd",
    "sg:city":"Chatham",
    "sg:classifiers":[
        {
            "category":"Wholesale",
            "subcategory":"Machinery & Supplies",
            "type":"Manufacturing & Wholesale Goods"
        }
    ],
    "sg:phone":"+1 217 483 7938",
    "sg:postcode":"62629",
    "sg:province":"IL",
    "sg:tags":[
        "equipment",
        "irrigation",
        "system"
    ],
    "wof:name":"Design Irrigation",
    "wof:placetype":"venue"
},
  "geometry": {"coordinates":[-89.672492,39.670286],"type":"Point"}
}