{
  "type": "Feature",
  "properties": {
    "iso:country":"US",
    "sg:address":"1229 W George St",
    "sg:city":"Chicago",
    "sg:classifiers":[
        {
            "category":"Real Estate",
            "subcategory":"Real Estate Agent",
            "type":"Services"
        }
    ],
    "sg:phone":"+1 773 525 3311",
    "sg:postcode":"60657",
    "sg:province":"IL",
    "wof:name":"City Real Estate Inc",
    "wof:placetype":"venue"
},
  "geometry": {"coordinates":[-87.660062,41.93428],"type":"Point"}
}