{
  "type": "Feature",
  "properties": {
    "iso:country":"US",
    "sg:address":"414 N Orleans St Ste 207",
    "sg:city":"Chicago",
    "sg:classifiers":[
        {
            "category":"Health Services",
            "subcategory":"Chiropractor",
            "type":"Services"
        }
    ],
    "sg:phone":"+1 312 832 9700",
    "sg:postcode":"60654",
    "sg:province":"IL",
    "sg:tags":[
        "chiropractic"
    ],
    "sg:website":"www.eastbankchiropractic.com",
    "wof:name":"East Bank Chiropractic",
    "wof:placetype":"venue"
},
  "geometry": {"coordinates":[-87.636999,41.889347],"type":"Point"}
}