{
  "type": "Feature",
  "properties": {
    "iso:country":"US",
    "sg:address":"3119 W Montrose Ave",
    "sg:city":"Chicago",
    "sg:classifiers":[
        {
            "category":"Shopping",
            "subcategory":"Antiques",
            "type":"Retail Goods"
        }
    ],
    "sg:phone":"+1 773 334 7033",
    "sg:postcode":"60618",
    "sg:province":"IL",
    "sg:website":"richsoldiesandgoodies.com",
    "wof:name":"Rich's Oldies & Goodies",
    "wof:placetype":"venue"
},
  "geometry": {"coordinates":[-87.706529,41.961208],"type":"Point"}
}