{
  "type": "Feature",
  "properties": {
    "iso:country":"US",
    "sg:address":"350 Co Rd Ll",
    "sg:city":"Rock Island",
    "sg:classifiers":[
        {
            "category":"Professional",
            "subcategory":"Computer Services",
            "type":"Services"
        }
    ],
    "sg:phone":"+1 309 283 0290",
    "sg:postcode":"61264",
    "sg:province":"IL",
    "sg:tags":[
        "information",
        "technology"
    ],
    "wof:name":"TDF Corp",
    "wof:placetype":"venue"
},
  "geometry": {"coordinates":[-90.574342,41.392394],"type":"Point"}
}