{
  "type": "Feature",
  "properties": {
    "addr:full":"2110 Forestview Rd Evanston IL 60201",
    "addr:housenumber":"2110",
    "addr:postcode":"60201",
    "addr:street":"Forestview Rd",
    "iso:country":"US",
    "sg:address":"2110 Forestview Rd",
    "sg:city":"Evanston",
    "sg:classifiers":[
        {
            "category":"Home & Garden",
            "subcategory":"Home Furnishings",
            "type":"Retail Goods"
        }
    ],
    "sg:phone":"+1   ",
    "sg:postcode":"60201",
    "sg:province":"IL",
    "wof:name":"Up In Smoke Grills",
    "wof:placetype":"venue"
},
  "geometry": {"coordinates":[-87.714369,42.05633],"type":"Point"}
}