{
  "type": "Feature",
  "properties": {
    "iso:country":"US",
    "sg:address":"17 E Northwest Hwy",
    "sg:city":"Palatine",
    "sg:classifiers":[
        {
            "category":"Personal",
            "type":"Services"
        }
    ],
    "sg:phone":"+1 847 991 6868",
    "sg:postcode":"60067",
    "sg:province":"IL",
    "sg:tags":[
        "electrolysis"
    ],
    "wof:name":"Clinicare II LTD",
    "wof:placetype":"venue"
},
  "geometry": {"coordinates":[-88.043589,42.12105],"type":"Point"}
}