{
  "type": "Feature",
  "properties": {
    "iso:country":"US",
    "sg:address":"305 W Jackson St",
    "sg:city":"Carbondale",
    "sg:classifiers":[
        {
            "category":"Health Services",
            "subcategory":"Doctor",
            "type":"Services"
        }
    ],
    "sg:phone":"+1 618 536 6621",
    "sg:postcode":"62901",
    "sg:province":"IL",
    "sg:tags":[
        "physician",
        "family",
        "gynecology",
        "practice",
        "surgeons",
        "obstetrics",
        "medicine",
        "surgeon",
        "sport",
        "public"
    ],
    "sg:website":"http://www.siumed.edu/cfpc/",
    "wof:name":"Southern Illinois Family Medicine-Carbondale",
    "wof:placetype":"venue"
},
  "geometry": {"coordinates":[-89.217922,37.728117],"type":"Point"}
}