{
  "type": "Feature",
  "properties": {
    "iso:country":"US",
    "sg:address":"606 W Dewitt St",
    "sg:city":"Pana",
    "sg:classifiers":[
        {
            "category":"Farming",
            "subcategory":"Livestock Farm",
            "type":"Manufacturing & Wholesale Goods"
        },
        {
            "category":"Farming",
            "subcategory":"Farm",
            "type":"Manufacturing & Wholesale Goods"
        }
    ],
    "sg:phone":"+1 217 562 5135",
    "sg:postcode":"62557",
    "sg:province":"IL",
    "wof:name":"V Altersberger",
    "wof:placetype":"venue"
},
  "geometry": {"coordinates":[-89.093339,39.395193],"type":"Point"}
}