{
  "type": "Feature",
  "properties": {
    "addr:full":"1648 Wisconsin Ave Beloit IL 53511",
    "addr:housenumber":"1648",
    "addr:postcode":"53511",
    "addr:street":"Wisconsin Ave",
    "iso:country":"US",
    "sg:address":"1648 Wisconsin Ave",
    "sg:city":"Beloit",
    "sg:classifiers":[
        {
            "category":"Organizations",
            "subcategory":"Religious Organization",
            "type":"Services"
        }
    ],
    "sg:phone":"+1 608 362 4665",
    "sg:postcode":"53511",
    "sg:province":"IL",
    "sg:tags":[
        "church"
    ],
    "wof:name":"Pentecostal Church Of God",
    "wof:placetype":"venue"
},
  "geometry": {"coordinates":[-89.024242,42.518994],"type":"Point"}
}