{
  "type": "Feature",
  "properties": {
    "iso:country":"US",
    "sg:address":"404 Gramercy Ct Apt 12",
    "sg:city":"Rockford",
    "sg:classifiers":[
        {
            "category":"Food & Beverages",
            "subcategory":"Groceries & Convenience Stores",
            "type":"Retail Goods"
        }
    ],
    "sg:phone":"+1 815 229 5369",
    "sg:postcode":"61107",
    "sg:province":"IL",
    "wof:name":"Leonidas Mercado",
    "wof:placetype":"venue"
},
  "geometry": {"coordinates":[-89.00376,42.271923],"type":"Point"}
}