{
  "type": "Feature",
  "properties": {
    "iso:country":"US",
    "sg:address":"14 N Broadway",
    "sg:city":"Aurora",
    "sg:classifiers":[
        {
            "category":"Shopping",
            "subcategory":"Clothing, Apparel, & Fashions",
            "type":"Retail Goods"
        }
    ],
    "sg:phone":"+1   ",
    "sg:postcode":"60505",
    "sg:province":"IL",
    "wof:name":"Estrellas Bridal",
    "wof:placetype":"venue"
},
  "geometry": {"coordinates":[-88.31230100000001,41.757853],"type":"Point"}
}