{
  "type": "Feature",
  "properties": {
    "iso:country":"US",
    "sg:address":"1021 Avenue E",
    "sg:city":"Rochelle",
    "sg:classifiers":[
        {
            "category":"Organizations",
            "subcategory":"Membership Organization",
            "type":"Services"
        }
    ],
    "sg:phone":"+1 815 562 1963",
    "sg:postcode":"61068",
    "sg:province":"IL",
    "wof:name":"Rochelle Remote Control Club",
    "wof:placetype":"venue"
},
  "geometry": {"coordinates":[-89.072738,41.91469],"type":"Point"}
}