{
  "type": "Feature",
  "properties": {
    "iso:country":"US",
    "sg:address":"544 W Colfax St",
    "sg:city":"Palatine",
    "sg:classifiers":[
        {
            "category":"Building & Trades",
            "subcategory":"Construction",
            "type":"Services"
        }
    ],
    "sg:phone":"+1 847 359 4000",
    "sg:postcode":"60067",
    "sg:province":"IL",
    "sg:tags":[
        "concrete",
        "contractor"
    ],
    "wof:name":"Zemon Concrete Corporation",
    "wof:placetype":"venue"
},
  "geometry": {"coordinates":[-88.054929,42.116388],"type":"Point"}
}