{
  "type": "Feature",
  "properties": {
    "addr:full":"1669 Oakton Pl Des Plaines IL 60018",
    "addr:housenumber":"1669",
    "addr:postcode":"60018",
    "addr:street":"Oakton Pl",
    "iso:country":"US",
    "sg:address":"1669 Oakton Pl",
    "sg:city":"Des Plaines",
    "sg:classifiers":[
        {
            "category":"Restaurant",
            "type":"Food & Drink"
        }
    ],
    "sg:phone":"+1   ",
    "sg:postcode":"60018",
    "sg:province":"IL",
    "sg:tags":[
        "eating"
    ],
    "wof:name":"Rinconcito Hispano",
    "wof:placetype":"venue"
},
  "geometry": {"coordinates":[-87.897927,42.023531],"type":"Point"}
}