{
  "type": "Feature",
  "properties": {
    "addr:full":"850 Brook Forest Ave Shorewood IL 60431",
    "addr:housenumber":"850",
    "addr:postcode":"60431",
    "addr:street":"Brook Forest Ave",
    "iso:country":"US",
    "sg:address":"850 Brook Forest Ave",
    "sg:city":"Shorewood",
    "sg:classifiers":[
        {
            "category":"Wholesale",
            "subcategory":"Groceries",
            "type":"Manufacturing & Wholesale Goods"
        }
    ],
    "sg:phone":"+1 815 744 9805",
    "sg:postcode":"60431",
    "sg:province":"IL",
    "sg:tags":[
        "baker"
    ],
    "wof:name":"Interstate Brands Corp",
    "wof:placetype":"venue"
},
  "geometry": {"coordinates":[-88.199179,41.537118],"type":"Point"}
}