{
  "type": "Feature",
  "properties": {
    "addr:full":"521 N Milwaukee Ave Libertyville IL 60048",
    "addr:housenumber":"521",
    "addr:postcode":"60048",
    "addr:street":"N Milwaukee Ave",
    "iso:country":"US",
    "sg:address":"521 N Milwaukee Ave",
    "sg:city":"Libertyville",
    "sg:classifiers":[
        {
            "category":"Shopping",
            "subcategory":"Hobbies, Toys, & Games",
            "type":"Retail Goods"
        }
    ],
    "sg:phone":"+1 847 549 6020",
    "sg:postcode":"60048",
    "sg:province":"IL",
    "sg:tags":[
        "basket"
    ],
    "sg:website":"www.someothernuts.com",
    "wof:name":"Some Other Baskets & Nuts",
    "wof:placetype":"venue"
},
  "geometry": {"coordinates":[-87.954466,42.288161],"type":"Point"}
}