{
  "type": "Feature",
  "properties": {
    "iso:country":"US",
    "sg:address":"124 Pitz Ln",
    "sg:city":"Batavia",
    "sg:classifiers":[
        {
            "category":"Wholesale",
            "subcategory":"Non-durable Goods",
            "type":"Manufacturing & Wholesale Goods"
        }
    ],
    "sg:phone":"+1 630 879 0700",
    "sg:postcode":"60510",
    "sg:province":"IL",
    "sg:tags":[
        "advertising"
    ],
    "sg:website":"www.bruceshay.com",
    "wof:name":"Bruce Shay Advertising Inc",
    "wof:placetype":"venue"
},
  "geometry": {"coordinates":[-88.32784,41.847285],"type":"Point"}
}