{
  "type": "Feature",
  "properties": {
    "iso:country":"US",
    "sg:address":"501 Hecker St",
    "sg:city":"Belleville",
    "sg:classifiers":[
        {
            "category":"Utilities",
            "subcategory":"Refuse",
            "type":"Services"
        }
    ],
    "sg:phone":"+1 618 233 2425",
    "sg:postcode":"62221",
    "sg:province":"IL",
    "sg:tags":[
        "recycles",
        "wholesale",
        "scrap",
        "metal",
        "paper",
        "waste",
        "pro"
    ],
    "wof:name":"Belleville Recycling Inc",
    "wof:placetype":"venue"
},
  "geometry": {"coordinates":[-89.970916,38.522203],"type":"Point"}
}