{
  "type": "Feature",
  "properties": {
    "iso:country":"US",
    "sg:address":"1805 State St",
    "sg:city":"East Saint Louis",
    "sg:classifiers":[
        {
            "category":"Food & Beverages",
            "subcategory":"Liquor & Beverages",
            "type":"Retail Goods"
        }
    ],
    "sg:phone":"+1 618 874 4000",
    "sg:postcode":"62205",
    "sg:province":"IL",
    "sg:tags":[
        "beer",
        "spirit",
        "wine"
    ],
    "wof:name":"Regal Package Liquor",
    "wof:placetype":"venue"
},
  "geometry": {"coordinates":[-90.137199,38.6199],"type":"Point"}
}