{
  "type": "Feature",
  "properties": {
    "iso:country":"US",
    "sg:address":"7409 Woodridge Dr",
    "sg:city":"Woodridge",
    "sg:classifiers":[
        {
            "category":"Health Services",
            "subcategory":"Podiatrist",
            "type":"Services"
        }
    ],
    "sg:phone":"+1 630 493 0200",
    "sg:postcode":"60517",
    "sg:province":"IL",
    "wof:name":"South Dupage Foot & Ankle Spec",
    "wof:placetype":"venue"
},
  "geometry": {"coordinates":[-88.05167899999999,41.751315],"type":"Point"}
}