{
  "type": "Feature",
  "properties": {
    "iso:country":"US",
    "sg:address":"1344 N Wells St",
    "sg:city":"Chicago",
    "sg:classifiers":[
        {
            "category":"Wholesale",
            "subcategory":"Stationery",
            "type":"Manufacturing & Wholesale Goods"
        }
    ],
    "sg:phone":"+1 312 475 1344",
    "sg:postcode":"60610",
    "sg:province":"IL",
    "sg:tags":[
        "card"
    ],
    "sg:website":"pulpandink.com",
    "wof:name":"Pulp & Ink",
    "wof:placetype":"venue"
},
  "geometry": {"coordinates":[-87.634399,41.906399],"type":"Point"}
}