{
  "type": "Feature",
  "properties": {
    "iso:country":"US",
    "sg:address":"1033 8th St",
    "sg:city":"La Salle",
    "sg:classifiers":[
        {
            "category":"Shopping",
            "subcategory":"Pharmacy",
            "type":"Retail Goods"
        }
    ],
    "sg:phone":"+1   ",
    "sg:postcode":"61301",
    "sg:province":"IL",
    "sg:tags":[
        "drug"
    ],
    "wof:name":"Arkins",
    "wof:placetype":"venue"
},
  "geometry": {"coordinates":[-89.09153999999999,41.33631],"type":"Point"}
}