{
  "type": "Feature",
  "properties": {
    "addr:full":"1995 S Kensington Ave Kankakee IL 60901",
    "addr:housenumber":"1995",
    "addr:postcode":"60901",
    "addr:street":"S Kensington Ave",
    "iso:country":"US",
    "sg:address":"1995 S Kensington Ave",
    "sg:city":"Kankakee",
    "sg:classifiers":[
        {
            "category":"Wholesale",
            "subcategory":"Hardware",
            "type":"Manufacturing & Wholesale Goods"
        }
    ],
    "sg:phone":"+1 815 933 9474",
    "sg:postcode":"60901",
    "sg:province":"IL",
    "sg:tags":[
        "tool"
    ],
    "wof:name":"Offko Tool Inc",
    "wof:placetype":"venue"
},
  "geometry": {"coordinates":[-87.873396,41.096779],"type":"Point"}
}