{
  "type": "Feature",
  "properties": {
    "iso:country":"US",
    "sg:address":"6842 Garden Ln",
    "sg:city":"Bridgeview",
    "sg:classifiers":[
        {
            "category":"Retail",
            "subcategory":"Auto Repair",
            "type":"Services"
        }
    ],
    "sg:phone":"+1 708 496 1130",
    "sg:postcode":"60455",
    "sg:province":"IL",
    "wof:name":"J D Automotive John S Antiqu",
    "wof:placetype":"venue"
},
  "geometry": {"coordinates":[-87.818388,41.766401],"type":"Point"}
}