{
  "type": "Feature",
  "properties": {
    "addr:full":"401 N Wabash Ave Ste 623 Chicago IL 60611",
    "addr:housenumber":"401",
    "addr:postcode":"60611",
    "addr:street":"N Wabash Ave Ste 623",
    "iso:country":"US",
    "sg:address":"401 N Wabash Ave Ste 623",
    "sg:city":"Chicago",
    "sg:classifiers":[
        {
            "category":"Real Estate",
            "subcategory":"Architect",
            "type":"Services"
        }
    ],
    "sg:phone":"+1 312 644 9850",
    "sg:postcode":"60611",
    "sg:province":"IL",
    "wof:name":"S T L Architects",
    "wof:placetype":"venue"
},
  "geometry": {"coordinates":[-87.626701,41.889301],"type":"Point"}
}