{
  "type": "Feature",
  "properties": {
    "addr:full":"4100 W Grand Ave Chicago IL 60651",
    "addr:housenumber":"4100",
    "addr:postcode":"60651",
    "addr:street":"W Grand Ave",
    "iso:country":"US",
    "sg:address":"4100 W Grand Ave",
    "sg:city":"Chicago",
    "sg:classifiers":[
        {
            "category":"Retail",
            "subcategory":"Auto Repair",
            "type":"Services"
        }
    ],
    "sg:phone":"+1 773 342 9120",
    "sg:postcode":"60651",
    "sg:province":"IL",
    "sg:tags":[
        "automobile",
        "electric"
    ],
    "wof:name":"Technical Auto Electric",
    "wof:placetype":"venue"
},
  "geometry": {"coordinates":[-87.728889,41.90715],"type":"Point"}
}