{
  "type": "Feature",
  "properties": {
    "iso:country":"US",
    "sg:address":"1130 Elgin Ave",
    "sg:city":"Forest Park",
    "sg:classifiers":[
        {
            "category":"Professional",
            "subcategory":"Business Services",
            "type":"Services"
        }
    ],
    "sg:phone":"+1 708 771 0552",
    "sg:postcode":"60130",
    "sg:province":"IL",
    "wof:name":"Mahoney Express Inc",
    "wof:placetype":"venue"
},
  "geometry": {"coordinates":[-87.805376,41.866032],"type":"Point"}
}