{
  "type": "Feature",
  "properties": {
    "addr:full":"39W719 Lori Ln Elgin IL 60124",
    "addr:housenumber":"39w719",
    "addr:postcode":"60124",
    "addr:street":"Lori Ln",
    "iso:country":"US",
    "sg:address":"39W719 Lori Ln",
    "sg:city":"Elgin",
    "sg:classifiers":[
        {
            "category":"Building & Trades",
            "subcategory":"Landscaping Services",
            "type":"Services"
        }
    ],
    "sg:phone":"+1 847 741 0435",
    "sg:postcode":"60124",
    "sg:province":"IL",
    "sg:tags":[
        "tree"
    ],
    "sg:website":"http://www.zipweb.com/?businessName=FowlerTreeSurgeryInc/",
    "wof:name":"Fowler Tree Surgery Inc",
    "wof:placetype":"venue"
},
  "geometry": {"coordinates":[-88.387981,42.008991],"type":"Point"}
}