{
  "type": "Feature",
  "properties": {
    "iso:country":"US",
    "sg:address":"10536 Main St",
    "sg:city":"Roscoe",
    "sg:classifiers":[
        {
            "category":"Personal",
            "subcategory":"Beauty Salon",
            "type":"Services"
        }
    ],
    "sg:phone":"+1   ",
    "sg:postcode":"61073",
    "sg:province":"IL",
    "sg:tags":[
        "shop",
        "clothing"
    ],
    "wof:name":"Marys Shear Artistry Day Spa",
    "wof:placetype":"venue"
},
  "geometry": {"coordinates":[-89.009578,42.413702],"type":"Point"}
}