{
  "type": "Feature",
  "properties": {
    "iso:country":"US",
    "sg:address":"109 Rand Rd",
    "sg:city":"Lakemoor",
    "sg:classifiers":[
        {
            "category":"Real Estate",
            "subcategory":"Real Estate Agent",
            "type":"Services"
        }
    ],
    "sg:phone":"+1 815 385 9958",
    "sg:postcode":"60051",
    "sg:province":"IL",
    "wof:name":"Stedman's Real Estate",
    "wof:placetype":"venue"
},
  "geometry": {"coordinates":[-88.198791,42.328557],"type":"Point"}
}