{
  "type": "Feature",
  "properties": {
    "iso:country":"US",
    "sg:address":"732 N 4th St",
    "sg:city":"Breese",
    "sg:classifiers":[
        {
            "category":"Sports & Exercise",
            "subcategory":"Bowling",
            "type":"Entertainment"
        },
        {
            "category":"Restaurant",
            "type":"Food & Drink"
        }
    ],
    "sg:phone":"+1 618 526 7881",
    "sg:postcode":"62230",
    "sg:province":"IL",
    "sg:tags":[
        "drinking",
        "center"
    ],
    "wof:name":"V & H Recreation",
    "wof:placetype":"venue"
},
  "geometry": {"coordinates":[-89.52542,38.610615],"type":"Point"}
}