{
  "type": "Feature",
  "properties": {
    "iso:country":"US",
    "sg:address":"1316 Van Buren Ave",
    "sg:city":"Des Plaines",
    "sg:classifiers":[
        {
            "category":"Building & Trades",
            "subcategory":"Construction",
            "type":"Services"
        }
    ],
    "sg:phone":"+1 847 390 9663",
    "sg:postcode":"60018",
    "sg:province":"IL",
    "sg:tags":[
        "house"
    ],
    "wof:name":"Bloxsom Construction",
    "wof:placetype":"venue"
},
  "geometry": {"coordinates":[-87.891617,42.030553],"type":"Point"}
}