{
  "type": "Feature",
  "properties": {
    "addr:full":"1475 W Balmoral Ave Chicago IL 60640",
    "addr:housenumber":"1475",
    "addr:postcode":"60640",
    "addr:street":"W Balmoral Ave",
    "iso:country":"US",
    "sg:address":"1475 W Balmoral Ave",
    "sg:city":"Chicago",
    "sg:classifiers":[
        {
            "category":"Restaurant",
            "type":"Food & Drink"
        }
    ],
    "sg:phone":"+1   ",
    "sg:postcode":"60640",
    "sg:province":"IL",
    "sg:tags":[
        "eating"
    ],
    "wof:name":"La Tache",
    "wof:placetype":"venue"
},
  "geometry": {"coordinates":[-87.666162,41.97981],"type":"Point"}
}