{
  "type": "Feature",
  "properties": {
    "addr:full":"512 Mack St Joliet IL 60435",
    "addr:housenumber":"512",
    "addr:postcode":"60435",
    "addr:street":"Mack St",
    "iso:country":"US",
    "sg:address":"512 Mack St",
    "sg:city":"Joliet",
    "sg:classifiers":[
        {
            "category":"Health Services",
            "subcategory":"Optometrist",
            "type":"Services"
        }
    ],
    "sg:phone":"+1 815 727 2093",
    "sg:postcode":"60435",
    "sg:province":"IL",
    "wof:name":"Patricia H Simpson Od",
    "wof:placetype":"venue"
},
  "geometry": {"coordinates":[-88.10834699999999,41.533741],"type":"Point"}
}