{
  "type": "Feature",
  "properties": {
    "addr:full":"3895 E Main St Saint Charles IL 60174",
    "addr:housenumber":"3895",
    "addr:postcode":"60174",
    "addr:street":"E Main St",
    "iso:country":"US",
    "sg:address":"3895 E Main St",
    "sg:city":"Saint Charles",
    "sg:classifiers":[
        {
            "category":"Restaurant",
            "type":"Food & Drink"
        }
    ],
    "sg:menulink":"http://www.allmenus.com/il/st-charles/234415-portillos-hot-dogs/menu/",
    "sg:phone":"+1 630 762 8484",
    "sg:postcode":"60174",
    "sg:province":"IL",
    "sg:tags":[
        "american",
        "hot",
        "dog"
    ],
    "wof:name":"Portillo's Hot Dogs",
    "wof:placetype":"venue"
},
  "geometry": {"coordinates":[-88.263043,41.921154],"type":"Point"}
}