{
  "type": "Feature",
  "properties": {
    "addr:full":"17848 W Oak Ave Lockport IL 60441",
    "addr:housenumber":"17848",
    "addr:postcode":"60441",
    "addr:street":"W Oak Ave",
    "iso:country":"US",
    "sg:address":"17848 W Oak Ave",
    "sg:city":"Lockport",
    "sg:classifiers":[
        {
            "category":"Building & Trades",
            "subcategory":"Construction",
            "type":"Services"
        }
    ],
    "sg:phone":"+1 815 726 4943",
    "sg:postcode":"60441",
    "sg:province":"IL",
    "sg:tags":[
        "house"
    ],
    "wof:name":"Ernest Banks",
    "wof:placetype":"venue"
},
  "geometry": {"coordinates":[-88.050764,41.560824],"type":"Point"}
}