{
  "type": "Feature",
  "properties": {
    "addr:full":"8150 W 111th St Palos Hills IL 60465",
    "addr:housenumber":"8150",
    "addr:postcode":"60465",
    "addr:street":"W 111Th St",
    "iso:country":"US",
    "sg:address":"8150 W 111th St",
    "sg:city":"Palos Hills",
    "sg:classifiers":[
        {
            "category":"Insurance",
            "subcategory":"Insurance Agent",
            "type":"Services"
        }
    ],
    "sg:phone":"+1 708 974 0600",
    "sg:postcode":"60465",
    "sg:province":"IL",
    "wof:name":"Dan Bertolucci Insurance Agcy",
    "wof:placetype":"venue"
},
  "geometry": {"coordinates":[-87.822091,41.689444],"type":"Point"}
}