{
  "type": "Feature",
  "properties": {
    "iso:country":"US",
    "sg:address":"3225 167th St",
    "sg:city":"Hazel Crest",
    "sg:classifiers":[
        {
            "category":"Wholesale",
            "subcategory":"Machinery & Supplies",
            "type":"Manufacturing & Wholesale Goods"
        }
    ],
    "sg:phone":"+1 708 333 9745",
    "sg:postcode":"60429",
    "sg:province":"IL",
    "sg:tags":[
        "dry wall",
        "contractor"
    ],
    "wof:name":"Allied Dry Wall Material Supls",
    "wof:placetype":"venue"
},
  "geometry": {"coordinates":[-87.694665,41.586172],"type":"Point"}
}