{
  "type": "Feature",
  "properties": {
    "iso:country":"US",
    "sg:address":"14205 Chicago Rd",
    "sg:city":"Dolton",
    "sg:classifiers":[
        {
            "category":"Personal",
            "subcategory":"Beauty Salon",
            "type":"Services"
        }
    ],
    "sg:phone":"+1 708 841 6331",
    "sg:postcode":"60419",
    "sg:province":"IL",
    "sg:tags":[
        "hair",
        "stylist"
    ],
    "wof:name":"A New You",
    "wof:placetype":"venue"
},
  "geometry": {"coordinates":[-87.607552,41.63696],"type":"Point"}
}