{
  "type": "Feature",
  "properties": {
    "addr:full":"9911 Lucas Rd Woodstock IL 60098",
    "addr:housenumber":"9911",
    "addr:postcode":"60098",
    "addr:street":"Lucas Rd",
    "iso:country":"US",
    "sg:address":"9911 Lucas Rd",
    "sg:city":"Woodstock",
    "sg:classifiers":[
        {
            "category":"Professional",
            "subcategory":"Printing & Photocopies",
            "type":"Services"
        }
    ],
    "sg:phone":"+1 815 334 9945",
    "sg:postcode":"60098",
    "sg:province":"IL",
    "sg:tags":[
        "consultant"
    ],
    "sg:website":"http://www.jamesarmstrongassoc.com",
    "wof:name":"James Armstrong & Associates",
    "wof:placetype":"venue"
},
  "geometry": {"coordinates":[-88.38832600000001,42.2575],"type":"Point"}
}