{
  "type": "Feature",
  "properties": {
    "addr:full":"214 Palmyra Rd Dixon IL 61021",
    "addr:housenumber":"214",
    "addr:postcode":"61021",
    "addr:street":"Palmyra Rd",
    "iso:country":"US",
    "sg:address":"214 Palmyra Rd",
    "sg:city":"Dixon",
    "sg:classifiers":[
        {
            "category":"Government",
            "subcategory":"Office",
            "type":"Public Place"
        }
    ],
    "sg:phone":"+1   ",
    "sg:postcode":"61021",
    "sg:province":"IL",
    "sg:tags":[
        "transportation"
    ],
    "wof:name":"Road Dept",
    "wof:placetype":"venue"
},
  "geometry": {"coordinates":[-89.586084,41.850312],"type":"Point"}
}