{
  "type": "Feature",
  "properties": {
    "addr:full":"946 S Wesley Ave Oak Park IL 60304",
    "addr:housenumber":"946",
    "addr:postcode":"60304",
    "addr:street":"S Wesley Ave",
    "iso:country":"US",
    "sg:address":"946 S Wesley Ave",
    "sg:city":"Oak Park",
    "sg:classifiers":[
        {
            "category":"Professional",
            "subcategory":"Lawyer & Legal Services",
            "type":"Services"
        }
    ],
    "sg:phone":"+1 708 524 2353",
    "sg:postcode":"60304",
    "sg:province":"IL",
    "wof:name":"Gradel Joyce Ford PC",
    "wof:placetype":"venue"
},
  "geometry": {"coordinates":[-87.791427,41.870792],"type":"Point"}
}