{
  "type": "Feature",
  "properties": {
    "addr:full":"1110 W Golf Rd Libertyville IL 60048",
    "addr:housenumber":"1110",
    "addr:postcode":"60048",
    "addr:street":"W Golf Rd",
    "iso:country":"US",
    "sg:address":"1110 W Golf Rd",
    "sg:city":"Libertyville",
    "sg:classifiers":[
        {
            "category":"Health Services",
            "subcategory":"Doctor",
            "type":"Services"
        }
    ],
    "sg:phone":"+1 847 689 2805",
    "sg:postcode":"60048",
    "sg:province":"IL",
    "sg:tags":[
        "physician",
        "surgeon"
    ],
    "wof:name":"Timothy O Ts'o MD",
    "wof:placetype":"venue"
},
  "geometry": {"coordinates":[-87.971306,42.270987],"type":"Point"}
}