{
  "type": "Feature",
  "properties": {
    "iso:country":"US",
    "sg:address":"100 N Bokelman St",
    "sg:city":"Roselle",
    "sg:classifiers":[
        {
            "category":"Real Estate",
            "subcategory":"Real Estate Services",
            "type":"Services"
        },
        {
            "category":"Real Estate",
            "subcategory":"Real Estate Agent",
            "type":"Services"
        }
    ],
    "sg:phone":"+1 630 539 7076",
    "sg:postcode":"60172",
    "sg:province":"IL",
    "sg:tags":[
        "buyer",
        "broker"
    ],
    "wof:name":"Avian Realty",
    "wof:placetype":"venue"
},
  "geometry": {"coordinates":[-88.078827,41.98447],"type":"Point"}
}