{
  "type": "Feature",
  "properties": {
    "iso:country":"US",
    "sg:address":"1045 W State St",
    "sg:city":"Rockford",
    "sg:classifiers":[
        {
            "category":"Social Services",
            "type":"Services"
        }
    ],
    "sg:phone":"+1 815 963 2575",
    "sg:postcode":"61102",
    "sg:province":"IL",
    "sg:tags":[
        "youth",
        "organization",
        "center"
    ],
    "wof:name":"Let's Talk It Out",
    "wof:placetype":"venue"
},
  "geometry": {"coordinates":[-89.104016,42.275161],"type":"Point"}
}