{
  "type": "Feature",
  "properties": {
    "addr:full":"3101 W Harmon Hwy Ste B Peoria IL 61604",
    "addr:housenumber":"3101",
    "addr:postcode":"61604",
    "addr:street":"W Harmon Hwy Ste B",
    "iso:country":"US",
    "sg:address":"3101 W Harmon Hwy Ste B",
    "sg:city":"Peoria",
    "sg:classifiers":[
        {
            "category":"Professional",
            "subcategory":"Lawyer & Legal Services",
            "type":"Services"
        }
    ],
    "sg:phone":"+1 309 745 9391",
    "sg:postcode":"61604",
    "sg:province":"IL",
    "sg:tags":[
        "attorney",
        "practice"
    ],
    "wof:name":"Randall M Jacobs",
    "wof:placetype":"venue"
},
  "geometry": {"coordinates":[-89.642189,40.681469],"type":"Point"}
}