{
  "type": "Feature",
  "properties": {
    "iso:country":"US",
    "sg:address":"1850 N Western Ave",
    "sg:city":"Chicago",
    "sg:classifiers":[
        {
            "category":"Retail",
            "subcategory":"Car Wash",
            "type":"Services"
        },
        {
            "category":"Retail",
            "subcategory":"Auto Repair",
            "type":"Services"
        }
    ],
    "sg:phone":"+1 773 362 1222",
    "sg:postcode":"60647",
    "sg:province":"IL",
    "sg:tags":[
        "detailing"
    ],
    "sg:website":"www.chicagohandcarwash.com",
    "wof:name":"Plateau Auto Hand Wash And Detailing",
    "wof:placetype":"venue"
},
  "geometry": {"coordinates":[-87.687703,41.915433],"type":"Point"}
}