{
  "type": "Feature",
  "properties": {
    "iso:country":"US",
    "sg:address":"149 E Jackson St",
    "sg:city":"Virden",
    "sg:classifiers":[
        {
            "category":"Personal",
            "subcategory":"Tanning Parlor",
            "type":"Services"
        }
    ],
    "sg:phone":"+1 217 965 3888",
    "sg:postcode":"62690",
    "sg:province":"IL",
    "sg:tags":[
        "salon"
    ],
    "wof:name":"Hot Spot",
    "wof:placetype":"venue"
},
  "geometry": {"coordinates":[-89.767019,39.501672],"type":"Point"}
}