{
  "type": "Feature",
  "properties": {
    "addr:full":"425 S Main St Ste 101 Lombard IL 60148",
    "addr:housenumber":"425",
    "addr:postcode":"60148",
    "addr:street":"S Main St Ste 101",
    "iso:country":"US",
    "sg:address":"425 S Main St Ste 101",
    "sg:city":"Lombard",
    "sg:classifiers":[
        {
            "category":"Structure",
            "subcategory":"Office Building",
            "type":"Public Place"
        }
    ],
    "sg:phone":"+1 630 705 1700",
    "sg:postcode":"60148",
    "sg:province":"IL",
    "sg:tags":[
        "park"
    ],
    "wof:name":"K2 Properties",
    "wof:placetype":"venue"
},
  "geometry": {"coordinates":[-88.018214,41.879512],"type":"Point"}
}