{
  "type": "Feature",
  "properties": {
    "addr:full":"1001 Cambridge Dr Elk Grove Village IL 60007",
    "addr:housenumber":"1001",
    "addr:postcode":"60007",
    "addr:street":"Cambridge Dr",
    "iso:country":"US",
    "sg:address":"1001 Cambridge Dr",
    "sg:city":"Elk Grove Village",
    "sg:classifiers":[
        {
            "category":"Manufacturing",
            "subcategory":"Tools & Machinery",
            "type":"Manufacturing & Wholesale Goods"
        }
    ],
    "sg:phone":"+1 847 391 9400",
    "sg:postcode":"60007",
    "sg:province":"IL",
    "sg:tags":[
        "manufacture",
        "front",
        "develops",
        "system",
        "advanced"
    ],
    "wof:name":"Isco International Inc",
    "wof:placetype":"venue"
},
  "geometry": {"coordinates":[-87.957779,42.013208],"type":"Point"}
}