{
  "type": "Feature",
  "properties": {
    "addr:full":"1516 N Naper Blvd Naperville IL 60563",
    "addr:housenumber":"1516",
    "addr:postcode":"60563",
    "addr:street":"N Naper Blvd",
    "iso:country":"US",
    "sg:address":"1516 N Naper Blvd",
    "sg:city":"Naperville",
    "sg:classifiers":[
        {
            "category":"Restaurant",
            "type":"Food & Drink"
        }
    ],
    "sg:menulink":"http://www.allmenus.com/il/lisle/75496-tgi-fridays/menu/",
    "sg:phone":"+1 630 505 9076",
    "sg:postcode":"60563",
    "sg:province":"IL",
    "sg:tags":[
        "american"
    ],
    "wof:name":"T.G.I. Friday's",
    "wof:placetype":"venue"
},
  "geometry": {"coordinates":[-88.119663,41.797956],"type":"Point"}
}