{
  "type": "Feature",
  "properties": {
    "iso:country":"US",
    "sg:address":"276 N Co Rd 425 E",
    "sg:city":"Arthur",
    "sg:classifiers":[
        {
            "category":"Freight",
            "type":"Transportation"
        }
    ],
    "sg:phone":"+1 217 543 2963",
    "sg:postcode":"61911",
    "sg:province":"IL",
    "sg:tags":[
        "local",
        "trucking"
    ],
    "wof:name":"Rolling H Lines",
    "wof:placetype":"venue"
},
  "geometry": {"coordinates":[-88.390381,39.694132],"type":"Point"}
}