{
  "type": "Feature",
  "properties": {
    "addr:full":"222 N Aberdeen St Chicago IL 60607",
    "addr:housenumber":"222",
    "addr:postcode":"60607",
    "addr:street":"N Aberdeen St",
    "iso:country":"US",
    "sg:address":"222 N Aberdeen St",
    "sg:city":"Chicago",
    "sg:classifiers":[
        {
            "category":"Wholesale",
            "subcategory":"Non-durable Goods",
            "type":"Manufacturing & Wholesale Goods"
        }
    ],
    "sg:phone":"+1 708 224 5483",
    "sg:postcode":"60607",
    "sg:province":"IL",
    "sg:tags":[
        "merchandise-wholesale"
    ],
    "wof:name":"Knightowl Trading",
    "wof:placetype":"venue"
},
  "geometry": {"coordinates":[-87.65447899999999,41.88585],"type":"Point"}
}