{
  "type": "Feature",
  "properties": {
    "addr:full":"8231 S South Shore Dr Chicago IL 60617",
    "addr:housenumber":"8231",
    "addr:postcode":"60617",
    "addr:street":"S South Shore Dr",
    "iso:country":"US",
    "sg:address":"8231 S South Shore Dr",
    "sg:city":"Chicago",
    "sg:classifiers":[
        {
            "category":"Education",
            "subcategory":"School",
            "type":"Public Place"
        }
    ],
    "sg:phone":"+1 773 768 1453",
    "sg:postcode":"60617",
    "sg:province":"IL",
    "wof:name":"St Michael's School",
    "wof:placetype":"venue"
},
  "geometry": {"coordinates":[-87.547743,41.74596],"type":"Point"}
}