{
  "type": "Feature",
  "properties": {
    "addr:full":"5700 W Fullerton Ave Chicago IL 60639",
    "addr:housenumber":"5700",
    "addr:postcode":"60639",
    "addr:street":"W Fullerton Ave",
    "iso:country":"US",
    "sg:address":"5700 W Fullerton Ave",
    "sg:city":"Chicago",
    "sg:classifiers":[
        {
            "category":"Health Services",
            "subcategory":"Doctor",
            "type":"Services"
        },
        {
            "category":"Health Services",
            "subcategory":"Chiropractor",
            "type":"Services"
        }
    ],
    "sg:phone":"+1 773 237 3159",
    "sg:postcode":"60639",
    "sg:province":"IL",
    "wof:name":"Cicero Gerard J DC",
    "wof:placetype":"venue"
},
  "geometry": {"coordinates":[-87.768501,41.924],"type":"Point"}
}