{
  "type": "Feature",
  "properties": {
    "addr:full":"529 E 71st Street Chicago IL 60619",
    "addr:housenumber":"529",
    "addr:postcode":"60619",
    "addr:street":"E 71St Street",
    "iso:country":"US",
    "sg:address":"529 E 71st Street",
    "sg:city":"Chicago",
    "sg:classifiers":[
        {
            "category":"Personal",
            "subcategory":"Barber",
            "type":"Services"
        }
    ],
    "sg:phone":"+1 773 783 3233",
    "sg:postcode":"60619",
    "sg:province":"IL",
    "wof:name":"Got You Faded",
    "wof:placetype":"venue"
},
  "geometry": {"coordinates":[-87.611823,41.765751],"type":"Point"}
}