{
  "type": "Feature",
  "properties": {
    "addr:full":"134 S Locust St Centralia IL 62801",
    "addr:housenumber":"134",
    "addr:postcode":"62801",
    "addr:street":"S Locust St",
    "iso:country":"US",
    "sg:address":"134 S Locust St",
    "sg:city":"Centralia",
    "sg:classifiers":[
        {
            "category":"Professional",
            "subcategory":"Lawyer & Legal Services",
            "type":"Services"
        }
    ],
    "sg:phone":"+1 618 532 4400",
    "sg:postcode":"62801",
    "sg:province":"IL",
    "sg:tags":[
        "attorney"
    ],
    "wof:name":"Daniels Law Office",
    "wof:placetype":"venue"
},
  "geometry": {"coordinates":[-89.134462,38.52723],"type":"Point"}
}