{
  "type": "Feature",
  "properties": {
    "iso:country":"US",
    "sg:address":"220 N Sangamon Ave",
    "sg:city":"Gibson City",
    "sg:classifiers":[
        {
            "category":"Shopping",
            "subcategory":"Pharmacy",
            "type":"Retail Goods"
        }
    ],
    "sg:phone":"+1 217 784 8241",
    "sg:postcode":"60936",
    "sg:province":"IL",
    "wof:name":"Scott's Pharmacy",
    "wof:placetype":"venue"
},
  "geometry": {"coordinates":[-88.375274,40.466999],"type":"Point"}
}