{
  "type": "Feature",
  "properties": {
    "addr:full":"3254 Sanders Rd Northbrook IL 60062",
    "addr:housenumber":"3254",
    "addr:postcode":"60062",
    "addr:street":"Sanders Rd",
    "iso:country":"US",
    "sg:address":"3254 Sanders Rd",
    "sg:city":"Northbrook",
    "sg:classifiers":[
        {
            "category":"Building & Trades",
            "subcategory":"Plumbing",
            "type":"Services"
        }
    ],
    "sg:phone":"+1 847 297 8747",
    "sg:postcode":"60062",
    "sg:province":"IL",
    "sg:tags":[
        "contractor"
    ],
    "wof:name":"Tff Heating & Cooling Company",
    "wof:placetype":"venue"
},
  "geometry": {"coordinates":[-87.87358999999999,42.091516],"type":"Point"}
}