{
  "type": "Feature",
  "properties": {
    "addr:full":"1755 Park St Naperville IL 60563",
    "addr:housenumber":"1755",
    "addr:postcode":"60563",
    "addr:street":"Park St",
    "iso:country":"US",
    "sg:address":"1755 Park St",
    "sg:city":"Naperville",
    "sg:classifiers":[
        {
            "category":"Real Estate",
            "subcategory":"Real Estate Services",
            "type":"Services"
        },
        {
            "category":"Real Estate",
            "subcategory":"Real Estate Agent",
            "type":"Services"
        }
    ],
    "sg:phone":"+1 630 428 2775",
    "sg:postcode":"60563",
    "sg:province":"IL",
    "sg:tags":[
        "buyer",
        "broker"
    ],
    "wof:name":"Charles Rutenberge Realty",
    "wof:placetype":"venue"
},
  "geometry": {"coordinates":[-88.148939,41.801628],"type":"Point"}
}