{
  "type": "Feature",
  "properties": {
    "iso:country":"US",
    "sg:address":"6359 W Grand Ave",
    "sg:city":"Chicago",
    "sg:classifiers":[
        {
            "category":"Autos & Motor Vehicles",
            "subcategory":"Fuel & Gas Station",
            "type":"Retail Goods"
        },
        {
            "category":"Retail",
            "subcategory":"Auto Repair",
            "type":"Services"
        }
    ],
    "sg:phone":"+1 773 237 2500",
    "sg:postcode":"60639",
    "sg:province":"IL",
    "wof:name":"Cyto Two Inc",
    "wof:placetype":"venue"
},
  "geometry": {"coordinates":[-87.785004,41.922298],"type":"Point"}
}