{
  "type": "Feature",
  "properties": {
    "iso:country":"US",
    "sg:address":"300 N 10th St",
    "sg:city":"Fulton",
    "sg:classifiers":[
        {
            "category":"Building & Trades",
            "subcategory":"Landscaping Services",
            "type":"Services"
        }
    ],
    "sg:phone":"+1 815 589 4997",
    "sg:postcode":"61252",
    "sg:province":"IL",
    "sg:tags":[
        "lawn",
        "care"
    ],
    "wof:name":"Cut Rite Lawn Care",
    "wof:placetype":"venue"
},
  "geometry": {"coordinates":[-90.157667,41.876274],"type":"Point"}
}