{
  "type": "Feature",
  "properties": {
    "iso:country":"US",
    "sg:address":"454 S Ohio St",
    "sg:city":"Aurora",
    "sg:classifiers":[
        {
            "category":"Building & Trades",
            "subcategory":"Landscaping Services",
            "type":"Services"
        }
    ],
    "sg:phone":"+1 630 898 7757",
    "sg:postcode":"60505",
    "sg:province":"IL",
    "sg:tags":[
        "lawn",
        "maintenance",
        "grounds"
    ],
    "wof:name":"Automated Lawn Builders",
    "wof:placetype":"venue"
},
  "geometry": {"coordinates":[-88.291028,41.747233],"type":"Point"}
}