{
  "type": "Feature",
  "properties": {
    "iso:country":"US",
    "sg:address":"600 W Cermak Rd",
    "sg:city":"Chicago",
    "sg:classifiers":[
        {
            "category":"Building & Trades",
            "subcategory":"Construction",
            "type":"Services"
        }
    ],
    "sg:phone":"+1 312 492 6233",
    "sg:postcode":"60616",
    "sg:province":"IL",
    "sg:tags":[
        "interior",
        "design",
        "contractor"
    ],
    "wof:name":"Tonka Group",
    "wof:placetype":"venue"
},
  "geometry": {"coordinates":[-87.64166400000001,41.852714],"type":"Point"}
}