{
  "type": "Feature",
  "properties": {
    "iso:country":"US",
    "sg:address":"2350 Bernice Rd",
    "sg:city":"Lansing",
    "sg:classifiers":[
        {
            "category":"Social Services",
            "subcategory":"Child Care",
            "type":"Services"
        }
    ],
    "sg:phone":"+1 708 418 9999",
    "sg:postcode":"60438",
    "sg:province":"IL",
    "sg:tags":[
        "day"
    ],
    "wof:name":"Academy For Children",
    "wof:placetype":"venue"
},
  "geometry": {"coordinates":[-87.563202,41.579102],"type":"Point"}
}