{
  "type": "Feature",
  "properties": {
    "addr:full":"14701 Pulaski Rd Midlothian IL 60445",
    "addr:housenumber":"14701",
    "addr:postcode":"60445",
    "addr:street":"Pulaski Rd",
    "iso:country":"US",
    "sg:address":"14701 Pulaski Rd",
    "sg:city":"Midlothian",
    "sg:classifiers":[
        {
            "category":"Shopping",
            "subcategory":"Pharmacy",
            "type":"Retail Goods"
        }
    ],
    "sg:phone":"+1 708 239 2150",
    "sg:postcode":"60445",
    "sg:province":"IL",
    "sg:tags":[
        "drugstore"
    ],
    "sg:website":"www.cvs.com",
    "wof:name":"Cvs Pharmacy",
    "wof:placetype":"venue"
},
  "geometry": {"coordinates":[-87.717444,41.625456],"type":"Point"}
}