{
  "type": "Feature",
  "properties": {
    "addr:full":"623 26th Ave Rock Island IL 61201",
    "addr:housenumber":"623",
    "addr:postcode":"61201",
    "addr:street":"26Th Ave",
    "iso:country":"US",
    "sg:address":"623 26th Ave",
    "sg:city":"Rock Island",
    "sg:classifiers":[
        {
            "category":"Professional",
            "subcategory":"Engineering",
            "type":"Services"
        }
    ],
    "sg:phone":"+1 309 788 0673",
    "sg:postcode":"61201",
    "sg:province":"IL",
    "sg:tags":[
        "engineer"
    ],
    "sg:website":"www.kjww.com",
    "wof:name":"KJWW Engineering Cnsltnts",
    "wof:placetype":"venue"
},
  "geometry": {"coordinates":[-90.590056,41.485175],"type":"Point"}
}