{
  "type": "Feature",
  "properties": {
    "iso:country":"US",
    "sg:address":"400 N Commercial St",
    "sg:city":"Lacon",
    "sg:classifiers":[
        {
            "category":"Retail",
            "subcategory":"Repair Shop",
            "type":"Services"
        }
    ],
    "sg:phone":"+1 309 246 8456",
    "sg:postcode":"61537",
    "sg:province":"IL",
    "sg:tags":[
        "steel",
        "packaging",
        "fabrication",
        "generator"
    ],
    "wof:name":"Hardin Industries Inc",
    "wof:placetype":"venue"
},
  "geometry": {"coordinates":[-89.36922,41.109311],"type":"Point"}
}