{
  "type": "Feature",
  "properties": {
    "iso:country":"US",
    "sg:address":"6914 N Olcott Ave",
    "sg:city":"Chicago",
    "sg:classifiers":[
        {
            "category":"Professional",
            "subcategory":"Engineering",
            "type":"Services"
        }
    ],
    "sg:phone":"+1 773 774 9899",
    "sg:postcode":"60631",
    "sg:province":"IL",
    "sg:tags":[
        "system",
        "equipment",
        "air conditioning"
    ],
    "wof:name":"Custom Environmental Inc",
    "wof:placetype":"venue"
},
  "geometry": {"coordinates":[-87.81366300000001,42.006349],"type":"Point"}
}