{
  "type": "Feature",
  "properties": {
    "addr:full":"122 Town Center Rd # 103 Matteson IL 60443",
    "addr:housenumber":"122",
    "addr:postcode":"60443",
    "addr:street":"Town Center Rd # 103",
    "iso:country":"US",
    "sg:address":"122 Town Center Rd # 103",
    "sg:city":"Matteson",
    "sg:classifiers":[
        {
            "category":"Deli",
            "type":"Food & Drink"
        },
        {
            "category":"Restaurant",
            "type":"Food & Drink"
        },
        {
            "category":"Food & Beverages",
            "subcategory":"Groceries & Convenience Stores",
            "type":"Retail Goods"
        }
    ],
    "sg:phone":"+1 708 747 7371",
    "sg:postcode":"60443",
    "sg:province":"IL",
    "sg:tags":[
        "shop",
        "delicatessen",
        "sandwich"
    ],
    "wof:name":"Subway Office",
    "wof:placetype":"venue"
},
  "geometry": {"coordinates":[-87.73625800000001,41.50446],"type":"Point"}
}