{
  "type": "Feature",
  "properties": {
    "iso:country":"US",
    "sg:address":"239 E Riverside Blvd",
    "sg:city":"Loves Park",
    "sg:classifiers":[
        {
            "category":"Retail",
            "subcategory":"Repair Shop",
            "type":"Services"
        }
    ],
    "sg:phone":"+1 815 639 9183",
    "sg:postcode":"61111",
    "sg:province":"IL",
    "wof:name":"Frana Vehicles",
    "wof:placetype":"venue"
},
  "geometry": {"coordinates":[-89.064134,42.315982],"type":"Point"}
}