{
  "type": "Feature",
  "properties": {
    "addr:full":"6804 W 111th St Worth IL 60482",
    "addr:housenumber":"6804",
    "addr:postcode":"60482",
    "addr:street":"W 111Th St",
    "iso:country":"US",
    "sg:address":"6804 W 111th St",
    "sg:city":"Worth",
    "sg:classifiers":[
        {
            "category":"Personal",
            "subcategory":"Tattoo Parlor",
            "type":"Services"
        }
    ],
    "sg:phone":"+1 708 361 3763",
    "sg:postcode":"60482",
    "sg:province":"IL",
    "wof:name":"New Tribe Tatto",
    "wof:placetype":"venue"
},
  "geometry": {"coordinates":[-87.78864400000001,41.690365],"type":"Point"}
}