{
  "type": "Feature",
  "properties": {
    "addr:full":"4750 S Washtenaw Ave Chicago IL 60632",
    "addr:housenumber":"4750",
    "addr:postcode":"60632",
    "addr:street":"S Washtenaw Ave",
    "iso:country":"US",
    "sg:address":"4750 S Washtenaw Ave",
    "sg:city":"Chicago",
    "sg:classifiers":[
        {
            "category":"Bakery",
            "type":"Food & Drink"
        }
    ],
    "sg:phone":"+1 773 523 5675",
    "sg:postcode":"60632",
    "sg:province":"IL",
    "wof:name":"Tom Tom Tamale & Bakery Company",
    "wof:placetype":"venue"
},
  "geometry": {"coordinates":[-87.69173499999999,41.806735],"type":"Point"}
}