{
  "type": "Feature",
  "properties": {
    "iso:country":"US",
    "sg:address":"2326 W Pinnacle Dr",
    "sg:city":"Dunlap",
    "sg:classifiers":[
        {
            "category":"Shopping",
            "subcategory":"Crafts & Fabrics",
            "type":"Retail Goods"
        }
    ],
    "sg:phone":"+1   ",
    "sg:postcode":"61525",
    "sg:province":"IL",
    "sg:tags":[
        "sewing"
    ],
    "wof:name":"Mickeys Knitting Post",
    "wof:placetype":"venue"
},
  "geometry": {"coordinates":[-89.62869999999999,40.833843],"type":"Point"}
}