{
  "type": "Feature",
  "properties": {
    "addr:full":"3143 W 95th St Evergreen Park IL 60805",
    "addr:housenumber":"3143",
    "addr:postcode":"60805",
    "addr:street":"W 95Th St",
    "iso:country":"US",
    "sg:address":"3143 W 95th St",
    "sg:city":"Evergreen Park",
    "sg:classifiers":[
        {
            "category":"Wholesale",
            "subcategory":"Groceries",
            "type":"Manufacturing & Wholesale Goods"
        }
    ],
    "sg:phone":"+1 708 425 3813",
    "sg:postcode":"60805",
    "sg:province":"IL",
    "sg:tags":[
        "bakery",
        "retail"
    ],
    "wof:name":"Lady Dis Bakery",
    "wof:placetype":"venue"
},
  "geometry": {"coordinates":[-87.701714,41.720658],"type":"Point"}
}