{
  "type": "Feature",
  "properties": {
    "addr:full":"1000 S Cedar Rd New Lenox IL 60451",
    "addr:housenumber":"1000",
    "addr:postcode":"60451",
    "addr:street":"S Cedar Rd",
    "iso:country":"US",
    "sg:address":"1000 S Cedar Rd",
    "sg:city":"New Lenox",
    "sg:classifiers":[
        {
            "category":"Building & Trades",
            "subcategory":"Construction",
            "type":"Services"
        }
    ],
    "sg:phone":"+1 815 485 2564",
    "sg:postcode":"60451",
    "sg:province":"IL",
    "sg:tags":[
        "maker",
        "cabinet"
    ],
    "sg:website":"www.tristarcabinets.com",
    "wof:name":"Tri-Star Cabinet Top Co",
    "wof:placetype":"venue"
},
  "geometry": {"coordinates":[-87.965271,41.4976],"type":"Point"}
}