{
  "type": "Feature",
  "properties": {
    "addr:full":"2000 Lehigh Ave Glenview IL 60026",
    "addr:housenumber":"2000",
    "addr:postcode":"60026",
    "addr:street":"Lehigh Ave",
    "iso:country":"US",
    "sg:address":"2000 Lehigh Ave",
    "sg:city":"Glenview",
    "sg:classifiers":[
        {
            "category":"Building & Trades",
            "subcategory":"Construction",
            "type":"Services"
        }
    ],
    "sg:phone":"+1 847 724 4146",
    "sg:postcode":"60026",
    "sg:province":"IL",
    "sg:tags":[
        "contractor",
        "paving",
        "asphalt",
        "sealcoating"
    ],
    "sg:website":"http://www.finneganpaving.net",
    "wof:name":"Finnegan Paving Inc",
    "wof:placetype":"venue"
},
  "geometry": {"coordinates":[-87.812155,42.088243],"type":"Point"}
}