{
  "type": "Feature",
  "properties": {
    "addr:full":"312 Warren St Calumet City IL 60409",
    "addr:housenumber":"312",
    "addr:postcode":"60409",
    "addr:street":"Warren St",
    "iso:country":"US",
    "sg:address":"312 Warren St",
    "sg:city":"Calumet City",
    "sg:classifiers":[
        {
            "category":"Organizations",
            "subcategory":"Community Association",
            "type":"Services"
        }
    ],
    "sg:phone":"+1 708 730 1883",
    "sg:postcode":"60409",
    "sg:province":"IL",
    "wof:name":"American Legion Aux 792 W",
    "wof:placetype":"venue"
},
  "geometry": {"coordinates":[-87.534481,41.608633],"type":"Point"}
}