{
  "type": "Feature",
  "properties": {
    "iso:country":"US",
    "sg:address":"1907 Oceola Dr",
    "sg:city":"Algonquin",
    "sg:classifiers":[
        {
            "category":"Arts & Performance",
            "subcategory":"Arts Center",
            "type":"Entertainment"
        },
        {
            "category":"Manufacturing",
            "subcategory":"Textiles",
            "type":"Manufacturing & Wholesale Goods"
        },
        {
            "category":"Building & Trades",
            "subcategory":"Construction",
            "type":"Services"
        }
    ],
    "sg:phone":"+1 847 658 5562",
    "sg:postcode":"60102",
    "sg:province":"IL",
    "sg:tags":[
        "wallcoverings-installation",
        "decorating",
        "wallpaper",
        "painting",
        "hand"
    ],
    "sg:website":"http://ralphspainting.net",
    "wof:name":"Ralph's Painting Service, Inc.",
    "wof:placetype":"venue"
},
  "geometry": {"coordinates":[-88.29158700000001,42.153856],"type":"Point"}
}