{
  "type": "Feature",
  "properties": {
    "iso:country":"US",
    "sg:address":"6697 Revere Ct",
    "sg:city":"Gurnee",
    "sg:classifiers":[
        {
            "category":"Home & Garden",
            "subcategory":"Home Furnishings",
            "type":"Retail Goods"
        }
    ],
    "sg:phone":"+1 847 855 7480",
    "sg:postcode":"60031",
    "sg:province":"IL",
    "sg:tags":[
        "draperies",
        "window",
        "treatment",
        "curtain",
        "drapery",
        "trimming"
    ],
    "wof:name":"Decor Eight",
    "wof:placetype":"venue"
},
  "geometry": {"coordinates":[-87.969476,42.374044],"type":"Point"}
}