{
  "type": "Feature",
  "properties": {
    "iso:country":"US",
    "sg:address":"850 Tollgate Rd",
    "sg:city":"Elgin",
    "sg:classifiers":[
        {
            "category":"Building & Trades",
            "subcategory":"Construction",
            "type":"Services"
        }
    ],
    "sg:phone":"+1 847 888 3500",
    "sg:postcode":"60123",
    "sg:province":"IL",
    "sg:tags":[
        "steel",
        "erectors"
    ],
    "wof:name":"Regal Steel Erectors LLC",
    "wof:placetype":"venue"
},
  "geometry": {"coordinates":[-88.300263,42.070835],"type":"Point"}
}