{
  "type": "Feature",
  "properties": {
    "iso:country":"US",
    "sg:address":"2130 Vadalabene Dr",
    "sg:city":"Maryville",
    "sg:classifiers":[
        {
            "category":"Health Services",
            "subcategory":"Hospital",
            "type":"Services"
        }
    ],
    "sg:phone":"+1 618 288 0703",
    "sg:postcode":"62062",
    "sg:province":"IL",
    "sg:tags":[
        "dialysis"
    ],
    "sg:website":"http://www.davita.com",
    "wof:name":"Maryville Dialysis",
    "wof:placetype":"venue"
},
  "geometry": {"coordinates":[-89.951226,38.733481],"type":"Point"}
}