{
  "type": "Feature",
  "properties": {
    "addr:full":"604 E Daniel St Champaign IL 61820",
    "addr:housenumber":"604",
    "addr:postcode":"61820",
    "addr:street":"E Daniel St",
    "iso:country":"US",
    "sg:address":"604 E Daniel St",
    "sg:city":"Champaign",
    "sg:classifiers":[
        {
            "category":"Restaurant",
            "type":"Food & Drink"
        }
    ],
    "sg:phone":"+1 217 344 7483",
    "sg:postcode":"61820",
    "sg:province":"IL",
    "sg:tags":[
        "thai",
        "chinese"
    ],
    "sg:website":"www.homeofgourmet.com/",
    "wof:name":"Home of Gourmet Chinese & Thai Restaurant",
    "wof:placetype":"venue"
},
  "geometry": {"coordinates":[-88.230003,40.107899],"type":"Point"}
}