{
  "type": "Feature",
  "properties": {
    "iso:country":"US",
    "sg:address":"3270 N Lake Shore Drive",
    "sg:city":"Chicago",
    "sg:classifiers":[
        {
            "category":"Real Estate",
            "subcategory":"Real Estate Operator",
            "type":"Services"
        }
    ],
    "sg:phone":"+1 773 525 3260",
    "sg:postcode":"60657",
    "sg:province":"IL",
    "sg:tags":[
        "apartment"
    ],
    "wof:name":"3260 70 N Lake Shore Drive Bldg",
    "wof:placetype":"venue"
},
  "geometry": {"coordinates":[-87.639797,41.941911],"type":"Point"}
}