{
  "type": "Feature",
  "properties": {
    "iso:country":"US",
    "sg:address":"13697 Best Rd",
    "sg:city":"Davis",
    "sg:classifiers":[
        {
            "category":"Banks & Credit Unions",
            "subcategory":"Bank",
            "type":"Services"
        }
    ],
    "sg:phone":"+1 815 248 2711",
    "sg:postcode":"61019",
    "sg:province":"IL",
    "wof:name":"Durand State Bank Inc",
    "wof:placetype":"venue"
},
  "geometry": {"coordinates":[-89.38111,42.454685],"type":"Point"}
}