{
  "type": "Feature",
  "properties": {
    "iso:country":"US",
    "sg:address":"34 E Hinsdale Ave",
    "sg:city":"Hinsdale",
    "sg:classifiers":[
        {
            "category":"Personal",
            "subcategory":"Beauty Salon",
            "type":"Services"
        }
    ],
    "sg:phone":"+1 630 323 0353",
    "sg:postcode":"60521",
    "sg:province":"IL",
    "wof:name":"James Sherman Salon",
    "wof:placetype":"venue"
},
  "geometry": {"coordinates":[-87.928786,41.8026],"type":"Point"}
}