{
  "type": "Feature",
  "properties": {
    "addr:full":"416 S Ridgeland Ave Oak Park IL 60302",
    "addr:housenumber":"416",
    "addr:postcode":"60302",
    "addr:street":"S Ridgeland Ave",
    "iso:country":"US",
    "sg:address":"416 S Ridgeland Ave",
    "sg:city":"Oak Park",
    "sg:classifiers":[
        {
            "category":"Education",
            "subcategory":"School",
            "type":"Public Place"
        }
    ],
    "sg:phone":"+1 708 524 3040",
    "sg:postcode":"60302",
    "sg:province":"IL",
    "wof:name":"Julian Junior High School",
    "wof:placetype":"venue"
},
  "geometry": {"coordinates":[-87.784425,41.881461],"type":"Point"}
}