{
  "type": "Feature",
  "properties": {
    "iso:country":"US",
    "sg:address":"20017 N Isaacson Dr",
    "sg:city":"Chillicothe",
    "sg:classifiers":[
        {
            "category":"Building & Trades",
            "subcategory":"Plumbing",
            "type":"Services"
        }
    ],
    "sg:phone":"+1 309 274 3991",
    "sg:postcode":"61523",
    "sg:province":"IL",
    "sg:tags":[
        "plumbing",
        "electrical",
        "contractor"
    ],
    "wof:name":"Frank's Electric",
    "wof:placetype":"venue"
},
  "geometry": {"coordinates":[-89.58968900000001,40.930318],"type":"Point"}
}