{
  "type": "Feature",
  "properties": {
    "addr:full":"4120 Avenue Of The Cities Moline IL 61265",
    "addr:housenumber":"4120",
    "addr:postcode":"61265",
    "addr:street":"Avenue Of The",
    "iso:country":"US",
    "sg:address":"4120 Avenue Of The Cities",
    "sg:city":"Moline",
    "sg:classifiers":[
        {
            "category":"Fast Food",
            "type":"Food & Drink"
        },
        {
            "category":"Restaurant",
            "type":"Food & Drink"
        }
    ],
    "sg:phone":"+1 563 322 3220",
    "sg:postcode":"61265",
    "sg:province":"IL",
    "sg:tags":[
        "mexican"
    ],
    "sg:website":"http://www.tacobell.com",
    "wof:name":"Taco Bell",
    "wof:placetype":"venue"
},
  "geometry": {"coordinates":[-90.47978500000001,41.490141],"type":"Point"}
}