{
  "type": "Feature",
  "properties": {
    "iso:country":"US",
    "sg:address":"2825 N Center St",
    "sg:city":"Maryville",
    "sg:phone":"+1 618 288 1730",
    "sg:postcode":"62062",
    "sg:province":"IL",
    "sg:website":"http://www.rehabmassage.com",
    "wof:name":"Rehabilitative Massage & Bodywork",
    "wof:placetype":"venue"
},
  "geometry": {"coordinates":[-89.956735,38.732523],"type":"Point"}
}