{
  "type": "Feature",
  "properties": {
    "addr:full":"8360 Field Crest Ave Willow Springs IL 60480",
    "addr:housenumber":"8360",
    "addr:postcode":"60480",
    "addr:street":"Field Crest Ave",
    "iso:country":"US",
    "sg:address":"8360 Field Crest Ave",
    "sg:city":"Willow Springs",
    "sg:classifiers":[
        {
            "category":"Professional",
            "type":"Services"
        }
    ],
    "sg:phone":"+1 708 839 0889",
    "sg:postcode":"60480",
    "sg:province":"IL",
    "wof:name":"Sortino Sortino",
    "wof:placetype":"venue"
},
  "geometry": {"coordinates":[-87.898183,41.736709],"type":"Point"}
}