{
  "type": "Feature",
  "properties": {
    "iso:country":"US",
    "sg:address":"620 E 4th St",
    "sg:city":"Gibson City",
    "sg:classifiers":[
        {
            "category":"Farming",
            "subcategory":"Farm & Veterinary Services",
            "type":"Manufacturing & Wholesale Goods"
        }
    ],
    "sg:phone":"+1 217 784 8416",
    "sg:postcode":"60936",
    "sg:province":"IL",
    "sg:tags":[
        "crop",
        "harvesting"
    ],
    "wof:name":"S Wurmnest",
    "wof:placetype":"venue"
},
  "geometry": {"coordinates":[-88.367181,40.46016],"type":"Point"}
}