{
  "type": "Feature",
  "properties": {
    "iso:country":"US",
    "sg:address":"631 E Boughton Rd Ste 130",
    "sg:city":"Bolingbrook",
    "sg:classifiers":[
        {
            "category":"Shopping",
            "subcategory":"Clothing, Apparel, & Fashions",
            "type":"Retail Goods"
        }
    ],
    "sg:phone":"+1 630 739 5672",
    "sg:postcode":"60440",
    "sg:province":"IL",
    "sg:tags":[
        "apparel",
        "accessory",
        "clothing",
        "store",
        "women's"
    ],
    "sg:website":"http://www.forever21.com",
    "wof:name":"Forever 21",
    "wof:placetype":"venue"
},
  "geometry": {"coordinates":[-88.044769,41.720242],"type":"Point"}
}