{
  "type": "Feature",
  "properties": {
    "iso:country":"US",
    "sg:address":"916 Kenilworth Ave",
    "sg:city":"Glen Ellyn",
    "sg:classifiers":[
        {
            "category":"Professional",
            "subcategory":"Business Services",
            "type":"Services"
        }
    ],
    "sg:phone":"+1 630 469 7140",
    "sg:postcode":"60137",
    "sg:province":"IL",
    "wof:name":"Phone Works",
    "wof:placetype":"venue"
},
  "geometry": {"coordinates":[-88.078492,41.894457],"type":"Point"}
}