{
  "type": "Feature",
  "properties": {
    "addr:full":"7501 W Cermak Rd Chicago IL 60623",
    "addr:housenumber":"7501",
    "addr:postcode":"60623",
    "addr:street":"W Cermak Rd",
    "iso:country":"US",
    "sg:address":"7501 W Cermak Rd",
    "sg:city":"Chicago",
    "sg:classifiers":[
        {
            "category":"Restaurant",
            "type":"Food & Drink"
        }
    ],
    "sg:phone":"+1 708 447 5442",
    "sg:postcode":"60623",
    "sg:province":"IL",
    "sg:tags":[
        "mexican"
    ],
    "wof:name":"Taqueria El Milagro",
    "wof:placetype":"venue"
},
  "geometry": {"coordinates":[-87.73890900000001,41.85132],"type":"Point"}
}