{
  "type": "Feature",
  "properties": {
    "iso:country":"US",
    "sg:address":"222 Alton Sq",
    "sg:city":"Alton",
    "sg:classifiers":[
        {
            "category":"Food & Beverages",
            "subcategory":"Specialty",
            "type":"Retail Goods"
        }
    ],
    "sg:phone":"+1 618 462 8145",
    "sg:postcode":"62002",
    "sg:province":"IL",
    "sg:tags":[
        "vitamin"
    ],
    "wof:name":"Vitamin World",
    "wof:placetype":"venue"
},
  "geometry": {"coordinates":[-90.17571100000001,38.926878],"type":"Point"}
}