{
  "type": "Feature",
  "properties": {
    "iso:country":"US",
    "sg:address":"3109 W 63rd St",
    "sg:city":"Chicago",
    "sg:classifiers":[
        {
            "category":"Shopping",
            "subcategory":"Clothing, Apparel, & Fashions",
            "type":"Retail Goods"
        }
    ],
    "sg:phone":"+1 773 931 5040",
    "sg:postcode":"60629",
    "sg:province":"IL",
    "sg:tags":[
        "clothing",
        "glove",
        "store"
    ],
    "wof:name":"Urban Legendz Fashion",
    "wof:placetype":"venue"
},
  "geometry": {"coordinates":[-87.701036,41.778994],"type":"Point"}
}