{
  "type": "Feature",
  "properties": {
    "iso:country":"US",
    "sg:address":"410 E Clover St",
    "sg:city":"Hutsonville",
    "sg:classifiers":[
        {
            "category":"Autos & Motor Vehicles",
            "subcategory":"Fuel & Gas Station",
            "type":"Retail Goods"
        },
        {
            "category":"Utilities",
            "subcategory":"Fuel Oil & Lpg",
            "type":"Services"
        },
        {
            "category":"Food & Beverages",
            "subcategory":"Groceries & Convenience Stores",
            "type":"Retail Goods"
        }
    ],
    "sg:phone":"+1 618 563 4450",
    "sg:postcode":"62433",
    "sg:province":"IL",
    "sg:tags":[
        "bulk",
        "petroleum-bottled",
        "gas-liquefied"
    ],
    "wof:name":"Jambaa, Inc.",
    "wof:placetype":"venue"
},
  "geometry": {"coordinates":[-87.657445,39.109154],"type":"Point"}
}