{
  "type": "Feature",
  "properties": {
    "iso:country":"US",
    "sg:address":"2100 Manchester Rd",
    "sg:city":"Wheaton",
    "sg:classifiers":[
        {
            "category":"Personal",
            "subcategory":"Massage",
            "type":"Services"
        }
    ],
    "sg:phone":"+1 630 863 4712",
    "sg:postcode":"60187",
    "sg:province":"IL",
    "sg:website":"www.essentialhm.com",
    "wof:name":"Essential Healing & Massage",
    "wof:placetype":"venue"
},
  "geometry": {"coordinates":[-88.134719,41.865696],"type":"Point"}
}