{
  "type": "Feature",
  "properties": {
    "iso:country":"US",
    "sg:address":"3840 W 78th St",
    "sg:city":"Chicago",
    "sg:classifiers":[
        {
            "category":"Shopping",
            "subcategory":"Computers & Home Electronics",
            "type":"Retail Goods"
        }
    ],
    "sg:phone":"+1 773 735 1141",
    "sg:postcode":"60652",
    "sg:province":"IL",
    "sg:tags":[
        "equipment",
        "satellite",
        "system"
    ],
    "wof:name":"American Satellite",
    "wof:placetype":"venue"
},
  "geometry": {"coordinates":[-87.71963,41.751472],"type":"Point"}
}