{
  "type": "Feature",
  "properties": {
    "iso:country":"US",
    "sg:address":"250 N Cone St",
    "sg:city":"Farmington",
    "sg:classifiers":[
        {
            "category":"Personal",
            "subcategory":"Beauty Salon",
            "type":"Services"
        }
    ],
    "sg:phone":"+1 309 647 2545",
    "sg:postcode":"61531",
    "sg:province":"IL",
    "sg:tags":[
        "shop"
    ],
    "wof:name":"Fantastic Sams",
    "wof:placetype":"venue"
},
  "geometry": {"coordinates":[-90.00318900000001,40.702876],"type":"Point"}
}