{
  "type": "Feature",
  "properties": {
    "addr:full":"4709 N Damen Ave Chicago IL 60625",
    "addr:housenumber":"4709",
    "addr:postcode":"60625",
    "addr:street":"N Damen Ave",
    "iso:country":"US",
    "sg:address":"4709 N Damen Ave",
    "sg:city":"Chicago",
    "sg:classifiers":[
        {
            "category":"Banks & Credit Unions",
            "subcategory":"Bank",
            "type":"Services"
        }
    ],
    "sg:phone":"+1 773 334 0576",
    "sg:postcode":"60625",
    "sg:province":"IL",
    "wof:name":"Midwest Bank Card",
    "wof:placetype":"venue"
},
  "geometry": {"coordinates":[-87.679148,41.967194],"type":"Point"}
}