{
  "type": "Feature",
  "properties": {
    "iso:country":"US",
    "sg:address":"404 Strong Ave",
    "sg:city":"Joliet",
    "sg:classifiers":[
        {
            "category":"Wholesale",
            "subcategory":"Electrical",
            "type":"Manufacturing & Wholesale Goods"
        }
    ],
    "sg:phone":"+1 815 723 4175",
    "sg:postcode":"60433",
    "sg:province":"IL",
    "sg:tags":[
        "cell",
        "phone",
        "electronics",
        "computer"
    ],
    "wof:name":"Neal International Pdts Inc",
    "wof:placetype":"venue"
},
  "geometry": {"coordinates":[-88.06814,41.514404],"type":"Point"}
}