{
  "type": "Feature",
  "properties": {
    "iso:country":"US",
    "sg:address":"8400 Springfield Ave",
    "sg:city":"Skokie",
    "sg:classifiers":[
        {
            "category":"Manufacturing",
            "subcategory":"Electronics",
            "type":"Manufacturing & Wholesale Goods"
        }
    ],
    "sg:phone":"+1 847 679 2696",
    "sg:postcode":"60076",
    "sg:province":"IL",
    "sg:tags":[
        "electronic",
        "component",
        "mfg"
    ],
    "wof:name":"Bradley-Rogers Corp",
    "wof:placetype":"venue"
},
  "geometry": {"coordinates":[-87.725554,42.033992],"type":"Point"}
}