{
  "type": "Feature",
  "properties": {
    "addr:full":"1112 N Eastern Ave Urbana IL 61802",
    "addr:housenumber":"1112",
    "addr:postcode":"61802",
    "addr:street":"N Eastern Ave",
    "iso:country":"US",
    "sg:address":"1112 N Eastern Ave",
    "sg:city":"Urbana",
    "sg:classifiers":[
        {
            "category":"Freight",
            "type":"Transportation"
        }
    ],
    "sg:phone":"+1 217 328 5126",
    "sg:postcode":"61802",
    "sg:province":"IL",
    "sg:tags":[
        "operator",
        "local",
        "trucking"
    ],
    "wof:name":"Tims Trucking Inc",
    "wof:placetype":"venue"
},
  "geometry": {"coordinates":[-88.192268,40.126463],"type":"Point"}
}