{
  "type": "Feature",
  "properties": {
    "iso:country":"US",
    "sg:address":"101 Barberis Ln",
    "sg:city":"Collinsville",
    "sg:classifiers":[
        {
            "category":"Building & Trades",
            "subcategory":"Construction",
            "type":"Services"
        },
        {
            "category":"Building & Trades",
            "subcategory":"Electrical",
            "type":"Services"
        }
    ],
    "sg:phone":"+1 618 345 0269",
    "sg:postcode":"62234",
    "sg:province":"IL",
    "sg:tags":[
        "electrician",
        "contractor"
    ],
    "wof:name":"Barberis Electrical Co",
    "wof:placetype":"venue"
},
  "geometry": {"coordinates":[-89.963303,38.676201],"type":"Point"}
}