{
  "type": "Feature",
  "properties": {
    "iso:country":"US",
    "sg:address":"3743 Highland Ave",
    "sg:city":"Downers Grove",
    "sg:classifiers":[
        {
            "category":"Travel",
            "subcategory":"Hotels & Motels",
            "type":"Entertainment"
        }
    ],
    "sg:phone":"+1 630 435 6200",
    "sg:postcode":"60515",
    "sg:province":"IL",
    "wof:name":"Dupage Specialty Suites",
    "wof:placetype":"venue"
},
  "geometry": {"coordinates":[-88.010136,41.81826],"type":"Point"}
}