{
  "type": "Feature",
  "properties": {
    "iso:country":"US",
    "sg:address":"103 S Morrison Ave",
    "sg:city":"Collinsville",
    "sg:classifiers":[
        {
            "category":"Professional",
            "subcategory":"Lawyer & Legal Services",
            "type":"Services"
        }
    ],
    "sg:phone":"+1 618 345 9258",
    "sg:postcode":"62234",
    "sg:province":"IL",
    "sg:tags":[
        "attorney"
    ],
    "wof:name":"Armstrong Law Offices",
    "wof:placetype":"venue"
},
  "geometry": {"coordinates":[-89.984609,38.669868],"type":"Point"}
}