{
  "type": "Feature",
  "properties": {
    "iso:country":"US",
    "sg:address":"107 W Commercial Dr Ste A",
    "sg:city":"Carterville",
    "sg:classifiers":[
        {
            "category":"Real Estate",
            "subcategory":"Real Estate Services",
            "type":"Services"
        },
        {
            "category":"Banks & Credit Unions",
            "subcategory":"Bank",
            "type":"Services"
        },
        {
            "category":"Banks & Credit Unions",
            "subcategory":"Financial Services",
            "type":"Services"
        }
    ],
    "sg:phone":"+1 618 985 2166",
    "sg:postcode":"62918",
    "sg:province":"IL",
    "sg:tags":[
        "loan",
        "broker",
        "mortgage"
    ],
    "sg:website":"http://www.mams.net",
    "wof:name":"Mid America Mortgage Services of Illinois Inc",
    "wof:placetype":"venue"
},
  "geometry": {"coordinates":[-89.077499,37.744701],"type":"Point"}
}