{
  "type": "Feature",
  "properties": {
    "addr:full":"1629 S Hamilton St Lockport IL 60441",
    "addr:housenumber":"1629",
    "addr:postcode":"60441",
    "addr:street":"S Hamilton St",
    "iso:country":"US",
    "sg:address":"1629 S Hamilton St",
    "sg:city":"Lockport",
    "sg:classifiers":[
        {
            "category":"Manufacturing",
            "subcategory":"Retail Goods",
            "type":"Manufacturing & Wholesale Goods"
        }
    ],
    "sg:phone":"+1 815 834 0988",
    "sg:postcode":"60441",
    "sg:province":"IL",
    "sg:tags":[
        "manufacturer"
    ],
    "wof:name":"MBQ Systems Inc",
    "wof:placetype":"venue"
},
  "geometry": {"coordinates":[-88.05994099999999,41.580961],"type":"Point"}
}