{
  "type": "Feature",
  "properties": {
    "iso:country":"US",
    "sg:address":"6458 N Sacramento Ave",
    "sg:city":"Chicago",
    "sg:classifiers":[
        {
            "category":"Transit Center",
            "subcategory":"Freight",
            "type":"Transportation"
        }
    ],
    "sg:phone":"+1 773 564 9239",
    "sg:postcode":"60645",
    "sg:province":"IL",
    "sg:tags":[
        "forwarding",
        "container"
    ],
    "wof:name":"Inc National Freight Lines",
    "wof:placetype":"venue"
},
  "geometry": {"coordinates":[-87.70453000000001,41.99856],"type":"Point"}
}