{
  "type": "Feature",
  "properties": {
    "iso:country":"US",
    "sg:address":"3160 S Wells Street",
    "sg:city":"Chicago",
    "sg:classifiers":[
        {
            "category":"Food & Beverages",
            "subcategory":"Specialty",
            "type":"Retail Goods"
        },
        {
            "category":"Bakery",
            "type":"Food & Drink"
        }
    ],
    "sg:phone":"+1 312 842 7670",
    "sg:postcode":"60616",
    "sg:province":"IL",
    "wof:name":"Biscotti's Galore and More",
    "wof:placetype":"venue"
},
  "geometry": {"coordinates":[-87.63287200000001,41.837094],"type":"Point"}
}