{
  "type": "Feature",
  "properties": {
    "addr:full":"427 S State St Belvidere IL 61008",
    "addr:housenumber":"427",
    "addr:postcode":"61008",
    "addr:street":"S State St",
    "iso:country":"US",
    "sg:address":"427 S State St",
    "sg:city":"Belvidere",
    "sg:classifiers":[
        {
            "category":"Banks & Credit Unions",
            "subcategory":"Bank",
            "type":"Services"
        }
    ],
    "sg:phone":"+1 815 547 4933",
    "sg:postcode":"61008",
    "sg:province":"IL",
    "sg:tags":[
        "alternative",
        "loan",
        "business",
        "institution"
    ],
    "sg:website":"http://www.cashstore.com/IL/Trademark/yp.com",
    "wof:name":"Cash Store",
    "wof:placetype":"venue"
},
  "geometry": {"coordinates":[-88.84020700000001,42.256315],"type":"Point"}
}