{
  "type": "Feature",
  "properties": {
    "iso:country":"US",
    "sg:address":"4746 S Ashland Ave",
    "sg:city":"Chicago",
    "sg:classifiers":[
        {
            "category":"Shopping",
            "subcategory":"Clothing, Apparel, & Fashions",
            "type":"Retail Goods"
        }
    ],
    "sg:phone":"+1 773 847 7703",
    "sg:postcode":"60609",
    "sg:province":"IL",
    "sg:tags":[
        "work",
        "uniform",
        "clothing",
        "store",
        "clothes"
    ],
    "wof:name":"J Bees Sports & Casual Wear",
    "wof:placetype":"venue"
},
  "geometry": {"coordinates":[-87.664948,41.807759],"type":"Point"}
}