{
  "type": "Feature",
  "properties": {
    "addr:full":"14 Litchfield Plz Ste 2 Litchfield IL 62056",
    "addr:housenumber":"14",
    "addr:postcode":"62056",
    "addr:street":"Litchfield Plz Ste 2",
    "iso:country":"US",
    "sg:address":"14 Litchfield Plz Ste 2",
    "sg:city":"Litchfield",
    "sg:classifiers":[
        {
            "category":"Shopping",
            "subcategory":"Gifts & Souvenirs",
            "type":"Retail Goods"
        }
    ],
    "sg:phone":"+1 217 324 2311",
    "sg:postcode":"62056",
    "sg:province":"IL",
    "sg:tags":[
        "shop"
    ],
    "sg:website":"http://www.kirlins.com",
    "wof:name":"Kirlin's Hallmark",
    "wof:placetype":"venue"
},
  "geometry": {"coordinates":[-89.668655,39.17916],"type":"Point"}
}