{
  "type": "Feature",
  "properties": {
    "iso:country":"US",
    "sg:address":"5218 East Dr",
    "sg:city":"Loves Park",
    "sg:classifiers":[
        {
            "category":"Building & Trades",
            "subcategory":"Construction",
            "type":"Services"
        }
    ],
    "sg:phone":"+1 815 243 1999",
    "sg:postcode":"61111",
    "sg:province":"IL",
    "sg:tags":[
        "roofing",
        "contractor"
    ],
    "wof:name":"C J Whiteford Roofing",
    "wof:placetype":"venue"
},
  "geometry": {"coordinates":[-89.065904,42.305483],"type":"Point"}
}