{
  "type": "Feature",
  "properties": {
    "addr:full":"122 W Center St Girard IL 62640",
    "addr:housenumber":"122",
    "addr:postcode":"62640",
    "addr:street":"W Center St",
    "iso:country":"US",
    "sg:address":"122 W Center St",
    "sg:city":"Girard",
    "sg:classifiers":[
        {
            "category":"Restaurant",
            "type":"Food & Drink"
        }
    ],
    "sg:phone":"+1 217 627 2613",
    "sg:postcode":"62640",
    "sg:province":"IL",
    "sg:tags":[
        "bar"
    ],
    "wof:name":"Grub-N-Pub",
    "wof:placetype":"venue"
},
  "geometry": {"coordinates":[-89.77897,39.446442],"type":"Point"}
}