{
  "type": "Feature",
  "properties": {
    "addr:full":"1226A S Roselle Rd Schaumburg IL 60193",
    "addr:housenumber":"1226a",
    "addr:postcode":"60193",
    "addr:street":"S Roselle Rd",
    "iso:country":"US",
    "sg:address":"1226A S Roselle Rd",
    "sg:city":"Schaumburg",
    "sg:classifiers":[
        {
            "category":"Insurance",
            "subcategory":"Insurance Agent",
            "type":"Services"
        },
        {
            "category":"Insurance",
            "subcategory":"Hazard Insurance",
            "type":"Services"
        },
        {
            "category":"Insurance",
            "subcategory":"Title Insurance",
            "type":"Services"
        },
        {
            "category":"Insurance",
            "subcategory":"Life Insurance",
            "type":"Services"
        }
    ],
    "sg:phone":"+1 847 882 5500",
    "sg:postcode":"60193",
    "sg:province":"IL",
    "sg:tags":[
        "business",
        "auto",
        "commercial",
        "homeowner",
        "motorcycle",
        "renter"
    ],
    "wof:name":"Allstate Insurance Company - Lou Stavroplus",
    "wof:placetype":"venue"
},
  "geometry": {"coordinates":[-88.080091,42.004053],"type":"Point"}
}