{
  "type": "Feature",
  "properties": {
    "iso:country":"US",
    "sg:address":"1655 Tall Grass Ln",
    "sg:city":"Lake Forest",
    "sg:classifiers":[
        {
            "category":"Building & Trades",
            "subcategory":"Construction",
            "type":"Services"
        }
    ],
    "sg:phone":"+1 847 295 6062",
    "sg:postcode":"60045",
    "sg:province":"IL",
    "sg:tags":[
        "house"
    ],
    "wof:name":"Peters Masonry Inc",
    "wof:placetype":"venue"
},
  "geometry": {"coordinates":[-87.887385,42.222814],"type":"Point"}
}