{
  "type": "Feature",
  "properties": {
    "addr:full":"4712 N Sheridan Rd Chicago IL 60640",
    "addr:housenumber":"4712",
    "addr:postcode":"60640",
    "addr:street":"N Sheridan Rd",
    "iso:country":"US",
    "sg:address":"4712 N Sheridan Rd",
    "sg:city":"Chicago",
    "sg:classifiers":[
        {
            "category":"Restaurant",
            "type":"Food & Drink"
        }
    ],
    "sg:phone":"+1 773 769 6602",
    "sg:postcode":"60640",
    "sg:province":"IL",
    "sg:tags":[
        "thai",
        "eating"
    ],
    "wof:name":"Siam Cafe",
    "wof:placetype":"venue"
},
  "geometry": {"coordinates":[-87.654602,41.967602],"type":"Point"}
}