{
  "type": "Feature",
  "properties": {
    "addr:full":"1021 Arlington Heights Rd Arlington Heights IL 60005",
    "addr:housenumber":"1021",
    "addr:postcode":"60005",
    "addr:street":"Arlington Heights Rd",
    "iso:country":"US",
    "sg:address":"1021 Arlington Heights Rd",
    "sg:city":"Arlington Heights",
    "sg:classifiers":[
        {
            "category":"Home & Garden",
            "subcategory":"Building Materials",
            "type":"Retail Goods"
        }
    ],
    "sg:phone":"+1   ",
    "sg:postcode":"60005",
    "sg:province":"IL",
    "wof:name":"Merry-Go-Round Stained GL Ctr",
    "wof:placetype":"venue"
},
  "geometry": {"coordinates":[-87.979868,42.066488],"type":"Point"}
}