{
  "type": "Feature",
  "properties": {
    "addr:full":"606 N Elida St Winnebago IL 61088",
    "addr:housenumber":"606",
    "addr:postcode":"61088",
    "addr:street":"N Elida St",
    "iso:country":"US",
    "sg:address":"606 N Elida St",
    "sg:city":"Winnebago",
    "sg:classifiers":[
        {
            "category":"Banks & Credit Unions",
            "subcategory":"Bank",
            "type":"Services"
        },
        {
            "category":"Banks & Credit Unions",
            "subcategory":"Financial Services",
            "type":"Services"
        }
    ],
    "sg:phone":"+1 815 335 2600",
    "sg:postcode":"61088",
    "sg:province":"IL",
    "sg:tags":[
        "saving",
        "loan",
        "commercial"
    ],
    "sg:website":"http://www.usbank.com",
    "wof:name":"U.S. Bank",
    "wof:placetype":"venue"
},
  "geometry": {"coordinates":[-89.241506,42.273171],"type":"Point"}
}