{
  "type": "Feature",
  "properties": {
    "addr:full":"1760 E 72nd St Chicago IL 60649",
    "addr:housenumber":"1760",
    "addr:postcode":"60649",
    "addr:street":"E 72Nd St",
    "iso:country":"US",
    "sg:address":"1760 E 72nd St",
    "sg:city":"Chicago",
    "sg:classifiers":[
        {
            "category":"Real Estate",
            "subcategory":"Real Estate Agent",
            "type":"Services"
        }
    ],
    "sg:phone":"+1 773 908 8604",
    "sg:postcode":"60649",
    "sg:province":"IL",
    "sg:tags":[
        "rental",
        "leasing",
        "investment"
    ],
    "wof:name":"Investmasters LLC",
    "wof:placetype":"venue"
},
  "geometry": {"coordinates":[-87.58240000000001,41.764269],"type":"Point"}
}