{
  "type": "Feature",
  "properties": {
    "iso:country":"US",
    "sg:address":"4807 N Spaulding Avenue",
    "sg:city":"Chicago",
    "sg:classifiers":[
        {
            "category":"Coffee & Tea",
            "type":"Food & Drink"
        }
    ],
    "sg:phone":"+1 773 588 2165",
    "sg:postcode":"60625",
    "sg:province":"IL",
    "wof:name":"Coffe Liberte",
    "wof:placetype":"venue"
},
  "geometry": {"coordinates":[-87.71110899999999,41.968572],"type":"Point"}
}