{
  "type": "Feature",
  "properties": {
    "iso:country":"US",
    "sg:address":"2011 Rock St Ste F",
    "sg:city":"Peru",
    "sg:classifiers":[
        {
            "category":"Health Services",
            "subcategory":"Chiropractor",
            "type":"Services"
        }
    ],
    "sg:phone":"+1 815 224 8090",
    "sg:postcode":"61354",
    "sg:province":"IL",
    "sg:tags":[
        "chiropractic"
    ],
    "wof:name":"Mertis Family Chiropracti",
    "wof:placetype":"venue"
},
  "geometry": {"coordinates":[-89.121753,41.33859],"type":"Point"}
}