{
  "type": "Feature",
  "properties": {
    "iso:country":"US",
    "sg:address":"590 Belmont Dr",
    "sg:city":"Romeoville",
    "sg:classifiers":[
        {
            "category":"Education",
            "subcategory":"Special Training",
            "type":"Public Place"
        }
    ],
    "sg:phone":"+1 815 886 7831",
    "sg:postcode":"60446",
    "sg:province":"IL",
    "sg:tags":[
        "organization",
        "educational",
        "cooperative"
    ],
    "wof:name":"Valley View Educational",
    "wof:placetype":"venue"
},
  "geometry": {"coordinates":[-88.098958,41.641571],"type":"Point"}
}