{
  "type": "Feature",
  "properties": {
    "iso:country":"US",
    "sg:address":"780 Rosewood Ave",
    "sg:city":"Winnetka",
    "sg:classifiers":[
        {
            "category":"Banks & Credit Unions",
            "subcategory":"Investment Brokerage",
            "type":"Services"
        },
        {
            "category":"Real Estate",
            "subcategory":"Developer",
            "type":"Services"
        }
    ],
    "sg:phone":"+1 847 441 5576",
    "sg:postcode":"60093",
    "sg:province":"IL",
    "sg:tags":[
        "investing"
    ],
    "wof:name":"Leeder Hill Partners",
    "wof:placetype":"venue"
},
  "geometry": {"coordinates":[-87.743993,42.112431],"type":"Point"}
}