{
  "type": "Feature",
  "properties": {
    "addr:full":"115 N Johnson St Woodstock IL 60098",
    "addr:housenumber":"115",
    "addr:postcode":"60098",
    "addr:street":"N Johnson St",
    "iso:country":"US",
    "sg:address":"115 N Johnson St",
    "sg:city":"Woodstock",
    "sg:classifiers":[
        {
            "category":"Restaurant",
            "type":"Food & Drink"
        }
    ],
    "sg:phone":"+1 815 337 0765",
    "sg:postcode":"60098",
    "sg:province":"IL",
    "sg:tags":[
        "french"
    ],
    "wof:name":"Kristine Ferru",
    "wof:placetype":"venue"
},
  "geometry": {"coordinates":[-88.447998,42.31476],"type":"Point"}
}