{
  "type": "Feature",
  "properties": {
    "iso:country":"US",
    "sg:address":"2068 Hallmark Ct",
    "sg:city":"Wheaton",
    "sg:classifiers":[
        {
            "category":"Manufacturing",
            "subcategory":"Chemicals & Compounds",
            "type":"Manufacturing & Wholesale Goods"
        }
    ],
    "sg:phone":"+1 630 933 8122",
    "sg:postcode":"60187",
    "sg:province":"IL",
    "sg:tags":[
        "mfg"
    ],
    "wof:name":"Church & Dwight Co Inc",
    "wof:placetype":"venue"
},
  "geometry": {"coordinates":[-88.102285,41.886945],"type":"Point"}
}