{
  "type": "Feature",
  "properties": {
    "addr:full":"1645 W North Ave Chicago IL 60622",
    "addr:housenumber":"1645",
    "addr:postcode":"60622",
    "addr:street":"W North Ave",
    "iso:country":"US",
    "sg:address":"1645 W North Ave",
    "sg:city":"Chicago",
    "sg:classifiers":[
        {
            "category":"Health Services",
            "subcategory":"Clinic",
            "type":"Services"
        },
        {
            "category":"Personal",
            "subcategory":"Hair Removal",
            "type":"Services"
        },
        {
            "category":"Personal",
            "subcategory":"Skin Care",
            "type":"Services"
        }
    ],
    "sg:phone":"+1 773 904 8310",
    "sg:postcode":"60622",
    "sg:province":"IL",
    "sg:tags":[
        "spa",
        "medical",
        "laser"
    ],
    "sg:website":"enfusemedspas.com/",
    "wof:name":"Enfuse Laser Center & Medical Spa",
    "wof:placetype":"venue"
},
  "geometry": {"coordinates":[-87.669449,41.910531],"type":"Point"}
}