{
  "type": "Feature",
  "properties": {
    "iso:country":"US",
    "sg:address":"7601 Madison St",
    "sg:city":"Forest Park",
    "sg:classifiers":[
        {
            "category":"Professional",
            "subcategory":"Research",
            "type":"Services"
        }
    ],
    "sg:phone":"+1 708 366 0383",
    "sg:postcode":"60130",
    "sg:province":"IL",
    "sg:tags":[
        "environmental",
        "ecological"
    ],
    "wof:name":"AEI Consultants",
    "wof:placetype":"venue"
},
  "geometry": {"coordinates":[-87.81608,41.879411],"type":"Point"}
}