{
  "type": "Feature",
  "properties": {
    "addr:full":"1423 2nd St Charleston IL 61920",
    "addr:housenumber":"1423",
    "addr:postcode":"61920",
    "addr:street":"2Nd St",
    "iso:country":"US",
    "sg:address":"1423 2nd St",
    "sg:city":"Charleston",
    "sg:classifiers":[
        {
            "category":"Building & Trades",
            "subcategory":"Construction",
            "type":"Services"
        }
    ],
    "sg:phone":"+1 217 962 1150",
    "sg:postcode":"61920",
    "sg:province":"IL",
    "sg:tags":[
        "excavating",
        "contractor"
    ],
    "wof:name":"Homann Excavating",
    "wof:placetype":"venue"
},
  "geometry": {"coordinates":[-88.179288,39.485068],"type":"Point"}
}