{
  "type": "Feature",
  "properties": {
    "addr:full":"4828 W Irving Park Rd Chicago IL 60641",
    "addr:housenumber":"4828",
    "addr:postcode":"60641",
    "addr:street":"W Irving Park Rd",
    "iso:country":"US",
    "sg:address":"4828 W Irving Park Rd",
    "sg:city":"Chicago",
    "sg:classifiers":[
        {
            "category":"Shopping",
            "subcategory":"Discount & Variety Stores",
            "type":"Retail Goods"
        },
        {
            "category":"Shopping",
            "subcategory":"Department Store",
            "type":"Retail Goods"
        }
    ],
    "sg:phone":"+1 773 283 0049",
    "sg:postcode":"60641",
    "sg:province":"IL",
    "sg:tags":[
        "shop"
    ],
    "sg:website":"www.familydollar.com",
    "wof:name":"Family Dollar Stores",
    "wof:placetype":"venue"
},
  "geometry": {"coordinates":[-87.74986,41.953385],"type":"Point"}
}