{
  "type": "Feature",
  "properties": {
    "addr:full":"504 S Spencer St Aurora IL 60505",
    "addr:housenumber":"504",
    "addr:postcode":"60505",
    "addr:street":"S Spencer St",
    "iso:country":"US",
    "sg:address":"504 S Spencer St",
    "sg:city":"Aurora",
    "sg:classifiers":[
        {
            "category":"Retail",
            "subcategory":"Auto Repair",
            "type":"Services"
        }
    ],
    "sg:phone":"+1 630 898 4616",
    "sg:postcode":"60505",
    "sg:province":"IL",
    "sg:tags":[
        "general"
    ],
    "wof:name":"Auto Service El Rapido",
    "wof:placetype":"venue"
},
  "geometry": {"coordinates":[-88.304805,41.743926],"type":"Point"}
}