{
  "type": "Feature",
  "properties": {
    "iso:country":"US",
    "sg:address":"424 Buckbee St",
    "sg:city":"Rockford",
    "sg:classifiers":[
        {
            "category":"Manufacturing",
            "subcategory":"Tools & Machinery",
            "type":"Manufacturing & Wholesale Goods"
        }
    ],
    "sg:phone":"+1 815 963 0005",
    "sg:postcode":"61104",
    "sg:province":"IL",
    "sg:tags":[
        "industrial",
        "mfg",
        "process",
        "furnaces-industrial",
        "oven",
        "furnace"
    ],
    "sg:website":"http://www.beavermatic.com",
    "wof:name":"Beavermatic Heat Furnaces",
    "wof:placetype":"venue"
},
  "geometry": {"coordinates":[-89.09162499999999,42.25289],"type":"Point"}
}