{
  "type": "Feature",
  "properties": {
    "iso:country":"US",
    "sg:address":"404 E Washington St",
    "sg:city":"Oregon",
    "sg:classifiers":[
        {
            "category":"Restaurant",
            "type":"Food & Drink"
        }
    ],
    "sg:menulink":"http://www.allmenus.com/il/oregon-nashua/79889-pizza-hut/menu/",
    "sg:phone":"+1 815 732 4444",
    "sg:postcode":"61061",
    "sg:province":"IL",
    "sg:tags":[
        "american",
        "pizza"
    ],
    "wof:name":"Pizza Hut",
    "wof:placetype":"venue"
},
  "geometry": {"coordinates":[-89.322841,42.014426],"type":"Point"}
}