{
  "type": "Feature",
  "properties": {
    "iso:country":"US",
    "sg:address":"10718 S Cicero Ave",
    "sg:city":"Oak Lawn",
    "sg:classifiers":[
        {
            "category":"Building & Trades",
            "subcategory":"Construction",
            "type":"Services"
        }
    ],
    "sg:phone":"+1 708 425 1613",
    "sg:postcode":"60453",
    "sg:province":"IL",
    "sg:tags":[
        "general",
        "contractor"
    ],
    "wof:name":"Allied Design Build",
    "wof:placetype":"venue"
},
  "geometry": {"coordinates":[-87.74002,41.696754],"type":"Point"}
}