{
  "type": "Feature",
  "properties": {
    "iso:country":"US",
    "sg:address":"1673 N Belmont Ave",
    "sg:city":"Arlington Heights",
    "sg:classifiers":[
        {
            "category":"Professional",
            "subcategory":"Computer Services",
            "type":"Services"
        }
    ],
    "sg:phone":"+1 847 255 4079",
    "sg:postcode":"60004",
    "sg:province":"IL",
    "wof:name":"Dr Desktop",
    "wof:placetype":"venue"
},
  "geometry": {"coordinates":[-87.977873,42.106234],"type":"Point"}
}