{
  "type": "Feature",
  "properties": {
    "addr:full":"1705 W 18th St Chicago IL 60608",
    "addr:housenumber":"1705",
    "addr:postcode":"60608",
    "addr:street":"W 18Th St",
    "iso:country":"US",
    "sg:address":"1705 W 18th St",
    "sg:city":"Chicago",
    "sg:classifiers":[
        {
            "category":"Banks & Credit Unions",
            "subcategory":"Bank",
            "type":"Services"
        }
    ],
    "sg:postcode":"60608",
    "sg:province":"IL",
    "sg:website":"www.bankofamerica.com",
    "wof:name":"Bank of America",
    "wof:placetype":"venue"
},
  "geometry": {"coordinates":[-87.668948,41.857747],"type":"Point"}
}