{
  "type": "Feature",
  "properties": {
    "addr:full":"3086 Old Peoria Rd Danvers IL 61732",
    "addr:housenumber":"3086",
    "addr:postcode":"61732",
    "addr:street":"Old Peoria Rd",
    "iso:country":"US",
    "sg:address":"3086 Old Peoria Rd",
    "sg:city":"Danvers",
    "sg:classifiers":[
        {
            "category":"Retail",
            "subcategory":"Car Wash",
            "type":"Services"
        }
    ],
    "sg:phone":"+1 309 963 6086",
    "sg:postcode":"61732",
    "sg:province":"IL",
    "sg:tags":[
        "carwash"
    ],
    "wof:name":"Altes Pressure Wash",
    "wof:placetype":"venue"
},
  "geometry": {"coordinates":[-89.204572,40.534047],"type":"Point"}
}