{
  "type": "Feature",
  "properties": {
    "addr:full":"1011 S Main St Altamont IL 62411",
    "addr:housenumber":"1011",
    "addr:postcode":"62411",
    "addr:street":"S Main St",
    "iso:country":"US",
    "sg:address":"1011 S Main St",
    "sg:city":"Altamont",
    "sg:classifiers":[
        {
            "category":"Food & Beverages",
            "subcategory":"Groceries & Convenience Stores",
            "type":"Retail Goods"
        }
    ],
    "sg:phone":"+1 618 483 3173",
    "sg:postcode":"62411",
    "sg:province":"IL",
    "wof:name":"Besaj Inc",
    "wof:placetype":"venue"
},
  "geometry": {"coordinates":[-88.747974,39.049925],"type":"Point"}
}