{
  "type": "Feature",
  "properties": {
    "addr:full":"529 Cooper Dr East Saint Louis IL 62206",
    "addr:housenumber":"529",
    "addr:postcode":"62206",
    "addr:street":"Cooper Dr East",
    "iso:country":"US",
    "sg:address":"529 Cooper Dr",
    "sg:city":"East Saint Louis",
    "sg:classifiers":[
        {
            "category":"Retail",
            "subcategory":"Auto Repair",
            "type":"Services"
        }
    ],
    "sg:phone":"+1 618 337 7277",
    "sg:postcode":"62206",
    "sg:province":"IL",
    "wof:name":"Stokes Bros Automatic Transmission Serv",
    "wof:placetype":"venue"
},
  "geometry": {"coordinates":[-90.176903,38.5672],"type":"Point"}
}