{
  "type": "Feature",
  "properties": {
    "iso:country":"US",
    "sg:address":"506 N Clark St # 201",
    "sg:city":"Chicago",
    "sg:classifiers":[
        {
            "category":"Arts & Performance",
            "subcategory":"Music",
            "type":"Entertainment"
        }
    ],
    "sg:phone":"+1 312 828 0556",
    "sg:postcode":"60654",
    "sg:province":"IL",
    "sg:tags":[
        "arranger",
        "composer"
    ],
    "wof:name":"Steve Ford Music",
    "wof:placetype":"venue"
},
  "geometry": {"coordinates":[-87.631094,41.891028],"type":"Point"}
}