{
  "type": "Feature",
  "properties": {
    "addr:full":"600 E. Grand Avenue Chicago IL 60611",
    "addr:housenumber":"600",
    "addr:postcode":"60611",
    "addr:street":"E. Grand Avenue",
    "iso:country":"US",
    "sg:address":"600 E. Grand Avenue",
    "sg:city":"Chicago",
    "sg:classifiers":[
        {
            "category":"Ice Cream",
            "type":"Food & Drink"
        }
    ],
    "sg:phone":"+1 312 595 5487",
    "sg:postcode":"60611",
    "sg:province":"IL",
    "sg:tags":[
        "frozen",
        "yogurt"
    ],
    "sg:website":"www.benjerry.com/",
    "wof:name":"Ben & Jerry's",
    "wof:placetype":"venue"
},
  "geometry": {"coordinates":[-87.609667,41.892125],"type":"Point"}
}