{
  "type": "Feature",
  "properties": {
    "iso:country":"US",
    "sg:address":"6056 W Irving Park Rd",
    "sg:city":"Chicago",
    "sg:classifiers":[
        {
            "category":"Education",
            "subcategory":"Music School",
            "type":"Public Place"
        },
        {
            "category":"Education",
            "subcategory":"School",
            "type":"Public Place"
        }
    ],
    "sg:phone":"+1 773 283 8349",
    "sg:postcode":"60634",
    "sg:province":"IL",
    "wof:name":"Purple Beacon, The",
    "wof:placetype":"venue"
},
  "geometry": {"coordinates":[-87.778453,41.953022],"type":"Point"}
}