{
  "type": "Feature",
  "properties": {
    "iso:country":"US",
    "sg:address":"1022 Lake St",
    "sg:city":"Oak Park",
    "sg:classifiers":[
        {
            "category":"Cinema",
            "subcategory":"Movie Theater",
            "type":"Entertainment"
        }
    ],
    "sg:phone":"+1 708 848 9088",
    "sg:postcode":"60301",
    "sg:province":"IL",
    "sg:website":"www.classiccinemas.com",
    "wof:name":"Classic Cinemas Lake Theatre",
    "wof:placetype":"venue"
},
  "geometry": {"coordinates":[-87.7985,41.888699],"type":"Point"}
}