{
  "type": "Feature",
  "properties": {
    "addr:full":"649 Devonshire Ln Crystal Lake IL 60014",
    "addr:housenumber":"649",
    "addr:postcode":"60014",
    "addr:street":"Devonshire Ln",
    "iso:country":"US",
    "sg:address":"649 Devonshire Ln",
    "sg:city":"Crystal Lake",
    "sg:classifiers":[
        {
            "category":"Social Services",
            "subcategory":"Child Care",
            "type":"Services"
        }
    ],
    "sg:phone":"+1 815 455 5653",
    "sg:postcode":"60014",
    "sg:province":"IL",
    "sg:tags":[
        "day"
    ],
    "wof:name":"Cynthia J Daurio",
    "wof:placetype":"venue"
},
  "geometry": {"coordinates":[-88.331183,42.222862],"type":"Point"}
}