{
  "type": "Feature",
  "properties": {
    "addr:full":"204 Orland Park Pl Orland Park IL 60462",
    "addr:housenumber":"204",
    "addr:postcode":"60462",
    "addr:street":"Orland Park Pl",
    "iso:country":"US",
    "sg:address":"204 Orland Park Pl",
    "sg:city":"Orland Park",
    "sg:classifiers":[
        {
            "category":"Shopping",
            "subcategory":"Department Store",
            "type":"Retail Goods"
        }
    ],
    "sg:phone":"+1   ",
    "sg:postcode":"60462",
    "sg:province":"IL",
    "wof:name":"Stein Mart",
    "wof:placetype":"venue"
},
  "geometry": {"coordinates":[-87.850891,41.613773],"type":"Point"}
}