{
  "type": "Feature",
  "properties": {
    "addr:full":"550 W Washington Blvd Chicago IL 60661",
    "addr:housenumber":"550",
    "addr:postcode":"60661",
    "addr:street":"W Washington Blvd",
    "iso:country":"US",
    "sg:address":"550 W Washington Blvd",
    "sg:city":"Chicago",
    "sg:classifiers":[
        {
            "category":"Professional",
            "subcategory":"Management & Consulting",
            "type":"Services"
        }
    ],
    "sg:phone":"+1 312 474 8300",
    "sg:postcode":"60661",
    "sg:province":"IL",
    "sg:tags":[
        "marketing",
        "sales",
        "client",
        "through",
        "provides",
        "activity"
    ],
    "wof:name":"Mosaic Infoforce LP",
    "wof:placetype":"venue"
},
  "geometry": {"coordinates":[-87.64269899999999,41.883171],"type":"Point"}
}