{
  "type": "Feature",
  "properties": {
    "iso:country":"US",
    "sg:address":"1 E Wacker Dr",
    "sg:city":"Chicago",
    "sg:classifiers":[
        {
            "category":"Wholesale",
            "subcategory":"Groceries",
            "type":"Manufacturing & Wholesale Goods"
        }
    ],
    "sg:phone":"+1 312 836 1850",
    "sg:postcode":"60601",
    "sg:province":"IL",
    "sg:tags":[
        "grocers-wholesale"
    ],
    "wof:name":"Jetro Chicago",
    "wof:placetype":"venue"
},
  "geometry": {"coordinates":[-87.627983,41.886791],"type":"Point"}
}