{
  "type": "Feature",
  "properties": {
    "addr:full":"10610 S Cicero Ave Ste 2 Oak Lawn IL 60453",
    "addr:housenumber":"10610",
    "addr:postcode":"60453",
    "addr:street":"S Cicero Ave Ste 2",
    "iso:country":"US",
    "sg:address":"10610 S Cicero Ave Ste 2",
    "sg:city":"Oak Lawn",
    "sg:classifiers":[
        {
            "category":"Professional",
            "subcategory":"Lawyer & Legal Services",
            "type":"Services"
        }
    ],
    "sg:phone":"+1 708 636 2567",
    "sg:postcode":"60453",
    "sg:province":"IL",
    "wof:name":"Krause Daniel W Law Offices of",
    "wof:placetype":"venue"
},
  "geometry": {"coordinates":[-87.74042900000001,41.699795],"type":"Point"}
}