{
  "type": "Feature",
  "properties": {
    "addr:full":"1101 Lee St Des Plaines IL 60016",
    "addr:housenumber":"1101",
    "addr:postcode":"60016",
    "addr:street":"Lee St",
    "iso:country":"US",
    "sg:address":"1101 Lee St",
    "sg:city":"Des Plaines",
    "sg:classifiers":[
        {
            "category":"Personal",
            "type":"Services"
        }
    ],
    "sg:phone":"+1 847 298 1996",
    "sg:postcode":"60016",
    "sg:province":"IL",
    "wof:name":"Pai Medical Group",
    "wof:placetype":"venue"
},
  "geometry": {"coordinates":[-87.89437,42.032092],"type":"Point"}
}