{
  "type": "Feature",
  "properties": {
    "iso:country":"US",
    "sg:address":"2350 State St",
    "sg:city":"Alton",
    "sg:classifiers":[
        {
            "category":"Autos & Motor Vehicles",
            "subcategory":"Automobile Sales",
            "type":"Retail Goods"
        }
    ],
    "sg:phone":"+1   ",
    "sg:postcode":"62002",
    "sg:province":"IL",
    "sg:tags":[
        "used"
    ],
    "wof:name":"Abbotts Antique Autos",
    "wof:placetype":"venue"
},
  "geometry": {"coordinates":[-90.19266,38.919021],"type":"Point"}
}