{
  "type": "Feature",
  "properties": {
    "iso:country":"US",
    "sg:address":"545 Arlington Heights Rd",
    "sg:city":"Arlington Heights",
    "sg:classifiers":[
        {
            "category":"Manufacturing",
            "subcategory":"Lumber",
            "type":"Manufacturing & Wholesale Goods"
        }
    ],
    "sg:phone":"+1 847 290 9020",
    "sg:postcode":"60005",
    "sg:province":"IL",
    "sg:tags":[
        "hardwood",
        "mill"
    ],
    "wof:name":"Connor Sports Flooring",
    "wof:placetype":"venue"
},
  "geometry": {"coordinates":[-87.980468,42.074563],"type":"Point"}
}