{
  "type": "Feature",
  "properties": {
    "iso:country":"US",
    "sg:address":"101 E Jefferson St",
    "sg:city":"La Fayette",
    "sg:classifiers":[
        {
            "category":"Professional",
            "subcategory":"Advertising",
            "type":"Services"
        }
    ],
    "sg:phone":"+1 309 995 3877",
    "sg:postcode":"61449",
    "sg:province":"IL",
    "wof:name":"Prairie Shopper",
    "wof:placetype":"venue"
},
  "geometry": {"coordinates":[-89.974204,41.112604],"type":"Point"}
}