{
  "type": "Feature",
  "properties": {
    "iso:country":"US",
    "sg:address":"1340 N Main St",
    "sg:city":"Wheaton",
    "sg:classifiers":[
        {
            "category":"Building & Trades",
            "subcategory":"Cleaning & Sanitation",
            "type":"Services"
        }
    ],
    "sg:phone":"+1 630 784 0223",
    "sg:postcode":"60187",
    "sg:province":"IL",
    "sg:tags":[
        "maintenance"
    ],
    "wof:name":"Velebit",
    "wof:placetype":"venue"
},
  "geometry": {"coordinates":[-88.10686800000001,41.882669],"type":"Point"}
}