{
  "type": "Feature",
  "properties": {
    "addr:full":"251 Fleetwood Ln Elk Grove Village IL 60007",
    "addr:housenumber":"251",
    "addr:postcode":"60007",
    "addr:street":"Fleetwood Ln",
    "iso:country":"US",
    "sg:address":"251 Fleetwood Ln",
    "sg:city":"Elk Grove Village",
    "sg:classifiers":[
        {
            "category":"Building & Trades",
            "subcategory":"Construction",
            "type":"Services"
        }
    ],
    "sg:phone":"+1 847 439 0515",
    "sg:postcode":"60007",
    "sg:province":"IL",
    "sg:tags":[
        "house"
    ],
    "wof:name":"Medallion Healthy Homes CHI",
    "wof:placetype":"venue"
},
  "geometry": {"coordinates":[-87.97506799999999,42.015472],"type":"Point"}
}