{
  "type": "Feature",
  "properties": {
    "iso:country":"US",
    "sg:address":"251 Fleetwood Ln",
    "sg:city":"Elk Grove Village",
    "sg:classifiers":[
        {
            "category":"Building & Trades",
            "subcategory":"Construction",
            "type":"Services"
        }
    ],
    "sg:phone":"+1 847 439 0515",
    "sg:postcode":"60007",
    "sg:province":"IL",
    "sg:tags":[
        "house"
    ],
    "wof:name":"Medallion Healthy Homes CHI",
    "wof:placetype":"venue"
},
  "geometry": {"coordinates":[-87.975068,42.015472],"type":"Point"}
}