{
  "type": "Feature",
  "properties": {
    "addr:full":"795 Kimberly Dr Carol Stream IL 60188",
    "addr:housenumber":"795",
    "addr:postcode":"60188",
    "addr:street":"Kimberly Dr",
    "iso:country":"US",
    "sg:address":"795 Kimberly Dr",
    "sg:city":"Carol Stream",
    "sg:classifiers":[
        {
            "category":"Manufacturing",
            "subcategory":"Metals",
            "type":"Manufacturing & Wholesale Goods"
        }
    ],
    "sg:phone":"+1 630 260 1735",
    "sg:postcode":"60188",
    "sg:province":"IL",
    "sg:tags":[
        "machine",
        "screw",
        "product",
        "mfg"
    ],
    "wof:name":"K & K Screw Products LLC",
    "wof:placetype":"venue"
},
  "geometry": {"coordinates":[-88.111856,41.925279],"type":"Point"}
}