{
  "type": "Feature",
  "properties": {
    "iso:country":"US",
    "sg:address":"556 W 18th Street",
    "sg:city":"Chicago",
    "sg:classifiers":[
        {
            "category":"Arts & Performance",
            "subcategory":"Art Gallery",
            "type":"Entertainment"
        },
        {
            "category":"Personal",
            "type":"Services"
        }
    ],
    "sg:phone":"+1 312 738 0860",
    "sg:postcode":"60686",
    "sg:province":"IL",
    "sg:tags":[
        "local"
    ],
    "sg:website":"www.meztli.net",
    "wof:name":"Meztli Gallery & Cultural Organization",
    "wof:placetype":"venue"
},
  "geometry": {"coordinates":[-87.64115099999999,41.857738],"type":"Point"}
}