{
  "type": "Feature",
  "properties": {
    "addr:full":"10051 S Kitty Ave Chicago Ridge IL 60415",
    "addr:housenumber":"10051",
    "addr:postcode":"60415",
    "addr:street":"S Kitty Ave",
    "iso:country":"US",
    "sg:address":"10051 S Kitty Ave",
    "sg:city":"Chicago Ridge",
    "sg:classifiers":[
        {
            "category":"Health Services",
            "subcategory":"Health Practitioner",
            "type":"Services"
        },
        {
            "category":"Retail",
            "subcategory":"Veterinary Services",
            "type":"Services"
        },
        {
            "category":"Retail",
            "subcategory":"Animal Services",
            "type":"Services"
        }
    ],
    "sg:phone":"+1 708 423 3200",
    "sg:postcode":"60415",
    "sg:province":"IL",
    "sg:tags":[
        "acupuncture",
        "pet",
        "veterinarian"
    ],
    "sg:website":"www.chicagoanimalrehab.com",
    "wof:name":"Chicago Animal Rehab",
    "wof:placetype":"venue"
},
  "geometry": {"coordinates":[-87.786045,41.709081],"type":"Point"}
}