{
  "type": "Feature",
  "properties": {
    "iso:country":"US",
    "sg:address":"680 Summit Dr",
    "sg:city":"Lockport",
    "sg:classifiers":[
        {
            "category":"Building & Trades",
            "subcategory":"Construction",
            "type":"Services"
        }
    ],
    "sg:phone":"+1 815 838 2076",
    "sg:postcode":"60441",
    "sg:province":"IL",
    "sg:tags":[
        "general",
        "contractor"
    ],
    "wof:name":"Pasch & Sons Construction Co",
    "wof:placetype":"venue"
},
  "geometry": {"coordinates":[-88.040378,41.592826],"type":"Point"}
}