{
  "type": "Feature",
  "properties": {
    "addr:full":"886 George Towne Ln Barrington IL 60010",
    "addr:housenumber":"886",
    "addr:postcode":"60010",
    "addr:street":"George Towne Ln",
    "iso:country":"US",
    "sg:address":"886 George Towne Ln",
    "sg:city":"Barrington",
    "sg:classifiers":[
        {
            "category":"Real Estate",
            "subcategory":"Developer",
            "type":"Services"
        }
    ],
    "sg:phone":"+1 847 387 3298",
    "sg:postcode":"60010",
    "sg:province":"IL",
    "wof:name":"Prairie Artisan Developers Inc",
    "wof:placetype":"venue"
},
  "geometry": {"coordinates":[-88.129723,42.16647],"type":"Point"}
}