{
  "type": "Feature",
  "properties": {
    "addr:full":"5 E Van Buren St Joliet IL 60432",
    "addr:housenumber":"5",
    "addr:postcode":"60432",
    "addr:street":"E Van Buren St",
    "iso:country":"US",
    "sg:address":"5 E Van Buren St",
    "sg:city":"Joliet",
    "sg:classifiers":[
        {
            "category":"Professional",
            "subcategory":"Lawyer & Legal Services",
            "type":"Services"
        }
    ],
    "sg:phone":"+1 815 726 0756",
    "sg:postcode":"60432",
    "sg:province":"IL",
    "sg:tags":[
        "attorney"
    ],
    "wof:name":"Troy & Assoc",
    "wof:placetype":"venue"
},
  "geometry": {"coordinates":[-88.08027,41.526037],"type":"Point"}
}