{
  "type": "Feature",
  "properties": {
    "addr:full":"2034 W Grand Ave Chicago IL 60612",
    "addr:housenumber":"2034",
    "addr:postcode":"60612",
    "addr:street":"W Grand Ave",
    "iso:country":"US",
    "sg:address":"2034 W Grand Ave",
    "sg:city":"Chicago",
    "sg:classifiers":[
        {
            "category":"Personal",
            "type":"Services"
        },
        {
            "category":"Retail",
            "subcategory":"Portrait Studio",
            "type":"Services"
        },
        {
            "category":"Professional",
            "subcategory":"Art Services",
            "type":"Services"
        },
        {
            "category":"Professional",
            "subcategory":"Printing & Photocopies",
            "type":"Services"
        }
    ],
    "sg:phone":"+1 312 226 1114",
    "sg:postcode":"60612",
    "sg:province":"IL",
    "sg:tags":[
        "photographers-portrait",
        "videography",
        "darkroom",
        "photographer",
        "photography",
        "wedding",
        "rental",
        "photographers-commercial",
        "photographic"
    ],
    "sg:website":"www.yamashirostudio.com",
    "wof:name":"Yamashiro Studio",
    "wof:placetype":"venue"
},
  "geometry": {"coordinates":[-87.678318,41.891015],"type":"Point"}
}