{
  "type": "Feature",
  "properties": {
    "addr:full":"Salon Wesley 208 W Wesley St Wheaton IL 60187",
    "addr:housenumber":"208",
    "addr:postcode":"60187",
    "addr:street":"Wesley;W Wesley St",
    "iso:country":"US",
    "sg:address":"Salon Wesley 208 W Wesley St",
    "sg:city":"Wheaton",
    "sg:classifiers":[
        {
            "category":"Personal",
            "subcategory":"Beauty Salon",
            "type":"Services"
        }
    ],
    "sg:phone":"+1 630 890 6876",
    "sg:postcode":"60187",
    "sg:province":"IL",
    "sg:tags":[
        "hair"
    ],
    "wof:name":"Imma's Hair Studio",
    "wof:placetype":"venue"
},
  "geometry": {"coordinates":[-88.108552,41.865935],"type":"Point"}
}