{
  "type": "Feature",
  "properties": {
    "iso:country":"US",
    "sg:address":"4045 N Rockwell Street",
    "sg:city":"Chicago",
    "sg:classifiers":[
        {
            "category":"Shopping",
            "subcategory":"Stationery & Office Supplies",
            "type":"Retail Goods"
        }
    ],
    "sg:phone":"+1 773 463 2424",
    "sg:postcode":"60618",
    "sg:province":"IL",
    "sg:tags":[
        "equipment"
    ],
    "wof:name":"General Products",
    "wof:placetype":"venue"
},
  "geometry": {"coordinates":[-87.69341,41.955222],"type":"Point"}
}