{
  "type": "Feature",
  "properties": {
    "addr:full":"223 W Main St Barrington IL 60010",
    "addr:housenumber":"223",
    "addr:postcode":"60010",
    "addr:street":"W Main St",
    "iso:country":"US",
    "sg:address":"223 W Main St",
    "sg:city":"Barrington",
    "sg:classifiers":[
        {
            "category":"Wholesale",
            "subcategory":"Non-durable Goods",
            "type":"Manufacturing & Wholesale Goods"
        }
    ],
    "sg:phone":"+1 847 304 8550",
    "sg:postcode":"60010",
    "sg:province":"IL",
    "sg:tags":[
        "advertising",
        "specialty"
    ],
    "wof:name":"Identity Inc Corporate",
    "wof:placetype":"venue"
},
  "geometry": {"coordinates":[-88.13956899999999,42.154147],"type":"Point"}
}