{
  "type": "Feature",
  "properties": {
    "iso:country":"US",
    "sg:address":"1061 Little Falls Dr",
    "sg:city":"Elgin",
    "sg:classifiers":[
        {
            "category":"Manufacturing",
            "subcategory":"Tools & Machinery",
            "type":"Manufacturing & Wholesale Goods"
        }
    ],
    "sg:phone":"+1 847 741 2572",
    "sg:postcode":"60120",
    "sg:province":"IL",
    "sg:tags":[
        "photographic",
        "mfg"
    ],
    "wof:name":"Time In A Bottle",
    "wof:placetype":"venue"
},
  "geometry": {"coordinates":[-88.24723400000001,42.059062],"type":"Point"}
}