{
  "type": "Feature",
  "properties": {
    "iso:country":"US",
    "sg:address":"2237 W Schaumburg Rd",
    "sg:city":"Schaumburg",
    "sg:classifiers":[
        {
            "category":"Shopping",
            "subcategory":"Pets & Pet Supplies",
            "type":"Retail Goods"
        },
        {
            "category":"Retail",
            "subcategory":"Veterinary Services",
            "type":"Services"
        }
    ],
    "sg:phone":"+1 847 891 8944",
    "sg:postcode":"60194",
    "sg:province":"IL",
    "sg:tags":[
        "veterinarian",
        "product",
        "health",
        "animal"
    ],
    "sg:website":"http://www.knollwoodhospitalforpets.com",
    "wof:name":"Knollwood Hospital For Pets",
    "wof:placetype":"venue"
},
  "geometry": {"coordinates":[-88.13539299999999,42.025148],"type":"Point"}
}