{
  "type": "Feature",
  "properties": {
    "addr:full":"305 E Black Rd Joliet IL 60431",
    "addr:housenumber":"305",
    "addr:postcode":"60431",
    "addr:street":"E Black Rd",
    "iso:country":"US",
    "sg:address":"305 E Black Rd",
    "sg:city":"Joliet",
    "sg:classifiers":[
        {
            "category":"Organizations",
            "subcategory":"Religious Organization",
            "type":"Services"
        }
    ],
    "sg:phone":"+1 815 741 2428",
    "sg:postcode":"60431",
    "sg:province":"IL",
    "sg:tags":[
        "church"
    ],
    "wof:name":"Hope Lutheran Church",
    "wof:placetype":"venue"
},
  "geometry": {"coordinates":[-88.08824199999999,41.537973],"type":"Point"}
}