{
  "type": "Feature",
  "properties": {
    "addr:full":"11100 S Indiana Avenue Chicago IL 60628",
    "addr:housenumber":"11100",
    "addr:postcode":"60628",
    "addr:street":"S Indiana Avenue",
    "iso:country":"US",
    "sg:address":"11100 S Indiana Avenue",
    "sg:city":"Chicago",
    "sg:classifiers":[
        {
            "category":"Park",
            "type":"Public Place"
        }
    ],
    "sg:phone":"+1 312 747 6576",
    "sg:postcode":"60628",
    "sg:province":"IL",
    "wof:name":"Chicago Park District",
    "wof:placetype":"venue"
},
  "geometry": {"coordinates":[-87.61839500000001,41.692449],"type":"Point"}
}