{
  "type": "Feature",
  "properties": {
    "iso:country":"US",
    "sg:address":"5555 W Sunnyside Ave",
    "sg:city":"Chicago",
    "sg:classifiers":[
        {
            "category":"Autos & Motor Vehicles",
            "subcategory":"Automobile Sales",
            "type":"Retail Goods"
        }
    ],
    "sg:phone":"+1 773 685 6856",
    "sg:postcode":"60630",
    "sg:province":"IL",
    "sg:tags":[
        "limo"
    ],
    "wof:name":"Trans Chicago Limousine Service",
    "wof:placetype":"venue"
},
  "geometry": {"coordinates":[-87.766187,41.962245],"type":"Point"}
}