{
  "type": "Feature",
  "properties": {
    "addr:full":"652 Carlyle Ave Belleville IL 62221",
    "addr:housenumber":"652",
    "addr:postcode":"62221",
    "addr:street":"Carlyle Ave",
    "iso:country":"US",
    "sg:address":"652 Carlyle Ave",
    "sg:city":"Belleville",
    "sg:classifiers":[
        {
            "category":"Restaurant",
            "type":"Food & Drink"
        }
    ],
    "sg:menulink":"http://www.allmenus.com/il/belleville/79867-pizza-hut/menu/",
    "sg:phone":"+1 618 233 8194",
    "sg:postcode":"62221",
    "sg:province":"IL",
    "sg:tags":[
        "american",
        "pizza"
    ],
    "wof:name":"Pizza Hut",
    "wof:placetype":"venue"
},
  "geometry": {"coordinates":[-89.955215,38.516308],"type":"Point"}
}