{
  "type": "Feature",
  "properties": {
    "iso:country":"US",
    "sg:address":"3636 N Talman Ave",
    "sg:city":"Chicago",
    "sg:classifiers":[
        {
            "category":"Wholesale",
            "subcategory":"Painting Supplies",
            "type":"Manufacturing & Wholesale Goods"
        },
        {
            "category":"Shopping",
            "subcategory":"Crafts & Fabrics",
            "type":"Retail Goods"
        }
    ],
    "sg:phone":"+1 312 433 7700",
    "sg:postcode":"60618",
    "sg:province":"IL",
    "sg:tags":[
        "goods-wholesale",
        "art",
        "manufacturer"
    ],
    "wof:name":"Shiraleah",
    "wof:placetype":"venue"
},
  "geometry": {"coordinates":[-87.69487599999999,41.947178],"type":"Point"}
}