{
  "type": "Feature",
  "properties": {
    "addr:full":"32045 S Rte 45 Peotone IL 60468",
    "addr:housenumber":"32045",
    "addr:postcode":"60468",
    "addr:street":"S Rte 45",
    "iso:country":"US",
    "sg:address":"32045 S Rte 45",
    "sg:city":"Peotone",
    "sg:classifiers":[
        {
            "category":"Farming",
            "subcategory":"Farm & Veterinary Services",
            "type":"Manufacturing & Wholesale Goods"
        }
    ],
    "sg:phone":"+1 708 258 3309",
    "sg:postcode":"60468",
    "sg:province":"IL",
    "sg:website":"www.continentalfarmsinc.com",
    "wof:name":"Continental Farms",
    "wof:placetype":"venue"
},
  "geometry": {"coordinates":[-87.881204,41.305475],"type":"Point"}
}