{
  "type": "Feature",
  "properties": {
    "addr:full":"200 N 3rd St Effingham IL 62401",
    "addr:housenumber":"200",
    "addr:postcode":"62401",
    "addr:street":"N 3Rd St",
    "iso:country":"US",
    "sg:address":"200 N 3rd St",
    "sg:city":"Effingham",
    "sg:classifiers":[
        {
            "category":"Professional",
            "type":"Services"
        }
    ],
    "sg:phone":"+1 217 342 4312",
    "sg:postcode":"62401",
    "sg:province":"IL",
    "sg:tags":[
        "establishment"
    ],
    "wof:name":"Banyon Group Inc",
    "wof:placetype":"venue"
},
  "geometry": {"coordinates":[-88.54079,39.122656],"type":"Point"}
}