{
  "type": "Feature",
  "properties": {
    "iso:country":"US",
    "sg:address":"7862 W Sunset Dr",
    "sg:city":"Elmwood Park",
    "sg:classifiers":[
        {
            "category":"Building & Trades",
            "subcategory":"Electrical",
            "type":"Services"
        }
    ],
    "sg:phone":"+1 773 744 6054",
    "sg:postcode":"60707",
    "sg:province":"IL",
    "sg:tags":[
        "electrician"
    ],
    "sg:website":"www.allelectrical.us/",
    "wof:name":"All Electrical Contractors Inc",
    "wof:placetype":"venue"
},
  "geometry": {"coordinates":[-87.82317399999999,41.932417],"type":"Point"}
}