{
  "type": "Feature",
  "properties": {
    "addr:full":"11730 S Marshfield Ave Chicago IL 60643",
    "addr:housenumber":"11730",
    "addr:postcode":"60643",
    "addr:street":"S Marshfield Ave",
    "iso:country":"US",
    "sg:address":"11730 S Marshfield Ave",
    "sg:city":"Chicago",
    "sg:classifiers":[
        {
            "category":"Food & Beverages",
            "subcategory":"Groceries & Convenience Stores",
            "type":"Retail Goods"
        }
    ],
    "sg:phone":"+1 773 568 8157",
    "sg:postcode":"60643",
    "sg:province":"IL",
    "wof:name":"Jewel-Osco 3187",
    "wof:placetype":"venue"
},
  "geometry": {"coordinates":[-87.662631,41.680485],"type":"Point"}
}