{
  "type": "Feature",
  "properties": {
    "iso:country":"US",
    "sg:address":"302 Randall Rd",
    "sg:city":"Geneva",
    "sg:classifiers":[
        {
            "category":"Health Services",
            "subcategory":"Doctor",
            "type":"Services"
        }
    ],
    "sg:phone":"+1 630 897 6044",
    "sg:postcode":"60134",
    "sg:province":"IL",
    "sg:tags":[
        "physician",
        "surgeon"
    ],
    "wof:name":"Fox Valley Womens Health",
    "wof:placetype":"venue"
},
  "geometry": {"coordinates":[-88.34045999999999,41.886836],"type":"Point"}
}