{
  "type": "Feature",
  "properties": {
    "addr:full":"2651 Warrenville Rd Downers Grove IL 60515",
    "addr:housenumber":"2651",
    "addr:postcode":"60515",
    "addr:street":"Warrenville Rd",
    "iso:country":"US",
    "sg:address":"2651 Warrenville Rd",
    "sg:city":"Downers Grove",
    "sg:classifiers":[
        {
            "category":"Banks & Credit Unions",
            "subcategory":"Bank",
            "type":"Services"
        }
    ],
    "sg:phone":"+1 630 725 1560",
    "sg:postcode":"60515",
    "sg:province":"IL",
    "sg:tags":[
        "loan",
        "real estate"
    ],
    "sg:website":"www.accredhome.com",
    "wof:name":"Accredited Home Loans",
    "wof:placetype":"venue"
},
  "geometry": {"coordinates":[-88.049021,41.807567],"type":"Point"}
}