{
  "type": "Feature",
  "properties": {
    "addr:full":"325 Harrison St Oak Park IL 60304",
    "addr:housenumber":"325",
    "addr:postcode":"60304",
    "addr:street":"Harrison St",
    "iso:country":"US",
    "sg:address":"325 Harrison St",
    "sg:city":"Oak Park",
    "sg:classifiers":[
        {
            "category":"Shopping",
            "subcategory":"Music",
            "type":"Retail Goods"
        }
    ],
    "sg:phone":"+1 708 948 7086",
    "sg:postcode":"60304",
    "sg:province":"IL",
    "sg:tags":[
        "dvd's"
    ],
    "sg:website":"www.sitaremporium.com/Wonderwall...",
    "wof:name":"Wonderwall Music Shoppe & Emporium",
    "wof:placetype":"venue"
},
  "geometry": {"coordinates":[-87.782957,41.872649],"type":"Point"}
}