{
  "type": "Feature",
  "properties": {
    "addr:full":"5305 N Delphia Ave Chicago IL 60656",
    "addr:housenumber":"5305",
    "addr:postcode":"60656",
    "addr:street":"N Delphia Ave",
    "iso:country":"US",
    "sg:address":"5305 N Delphia Ave",
    "sg:city":"Chicago",
    "sg:classifiers":[
        {
            "category":"Shopping",
            "subcategory":"Jewelry",
            "type":"Retail Goods"
        }
    ],
    "sg:phone":"+1   ",
    "sg:postcode":"60656",
    "sg:province":"IL",
    "wof:name":"Mova Jewelry Shop Inc",
    "wof:placetype":"venue"
},
  "geometry": {"coordinates":[-87.841469,41.975932],"type":"Point"}
}