{
  "type": "Feature",
  "properties": {
    "iso:country":"US",
    "sg:address":"153 Schiller St",
    "sg:city":"Elmhurst",
    "sg:classifiers":[
        {
            "category":"Shopping",
            "subcategory":"Pharmacy",
            "type":"Retail Goods"
        }
    ],
    "sg:phone":"+1   ",
    "sg:postcode":"60126",
    "sg:province":"IL",
    "sg:tags":[
        "drug",
        "store"
    ],
    "wof:name":"Osco Drug 3346",
    "wof:placetype":"venue"
},
  "geometry": {"coordinates":[-87.936581,41.901234],"type":"Point"}
}