{
  "type": "Feature",
  "properties": {
    "iso:country":"US",
    "sg:address":"8372 Robinson Rd",
    "sg:city":"Ellis Grove",
    "sg:classifiers":[
        {
            "category":"Farming",
            "subcategory":"Farm",
            "type":"Manufacturing & Wholesale Goods"
        }
    ],
    "sg:phone":"+1 618 774 2263",
    "sg:postcode":"62241",
    "sg:province":"IL",
    "sg:tags":[
        "crop",
        "general"
    ],
    "wof:name":"Schulein Farm",
    "wof:placetype":"venue"
},
  "geometry": {"coordinates":[-89.835688,38.015812],"type":"Point"}
}