{
  "type": "Feature",
  "properties": {
    "iso:country":"US",
    "sg:address":"1000 River Park Dr",
    "sg:city":"Loves Park",
    "sg:classifiers":[
        {
            "category":"Organizations",
            "subcategory":"Professional Association",
            "type":"Services"
        }
    ],
    "sg:phone":"+1 815 633 3999",
    "sg:postcode":"61111",
    "sg:province":"IL",
    "sg:tags":[
        "chambers",
        "commerce"
    ],
    "wof:name":"Loves Pk Machesney Pk Cham Cmm",
    "wof:placetype":"venue"
},
  "geometry": {"coordinates":[-89.047746,42.314348],"type":"Point"}
}