{
  "type": "Feature",
  "properties": {
    "addr:full":"1300 W Altgeld St Chicago IL 60614",
    "addr:housenumber":"1300",
    "addr:postcode":"60614",
    "addr:street":"W Altgeld St",
    "iso:country":"US",
    "sg:address":"1300 W Altgeld St",
    "sg:city":"Chicago",
    "sg:classifiers":[
        {
            "category":"Communications",
            "subcategory":"Newspaper",
            "type":"Services"
        }
    ],
    "sg:phone":"+1 773 755 8990",
    "sg:postcode":"60614",
    "sg:province":"IL",
    "sg:tags":[
        "magazine"
    ],
    "wof:name":"Dairy Foods",
    "wof:placetype":"venue"
},
  "geometry": {"coordinates":[-87.660552,41.927207],"type":"Point"}
}