{
  "type": "Feature",
  "properties": {
    "addr:full":"6668 N Northwest Hwy Chicago IL 60631",
    "addr:housenumber":"6668",
    "addr:postcode":"60631",
    "addr:street":"N Northwest Hwy",
    "iso:country":"US",
    "sg:address":"6668 N Northwest Hwy",
    "sg:city":"Chicago",
    "sg:classifiers":[
        {
            "category":"Retail",
            "subcategory":"Repair Shop",
            "type":"Services"
        }
    ],
    "sg:phone":"+1 773 774 0088",
    "sg:postcode":"60631",
    "sg:province":"IL",
    "sg:tags":[
        "reupholstery",
        "furniture"
    ],
    "wof:name":"Alfa Upholstery and Interiors",
    "wof:placetype":"venue"
},
  "geometry": {"coordinates":[-87.814803,42.002073],"type":"Point"}
}