{
  "type": "Feature",
  "properties": {
    "addr:full":"6700 S 78th Ave Bedford Park IL 60499",
    "addr:housenumber":"6700",
    "addr:postcode":"60499",
    "addr:street":"S 78Th Ave",
    "iso:country":"US",
    "sg:address":"6700 S 78th Ave",
    "sg:city":"Bedford Park",
    "sg:classifiers":[
        {
            "category":"Park",
            "type":"Public Place"
        }
    ],
    "sg:phone":"+1 708 458 3536",
    "sg:postcode":"60499",
    "sg:province":"IL",
    "wof:name":"Bedford Park Buildings & Grounds",
    "wof:placetype":"venue"
},
  "geometry": {"coordinates":[-87.786697,41.759499],"type":"Point"}
}