{
  "type": "Feature",
  "properties": {
    "addr:full":"6206 N. Leavitt Chicago IL 60659",
    "addr:housenumber":"6206",
    "addr:postcode":"60659",
    "addr:street":"N. Leavitt",
    "iso:country":"US",
    "sg:address":"6206 N. Leavitt",
    "sg:city":"Chicago",
    "sg:classifiers":[
        {
            "category":"Education",
            "subcategory":"Special Training",
            "type":"Public Place"
        }
    ],
    "sg:phone":"+1 847 420 3207",
    "sg:postcode":"60659",
    "sg:province":"IL",
    "sg:tags":[
        "tutoring"
    ],
    "sg:website":"www.lakeviewacademics.com",
    "wof:name":"Lakeview Academics",
    "wof:placetype":"venue"
},
  "geometry": {"coordinates":[-87.684792,41.994288],"type":"Point"}
}