{
  "type": "Feature",
  "properties": {
    "addr:full":"338 N Highland Ave Elmhurst IL 60126",
    "addr:housenumber":"338",
    "addr:postcode":"60126",
    "addr:street":"N Highland Ave",
    "iso:country":"US",
    "sg:address":"338 N Highland Ave",
    "sg:city":"Elmhurst",
    "sg:classifiers":[
        {
            "category":"Professional",
            "subcategory":"Management & Consulting",
            "type":"Services"
        }
    ],
    "sg:phone":"+1 630 279 8144",
    "sg:postcode":"60126",
    "sg:province":"IL",
    "sg:tags":[
        "business"
    ],
    "wof:name":"T R Mandigo & Co",
    "wof:placetype":"venue"
},
  "geometry": {"coordinates":[-87.953338,41.906131],"type":"Point"}
}