{
  "type": "Feature",
  "properties": {
    "addr:full":"303 Tenney St Kewanee IL 61443",
    "addr:housenumber":"303",
    "addr:postcode":"61443",
    "addr:street":"Tenney St",
    "iso:country":"US",
    "sg:address":"303 Tenney St",
    "sg:city":"Kewanee",
    "sg:classifiers":[
        {
            "category":"Autos & Motor Vehicles",
            "subcategory":"Automobile Sales",
            "type":"Retail Goods"
        }
    ],
    "sg:phone":"+1 309 852 2188",
    "sg:postcode":"61443",
    "sg:province":"IL",
    "sg:tags":[
        "car",
        "dealer"
    ],
    "sg:website":"www.taylorsononline.com",
    "wof:name":"Taylor & Son Jeep Chrysler",
    "wof:placetype":"venue"
},
  "geometry": {"coordinates":[-89.92733,41.230384],"type":"Point"}
}