{
  "type": "Feature",
  "properties": {
    "iso:country":"US",
    "sg:address":"705 Yates Ave",
    "sg:city":"Romeoville",
    "sg:classifiers":[
        {
            "category":"Social Services",
            "subcategory":"Child Care",
            "type":"Services"
        }
    ],
    "sg:phone":"+1 815 474 7606",
    "sg:postcode":"60446",
    "sg:province":"IL",
    "sg:tags":[
        "day"
    ],
    "wof:name":"Maria's Playhouse",
    "wof:placetype":"venue"
},
  "geometry": {"coordinates":[-88.104093,41.642452],"type":"Point"}
}