{
  "type": "Feature",
  "properties": {
    "iso:country":"US",
    "sg:address":"1858 W 18th St Apt 1F",
    "sg:city":"Chicago",
    "sg:classifiers":[
        {
            "category":"Banks & Credit Unions",
            "subcategory":"Investment Brokerage",
            "type":"Services"
        },
        {
            "category":"Insurance",
            "subcategory":"Hazard Insurance",
            "type":"Services"
        }
    ],
    "sg:phone":"+1 312 226 1033",
    "sg:postcode":"60608",
    "sg:province":"IL",
    "sg:tags":[
        "commercial",
        "agent",
        "business",
        "resume"
    ],
    "wof:name":"Capitol Insurance Agency, Inc",
    "wof:placetype":"venue"
},
  "geometry": {"coordinates":[-87.672522,41.857713],"type":"Point"}
}