{
  "type": "Feature",
  "properties": {
    "iso:country":"US",
    "sg:address":"4928 S Kolin Ave",
    "sg:city":"Chicago",
    "sg:classifiers":[
        {
            "category":"Professional",
            "subcategory":"Advertising",
            "type":"Services"
        }
    ],
    "sg:phone":"+1 773 616 1443",
    "sg:postcode":"60632",
    "sg:province":"IL",
    "sg:tags":[
        "marketing",
        "specialty",
        "internet"
    ],
    "wof:name":"Mobile Outdoors Ads Media Inc.",
    "wof:placetype":"venue"
},
  "geometry": {"coordinates":[-87.732004,41.803569],"type":"Point"}
}