{
  "type": "Feature",
  "properties": {
    "iso:country":"US",
    "sg:address":"550 E Boughton Rd",
    "sg:city":"Bolingbrook",
    "sg:classifiers":[
        {
            "category":"Health Services",
            "subcategory":"Doctor",
            "type":"Services"
        }
    ],
    "sg:phone":"+1 630 972 1200",
    "sg:postcode":"60440",
    "sg:province":"IL",
    "sg:tags":[
        "medical"
    ],
    "wof:name":"La Grange Women S Clinic SC",
    "wof:placetype":"venue"
},
  "geometry": {"coordinates":[-88.047981,41.719014],"type":"Point"}
}