{
  "type": "Feature",
  "properties": {
    "addr:full":"3149 S Princeton Ave Chicago IL 60616",
    "addr:housenumber":"3149",
    "addr:postcode":"60616",
    "addr:street":"S Princeton Ave",
    "iso:country":"US",
    "sg:address":"3149 S Princeton Ave",
    "sg:city":"Chicago",
    "sg:classifiers":[
        {
            "category":"Professional",
            "subcategory":"Detective & Security Services",
            "type":"Services"
        }
    ],
    "sg:phone":"+1 312 259 4415",
    "sg:postcode":"60616",
    "sg:province":"IL",
    "sg:tags":[
        "information",
        "bureau"
    ],
    "wof:name":"J.R. Services",
    "wof:placetype":"venue"
},
  "geometry": {"coordinates":[-87.634068,41.83729],"type":"Point"}
}