{
  "type": "Feature",
  "properties": {
    "iso:country":"US",
    "sg:address":"413 4th Ave",
    "sg:city":"Rochelle",
    "sg:classifiers":[
        {
            "category":"Banks & Credit Unions",
            "subcategory":"Investment Brokerage",
            "type":"Services"
        }
    ],
    "sg:phone":"+1 815 561 1113",
    "sg:postcode":"61068",
    "sg:province":"IL",
    "sg:tags":[
        "advisory",
        "financial"
    ],
    "wof:name":"Tyler Financial Svc",
    "wof:placetype":"venue"
},
  "geometry": {"coordinates":[-89.065235,41.922811],"type":"Point"}
}