{
  "type": "Feature",
  "properties": {
    "iso:country":"US",
    "sg:address":"4210 Bunkum Rd",
    "sg:city":"East St Louis",
    "sg:classifiers":[
        {
            "category":"Retail",
            "subcategory":"Car Wash",
            "type":"Services"
        }
    ],
    "sg:phone":"+1 618 875 9094",
    "sg:postcode":"62204",
    "sg:province":"IL",
    "sg:tags":[
        "automobile",
        "detail",
        "clean"
    ],
    "wof:name":"East Side Customs & Detailing",
    "wof:placetype":"venue"
},
  "geometry": {"coordinates":[-90.105235,38.623311],"type":"Point"}
}