{
  "type": "Feature",
  "properties": {
    "iso:country":"US",
    "sg:address":"1061 E 41st Pl Ste 806",
    "sg:city":"Chicago",
    "sg:classifiers":[
        {
            "category":"Shopping",
            "subcategory":"Pets & Pet Supplies",
            "type":"Retail Goods"
        }
    ],
    "sg:phone":"+1 773 507 6316",
    "sg:postcode":"60653",
    "sg:province":"IL",
    "sg:tags":[
        "walker",
        "dog"
    ],
    "wof:name":"We Walk 'Em",
    "wof:placetype":"venue"
},
  "geometry": {"coordinates":[-87.601268,41.819592],"type":"Point"}
}