{
  "type": "Feature",
  "properties": {
    "iso:country":"US",
    "sg:address":"1528 Forever Ave",
    "sg:city":"Libertyville",
    "sg:classifiers":[
        {
            "category":"Airline",
            "type":"Transportation"
        }
    ],
    "sg:phone":"+1 847 362 9137",
    "sg:postcode":"60048",
    "sg:province":"IL",
    "sg:tags":[
        "nonscheduled",
        "air"
    ],
    "wof:name":"Vs Charter Service Ltd",
    "wof:placetype":"venue"
},
  "geometry": {"coordinates":[-87.990206,42.300921],"type":"Point"}
}