{
  "type": "Feature",
  "properties": {
    "addr:full":"200 Bourdelais Dr Belleville IL 62226",
    "addr:housenumber":"200",
    "addr:postcode":"62226",
    "addr:street":"Bourdelais Dr",
    "iso:country":"US",
    "sg:address":"200 Bourdelais Dr",
    "sg:city":"Belleville",
    "sg:classifiers":[
        {
            "category":"Health Services",
            "subcategory":"Doctor",
            "type":"Services"
        }
    ],
    "sg:phone":"+1 618 234 4695",
    "sg:postcode":"62226",
    "sg:province":"IL",
    "sg:tags":[
        "medical"
    ],
    "wof:name":"Grogan Communications Inc",
    "wof:placetype":"venue"
},
  "geometry": {"coordinates":[-89.993747,38.564751],"type":"Point"}
}