{
  "type": "Feature",
  "properties": {
    "iso:country":"US",
    "sg:address":"1871 Shady Oaks Rd",
    "sg:city":"Amboy",
    "sg:classifiers":[
        {
            "category":"Building & Trades",
            "subcategory":"Construction",
            "type":"Services"
        }
    ],
    "sg:phone":"+1 815 849 5187",
    "sg:postcode":"61310",
    "sg:province":"IL",
    "sg:tags":[
        "house",
        "contractor"
    ],
    "wof:name":"Flessner Construction Inc",
    "wof:placetype":"venue"
},
  "geometry": {"coordinates":[-89.261323,41.671355],"type":"Point"}
}