{
  "type": "Feature",
  "properties": {
    "iso:country":"US",
    "sg:address":"8616 Travis Ct",
    "sg:city":"Herrin",
    "sg:classifiers":[
        {
            "category":"Social Services",
            "subcategory":"Child Care",
            "type":"Services"
        }
    ],
    "sg:phone":"+1 618 942 7854",
    "sg:postcode":"62948",
    "sg:province":"IL",
    "sg:tags":[
        "day"
    ],
    "wof:name":"Sonya's Child Care",
    "wof:placetype":"venue"
},
  "geometry": {"coordinates":[-89.000936,37.803209],"type":"Point"}
}