{
  "type": "Feature",
  "properties": {
    "iso:country":"US",
    "sg:address":"13417 N 800th St",
    "sg:city":"Effingham",
    "sg:classifiers":[
        {
            "category":"Farming",
            "subcategory":"Livestock Farm",
            "type":"Manufacturing & Wholesale Goods"
        }
    ],
    "sg:phone":"+1 217 868 5149",
    "sg:postcode":"62401",
    "sg:province":"IL",
    "sg:tags":[
        "corn",
        "beef",
        "feedlot",
        "cattle"
    ],
    "wof:name":"Allan Soltwedel",
    "wof:placetype":"venue"
},
  "geometry": {"coordinates":[-88.65186,39.103253],"type":"Point"}
}