{
  "type": "Feature",
  "properties": {
    "iso:country":"US",
    "sg:address":"2869 83rd St",
    "sg:city":"Darien",
    "sg:classifiers":[
        {
            "category":"Health Services",
            "subcategory":"Doctor",
            "type":"Services"
        },
        {
            "category":"Health Services",
            "subcategory":"Chiropractor",
            "type":"Services"
        }
    ],
    "sg:phone":"+1 630 985 8602",
    "sg:postcode":"60561",
    "sg:province":"IL",
    "sg:tags":[
        "physician",
        "surgeon",
        "chiropractic"
    ],
    "wof:name":"Quirk L Lee DC DR",
    "wof:placetype":"venue"
},
  "geometry": {"coordinates":[-88.015502,41.736481],"type":"Point"}
}