{
  "type": "Feature",
  "properties": {
    "iso:country":"US",
    "sg:address":"216 W Front St",
    "sg:city":"Wheaton",
    "sg:classifiers":[
        {
            "category":"Personal",
            "type":"Services"
        },
        {
            "category":"Personal",
            "subcategory":"Shoe Repair & Shine",
            "type":"Services"
        },
        {
            "category":"Shopping",
            "subcategory":"Shoes",
            "type":"Retail Goods"
        }
    ],
    "sg:phone":"+1 630 665 2778",
    "sg:postcode":"60187",
    "sg:province":"IL",
    "sg:tags":[
        "sewing",
        "alteration",
        "store"
    ],
    "wof:name":"Wheaton Shoe Repair",
    "wof:placetype":"venue"
},
  "geometry": {"coordinates":[-88.1091,41.864899],"type":"Point"}
}