{
  "type": "Feature",
  "properties": {
    "iso:country":"US",
    "sg:address":"3703 James St Apt 3A",
    "sg:city":"Mchenry",
    "sg:classifiers":[
        {
            "category":"Professional",
            "subcategory":"Detective & Security Services",
            "type":"Services"
        }
    ],
    "sg:phone":"+1 815 578 4231",
    "sg:postcode":"60050",
    "sg:province":"IL",
    "sg:tags":[
        "information",
        "bureau"
    ],
    "wof:name":"Kevin Handyman Services",
    "wof:placetype":"venue"
},
  "geometry": {"coordinates":[-88.270409,42.340881],"type":"Point"}
}