{
  "type": "Feature",
  "properties": {
    "addr:full":"5974 Torch Lite Trl Loves Park IL 61111",
    "addr:housenumber":"5974",
    "addr:postcode":"61111",
    "addr:street":"Torch Lite Trl",
    "iso:country":"US",
    "sg:address":"5974 Torch Lite Trl",
    "sg:city":"Loves Park",
    "sg:classifiers":[
        {
            "category":"Autos & Motor Vehicles",
            "subcategory":"Automobile Sales",
            "type":"Retail Goods"
        }
    ],
    "sg:phone":"+1   ",
    "sg:postcode":"61111",
    "sg:province":"IL",
    "sg:tags":[
        "repair",
        "used",
        "general"
    ],
    "wof:name":"Autohaus",
    "wof:placetype":"venue"
},
  "geometry": {"coordinates":[-88.99578,42.334922],"type":"Point"}
}