{
  "type": "Feature",
  "properties": {
    "addr:full":"401 N West Ave Kankakee IL 60901",
    "addr:housenumber":"401",
    "addr:postcode":"60901",
    "addr:street":"N West Ave",
    "iso:country":"US",
    "sg:address":"401 N West Ave",
    "sg:city":"Kankakee",
    "sg:classifiers":[
        {
            "category":"Manufacturing",
            "subcategory":"Glass & Minerals",
            "type":"Manufacturing & Wholesale Goods"
        }
    ],
    "sg:phone":"+1 815 932 7491",
    "sg:postcode":"60901",
    "sg:province":"IL",
    "sg:tags":[
        "ready",
        "mixed",
        "mfg",
        "building",
        "concrete"
    ],
    "wof:name":"Raspolich Material Co",
    "wof:placetype":"venue"
},
  "geometry": {"coordinates":[-87.86543899999999,41.124451],"type":"Point"}
}