{
  "type": "Feature",
  "properties": {
    "addr:full":"40 N Ayer St Harvard IL 60033",
    "addr:housenumber":"40",
    "addr:postcode":"60033",
    "addr:street":"N Ayer St",
    "iso:country":"US",
    "sg:address":"40 N Ayer St",
    "sg:city":"Harvard",
    "sg:classifiers":[
        {
            "category":"Communications",
            "subcategory":"Newspaper",
            "type":"Services"
        }
    ],
    "sg:phone":"+1 815 943 4411",
    "sg:postcode":"60033",
    "sg:province":"IL",
    "wof:name":"Northwest Herald Service Center",
    "wof:placetype":"venue"
},
  "geometry": {"coordinates":[-88.61523699999999,42.420583],"type":"Point"}
}