{
  "type": "Feature",
  "properties": {
    "addr:full":"953 W Wise Rd Schaumburg IL 60193",
    "addr:housenumber":"953",
    "addr:postcode":"60193",
    "addr:street":"W Wise Rd",
    "iso:country":"US",
    "sg:address":"953 W Wise Rd",
    "sg:city":"Schaumburg",
    "sg:classifiers":[
        {
            "category":"Banks & Credit Unions",
            "subcategory":"Financial Services",
            "type":"Services"
        }
    ],
    "sg:phone":"+1 847 352 0238",
    "sg:postcode":"60193",
    "sg:province":"IL",
    "sg:tags":[
        "loan"
    ],
    "wof:name":"Ics Loans",
    "wof:placetype":"venue"
},
  "geometry": {"coordinates":[-88.103329,42.004448],"type":"Point"}
}