{
  "type": "Feature",
  "properties": {
    "addr:full":"1239 Parkside Ln Deerfield IL 60015",
    "addr:housenumber":"1239",
    "addr:postcode":"60015",
    "addr:street":"Parkside Ln",
    "iso:country":"US",
    "sg:address":"1239 Parkside Ln",
    "sg:city":"Deerfield",
    "sg:classifiers":[
        {
            "category":"Wholesale",
            "subcategory":"Durable Goods & Equipment",
            "type":"Manufacturing & Wholesale Goods"
        }
    ],
    "sg:phone":"+1 847 945 2991",
    "sg:postcode":"60015",
    "sg:province":"IL",
    "sg:tags":[
        "representative",
        "manufacturer"
    ],
    "wof:name":"Lotus Carpets",
    "wof:placetype":"venue"
},
  "geometry": {"coordinates":[-87.85421599999999,42.175132],"type":"Point"}
}