{
  "type": "Feature",
  "properties": {
    "addr:full":"4640 Hoffman Blvd Hoffman Estates IL 60192",
    "addr:housenumber":"4640",
    "addr:postcode":"60192",
    "addr:street":"Hoffman Blvd",
    "iso:country":"US",
    "sg:address":"4640 Hoffman Blvd",
    "sg:city":"Hoffman Estates",
    "sg:classifiers":[
        {
            "category":"Personal",
            "subcategory":"Beauty Salon",
            "type":"Services"
        },
        {
            "category":"Personal",
            "subcategory":"Barber",
            "type":"Services"
        }
    ],
    "sg:phone":"+1 847 645 9680",
    "sg:postcode":"60192",
    "sg:province":"IL",
    "sg:tags":[
        "hair"
    ],
    "sg:website":"www.greatclips.com",
    "wof:name":"Great Clips",
    "wof:placetype":"venue"
},
  "geometry": {"coordinates":[-88.19194400000001,42.069712],"type":"Point"}
}