{
  "type": "Feature",
  "properties": {
    "addr:full":"200 Danada Sq W Wheaton IL 60187",
    "addr:housenumber":"200",
    "addr:postcode":"60187",
    "addr:street":"Danada Sq W",
    "iso:country":"US",
    "sg:address":"200 Danada Sq W",
    "sg:city":"Wheaton",
    "sg:classifiers":[
        {
            "category":"Restaurant",
            "type":"Food & Drink"
        }
    ],
    "sg:phone":"+1   ",
    "sg:postcode":"60187",
    "sg:province":"IL",
    "sg:tags":[
        "eating"
    ],
    "wof:name":"Village Cof & Tea Shoppe Ltd",
    "wof:placetype":"venue"
},
  "geometry": {"coordinates":[-88.110035,41.832098],"type":"Point"}
}