{
  "type": "Feature",
  "properties": {
    "iso:country":"US",
    "sg:address":"803 Linder Blvd",
    "sg:city":"Greenville",
    "sg:classifiers":[
        {
            "category":"Organizations",
            "subcategory":"Religious Organization",
            "type":"Services"
        }
    ],
    "sg:phone":"+1 618 664 2294",
    "sg:postcode":"62246",
    "sg:province":"IL",
    "wof:name":"Herbert H Coates Reverend",
    "wof:placetype":"venue"
},
  "geometry": {"coordinates":[-89.386738,38.900409],"type":"Point"}
}