{
  "type": "Feature",
  "properties": {
    "addr:full":"18521 Spring Creek Dr Tinley Park IL 60477",
    "addr:housenumber":"18521",
    "addr:postcode":"60477",
    "addr:street":"Spring Creek Dr",
    "iso:country":"US",
    "sg:address":"18521 Spring Creek Dr",
    "sg:city":"Tinley Park",
    "sg:classifiers":[
        {
            "category":"Shopping",
            "subcategory":"Computers & Home Electronics",
            "type":"Retail Goods"
        }
    ],
    "sg:phone":"+1   ",
    "sg:postcode":"60477",
    "sg:province":"IL",
    "sg:tags":[
        "repair",
        "telephone"
    ],
    "wof:name":"Preferred Comm Systems Inc",
    "wof:placetype":"venue"
},
  "geometry": {"coordinates":[-87.796919,41.555677],"type":"Point"}
}