{
  "type": "Feature",
  "properties": {
    "addr:full":"1357 N Western Ave Chicago IL 60622",
    "addr:housenumber":"1357",
    "addr:postcode":"60622",
    "addr:street":"N Western Ave",
    "iso:country":"US",
    "sg:address":"1357 N Western Ave",
    "sg:city":"Chicago",
    "sg:classifiers":[
        {
            "category":"Restaurant",
            "type":"Food & Drink"
        }
    ],
    "sg:phone":"+1 773 276 5842",
    "sg:postcode":"60622",
    "sg:province":"IL",
    "wof:name":"Bismark Restaurant",
    "wof:placetype":"venue"
},
  "geometry": {"coordinates":[-87.68710299999999,41.905998],"type":"Point"}
}