{
  "type": "Feature",
  "properties": {
    "iso:country":"US",
    "sg:address":"6809 Barnard Mill Rd",
    "sg:city":"Ringwood",
    "sg:classifiers":[
        {
            "category":"Banks & Credit Unions",
            "subcategory":"Investment Brokerage",
            "type":"Services"
        },
        {
            "category":"Insurance",
            "subcategory":"Hazard Insurance",
            "type":"Services"
        }
    ],
    "sg:phone":"+1 815 728 0404",
    "sg:postcode":"60072",
    "sg:province":"IL",
    "sg:tags":[
        "agent",
        "resume"
    ],
    "wof:name":"Letizia Financial",
    "wof:placetype":"venue"
},
  "geometry": {"coordinates":[-88.331062,42.402996],"type":"Point"}
}