{
  "type": "Feature",
  "properties": {
    "iso:country":"US",
    "sg:address":"6771 11th St",
    "sg:city":"Rockford",
    "sg:classifiers":[
        {
            "category":"Government",
            "subcategory":"Office",
            "type":"Public Place"
        }
    ],
    "sg:phone":"+1   ",
    "sg:postcode":"61109",
    "sg:province":"IL",
    "sg:tags":[
        "town"
    ],
    "wof:name":"Village of New Milford",
    "wof:placetype":"venue"
},
  "geometry": {"coordinates":[-89.072049,42.187143],"type":"Point"}
}