{
  "type": "Feature",
  "properties": {
    "iso:country":"US",
    "sg:address":"6565 N Avondale Ave Ste 4",
    "sg:city":"Chicago",
    "sg:classifiers":[
        {
            "category":"Banks & Credit Unions",
            "subcategory":"Financial Services",
            "type":"Services"
        }
    ],
    "sg:phone":"+1 773 792 0000",
    "sg:postcode":"60631",
    "sg:province":"IL",
    "sg:tags":[
        "broker",
        "mortgage"
    ],
    "wof:name":"Integra Financial Group Inc",
    "wof:placetype":"venue"
},
  "geometry": {"coordinates":[-87.81487300000001,41.999864],"type":"Point"}
}