{
  "type": "Feature",
  "properties": {
    "iso:country":"US",
    "sg:address":"5329 Meadow Ln",
    "sg:city":"Downers Grove",
    "sg:classifiers":[
        {
            "category":"Professional",
            "type":"Services"
        }
    ],
    "sg:phone":"+1 630 515 0482",
    "sg:postcode":"60515",
    "sg:province":"IL",
    "sg:tags":[
        "consulting"
    ],
    "wof:name":"Robert Deyoung",
    "wof:placetype":"venue"
},
  "geometry": {"coordinates":[-88.017652,41.789625],"type":"Point"}
}