{
  "type": "Feature",
  "properties": {
    "iso:country":"US",
    "sg:address":"943 E 192nd Pl",
    "sg:city":"Glenwood",
    "sg:classifiers":[
        {
            "category":"Autos & Motor Vehicles",
            "subcategory":"Automobile Sales",
            "type":"Retail Goods"
        }
    ],
    "sg:phone":"+1 708 758 5466",
    "sg:postcode":"60425",
    "sg:province":"IL",
    "sg:tags":[
        "limo"
    ],
    "wof:name":"Butler Limousine",
    "wof:placetype":"venue"
},
  "geometry": {"coordinates":[-87.58850099999999,41.539001],"type":"Point"}
}