{
  "type": "Feature",
  "properties": {
    "iso:country":"US",
    "sg:address":"1117 S Oak St",
    "sg:city":"Champaign",
    "sg:classifiers":[
        {
            "category":"Professional",
            "type":"Services"
        }
    ],
    "sg:phone":"+1 217 337 1405",
    "sg:postcode":"61820",
    "sg:province":"IL",
    "sg:tags":[
        "establishment"
    ],
    "wof:name":"Frank Lill & Sons Inc",
    "wof:placetype":"venue"
},
  "geometry": {"coordinates":[-88.241591,40.104337],"type":"Point"}
}