{
  "type": "Feature",
  "properties": {
    "iso:country":"US",
    "sg:address":"2209 Highland Ave",
    "sg:city":"Berwyn",
    "sg:classifiers":[
        {
            "category":"Real Estate",
            "subcategory":"Real Estate Services",
            "type":"Services"
        },
        {
            "category":"Banks & Credit Unions",
            "subcategory":"Financial Services",
            "type":"Services"
        }
    ],
    "sg:phone":"+1 708 484 9752",
    "sg:postcode":"60402",
    "sg:province":"IL",
    "sg:tags":[
        "financing",
        "loan",
        "mortgage"
    ],
    "wof:name":"My Home Loan Rescuer & Tax Service Inc",
    "wof:placetype":"venue"
},
  "geometry": {"coordinates":[-87.78105600000001,41.850545],"type":"Point"}
}