{
  "type": "Feature",
  "properties": {
    "addr:full":"739 Roosevelt Rd Glen Ellyn IL 60137",
    "addr:housenumber":"739",
    "addr:postcode":"60137",
    "addr:street":"Roosevelt Rd",
    "iso:country":"US",
    "sg:address":"739 Roosevelt Rd",
    "sg:city":"Glen Ellyn",
    "sg:classifiers":[
        {
            "category":"Social Services",
            "subcategory":"Child Care",
            "type":"Services"
        }
    ],
    "sg:phone":"+1 630 790 8137",
    "sg:postcode":"60137",
    "sg:province":"IL",
    "sg:tags":[
        "day"
    ],
    "wof:name":"Child Care Referral Services",
    "wof:placetype":"venue"
},
  "geometry": {"coordinates":[-88.056099,41.859402],"type":"Point"}
}