{
  "type": "Feature",
  "properties": {
    "iso:country":"US",
    "sg:address":"18 S Northwest Hwy",
    "sg:city":"Park Ridge",
    "sg:classifiers":[
        {
            "category":"Professional",
            "subcategory":"Computer Services",
            "type":"Services"
        }
    ],
    "sg:phone":"+1 847 275 5525",
    "sg:postcode":"60068",
    "sg:province":"IL",
    "sg:tags":[
        "design",
        "system"
    ],
    "wof:name":"Watermark Solutions",
    "wof:placetype":"venue"
},
  "geometry": {"coordinates":[-87.828243,42.01038],"type":"Point"}
}