{
  "type": "Feature",
  "properties": {
    "iso:country":"US",
    "sg:address":"662 E 2053rd Ln",
    "sg:city":"Liberty",
    "sg:classifiers":[
        {
            "category":"Farming",
            "subcategory":"Dairy Farm",
            "type":"Manufacturing & Wholesale Goods"
        }
    ],
    "sg:phone":"+1 217 645 3289",
    "sg:postcode":"62347",
    "sg:province":"IL",
    "wof:name":"PR Farms",
    "wof:placetype":"venue"
},
  "geometry": {"coordinates":[-91.116587,39.858396],"type":"Point"}
}