{
  "type": "Feature",
  "properties": {
    "iso:country":"US",
    "sg:address":"709 N Milwaukee Ave",
    "sg:city":"Libertyville",
    "sg:classifiers":[
        {
            "category":"Insurance",
            "subcategory":"Insurance Agent",
            "type":"Services"
        }
    ],
    "sg:phone":"+1 847 362 2555",
    "sg:postcode":"60048",
    "sg:province":"IL",
    "sg:tags":[
        "agency"
    ],
    "wof:name":"Market Financial",
    "wof:placetype":"venue"
},
  "geometry": {"coordinates":[-87.954771,42.289992],"type":"Point"}
}