{
  "type": "Feature",
  "properties": {
    "iso:country":"US",
    "sg:address":"831 S 4th St",
    "sg:city":"Dekalb",
    "sg:classifiers":[
        {
            "category":"Restaurant",
            "type":"Food & Drink"
        }
    ],
    "sg:phone":"+1 815 754 2090",
    "sg:postcode":"60115",
    "sg:province":"IL",
    "sg:tags":[
        "style",
        "american",
        "family"
    ],
    "wof:name":"Zack's Family Restaurant",
    "wof:placetype":"venue"
},
  "geometry": {"coordinates":[-88.75344800000001,41.921311],"type":"Point"}
}