{
  "type": "Feature",
  "properties": {
    "addr:full":"1897 Cheshire Ln Wheaton IL 60187",
    "addr:housenumber":"1897",
    "addr:postcode":"60187",
    "addr:street":"Cheshire Ln",
    "iso:country":"US",
    "sg:address":"1897 Cheshire Ln",
    "sg:city":"Wheaton",
    "sg:classifiers":[
        {
            "category":"Building & Trades",
            "subcategory":"Construction",
            "type":"Services"
        }
    ],
    "sg:phone":"+1 630 690 7151",
    "sg:postcode":"60187",
    "sg:province":"IL",
    "sg:tags":[
        "hanging",
        "contractor"
    ],
    "wof:name":"Van Kampen Decorating",
    "wof:placetype":"venue"
},
  "geometry": {"coordinates":[-88.08241700000001,41.836565],"type":"Point"}
}