{
  "type": "Feature",
  "properties": {
    "addr:full":"2701 W 63rd St Chicago IL 60629",
    "addr:housenumber":"2701",
    "addr:postcode":"60629",
    "addr:street":"W 63Rd St",
    "iso:country":"US",
    "sg:address":"2701 W 63rd St",
    "sg:city":"Chicago",
    "sg:classifiers":[
        {
            "category":"Retail",
            "subcategory":"Funeral Services",
            "type":"Services"
        }
    ],
    "sg:phone":"+1 773 434 2400",
    "sg:postcode":"60629",
    "sg:province":"IL",
    "sg:tags":[
        "director",
        "plans-pre-arranged",
        "supply"
    ],
    "sg:website":"http://www.jacksonfuneralhome.com",
    "wof:name":"W W Jackson Funeral Home",
    "wof:placetype":"venue"
},
  "geometry": {"coordinates":[-87.69096399999999,41.779148],"type":"Point"}
}