{
  "type": "Feature",
  "properties": {
    "addr:full":"640 S Washington St Hinsdale IL 60521",
    "addr:housenumber":"640",
    "addr:postcode":"60521",
    "addr:street":"S Washington St",
    "iso:country":"US",
    "sg:address":"640 S Washington St",
    "sg:city":"Hinsdale",
    "sg:classifiers":[
        {
            "category":"Professional",
            "subcategory":"Business Services",
            "type":"Services"
        }
    ],
    "sg:phone":"+1 630 325 4996",
    "sg:postcode":"60521",
    "sg:province":"IL",
    "sg:tags":[
        "auction"
    ],
    "wof:name":"Ptm Auctions",
    "wof:placetype":"venue"
},
  "geometry": {"coordinates":[-87.92897600000001,41.79533],"type":"Point"}
}