{
  "type": "Feature",
  "properties": {
    "addr:full":"3601 W Grand Ave Chicago IL 60651",
    "addr:housenumber":"3601",
    "addr:postcode":"60651",
    "addr:street":"W Grand Ave",
    "iso:country":"US",
    "sg:address":"3601 W Grand Ave",
    "sg:city":"Chicago",
    "sg:classifiers":[
        {
            "category":"Food & Beverages",
            "subcategory":"Groceries & Convenience Stores",
            "type":"Retail Goods"
        }
    ],
    "sg:phone":"+1 773 292 6004",
    "sg:postcode":"60651",
    "sg:province":"IL",
    "wof:name":"Grand Avenue Station",
    "wof:placetype":"venue"
},
  "geometry": {"coordinates":[-87.7166,41.902133],"type":"Point"}
}