{
  "type": "Feature",
  "properties": {
    "addr:full":"3205 W Southmor Rd Morris IL 60450",
    "addr:housenumber":"3205",
    "addr:postcode":"60450",
    "addr:street":"W Southmor Rd",
    "iso:country":"US",
    "sg:address":"3205 W Southmor Rd",
    "sg:city":"Morris",
    "sg:classifiers":[
        {
            "category":"Banks & Credit Unions",
            "subcategory":"Financial Services",
            "type":"Services"
        }
    ],
    "sg:phone":"+1 815 942 0900",
    "sg:postcode":"60450",
    "sg:province":"IL",
    "sg:tags":[
        "company",
        "holding"
    ],
    "wof:name":"All Seasons Development Corp",
    "wof:placetype":"venue"
},
  "geometry": {"coordinates":[-88.48161,41.326983],"type":"Point"}
}