{
  "type": "Feature",
  "properties": {
    "iso:country":"US",
    "sg:address":"129 Caroline Ct",
    "sg:city":"Geneva",
    "sg:classifiers":[
        {
            "category":"Building & Trades",
            "subcategory":"Cleaning & Sanitation",
            "type":"Services"
        }
    ],
    "sg:phone":"+1 630 845 8622",
    "sg:postcode":"60134",
    "sg:province":"IL",
    "sg:tags":[
        "janitor",
        "maintenance"
    ],
    "wof:name":"Superior Maintenance Service",
    "wof:placetype":"venue"
},
  "geometry": {"coordinates":[-88.290524,41.884278],"type":"Point"}
}