{
  "type": "Feature",
  "properties": {
    "addr:full":"110 Hunters Path Lake In The Hls IL 60156",
    "addr:housenumber":"110",
    "addr:postcode":"60156",
    "addr:street":"Hunters Path",
    "iso:country":"US",
    "sg:address":"110 Hunters Path",
    "sg:city":"Lake In The Hls",
    "sg:classifiers":[
        {
            "category":"Building & Trades",
            "subcategory":"Construction",
            "type":"Services"
        }
    ],
    "sg:phone":"+1 847 458 8464",
    "sg:postcode":"60156",
    "sg:province":"IL",
    "sg:tags":[
        "general",
        "contractor"
    ],
    "wof:name":"Able Builders",
    "wof:placetype":"venue"
},
  "geometry": {"coordinates":[-88.32505,42.17977],"type":"Point"}
}