{
  "type": "Feature",
  "properties": {
    "addr:full":"323 E Garfield Blvd Chicago IL 60637",
    "addr:housenumber":"323",
    "addr:postcode":"60637",
    "addr:street":"E Garfield Blvd",
    "iso:country":"US",
    "sg:address":"323 E Garfield Blvd",
    "sg:city":"Chicago",
    "sg:classifiers":[
        {
            "category":"Fast Food",
            "type":"Food & Drink"
        }
    ],
    "sg:phone":"+1 773 753 0233",
    "sg:postcode":"60637",
    "sg:province":"IL",
    "wof:name":"Fast Food Neals",
    "wof:placetype":"venue"
},
  "geometry": {"coordinates":[-87.61823200000001,41.794335],"type":"Point"}
}