{
  "type": "Feature",
  "properties": {
    "iso:country":"US",
    "sg:address":"11253 Endicott Ct",
    "sg:city":"Orland Park",
    "sg:classifiers":[
        {
            "category":"Professional",
            "subcategory":"Business Services",
            "type":"Services"
        }
    ],
    "sg:phone":"+1 708 873 1098",
    "sg:postcode":"60467",
    "sg:province":"IL",
    "sg:tags":[
        "translation"
    ],
    "wof:name":"3 Star Translators LLC",
    "wof:placetype":"venue"
},
  "geometry": {"coordinates":[-87.89464599999999,41.630172],"type":"Point"}
}