{
  "type": "Feature",
  "properties": {
    "addr:full":"904 St Louis Ave East St Louis IL 62201",
    "addr:housenumber":"904",
    "addr:postcode":"62201",
    "addr:street":"St Louis Ave",
    "iso:country":"US",
    "sg:address":"904 St Louis Ave",
    "sg:city":"East St Louis",
    "sg:classifiers":[
        {
            "category":"Personal",
            "subcategory":"Barber",
            "type":"Services"
        }
    ],
    "sg:phone":"+1 618 875 3379",
    "sg:postcode":"62201",
    "sg:province":"IL",
    "wof:name":"Hair Connection",
    "wof:placetype":"venue"
},
  "geometry": {"coordinates":[-90.15246500000001,38.62337],"type":"Point"}
}