{
  "type": "Feature",
  "properties": {
    "iso:country":"US",
    "sg:address":"4005 W Kane Ave Ste H",
    "sg:city":"Mchenry",
    "sg:classifiers":[
        {
            "category":"Real Estate",
            "subcategory":"Real Estate Agent",
            "type":"Services"
        }
    ],
    "sg:phone":"+1 815 385 6770",
    "sg:postcode":"60050",
    "sg:province":"IL",
    "wof:name":"Re/Max Plaza",
    "wof:placetype":"venue"
},
  "geometry": {"coordinates":[-88.276392,42.337907],"type":"Point"}
}