{
  "type": "Feature",
  "properties": {
    "addr:full":"271 E 159th St Harvey IL 60426",
    "addr:housenumber":"271",
    "addr:postcode":"60426",
    "addr:street":"E 159Th St",
    "iso:country":"US",
    "sg:address":"271 E 159th St",
    "sg:city":"Harvey",
    "sg:classifiers":[
        {
            "category":"Restaurant",
            "type":"Food & Drink"
        }
    ],
    "sg:phone":"+1 708 331 8906",
    "sg:postcode":"60426",
    "sg:province":"IL",
    "wof:name":"International Food Service Restrnt",
    "wof:placetype":"venue"
},
  "geometry": {"coordinates":[-87.640602,41.600899],"type":"Point"}
}