{
  "type": "Feature",
  "properties": {
    "iso:country":"US",
    "sg:address":"611 E State St",
    "sg:city":"Jacksonville",
    "sg:classifiers":[
        {
            "category":"Communications",
            "subcategory":"Film & Video Production",
            "type":"Services"
        }
    ],
    "sg:phone":"+1 217 243 4567",
    "sg:postcode":"62650",
    "sg:province":"IL",
    "sg:tags":[
        "distribution"
    ],
    "wof:name":"New Dimension Films",
    "wof:placetype":"venue"
},
  "geometry": {"coordinates":[-90.219155,39.734133],"type":"Point"}
}