{
  "type": "Feature",
  "properties": {
    "iso:country":"US",
    "sg:address":"105 5th St",
    "sg:city":"Colona",
    "sg:classifiers":[
        {
            "category":"Building & Trades",
            "subcategory":"Construction",
            "type":"Services"
        }
    ],
    "sg:phone":"+1 309 796 0871",
    "sg:postcode":"61241",
    "sg:province":"IL",
    "sg:tags":[
        "repairing",
        "lane",
        "refinishing",
        "bowling"
    ],
    "wof:name":"Midwest Bowling Supply",
    "wof:placetype":"venue"
},
  "geometry": {"coordinates":[-90.363891,41.481845],"type":"Point"}
}