{
  "type": "Feature",
  "properties": {
    "iso:country":"US",
    "sg:address":"2184 N. Elston",
    "sg:city":"Chicago",
    "sg:classifiers":[
        {
            "category":"Shopping",
            "subcategory":"Hobbies, Toys, & Games",
            "type":"Retail Goods"
        }
    ],
    "sg:phone":"+1 773 489 1264",
    "sg:postcode":"60614",
    "sg:province":"IL",
    "sg:tags":[
        "shop",
        "hobby"
    ],
    "sg:website":"www.chicagocostume.com",
    "wof:name":"Chicago Costume Company",
    "wof:placetype":"venue"
},
  "geometry": {"coordinates":[-87.671935,41.921224],"type":"Point"}
}