{
  "type": "Feature",
  "properties": {
    "iso:country":"US",
    "sg:address":"3055 Koepke Rd",
    "sg:city":"Northbrook",
    "sg:classifiers":[
        {
            "category":"Shopping",
            "subcategory":"Hobbies, Toys, & Games",
            "type":"Retail Goods"
        }
    ],
    "sg:phone":"+1   ",
    "sg:postcode":"60062",
    "sg:province":"IL",
    "wof:name":"The Toy Box",
    "wof:placetype":"venue"
},
  "geometry": {"coordinates":[-87.855072,42.12196],"type":"Point"}
}