{
  "type": "Feature",
  "properties": {
    "addr:full":"4912 Northwest Hwy Crystal Lake IL 60014",
    "addr:housenumber":"4912",
    "addr:postcode":"60014",
    "addr:street":"Northwest Hwy",
    "iso:country":"US",
    "sg:address":"4912 Northwest Hwy",
    "sg:city":"Crystal Lake",
    "sg:classifiers":[
        {
            "category":"Restaurant",
            "type":"Food & Drink"
        }
    ],
    "sg:menulink":"http://www.allmenus.com/il/algonquin/104623-noodles--company/menu/",
    "sg:phone":"+1 815 459 4400",
    "sg:postcode":"60014",
    "sg:province":"IL",
    "sg:tags":[
        "noodle",
        "bar",
        "salad",
        "chinese",
        "japanese",
        "soup",
        "american",
        "asian",
        "thai",
        "italian"
    ],
    "wof:name":"Noodles & Company",
    "wof:placetype":"venue"
},
  "geometry": {"coordinates":[-88.29310099999999,42.226667],"type":"Point"}
}