{
  "type": "Feature",
  "properties": {
    "iso:country":"US",
    "sg:address":"1329 Fountain Green Dr",
    "sg:city":"Crystal Lake",
    "sg:classifiers":[
        {
            "category":"Professional",
            "subcategory":"Computer Services",
            "type":"Services"
        }
    ],
    "sg:phone":"+1 815 788 9681",
    "sg:postcode":"60014",
    "sg:province":"IL",
    "sg:tags":[
        "datum"
    ],
    "wof:name":"Oswald Enterprises",
    "wof:placetype":"venue"
},
  "geometry": {"coordinates":[-88.340975,42.202115],"type":"Point"}
}