{
  "type": "Feature",
  "properties": {
    "addr:full":"812 Warrington Ave Danville IL 61832",
    "addr:housenumber":"812",
    "addr:postcode":"61832",
    "addr:street":"Warrington Ave",
    "iso:country":"US",
    "sg:address":"812 Warrington Ave",
    "sg:city":"Danville",
    "sg:classifiers":[
        {
            "category":"Building & Trades",
            "subcategory":"Cleaning & Sanitation",
            "type":"Services"
        }
    ],
    "sg:phone":"+1 217 443 4915",
    "sg:postcode":"61832",
    "sg:province":"IL",
    "sg:tags":[
        "maintenance"
    ],
    "wof:name":"Your-Rite Cleaning Services",
    "wof:placetype":"venue"
},
  "geometry": {"coordinates":[-87.658883,40.125248],"type":"Point"}
}