{
  "type": "Feature",
  "properties": {
    "addr:full":"450 S Cips St Watseka IL 60970",
    "addr:housenumber":"450",
    "addr:postcode":"60970",
    "addr:street":"S Cips St",
    "iso:country":"US",
    "sg:address":"450 S Cips St",
    "sg:city":"Watseka",
    "sg:classifiers":[
        {
            "category":"Manufacturing",
            "subcategory":"Metals",
            "type":"Manufacturing & Wholesale Goods"
        }
    ],
    "sg:phone":"+1 815 432 2125",
    "sg:postcode":"60970",
    "sg:province":"IL",
    "sg:tags":[
        "stamping"
    ],
    "wof:name":"T D Metal Products",
    "wof:placetype":"venue"
},
  "geometry": {"coordinates":[-87.738747,40.77026],"type":"Point"}
}