{
  "type": "Feature",
  "properties": {
    "iso:country":"US",
    "sg:address":"20 Savannah Ct",
    "sg:city":"Belleville",
    "sg:classifiers":[
        {
            "category":"Building & Trades",
            "subcategory":"Plumbing",
            "type":"Services"
        }
    ],
    "sg:phone":"+1 618 239 9122",
    "sg:postcode":"62221",
    "sg:province":"IL",
    "sg:tags":[
        "heating",
        "contractor"
    ],
    "wof:name":"Maintenance Man Svc & Repair",
    "wof:placetype":"venue"
},
  "geometry": {"coordinates":[-89.93941,38.513329],"type":"Point"}
}