{
  "type": "Feature",
  "properties": {
    "addr:full":"1840 Industrial Dr Libertyville IL 60048",
    "addr:housenumber":"1840",
    "addr:postcode":"60048",
    "addr:street":"Industrial Dr",
    "iso:country":"US",
    "sg:address":"1840 Industrial Dr",
    "sg:city":"Libertyville",
    "sg:classifiers":[
        {
            "category":"Manufacturing",
            "subcategory":"Chemicals & Compounds",
            "type":"Manufacturing & Wholesale Goods"
        }
    ],
    "sg:phone":"+1 847 918 9018",
    "sg:postcode":"60048",
    "sg:province":"IL",
    "sg:tags":[
        "inorganic",
        "industrial",
        "commercial",
        "physical",
        "mfg"
    ],
    "wof:name":"Pharmasyn Inc",
    "wof:placetype":"venue"
},
  "geometry": {"coordinates":[-88.007251,42.307715],"type":"Point"}
}