{
  "type": "Feature",
  "properties": {
    "iso:country":"US",
    "sg:address":"1437 W Highland Ave",
    "sg:city":"Chicago",
    "sg:classifiers":[
        {
            "category":"Professional",
            "subcategory":"Business Services",
            "type":"Services"
        }
    ],
    "sg:phone":"+1 773 761 0459",
    "sg:postcode":"60660",
    "sg:province":"IL",
    "wof:name":"Celinda B Benavides",
    "wof:placetype":"venue"
},
  "geometry": {"coordinates":[-87.667624,41.997216],"type":"Point"}
}