{
  "type": "Feature",
  "properties": {
    "iso:country":"US",
    "sg:address":"350 N Eric Dr",
    "sg:city":"Palatine",
    "sg:classifiers":[
        {
            "category":"Shopping",
            "subcategory":"Jewelry",
            "type":"Retail Goods"
        }
    ],
    "sg:phone":"+1 847 359 8999",
    "sg:postcode":"60067",
    "sg:province":"IL",
    "sg:tags":[
        "item",
        "emblematic"
    ],
    "wof:name":"Young Thomas",
    "wof:placetype":"venue"
},
  "geometry": {"coordinates":[-88.051818,42.117597],"type":"Point"}
}