{
  "type": "Feature",
  "properties": {
    "addr:full":"12905 N State Rte 40 Dunlap IL 61525",
    "addr:housenumber":"12905",
    "addr:postcode":"61525",
    "addr:street":"N State Rte 40",
    "iso:country":"US",
    "sg:address":"12905 N State Rte 40",
    "sg:city":"Dunlap",
    "sg:classifiers":[
        {
            "category":"Retail",
            "subcategory":"Repair Shop",
            "type":"Services"
        }
    ],
    "sg:phone":"+1 309 686 8030",
    "sg:postcode":"61525",
    "sg:province":"IL",
    "wof:name":"Mikes Lock & Key Serv",
    "wof:placetype":"venue"
},
  "geometry": {"coordinates":[-89.627925,40.847255],"type":"Point"}
}