{
  "type": "Feature",
  "properties": {
    "addr:full":"6715 W State St Rockford IL 61102",
    "addr:housenumber":"6715",
    "addr:postcode":"61102",
    "addr:street":"W State St",
    "iso:country":"US",
    "sg:address":"6715 W State St",
    "sg:city":"Rockford",
    "sg:classifiers":[
        {
            "category":"Manufacturing",
            "subcategory":"Rubber & Plastics",
            "type":"Manufacturing & Wholesale Goods"
        }
    ],
    "sg:phone":"+1 815 963 4465",
    "sg:postcode":"61102",
    "sg:province":"IL",
    "sg:tags":[
        "product"
    ],
    "wof:name":"Rockford Central Plastics",
    "wof:placetype":"venue"
},
  "geometry": {"coordinates":[-89.16487499999999,42.278863],"type":"Point"}
}