{
  "type": "Feature",
  "properties": {
    "addr:full":"211 W Morris St Elwood IL 60421",
    "addr:housenumber":"211",
    "addr:postcode":"60421",
    "addr:street":"W Morris St",
    "iso:country":"US",
    "sg:address":"211 W Morris St",
    "sg:city":"Elwood",
    "sg:classifiers":[
        {
            "category":"Manufacturing",
            "subcategory":"Tools & Machinery",
            "type":"Manufacturing & Wholesale Goods"
        },
        {
            "category":"Retail",
            "subcategory":"Laundry & Dry Cleaning",
            "type":"Services"
        },
        {
            "category":"Industrial Area",
            "type":"Public Place"
        },
        {
            "category":"Building & Trades",
            "subcategory":"Construction",
            "type":"Services"
        },
        {
            "category":"Building & Trades",
            "subcategory":"Cleaning & Sanitation",
            "type":"Services"
        }
    ],
    "sg:phone":"+1 815 423 2080",
    "sg:postcode":"60421",
    "sg:province":"IL",
    "sg:tags":[
        "cleaner",
        "machinery-rebuild",
        "house",
        "system",
        "specialty",
        "heating",
        "air conditioning",
        "contractor",
        "repair",
        "equipment-repairing"
    ],
    "sg:website":"http://www.airwizards.com",
    "wof:name":"Air Wizards Heating & A/C Inc",
    "wof:placetype":"venue"
},
  "geometry": {"coordinates":[-88.11388700000001,41.401866],"type":"Point"}
}