{
  "type": "Feature",
  "properties": {
    "iso:country":"US",
    "sg:address":"228 E Wilson St",
    "sg:city":"Batavia",
    "sg:classifiers":[
        {
            "category":"Professional",
            "subcategory":"Lawyer & Legal Services",
            "type":"Services"
        }
    ],
    "sg:phone":"+1 630 879 8550",
    "sg:postcode":"60510",
    "sg:province":"IL",
    "sg:tags":[
        "attorney"
    ],
    "wof:name":"Ralph S Beck",
    "wof:placetype":"venue"
},
  "geometry": {"coordinates":[-88.303388,41.849955],"type":"Point"}
}