{
  "type": "Feature",
  "properties": {
    "addr:full":"5988 N High Ridge Rd Galena IL 61036",
    "addr:housenumber":"5988",
    "addr:postcode":"61036",
    "addr:street":"N High Ridge Rd",
    "iso:country":"US",
    "sg:address":"5988 N High Ridge Rd",
    "sg:city":"Galena",
    "sg:classifiers":[
        {
            "category":"Building & Trades",
            "subcategory":"Construction",
            "type":"Services"
        }
    ],
    "sg:phone":"+1 815 777 2691",
    "sg:postcode":"61036",
    "sg:province":"IL",
    "sg:tags":[
        "road",
        "contractor"
    ],
    "wof:name":"Highway Dept Garage",
    "wof:placetype":"venue"
},
  "geometry": {"coordinates":[-90.46190900000001,42.460305],"type":"Point"}
}