{
  "type": "Feature",
  "properties": {
    "iso:country":"US",
    "sg:address":"6430 Cermak Rd",
    "sg:city":"Berwyn",
    "sg:classifiers":[
        {
            "category":"Health Services",
            "subcategory":"Health Practitioner",
            "type":"Services"
        },
        {
            "category":"Health Services",
            "subcategory":"Chiropractor",
            "type":"Services"
        }
    ],
    "sg:phone":"+1 708 749 0100",
    "sg:postcode":"60402",
    "sg:province":"IL",
    "sg:tags":[
        "acupuncture"
    ],
    "sg:website":"www.drbrucerachum.com",
    "wof:name":"Dr. Bruce Rachum",
    "wof:placetype":"venue"
},
  "geometry": {"coordinates":[-87.785241,41.850777],"type":"Point"}
}