{
  "type": "Feature",
  "properties": {
    "addr:full":"5995 State Rte 75 E Dakota IL 61018",
    "addr:housenumber":"5995",
    "addr:postcode":"61018",
    "addr:street":"State Rte 75 E",
    "iso:country":"US",
    "sg:address":"5995 State Rte 75 E",
    "sg:city":"Dakota",
    "sg:classifiers":[
        {
            "category":"Wholesale",
            "subcategory":"Farm Supplies",
            "type":"Manufacturing & Wholesale Goods"
        }
    ],
    "sg:phone":"+1 815 449 2215",
    "sg:postcode":"61018",
    "sg:province":"IL",
    "sg:tags":[
        "livestock"
    ],
    "wof:name":"Schrader Marketing Ctr",
    "wof:placetype":"venue"
},
  "geometry": {"coordinates":[-89.50487,42.404282],"type":"Point"}
}