{
  "type": "Feature",
  "properties": {
    "addr:full":"519 State Ave Hampton IL 61256",
    "addr:housenumber":"519",
    "addr:postcode":"61256",
    "addr:street":"State Ave",
    "iso:country":"US",
    "sg:address":"519 State Ave",
    "sg:city":"Hampton",
    "sg:classifiers":[
        {
            "category":"Retail",
            "subcategory":"Auto Repair",
            "type":"Services"
        }
    ],
    "sg:phone":"+1 309 278 0366",
    "sg:postcode":"61256",
    "sg:province":"IL",
    "sg:tags":[
        "body",
        "shop"
    ],
    "wof:name":"Advantage Autobody",
    "wof:placetype":"venue"
},
  "geometry": {"coordinates":[-90.409762,41.554706],"type":"Point"}
}