{
  "type": "Feature",
  "properties": {
    "iso:country":"US",
    "sg:address":"2183 Strawn Crossing Rd",
    "sg:city":"Jacksonville",
    "sg:classifiers":[
        {
            "category":"Structure",
            "subcategory":"Warehouse",
            "type":"Public Place"
        },
        {
            "category":"Retail",
            "subcategory":"Storage",
            "type":"Services"
        }
    ],
    "sg:phone":"+1 217 245 0677",
    "sg:postcode":"62650",
    "sg:province":"IL",
    "sg:tags":[
        "commercial",
        "self",
        "warehouses-merchandise",
        "household"
    ],
    "wof:name":"Dobson Storage",
    "wof:placetype":"venue"
},
  "geometry": {"coordinates":[-90.193047,39.759281],"type":"Point"}
}