{
  "type": "Feature",
  "properties": {
    "iso:country":"US",
    "sg:address":"2428 Stokebridge Rd",
    "sg:city":"Springfield",
    "sg:classifiers":[
        {
            "category":"Professional",
            "subcategory":"Computer Services",
            "type":"Services"
        }
    ],
    "sg:phone":"+1 217 341 1900",
    "sg:postcode":"62702",
    "sg:province":"IL",
    "sg:tags":[
        "technical",
        "assistance",
        "support"
    ],
    "wof:name":"Alegna Consultants, The",
    "wof:placetype":"venue"
},
  "geometry": {"coordinates":[-89.618716,39.826088],"type":"Point"}
}