{
  "type": "Feature",
  "properties": {
    "addr:full":"8903 Moore Dr Bridgeview IL 60455",
    "addr:housenumber":"8903",
    "addr:postcode":"60455",
    "addr:street":"Moore Dr",
    "iso:country":"US",
    "sg:address":"8903 Moore Dr",
    "sg:city":"Bridgeview",
    "sg:classifiers":[
        {
            "category":"Retail",
            "subcategory":"Auto Repair",
            "type":"Services"
        }
    ],
    "sg:phone":"+1 708 430 4957",
    "sg:postcode":"60455",
    "sg:province":"IL",
    "wof:name":"Auto Tech",
    "wof:placetype":"venue"
},
  "geometry": {"coordinates":[-87.801666,41.729195],"type":"Point"}
}