{
  "type": "Feature",
  "properties": {
    "iso:country":"US",
    "sg:address":"803 Joliet Rd",
    "sg:city":"La Grange",
    "sg:classifiers":[
        {
            "category":"Restaurant",
            "type":"Food & Drink"
        }
    ],
    "sg:menulink":"http://www.allmenus.com/il/lyons/22226-the-flame/menu/",
    "sg:phone":"+1 708 352 3442",
    "sg:postcode":"60525",
    "sg:province":"IL",
    "sg:tags":[
        "american"
    ],
    "wof:name":"The Flame",
    "wof:placetype":"venue"
},
  "geometry": {"coordinates":[-87.87847499999999,41.774384],"type":"Point"}
}