{
  "type": "Feature",
  "properties": {
    "addr:full":"4900 W Cermak Rd Cicero IL 60804",
    "addr:housenumber":"4900",
    "addr:postcode":"60804",
    "addr:street":"W Cermak Rd",
    "iso:country":"US",
    "sg:address":"4900 W Cermak Rd",
    "sg:city":"Cicero",
    "sg:classifiers":[
        {
            "category":"Food & Beverages",
            "subcategory":"Specialty",
            "type":"Retail Goods"
        }
    ],
    "sg:phone":"+1   ",
    "sg:postcode":"60804",
    "sg:province":"IL",
    "wof:name":"Health Store New Life",
    "wof:placetype":"venue"
},
  "geometry": {"coordinates":[-87.74917499999999,41.851268],"type":"Point"}
}