{
  "type": "Feature",
  "properties": {
    "addr:full":"316 Republic Ave Joliet IL 60435",
    "addr:housenumber":"316",
    "addr:postcode":"60435",
    "addr:street":"Republic Ave",
    "iso:country":"US",
    "sg:address":"316 Republic Ave",
    "sg:city":"Joliet",
    "sg:classifiers":[
        {
            "category":"Home & Garden",
            "subcategory":"Garden Supply",
            "type":"Retail Goods"
        }
    ],
    "sg:phone":"+1   ",
    "sg:postcode":"60435",
    "sg:province":"IL",
    "sg:tags":[
        "hardware",
        "lawnmowers"
    ],
    "wof:name":"Ace Lawn & Vacuum",
    "wof:placetype":"venue"
},
  "geometry": {"coordinates":[-88.138981,41.523778],"type":"Point"}
}