{
  "type": "Feature",
  "properties": {
    "iso:country":"US",
    "sg:address":"5454 W Washington St",
    "sg:city":"Colona",
    "sg:classifiers":[
        {
            "category":"Building & Trades",
            "subcategory":"Construction",
            "type":"Services"
        }
    ],
    "sg:phone":"+1 309 792 8280",
    "sg:postcode":"61241",
    "sg:province":"IL",
    "sg:tags":[
        "contractor"
    ],
    "wof:name":"Standard Drywall Inc",
    "wof:placetype":"venue"
},
  "geometry": {"coordinates":[-90.338048,41.510839],"type":"Point"}
}