{
  "type": "Feature",
  "properties": {
    "iso:country":"US",
    "sg:address":"9012 S Cicero Ave",
    "sg:city":"Oak Lawn",
    "sg:classifiers":[
        {
            "category":"Personal",
            "subcategory":"Beauty Salon",
            "type":"Services"
        }
    ],
    "sg:phone":"+1 708 422 0440",
    "sg:postcode":"60453",
    "sg:province":"IL",
    "sg:tags":[
        "shop"
    ],
    "wof:name":"Designing Women Hair Salon",
    "wof:placetype":"venue"
},
  "geometry": {"coordinates":[-87.74112,41.727582],"type":"Point"}
}