{
  "type": "Feature",
  "properties": {
    "iso:country":"US",
    "sg:address":"414 Grove St",
    "sg:city":"Prophetstown",
    "sg:classifiers":[
        {
            "category":"Real Estate",
            "subcategory":"Real Estate Agent",
            "type":"Services"
        }
    ],
    "sg:phone":"+1 815 537 5537",
    "sg:postcode":"61277",
    "sg:province":"IL",
    "wof:name":"S Stewart Connie",
    "wof:placetype":"venue"
},
  "geometry": {"coordinates":[-89.942732,41.670602],"type":"Point"}
}