{
  "type": "Feature",
  "properties": {
    "iso:country":"US",
    "sg:address":"27W461 Chicago Ave",
    "sg:city":"Winfield",
    "sg:classifiers":[
        {
            "category":"Retail",
            "subcategory":"Laundry & Dry Cleaning",
            "type":"Services"
        }
    ],
    "sg:phone":"+1 630 462 7761",
    "sg:postcode":"60190",
    "sg:province":"IL",
    "wof:name":"Winfield Cleaners",
    "wof:placetype":"venue"
},
  "geometry": {"coordinates":[-88.15270200000001,41.871899],"type":"Point"}
}