{
  "type": "Feature",
  "properties": {
    "addr:full":"5535 Ann Marie Ln Oak Forest IL 60452",
    "addr:housenumber":"5535",
    "addr:postcode":"60452",
    "addr:street":"Ann Marie Ln",
    "iso:country":"US",
    "sg:address":"5535 Ann Marie Ln",
    "sg:city":"Oak Forest",
    "sg:classifiers":[
        {
            "category":"Autos & Motor Vehicles",
            "subcategory":"Auto Supplies",
            "type":"Retail Goods"
        }
    ],
    "sg:phone":"+1   ",
    "sg:postcode":"60452",
    "sg:province":"IL",
    "wof:name":"McKeever Enterprises",
    "wof:placetype":"venue"
},
  "geometry": {"coordinates":[-87.755523,41.608719],"type":"Point"}
}