{
  "type": "Feature",
  "properties": {
    "iso:country":"US",
    "sg:address":"900 Front St",
    "sg:city":"Tamms",
    "sg:classifiers":[
        {
            "category":"Insurance",
            "subcategory":"Hazard Insurance",
            "type":"Services"
        }
    ],
    "sg:phone":"+1 618 747 2603",
    "sg:postcode":"62988",
    "sg:province":"IL",
    "sg:website":"http://national.citysearch.com/profile/external/35329960/tamms_il/country_financial.html?publisher=yellowpages&reference_id=1&placement=ypwebsitemip",
    "wof:name":"COUNTRY Financial",
    "wof:placetype":"venue"
},
  "geometry": {"coordinates":[-89.260273,37.241529],"type":"Point"}
}