{
  "type": "Feature",
  "properties": {
    "addr:full":"301 W State St Jacksonville IL 62650",
    "addr:housenumber":"301",
    "addr:postcode":"62650",
    "addr:street":"W State St",
    "iso:country":"US",
    "sg:address":"301 W State St",
    "sg:city":"Jacksonville",
    "sg:classifiers":[
        {
            "category":"Professional",
            "subcategory":"Lawyer & Legal Services",
            "type":"Services"
        }
    ],
    "sg:phone":"+1 217 243 3434",
    "sg:postcode":"62650",
    "sg:province":"IL",
    "sg:tags":[
        "information",
        "attorney",
        "referral"
    ],
    "wof:name":"Michael A Hankins",
    "wof:placetype":"venue"
},
  "geometry": {"coordinates":[-90.231438,39.734291],"type":"Point"}
}