{
  "type": "Feature",
  "properties": {
    "iso:country":"US",
    "sg:address":"6023 Dempster St",
    "sg:city":"Morton Grove",
    "sg:classifiers":[
        {
            "category":"Food & Beverages",
            "subcategory":"Groceries & Convenience Stores",
            "type":"Retail Goods"
        }
    ],
    "sg:phone":"+1   ",
    "sg:postcode":"60053",
    "sg:province":"IL",
    "wof:name":"F & G Oriental Foods Inc",
    "wof:placetype":"venue"
},
  "geometry": {"coordinates":[-87.776787,42.040846],"type":"Point"}
}