{
  "type": "Feature",
  "properties": {
    "iso:country":"US",
    "sg:address":"2133 Bond Ave",
    "sg:city":"East Saint Louis",
    "sg:classifiers":[
        {
            "category":"Manufacturing",
            "subcategory":"Metals",
            "type":"Manufacturing & Wholesale Goods"
        }
    ],
    "sg:phone":"+1 618 274 0459",
    "sg:postcode":"62207",
    "sg:province":"IL",
    "wof:name":"Hard Chrome Platers",
    "wof:placetype":"venue"
},
  "geometry": {"coordinates":[-90.144972,38.603577],"type":"Point"}
}