{
  "type": "Feature",
  "properties": {
    "iso:country":"US",
    "sg:address":"426 E 142nd St",
    "sg:city":"Dolton",
    "sg:classifiers":[
        {
            "category":"Retail",
            "subcategory":"Auto Repair",
            "type":"Services"
        }
    ],
    "sg:phone":"+1 708 896 7186",
    "sg:postcode":"60419",
    "sg:province":"IL",
    "wof:name":"Auto Tech",
    "wof:placetype":"venue"
},
  "geometry": {"coordinates":[-87.610772,41.63727],"type":"Point"}
}