{
  "type": "Feature",
  "properties": {
    "iso:country":"US",
    "sg:address":"2707 S US Hwy 45 52",
    "sg:city":"Kankakee",
    "sg:classifiers":[
        {
            "category":"Restaurant",
            "type":"Food & Drink"
        }
    ],
    "sg:phone":"+1 815 939 1409",
    "sg:postcode":"60901",
    "sg:province":"IL",
    "wof:name":"J J Ruffles",
    "wof:placetype":"venue"
},
  "geometry": {"coordinates":[-87.868892,41.08128],"type":"Point"}
}