{
  "type": "Feature",
  "properties": {
    "addr:full":"420 Village Dr Carol Stream IL 60188",
    "addr:housenumber":"420",
    "addr:postcode":"60188",
    "addr:street":"Village Dr",
    "iso:country":"US",
    "sg:address":"420 Village Dr",
    "sg:city":"Carol Stream",
    "sg:classifiers":[
        {
            "category":"Personal",
            "subcategory":"Beauty Salon",
            "type":"Services"
        }
    ],
    "sg:phone":"+1 630 668 2650",
    "sg:postcode":"60188",
    "sg:province":"IL",
    "sg:tags":[
        "shop"
    ],
    "wof:name":"Heads You Win Inc",
    "wof:placetype":"venue"
},
  "geometry": {"coordinates":[-88.118492,41.913224],"type":"Point"}
}