{
  "type": "Feature",
  "properties": {
    "addr:full":"1771 E Wood Ln Mount Prospect IL 60056",
    "addr:housenumber":"1771",
    "addr:postcode":"60056",
    "addr:street":"E Wood Ln",
    "iso:country":"US",
    "sg:address":"1771 E Wood Ln",
    "sg:city":"Mount Prospect",
    "sg:classifiers":[
        {
            "category":"Retail",
            "subcategory":"Repair Shop",
            "type":"Services"
        }
    ],
    "sg:phone":"+1 773 743 0300",
    "sg:postcode":"60056",
    "sg:province":"IL",
    "wof:name":"Kane Phillips Fine CRPt&uphol",
    "wof:placetype":"venue"
},
  "geometry": {"coordinates":[-87.90418,42.094042],"type":"Point"}
}