{
  "type": "Feature",
  "properties": {
    "iso:country":"US",
    "sg:address":"22288 Green River Rd",
    "sg:city":"Colona",
    "sg:classifiers":[
        {
            "category":"Utilities",
            "subcategory":"Telephone",
            "type":"Services"
        }
    ],
    "sg:phone":"+1 309 949 2100",
    "sg:postcode":"61241",
    "sg:province":"IL",
    "sg:tags":[
        "company"
    ],
    "wof:name":"Geneseo Telephone Co",
    "wof:placetype":"venue"
},
  "geometry": {"coordinates":[-90.319432,41.470649],"type":"Point"}
}