{
  "type": "Feature",
  "properties": {
    "iso:country":"US",
    "sg:address":"1880 Black Ln",
    "sg:city":"Caseyville",
    "sg:classifiers":[
        {
            "category":"Autos & Motor Vehicles",
            "subcategory":"Auto Supplies",
            "type":"Retail Goods"
        }
    ],
    "sg:phone":"+1 618 398 5477",
    "sg:postcode":"62232",
    "sg:province":"IL",
    "sg:tags":[
        "automobile",
        "parts"
    ],
    "sg:website":"www.blacklaneauto.com",
    "wof:name":"Black Lane",
    "wof:placetype":"venue"
},
  "geometry": {"coordinates":[-90.046628,38.634856],"type":"Point"}
}