{
  "type": "Feature",
  "properties": {
    "iso:country":"US",
    "sg:address":"105 E North St",
    "sg:city":"Elburn",
    "sg:classifiers":[
        {
            "category":"Personal",
            "subcategory":"Beauty Salon",
            "type":"Services"
        }
    ],
    "sg:phone":"+1 630 365 2820",
    "sg:postcode":"60119",
    "sg:province":"IL",
    "wof:name":"Shear Image",
    "wof:placetype":"venue"
},
  "geometry": {"coordinates":[-88.472401,41.892209],"type":"Point"}
}