{
  "type": "Feature",
  "properties": {
    "addr:full":"1150 Windham Pkwy Romeoville IL 60446",
    "addr:housenumber":"1150",
    "addr:postcode":"60446",
    "addr:street":"Windham Pkwy",
    "iso:country":"US",
    "sg:address":"1150 Windham Pkwy",
    "sg:city":"Romeoville",
    "sg:classifiers":[
        {
            "category":"Retail",
            "subcategory":"Laundry & Dry Cleaning",
            "type":"Services"
        }
    ],
    "sg:phone":"+1 630 378 1500",
    "sg:postcode":"60446",
    "sg:province":"IL",
    "sg:tags":[
        "uniform",
        "supply"
    ],
    "wof:name":"Cintas The Uniform People",
    "wof:placetype":"venue"
},
  "geometry": {"coordinates":[-88.117036,41.662288],"type":"Point"}
}