{
  "type": "Feature",
  "properties": {
    "addr:full":"201 S Cedar St Shelbyville IL 62565",
    "addr:housenumber":"201",
    "addr:postcode":"62565",
    "addr:street":"S Cedar St",
    "iso:country":"US",
    "sg:address":"201 S Cedar St",
    "sg:city":"Shelbyville",
    "sg:classifiers":[
        {
            "category":"Health Services",
            "subcategory":"Doctor",
            "type":"Services"
        },
        {
            "category":"Health Services",
            "subcategory":"Clinic",
            "type":"Services"
        }
    ],
    "sg:phone":"+1 217 774 7883",
    "sg:postcode":"62565",
    "sg:province":"IL",
    "sg:tags":[
        "physician",
        "family",
        "practice",
        "surgeons",
        "osteopathic",
        "medicine"
    ],
    "wof:name":"David M Oligschlaeger Do",
    "wof:placetype":"venue"
},
  "geometry": {"coordinates":[-88.80716700000001,39.407619],"type":"Point"}
}