{
  "type": "Feature",
  "properties": {
    "iso:country":"US",
    "sg:address":"659 Fairway Ln",
    "sg:city":"Frankfort",
    "sg:classifiers":[
        {
            "category":"Insurance",
            "subcategory":"Insurance Agent",
            "type":"Services"
        }
    ],
    "sg:phone":"+1 815 464 2711",
    "sg:postcode":"60423",
    "sg:province":"IL",
    "wof:name":"Flag Insurance Svc",
    "wof:placetype":"venue"
},
  "geometry": {"coordinates":[-87.814801,41.497693],"type":"Point"}
}