{
  "type": "Feature",
  "properties": {
    "iso:country":"US",
    "sg:address":"6603 Prairie Flower",
    "sg:city":"Roscoe",
    "sg:classifiers":[
        {
            "category":"Communications",
            "subcategory":"Film & Video Production",
            "type":"Services"
        }
    ],
    "sg:phone":"+1 815 623 7477",
    "sg:postcode":"61073",
    "sg:province":"IL",
    "sg:tags":[
        "tv",
        "radio",
        "services-commercial",
        "companies-film"
    ],
    "wof:name":"Hunt N Fry M Productions",
    "wof:placetype":"venue"
},
  "geometry": {"coordinates":[-88.987754,42.395976],"type":"Point"}
}