{
  "type": "Feature",
  "properties": {
    "iso:country":"US",
    "sg:address":"1304 Brooke Rd",
    "sg:city":"Rockford",
    "sg:classifiers":[
        {
            "category":"Retail",
            "subcategory":"Laundry & Dry Cleaning",
            "type":"Services"
        }
    ],
    "sg:phone":"+1 815 398 9322",
    "sg:postcode":"61109",
    "sg:province":"IL",
    "sg:tags":[
        "drycleaning",
        "plant",
        "power"
    ],
    "wof:name":"Brooke Road Cleaners",
    "wof:placetype":"venue"
},
  "geometry": {"coordinates":[-89.075295,42.230373],"type":"Point"}
}