{
  "type": "Feature",
  "properties": {
    "iso:country":"US",
    "sg:address":"9520 Columbus Rd",
    "sg:city":"Fowler",
    "sg:classifiers":[
        {
            "category":"Farming",
            "subcategory":"Livestock Farm",
            "type":"Manufacturing & Wholesale Goods"
        }
    ],
    "sg:phone":"+1 217 434 8376",
    "sg:postcode":"62338",
    "sg:province":"IL",
    "sg:tags":[
        "hog",
        "or",
        "feedlot"
    ],
    "wof:name":"Ronald Wellman",
    "wof:placetype":"venue"
},
  "geometry": {"coordinates":[-91.26666400000001,39.959929],"type":"Point"}
}