{
  "type": "Feature",
  "properties": {
    "iso:country":"US",
    "sg:address":"4600 N Illinois St",
    "sg:city":"Fairview Heights",
    "sg:classifiers":[
        {
            "category":"Personal",
            "type":"Services"
        },
        {
            "category":"Banks & Credit Unions",
            "subcategory":"Financial Services",
            "type":"Services"
        }
    ],
    "sg:phone":"+1 618 825 0673",
    "sg:postcode":"62208",
    "sg:province":"IL",
    "sg:tags":[
        "mover",
        "broker",
        "mortgage"
    ],
    "wof:name":"Mortgage Makers",
    "wof:placetype":"venue"
},
  "geometry": {"coordinates":[-89.984703,38.571098],"type":"Point"}
}