{
  "type": "Feature",
  "properties": {
    "iso:country":"US",
    "sg:address":"13000 Maple Ave",
    "sg:city":"Blue Island",
    "sg:classifiers":[
        {
            "category":"Health Services",
            "subcategory":"Doctor",
            "type":"Services"
        }
    ],
    "sg:phone":"+1 708 293 7627",
    "sg:postcode":"60406",
    "sg:province":"IL",
    "sg:tags":[
        "clinic"
    ],
    "wof:name":"Blue Island Access Clinic",
    "wof:placetype":"venue"
},
  "geometry": {"coordinates":[-87.684869,41.656676],"type":"Point"}
}