{
  "type": "Feature",
  "properties": {
    "iso:country":"US",
    "sg:address":"213 S Main St",
    "sg:city":"Vermont",
    "sg:classifiers":[
        {
            "category":"Social Services",
            "type":"Services"
        }
    ],
    "sg:phone":"+1 309 784 2111",
    "sg:postcode":"61484",
    "sg:province":"IL",
    "wof:name":"Y W C A Metropolitan Chicago",
    "wof:placetype":"venue"
},
  "geometry": {"coordinates":[-90.427693,40.293549],"type":"Point"}
}