{
  "type": "Feature",
  "properties": {
    "addr:full":"8286 Blank Rd Iuka IL 62849",
    "addr:housenumber":"8286",
    "addr:postcode":"62849",
    "addr:street":"Blank Rd",
    "iso:country":"US",
    "sg:address":"8286 Blank Rd",
    "sg:city":"Iuka",
    "sg:classifiers":[
        {
            "category":"Farming",
            "subcategory":"Farm",
            "type":"Manufacturing & Wholesale Goods"
        }
    ],
    "sg:phone":"+1 618 323 6665",
    "sg:postcode":"62849",
    "sg:province":"IL",
    "wof:name":"Blank Farm",
    "wof:placetype":"venue"
},
  "geometry": {"coordinates":[-88.756507,38.591309],"type":"Point"}
}