{
  "type": "Feature",
  "properties": {
    "iso:country":"US",
    "sg:address":"139 Old Orchard Shopping Center",
    "sg:city":"Skokie",
    "sg:classifiers":[
        {
            "category":"Personal",
            "type":"Services"
        }
    ],
    "sg:phone":"+1 847 679 5800",
    "sg:postcode":"60077",
    "sg:province":"IL",
    "sg:tags":[
        "wear",
        "formal"
    ],
    "wof:name":"After Hours Formalwear",
    "wof:placetype":"venue"
},
  "geometry": {"coordinates":[-87.748037,42.06156],"type":"Point"}
}