{
  "type": "Feature",
  "properties": {
    "addr:full":"250 Parkway Dr Lincolnshire IL 60069",
    "addr:housenumber":"250",
    "addr:postcode":"60069",
    "addr:street":"Parkway Dr",
    "iso:country":"US",
    "sg:address":"250 Parkway Dr",
    "sg:city":"Lincolnshire",
    "sg:classifiers":[
        {
            "category":"Building & Trades",
            "subcategory":"Construction",
            "type":"Services"
        }
    ],
    "sg:phone":"+1 847 229 9200",
    "sg:postcode":"60069",
    "sg:province":"IL",
    "sg:tags":[
        "remodeling",
        "general",
        "commercial",
        "contractor"
    ],
    "wof:name":"Sjg Construction Company",
    "wof:placetype":"venue"
},
  "geometry": {"coordinates":[-87.926102,42.177818],"type":"Point"}
}