{
  "type": "Feature",
  "properties": {
    "iso:country":"US",
    "sg:address":"3028 Downing Ave",
    "sg:city":"Westchester",
    "sg:classifiers":[
        {
            "category":"Banks & Credit Unions",
            "subcategory":"Investment Brokerage",
            "type":"Services"
        }
    ],
    "sg:phone":"+1 708 531 8069",
    "sg:postcode":"60154",
    "sg:province":"IL",
    "sg:tags":[
        "advisory"
    ],
    "wof:name":"Lt Financial Inc",
    "wof:placetype":"venue"
},
  "geometry": {"coordinates":[-87.888565,41.834929],"type":"Point"}
}