{
  "type": "Feature",
  "properties": {
    "iso:country":"US",
    "sg:address":"1908 Broadway St",
    "sg:city":"Mount Vernon",
    "sg:classifiers":[
        {
            "category":"Professional",
            "subcategory":"Lawyer & Legal Services",
            "type":"Services"
        }
    ],
    "sg:phone":"+1 618 246 9370",
    "sg:postcode":"62864",
    "sg:province":"IL",
    "wof:name":"Cheryl A Powell Attorney",
    "wof:placetype":"venue"
},
  "geometry": {"coordinates":[-88.91349700000001,38.316263],"type":"Point"}
}