{
  "type": "Feature",
  "properties": {
    "addr:full":"Seward Park Chicago IL 60610",
    "addr:postcode":"60610",
    "iso:country":"US",
    "sg:address":"Seward Park",
    "sg:city":"Chicago",
    "sg:classifiers":[
        {
            "category":"Sports & Exercise",
            "subcategory":"Sports Center",
            "type":"Entertainment"
        }
    ],
    "sg:postcode":"60610",
    "sg:province":"IL",
    "sg:tags":[
        "amateur",
        "team"
    ],
    "sg:website":"www.playballchicago.com",
    "wof:name":"PlayBall Chicago",
    "wof:placetype":"venue"
},
  "geometry": {"coordinates":[-87.63903000000001,41.902863],"type":"Point"}
}