{
  "type": "Feature",
  "properties": {
    "iso:country":"US",
    "sg:address":"3135 W 25th St",
    "sg:city":"Chicago",
    "sg:classifiers":[
        {
            "category":"Food & Beverages",
            "subcategory":"Groceries & Convenience Stores",
            "type":"Retail Goods"
        }
    ],
    "sg:phone":"+1 773 247 7314",
    "sg:postcode":"60623",
    "sg:province":"IL",
    "wof:name":"Guanajuato Grocery Inc",
    "wof:placetype":"venue"
},
  "geometry": {"coordinates":[-87.703883,41.846213],"type":"Point"}
}