{
  "type": "Feature",
  "properties": {
    "addr:full":"9302 S 83rd Ct Hickory Hills IL 60457",
    "addr:housenumber":"9302",
    "addr:postcode":"60457",
    "addr:street":"S 83Rd Ct",
    "iso:country":"US",
    "sg:address":"9302 S 83rd Ct",
    "sg:city":"Hickory Hills",
    "sg:classifiers":[
        {
            "category":"Banks & Credit Unions",
            "subcategory":"Investment Brokerage",
            "type":"Services"
        }
    ],
    "sg:phone":"+1 708 233 0736",
    "sg:postcode":"60457",
    "sg:province":"IL",
    "sg:tags":[
        "investing"
    ],
    "wof:name":"Futura Llc",
    "wof:placetype":"venue"
},
  "geometry": {"coordinates":[-87.82669199999999,41.722006],"type":"Point"}
}