{
  "type": "Feature",
  "properties": {
    "iso:country":"US",
    "sg:address":"3710 Commercial Ave",
    "sg:city":"Northbrook",
    "sg:classifiers":[
        {
            "category":"Professional",
            "subcategory":"Lawyer & Legal Services",
            "type":"Services"
        }
    ],
    "sg:phone":"+1 847 656 8958",
    "sg:postcode":"60062",
    "sg:province":"IL",
    "sg:tags":[
        "attorney"
    ],
    "wof:name":"Sharon F Banks",
    "wof:placetype":"venue"
},
  "geometry": {"coordinates":[-87.872553,42.146678],"type":"Point"}
}