{
  "type": "Feature",
  "properties": {
    "addr:full":"431 W Liberty St Wauconda IL 60084",
    "addr:housenumber":"431",
    "addr:postcode":"60084",
    "addr:street":"W Liberty St",
    "iso:country":"US",
    "sg:address":"431 W Liberty St",
    "sg:city":"Wauconda",
    "sg:classifiers":[
        {
            "category":"Health Services",
            "subcategory":"Doctor",
            "type":"Services"
        }
    ],
    "sg:phone":"+1 847 526 2151",
    "sg:postcode":"60084",
    "sg:province":"IL",
    "sg:tags":[
        "physician",
        "surgeon"
    ],
    "wof:name":"Family Medicine Specialists",
    "wof:placetype":"venue"
},
  "geometry": {"coordinates":[-88.154411,42.258087],"type":"Point"}
}