{
  "type": "Feature",
  "properties": {
    "addr:full":"7835 W Belmont Ave Elmwood Park IL 60707",
    "addr:housenumber":"7835",
    "addr:postcode":"60707",
    "addr:street":"W Belmont Ave",
    "iso:country":"US",
    "sg:address":"7835 W Belmont Ave",
    "sg:city":"Elmwood Park",
    "sg:classifiers":[
        {
            "category":"Autos & Motor Vehicles",
            "subcategory":"Fuel & Gas Station",
            "type":"Retail Goods"
        },
        {
            "category":"Retail",
            "subcategory":"Auto Repair",
            "type":"Services"
        }
    ],
    "sg:phone":"+1 708 452 0011",
    "sg:postcode":"60707",
    "sg:province":"IL",
    "wof:name":"Caira Super Service Inc",
    "wof:placetype":"venue"
},
  "geometry": {"coordinates":[-87.8228,41.937599],"type":"Point"}
}