{
  "type": "Feature",
  "properties": {
    "iso:country":"US",
    "sg:address":"134 Virginia Rd",
    "sg:city":"Crystal Lake",
    "sg:classifiers":[
        {
            "category":"Personal",
            "type":"Services"
        },
        {
            "category":"Health Services",
            "subcategory":"Clinic",
            "type":"Services"
        }
    ],
    "sg:phone":"+1 815 444 6159",
    "sg:postcode":"60014",
    "sg:province":"IL",
    "sg:tags":[
        "control",
        "specialty",
        "weight",
        "outpatient"
    ],
    "wof:name":"Why Weight",
    "wof:placetype":"venue"
},
  "geometry": {"coordinates":[-88.313429,42.214152],"type":"Point"}
}