{
  "type": "Feature",
  "properties": {
    "iso:country":"US",
    "sg:address":"221 Town Sq",
    "sg:city":"Wheaton",
    "sg:classifiers":[
        {
            "category":"Coffee & Tea",
            "type":"Food & Drink"
        },
        {
            "category":"Restaurant",
            "type":"Food & Drink"
        }
    ],
    "sg:phone":"+1 630 260 9001",
    "sg:postcode":"60189",
    "sg:province":"IL",
    "sg:tags":[
        "espresso"
    ],
    "wof:name":"Egg Lectic Cafe Inc",
    "wof:placetype":"venue"
},
  "geometry": {"coordinates":[-88.100528,41.834875],"type":"Point"}
}