{
  "type": "Feature",
  "properties": {
    "iso:country":"US",
    "sg:address":"14611 Sherman Ave",
    "sg:city":"Posen",
    "sg:classifiers":[
        {
            "category":"Wholesale",
            "subcategory":"Jewelry",
            "type":"Manufacturing & Wholesale Goods"
        }
    ],
    "sg:phone":"+1 708 389 6355",
    "sg:postcode":"60469",
    "sg:province":"IL",
    "sg:tags":[
        "stone"
    ],
    "wof:name":"Money Makers of Illinois Inc",
    "wof:placetype":"venue"
},
  "geometry": {"coordinates":[-87.68010099999999,41.628855],"type":"Point"}
}