{
  "type": "Feature",
  "properties": {
    "iso:country":"US",
    "sg:address":"7009 W Higgins Ave",
    "sg:city":"Chicago",
    "sg:classifiers":[
        {
            "category":"Deli",
            "type":"Food & Drink"
        },
        {
            "category":"Restaurant",
            "type":"Food & Drink"
        }
    ],
    "sg:menulink":"http://www.allmenus.com/il/chicago/223428-trios-pizza/menu/",
    "sg:phone":"+1 773 775 3974",
    "sg:postcode":"60656",
    "sg:province":"IL",
    "sg:tags":[
        "deli",
        "american"
    ],
    "wof:name":"Trios Pizza",
    "wof:placetype":"venue"
},
  "geometry": {"coordinates":[-87.802564,41.980092],"type":"Point"}
}