{
  "type": "Feature",
  "properties": {
    "addr:full":"218 N la Salle Ave Bradley IL 60915",
    "addr:housenumber":"218",
    "addr:postcode":"60915",
    "addr:street":"N La Salle Ave",
    "iso:country":"US",
    "sg:address":"218 N la Salle Ave",
    "sg:city":"Bradley",
    "sg:classifiers":[
        {
            "category":"Retail",
            "subcategory":"Laundry & Dry Cleaning",
            "type":"Services"
        },
        {
            "category":"Building & Trades",
            "subcategory":"Cleaning & Sanitation",
            "type":"Services"
        }
    ],
    "sg:phone":"+1 815 928 9486",
    "sg:postcode":"60915",
    "sg:province":"IL",
    "sg:tags":[
        "cleaner",
        "fabric",
        "fire",
        "damage",
        "rug",
        "water",
        "protection",
        "furniture",
        "restoration",
        "carpet"
    ],
    "wof:name":"Steam Rite Carpet & Upholstery Care",
    "wof:placetype":"venue"
},
  "geometry": {"coordinates":[-87.85237100000001,41.146671],"type":"Point"}
}