{
  "type": "Feature",
  "properties": {
    "addr:full":"203 S Logan St Lincoln IL 62656",
    "addr:housenumber":"203",
    "addr:postcode":"62656",
    "addr:street":"S Logan St",
    "iso:country":"US",
    "sg:address":"203 S Logan St",
    "sg:city":"Lincoln",
    "sg:classifiers":[
        {
            "category":"Home & Garden",
            "subcategory":"Hardware",
            "type":"Retail Goods"
        }
    ],
    "sg:phone":"+1 217 735 2918",
    "sg:postcode":"62656",
    "sg:province":"IL",
    "wof:name":"Pete's Hardware",
    "wof:placetype":"venue"
},
  "geometry": {"coordinates":[-89.36620600000001,40.147815],"type":"Point"}
}