{
  "type": "Feature",
  "properties": {
    "addr:full":"1452 Sebastopol Rd Highland IL 62249",
    "addr:housenumber":"1452",
    "addr:postcode":"62249",
    "addr:street":"Sebastopol Rd",
    "iso:country":"US",
    "sg:address":"1452 Sebastopol Rd",
    "sg:city":"Highland",
    "sg:classifiers":[
        {
            "category":"Organizations",
            "subcategory":"Religious Organization",
            "type":"Services"
        }
    ],
    "sg:phone":"+1 618 654 3001",
    "sg:postcode":"62249",
    "sg:province":"IL",
    "wof:name":"Bethany Baptist Church",
    "wof:placetype":"venue"
},
  "geometry": {"coordinates":[-89.601355,38.719933],"type":"Point"}
}