{
  "type": "Feature",
  "properties": {
    "addr:full":"1361 W Jeffery St Kankakee IL 60901",
    "addr:housenumber":"1361",
    "addr:postcode":"60901",
    "addr:street":"W Jeffery St",
    "iso:country":"US",
    "sg:address":"1361 W Jeffery St",
    "sg:city":"Kankakee",
    "sg:classifiers":[
        {
            "category":"Education",
            "subcategory":"Dance Studio",
            "type":"Public Place"
        }
    ],
    "sg:phone":"+1 815 939 7177",
    "sg:postcode":"60901",
    "sg:province":"IL",
    "wof:name":"Aubry Paula School of Dancing",
    "wof:placetype":"venue"
},
  "geometry": {"coordinates":[-87.889635,41.106128],"type":"Point"}
}