{
  "type": "Feature",
  "properties": {
    "addr:full":"35 State Rte 59 Aurora IL 60504",
    "addr:housenumber":"35",
    "addr:postcode":"60504",
    "addr:street":"State Rte 59",
    "iso:country":"US",
    "sg:address":"35 State Rte 59",
    "sg:city":"Aurora",
    "sg:classifiers":[
        {
            "category":"Retail",
            "subcategory":"Car Wash",
            "type":"Services"
        }
    ],
    "sg:phone":"+1 630 851 0700",
    "sg:postcode":"60504",
    "sg:province":"IL",
    "sg:tags":[
        "polishing",
        "carwash",
        "washing"
    ],
    "wof:name":"Turtle Wax Car Wash & Auto App",
    "wof:placetype":"venue"
},
  "geometry": {"coordinates":[-88.20596,41.762741],"type":"Point"}
}