{
  "type": "Feature",
  "properties": {
    "addr:full":"202 W State St Rockford IL 61101",
    "addr:housenumber":"202",
    "addr:postcode":"61101",
    "addr:street":"W State St",
    "iso:country":"US",
    "sg:address":"202 W State St",
    "sg:city":"Rockford",
    "sg:classifiers":[
        {
            "category":"Shopping",
            "subcategory":"Computers & Home Electronics",
            "type":"Retail Goods"
        }
    ],
    "sg:phone":"+1 815 963 4414",
    "sg:postcode":"61101",
    "sg:province":"IL",
    "sg:tags":[
        "software"
    ],
    "wof:name":"Indo American Capital & Tech",
    "wof:placetype":"venue"
},
  "geometry": {"coordinates":[-89.09417000000001,42.271225],"type":"Point"}
}