{
  "type": "Feature",
  "properties": {
    "iso:country":"US",
    "sg:address":"1301 S 47th Ave",
    "sg:city":"Cicero",
    "sg:classifiers":[
        {
            "category":"Manufacturing",
            "subcategory":"Paper Products",
            "type":"Manufacturing & Wholesale Goods"
        }
    ],
    "sg:phone":"+1 708 656 0400",
    "sg:postcode":"60804",
    "sg:province":"IL",
    "sg:tags":[
        "corrugated",
        "solid",
        "fiber",
        "box"
    ],
    "wof:name":"ABC Shipping Supply Co",
    "wof:placetype":"venue"
},
  "geometry": {"coordinates":[-87.742183,41.862265],"type":"Point"}
}