{
  "type": "Feature",
  "properties": {
    "addr:full":"1725 W Harrison St Ste 425 Chicago IL 60612",
    "addr:housenumber":"1725",
    "addr:postcode":"60612",
    "addr:street":"W Harrison St Ste 425",
    "iso:country":"US",
    "sg:address":"1725 W Harrison St Ste 425",
    "sg:city":"Chicago",
    "sg:classifiers":[
        {
            "category":"Health Services",
            "subcategory":"Doctor",
            "type":"Services"
        }
    ],
    "sg:phone":"+1 312 563 3000",
    "sg:postcode":"60612",
    "sg:province":"IL",
    "sg:tags":[
        "physician",
        "reconstructive",
        "surgeons",
        "cosmetic",
        "plastic",
        "surgeon",
        "surgery"
    ],
    "wof:name":"Polley, John W, Md - Rush Cranio Facial Ctr",
    "wof:placetype":"venue"
},
  "geometry": {"coordinates":[-87.66970499999999,41.87418],"type":"Point"}
}