{
  "type": "Feature",
  "properties": {
    "addr:full":"3400 Dundee Rd Northbrook IL 60062",
    "addr:housenumber":"3400",
    "addr:postcode":"60062",
    "addr:street":"Dundee Rd",
    "iso:country":"US",
    "sg:address":"3400 Dundee Rd",
    "sg:city":"Northbrook",
    "sg:classifiers":[
        {
            "category":"Professional",
            "subcategory":"Employment Agencies",
            "type":"Services"
        }
    ],
    "sg:phone":"+1 847 509 9000",
    "sg:postcode":"60062",
    "sg:province":"IL",
    "sg:tags":[
        "personnel",
        "placement"
    ],
    "wof:name":"Management Recruiters Intl",
    "wof:placetype":"venue"
},
  "geometry": {"coordinates":[-87.85825199999999,42.138348],"type":"Point"}
}