{
  "type": "Feature",
  "properties": {
    "addr:full":"30 N Michigan Ave Ste 1301 Chicago IL 60602",
    "addr:housenumber":"30",
    "addr:postcode":"60602",
    "addr:street":"N Michigan Ave Ste 1301",
    "iso:country":"US",
    "sg:address":"30 N Michigan Ave Ste 1301",
    "sg:city":"Chicago",
    "sg:classifiers":[
        {
            "category":"Health Services",
            "subcategory":"Doctor",
            "type":"Services"
        }
    ],
    "sg:phone":"+1 312 332 7303",
    "sg:postcode":"60602",
    "sg:province":"IL",
    "sg:tags":[
        "dermatologist"
    ],
    "wof:name":"Wise Ronald D MD",
    "wof:placetype":"venue"
},
  "geometry": {"coordinates":[-87.624515,41.882504],"type":"Point"}
}