{
  "type": "Feature",
  "properties": {
    "iso:country":"US",
    "sg:address":"2433 Ridge Rd",
    "sg:city":"Lansing",
    "sg:classifiers":[
        {
            "category":"Restaurant",
            "type":"Food & Drink"
        }
    ],
    "sg:phone":"+1 708 895 6844",
    "sg:postcode":"60438",
    "sg:province":"IL",
    "sg:tags":[
        "caterer",
        "catering"
    ],
    "wof:name":"Lencioni Catering",
    "wof:placetype":"venue"
},
  "geometry": {"coordinates":[-87.55789900000001,41.564899],"type":"Point"}
}