{
  "type": "Feature",
  "properties": {
    "iso:country":"US",
    "sg:address":"3 Tom Lambrecht Dr",
    "sg:city":"Romeoville",
    "sg:classifiers":[
        {
            "category":"Professional",
            "subcategory":"Detective & Security Services",
            "type":"Services"
        }
    ],
    "sg:phone":"+1 815 836 8724",
    "sg:postcode":"60446",
    "sg:province":"IL",
    "sg:tags":[
        "information",
        "bureau"
    ],
    "wof:name":"Windwalker",
    "wof:placetype":"venue"
},
  "geometry": {"coordinates":[-88.09111799999999,41.603669],"type":"Point"}
}