{
  "type": "Feature",
  "properties": {
    "iso:country":"US",
    "sg:address":"1903 Pratt Ln",
    "sg:city":"Ottawa",
    "sg:classifiers":[
        {
            "category":"Social Services",
            "subcategory":"Child Care",
            "type":"Services"
        }
    ],
    "sg:phone":"+1 815 433 9750",
    "sg:postcode":"61350",
    "sg:province":"IL",
    "sg:tags":[
        "kindergarten",
        "academic",
        "school"
    ],
    "wof:name":"Tri-County Headstart Program",
    "wof:placetype":"venue"
},
  "geometry": {"coordinates":[-88.830546,41.361275],"type":"Point"}
}