{
  "type": "Feature",
  "properties": {
    "iso:country":"US",
    "sg:address":"4150 Grove Ave",
    "sg:city":"Gurnee",
    "sg:classifiers":[
        {
            "category":"Restaurant",
            "type":"Food & Drink"
        }
    ],
    "sg:menulink":"http://www.allmenus.com/il/warren/181013-wendys/menu/",
    "sg:phone":"+1 847 336 3519",
    "sg:postcode":"60031",
    "sg:province":"IL",
    "sg:tags":[
        "burger",
        "american",
        "soup"
    ],
    "wof:name":"Wendy's",
    "wof:placetype":"venue"
},
  "geometry": {"coordinates":[-87.90528,42.37929],"type":"Point"}
}