{
  "type": "Feature",
  "properties": {
    "addr:full":"1728 W Winnemac Ave Chicago IL 60640",
    "addr:housenumber":"1728",
    "addr:postcode":"60640",
    "addr:street":"W Winnemac Ave",
    "iso:country":"US",
    "sg:address":"1728 W Winnemac Ave",
    "sg:city":"Chicago",
    "sg:classifiers":[
        {
            "category":"Government",
            "subcategory":"Fire Station",
            "type":"Public Place"
        }
    ],
    "sg:phone":"+1 773 405 6965",
    "sg:postcode":"60640",
    "sg:province":"IL",
    "sg:tags":[
        "department"
    ],
    "wof:name":"Gray Fire",
    "wof:placetype":"venue"
},
  "geometry": {"coordinates":[-87.67224299999999,41.973398],"type":"Point"}
}