{
  "type": "Feature",
  "properties": {
    "iso:country":"US",
    "sg:address":"35946 N Knowles Rd",
    "sg:city":"Lake Villa",
    "sg:classifiers":[
        {
            "category":"Building & Trades",
            "subcategory":"Landscaping Services",
            "type":"Services"
        }
    ],
    "sg:phone":"+1 847 356 8852",
    "sg:postcode":"60046",
    "sg:province":"IL",
    "sg:tags":[
        "lawn",
        "planning",
        "garden",
        "landscape"
    ],
    "wof:name":"Meyer Landscaping & Maint Svc",
    "wof:placetype":"venue"
},
  "geometry": {"coordinates":[-87.997721,42.383751],"type":"Point"}
}