{
  "type": "Feature",
  "properties": {
    "addr:full":"4513 Lincoln Ave Lisle IL 60532",
    "addr:housenumber":"4513",
    "addr:postcode":"60532",
    "addr:street":"Lincoln Ave",
    "iso:country":"US",
    "sg:address":"4513 Lincoln Ave",
    "sg:city":"Lisle",
    "sg:classifiers":[
        {
            "category":"Professional",
            "subcategory":"Lawyer & Legal Services",
            "type":"Services"
        }
    ],
    "sg:phone":"+1 630 717 1255",
    "sg:postcode":"60532",
    "sg:province":"IL",
    "sg:tags":[
        "attorney"
    ],
    "wof:name":"Fenelon Terence",
    "wof:placetype":"venue"
},
  "geometry": {"coordinates":[-88.07678199999999,41.803867],"type":"Point"}
}