{
  "type": "Feature",
  "properties": {
    "addr:full":"522 W North Ave Elmhurst IL 60126",
    "addr:housenumber":"522",
    "addr:postcode":"60126",
    "addr:street":"W North Ave",
    "iso:country":"US",
    "sg:address":"522 W North Ave",
    "sg:city":"Elmhurst",
    "sg:classifiers":[
        {
            "category":"Restaurant",
            "type":"Food & Drink"
        }
    ],
    "sg:phone":"+1   ",
    "sg:postcode":"60126",
    "sg:province":"IL",
    "sg:tags":[
        "eating"
    ],
    "wof:name":"Hickory Roasters",
    "wof:placetype":"venue"
},
  "geometry": {"coordinates":[-87.959369,41.905781],"type":"Point"}
}