{
  "type": "Feature",
  "properties": {
    "iso:country":"US",
    "sg:address":"215 1st St",
    "sg:city":"Colona",
    "sg:classifiers":[
        {
            "category":"Government",
            "subcategory":"Police Station",
            "type":"Public Place"
        }
    ],
    "sg:phone":"+1 309 792 1511",
    "sg:postcode":"61241",
    "sg:province":"IL",
    "sg:tags":[
        "department"
    ],
    "wof:name":"City Of Colona Police Dept",
    "wof:placetype":"venue"
},
  "geometry": {"coordinates":[-90.35808900000001,41.479938],"type":"Point"}
}