{
  "type": "Feature",
  "properties": {
    "addr:full":"621 State Ave Hampton IL 61256",
    "addr:housenumber":"621",
    "addr:postcode":"61256",
    "addr:street":"State Ave",
    "iso:country":"US",
    "sg:address":"621 State Ave",
    "sg:city":"Hampton",
    "sg:classifiers":[
        {
            "category":"Shopping",
            "subcategory":"Pharmacy",
            "type":"Retail Goods"
        }
    ],
    "sg:phone":"+1 309 755 3862",
    "sg:postcode":"61256",
    "sg:province":"IL",
    "sg:tags":[
        "drugstore"
    ],
    "wof:name":"Porter's Village Rx",
    "wof:placetype":"venue"
},
  "geometry": {"coordinates":[-90.405197,41.553799],"type":"Point"}
}