{
  "type": "Feature",
  "properties": {
    "addr:full":"3018 W Devon Ave Chicago IL 60659",
    "addr:housenumber":"3018",
    "addr:postcode":"60659",
    "addr:street":"W Devon Ave",
    "iso:country":"US",
    "sg:address":"3018 W Devon Ave",
    "sg:city":"Chicago",
    "sg:classifiers":[
        {
            "category":"Manufacturing",
            "subcategory":"Leather Goods",
            "type":"Manufacturing & Wholesale Goods"
        }
    ],
    "sg:phone":"+1 773 508 9680",
    "sg:postcode":"60659",
    "sg:province":"IL",
    "wof:name":"Leather Options",
    "wof:placetype":"venue"
},
  "geometry": {"coordinates":[-87.705352,41.997727],"type":"Point"}
}