{
  "type": "Feature",
  "properties": {
    "iso:country":"US",
    "sg:address":"1220 W 95th Pl",
    "sg:city":"Chicago",
    "sg:classifiers":[
        {
            "category":"Arts & Performance",
            "subcategory":"Music",
            "type":"Entertainment"
        }
    ],
    "sg:phone":"+1 773 239 3606",
    "sg:postcode":"60643",
    "sg:province":"IL",
    "sg:tags":[
        "jockey",
        "disc"
    ],
    "wof:name":"Music On The Run",
    "wof:placetype":"venue"
},
  "geometry": {"coordinates":[-87.65339899999999,41.720304],"type":"Point"}
}