{
  "type": "Feature",
  "properties": {
    "iso:country":"US",
    "sg:address":"4551 W Fulton St",
    "sg:city":"Chicago",
    "sg:classifiers":[
        {
            "category":"Professional",
            "subcategory":"Business Services",
            "type":"Services"
        },
        {
            "category":"Professional",
            "subcategory":"Printing & Photocopies",
            "type":"Services"
        }
    ],
    "sg:phone":"+1 773 261 2323",
    "sg:postcode":"60624",
    "sg:province":"IL",
    "sg:tags":[
        "mail",
        "services-commercial",
        "shipping"
    ],
    "sg:website":"http://www.universalmailing.com",
    "wof:name":"Universal Mailing And Printing Services Inc.",
    "wof:placetype":"venue"
},
  "geometry": {"coordinates":[-87.74004499999999,41.885342],"type":"Point"}
}