{
  "type": "Feature",
  "properties": {
    "iso:country":"US",
    "sg:address":"17275 N 1800th St",
    "sg:city":"Marshall",
    "sg:classifiers":[
        {
            "category":"Retail",
            "subcategory":"Veterinary Services",
            "type":"Services"
        }
    ],
    "sg:phone":"+1 217 826 1177",
    "sg:postcode":"62441",
    "sg:province":"IL",
    "sg:tags":[
        "clinic",
        "hospital",
        "specialty"
    ],
    "wof:name":"Animal Care Clinic",
    "wof:placetype":"venue"
},
  "geometry": {"coordinates":[-87.684016,39.401758],"type":"Point"}
}