{
  "type": "Feature",
  "properties": {
    "iso:country":"US",
    "sg:address":"435 Duane St",
    "sg:city":"Glen Ellyn",
    "sg:classifiers":[
        {
            "category":"Building & Trades",
            "subcategory":"Construction",
            "type":"Services"
        }
    ],
    "sg:phone":"+1 630 790 0535",
    "sg:postcode":"60137",
    "sg:province":"IL",
    "sg:tags":[
        "contractor"
    ],
    "wof:name":"Spengler Design and Construction Inc",
    "wof:placetype":"venue"
},
  "geometry": {"coordinates":[-88.070396,41.875599],"type":"Point"}
}