{
  "type": "Feature",
  "properties": {
    "addr:full":"35820 Pearl St Kirkland IL 60146",
    "addr:housenumber":"35820",
    "addr:postcode":"60146",
    "addr:street":"Pearl St",
    "iso:country":"US",
    "sg:address":"35820 Pearl St",
    "sg:city":"Kirkland",
    "sg:phone":"+1 815 522 3343",
    "sg:postcode":"60146",
    "sg:province":"IL",
    "sg:tags":[
        "farm",
        "grain",
        "cash"
    ],
    "wof:name":"Mende Farms",
    "wof:placetype":"venue"
},
  "geometry": {"coordinates":[-88.839203,42.150366],"type":"Point"}
}