{
  "type": "Feature",
  "properties": {
    "iso:country":"US",
    "sg:address":"305 S Main St",
    "sg:city":"Homer",
    "sg:classifiers":[
        {
            "category":"Organizations",
            "subcategory":"Religious Organization",
            "type":"Services"
        }
    ],
    "sg:phone":"+1 217 896 2551",
    "sg:postcode":"61849",
    "sg:province":"IL",
    "wof:name":"Steve Burwell",
    "wof:placetype":"venue"
},
  "geometry": {"coordinates":[-87.957966,40.033336],"type":"Point"}
}