{
  "type": "Feature",
  "properties": {
    "iso:country":"US",
    "sg:address":"449 Pine Lake Cir",
    "sg:city":"Vernon Hills",
    "sg:classifiers":[
        {
            "category":"Restaurant",
            "type":"Food & Drink"
        }
    ],
    "sg:phone":"+1   ",
    "sg:postcode":"60061",
    "sg:province":"IL",
    "sg:tags":[
        "eating"
    ],
    "wof:name":"Schlotzkys Deli",
    "wof:placetype":"venue"
},
  "geometry": {"coordinates":[-87.954626,42.251085],"type":"Point"}
}