{
  "type": "Feature",
  "properties": {
    "iso:country":"US",
    "sg:address":"12301 S 80th Ave",
    "sg:city":"Palos Park",
    "sg:classifiers":[
        {
            "category":"Food & Beverages",
            "subcategory":"Groceries & Convenience Stores",
            "type":"Retail Goods"
        }
    ],
    "sg:phone":"+1   ",
    "sg:postcode":"60464",
    "sg:province":"IL",
    "sg:tags":[
        "gasoline"
    ],
    "wof:name":"Citgo",
    "wof:placetype":"venue"
},
  "geometry": {"coordinates":[-87.81584599999999,41.665814],"type":"Point"}
}