{
  "type": "Feature",
  "properties": {
    "addr:full":"1950 Larkin Ave Elgin IL 60123",
    "addr:housenumber":"1950",
    "addr:postcode":"60123",
    "addr:street":"Larkin Ave",
    "iso:country":"US",
    "sg:address":"1950 Larkin Ave",
    "sg:city":"Elgin",
    "sg:classifiers":[
        {
            "category":"Health Services",
            "subcategory":"Nursing And Care Facility",
            "type":"Services"
        }
    ],
    "sg:phone":"+1 847 742 7070",
    "sg:postcode":"60123",
    "sg:province":"IL",
    "sg:tags":[
        "skilled"
    ],
    "sg:website":"www.shermanhospital.org",
    "wof:name":"Sherman West Court",
    "wof:placetype":"venue"
},
  "geometry": {"coordinates":[-88.32529100000001,42.032748],"type":"Point"}
}