{
  "type": "Feature",
  "properties": {
    "addr:full":"6201 S Stewart Ave Chicago IL 60621",
    "addr:housenumber":"6201",
    "addr:postcode":"60621",
    "addr:street":"S Stewart Ave",
    "iso:country":"US",
    "sg:address":"6201 S Stewart Ave",
    "sg:city":"Chicago",
    "sg:classifiers":[
        {
            "category":"Community Center",
            "subcategory":"Youth",
            "type":"Public Place"
        }
    ],
    "sg:phone":"+1 773 535 0010",
    "sg:postcode":"60621",
    "sg:province":"IL",
    "wof:name":"Boys & Girls Club of America",
    "wof:placetype":"venue"
},
  "geometry": {"coordinates":[-87.635087,41.781508],"type":"Point"}
}