{
  "type": "Feature",
  "properties": {
    "addr:full":"128 Sturtz St Barrington IL 60010",
    "addr:housenumber":"128",
    "addr:postcode":"60010",
    "addr:street":"Sturtz St",
    "iso:country":"US",
    "sg:address":"128 Sturtz St",
    "sg:city":"Barrington",
    "sg:classifiers":[
        {
            "category":"Wholesale",
            "subcategory":"Machinery & Supplies",
            "type":"Manufacturing & Wholesale Goods"
        }
    ],
    "sg:phone":"+1 847 382 2240",
    "sg:postcode":"60010",
    "sg:province":"IL",
    "sg:tags":[
        "machine",
        "metalworking",
        "tool"
    ],
    "wof:name":"Norman/Wills Machinery Co",
    "wof:placetype":"venue"
},
  "geometry": {"coordinates":[-88.137728,42.147589],"type":"Point"}
}