{
  "type": "Feature",
  "properties": {
    "iso:country":"US",
    "sg:address":"7831 Giltner Rd",
    "sg:city":"Brookport",
    "sg:classifiers":[
        {
            "category":"Shopping",
            "subcategory":"Bicycles & Sporting Goods",
            "type":"Retail Goods"
        }
    ],
    "sg:phone":"+1   ",
    "sg:postcode":"62910",
    "sg:province":"IL",
    "wof:name":"Guys & Gals Athletics",
    "wof:placetype":"venue"
},
  "geometry": {"coordinates":[-88.574128,37.144659],"type":"Point"}
}