{
  "type": "Feature",
  "properties": {
    "iso:country":"US",
    "sg:address":"2154 E 71st St",
    "sg:city":"Chicago",
    "sg:classifiers":[
        {
            "category":"Shopping",
            "subcategory":"Beauty & Cosmetics",
            "type":"Retail Goods"
        },
        {
            "category":"Personal",
            "subcategory":"Skin Care",
            "type":"Services"
        },
        {
            "category":"Professional",
            "subcategory":"Management & Consulting",
            "type":"Services"
        }
    ],
    "sg:phone":"+1 773 643 1425",
    "sg:postcode":"60649",
    "sg:province":"IL",
    "sg:tags":[
        "life",
        "coach",
        "supply"
    ],
    "sg:website":"www.thescentuary.com",
    "wof:name":"The Scentuary",
    "wof:placetype":"venue"
},
  "geometry": {"coordinates":[-87.57198099999999,41.766287],"type":"Point"}
}