{
  "type": "Feature",
  "properties": {
    "iso:country":"US",
    "sg:address":"440 N Wells Street",
    "sg:city":"Chicago",
    "sg:classifiers":[
        {
            "category":"Banks & Credit Unions",
            "subcategory":"Investment Brokerage",
            "type":"Services"
        }
    ],
    "sg:phone":"+1 312 670 0970",
    "sg:postcode":"60610",
    "sg:province":"IL",
    "sg:tags":[
        "investing"
    ],
    "wof:name":"Thomas F White",
    "wof:placetype":"venue"
},
  "geometry": {"coordinates":[-87.634077,41.890126],"type":"Point"}
}