{
  "type": "Feature",
  "properties": {
    "iso:country":"US",
    "sg:address":"601 10th St",
    "sg:city":"North Chicago",
    "sg:classifiers":[
        {
            "category":"Organizations",
            "subcategory":"Non-profit Organization",
            "type":"Services"
        }
    ],
    "sg:phone":"+1 847 473 0457",
    "sg:postcode":"60064",
    "sg:province":"IL",
    "sg:tags":[
        "charitable",
        "institution"
    ],
    "wof:name":"Catholic Charities",
    "wof:placetype":"venue"
},
  "geometry": {"coordinates":[-87.83922200000001,42.341285],"type":"Point"}
}