{
  "type": "Feature",
  "properties": {
    "iso:country":"US",
    "sg:address":"728 N Prospect St",
    "sg:city":"Rockford",
    "sg:classifiers":[
        {
            "category":"Insurance",
            "subcategory":"Insurance Agent",
            "type":"Services"
        }
    ],
    "sg:phone":"+1 815 965 1259",
    "sg:postcode":"61107",
    "sg:province":"IL",
    "wof:name":"Northwestern Mutual Financial",
    "wof:placetype":"venue"
},
  "geometry": {"coordinates":[-89.068139,42.276483],"type":"Point"}
}