{
  "type": "Feature",
  "properties": {
    "addr:full":"225 Sheridan St Rockford IL 61103",
    "addr:housenumber":"225",
    "addr:postcode":"61103",
    "addr:street":"Sheridan St",
    "iso:country":"US",
    "sg:address":"225 Sheridan St",
    "sg:city":"Rockford",
    "sg:classifiers":[
        {
            "category":"Professional",
            "subcategory":"Art Services",
            "type":"Services"
        }
    ],
    "sg:phone":"+1 815 963 2089",
    "sg:postcode":"61103",
    "sg:province":"IL",
    "sg:tags":[
        "artist"
    ],
    "sg:website":"www.lasalledesigngraphics.com",
    "wof:name":"F Patrick Lasalle Design",
    "wof:placetype":"venue"
},
  "geometry": {"coordinates":[-89.076059,42.28529],"type":"Point"}
}