{
  "type": "Feature",
  "properties": {
    "addr:full":"2168 Randall Rd Carpentersville IL 60110",
    "addr:housenumber":"2168",
    "addr:postcode":"60110",
    "addr:street":"Randall Rd",
    "iso:country":"US",
    "sg:address":"2168 Randall Rd",
    "sg:city":"Carpentersville",
    "sg:classifiers":[
        {
            "category":"Coffee & Tea",
            "type":"Food & Drink"
        }
    ],
    "sg:menulink":"http://www.allmenus.com/il/dundee/221093-caribou-coffee/menu/",
    "sg:phone":"+1 847 836 9450",
    "sg:postcode":"60110",
    "sg:province":"IL",
    "sg:tags":[
        "american",
        "diner"
    ],
    "wof:name":"Caribou Coffee",
    "wof:placetype":"venue"
},
  "geometry": {"coordinates":[-88.335059,42.119096],"type":"Point"}
}