{
  "type": "Feature",
  "properties": {
    "iso:country":"US",
    "sg:address":"2702 N Prospect Ave",
    "sg:city":"Champaign",
    "sg:classifiers":[
        {
            "category":"Coffee & Tea",
            "type":"Food & Drink"
        }
    ],
    "sg:menulink":"http://www.allmenus.com/il/champaign-city/112322-starbucks-coffee/menu/",
    "sg:phone":"+1 217 398 0821",
    "sg:postcode":"61822",
    "sg:province":"IL",
    "sg:tags":[
        "american"
    ],
    "wof:name":"Starbucks Coffee",
    "wof:placetype":"venue"
},
  "geometry": {"coordinates":[-88.257969,40.148523],"type":"Point"}
}