{
  "type": "Feature",
  "properties": {
    "iso:country":"US",
    "sg:address":"3435 Burr Oak Ave",
    "sg:city":"Blue Island",
    "sg:classifiers":[
        {
            "category":"Autos & Motor Vehicles",
            "subcategory":"Automobile Sales",
            "type":"Retail Goods"
        }
    ],
    "sg:phone":"+1   ",
    "sg:postcode":"60406",
    "sg:province":"IL",
    "sg:tags":[
        "used"
    ],
    "wof:name":"Blue Island Auto Sales Inc",
    "wof:placetype":"venue"
},
  "geometry": {"coordinates":[-87.70732,41.662192],"type":"Point"}
}