{
  "type": "Feature",
  "properties": {
    "iso:country":"US",
    "sg:address":"6120 Godfrey Rd",
    "sg:city":"Godfrey",
    "sg:classifiers":[
        {
            "category":"Insurance",
            "subcategory":"Insurance Agent",
            "type":"Services"
        },
        {
            "category":"Insurance",
            "subcategory":"Hazard Insurance",
            "type":"Services"
        },
        {
            "category":"Insurance",
            "subcategory":"Title Insurance",
            "type":"Services"
        },
        {
            "category":"Insurance",
            "subcategory":"Life Insurance",
            "type":"Services"
        }
    ],
    "sg:phone":"+1 618 466 7600",
    "sg:postcode":"62035",
    "sg:province":"IL",
    "sg:tags":[
        "business",
        "auto",
        "commercial",
        "homeowner",
        "motorcycle",
        "renter"
    ],
    "wof:name":"Allstate Insurance Company - Genell Mills",
    "wof:placetype":"venue"
},
  "geometry": {"coordinates":[-90.190773,38.956183],"type":"Point"}
}