{
  "type": "Feature",
  "properties": {
    "addr:full":"6410 W 74th St Chicago IL 60638",
    "addr:housenumber":"6410",
    "addr:postcode":"60638",
    "addr:street":"W 74Th St",
    "iso:country":"US",
    "sg:address":"6410 W 74th St",
    "sg:city":"Chicago",
    "sg:classifiers":[
        {
            "category":"Manufacturing",
            "subcategory":"Motor Vehicles & Parts",
            "type":"Manufacturing & Wholesale Goods"
        },
        {
            "category":"Autos & Motor Vehicles",
            "subcategory":"Auto Supplies",
            "type":"Retail Goods"
        }
    ],
    "sg:phone":"+1 773 788 9794",
    "sg:postcode":"60638",
    "sg:province":"IL",
    "sg:tags":[
        "automobile",
        "driveshaft"
    ],
    "wof:name":"Power Plus Products",
    "wof:placetype":"venue"
},
  "geometry": {"coordinates":[-87.784747,41.757465],"type":"Point"}
}