{
  "type": "Feature",
  "properties": {
    "addr:full":"8520 Pine St Orland Park IL 60462",
    "addr:housenumber":"8520",
    "addr:postcode":"60462",
    "addr:street":"Pine St",
    "iso:country":"US",
    "sg:address":"8520 Pine St",
    "sg:city":"Orland Park",
    "sg:classifiers":[
        {
            "category":"Professional",
            "subcategory":"Computer Services",
            "type":"Services"
        }
    ],
    "sg:phone":"+1 708 349 3733",
    "sg:postcode":"60462",
    "sg:province":"IL",
    "sg:tags":[
        "integrator",
        "system"
    ],
    "wof:name":"Pse Systems Inc",
    "wof:placetype":"venue"
},
  "geometry": {"coordinates":[-87.830783,41.643186],"type":"Point"}
}