{
  "type": "Feature",
  "properties": {
    "iso:country":"US",
    "sg:address":"2423 W 59th St",
    "sg:city":"Chicago",
    "sg:classifiers":[
        {
            "category":"Retail",
            "subcategory":"Auto Repair",
            "type":"Services"
        }
    ],
    "sg:phone":"+1 773 863 0266",
    "sg:postcode":"60629",
    "sg:province":"IL",
    "sg:tags":[
        "body",
        "painting",
        "repairing",
        "automobile"
    ],
    "wof:name":"Jm Autobody Repair",
    "wof:placetype":"venue"
},
  "geometry": {"coordinates":[-87.68479499999999,41.786541],"type":"Point"}
}