{
  "type": "Feature",
  "properties": {
    "iso:country":"US",
    "sg:address":"3157 Dundee Rd",
    "sg:city":"Northbrook",
    "sg:classifiers":[
        {
            "category":"Health Services",
            "subcategory":"Doctor",
            "type":"Services"
        }
    ],
    "sg:phone":"+1 847 480 2292",
    "sg:postcode":"60062",
    "sg:province":"IL",
    "sg:tags":[
        "dentist"
    ],
    "wof:name":"Dundee Dental Ctr",
    "wof:placetype":"venue"
},
  "geometry": {"coordinates":[-87.857758,42.13827],"type":"Point"}
}