{
  "type": "Feature",
  "properties": {
    "iso:country":"US",
    "sg:address":"2621 Columbia Lakes Dr",
    "sg:city":"Columbia",
    "sg:classifiers":[
        {
            "category":"Professional",
            "subcategory":"Business Services",
            "type":"Services"
        }
    ],
    "sg:phone":"+1 618 281 6554",
    "sg:postcode":"62236",
    "sg:province":"IL",
    "wof:name":"Tammy Wampler",
    "wof:placetype":"venue"
},
  "geometry": {"coordinates":[-90.221386,38.469191],"type":"Point"}
}