{
  "type": "Feature",
  "properties": {
    "addr:full":"375 Cimarron Dr W Aurora IL 60504",
    "addr:housenumber":"375",
    "addr:postcode":"60504",
    "addr:street":"Cimarron Dr W",
    "iso:country":"US",
    "sg:address":"375 Cimarron Dr W",
    "sg:city":"Aurora",
    "sg:classifiers":[
        {
            "category":"Professional",
            "subcategory":"Business Services",
            "type":"Services"
        }
    ],
    "sg:phone":"+1 630 978 7557",
    "sg:postcode":"60504",
    "sg:province":"IL",
    "wof:name":"Phyls Memories By Design Studi",
    "wof:placetype":"venue"
},
  "geometry": {"coordinates":[-88.24623200000001,41.748039],"type":"Point"}
}