{
  "type": "Feature",
  "properties": {
    "iso:country":"US",
    "sg:address":"5900 W Ogden Ave",
    "sg:city":"Cicero",
    "sg:classifiers":[
        {
            "category":"Manufacturing",
            "subcategory":"Tools & Machinery",
            "type":"Manufacturing & Wholesale Goods"
        }
    ],
    "sg:phone":"+1 708 656 7800",
    "sg:postcode":"60804",
    "sg:province":"IL",
    "sg:tags":[
        "pumps-wholesale",
        "manufacturer"
    ],
    "wof:name":"Industrial Filter & Pump Manufacturing Co. Inc.",
    "wof:placetype":"venue"
},
  "geometry": {"coordinates":[-87.770813,41.83485],"type":"Point"}
}