{
  "type": "Feature",
  "properties": {
    "addr:full":"595 Gundersen Dr Carol Stream IL 60188",
    "addr:housenumber":"595",
    "addr:postcode":"60188",
    "addr:street":"Gundersen Dr",
    "iso:country":"US",
    "sg:address":"595 Gundersen Dr",
    "sg:city":"Carol Stream",
    "sg:classifiers":[
        {
            "category":"Real Estate",
            "subcategory":"Real Estate Operator",
            "type":"Services"
        }
    ],
    "sg:phone":"+1 630 682 8569",
    "sg:postcode":"60188",
    "sg:province":"IL",
    "sg:tags":[
        "apartment"
    ],
    "wof:name":"French Quarter Apts",
    "wof:placetype":"venue"
},
  "geometry": {"coordinates":[-88.097763,41.89394],"type":"Point"}
}