{
  "type": "Feature",
  "properties": {
    "iso:country":"US",
    "sg:address":"2391 N Hicks Rd",
    "sg:city":"Palatine",
    "sg:classifiers":[
        {
            "category":"Food & Beverages",
            "subcategory":"Groceries & Convenience Stores",
            "type":"Retail Goods"
        }
    ],
    "sg:phone":"+1   ",
    "sg:postcode":"60074",
    "sg:province":"IL",
    "wof:name":"Convenient Food Mart",
    "wof:placetype":"venue"
},
  "geometry": {"coordinates":[-88.029197,42.152765],"type":"Point"}
}