{
  "type": "Feature",
  "properties": {
    "iso:country":"US",
    "sg:address":"1406 SW 3rd Ave",
    "sg:city":"Aledo",
    "sg:classifiers":[
        {
            "category":"Restaurant",
            "type":"Food & Drink"
        }
    ],
    "sg:phone":"+1 309 582 2040",
    "sg:postcode":"61231",
    "sg:province":"IL",
    "sg:tags":[
        "banquet",
        "rooms"
    ],
    "wof:name":"Town & Country Restaurant",
    "wof:placetype":"venue"
},
  "geometry": {"coordinates":[-90.752359,41.188538],"type":"Point"}
}