{
  "type": "Feature",
  "properties": {
    "iso:country":"US",
    "sg:address":"207 N Main St",
    "sg:city":"Mackinaw",
    "sg:classifiers":[
        {
            "category":"Shopping",
            "subcategory":"Gifts & Souvenirs",
            "type":"Retail Goods"
        }
    ],
    "sg:phone":"+1   ",
    "sg:postcode":"61755",
    "sg:province":"IL",
    "sg:tags":[
        "floral",
        "shop"
    ],
    "wof:name":"Garden Gate Floral Inc",
    "wof:placetype":"venue"
},
  "geometry": {"coordinates":[-89.359206,40.53882],"type":"Point"}
}