{
  "type": "Feature",
  "properties": {
    "addr:full":"3757 W 34th St Chicago IL 60623",
    "addr:housenumber":"3757",
    "addr:postcode":"60623",
    "addr:street":"W 34Th St",
    "iso:country":"US",
    "sg:address":"3757 W 34th St",
    "sg:city":"Chicago",
    "sg:classifiers":[
        {
            "category":"Professional",
            "subcategory":"Engineering",
            "type":"Services"
        },
        {
            "category":"Professional",
            "subcategory":"Management & Consulting",
            "type":"Services"
        }
    ],
    "sg:phone":"+1 773 847 5375",
    "sg:postcode":"60623",
    "sg:province":"IL",
    "sg:tags":[
        "consultant",
        "ecological",
        "engineer",
        "environmental"
    ],
    "sg:website":"http://www.republicservices.com/",
    "wof:name":"Republic Services, Inc.",
    "wof:placetype":"venue"
},
  "geometry": {"coordinates":[-87.71774600000001,41.831563],"type":"Point"}
}