{
  "type": "Feature",
  "properties": {
    "addr:full":"4901 W 79th St Ste 5 Burbank IL 60459",
    "addr:housenumber":"4901",
    "addr:postcode":"60459",
    "addr:street":"W 79Th St Ste 5",
    "iso:country":"US",
    "sg:address":"4901 W 79th St Ste 5",
    "sg:city":"Burbank",
    "sg:classifiers":[
        {
            "category":"Health Services",
            "subcategory":"Doctor",
            "type":"Services"
        }
    ],
    "sg:phone":"+1 708 636 1177",
    "sg:postcode":"60459",
    "sg:province":"IL",
    "wof:name":"Ramadurai Jayanthi R MD Sc",
    "wof:placetype":"venue"
},
  "geometry": {"coordinates":[-87.744102,41.749001],"type":"Point"}
}