{
  "type": "Feature",
  "properties": {
    "addr:full":"1644 N. Honore Suite 105 Chicago IL 60622",
    "addr:housenumber":"1644",
    "addr:postcode":"60622",
    "addr:street":"N. Honore Suite 105",
    "iso:country":"US",
    "sg:address":"1644 N. Honore Suite 105",
    "sg:city":"Chicago",
    "sg:classifiers":[
        {
            "category":"Professional",
            "subcategory":"Computer Services",
            "type":"Services"
        }
    ],
    "sg:phone":"+1 773 862 4246",
    "sg:postcode":"60622",
    "sg:province":"IL",
    "sg:tags":[
        "live-event-management-software",
        "vip-ticketing-solutions",
        "live-event-marketplace"
    ],
    "sg:website":"http://www.eventric.com",
    "wof:name":"Eventric",
    "wof:placetype":"venue"
},
  "geometry": {"coordinates":[-87.673906,41.911467],"type":"Point"}
}