{
  "type": "Feature",
  "properties": {
    "addr:full":"270 E Westminster Ave Lake Forest IL 60045",
    "addr:housenumber":"270",
    "addr:postcode":"60045",
    "addr:street":"E Westminster Ave",
    "iso:country":"US",
    "sg:address":"270 E Westminster Ave",
    "sg:city":"Lake Forest",
    "sg:classifiers":[
        {
            "category":"Professional",
            "type":"Services"
        },
        {
            "category":"Banks & Credit Unions",
            "subcategory":"Financial Services",
            "type":"Services"
        }
    ],
    "sg:phone":"+1 847 283 0000",
    "sg:postcode":"60045",
    "sg:province":"IL",
    "sg:tags":[
        "establishment",
        "investor"
    ],
    "wof:name":"Palmer-Florida Corporation",
    "wof:placetype":"venue"
},
  "geometry": {"coordinates":[-87.84080400000001,42.253251],"type":"Point"}
}