{
  "type": "Feature",
  "properties": {
    "addr:full":"2343 Vista Dr Woodridge IL 60517",
    "addr:housenumber":"2343",
    "addr:postcode":"60517",
    "addr:street":"Vista Dr",
    "iso:country":"US",
    "sg:address":"2343 Vista Dr",
    "sg:city":"Woodridge",
    "sg:classifiers":[
        {
            "category":"Retail",
            "subcategory":"Laundry & Dry Cleaning",
            "type":"Services"
        }
    ],
    "sg:phone":"+1 630 963 7235",
    "sg:postcode":"60517",
    "sg:province":"IL",
    "sg:tags":[
        "drycleaning",
        "plant"
    ],
    "wof:name":"Lucky Cleaners",
    "wof:placetype":"venue"
},
  "geometry": {"coordinates":[-88.037356,41.761101],"type":"Point"}
}