{
  "type": "Feature",
  "properties": {
    "iso:country":"US",
    "sg:address":"12930 Beloit Rd",
    "sg:city":"Caledonia",
    "sg:classifiers":[
        {
            "category":"Farming",
            "subcategory":"Dairy Farm",
            "type":"Manufacturing & Wholesale Goods"
        }
    ],
    "sg:phone":"+1 815 885 3271",
    "sg:postcode":"61011",
    "sg:province":"IL",
    "wof:name":"Dan Salley",
    "wof:placetype":"venue"
},
  "geometry": {"coordinates":[-88.936082,42.357649],"type":"Point"}
}