{
  "type": "Feature",
  "properties": {
    "iso:country":"US",
    "sg:address":"2124 W 22nd Pl",
    "sg:city":"Chicago",
    "sg:classifiers":[
        {
            "category":"Place Of Worship",
            "subcategory":"Church",
            "type":"Public Place"
        },
        {
            "category":"Place Of Worship",
            "type":"Public Place"
        }
    ],
    "sg:phone":"+1 773 254 4226",
    "sg:postcode":"60608",
    "sg:province":"IL",
    "sg:tags":[
        "churches-catholic-traditional",
        "churches-catholic"
    ],
    "wof:name":"Claret Casa",
    "wof:placetype":"venue"
},
  "geometry": {"coordinates":[-87.678859,41.85122],"type":"Point"}
}