{
  "type": "Feature",
  "properties": {
    "addr:full":"1325 N Mason Ave Chicago IL 60651",
    "addr:housenumber":"1325",
    "addr:postcode":"60651",
    "addr:street":"N Mason Ave",
    "iso:country":"US",
    "sg:address":"1325 N Mason Ave",
    "sg:city":"Chicago",
    "sg:classifiers":[
        {
            "category":"Building & Trades",
            "subcategory":"Plumbing",
            "type":"Services"
        }
    ],
    "sg:phone":"+1 773 533 9153",
    "sg:postcode":"60651",
    "sg:province":"IL",
    "sg:tags":[
        "heating",
        "contractor"
    ],
    "wof:name":"Burns Heating & Air Cond",
    "wof:placetype":"venue"
},
  "geometry": {"coordinates":[-87.774179,41.9052],"type":"Point"}
}