{
  "type": "Feature",
  "properties": {
    "iso:country":"US",
    "sg:address":"154 3rd St",
    "sg:city":"La Salle",
    "sg:classifiers":[
        {
            "category":"Restaurant",
            "type":"Food & Drink"
        }
    ],
    "sg:phone":"+1 815 223 6650",
    "sg:postcode":"61301",
    "sg:province":"IL",
    "wof:name":"Papa's Hamburgers & Soft Serv",
    "wof:placetype":"venue"
},
  "geometry": {"coordinates":[-89.103358,41.329564],"type":"Point"}
}