{
  "type": "Feature",
  "properties": {
    "iso:country":"US",
    "sg:address":"124 W Santa Fe Ave",
    "sg:city":"Toluca",
    "sg:classifiers":[
        {
            "category":"Food & Beverages",
            "subcategory":"Supermarket",
            "type":"Retail Goods"
        },
        {
            "category":"Food & Beverages",
            "subcategory":"Groceries & Convenience Stores",
            "type":"Retail Goods"
        }
    ],
    "sg:phone":"+1 815 452 2336",
    "sg:postcode":"61369",
    "sg:province":"IL",
    "sg:tags":[
        "super"
    ],
    "wof:name":"Toluca Iga",
    "wof:placetype":"venue"
},
  "geometry": {"coordinates":[-89.134203,41.001891],"type":"Point"}
}