{
  "type": "Feature",
  "properties": {
    "iso:country":"US",
    "sg:address":"4343 Old Grand Ave",
    "sg:city":"Gurnee",
    "sg:classifiers":[
        {
            "category":"Insurance",
            "subcategory":"Insurance Agent",
            "type":"Services"
        },
        {
            "category":"Insurance",
            "subcategory":"Hazard Insurance",
            "type":"Services"
        },
        {
            "category":"Insurance",
            "subcategory":"Title Insurance",
            "type":"Services"
        }
    ],
    "sg:phone":"+1 847 599 8600",
    "sg:postcode":"60031",
    "sg:province":"IL",
    "sg:tags":[
        "auto",
        "homeowner"
    ],
    "sg:website":"http://apps.amfam.com/agentlocator/CCHOATE?sourceid=yp3",
    "wof:name":"American Family Insurance- Chuck Choate",
    "wof:placetype":"venue"
},
  "geometry": {"coordinates":[-87.91083,42.370962],"type":"Point"}
}