{
  "type": "Feature",
  "properties": {
    "addr:full":"5606 N Ridge Ave Chicago IL 60660",
    "addr:housenumber":"5606",
    "addr:postcode":"60660",
    "addr:street":"N Ridge Ave",
    "iso:country":"US",
    "sg:address":"5606 N Ridge Ave",
    "sg:city":"Chicago",
    "sg:classifiers":[
        {
            "category":"Shopping",
            "subcategory":"Hobbies, Toys, & Games",
            "type":"Retail Goods"
        }
    ],
    "sg:phone":"+1 773 907 9550",
    "sg:postcode":"60660",
    "sg:province":"IL",
    "wof:name":"El Torbellino",
    "wof:placetype":"venue"
},
  "geometry": {"coordinates":[-87.66109,41.984149],"type":"Point"}
}