{
  "type": "Feature",
  "properties": {
    "addr:full":"4014 W 26th St Chicago IL 60623",
    "addr:housenumber":"4014",
    "addr:postcode":"60623",
    "addr:street":"W 26Th St",
    "iso:country":"US",
    "sg:address":"4014 W 26th St",
    "sg:city":"Chicago",
    "sg:classifiers":[
        {
            "category":"Professional",
            "subcategory":"Advertising",
            "type":"Services"
        }
    ],
    "sg:phone":"+1 773 577 1795",
    "sg:postcode":"60623",
    "sg:province":"IL",
    "sg:tags":[
        "advertising-telephone",
        "fax",
        "telemarketing"
    ],
    "wof:name":"Zeus International Net Corporation.",
    "wof:placetype":"venue"
},
  "geometry": {"coordinates":[-87.725182,41.844261],"type":"Point"}
}