{
  "type": "Feature",
  "properties": {
    "addr:full":"6901 Cardnal Ln Charleston IL 61920",
    "addr:housenumber":"6901",
    "addr:postcode":"61920",
    "addr:street":"Cardnal Ln",
    "iso:country":"US",
    "sg:address":"6901 Cardnal Ln",
    "sg:city":"Charleston",
    "sg:classifiers":[
        {
            "category":"Manufacturing",
            "subcategory":"Jewelry",
            "type":"Manufacturing & Wholesale Goods"
        }
    ],
    "sg:phone":"+1 217 348 1538",
    "sg:postcode":"61920",
    "sg:province":"IL",
    "sg:tags":[
        "costume",
        "mfg"
    ],
    "wof:name":"Earthstar Creations",
    "wof:placetype":"venue"
},
  "geometry": {"coordinates":[-88.137022,39.476052],"type":"Point"}
}