{
  "type": "Feature",
  "properties": {
    "iso:country":"US",
    "sg:address":"1825 Lemar Ave Apt A",
    "sg:city":"Evanston",
    "sg:classifiers":[
        {
            "category":"Shopping",
            "type":"Retail Goods"
        }
    ],
    "sg:phone":"+1 847 475 4537",
    "sg:postcode":"60201",
    "sg:province":"IL",
    "sg:tags":[
        "item",
        "boutique"
    ],
    "wof:name":"Sherria S Boutique",
    "wof:placetype":"venue"
},
  "geometry": {"coordinates":[-87.706034,42.050521],"type":"Point"}
}