{
  "type": "Feature",
  "properties": {
    "iso:country":"US",
    "sg:address":"1150 Davis Rd Ste F",
    "sg:city":"Elgin",
    "sg:classifiers":[
        {
            "category":"Professional",
            "type":"Services"
        },
        {
            "category":"Professional",
            "subcategory":"Advertising",
            "type":"Services"
        }
    ],
    "sg:phone":"+1 847 468 9800",
    "sg:postcode":"60123",
    "sg:province":"IL",
    "sg:tags":[
        "product",
        "fair",
        "trade",
        "exposition",
        "advertising-promotional",
        "shows"
    ],
    "sg:website":"http://www.fulfillmentnetwork.com",
    "wof:name":"The Fulfillment Network Inc",
    "wof:placetype":"venue"
},
  "geometry": {"coordinates":[-88.301277,42.067811],"type":"Point"}
}