{
  "type": "Feature",
  "properties": {
    "iso:country":"US",
    "sg:address":"11627 W State Rte 72",
    "sg:city":"Forreston",
    "sg:classifiers":[
        {
            "category":"Shopping",
            "subcategory":"Used Merchandise",
            "type":"Retail Goods"
        }
    ],
    "sg:phone":"+1 815 938 3120",
    "sg:postcode":"61030",
    "sg:province":"IL",
    "sg:tags":[
        "antique"
    ],
    "wof:name":"ACS",
    "wof:placetype":"venue"
},
  "geometry": {"coordinates":[-89.561851,42.127769],"type":"Point"}
}