{
  "type": "Feature",
  "properties": {
    "iso:country":"US",
    "sg:address":"183 N Monterey Dr",
    "sg:city":"Kankakee",
    "sg:classifiers":[
        {
            "category":"Professional",
            "subcategory":"Business Services",
            "type":"Services"
        }
    ],
    "sg:phone":"+1 815 939 3486",
    "sg:postcode":"60901",
    "sg:province":"IL",
    "wof:name":"Christopher Auto Appraisal",
    "wof:placetype":"venue"
},
  "geometry": {"coordinates":[-87.94388,41.120409],"type":"Point"}
}