{
  "type": "Feature",
  "properties": {
    "iso:country":"US",
    "sg:address":"1434 Waukegan Rd",
    "sg:city":"Glenview",
    "sg:classifiers":[
        {
            "category":"Restaurant",
            "type":"Food & Drink"
        }
    ],
    "sg:phone":"+1 847 730 5132",
    "sg:postcode":"60025",
    "sg:province":"IL",
    "sg:tags":[
        "house",
        "steak",
        "barbecue"
    ],
    "wof:name":"Rail Good Bbq",
    "wof:placetype":"venue"
},
  "geometry": {"coordinates":[-87.798412,42.080791],"type":"Point"}
}