{
  "type": "Feature",
  "properties": {
    "iso:country":"US",
    "sg:address":"415 3rd St",
    "sg:city":"Savanna",
    "sg:classifiers":[
        {
            "category":"Organizations",
            "subcategory":"Religious Organization",
            "type":"Services"
        }
    ],
    "sg:phone":"+1 815 273 3251",
    "sg:postcode":"61074",
    "sg:province":"IL",
    "sg:tags":[
        "church"
    ],
    "wof:name":"Assembly Of God Church",
    "wof:placetype":"venue"
},
  "geometry": {"coordinates":[-90.155776,42.095261],"type":"Point"}
}