{
  "type": "Feature",
  "properties": {
    "iso:country":"US",
    "sg:address":"135 W Adams St",
    "sg:city":"Villa Park",
    "sg:classifiers":[
        {
            "category":"Professional",
            "subcategory":"Management & Consulting",
            "type":"Services"
        }
    ],
    "sg:phone":"+1 630 941 8840",
    "sg:postcode":"60181",
    "sg:province":"IL",
    "sg:tags":[
        "party",
        "planning"
    ],
    "wof:name":"A & B Party Planners",
    "wof:placetype":"venue"
},
  "geometry": {"coordinates":[-87.983079,41.872522],"type":"Point"}
}