{
  "type": "Feature",
  "properties": {
    "addr:full":"816 W Main St Thomson IL 61285",
    "addr:housenumber":"816",
    "addr:postcode":"61285",
    "addr:street":"W Main St",
    "iso:country":"US",
    "sg:address":"816 W Main St",
    "sg:city":"Thomson",
    "sg:classifiers":[
        {
            "category":"Personal",
            "subcategory":"Beauty Salon",
            "type":"Services"
        }
    ],
    "sg:phone":"+1 815 259 4247",
    "sg:postcode":"61285",
    "sg:province":"IL",
    "wof:name":"Hair For You",
    "wof:placetype":"venue"
},
  "geometry": {"coordinates":[-90.09957,41.958896],"type":"Point"}
}