{
  "type": "Feature",
  "properties": {
    "iso:country":"US",
    "sg:address":"10 E Main St",
    "sg:city":"Lake Zurich",
    "sg:classifiers":[
        {
            "category":"Building & Trades",
            "subcategory":"Construction",
            "type":"Services"
        }
    ],
    "sg:phone":"+1 847 550 9750",
    "sg:postcode":"60047",
    "sg:province":"IL",
    "sg:tags":[
        "resurfacing",
        "refinishing",
        "floor"
    ],
    "wof:name":"C B Flooring",
    "wof:placetype":"venue"
},
  "geometry": {"coordinates":[-88.091126,42.197494],"type":"Point"}
}