{
  "type": "Feature",
  "properties": {
    "addr:full":"6118 N Bernard St Chicago IL 60659",
    "addr:housenumber":"6118",
    "addr:postcode":"60659",
    "addr:street":"N Bernard St",
    "iso:country":"US",
    "sg:address":"6118 N Bernard St",
    "sg:city":"Chicago",
    "sg:classifiers":[
        {
            "category":"Professional",
            "subcategory":"Lawyer & Legal Services",
            "type":"Services"
        }
    ],
    "sg:phone":"+1 773 478 9459",
    "sg:postcode":"60659",
    "sg:province":"IL",
    "wof:name":"Runo Remedios Attorney",
    "wof:placetype":"venue"
},
  "geometry": {"coordinates":[-87.715378,41.993468],"type":"Point"}
}