{
  "type": "Feature",
  "properties": {
    "iso:country":"US",
    "sg:address":"1024 N Taylor Ave",
    "sg:city":"Oak Park",
    "sg:classifiers":[
        {
            "category":"Professional",
            "subcategory":"Art Services",
            "type":"Services"
        }
    ],
    "sg:phone":"+1 708 848 5887",
    "sg:postcode":"60302",
    "sg:province":"IL",
    "sg:tags":[
        "photography",
        "commercial"
    ],
    "wof:name":"Wedgworth Images",
    "wof:placetype":"venue"
},
  "geometry": {"coordinates":[-87.77784200000001,41.905372],"type":"Point"}
}