{
  "type": "Feature",
  "properties": {
    "iso:country":"US",
    "sg:address":"776 Chidester Ave",
    "sg:city":"Glen Ellyn",
    "sg:classifiers":[
        {
            "category":"Building & Trades",
            "subcategory":"Construction",
            "type":"Services"
        }
    ],
    "sg:phone":"+1 630 920 7300",
    "sg:postcode":"60137",
    "sg:province":"IL",
    "sg:tags":[
        "general",
        "contractor"
    ],
    "wof:name":"Construction Concepts",
    "wof:placetype":"venue"
},
  "geometry": {"coordinates":[-88.053794,41.886822],"type":"Point"}
}