{
  "type": "Feature",
  "properties": {
    "addr:full":"2241 Rt 59 West Chicago IL 60185",
    "addr:housenumber":"2241",
    "addr:postcode":"60185",
    "addr:street":"Rt 59 West",
    "iso:country":"US",
    "sg:address":"2241 Rt 59",
    "sg:city":"West Chicago",
    "sg:classifiers":[
        {
            "category":"Retail",
            "subcategory":"Event Space",
            "type":"Services"
        },
        {
            "category":"Sports & Exercise",
            "subcategory":"Golf",
            "type":"Entertainment"
        }
    ],
    "sg:phone":"+1 630 231 3100",
    "sg:postcode":"60185",
    "sg:province":"IL",
    "sg:tags":[
        "venue"
    ],
    "sg:website":"www.standrewsgc.com",
    "wof:name":"St. Andrews Golf & Country Club",
    "wof:placetype":"venue"
},
  "geometry": {"coordinates":[-88.20886900000001,41.921834],"type":"Point"}
}