{
  "type": "Feature",
  "properties": {
    "iso:country":"US",
    "sg:address":"7021 W 153rd St",
    "sg:city":"Orland Park",
    "sg:classifiers":[
        {
            "category":"Professional",
            "subcategory":"Lawyer & Legal Services",
            "type":"Services"
        }
    ],
    "sg:phone":"+1 708 687 9300",
    "sg:postcode":"60462",
    "sg:province":"IL",
    "sg:tags":[
        "attorney"
    ],
    "wof:name":"Beranek & De Wilkins",
    "wof:placetype":"venue"
},
  "geometry": {"coordinates":[-87.790416,41.613277],"type":"Point"}
}