{
  "type": "Feature",
  "properties": {
    "iso:country":"US",
    "sg:address":"201 S Milwaukee Ave",
    "sg:city":"Lake Villa",
    "sg:classifiers":[
        {
            "category":"Health Services",
            "subcategory":"Doctor",
            "type":"Services"
        }
    ],
    "sg:phone":"+1 847 356 9009",
    "sg:postcode":"60046",
    "sg:province":"IL",
    "sg:tags":[
        "physician",
        "clinic",
        "surgeon"
    ],
    "wof:name":"Medical Care Ctr",
    "wof:placetype":"venue"
},
  "geometry": {"coordinates":[-88.070134,42.412756],"type":"Point"}
}