{
  "type": "Feature",
  "properties": {
    "iso:country":"US",
    "sg:address":"20130 S Rosewood Dr",
    "sg:city":"Frankfort",
    "sg:classifiers":[
        {
            "category":"Education",
            "subcategory":"School",
            "type":"Public Place"
        }
    ],
    "sg:phone":"+1 815 469 4330",
    "sg:postcode":"60423",
    "sg:province":"IL",
    "wof:name":"Summit Hill Junior High School",
    "wof:placetype":"venue"
},
  "geometry": {"coordinates":[-87.817192,41.52506],"type":"Point"}
}