{
  "type": "Feature",
  "properties": {
    "iso:country":"US",
    "sg:address":"19288 Quiver Beach Rd",
    "sg:city":"Havana",
    "sg:classifiers":[
        {
            "category":"Professional",
            "type":"Services"
        }
    ],
    "sg:phone":"+1 309 543 6872",
    "sg:postcode":"62644",
    "sg:province":"IL",
    "wof:name":"Emergency Services Educators",
    "wof:placetype":"venue"
},
  "geometry": {"coordinates":[-90.03956599999999,40.339811],"type":"Point"}
}