{
  "type": "Feature",
  "properties": {
    "addr:full":"1321 Lake Park Dr Germantown IL 62245",
    "addr:housenumber":"1321",
    "addr:postcode":"62245",
    "addr:street":"Lake Park Dr",
    "iso:country":"US",
    "sg:address":"1321 Lake Park Dr",
    "sg:city":"Germantown",
    "sg:classifiers":[
        {
            "category":"Food & Beverages",
            "subcategory":"Groceries & Convenience Stores",
            "type":"Retail Goods"
        }
    ],
    "sg:phone":"+1 618 523 4126",
    "sg:postcode":"62245",
    "sg:province":"IL",
    "wof:name":"Becker's Convenience Mart",
    "wof:placetype":"venue"
},
  "geometry": {"coordinates":[-89.549406,38.552273],"type":"Point"}
}