{
  "type": "Feature",
  "properties": {
    "iso:country":"US",
    "sg:address":"12841 Western Ave Ste 1",
    "sg:city":"Blue Island",
    "sg:classifiers":[
        {
            "category":"Shopping",
            "subcategory":"Music",
            "type":"Retail Goods"
        }
    ],
    "sg:phone":"+1 708 597 9612",
    "sg:postcode":"60406",
    "sg:province":"IL",
    "sg:tags":[
        "dvd's"
    ],
    "wof:name":"Charlie's Music",
    "wof:placetype":"venue"
},
  "geometry": {"coordinates":[-87.67988200000001,41.659736],"type":"Point"}
}