{
  "type": "Feature",
  "properties": {
    "addr:full":"15410 S 94th Ave Orland Park IL 60467",
    "addr:housenumber":"15410",
    "addr:postcode":"60467",
    "addr:street":"S 94Th Ave",
    "iso:country":"US",
    "sg:address":"15410 S 94th Ave",
    "sg:city":"Orland Park",
    "sg:classifiers":[
        {
            "category":"Restaurant",
            "type":"Food & Drink"
        }
    ],
    "sg:phone":"+1   ",
    "sg:postcode":"60467",
    "sg:province":"IL",
    "sg:tags":[
        "dining"
    ],
    "wof:name":"94 West",
    "wof:placetype":"venue"
},
  "geometry": {"coordinates":[-87.848438,41.613368],"type":"Point"}
}