{
  "type": "Feature",
  "properties": {
    "addr:full":"33 N Dearborn St Chicago IL 60602",
    "addr:housenumber":"33",
    "addr:postcode":"60602",
    "addr:street":"N Dearborn St",
    "iso:country":"US",
    "sg:address":"33 N Dearborn St",
    "sg:city":"Chicago",
    "sg:classifiers":[
        {
            "category":"Professional",
            "subcategory":"Lawyer & Legal Services",
            "type":"Services"
        }
    ],
    "sg:phone":"+1 312 789 5460",
    "sg:postcode":"60602",
    "sg:province":"IL",
    "sg:tags":[
        "attorney",
        "accident",
        "worker",
        "damage",
        "benefit",
        "malpractice",
        "employee",
        "property",
        "compensation",
        "law"
    ],
    "sg:website":"http://www.lane-lane.com",
    "wof:name":"Lane & Lane LLC",
    "wof:placetype":"venue"
},
  "geometry": {"coordinates":[-87.62943300000001,41.882599],"type":"Point"}
}