{
  "type": "Feature",
  "properties": {
    "iso:country":"US",
    "sg:address":"1974 W Lawrence Ave",
    "sg:city":"Chicago",
    "sg:classifiers":[
        {
            "category":"Shopping",
            "subcategory":"Jewelry",
            "type":"Retail Goods"
        }
    ],
    "sg:phone":"+1 773 275 8683",
    "sg:postcode":"60640",
    "sg:province":"IL",
    "wof:name":"Jessica Jewelry Shop II",
    "wof:placetype":"venue"
},
  "geometry": {"coordinates":[-87.67890199999999,41.968899],"type":"Point"}
}