{
  "type": "Feature",
  "properties": {
    "iso:country":"US",
    "sg:address":"1129 W Thorndale Ave",
    "sg:city":"Chicago",
    "sg:classifiers":[
        {
            "category":"Restaurant",
            "type":"Food & Drink"
        }
    ],
    "sg:menulink":"http://www.allmenus.com/il/chicago/209648-grand-china-express/menu/",
    "sg:phone":"+1 773 271 3010",
    "sg:postcode":"60660",
    "sg:province":"IL",
    "sg:tags":[
        "asian",
        "chinese"
    ],
    "wof:name":"Grand China Express",
    "wof:placetype":"venue"
},
  "geometry": {"coordinates":[-87.65917899999999,41.98999],"type":"Point"}
}