{
  "type": "Feature",
  "properties": {
    "iso:country":"US",
    "sg:address":"2653 W Division Street",
    "sg:city":"Chicago",
    "sg:classifiers":[
        {
            "category":"Personal",
            "subcategory":"Barber",
            "type":"Services"
        }
    ],
    "sg:phone":"+1 773 235 7685",
    "sg:postcode":"60622",
    "sg:province":"IL",
    "wof:name":"Sportz Kuttz",
    "wof:placetype":"venue"
},
  "geometry": {"coordinates":[-87.693935,41.902837],"type":"Point"}
}