{
  "type": "Feature",
  "properties": {
    "iso:country":"US",
    "sg:address":"2902 N Clark St",
    "sg:city":"Chicago",
    "sg:classifiers":[
        {
            "category":"Home & Garden",
            "subcategory":"Carpets & Floor Coverings",
            "type":"Retail Goods"
        }
    ],
    "sg:phone":"+1 773 883 4410",
    "sg:postcode":"60657",
    "sg:province":"IL",
    "sg:tags":[
        "flooring",
        "carpeting"
    ],
    "sg:website":"www.olsonrug.com/",
    "wof:name":"Olson Rug Company",
    "wof:placetype":"venue"
},
  "geometry": {"coordinates":[-87.64669600000001,41.935022],"type":"Point"}
}