{
  "type": "Feature",
  "properties": {
    "addr:full":"619 Niedringhaus Ave Granite City IL 62040",
    "addr:housenumber":"619",
    "addr:postcode":"62040",
    "addr:street":"Niedringhaus Ave",
    "iso:country":"US",
    "sg:address":"619 Niedringhaus Ave",
    "sg:city":"Granite City",
    "sg:classifiers":[
        {
            "category":"Shopping",
            "subcategory":"Antiques",
            "type":"Retail Goods"
        }
    ],
    "sg:phone":"+1 618 876 5960",
    "sg:postcode":"62040",
    "sg:province":"IL",
    "wof:name":"Heritage Antiques",
    "wof:placetype":"venue"
},
  "geometry": {"coordinates":[-90.168356,38.701597],"type":"Point"}
}