{
  "type": "Feature",
  "properties": {
    "iso:country":"US",
    "sg:address":"2937 N Milwaukee",
    "sg:city":"Chicago",
    "sg:classifiers":[
        {
            "category":"Bars & Pubs",
            "type":"Food & Drink"
        },
        {
            "category":"Community Center",
            "subcategory":"Social",
            "type":"Public Place"
        }
    ],
    "sg:phone":"+1 773 227 2937",
    "sg:postcode":"60618",
    "sg:province":"IL",
    "sg:tags":[
        "club"
    ],
    "sg:website":"www.facebook.com/pages/Moes-Tave...",
    "wof:name":"Moe's Tavern",
    "wof:placetype":"venue"
},
  "geometry": {"coordinates":[-87.71633,41.934867],"type":"Point"}
}