{
  "type": "Feature",
  "properties": {
    "addr:full":"924 Wood Ave Geneva IL 60134",
    "addr:housenumber":"924",
    "addr:postcode":"60134",
    "addr:street":"Wood Ave",
    "iso:country":"US",
    "sg:address":"924 Wood Ave",
    "sg:city":"Geneva",
    "sg:classifiers":[
        {
            "category":"Wholesale",
            "subcategory":"Sporting Goods",
            "type":"Manufacturing & Wholesale Goods"
        }
    ],
    "sg:phone":"+1 630 232 3969",
    "sg:postcode":"60134",
    "sg:province":"IL",
    "sg:tags":[
        "equipment",
        "golf",
        "mfg"
    ],
    "wof:name":"Nicholas Corey Group Inc",
    "wof:placetype":"venue"
},
  "geometry": {"coordinates":[-88.348758,41.876787],"type":"Point"}
}