{
  "type": "Feature",
  "properties": {
    "addr:full":"2222 S Central Ave Cicero IL 60804",
    "addr:housenumber":"2222",
    "addr:postcode":"60804",
    "addr:street":"S Central Ave",
    "iso:country":"US",
    "sg:address":"2222 S Central Ave",
    "sg:city":"Cicero",
    "sg:classifiers":[
        {
            "category":"Manufacturing",
            "subcategory":"Musical Instruments",
            "type":"Manufacturing & Wholesale Goods"
        }
    ],
    "sg:phone":"+1 708 656 1358",
    "sg:postcode":"60804",
    "sg:province":"IL",
    "wof:name":"Discoteca Miravalle",
    "wof:placetype":"venue"
},
  "geometry": {"coordinates":[-87.763859,41.849174],"type":"Point"}
}