{
  "type": "Feature",
  "properties": {
    "iso:country":"US",
    "sg:address":"7380 N 1900 East Rd",
    "sg:city":"Fairbury",
    "sg:classifiers":[
        {
            "category":"Professional",
            "subcategory":"Management & Consulting",
            "type":"Services"
        }
    ],
    "sg:phone":"+1 815 692 2870",
    "sg:postcode":"61739",
    "sg:province":"IL",
    "sg:tags":[
        "farm"
    ],
    "wof:name":"Donna Wessels",
    "wof:placetype":"venue"
},
  "geometry": {"coordinates":[-88.56409499999999,40.734446],"type":"Point"}
}