{
  "type": "Feature",
  "properties": {
    "addr:full":"2425 S Wallace Street Chicago IL 60616",
    "addr:housenumber":"2425",
    "addr:postcode":"60616",
    "addr:street":"S Wallace Street",
    "iso:country":"US",
    "sg:address":"2425 S Wallace Street",
    "sg:city":"Chicago",
    "sg:classifiers":[
        {
            "category":"Food & Beverages",
            "subcategory":"Groceries & Convenience Stores",
            "type":"Retail Goods"
        }
    ],
    "sg:phone":"+1 312 225 4775",
    "sg:postcode":"60616",
    "sg:province":"IL",
    "wof:name":"Oriental Delicacies",
    "wof:placetype":"venue"
},
  "geometry": {"coordinates":[-87.641642,41.848448],"type":"Point"}
}