{
  "type": "Feature",
  "properties": {
    "addr:full":"306 W Golf Rd Libertyville IL 60048",
    "addr:housenumber":"306",
    "addr:postcode":"60048",
    "addr:street":"W Golf Rd",
    "iso:country":"US",
    "sg:address":"306 W Golf Rd",
    "sg:city":"Libertyville",
    "sg:classifiers":[
        {
            "category":"Shopping",
            "subcategory":"Optical Goods",
            "type":"Retail Goods"
        }
    ],
    "sg:phone":"+1 847 680 3315",
    "sg:postcode":"60048",
    "sg:province":"IL",
    "sg:tags":[
        "optician"
    ],
    "wof:name":"Optical Images",
    "wof:placetype":"venue"
},
  "geometry": {"coordinates":[-87.957227,42.27039],"type":"Point"}
}