{
  "type": "Feature",
  "properties": {
    "addr:full":"5 Michigan Ave East Dundee IL 60118",
    "addr:housenumber":"5",
    "addr:postcode":"60118",
    "addr:street":"Michigan Ave",
    "iso:country":"US",
    "sg:address":"5 Michigan Ave",
    "sg:city":"East Dundee",
    "sg:classifiers":[
        {
            "category":"Building & Trades",
            "subcategory":"Cleaning & Sanitation",
            "type":"Services"
        }
    ],
    "sg:phone":"+1 847 428 3152",
    "sg:postcode":"60118",
    "sg:province":"IL",
    "sg:tags":[
        "carpet"
    ],
    "wof:name":"Phil's Cleaning Service A",
    "wof:placetype":"venue"
},
  "geometry": {"coordinates":[-88.28220399999999,42.103001],"type":"Point"}
}