{
  "type": "Feature",
  "properties": {
    "iso:country":"US",
    "sg:address":"111 S Oak St",
    "sg:city":"Nokomis",
    "sg:classifiers":[
        {
            "category":"Professional",
            "subcategory":"Business Services",
            "type":"Services"
        }
    ],
    "sg:phone":"+1 217 563 2786",
    "sg:postcode":"62075",
    "sg:province":"IL",
    "sg:tags":[
        "auction"
    ],
    "wof:name":"Matthews Auctions",
    "wof:placetype":"venue"
},
  "geometry": {"coordinates":[-89.283215,39.302408],"type":"Point"}
}