{
  "type": "Feature",
  "properties": {
    "iso:country":"US",
    "sg:address":"1201 W Blair St",
    "sg:city":"Salem",
    "sg:phone":"+1 618 548 5835",
    "sg:postcode":"62881",
    "sg:province":"IL",
    "sg:tags":[
        "farm",
        "wheat"
    ],
    "wof:name":"Steven Brummel",
    "wof:placetype":"venue"
},
  "geometry": {"coordinates":[-88.96212800000001,38.620089],"type":"Point"}
}