{
  "type": "Feature",
  "properties": {
    "addr:full":"16736 Oketo Ave Tinley Park IL 60477",
    "addr:housenumber":"16736",
    "addr:postcode":"60477",
    "addr:street":"Oketo Ave",
    "iso:country":"US",
    "sg:address":"16736 Oketo Ave",
    "sg:city":"Tinley Park",
    "sg:classifiers":[
        {
            "category":"Building & Trades",
            "subcategory":"Plumbing",
            "type":"Services"
        }
    ],
    "sg:phone":"+1 708 429 3497",
    "sg:postcode":"60477",
    "sg:province":"IL",
    "sg:tags":[
        "contractor",
        "mfg"
    ],
    "wof:name":"Rich N Son Htg Airconditioning",
    "wof:placetype":"venue"
},
  "geometry": {"coordinates":[-87.799206,41.585616],"type":"Point"}
}