{
  "type": "Feature",
  "properties": {
    "iso:country":"US",
    "sg:address":"3827 N Ashland Ave",
    "sg:city":"Chicago",
    "sg:classifiers":[
        {
            "category":"Building & Trades",
            "subcategory":"Locksmith",
            "type":"Services"
        }
    ],
    "sg:phone":"+1 773 349 8988",
    "sg:postcode":"60613",
    "sg:province":"IL",
    "sg:tags":[
        "key"
    ],
    "wof:name":"A1 24 Hour Locksmith Services",
    "wof:placetype":"venue"
},
  "geometry": {"coordinates":[-87.668684,41.951354],"type":"Point"}
}