{
  "type": "Feature",
  "properties": {
    "iso:country":"US",
    "sg:address":"1422 W Morse Ave",
    "sg:city":"Chicago",
    "sg:classifiers":[
        {
            "category":"Fast Food",
            "type":"Food & Drink"
        },
        {
            "category":"Restaurant",
            "type":"Food & Drink"
        },
        {
            "category":"Travel",
            "subcategory":"Bed & Breakfast",
            "type":"Entertainment"
        }
    ],
    "sg:phone":"+1 773 465 8080",
    "sg:postcode":"60626",
    "sg:province":"IL",
    "sg:tags":[
        "grill",
        "style",
        "bar",
        "family",
        "lunch",
        "inn",
        "take",
        "brunch"
    ],
    "wof:name":"Grill Inn",
    "wof:placetype":"venue"
},
  "geometry": {"coordinates":[-87.66653100000001,42.007896],"type":"Point"}
}