{
  "type": "Feature",
  "properties": {
    "addr:full":"1274 N 900E Rd Melvin IL 60952",
    "addr:housenumber":"1274",
    "addr:postcode":"60952",
    "addr:street":"N 900E Rd",
    "iso:country":"US",
    "sg:address":"1274 N 900E Rd",
    "sg:city":"Melvin",
    "sg:classifiers":[
        {
            "category":"Farming",
            "subcategory":"Livestock Farm",
            "type":"Manufacturing & Wholesale Goods"
        },
        {
            "category":"Farming",
            "subcategory":"Farm",
            "type":"Manufacturing & Wholesale Goods"
        }
    ],
    "sg:phone":"+1 217 388 2293",
    "sg:postcode":"60952",
    "sg:province":"IL",
    "wof:name":"R & R Arends",
    "wof:placetype":"venue"
},
  "geometry": {"coordinates":[-88.291115,40.585815],"type":"Point"}
}