{
  "type": "Feature",
  "properties": {
    "iso:country":"US",
    "sg:address":"6513 Benz Rd",
    "sg:city":"Payson",
    "sg:classifiers":[
        {
            "category":"Professional",
            "subcategory":"Management & Consulting",
            "type":"Services"
        }
    ],
    "sg:phone":"+1 217 656 3668",
    "sg:postcode":"62360",
    "sg:province":"IL",
    "sg:tags":[
        "managing",
        "consultant",
        "maintenance"
    ],
    "sg:website":"http://www.booneconsulting.com",
    "wof:name":"Boone Consulting",
    "wof:placetype":"venue"
},
  "geometry": {"coordinates":[-91.31067299999999,39.863299],"type":"Point"}
}