{
  "type": "Feature",
  "properties": {
    "iso:country":"US",
    "sg:address":"2034 N Clark Street Fl 2",
    "sg:city":"Chicago",
    "sg:classifiers":[
        {
            "category":"Real Estate",
            "subcategory":"Real Estate Services",
            "type":"Services"
        }
    ],
    "sg:phone":"+1 773 281 4464",
    "sg:postcode":"60614",
    "sg:province":"IL",
    "sg:tags":[
        "management",
        "property"
    ],
    "wof:name":"Dimensions Management",
    "wof:placetype":"venue"
},
  "geometry": {"coordinates":[-87.636453,41.919274],"type":"Point"}
}