{
  "type": "Feature",
  "properties": {
    "iso:country":"US",
    "sg:address":"28W500 Kenwood Ave",
    "sg:city":"West Chicago",
    "sg:classifiers":[
        {
            "category":"Place Of Worship",
            "subcategory":"Temple",
            "type":"Public Place"
        }
    ],
    "sg:phone":"+1 630 562 7277",
    "sg:postcode":"60185",
    "sg:province":"IL",
    "sg:tags":[
        "hindu"
    ],
    "wof:name":"Shri Param Hans Advait Mat",
    "wof:placetype":"venue"
},
  "geometry": {"coordinates":[-88.17747900000001,41.918586],"type":"Point"}
}