{
  "type": "Feature",
  "properties": {
    "iso:country":"US",
    "sg:address":"500 W Madison Street",
    "sg:city":"Chicago",
    "sg:classifiers":[
        {
            "category":"Health Services",
            "subcategory":"Health Practitioner",
            "type":"Services"
        }
    ],
    "sg:phone":"+1 312 474 0160",
    "sg:postcode":"60661",
    "sg:province":"IL",
    "sg:tags":[
        "nutritionist"
    ],
    "wof:name":"Healthwish Dba Gnc",
    "wof:placetype":"venue"
},
  "geometry": {"coordinates":[-87.639675,41.881896],"type":"Point"}
}