{
  "type": "Feature",
  "properties": {
    "addr:full":"3351 Venard Rd Downers Grove IL 60515",
    "addr:housenumber":"3351",
    "addr:postcode":"60515",
    "addr:street":"Venard Rd",
    "iso:country":"US",
    "sg:address":"3351 Venard Rd",
    "sg:city":"Downers Grove",
    "sg:classifiers":[
        {
            "category":"Wholesale",
            "subcategory":"Durable Goods & Equipment",
            "type":"Manufacturing & Wholesale Goods"
        }
    ],
    "sg:phone":"+1 630 515 9251",
    "sg:postcode":"60515",
    "sg:province":"IL",
    "sg:tags":[
        "specialty",
        "mfg"
    ],
    "wof:name":"Storks By Shirley",
    "wof:placetype":"venue"
},
  "geometry": {"coordinates":[-88.0193,41.825514],"type":"Point"}
}