{
  "type": "Feature",
  "properties": {
    "addr:full":"502 N 4th St Sheldon IN 60966",
    "addr:housenumber":"502",
    "addr:postcode":"60966",
    "addr:street":"N 4Th St",
    "iso:country":"US",
    "sg:address":"502 N 4th St",
    "sg:city":"Sheldon",
    "sg:classifiers":[
        {
            "category":"Shopping",
            "subcategory":"Hobbies, Toys, & Games",
            "type":"Retail Goods"
        }
    ],
    "sg:phone":"+1 815 429 3011",
    "sg:postcode":"60966",
    "sg:province":"IN",
    "sg:tags":[
        "craft",
        "supply"
    ],
    "wof:name":"Jackee's Crafts",
    "wof:placetype":"venue"
},
  "geometry": {"coordinates":[-87.564218,40.776641],"type":"Point"}
}