{
  "type": "Feature",
  "properties": {
    "addr:full":"8210 S Racine Ave Chicago IL 60620",
    "addr:housenumber":"8210",
    "addr:postcode":"60620",
    "addr:street":"S Racine Ave",
    "iso:country":"US",
    "sg:address":"8210 S Racine Ave",
    "sg:city":"Chicago",
    "sg:classifiers":[
        {
            "category":"Place Of Worship",
            "subcategory":"Church",
            "type":"Public Place"
        },
        {
            "category":"Place Of Worship",
            "type":"Public Place"
        }
    ],
    "sg:phone":"+1 773 488 0611",
    "sg:postcode":"60620",
    "sg:province":"IL",
    "sg:tags":[
        "churches-baptist-general",
        "denomination",
        "churches-baptist",
        "churches-interdenominational",
        "churches-various"
    ],
    "wof:name":"Holiness Is The Way Gospel Temple",
    "wof:placetype":"venue"
},
  "geometry": {"coordinates":[-87.653589,41.744698],"type":"Point"}
}