{
  "type": "Feature",
  "properties": {
    "iso:country":"US",
    "sg:address":"1110 E Broadway",
    "sg:city":"Alton",
    "sg:classifiers":[
        {
            "category":"Autos & Motor Vehicles",
            "subcategory":"Fuel & Gas Station",
            "type":"Retail Goods"
        }
    ],
    "sg:phone":"+1   ",
    "sg:postcode":"62002",
    "sg:province":"IL",
    "sg:tags":[
        "station",
        "gasoline"
    ],
    "wof:name":"Alton Citgo",
    "wof:placetype":"venue"
},
  "geometry": {"coordinates":[-90.168232,38.888176],"type":"Point"}
}