{
  "type": "Feature",
  "properties": {
    "addr:full":"3803 W Roosevelt Rd Chicago IL 60624",
    "addr:housenumber":"3803",
    "addr:postcode":"60624",
    "addr:street":"W Roosevelt Rd",
    "iso:country":"US",
    "sg:address":"3803 W Roosevelt Rd",
    "sg:city":"Chicago",
    "sg:classifiers":[
        {
            "category":"Building & Trades",
            "subcategory":"Locksmith",
            "type":"Services"
        }
    ],
    "sg:phone":"+1 773 893 1011",
    "sg:postcode":"60624",
    "sg:province":"IL",
    "sg:tags":[
        "key"
    ],
    "wof:name":"24Hr All Chicago Locksmith and Lockout",
    "wof:placetype":"venue"
},
  "geometry": {"coordinates":[-87.72018199999999,41.866063],"type":"Point"}
}