{
  "type": "Feature",
  "properties": {
    "iso:country":"US",
    "sg:address":"2641 Poplar Ave",
    "sg:city":"Evanston",
    "sg:classifiers":[
        {
            "category":"Professional",
            "subcategory":"Management & Consulting",
            "type":"Services"
        }
    ],
    "sg:phone":"+1 847 328 0823",
    "sg:postcode":"60201",
    "sg:province":"IL",
    "sg:tags":[
        "construction"
    ],
    "wof:name":"Construction Concept Mgt Corp",
    "wof:placetype":"venue"
},
  "geometry": {"coordinates":[-87.69922,42.065613],"type":"Point"}
}