{
  "type": "Feature",
  "properties": {
    "iso:country":"US",
    "sg:address":"5400 Walnut Ave",
    "sg:city":"Downers Grove",
    "sg:classifiers":[
        {
            "category":"Professional",
            "subcategory":"Art Services",
            "type":"Services"
        },
        {
            "category":"Manufacturing",
            "subcategory":"Printing",
            "type":"Manufacturing & Wholesale Goods"
        }
    ],
    "sg:phone":"+1 630 960 2972",
    "sg:postcode":"60515",
    "sg:province":"IL",
    "sg:tags":[
        "commercial",
        "graphic",
        "lithographic",
        "designer"
    ],
    "wof:name":"Fountainhead Graphics Inc",
    "wof:placetype":"venue"
},
  "geometry": {"coordinates":[-88.05203899999999,41.78814],"type":"Point"}
}