{
  "type": "Feature",
  "properties": {
    "addr:full":"57 Fossil Ridge Ct Wilmington IL 60481",
    "addr:housenumber":"57",
    "addr:postcode":"60481",
    "addr:street":"Fossil Ridge Ct",
    "iso:country":"US",
    "sg:address":"57 Fossil Ridge Ct",
    "sg:city":"Wilmington",
    "sg:classifiers":[
        {
            "category":"Insurance",
            "subcategory":"Hazard Insurance",
            "type":"Services"
        }
    ],
    "sg:phone":"+1 815 458 3739",
    "sg:postcode":"60481",
    "sg:province":"IL",
    "wof:name":"Jennifer Marie Mann",
    "wof:placetype":"venue"
},
  "geometry": {"coordinates":[-88.20607,41.283249],"type":"Point"}
}