{
  "type": "Feature",
  "properties": {
    "iso:country":"US",
    "sg:address":"313 W Main St",
    "sg:city":"Monticello",
    "sg:classifiers":[
        {
            "category":"Real Estate",
            "subcategory":"Real Estate Agent",
            "type":"Services"
        }
    ],
    "sg:phone":"+1 817 283 2883",
    "sg:postcode":"61856",
    "sg:province":"IL",
    "wof:name":"Zeigler Real Estate",
    "wof:placetype":"venue"
},
  "geometry": {"coordinates":[-88.57437400000001,40.024927],"type":"Point"}
}