{
  "type": "Feature",
  "properties": {
    "iso:country":"US",
    "sg:address":"3053 N Linder Ave",
    "sg:city":"Chicago",
    "sg:classifiers":[
        {
            "category":"Organizations",
            "subcategory":"Religious Organization",
            "type":"Services"
        }
    ],
    "sg:phone":"+1 773 202 1293",
    "sg:postcode":"60641",
    "sg:province":"IL",
    "wof:name":"Iglesia Cristiana De La Familia",
    "wof:placetype":"venue"
},
  "geometry": {"coordinates":[-87.764099,41.9366],"type":"Point"}
}