{
  "type": "Feature",
  "properties": {
    "iso:country":"US",
    "sg:address":"2546 Lund Ave",
    "sg:city":"Rockford",
    "sg:classifiers":[
        {
            "category":"Organizations",
            "subcategory":"Religious Organization",
            "type":"Services"
        }
    ],
    "sg:phone":"+1 815 874 8064",
    "sg:postcode":"61109",
    "sg:province":"IL",
    "wof:name":"Wm L Welk Rev",
    "wof:placetype":"venue"
},
  "geometry": {"coordinates":[-89.052367,42.221547],"type":"Point"}
}