{
  "type": "Feature",
  "properties": {
    "iso:country":"US",
    "sg:address":"821 1st St",
    "sg:city":"La Salle",
    "sg:classifiers":[
        {
            "category":"Shopping",
            "subcategory":"Books",
            "type":"Retail Goods"
        }
    ],
    "sg:phone":"+1 815 223 9433",
    "sg:postcode":"61301",
    "sg:province":"IL",
    "sg:tags":[
        "comic"
    ],
    "wof:name":"Metropolis Comics",
    "wof:placetype":"venue"
},
  "geometry": {"coordinates":[-89.092952,41.328388],"type":"Point"}
}