{
  "type": "Feature",
  "properties": {
    "addr:full":"615 Main St Farmersville IL 62533",
    "addr:housenumber":"615",
    "addr:postcode":"62533",
    "addr:street":"Main St",
    "iso:country":"US",
    "sg:address":"615 Main St",
    "sg:city":"Farmersville",
    "sg:classifiers":[
        {
            "category":"Manufacturing",
            "subcategory":"Food",
            "type":"Manufacturing & Wholesale Goods"
        }
    ],
    "sg:phone":"+1 217 227 4144",
    "sg:postcode":"62533",
    "sg:province":"IL",
    "sg:tags":[
        "product"
    ],
    "wof:name":"Perry Hendricks",
    "wof:placetype":"venue"
},
  "geometry": {"coordinates":[-89.651765,39.443293],"type":"Point"}
}