{
  "type": "Feature",
  "properties": {
    "addr:full":"1721 Mission Hills Rd Northbrook IL 60062",
    "addr:housenumber":"1721",
    "addr:postcode":"60062",
    "addr:street":"Mission Hills Rd",
    "iso:country":"US",
    "sg:address":"1721 Mission Hills Rd",
    "sg:city":"Northbrook",
    "sg:classifiers":[
        {
            "category":"Professional",
            "type":"Services"
        }
    ],
    "sg:phone":"+1 847 480 0427",
    "sg:postcode":"60062",
    "sg:province":"IL",
    "wof:name":"Bernard Wolnak Assoc",
    "wof:placetype":"venue"
},
  "geometry": {"coordinates":[-87.877786,42.121414],"type":"Point"}
}