{
  "type": "Feature",
  "properties": {
    "iso:country":"US",
    "sg:address":"1503 A Ave",
    "sg:city":"Rock Falls",
    "sg:classifiers":[
        {
            "category":"Organizations",
            "subcategory":"Non-profit Organization",
            "type":"Services"
        }
    ],
    "sg:phone":"+1 815 626 2800",
    "sg:postcode":"61071",
    "sg:province":"IL",
    "sg:tags":[
        "information",
        "alcoholism",
        "treatment"
    ],
    "wof:name":"Recovery Zone",
    "wof:placetype":"venue"
},
  "geometry": {"coordinates":[-89.68817,41.767466],"type":"Point"}
}