{
  "type": "Feature",
  "properties": {
    "iso:country":"US",
    "sg:address":"6707 W Applewood Ln",
    "sg:city":"Spring Grove",
    "sg:classifiers":[
        {
            "category":"Professional",
            "subcategory":"Advertising",
            "type":"Services"
        }
    ],
    "sg:phone":"+1 815 675 9533",
    "sg:postcode":"60081",
    "sg:province":"IL",
    "sg:tags":[
        "agency"
    ],
    "wof:name":"Wordsmith",
    "wof:placetype":"venue"
},
  "geometry": {"coordinates":[-88.231502,42.424708],"type":"Point"}
}