{
  "type": "Feature",
  "properties": {
    "iso:country":"US",
    "sg:address":"314 Blue Lake Ave",
    "sg:city":"Rockford",
    "sg:classifiers":[
        {
            "category":"Building & Trades",
            "subcategory":"Construction",
            "type":"Services"
        }
    ],
    "sg:phone":"+1 815 967 0982",
    "sg:postcode":"61102",
    "sg:province":"IL",
    "sg:tags":[
        "resurfacing",
        "refinishing",
        "floor"
    ],
    "wof:name":"Horan Floors",
    "wof:placetype":"venue"
},
  "geometry": {"coordinates":[-89.162068,42.182956],"type":"Point"}
}