{
  "type": "Feature",
  "properties": {
    "addr:full":"155 N Michigan Are Ste Ste 9001 Chicago IL 60607",
    "addr:housenumber":"155",
    "addr:postcode":"60607",
    "addr:street":"N;Ste;9001",
    "iso:country":"US",
    "sg:address":"155 N Michigan Are Ste Ste 9001",
    "sg:city":"Chicago",
    "sg:classifiers":[
        {
            "category":"Professional",
            "subcategory":"Lawyer & Legal Services",
            "type":"Services"
        }
    ],
    "sg:phone":"+1 866 891 9211",
    "sg:postcode":"60607",
    "sg:province":"IL",
    "sg:tags":[
        "personal",
        "injury"
    ],
    "sg:website":"www.illinoisinjury.com",
    "wof:name":"Woodruff & Johnson",
    "wof:placetype":"venue"
},
  "geometry": {"coordinates":[-87.62434500000001,41.884825],"type":"Point"}
}