{
  "type": "Feature",
  "properties": {
    "addr:full":"5455 N Lincoln Avenue Chicago IL 60625",
    "addr:housenumber":"5455",
    "addr:postcode":"60625",
    "addr:street":"N Lincoln Avenue",
    "iso:country":"US",
    "sg:address":"5455 N Lincoln Avenue",
    "sg:city":"Chicago",
    "sg:classifiers":[
        {
            "category":"Autos & Motor Vehicles",
            "subcategory":"Auto Supplies",
            "type":"Retail Goods"
        }
    ],
    "sg:phone":"+1 773 784 4000",
    "sg:postcode":"60625",
    "sg:province":"IL",
    "sg:tags":[
        "tire"
    ],
    "wof:name":"Lincoln Automotive Group #2",
    "wof:placetype":"venue"
},
  "geometry": {"coordinates":[-87.692891,41.980856],"type":"Point"}
}