{
  "type": "Feature",
  "properties": {
    "addr:full":"4630 N Milwaukee Avenue Chicago IL 60630",
    "addr:housenumber":"4630",
    "addr:postcode":"60630",
    "addr:street":"N Milwaukee Avenue",
    "iso:country":"US",
    "sg:address":"4630 N Milwaukee Avenue",
    "sg:city":"Chicago",
    "sg:classifiers":[
        {
            "category":"Sports & Exercise",
            "subcategory":"Sports Center",
            "type":"Entertainment"
        }
    ],
    "sg:phone":"+1 773 685 6454",
    "sg:postcode":"60630",
    "sg:province":"IL",
    "sg:tags":[
        "amateur",
        "team"
    ],
    "wof:name":"Chicago Park District",
    "wof:placetype":"venue"
},
  "geometry": {"coordinates":[-87.75806300000001,41.964945],"type":"Point"}
}