{
  "type": "Feature",
  "properties": {
    "addr:full":"4247 W Armitage Ave Chicago IL 60639",
    "addr:housenumber":"4247",
    "addr:postcode":"60639",
    "addr:street":"W Armitage Ave",
    "iso:country":"US",
    "sg:address":"4247 W Armitage Ave",
    "sg:city":"Chicago",
    "sg:classifiers":[
        {
            "category":"Restaurant",
            "type":"Food & Drink"
        }
    ],
    "sg:phone":"+1 773 292 4377",
    "sg:postcode":"60639",
    "sg:province":"IL",
    "sg:tags":[
        "mexican"
    ],
    "wof:name":"El Morro Cafe",
    "wof:placetype":"venue"
},
  "geometry": {"coordinates":[-87.732872,41.916969],"type":"Point"}
}