{
  "type": "Feature",
  "properties": {
    "iso:country":"US",
    "sg:address":"570 Estes Ave",
    "sg:city":"Schaumburg",
    "sg:classifiers":[
        {
            "category":"Professional",
            "subcategory":"Engineering",
            "type":"Services"
        },
        {
            "category":"Building & Trades",
            "subcategory":"Cleaning & Sanitation",
            "type":"Services"
        },
        {
            "category":"Autos & Motor Vehicles",
            "subcategory":"Boat Sales",
            "type":"Retail Goods"
        },
        {
            "category":"Building & Trades",
            "subcategory":"Construction",
            "type":"Services"
        },
        {
            "category":"Wholesale",
            "subcategory":"Construction Materials",
            "type":"Manufacturing & Wholesale Goods"
        }
    ],
    "sg:phone":"+1 847 524 2400",
    "sg:postcode":"60193",
    "sg:province":"IL",
    "sg:tags":[
        "industrial",
        "elevator-consultants",
        "elevators-repairing",
        "elevator",
        "passenger-commercial",
        "dumbwaiter",
        "elevators-freight",
        "inspector"
    ],
    "wof:name":"Jeffrey Elevators Co",
    "wof:placetype":"venue"
},
  "geometry": {"coordinates":[-88.095077,42.00291],"type":"Point"}
}