{
  "type": "Feature",
  "properties": {
    "addr:full":"1415 Co Rd 1600 N Crescent City IL 60928",
    "addr:housenumber":"1415",
    "addr:postcode":"60928",
    "addr:street":"Co Rd 1600 N Crescent",
    "iso:country":"US",
    "sg:address":"1415 Co Rd 1600 N",
    "sg:city":"Crescent City",
    "sg:phone":"+1 815 683 2559",
    "sg:postcode":"60928",
    "sg:province":"IL",
    "sg:tags":[
        "farm",
        "grain",
        "cash"
    ],
    "wof:name":"Curtis Rosalius",
    "wof:placetype":"venue"
},
  "geometry": {"coordinates":[-87.845524,40.741081],"type":"Point"}
}