{
  "type": "Feature",
  "properties": {
    "addr:full":"310 Nevada St Frankfort IL 60423",
    "addr:housenumber":"310",
    "addr:postcode":"60423",
    "addr:street":"Nevada St",
    "iso:country":"US",
    "sg:address":"310 Nevada St",
    "sg:city":"Frankfort",
    "sg:classifiers":[
        {
            "category":"Restaurant",
            "type":"Food & Drink"
        }
    ],
    "sg:phone":"+1   ",
    "sg:postcode":"60423",
    "sg:province":"IL",
    "sg:tags":[
        "eating"
    ],
    "wof:name":"Toupalik of Homewood Inc",
    "wof:placetype":"venue"
},
  "geometry": {"coordinates":[-87.838442,41.496701],"type":"Point"}
}