{
  "type": "Feature",
  "properties": {
    "iso:country":"US",
    "sg:address":"7306 S Luella Ave",
    "sg:city":"Chicago",
    "sg:classifiers":[
        {
            "category":"Retail",
            "subcategory":"Repair Shop",
            "type":"Services"
        }
    ],
    "sg:phone":"+1 773 852 2004",
    "sg:postcode":"60649",
    "sg:province":"IL",
    "sg:tags":[
        "bathtub",
        "sink",
        "refinishing"
    ],
    "wof:name":"Ada Bathtub Refinishing",
    "wof:placetype":"venue"
},
  "geometry": {"coordinates":[-87.570126,41.760876],"type":"Point"}
}