{
  "type": "Feature",
  "properties": {
    "iso:country":"US",
    "sg:address":"1214 S Bataan Rd",
    "sg:city":"Dixon",
    "sg:classifiers":[
        {
            "category":"Utilities",
            "subcategory":"Refuse",
            "type":"Services"
        }
    ],
    "sg:phone":"+1 815 625 1000",
    "sg:postcode":"61021",
    "sg:province":"IL",
    "sg:tags":[
        "system"
    ],
    "wof:name":"Allied Waste Transportation",
    "wof:placetype":"venue"
},
  "geometry": {"coordinates":[-89.39759599999999,41.728386],"type":"Point"}
}