{
  "type": "Feature",
  "properties": {
    "iso:country":"US",
    "sg:address":"9502 Gulfstream Rd",
    "sg:city":"Frankfort",
    "sg:classifiers":[
        {
            "category":"Wholesale",
            "subcategory":"Electrical",
            "type":"Manufacturing & Wholesale Goods"
        }
    ],
    "sg:phone":"+1 815 464 5004",
    "sg:postcode":"60423",
    "sg:province":"IL",
    "sg:tags":[
        "me",
        "industrial",
        "electronic",
        "parts",
        "mfg"
    ],
    "wof:name":"Mescon Technologies Inc",
    "wof:placetype":"venue"
},
  "geometry": {"coordinates":[-87.846675,41.474608],"type":"Point"}
}