{
  "type": "Feature",
  "properties": {
    "iso:country":"US",
    "sg:address":"2127 9th St",
    "sg:city":"Rock Island",
    "sg:classifiers":[
        {
            "category":"Social Services",
            "subcategory":"Child Care",
            "type":"Services"
        }
    ],
    "sg:phone":"+1 309 786 8355",
    "sg:postcode":"61201",
    "sg:province":"IL",
    "sg:tags":[
        "day"
    ],
    "wof:name":"Pearline Jones Daycare",
    "wof:placetype":"venue"
},
  "geometry": {"coordinates":[-90.586214,41.489222],"type":"Point"}
}