{
  "type": "Feature",
  "properties": {
    "iso:country":"US",
    "sg:address":"430 Windy Point Dr",
    "sg:city":"Glendale Heights",
    "sg:classifiers":[
        {
            "category":"Wholesale",
            "subcategory":"Machinery & Supplies",
            "type":"Manufacturing & Wholesale Goods"
        }
    ],
    "sg:phone":"+1 630 545 1310",
    "sg:postcode":"60139",
    "sg:province":"IL",
    "sg:tags":[
        "repair",
        "pump"
    ],
    "sg:website":"www.buschpump.com",
    "wof:name":"Busch Inc",
    "wof:placetype":"venue"
},
  "geometry": {"coordinates":[-88.066745,41.92277],"type":"Point"}
}