{
  "type": "Feature",
  "properties": {
    "iso:country":"US",
    "sg:address":"801 Parkwood Ave",
    "sg:city":"Park Ridge",
    "sg:classifiers":[
        {
            "category":"Building & Trades",
            "subcategory":"Construction",
            "type":"Services"
        }
    ],
    "sg:phone":"+1 847 710 9996",
    "sg:postcode":"60068",
    "sg:province":"IL",
    "sg:tags":[
        "siding",
        "contractor"
    ],
    "wof:name":"Proline Exteriors",
    "wof:placetype":"venue"
},
  "geometry": {"coordinates":[-87.856363,42.021295],"type":"Point"}
}