{
  "type": "Feature",
  "properties": {
    "iso:country":"US",
    "sg:address":"403 Meadow Ln",
    "sg:city":"Lake In The Hls",
    "sg:classifiers":[
        {
            "category":"Building & Trades",
            "subcategory":"Plumbing",
            "type":"Services"
        }
    ],
    "sg:phone":"+1 847 658 8885",
    "sg:postcode":"60156",
    "sg:province":"IL",
    "sg:tags":[
        "conditioning",
        "air",
        "system",
        "contractor"
    ],
    "wof:name":"Electrotec Air-Conditioning",
    "wof:placetype":"venue"
},
  "geometry": {"coordinates":[-88.329057,42.184934],"type":"Point"}
}