{
  "type": "Feature",
  "properties": {
    "addr:full":"5921 W Dickens Ave Chicago IL 60639",
    "addr:housenumber":"5921",
    "addr:postcode":"60639",
    "addr:street":"W Dickens Ave",
    "iso:country":"US",
    "sg:address":"5921 W Dickens Ave",
    "sg:city":"Chicago",
    "sg:classifiers":[
        {
            "category":"Retail",
            "subcategory":"Storage",
            "type":"Services"
        }
    ],
    "sg:phone":"+1 773 696 2848",
    "sg:postcode":"60639",
    "sg:province":"IL",
    "sg:tags":[
        "self"
    ],
    "sg:website":"www.metrostorage.com",
    "wof:name":"Metro Self Storage",
    "wof:placetype":"venue"
},
  "geometry": {"coordinates":[-87.77435699999999,41.917321],"type":"Point"}
}