{
  "type": "Feature",
  "properties": {
    "iso:country":"US",
    "sg:address":"2916 Chadwick Dr",
    "sg:city":"Rockford",
    "sg:classifiers":[
        {
            "category":"Organizations",
            "subcategory":"Religious Organization",
            "type":"Services"
        }
    ],
    "sg:phone":"+1 815 397 2110",
    "sg:postcode":"61109",
    "sg:province":"IL",
    "wof:name":"Jehovah S Witnesses South",
    "wof:placetype":"venue"
},
  "geometry": {"coordinates":[-89.048194,42.237223],"type":"Point"}
}