{
  "type": "Feature",
  "properties": {
    "iso:country":"US",
    "sg:address":"13640 Cicero Avenue",
    "sg:city":"Crestwood",
    "sg:classifiers":[
        {
            "category":"Restaurant",
            "type":"Food & Drink"
        }
    ],
    "sg:phone":"+1 708 371 9668",
    "sg:postcode":"60445",
    "sg:province":"IL",
    "wof:name":"El Gallo Tapatio II",
    "wof:placetype":"venue"
},
  "geometry": {"coordinates":[-87.738051,41.644549],"type":"Point"}
}