{
  "type": "Feature",
  "properties": {
    "iso:country":"US",
    "sg:address":"514 Breezeway Dr",
    "sg:city":"Pearl City",
    "sg:classifiers":[
        {
            "category":"Manufacturing",
            "subcategory":"Tools & Machinery",
            "type":"Manufacturing & Wholesale Goods"
        }
    ],
    "sg:phone":"+1 815 599 0662",
    "sg:postcode":"61062",
    "sg:province":"IL",
    "sg:tags":[
        "sound",
        "equipment",
        "electric",
        "mfg"
    ],
    "wof:name":"Precision Sound Products Inc",
    "wof:placetype":"venue"
},
  "geometry": {"coordinates":[-89.827898,42.258154],"type":"Point"}
}