{
  "type": "Feature",
  "properties": {
    "addr:full":"182 E Wend St Lemont IL 60439",
    "addr:housenumber":"182",
    "addr:postcode":"60439",
    "addr:street":"E Wend St",
    "iso:country":"US",
    "sg:address":"182 E Wend St",
    "sg:city":"Lemont",
    "sg:classifiers":[
        {
            "category":"Home & Garden",
            "subcategory":"Building Materials",
            "type":"Retail Goods"
        }
    ],
    "sg:phone":"+1 630 257 5678",
    "sg:postcode":"60439",
    "sg:province":"IL",
    "sg:tags":[
        "carpeting",
        "flooring",
        "ceramic",
        "wood",
        "install",
        "tile"
    ],
    "wof:name":"Cameo Interiors Inc",
    "wof:placetype":"venue"
},
  "geometry": {"coordinates":[-88.000162,41.658421],"type":"Point"}
}