{
  "type": "Feature",
  "properties": {
    "addr:full":"19836 Wolf Rd Mokena IL 60448",
    "addr:housenumber":"19836",
    "addr:postcode":"60448",
    "addr:street":"Wolf Rd",
    "iso:country":"US",
    "sg:address":"19836 Wolf Rd",
    "sg:city":"Mokena",
    "sg:classifiers":[
        {
            "category":"Professional",
            "type":"Services"
        },
        {
            "category":"Restaurant",
            "type":"Food & Drink"
        }
    ],
    "sg:phone":"+1 708 478 0022",
    "sg:postcode":"60448",
    "sg:province":"IL",
    "sg:tags":[
        "caterer",
        "pizza"
    ],
    "sg:website":"http://www.aureliosofnaples.com",
    "wof:name":"Aurelio's Pizza",
    "wof:placetype":"venue"
},
  "geometry": {"coordinates":[-87.88934399999999,41.528203],"type":"Point"}
}