{
  "type": "Feature",
  "properties": {
    "addr:full":"3550 Birch St Franklin Park IL 60131",
    "addr:housenumber":"3550",
    "addr:postcode":"60131",
    "addr:street":"Birch St",
    "iso:country":"US",
    "sg:address":"3550 Birch St",
    "sg:city":"Franklin Park",
    "sg:classifiers":[
        {
            "category":"Manufacturing",
            "subcategory":"Aerospace",
            "type":"Manufacturing & Wholesale Goods"
        }
    ],
    "sg:phone":"+1 847 678 1192",
    "sg:postcode":"60131",
    "sg:province":"IL",
    "sg:tags":[
        "machine",
        "parts",
        "precision",
        "mfg"
    ],
    "sg:website":"www.chucking.com",
    "wof:name":"Chucking Machine Products Inc",
    "wof:placetype":"venue"
},
  "geometry": {"coordinates":[-87.85860599999999,41.943618],"type":"Point"}
}