{
  "type": "Feature",
  "properties": {
    "iso:country":"US",
    "sg:address":"701 N Belt W",
    "sg:city":"Belleville",
    "sg:classifiers":[
        {
            "category":"Retail",
            "subcategory":"Auto Rental",
            "type":"Services"
        }
    ],
    "sg:phone":"+1 618 236 3900",
    "sg:postcode":"62226",
    "sg:province":"IL",
    "sg:tags":[
        "truck",
        "leasing"
    ],
    "wof:name":"Simco Rental & Leasing Inc",
    "wof:placetype":"venue"
},
  "geometry": {"coordinates":[-89.991692,38.536723],"type":"Point"}
}