{
  "type": "Feature",
  "properties": {
    "addr:full":"600 W Wise Rd Schaumburg IL 60193",
    "addr:housenumber":"600",
    "addr:postcode":"60193",
    "addr:street":"W Wise Rd",
    "iso:country":"US",
    "sg:address":"600 W Wise Rd",
    "sg:city":"Schaumburg",
    "sg:classifiers":[
        {
            "category":"Personal",
            "subcategory":"Nail Salon",
            "type":"Services"
        }
    ],
    "sg:phone":"+1 847 524 5717",
    "sg:postcode":"60193",
    "sg:province":"IL",
    "wof:name":"Jinny Nails Inc",
    "wof:placetype":"venue"
},
  "geometry": {"coordinates":[-88.096232,42.004714],"type":"Point"}
}