{
  "type": "Feature",
  "properties": {
    "addr:full":"12 Douglas Ave Elgin IL 60120",
    "addr:housenumber":"12",
    "addr:postcode":"60120",
    "addr:street":"Douglas Ave",
    "iso:country":"US",
    "sg:address":"12 Douglas Ave",
    "sg:city":"Elgin",
    "sg:classifiers":[
        {
            "category":"Professional",
            "subcategory":"Management & Consulting",
            "type":"Services"
        }
    ],
    "sg:phone":"+1 847 841 7266",
    "sg:postcode":"60120",
    "sg:province":"IL",
    "sg:tags":[
        "marketing",
        "program"
    ],
    "wof:name":"Marketing Group",
    "wof:placetype":"venue"
},
  "geometry": {"coordinates":[-88.284102,42.037951],"type":"Point"}
}