{
  "type": "Feature",
  "properties": {
    "iso:country":"US",
    "sg:address":"1133 Beloit Ave",
    "sg:city":"Forest Park",
    "sg:classifiers":[
        {
            "category":"Retail",
            "subcategory":"Funeral Services",
            "type":"Services"
        }
    ],
    "sg:phone":"+1 708 771 4031",
    "sg:postcode":"60130",
    "sg:province":"IL",
    "sg:tags":[
        "firm",
        "memorial",
        "consulting"
    ],
    "wof:name":"Crowder & Gore Memorials Inc",
    "wof:placetype":"venue"
},
  "geometry": {"coordinates":[-87.811599,41.865946],"type":"Point"}
}