{
  "type": "Feature",
  "properties": {
    "iso:country":"US",
    "sg:address":"151 N Michigan Avenue",
    "sg:city":"Chicago",
    "sg:classifiers":[
        {
            "category":"Health Services",
            "subcategory":"Doctor",
            "type":"Services"
        }
    ],
    "sg:phone":"+1 312 938 8774",
    "sg:postcode":"60601",
    "sg:province":"IL",
    "wof:name":"Ashley Camilla MD",
    "wof:placetype":"venue"
},
  "geometry": {"coordinates":[-87.62437799999999,41.88523],"type":"Point"}
}