{
  "type": "Feature",
  "properties": {
    "addr:full":"2783 Maple Ave Lisle IL 60532",
    "addr:housenumber":"2783",
    "addr:postcode":"60532",
    "addr:street":"Maple Ave",
    "iso:country":"US",
    "sg:address":"2783 Maple Ave",
    "sg:city":"Lisle",
    "sg:classifiers":[
        {
            "category":"Shopping",
            "subcategory":"Shoes",
            "type":"Retail Goods"
        }
    ],
    "sg:phone":"+1   ",
    "sg:postcode":"60532",
    "sg:province":"IL",
    "wof:name":"Dick Pond Athletics Inc",
    "wof:placetype":"venue"
},
  "geometry": {"coordinates":[-88.10533700000001,41.780231],"type":"Point"}
}