{
  "type": "Feature",
  "properties": {
    "addr:full":"203 N Skokie Hwy Lake Bluff IL 60044",
    "addr:housenumber":"203",
    "addr:postcode":"60044",
    "addr:street":"N Skokie Hwy",
    "iso:country":"US",
    "sg:address":"203 N Skokie Hwy",
    "sg:city":"Lake Bluff",
    "sg:classifiers":[
        {
            "category":"Real Estate",
            "subcategory":"Real Estate Operator",
            "type":"Services"
        }
    ],
    "sg:phone":"+1 847 615 8100",
    "sg:postcode":"60044",
    "sg:province":"IL",
    "sg:tags":[
        "mobile",
        "home",
        "community"
    ],
    "wof:name":"Rockland Mobile Home Park",
    "wof:placetype":"venue"
},
  "geometry": {"coordinates":[-87.870435,42.282255],"type":"Point"}
}