{
  "type": "Feature",
  "properties": {
    "addr:full":"850 W Jackson Blvd # 305 Chicago IL 60607",
    "addr:housenumber":"850",
    "addr:postcode":"60607",
    "addr:street":"W Jackson Blvd # 305",
    "iso:country":"US",
    "sg:address":"850 W Jackson Blvd # 305",
    "sg:city":"Chicago",
    "sg:classifiers":[
        {
            "category":"Personal",
            "type":"Services"
        }
    ],
    "sg:phone":"+1 773 548 8427",
    "sg:postcode":"60607",
    "sg:province":"IL",
    "sg:tags":[
        "assistant"
    ],
    "wof:name":"Baby On Board",
    "wof:placetype":"venue"
},
  "geometry": {"coordinates":[-87.648392,41.87793],"type":"Point"}
}