{
  "type": "Feature",
  "properties": {
    "iso:country":"US",
    "sg:address":"905 N Springfield St",
    "sg:city":"Virden",
    "sg:classifiers":[
        {
            "category":"Restaurant",
            "type":"Food & Drink"
        }
    ],
    "sg:menulink":"http://www.allmenus.com/il/virden/155779-hardees/menu/",
    "sg:phone":"+1 217 965 3715",
    "sg:postcode":"62690",
    "sg:province":"IL",
    "sg:tags":[
        "burger",
        "american"
    ],
    "wof:name":"Hardee's",
    "wof:placetype":"venue"
},
  "geometry": {"coordinates":[-89.767306,39.509788],"type":"Point"}
}