{
  "type": "Feature",
  "properties": {
    "addr:full":"205 N Michigan Avenue Lbby 2 Chicago IL 60601",
    "addr:housenumber":"205;2",
    "addr:postcode":"60601",
    "addr:street":"N Michigan Avenue Lbby",
    "iso:country":"US",
    "sg:address":"205 N Michigan Avenue Lbby 2",
    "sg:city":"Chicago",
    "sg:classifiers":[
        {
            "category":"Communications",
            "subcategory":"Television Station",
            "type":"Services"
        }
    ],
    "sg:phone":"+1 312 565 4824",
    "sg:postcode":"60601",
    "sg:province":"IL",
    "wof:name":"Wfld Channel 32",
    "wof:placetype":"venue"
},
  "geometry": {"coordinates":[-87.624403,41.885796],"type":"Point"}
}