{
  "type": "Feature",
  "properties": {
    "addr:full":"3429 W Diversey Ave Chicago IL 60647",
    "addr:housenumber":"3429",
    "addr:postcode":"60647",
    "addr:street":"W Diversey Ave",
    "iso:country":"US",
    "sg:address":"3429 W Diversey Ave",
    "sg:city":"Chicago",
    "sg:classifiers":[
        {
            "category":"Real Estate",
            "subcategory":"Real Estate Operator",
            "type":"Services"
        }
    ],
    "sg:phone":"+1 773 252 7477",
    "sg:postcode":"60647",
    "sg:province":"IL",
    "sg:tags":[
        "building",
        "nonresidential"
    ],
    "wof:name":"Zero Investments & Management",
    "wof:placetype":"venue"
},
  "geometry": {"coordinates":[-87.713568,41.93188],"type":"Point"}
}