{
  "type": "Feature",
  "properties": {
    "addr:full":"1051 Rohlwing Rd Rolling Meadows IL 60008",
    "addr:housenumber":"1051",
    "addr:postcode":"60008",
    "addr:street":"Rohlwing Rd",
    "iso:country":"US",
    "sg:address":"1051 Rohlwing Rd",
    "sg:city":"Rolling Meadows",
    "sg:classifiers":[
        {
            "category":"Wholesale",
            "subcategory":"Electrical",
            "type":"Manufacturing & Wholesale Goods"
        }
    ],
    "sg:phone":"+1 847 398 8600",
    "sg:postcode":"60008",
    "sg:province":"IL",
    "sg:tags":[
        "representative",
        "heating"
    ],
    "wof:name":"Industrial Thermo Products",
    "wof:placetype":"venue"
},
  "geometry": {"coordinates":[-88.02431199999999,42.099235],"type":"Point"}
}