{
  "type": "Feature",
  "properties": {
    "iso:country":"US",
    "sg:address":"1602 E University Ave",
    "sg:city":"Urbana",
    "sg:classifiers":[
        {
            "category":"Building & Trades",
            "subcategory":"Construction",
            "type":"Services"
        }
    ],
    "sg:phone":"+1 217 344 8773",
    "sg:postcode":"61802",
    "sg:province":"IL",
    "sg:tags":[
        "contractor"
    ],
    "wof:name":"American Electrical Services Inc",
    "wof:placetype":"venue"
},
  "geometry": {"coordinates":[-88.185664,40.115934],"type":"Point"}
}