{
  "type": "Feature",
  "properties": {
    "addr:full":"18600 Oak Park Ave Tinley Park IL 60477",
    "addr:housenumber":"18600",
    "addr:postcode":"60477",
    "addr:street":"Oak Park Ave",
    "iso:country":"US",
    "sg:address":"18600 Oak Park Ave",
    "sg:city":"Tinley Park",
    "sg:classifiers":[
        {
            "category":"Communications",
            "subcategory":"Television Station",
            "type":"Services"
        }
    ],
    "sg:phone":"+1 708 633 0001",
    "sg:postcode":"60477",
    "sg:province":"IL",
    "wof:name":"Wjys Tv/Channel 62",
    "wof:placetype":"venue"
},
  "geometry": {"coordinates":[-87.783613,41.551862],"type":"Point"}
}