{
  "type": "Feature",
  "properties": {
    "addr:full":"621 N Belmont Ave Arlington Heights IL 60004",
    "addr:housenumber":"621",
    "addr:postcode":"60004",
    "addr:street":"N Belmont Ave",
    "iso:country":"US",
    "sg:address":"621 N Belmont Ave",
    "sg:city":"Arlington Heights",
    "sg:classifiers":[
        {
            "category":"Professional",
            "type":"Services"
        }
    ],
    "sg:phone":"+1 847 506 4214",
    "sg:postcode":"60004",
    "sg:province":"IL",
    "sg:tags":[
        "design",
        "public",
        "relations",
        "strategy"
    ],
    "wof:name":"Cyberink",
    "wof:placetype":"venue"
},
  "geometry": {"coordinates":[-87.977946,42.08971],"type":"Point"}
}