{
  "type": "Feature",
  "properties": {
    "iso:country":"US",
    "sg:address":"18707 Burnham Ave",
    "sg:city":"Lansing",
    "sg:classifiers":[
        {
            "category":"Health Services",
            "subcategory":"Optometrist",
            "type":"Services"
        },
        {
            "category":"Shopping",
            "subcategory":"Optician",
            "type":"Retail Goods"
        }
    ],
    "sg:phone":"+1 708 474 0404",
    "sg:postcode":"60438",
    "sg:province":"IL",
    "sg:tags":[
        "eyewear"
    ],
    "wof:name":"Hamann Joseph A OD",
    "wof:placetype":"venue"
},
  "geometry": {"coordinates":[-87.539299,41.555599],"type":"Point"}
}