{
  "type": "Feature",
  "properties": {
    "iso:country":"US",
    "sg:address":"892 Snake Rd",
    "sg:city":"Dorsey",
    "sg:classifiers":[
        {
            "category":"Retail",
            "subcategory":"Auto Repair",
            "type":"Services"
        }
    ],
    "sg:phone":"+1 618 278 4480",
    "sg:postcode":"62021",
    "sg:province":"IL",
    "wof:name":"Huber Automotive",
    "wof:placetype":"venue"
},
  "geometry": {"coordinates":[-90.0289,39.012901],"type":"Point"}
}