{
  "type": "Feature",
  "properties": {
    "addr:full":"758 W North Ave Chicago IL 60610",
    "addr:housenumber":"758",
    "addr:postcode":"60610",
    "addr:street":"W North Ave",
    "iso:country":"US",
    "sg:address":"758 W North Ave",
    "sg:city":"Chicago",
    "sg:classifiers":[
        {
            "category":"Banks & Credit Unions",
            "subcategory":"Bank",
            "type":"Services"
        }
    ],
    "sg:phone":"+1 312 335 5501",
    "sg:postcode":"60610",
    "sg:province":"IL",
    "wof:name":"Lasalle Bank",
    "wof:placetype":"venue"
},
  "geometry": {"coordinates":[-87.647301,41.910999],"type":"Point"}
}