{
  "type": "Feature",
  "properties": {
    "addr:full":"946 S Osborn Ave Kankakee IL 60901",
    "addr:housenumber":"946",
    "addr:postcode":"60901",
    "addr:street":"S Osborn Ave",
    "iso:country":"US",
    "sg:address":"946 S Osborn Ave",
    "sg:city":"Kankakee",
    "sg:classifiers":[
        {
            "category":"Social Services",
            "subcategory":"Child Care",
            "type":"Services"
        }
    ],
    "sg:phone":"+1 815 937 9295",
    "sg:postcode":"60901",
    "sg:province":"IL",
    "wof:name":"Glenlees",
    "wof:placetype":"venue"
},
  "geometry": {"coordinates":[-87.84803700000001,41.107404],"type":"Point"}
}