{
  "type": "Feature",
  "properties": {
    "iso:country":"US",
    "sg:address":"219 N Elmwood Ave",
    "sg:city":"Oak Park",
    "sg:classifiers":[
        {
            "category":"Manufacturing",
            "subcategory":"Electronics",
            "type":"Manufacturing & Wholesale Goods"
        }
    ],
    "sg:phone":"+1 708 524 1348",
    "sg:postcode":"60302",
    "sg:province":"IL",
    "sg:tags":[
        "semiconductor",
        "design",
        "assembles",
        "electronic",
        "devices"
    ],
    "wof:name":"Nanometric Systems Inc",
    "wof:placetype":"venue"
},
  "geometry": {"coordinates":[-87.78648699999999,41.891433],"type":"Point"}
}