{
  "type": "Feature",
  "properties": {
    "addr:full":"200 Main St Park Forest IL 60466",
    "addr:housenumber":"200",
    "addr:postcode":"60466",
    "addr:street":"Main St",
    "iso:country":"US",
    "sg:address":"200 Main St",
    "sg:city":"Park Forest",
    "sg:classifiers":[
        {
            "category":"Shopping",
            "type":"Retail Goods"
        }
    ],
    "sg:phone":"+1 708 283 1543",
    "sg:postcode":"60466",
    "sg:province":"IL",
    "sg:tags":[
        "material",
        "artist",
        "supply"
    ],
    "wof:name":"Gensis South Artist Village",
    "wof:placetype":"venue"
},
  "geometry": {"coordinates":[-87.678837,41.483392],"type":"Point"}
}