{
  "type": "Feature",
  "properties": {
    "addr:full":"720 Main St NW Bourbonnais IL 60914",
    "addr:housenumber":"720",
    "addr:postcode":"bourbonnais il 60914",
    "addr:street":"Main St Nw",
    "iso:country":"US",
    "sg:address":"720 Main St NW",
    "sg:city":"Bourbonnais",
    "sg:classifiers":[
        {
            "category":"Banks & Credit Unions",
            "subcategory":"Bank",
            "type":"Services"
        }
    ],
    "sg:phone":"+1 815 935 8000",
    "sg:postcode":"60914",
    "sg:province":"IL",
    "sg:website":"www.municipaltrustandsavingsbank.com",
    "wof:name":"Municipal Trust & Savings Bank",
    "wof:placetype":"venue"
},
  "geometry": {"coordinates":[-87.890377,41.161295],"type":"Point"}
}