{
  "type": "Feature",
  "properties": {
    "iso:country":"US",
    "sg:address":"804 Tyler Ct",
    "sg:city":"Monticello",
    "sg:classifiers":[
        {
            "category":"Social Services",
            "subcategory":"Child Care",
            "type":"Services"
        }
    ],
    "sg:phone":"+1 217 762 4136",
    "sg:postcode":"61856",
    "sg:province":"IL",
    "sg:tags":[
        "day"
    ],
    "wof:name":"Trimble Pacie",
    "wof:placetype":"venue"
},
  "geometry": {"coordinates":[-88.564476,40.020248],"type":"Point"}
}