{
  "type": "Feature",
  "properties": {
    "iso:country":"US",
    "sg:address":"450 W Roosevelt Rd",
    "sg:city":"Villa Park",
    "sg:classifiers":[
        {
            "category":"Insurance",
            "subcategory":"Insurance Agent",
            "type":"Services"
        }
    ],
    "sg:phone":"+1 630 620 8800",
    "sg:postcode":"60187",
    "sg:province":"IL",
    "wof:name":"Comar Industries",
    "wof:placetype":"venue"
},
  "geometry": {"coordinates":[-88.114714,41.858568],"type":"Point"}
}