{
  "type": "Feature",
  "properties": {
    "addr:full":"845 Oakwood Dr Frankfort IL 60423",
    "addr:housenumber":"845",
    "addr:postcode":"60423",
    "addr:street":"Oakwood Dr",
    "iso:country":"US",
    "sg:address":"845 Oakwood Dr",
    "sg:city":"Frankfort",
    "sg:classifiers":[
        {
            "category":"Professional",
            "subcategory":"Business Services",
            "type":"Services"
        }
    ],
    "sg:phone":"+1 815 464 5717",
    "sg:postcode":"60423",
    "sg:province":"IL",
    "sg:tags":[
        "water",
        "treatment"
    ],
    "wof:name":"Aquatech Water Filtration Co",
    "wof:placetype":"venue"
},
  "geometry": {"coordinates":[-87.86841699999999,41.516285],"type":"Point"}
}