{
  "type": "Feature",
  "properties": {
    "iso:country":"US",
    "sg:address":"1303 S Central Ave",
    "sg:city":"Cicero",
    "sg:classifiers":[
        {
            "category":"Building & Trades",
            "subcategory":"Construction",
            "type":"Services"
        }
    ],
    "sg:phone":"+1 708 222 2995",
    "sg:postcode":"60804",
    "sg:province":"IL",
    "sg:tags":[
        "home",
        "improvement"
    ],
    "wof:name":"A J Development & Rehab Corp",
    "wof:placetype":"venue"
},
  "geometry": {"coordinates":[-87.764123,41.861986],"type":"Point"}
}