{
  "type": "Feature",
  "properties": {
    "addr:full":"178 Montclare Ln Wood Dale IL 60191",
    "addr:housenumber":"178",
    "addr:postcode":"60191",
    "addr:street":"Montclare Ln",
    "iso:country":"US",
    "sg:address":"178 Montclare Ln",
    "sg:city":"Wood Dale",
    "sg:classifiers":[
        {
            "category":"Professional",
            "subcategory":"Management & Consulting",
            "type":"Services"
        }
    ],
    "sg:phone":"+1 630 694 0001",
    "sg:postcode":"60191",
    "sg:province":"IL",
    "sg:tags":[
        "public",
        "relations"
    ],
    "wof:name":"Cr Promotions Inc",
    "wof:placetype":"venue"
},
  "geometry": {"coordinates":[-87.97023299999999,41.954173],"type":"Point"}
}