{
  "type": "Feature",
  "properties": {
    "addr:full":"9009 Pater Ct Spring Grove IL 60081",
    "addr:postcode":"9009;60081",
    "addr:street":"Pater Ct",
    "iso:country":"US",
    "sg:address":"9009 Pater Ct",
    "sg:city":"Spring Grove",
    "sg:classifiers":[
        {
            "category":"Professional",
            "subcategory":"Management & Consulting",
            "type":"Services"
        }
    ],
    "sg:phone":"+1 815 675 0795",
    "sg:postcode":"60081",
    "sg:province":"IL",
    "sg:tags":[
        "public",
        "relations"
    ],
    "wof:name":"Jana Inc",
    "wof:placetype":"venue"
},
  "geometry": {"coordinates":[-88.246286,42.457716],"type":"Point"}
}