{
  "type": "Feature",
  "properties": {
    "addr:full":"2428 Reeves Rd Joliet IL 60436",
    "addr:housenumber":"2428",
    "addr:postcode":"60436",
    "addr:street":"Reeves Rd",
    "iso:country":"US",
    "sg:address":"2428 Reeves Rd",
    "sg:city":"Joliet",
    "sg:classifiers":[
        {
            "category":"Wholesale",
            "subcategory":"Construction Materials",
            "type":"Manufacturing & Wholesale Goods"
        }
    ],
    "sg:phone":"+1 815 741 4777",
    "sg:postcode":"60436",
    "sg:province":"IL",
    "sg:tags":[
        "roofing"
    ],
    "wof:name":"Shelter Distribution",
    "wof:placetype":"venue"
},
  "geometry": {"coordinates":[-88.14124,41.49107],"type":"Point"}
}