{
  "type": "Feature",
  "properties": {
    "iso:country":"US",
    "sg:address":"216 E Davie St",
    "sg:city":"Anna",
    "sg:classifiers":[
        {
            "category":"Recreation",
            "type":"Entertainment"
        }
    ],
    "sg:phone":"+1 618 833 4447",
    "sg:postcode":"62906",
    "sg:province":"IL",
    "sg:tags":[
        "skating",
        "rink"
    ],
    "wof:name":"Ole Skate Barn",
    "wof:placetype":"venue"
},
  "geometry": {"coordinates":[-89.246734,37.459503],"type":"Point"}
}