{
  "type": "Feature",
  "properties": {
    "addr:full":"25 Wedgewood Dr Belleville IL 62221",
    "addr:housenumber":"25",
    "addr:postcode":"62221",
    "addr:street":"Wedgewood Dr",
    "iso:country":"US",
    "sg:address":"25 Wedgewood Dr",
    "sg:city":"Belleville",
    "sg:classifiers":[
        {
            "category":"Professional",
            "subcategory":"Computer Services",
            "type":"Services"
        }
    ],
    "sg:phone":"+1 618 222 1835",
    "sg:postcode":"62221",
    "sg:province":"IL",
    "sg:tags":[
        "datum"
    ],
    "wof:name":"Tiffin Services and Solutions",
    "wof:placetype":"venue"
},
  "geometry": {"coordinates":[-89.97282199999999,38.531628],"type":"Point"}
}