{
  "type": "Feature",
  "properties": {
    "addr:full":"440 N Wells St Chicago IL 60610",
    "addr:housenumber":"440",
    "addr:postcode":"60610",
    "addr:street":"N Wells St",
    "iso:country":"US",
    "sg:address":"440 N Wells St",
    "sg:city":"Chicago",
    "sg:classifiers":[
        {
            "category":"Home & Garden",
            "subcategory":"Furniture",
            "type":"Retail Goods"
        }
    ],
    "sg:phone":"+1 312 222 9300",
    "sg:postcode":"60610",
    "sg:province":"IL",
    "sg:tags":[
        "store"
    ],
    "sg:website":"www.lignerosetchicago.com",
    "wof:name":"Ligne Roset",
    "wof:placetype":"venue"
},
  "geometry": {"coordinates":[-87.634057,41.890134],"type":"Point"}
}