{
  "type": "Feature",
  "properties": {
    "iso:country":"US",
    "sg:address":"2601 W 59th St",
    "sg:city":"Chicago",
    "sg:classifiers":[
        {
            "category":"Food & Beverages",
            "subcategory":"Groceries & Convenience Stores",
            "type":"Retail Goods"
        }
    ],
    "sg:phone":"+1 773 436 3715",
    "sg:postcode":"60629",
    "sg:province":"IL",
    "wof:name":"Mi Mexico Grocery Store",
    "wof:placetype":"venue"
},
  "geometry": {"coordinates":[-87.689003,41.786301],"type":"Point"}
}