{
  "type": "Feature",
  "properties": {
    "iso:country":"US",
    "sg:address":"643 Longview Dr",
    "sg:city":"Antioch",
    "sg:classifiers":[
        {
            "category":"Organizations",
            "subcategory":"Membership Organization",
            "type":"Services"
        }
    ],
    "sg:phone":"+1 847 395 4567",
    "sg:postcode":"60002",
    "sg:province":"IL",
    "wof:name":"River Valley Kart Association",
    "wof:placetype":"venue"
},
  "geometry": {"coordinates":[-88.085144,42.482779],"type":"Point"}
}