{
  "type": "Feature",
  "properties": {
    "iso:country":"US",
    "sg:address":"1000 S Barrington Rd",
    "sg:city":"Streamwood",
    "sg:classifiers":[
        {
            "category":"Insurance",
            "subcategory":"Hazard Insurance",
            "type":"Services"
        },
        {
            "category":"Banks & Credit Unions",
            "subcategory":"Financial Services",
            "type":"Services"
        }
    ],
    "sg:phone":"+1 800 318 3929",
    "sg:postcode":"60107",
    "sg:province":"IL",
    "sg:tags":[
        "loan"
    ],
    "wof:name":"Countrywide: Full Spectrum Lending",
    "wof:placetype":"venue"
},
  "geometry": {"coordinates":[-88.144685,42.012015],"type":"Point"}
}