{
  "type": "Feature",
  "properties": {
    "iso:country":"US",
    "sg:address":"31 N Main St",
    "sg:city":"Breese",
    "sg:classifiers":[
        {
            "category":"Education",
            "subcategory":"Dance Studio",
            "type":"Public Place"
        },
        {
            "category":"Education",
            "subcategory":"Special Training",
            "type":"Public Place"
        }
    ],
    "sg:phone":"+1 618 526 7166",
    "sg:postcode":"62230",
    "sg:province":"IL",
    "sg:tags":[
        "instruction",
        "dancing"
    ],
    "wof:name":"Studio B Dance",
    "wof:placetype":"venue"
},
  "geometry": {"coordinates":[-89.527628,38.607529],"type":"Point"}
}