{
  "type": "Feature",
  "properties": {
    "iso:country":"US",
    "sg:address":"1400 W Devon Ave PO Box 102",
    "sg:city":"Chicago",
    "sg:classifiers":[
        {
            "category":"Shopping",
            "subcategory":"Pets & Pet Supplies",
            "type":"Retail Goods"
        }
    ],
    "sg:phone":"+1 773 856 0473",
    "sg:postcode":"60660",
    "sg:province":"IL",
    "sg:tags":[
        "walker",
        "dog"
    ],
    "sg:website":"www.roversdogwalkers.com",
    "wof:name":"Rovers Dog Walkers",
    "wof:placetype":"venue"
},
  "geometry": {"coordinates":[-87.66545499999999,41.998017],"type":"Point"}
}