{
  "type": "Feature",
  "properties": {
    "iso:country":"US",
    "sg:address":"106 W Wall St",
    "sg:city":"Ancona",
    "sg:classifiers":[
        {
            "category":"Organizations",
            "subcategory":"Religious Organization",
            "type":"Services"
        }
    ],
    "sg:phone":"+1 815 672 6125",
    "sg:postcode":"61311",
    "sg:province":"IL",
    "sg:tags":[
        "church"
    ],
    "wof:name":"Ancona Church Parsonage",
    "wof:placetype":"venue"
},
  "geometry": {"coordinates":[-88.873589,41.041025],"type":"Point"}
}