{
  "type": "Feature",
  "properties": {
    "addr:full":"2308 Prospect Ave Evanston IL 60201",
    "addr:housenumber":"2308",
    "addr:postcode":"60201",
    "addr:street":"Prospect Ave",
    "iso:country":"US",
    "sg:address":"2308 Prospect Ave",
    "sg:city":"Evanston",
    "sg:classifiers":[
        {
            "category":"Professional",
            "subcategory":"Business Services",
            "type":"Services"
        }
    ],
    "sg:phone":"+1 847 328 4320",
    "sg:postcode":"60201",
    "sg:province":"IL",
    "wof:name":"Elizabeth Bald Interiors",
    "wof:placetype":"venue"
},
  "geometry": {"coordinates":[-87.725679,42.05924],"type":"Point"}
}