{
  "type": "Feature",
  "properties": {
    "iso:country":"US",
    "sg:address":"700 E Main St",
    "sg:city":"Carbondale",
    "sg:classifiers":[
        {
            "category":"Travel",
            "subcategory":"Hotels & Motels",
            "type":"Entertainment"
        }
    ],
    "sg:phone":"+1 618 457 5566",
    "sg:postcode":"62901",
    "sg:province":"IL",
    "wof:name":"Motel 6",
    "wof:placetype":"venue"
},
  "geometry": {"coordinates":[-89.205299,37.728001],"type":"Point"}
}