{
  "type": "Feature",
  "properties": {
    "iso:country":"US",
    "sg:address":"5423 135th St",
    "sg:city":"Crestwood",
    "sg:classifiers":[
        {
            "category":"Restaurant",
            "type":"Food & Drink"
        }
    ],
    "sg:phone":"+1 708 388 8620",
    "sg:postcode":"60445",
    "sg:province":"IL",
    "sg:tags":[
        "pizza"
    ],
    "wof:name":"Angelo's Pizza",
    "wof:placetype":"venue"
},
  "geometry": {"coordinates":[-87.75279999999999,41.646801],"type":"Point"}
}