{
  "type": "Feature",
  "properties": {
    "addr:full":"7831 S Michigan Ave Chicago IL 60619",
    "addr:housenumber":"7831",
    "addr:postcode":"60619",
    "addr:street":"S Michigan Ave",
    "iso:country":"US",
    "sg:address":"7831 S Michigan Ave",
    "sg:city":"Chicago",
    "sg:classifiers":[
        {
            "category":"Building & Trades",
            "subcategory":"Landscaping Services",
            "type":"Services"
        }
    ],
    "sg:phone":"+1 773 224 4069",
    "sg:postcode":"60619",
    "sg:province":"IL",
    "sg:tags":[
        "landscape",
        "contractor"
    ],
    "wof:name":"Emerging Towards Development",
    "wof:placetype":"venue"
},
  "geometry": {"coordinates":[-87.62139500000001,41.75227],"type":"Point"}
}