{
  "type": "Feature",
  "properties": {
    "addr:full":"273 W State Rte 173 Antioch IL 60002",
    "addr:housenumber":"273",
    "addr:postcode":"60002",
    "addr:street":"W State Rte 173",
    "iso:country":"US",
    "sg:address":"273 W State Rte 173",
    "sg:city":"Antioch",
    "sg:classifiers":[
        {
            "category":"Retail",
            "subcategory":"Laundry & Dry Cleaning",
            "type":"Services"
        }
    ],
    "sg:phone":"+1 847 395 5915",
    "sg:postcode":"60002",
    "sg:province":"IL",
    "sg:tags":[
        "cleaners"
    ],
    "wof:name":"Antioch Cleaners & Laundromat",
    "wof:placetype":"venue"
},
  "geometry": {"coordinates":[-88.091326,42.470715],"type":"Point"}
}