{
  "type": "Feature",
  "properties": {
    "iso:country":"US",
    "sg:address":"8000 Dustman Rd",
    "sg:city":"Worden",
    "sg:classifiers":[
        {
            "category":"Farming",
            "subcategory":"Livestock Farm",
            "type":"Manufacturing & Wholesale Goods"
        }
    ],
    "sg:phone":"+1 618 459 3619",
    "sg:postcode":"62097",
    "sg:province":"IL",
    "sg:tags":[
        "animal",
        "general"
    ],
    "wof:name":"Phyllis Battoe",
    "wof:placetype":"venue"
},
  "geometry": {"coordinates":[-89.888239,38.942304],"type":"Point"}
}