{
  "type": "Feature",
  "properties": {
    "addr:full":"11 164th St Calumet City IL 60409",
    "addr:housenumber":"11",
    "addr:postcode":"60409",
    "addr:street":"164Th St",
    "iso:country":"US",
    "sg:address":"11 164th St",
    "sg:city":"Calumet City",
    "sg:classifiers":[
        {
            "category":"Professional",
            "type":"Services"
        }
    ],
    "sg:phone":"+1 708 862 2479",
    "sg:postcode":"60409",
    "sg:province":"IL",
    "wof:name":"B&M Services",
    "wof:placetype":"venue"
},
  "geometry": {"coordinates":[-87.525548,41.591914],"type":"Point"}
}