{
  "type": "Feature",
  "properties": {
    "iso:country":"US",
    "sg:address":"535 S Bowman Ave",
    "sg:city":"Danville",
    "sg:classifiers":[
        {
            "category":"Organizations",
            "subcategory":"Religious Organization",
            "type":"Services"
        }
    ],
    "sg:phone":"+1 217 446 7289",
    "sg:postcode":"61832",
    "sg:province":"IL",
    "wof:name":"Community Church Of God",
    "wof:placetype":"venue"
},
  "geometry": {"coordinates":[-87.611458,40.118105],"type":"Point"}
}