{
  "type": "Feature",
  "properties": {
    "iso:country":"US",
    "sg:address":"82 Brookstone Dr",
    "sg:city":"Streamwood",
    "sg:classifiers":[
        {
            "category":"Food & Beverages",
            "subcategory":"Groceries & Convenience Stores",
            "type":"Retail Goods"
        }
    ],
    "sg:phone":"+1 630 372 0305",
    "sg:postcode":"60107",
    "sg:province":"IL",
    "wof:name":"Besana Save",
    "wof:placetype":"venue"
},
  "geometry": {"coordinates":[-88.19210099999999,42.017204],"type":"Point"}
}