{
  "type": "Feature",
  "properties": {
    "addr:full":"831 S Oak Park Ave Oak Park IL 60304",
    "addr:housenumber":"831",
    "addr:postcode":"60304",
    "addr:street":"S Oak Park Ave",
    "iso:country":"US",
    "sg:address":"831 S Oak Park Ave",
    "sg:city":"Oak Park",
    "sg:classifiers":[
        {
            "category":"Personal",
            "subcategory":"Beauty Salon",
            "type":"Services"
        }
    ],
    "sg:phone":"+1 708 848 4375",
    "sg:postcode":"60304",
    "sg:province":"IL",
    "sg:tags":[
        "hair",
        "shop"
    ],
    "wof:name":"Park Avenue Hair Studio",
    "wof:placetype":"venue"
},
  "geometry": {"coordinates":[-87.793701,41.8731],"type":"Point"}
}