{
  "type": "Feature",
  "properties": {
    "addr:full":"1409 W Farwell Ave Chicago IL 60626",
    "addr:housenumber":"1409",
    "addr:postcode":"60626",
    "addr:street":"W Farwell Ave",
    "iso:country":"US",
    "sg:address":"1409 W Farwell Ave",
    "sg:city":"Chicago",
    "sg:classifiers":[
        {
            "category":"Personal",
            "type":"Services"
        },
        {
            "category":"Professional",
            "subcategory":"Art Services",
            "type":"Services"
        }
    ],
    "sg:phone":"+1 847 729 4466",
    "sg:postcode":"60626",
    "sg:province":"IL",
    "sg:tags":[
        "photography",
        "videography",
        "wedding"
    ],
    "sg:website":"http://www.nicolethomas.com",
    "wof:name":"Nicole Thomas Photography, Ltd.",
    "wof:placetype":"venue"
},
  "geometry": {"coordinates":[-87.66623199999999,42.006676],"type":"Point"}
}