{
  "type": "Feature",
  "properties": {
    "addr:full":"15436 Cicero Ave Oak Forest IL 60452",
    "addr:housenumber":"15436",
    "addr:postcode":"60452",
    "addr:street":"Cicero Ave",
    "iso:country":"US",
    "sg:address":"15436 Cicero Ave",
    "sg:city":"Oak Forest",
    "sg:classifiers":[
        {
            "category":"Retail",
            "subcategory":"Auto Repair",
            "type":"Services"
        }
    ],
    "sg:phone":"+1 708 535 8979",
    "sg:postcode":"60452",
    "sg:province":"IL",
    "sg:tags":[
        "muffler",
        "exhaust",
        "system"
    ],
    "wof:name":"Fair Undercar Care Inc",
    "wof:placetype":"venue"
},
  "geometry": {"coordinates":[-87.736858,41.611245],"type":"Point"}
}