{
  "type": "Feature",
  "properties": {
    "addr:full":"1200 Lakeside Dr Deerfield IL 60015",
    "addr:housenumber":"1200",
    "addr:postcode":"60015",
    "addr:street":"Lakeside Dr",
    "iso:country":"US",
    "sg:address":"1200 Lakeside Dr",
    "sg:city":"Deerfield",
    "sg:classifiers":[
        {
            "category":"Banks & Credit Unions",
            "subcategory":"Bank",
            "type":"Services"
        }
    ],
    "sg:phone":"+1 847 607 6033",
    "sg:postcode":"60015",
    "sg:province":"IL",
    "sg:tags":[
        "federal"
    ],
    "wof:name":"Moore Federal Credit Union",
    "wof:placetype":"venue"
},
  "geometry": {"coordinates":[-87.884559,42.2002],"type":"Point"}
}