{
  "type": "Feature",
  "properties": {
    "iso:country":"US",
    "sg:address":"1386 Jarvis Ave",
    "sg:city":"Elk Grove Vlg",
    "sg:classifiers":[
        {
            "category":"Wholesale",
            "subcategory":"Electrical",
            "type":"Manufacturing & Wholesale Goods"
        }
    ],
    "sg:phone":"+1 847 640 4635",
    "sg:postcode":"60007",
    "sg:province":"IL",
    "sg:tags":[
        "control",
        "instrument",
        "electronic",
        "electric",
        "equipment"
    ],
    "sg:website":"www.borggeneral.com",
    "wof:name":"Borg General Controls LLC",
    "wof:placetype":"venue"
},
  "geometry": {"coordinates":[-87.962044,42.013298],"type":"Point"}
}