{
  "type": "Feature",
  "properties": {
    "addr:full":"2413 N Clark St Chicago IL 60614",
    "addr:housenumber":"2413",
    "addr:postcode":"60614",
    "addr:street":"N Clark St",
    "iso:country":"US",
    "sg:address":"2413 N Clark St",
    "sg:city":"Chicago",
    "sg:classifiers":[
        {
            "category":"Restaurant",
            "type":"Food & Drink"
        }
    ],
    "sg:phone":"+1 773 549 4400",
    "sg:postcode":"60614",
    "sg:province":"IL",
    "sg:tags":[
        "new",
        "american",
        "brunch",
        "breakfast"
    ],
    "sg:website":"www.orangerestaurantchicago.com/",
    "wof:name":"Orange",
    "wof:placetype":"venue"
},
  "geometry": {"coordinates":[-87.640463,41.926227],"type":"Point"}
}