{
  "type": "Feature",
  "properties": {
    "iso:country":"US",
    "sg:address":"6385 Kilburn Ave",
    "sg:city":"Rockford",
    "sg:classifiers":[
        {
            "category":"Farming",
            "subcategory":"Orchard",
            "type":"Manufacturing & Wholesale Goods"
        }
    ],
    "sg:phone":"+1 815 963 7848",
    "sg:postcode":"61101",
    "sg:province":"IL",
    "sg:tags":[
        "fruit",
        "tree"
    ],
    "wof:name":"Currans Orchard Inc",
    "wof:placetype":"venue"
},
  "geometry": {"coordinates":[-89.162458,42.327867],"type":"Point"}
}