{
  "type": "Feature",
  "properties": {
    "addr:full":"2431 E Devon Ave Elk Grove Village IL 60007",
    "addr:housenumber":"2431",
    "addr:postcode":"60007",
    "addr:street":"E Devon Ave",
    "iso:country":"US",
    "sg:address":"2431 E Devon Ave",
    "sg:city":"Elk Grove Village",
    "sg:classifiers":[
        {
            "category":"Wholesale",
            "subcategory":"Non-durable Goods",
            "type":"Manufacturing & Wholesale Goods"
        }
    ],
    "sg:phone":"+1 847 350 0722",
    "sg:postcode":"60007",
    "sg:province":"IL",
    "wof:name":"Pontie Trading Inc",
    "wof:placetype":"venue"
},
  "geometry": {"coordinates":[-87.942836,41.993531],"type":"Point"}
}