{
  "type": "Feature",
  "properties": {
    "addr:full":"1937 E 79th St Chicago IL 60649",
    "addr:housenumber":"1937",
    "addr:postcode":"60649",
    "addr:street":"E 79Th St",
    "iso:country":"US",
    "sg:address":"1937 E 79th St",
    "sg:city":"Chicago",
    "sg:classifiers":[
        {
            "category":"Personal",
            "subcategory":"Nail Salon",
            "type":"Services"
        }
    ],
    "sg:phone":"+1 773 375 4786",
    "sg:postcode":"60649",
    "sg:province":"IL",
    "wof:name":"Top Ten Nails",
    "wof:placetype":"venue"
},
  "geometry": {"coordinates":[-87.577003,41.751701],"type":"Point"}
}