{
  "type": "Feature",
  "properties": {
    "addr:full":"953 W Webster Ave Chicago IL 60614",
    "addr:housenumber":"953",
    "addr:postcode":"60614",
    "addr:street":"W Webster Ave",
    "iso:country":"US",
    "sg:address":"953 W Webster Ave",
    "sg:city":"Chicago",
    "sg:classifiers":[
        {
            "category":"Food & Beverages",
            "subcategory":"Liquor & Beverages",
            "type":"Retail Goods"
        },
        {
            "category":"Food & Beverages",
            "subcategory":"Cheese",
            "type":"Retail Goods"
        },
        {
            "category":"Wholesale",
            "subcategory":"Wine & Distilled Alcoholic Beverages",
            "type":"Manufacturing & Wholesale Goods"
        }
    ],
    "sg:phone":"+1 773 549 9740",
    "sg:postcode":"60614",
    "sg:province":"IL",
    "sg:tags":[
        "shop",
        "beer",
        "broker",
        "spirit"
    ],
    "sg:website":"www.vraiamour.com",
    "wof:name":"Vrai Amour",
    "wof:placetype":"venue"
},
  "geometry": {"coordinates":[-87.653036,41.92156],"type":"Point"}
}