{
  "type": "Feature",
  "properties": {
    "iso:country":"US",
    "sg:address":"2817 S Rte 45-52",
    "sg:city":"Kankakee",
    "sg:classifiers":[
        {
            "category":"Travel",
            "subcategory":"Travel Agent",
            "type":"Entertainment"
        }
    ],
    "sg:phone":"+1 815 939 2211",
    "sg:postcode":"60901",
    "sg:province":"IL",
    "sg:tags":[
        "passenger",
        "transportation",
        "arrangement"
    ],
    "wof:name":"Greyhound",
    "wof:placetype":"venue"
},
  "geometry": {"coordinates":[-87.868895,41.079957],"type":"Point"}
}