{
  "type": "Feature",
  "properties": {
    "addr:full":"415 E North Water St Chicago IL 60611",
    "addr:housenumber":"415",
    "addr:postcode":"60611",
    "addr:street":"E North Water St",
    "iso:country":"US",
    "sg:address":"415 E North Water St",
    "sg:city":"Chicago",
    "sg:classifiers":[
        {
            "category":"Professional",
            "subcategory":"Lawyer & Legal Services",
            "type":"Services"
        }
    ],
    "sg:phone":"+1 312 329 9620",
    "sg:postcode":"60611",
    "sg:province":"IL",
    "wof:name":"Tillery Katherine J Atty",
    "wof:placetype":"venue"
},
  "geometry": {"coordinates":[-87.617107,41.88938],"type":"Point"}
}