{
  "type": "Feature",
  "properties": {
    "iso:country":"US",
    "sg:address":"10411 5th Ave Cut Off",
    "sg:city":"Countryside",
    "sg:classifiers":[
        {
            "category":"Real Estate",
            "subcategory":"Architect",
            "type":"Services"
        }
    ],
    "sg:phone":"+1 708 579 0622",
    "sg:postcode":"60525",
    "sg:province":"IL",
    "wof:name":"Krantz Wesley G Architect",
    "wof:placetype":"venue"
},
  "geometry": {"coordinates":[-87.878304,41.757301],"type":"Point"}
}