{
  "type": "Feature",
  "properties": {
    "addr:full":"916 1st Ave Silvis IL 61282",
    "addr:housenumber":"916",
    "addr:postcode":"61282",
    "addr:street":"1St Ave",
    "iso:country":"US",
    "sg:address":"916 1st Ave",
    "sg:city":"Silvis",
    "sg:classifiers":[
        {
            "category":"Shopping",
            "subcategory":"Florist",
            "type":"Retail Goods"
        }
    ],
    "sg:phone":"+1 309 792 5383",
    "sg:postcode":"61282",
    "sg:province":"IL",
    "wof:name":"Country Greenery",
    "wof:placetype":"venue"
},
  "geometry": {"coordinates":[-90.414902,41.512001],"type":"Point"}
}