{
  "type": "Feature",
  "properties": {
    "addr:full":"313 S Raven Rd Shorewood IL 60404",
    "addr:housenumber":"313",
    "addr:postcode":"60404",
    "addr:street":"S Raven Rd",
    "iso:country":"US",
    "sg:address":"313 S Raven Rd",
    "sg:city":"Shorewood",
    "sg:classifiers":[
        {
            "category":"Recreation",
            "type":"Entertainment"
        }
    ],
    "sg:phone":"+1 815 741 3432",
    "sg:postcode":"60404",
    "sg:province":"IL",
    "sg:tags":[
        "entertainers-family",
        "business"
    ],
    "wof:name":"Jpw Productions",
    "wof:placetype":"venue"
},
  "geometry": {"coordinates":[-88.207539,41.519599],"type":"Point"}
}