{
  "type": "Feature",
  "properties": {
    "iso:country":"US",
    "sg:address":"3720 Green Mount Crossing Dr",
    "sg:city":"O Fallon",
    "sg:classifiers":[
        {
            "category":"Wholesale",
            "subcategory":"Computers",
            "type":"Manufacturing & Wholesale Goods"
        },
        {
            "category":"Professional",
            "subcategory":"Computer Services",
            "type":"Services"
        }
    ],
    "sg:phone":"+1 618 624 4440",
    "sg:postcode":"62269",
    "sg:province":"IL",
    "sg:tags":[
        "repair"
    ],
    "sg:website":"www.computerroom.us",
    "wof:name":"Computer Room",
    "wof:placetype":"venue"
},
  "geometry": {"coordinates":[-89.924193,38.571364],"type":"Point"}
}