{
  "type": "Feature",
  "properties": {
    "iso:country":"US",
    "sg:address":"1238 N Kostner Ave",
    "sg:city":"Chicago",
    "sg:classifiers":[
        {
            "category":"Social Services",
            "subcategory":"Adult Care",
            "type":"Services"
        }
    ],
    "sg:phone":"+1 773 235 4300",
    "sg:postcode":"60651",
    "sg:province":"IL",
    "sg:tags":[
        "slitting",
        "cutting"
    ],
    "wof:name":"Quantum Laser Services, Inc.",
    "wof:placetype":"venue"
},
  "geometry": {"coordinates":[-87.73612199999999,41.903071],"type":"Point"}
}