{
  "type": "Feature",
  "properties": {
    "addr:full":"1428 W Chicago Avenue Chicago IL 60622",
    "addr:housenumber":"1428",
    "addr:postcode":"60622",
    "addr:street":"W Chicago Avenue",
    "iso:country":"US",
    "sg:address":"1428 W Chicago Avenue",
    "sg:city":"Chicago",
    "sg:classifiers":[
        {
            "category":"Banks & Credit Unions",
            "subcategory":"Financial Services",
            "type":"Services"
        }
    ],
    "sg:phone":"+1 312 324 6040",
    "sg:postcode":"60622",
    "sg:province":"IL",
    "sg:tags":[
        "broker",
        "mortgage"
    ],
    "wof:name":"Metropolitan Financial",
    "wof:placetype":"venue"
},
  "geometry": {"coordinates":[-87.663588,41.896234],"type":"Point"}
}