{
  "type": "Feature",
  "properties": {
    "iso:country":"US",
    "sg:address":"849 Waukegan Rd",
    "sg:city":"Deerfield",
    "sg:classifiers":[
        {
            "category":"Organizations",
            "subcategory":"Community Association",
            "type":"Services"
        }
    ],
    "sg:phone":"+1 847 945 9821",
    "sg:postcode":"60015",
    "sg:province":"IL",
    "wof:name":"American Legion",
    "wof:placetype":"venue"
},
  "geometry": {"coordinates":[-87.84616800000001,42.169094],"type":"Point"}
}