{
  "type": "Feature",
  "properties": {
    "iso:country":"US",
    "sg:address":"1133 W Lake Street",
    "sg:city":"Chicago",
    "sg:classifiers":[
        {
            "category":"Restaurant",
            "type":"Food & Drink"
        },
        {
            "category":"Food & Beverages",
            "subcategory":"Meat & Fish",
            "type":"Retail Goods"
        }
    ],
    "sg:phone":"+1 312 243 2330",
    "sg:postcode":"60607",
    "sg:province":"IL",
    "sg:tags":[
        "seafood",
        "market"
    ],
    "wof:name":"Internatl Seafoods of Chicago",
    "wof:placetype":"venue"
},
  "geometry": {"coordinates":[-87.656004,41.885407],"type":"Point"}
}