{
  "type": "Feature",
  "properties": {
    "iso:country":"US",
    "sg:address":"6824 W. Archer Ave",
    "sg:city":"Chicago",
    "sg:classifiers":[
        {
            "category":"Shopping",
            "subcategory":"Pets & Pet Supplies",
            "type":"Retail Goods"
        }
    ],
    "sg:phone":"+1 773 229 1717",
    "sg:postcode":"60638",
    "sg:province":"IL",
    "sg:tags":[
        "groomers"
    ],
    "sg:website":"www.doginsudsgrooming.com",
    "wof:name":"Dog In Suds Grooming",
    "wof:placetype":"venue"
},
  "geometry": {"coordinates":[-87.79261200000001,41.792175],"type":"Point"}
}