{
  "type": "Feature",
  "properties": {
    "addr:full":"466 Central Ave Northfield IL 60093",
    "addr:housenumber":"466",
    "addr:postcode":"60093",
    "addr:street":"Central Ave",
    "iso:country":"US",
    "sg:address":"466 Central Ave",
    "sg:city":"Northfield",
    "sg:classifiers":[
        {
            "category":"Health Services",
            "subcategory":"Doctor",
            "type":"Services"
        },
        {
            "category":"Health Services",
            "subcategory":"Clinic",
            "type":"Services"
        }
    ],
    "sg:phone":"+1 847 446 5526",
    "sg:postcode":"60093",
    "sg:province":"IL",
    "sg:tags":[
        "psychological",
        "psychologist"
    ],
    "wof:name":"Brown & Intrater Therapeutics",
    "wof:placetype":"venue"
},
  "geometry": {"coordinates":[-87.77076,42.10408],"type":"Point"}
}