{
  "type": "Feature",
  "properties": {
    "iso:country":"US",
    "sg:address":"945 N Larch Ave",
    "sg:city":"Elmhurst",
    "sg:classifiers":[
        {
            "category":"Manufacturing",
            "subcategory":"Tools & Machinery",
            "type":"Manufacturing & Wholesale Goods"
        },
        {
            "category":"Manufacturing",
            "subcategory":"Printing",
            "type":"Manufacturing & Wholesale Goods"
        }
    ],
    "sg:phone":"+1 630 833 8881",
    "sg:postcode":"60126",
    "sg:province":"IL",
    "sg:tags":[
        "die",
        "cutting",
        "miscellaneous",
        "publishing"
    ],
    "sg:website":"www.garlandconverting.com",
    "wof:name":"Garland Converting Co",
    "wof:placetype":"venue"
},
  "geometry": {"coordinates":[-87.943771,41.925569],"type":"Point"}
}