{
  "type": "Feature",
  "properties": {
    "addr:full":"1950 E Touhy Ave Des Plaines IL 60018",
    "addr:housenumber":"1950",
    "addr:postcode":"60018",
    "addr:street":"E Touhy Ave",
    "iso:country":"US",
    "sg:address":"1950 E Touhy Ave",
    "sg:city":"Des Plaines",
    "sg:classifiers":[
        {
            "category":"Food & Beverages",
            "subcategory":"Groceries & Convenience Stores",
            "type":"Retail Goods"
        }
    ],
    "sg:phone":"+1   ",
    "sg:postcode":"60018",
    "sg:province":"IL",
    "wof:name":"7-Eleven",
    "wof:placetype":"venue"
},
  "geometry": {"coordinates":[-87.87469900000001,42.00993],"type":"Point"}
}