{
  "type": "Feature",
  "properties": {
    "iso:country":"US",
    "sg:address":"2600 Keslinger Rd Ste 17",
    "sg:city":"Geneva",
    "sg:classifiers":[
        {
            "category":"Retail",
            "subcategory":"Portrait Studio",
            "type":"Services"
        },
        {
            "category":"Professional",
            "subcategory":"Art Services",
            "type":"Services"
        }
    ],
    "sg:phone":"+1 630 208 0099",
    "sg:postcode":"60134",
    "sg:province":"IL",
    "sg:tags":[
        "rental",
        "photographers-portrait",
        "photographic",
        "darkroom"
    ],
    "wof:name":"William Spelman Studio",
    "wof:placetype":"venue"
},
  "geometry": {"coordinates":[-88.343529,41.88308],"type":"Point"}
}