{
  "type": "Feature",
  "properties": {
    "addr:full":"151 N Main St Elizabeth IL 61028",
    "addr:housenumber":"151",
    "addr:postcode":"61028",
    "addr:street":"N Main St",
    "iso:country":"US",
    "sg:address":"151 N Main St",
    "sg:city":"Elizabeth",
    "sg:classifiers":[
        {
            "category":"Banks & Credit Unions",
            "subcategory":"Bank",
            "type":"Services"
        }
    ],
    "sg:phone":"+1 815 858 2221",
    "sg:postcode":"61028",
    "sg:province":"IL",
    "sg:tags":[
        "state",
        "commercial"
    ],
    "wof:name":"Elizabeth State Bank",
    "wof:placetype":"venue"
},
  "geometry": {"coordinates":[-90.221807,42.31833],"type":"Point"}
}