{
  "type": "Feature",
  "properties": {
    "iso:country":"US",
    "sg:address":"7700 W 79th St",
    "sg:city":"Bridgeview",
    "sg:classifiers":[
        {
            "category":"Manufacturing",
            "subcategory":"Metals",
            "type":"Manufacturing & Wholesale Goods"
        }
    ],
    "sg:phone":"+1 708 563 9780",
    "sg:postcode":"60455",
    "sg:province":"IL",
    "sg:tags":[
        "engraver"
    ],
    "wof:name":"Creative Card",
    "wof:placetype":"venue"
},
  "geometry": {"coordinates":[-87.81142800000001,41.747917],"type":"Point"}
}