{
  "type": "Feature",
  "properties": {
    "addr:full":"30 E Anthony Dr Champaign IL 61820",
    "addr:housenumber":"30",
    "addr:postcode":"61820",
    "addr:street":"E Anthony Dr",
    "iso:country":"US",
    "sg:address":"30 E Anthony Dr",
    "sg:city":"Champaign",
    "sg:classifiers":[
        {
            "category":"Restaurant",
            "type":"Food & Drink"
        }
    ],
    "sg:menulink":"http://www.allmenus.com/il/champaign-city/14042-olive-garden-italian-restaurant/menu/",
    "sg:phone":"+1 217 351 6339",
    "sg:postcode":"61820",
    "sg:province":"IL",
    "sg:tags":[
        "italian"
    ],
    "wof:name":"Olive Garden Italian Restaurant",
    "wof:placetype":"venue"
},
  "geometry": {"coordinates":[-88.242431,40.136223],"type":"Point"}
}