{
  "type": "Feature",
  "properties": {
    "iso:country":"US",
    "sg:address":"128 Wool St",
    "sg:city":"Barrington",
    "sg:classifiers":[
        {
            "category":"Professional",
            "subcategory":"Lawyer & Legal Services",
            "type":"Services"
        }
    ],
    "sg:phone":"+1 847 381 8740",
    "sg:postcode":"60010",
    "sg:province":"IL",
    "wof:name":"Law Offces Aimee E Forsberg PC",
    "wof:placetype":"venue"
},
  "geometry": {"coordinates":[-88.13047899999999,42.153195],"type":"Point"}
}