{
  "type": "Feature",
  "properties": {
    "iso:country":"US",
    "sg:address":"384 Lovell St",
    "sg:city":"Elgin",
    "sg:classifiers":[
        {
            "category":"Building & Trades",
            "subcategory":"Construction",
            "type":"Services"
        }
    ],
    "sg:phone":"+1 847 695 0709",
    "sg:postcode":"60120",
    "sg:province":"IL",
    "sg:tags":[
        "home",
        "reconstruction"
    ],
    "wof:name":"George D Heuvelman",
    "wof:placetype":"venue"
},
  "geometry": {"coordinates":[-88.275776,42.049991],"type":"Point"}
}