{
  "type": "Feature",
  "properties": {
    "iso:country":"US",
    "sg:address":"1562 Noble Quest Dr",
    "sg:city":"Bradley",
    "sg:classifiers":[
        {
            "category":"Professional",
            "subcategory":"Business Services",
            "type":"Services"
        }
    ],
    "sg:phone":"+1 815 932 2223",
    "sg:postcode":"60914",
    "sg:province":"IL",
    "wof:name":"M&J Cad Services",
    "wof:placetype":"venue"
},
  "geometry": {"coordinates":[-87.83261400000001,41.158066],"type":"Point"}
}