{
  "type": "Feature",
  "properties": {
    "addr:full":"318 S Promenade St Havana IL 62644",
    "addr:housenumber":"318",
    "addr:postcode":"62644",
    "addr:street":"S Promenade St",
    "iso:country":"US",
    "sg:address":"318 S Promenade St",
    "sg:city":"Havana",
    "sg:classifiers":[
        {
            "category":"Cinema",
            "subcategory":"Movie Rental",
            "type":"Entertainment"
        }
    ],
    "sg:phone":"+1 309 543 4082",
    "sg:postcode":"62644",
    "sg:province":"IL",
    "sg:tags":[
        "video",
        "tape"
    ],
    "wof:name":"Video Store Inc",
    "wof:placetype":"venue"
},
  "geometry": {"coordinates":[-90.056226,40.29775],"type":"Point"}
}