{
  "type": "Feature",
  "properties": {
    "iso:country":"US",
    "sg:address":"517 N Chestnut St",
    "sg:city":"Princeton",
    "sg:classifiers":[
        {
            "category":"Building & Trades",
            "subcategory":"Construction",
            "type":"Services"
        }
    ],
    "sg:phone":"+1 815 879 6171",
    "sg:postcode":"61356",
    "sg:province":"IL",
    "sg:tags":[
        "contractor"
    ],
    "wof:name":"Reuter Siding & Construction C",
    "wof:placetype":"venue"
},
  "geometry": {"coordinates":[-89.461365,41.38143],"type":"Point"}
}