{
  "type": "Feature",
  "properties": {
    "addr:full":"26020 W State Rte 173 Antioch IL 60002",
    "addr:housenumber":"26020",
    "addr:postcode":"60002",
    "addr:street":"W State Rte 173",
    "iso:country":"US",
    "sg:address":"26020 W State Rte 173",
    "sg:city":"Antioch",
    "sg:classifiers":[
        {
            "category":"Organizations",
            "subcategory":"Community Association",
            "type":"Services"
        }
    ],
    "sg:phone":"+1 847 395 9780",
    "sg:postcode":"60002",
    "sg:province":"IL",
    "sg:tags":[
        "fraternal"
    ],
    "sg:website":"www.moose525antioch.org",
    "wof:name":"Loyal Order Of Moose",
    "wof:placetype":"venue"
},
  "geometry": {"coordinates":[-88.141133,42.475477],"type":"Point"}
}