{
  "type": "Feature",
  "properties": {
    "addr:full":"5429 W Washington Blvd Chicago IL 60644",
    "addr:housenumber":"5429",
    "addr:postcode":"60644",
    "addr:street":"W Washington Blvd",
    "iso:country":"US",
    "sg:address":"5429 W Washington Blvd",
    "sg:city":"Chicago",
    "sg:classifiers":[
        {
            "category":"Real Estate",
            "subcategory":"Real Estate Agent",
            "type":"Services"
        }
    ],
    "sg:phone":"+1 773 287 2246",
    "sg:postcode":"60644",
    "sg:province":"IL",
    "sg:tags":[
        "finding",
        "apartment",
        "rental"
    ],
    "wof:name":"Evoywest",
    "wof:placetype":"venue"
},
  "geometry": {"coordinates":[-87.761199,41.882217],"type":"Point"}
}