{
  "type": "Feature",
  "properties": {
    "iso:country":"US",
    "sg:address":"5537 W Edgewood Rd",
    "sg:city":"Dixon",
    "sg:classifiers":[
        {
            "category":"Building & Trades",
            "subcategory":"Landscaping Services",
            "type":"Services"
        }
    ],
    "sg:phone":"+1 815 652 8733",
    "sg:postcode":"61021",
    "sg:province":"IL",
    "sg:tags":[
        "tree"
    ],
    "wof:name":"Arbor Care Tree Svc",
    "wof:placetype":"venue"
},
  "geometry": {"coordinates":[-89.44832100000001,41.925916],"type":"Point"}
}