{
  "type": "Feature",
  "properties": {
    "addr:full":"5100 E State St Rockford IL 61108",
    "addr:housenumber":"5100",
    "addr:postcode":"61108",
    "addr:street":"E State St",
    "iso:country":"US",
    "sg:address":"5100 E State St",
    "sg:city":"Rockford",
    "sg:classifiers":[
        {
            "category":"Real Estate",
            "subcategory":"Real Estate Agent",
            "type":"Services"
        }
    ],
    "sg:phone":"+1 815 229 8031",
    "sg:postcode":"61108",
    "sg:province":"IL",
    "wof:name":"Glenda Jaros",
    "wof:placetype":"venue"
},
  "geometry": {"coordinates":[-89.015204,42.26455],"type":"Point"}
}