{
  "type": "Feature",
  "properties": {
    "addr:full":"1130 Arthur Ave Rockford IL 61101",
    "addr:housenumber":"1130",
    "addr:postcode":"61101",
    "addr:street":"Arthur Ave",
    "iso:country":"US",
    "sg:address":"1130 Arthur Ave",
    "sg:city":"Rockford",
    "sg:classifiers":[
        {
            "category":"Government",
            "subcategory":"Office",
            "type":"Public Place"
        }
    ],
    "sg:phone":"+1 815 963 5422",
    "sg:postcode":"61101",
    "sg:province":"IL",
    "sg:tags":[
        "federal",
        "security"
    ],
    "wof:name":"US Army Reserve",
    "wof:placetype":"venue"
},
  "geometry": {"coordinates":[-89.108068,42.28639],"type":"Point"}
}