{
  "type": "Feature",
  "properties": {
    "addr:full":"4730 W Irving Park Rd Chicago IL 60641",
    "addr:housenumber":"4730",
    "addr:postcode":"60641",
    "addr:street":"W Irving Park Rd",
    "iso:country":"US",
    "sg:address":"4730 W Irving Park Rd",
    "sg:city":"Chicago",
    "sg:classifiers":[
        {
            "category":"Personal",
            "type":"Services"
        }
    ],
    "sg:phone":"+1 773 205 3864",
    "sg:postcode":"60641",
    "sg:province":"IL",
    "sg:tags":[
        "wear",
        "formal"
    ],
    "wof:name":"Gingiss Formalwear",
    "wof:placetype":"venue"
},
  "geometry": {"coordinates":[-87.74681,41.953506],"type":"Point"}
}