{
  "type": "Feature",
  "properties": {
    "addr:full":"9940 Bunkum Rd Fairview Heights IL 62208",
    "addr:postcode":"9940;62208",
    "addr:street":"Bunkum Rd",
    "iso:country":"US",
    "sg:address":"9940 Bunkum Rd",
    "sg:city":"Fairview Heights",
    "sg:classifiers":[
        {
            "category":"Education",
            "subcategory":"School",
            "type":"Public Place"
        }
    ],
    "sg:phone":"+1 618 397 7277",
    "sg:postcode":"62208",
    "sg:province":"IL",
    "wof:name":"Our Lady-Assumption Rectory",
    "wof:placetype":"venue"
},
  "geometry": {"coordinates":[-90.01741699999999,38.605888],"type":"Point"}
}