{
  "type": "Feature",
  "properties": {
    "iso:country":"US",
    "sg:address":"444 S York Rd",
    "sg:city":"Elmhurst",
    "sg:classifiers":[
        {
            "category":"Professional",
            "subcategory":"Computer Services",
            "type":"Services"
        }
    ],
    "sg:phone":"+1 630 279 9292",
    "sg:postcode":"60126",
    "sg:province":"IL",
    "sg:tags":[
        "consultant",
        "designer",
        "datum",
        "system"
    ],
    "sg:website":"www.efaxcorp.com",
    "wof:name":"Efax Corp",
    "wof:placetype":"venue"
},
  "geometry": {"coordinates":[-87.932442,41.867391],"type":"Point"}
}