{
  "type": "Feature",
  "properties": {
    "iso:country":"US",
    "sg:address":"1768 N 2759th Rd",
    "sg:city":"Ottawa",
    "sg:classifiers":[
        {
            "category":"Professional",
            "subcategory":"Business Services",
            "type":"Services"
        }
    ],
    "sg:phone":"+1 815 433 5433",
    "sg:postcode":"61350",
    "sg:province":"IL",
    "wof:name":"Wild Goose Chase Design",
    "wof:placetype":"venue"
},
  "geometry": {"coordinates":[-88.821382,41.334816],"type":"Point"}
}