{
  "type": "Feature",
  "properties": {
    "iso:country":"US",
    "sg:address":"209 Santos Ave",
    "sg:city":"Minooka",
    "sg:classifiers":[
        {
            "category":"Professional",
            "subcategory":"Management & Consulting",
            "type":"Services"
        }
    ],
    "sg:phone":"+1 815 467 1407",
    "sg:postcode":"60447",
    "sg:province":"IL",
    "wof:name":"Lakesidevents Inc",
    "wof:placetype":"venue"
},
  "geometry": {"coordinates":[-88.244647,41.44596],"type":"Point"}
}