{
  "type": "Feature",
  "properties": {
    "iso:country":"US",
    "sg:address":"629 W Cermak Rd Ste 205",
    "sg:city":"Chicago",
    "sg:classifiers":[
        {
            "category":"Professional",
            "subcategory":"Management & Consulting",
            "type":"Services"
        },
        {
            "category":"Professional",
            "subcategory":"Business Services",
            "type":"Services"
        }
    ],
    "sg:phone":"+1 773 268 5620",
    "sg:postcode":"60616",
    "sg:province":"IL",
    "sg:tags":[
        "consultant",
        "life",
        "coach"
    ],
    "sg:website":"www.visioncatalystconsulting.com",
    "wof:name":"Vision Catalyst Consulting",
    "wof:placetype":"venue"
},
  "geometry": {"coordinates":[-87.643198,41.852408],"type":"Point"}
}