{
  "type": "Feature",
  "properties": {
    "iso:country":"US",
    "sg:address":"2115 N Sedgwick St 1B",
    "sg:city":"Chicago",
    "sg:classifiers":[
        {
            "category":"Food & Beverages",
            "subcategory":"Specialty",
            "type":"Retail Goods"
        }
    ],
    "sg:phone":"+1 773 412 3843",
    "sg:postcode":"60614",
    "sg:province":"IL",
    "sg:tags":[
        "product",
        "health",
        "diet"
    ],
    "wof:name":"Workoutsupplies.com",
    "wof:placetype":"venue"
},
  "geometry": {"coordinates":[-87.638846,41.92039],"type":"Point"}
}