{
  "type": "Feature",
  "properties": {
    "iso:country":"US",
    "sg:address":"25 Church St",
    "sg:city":"German Valley",
    "sg:classifiers":[
        {
            "category":"Restaurant",
            "type":"Food & Drink"
        }
    ],
    "sg:phone":"+1 815 362 3000",
    "sg:postcode":"61039",
    "sg:province":"IL",
    "wof:name":"Gibby's Restaurant",
    "wof:placetype":"venue"
},
  "geometry": {"coordinates":[-89.47407699999999,42.215303],"type":"Point"}
}