{
  "type": "Feature",
  "properties": {
    "addr:full":"21 S Clark Street Chicago IL 60603",
    "addr:housenumber":"21",
    "addr:postcode":"60603",
    "addr:street":"S Clark Street",
    "iso:country":"US",
    "sg:address":"21 S Clark Street",
    "sg:city":"Chicago",
    "sg:classifiers":[
        {
            "category":"Banks & Credit Unions",
            "subcategory":"Financial Services",
            "type":"Services"
        }
    ],
    "sg:phone":"+1 312 984 5056",
    "sg:postcode":"60603",
    "sg:province":"IL",
    "sg:tags":[
        "broker",
        "mortgage"
    ],
    "wof:name":"Seamens",
    "wof:placetype":"venue"
},
  "geometry": {"coordinates":[-87.63083399999999,41.881702],"type":"Point"}
}