{
  "type": "Feature",
  "properties": {
    "addr:full":"615 S Main St Bourbonnais IL 60914",
    "addr:housenumber":"615",
    "addr:postcode":"60914",
    "addr:street":"S Main St",
    "iso:country":"US",
    "sg:address":"615 S Main St",
    "sg:city":"Bourbonnais",
    "sg:classifiers":[
        {
            "category":"Social Services",
            "subcategory":"Child Care",
            "type":"Services"
        }
    ],
    "sg:phone":"+1 815 932 8411",
    "sg:postcode":"60914",
    "sg:province":"IL",
    "sg:tags":[
        "day"
    ],
    "wof:name":"Alfred Fortin Villa",
    "wof:placetype":"venue"
},
  "geometry": {"coordinates":[-87.87565600000001,41.149771],"type":"Point"}
}