{
  "type": "Feature",
  "properties": {
    "iso:country":"US",
    "sg:address":"121 N 1st St",
    "sg:city":"Sherman",
    "sg:classifiers":[
        {
            "category":"Bars & Pubs",
            "type":"Food & Drink"
        }
    ],
    "sg:phone":"+1 217 496 3811",
    "sg:postcode":"62684",
    "sg:province":"IL",
    "wof:name":"Double H Bar",
    "wof:placetype":"venue"
},
  "geometry": {"coordinates":[-89.600451,39.895882],"type":"Point"}
}