{
  "type": "Feature",
  "properties": {
    "iso:country":"US",
    "sg:address":"1926 W Harrison St",
    "sg:city":"Chicago",
    "sg:classifiers":[
        {
            "category":"Travel",
            "subcategory":"Travel Agent",
            "type":"Entertainment"
        },
        {
            "category":"Landmark",
            "subcategory":"Tourist Information",
            "type":"Public Place"
        }
    ],
    "sg:phone":"+1 312 226 3660",
    "sg:postcode":"60612",
    "sg:province":"IL",
    "sg:tags":[
        "agency",
        "services-commercial",
        "tours-operators",
        "promoter"
    ],
    "wof:name":"Direct Express Tours",
    "wof:placetype":"venue"
},
  "geometry": {"coordinates":[-87.675021,41.874059],"type":"Point"}
}