{
  "type": "Feature",
  "properties": {
    "addr:full":"177 N Center St Braidwood IL 60408",
    "addr:housenumber":"177",
    "addr:postcode":"60408",
    "addr:street":"N Center St",
    "iso:country":"US",
    "sg:address":"177 N Center St",
    "sg:city":"Braidwood",
    "sg:classifiers":[
        {
            "category":"Building & Trades",
            "subcategory":"Construction",
            "type":"Services"
        }
    ],
    "sg:phone":"+1 815 634 2072",
    "sg:postcode":"60408",
    "sg:province":"IL",
    "sg:tags":[
        "roofing",
        "contractor"
    ],
    "wof:name":"Look Up Roofing",
    "wof:placetype":"venue"
},
  "geometry": {"coordinates":[-88.217291,41.266655],"type":"Point"}
}