{
  "type": "Feature",
  "properties": {
    "iso:country":"US",
    "sg:address":"280 S Summit Ave",
    "sg:city":"Villa Park",
    "sg:classifiers":[
        {
            "category":"Professional",
            "subcategory":"Management & Consulting",
            "type":"Services"
        }
    ],
    "sg:phone":"+1 630 916 7373",
    "sg:postcode":"60181",
    "sg:province":"IL",
    "wof:name":"Priebe Rd & Assoc",
    "wof:placetype":"venue"
},
  "geometry": {"coordinates":[-87.974136,41.884294],"type":"Point"}
}