{
  "type": "Feature",
  "properties": {
    "iso:country":"US",
    "sg:address":"6949 North Ave",
    "sg:city":"Oak Park",
    "sg:classifiers":[
        {
            "category":"Utilities",
            "subcategory":"Mobile Phone",
            "type":"Services"
        }
    ],
    "sg:phone":"+1 708 386 6999",
    "sg:postcode":"60302",
    "sg:province":"IL",
    "sg:tags":[
        "equipment",
        "paging",
        "system",
        "signaling"
    ],
    "wof:name":"Don't Call Me I'll Call You",
    "wof:placetype":"venue"
},
  "geometry": {"coordinates":[-87.800003,41.908798],"type":"Point"}
}