{
  "type": "Feature",
  "properties": {
    "iso:country":"US",
    "sg:address":"104 Main St",
    "sg:city":"West Chicago",
    "sg:classifiers":[
        {
            "category":"Health Services",
            "subcategory":"Chiropractor",
            "type":"Services"
        }
    ],
    "sg:phone":"+1 630 231 0445",
    "sg:postcode":"60185",
    "sg:province":"IL",
    "wof:name":"Community Chiropractic Center",
    "wof:placetype":"venue"
},
  "geometry": {"coordinates":[-88.20504200000001,41.884525],"type":"Point"}
}