{
  "type": "Feature",
  "properties": {
    "iso:country":"US",
    "sg:address":"689 Tomahawk Ln",
    "sg:city":"Crystal Lake",
    "sg:classifiers":[
        {
            "category":"Professional",
            "subcategory":"Business Services",
            "type":"Services"
        }
    ],
    "sg:phone":"+1   ",
    "sg:postcode":"60012",
    "sg:province":"IL",
    "sg:tags":[
        "as",
        "operates",
        "window",
        "design",
        "interior",
        "retail"
    ],
    "wof:name":"Curtain Call",
    "wof:placetype":"venue"
},
  "geometry": {"coordinates":[-88.314753,42.259214],"type":"Point"}
}