{
  "type": "Feature",
  "properties": {
    "iso:country":"US",
    "sg:address":"315 S Main St",
    "sg:city":"Rockford",
    "sg:classifiers":[
        {
            "category":"Bars & Pubs",
            "type":"Food & Drink"
        }
    ],
    "sg:phone":"+1 815 962 3963",
    "sg:postcode":"61101",
    "sg:province":"IL",
    "wof:name":"J-Bears Place",
    "wof:placetype":"venue"
},
  "geometry": {"coordinates":[-89.096148,42.269189],"type":"Point"}
}