{
  "type": "Feature",
  "properties": {
    "iso:country":"US",
    "sg:address":"711 E 75th Street",
    "sg:city":"Chicago",
    "sg:classifiers":[
        {
            "category":"Professional",
            "subcategory":"Lawyer & Legal Services",
            "type":"Services"
        }
    ],
    "sg:phone":"+1 773 846 2500",
    "sg:postcode":"60619",
    "sg:province":"IL",
    "wof:name":"Wright E Kenneth Lwyr Jr",
    "wof:placetype":"venue"
},
  "geometry": {"coordinates":[-87.607429,41.758517],"type":"Point"}
}