{
  "type": "Feature",
  "properties": {
    "addr:full":"8850 Petroff Dr Caseyville IL 62232",
    "addr:postcode":"8850;62232",
    "addr:street":"Petroff Dr",
    "iso:country":"US",
    "sg:address":"8850 Petroff Dr",
    "sg:city":"Caseyville",
    "sg:classifiers":[
        {
            "category":"Restaurant",
            "type":"Food & Drink"
        }
    ],
    "sg:phone":"+1 618 398 0704",
    "sg:postcode":"62232",
    "sg:province":"IL",
    "sg:website":"www.hardees.com",
    "wof:name":"Hardee's",
    "wof:placetype":"venue"
},
  "geometry": {"coordinates":[-90.044601,38.615601],"type":"Point"}
}