{
  "type": "Feature",
  "properties": {
    "addr:full":"4554 S Drexel Blvd Chicago IL 60653",
    "addr:housenumber":"4554",
    "addr:postcode":"60653",
    "addr:street":"S Drexel Blvd",
    "iso:country":"US",
    "sg:address":"4554 S Drexel Blvd",
    "sg:city":"Chicago",
    "sg:classifiers":[
        {
            "category":"Real Estate",
            "subcategory":"Real Estate Operator",
            "type":"Services"
        }
    ],
    "sg:phone":"+1 773 924 5016",
    "sg:postcode":"60653",
    "sg:province":"IL",
    "sg:tags":[
        "building",
        "apartment"
    ],
    "wof:name":"Spring Grove Apts",
    "wof:placetype":"venue"
},
  "geometry": {"coordinates":[-87.604401,41.812199],"type":"Point"}
}