{
  "type": "Feature",
  "properties": {
    "iso:country":"US",
    "sg:address":"1703 S Banker St",
    "sg:city":"Effingham",
    "sg:classifiers":[
        {
            "category":"Home & Garden",
            "subcategory":"Furniture",
            "type":"Retail Goods"
        }
    ],
    "sg:phone":"+1 217 343 1623",
    "sg:postcode":"62401",
    "sg:province":"IL",
    "sg:tags":[
        "cabinet"
    ],
    "wof:name":"Effingham Wholesale Cabinets",
    "wof:placetype":"venue"
},
  "geometry": {"coordinates":[-88.547031,39.106914],"type":"Point"}
}