{
  "type": "Feature",
  "properties": {
    "iso:country":"US",
    "sg:address":"102 S West St",
    "sg:city":"Danvers",
    "sg:classifiers":[
        {
            "category":"Museum",
            "type":"Entertainment"
        }
    ],
    "sg:phone":"+1 309 963 4249",
    "sg:postcode":"61732",
    "sg:province":"IL",
    "wof:name":"Danvers Musuem Meeting Rm",
    "wof:placetype":"venue"
},
  "geometry": {"coordinates":[-89.1968,40.527199],"type":"Point"}
}