{
  "type": "Feature",
  "properties": {
    "iso:country":"US",
    "sg:address":"5300 N River Rd",
    "sg:city":"Rosemont",
    "sg:classifiers":[
        {
            "category":"Shopping",
            "type":"Retail Goods"
        }
    ],
    "sg:phone":"+1 847 447 4112",
    "sg:postcode":"60018",
    "sg:province":"IL",
    "sg:tags":[
        "equipment",
        "clothing",
        "safety"
    ],
    "wof:name":"Cintas",
    "wof:placetype":"venue"
},
  "geometry": {"coordinates":[-87.862419,41.973942],"type":"Point"}
}