{
  "type": "Feature",
  "properties": {
    "iso:country":"US",
    "sg:address":"2626 E Andrew Rd",
    "sg:city":"Sherman",
    "sg:classifiers":[
        {
            "category":"Organizations",
            "subcategory":"Non-profit Organization",
            "type":"Services"
        }
    ],
    "sg:phone":"+1 217 496 2371",
    "sg:postcode":"62684",
    "sg:province":"IL",
    "wof:name":"Illinois Sheriffs' Assoc",
    "wof:placetype":"venue"
},
  "geometry": {"coordinates":[-89.607023,39.896125],"type":"Point"}
}