{
  "type": "Feature",
  "properties": {
    "addr:full":"1905 W Bradley Ave Champaign IL 61821",
    "addr:housenumber":"1905",
    "addr:postcode":"61821",
    "addr:street":"W Bradley Ave",
    "iso:country":"US",
    "sg:address":"1905 W Bradley Ave",
    "sg:city":"Champaign",
    "sg:classifiers":[
        {
            "category":"Retail",
            "subcategory":"Car Wash",
            "type":"Services"
        }
    ],
    "sg:phone":"+1 217 352 9200",
    "sg:postcode":"61821",
    "sg:province":"IL",
    "wof:name":"Triple T Car Wash",
    "wof:placetype":"venue"
},
  "geometry": {"coordinates":[-88.27950300000001,40.1273],"type":"Point"}
}