{
  "type": "Feature",
  "properties": {
    "addr:full":"17340 Torrence Ave Lansing IL 60438",
    "addr:housenumber":"17340",
    "addr:postcode":"60438",
    "addr:street":"Torrence Ave",
    "iso:country":"US",
    "sg:address":"17340 Torrence Ave",
    "sg:city":"Lansing",
    "sg:classifiers":[
        {
            "category":"Banks & Credit Unions",
            "subcategory":"Bank",
            "type":"Services"
        }
    ],
    "sg:phone":"+1 708 474 7448",
    "sg:postcode":"60438",
    "sg:province":"IL",
    "sg:tags":[
        "financing",
        "consumer",
        "loan"
    ],
    "sg:website":"http://www.americashloans.net",
    "wof:name":"Americash Loans",
    "wof:placetype":"venue"
},
  "geometry": {"coordinates":[-87.558891,41.580247],"type":"Point"}
}