{
  "type": "Feature",
  "properties": {
    "addr:full":"5539 Winners Cir Caledonia IL 61011",
    "addr:housenumber":"5539",
    "addr:postcode":"61011",
    "addr:street":"Winners Cir",
    "iso:country":"US",
    "sg:address":"5539 Winners Cir",
    "sg:city":"Caledonia",
    "sg:classifiers":[
        {
            "category":"Organizations",
            "subcategory":"Community Association",
            "type":"Services"
        }
    ],
    "sg:phone":"+1 815 885 9002",
    "sg:postcode":"61011",
    "sg:province":"IL",
    "wof:name":"Military Order of Purple Heart",
    "wof:placetype":"venue"
},
  "geometry": {"coordinates":[-88.966679,42.342343],"type":"Point"}
}