{
  "type": "Feature",
  "properties": {
    "iso:country":"US",
    "sg:address":"201 N 3rd St",
    "sg:city":"Fisher",
    "sg:classifiers":[
        {
            "category":"Government",
            "subcategory":"Office",
            "type":"Public Place"
        }
    ],
    "sg:phone":"+1 217 897 1328",
    "sg:postcode":"61843",
    "sg:province":"IL",
    "sg:tags":[
        "village"
    ],
    "wof:name":"Brown Township",
    "wof:placetype":"venue"
},
  "geometry": {"coordinates":[-88.3498,40.319642],"type":"Point"}
}