{
  "type": "Feature",
  "properties": {
    "iso:country":"US",
    "sg:address":"1440 W Vermont Ave",
    "sg:city":"Calumet Park",
    "sg:classifiers":[
        {
            "category":"Education",
            "subcategory":"School",
            "type":"Public Place"
        }
    ],
    "sg:phone":"+1 708 824 3090",
    "sg:postcode":"60827",
    "sg:province":"IL",
    "sg:tags":[
        "high",
        "middle",
        "elementary"
    ],
    "wof:name":"Burr Oak Acadeny",
    "wof:placetype":"venue"
},
  "geometry": {"coordinates":[-87.65709699999999,41.659401],"type":"Point"}
}