{
  "type": "Feature",
  "properties": {
    "addr:full":"25218 W Il Route 173 Antioch IL 60002",
    "addr:housenumber":"25218",
    "addr:postcode":"60002",
    "addr:street":"W Il Route 173",
    "iso:country":"US",
    "sg:address":"25218 W Il Route 173",
    "sg:city":"Antioch",
    "sg:classifiers":[
        {
            "category":"Personal",
            "subcategory":"Tattoo Parlor",
            "type":"Services"
        }
    ],
    "sg:phone":"+1 847 838 4656",
    "sg:postcode":"60002",
    "sg:province":"IL",
    "wof:name":"Visionary Tattoo",
    "wof:placetype":"venue"
},
  "geometry": {"coordinates":[-88.132599,42.479],"type":"Point"}
}