{
  "type": "Feature",
  "properties": {
    "addr:full":"8601 W 107th St Palos Hills IL 60465",
    "addr:housenumber":"8601",
    "addr:postcode":"60465",
    "addr:street":"W 107Th St",
    "iso:country":"US",
    "sg:address":"8601 W 107th St",
    "sg:city":"Palos Hills",
    "sg:classifiers":[
        {
            "category":"Education",
            "subcategory":"Preschool",
            "type":"Public Place"
        },
        {
            "category":"Education",
            "subcategory":"School",
            "type":"Public Place"
        }
    ],
    "sg:phone":"+1 708 599 1299",
    "sg:postcode":"60465",
    "sg:province":"IL",
    "sg:tags":[
        "elementary"
    ],
    "wof:name":"Moraine Valley Cmty Pre-School",
    "wof:placetype":"venue"
},
  "geometry": {"coordinates":[-87.831802,41.696301],"type":"Point"}
}