{
  "type": "Feature",
  "properties": {
    "addr:full":"5400 N Lawler Avenue Chicago IL 60630",
    "addr:housenumber":"5400",
    "addr:postcode":"60630",
    "addr:street":"N Lawler Avenue",
    "iso:country":"US",
    "sg:address":"5400 N Lawler Avenue",
    "sg:city":"Chicago",
    "sg:classifiers":[
        {
            "category":"Organizations",
            "subcategory":"Religious Organization",
            "type":"Services"
        }
    ],
    "sg:phone":"+1 773 481 1618",
    "sg:postcode":"60630",
    "sg:province":"IL",
    "wof:name":"Holy Mountain Evangelical Church",
    "wof:placetype":"venue"
},
  "geometry": {"coordinates":[-87.753322,41.979932],"type":"Point"}
}