{
  "type": "Feature",
  "properties": {
    "addr:full":"301 S Columbia Ave Oglesby IL 61348",
    "addr:housenumber":"301",
    "addr:postcode":"61348",
    "addr:street":"S Columbia Ave",
    "iso:country":"US",
    "sg:address":"301 S Columbia Ave",
    "sg:city":"Oglesby",
    "sg:classifiers":[
        {
            "category":"Banks & Credit Unions",
            "subcategory":"Bank",
            "type":"Services"
        }
    ],
    "sg:phone":"+1 815 883 8400",
    "sg:postcode":"61348",
    "sg:province":"IL",
    "sg:website":"www.illinistatebank.com",
    "wof:name":"Illini State Bank",
    "wof:placetype":"venue"
},
  "geometry": {"coordinates":[-89.06816999999999,41.292632],"type":"Point"}
}