{
  "type": "Feature",
  "properties": {
    "addr:full":"1117 Howard St Evanston IL 60202",
    "addr:housenumber":"1117",
    "addr:postcode":"60202",
    "addr:street":"Howard St",
    "iso:country":"US",
    "sg:address":"1117 Howard St",
    "sg:city":"Evanston",
    "sg:classifiers":[
        {
            "category":"Restaurant",
            "type":"Food & Drink"
        }
    ],
    "sg:menulink":"http://www.allmenus.com/il/evanston/212346-mcdonalds/menu/",
    "sg:postcode":"60202",
    "sg:province":"IL",
    "sg:tags":[
        "burger",
        "american"
    ],
    "wof:name":"McDonald's",
    "wof:placetype":"venue"
},
  "geometry": {"coordinates":[-87.68787,42.019662],"type":"Point"}
}