{
  "type": "Feature",
  "properties": {
    "addr:full":"8313 W Lawrence Ave Norridge IL 60706",
    "addr:housenumber":"8313",
    "addr:postcode":"60706",
    "addr:street":"W Lawrence Ave",
    "iso:country":"US",
    "sg:address":"8313 W Lawrence Ave",
    "sg:city":"Norridge",
    "sg:classifiers":[
        {
            "category":"Restaurant",
            "type":"Food & Drink"
        }
    ],
    "sg:phone":"+1 708 452 1545",
    "sg:postcode":"60706",
    "sg:province":"IL",
    "sg:tags":[
        "italian"
    ],
    "sg:website":"www.the3olives.com",
    "wof:name":"The 3 Olives Italian Cuisine",
    "wof:placetype":"venue"
},
  "geometry": {"coordinates":[-87.834473,41.966631],"type":"Point"}
}