{
  "type": "Feature",
  "properties": {
    "addr:full":"3467 N Broadway Street Chicago IL 60657",
    "addr:housenumber":"3467",
    "addr:postcode":"60657",
    "addr:street":"N Broadway Street",
    "iso:country":"US",
    "sg:address":"3467 N Broadway Street",
    "sg:city":"Chicago",
    "sg:classifiers":[
        {
            "category":"Shopping",
            "subcategory":"Florist",
            "type":"Retail Goods"
        }
    ],
    "sg:phone":"+1 773 697 0186",
    "sg:postcode":"60657",
    "sg:province":"IL",
    "sg:website":"anthosflowers.com",
    "wof:name":"Anthos Fresh Flowers And Gifts",
    "wof:placetype":"venue"
},
  "geometry": {"coordinates":[-87.645736,41.945228],"type":"Point"}
}