{
  "type": "Feature",
  "properties": {
    "addr:full":"13 S 3rd St Geneva IL 60134",
    "addr:housenumber":"13",
    "addr:postcode":"60134",
    "addr:street":"S 3Rd St",
    "iso:country":"US",
    "sg:address":"13 S 3rd St",
    "sg:city":"Geneva",
    "sg:classifiers":[
        {
            "category":"Professional",
            "type":"Services"
        }
    ],
    "sg:phone":"+1 630 232 6669",
    "sg:postcode":"60134",
    "sg:province":"IL",
    "sg:tags":[
        "establishment"
    ],
    "wof:name":"Bravissimo",
    "wof:placetype":"venue"
},
  "geometry": {"coordinates":[-88.308014,41.886969],"type":"Point"}
}