{
  "type": "Feature",
  "properties": {
    "addr:full":"787 Greenbay Ave Calumet City IL 60409",
    "addr:housenumber":"787",
    "addr:postcode":"60409",
    "addr:street":"Greenbay Ave",
    "iso:country":"US",
    "sg:address":"787 Greenbay Ave",
    "sg:city":"Calumet City",
    "sg:classifiers":[
        {
            "category":"Shopping",
            "type":"Retail Goods"
        }
    ],
    "sg:phone":"+1   ",
    "sg:postcode":"60409",
    "sg:province":"IL",
    "sg:tags":[
        "merchandise"
    ],
    "wof:name":"Glos Boutique Shop",
    "wof:placetype":"venue"
},
  "geometry": {"coordinates":[-87.54067000000001,41.610527],"type":"Point"}
}