{
  "type": "Feature",
  "properties": {
    "iso:country":"US",
    "sg:address":"911 Pekin St",
    "sg:city":"Lincoln",
    "sg:classifiers":[
        {
            "category":"Government",
            "subcategory":"Office",
            "type":"Public Place"
        },
        {
            "category":"Government",
            "subcategory":"Court House",
            "type":"Public Place"
        }
    ],
    "sg:phone":"+1 217 732 9491",
    "sg:postcode":"62656",
    "sg:province":"IL",
    "sg:tags":[
        "county",
        "executive",
        "safety",
        "order"
    ],
    "wof:name":"Lincoln-Logan Emergency Svcs-D",
    "wof:placetype":"venue"
},
  "geometry": {"coordinates":[-89.359509,40.146075],"type":"Point"}
}