{
  "type": "Feature",
  "properties": {
    "addr:full":"4512 W Schubert Chicago IL 60639",
    "addr:housenumber":"4512",
    "addr:postcode":"60639",
    "addr:street":"W Schubert",
    "iso:country":"US",
    "sg:address":"4512 W Schubert",
    "sg:city":"Chicago",
    "sg:classifiers":[
        {
            "category":"Place Of Worship",
            "subcategory":"Church",
            "type":"Public Place"
        }
    ],
    "sg:phone":"+1 773 621 1890",
    "sg:postcode":"60639",
    "sg:province":"IL",
    "sg:website":"www.hourofchangeministries.com",
    "wof:name":"Hour Of Change Ministries",
    "wof:placetype":"venue"
},
  "geometry": {"coordinates":[-87.739755,41.929857],"type":"Point"}
}