{
  "type": "Feature",
  "properties": {
    "iso:country":"US",
    "sg:address":"9428 47th St",
    "sg:city":"Brookfield",
    "sg:classifiers":[
        {
            "category":"Wholesale",
            "subcategory":"Machinery & Supplies",
            "type":"Manufacturing & Wholesale Goods"
        }
    ],
    "sg:phone":"+1 708 387 3170",
    "sg:postcode":"60513",
    "sg:province":"IL",
    "sg:tags":[
        "equipment",
        "pump",
        "pumping"
    ],
    "wof:name":"P S I",
    "wof:placetype":"venue"
},
  "geometry": {"coordinates":[-87.85456499999999,41.805371],"type":"Point"}
}