{
  "type": "Feature",
  "properties": {
    "addr:full":"2741 Abbington Dr New Lenox IL 60451",
    "addr:postcode":"2741;60451",
    "addr:street":"Abbington Dr",
    "iso:country":"US",
    "sg:address":"2741 Abbington Dr",
    "sg:city":"New Lenox",
    "sg:classifiers":[
        {
            "category":"Travel",
            "subcategory":"Travel Agent",
            "type":"Entertainment"
        }
    ],
    "sg:phone":"+1 815 485 1825",
    "sg:postcode":"60451",
    "sg:province":"IL",
    "sg:tags":[
        "agency"
    ],
    "wof:name":"Sun & Sea Travel",
    "wof:placetype":"venue"
},
  "geometry": {"coordinates":[-87.927369,41.47324],"type":"Point"}
}