{
  "type": "Feature",
  "properties": {
    "iso:country":"US",
    "sg:address":"13647 Southwest Hwy",
    "sg:city":"Orland Park",
    "sg:classifiers":[
        {
            "category":"Wholesale",
            "subcategory":"Apparel",
            "type":"Manufacturing & Wholesale Goods"
        }
    ],
    "sg:phone":"+1 708 403 1800",
    "sg:postcode":"60462",
    "sg:province":"IL",
    "sg:tags":[
        "import",
        "clothing"
    ],
    "wof:name":"Paul John International Inc",
    "wof:placetype":"venue"
},
  "geometry": {"coordinates":[-87.849088,41.641191],"type":"Point"}
}