{
  "type": "Feature",
  "properties": {
    "addr:full":"248 Houston St Batavia IL 60510",
    "addr:housenumber":"248",
    "addr:postcode":"60510",
    "addr:street":"Houston St",
    "iso:country":"US",
    "sg:address":"248 Houston St",
    "sg:city":"Batavia",
    "sg:classifiers":[
        {
            "category":"Manufacturing",
            "subcategory":"Retail Goods",
            "type":"Manufacturing & Wholesale Goods"
        }
    ],
    "sg:phone":"+1 630 879 2112",
    "sg:postcode":"60510",
    "sg:province":"IL",
    "sg:tags":[
        "rubber",
        "stamp"
    ],
    "wof:name":"Rayco Stamps",
    "wof:placetype":"venue"
},
  "geometry": {"coordinates":[-88.311682,41.851039],"type":"Point"}
}