{
  "type": "Feature",
  "properties": {
    "iso:country":"US",
    "sg:address":"4402 Smelting Works Rd",
    "sg:city":"Swansea",
    "sg:classifiers":[
        {
            "category":"Ice Cream",
            "type":"Food & Drink"
        }
    ],
    "sg:phone":"+1 618 234 2163",
    "sg:postcode":"62226",
    "sg:province":"IL",
    "sg:tags":[
        "frozen",
        "yogurt"
    ],
    "wof:name":"Reeb's Wholesale",
    "wof:placetype":"venue"
},
  "geometry": {"coordinates":[-89.982101,38.5704],"type":"Point"}
}