{
  "type": "Feature",
  "properties": {
    "addr:full":"4531 W 65th St Chicago IL 60629",
    "addr:housenumber":"4531",
    "addr:postcode":"60629",
    "addr:street":"W 65Th St",
    "iso:country":"US",
    "sg:address":"4531 W 65th St",
    "sg:city":"Chicago",
    "sg:classifiers":[
        {
            "category":"Home & Garden",
            "subcategory":"Home Furnishings",
            "type":"Retail Goods"
        }
    ],
    "sg:phone":"+1 773 512 6444",
    "sg:postcode":"60629",
    "sg:province":"IL",
    "sg:tags":[
        "refacing",
        "resurfacing",
        "cabinets-refinishing",
        "kitchen"
    ],
    "sg:website":"http://www.servicemagic.com/rated.CreativeCustomPainting.16558277.AllCats.html?m=cahscitysrchxm&entry_point_id=479710",
    "wof:name":"Creative Custom Painting, Inc.",
    "wof:placetype":"venue"
},
  "geometry": {"coordinates":[-87.73539100000001,41.774865],"type":"Point"}
}