{
  "type": "Feature",
  "properties": {
    "addr:full":"1127 Andres Ln Winchester IL 62694",
    "addr:housenumber":"1127",
    "addr:postcode":"62694",
    "addr:street":"Andres Ln",
    "iso:country":"US",
    "sg:address":"1127 Andres Ln",
    "sg:city":"Winchester",
    "sg:phone":"+1 217 754 3919",
    "sg:postcode":"62694",
    "sg:province":"IL",
    "sg:tags":[
        "farm",
        "corn"
    ],
    "wof:name":"Harvey Andres",
    "wof:placetype":"venue"
},
  "geometry": {"coordinates":[-90.53231100000001,39.684723],"type":"Point"}
}