{
  "type": "Feature",
  "properties": {
    "iso:country":"US",
    "sg:address":"3525 W Peterson Ave # 103",
    "sg:city":"Chicago",
    "sg:classifiers":[
        {
            "category":"Health Services",
            "subcategory":"Dentist",
            "type":"Services"
        }
    ],
    "sg:phone":"+1 773 588 8378",
    "sg:postcode":"60659",
    "sg:province":"IL",
    "sg:tags":[
        "laboratories-medical",
        "dental",
        "x-ray"
    ],
    "wof:name":"Accurate Imaging Diagnostic Ltd",
    "wof:placetype":"venue"
},
  "geometry": {"coordinates":[-87.717448,41.990299],"type":"Point"}
}