{
  "type": "Feature",
  "properties": {
    "addr:full":"5100 N Marine Dr Chicago IL 60640",
    "addr:housenumber":"5100",
    "addr:postcode":"60640",
    "addr:street":"N Marine Dr",
    "iso:country":"US",
    "sg:address":"5100 N Marine Dr",
    "sg:city":"Chicago",
    "sg:classifiers":[
        {
            "category":"Real Estate",
            "subcategory":"Real Estate Operator",
            "type":"Services"
        }
    ],
    "sg:phone":"+1 773 275 5100",
    "sg:postcode":"60640",
    "sg:province":"IL",
    "sg:tags":[
        "condominium"
    ],
    "wof:name":"5100 N Marine Drive Condo",
    "wof:placetype":"venue"
},
  "geometry": {"coordinates":[-87.651956,41.975919],"type":"Point"}
}