{
  "type": "Feature",
  "properties": {
    "iso:country":"US",
    "sg:address":"7200 Harrison Ave",
    "sg:city":"Rockford",
    "sg:classifiers":[
        {
            "category":"Shopping",
            "subcategory":"Optical Goods",
            "type":"Retail Goods"
        }
    ],
    "sg:phone":"+1   ",
    "sg:postcode":"61112",
    "sg:province":"IL",
    "wof:name":"Sears Optical",
    "wof:placetype":"venue"
},
  "geometry": {"coordinates":[-88.97232099999999,42.240767],"type":"Point"}
}