{
  "type": "Feature",
  "properties": {
    "addr:full":"3620 W 16th Street Chicago IL 60623",
    "addr:housenumber":"3620",
    "addr:postcode":"60623",
    "addr:street":"W 16Th Street",
    "iso:country":"US",
    "sg:address":"3620 W 16th Street",
    "sg:city":"Chicago",
    "sg:classifiers":[
        {
            "category":"Restaurant",
            "type":"Food & Drink"
        }
    ],
    "sg:phone":"+1 773 762 1650",
    "sg:postcode":"60623",
    "sg:province":"IL",
    "wof:name":"Great Lakes Fish and Chicken",
    "wof:placetype":"venue"
},
  "geometry": {"coordinates":[-87.716036,41.858982],"type":"Point"}
}