{
  "type": "Feature",
  "properties": {
    "addr:full":"2252 24th St Rock Island IL 61201",
    "addr:housenumber":"2252",
    "addr:postcode":"61201",
    "addr:street":"24Th St",
    "iso:country":"US",
    "sg:address":"2252 24th St",
    "sg:city":"Rock Island",
    "sg:classifiers":[
        {
            "category":"Food & Beverages",
            "subcategory":"Groceries & Convenience Stores",
            "type":"Retail Goods"
        }
    ],
    "sg:phone":"+1   ",
    "sg:postcode":"61201",
    "sg:province":"IL",
    "wof:name":"Rock Island Country Mkts LLC",
    "wof:placetype":"venue"
},
  "geometry": {"coordinates":[-90.567033,41.488209],"type":"Point"}
}