{
  "type": "Feature",
  "properties": {
    "iso:country":"US",
    "sg:address":"1722 W 18th",
    "sg:city":"Chicago",
    "sg:classifiers":[
        {
            "category":"Home & Garden",
            "subcategory":"Household Appliances",
            "type":"Retail Goods"
        }
    ],
    "sg:phone":"+1 312 563 0550",
    "sg:postcode":"60607",
    "sg:province":"IL",
    "wof:name":"Mossos Appliances Heating & Cooling",
    "wof:placetype":"venue"
},
  "geometry": {"coordinates":[-87.669408,41.856965],"type":"Point"}
}