{
  "type": "Feature",
  "properties": {
    "addr:full":"107 W Commercial Dr Carterville IL 62918",
    "addr:housenumber":"107",
    "addr:postcode":"62918",
    "addr:street":"W Commercial Dr",
    "iso:country":"US",
    "sg:address":"107 W Commercial Dr",
    "sg:city":"Carterville",
    "sg:classifiers":[
        {
            "category":"Insurance",
            "subcategory":"Insurance Agent",
            "type":"Services"
        }
    ],
    "sg:phone":"+1 618 985 3736",
    "sg:postcode":"62918",
    "sg:province":"IL",
    "wof:name":"State Farm Insurance",
    "wof:placetype":"venue"
},
  "geometry": {"coordinates":[-89.077316,37.744465],"type":"Point"}
}