{
  "type": "Feature",
  "properties": {
    "iso:country":"US",
    "sg:address":"730 Terra West Dr",
    "sg:city":"Freeport",
    "sg:classifiers":[
        {
            "category":"Real Estate",
            "subcategory":"Real Estate Operator",
            "type":"Services"
        }
    ],
    "sg:phone":"+1 815 235 2362",
    "sg:postcode":"61032",
    "sg:province":"IL",
    "sg:tags":[
        "property",
        "lessor"
    ],
    "wof:name":"Chester & Dorothy Miller",
    "wof:placetype":"venue"
},
  "geometry": {"coordinates":[-89.66933,42.293454],"type":"Point"}
}