{
  "type": "Feature",
  "properties": {
    "addr:full":"1213 E Oakton St Arlington Heights IL 60004",
    "addr:housenumber":"1213",
    "addr:postcode":"60004",
    "addr:street":"E Oakton St",
    "iso:country":"US",
    "sg:address":"1213 E Oakton St",
    "sg:city":"Arlington Heights",
    "sg:classifiers":[
        {
            "category":"Education",
            "subcategory":"School",
            "type":"Public Place"
        }
    ],
    "sg:phone":"+1 847 392 4050",
    "sg:postcode":"60004",
    "sg:province":"IL",
    "sg:tags":[
        "high"
    ],
    "wof:name":"St Viator High School",
    "wof:placetype":"venue"
},
  "geometry": {"coordinates":[-87.966522,42.095378],"type":"Point"}
}