{
  "type": "Feature",
  "properties": {
    "iso:country":"US",
    "sg:address":"7406 W Hillside Rd",
    "sg:city":"Crystal Lake",
    "sg:classifiers":[
        {
            "category":"Shopping",
            "subcategory":"Catalog Store",
            "type":"Retail Goods"
        }
    ],
    "sg:phone":"+1   ",
    "sg:postcode":"60012",
    "sg:province":"IL",
    "sg:tags":[
        "mail",
        "house"
    ],
    "wof:name":"Pastperfect",
    "wof:placetype":"venue"
},
  "geometry": {"coordinates":[-88.34148,42.266582],"type":"Point"}
}