{
  "type": "Feature",
  "properties": {
    "addr:full":"1 W Superior Street Chicago IL 60654",
    "addr:housenumber":"1",
    "addr:postcode":"60654",
    "addr:street":"W Superior Street",
    "iso:country":"US",
    "sg:address":"1 W Superior Street",
    "sg:city":"Chicago",
    "sg:classifiers":[
        {
            "category":"Cinema",
            "subcategory":"Movie Rental",
            "type":"Entertainment"
        },
        {
            "category":"Shopping",
            "subcategory":"Music",
            "type":"Retail Goods"
        }
    ],
    "sg:phone":"+1 312 337 2660",
    "sg:postcode":"60654",
    "sg:province":"IL",
    "sg:tags":[
        "game",
        "video",
        "dvd's"
    ],
    "sg:website":"www.blockbuster.com",
    "wof:name":"Blockbuster Video",
    "wof:placetype":"venue"
},
  "geometry": {"coordinates":[-87.628927,41.895617],"type":"Point"}
}