{
  "type": "Feature",
  "properties": {
    "addr:full":"10 E Grand Ave Chicago IL 60611",
    "addr:housenumber":"10",
    "addr:postcode":"60611",
    "addr:street":"E Grand Ave",
    "iso:country":"US",
    "sg:address":"10 E Grand Ave",
    "sg:city":"Chicago",
    "sg:classifiers":[
        {
            "category":"Parking",
            "type":"Transportation"
        },
        {
            "category":"Parking",
            "subcategory":"Garage",
            "type":"Transportation"
        }
    ],
    "sg:phone":"+1 312 822 1007",
    "sg:postcode":"60611",
    "sg:province":"IL",
    "sg:tags":[
        "attendant",
        "lot"
    ],
    "wof:name":"Inter Park",
    "wof:placetype":"venue"
},
  "geometry": {"coordinates":[-87.627724,41.891665],"type":"Point"}
}