{
  "type": "Feature",
  "properties": {
    "iso:country":"US",
    "sg:address":"2659 W Armitage Avenue",
    "sg:city":"Chicago",
    "sg:classifiers":[
        {
            "category":"Personal",
            "type":"Services"
        },
        {
            "category":"Retail",
            "subcategory":"Laundry & Dry Cleaning",
            "type":"Services"
        }
    ],
    "sg:phone":"+1 773 384 3474",
    "sg:postcode":"60647",
    "sg:province":"IL",
    "sg:tags":[
        "sewing",
        "alteration"
    ],
    "wof:name":"Gina's Cleaners",
    "wof:placetype":"venue"
},
  "geometry": {"coordinates":[-87.694177,41.917517],"type":"Point"}
}