{
  "type": "Feature",
  "properties": {
    "iso:country":"US",
    "sg:address":"16425 Plymouth Dr",
    "sg:city":"Markham",
    "sg:classifiers":[
        {
            "category":"Building & Trades",
            "subcategory":"Construction",
            "type":"Services"
        }
    ],
    "sg:phone":"+1 708 331 7743",
    "sg:postcode":"60428",
    "sg:province":"IL",
    "sg:tags":[
        "contractor"
    ],
    "wof:name":"Dream Wurks Cleaning Service",
    "wof:placetype":"venue"
},
  "geometry": {"coordinates":[-87.68344999999999,41.591271],"type":"Point"}
}