{
  "type": "Feature",
  "properties": {
    "addr:full":"2468 Lincoln Hwy Olympia Fields IL 60461",
    "addr:housenumber":"2468",
    "addr:postcode":"60461",
    "addr:street":"Lincoln Hwy",
    "iso:country":"US",
    "sg:address":"2468 Lincoln Hwy",
    "sg:city":"Olympia Fields",
    "sg:classifiers":[
        {
            "category":"Shopping",
            "subcategory":"Discount & Variety Stores",
            "type":"Retail Goods"
        }
    ],
    "sg:phone":"+1 708 503 9760",
    "sg:postcode":"60461",
    "sg:province":"IL",
    "wof:name":"Dollar Store",
    "wof:placetype":"venue"
},
  "geometry": {"coordinates":[-87.676374,41.506103],"type":"Point"}
}