{
  "type": "Feature",
  "properties": {
    "addr:full":"100 S River St Aurora IL 60506",
    "addr:housenumber":"100",
    "addr:postcode":"60506",
    "addr:street":"S River St",
    "iso:country":"US",
    "sg:address":"100 S River St",
    "sg:city":"Aurora",
    "sg:classifiers":[
        {
            "category":"Wholesale",
            "subcategory":"Medical Equipment & Supplies",
            "type":"Manufacturing & Wholesale Goods"
        }
    ],
    "sg:phone":"+1 630 906 9852",
    "sg:postcode":"60506",
    "sg:province":"IL",
    "sg:tags":[
        "handicapped"
    ],
    "wof:name":"East Side Automotive-Constr",
    "wof:placetype":"venue"
},
  "geometry": {"coordinates":[-88.321612,41.755427],"type":"Point"}
}