{
  "type": "Feature",
  "properties": {
    "addr:full":"712 Oakwood Ave Lake Forest IL 60045",
    "addr:housenumber":"712",
    "addr:postcode":"60045",
    "addr:street":"Oakwood Ave",
    "iso:country":"US",
    "sg:address":"712 Oakwood Ave",
    "sg:city":"Lake Forest",
    "sg:classifiers":[
        {
            "category":"Professional",
            "type":"Services"
        }
    ],
    "sg:phone":"+1 847 735 0923",
    "sg:postcode":"60045",
    "sg:province":"IL",
    "sg:tags":[
        "establishment"
    ],
    "wof:name":"Case Corp",
    "wof:placetype":"venue"
},
  "geometry": {"coordinates":[-87.842454,42.251362],"type":"Point"}
}