{
  "type": "Feature",
  "properties": {
    "iso:country":"US",
    "sg:address":"319 S Jefferson St",
    "sg:city":"Chicago",
    "sg:classifiers":[
        {
            "category":"Food & Beverages",
            "subcategory":"Bakery",
            "type":"Retail Goods"
        }
    ],
    "sg:phone":"+1 312 461 0377",
    "sg:postcode":"60661",
    "sg:province":"IL",
    "sg:tags":[
        "sandwich"
    ],
    "sg:website":"www.subway.com",
    "wof:name":"Subway",
    "wof:placetype":"venue"
},
  "geometry": {"coordinates":[-87.642084,41.877369],"type":"Point"}
}