{
  "type": "Feature",
  "properties": {
    "iso:country":"US",
    "sg:address":"2157 Hull Dr",
    "sg:city":"Wheaton",
    "sg:classifiers":[
        {
            "category":"Building & Trades",
            "subcategory":"Construction",
            "type":"Services"
        }
    ],
    "sg:phone":"+1 630 682 1420",
    "sg:postcode":"60187",
    "sg:province":"IL",
    "sg:tags":[
        "painting",
        "contractor"
    ],
    "wof:name":"Leo & Sons Decorating Inc",
    "wof:placetype":"venue"
},
  "geometry": {"coordinates":[-88.08984700000001,41.827601],"type":"Point"}
}