{
  "type": "Feature",
  "properties": {
    "iso:country":"US",
    "sg:address":"10221 W Steger Rd",
    "sg:city":"Frankfort",
    "sg:classifiers":[
        {
            "category":"Freight",
            "type":"Transportation"
        }
    ],
    "sg:phone":"+1 815 464 7452",
    "sg:postcode":"60423",
    "sg:province":"IL",
    "sg:tags":[
        "operator",
        "local",
        "trucking"
    ],
    "wof:name":"Bishop Trucking Inc",
    "wof:placetype":"venue"
},
  "geometry": {"coordinates":[-87.860903,41.469926],"type":"Point"}
}