{
  "type": "Feature",
  "properties": {
    "iso:country":"US",
    "sg:address":"9748 N Il Route 47",
    "sg:city":"Huntley",
    "sg:classifiers":[
        {
            "category":"Personal",
            "subcategory":"Nail Salon",
            "type":"Services"
        }
    ],
    "sg:phone":"+1 847 669 2800",
    "sg:postcode":"60142",
    "sg:province":"IL",
    "wof:name":"Nails Spa",
    "wof:placetype":"venue"
},
  "geometry": {"coordinates":[-88.422265,42.187156],"type":"Point"}
}