{
  "type": "Feature",
  "properties": {
    "iso:country":"US",
    "sg:address":"335 S Green Bay Rd",
    "sg:city":"Waukegan",
    "sg:classifiers":[
        {
            "category":"Wholesale",
            "subcategory":"Machinery & Supplies",
            "type":"Manufacturing & Wholesale Goods"
        },
        {
            "category":"Wholesale",
            "subcategory":"Groceries",
            "type":"Manufacturing & Wholesale Goods"
        }
    ],
    "sg:phone":"+1 847 623 3478",
    "sg:postcode":"60085",
    "sg:province":"IL",
    "sg:tags":[
        "baker"
    ],
    "sg:website":"www.bevsworldonline.com",
    "wof:name":"Bev's World",
    "wof:placetype":"venue"
},
  "geometry": {"coordinates":[-87.873707,42.354094],"type":"Point"}
}