{
  "type": "Feature",
  "properties": {
    "addr:full":"385 Waukegan Rd Northbrook IL 60062",
    "addr:housenumber":"385",
    "addr:postcode":"60062",
    "addr:street":"Waukegan Rd",
    "iso:country":"US",
    "sg:address":"385 Waukegan Rd",
    "sg:city":"Northbrook",
    "sg:classifiers":[
        {
            "category":"Retail",
            "subcategory":"Funeral Services",
            "type":"Services"
        }
    ],
    "sg:phone":"+1 847 272 3890",
    "sg:postcode":"60062",
    "sg:province":"IL",
    "sg:tags":[
        "home"
    ],
    "wof:name":"Hanekamp Funeral Home PC",
    "wof:placetype":"venue"
},
  "geometry": {"coordinates":[-87.831534,42.147065],"type":"Point"}
}