{
  "type": "Feature",
  "properties": {
    "addr:full":"4826 Venture St Lisle IL 60532",
    "addr:housenumber":"4826",
    "addr:postcode":"60532",
    "addr:street":"Venture St",
    "iso:country":"US",
    "sg:address":"4826 Venture St",
    "sg:city":"Lisle",
    "sg:classifiers":[
        {
            "category":"Real Estate",
            "subcategory":"Real Estate Services",
            "type":"Services"
        },
        {
            "category":"Real Estate",
            "subcategory":"Real Estate Agent",
            "type":"Services"
        }
    ],
    "sg:phone":"+1 630 852 0300",
    "sg:postcode":"60532",
    "sg:province":"IL",
    "sg:tags":[
        "buyer",
        "broker"
    ],
    "wof:name":"Calmark Realty",
    "wof:placetype":"venue"
},
  "geometry": {"coordinates":[-88.066113,41.797525],"type":"Point"}
}