{
  "type": "Feature",
  "properties": {
    "iso:country":"US",
    "sg:address":"333 E Ogden Ave",
    "sg:city":"Geneseo",
    "sg:classifiers":[
        {
            "category":"Education",
            "subcategory":"School",
            "type":"Public Place"
        }
    ],
    "sg:phone":"+1 309 945 0555",
    "sg:postcode":"61254",
    "sg:province":"IL",
    "sg:tags":[
        "middle"
    ],
    "wof:name":"Geneseo Middle School Homework Hotline All Grades",
    "wof:placetype":"venue"
},
  "geometry": {"coordinates":[-90.151619,41.461948],"type":"Point"}
}