{
  "type": "Feature",
  "properties": {
    "addr:full":"3267 W Fullerton Ave Chicago IL 60647",
    "addr:housenumber":"3267",
    "addr:postcode":"60647",
    "addr:street":"W Fullerton Ave",
    "iso:country":"US",
    "sg:address":"3267 W Fullerton Ave",
    "sg:city":"Chicago",
    "sg:classifiers":[
        {
            "category":"Autos & Motor Vehicles",
            "subcategory":"Auto Supplies",
            "type":"Retail Goods"
        },
        {
            "category":"Retail",
            "subcategory":"Auto Repair",
            "type":"Services"
        }
    ],
    "sg:phone":"+1 773 772 5232",
    "sg:postcode":"60647",
    "sg:province":"IL",
    "sg:tags":[
        "automobile",
        "accessory",
        "parts",
        "accessories-wholesale",
        "part",
        "manufacturer"
    ],
    "wof:name":"Torres Auto Accessories",
    "wof:placetype":"venue"
},
  "geometry": {"coordinates":[-87.71034299999999,41.924689],"type":"Point"}
}