{
  "type": "Feature",
  "properties": {
    "addr:full":"1 S Dearborn St 21st Floor Chicago IL 60603",
    "addr:housenumber":"1",
    "addr:postcode":"60603",
    "addr:street":"S Dearborn St;Floor",
    "iso:country":"US",
    "sg:address":"1 S Dearborn St 21st Floor",
    "sg:city":"Chicago",
    "sg:classifiers":[
        {
            "category":"Bars & Pubs",
            "type":"Food & Drink"
        },
        {
            "category":"Restaurant",
            "type":"Food & Drink"
        }
    ],
    "sg:phone":"+1 312 278 4438",
    "sg:postcode":"60603",
    "sg:province":"IL",
    "wof:name":"Tasty Chicago Singles Dining Network",
    "wof:placetype":"venue"
},
  "geometry": {"coordinates":[-87.629417,41.882],"type":"Point"}
}