{
  "type": "Feature",
  "properties": {
    "iso:country":"US",
    "sg:address":"18207 Dixie Hwy",
    "sg:city":"Homewood",
    "sg:classifiers":[
        {
            "category":"Insurance",
            "subcategory":"Insurance Agent",
            "type":"Services"
        }
    ],
    "sg:phone":"+1 708 957 0810",
    "sg:postcode":"60430",
    "sg:province":"IL",
    "wof:name":"Fred Hardy Agency Inc",
    "wof:placetype":"venue"
},
  "geometry": {"coordinates":[-87.665314,41.558537],"type":"Point"}
}