{
  "type": "Feature",
  "properties": {
    "addr:full":"215 W Washington St Chicago IL 60606",
    "addr:housenumber":"215",
    "addr:postcode":"60606",
    "addr:street":"W Washington St",
    "iso:country":"US",
    "sg:address":"215 W Washington St",
    "sg:city":"Chicago",
    "sg:classifiers":[
        {
            "category":"Real Estate",
            "subcategory":"Real Estate Operator",
            "type":"Services"
        }
    ],
    "sg:phone":"+1 877 215 9378",
    "sg:postcode":"60606",
    "sg:province":"IL",
    "sg:tags":[
        "apartment"
    ],
    "sg:website":"www.215westapts.com",
    "wof:name":"215 West Apartments",
    "wof:placetype":"venue"
},
  "geometry": {"coordinates":[-87.634512,41.882816],"type":"Point"}
}