{
  "type": "Feature",
  "properties": {
    "addr:full":"1510 Madison St Maywood IL 60153",
    "addr:housenumber":"1510",
    "addr:postcode":"60153",
    "addr:street":"Madison St",
    "iso:country":"US",
    "sg:address":"1510 Madison St",
    "sg:city":"Maywood",
    "sg:classifiers":[
        {
            "category":"Real Estate",
            "subcategory":"Real Estate Agent",
            "type":"Services"
        }
    ],
    "sg:phone":"+1 773 251 6652",
    "sg:postcode":"60153",
    "sg:province":"IL",
    "wof:name":"Tja Inc",
    "wof:placetype":"venue"
},
  "geometry": {"coordinates":[-87.851859,41.878604],"type":"Point"}
}