{
  "type": "Feature",
  "properties": {
    "addr:full":"1936 N Clark St Chicago IL 60614",
    "addr:housenumber":"1936",
    "addr:postcode":"60614",
    "addr:street":"N Clark St",
    "iso:country":"US",
    "sg:address":"1936 N Clark St",
    "sg:city":"Chicago",
    "sg:classifiers":[
        {
            "category":"Shopping",
            "subcategory":"Pets & Pet Supplies",
            "type":"Retail Goods"
        },
        {
            "category":"Retail",
            "subcategory":"Pet Boarding",
            "type":"Services"
        }
    ],
    "sg:phone":"+1 773 687 9603",
    "sg:postcode":"60614",
    "sg:province":"IL",
    "sg:tags":[
        "walker",
        "dog",
        "boarding/pet",
        "sitting"
    ],
    "sg:website":"www.nortonpetsit.com",
    "wof:name":"Norton Pet Sitting",
    "wof:placetype":"venue"
},
  "geometry": {"coordinates":[-87.635729,41.917602],"type":"Point"}
}