{
  "type": "Feature",
  "properties": {
    "iso:country":"US",
    "sg:address":"504 W Northwest Hwy",
    "sg:city":"Arlington Heights",
    "sg:classifiers":[
        {
            "category":"Shopping",
            "subcategory":"Computers & Home Electronics",
            "type":"Retail Goods"
        }
    ],
    "sg:phone":"+1   ",
    "sg:postcode":"60004",
    "sg:province":"IL",
    "sg:tags":[
        "communications",
        "paging",
        "devices"
    ],
    "wof:name":"North Amercn Paging & Cellular",
    "wof:placetype":"venue"
},
  "geometry": {"coordinates":[-87.990011,42.08735],"type":"Point"}
}