{
  "type": "Feature",
  "properties": {
    "addr:full":"204 E Walnut St Carbondale IL 62901",
    "addr:housenumber":"204",
    "addr:postcode":"62901",
    "addr:street":"E Walnut St",
    "iso:country":"US",
    "sg:address":"204 E Walnut St",
    "sg:city":"Carbondale",
    "sg:classifiers":[
        {
            "category":"Home & Garden",
            "subcategory":"Building Materials",
            "type":"Retail Goods"
        }
    ],
    "sg:phone":"+1 618 457 8143",
    "sg:postcode":"62901",
    "sg:province":"IL",
    "sg:tags":[
        "paint"
    ],
    "wof:name":"MAB Paint Store",
    "wof:placetype":"venue"
},
  "geometry": {"coordinates":[-89.213517,37.7256],"type":"Point"}
}