{
  "type": "Feature",
  "properties": {
    "iso:country":"US",
    "sg:address":"1214 Killarney Dr",
    "sg:city":"Greenville",
    "sg:classifiers":[
        {
            "category":"Retail",
            "subcategory":"Laundry & Dry Cleaning",
            "type":"Services"
        }
    ],
    "sg:phone":"+1 618 664 4787",
    "sg:postcode":"62246",
    "sg:province":"IL",
    "sg:tags":[
        "cleaner",
        "rug",
        "carpet"
    ],
    "wof:name":"Holcomb Cleaning Service",
    "wof:placetype":"venue"
},
  "geometry": {"coordinates":[-89.39538899999999,38.897328],"type":"Point"}
}