{
  "type": "Feature",
  "properties": {
    "iso:country":"US",
    "sg:address":"11606 S Western Ave",
    "sg:city":"Chicago",
    "sg:classifiers":[
        {
            "category":"Health Services",
            "subcategory":"Dentist",
            "type":"Services"
        }
    ],
    "sg:phone":"+1 773 233 0155",
    "sg:postcode":"60643",
    "sg:province":"IL",
    "wof:name":"Family Care Gentle Dental Center",
    "wof:placetype":"venue"
},
  "geometry": {"coordinates":[-87.68090100000001,41.682499],"type":"Point"}
}