{
  "type": "Feature",
  "properties": {
    "iso:country":"US",
    "sg:address":"510 Franklin Blvd",
    "sg:city":"Elgin",
    "sg:classifiers":[
        {
            "category":"Education",
            "subcategory":"School",
            "type":"Public Place"
        }
    ],
    "sg:phone":"+1 847 888 5266",
    "sg:postcode":"60120",
    "sg:province":"IL",
    "sg:tags":[
        "elementary"
    ],
    "wof:name":"Sheridan Elementary School",
    "wof:placetype":"venue"
},
  "geometry": {"coordinates":[-88.270302,42.042831],"type":"Point"}
}