{
  "type": "Feature",
  "properties": {
    "addr:full":"1805 Gaty Ave East Saint Louis IL 62205",
    "addr:housenumber":"1805",
    "addr:postcode":"62205",
    "addr:street":"Gaty Ave East",
    "iso:country":"US",
    "sg:address":"1805 Gaty Ave",
    "sg:city":"East Saint Louis",
    "sg:classifiers":[
        {
            "category":"Retail",
            "subcategory":"Repair Shop",
            "type":"Services"
        }
    ],
    "sg:phone":"+1 618 337 2500",
    "sg:postcode":"62205",
    "sg:province":"IL",
    "wof:name":"Mr Fix It & Co",
    "wof:placetype":"venue"
},
  "geometry": {"coordinates":[-90.140064,38.611677],"type":"Point"}
}