{
  "type": "Feature",
  "properties": {
    "iso:country":"US",
    "sg:address":"1900 Keokuk St",
    "sg:city":"Hamilton",
    "sg:classifiers":[
        {
            "category":"Health Services",
            "subcategory":"Doctor",
            "type":"Services"
        }
    ],
    "sg:phone":"+1 217 847 3611",
    "sg:postcode":"62341",
    "sg:province":"IL",
    "sg:tags":[
        "medical"
    ],
    "wof:name":"James A Gwaltney MD",
    "wof:placetype":"venue"
},
  "geometry": {"coordinates":[-91.329944,40.396328],"type":"Point"}
}