{
  "type": "Feature",
  "properties": {
    "iso:country":"US",
    "sg:address":"7814 N Sommer St",
    "sg:city":"Peoria",
    "sg:phone":"+1 309 692 2528",
    "sg:postcode":"61615",
    "sg:province":"IL",
    "wof:name":"Two Envy Inc",
    "wof:placetype":"venue"
},
  "geometry": {"coordinates":[-89.613317,40.781861],"type":"Point"}
}