{
  "type": "Feature",
  "properties": {
    "addr:full":"430 Keith Ave Crystal Lake IL 60014",
    "addr:housenumber":"430",
    "addr:postcode":"60014",
    "addr:street":"Keith Ave",
    "iso:country":"US",
    "sg:address":"430 Keith Ave",
    "sg:city":"Crystal Lake",
    "sg:classifiers":[
        {
            "category":"Professional",
            "type":"Services"
        }
    ],
    "sg:phone":"+1 815 459 0350",
    "sg:postcode":"60014",
    "sg:province":"IL",
    "sg:tags":[
        "establishment"
    ],
    "wof:name":"Idec",
    "wof:placetype":"venue"
},
  "geometry": {"coordinates":[-88.326154,42.229156],"type":"Point"}
}