{
  "type": "Feature",
  "properties": {
    "addr:full":"5817 W Cermak Rd Cicero IL 60804",
    "addr:housenumber":"5817",
    "addr:postcode":"60804",
    "addr:street":"W Cermak Rd",
    "iso:country":"US",
    "sg:address":"5817 W Cermak Rd",
    "sg:city":"Cicero",
    "sg:classifiers":[
        {
            "category":"Shopping",
            "subcategory":"Beauty & Cosmetics",
            "type":"Retail Goods"
        }
    ],
    "sg:phone":"+1 708 780 1800",
    "sg:postcode":"60804",
    "sg:province":"IL",
    "sg:tags":[
        "supply"
    ],
    "wof:name":"Sharon Beauty Supply",
    "wof:placetype":"venue"
},
  "geometry": {"coordinates":[-87.76984400000001,41.850725],"type":"Point"}
}