{
  "type": "Feature",
  "properties": {
    "iso:country":"US",
    "sg:address":"573 S Consumers Ave",
    "sg:city":"Palatine",
    "sg:classifiers":[
        {
            "category":"Arena",
            "subcategory":"Sports Club",
            "type":"Entertainment"
        }
    ],
    "sg:phone":"+1 847 590 8430",
    "sg:postcode":"60074",
    "sg:province":"IL",
    "wof:name":"Chicago Football LLC",
    "wof:placetype":"venue"
},
  "geometry": {"coordinates":[-88.010997,42.098266],"type":"Point"}
}