{
  "type": "Feature",
  "properties": {
    "iso:country":"US",
    "sg:address":"111 N Public Sq",
    "sg:city":"Knoxville",
    "sg:classifiers":[
        {
            "category":"Organizations",
            "subcategory":"Labor Organization",
            "type":"Services"
        }
    ],
    "sg:phone":"+1 309 289 9114",
    "sg:postcode":"61448",
    "sg:province":"IL",
    "wof:name":"Teamsters",
    "wof:placetype":"venue"
},
  "geometry": {"coordinates":[-90.283618,40.908359],"type":"Point"}
}