{
  "type": "Feature",
  "properties": {
    "addr:full":"19636 97th Ave Mokena IL 60448",
    "addr:housenumber":"19636",
    "addr:postcode":"60448",
    "addr:street":"97Th Ave",
    "iso:country":"US",
    "sg:address":"19636 97th Ave",
    "sg:city":"Mokena",
    "sg:classifiers":[
        {
            "category":"Shopping",
            "subcategory":"Gifts & Souvenirs",
            "type":"Retail Goods"
        },
        {
            "category":"Shopping",
            "subcategory":"Florist",
            "type":"Retail Goods"
        }
    ],
    "sg:phone":"+1 708 478 3320",
    "sg:postcode":"60448",
    "sg:province":"IL",
    "sg:tags":[
        "shop"
    ],
    "wof:name":"Lori's Flowers & Gifts Inc",
    "wof:placetype":"venue"
},
  "geometry": {"coordinates":[-87.853961,41.533221],"type":"Point"}
}