{
  "type": "Feature",
  "properties": {
    "addr:full":"245 Waukegan Rd Suite 240 Northfield IL 60093",
    "addr:housenumber":"245",
    "addr:postcode":"60093",
    "addr:street":"Waukegan Rd Suite 240",
    "iso:country":"US",
    "sg:address":"245 Waukegan Rd Suite 240",
    "sg:city":"Northfield",
    "sg:classifiers":[
        {
            "category":"Real Estate",
            "subcategory":"Real Estate Agent",
            "type":"Services"
        }
    ],
    "sg:phone":"+1 773 501 5025",
    "sg:postcode":"60093",
    "sg:province":"IL",
    "wof:name":"The Dearborn-Buckingham Group, Inc.",
    "wof:placetype":"venue"
},
  "geometry": {"coordinates":[-87.798436,42.09874],"type":"Point"}
}