{
  "type": "Feature",
  "properties": {
    "iso:country":"US",
    "sg:address":"230 W Main St",
    "sg:city":"Ottawa",
    "sg:classifiers":[
        {
            "category":"Health Services",
            "subcategory":"Doctor",
            "type":"Services"
        }
    ],
    "sg:phone":"+1 815 434 0492",
    "sg:postcode":"61350",
    "sg:province":"IL",
    "wof:name":"Hunter Davis Dr",
    "wof:placetype":"venue"
},
  "geometry": {"coordinates":[-88.843705,41.345811],"type":"Point"}
}