{
  "type": "Feature",
  "properties": {
    "addr:full":"8627 W 98th St Palos Hills IL 60465",
    "addr:housenumber":"8627",
    "addr:postcode":"60465",
    "addr:street":"W 98Th St",
    "iso:country":"US",
    "sg:address":"8627 W 98th St",
    "sg:city":"Palos Hills",
    "sg:classifiers":[
        {
            "category":"Professional",
            "subcategory":"Accounting & Tax Preparation",
            "type":"Services"
        }
    ],
    "sg:phone":"+1 708 599 1532",
    "sg:postcode":"60465",
    "sg:province":"IL",
    "wof:name":"Hasan S Issa CPA",
    "wof:placetype":"venue"
},
  "geometry": {"coordinates":[-87.8325,41.712741],"type":"Point"}
}