{
  "type": "Feature",
  "properties": {
    "iso:country":"US",
    "sg:address":"10505 S Normal Ave",
    "sg:city":"Chicago",
    "sg:classifiers":[
        {
            "category":"Retail",
            "subcategory":"Auto Repair",
            "type":"Services"
        }
    ],
    "sg:phone":"+1 773 264 8157",
    "sg:postcode":"60628",
    "sg:province":"IL",
    "sg:tags":[
        "body",
        "automobile",
        "painting",
        "repairing"
    ],
    "wof:name":"Dent",
    "wof:placetype":"venue"
},
  "geometry": {"coordinates":[-87.63546599999999,41.703295],"type":"Point"}
}