{
  "type": "Feature",
  "properties": {
    "addr:full":"4545 N Ravenswood Ave Chicago IL 60640",
    "addr:housenumber":"4545",
    "addr:postcode":"60640",
    "addr:street":"N Ravenswood Ave",
    "iso:country":"US",
    "sg:address":"4545 N Ravenswood Ave",
    "sg:city":"Chicago",
    "sg:classifiers":[
        {
            "category":"Banks & Credit Unions",
            "subcategory":"Financial Services",
            "type":"Services"
        },
        {
            "category":"Professional",
            "subcategory":"Credit Reporting & Collection",
            "type":"Services"
        }
    ],
    "sg:phone":"+1 773 878 2110",
    "sg:postcode":"60640",
    "sg:province":"IL",
    "sg:tags":[
        "agency",
        "adjuster",
        "debt"
    ],
    "wof:name":"Chicago Collections Services, Inc.",
    "wof:placetype":"venue"
},
  "geometry": {"coordinates":[-87.674042,41.964163],"type":"Point"}
}