{
  "type": "Feature",
  "properties": {
    "addr:full":"12116 N 9th Ave Hillsboro IL 62049",
    "addr:housenumber":"12116",
    "addr:postcode":"62049",
    "addr:street":"N 9Th Ave",
    "iso:country":"US",
    "sg:address":"12116 N 9th Ave",
    "sg:city":"Hillsboro",
    "sg:classifiers":[
        {
            "category":"Wholesale",
            "subcategory":"Farm Supplies",
            "type":"Manufacturing & Wholesale Goods"
        },
        {
            "category":"Farming",
            "subcategory":"Farm",
            "type":"Manufacturing & Wholesale Goods"
        }
    ],
    "sg:phone":"+1 217 532 3650",
    "sg:postcode":"62049",
    "sg:province":"IL",
    "sg:tags":[
        "grain"
    ],
    "wof:name":"Jan Spinner",
    "wof:placetype":"venue"
},
  "geometry": {"coordinates":[-89.47121300000001,39.129587],"type":"Point"}
}