{
  "type": "Feature",
  "properties": {
    "iso:country":"US",
    "sg:address":"2055 Landwehr Rd",
    "sg:city":"Northbrook",
    "sg:classifiers":[
        {
            "category":"Education",
            "subcategory":"School",
            "type":"Public Place"
        }
    ],
    "sg:phone":"+1 847 272 6884",
    "sg:postcode":"60062",
    "sg:province":"IL",
    "wof:name":"Field Junior High School",
    "wof:placetype":"venue"
},
  "geometry": {"coordinates":[-87.858536,42.116399],"type":"Point"}
}