{
  "type": "Feature",
  "properties": {
    "addr:full":"1980 University Ln Lisle IL 60532",
    "addr:housenumber":"1980",
    "addr:postcode":"60532",
    "addr:street":"University Ln",
    "iso:country":"US",
    "sg:address":"1980 University Ln",
    "sg:city":"Lisle",
    "sg:classifiers":[
        {
            "category":"Building & Trades",
            "subcategory":"Electrical",
            "type":"Services"
        }
    ],
    "sg:phone":"+1 630 521 0234",
    "sg:postcode":"60532",
    "sg:province":"IL",
    "sg:tags":[
        "control",
        "regulator",
        "system",
        "controls"
    ],
    "sg:website":"http://www.pcsoc.com",
    "wof:name":"Precision Control Systems Of Chicago, Inc.",
    "wof:placetype":"venue"
},
  "geometry": {"coordinates":[-88.088234,41.792821],"type":"Point"}
}