{
  "type": "Feature",
  "properties": {
    "addr:full":"7351 S 78th Ave Bridgeview IL 60455",
    "addr:housenumber":"7351",
    "addr:postcode":"60455",
    "addr:street":"S 78Th Ave",
    "iso:country":"US",
    "sg:address":"7351 S 78th Ave",
    "sg:city":"Bridgeview",
    "sg:classifiers":[
        {
            "category":"Wholesale",
            "subcategory":"Meat",
            "type":"Manufacturing & Wholesale Goods"
        }
    ],
    "sg:phone":"+1 708 594 1432",
    "sg:postcode":"60455",
    "sg:province":"IL",
    "sg:tags":[
        "pork",
        "mfg",
        "beef",
        "prepared"
    ],
    "wof:name":"Stampede Meat Inc",
    "wof:placetype":"venue"
},
  "geometry": {"coordinates":[-87.814605,41.757801],"type":"Point"}
}