{
  "type": "Feature",
  "properties": {
    "iso:country":"US",
    "sg:address":"307 Brookside Cir",
    "sg:city":"Wheaton",
    "sg:classifiers":[
        {
            "category":"Professional",
            "subcategory":"Employment Agencies",
            "type":"Services"
        }
    ],
    "sg:phone":"+1 630 682 4063",
    "sg:postcode":"60187",
    "sg:province":"IL",
    "wof:name":"Jackie Denman",
    "wof:placetype":"venue"
},
  "geometry": {"coordinates":[-88.10308499999999,41.885669],"type":"Point"}
}