{
  "type": "Feature",
  "properties": {
    "iso:country":"US",
    "sg:address":"15200 Dan Patch Dr",
    "sg:city":"Plainfield",
    "sg:classifiers":[
        {
            "category":"Building & Trades",
            "subcategory":"Electrical",
            "type":"Services"
        }
    ],
    "sg:phone":"+1 815 254 4037",
    "sg:postcode":"60544",
    "sg:province":"IL",
    "sg:tags":[
        "electrician"
    ],
    "wof:name":"Mcgill Electric Co Inc",
    "wof:placetype":"venue"
},
  "geometry": {"coordinates":[-88.21946,41.604511],"type":"Point"}
}