{
  "type": "Feature",
  "properties": {
    "iso:country":"US",
    "sg:address":"2401 S Troy St",
    "sg:city":"Chicago",
    "sg:phone":"+1 773 522 1822",
    "sg:postcode":"60623",
    "sg:province":"IL",
    "wof:name":"AAA",
    "wof:placetype":"venue"
},
  "geometry": {"coordinates":[-87.703903,41.848148],"type":"Point"}
}