{
  "type": "Feature",
  "properties": {
    "iso:country":"US",
    "sg:address":"3150 N Lake Shore Dr Apt 5D",
    "sg:city":"Chicago",
    "sg:classifiers":[
        {
            "category":"Shopping",
            "subcategory":"Antiques",
            "type":"Retail Goods"
        }
    ],
    "sg:phone":"+1 773 929 3150",
    "sg:postcode":"60657",
    "sg:province":"IL",
    "wof:name":"3150 Condominium Assn",
    "wof:placetype":"venue"
},
  "geometry": {"coordinates":[-87.63800000000001,41.938999],"type":"Point"}
}