{
  "type": "Feature",
  "properties": {
    "addr:full":"3500 W 63rd Pl Chicago IL 60629",
    "addr:housenumber":"3500",
    "addr:postcode":"60629",
    "addr:street":"W 63Rd Pl",
    "iso:country":"US",
    "sg:address":"3500 W 63rd Pl",
    "sg:city":"Chicago",
    "sg:classifiers":[
        {
            "category":"Building & Trades",
            "subcategory":"Landscaping Services",
            "type":"Services"
        }
    ],
    "sg:phone":"+1 773 436 3806",
    "sg:postcode":"60629",
    "sg:province":"IL",
    "sg:tags":[
        "lawn",
        "maintenance"
    ],
    "wof:name":"Chicago Lawn United",
    "wof:placetype":"venue"
},
  "geometry": {"coordinates":[-87.710373,41.777939],"type":"Point"}
}