{
  "type": "Feature",
  "properties": {
    "iso:country":"US",
    "sg:address":"3511 Washington Ave",
    "sg:city":"Cairo",
    "sg:classifiers":[
        {
            "category":"Organizations",
            "subcategory":"Religious Organization",
            "type":"Services"
        }
    ],
    "sg:phone":"+1 618 734 1862",
    "sg:postcode":"62914",
    "sg:province":"IL",
    "wof:name":"Cairo Cngrgtion Jhvahs Wtnsses",
    "wof:placetype":"venue"
},
  "geometry": {"coordinates":[-89.186449,37.014429],"type":"Point"}
}