{
  "type": "Feature",
  "properties": {
    "iso:country":"US",
    "sg:address":"431 Phelps Ave",
    "sg:city":"Rockford",
    "sg:classifiers":[
        {
            "category":"Professional",
            "subcategory":"Employment Agencies",
            "type":"Services"
        }
    ],
    "sg:phone":"+1 815 397 8888",
    "sg:postcode":"61108",
    "sg:province":"IL",
    "sg:tags":[
        "temporary",
        "help",
        "contractor"
    ],
    "wof:name":"Assured Staffing",
    "wof:placetype":"venue"
},
  "geometry": {"coordinates":[-89.00467999999999,42.265376],"type":"Point"}
}