{
  "type": "Feature",
  "properties": {
    "iso:country":"US",
    "sg:address":"5827 N Kenneth Ave",
    "sg:city":"Chicago",
    "sg:classifiers":[
        {
            "category":"Building & Trades",
            "subcategory":"Construction",
            "type":"Services"
        }
    ],
    "sg:phone":"+1 773 725 8610",
    "sg:postcode":"60646",
    "sg:province":"IL",
    "sg:tags":[
        "house"
    ],
    "wof:name":"Kelly Construction Company",
    "wof:placetype":"venue"
},
  "geometry": {"coordinates":[-87.739457,41.988006],"type":"Point"}
}