{
  "type": "Feature",
  "properties": {
    "addr:full":"500 E Cincinnati St Greenup IL 62428",
    "addr:housenumber":"500",
    "addr:postcode":"62428",
    "addr:street":"E Cincinnati St",
    "iso:country":"US",
    "sg:address":"500 E Cincinnati St",
    "sg:city":"Greenup",
    "sg:classifiers":[
        {
            "category":"Personal",
            "subcategory":"Beauty Salon",
            "type":"Services"
        }
    ],
    "sg:phone":"+1 217 923 5655",
    "sg:postcode":"62428",
    "sg:province":"IL",
    "wof:name":"Heather Hair Studio",
    "wof:placetype":"venue"
},
  "geometry": {"coordinates":[-88.156446,39.247209],"type":"Point"}
}