{
  "type": "Feature",
  "properties": {
    "addr:full":"4609 S California Ave Chicago IL 60632",
    "addr:housenumber":"4609",
    "addr:postcode":"60632",
    "addr:street":"S California Ave",
    "iso:country":"US",
    "sg:address":"4609 S California Ave",
    "sg:city":"Chicago",
    "sg:classifiers":[
        {
            "category":"Personal",
            "subcategory":"Beauty Salon",
            "type":"Services"
        }
    ],
    "sg:phone":"+1 773 376 3110",
    "sg:postcode":"60632",
    "sg:province":"IL",
    "wof:name":"New Look Hair Salon 4609",
    "wof:placetype":"venue"
},
  "geometry": {"coordinates":[-87.694248,41.80994],"type":"Point"}
}