{
  "type": "Feature",
  "properties": {
    "iso:country":"US",
    "sg:address":"11018 W Wilmington Rd",
    "sg:city":"Peotone",
    "sg:classifiers":[
        {
            "category":"Travel",
            "subcategory":"Campground",
            "type":"Entertainment"
        }
    ],
    "sg:phone":"+1 708 258 6040",
    "sg:postcode":"60468",
    "sg:province":"IL",
    "wof:name":"Enchanted Shores Of Killarney",
    "wof:placetype":"venue"
},
  "geometry": {"coordinates":[-87.87746199999999,41.323835],"type":"Point"}
}