{
  "type": "Feature",
  "properties": {
    "iso:country":"US",
    "sg:address":"7013 W Dempster St",
    "sg:city":"Niles",
    "sg:classifiers":[
        {
            "category":"Personal",
            "subcategory":"Shoe Repair & Shine",
            "type":"Services"
        },
        {
            "category":"Shopping",
            "subcategory":"Shoes",
            "type":"Retail Goods"
        }
    ],
    "sg:phone":"+1 877 414 9938",
    "sg:postcode":"60714",
    "sg:province":"IL",
    "sg:tags":[
        "boots-custom",
        "made",
        "store"
    ],
    "sg:website":"http://www.waxbergs.com",
    "wof:name":"Waxberg's Walk Shoppe",
    "wof:placetype":"venue"
},
  "geometry": {"coordinates":[-87.80091899999999,42.04084],"type":"Point"}
}