{
  "type": "Feature",
  "properties": {
    "iso:country":"US",
    "sg:address":"1920 W North Ave",
    "sg:city":"Chicago",
    "sg:classifiers":[
        {
            "category":"Shopping",
            "subcategory":"Clothing, Apparel, & Fashions",
            "type":"Retail Goods"
        }
    ],
    "sg:phone":"+1 773 486 0293",
    "sg:postcode":"60622",
    "sg:province":"IL",
    "sg:tags":[
        "accessory",
        "clothing",
        "women's"
    ],
    "sg:website":"www.francescascollections.com",
    "wof:name":"Francesca's Collections",
    "wof:placetype":"venue"
},
  "geometry": {"coordinates":[-87.676002,41.910503],"type":"Point"}
}