{
  "type": "Feature",
  "properties": {
    "iso:country":"US",
    "sg:address":"609 Clinton St",
    "sg:city":"Keyesport",
    "sg:classifiers":[
        {
            "category":"Restaurant",
            "type":"Food & Drink"
        }
    ],
    "sg:phone":"+1 618 749 5533",
    "sg:postcode":"62253",
    "sg:province":"IL",
    "wof:name":"Milly's Cafe",
    "wof:placetype":"venue"
},
  "geometry": {"coordinates":[-89.27765100000001,38.742045],"type":"Point"}
}