{
  "type": "Feature",
  "properties": {
    "iso:country":"US",
    "sg:address":"9730 W 143rd St",
    "sg:city":"Orland Park",
    "sg:classifiers":[
        {
            "category":"Home & Garden",
            "subcategory":"Building Materials",
            "type":"Retail Goods"
        }
    ],
    "sg:phone":"+1 708 349 2900",
    "sg:postcode":"60462",
    "sg:province":"IL",
    "sg:tags":[
        "lumber"
    ],
    "sg:website":"www.beattylumber.com",
    "wof:name":"Beatty Lumber Co",
    "wof:placetype":"venue"
},
  "geometry": {"coordinates":[-87.858136,41.630493],"type":"Point"}
}