{
  "type": "Feature",
  "properties": {
    "iso:country":"US",
    "sg:address":"615 Missouri Dr",
    "sg:city":"Dixon",
    "sg:classifiers":[
        {
            "category":"Building & Trades",
            "subcategory":"Construction",
            "type":"Services"
        }
    ],
    "sg:phone":"+1 815 652 3561",
    "sg:postcode":"61021",
    "sg:province":"IL",
    "sg:tags":[
        "house"
    ],
    "wof:name":"Janes Remodeling",
    "wof:placetype":"venue"
},
  "geometry": {"coordinates":[-89.370338,41.914511],"type":"Point"}
}