{
  "type": "Feature",
  "properties": {
    "addr:full":"268 W 26th Street Chicago IL 60616",
    "addr:housenumber":"268",
    "addr:postcode":"60616",
    "addr:street":"W 26Th Street",
    "iso:country":"US",
    "sg:address":"268 W 26th Street",
    "sg:city":"Chicago",
    "sg:classifiers":[
        {
            "category":"Professional",
            "type":"Services"
        },
        {
            "category":"Restaurant",
            "type":"Food & Drink"
        }
    ],
    "sg:phone":"+1 312 326 6330",
    "sg:postcode":"60616",
    "sg:province":"IL",
    "sg:tags":[
        "pizza",
        "caterer"
    ],
    "wof:name":"Office Ricobene's",
    "wof:placetype":"venue"
},
  "geometry": {"coordinates":[-87.63448699999999,41.845614],"type":"Point"}
}