{
  "type": "Feature",
  "properties": {
    "addr:full":"5505 W Race Ave Chicago IL 60644",
    "addr:housenumber":"5505",
    "addr:postcode":"60644",
    "addr:street":"W Race Ave",
    "iso:country":"US",
    "sg:address":"5505 W Race Ave",
    "sg:city":"Chicago",
    "sg:classifiers":[
        {
            "category":"Organizations",
            "subcategory":"Religious Organization",
            "type":"Services"
        }
    ],
    "sg:phone":"+1 773 378 5845",
    "sg:postcode":"60644",
    "sg:province":"IL",
    "wof:name":"Mount Calvary Chrch of God In",
    "wof:placetype":"venue"
},
  "geometry": {"coordinates":[-87.76422599999999,41.889225],"type":"Point"}
}