{
  "type": "Feature",
  "properties": {
    "iso:country":"US",
    "sg:address":"5405 Craftwell Dr",
    "sg:city":"Ringwood",
    "sg:classifiers":[
        {
            "category":"Building & Trades",
            "subcategory":"Construction",
            "type":"Services"
        }
    ],
    "sg:phone":"+1 815 653 2020",
    "sg:postcode":"60072",
    "sg:province":"IL",
    "sg:tags":[
        "concrete",
        "contractor"
    ],
    "wof:name":"Vernon Weidner & Company Inc",
    "wof:placetype":"venue"
},
  "geometry": {"coordinates":[-88.302792,42.401601],"type":"Point"}
}