{
  "type": "Feature",
  "properties": {
    "iso:country":"US",
    "sg:address":"863 Glenlake Dr",
    "sg:city":"Carol Stream",
    "sg:classifiers":[
        {
            "category":"Building & Trades",
            "subcategory":"Plumbing",
            "type":"Services"
        }
    ],
    "sg:phone":"+1 630 483 2861",
    "sg:postcode":"60188",
    "sg:province":"IL",
    "sg:tags":[
        "contractor"
    ],
    "wof:name":"Marcs Heating & Cooling",
    "wof:placetype":"venue"
},
  "geometry": {"coordinates":[-88.15208800000001,41.938566],"type":"Point"}
}