{
  "type": "Feature",
  "properties": {
    "iso:country":"US",
    "sg:address":"1821 Larkdale Rd",
    "sg:city":"Northbrook",
    "sg:classifiers":[
        {
            "category":"Wholesale",
            "subcategory":"Durable Goods & Equipment",
            "type":"Manufacturing & Wholesale Goods"
        }
    ],
    "sg:phone":"+1 847 480 1141",
    "sg:postcode":"60062",
    "sg:province":"IL",
    "sg:tags":[
        "representative",
        "manufacturer"
    ],
    "wof:name":"Gerald Krassek Associates",
    "wof:placetype":"venue"
},
  "geometry": {"coordinates":[-87.844302,42.119251],"type":"Point"}
}