{
  "type": "Feature",
  "properties": {
    "addr:full":"400 E Illinois Rd Lake Forest IL 60045",
    "addr:housenumber":"400",
    "addr:postcode":"60045",
    "addr:street":"E Illinois Rd",
    "iso:country":"US",
    "sg:address":"400 E Illinois Rd",
    "sg:city":"Lake Forest",
    "sg:classifiers":[
        {
            "category":"Social Services",
            "subcategory":"Child Care",
            "type":"Services"
        }
    ],
    "sg:phone":"+1 847 234 2799",
    "sg:postcode":"60045",
    "sg:province":"IL",
    "sg:website":"www.childrensdropincenter.com",
    "wof:name":"Lake Forest Children's Drop-In",
    "wof:placetype":"venue"
},
  "geometry": {"coordinates":[-87.837699,42.250299],"type":"Point"}
}