{
  "type": "Feature",
  "properties": {
    "iso:country":"US",
    "sg:address":"403 Laurel Dr",
    "sg:city":"St Joseph",
    "sg:classifiers":[
        {
            "category":"Freight",
            "type":"Transportation"
        }
    ],
    "sg:phone":"+1 217 469 8274",
    "sg:postcode":"61873",
    "sg:province":"IL",
    "sg:tags":[
        "trucking"
    ],
    "wof:name":"Celadon Trucking Svc Inc",
    "wof:placetype":"venue"
},
  "geometry": {"coordinates":[-88.029246,40.113703],"type":"Point"}
}