{
  "type": "Feature",
  "properties": {
    "addr:full":"13301 S Brainard Ave Chicago IL 60633",
    "addr:housenumber":"13301",
    "addr:postcode":"60633",
    "addr:street":"S Brainard Ave",
    "iso:country":"US",
    "sg:address":"13301 S Brainard Ave",
    "sg:city":"Chicago",
    "sg:classifiers":[
        {
            "category":"Organizations",
            "subcategory":"Membership Organization",
            "type":"Services"
        }
    ],
    "sg:phone":"+1 773 646 9725",
    "sg:postcode":"60633",
    "sg:province":"IL",
    "sg:tags":[
        "military",
        "veteran"
    ],
    "wof:name":"Vfw",
    "wof:placetype":"venue"
},
  "geometry": {"coordinates":[-87.552719,41.65369],"type":"Point"}
}