{
  "type": "Feature",
  "properties": {
    "iso:country":"US",
    "sg:address":"225 Donelda Ln",
    "sg:city":"Rockford",
    "sg:classifiers":[
        {
            "category":"Freight",
            "type":"Transportation"
        }
    ],
    "sg:phone":"+1 815 962 4881",
    "sg:postcode":"61102",
    "sg:province":"IL",
    "sg:tags":[
        "trucking"
    ],
    "wof:name":"I AM Thee Inc",
    "wof:placetype":"venue"
},
  "geometry": {"coordinates":[-89.169522,42.276737],"type":"Point"}
}