{
  "type": "Feature",
  "properties": {
    "iso:country":"US",
    "sg:address":"680 N Lake Shore Dr",
    "sg:city":"Chicago",
    "sg:classifiers":[
        {
            "category":"Banks & Credit Unions",
            "subcategory":"Financial Services",
            "type":"Services"
        }
    ],
    "sg:phone":"+1 312 335 3927",
    "sg:postcode":"60611",
    "sg:province":"IL",
    "sg:tags":[
        "cashing",
        "check"
    ],
    "wof:name":"D NA-Id Check In",
    "wof:placetype":"venue"
},
  "geometry": {"coordinates":[-87.615621,41.894691],"type":"Point"}
}