{
  "type": "Feature",
  "properties": {
    "iso:country":"US",
    "sg:address":"1603 S 4th St",
    "sg:city":"Rockford",
    "sg:classifiers":[
        {
            "category":"Social Services",
            "type":"Services"
        }
    ],
    "sg:phone":"+1 815 962 4858",
    "sg:postcode":"61104",
    "sg:province":"IL",
    "sg:tags":[
        "organization",
        "welfare"
    ],
    "wof:name":"Motherhouse Home",
    "wof:placetype":"venue"
},
  "geometry": {"coordinates":[-89.085405,42.249977],"type":"Point"}
}