{
  "type": "Feature",
  "properties": {
    "iso:country":"US",
    "sg:address":"823 Emerald Ln",
    "sg:city":"Machesney Park",
    "sg:classifiers":[
        {
            "category":"Social Services",
            "subcategory":"Child Care",
            "type":"Services"
        }
    ],
    "sg:phone":"+1 815 633 5639",
    "sg:postcode":"61115",
    "sg:province":"IL",
    "sg:tags":[
        "day"
    ],
    "wof:name":"Jeanette Paddock",
    "wof:placetype":"venue"
},
  "geometry": {"coordinates":[-89.0439,42.352369],"type":"Point"}
}