{
  "type": "Feature",
  "properties": {
    "addr:full":"3359 N Lincoln Ave Chicago IL 60657",
    "addr:housenumber":"3359",
    "addr:postcode":"60657",
    "addr:street":"N Lincoln Ave",
    "iso:country":"US",
    "sg:address":"3359 N Lincoln Ave",
    "sg:city":"Chicago",
    "sg:classifiers":[
        {
            "category":"Shopping",
            "type":"Retail Goods"
        }
    ],
    "sg:phone":"+1   ",
    "sg:postcode":"60657",
    "sg:province":"IL",
    "sg:tags":[
        "supply",
        "art",
        "framing",
        "custom"
    ],
    "wof:name":"Lake View Art Supply Inc",
    "wof:placetype":"venue"
},
  "geometry": {"coordinates":[-87.66992999999999,41.941503],"type":"Point"}
}