{
  "type": "Feature",
  "properties": {
    "addr:full":"5241 W Stuenkel Rd Monee IL 60449",
    "addr:housenumber":"5241",
    "addr:postcode":"60449",
    "addr:street":"W Stuenkel Rd",
    "iso:country":"US",
    "sg:address":"5241 W Stuenkel Rd",
    "sg:city":"Monee",
    "sg:classifiers":[
        {
            "category":"Retail",
            "subcategory":"Animal Services",
            "type":"Services"
        }
    ],
    "sg:phone":"+1 708 534 2334",
    "sg:postcode":"60449",
    "sg:province":"IL",
    "sg:tags":[
        "pet",
        "breeder"
    ],
    "wof:name":"Kashers Bouviers",
    "wof:placetype":"venue"
},
  "geometry": {"coordinates":[-87.747073,41.456146],"type":"Point"}
}