{
  "type": "Feature",
  "properties": {
    "addr:full":"1177 N Highland Ave Aurora IL 60506",
    "addr:housenumber":"1177",
    "addr:postcode":"60506",
    "addr:street":"N Highland Ave",
    "iso:country":"US",
    "sg:address":"1177 N Highland Ave",
    "sg:city":"Aurora",
    "sg:classifiers":[
        {
            "category":"Health Services",
            "subcategory":"Doctor",
            "type":"Services"
        }
    ],
    "sg:phone":"+1 630 801 1496",
    "sg:postcode":"60506",
    "sg:province":"IL",
    "sg:tags":[
        "dentist"
    ],
    "wof:name":"Innovative Peridontics",
    "wof:placetype":"venue"
},
  "geometry": {"coordinates":[-88.329425,41.78079],"type":"Point"}
}