{
  "type": "Feature",
  "properties": {
    "iso:country":"US",
    "sg:address":"4158 Greenwood St",
    "sg:city":"Skokie",
    "sg:classifiers":[
        {
            "category":"Professional",
            "subcategory":"Accounting & Tax Preparation",
            "type":"Services"
        }
    ],
    "sg:phone":"+1 847 679 1767",
    "sg:postcode":"60076",
    "sg:province":"IL",
    "wof:name":"Lance Wise",
    "wof:placetype":"venue"
},
  "geometry": {"coordinates":[-87.731154,42.042649],"type":"Point"}
}