{
  "type": "Feature",
  "properties": {
    "iso:country":"US",
    "sg:address":"1042 W Barry Ave",
    "sg:city":"Chicago",
    "sg:classifiers":[
        {
            "category":"Building & Trades",
            "subcategory":"Cleaning & Sanitation",
            "type":"Services"
        }
    ],
    "sg:phone":"+1 773 472 8256",
    "sg:postcode":"60657",
    "sg:province":"IL",
    "sg:tags":[
        "maintenance"
    ],
    "wof:name":"Tecnet Internet Maintenance",
    "wof:placetype":"venue"
},
  "geometry": {"coordinates":[-87.65574599999999,41.938139],"type":"Point"}
}