{
  "type": "Feature",
  "properties": {
    "addr:full":"1532 N Milwaukee Ave Ste 204 Chicago IL 60622",
    "addr:housenumber":"1532",
    "addr:postcode":"60622",
    "addr:street":"N Milwaukee Ave Ste 204",
    "iso:country":"US",
    "sg:address":"1532 N Milwaukee Ave Ste 204",
    "sg:city":"Chicago",
    "sg:classifiers":[
        {
            "category":"Professional",
            "subcategory":"Art Services",
            "type":"Services"
        }
    ],
    "sg:phone":"+1 773 320 7275",
    "sg:postcode":"60622",
    "sg:province":"IL",
    "sg:tags":[
        "photographer",
        "graphic",
        "design"
    ],
    "sg:website":"www.gingerbydesign.com",
    "wof:name":"Ginger by Design",
    "wof:placetype":"venue"
},
  "geometry": {"coordinates":[-87.67585800000001,41.909374],"type":"Point"}
}