{
  "type": "Feature",
  "properties": {
    "iso:country":"US",
    "sg:address":"893 Tiffany Rd",
    "sg:city":"Antioch",
    "sg:classifiers":[
        {
            "category":"Building & Trades",
            "subcategory":"Plumbing",
            "type":"Services"
        }
    ],
    "sg:phone":"+1 847 395 9105",
    "sg:postcode":"60002",
    "sg:province":"IL",
    "sg:tags":[
        "septic"
    ],
    "wof:name":"R & R Sanitary",
    "wof:placetype":"venue"
},
  "geometry": {"coordinates":[-88.108965,42.479659],"type":"Point"}
}