{
  "type": "Feature",
  "properties": {
    "iso:country":"US",
    "sg:address":"421 N Lake St",
    "sg:city":"Mundelein",
    "sg:classifiers":[
        {
            "category":"Shopping",
            "subcategory":"Florist",
            "type":"Retail Goods"
        }
    ],
    "sg:phone":"+1   ",
    "sg:postcode":"60060",
    "sg:province":"IL",
    "wof:name":"Debbies Floral Inc",
    "wof:placetype":"venue"
},
  "geometry": {"coordinates":[-88.003937,42.269746],"type":"Point"}
}