{
  "type": "Feature",
  "properties": {
    "iso:country":"US",
    "sg:address":"618 S Access Road",
    "sg:city":"Chicago",
    "sg:classifiers":[
        {
            "category":"Airline",
            "type":"Transportation"
        }
    ],
    "sg:phone":"+1 773 686 0782",
    "sg:postcode":"60607",
    "sg:province":"IL",
    "sg:tags":[
        "shuttle",
        "airport"
    ],
    "wof:name":"America West Airlines",
    "wof:placetype":"venue"
},
  "geometry": {"coordinates":[-87.656932,41.873792],"type":"Point"}
}