{
  "type": "Feature",
  "properties": {
    "addr:full":"2199 S 1st Ave Maywood IL 60153",
    "addr:housenumber":"2199",
    "addr:postcode":"60153",
    "addr:street":"S 1St Ave",
    "iso:country":"US",
    "sg:address":"2199 S 1st Ave",
    "sg:city":"Maywood",
    "sg:classifiers":[
        {
            "category":"Government",
            "subcategory":"Office",
            "type":"Public Place"
        }
    ],
    "sg:phone":"+1   ",
    "sg:postcode":"60153",
    "sg:province":"IL",
    "sg:tags":[
        "forestry",
        "executive"
    ],
    "wof:name":"Forest Preserve",
    "wof:placetype":"venue"
},
  "geometry": {"coordinates":[-87.833461,41.866251],"type":"Point"}
}