{
  "type": "Feature",
  "properties": {
    "iso:country":"US",
    "sg:address":"701 Lee St",
    "sg:city":"Des Plaines",
    "sg:classifiers":[
        {
            "category":"Shopping",
            "subcategory":"Discount & Variety Stores",
            "type":"Retail Goods"
        }
    ],
    "sg:phone":"+1 847 803 1910",
    "sg:postcode":"60016",
    "sg:province":"IL",
    "sg:tags":[
        "merchandise",
        "general"
    ],
    "wof:name":"Budget Motel Supply Corp",
    "wof:placetype":"venue"
},
  "geometry": {"coordinates":[-87.890509,42.038081],"type":"Point"}
}