{
  "type": "Feature",
  "properties": {
    "addr:full":"17809 N Manito Rd Havana IL 62644",
    "addr:housenumber":"17809",
    "addr:postcode":"62644",
    "addr:street":"N Manito Rd",
    "iso:country":"US",
    "sg:address":"17809 N Manito Rd",
    "sg:city":"Havana",
    "sg:classifiers":[
        {
            "category":"Railroad",
            "type":"Transportation"
        }
    ],
    "sg:phone":"+1 309 543 4234",
    "sg:postcode":"62644",
    "sg:province":"IL",
    "wof:name":"Illinois & Midland Rr INC",
    "wof:placetype":"venue"
},
  "geometry": {"coordinates":[-89.998822,40.326907],"type":"Point"}
}