{
  "type": "Feature",
  "properties": {
    "addr:full":"10 S Wacker Dr Ste 2600 Chicago IL 60606",
    "addr:housenumber":"10",
    "addr:postcode":"60606",
    "addr:street":"S;Dr Ste 2600",
    "iso:country":"US",
    "sg:address":"10 S Wacker Dr Ste 2600",
    "sg:city":"Chicago",
    "sg:classifiers":[
        {
            "category":"Professional",
            "subcategory":"Employment Agencies",
            "type":"Services"
        }
    ],
    "sg:phone":"+1 312 795 4200",
    "sg:postcode":"60606",
    "sg:province":"IL",
    "sg:website":"us.hudson.com/node.asp?kwd=chica...",
    "wof:name":"Hudson",
    "wof:placetype":"venue"
},
  "geometry": {"coordinates":[-87.637062,41.881804],"type":"Point"}
}