{
  "type": "Feature",
  "properties": {
    "iso:country":"US",
    "sg:address":"4810 N Sheridan Rd",
    "sg:city":"Chicago",
    "sg:classifiers":[
        {
            "category":"Deli",
            "type":"Food & Drink"
        }
    ],
    "sg:menulink":"http://www.allmenus.com/il/chicago/209755-u-s-sub--grill--2/menu/",
    "sg:phone":"+1 773 271 2222",
    "sg:postcode":"60640",
    "sg:province":"IL",
    "sg:tags":[
        "american"
    ],
    "wof:name":"U S Sub & Grill # 2",
    "wof:placetype":"venue"
},
  "geometry": {"coordinates":[-87.654811,41.969371],"type":"Point"}
}