{
  "type": "Feature",
  "properties": {
    "iso:country":"US",
    "sg:address":"301 W Garfield Ave",
    "sg:city":"Cissna Park",
    "sg:classifiers":[
        {
            "category":"Shopping",
            "type":"Retail Goods"
        }
    ],
    "sg:phone":"+1 815 457 2468",
    "sg:postcode":"60924",
    "sg:province":"IL",
    "sg:tags":[
        "picture",
        "frame"
    ],
    "wof:name":"Master's Touch",
    "wof:placetype":"venue"
},
  "geometry": {"coordinates":[-87.895534,40.563675],"type":"Point"}
}