{
  "type": "Feature",
  "properties": {
    "addr:full":"272 Southwoods Center Columbia IL 62236",
    "addr:housenumber":"272",
    "addr:postcode":"62236",
    "addr:street":"Southwoods Center",
    "iso:country":"US",
    "sg:address":"272 Southwoods Center",
    "sg:city":"Columbia",
    "sg:classifiers":[
        {
            "category":"Insurance",
            "subcategory":"Insurance Agent",
            "type":"Services"
        }
    ],
    "sg:phone":"+1 618 281 9292",
    "sg:postcode":"62236",
    "sg:province":"IL",
    "wof:name":"Alternatives Insurance",
    "wof:placetype":"venue"
},
  "geometry": {"coordinates":[-90.195739,38.435936],"type":"Point"}
}