{
  "type": "Feature",
  "properties": {
    "iso:country":"US",
    "sg:address":"111 N Wabash Ave Ste 1605",
    "sg:city":"Chicago",
    "sg:classifiers":[
        {
            "category":"Health Services",
            "subcategory":"Medical Lab",
            "type":"Services"
        }
    ],
    "sg:phone":"+1 312 263 7437",
    "sg:postcode":"60602",
    "sg:province":"IL",
    "sg:tags":[
        "laboratories-pathological",
        "laboratory"
    ],
    "wof:name":"Metromed Labs",
    "wof:placetype":"venue"
},
  "geometry": {"coordinates":[-87.626222,41.883479],"type":"Point"}
}