{
  "type": "Feature",
  "properties": {
    "addr:full":"1012 W Randolph St Chicago IL 60607",
    "addr:housenumber":"1012",
    "addr:postcode":"60607",
    "addr:street":"W Randolph St",
    "iso:country":"US",
    "sg:address":"1012 W Randolph St",
    "sg:city":"Chicago",
    "sg:classifiers":[
        {
            "category":"Education",
            "subcategory":"Dance Studio",
            "type":"Public Place"
        },
        {
            "category":"Arts & Performance",
            "subcategory":"Dance",
            "type":"Entertainment"
        }
    ],
    "sg:phone":"+1 312 243 0700",
    "sg:postcode":"60607",
    "sg:province":"IL",
    "sg:tags":[
        "school",
        "instruction",
        "dancing"
    ],
    "sg:website":"www.bigcityswing.com",
    "wof:name":"Big City Swing",
    "wof:placetype":"venue"
},
  "geometry": {"coordinates":[-87.652501,41.884611],"type":"Point"}
}