{
  "type": "Feature",
  "properties": {
    "iso:country":"US",
    "sg:address":"1951 Airway Ct",
    "sg:city":"New Lenox",
    "sg:classifiers":[
        {
            "category":"Building & Trades",
            "subcategory":"Construction",
            "type":"Services"
        }
    ],
    "sg:phone":"+1 815 462 6927",
    "sg:postcode":"60451",
    "sg:province":"IL",
    "sg:tags":[
        "roofing",
        "contractor"
    ],
    "wof:name":"Boss Roofing & Sheet Metal",
    "wof:placetype":"venue"
},
  "geometry": {"coordinates":[-87.92710599999999,41.484811],"type":"Point"}
}