{
  "type": "Feature",
  "properties": {
    "iso:country":"US",
    "sg:address":"130 N Main St",
    "sg:city":"Princeton",
    "sg:classifiers":[
        {
            "category":"Health Services",
            "subcategory":"Doctor",
            "type":"Services"
        }
    ],
    "sg:phone":"+1 815 875 6001",
    "sg:postcode":"61356",
    "sg:province":"IL",
    "sg:tags":[
        "physician",
        "surgeon"
    ],
    "wof:name":"Bureau Valley Anesthesia",
    "wof:placetype":"venue"
},
  "geometry": {"coordinates":[-89.46513400000001,41.376861],"type":"Point"}
}