{
  "type": "Feature",
  "properties": {
    "iso:country":"US",
    "sg:address":"1850 Greenleaf Ave",
    "sg:city":"Elk Grove Village",
    "sg:classifiers":[
        {
            "category":"Freight",
            "type":"Transportation"
        }
    ],
    "sg:phone":"+1 847 981 9500",
    "sg:postcode":"60007",
    "sg:province":"IL",
    "sg:tags":[
        "forwarders"
    ],
    "wof:name":"Wilson Logistics Inc",
    "wof:placetype":"venue"
},
  "geometry": {"coordinates":[-87.952192,42.004232],"type":"Point"}
}