{
  "type": "Feature",
  "properties": {
    "addr:full":"1080 Nerge Rd Elk Grove Village IL 60007",
    "addr:housenumber":"1080",
    "addr:postcode":"60007",
    "addr:street":"Nerge Rd",
    "iso:country":"US",
    "sg:address":"1080 Nerge Rd",
    "sg:city":"Elk Grove Village",
    "sg:classifiers":[
        {
            "category":"Insurance",
            "subcategory":"Insurance Agent",
            "type":"Services"
        }
    ],
    "sg:phone":"+1 847 923 9500",
    "sg:postcode":"60007",
    "sg:province":"IL",
    "wof:name":"Fred Resner",
    "wof:placetype":"venue"
},
  "geometry": {"coordinates":[-88.02826399999999,41.994465],"type":"Point"}
}