{
  "type": "Feature",
  "properties": {
    "iso:country":"US",
    "sg:address":"40931 260th Ave",
    "sg:city":"Pittsfield",
    "sg:classifiers":[
        {
            "category":"Manufacturing",
            "subcategory":"Food",
            "type":"Manufacturing & Wholesale Goods"
        },
        {
            "category":"Farming",
            "subcategory":"Farm",
            "type":"Manufacturing & Wholesale Goods"
        }
    ],
    "sg:phone":"+1 217 285 9809",
    "sg:postcode":"62363",
    "sg:province":"IL",
    "sg:tags":[
        "corn",
        "product"
    ],
    "wof:name":"Steven Rumple",
    "wof:placetype":"venue"
},
  "geometry": {"coordinates":[-90.761463,39.634773],"type":"Point"}
}