{
  "type": "Feature",
  "properties": {
    "addr:full":"904 Edwardsville Rd Troy IL 62294",
    "addr:housenumber":"904",
    "addr:postcode":"62294",
    "addr:street":"Edwardsville Rd",
    "iso:country":"US",
    "sg:address":"904 Edwardsville Rd",
    "sg:city":"Troy",
    "sg:classifiers":[
        {
            "category":"Restaurant",
            "type":"Food & Drink"
        }
    ],
    "sg:menulink":"http://www.allmenus.com/il/jarvis/86616-imos-pizza/menu/",
    "sg:phone":"+1 618 667 7181",
    "sg:postcode":"62294",
    "sg:province":"IL",
    "sg:tags":[
        "american",
        "pizza"
    ],
    "wof:name":"Imo's Pizza",
    "wof:placetype":"venue"
},
  "geometry": {"coordinates":[-89.915367,38.732831],"type":"Point"}
}