{
  "type": "Feature",
  "properties": {
    "addr:full":"1 Busch Pl Saint Louis MO 63118",
    "addr:housenumber":"1",
    "addr:postcode":"63118",
    "addr:street":"Busch Pl",
    "iso:country":"US",
    "sg:address":"1 Busch Pl",
    "sg:city":"Saint Louis",
    "sg:classifiers":[
        {
            "category":"Brewery",
            "type":"Food & Drink"
        }
    ],
    "sg:phone":"+1 314 577 0654",
    "sg:postcode":"63118",
    "sg:province":"MO",
    "wof:name":"Anheuser-Busch Companies",
    "wof:placetype":"venue"
},
  "geometry": {"coordinates":[-90.21080000000001,38.597198],"type":"Point"}
}