{
  "type": "Feature",
  "properties": {
    "iso:country":"US",
    "sg:address":"3004 Grand Ave",
    "sg:city":"Waukegan",
    "sg:classifiers":[
        {
            "category":"Social Services",
            "type":"Services"
        }
    ],
    "sg:phone":"+1 847 377 7800",
    "sg:postcode":"60085",
    "sg:province":"IL",
    "sg:tags":[
        "probation"
    ],
    "wof:name":"Lake County Juvenile Probation",
    "wof:placetype":"venue"
},
  "geometry": {"coordinates":[-87.876953,42.370462],"type":"Point"}
}