{
  "type": "Feature",
  "properties": {
    "iso:country":"US",
    "sg:address":"218 W 13th St",
    "sg:city":"Mount Carmel",
    "sg:classifiers":[
        {
            "category":"Education",
            "subcategory":"Special Training",
            "type":"Public Place"
        }
    ],
    "sg:phone":"+1 618 263 3044",
    "sg:postcode":"62863",
    "sg:province":"IL",
    "wof:name":"Project Cares",
    "wof:placetype":"venue"
},
  "geometry": {"coordinates":[-87.769343,38.419967],"type":"Point"}
}