{
  "type": "Feature",
  "properties": {
    "iso:country":"US",
    "sg:address":"15555 Crawford Ave",
    "sg:city":"Harvey",
    "sg:classifiers":[
        {
            "category":"Travel",
            "subcategory":"Hotels & Motels",
            "type":"Entertainment"
        }
    ],
    "sg:phone":"+1 708 596 4411",
    "sg:postcode":"60428",
    "sg:province":"IL",
    "wof:name":"D-Lux Budget Motel",
    "wof:placetype":"venue"
},
  "geometry": {"coordinates":[-87.716241,41.605927],"type":"Point"}
}