{
  "type": "Feature",
  "properties": {
    "iso:country":"US",
    "sg:address":"802 Leland Rd",
    "sg:city":"Leland",
    "sg:classifiers":[
        {
            "category":"Government",
            "subcategory":"Office",
            "type":"Public Place"
        }
    ],
    "sg:phone":"+1   ",
    "sg:postcode":"60531",
    "sg:province":"IL",
    "sg:tags":[
        "executive"
    ],
    "wof:name":"Township of Victor",
    "wof:placetype":"venue"
},
  "geometry": {"coordinates":[-88.79944,41.634379],"type":"Point"}
}