{
  "type": "Feature",
  "properties": {
    "iso:country":"US",
    "sg:address":"401 W Half Day Rd",
    "sg:city":"Buffalo Grove",
    "sg:classifiers":[
        {
            "category":"Restaurant",
            "type":"Food & Drink"
        }
    ],
    "sg:phone":"+1 847 913 1324",
    "sg:postcode":"60089",
    "sg:province":"IL",
    "wof:name":"Aboretum Snack Shop",
    "wof:placetype":"venue"
},
  "geometry": {"coordinates":[-87.96485800000001,42.196102],"type":"Point"}
}