{
  "type": "Feature",
  "properties": {
    "iso:country":"US",
    "sg:address":"1809 W Mccord St",
    "sg:city":"Centralia",
    "sg:classifiers":[
        {
            "category":"Health Services",
            "subcategory":"Health Practitioner",
            "type":"Services"
        }
    ],
    "sg:phone":"+1 618 533 2781",
    "sg:postcode":"62801",
    "sg:province":"IL",
    "sg:tags":[
        "home"
    ],
    "wof:name":"V NA Tip Homecare",
    "wof:placetype":"venue"
},
  "geometry": {"coordinates":[-89.175271,38.534003],"type":"Point"}
}