{
  "type": "Feature",
  "properties": {
    "iso:country":"US",
    "sg:address":"4114 N Ravenswood Ave # 1",
    "sg:city":"Chicago",
    "sg:classifiers":[
        {
            "category":"Wholesale",
            "subcategory":"Medical Equipment & Supplies",
            "type":"Manufacturing & Wholesale Goods"
        }
    ],
    "sg:phone":"+1 773 327 4520",
    "sg:postcode":"60613",
    "sg:province":"IL",
    "sg:tags":[
        "laboratory"
    ],
    "sg:website":"http://www.atlas-mts.com",
    "wof:name":"K H Steuernagel Technical Lighting",
    "wof:placetype":"venue"
},
  "geometry": {"coordinates":[-87.674263,41.956495],"type":"Point"}
}