{
  "type": "Feature",
  "properties": {
    "iso:country":"US",
    "sg:address":"1834 Glenview Rd Ste 2E",
    "sg:city":"Glenview",
    "sg:classifiers":[
        {
            "category":"Real Estate",
            "subcategory":"Real Estate Services",
            "type":"Services"
        },
        {
            "category":"Real Estate",
            "subcategory":"Real Estate Agent",
            "type":"Services"
        }
    ],
    "sg:phone":"+1 847 832 5800",
    "sg:postcode":"60025",
    "sg:province":"IL",
    "sg:tags":[
        "management"
    ],
    "wof:name":"Robbins Group Real Estate Marketing",
    "wof:placetype":"venue"
},
  "geometry": {"coordinates":[-87.803774,42.072799],"type":"Point"}
}