{
  "type": "Feature",
  "properties": {
    "addr:full":"27791 N 1575 East Rd Danville IL 61834",
    "addr:housenumber":"27791;1575",
    "addr:postcode":"61834",
    "addr:street":"N;East Rd",
    "iso:country":"US",
    "sg:address":"27791 N 1575 East Rd",
    "sg:city":"Danville",
    "sg:classifiers":[
        {
            "category":"Personal",
            "subcategory":"Beauty Salon",
            "type":"Services"
        }
    ],
    "sg:phone":"+1 217 759 7928",
    "sg:postcode":"61834",
    "sg:province":"IL",
    "wof:name":"Sue's Styling",
    "wof:placetype":"venue"
},
  "geometry": {"coordinates":[-87.64743300000001,40.269477],"type":"Point"}
}