{
  "type": "Feature",
  "properties": {
    "iso:country":"US",
    "sg:address":"510 S 9th St",
    "sg:city":"Quincy",
    "sg:classifiers":[
        {
            "category":"Building & Trades",
            "subcategory":"Construction",
            "type":"Services"
        }
    ],
    "sg:phone":"+1 217 224 2292",
    "sg:postcode":"62301",
    "sg:province":"IL",
    "sg:tags":[
        "home",
        "contractor",
        "improvement"
    ],
    "wof:name":"Darnell Home Improvement Co",
    "wof:placetype":"venue"
},
  "geometry": {"coordinates":[-91.401689,39.926403],"type":"Point"}
}