{
  "type": "Feature",
  "properties": {
    "iso:country":"US",
    "sg:address":"140 Regency Centre",
    "sg:city":"Collinsville",
    "sg:classifiers":[
        {
            "category":"Real Estate",
            "subcategory":"Real Estate Services",
            "type":"Services"
        }
    ],
    "sg:phone":"+1 618 346 8009",
    "sg:postcode":"62234",
    "sg:province":"IL",
    "sg:tags":[
        "company",
        "title"
    ],
    "wof:name":"Abstracts & Title Inc",
    "wof:placetype":"venue"
},
  "geometry": {"coordinates":[-89.989676,38.692564],"type":"Point"}
}