{
  "type": "Feature",
  "properties": {
    "iso:country":"US",
    "sg:address":"304 N Gardiner Ave",
    "sg:city":"Rockford",
    "sg:classifiers":[
        {
            "category":"Professional",
            "subcategory":"Business Services",
            "type":"Services"
        }
    ],
    "sg:phone":"+1 815 229 7757",
    "sg:postcode":"61107",
    "sg:province":"IL",
    "wof:name":"Creative Atmospheres",
    "wof:placetype":"venue"
},
  "geometry": {"coordinates":[-89.06659399999999,42.271397],"type":"Point"}
}