{
  "type": "Feature",
  "properties": {
    "iso:country":"US",
    "sg:address":"821 Westwood Ave",
    "sg:city":"Joliet",
    "sg:classifiers":[
        {
            "category":"Retail",
            "subcategory":"Repair Shop",
            "type":"Services"
        }
    ],
    "sg:phone":"+1 815 744 3153",
    "sg:postcode":"60436",
    "sg:province":"IL",
    "wof:name":"Lyle & Co",
    "wof:placetype":"venue"
},
  "geometry": {"coordinates":[-88.102311,41.516441],"type":"Point"}
}