{
  "type": "Feature",
  "properties": {
    "iso:country":"US",
    "sg:address":"440 N La Salle Dr",
    "sg:city":"Chicago",
    "sg:classifiers":[
        {
            "category":"Retail",
            "subcategory":"Auto Rental",
            "type":"Services"
        }
    ],
    "sg:phone":"+1 773 686 6780",
    "sg:postcode":"60610",
    "sg:province":"IL",
    "sg:tags":[
        "car"
    ],
    "wof:name":"Sears Car & Truck Rental",
    "wof:placetype":"venue"
},
  "geometry": {"coordinates":[-87.63249999999999,41.890301],"type":"Point"}
}