{
  "type": "Feature",
  "properties": {
    "addr:full":"2101 W Howard St Chicago IL 60645",
    "addr:housenumber":"2101",
    "addr:postcode":"60645",
    "addr:street":"W Howard St",
    "iso:country":"US",
    "sg:address":"2101 W Howard St",
    "sg:city":"Chicago",
    "sg:classifiers":[
        {
            "category":"Personal",
            "type":"Services"
        },
        {
            "category":"Retail",
            "subcategory":"Storage",
            "type":"Services"
        }
    ],
    "sg:phone":"+1 877 258 8230",
    "sg:postcode":"60645",
    "sg:province":"IL",
    "sg:tags":[
        "full",
        "self",
        "commercial",
        "mover",
        "household"
    ],
    "sg:website":"http://www.publicstorage.com/?pid=ypcomCPCingenio",
    "wof:name":"Public Storage",
    "wof:placetype":"venue"
},
  "geometry": {"coordinates":[-87.682947,42.019459],"type":"Point"}
}