{
  "type": "Feature",
  "properties": {
    "iso:country":"US",
    "sg:address":"3429 County Road 450 E",
    "sg:city":"Foosland",
    "sg:classifiers":[
        {
            "category":"Social Services",
            "type":"Services"
        }
    ],
    "sg:phone":"+1 217 784 4222",
    "sg:postcode":"61845",
    "sg:province":"IL",
    "wof:name":"Foosland Sportsman Club",
    "wof:placetype":"venue"
},
  "geometry": {"coordinates":[-88.37535200000001,40.376152],"type":"Point"}
}