{
  "type": "Feature",
  "properties": {
    "addr:full":"1051 Talma St Aurora IL 60505",
    "addr:housenumber":"1051",
    "addr:postcode":"60505",
    "addr:street":"Talma St",
    "iso:country":"US",
    "sg:address":"1051 Talma St",
    "sg:city":"Aurora",
    "sg:classifiers":[
        {
            "category":"Personal",
            "subcategory":"Beauty Salon",
            "type":"Services"
        }
    ],
    "sg:phone":"+1 630 585 2400",
    "sg:postcode":"60505",
    "sg:province":"IL",
    "wof:name":"Talma Salon",
    "wof:placetype":"venue"
},
  "geometry": {"coordinates":[-88.311626,41.736535],"type":"Point"}
}