{
  "type": "Feature",
  "properties": {
    "iso:country":"US",
    "sg:address":"3436 S King Drive",
    "sg:city":"Chicago",
    "sg:classifiers":[
        {
            "category":"Education",
            "subcategory":"Library",
            "type":"Public Place"
        }
    ],
    "sg:phone":"+1 312 747 7543",
    "sg:postcode":"60616",
    "sg:province":"IL",
    "sg:website":"www.chipublib.org",
    "wof:name":"Chicago Public Library",
    "wof:placetype":"venue"
},
  "geometry": {"coordinates":[-87.61776399999999,41.831798],"type":"Point"}
}