{
  "type": "Feature",
  "properties": {
    "addr:full":"9051 Archer Ave Willow Springs IL 60480",
    "addr:housenumber":"9051",
    "addr:postcode":"60480",
    "addr:street":"Archer Ave",
    "iso:country":"US",
    "sg:address":"9051 Archer Ave",
    "sg:city":"Willow Springs",
    "sg:classifiers":[
        {
            "category":"Professional",
            "subcategory":"Management & Consulting",
            "type":"Services"
        }
    ],
    "sg:phone":"+1 708 839 4020",
    "sg:postcode":"60480",
    "sg:province":"IL",
    "wof:name":"Human Factor",
    "wof:placetype":"venue"
},
  "geometry": {"coordinates":[-87.878376,41.73114],"type":"Point"}
}