{
  "type": "Feature",
  "properties": {
    "iso:country":"US",
    "sg:address":"22426 N Blue Ridge Rd",
    "sg:city":"Edelstein",
    "sg:classifiers":[
        {
            "category":"Organizations",
            "subcategory":"Religious Organization",
            "type":"Services"
        }
    ],
    "sg:phone":"+1 309 249 4851",
    "sg:postcode":"61526",
    "sg:province":"IL",
    "sg:tags":[
        "church"
    ],
    "wof:name":"Blue Ridge Methodist Church",
    "wof:placetype":"venue"
},
  "geometry": {"coordinates":[-89.572789,40.958743],"type":"Point"}
}