{
  "type": "Feature",
  "properties": {
    "iso:country":"US",
    "sg:address":"16447 Cherry Hill Ave",
    "sg:city":"Tinley Park",
    "sg:classifiers":[
        {
            "category":"Manufacturing",
            "subcategory":"Tools & Machinery",
            "type":"Manufacturing & Wholesale Goods"
        }
    ],
    "sg:phone":"+1 708 633 8796",
    "sg:postcode":"60487",
    "sg:province":"IL",
    "sg:tags":[
        "industrial",
        "mfg"
    ],
    "wof:name":"Lepel Corporation",
    "wof:placetype":"venue"
},
  "geometry": {"coordinates":[-87.827614,41.591378],"type":"Point"}
}