{
  "type": "Feature",
  "properties": {
    "iso:country":"US",
    "sg:address":"5959 S Harlem Ave",
    "sg:city":"Chicago",
    "sg:classifiers":[
        {
            "category":"Communications",
            "subcategory":"Newspaper",
            "type":"Services"
        }
    ],
    "sg:phone":"+1 800 631 2500",
    "sg:postcode":"60638",
    "sg:province":"IL",
    "sg:tags":[
        "print",
        "medium"
    ],
    "wof:name":"New York Times",
    "wof:placetype":"venue"
},
  "geometry": {"coordinates":[-87.8009,41.783365],"type":"Point"}
}