{
  "type": "Feature",
  "properties": {
    "iso:country":"US",
    "sg:address":"200 E 99th Street",
    "sg:city":"Chicago",
    "sg:classifiers":[
        {
            "category":"Education",
            "subcategory":"School",
            "type":"Public Place"
        }
    ],
    "sg:phone":"+1 773 535 5457",
    "sg:postcode":"60628",
    "sg:province":"IL",
    "sg:tags":[
        "high",
        "middle",
        "elementary"
    ],
    "wof:name":"Schools Public",
    "wof:placetype":"venue"
},
  "geometry": {"coordinates":[-87.618376,41.714414],"type":"Point"}
}