{
  "type": "Feature",
  "properties": {
    "addr:full":"1368 N Milwaukee Ave Chicago IL 60622",
    "addr:housenumber":"1368",
    "addr:postcode":"60622",
    "addr:street":"N Milwaukee Ave",
    "iso:country":"US",
    "sg:address":"1368 N Milwaukee Ave",
    "sg:city":"Chicago",
    "sg:classifiers":[
        {
            "category":"Health Services",
            "subcategory":"Doctor",
            "type":"Services"
        }
    ],
    "sg:phone":"+1 773 235 2882",
    "sg:postcode":"60622",
    "sg:province":"IL",
    "wof:name":"Ricaurte Francisco MD",
    "wof:placetype":"venue"
},
  "geometry": {"coordinates":[-87.6717,41.906898],"type":"Point"}
}