{
  "type": "Feature",
  "properties": {
    "iso:country":"US",
    "sg:address":"615 S Main St",
    "sg:city":"Princeton",
    "sg:classifiers":[
        {
            "category":"Shopping",
            "subcategory":"Clothing, Apparel, & Fashions",
            "type":"Retail Goods"
        }
    ],
    "sg:phone":"+1   ",
    "sg:postcode":"61356",
    "sg:province":"IL",
    "wof:name":"Villager The",
    "wof:placetype":"venue"
},
  "geometry": {"coordinates":[-89.464984,41.369308],"type":"Point"}
}