{
  "type": "Feature",
  "properties": {
    "iso:country":"US",
    "sg:address":"3356 Jaeger Ln",
    "sg:city":"Louisville",
    "sg:classifiers":[
        {
            "category":"Farming",
            "subcategory":"Livestock Farm",
            "type":"Manufacturing & Wholesale Goods"
        },
        {
            "category":"Farming",
            "subcategory":"Farm",
            "type":"Manufacturing & Wholesale Goods"
        }
    ],
    "sg:phone":"+1 618 665 3283",
    "sg:postcode":"62858",
    "sg:province":"IL",
    "wof:name":"Bob Bailey Farm",
    "wof:placetype":"venue"
},
  "geometry": {"coordinates":[-88.57615300000001,38.753812],"type":"Point"}
}