{
  "type": "Feature",
  "properties": {
    "addr:full":"8217 S Pulaski Rd Chicago IL 60652",
    "addr:housenumber":"8217",
    "addr:postcode":"60652",
    "addr:street":"S Pulaski Rd",
    "iso:country":"US",
    "sg:address":"8217 S Pulaski Rd",
    "sg:city":"Chicago",
    "sg:classifiers":[
        {
            "category":"Autos & Motor Vehicles",
            "subcategory":"Fuel & Gas Station",
            "type":"Retail Goods"
        },
        {
            "category":"Retail",
            "subcategory":"Auto Repair",
            "type":"Services"
        }
    ],
    "sg:phone":"+1 773 581 6925",
    "sg:postcode":"60652",
    "sg:province":"IL",
    "wof:name":"Nick & Denny's Auto Repair",
    "wof:placetype":"venue"
},
  "geometry": {"coordinates":[-87.721397,41.743301],"type":"Point"}
}