{
  "type": "Feature",
  "properties": {
    "addr:full":"2188 Inverray Rd Inverness IL 60067",
    "addr:housenumber":"2188",
    "addr:postcode":"60067",
    "addr:street":"Inverray Rd",
    "iso:country":"US",
    "sg:address":"2188 Inverray Rd",
    "sg:city":"Inverness",
    "sg:classifiers":[
        {
            "category":"Real Estate",
            "subcategory":"Real Estate Agent",
            "type":"Services"
        }
    ],
    "sg:phone":"+1 847 705 9066",
    "sg:postcode":"60067",
    "sg:province":"IL",
    "wof:name":"Accurate Appraisals",
    "wof:placetype":"venue"
},
  "geometry": {"coordinates":[-88.09540699999999,42.105202],"type":"Point"}
}