{
  "type": "Feature",
  "properties": {
    "iso:country":"US",
    "sg:address":"2188 Inverray Rd",
    "sg:city":"Inverness",
    "sg:classifiers":[
        {
            "category":"Real Estate",
            "subcategory":"Real Estate Agent",
            "type":"Services"
        }
    ],
    "sg:phone":"+1 847 705 9066",
    "sg:postcode":"60067",
    "sg:province":"IL",
    "wof:name":"Accurate Appraisals",
    "wof:placetype":"venue"
},
  "geometry": {"coordinates":[-88.095407,42.105202],"type":"Point"}
}