{
  "type": "Feature",
  "properties": {
    "iso:country":"US",
    "sg:address":"8603 Pyott Rd",
    "sg:city":"Lake In The Hls",
    "sg:classifiers":[
        {
            "category":"Building & Trades",
            "subcategory":"Construction",
            "type":"Services"
        }
    ],
    "sg:phone":"+1 815 356 6500",
    "sg:postcode":"60156",
    "sg:province":"IL",
    "sg:tags":[
        "a",
        "excavating",
        "excavation",
        "contractor",
        "concrete",
        "removal",
        "demolition"
    ],
    "wof:name":"Snelten Inc",
    "wof:placetype":"venue"
},
  "geometry": {"coordinates":[-88.312139,42.198714],"type":"Point"}
}