{
  "type": "Feature",
  "properties": {
    "iso:country":"US",
    "sg:address":"2144 W Concord Pl",
    "sg:city":"Chicago",
    "sg:classifiers":[
        {
            "category":"Building & Trades",
            "subcategory":"Construction",
            "type":"Services"
        }
    ],
    "sg:phone":"+1 773 278 3320",
    "sg:postcode":"60647",
    "sg:province":"IL",
    "sg:tags":[
        "designer"
    ],
    "wof:name":"Christopher S Tuscan Inc",
    "wof:placetype":"venue"
},
  "geometry": {"coordinates":[-87.682367,41.911201],"type":"Point"}
}