{
  "type": "Feature",
  "properties": {
    "iso:country":"US",
    "sg:address":"4200 W Wrightwood Ave",
    "sg:city":"Chicago",
    "sg:classifiers":[
        {
            "category":"Professional",
            "subcategory":"Art Services",
            "type":"Services"
        },
        {
            "category":"Professional",
            "subcategory":"Printing & Photocopies",
            "type":"Services"
        }
    ],
    "sg:phone":"+1 888 800 5646",
    "sg:postcode":"60639",
    "sg:province":"IL",
    "sg:tags":[
        "graphic",
        "design"
    ],
    "sg:website":"www.sharprint.com",
    "wof:name":"Sharprint",
    "wof:placetype":"venue"
},
  "geometry": {"coordinates":[-87.732336,41.928334],"type":"Point"}
}