{
  "type": "Feature",
  "properties": {
    "addr:full":"1724 W Thorndale Ave Chicago IL 60660",
    "addr:housenumber":"1724",
    "addr:postcode":"60660",
    "addr:street":"W Thorndale Ave",
    "iso:country":"US",
    "sg:address":"1724 W Thorndale Ave",
    "sg:city":"Chicago",
    "sg:classifiers":[
        {
            "category":"Retail",
            "subcategory":"Auto Repair",
            "type":"Services"
        }
    ],
    "sg:phone":"+1 773 275 1219",
    "sg:postcode":"60660",
    "sg:province":"IL",
    "sg:tags":[
        "body",
        "shop"
    ],
    "wof:name":"Presto Dent Co",
    "wof:placetype":"venue"
},
  "geometry": {"coordinates":[-87.67269899999999,41.9884],"type":"Point"}
}