{
  "type": "Feature",
  "properties": {
    "addr:full":"5530 S Ellis Ave Chicago IL 60637",
    "addr:housenumber":"5530",
    "addr:postcode":"60637",
    "addr:street":"S Ellis Ave",
    "iso:country":"US",
    "sg:address":"5530 S Ellis Ave",
    "sg:city":"Chicago",
    "sg:classifiers":[
        {
            "category":"Sports & Exercise",
            "subcategory":"Gym",
            "type":"Entertainment"
        }
    ],
    "sg:postcode":"60637",
    "sg:province":"IL",
    "sg:website":"athletics.uchicago.edu/facilitie...",
    "wof:name":"Gerald Ratner Athletic Center",
    "wof:placetype":"venue"
},
  "geometry": {"coordinates":[-87.60137899999999,41.794427],"type":"Point"}
}