{
  "type": "Feature",
  "properties": {
    "addr:full":"960 S Arthur Ave Arlington Hts IL 60005",
    "addr:housenumber":"960",
    "addr:postcode":"60005",
    "addr:street":"S Arthur Ave",
    "iso:country":"US",
    "sg:address":"960 S Arthur Ave",
    "sg:city":"Arlington Hts",
    "sg:classifiers":[
        {
            "category":"Education",
            "subcategory":"Vocational School",
            "type":"Public Place"
        }
    ],
    "sg:phone":"+1 847 632 0185",
    "sg:postcode":"60005",
    "sg:province":"IL",
    "sg:tags":[
        "sewing",
        "instruction"
    ],
    "sg:website":"www.geraghtyheirloom.com",
    "wof:name":"Geraghty Heirloom",
    "wof:placetype":"venue"
},
  "geometry": {"coordinates":[-87.966143,42.073628],"type":"Point"}
}