{
  "type": "Feature",
  "properties": {
    "addr:full":"321 E Indian Trl Aurora IL 60505",
    "addr:housenumber":"321",
    "addr:postcode":"60505",
    "addr:street":"E Indian Trl",
    "iso:country":"US",
    "sg:address":"321 E Indian Trl",
    "sg:city":"Aurora",
    "sg:classifiers":[
        {
            "category":"Personal",
            "subcategory":"Beauty Salon",
            "type":"Services"
        }
    ],
    "sg:phone":"+1 630 897 5678",
    "sg:postcode":"60505",
    "sg:province":"IL",
    "sg:tags":[
        "shop"
    ],
    "wof:name":"LA Belle Petite Beauty Salon",
    "wof:placetype":"venue"
},
  "geometry": {"coordinates":[-88.307363,41.782036],"type":"Point"}
}