{
  "type": "Feature",
  "properties": {
    "iso:country":"US",
    "sg:address":"1925 W Division St",
    "sg:city":"Chicago",
    "sg:classifiers":[
        {
            "category":"Personal",
            "subcategory":"Barber",
            "type":"Services"
        }
    ],
    "sg:phone":"+1 773 687 9057",
    "sg:postcode":"60622",
    "sg:province":"IL",
    "sg:website":"www.urbanjoe.com",
    "wof:name":"Urban Joe",
    "wof:placetype":"venue"
},
  "geometry": {"coordinates":[-87.67586300000001,41.902992],"type":"Point"}
}