{
  "type": "Feature",
  "properties": {
    "iso:country":"US",
    "sg:address":"109 5th St",
    "sg:city":"Colona",
    "sg:classifiers":[
        {
            "category":"Freight",
            "type":"Transportation"
        }
    ],
    "sg:phone":"+1 309 792 1773",
    "sg:postcode":"61241",
    "sg:province":"IL",
    "sg:tags":[
        "trucking"
    ],
    "wof:name":"GTX Trucking",
    "wof:placetype":"venue"
},
  "geometry": {"coordinates":[-90.363892,41.48191],"type":"Point"}
}