{
  "type": "Feature",
  "properties": {
    "iso:country":"US",
    "sg:address":"236 N Gables Blvd",
    "sg:city":"Wheaton",
    "sg:classifiers":[
        {
            "category":"Shopping",
            "subcategory":"Optical Goods",
            "type":"Retail Goods"
        }
    ],
    "sg:phone":"+1 630 510 1706",
    "sg:postcode":"60187",
    "sg:province":"IL",
    "sg:tags":[
        "optician",
        "eyewear"
    ],
    "wof:name":"Done Right Optical",
    "wof:placetype":"venue"
},
  "geometry": {"coordinates":[-88.12039900000001,41.866299],"type":"Point"}
}