{
  "type": "Feature",
  "properties": {
    "iso:country":"US",
    "sg:address":"18150 Halsted St",
    "sg:city":"Homewood",
    "sg:classifiers":[
        {
            "category":"Home & Garden",
            "subcategory":"Furniture",
            "type":"Retail Goods"
        },
        {
            "category":"Professional",
            "subcategory":"Employment Agencies",
            "type":"Services"
        }
    ],
    "sg:phone":"+1 708 799 3200",
    "sg:postcode":"60430",
    "sg:province":"IL",
    "sg:tags":[
        "employee",
        "leasing"
    ],
    "sg:website":"www.bayfurniture.com",
    "wof:name":"Bay Furniture Co",
    "wof:placetype":"venue"
},
  "geometry": {"coordinates":[-87.636185,41.560192],"type":"Point"}
}