{
  "type": "Feature",
  "properties": {
    "addr:full":"1927 Reynolds Dr Charleston IL 61920",
    "addr:housenumber":"1927",
    "addr:postcode":"61920",
    "addr:street":"Reynolds Dr",
    "iso:country":"US",
    "sg:address":"1927 Reynolds Dr",
    "sg:city":"Charleston",
    "sg:classifiers":[
        {
            "category":"Real Estate",
            "subcategory":"Real Estate Operator",
            "type":"Services"
        }
    ],
    "sg:phone":"+1 217 348 0209",
    "sg:postcode":"61920",
    "sg:province":"IL",
    "sg:tags":[
        "apartment"
    ],
    "wof:name":"Quinlan Apts",
    "wof:placetype":"venue"
},
  "geometry": {"coordinates":[-88.191087,39.478861],"type":"Point"}
}