{
  "type": "Feature",
  "properties": {
    "iso:country":"US",
    "sg:address":"7526 W Main St",
    "sg:city":"Belleville",
    "sg:classifiers":[
        {
            "category":"Professional",
            "subcategory":"Accounting & Tax Preparation",
            "type":"Services"
        }
    ],
    "sg:phone":"+1 618 394 7572",
    "sg:postcode":"62223",
    "sg:province":"IL",
    "sg:tags":[
        "accountant"
    ],
    "wof:name":"Charles H Clarke",
    "wof:placetype":"venue"
},
  "geometry": {"coordinates":[-90.046864,38.561301],"type":"Point"}
}