{
  "type": "Feature",
  "properties": {
    "iso:country":"US",
    "sg:address":"4147 N Ravenswood Ave # 301",
    "sg:city":"Chicago",
    "sg:classifiers":[
        {
            "category":"Communications",
            "type":"Services"
        }
    ],
    "sg:phone":"+1 773 935 5788",
    "sg:postcode":"60613",
    "sg:province":"IL",
    "sg:tags":[
        "consultant",
        "engineer"
    ],
    "wof:name":"Rainbow Creative Concepts Corp",
    "wof:placetype":"venue"
},
  "geometry": {"coordinates":[-87.67384199999999,41.956919],"type":"Point"}
}