{
  "type": "Feature",
  "properties": {
    "iso:country":"US",
    "sg:address":"8251 Bunkum Rd",
    "sg:city":"Caseyville",
    "sg:classifiers":[
        {
            "category":"Building & Trades",
            "subcategory":"Construction",
            "type":"Services"
        }
    ],
    "sg:phone":"+1 618 397 4212",
    "sg:postcode":"62232",
    "sg:province":"IL",
    "sg:tags":[
        "waterproofing",
        "contractor"
    ],
    "wof:name":"Helitech",
    "wof:placetype":"venue"
},
  "geometry": {"coordinates":[-90.058729,38.622528],"type":"Point"}
}