{
  "type": "Feature",
  "properties": {
    "iso:country":"US",
    "sg:address":"8557 Niles Center Rd",
    "sg:city":"Skokie",
    "sg:classifiers":[
        {
            "category":"Taxi",
            "type":"Transportation"
        }
    ],
    "sg:phone":"+1 773 273 1550",
    "sg:postcode":"60077",
    "sg:province":"IL",
    "wof:name":"Taxi Number 16",
    "wof:placetype":"venue"
},
  "geometry": {"coordinates":[-87.74989600000001,42.036496],"type":"Point"}
}