{
  "type": "Feature",
  "properties": {
    "iso:country":"US",
    "sg:address":"77 Wilbur Ln",
    "sg:city":"Carbondale",
    "sg:classifiers":[
        {
            "category":"Building & Trades",
            "subcategory":"Landscaping Services",
            "type":"Services"
        }
    ],
    "sg:phone":"+1 618 457 2622",
    "sg:postcode":"62903",
    "sg:province":"IL",
    "sg:tags":[
        "landscape",
        "contractor"
    ],
    "wof:name":"Cedar Lake Landscape & Constr",
    "wof:placetype":"venue"
},
  "geometry": {"coordinates":[-89.252698,37.672755],"type":"Point"}
}