{
  "type": "Feature",
  "properties": {
    "iso:country":"US",
    "sg:address":"149 S Washington St",
    "sg:city":"Bunker Hill",
    "sg:classifiers":[
        {
            "category":"Autos & Motor Vehicles",
            "subcategory":"Auto Supplies",
            "type":"Retail Goods"
        }
    ],
    "sg:phone":"+1 618 585 3686",
    "sg:postcode":"62014",
    "sg:province":"IL",
    "sg:tags":[
        "automotive",
        "parts",
        "automobile"
    ],
    "wof:name":"Bunker Hill Auto Parts Inc",
    "wof:placetype":"venue"
},
  "geometry": {"coordinates":[-89.951635,39.04088],"type":"Point"}
}