{
  "type": "Feature",
  "properties": {
    "addr:full":"6283 W Howard St Niles IL 60714",
    "addr:housenumber":"6283",
    "addr:postcode":"60714",
    "addr:street":"W Howard St",
    "iso:country":"US",
    "sg:address":"6283 W Howard St",
    "sg:city":"Niles",
    "sg:classifiers":[
        {
            "category":"Shopping",
            "subcategory":"Clothing, Apparel, & Fashions",
            "type":"Retail Goods"
        }
    ],
    "sg:phone":"+1 847 647 8850",
    "sg:postcode":"60714",
    "sg:province":"IL",
    "sg:tags":[
        "clothing",
        "store"
    ],
    "wof:name":"H K Fashion",
    "wof:placetype":"venue"
},
  "geometry": {"coordinates":[-87.785156,42.019217],"type":"Point"}
}