{
  "type": "Feature",
  "properties": {
    "iso:country":"US",
    "sg:address":"1502 Airport Rd",
    "sg:city":"Urbana",
    "sg:classifiers":[
        {
            "category":"Building & Trades",
            "subcategory":"Plumbing",
            "type":"Services"
        }
    ],
    "sg:phone":"+1 217 337 6300",
    "sg:postcode":"61802",
    "sg:province":"IL",
    "sg:tags":[
        "contractor"
    ],
    "wof:name":"Zonfrilli John",
    "wof:placetype":"venue"
},
  "geometry": {"coordinates":[-88.19046299999999,40.142081],"type":"Point"}
}