{
  "type": "Feature",
  "properties": {
    "addr:full":"1608 W Belmont Ave Chicago IL 60657",
    "addr:housenumber":"1608",
    "addr:postcode":"60657",
    "addr:street":"W Belmont Ave",
    "iso:country":"US",
    "sg:address":"1608 W Belmont Ave",
    "sg:city":"Chicago",
    "sg:classifiers":[
        {
            "category":"Personal",
            "subcategory":"Hair Removal",
            "type":"Services"
        }
    ],
    "sg:phone":"+1 773 477 7884",
    "sg:postcode":"60657",
    "sg:province":"IL",
    "sg:tags":[
        "removing",
        "electrolysis"
    ],
    "wof:name":"Debbie's Electrolysis",
    "wof:placetype":"venue"
},
  "geometry": {"coordinates":[-87.669403,41.939701],"type":"Point"}
}