{
  "type": "Feature",
  "properties": {
    "iso:country":"US",
    "sg:address":"305 N Central Ave",
    "sg:city":"Casey",
    "sg:classifiers":[
        {
            "category":"Banks & Credit Unions",
            "subcategory":"Bank",
            "type":"Services"
        }
    ],
    "sg:phone":"+1 217 932 2136",
    "sg:postcode":"62420",
    "sg:province":"IL",
    "wof:name":"Casey State Bank",
    "wof:placetype":"venue"
},
  "geometry": {"coordinates":[-87.993013,39.302559],"type":"Point"}
}