{
  "type": "Feature",
  "properties": {
    "iso:country":"US",
    "sg:address":"5948 W Diversey Ave",
    "sg:city":"Chicago",
    "sg:classifiers":[
        {
            "category":"Bars & Pubs",
            "subcategory":"Lounge",
            "type":"Food & Drink"
        }
    ],
    "sg:phone":"+1 773 622 0404",
    "sg:postcode":"60639",
    "sg:province":"IL",
    "sg:website":"www.myspace.com/atluckychicago",
    "wof:name":"Lucky \u00a0Inn",
    "wof:placetype":"venue"
},
  "geometry": {"coordinates":[-87.77548299999999,41.931406],"type":"Point"}
}