{
  "type": "Feature",
  "properties": {
    "addr:full":"700 N Michigan Ave Ste 202 Chicago IL 60611",
    "addr:housenumber":"700",
    "addr:postcode":"60611",
    "addr:street":"N Michigan Ave Ste 202",
    "iso:country":"US",
    "sg:address":"700 N Michigan Ave Ste 202",
    "sg:city":"Chicago",
    "sg:classifiers":[
        {
            "category":"Home & Garden",
            "subcategory":"Household Appliances",
            "type":"Retail Goods"
        },
        {
            "category":"Food & Beverages",
            "subcategory":"Specialty",
            "type":"Retail Goods"
        },
        {
            "category":"Home & Garden",
            "subcategory":"Home Furnishings",
            "type":"Retail Goods"
        },
        {
            "category":"Manufacturing",
            "subcategory":"Glass & Minerals",
            "type":"Manufacturing & Wholesale Goods"
        },
        {
            "category":"Home & Garden",
            "subcategory":"Kitchen Supply",
            "type":"Retail Goods"
        }
    ],
    "sg:phone":"+1 312 787 8991",
    "sg:postcode":"60611",
    "sg:province":"IL",
    "sg:tags":[
        "shop",
        "gourmet",
        "house",
        "appliances-small",
        "accessory",
        "crystal",
        "cookware",
        "china",
        "utensil",
        "housewares",
        "glassware"
    ],
    "sg:website":"http://www.williams-sonoma.com/",
    "wof:name":"Williams-Sonoma",
    "wof:placetype":"venue"
},
  "geometry": {"coordinates":[-87.62423699999999,41.894939],"type":"Point"}
}