{
  "type": "Feature",
  "properties": {
    "addr:full":"314 W Army Trail Rd Bloomingdale IL 60108",
    "addr:housenumber":"314",
    "addr:postcode":"60108",
    "addr:street":"W Army Trail Rd",
    "iso:country":"US",
    "sg:address":"314 W Army Trail Rd",
    "sg:city":"Bloomingdale",
    "sg:classifiers":[
        {
            "category":"Shopping",
            "subcategory":"Department Store",
            "type":"Retail Goods"
        },
        {
            "category":"Shopping",
            "subcategory":"Mobile Phones",
            "type":"Retail Goods"
        },
        {
            "category":"Food & Beverages",
            "subcategory":"Groceries & Convenience Stores",
            "type":"Retail Goods"
        }
    ],
    "sg:phone":"+1 630 893 5000",
    "sg:postcode":"60108",
    "sg:province":"IL",
    "sg:website":"www.walmart.com",
    "wof:name":"Walmart",
    "wof:placetype":"venue"
},
  "geometry": {"coordinates":[-88.10257300000001,41.937006],"type":"Point"}
}