{
  "type": "Feature",
  "properties": {
    "addr:full":"3553 W Roosevelt Rd Chicago IL 60624",
    "addr:housenumber":"3553",
    "addr:postcode":"60624",
    "addr:street":"W Roosevelt Rd",
    "iso:country":"US",
    "sg:address":"3553 W Roosevelt Rd",
    "sg:city":"Chicago",
    "sg:classifiers":[
        {
            "category":"Food & Beverages",
            "subcategory":"Groceries & Convenience Stores",
            "type":"Retail Goods"
        }
    ],
    "sg:phone":"+1 773 542 6998",
    "sg:postcode":"60624",
    "sg:province":"IL",
    "wof:name":"Dallas A Submarine",
    "wof:placetype":"venue"
},
  "geometry": {"coordinates":[-87.714246,41.866182],"type":"Point"}
}