{
  "type": "Feature",
  "properties": {
    "addr:full":"7011 159th St Tinley Park IL 60477",
    "addr:housenumber":"7011",
    "addr:postcode":"60477",
    "addr:street":"159Th St",
    "iso:country":"US",
    "sg:address":"7011 159th St",
    "sg:city":"Tinley Park",
    "sg:classifiers":[
        {
            "category":"Retail",
            "subcategory":"Auto Repair",
            "type":"Services"
        }
    ],
    "sg:phone":"+1 708 614 1600",
    "sg:postcode":"60477",
    "sg:province":"IL",
    "sg:tags":[
        "muffler"
    ],
    "wof:name":"Midas Muffler",
    "wof:placetype":"venue"
},
  "geometry": {"coordinates":[-87.789366,41.602264],"type":"Point"}
}