{
  "type": "Feature",
  "properties": {
    "iso:country":"US",
    "sg:address":"6116 Ojibwa Ln",
    "sg:city":"Mchenry",
    "sg:classifiers":[
        {
            "category":"Government",
            "subcategory":"Fire Station",
            "type":"Public Place"
        },
        {
            "category":"Home & Garden",
            "subcategory":"Hardware",
            "type":"Retail Goods"
        }
    ],
    "sg:phone":"+1 815 344 4600",
    "sg:postcode":"60050",
    "sg:province":"IL",
    "sg:tags":[
        "industrial",
        "protection",
        "consultant",
        "commercial",
        "sprinklers-residential",
        "automatic"
    ],
    "wof:name":"Advanced Fire Protection & Safety Inc",
    "wof:placetype":"venue"
},
  "geometry": {"coordinates":[-88.317319,42.34454],"type":"Point"}
}