{
  "type": "Feature",
  "properties": {
    "addr:full":"11008 W Lincoln Hwy Frankfort IL 60423",
    "addr:housenumber":"11008",
    "addr:postcode":"60423",
    "addr:street":"W Lincoln Hwy",
    "iso:country":"US",
    "sg:address":"11008 W Lincoln Hwy",
    "sg:city":"Frankfort",
    "sg:classifiers":[
        {
            "category":"Social Services",
            "type":"Services"
        }
    ],
    "sg:phone":"+1 815 469 4778",
    "sg:postcode":"60423",
    "sg:province":"IL",
    "sg:tags":[
        "counselor",
        "marriage",
        "family"
    ],
    "wof:name":"Family Counseling Agency",
    "wof:placetype":"venue"
},
  "geometry": {"coordinates":[-87.884535,41.502806],"type":"Point"}
}