{
  "type": "Feature",
  "properties": {
    "iso:country":"US",
    "sg:address":"5618 W 95th St",
    "sg:city":"Oak Lawn",
    "sg:classifiers":[
        {
            "category":"Shopping",
            "type":"Retail Goods"
        },
        {
            "category":"Wholesale",
            "subcategory":"Durable Goods & Equipment",
            "type":"Manufacturing & Wholesale Goods"
        }
    ],
    "sg:phone":"+1 708 422 2250",
    "sg:postcode":"60453",
    "sg:province":"IL",
    "sg:tags":[
        "fire",
        "extinguisher",
        "merchandise"
    ],
    "wof:name":"Classic Fire Equipment Company",
    "wof:placetype":"venue"
},
  "geometry": {"coordinates":[-87.76088900000001,41.719807],"type":"Point"}
}