{
  "type": "Feature",
  "properties": {
    "iso:country":"US",
    "sg:address":"7245 Cunningham Rd",
    "sg:city":"Rockford",
    "sg:classifiers":[
        {
            "category":"Wholesale",
            "subcategory":"Petroleum",
            "type":"Manufacturing & Wholesale Goods"
        }
    ],
    "sg:phone":"+1 815 965 6623",
    "sg:postcode":"61102",
    "sg:province":"IL",
    "sg:tags":[
        "transmission",
        "refined",
        "pipeline"
    ],
    "wof:name":"Megellan Pipeline Company LLC",
    "wof:placetype":"venue"
},
  "geometry": {"coordinates":[-89.181145,42.260221],"type":"Point"}
}