{
  "type": "Feature",
  "properties": {
    "iso:country":"US",
    "sg:address":"5727 N Mango Ave",
    "sg:city":"Chicago",
    "sg:classifiers":[
        {
            "category":"Organizations",
            "subcategory":"Community Association",
            "type":"Services"
        }
    ],
    "sg:phone":"+1 708 841 9807",
    "sg:postcode":"60646",
    "sg:province":"IL",
    "wof:name":"Riverwood Condos",
    "wof:placetype":"venue"
},
  "geometry": {"coordinates":[-87.771836,41.985694],"type":"Point"}
}