{
  "type": "Feature",
  "properties": {
    "iso:country":"US",
    "sg:address":"28 E Randolph St",
    "sg:city":"Chicago",
    "sg:classifiers":[
        {
            "category":"Shopping",
            "subcategory":"Shoes",
            "type":"Retail Goods"
        }
    ],
    "sg:phone":"+1 312 346 5838",
    "sg:postcode":"60601",
    "sg:province":"IL",
    "sg:tags":[
        "store"
    ],
    "wof:name":"Naturalizer Shoes",
    "wof:placetype":"venue"
},
  "geometry": {"coordinates":[-87.62690000000001,41.884399],"type":"Point"}
}