{
  "type": "Feature",
  "properties": {
    "addr:full":"1818 Washington Ave Alton IL 62002",
    "addr:housenumber":"1818",
    "addr:postcode":"62002",
    "addr:street":"Washington Ave",
    "iso:country":"US",
    "sg:address":"1818 Washington Ave",
    "sg:city":"Alton",
    "sg:classifiers":[
        {
            "category":"Wholesale",
            "subcategory":"Groceries",
            "type":"Manufacturing & Wholesale Goods"
        }
    ],
    "sg:phone":"+1 618 465 9402",
    "sg:postcode":"62002",
    "sg:province":"IL",
    "sg:tags":[
        "grocer"
    ],
    "wof:name":"Hit-N-Run Food Stores",
    "wof:placetype":"venue"
},
  "geometry": {"coordinates":[-90.149863,38.905466],"type":"Point"}
}