{
  "type": "Feature",
  "properties": {
    "iso:country":"US",
    "sg:address":"1415 W Elm St",
    "sg:city":"Arlington Hts",
    "sg:classifiers":[
        {
            "category":"Professional",
            "subcategory":"Business Services",
            "type":"Services"
        },
        {
            "category":"Building & Trades",
            "subcategory":"Landscaping Services",
            "type":"Services"
        }
    ],
    "sg:phone":"+1 847 392 3079",
    "sg:postcode":"60004",
    "sg:province":"IL",
    "sg:tags":[
        "landscape",
        "contractor"
    ],
    "wof:name":"H R Boyd Landscaping",
    "wof:placetype":"venue"
},
  "geometry": {"coordinates":[-88.000923,42.092973],"type":"Point"}
}