{
  "type": "Feature",
  "properties": {
    "addr:full":"132 N 1st St Geneva IL 60134",
    "addr:housenumber":"132",
    "addr:postcode":"60134",
    "addr:street":"N 1St St",
    "iso:country":"US",
    "sg:address":"132 N 1st St",
    "sg:city":"Geneva",
    "sg:classifiers":[
        {
            "category":"Building & Trades",
            "subcategory":"Construction",
            "type":"Services"
        }
    ],
    "sg:phone":"+1 630 845 2603",
    "sg:postcode":"60134",
    "sg:province":"IL",
    "sg:tags":[
        "excavation",
        "contractor"
    ],
    "wof:name":"B and B Industrial Services",
    "wof:placetype":"venue"
},
  "geometry": {"coordinates":[-88.304755,41.889329],"type":"Point"}
}