{
  "type": "Feature",
  "properties": {
    "addr:full":"2548 W 63rd St Chicago IL 60629",
    "addr:housenumber":"2548",
    "addr:postcode":"60629",
    "addr:street":"W 63Rd St",
    "iso:country":"US",
    "sg:address":"2548 W 63rd St",
    "sg:city":"Chicago",
    "sg:classifiers":[
        {
            "category":"Autos & Motor Vehicles",
            "subcategory":"Auto Supplies",
            "type":"Retail Goods"
        }
    ],
    "sg:phone":"+1 773 925 6053",
    "sg:postcode":"60629",
    "sg:province":"IL",
    "sg:tags":[
        "tire"
    ],
    "wof:name":"Brothers Tire Shop",
    "wof:placetype":"venue"
},
  "geometry": {"coordinates":[-87.687798,41.779202],"type":"Point"}
}