{
  "type": "Feature",
  "properties": {
    "iso:country":"US",
    "sg:address":"105 Albrecht Dr",
    "sg:city":"Lake Bluff",
    "sg:classifiers":[
        {
            "category":"Manufacturing",
            "subcategory":"Tools & Machinery",
            "type":"Manufacturing & Wholesale Goods"
        }
    ],
    "sg:phone":"+1 847 295 1050",
    "sg:postcode":"60044",
    "sg:province":"IL",
    "sg:tags":[
        "device",
        "totalizing",
        "fluid",
        "mfg"
    ],
    "sg:website":"www.liquidcontrols.org",
    "wof:name":"Liquid Controls Inc",
    "wof:placetype":"venue"
},
  "geometry": {"coordinates":[-87.87229499999999,42.275697],"type":"Point"}
}