{
  "type": "Feature",
  "properties": {
    "addr:full":"8525 Hickory Hills Dr Argenta IL 62501",
    "addr:housenumber":"8525",
    "addr:postcode":"62501",
    "addr:street":"Hickory Hills Dr Argenta",
    "iso:country":"US",
    "sg:address":"8525 Hickory Hills Dr",
    "sg:city":"Argenta",
    "sg:classifiers":[
        {
            "category":"Manufacturing",
            "subcategory":"Buildings",
            "type":"Manufacturing & Wholesale Goods"
        },
        {
            "category":"Building & Trades",
            "subcategory":"Construction",
            "type":"Services"
        }
    ],
    "sg:phone":"+1 217 795 4403",
    "sg:postcode":"62501",
    "sg:province":"IL",
    "sg:tags":[
        "home",
        "builder",
        "contractor"
    ],
    "wof:name":"Mike Horve Builder",
    "wof:placetype":"venue"
},
  "geometry": {"coordinates":[-88.814864,39.999766],"type":"Point"}
}