{
  "type": "Feature",
  "properties": {
    "iso:country":"US",
    "sg:address":"9513 S Cicero Ave",
    "sg:city":"Oak Lawn",
    "sg:classifiers":[
        {
            "category":"Shopping",
            "subcategory":"Comic Books",
            "type":"Retail Goods"
        }
    ],
    "sg:phone":"+1 708 636 0806",
    "sg:postcode":"60453",
    "sg:province":"IL",
    "wof:name":"Tenth Planet",
    "wof:placetype":"venue"
},
  "geometry": {"coordinates":[-87.740601,41.720001],"type":"Point"}
}