{
  "type": "Feature",
  "properties": {
    "iso:country":"US",
    "sg:address":"808 Commercial Ave",
    "sg:city":"Cairo",
    "sg:classifiers":[
        {
            "category":"Bars & Pubs",
            "type":"Food & Drink"
        }
    ],
    "sg:phone":"+1 618 734 9327",
    "sg:postcode":"62914",
    "sg:province":"IL",
    "wof:name":"Capt N Wades Bar & Grill",
    "wof:placetype":"venue"
},
  "geometry": {"coordinates":[-89.166562,37.001542],"type":"Point"}
}