{
  "type": "Feature",
  "properties": {
    "iso:country":"US",
    "sg:address":"4810 Eastwood Ct",
    "sg:city":"Waukegan",
    "sg:classifiers":[
        {
            "category":"Insurance",
            "subcategory":"Hazard Insurance",
            "type":"Services"
        }
    ],
    "sg:phone":"+1 847 360 0585",
    "sg:postcode":"60087",
    "sg:province":"IL",
    "sg:tags":[
        "commercial",
        "business"
    ],
    "wof:name":"Sunrise Insurance Agency Inc",
    "wof:placetype":"venue"
},
  "geometry": {"coordinates":[-87.92139899999999,42.41295],"type":"Point"}
}