{
  "type": "Feature",
  "properties": {
    "iso:country":"US",
    "sg:address":"3701 Roth Ter",
    "sg:city":"Skokie",
    "sg:classifiers":[
        {
            "category":"Professional",
            "subcategory":"Accounting & Tax Preparation",
            "type":"Services"
        }
    ],
    "sg:phone":"+1 847 675 3272",
    "sg:postcode":"60076",
    "sg:province":"IL",
    "wof:name":"Wiseman & Cohen Numbers Inc",
    "wof:placetype":"venue"
},
  "geometry": {"coordinates":[-87.721268,42.036289],"type":"Point"}
}