{
  "type": "Feature",
  "properties": {
    "addr:full":"5652 N Western Ave Chicago IL 60659",
    "addr:housenumber":"5652",
    "addr:postcode":"60659",
    "addr:street":"N Western Ave",
    "iso:country":"US",
    "sg:address":"5652 N Western Ave",
    "sg:city":"Chicago",
    "sg:classifiers":[
        {
            "category":"Restaurant",
            "type":"Food & Drink"
        }
    ],
    "sg:phone":"+1   ",
    "sg:postcode":"60659",
    "sg:province":"IL",
    "sg:tags":[
        "drinking",
        "eating"
    ],
    "wof:name":"Edge Inn",
    "wof:placetype":"venue"
},
  "geometry": {"coordinates":[-87.689536,41.984022],"type":"Point"}
}