{
  "type": "Feature",
  "properties": {
    "addr:full":"1571 Sherman Ave Evanston IL 60201",
    "addr:housenumber":"1571",
    "addr:postcode":"60201",
    "addr:street":"Sherman Ave",
    "iso:country":"US",
    "sg:address":"1571 Sherman Ave",
    "sg:city":"Evanston",
    "sg:classifiers":[
        {
            "category":"Fast Food",
            "type":"Food & Drink"
        },
        {
            "category":"Restaurant",
            "type":"Food & Drink"
        }
    ],
    "sg:phone":"+1 847 864 3396",
    "sg:postcode":"60201",
    "sg:province":"IL",
    "sg:tags":[
        "hamburger",
        "dog",
        "lunch",
        "hot",
        "take",
        "brunch",
        "breakfast"
    ],
    "wof:name":"Edzo's Burger Shop",
    "wof:placetype":"venue"
},
  "geometry": {"coordinates":[-87.68187,42.046035],"type":"Point"}
}