{
  "type": "Feature",
  "properties": {
    "addr:full":"361 W Main St Albion IL 62806",
    "addr:housenumber":"361",
    "addr:postcode":"62806",
    "addr:street":"W Main St",
    "iso:country":"US",
    "sg:address":"361 W Main St",
    "sg:city":"Albion",
    "sg:classifiers":[
        {
            "category":"Education",
            "subcategory":"School",
            "type":"Public Place"
        }
    ],
    "sg:phone":"+1 618 445 2327",
    "sg:postcode":"62806",
    "sg:province":"IL",
    "wof:name":"Albion Grade School",
    "wof:placetype":"venue"
},
  "geometry": {"coordinates":[-88.06444999999999,38.376921],"type":"Point"}
}