{
  "type": "Feature",
  "properties": {
    "iso:country":"US",
    "sg:address":"2635 S Western Avenue",
    "sg:city":"Chicago",
    "sg:classifiers":[
        {
            "category":"Food & Beverages",
            "subcategory":"Meat & Fish",
            "type":"Retail Goods"
        }
    ],
    "sg:phone":"+1 773 254 8577",
    "sg:postcode":"60608",
    "sg:province":"IL",
    "sg:tags":[
        "shop"
    ],
    "wof:name":"L P I Distrubution",
    "wof:placetype":"venue"
},
  "geometry": {"coordinates":[-87.685256,41.84442],"type":"Point"}
}