{
  "type": "Feature",
  "properties": {
    "addr:full":"5900 159th St Oak Forest IL 60452",
    "addr:housenumber":"5900",
    "addr:postcode":"60452",
    "addr:street":"159Th St",
    "iso:country":"US",
    "sg:address":"5900 159th St",
    "sg:city":"Oak Forest",
    "sg:classifiers":[
        {
            "category":"Autos & Motor Vehicles",
            "subcategory":"Automobile Sales",
            "type":"Retail Goods"
        }
    ],
    "sg:phone":"+1 708 687 0400",
    "sg:postcode":"60452",
    "sg:province":"IL",
    "sg:tags":[
        "car",
        "dealer"
    ],
    "wof:name":"Community Pontiac Mazda",
    "wof:placetype":"venue"
},
  "geometry": {"coordinates":[-87.761126,41.602906],"type":"Point"}
}