{
  "type": "Feature",
  "properties": {
    "addr:full":"620 S Allen Ln Arlington Heights IL 60005",
    "addr:housenumber":"620",
    "addr:postcode":"60005",
    "addr:street":"S Allen Ln",
    "iso:country":"US",
    "sg:address":"620 S Allen Ln",
    "sg:city":"Arlington Heights",
    "sg:classifiers":[
        {
            "category":"Shopping",
            "subcategory":"Gifts & Souvenirs",
            "type":"Retail Goods"
        }
    ],
    "sg:phone":"+1   ",
    "sg:postcode":"60005",
    "sg:province":"IL",
    "wof:name":"Never Before Baskets",
    "wof:placetype":"venue"
},
  "geometry": {"coordinates":[-88.00138200000001,42.073588],"type":"Point"}
}