{
  "type": "Feature",
  "properties": {
    "iso:country":"US",
    "sg:address":"6364 N Sheridan Road",
    "sg:city":"Chicago",
    "sg:classifiers":[
        {
            "category":"Education",
            "subcategory":"School",
            "type":"Public Place"
        }
    ],
    "sg:phone":"+1 773 274 7970",
    "sg:postcode":"60660",
    "sg:province":"IL",
    "wof:name":"St Mary Alumna Assn",
    "wof:placetype":"venue"
},
  "geometry": {"coordinates":[-87.655811,41.998169],"type":"Point"}
}