{
  "type": "Feature",
  "properties": {
    "addr:full":"101 E Van Buren St Woodstock IL 60098",
    "addr:housenumber":"101",
    "addr:postcode":"60098",
    "addr:street":"E Van Buren St",
    "iso:country":"US",
    "sg:address":"101 E Van Buren St",
    "sg:city":"Woodstock",
    "sg:classifiers":[
        {
            "category":"Professional",
            "subcategory":"Lawyer & Legal Services",
            "type":"Services"
        }
    ],
    "sg:phone":"+1 815 338 1334",
    "sg:postcode":"60098",
    "sg:province":"IL",
    "sg:tags":[
        "attorney"
    ],
    "wof:name":"Hamer Schuh & Cuda",
    "wof:placetype":"venue"
},
  "geometry": {"coordinates":[-88.44740299999999,42.31435],"type":"Point"}
}