{
  "type": "Feature",
  "properties": {
    "iso:country":"US",
    "sg:address":"809 N Cedar Rd",
    "sg:city":"New Lenox",
    "sg:classifiers":[
        {
            "category":"Education",
            "subcategory":"School",
            "type":"Public Place"
        }
    ],
    "sg:phone":"+1 815 485 6150",
    "sg:postcode":"60451",
    "sg:province":"IL",
    "wof:name":"Oakview Junior High School",
    "wof:placetype":"venue"
},
  "geometry": {"coordinates":[-87.966109,41.520701],"type":"Point"}
}