{
  "type": "Feature",
  "properties": {
    "iso:country":"US",
    "sg:address":"9257 Franklin Ave",
    "sg:city":"Frankfort",
    "sg:classifiers":[
        {
            "category":"Building & Trades",
            "subcategory":"Construction",
            "type":"Services"
        }
    ],
    "sg:phone":"+1 815 469 3129",
    "sg:postcode":"60423",
    "sg:province":"IL",
    "sg:tags":[
        "house"
    ],
    "wof:name":"Richard Pedigo Construction",
    "wof:placetype":"venue"
},
  "geometry": {"coordinates":[-87.84094,41.502827],"type":"Point"}
}