{
  "type": "Feature",
  "properties": {
    "addr:full":"910 Martin Luther King Dr East Saint Louis IL 62201",
    "addr:housenumber":"910",
    "addr:postcode":"62201",
    "addr:street":"Martin Luther King Dr East",
    "iso:country":"US",
    "sg:address":"910 Martin Luther King Dr",
    "sg:city":"East Saint Louis",
    "sg:classifiers":[
        {
            "category":"Banks & Credit Unions",
            "subcategory":"Bank",
            "type":"Services"
        }
    ],
    "sg:phone":"+1 618 875 7000",
    "sg:postcode":"62201",
    "sg:province":"IL",
    "sg:tags":[
        "personal",
        "institution"
    ],
    "wof:name":"Stewart Finance Co of Illinois",
    "wof:placetype":"venue"
},
  "geometry": {"coordinates":[-90.15079799999999,38.624654],"type":"Point"}
}