{
  "type": "Feature",
  "properties": {
    "iso:country":"US",
    "sg:address":"1730 Larkdale Rd",
    "sg:city":"Northbrook",
    "sg:classifiers":[
        {
            "category":"Health Services",
            "subcategory":"Doctor",
            "type":"Services"
        }
    ],
    "sg:phone":"+1 312 787 9494",
    "sg:postcode":"60062",
    "sg:province":"IL",
    "sg:tags":[
        "physician",
        "surgeon"
    ],
    "wof:name":"Estela D Blei MD",
    "wof:placetype":"venue"
},
  "geometry": {"coordinates":[-87.845482,42.119746],"type":"Point"}
}