{
  "type": "Feature",
  "properties": {
    "addr:full":"8639 Riverside Ave Brookfield IL 60513",
    "addr:housenumber":"8639",
    "addr:postcode":"60513",
    "addr:street":"Riverside Ave",
    "iso:country":"US",
    "sg:address":"8639 Riverside Ave",
    "sg:city":"Brookfield",
    "sg:classifiers":[
        {
            "category":"Social Services",
            "subcategory":"Child Care",
            "type":"Services"
        }
    ],
    "sg:phone":"+1 708 387 9146",
    "sg:postcode":"60513",
    "sg:province":"IL",
    "sg:tags":[
        "day"
    ],
    "wof:name":"Rebekah M Pierce",
    "wof:placetype":"venue"
},
  "geometry": {"coordinates":[-87.83847799999999,41.822372],"type":"Point"}
}