{
  "type": "Feature",
  "properties": {
    "addr:full":"2950 Westridge Pl Carbondale IL 62901",
    "addr:housenumber":"2950",
    "addr:postcode":"62901",
    "addr:street":"Westridge Pl",
    "iso:country":"US",
    "sg:address":"2950 Westridge Pl",
    "sg:city":"Carbondale",
    "sg:classifiers":[
        {
            "category":"Health Services",
            "subcategory":"Nursing And Care Facility",
            "type":"Services"
        }
    ],
    "sg:phone":"+1 618 351 6557",
    "sg:postcode":"62901",
    "sg:province":"IL",
    "sg:tags":[
        "home",
        "retirement",
        "community",
        "government"
    ],
    "wof:name":"Liberty Village Of Carbondale",
    "wof:placetype":"venue"
},
  "geometry": {"coordinates":[-89.256714,37.733388],"type":"Point"}
}