{
  "type": "Feature",
  "properties": {
    "addr:full":"516 N Main St Kewanee IL 61443",
    "addr:housenumber":"516",
    "addr:postcode":"61443",
    "addr:street":"N Main St",
    "iso:country":"US",
    "sg:address":"516 N Main St",
    "sg:city":"Kewanee",
    "sg:classifiers":[
        {
            "category":"Recreation",
            "type":"Entertainment"
        },
        {
            "category":"Shopping",
            "subcategory":"Bicycles & Sporting Goods",
            "type":"Retail Goods"
        }
    ],
    "sg:phone":"+1 309 852 4760",
    "sg:postcode":"61443",
    "sg:province":"IL",
    "sg:tags":[
        "shop",
        "archery",
        "art",
        "shoes",
        "gift",
        "fishing",
        "tackle",
        "bait",
        "fine"
    ],
    "wof:name":"Northside Bait and Archery",
    "wof:placetype":"venue"
},
  "geometry": {"coordinates":[-89.924773,41.248931],"type":"Point"}
}