{
  "type": "Feature",
  "properties": {
    "addr:full":"1870 N Roselle Rd Schaumburg IL 60195",
    "addr:housenumber":"1870",
    "addr:postcode":"60195",
    "addr:street":"N Roselle Rd",
    "iso:country":"US",
    "sg:address":"1870 N Roselle Rd",
    "sg:city":"Schaumburg",
    "sg:classifiers":[
        {
            "category":"Health Services",
            "subcategory":"Doctor",
            "type":"Services"
        }
    ],
    "sg:phone":"+1 847 490 0060",
    "sg:postcode":"60195",
    "sg:province":"IL",
    "sg:tags":[
        "physician",
        "surgeon",
        "medical"
    ],
    "wof:name":"Francis S Cheng MD",
    "wof:placetype":"venue"
},
  "geometry": {"coordinates":[-88.079607,42.062313],"type":"Point"}
}