{
  "type": "Feature",
  "properties": {
    "addr:full":"7895 159th St Tinley Park IL 60477",
    "addr:housenumber":"7895",
    "addr:postcode":"60477",
    "addr:street":"159Th St",
    "iso:country":"US",
    "sg:address":"7895 159th St",
    "sg:city":"Tinley Park",
    "sg:classifiers":[
        {
            "category":"Health Services",
            "subcategory":"Doctor",
            "type":"Services"
        }
    ],
    "sg:phone":"+1 708 429 7373",
    "sg:postcode":"60477",
    "sg:province":"IL",
    "sg:tags":[
        "osteopathic"
    ],
    "wof:name":"Tinley Community Medical",
    "wof:placetype":"venue"
},
  "geometry": {"coordinates":[-87.811154,41.601947],"type":"Point"}
}