{
  "type": "Feature",
  "properties": {
    "addr:full":"612 White Pine Rd Buffalo Grove IL 60089",
    "addr:housenumber":"612",
    "addr:postcode":"60089",
    "addr:street":"White Pine Rd",
    "iso:country":"US",
    "sg:address":"612 White Pine Rd",
    "sg:city":"Buffalo Grove",
    "sg:classifiers":[
        {
            "category":"Professional",
            "subcategory":"Management & Consulting",
            "type":"Services"
        }
    ],
    "sg:phone":"+1 847 459 9189",
    "sg:postcode":"60089",
    "sg:province":"IL",
    "wof:name":"Tyson Consulting Group",
    "wof:placetype":"venue"
},
  "geometry": {"coordinates":[-87.97418399999999,42.143195],"type":"Point"}
}