{
  "type": "Feature",
  "properties": {
    "addr:full":"3423 N Southport Ave Chicago IL 60657",
    "addr:housenumber":"3423",
    "addr:postcode":"60657",
    "addr:street":"N Southport Ave",
    "iso:country":"US",
    "sg:address":"3423 N Southport Ave",
    "sg:city":"Chicago",
    "sg:classifiers":[
        {
            "category":"Restaurant",
            "type":"Food & Drink"
        }
    ],
    "sg:menulink":"http://www.allmenus.com/il/chicago/21162-coobah/menu/",
    "sg:phone":"+1 773 528 2220",
    "sg:postcode":"60657",
    "sg:province":"IL",
    "sg:tags":[
        "jamaican",
        "spanish"
    ],
    "wof:name":"Coobah",
    "wof:placetype":"venue"
},
  "geometry": {"coordinates":[-87.66394,41.944093],"type":"Point"}
}