{
  "type": "Feature",
  "properties": {
    "iso:country":"US",
    "sg:address":"353 E Burlington St Ste 100",
    "sg:city":"Riverside",
    "sg:classifiers":[
        {
            "category":"Health Services",
            "subcategory":"Doctor",
            "type":"Services"
        }
    ],
    "sg:phone":"+1 708 442 0221",
    "sg:postcode":"60546",
    "sg:province":"IL",
    "wof:name":"Ho Erling MD",
    "wof:placetype":"venue"
},
  "geometry": {"coordinates":[-87.804357,41.831304],"type":"Point"}
}