{
  "type": "Feature",
  "properties": {
    "iso:country":"US",
    "sg:address":"1000 Wellington Ave",
    "sg:city":"Elk Grove Village",
    "sg:classifiers":[
        {
            "category":"Personal",
            "type":"Services"
        }
    ],
    "sg:phone":"+1   ",
    "sg:postcode":"60007",
    "sg:province":"IL",
    "sg:tags":[
        "eating"
    ],
    "wof:name":"Garden Terrace Banquets",
    "wof:placetype":"venue"
},
  "geometry": {"coordinates":[-88.008713,42.001041],"type":"Point"}
}