{
  "type": "Feature",
  "properties": {
    "addr:full":"41055 N State Rte 83 Antioch IL 60002",
    "addr:housenumber":"41055",
    "addr:postcode":"60002",
    "addr:street":"N State Rte 83",
    "iso:country":"US",
    "sg:address":"41055 N State Rte 83",
    "sg:city":"Antioch",
    "sg:classifiers":[
        {
            "category":"Home & Garden",
            "subcategory":"Carpets & Floor Coverings",
            "type":"Retail Goods"
        }
    ],
    "sg:phone":"+1   ",
    "sg:postcode":"60002",
    "sg:province":"IL",
    "wof:name":"Lakes Company Inc",
    "wof:placetype":"venue"
},
  "geometry": {"coordinates":[-88.09175999999999,42.459613],"type":"Point"}
}