{
  "type": "Feature",
  "properties": {
    "iso:country":"US",
    "sg:address":"6947 Cermak Rd",
    "sg:city":"Berwyn",
    "sg:classifiers":[
        {
            "category":"Retail",
            "subcategory":"Self-service Laundry",
            "type":"Services"
        }
    ],
    "sg:phone":"+1 708 749 1986",
    "sg:postcode":"60402",
    "sg:province":"IL",
    "sg:tags":[
        "coin"
    ],
    "wof:name":"Laundry World Company",
    "wof:placetype":"venue"
},
  "geometry": {"coordinates":[-87.798153,41.85041],"type":"Point"}
}