{
  "type": "Feature",
  "properties": {
    "iso:country":"US",
    "sg:address":"60 E 36th Pl",
    "sg:city":"Chicago",
    "sg:classifiers":[
        {
            "category":"Real Estate",
            "subcategory":"Real Estate Operator",
            "type":"Services"
        }
    ],
    "sg:phone":"+1 773 268 4811",
    "sg:postcode":"60653",
    "sg:province":"IL",
    "sg:tags":[
        "building",
        "apartment"
    ],
    "wof:name":"Meds Apartments Inc",
    "wof:placetype":"venue"
},
  "geometry": {"coordinates":[-87.624662,41.828812],"type":"Point"}
}