{
  "type": "Feature",
  "properties": {
    "iso:country":"US",
    "sg:address":"1726 Johnson Ave",
    "sg:city":"Rockford",
    "sg:classifiers":[
        {
            "category":"Building & Trades",
            "subcategory":"Plumbing",
            "type":"Services"
        }
    ],
    "sg:phone":"+1 815 229 8599",
    "sg:postcode":"61109",
    "sg:province":"IL",
    "sg:tags":[
        "septic"
    ],
    "wof:name":"Watson Septic Plbg & Repair",
    "wof:placetype":"venue"
},
  "geometry": {"coordinates":[-89.067964,42.224628],"type":"Point"}
}