{
  "type": "Feature",
  "properties": {
    "iso:country":"US",
    "sg:address":"601 Acorn Ct",
    "sg:city":"Antioch",
    "sg:classifiers":[
        {
            "category":"Manufacturing",
            "subcategory":"Tools & Machinery",
            "type":"Manufacturing & Wholesale Goods"
        }
    ],
    "sg:phone":"+1 414 570 9530",
    "sg:postcode":"60002",
    "sg:province":"IL",
    "sg:tags":[
        "machine",
        "ma",
        "industrial",
        "rebuilds"
    ],
    "wof:name":"3 S Incorporated",
    "wof:placetype":"venue"
},
  "geometry": {"coordinates":[-88.119914,42.487353],"type":"Point"}
}