{
  "type": "Feature",
  "properties": {
    "addr:full":"2736 19th St Rockford IL 61109",
    "addr:housenumber":"2736",
    "addr:postcode":"61109",
    "addr:street":"19Th St",
    "iso:country":"US",
    "sg:address":"2736 19th St",
    "sg:city":"Rockford",
    "sg:classifiers":[
        {
            "category":"Autos & Motor Vehicles",
            "subcategory":"Automobile Sales",
            "type":"Retail Goods"
        }
    ],
    "sg:phone":"+1 815 968 1944",
    "sg:postcode":"61109",
    "sg:province":"IL",
    "sg:tags":[
        "car",
        "dealer"
    ],
    "wof:name":"Carlos Auto Sales",
    "wof:placetype":"venue"
},
  "geometry": {"coordinates":[-89.05876000000001,42.235051],"type":"Point"}
}