{
  "type": "Feature",
  "properties": {
    "addr:full":"1570 Orchard St Des Plaines IL 60018",
    "addr:housenumber":"1570",
    "addr:postcode":"60018",
    "addr:street":"Orchard St",
    "iso:country":"US",
    "sg:address":"1570 Orchard St",
    "sg:city":"Des Plaines",
    "sg:classifiers":[
        {
            "category":"Autos & Motor Vehicles",
            "subcategory":"Auto Supplies",
            "type":"Retail Goods"
        }
    ],
    "sg:phone":"+1 847 824 2760",
    "sg:postcode":"60018",
    "sg:province":"IL",
    "sg:tags":[
        "automobile",
        "alarm"
    ],
    "wof:name":"Audiomex",
    "wof:placetype":"venue"
},
  "geometry": {"coordinates":[-87.882113,42.025118],"type":"Point"}
}