{
  "type": "Feature",
  "properties": {
    "iso:country":"US",
    "sg:address":"285 Hidden Creek Rd",
    "sg:city":"Lake Zurich",
    "sg:classifiers":[
        {
            "category":"Building & Trades",
            "subcategory":"Equipment Rental",
            "type":"Services"
        }
    ],
    "sg:phone":"+1 847 550 6274",
    "sg:postcode":"60047",
    "sg:province":"IL",
    "sg:tags":[
        "party",
        "supply"
    ],
    "wof:name":"Senor Margarita Inc",
    "wof:placetype":"venue"
},
  "geometry": {"coordinates":[-88.065879,42.192211],"type":"Point"}
}