{
  "type": "Feature",
  "properties": {
    "iso:country":"US",
    "sg:address":"805 S Bartlett Rd",
    "sg:city":"Bartlett",
    "sg:classifiers":[
        {
            "category":"Insurance",
            "subcategory":"Insurance Agent",
            "type":"Services"
        },
        {
            "category":"Insurance",
            "subcategory":"Hazard Insurance",
            "type":"Services"
        },
        {
            "category":"Insurance",
            "subcategory":"Title Insurance",
            "type":"Services"
        }
    ],
    "sg:phone":"+1 630 289 6200",
    "sg:postcode":"60103",
    "sg:province":"IL",
    "sg:tags":[
        "auto",
        "homeowner"
    ],
    "sg:website":"http://apps.amfam.com/agentlocator/RDECANIO?sourceid=yp3",
    "wof:name":"American Family Insurance- Robert Decanio",
    "wof:placetype":"venue"
},
  "geometry": {"coordinates":[-88.18364699999999,41.979099],"type":"Point"}
}