{
  "type": "Feature",
  "properties": {
    "iso:country":"US",
    "sg:address":"4432 N Ravenswood Ave",
    "sg:city":"Chicago",
    "sg:classifiers":[
        {
            "category":"Education",
            "subcategory":"School",
            "type":"Public Place"
        }
    ],
    "sg:phone":"+1 773 506 7140",
    "sg:postcode":"60640",
    "sg:province":"IL",
    "sg:website":"www.barrelofmonkeys.org",
    "wof:name":"Barrel of Monkeys Productions",
    "wof:placetype":"venue"
},
  "geometry": {"coordinates":[-87.674899,41.962513],"type":"Point"}
}