{
  "type": "Feature",
  "properties": {
    "iso:country":"US",
    "sg:address":"1500 S Western Ave Ste 12",
    "sg:city":"Chicago",
    "sg:classifiers":[
        {
            "category":"Retail",
            "subcategory":"Repair Shop",
            "type":"Services"
        }
    ],
    "sg:phone":"+1 312 733 1098",
    "sg:postcode":"60608",
    "sg:province":"IL",
    "sg:tags":[
        "upholsterer"
    ],
    "wof:name":"Lenova, Inc.",
    "wof:placetype":"venue"
},
  "geometry": {"coordinates":[-87.685883,41.861179],"type":"Point"}
}