{
  "type": "Feature",
  "properties": {
    "addr:full":"6314 N Claremont Ave Chicago IL 60659",
    "addr:housenumber":"6314",
    "addr:postcode":"60659",
    "addr:street":"N Claremont Ave",
    "iso:country":"US",
    "sg:address":"6314 N Claremont Ave",
    "sg:city":"Chicago",
    "sg:classifiers":[
        {
            "category":"Building & Trades",
            "subcategory":"Construction",
            "type":"Services"
        }
    ],
    "sg:phone":"+1 773 457 7281",
    "sg:postcode":"60659",
    "sg:province":"IL",
    "sg:tags":[
        "roofing",
        "contractor"
    ],
    "wof:name":"Brother Roofing",
    "wof:placetype":"venue"
},
  "geometry": {"coordinates":[-87.68871799999999,41.997036],"type":"Point"}
}