{
  "type": "Feature",
  "properties": {
    "iso:country":"US",
    "sg:address":"3454 W Devon Ave",
    "sg:city":"Lincolnwood",
    "sg:classifiers":[
        {
            "category":"Banks & Credit Unions",
            "subcategory":"Investment Brokerage",
            "type":"Services"
        }
    ],
    "sg:phone":"+1 847 675 5787",
    "sg:postcode":"60712",
    "sg:province":"IL",
    "sg:tags":[
        "tape",
        "video",
        "sale",
        "dvds-rental"
    ],
    "wof:name":"Movie King",
    "wof:placetype":"venue"
},
  "geometry": {"coordinates":[-87.715878,41.997311],"type":"Point"}
}