{
  "type": "Feature",
  "properties": {
    "iso:country":"US",
    "sg:address":"12740 S Aberdeen St",
    "sg:city":"Riverdale",
    "sg:classifiers":[
        {
            "category":"Professional",
            "subcategory":"Secretarial Services",
            "type":"Services"
        }
    ],
    "sg:phone":"+1 708 385 2118",
    "sg:postcode":"60827",
    "sg:province":"IL",
    "sg:tags":[
        "court",
        "monitor"
    ],
    "wof:name":"Josephine G Brown",
    "wof:placetype":"venue"
},
  "geometry": {"coordinates":[-87.648705,41.660489],"type":"Point"}
}