{
  "type": "Feature",
  "properties": {
    "addr:full":"102 W Lawn St Rushville IL 62681",
    "addr:housenumber":"102",
    "addr:postcode":"62681",
    "addr:street":"W Lawn St",
    "iso:country":"US",
    "sg:address":"102 W Lawn St",
    "sg:city":"Rushville",
    "sg:classifiers":[
        {
            "category":"Building & Trades",
            "subcategory":"Construction",
            "type":"Services"
        }
    ],
    "sg:phone":"+1 217 322 3117",
    "sg:postcode":"62681",
    "sg:province":"IL",
    "sg:tags":[
        "roofing",
        "contractor"
    ],
    "wof:name":"Cassady Roofing Co",
    "wof:placetype":"venue"
},
  "geometry": {"coordinates":[-90.57495,40.121551],"type":"Point"}
}