{
  "type": "Feature",
  "properties": {
    "iso:country":"US",
    "sg:address":"4119 Memorial Dr",
    "sg:city":"Belleville",
    "sg:classifiers":[
        {
            "category":"Building & Trades",
            "subcategory":"Construction",
            "type":"Services"
        }
    ],
    "sg:phone":"+1 618 235 4342",
    "sg:postcode":"62226",
    "sg:province":"IL",
    "sg:tags":[
        "house"
    ],
    "wof:name":"Lewis General Home Repair",
    "wof:placetype":"venue"
},
  "geometry": {"coordinates":[-90.015118,38.548926],"type":"Point"}
}