{
  "type": "Feature",
  "properties": {
    "iso:country":"US",
    "sg:address":"980 E Northwest Hwy",
    "sg:city":"Mount Prospect",
    "sg:classifiers":[
        {
            "category":"Professional",
            "subcategory":"Lawyer & Legal Services",
            "type":"Services"
        }
    ],
    "sg:phone":"+1 847 259 7774",
    "sg:postcode":"60056",
    "sg:province":"IL",
    "wof:name":"Petrucelli Leonard J",
    "wof:placetype":"venue"
},
  "geometry": {"coordinates":[-87.924248,42.058011],"type":"Point"}
}