{
  "type": "Feature",
  "properties": {
    "addr:full":"15120 127th St Lemont IL 60439",
    "addr:housenumber":"15120",
    "addr:postcode":"60439",
    "addr:street":"127Th St",
    "iso:country":"US",
    "sg:address":"15120 127th St",
    "sg:city":"Lemont",
    "sg:classifiers":[
        {
            "category":"Building & Trades",
            "subcategory":"Electrical",
            "type":"Services"
        }
    ],
    "sg:phone":"+1 630 257 9096",
    "sg:postcode":"60439",
    "sg:province":"IL",
    "sg:tags":[
        "security",
        "electrical",
        "system",
        "contractor"
    ],
    "wof:name":"Inner Security Systems Inc",
    "wof:placetype":"venue"
},
  "geometry": {"coordinates":[-87.98877299999999,41.656734],"type":"Point"}
}