{
  "type": "Feature",
  "properties": {
    "iso:country":"US",
    "sg:address":"18250 Hickory Cross Rd",
    "sg:city":"Virginia",
    "sg:phone":"+1 217 452 3216",
    "sg:postcode":"62691",
    "sg:province":"IL",
    "sg:tags":[
        "farm",
        "grain",
        "cash"
    ],
    "wof:name":"Ring Angus Farm",
    "wof:placetype":"venue"
},
  "geometry": {"coordinates":[-90.236255,39.989687],"type":"Point"}
}