{
  "type": "Feature",
  "properties": {
    "iso:country":"US",
    "sg:address":"5159 N Clark St",
    "sg:city":"Chicago",
    "sg:classifiers":[
        {
            "category":"Building & Trades",
            "subcategory":"Locksmith",
            "type":"Services"
        }
    ],
    "sg:phone":"+1 773 681 9033",
    "sg:postcode":"60640",
    "sg:province":"IL",
    "sg:tags":[
        "key"
    ],
    "wof:name":"1 Action Lock and Key",
    "wof:placetype":"venue"
},
  "geometry": {"coordinates":[-87.668201,41.975685],"type":"Point"}
}