{
  "type": "Feature",
  "properties": {
    "addr:full":"346 N Winston Dr Palatine IL 60074",
    "addr:housenumber":"346",
    "addr:postcode":"60074",
    "addr:street":"N Winston Dr",
    "iso:country":"US",
    "sg:address":"346 N Winston Dr",
    "sg:city":"Palatine",
    "sg:classifiers":[
        {
            "category":"Professional",
            "subcategory":"Management & Consulting",
            "type":"Services"
        }
    ],
    "sg:phone":"+1 847 359 9517",
    "sg:postcode":"60074",
    "sg:province":"IL",
    "sg:tags":[
        "business"
    ],
    "wof:name":"Glen Phelan",
    "wof:placetype":"venue"
},
  "geometry": {"coordinates":[-88.011561,42.116095],"type":"Point"}
}