{
  "type": "Feature",
  "properties": {
    "iso:country":"US",
    "sg:address":"21 W Railroad Ave",
    "sg:city":"Palatine",
    "sg:classifiers":[
        {
            "category":"Retail",
            "subcategory":"Portrait Studio",
            "type":"Services"
        }
    ],
    "sg:phone":"+1 847 991 4840",
    "sg:postcode":"60067",
    "sg:province":"IL",
    "sg:tags":[
        "photographer"
    ],
    "wof:name":"Studio One Photography",
    "wof:placetype":"venue"
},
  "geometry": {"coordinates":[-88.044183,42.111257],"type":"Point"}
}