{
  "type": "Feature",
  "properties": {
    "iso:country":"US",
    "sg:address":"1507 Chicago Ave",
    "sg:city":"Evanston",
    "sg:classifiers":[
        {
            "category":"Autos & Motor Vehicles",
            "subcategory":"Automobile Sales",
            "type":"Retail Goods"
        }
    ],
    "sg:phone":"+1 847 869 7803",
    "sg:postcode":"60201",
    "sg:province":"IL",
    "sg:tags":[
        "car",
        "dealer"
    ],
    "wof:name":"Auto Alert",
    "wof:placetype":"venue"
},
  "geometry": {"coordinates":[-87.679803,42.045699],"type":"Point"}
}