{
  "type": "Feature",
  "properties": {
    "addr:full":"1820 Ridge Rd Homewood IL 60430",
    "addr:housenumber":"1820",
    "addr:postcode":"60430",
    "addr:street":"Ridge Rd",
    "iso:country":"US",
    "sg:address":"1820 Ridge Rd",
    "sg:city":"Homewood",
    "sg:classifiers":[
        {
            "category":"Sports & Exercise",
            "subcategory":"Gym",
            "type":"Entertainment"
        }
    ],
    "sg:phone":"+1 708 206 3243",
    "sg:postcode":"60430",
    "sg:province":"IL",
    "sg:tags":[
        "facility",
        "club",
        "gymnasium",
        "health",
        "fitness",
        "studio",
        "physical"
    ],
    "wof:name":"Body Mechanics",
    "wof:placetype":"venue"
},
  "geometry": {"coordinates":[-87.661036,41.561499],"type":"Point"}
}