{
  "type": "Feature",
  "properties": {
    "iso:country":"US",
    "sg:address":"811 W Williams St",
    "sg:city":"Danville",
    "sg:classifiers":[
        {
            "category":"Personal",
            "subcategory":"Barber",
            "type":"Services"
        }
    ],
    "sg:phone":"+1 217 431 0751",
    "sg:postcode":"61832",
    "sg:province":"IL",
    "wof:name":"Ricardo Giuliani",
    "wof:placetype":"venue"
},
  "geometry": {"coordinates":[-87.641402,40.134014],"type":"Point"}
}