{
  "type": "Feature",
  "properties": {
    "addr:full":"1403 Chateaugay Dr Spring Grove IL 60081",
    "addr:housenumber":"1403",
    "addr:postcode":"60081",
    "addr:street":"Chateaugay Dr",
    "iso:country":"US",
    "sg:address":"1403 Chateaugay Dr",
    "sg:city":"Spring Grove",
    "sg:classifiers":[
        {
            "category":"Building & Trades",
            "subcategory":"Construction",
            "type":"Services"
        }
    ],
    "sg:phone":"+1 815 675 3423",
    "sg:postcode":"60081",
    "sg:province":"IL",
    "sg:tags":[
        "house"
    ],
    "wof:name":"R Palluck Builders",
    "wof:placetype":"venue"
},
  "geometry": {"coordinates":[-88.223719,42.471464],"type":"Point"}
}