{
  "type": "Feature",
  "properties": {
    "iso:country":"US",
    "sg:address":"909 E Rexford St",
    "sg:city":"Centralia",
    "sg:classifiers":[
        {
            "category":"Social Services",
            "type":"Services"
        }
    ],
    "sg:phone":"+1 618 533 1013",
    "sg:postcode":"62801",
    "sg:province":"IL",
    "sg:tags":[
        "organization",
        "welfare"
    ],
    "wof:name":"BCMW Headstart Ctr",
    "wof:placetype":"venue"
},
  "geometry": {"coordinates":[-89.123569,38.532614],"type":"Point"}
}