{
  "type": "Feature",
  "properties": {
    "iso:country":"US",
    "sg:address":"4850 W Belmont Avenue",
    "sg:city":"Chicago",
    "sg:classifiers":[
        {
            "category":"Shopping",
            "subcategory":"Crafts & Fabrics",
            "type":"Retail Goods"
        }
    ],
    "sg:phone":"+1 773 282 2247",
    "sg:postcode":"60641",
    "sg:province":"IL",
    "sg:tags":[
        "art",
        "supply"
    ],
    "wof:name":"Jannes Fine Arts",
    "wof:placetype":"venue"
},
  "geometry": {"coordinates":[-87.748915,41.93882],"type":"Point"}
}