{
  "type": "Feature",
  "properties": {
    "iso:country":"US",
    "sg:address":"1038 N Ashland Avenue",
    "sg:city":"Chicago",
    "sg:classifiers":[
        {
            "category":"Wholesale",
            "subcategory":"Computers",
            "type":"Manufacturing & Wholesale Goods"
        }
    ],
    "sg:phone":"+1 773 384 8300",
    "sg:postcode":"60622",
    "sg:province":"IL",
    "wof:name":"Digilog Electronics",
    "wof:placetype":"venue"
},
  "geometry": {"coordinates":[-87.66735799999999,41.900918],"type":"Point"}
}