{
  "type": "Feature",
  "properties": {
    "iso:country":"US",
    "sg:address":"250 Houston St",
    "sg:city":"Batavia",
    "sg:classifiers":[
        {
            "category":"Health Services",
            "subcategory":"Chiropractor",
            "type":"Services"
        }
    ],
    "sg:phone":"+1 630 309 0766",
    "sg:postcode":"60510",
    "sg:province":"IL",
    "wof:name":"Foxx Chiropractic",
    "wof:placetype":"venue"
},
  "geometry": {"coordinates":[-88.311659,41.851041],"type":"Point"}
}