{
  "type": "Feature",
  "properties": {
    "iso:country":"US",
    "sg:address":"6315 S Narragansett Avenue",
    "sg:city":"Chicago",
    "sg:classifiers":[
        {
            "category":"Real Estate",
            "subcategory":"Real Estate Services",
            "type":"Services"
        },
        {
            "category":"Real Estate",
            "subcategory":"Real Estate Agent",
            "type":"Services"
        }
    ],
    "sg:phone":"+1 773 229 0795",
    "sg:postcode":"60638",
    "sg:province":"IL",
    "sg:tags":[
        "management",
        "property"
    ],
    "wof:name":"Gv Properties of Illinois",
    "wof:placetype":"venue"
},
  "geometry": {"coordinates":[-87.781057,41.777426],"type":"Point"}
}