{
  "type": "Feature",
  "properties": {
    "addr:full":"4509 S Michigan Ave Chicago IL 60653",
    "addr:housenumber":"4509",
    "addr:postcode":"60653",
    "addr:street":"S Michigan Ave",
    "iso:country":"US",
    "sg:address":"4509 S Michigan Ave",
    "sg:city":"Chicago",
    "sg:classifiers":[
        {
            "category":"Manufacturing",
            "subcategory":"Retail Goods",
            "type":"Manufacturing & Wholesale Goods"
        }
    ],
    "sg:phone":"+1 773 538 4747",
    "sg:postcode":"60653",
    "sg:province":"IL",
    "sg:tags":[
        "manufacturer"
    ],
    "wof:name":"Fikr Industries",
    "wof:placetype":"venue"
},
  "geometry": {"coordinates":[-87.62281299999999,41.811264],"type":"Point"}
}