{
  "type": "Feature",
  "properties": {
    "addr:full":"10619 Main St Roscoe IL 61073",
    "addr:housenumber":"10619",
    "addr:postcode":"61073",
    "addr:street":"Main St",
    "iso:country":"US",
    "sg:address":"10619 Main St",
    "sg:city":"Roscoe",
    "sg:classifiers":[
        {
            "category":"Professional",
            "subcategory":"Detective & Security Services",
            "type":"Services"
        }
    ],
    "sg:phone":"+1 815 623 9063",
    "sg:postcode":"61073",
    "sg:province":"IL",
    "sg:tags":[
        "information",
        "bureau"
    ],
    "wof:name":"Illinois Driver Services Department, Ros",
    "wof:placetype":"venue"
},
  "geometry": {"coordinates":[-89.00952100000001,42.414392],"type":"Point"}
}