{
  "type": "Feature",
  "properties": {
    "addr:full":"1012 Bangs St Aurora IL 60505",
    "addr:housenumber":"1012",
    "addr:postcode":"60505",
    "addr:street":"Bangs St",
    "iso:country":"US",
    "sg:address":"1012 Bangs St",
    "sg:city":"Aurora",
    "sg:classifiers":[
        {
            "category":"Personal",
            "subcategory":"Beauty Salon",
            "type":"Services"
        }
    ],
    "sg:phone":"+1 630 898 4552",
    "sg:postcode":"60505",
    "sg:province":"IL",
    "sg:tags":[
        "shop"
    ],
    "wof:name":"Lords & Ladies",
    "wof:placetype":"venue"
},
  "geometry": {"coordinates":[-88.304306,41.735922],"type":"Point"}
}