{
  "type": "Feature",
  "properties": {
    "iso:country":"US",
    "sg:address":"519 Marchesano Dr",
    "sg:city":"Rockford",
    "sg:classifiers":[
        {
            "category":"Food & Beverages",
            "subcategory":"Groceries & Convenience Stores",
            "type":"Retail Goods"
        }
    ],
    "sg:phone":"+1 815 968 8178",
    "sg:postcode":"61102",
    "sg:province":"IL",
    "sg:tags":[
        "grocer"
    ],
    "wof:name":"One-Stop Foods",
    "wof:placetype":"venue"
},
  "geometry": {"coordinates":[-89.106602,42.251385],"type":"Point"}
}