{
  "type": "Feature",
  "properties": {
    "addr:full":"19001 Cicero Ave Country Club Hls IL 60478",
    "addr:housenumber":"19001",
    "addr:postcode":"60478",
    "addr:street":"Cicero Ave",
    "iso:country":"US",
    "sg:address":"19001 Cicero Ave",
    "sg:city":"Country Club Hls",
    "sg:classifiers":[
        {
            "category":"Social Services",
            "subcategory":"Child Care",
            "type":"Services"
        }
    ],
    "sg:phone":"+1 708 798 5937",
    "sg:postcode":"60478",
    "sg:province":"IL",
    "wof:name":"Academy Of Learning Inc",
    "wof:placetype":"venue"
},
  "geometry": {"coordinates":[-87.732626,41.544012],"type":"Point"}
}