{
  "type": "Feature",
  "properties": {
    "iso:country":"US",
    "sg:address":"1055 Paramount Pkwy",
    "sg:city":"Batavia",
    "sg:classifiers":[
        {
            "category":"Manufacturing",
            "subcategory":"Tools & Machinery",
            "type":"Manufacturing & Wholesale Goods"
        },
        {
            "category":"Manufacturing",
            "subcategory":"Rubber & Plastics",
            "type":"Manufacturing & Wholesale Goods"
        }
    ],
    "sg:phone":"+1 630 406 8982",
    "sg:postcode":"60510",
    "sg:province":"IL",
    "sg:tags":[
        "repair",
        "industrial",
        "general",
        "auto",
        "mfg"
    ],
    "wof:name":"M R Alsobrook Inc",
    "wof:placetype":"venue"
},
  "geometry": {"coordinates":[-88.27178600000001,41.860582],"type":"Point"}
}