{
  "type": "Feature",
  "properties": {
    "iso:country":"US",
    "sg:address":"319 N Seymour Ave",
    "sg:city":"Mundelein",
    "sg:classifiers":[
        {
            "category":"Health Services",
            "subcategory":"Chiropractor",
            "type":"Services"
        },
        {
            "category":"Health Services",
            "subcategory":"Doctor",
            "type":"Services"
        }
    ],
    "sg:phone":"+1 847 949 8882",
    "sg:postcode":"60060",
    "sg:province":"IL",
    "sg:tags":[
        "physician",
        "surgeon"
    ],
    "wof:name":"Family Chiropractor",
    "wof:placetype":"venue"
},
  "geometry": {"coordinates":[-88.002458,42.269368],"type":"Point"}
}