{
  "type": "Feature",
  "properties": {
    "iso:country":"US",
    "sg:address":"319 E Central Ave",
    "sg:city":"Atwood",
    "sg:classifiers":[
        {
            "category":"Freight",
            "type":"Transportation"
        }
    ],
    "sg:phone":"+1 217 578 2213",
    "sg:postcode":"61913",
    "sg:province":"IL",
    "sg:tags":[
        "grain",
        "elevator"
    ],
    "wof:name":"Topflight Grain Co",
    "wof:placetype":"venue"
},
  "geometry": {"coordinates":[-88.458483,39.799796],"type":"Point"}
}