{
  "type": "Feature",
  "properties": {
    "iso:country":"US",
    "sg:address":"810 W Springfield Ave",
    "sg:city":"Champaign",
    "sg:classifiers":[
        {
            "category":"Professional",
            "subcategory":"Employment Agencies",
            "type":"Services"
        }
    ],
    "sg:phone":"+1 217 352 7875",
    "sg:postcode":"61820",
    "sg:province":"IL",
    "wof:name":"Manpower",
    "wof:placetype":"venue"
},
  "geometry": {"coordinates":[-88.256798,40.112598],"type":"Point"}
}