{
  "type": "Feature",
  "properties": {
    "iso:country":"US",
    "sg:address":"5240 N Pulaski Rd Ste H",
    "sg:city":"Chicago",
    "sg:classifiers":[
        {
            "category":"Food & Beverages",
            "subcategory":"Bakery",
            "type":"Retail Goods"
        }
    ],
    "sg:phone":"+1 773 478 3665",
    "sg:postcode":"60630",
    "sg:province":"IL",
    "sg:tags":[
        "sandwich"
    ],
    "wof:name":"Subway",
    "wof:placetype":"venue"
},
  "geometry": {"coordinates":[-87.72820299999999,41.9762],"type":"Point"}
}