{
  "type": "Feature",
  "properties": {
    "iso:country":"US",
    "sg:address":"3170 N Sheridan Rd",
    "sg:city":"Chicago",
    "sg:classifiers":[
        {
            "category":"Real Estate",
            "subcategory":"Real Estate Operator",
            "type":"Services"
        }
    ],
    "sg:phone":"+1 773 248 2100",
    "sg:postcode":"60657",
    "sg:province":"IL",
    "sg:tags":[
        "professional",
        "apartment"
    ],
    "sg:website":"www.belmonthouse.com",
    "wof:name":"Belmont House",
    "wof:placetype":"venue"
},
  "geometry": {"coordinates":[-87.639539,41.939525],"type":"Point"}
}