{
  "type": "Feature",
  "properties": {
    "iso:country":"US",
    "sg:address":"75 Tri State Intl",
    "sg:city":"Lincolnshire",
    "sg:classifiers":[
        {
            "category":"Banks & Credit Unions",
            "subcategory":"Financial Services",
            "type":"Services"
        }
    ],
    "sg:phone":"+1 847 374 6300",
    "sg:postcode":"60069",
    "sg:province":"IL",
    "sg:tags":[
        "franchising"
    ],
    "wof:name":"KDD Sarpino's Of Illinois",
    "wof:placetype":"venue"
},
  "geometry": {"coordinates":[-87.890524,42.196904],"type":"Point"}
}