{
  "type": "Feature",
  "properties": {
    "iso:country":"US",
    "sg:address":"1025 W Everett Rd",
    "sg:city":"Lake Forest",
    "sg:classifiers":[
        {
            "category":"Real Estate",
            "subcategory":"Real Estate Agent",
            "type":"Services"
        }
    ],
    "sg:phone":"+1 847 234 3800",
    "sg:postcode":"60045",
    "sg:province":"IL",
    "sg:tags":[
        "broker"
    ],
    "sg:website":"www.coldwellbankeronline.com",
    "wof:name":"Coldwell Banker",
    "wof:placetype":"venue"
},
  "geometry": {"coordinates":[-87.87358399999999,42.221812],"type":"Point"}
}