{
  "type": "Feature",
  "properties": {
    "iso:country":"US",
    "sg:address":"1099 Touhy Ave",
    "sg:city":"Elk Grove Vlg",
    "sg:classifiers":[
        {
            "category":"Manufacturing",
            "subcategory":"Tools & Machinery",
            "type":"Manufacturing & Wholesale Goods"
        }
    ],
    "sg:phone":"+1 847 806 1901",
    "sg:postcode":"60007",
    "sg:province":"IL",
    "sg:tags":[
        "machine",
        "shop"
    ],
    "wof:name":"Commercial Machine Svc Inc",
    "wof:placetype":"venue"
},
  "geometry": {"coordinates":[-87.975496,42.007262],"type":"Point"}
}