{
  "type": "Feature",
  "properties": {
    "iso:country":"US",
    "sg:address":"9715 State Rte 34 N",
    "sg:city":"Galatia",
    "sg:classifiers":[
        {
            "category":"Retail",
            "subcategory":"Auto Repair",
            "type":"Services"
        }
    ],
    "sg:phone":"+1 618 268 6910",
    "sg:postcode":"62935",
    "sg:province":"IL",
    "sg:tags":[
        "repairing",
        "automobile"
    ],
    "wof:name":"Peyton Automotive Repair",
    "wof:placetype":"venue"
},
  "geometry": {"coordinates":[-88.599898,37.839319],"type":"Point"}
}