{
  "type": "Feature",
  "properties": {
    "addr:full":"1669 N Vine St Chicago IL 60614",
    "addr:housenumber":"1669",
    "addr:postcode":"60614",
    "addr:street":"N Vine St",
    "iso:country":"US",
    "sg:address":"1669 N Vine St",
    "sg:city":"Chicago",
    "sg:classifiers":[
        {
            "category":"Manufacturing",
            "subcategory":"Rubber & Plastics",
            "type":"Manufacturing & Wholesale Goods"
        },
        {
            "category":"Professional",
            "subcategory":"Business Services",
            "type":"Services"
        }
    ],
    "sg:phone":"+1 312 943 0500",
    "sg:postcode":"60614",
    "sg:province":"IL",
    "sg:tags":[
        "product",
        "coach",
        "plastics-fabricating",
        "consultant",
        "plastics-vacuum",
        "pressure",
        "forming-manufacturers",
        "finishing",
        "decorating"
    ],
    "sg:website":"http://www.resinex.com",
    "wof:name":"Plastics Inc",
    "wof:placetype":"venue"
},
  "geometry": {"coordinates":[-87.64436499999999,41.912033],"type":"Point"}
}