{
  "type": "Feature",
  "properties": {
    "addr:full":"1010 Market St Ste 1520 Saint Louis MO 63101",
    "addr:housenumber":"1010",
    "addr:postcode":"63101",
    "addr:street":"Market St Ste 1520",
    "iso:country":"US",
    "sg:address":"1010 Market St Ste 1520",
    "sg:city":"Saint Louis",
    "sg:classifiers":[
        {
            "category":"Professional",
            "subcategory":"Lawyer & Legal Services",
            "type":"Services"
        }
    ],
    "sg:phone":"+1 314 621 8383",
    "sg:postcode":"63101",
    "sg:province":"MO",
    "sg:website":"www.oliff.com",
    "wof:name":"Oliff & Berridge",
    "wof:placetype":"venue"
},
  "geometry": {"coordinates":[-90.196297,38.626999],"type":"Point"}
}