{
  "type": "Feature",
  "properties": {
    "addr:full":"4824 W Quincy St Chicago IL 60644",
    "addr:housenumber":"4824",
    "addr:postcode":"60644",
    "addr:street":"W Quincy St",
    "iso:country":"US",
    "sg:address":"4824 W Quincy St",
    "sg:city":"Chicago",
    "sg:classifiers":[
        {
            "category":"Building & Trades",
            "subcategory":"Plumbing",
            "type":"Services"
        }
    ],
    "sg:phone":"+1 773 412 4961",
    "sg:postcode":"60644",
    "sg:province":"IL",
    "sg:tags":[
        "contractor"
    ],
    "wof:name":"Ja Heating Appl Repa",
    "wof:placetype":"venue"
},
  "geometry": {"coordinates":[-87.745327,41.877767],"type":"Point"}
}