{
  "type": "Feature",
  "properties": {
    "addr:full":"500 Randy Rd Carol Stream IL 60188",
    "addr:housenumber":"500",
    "addr:postcode":"60188",
    "addr:street":"Randy Rd",
    "iso:country":"US",
    "sg:address":"500 Randy Rd",
    "sg:city":"Carol Stream",
    "sg:classifiers":[
        {
            "category":"Manufacturing",
            "subcategory":"Chemicals & Compounds",
            "type":"Manufacturing & Wholesale Goods"
        }
    ],
    "sg:phone":"+1 630 462 1900",
    "sg:postcode":"60188",
    "sg:province":"IL",
    "sg:tags":[
        "product",
        "carbide",
        "metal"
    ],
    "wof:name":"Dyna Cut Industries",
    "wof:placetype":"venue"
},
  "geometry": {"coordinates":[-88.10549899999999,41.906681],"type":"Point"}
}