{
  "type": "Feature",
  "properties": {
    "addr:full":"820 Darlington Ln Crystal Lake IL 60014",
    "addr:housenumber":"820",
    "addr:postcode":"60014",
    "addr:street":"Darlington Ln",
    "iso:country":"US",
    "sg:address":"820 Darlington Ln",
    "sg:city":"Crystal Lake",
    "sg:classifiers":[
        {
            "category":"Education",
            "subcategory":"School",
            "type":"Public Place"
        }
    ],
    "sg:phone":"+1 815 459 4231",
    "sg:postcode":"60014",
    "sg:province":"IL",
    "wof:name":"Coventry Elementary School",
    "wof:placetype":"venue"
},
  "geometry": {"coordinates":[-88.327314,42.219428],"type":"Point"}
}