{
  "type": "Feature",
  "properties": {
    "addr:full":"477 S River Rd Des Plaines IL 60016",
    "addr:housenumber":"477",
    "addr:postcode":"60016",
    "addr:street":"S River Rd Des",
    "iso:country":"US",
    "sg:address":"477 S River Rd",
    "sg:city":"Des Plaines",
    "sg:classifiers":[
        {
            "category":"Government",
            "subcategory":"Office",
            "type":"Public Place"
        }
    ],
    "sg:phone":"+1 847 294 4326",
    "sg:postcode":"60016",
    "sg:province":"IL",
    "sg:tags":[
        "program",
        "state",
        "adm"
    ],
    "sg:website":"www.icc.state.il.us",
    "wof:name":"Commerce Commission",
    "wof:placetype":"venue"
},
  "geometry": {"coordinates":[-87.88468,42.044352],"type":"Point"}
}