{
  "type": "Feature",
  "properties": {
    "iso:country":"US",
    "sg:address":"1401 Interstate Dr",
    "sg:city":"Champaign",
    "sg:classifiers":[
        {
            "category":"Building & Trades",
            "subcategory":"Cleaning & Sanitation",
            "type":"Services"
        }
    ],
    "sg:phone":"+1 217 425 7000",
    "sg:postcode":"61822",
    "sg:province":"IL",
    "sg:tags":[
        "carpet"
    ],
    "wof:name":"Service Master Clean",
    "wof:placetype":"venue"
},
  "geometry": {"coordinates":[-88.26979799999999,40.148602],"type":"Point"}
}