{
  "type": "Feature",
  "properties": {
    "addr:full":"10639 Buck Dr Orland Park IL 60467",
    "addr:housenumber":"10639",
    "addr:postcode":"60467",
    "addr:street":"Buck Dr",
    "iso:country":"US",
    "sg:address":"10639 Buck Dr",
    "sg:city":"Orland Park",
    "sg:classifiers":[
        {
            "category":"Building & Trades",
            "subcategory":"Construction",
            "type":"Services"
        }
    ],
    "sg:phone":"+1 708 403 9904",
    "sg:postcode":"60467",
    "sg:province":"IL",
    "sg:tags":[
        "carpentry",
        "contractor"
    ],
    "wof:name":"OSix Carpentery",
    "wof:placetype":"venue"
},
  "geometry": {"coordinates":[-87.876948,41.576644],"type":"Point"}
}