{
  "type": "Feature",
  "properties": {
    "iso:country":"US",
    "sg:address":"213 S Wheaton Ave",
    "sg:city":"Wheaton",
    "sg:classifiers":[
        {
            "category":"Organizations",
            "subcategory":"Membership Organization",
            "type":"Services"
        }
    ],
    "sg:phone":"+1 630 510 2380",
    "sg:postcode":"60187",
    "sg:province":"IL",
    "wof:name":"Rjn Foundation",
    "wof:placetype":"venue"
},
  "geometry": {"coordinates":[-88.109818,41.863262],"type":"Point"}
}