{
  "type": "Feature",
  "properties": {
    "iso:country":"US",
    "sg:address":"350 N Orleans St",
    "sg:city":"Chicago",
    "sg:classifiers":[
        {
            "category":"Manufacturing",
            "subcategory":"Jewelry",
            "type":"Manufacturing & Wholesale Goods"
        }
    ],
    "sg:phone":"+1 312 644 5322",
    "sg:postcode":"60654",
    "sg:province":"IL",
    "wof:name":"Eisenberg Jewelry",
    "wof:placetype":"venue"
},
  "geometry": {"coordinates":[-87.63591099999999,41.887358],"type":"Point"}
}