{
  "type": "Feature",
  "properties": {
    "iso:country":"US",
    "sg:address":"110 E Oak St.",
    "sg:city":"Chicago",
    "sg:classifiers":[
        {
            "category":"Shopping",
            "subcategory":"Clothing, Apparel, & Fashions",
            "type":"Retail Goods"
        },
        {
            "category":"Manufacturing",
            "subcategory":"Leather Goods",
            "type":"Manufacturing & Wholesale Goods"
        },
        {
            "category":"Shopping",
            "subcategory":"Shoes",
            "type":"Retail Goods"
        }
    ],
    "sg:phone":"+1 312 787 8175",
    "sg:postcode":"60611",
    "sg:province":"IL",
    "sg:tags":[
        "men's",
        "clothing",
        "store",
        "women's"
    ],
    "sg:website":"www.hermes.com",
    "wof:name":"Hermes of Paris",
    "wof:placetype":"venue"
},
  "geometry": {"coordinates":[-87.625801,41.900902],"type":"Point"}
}