{
  "type": "Feature",
  "properties": {
    "iso:country":"US",
    "sg:address":"2431 S Brookville Rd",
    "sg:city":"Polo",
    "sg:phone":"+1 815 225 7488",
    "sg:postcode":"61064",
    "sg:province":"IL",
    "sg:tags":[
        "farm",
        "grain",
        "cash"
    ],
    "wof:name":"George Hadley",
    "wof:placetype":"venue"
},
  "geometry": {"coordinates":[-89.682541,41.982288],"type":"Point"}
}