{
  "type": "Feature",
  "properties": {
    "iso:country":"US",
    "sg:address":"938 Ogden Ave",
    "sg:city":"Downers Grove",
    "sg:classifiers":[
        {
            "category":"Building & Trades",
            "subcategory":"Construction",
            "type":"Services"
        }
    ],
    "sg:phone":"+1 630 434 0717",
    "sg:postcode":"60515",
    "sg:province":"IL",
    "sg:tags":[
        "resurfacing",
        "refinishing",
        "floor"
    ],
    "wof:name":"Eddies Custom Hardwood",
    "wof:placetype":"venue"
},
  "geometry": {"coordinates":[-88.009668,41.808961],"type":"Point"}
}