{
  "type": "Feature",
  "properties": {
    "iso:country":"US",
    "sg:address":"3431 W Peterson Ave",
    "sg:city":"Chicago",
    "sg:classifiers":[
        {
            "category":"Restaurant",
            "type":"Food & Drink"
        }
    ],
    "sg:phone":"+1 773 478 5410",
    "sg:postcode":"60659",
    "sg:province":"IL",
    "sg:tags":[
        "style",
        "pizza",
        "family",
        "italian"
    ],
    "wof:name":"Martino's Restaurant",
    "wof:placetype":"venue"
},
  "geometry": {"coordinates":[-87.715103,41.990101],"type":"Point"}
}