{
  "type": "Feature",
  "properties": {
    "iso:country":"US",
    "sg:address":"1910 Black Rd",
    "sg:city":"Joliet",
    "sg:classifiers":[
        {
            "category":"Social Services",
            "subcategory":"Child Care",
            "type":"Services"
        }
    ],
    "sg:phone":"+1 815 725 1688",
    "sg:postcode":"60435",
    "sg:province":"IL",
    "sg:tags":[
        "kindergarten",
        "academic",
        "school"
    ],
    "wof:name":"Our Savior Lutheran Preschool",
    "wof:placetype":"venue"
},
  "geometry": {"coordinates":[-88.12799800000001,41.536996],"type":"Point"}
}