{
  "type": "Feature",
  "properties": {
    "iso:country":"US",
    "sg:address":"330 Georgetown Sq",
    "sg:city":"Wood Dale",
    "sg:classifiers":[
        {
            "category":"Health Services",
            "subcategory":"Doctor",
            "type":"Services"
        }
    ],
    "sg:phone":"+1 630 350 0067",
    "sg:postcode":"60191",
    "sg:province":"IL",
    "wof:name":"North American Dental Program",
    "wof:placetype":"venue"
},
  "geometry": {"coordinates":[-87.996628,41.965703],"type":"Point"}
}