{
  "type": "Feature",
  "properties": {
    "iso:country":"US",
    "sg:address":"1519 Hoffman Hammond",
    "sg:city":"Chicago",
    "sg:classifiers":[
        {
            "category":"Education",
            "subcategory":"School",
            "type":"Public Place"
        }
    ],
    "sg:phone":"+1 773 768 1778",
    "sg:postcode":"60607",
    "sg:province":"IL",
    "sg:tags":[
        "high",
        "middle",
        "elementary"
    ],
    "wof:name":"Bishop Noll",
    "wof:placetype":"venue"
},
  "geometry": {"coordinates":[-87.491957,41.626809],"type":"Point"}
}