{
  "type": "Feature",
  "properties": {
    "iso:country":"US",
    "sg:address":"136 W Vallette St",
    "sg:city":"Elmhurst",
    "sg:classifiers":[
        {
            "category":"Manufacturing",
            "subcategory":"Printing",
            "type":"Manufacturing & Wholesale Goods"
        }
    ],
    "sg:phone":"+1 630 832 5200",
    "sg:postcode":"60126",
    "sg:province":"IL",
    "sg:tags":[
        "magazine",
        "publishing"
    ],
    "wof:name":"Marking Devices Publishing Co",
    "wof:placetype":"venue"
},
  "geometry": {"coordinates":[-87.940726,41.883441],"type":"Point"}
}