{
  "type": "Feature",
  "properties": {
    "addr:full":"820 W Jackson Boulevard Chicago IL 60607",
    "addr:housenumber":"820",
    "addr:postcode":"60607",
    "addr:street":"W Jackson Boulevard",
    "iso:country":"US",
    "sg:address":"820 W Jackson Boulevard",
    "sg:city":"Chicago",
    "sg:classifiers":[
        {
            "category":"Health Services",
            "subcategory":"Doctor",
            "type":"Services"
        },
        {
            "category":"Health Services",
            "subcategory":"Clinic",
            "type":"Services"
        },
        {
            "category":"Health Services",
            "subcategory":"Hospital",
            "type":"Services"
        }
    ],
    "sg:phone":"+1 312 930 9365",
    "sg:postcode":"60607",
    "sg:province":"IL",
    "sg:tags":[
        "medical",
        "dialysis"
    ],
    "wof:name":"Chicago Dialysis Center",
    "wof:placetype":"venue"
},
  "geometry": {"coordinates":[-87.64807399999999,41.87795],"type":"Point"}
}