{
  "type": "Feature",
  "properties": {
    "iso:country":"US",
    "sg:address":"3206 N Kilbourn Ave",
    "sg:city":"Chicago",
    "sg:classifiers":[
        {
            "category":"Wholesale",
            "subcategory":"Electrical",
            "type":"Manufacturing & Wholesale Goods"
        },
        {
            "category":"Shopping",
            "subcategory":"Computers & Home Electronics",
            "type":"Retail Goods"
        }
    ],
    "sg:phone":"+1 773 685 9504",
    "sg:postcode":"60641",
    "sg:province":"IL",
    "sg:tags":[
        "equipment",
        "consumer",
        "electric",
        "supply"
    ],
    "wof:name":"George's Electronics",
    "wof:placetype":"venue"
},
  "geometry": {"coordinates":[-87.739476,41.939042],"type":"Point"}
}