{
  "type": "Feature",
  "properties": {
    "addr:full":"261 Richert Rd Wood Dale IL 60191",
    "addr:housenumber":"261",
    "addr:postcode":"60191",
    "addr:street":"Richert Rd",
    "iso:country":"US",
    "sg:address":"261 Richert Rd",
    "sg:city":"Wood Dale",
    "sg:classifiers":[
        {
            "category":"Restaurant",
            "type":"Food & Drink"
        }
    ],
    "sg:phone":"+1 630 927 4321",
    "sg:postcode":"60191",
    "sg:province":"IL",
    "sg:tags":[
        "caterer"
    ],
    "wof:name":"B & B Catering Co",
    "wof:placetype":"venue"
},
  "geometry": {"coordinates":[-87.97048700000001,41.978171],"type":"Point"}
}