{
  "type": "Feature",
  "properties": {
    "iso:country":"US",
    "sg:address":"2325 Grand Ave",
    "sg:city":"Galesburg",
    "sg:classifiers":[
        {
            "category":"Building & Trades",
            "subcategory":"Construction",
            "type":"Services"
        }
    ],
    "sg:phone":"+1 309 343 4240",
    "sg:postcode":"61401",
    "sg:province":"IL",
    "sg:tags":[
        "handyman"
    ],
    "wof:name":"Bill S Computer Repair",
    "wof:placetype":"venue"
},
  "geometry": {"coordinates":[-90.335217,40.93413],"type":"Point"}
}