{
  "type": "Feature",
  "properties": {
    "iso:country":"US",
    "sg:address":"620 Wabash Ave",
    "sg:city":"Carthage",
    "sg:classifiers":[
        {
            "category":"Government",
            "subcategory":"Office",
            "type":"Public Place"
        }
    ],
    "sg:phone":"+1 217 357 3116",
    "sg:postcode":"62321",
    "sg:province":"IL",
    "wof:name":"US Public Aid",
    "wof:placetype":"venue"
},
  "geometry": {"coordinates":[-91.134275,40.412259],"type":"Point"}
}