{
  "type": "Feature",
  "properties": {
    "addr:full":"3155 N Woodford St Decatur IL 62526",
    "addr:housenumber":"3155",
    "addr:postcode":"62526",
    "addr:street":"N Woodford St",
    "iso:country":"US",
    "sg:address":"3155 N Woodford St",
    "sg:city":"Decatur",
    "sg:classifiers":[
        {
            "category":"Insurance",
            "subcategory":"Hazard Insurance",
            "type":"Services"
        },
        {
            "category":"Insurance",
            "subcategory":"Insurance Agent",
            "type":"Services"
        },
        {
            "category":"Insurance",
            "subcategory":"Life Insurance",
            "type":"Services"
        }
    ],
    "sg:phone":"+1 217 876 8800",
    "sg:postcode":"62526",
    "sg:province":"IL",
    "sg:tags":[
        "auto"
    ],
    "sg:website":"http://statefarm.mqgroup.com/url.asp?usr=133895",
    "wof:name":"Schelling, Melanie - State Farm Insurance Agent",
    "wof:placetype":"venue"
},
  "geometry": {"coordinates":[-88.93618600000001,39.879416],"type":"Point"}
}