{
  "type": "Feature",
  "properties": {
    "addr:full":"208 Jana Rd Macomb IL 61455",
    "addr:housenumber":"208",
    "addr:postcode":"61455",
    "addr:street":"Jana Rd",
    "iso:country":"US",
    "sg:address":"208 Jana Rd",
    "sg:city":"Macomb",
    "sg:classifiers":[
        {
            "category":"Organizations",
            "subcategory":"Religious Organization",
            "type":"Services"
        }
    ],
    "sg:phone":"+1 309 837 2064",
    "sg:postcode":"61455",
    "sg:province":"IL",
    "wof:name":"Community of Christ",
    "wof:placetype":"venue"
},
  "geometry": {"coordinates":[-90.691333,40.471786],"type":"Point"}
}