{
  "type": "Feature",
  "properties": {
    "addr:full":"634 E Macarthur Dr Palatine IL 60074",
    "addr:housenumber":"634",
    "addr:postcode":"60074",
    "addr:street":"E Macarthur Dr",
    "iso:country":"US",
    "sg:address":"634 E Macarthur Dr",
    "sg:city":"Palatine",
    "sg:classifiers":[
        {
            "category":"Retail",
            "subcategory":"Laundry & Dry Cleaning",
            "type":"Services"
        }
    ],
    "sg:phone":"+1 847 991 2413",
    "sg:postcode":"60074",
    "sg:province":"IL",
    "wof:name":"Roel Carpet Cleaning",
    "wof:placetype":"venue"
},
  "geometry": {"coordinates":[-88.027389,42.114934],"type":"Point"}
}