{
  "type": "Feature",
  "properties": {
    "iso:country":"US",
    "sg:address":"105 N Parrish Ln",
    "sg:city":"Carbondale",
    "sg:classifiers":[
        {
            "category":"Organizations",
            "subcategory":"Religious Organization",
            "type":"Services"
        }
    ],
    "sg:phone":"+1 618 529 2439",
    "sg:postcode":"62901",
    "sg:province":"IL",
    "wof:name":"Unitarian Fellowship",
    "wof:placetype":"venue"
},
  "geometry": {"coordinates":[-89.251004,37.730365],"type":"Point"}
}