{
  "type": "Feature",
  "properties": {
    "iso:country":"US",
    "sg:address":"1015 1st St",
    "sg:city":"Silvis",
    "sg:classifiers":[
        {
            "category":"Restaurant",
            "type":"Food & Drink"
        }
    ],
    "sg:phone":"+1   ",
    "sg:postcode":"61282",
    "sg:province":"IL",
    "sg:tags":[
        "eating"
    ],
    "wof:name":"Little Caesars",
    "wof:placetype":"venue"
},
  "geometry": {"coordinates":[-90.424711,41.499741],"type":"Point"}
}