{
  "type": "Feature",
  "properties": {
    "iso:country":"US",
    "sg:address":"7228 S Cottage Grove Ave",
    "sg:city":"Chicago",
    "sg:classifiers":[
        {
            "category":"Personal",
            "subcategory":"Barber",
            "type":"Services"
        }
    ],
    "sg:phone":"+1 773 487 9456",
    "sg:postcode":"60619",
    "sg:province":"IL",
    "wof:name":"Cottage Barber Shop",
    "wof:placetype":"venue"
},
  "geometry": {"coordinates":[-87.605598,41.763199],"type":"Point"}
}