{
  "type": "Feature",
  "properties": {
    "addr:full":"527 Eichler Dr West Dundee IL 60118",
    "addr:housenumber":"527",
    "addr:postcode":"60118",
    "addr:street":"Eichler Dr",
    "iso:country":"US",
    "sg:address":"527 Eichler Dr",
    "sg:city":"West Dundee",
    "sg:classifiers":[
        {
            "category":"Building & Trades",
            "subcategory":"Construction",
            "type":"Services"
        }
    ],
    "sg:phone":"+1 847 836 4951",
    "sg:postcode":"60118",
    "sg:province":"IL",
    "sg:tags":[
        "interior",
        "design",
        "painter"
    ],
    "sg:website":"dfrancofinishes.com.com",
    "wof:name":"D' Franco Painting and Decorating",
    "wof:placetype":"venue"
},
  "geometry": {"coordinates":[-88.286018,42.092865],"type":"Point"}
}