{
  "type": "Feature",
  "properties": {
    "iso:country":"US",
    "sg:address":"14411 Cicero Ave",
    "sg:city":"Midlothian",
    "sg:classifiers":[
        {
            "category":"Shopping",
            "subcategory":"Pets & Pet Supplies",
            "type":"Retail Goods"
        }
    ],
    "sg:phone":"+1 708 293 0600",
    "sg:postcode":"60445",
    "sg:province":"IL",
    "sg:tags":[
        "store"
    ],
    "wof:name":"Animal Island",
    "wof:placetype":"venue"
},
  "geometry": {"coordinates":[-87.737297,41.629002],"type":"Point"}
}