{
  "type": "Feature",
  "properties": {
    "iso:country":"US",
    "sg:address":"230 E 8th St",
    "sg:city":"Lockport",
    "sg:classifiers":[
        {
            "category":"Personal",
            "subcategory":"Beauty Salon",
            "type":"Services"
        }
    ],
    "sg:phone":"+1 815 834 0401",
    "sg:postcode":"60441",
    "sg:province":"IL",
    "sg:tags":[
        "shop"
    ],
    "wof:name":"Tropical Trenz",
    "wof:placetype":"venue"
},
  "geometry": {"coordinates":[-88.054425,41.589828],"type":"Point"}
}