{
  "type": "Feature",
  "properties": {
    "iso:country":"US",
    "sg:address":"131 E 79th Street",
    "sg:city":"Chicago",
    "sg:classifiers":[
        {
            "category":"Restaurant",
            "type":"Food & Drink"
        }
    ],
    "sg:phone":"+1 773 994 1525",
    "sg:postcode":"60619",
    "sg:province":"IL",
    "sg:tags":[
        "mexican"
    ],
    "wof:name":"Pepe's Restaurant",
    "wof:placetype":"venue"
},
  "geometry": {"coordinates":[-87.620502,41.751013],"type":"Point"}
}