{
  "type": "Feature",
  "properties": {
    "iso:country":"US",
    "sg:address":"4241 Main St",
    "sg:city":"Skokie",
    "sg:classifiers":[
        {
            "category":"Professional",
            "subcategory":"Accounting & Tax Preparation",
            "type":"Services"
        }
    ],
    "sg:phone":"+1 847 677 0224",
    "sg:postcode":"60076",
    "sg:province":"IL",
    "wof:name":"Kenneth P Rapopart CPA Ltd",
    "wof:placetype":"venue"
},
  "geometry": {"coordinates":[-87.735142,42.033434],"type":"Point"}
}