{
  "type": "Feature",
  "properties": {
    "addr:full":"1685 Estate Cir Naperville IL 60565",
    "addr:housenumber":"1685",
    "addr:postcode":"60565",
    "addr:street":"Estate Cir",
    "iso:country":"US",
    "sg:address":"1685 Estate Cir",
    "sg:city":"Naperville",
    "sg:classifiers":[
        {
            "category":"Health Services",
            "subcategory":"Doctor",
            "type":"Services"
        },
        {
            "category":"Health Services",
            "subcategory":"Hospital",
            "type":"Services"
        }
    ],
    "sg:phone":"+1 630 428 3277",
    "sg:postcode":"60565",
    "sg:province":"IL",
    "sg:tags":[
        "consultant",
        "medical",
        "practice",
        "nursing",
        "home"
    ],
    "wof:name":"Systematic Management Systems",
    "wof:placetype":"venue"
},
  "geometry": {"coordinates":[-88.096616,41.747698],"type":"Point"}
}