{
  "type": "Feature",
  "properties": {
    "iso:country":"US",
    "sg:address":"2508 E Oaks Rd N",
    "sg:city":"Urbana",
    "sg:phone":"+1 217 344 3633",
    "sg:postcode":"61802",
    "sg:province":"IL",
    "sg:tags":[
        "farm",
        "corn",
        "soybean"
    ],
    "wof:name":"Michael Helregel",
    "wof:placetype":"venue"
},
  "geometry": {"coordinates":[-88.17904799999999,40.149431],"type":"Point"}
}