{
  "type": "Feature",
  "properties": {
    "iso:country":"US",
    "sg:address":"11936 S Oak Park Ave",
    "sg:city":"Palos Heights",
    "sg:classifiers":[
        {
            "category":"Building & Trades",
            "subcategory":"Construction",
            "type":"Services"
        }
    ],
    "sg:phone":"+1 708 448 2300",
    "sg:postcode":"60463",
    "sg:province":"IL",
    "sg:tags":[
        "contractor"
    ],
    "wof:name":"Precision Remodeling and Design",
    "wof:placetype":"venue"
},
  "geometry": {"coordinates":[-87.788134,41.674294],"type":"Point"}
}