{
  "type": "Feature",
  "properties": {
    "iso:country":"US",
    "sg:address":"9208 Hunter Dr",
    "sg:city":"Tinley Park",
    "sg:classifiers":[
        {
            "category":"Real Estate",
            "subcategory":"Real Estate Operator",
            "type":"Services"
        }
    ],
    "sg:phone":"+1 708 460 3880",
    "sg:postcode":"60487",
    "sg:province":"IL",
    "sg:tags":[
        "apartment",
        "complex"
    ],
    "wof:name":"Ace Management",
    "wof:placetype":"venue"
},
  "geometry": {"coordinates":[-87.84395000000001,41.595463],"type":"Point"}
}