{
  "type": "Feature",
  "properties": {
    "iso:country":"US",
    "sg:address":"1025 E 9th St",
    "sg:city":"Lockport",
    "sg:classifiers":[
        {
            "category":"Sports & Exercise",
            "subcategory":"Gym",
            "type":"Entertainment"
        }
    ],
    "sg:phone":"+1 815 588 1830",
    "sg:postcode":"60441",
    "sg:province":"IL",
    "sg:tags":[
        "club",
        "health",
        "studio",
        "gymnasium"
    ],
    "wof:name":"9th Street Fitness",
    "wof:placetype":"venue"
},
  "geometry": {"coordinates":[-88.039258,41.593574],"type":"Point"}
}