{
  "type": "Feature",
  "properties": {
    "iso:country":"US",
    "sg:address":"23648 N County Highway 38",
    "sg:city":"Marietta",
    "sg:classifiers":[
        {
            "category":"Manufacturing",
            "subcategory":"Food",
            "type":"Manufacturing & Wholesale Goods"
        },
        {
            "category":"Farming",
            "subcategory":"Farm",
            "type":"Manufacturing & Wholesale Goods"
        }
    ],
    "sg:phone":"+1 309 926 7321",
    "sg:postcode":"61459",
    "sg:province":"IL",
    "sg:tags":[
        "corn",
        "product"
    ],
    "wof:name":"Spangler Grain",
    "wof:placetype":"venue"
},
  "geometry": {"coordinates":[-90.35719,40.520631],"type":"Point"}
}