{
  "type": "Feature",
  "properties": {
    "addr:full":"417 W Main St Barrington IL 60010",
    "addr:housenumber":"417",
    "addr:postcode":"60010",
    "addr:street":"W Main St",
    "iso:country":"US",
    "sg:address":"417 W Main St",
    "sg:city":"Barrington",
    "sg:classifiers":[
        {
            "category":"Retail",
            "subcategory":"Auto Repair",
            "type":"Services"
        }
    ],
    "sg:phone":"+1 847 381 4467",
    "sg:postcode":"60010",
    "sg:province":"IL",
    "sg:tags":[
        "repairing",
        "automobile"
    ],
    "wof:name":"Reber Auto Svc",
    "wof:placetype":"venue"
},
  "geometry": {"coordinates":[-88.16499,42.154157],"type":"Point"}
}