{
  "type": "Feature",
  "properties": {
    "addr:full":"5435 N Milwaukee Ave Chicago IL 60630",
    "addr:housenumber":"5435",
    "addr:postcode":"60630",
    "addr:street":"N Milwaukee Ave",
    "iso:country":"US",
    "sg:address":"5435 N Milwaukee Ave",
    "sg:city":"Chicago",
    "sg:classifiers":[
        {
            "category":"Health Services",
            "subcategory":"Dentist",
            "type":"Services"
        }
    ],
    "sg:phone":"+1 773 763 6262",
    "sg:postcode":"60630",
    "sg:province":"IL",
    "sg:tags":[
        "orthodontist"
    ],
    "sg:website":"www.glenorthodontics.com",
    "wof:name":"Glen Orthodontics PC",
    "wof:placetype":"venue"
},
  "geometry": {"coordinates":[-87.771517,41.980442],"type":"Point"}
}