{
  "type": "Feature",
  "properties": {
    "iso:country":"US",
    "sg:address":"715 Lake Street Suite #220",
    "sg:city":"Oak Park",
    "sg:classifiers":[
        {
            "category":"Health Services",
            "subcategory":"Chiropractor",
            "type":"Services"
        }
    ],
    "sg:phone":"+1 708 660 0148",
    "sg:postcode":"60301",
    "sg:province":"IL",
    "wof:name":"Integrative Chiropractic & Natural Medicine Clinic",
    "wof:placetype":"venue"
},
  "geometry": {"coordinates":[-87.793486,41.888605],"type":"Point"}
}