{
  "type": "Feature",
  "properties": {
    "addr:full":"8711 S 77th Ave Bridgeview IL 60455",
    "addr:housenumber":"8711",
    "addr:postcode":"60455",
    "addr:street":"S 77Th Ave",
    "iso:country":"US",
    "sg:address":"8711 S 77th Ave",
    "sg:city":"Bridgeview",
    "sg:classifiers":[
        {
            "category":"Professional",
            "subcategory":"Advertising",
            "type":"Services"
        }
    ],
    "sg:phone":"+1 708 598 1212",
    "sg:postcode":"60455",
    "sg:province":"IL",
    "sg:tags":[
        "mail",
        "direct"
    ],
    "wof:name":"Jetson Multi-Graphics",
    "wof:placetype":"venue"
},
  "geometry": {"coordinates":[-87.81113499999999,41.732335],"type":"Point"}
}