{
  "type": "Feature",
  "properties": {
    "addr:full":"1220 W Taylor St Chicago IL 60607",
    "addr:housenumber":"1220",
    "addr:postcode":"60607",
    "addr:street":"W Taylor St",
    "iso:country":"US",
    "sg:address":"1220 W Taylor St",
    "sg:city":"Chicago",
    "sg:classifiers":[
        {
            "category":"Restaurant",
            "type":"Food & Drink"
        }
    ],
    "sg:phone":"+1 312 850 2000",
    "sg:postcode":"60607",
    "sg:province":"IL",
    "sg:tags":[
        "pizza"
    ],
    "sg:website":"www.taylormadepizza.com",
    "wof:name":"Taylor Made Pizza",
    "wof:placetype":"venue"
},
  "geometry": {"coordinates":[-87.65754,41.869491],"type":"Point"}
}