{
  "type": "Feature",
  "properties": {
    "iso:country":"US",
    "sg:address":"901 Junie Ct",
    "sg:city":"Joliet",
    "sg:classifiers":[
        {
            "category":"Restaurant",
            "type":"Food & Drink"
        },
        {
            "category":"Building & Trades",
            "subcategory":"Plumbing",
            "type":"Services"
        },
        {
            "category":"Retail",
            "subcategory":"Repair Shop",
            "type":"Services"
        },
        {
            "category":"Wholesale",
            "subcategory":"Machinery & Supplies",
            "type":"Manufacturing & Wholesale Goods"
        },
        {
            "category":"Building & Trades",
            "subcategory":"Construction",
            "type":"Services"
        }
    ],
    "sg:phone":"+1 815 741 2275",
    "sg:postcode":"60435",
    "sg:province":"IL",
    "sg:tags":[
        "heating",
        "boilers-repair",
        "equipment-commercial",
        "supplies-refrigeration",
        "specialty",
        "system",
        "air conditioning",
        "equipment",
        "industrial",
        "refrigeration",
        "clean",
        "contractor",
        "freezers-repair",
        "refrigerator"
    ],
    "wof:name":"A AA Comfort Heating & Air",
    "wof:placetype":"venue"
},
  "geometry": {"coordinates":[-88.112404,41.538819],"type":"Point"}
}