{
  "type": "Feature",
  "properties": {
    "iso:country":"US",
    "sg:address":"107 E Zarley Blvd",
    "sg:city":"Joliet",
    "sg:classifiers":[
        {
            "category":"Social Services",
            "subcategory":"Child Care",
            "type":"Services"
        }
    ],
    "sg:phone":"+1 815 723 6825",
    "sg:postcode":"60433",
    "sg:province":"IL",
    "sg:tags":[
        "nursery",
        "day"
    ],
    "wof:name":"Tees Teddybear Daycare",
    "wof:placetype":"venue"
},
  "geometry": {"coordinates":[-88.078639,41.495235],"type":"Point"}
}