{
  "type": "Feature",
  "properties": {
    "iso:country":"US",
    "sg:address":"3805 E State St",
    "sg:city":"Rockford",
    "sg:classifiers":[
        {
            "category":"Restaurant",
            "type":"Food & Drink"
        }
    ],
    "sg:menulink":"http://www.allmenus.com/il/rockford/196312-taco-bell/menu/",
    "sg:postcode":"61108",
    "sg:province":"IL",
    "sg:tags":[
        "mexican"
    ],
    "wof:name":"Taco Bell",
    "wof:placetype":"venue"
},
  "geometry": {"coordinates":[-89.03865,42.265878],"type":"Point"}
}