{
  "type": "Feature",
  "properties": {
    "iso:country":"US",
    "sg:address":"3301 N Lincoln Ave",
    "sg:city":"Chicago",
    "sg:classifiers":[
        {
            "category":"Professional",
            "subcategory":"Art Services",
            "type":"Services"
        }
    ],
    "sg:phone":"+1 773 549 1631",
    "sg:postcode":"60657",
    "sg:province":"IL",
    "sg:tags":[
        "photographer",
        "education",
        "adult"
    ],
    "sg:website":"www.chicagophoto.org",
    "wof:name":"Chicago Photography Center",
    "wof:placetype":"venue"
},
  "geometry": {"coordinates":[-87.66991299999999,41.941504],"type":"Point"}
}