{
  "type": "Feature",
  "properties": {
    "addr:full":"33546 N State Rd Genoa IL 60135",
    "addr:housenumber":"33546",
    "addr:postcode":"60135",
    "addr:street":"N State Rd",
    "iso:country":"US",
    "sg:address":"33546 N State Rd",
    "sg:city":"Genoa",
    "sg:classifiers":[
        {
            "category":"Cinema",
            "subcategory":"Movie Rental",
            "type":"Entertainment"
        }
    ],
    "sg:phone":"+1   ",
    "sg:postcode":"60135",
    "sg:province":"IL",
    "sg:tags":[
        "repair",
        "tape",
        "video",
        "electrical",
        "re"
    ],
    "wof:name":"Kearneys TV & Appliance",
    "wof:placetype":"venue"
},
  "geometry": {"coordinates":[-88.695599,42.119443],"type":"Point"}
}