{
  "type": "Feature",
  "properties": {
    "iso:country":"US",
    "sg:address":"521 Devonshire Ln",
    "sg:city":"Crystal Lake",
    "sg:classifiers":[
        {
            "category":"Health Services",
            "subcategory":"Doctor",
            "type":"Services"
        }
    ],
    "sg:phone":"+1 815 459 3434",
    "sg:postcode":"60014",
    "sg:province":"IL",
    "sg:tags":[
        "dentist",
        "orthodontist"
    ],
    "wof:name":"John P Howland DDS Ms PC",
    "wof:placetype":"venue"
},
  "geometry": {"coordinates":[-88.328877,42.226607],"type":"Point"}
}