{
  "type": "Feature",
  "properties": {
    "addr:full":"3319 W 91st St Evergreen Park IL 60805",
    "addr:housenumber":"3319",
    "addr:postcode":"60805",
    "addr:street":"W 91St St",
    "iso:country":"US",
    "sg:address":"3319 W 91st St",
    "sg:city":"Evergreen Park",
    "sg:classifiers":[
        {
            "category":"Shopping",
            "type":"Retail Goods"
        }
    ],
    "sg:phone":"+1   ",
    "sg:postcode":"60805",
    "sg:province":"IL",
    "sg:tags":[
        "merchandise"
    ],
    "wof:name":"Classic Memorials",
    "wof:placetype":"venue"
},
  "geometry": {"coordinates":[-87.70558,41.727914],"type":"Point"}
}