{
  "type": "Feature",
  "properties": {
    "addr:full":"2601 W North Ave Chicago IL 60647",
    "addr:housenumber":"2601",
    "addr:postcode":"60647",
    "addr:street":"W North Ave",
    "iso:country":"US",
    "sg:address":"2601 W North Ave",
    "sg:city":"Chicago",
    "sg:classifiers":[
        {
            "category":"Shopping",
            "type":"Retail Goods"
        }
    ],
    "sg:phone":"+1 773 342 1111",
    "sg:postcode":"60647",
    "sg:province":"IL",
    "sg:tags":[
        "telephone",
        "cellular"
    ],
    "wof:name":"ABC",
    "wof:placetype":"venue"
},
  "geometry": {"coordinates":[-87.69332300000001,41.910319],"type":"Point"}
}