{
  "type": "Feature",
  "properties": {
    "iso:country":"US",
    "sg:address":"300 Roxana Ave",
    "sg:city":"South Roxana",
    "sg:classifiers":[
        {
            "category":"Building & Trades",
            "subcategory":"Construction",
            "type":"Services"
        }
    ],
    "sg:phone":"+1 618 254 3855",
    "sg:postcode":"62087",
    "sg:province":"IL",
    "sg:tags":[
        "product",
        "asphalt"
    ],
    "sg:website":"www.camllcil.com",
    "wof:name":"Cam LLC",
    "wof:placetype":"venue"
},
  "geometry": {"coordinates":[-90.06420300000001,38.830306],"type":"Point"}
}