{
  "type": "Feature",
  "properties": {
    "iso:country":"US",
    "sg:address":"4155 Southwest Hwy",
    "sg:city":"Hometown",
    "sg:classifiers":[
        {
            "category":"Retail",
            "subcategory":"Repair Shop",
            "type":"Services"
        }
    ],
    "sg:phone":"+1 708 423 9473",
    "sg:postcode":"60456",
    "sg:province":"IL",
    "sg:tags":[
        "scooter",
        "motorcycle",
        "motor"
    ],
    "wof:name":"After Hours Cycle By PCD",
    "wof:placetype":"venue"
},
  "geometry": {"coordinates":[-87.72253,41.734729],"type":"Point"}
}