{
  "type": "Feature",
  "properties": {
    "iso:country":"US",
    "sg:address":"221 N La Salle Street",
    "sg:city":"Chicago",
    "sg:classifiers":[
        {
            "category":"Professional",
            "subcategory":"Lawyer & Legal Services",
            "type":"Services"
        }
    ],
    "sg:phone":"+1 312 372 1440",
    "sg:postcode":"60601",
    "sg:province":"IL",
    "wof:name":"Di Bella Frank J Atty",
    "wof:placetype":"venue"
},
  "geometry": {"coordinates":[-87.632397,41.88641],"type":"Point"}
}