{
  "type": "Feature",
  "properties": {
    "addr:full":"1669 Montgomery Rd Aurora IL 60504",
    "addr:housenumber":"1669",
    "addr:postcode":"60504",
    "addr:street":"Montgomery Rd",
    "iso:country":"US",
    "sg:address":"1669 Montgomery Rd",
    "sg:city":"Aurora",
    "sg:classifiers":[
        {
            "category":"Sports & Exercise",
            "subcategory":"Gym",
            "type":"Entertainment"
        }
    ],
    "sg:phone":"+1 630 236 1881",
    "sg:postcode":"60504",
    "sg:province":"IL",
    "sg:tags":[
        "pilate"
    ],
    "wof:name":"Pilates Fitness Inc",
    "wof:placetype":"venue"
},
  "geometry": {"coordinates":[-88.267151,41.736233],"type":"Point"}
}