{
  "type": "Feature",
  "properties": {
    "addr:full":"1034 Warren Ave Downers Grove IL 60515",
    "addr:housenumber":"1034",
    "addr:postcode":"60515",
    "addr:street":"Warren Ave",
    "iso:country":"US",
    "sg:address":"1034 Warren Ave",
    "sg:city":"Downers Grove",
    "sg:classifiers":[
        {
            "category":"Health Services",
            "subcategory":"Doctor",
            "type":"Services"
        }
    ],
    "sg:phone":"+1 630 960 5310",
    "sg:postcode":"60515",
    "sg:province":"IL",
    "sg:tags":[
        "medical"
    ],
    "wof:name":"Dino S Delicata MD",
    "wof:placetype":"venue"
},
  "geometry": {"coordinates":[-88.01178,41.795976],"type":"Point"}
}