{
  "type": "Feature",
  "properties": {
    "addr:full":"13223 Cicero Ave Midlothian IL 60445",
    "addr:housenumber":"13223",
    "addr:postcode":"60445",
    "addr:street":"Cicero Ave",
    "iso:country":"US",
    "sg:address":"13223 Cicero Ave",
    "sg:city":"Midlothian",
    "sg:classifiers":[
        {
            "category":"Restaurant",
            "type":"Food & Drink"
        }
    ],
    "sg:menulink":"http://www.allmenus.com/il/worth/79903-pizza-hut/menu/",
    "sg:phone":"+1 708 388 9798",
    "sg:postcode":"60445",
    "sg:province":"IL",
    "sg:tags":[
        "american",
        "pizza"
    ],
    "wof:name":"Pizza Hut",
    "wof:placetype":"venue"
},
  "geometry": {"coordinates":[-87.73813699999999,41.651276],"type":"Point"}
}