{
  "type": "Feature",
  "properties": {
    "addr:full":"9450 Bryn Mawr Ave Des Plaines IL 60018",
    "addr:housenumber":"9450",
    "addr:postcode":"60018",
    "addr:street":"Bryn Mawr Ave",
    "iso:country":"US",
    "sg:address":"9450 Bryn Mawr Ave",
    "sg:city":"Des Plaines",
    "sg:classifiers":[
        {
            "category":"Building & Trades",
            "subcategory":"Construction",
            "type":"Services"
        }
    ],
    "sg:phone":"+1 847 928 2400",
    "sg:postcode":"60018",
    "sg:province":"IL",
    "wof:name":"Comcast",
    "wof:placetype":"venue"
},
  "geometry": {"coordinates":[-87.858058,41.980763],"type":"Point"}
}