{
  "type": "Feature",
  "properties": {
    "addr:full":"10610 3rd Ave Pleasant Prairie IL 53158",
    "addr:housenumber":"10610",
    "addr:postcode":"53158",
    "addr:street":"3Rd Ave",
    "iso:country":"US",
    "sg:address":"10610 3rd Ave",
    "sg:city":"Pleasant Prairie",
    "sg:classifiers":[
        {
            "category":"Building & Trades",
            "subcategory":"Construction",
            "type":"Services"
        }
    ],
    "sg:phone":"+1 262 697 1362",
    "sg:postcode":"53158",
    "sg:province":"IL",
    "sg:tags":[
        "residential"
    ],
    "wof:name":"Martin Lee Development Inc",
    "wof:placetype":"venue"
},
  "geometry": {"coordinates":[-87.815043,42.519902],"type":"Point"}
}