{
  "type": "Feature",
  "properties": {
    "iso:country":"US",
    "sg:address":"302 W Springfield Ave",
    "sg:city":"Champaign",
    "sg:classifiers":[
        {
            "category":"Banks & Credit Unions",
            "subcategory":"Bank",
            "type":"Services"
        }
    ],
    "sg:phone":"+1 217 366 4535",
    "sg:postcode":"61820",
    "sg:province":"IL",
    "sg:tags":[
        "national",
        "commercial"
    ],
    "sg:website":"www.centralillinoisbank.com",
    "wof:name":"Central Illinois Bank",
    "wof:placetype":"venue"
},
  "geometry": {"coordinates":[-88.247594,40.112687],"type":"Point"}
}