{
  "type": "Feature",
  "properties": {
    "addr:full":"305 W Main St Ottawa IL 61350",
    "addr:housenumber":"305",
    "addr:postcode":"61350",
    "addr:street":"W Main St",
    "iso:country":"US",
    "sg:address":"305 W Main St",
    "sg:city":"Ottawa",
    "sg:classifiers":[
        {
            "category":"Restaurant",
            "type":"Food & Drink"
        }
    ],
    "sg:phone":"+1 815 434 3378",
    "sg:postcode":"61350",
    "sg:province":"IL",
    "sg:tags":[
        "eating"
    ],
    "wof:name":"Szechuan Chinese Restaurant",
    "wof:placetype":"venue"
},
  "geometry": {"coordinates":[-88.845585,41.345653],"type":"Point"}
}