{
  "type": "Feature",
  "properties": {
    "addr:full":"1013 Kelly Ave Joliet IL 60435",
    "addr:housenumber":"1013",
    "addr:postcode":"60435",
    "addr:street":"Kelly Ave",
    "iso:country":"US",
    "sg:address":"1013 Kelly Ave",
    "sg:city":"Joliet",
    "sg:classifiers":[
        {
            "category":"Mining & Drilling",
            "type":"Manufacturing & Wholesale Goods"
        }
    ],
    "sg:phone":"+1 815 740 1869",
    "sg:postcode":"60435",
    "sg:province":"IL",
    "sg:tags":[
        "boring",
        "contractor"
    ],
    "wof:name":"Pro Tech Coring",
    "wof:placetype":"venue"
},
  "geometry": {"coordinates":[-88.10020299999999,41.541615],"type":"Point"}
}