{
  "type": "Feature",
  "properties": {
    "addr:full":"2943 W White Oaks Dr Springfield IL 62704",
    "addr:housenumber":"2943",
    "addr:postcode":"62704",
    "addr:street":"W White Oaks Dr",
    "iso:country":"US",
    "sg:address":"2943 W White Oaks Dr",
    "sg:city":"Springfield",
    "sg:classifiers":[
        {
            "category":"Health Services",
            "subcategory":"Doctor",
            "type":"Services"
        },
        {
            "category":"Health Services",
            "subcategory":"Dentist",
            "type":"Services"
        }
    ],
    "sg:phone":"+1 217 793 8899",
    "sg:postcode":"62704",
    "sg:province":"IL",
    "sg:tags":[
        "dentists-oral",
        "physician",
        "maxillofacial",
        "dental",
        "surgeons",
        "clinic",
        "surgery",
        "oral"
    ],
    "wof:name":"White Oaks Dental",
    "wof:placetype":"venue"
},
  "geometry": {"coordinates":[-89.71022000000001,39.765953],"type":"Point"}
}