{
  "type": "Feature",
  "properties": {
    "iso:country":"US",
    "sg:address":"932 Madison St",
    "sg:city":"Oak Park",
    "sg:classifiers":[
        {
            "category":"Food & Beverages",
            "subcategory":"Groceries & Convenience Stores",
            "type":"Retail Goods"
        }
    ],
    "sg:phone":"+1   ",
    "sg:postcode":"60302",
    "sg:province":"IL",
    "wof:name":"Ramels Oriental Food Store",
    "wof:placetype":"venue"
},
  "geometry": {"coordinates":[-87.798755,41.879763],"type":"Point"}
}