{
  "type": "Feature",
  "properties": {
    "iso:country":"US",
    "sg:address":"790 Royal Saint George Dr",
    "sg:city":"Naperville",
    "sg:phone":"+1 630 689 9538",
    "sg:postcode":"60563",
    "sg:province":"IL",
    "sg:website":"http://www.elegantesalons-spas.com",
    "wof:name":"Elegante Salons & Day Spas Of Naperville",
    "wof:placetype":"venue"
},
  "geometry": {"coordinates":[-88.167007,41.784111],"type":"Point"}
}