{
  "type": "Feature",
  "properties": {
    "iso:country":"US",
    "sg:address":"657 W Lake St",
    "sg:city":"Chicago",
    "sg:classifiers":[
        {
            "category":"Manufacturing",
            "subcategory":"Printing",
            "type":"Manufacturing & Wholesale Goods"
        }
    ],
    "sg:phone":"+1 312 559 8990",
    "sg:postcode":"60661",
    "sg:province":"IL",
    "sg:tags":[
        "distribution",
        "publishing"
    ],
    "wof:name":"Publishers Distribution Netwrk",
    "wof:placetype":"venue"
},
  "geometry": {"coordinates":[-87.644757,41.88562],"type":"Point"}
}