{
  "type": "Feature",
  "properties": {
    "addr:full":"4030 Kennedy Dr East Moline IL 61244",
    "addr:housenumber":"4030",
    "addr:postcode":"61244",
    "addr:street":"Kennedy Dr East",
    "iso:country":"US",
    "sg:address":"4030 Kennedy Dr",
    "sg:city":"East Moline",
    "sg:classifiers":[
        {
            "category":"Restaurant",
            "type":"Food & Drink"
        }
    ],
    "sg:phone":"+1 309 755 8427",
    "sg:postcode":"61244",
    "sg:province":"IL",
    "sg:tags":[
        "mexican"
    ],
    "sg:website":"www.adolphsmexicanfoods.com",
    "wof:name":"Adolph's Mexican Food",
    "wof:placetype":"venue"
},
  "geometry": {"coordinates":[-90.456299,41.492298],"type":"Point"}
}