{
  "type": "Feature",
  "properties": {
    "iso:country":"US",
    "sg:address":"3246 Quincy Mall",
    "sg:city":"Quincy",
    "sg:classifiers":[
        {
            "category":"Shopping",
            "subcategory":"Books",
            "type":"Retail Goods"
        }
    ],
    "sg:phone":"+1   ",
    "sg:postcode":"62301",
    "sg:province":"IL",
    "sg:tags":[
        "merchandise"
    ],
    "wof:name":"Mustard Seed Inc",
    "wof:placetype":"venue"
},
  "geometry": {"coordinates":[-91.364149,39.935713],"type":"Point"}
}