{
  "type": "Feature",
  "properties": {
    "iso:country":"US",
    "sg:address":"1190 Western Ave",
    "sg:city":"Northbrook",
    "sg:classifiers":[
        {
            "category":"Organizations",
            "subcategory":"Religious Organization",
            "type":"Services"
        }
    ],
    "sg:phone":"+1 847 205 9642",
    "sg:postcode":"60062",
    "sg:province":"IL",
    "sg:tags":[
        "church"
    ],
    "wof:name":"Glenbrook Korean United Meth",
    "wof:placetype":"venue"
},
  "geometry": {"coordinates":[-87.838859,42.133768],"type":"Point"}
}