{
  "type": "Feature",
  "properties": {
    "addr:full":"3260 N Clark St Apt 506 Chicago IL 60657",
    "addr:housenumber":"3260;506",
    "addr:postcode":"60657",
    "addr:street":"N Clark St Apt",
    "iso:country":"US",
    "sg:address":"3260 N Clark St Apt 506",
    "sg:city":"Chicago",
    "sg:classifiers":[
        {
            "category":"Professional",
            "subcategory":"Management & Consulting",
            "type":"Services"
        }
    ],
    "sg:phone":"+1 773 528 7450",
    "sg:postcode":"60657",
    "sg:province":"IL",
    "sg:tags":[
        "aviation",
        "consultant"
    ],
    "wof:name":"Prm Aviation Llc",
    "wof:placetype":"venue"
},
  "geometry": {"coordinates":[-87.651574,41.941159],"type":"Point"}
}