{
  "type": "Feature",
  "properties": {
    "iso:country":"US",
    "sg:address":"1101 W Park Ave",
    "sg:city":"Libertyville",
    "sg:classifiers":[
        {
            "category":"Retail",
            "subcategory":"Veterinary Services",
            "type":"Services"
        }
    ],
    "sg:phone":"+1 847 549 8500",
    "sg:postcode":"60048",
    "sg:province":"IL",
    "sg:tags":[
        "veterinarian"
    ],
    "wof:name":"Care Animal Hospital",
    "wof:placetype":"venue"
},
  "geometry": {"coordinates":[-87.97125699999999,42.281824],"type":"Point"}
}