{
  "type": "Feature",
  "properties": {
    "iso:country":"US",
    "sg:address":"2901 W Springfield Ave",
    "sg:city":"Champaign",
    "sg:classifiers":[
        {
            "category":"Recreation",
            "type":"Entertainment"
        }
    ],
    "sg:phone":"+1 217 355 0205",
    "sg:postcode":"61821",
    "sg:province":"IL",
    "sg:tags":[
        "club",
        "bridge",
        "membership",
        "instruction"
    ],
    "wof:name":"Bridge At Ginger Creek",
    "wof:placetype":"venue"
},
  "geometry": {"coordinates":[-88.293641,40.112931],"type":"Point"}
}