{
  "type": "Feature",
  "properties": {
    "addr:full":"1212 N Dearborn St Chicago IL 60610",
    "addr:housenumber":"1212",
    "addr:postcode":"60610",
    "addr:street":"N Dearborn St",
    "iso:country":"US",
    "sg:address":"1212 N Dearborn St",
    "sg:city":"Chicago",
    "sg:classifiers":[
        {
            "category":"Education",
            "subcategory":"School",
            "type":"Public Place"
        }
    ],
    "sg:phone":"+1 773 534 8690",
    "sg:postcode":"60610",
    "sg:province":"IL",
    "sg:tags":[
        "high",
        "middle",
        "elementary"
    ],
    "wof:name":"Schools Public",
    "wof:placetype":"venue"
},
  "geometry": {"coordinates":[-87.63043399999999,41.904391],"type":"Point"}
}