{
  "type": "Feature",
  "properties": {
    "iso:country":"US",
    "sg:address":"250 W Kenwood Ave",
    "sg:city":"Decatur",
    "sg:classifiers":[
        {
            "category":"Health Services",
            "subcategory":"Doctor",
            "type":"Services"
        }
    ],
    "sg:phone":"+1 217 872 3800",
    "sg:postcode":"62526",
    "sg:province":"IL",
    "sg:tags":[
        "physician",
        "family",
        "practice",
        "surgeons",
        "medicine"
    ],
    "wof:name":"Siu Family Physicians",
    "wof:placetype":"venue"
},
  "geometry": {"coordinates":[-88.958623,39.867395],"type":"Point"}
}