{
  "type": "Feature",
  "properties": {
    "iso:country":"US",
    "sg:address":"3310 N Harlem Avenue",
    "sg:city":"Chicago",
    "sg:classifiers":[
        {
            "category":"Professional",
            "subcategory":"Lawyer & Legal Services",
            "type":"Services"
        }
    ],
    "sg:phone":"+1 773 622 2660",
    "sg:postcode":"60634",
    "sg:province":"IL",
    "wof:name":"Paprocki Paul Atty At Law",
    "wof:placetype":"venue"
},
  "geometry": {"coordinates":[-87.806731,41.939897],"type":"Point"}
}