{
  "type": "Feature",
  "properties": {
    "iso:country":"US",
    "sg:address":"5239 W Diversey Ave",
    "sg:city":"Chicago",
    "sg:classifiers":[
        {
            "category":"Insurance",
            "subcategory":"Hazard Insurance",
            "type":"Services"
        },
        {
            "category":"Insurance",
            "subcategory":"Insurance Agent",
            "type":"Services"
        },
        {
            "category":"Insurance",
            "subcategory":"Life Insurance",
            "type":"Services"
        },
        {
            "category":"Insurance",
            "subcategory":"Title Insurance",
            "type":"Services"
        }
    ],
    "sg:phone":"+1 773 622 6715",
    "sg:postcode":"60639",
    "sg:province":"IL",
    "sg:tags":[
        "auto",
        "homeowner"
    ],
    "wof:name":"Olga Arbelo - Farmers Insurance",
    "wof:placetype":"venue"
},
  "geometry": {"coordinates":[-87.757335,41.931406],"type":"Point"}
}