{
  "type": "Feature",
  "properties": {
    "iso:country":"US",
    "sg:address":"112 W Grand Ave",
    "sg:city":"Chicago",
    "sg:classifiers":[
        {
            "category":"Shopping",
            "subcategory":"Florist",
            "type":"Retail Goods"
        }
    ],
    "sg:phone":"+1 312 494 0800",
    "sg:postcode":"60654",
    "sg:province":"IL",
    "sg:website":"www.raysposeypatch.com",
    "wof:name":"Ray's Posey Patch",
    "wof:placetype":"venue"
},
  "geometry": {"coordinates":[-87.63179700000001,41.891869],"type":"Point"}
}