{
  "type": "Feature",
  "properties": {
    "addr:full":"421 N Central Ave Wood Dale IL 60191",
    "addr:housenumber":"421",
    "addr:postcode":"60191",
    "addr:street":"N Central Ave",
    "iso:country":"US",
    "sg:address":"421 N Central Ave",
    "sg:city":"Wood Dale",
    "sg:classifiers":[
        {
            "category":"Building & Trades",
            "subcategory":"Construction",
            "type":"Services"
        }
    ],
    "sg:phone":"+1 630 860 2615",
    "sg:postcode":"60191",
    "sg:province":"IL",
    "sg:tags":[
        "carpentry",
        "contractor"
    ],
    "wof:name":"P & M Overhead Door Service",
    "wof:placetype":"venue"
},
  "geometry": {"coordinates":[-87.968959,41.968496],"type":"Point"}
}