{
  "type": "Feature",
  "properties": {
    "iso:country":"US",
    "sg:address":"460 Fort Hill Dr",
    "sg:city":"Naperville",
    "sg:classifiers":[
        {
            "category":"Retail",
            "subcategory":"Auto Rental",
            "type":"Services"
        }
    ],
    "sg:phone":"+1 630 983 4707",
    "sg:postcode":"60540",
    "sg:province":"IL",
    "sg:tags":[
        "car",
        "truck"
    ],
    "sg:website":"http://www.enterprise.com",
    "wof:name":"Enterprise Rent-A-Car",
    "wof:placetype":"venue"
},
  "geometry": {"coordinates":[-88.19598999999999,41.76606],"type":"Point"}
}