{
  "type": "Feature",
  "properties": {
    "iso:country":"US",
    "sg:address":"15 Suzy Q Cir",
    "sg:city":"De Soto",
    "sg:classifiers":[
        {
            "category":"Professional",
            "type":"Services"
        }
    ],
    "sg:phone":"+1 618 867 2484",
    "sg:postcode":"62924",
    "sg:province":"IL",
    "sg:tags":[
        "establishment"
    ],
    "wof:name":"Nanna's House",
    "wof:placetype":"venue"
},
  "geometry": {"coordinates":[-89.25439,37.849647],"type":"Point"}
}