{
  "type": "Feature",
  "properties": {
    "addr:full":"1603 Orrington Avenue, Suite 2050 Evanston IL 60201",
    "addr:housenumber":"1603",
    "addr:postcode":"60201",
    "addr:street":"Orrington Avenue Suite 2050",
    "iso:country":"US",
    "sg:address":"1603 Orrington Avenue, Suite 2050",
    "sg:city":"Evanston",
    "sg:classifiers":[
        {
            "category":"Professional",
            "subcategory":"Computer Services",
            "type":"Services"
        }
    ],
    "sg:phone":"+1 847 332 0400",
    "sg:postcode":"60201",
    "sg:province":"IL",
    "sg:website":"http://www.silveroaksp.com",
    "wof:name":"Silver Oak Services Partners",
    "wof:placetype":"venue"
},
  "geometry": {"coordinates":[-87.680701,42.048195],"type":"Point"}
}