{
  "type": "Feature",
  "properties": {
    "iso:country":"US",
    "sg:address":"2926 W Belmont Ave",
    "sg:city":"Chicago",
    "sg:classifiers":[
        {
            "category":"Personal",
            "subcategory":"Beauty Salon",
            "type":"Services"
        }
    ],
    "sg:phone":"+1 773 478 1097",
    "sg:postcode":"60618",
    "sg:province":"IL",
    "sg:tags":[
        "hair"
    ],
    "wof:name":"Orlando's Hair Studio",
    "wof:placetype":"venue"
},
  "geometry": {"coordinates":[-87.70128099999999,41.939636],"type":"Point"}
}