{
  "type": "Feature",
  "properties": {
    "iso:country":"US",
    "sg:address":"4237 State Rte 160",
    "sg:city":"Highland",
    "sg:classifiers":[
        {
            "category":"Professional",
            "subcategory":"Management & Consulting",
            "type":"Services"
        }
    ],
    "sg:phone":"+1 618 675 3834",
    "sg:postcode":"62249",
    "sg:province":"IL",
    "sg:tags":[
        "business"
    ],
    "wof:name":"Steiner Summit Resources",
    "wof:placetype":"venue"
},
  "geometry": {"coordinates":[-89.66896800000001,38.811368],"type":"Point"}
}