{
  "type": "Feature",
  "properties": {
    "addr:full":"125 Tubeway Dr Carol Stream IL 60188",
    "addr:housenumber":"125",
    "addr:postcode":"60188",
    "addr:street":"Tubeway Dr",
    "iso:country":"US",
    "sg:address":"125 Tubeway Dr",
    "sg:city":"Carol Stream",
    "sg:classifiers":[
        {
            "category":"Wholesale",
            "subcategory":"Machinery & Supplies",
            "type":"Manufacturing & Wholesale Goods"
        }
    ],
    "sg:phone":"+1 630 690 7200",
    "sg:postcode":"60188",
    "sg:province":"IL",
    "sg:tags":[
        "forming",
        "cutting",
        "metal",
        "plastic"
    ],
    "sg:website":"www.capitalequipment.com",
    "wof:name":"Capital Equipment LLC",
    "wof:placetype":"venue"
},
  "geometry": {"coordinates":[-88.12805299999999,41.89593],"type":"Point"}
}