{
  "type": "Feature",
  "properties": {
    "iso:country":"US",
    "sg:address":"1278 E Dundee Rd",
    "sg:city":"Palatine",
    "sg:classifiers":[
        {
            "category":"Restaurant",
            "type":"Food & Drink"
        }
    ],
    "sg:phone":"+1   ",
    "sg:postcode":"60074",
    "sg:province":"IL",
    "sg:tags":[
        "eating"
    ],
    "wof:name":"Qiznos Classics Subs",
    "wof:placetype":"venue"
},
  "geometry": {"coordinates":[-88.01353899999999,42.139214],"type":"Point"}
}