{
  "type": "Feature",
  "properties": {
    "iso:country":"US",
    "sg:address":"2439 Gurler Rd",
    "sg:city":"Ashton",
    "sg:classifiers":[
        {
            "category":"Professional",
            "subcategory":"Advertising",
            "type":"Services"
        }
    ],
    "sg:phone":"+1 815 562 2462",
    "sg:postcode":"61006",
    "sg:province":"IL",
    "sg:tags":[
        "distribution"
    ],
    "wof:name":"Schmitz Distributing",
    "wof:placetype":"venue"
},
  "geometry": {"coordinates":[-89.165687,41.889387],"type":"Point"}
}