{
  "type": "Feature",
  "properties": {
    "iso:country":"US",
    "sg:address":"304 S Maple St",
    "sg:city":"Brighton",
    "sg:classifiers":[
        {
            "category":"Place Of Worship",
            "subcategory":"Church",
            "type":"Public Place"
        },
        {
            "category":"Place Of Worship",
            "type":"Public Place"
        }
    ],
    "sg:phone":"+1 618 372 3201",
    "sg:postcode":"62012",
    "sg:province":"IL",
    "sg:tags":[
        "churches-baptist-general",
        "churches-baptist"
    ],
    "wof:name":"First Baptist Church",
    "wof:placetype":"venue"
},
  "geometry": {"coordinates":[-90.144874,39.036568],"type":"Point"}
}