{
  "type": "Feature",
  "properties": {
    "iso:country":"US",
    "sg:address":"14150 Cristina Ave",
    "sg:city":"Orland Park",
    "sg:classifiers":[
        {
            "category":"Building & Trades",
            "subcategory":"Construction",
            "type":"Services"
        }
    ],
    "sg:phone":"+1 708 349 6910",
    "sg:postcode":"60462",
    "sg:province":"IL",
    "sg:tags":[
        "house"
    ],
    "wof:name":"R&R Quality Construction",
    "wof:placetype":"venue"
},
  "geometry": {"coordinates":[-87.824245,41.632438],"type":"Point"}
}