{
  "type": "Feature",
  "properties": {
    "iso:country":"US",
    "sg:address":"909 W Willow Ln",
    "sg:city":"Mount Prospect",
    "sg:classifiers":[
        {
            "category":"Professional",
            "subcategory":"Computer Services",
            "type":"Services"
        }
    ],
    "sg:phone":"+1 847 437 1406",
    "sg:postcode":"60056",
    "sg:province":"IL",
    "sg:tags":[
        "related"
    ],
    "wof:name":"Enzo Inc",
    "wof:placetype":"venue"
},
  "geometry": {"coordinates":[-87.950295,42.044892],"type":"Point"}
}