{
  "type": "Feature",
  "properties": {
    "iso:country":"US",
    "sg:address":"1512 S Ridgeway Ave",
    "sg:city":"Chicago",
    "sg:classifiers":[
        {
            "category":"Landmark",
            "subcategory":"Tourist Information",
            "type":"Public Place"
        }
    ],
    "sg:phone":"+1 312 545 1372",
    "sg:postcode":"60623",
    "sg:province":"IL",
    "sg:tags":[
        "promoter",
        "tours-operators"
    ],
    "wof:name":"Travel With Style",
    "wof:placetype":"venue"
},
  "geometry": {"coordinates":[-87.7189,41.860525],"type":"Point"}
}