{
  "type": "Feature",
  "properties": {
    "addr:full":"7823 S Ellis Ave Chicago IL 60619",
    "addr:housenumber":"7823",
    "addr:postcode":"60619",
    "addr:street":"S Ellis Ave",
    "iso:country":"US",
    "sg:address":"7823 S Ellis Ave",
    "sg:city":"Chicago",
    "sg:classifiers":[
        {
            "category":"Education",
            "subcategory":"School",
            "type":"Public Place"
        }
    ],
    "sg:phone":"+1 773 651 1221",
    "sg:postcode":"60619",
    "sg:province":"IL",
    "sg:website":"http://www.prhs.org",
    "wof:name":"Board Of Education Of City Of Chicago",
    "wof:placetype":"venue"
},
  "geometry": {"coordinates":[-87.60035000000001,41.75274],"type":"Point"}
}