{
  "type": "Feature",
  "properties": {
    "iso:country":"US",
    "sg:address":"1830 E Roosevelt Rd",
    "sg:city":"Glen Ellyn",
    "sg:classifiers":[
        {
            "category":"Autos & Motor Vehicles",
            "subcategory":"Automobile Sales",
            "type":"Retail Goods"
        },
        {
            "category":"Retail",
            "subcategory":"Auto Repair",
            "type":"Services"
        }
    ],
    "sg:phone":"+1 630 668 8870",
    "sg:postcode":"60137",
    "sg:province":"IL",
    "sg:tags":[
        "body",
        "shop",
        "car"
    ],
    "wof:name":"Ford Authorized Service",
    "wof:placetype":"venue"
},
  "geometry": {"coordinates":[-88.063103,41.8675],"type":"Point"}
}