{
  "type": "Feature",
  "properties": {
    "iso:country":"US",
    "sg:address":"901 4th St",
    "sg:city":"Hampton",
    "sg:classifiers":[
        {
            "category":"Government",
            "subcategory":"Police Station",
            "type":"Public Place"
        }
    ],
    "sg:phone":"+1 309 496 9123",
    "sg:postcode":"61256",
    "sg:province":"IL",
    "sg:tags":[
        "department"
    ],
    "wof:name":"Hampton Police Department",
    "wof:placetype":"venue"
},
  "geometry": {"coordinates":[-90.40387699999999,41.551449],"type":"Point"}
}