{
  "type": "Feature",
  "properties": {
    "addr:full":"8995 W 95th St Palos Hills IL 60465",
    "addr:housenumber":"8995",
    "addr:postcode":"60465",
    "addr:street":"W 95Th St",
    "iso:country":"US",
    "sg:address":"8995 W 95th St",
    "sg:city":"Palos Hills",
    "sg:classifiers":[
        {
            "category":"Building & Trades",
            "subcategory":"Construction",
            "type":"Services"
        }
    ],
    "sg:phone":"+1 708 233 3800",
    "sg:postcode":"60465",
    "sg:province":"IL",
    "sg:tags":[
        "contractor"
    ],
    "wof:name":"Hartz Construction Co Corporate Office",
    "wof:placetype":"venue"
},
  "geometry": {"coordinates":[-87.840103,41.718102],"type":"Point"}
}