{
  "type": "Feature",
  "properties": {
    "iso:country":"US",
    "sg:address":"510 Doxbury Ln",
    "sg:city":"New Lenox",
    "sg:classifiers":[
        {
            "category":"Building & Trades",
            "subcategory":"Construction",
            "type":"Services"
        }
    ],
    "sg:phone":"+1 815 723 8049",
    "sg:postcode":"60451",
    "sg:province":"IL",
    "sg:tags":[
        "painter"
    ],
    "wof:name":"Laura's Painting & Custom Deck",
    "wof:placetype":"venue"
},
  "geometry": {"coordinates":[-88.008748,41.517186],"type":"Point"}
}