{
  "type": "Feature",
  "properties": {
    "addr:full":"1300 Glen Rock Ave Waukegan IL 60085",
    "addr:housenumber":"1300",
    "addr:postcode":"60085",
    "addr:street":"Glen Rock Ave",
    "iso:country":"US",
    "sg:address":"1300 Glen Rock Ave",
    "sg:city":"Waukegan",
    "sg:classifiers":[
        {
            "category":"Restaurant",
            "type":"Food & Drink"
        }
    ],
    "sg:phone":"+1 847 782 8660",
    "sg:postcode":"60085",
    "sg:province":"IL",
    "wof:name":"Jalisco Restaurant",
    "wof:placetype":"venue"
},
  "geometry": {"coordinates":[-87.84764,42.354639],"type":"Point"}
}