{
  "type": "Feature",
  "properties": {
    "addr:full":"1025 Florence Ave Pekin IL 61554",
    "addr:housenumber":"1025",
    "addr:postcode":"61554",
    "addr:street":"Florence Ave",
    "iso:country":"US",
    "sg:address":"1025 Florence Ave",
    "sg:city":"Pekin",
    "sg:classifiers":[
        {
            "category":"Structure",
            "subcategory":"Warehouse",
            "type":"Public Place"
        },
        {
            "category":"Retail",
            "subcategory":"Storage",
            "type":"Services"
        }
    ],
    "sg:phone":"+1 309 346 4150",
    "sg:postcode":"61554",
    "sg:province":"IL",
    "sg:tags":[
        "self",
        "commercial",
        "warehouses-public-commercial",
        "household"
    ],
    "wof:name":"Florence Avenue Mini Storage",
    "wof:placetype":"venue"
},
  "geometry": {"coordinates":[-89.62337100000001,40.575583],"type":"Point"}
}