{
  "type": "Feature",
  "properties": {
    "addr:full":"207 E Quincy St Pleasant Hill IL 62366",
    "addr:housenumber":"207 e",
    "addr:postcode":"62366",
    "addr:street":"Quincy St",
    "iso:country":"US",
    "sg:address":"207 E Quincy St",
    "sg:city":"Pleasant Hill",
    "sg:classifiers":[
        {
            "category":"Autos & Motor Vehicles",
            "subcategory":"Fuel & Gas Station",
            "type":"Retail Goods"
        }
    ],
    "sg:phone":"+1 217 734 9013",
    "sg:postcode":"62366",
    "sg:province":"IL",
    "sg:tags":[
        "oil"
    ],
    "wof:name":"Hannel's Service Station",
    "wof:placetype":"venue"
},
  "geometry": {"coordinates":[-90.87082700000001,39.44287],"type":"Point"}
}