{
  "type": "Feature",
  "properties": {
    "iso:country":"US",
    "sg:address":"2106 N US Hwy 12",
    "sg:city":"Spring Grove",
    "sg:classifiers":[
        {
            "category":"Bars & Pubs",
            "type":"Food & Drink"
        }
    ],
    "sg:phone":"+1 815 675 2779",
    "sg:postcode":"60081",
    "sg:province":"IL",
    "wof:name":"5 O'Clock Whistle",
    "wof:placetype":"venue"
},
  "geometry": {"coordinates":[-88.23768699999999,42.437196],"type":"Point"}
}