{
  "type": "Feature",
  "properties": {
    "addr:full":"1409 W Harrison St Freeport IL 61032",
    "addr:housenumber":"1409",
    "addr:postcode":"61032",
    "addr:street":"W Harrison St",
    "iso:country":"US",
    "sg:address":"1409 W Harrison St",
    "sg:city":"Freeport",
    "sg:classifiers":[
        {
            "category":"Building & Trades",
            "subcategory":"Construction",
            "type":"Services"
        }
    ],
    "sg:phone":"+1 815 266 2582",
    "sg:postcode":"61032",
    "sg:province":"IL",
    "sg:tags":[
        "painter"
    ],
    "wof:name":"Mark's Painting",
    "wof:placetype":"venue"
},
  "geometry": {"coordinates":[-89.647244,42.29215],"type":"Point"}
}