{
  "type": "Feature",
  "properties": {
    "iso:country":"US",
    "sg:address":"4111 W Eastwood Ave",
    "sg:city":"Chicago",
    "sg:classifiers":[
        {
            "category":"Organizations",
            "subcategory":"Non-profit Organization",
            "type":"Services"
        }
    ],
    "sg:phone":"+1 773 545 0632",
    "sg:postcode":"60630",
    "sg:province":"IL",
    "sg:tags":[
        "service/non-profit",
        "community"
    ],
    "wof:name":"Neumann Association",
    "wof:placetype":"venue"
},
  "geometry": {"coordinates":[-87.730467,41.965393],"type":"Point"}
}