{
  "type": "Feature",
  "properties": {
    "iso:country":"US",
    "sg:address":"2605 N Pecatonica Rd",
    "sg:city":"Pecatonica",
    "sg:classifiers":[
        {
            "category":"Retail",
            "subcategory":"Repair Shop",
            "type":"Services"
        }
    ],
    "sg:phone":"+1 815 239 1480",
    "sg:postcode":"61063",
    "sg:province":"IL",
    "wof:name":"NIEA",
    "wof:placetype":"venue"
},
  "geometry": {"coordinates":[-89.359144,42.298693],"type":"Point"}
}