{
  "type": "Feature",
  "properties": {
    "addr:full":"1719 S Euclid Ave Princeton IL 61356",
    "addr:housenumber":"1719",
    "addr:postcode":"61356",
    "addr:street":"S Euclid Ave",
    "iso:country":"US",
    "sg:address":"1719 S Euclid Ave",
    "sg:city":"Princeton",
    "sg:classifiers":[
        {
            "category":"Organizations",
            "subcategory":"Religious Organization",
            "type":"Services"
        }
    ],
    "sg:phone":"+1 815 879 6441",
    "sg:postcode":"61356",
    "sg:province":"IL",
    "sg:tags":[
        "church"
    ],
    "sg:website":"www.fbcprinceton.org",
    "wof:name":"First Baptist Church Inc",
    "wof:placetype":"venue"
},
  "geometry": {"coordinates":[-89.46004499999999,41.360088],"type":"Point"}
}