{
  "type": "Feature",
  "properties": {
    "iso:country":"US",
    "sg:address":"201 S Central Ave",
    "sg:city":"Paris",
    "sg:classifiers":[
        {
            "category":"Place Of Worship",
            "subcategory":"Church",
            "type":"Public Place"
        },
        {
            "category":"Place Of Worship",
            "type":"Public Place"
        }
    ],
    "sg:phone":"+1 217 463 1600",
    "sg:postcode":"61944",
    "sg:province":"IL",
    "sg:tags":[
        "churches-baptist-general",
        "churches-baptist"
    ],
    "wof:name":"First Baptist Church",
    "wof:placetype":"venue"
},
  "geometry": {"coordinates":[-87.69574,39.59346],"type":"Point"}
}