{
  "type": "Feature",
  "properties": {
    "iso:country":"US",
    "sg:address":"5S680 Heather Ct",
    "sg:city":"Naperville",
    "sg:classifiers":[
        {
            "category":"Home & Garden",
            "subcategory":"Carpets & Floor Coverings",
            "type":"Retail Goods"
        }
    ],
    "sg:phone":"+1 630 717 8734",
    "sg:postcode":"60540",
    "sg:province":"IL",
    "sg:tags":[
        "distributor",
        "rug",
        "manufacturer"
    ],
    "wof:name":"Bag And Brew Inc",
    "wof:placetype":"venue"
},
  "geometry": {"coordinates":[-88.108788,41.78688],"type":"Point"}
}