{
  "type": "Feature",
  "properties": {
    "iso:country":"US",
    "sg:address":"1156 W 79th Street",
    "sg:city":"Chicago",
    "sg:classifiers":[
        {
            "category":"Food & Beverages",
            "subcategory":"Groceries & Convenience Stores",
            "type":"Retail Goods"
        }
    ],
    "sg:phone":"+1 773 723 7000",
    "sg:postcode":"60620",
    "sg:province":"IL",
    "wof:name":"Bj's On Racine",
    "wof:placetype":"venue"
},
  "geometry": {"coordinates":[-87.653246,41.750523],"type":"Point"}
}