{
  "type": "Feature",
  "properties": {
    "iso:country":"US",
    "sg:address":"1712 4th St",
    "sg:city":"Peru",
    "sg:classifiers":[
        {
            "category":"Insurance",
            "subcategory":"Insurance Agent",
            "type":"Services"
        }
    ],
    "sg:phone":"+1 815 223 1900",
    "sg:postcode":"61354",
    "sg:province":"IL",
    "sg:website":"www.henryhackman.com",
    "wof:name":"State Farm Insurance",
    "wof:placetype":"venue"
},
  "geometry": {"coordinates":[-89.12903799999999,41.327542],"type":"Point"}
}