{
  "type": "Feature",
  "properties": {
    "iso:country":"US",
    "sg:address":"1119 Lynnville Woodson Rd",
    "sg:city":"Jacksonville",
    "sg:classifiers":[
        {
            "category":"Freight",
            "type":"Transportation"
        }
    ],
    "sg:phone":"+1 217 243 7077",
    "sg:postcode":"62650",
    "sg:province":"IL",
    "sg:tags":[
        "hauling",
        "trucking"
    ],
    "wof:name":"Young Trucking Inc",
    "wof:placetype":"venue"
},
  "geometry": {"coordinates":[-90.326954,39.681141],"type":"Point"}
}