{
  "type": "Feature",
  "properties": {
    "addr:full":"5824 W Division St Chicago IL 60651",
    "addr:housenumber":"5824",
    "addr:postcode":"60651",
    "addr:street":"W Division St",
    "iso:country":"US",
    "sg:address":"5824 W Division St",
    "sg:city":"Chicago",
    "sg:classifiers":[
        {
            "category":"Food & Beverages",
            "subcategory":"Groceries & Convenience Stores",
            "type":"Retail Goods"
        }
    ],
    "sg:phone":"+1 773 287 3007",
    "sg:postcode":"60651",
    "sg:province":"IL",
    "wof:name":"499 Dollar Store",
    "wof:placetype":"venue"
},
  "geometry": {"coordinates":[-87.771373,41.902212],"type":"Point"}
}