{
  "type": "Feature",
  "properties": {
    "addr:full":"1400 S Lake Shore Dr Museum Campus Chicago IL 60605",
    "addr:housenumber":"1400",
    "addr:postcode":"60605",
    "addr:street":"S Lake Shore",
    "iso:country":"US",
    "sg:address":"1400 S Lake Shore Dr Museum Campus",
    "sg:city":"Chicago",
    "sg:classifiers":[
        {
            "category":"Food & Beverages",
            "subcategory":"Meat & Fish",
            "type":"Retail Goods"
        }
    ],
    "sg:postcode":"60605",
    "sg:province":"IL",
    "sg:tags":[
        "hot",
        "dog"
    ],
    "wof:name":"Kim & Carlos Hot Dog Stand",
    "wof:placetype":"venue"
},
  "geometry": {"coordinates":[-87.618689,41.862568],"type":"Point"}
}