{
  "type": "Feature",
  "properties": {
    "iso:country":"US",
    "sg:address":"2133 Parkside Dr",
    "sg:city":"Park Ridge",
    "sg:classifiers":[
        {
            "category":"Retail",
            "subcategory":"Portrait Studio",
            "type":"Services"
        }
    ],
    "sg:phone":"+1 847 297 5343",
    "sg:postcode":"60068",
    "sg:province":"IL",
    "sg:tags":[
        "photo"
    ],
    "wof:name":"Santhoum Pictures",
    "wof:placetype":"venue"
},
  "geometry": {"coordinates":[-87.846563,42.045113],"type":"Point"}
}