{
  "type": "Feature",
  "properties": {
    "iso:country":"US",
    "sg:address":"17 S Wabash Avenue",
    "sg:city":"Chicago",
    "sg:classifiers":[
        {
            "category":"Fast Food",
            "type":"Food & Drink"
        }
    ],
    "sg:phone":"+1 312 578 1133",
    "sg:postcode":"60603",
    "sg:province":"IL",
    "wof:name":"Gold Coast Hot Dog",
    "wof:placetype":"venue"
},
  "geometry": {"coordinates":[-87.62612300000001,41.881984],"type":"Point"}
}