{
  "type": "Feature",
  "properties": {
    "iso:country":"US",
    "sg:address":"2644 N Mozart St",
    "sg:city":"Chicago",
    "sg:classifiers":[
        {
            "category":"Organizations",
            "subcategory":"Membership Organization",
            "type":"Services"
        }
    ],
    "sg:phone":"+1 773 489 6396",
    "sg:postcode":"60647",
    "sg:province":"IL",
    "wof:name":"Windy City Arts",
    "wof:placetype":"venue"
},
  "geometry": {"coordinates":[-87.698915,41.931811],"type":"Point"}
}