{
  "type": "Feature",
  "properties": {
    "addr:full":"2638 Kory Dr Columbia IL 62236",
    "addr:housenumber":"2638",
    "addr:postcode":"62236",
    "addr:street":"Kory Dr",
    "iso:country":"US",
    "sg:address":"2638 Kory Dr",
    "sg:city":"Columbia",
    "sg:classifiers":[
        {
            "category":"Professional",
            "subcategory":"Business Services",
            "type":"Services"
        }
    ],
    "sg:phone":"+1 618 281 9562",
    "sg:postcode":"62236",
    "sg:province":"IL",
    "sg:tags":[
        "consultant",
        "coach"
    ],
    "wof:name":"Stl Shipping Consultants",
    "wof:placetype":"venue"
},
  "geometry": {"coordinates":[-90.22072199999999,38.470337],"type":"Point"}
}