{
  "type": "Feature",
  "properties": {
    "addr:full":"1206 W Lawrence Ave Chicago IL 60640",
    "addr:housenumber":"1206",
    "addr:postcode":"60640",
    "addr:street":"W Lawrence Ave",
    "iso:country":"US",
    "sg:address":"1206 W Lawrence Ave",
    "sg:city":"Chicago",
    "sg:classifiers":[
        {
            "category":"Restaurant",
            "type":"Food & Drink"
        }
    ],
    "sg:phone":"+1   ",
    "sg:postcode":"60640",
    "sg:province":"IL",
    "sg:tags":[
        "eating"
    ],
    "wof:name":"Taquerias Uptown",
    "wof:placetype":"venue"
},
  "geometry": {"coordinates":[-87.661203,41.969173],"type":"Point"}
}