{
  "type": "Feature",
  "properties": {
    "iso:country":"US",
    "sg:address":"13984 S Grace Ave",
    "sg:city":"Robbins",
    "sg:classifiers":[
        {
            "category":"Professional",
            "type":"Services"
        }
    ],
    "sg:phone":"+1 708 597 7416",
    "sg:postcode":"60472",
    "sg:province":"IL",
    "sg:tags":[
        "establishment"
    ],
    "wof:name":"Everett Smith LLC",
    "wof:placetype":"venue"
},
  "geometry": {"coordinates":[-87.704201,41.639639],"type":"Point"}
}