{
  "type": "Feature",
  "properties": {
    "addr:full":"4837 Eastwood Ct Waukegan IL 60087",
    "addr:housenumber":"4837",
    "addr:postcode":"60087",
    "addr:street":"Eastwood Ct",
    "iso:country":"US",
    "sg:address":"4837 Eastwood Ct",
    "sg:city":"Waukegan",
    "sg:classifiers":[
        {
            "category":"Social Services",
            "type":"Services"
        }
    ],
    "sg:phone":"+1 847 244 3795",
    "sg:postcode":"60087",
    "sg:province":"IL",
    "sg:tags":[
        "counseling"
    ],
    "wof:name":"Hughes Community & Family",
    "wof:placetype":"venue"
},
  "geometry": {"coordinates":[-87.92168599999999,42.412879],"type":"Point"}
}