{
  "type": "Feature",
  "properties": {
    "iso:country":"US",
    "sg:address":"219 S Main St",
    "sg:city":"Galena",
    "sg:classifiers":[
        {
            "category":"Shopping",
            "subcategory":"Florist",
            "type":"Retail Goods"
        }
    ],
    "sg:phone":"+1 815 777 6882",
    "sg:postcode":"61036",
    "sg:province":"IL",
    "wof:name":"Floral Chic",
    "wof:placetype":"venue"
},
  "geometry": {"coordinates":[-90.429565,42.41559],"type":"Point"}
}