{
  "type": "Feature",
  "properties": {
    "iso:country":"US",
    "sg:address":"101 Kingsbury Ct",
    "sg:city":"Collinsville",
    "sg:classifiers":[
        {
            "category":"Retail",
            "subcategory":"Laundry & Dry Cleaning",
            "type":"Services"
        }
    ],
    "sg:phone":"+1 618 344 0766",
    "sg:postcode":"62234",
    "sg:province":"IL",
    "wof:name":"High Dry Crpet/Upholsetry Care",
    "wof:placetype":"venue"
},
  "geometry": {"coordinates":[-89.992582,38.692762],"type":"Point"}
}