{
  "type": "Feature",
  "properties": {
    "addr:full":"770 Lee St Des Plaines IL 60016",
    "addr:housenumber":"770",
    "addr:postcode":"60016",
    "addr:street":"Lee St",
    "iso:country":"US",
    "sg:address":"770 Lee St",
    "sg:city":"Des Plaines",
    "sg:classifiers":[
        {
            "category":"Professional",
            "subcategory":"Lawyer & Legal Services",
            "type":"Services"
        }
    ],
    "sg:phone":"+1 847 827 6884",
    "sg:postcode":"60016",
    "sg:province":"IL",
    "wof:name":"Brian Y Hamilton Atty",
    "wof:placetype":"venue"
},
  "geometry": {"coordinates":[-87.889859,42.039179],"type":"Point"}
}