{
  "type": "Feature",
  "properties": {
    "iso:country":"US",
    "sg:address":"800 W 1st St",
    "sg:city":"Homer",
    "sg:classifiers":[
        {
            "category":"Manufacturing",
            "subcategory":"Leather Goods",
            "type":"Manufacturing & Wholesale Goods"
        }
    ],
    "sg:phone":"+1 217 896 2437",
    "sg:postcode":"61849",
    "sg:province":"IL",
    "sg:tags":[
        "manufacture",
        "bag"
    ],
    "wof:name":"Toshware Inc",
    "wof:placetype":"venue"
},
  "geometry": {"coordinates":[-87.96704699999999,40.036137],"type":"Point"}
}