{
  "type": "Feature",
  "properties": {
    "iso:country":"US",
    "sg:address":"5555 Elinor Ave",
    "sg:city":"Downers Grove",
    "sg:classifiers":[
        {
            "category":"Building & Trades",
            "subcategory":"Plumbing",
            "type":"Services"
        }
    ],
    "sg:phone":"+1 630 964 7767",
    "sg:postcode":"60515",
    "sg:province":"IL",
    "sg:tags":[
        "contractor"
    ],
    "wof:name":"Ondracek Mechanical Services",
    "wof:placetype":"venue"
},
  "geometry": {"coordinates":[-88.04450799999999,41.787193],"type":"Point"}
}