{
  "type": "Feature",
  "properties": {
    "iso:country":"US",
    "sg:address":"6521 Main St",
    "sg:city":"Union",
    "sg:classifiers":[
        {
            "category":"Building & Trades",
            "subcategory":"Plumbing",
            "type":"Services"
        }
    ],
    "sg:phone":"+1 815 923 4510",
    "sg:postcode":"60180",
    "sg:province":"IL",
    "sg:tags":[
        "tank",
        "installation"
    ],
    "sg:website":"www.jdmech.com",
    "wof:name":"J & D Mechanical Industries",
    "wof:placetype":"venue"
},
  "geometry": {"coordinates":[-88.542977,42.233858],"type":"Point"}
}