{
  "type": "Feature",
  "properties": {
    "addr:full":"258 W Broadway St Bradley IL 60915",
    "addr:housenumber":"258",
    "addr:postcode":"60915",
    "addr:street":"W Broadway St",
    "iso:country":"US",
    "sg:address":"258 W Broadway St",
    "sg:city":"Bradley",
    "sg:classifiers":[
        {
            "category":"Government",
            "subcategory":"Post Office",
            "type":"Public Place"
        }
    ],
    "sg:phone":"+1 815 932 4133",
    "sg:postcode":"60915",
    "sg:province":"IL",
    "sg:tags":[
        "postal",
        "us"
    ],
    "wof:name":"Main Post Office",
    "wof:placetype":"venue"
},
  "geometry": {"coordinates":[-87.86423499999999,41.142216],"type":"Point"}
}