{
  "type": "Feature",
  "properties": {
    "iso:country":"US",
    "sg:address":"700 W Elk Grove Blvd",
    "sg:city":"Elk Grove Vlg",
    "sg:classifiers":[
        {
            "category":"Real Estate",
            "subcategory":"Architect",
            "type":"Services"
        }
    ],
    "sg:phone":"+1 847 952 9362",
    "sg:postcode":"60007",
    "sg:province":"IL",
    "wof:name":"Complete Concept Group Inc",
    "wof:placetype":"venue"
},
  "geometry": {"coordinates":[-87.99382900000001,42.008449],"type":"Point"}
}