{
  "type": "Feature",
  "properties": {
    "addr:full":"968 Brook Forest Ave Shorewood IL 60431",
    "addr:housenumber":"968",
    "addr:postcode":"60431",
    "addr:street":"Brook Forest Ave",
    "iso:country":"US",
    "sg:address":"968 Brook Forest Ave",
    "sg:city":"Shorewood",
    "sg:classifiers":[
        {
            "category":"Health Services",
            "subcategory":"Doctor",
            "type":"Services"
        }
    ],
    "sg:phone":"+1 815 254 1177",
    "sg:postcode":"60431",
    "sg:province":"IL",
    "sg:tags":[
        "dentist"
    ],
    "wof:name":"Troy Dental",
    "wof:placetype":"venue"
},
  "geometry": {"coordinates":[-88.199262,41.539153],"type":"Point"}
}