{
  "type": "Feature",
  "properties": {
    "iso:country":"US",
    "sg:address":"735 Hunter Dr",
    "sg:city":"Batavia",
    "sg:classifiers":[
        {
            "category":"Shopping",
            "type":"Retail Goods"
        },
        {
            "category":"Wholesale",
            "subcategory":"Electrical",
            "type":"Manufacturing & Wholesale Goods"
        }
    ],
    "sg:phone":"+1 630 406 5400",
    "sg:postcode":"60510",
    "sg:province":"IL",
    "sg:tags":[
        "mfg",
        "house",
        "system",
        "radio",
        "communication",
        "mail",
        "merchandise"
    ],
    "wof:name":"Communications Direct Inc",
    "wof:placetype":"venue"
},
  "geometry": {"coordinates":[-88.27440799999999,41.858945],"type":"Point"}
}