{
  "type": "Feature",
  "properties": {
    "iso:country":"US",
    "sg:address":"702 Halstead Ave",
    "sg:city":"Romeoville",
    "sg:classifiers":[
        {
            "category":"Arena",
            "subcategory":"Sports Club",
            "type":"Entertainment"
        }
    ],
    "sg:phone":"+1 815 886 9716",
    "sg:postcode":"60446",
    "sg:province":"IL",
    "sg:tags":[
        "soccer"
    ],
    "wof:name":"AYSO Region 367",
    "wof:placetype":"venue"
},
  "geometry": {"coordinates":[-88.100351,41.644291],"type":"Point"}
}