{
  "type": "Feature",
  "properties": {
    "iso:country":"US",
    "sg:address":"624 N Pershing St",
    "sg:city":"Energy",
    "sg:classifiers":[
        {
            "category":"Professional",
            "subcategory":"Computer Services",
            "type":"Services"
        }
    ],
    "sg:phone":"+1 618 942 8294",
    "sg:postcode":"62933",
    "sg:province":"IL",
    "sg:tags":[
        "website",
        "design"
    ],
    "sg:website":"www.evolutionmc.com",
    "wof:name":"Evolution Multimedia Corp",
    "wof:placetype":"venue"
},
  "geometry": {"coordinates":[-89.026393,37.779738],"type":"Point"}
}