{
  "type": "Feature",
  "properties": {
    "addr:full":"160 W Division St Chicago IL 60610",
    "addr:housenumber":"160",
    "addr:postcode":"60610",
    "addr:street":"W Division St",
    "iso:country":"US",
    "sg:address":"160 W Division St",
    "sg:city":"Chicago",
    "sg:classifiers":[
        {
            "category":"Professional",
            "subcategory":"Accounting & Tax Preparation",
            "type":"Services"
        },
        {
            "category":"Banks & Credit Unions",
            "subcategory":"Financial Services",
            "type":"Services"
        }
    ],
    "sg:phone":"+1 312 654 8611",
    "sg:postcode":"60610",
    "sg:province":"IL",
    "sg:tags":[
        "return",
        "preparation-business",
        "taxes-consultants",
        "loan",
        "reporting",
        "representative",
        "alternative",
        "bookkeeping"
    ],
    "sg:website":"http://www.hrblock.com",
    "wof:name":"H&R Block",
    "wof:placetype":"venue"
},
  "geometry": {"coordinates":[-87.633484,41.903848],"type":"Point"}
}