{
  "type": "Feature",
  "properties": {
    "iso:country":"US",
    "sg:address":"4757 W Fullerton Ave",
    "sg:city":"Chicago",
    "sg:classifiers":[
        {
            "category":"Food & Beverages",
            "subcategory":"Groceries & Convenience Stores",
            "type":"Retail Goods"
        }
    ],
    "sg:phone":"+1 773 889 8944",
    "sg:postcode":"60639",
    "sg:province":"IL",
    "wof:name":"Jj Pepper's Food Store",
    "wof:placetype":"venue"
},
  "geometry": {"coordinates":[-87.745903,41.924099],"type":"Point"}
}