{
  "type": "Feature",
  "properties": {
    "iso:country":"US",
    "sg:address":"645 N McClurg Ct",
    "sg:city":"Chicago",
    "sg:classifiers":[
        {
            "category":"Fast Food",
            "type":"Food & Drink"
        }
    ],
    "sg:phone":"+1 312 944 5665",
    "sg:postcode":"60611",
    "sg:province":"IL",
    "sg:tags":[
        "burger"
    ],
    "sg:website":"www.mcdonalds.com",
    "wof:name":"McDonald's",
    "wof:placetype":"venue"
},
  "geometry": {"coordinates":[-87.617734,41.893899],"type":"Point"}
}