{
  "type": "Feature",
  "properties": {
    "addr:full":"1727 W Chicago Ave Chicago IL 60622",
    "addr:housenumber":"1727",
    "addr:postcode":"60622",
    "addr:street":"W Chicago Ave",
    "iso:country":"US",
    "sg:address":"1727 W Chicago Ave",
    "sg:city":"Chicago",
    "sg:classifiers":[
        {
            "category":"Health Services",
            "subcategory":"Dentist",
            "type":"Services"
        }
    ],
    "sg:phone":"+1 773 888 1727",
    "sg:postcode":"60622",
    "sg:province":"IL",
    "sg:website":"www.chicagoavesmiles.com/",
    "wof:name":"Chicago Ave Smiles",
    "wof:placetype":"venue"
},
  "geometry": {"coordinates":[-87.670812,41.895897],"type":"Point"}
}