{
  "type": "Feature",
  "properties": {
    "addr:full":"11116 Siedschlag Rd Spring Grove IL 60081",
    "addr:housenumber":"11116",
    "addr:postcode":"60081",
    "addr:street":"Siedschlag Rd",
    "iso:country":"US",
    "sg:address":"11116 Siedschlag Rd",
    "sg:city":"Spring Grove",
    "sg:classifiers":[
        {
            "category":"Insurance",
            "subcategory":"Insurance Agent",
            "type":"Services"
        }
    ],
    "sg:phone":"+1 815 675 6210",
    "sg:postcode":"60081",
    "sg:province":"IL",
    "wof:name":"Peter Yore",
    "wof:placetype":"venue"
},
  "geometry": {"coordinates":[-88.218755,42.488617],"type":"Point"}
}