{
  "type": "Feature",
  "properties": {
    "iso:country":"US",
    "sg:address":"1020 Lunt Ave",
    "sg:city":"Schaumburg",
    "sg:classifiers":[
        {
            "category":"Manufacturing",
            "subcategory":"Tools & Machinery",
            "type":"Manufacturing & Wholesale Goods"
        }
    ],
    "sg:phone":"+1 847 923 0212",
    "sg:postcode":"60193",
    "sg:province":"IL",
    "sg:tags":[
        "industrial",
        "furnace",
        "mfg"
    ],
    "sg:website":"www.furnacefixers.com",
    "wof:name":"Furnace Fixers Inc",
    "wof:placetype":"venue"
},
  "geometry": {"coordinates":[-88.106749,42.001329],"type":"Point"}
}