{
  "type": "Feature",
  "properties": {
    "iso:country":"US",
    "sg:address":"1727 Benson Ave",
    "sg:city":"Evanston",
    "sg:classifiers":[
        {
            "category":"Bars & Pubs",
            "type":"Food & Drink"
        }
    ],
    "sg:menulink":"http://www.allmenus.com/il/evanston/21152-merles-barbeque/menu/",
    "sg:phone":"+1 847 475 7766",
    "sg:postcode":"60201",
    "sg:province":"IL",
    "sg:tags":[
        "barbecue",
        "american"
    ],
    "wof:name":"Merle's Barbeque",
    "wof:placetype":"venue"
},
  "geometry": {"coordinates":[-87.683385,42.048831],"type":"Point"}
}