{
  "type": "Feature",
  "properties": {
    "iso:country":"US",
    "sg:address":"1135 State St",
    "sg:city":"Lemont",
    "sg:classifiers":[
        {
            "category":"Education",
            "subcategory":"Special Training",
            "type":"Public Place"
        },
        {
            "category":"Education",
            "subcategory":"School",
            "type":"Public Place"
        }
    ],
    "sg:phone":"+1 630 257 9782",
    "sg:postcode":"60439",
    "sg:province":"IL",
    "sg:tags":[
        "educational"
    ],
    "wof:name":"Lemont Bomberek Combined Scho. Ol",
    "wof:placetype":"venue"
},
  "geometry": {"coordinates":[-87.999872,41.65932],"type":"Point"}
}