{
  "type": "Feature",
  "properties": {
    "iso:country":"US",
    "sg:address":"7 Maiden Ln",
    "sg:city":"East Dundee",
    "sg:classifiers":[
        {
            "category":"Home & Garden",
            "subcategory":"Home Furnishings",
            "type":"Retail Goods"
        },
        {
            "category":"Shopping",
            "subcategory":"Discount & Variety Stores",
            "type":"Retail Goods"
        }
    ],
    "sg:phone":"+1 847 426 3441",
    "sg:postcode":"60118",
    "sg:province":"IL",
    "sg:tags":[
        "decor",
        "outlet"
    ],
    "sg:website":"www.haegerpotteries.com",
    "wof:name":"The Haeger Potteries Inc",
    "wof:placetype":"venue"
},
  "geometry": {"coordinates":[-88.273088,42.096217],"type":"Point"}
}