{
  "type": "Feature",
  "properties": {
    "iso:country":"US",
    "sg:address":"5906 Elaine Dr",
    "sg:city":"Rockford",
    "sg:classifiers":[
        {
            "category":"Social Services",
            "type":"Services"
        },
        {
            "category":"Personal",
            "type":"Services"
        }
    ],
    "sg:phone":"+1 815 394 1556",
    "sg:postcode":"61108",
    "sg:province":"IL",
    "sg:tags":[
        "family",
        "counselors-licensed",
        "individual",
        "marriage",
        "child",
        "professional",
        "counselor"
    ],
    "sg:website":"http://www.jamesdavisconsulting.com",
    "wof:name":"Crossroads Of Today",
    "wof:placetype":"venue"
},
  "geometry": {"coordinates":[-89.000635,42.262854],"type":"Point"}
}