{
  "type": "Feature",
  "properties": {
    "addr:full":"535 Legion Ct Wauconda IL 60084",
    "addr:housenumber":"535",
    "addr:postcode":"60084",
    "addr:street":"Legion Ct",
    "iso:country":"US",
    "sg:address":"535 Legion Ct",
    "sg:city":"Wauconda",
    "sg:classifiers":[
        {
            "category":"Wholesale",
            "subcategory":"Medical Equipment & Supplies",
            "type":"Manufacturing & Wholesale Goods"
        }
    ],
    "sg:phone":"+1 847 487 8670",
    "sg:postcode":"60084",
    "sg:province":"IL",
    "sg:tags":[
        "x",
        "apparatus"
    ],
    "wof:name":"Mark Industries",
    "wof:placetype":"venue"
},
  "geometry": {"coordinates":[-88.135204,42.25241],"type":"Point"}
}