{
  "type": "Feature",
  "properties": {
    "addr:full":"18 Dundee Ln Barrington IL 60010",
    "addr:housenumber":"18",
    "addr:postcode":"60010",
    "addr:street":"Dundee Ln",
    "iso:country":"US",
    "sg:address":"18 Dundee Ln",
    "sg:city":"Barrington",
    "sg:classifiers":[
        {
            "category":"Wholesale",
            "subcategory":"Electrical",
            "type":"Manufacturing & Wholesale Goods"
        }
    ],
    "sg:phone":"+1 847 304 4095",
    "sg:postcode":"60010",
    "sg:province":"IL",
    "sg:tags":[
        "appliance"
    ],
    "wof:name":"Hamilton Beach Proctor-Silex",
    "wof:placetype":"venue"
},
  "geometry": {"coordinates":[-88.141143,42.14093],"type":"Point"}
}