{
  "type": "Feature",
  "properties": {
    "iso:country":"US",
    "sg:address":"7701 Austin Ave",
    "sg:city":"Skokie",
    "sg:classifiers":[
        {
            "category":"Wholesale",
            "subcategory":"Durable Goods & Equipment",
            "type":"Manufacturing & Wholesale Goods"
        }
    ],
    "sg:phone":"+1 847 965 9600",
    "sg:postcode":"60077",
    "sg:province":"IL",
    "sg:tags":[
        "representative",
        "manufacturer"
    ],
    "wof:name":"Denoyer Geppert Co",
    "wof:placetype":"venue"
},
  "geometry": {"coordinates":[-87.775776,42.019992],"type":"Point"}
}