{
  "type": "Feature",
  "properties": {
    "addr:full":"7475 S Union Ave Chicago IL 60621",
    "addr:housenumber":"7475",
    "addr:postcode":"60621",
    "addr:street":"S Union Ave",
    "iso:country":"US",
    "sg:address":"7475 S Union Ave",
    "sg:city":"Chicago",
    "sg:phone":"+1 630 518 9169",
    "sg:postcode":"60621",
    "sg:province":"IL",
    "wof:name":"Chrstine's Wedding Creations",
    "wof:placetype":"venue"
},
  "geometry": {"coordinates":[-87.641769,41.757984],"type":"Point"}
}