{
  "type": "Feature",
  "properties": {
    "addr:full":"500 W Main St Salem IL 62881",
    "addr:housenumber":"500",
    "addr:postcode":"62881",
    "addr:street":"W Main St",
    "iso:country":"US",
    "sg:address":"500 W Main St",
    "sg:city":"Salem",
    "sg:classifiers":[
        {
            "category":"Autos & Motor Vehicles",
            "subcategory":"Fuel & Gas Station",
            "type":"Retail Goods"
        }
    ],
    "sg:phone":"+1 618 548 2919",
    "sg:postcode":"62881",
    "sg:province":"IL",
    "sg:tags":[
        "oil"
    ],
    "wof:name":"Motomart Convenience Stores",
    "wof:placetype":"venue"
},
  "geometry": {"coordinates":[-88.94950799999999,38.627068],"type":"Point"}
}