{
  "type": "Feature",
  "properties": {
    "iso:country":"US",
    "sg:address":"817 S Charter St",
    "sg:city":"Monticello",
    "sg:classifiers":[
        {
            "category":"Health Services",
            "subcategory":"Doctor",
            "type":"Services"
        }
    ],
    "sg:phone":"+1 217 762 7313",
    "sg:postcode":"61856",
    "sg:province":"IL",
    "sg:tags":[
        "orthodontist"
    ],
    "wof:name":"Morgan C Powell PC",
    "wof:placetype":"venue"
},
  "geometry": {"coordinates":[-88.573435,40.020257],"type":"Point"}
}