{
  "type": "Feature",
  "properties": {
    "addr:full":"25 N Winfield Rd Winfield IL 60190",
    "addr:housenumber":"25",
    "addr:postcode":"60190",
    "addr:street":"N Winfield Rd",
    "iso:country":"US",
    "sg:address":"25 N Winfield Rd",
    "sg:city":"Winfield",
    "sg:classifiers":[
        {
            "category":"Health Services",
            "subcategory":"Doctor",
            "type":"Services"
        }
    ],
    "sg:phone":"+1 630 933 6248",
    "sg:postcode":"60190",
    "sg:province":"IL",
    "sg:tags":[
        "physician",
        "surgeon"
    ],
    "wof:name":"Patel Nilesh MD",
    "wof:placetype":"venue"
},
  "geometry": {"coordinates":[-88.15813300000001,41.87142],"type":"Point"}
}