{
  "type": "Feature",
  "properties": {
    "iso:country":"US",
    "sg:address":"6940 W Belmont Ave",
    "sg:city":"Chicago",
    "sg:classifiers":[
        {
            "category":"Retail",
            "subcategory":"Event Space",
            "type":"Services"
        }
    ],
    "sg:phone":"+1 773 545 0726",
    "sg:postcode":"60634",
    "sg:province":"IL",
    "sg:tags":[
        "venue"
    ],
    "wof:name":"Schorsch Village Hall Rental",
    "wof:placetype":"venue"
},
  "geometry": {"coordinates":[-87.799616,41.938234],"type":"Point"}
}