{
  "type": "Feature",
  "properties": {
    "iso:country":"US",
    "sg:address":"3910 W Diversey Avenue",
    "sg:city":"Chicago",
    "sg:classifiers":[
        {
            "category":"Building & Trades",
            "subcategory":"Plumbing",
            "type":"Services"
        }
    ],
    "sg:phone":"+1 773 777 3333",
    "sg:postcode":"60647",
    "sg:province":"IL",
    "wof:name":"Call First Ltd Sewer & Drainage",
    "wof:placetype":"venue"
},
  "geometry": {"coordinates":[-87.724856,41.931837],"type":"Point"}
}