{
  "type": "Feature",
  "properties": {
    "iso:country":"US",
    "sg:address":"709 N 8th St",
    "sg:city":"Monmouth",
    "sg:classifiers":[
        {
            "category":"Education",
            "subcategory":"School",
            "type":"Public Place"
        }
    ],
    "sg:phone":"+1 309 734 6221",
    "sg:postcode":"61462",
    "sg:province":"IL",
    "wof:name":"School Consulting Inc",
    "wof:placetype":"venue"
},
  "geometry": {"coordinates":[-90.63717,40.919785],"type":"Point"}
}