{
  "type": "Feature",
  "properties": {
    "iso:country":"US",
    "sg:address":"1119 Butterfield Cir W",
    "sg:city":"Shorewood",
    "sg:classifiers":[
        {
            "category":"Insurance",
            "subcategory":"Insurance Agent",
            "type":"Services"
        }
    ],
    "sg:phone":"+1 815 730 1117",
    "sg:postcode":"60404",
    "sg:province":"IL",
    "wof:name":"Farmers Insurance Group",
    "wof:placetype":"venue"
},
  "geometry": {"coordinates":[-88.225137,41.500716],"type":"Point"}
}