{
  "type": "Feature",
  "properties": {
    "addr:full":"1024 Hill St Galena IL 61036",
    "addr:housenumber":"1024",
    "addr:postcode":"61036",
    "addr:street":"Hill St",
    "iso:country":"US",
    "sg:address":"1024 Hill St",
    "sg:city":"Galena",
    "sg:classifiers":[
        {
            "category":"Building & Trades",
            "subcategory":"Construction",
            "type":"Services"
        }
    ],
    "sg:phone":"+1 815 777 9057",
    "sg:postcode":"61036",
    "sg:province":"IL",
    "sg:tags":[
        "painter"
    ],
    "wof:name":"Buman Painting & Decorating",
    "wof:placetype":"venue"
},
  "geometry": {"coordinates":[-90.43720500000001,42.424868],"type":"Point"}
}