{
  "type": "Feature",
  "properties": {
    "addr:full":"157 S Greenwood Ave Kankakee IL 60901",
    "addr:housenumber":"157",
    "addr:postcode":"60901",
    "addr:street":"S Greenwood Ave",
    "iso:country":"US",
    "sg:address":"157 S Greenwood Ave",
    "sg:city":"Kankakee",
    "sg:classifiers":[
        {
            "category":"Social Services",
            "type":"Services"
        }
    ],
    "sg:phone":"+1 815 802 0860",
    "sg:postcode":"60901",
    "sg:province":"IL",
    "sg:tags":[
        "organization",
        "welfare"
    ],
    "wof:name":"Hayse Social Svc",
    "wof:placetype":"venue"
},
  "geometry": {"coordinates":[-87.857112,41.118998],"type":"Point"}
}