{
  "type": "Feature",
  "properties": {
    "addr:full":"8206 S Stony Island Avenue Chicago IL 60617",
    "addr:housenumber":"8206",
    "addr:postcode":"60617",
    "addr:street":"S Stony Island Avenue",
    "iso:country":"US",
    "sg:address":"8206 S Stony Island Avenue",
    "sg:city":"Chicago",
    "sg:classifiers":[
        {
            "category":"Wholesale",
            "subcategory":"Computers",
            "type":"Manufacturing & Wholesale Goods"
        },
        {
            "category":"Professional",
            "subcategory":"Computer Services",
            "type":"Services"
        }
    ],
    "sg:phone":"+1 773 221 1990",
    "sg:postcode":"60617",
    "sg:province":"IL",
    "sg:tags":[
        "repair"
    ],
    "wof:name":"Fejitech",
    "wof:placetype":"venue"
},
  "geometry": {"coordinates":[-87.582854,41.743908],"type":"Point"}
}