{
  "type": "Feature",
  "properties": {
    "iso:country":"US",
    "sg:address":"200 E Randolph St",
    "sg:city":"Chicago",
    "sg:classifiers":[
        {
            "category":"Professional",
            "subcategory":"Lawyer & Legal Services",
            "type":"Services"
        }
    ],
    "sg:phone":"+1 312 861 2018",
    "sg:postcode":"60601",
    "sg:province":"IL",
    "wof:name":"Wexler Raymond P Lwyr",
    "wof:placetype":"venue"
},
  "geometry": {"coordinates":[-87.622299,41.884499],"type":"Point"}
}