{
  "type": "Feature",
  "properties": {
    "iso:country":"US",
    "sg:address":"601 W Polk St",
    "sg:city":"Chicago",
    "sg:classifiers":[
        {
            "category":"Professional",
            "subcategory":"Lawyer & Legal Services",
            "type":"Services"
        }
    ],
    "sg:phone":"+1 312 275 5289",
    "sg:postcode":"60607",
    "sg:province":"IL",
    "wof:name":"McDermott Will and Emery",
    "wof:placetype":"venue"
},
  "geometry": {"coordinates":[-87.642337,41.871843],"type":"Point"}
}