{
  "type": "Feature",
  "properties": {
    "addr:full":"108 N Main St Elizabethtown IL 62999",
    "addr:housenumber":"108",
    "addr:postcode":"62999",
    "addr:street":"N Main St",
    "iso:country":"US",
    "sg:address":"108 N Main St",
    "sg:city":"Elizabethtown",
    "sg:classifiers":[
        {
            "category":"Government",
            "subcategory":"Office",
            "type":"Public Place"
        }
    ],
    "sg:phone":"+1 618 683 2921",
    "sg:postcode":"62999",
    "sg:province":"IL",
    "sg:tags":[
        "state",
        "resource"
    ],
    "wof:name":"Dept Of Human Svc",
    "wof:placetype":"venue"
},
  "geometry": {"coordinates":[-89.05057100000001,37.901103],"type":"Point"}
}