{
  "type": "Feature",
  "properties": {
    "addr:full":"5323 S Western Blvd Chicago IL 60609",
    "addr:housenumber":"5323",
    "addr:postcode":"60609",
    "addr:street":"S Western Blvd",
    "iso:country":"US",
    "sg:address":"5323 S Western Blvd",
    "sg:city":"Chicago",
    "sg:phone":"+1 773 436 5382",
    "sg:postcode":"60609",
    "sg:province":"IL",
    "wof:name":"Illinois Department Of Human Services",
    "wof:placetype":"venue"
},
  "geometry": {"coordinates":[-87.683547,41.79685],"type":"Point"}
}