{
  "type": "Feature",
  "properties": {
    "iso:country":"US",
    "sg:address":"310 S Mill St",
    "sg:city":"Pontiac",
    "sg:classifiers":[
        {
            "category":"Education",
            "subcategory":"Special Training",
            "type":"Public Place"
        }
    ],
    "sg:phone":"+1 815 842 2678",
    "sg:postcode":"61764",
    "sg:province":"IL",
    "sg:tags":[
        "educational"
    ],
    "wof:name":"Illinois Education Assoc",
    "wof:placetype":"venue"
},
  "geometry": {"coordinates":[-88.629738,40.876377],"type":"Point"}
}