{
  "type": "Feature",
  "properties": {
    "iso:country":"US",
    "sg:address":"2 Ultraway Dr",
    "sg:city":"Highland",
    "sg:classifiers":[
        {
            "category":"Building & Trades",
            "subcategory":"Cleaning & Sanitation",
            "type":"Services"
        }
    ],
    "sg:phone":"+1 618 654 6559",
    "sg:postcode":"62249",
    "sg:province":"IL",
    "sg:tags":[
        "chemical"
    ],
    "sg:website":"www.pms1.com",
    "wof:name":"Plant Maintenance Svc",
    "wof:placetype":"venue"
},
  "geometry": {"coordinates":[-89.692175,38.742397],"type":"Point"}
}