{
  "type": "Feature",
  "properties": {
    "iso:country":"US",
    "sg:address":"98 Heather Dr",
    "sg:city":"Crystal Lake",
    "sg:classifiers":[
        {
            "category":"Building & Trades",
            "subcategory":"Construction",
            "type":"Services"
        }
    ],
    "sg:phone":"+1 815 459 7318",
    "sg:postcode":"60014",
    "sg:province":"IL",
    "sg:tags":[
        "general",
        "contractor"
    ],
    "wof:name":"Leifer Builders",
    "wof:placetype":"venue"
},
  "geometry": {"coordinates":[-88.37359,42.2402],"type":"Point"}
}