{
  "type": "Feature",
  "properties": {
    "addr:full":"1000 Co Rd 1400 N Henry IL 61537",
    "addr:housenumber":"1000",
    "addr:postcode":"61537",
    "addr:street":"Co Rd 1400 N",
    "iso:country":"US",
    "sg:address":"1000 Co Rd 1400 N",
    "sg:city":"Henry",
    "sg:phone":"+1 309 364 3581",
    "sg:postcode":"61537",
    "sg:province":"IL",
    "sg:tags":[
        "beef",
        "farm",
        "corn",
        "soybean",
        "cattle",
        "feedlot"
    ],
    "wof:name":"Edgewood Farm",
    "wof:placetype":"venue"
},
  "geometry": {"coordinates":[-89.449911,41.126578],"type":"Point"}
}