{
  "type": "Feature",
  "properties": {
    "addr:full":"609 22nd St Moline IL 61265",
    "addr:housenumber":"609",
    "addr:postcode":"61265",
    "addr:street":"22Nd St",
    "iso:country":"US",
    "sg:address":"609 22nd St",
    "sg:city":"Moline",
    "sg:classifiers":[
        {
            "category":"Health Services",
            "subcategory":"Doctor",
            "type":"Services"
        }
    ],
    "sg:phone":"+1 309 762 2726",
    "sg:postcode":"61265",
    "sg:province":"IL",
    "wof:name":"James R Millman DDS PC",
    "wof:placetype":"venue"
},
  "geometry": {"coordinates":[-90.506154,41.507991],"type":"Point"}
}