{
  "type": "Feature",
  "properties": {
    "iso:country":"US",
    "sg:address":"1711 Brushy Creek Rd",
    "sg:city":"Campbell Hill",
    "sg:phone":"+1 618 426 3570",
    "sg:postcode":"62916",
    "sg:province":"IL",
    "sg:tags":[
        "farm",
        "grain",
        "cash"
    ],
    "wof:name":"George Knop",
    "wof:placetype":"venue"
},
  "geometry": {"coordinates":[-89.530457,37.955798],"type":"Point"}
}