{
  "type": "Feature",
  "properties": {
    "addr:full":"406 3rd St Ivesdale IL 61851",
    "addr:housenumber":"406",
    "addr:postcode":"61851",
    "addr:street":"3Rd St",
    "iso:country":"US",
    "sg:address":"406 3rd St",
    "sg:city":"Ivesdale",
    "sg:classifiers":[
        {
            "category":"Government",
            "subcategory":"Fire Station",
            "type":"Public Place"
        }
    ],
    "sg:phone":"+1   ",
    "sg:postcode":"61851",
    "sg:province":"IL",
    "sg:tags":[
        "protection"
    ],
    "wof:name":"Ivesdale Fire Protection Dst",
    "wof:placetype":"venue"
},
  "geometry": {"coordinates":[-88.456039,39.944215],"type":"Point"}
}