{
  "type": "Feature",
  "properties": {
    "addr:full":"12111 W Heather Glen Ln Manhattan IL 60442",
    "addr:housenumber":"12111",
    "addr:postcode":"60442",
    "addr:street":"W Heather Glen Ln",
    "iso:country":"US",
    "sg:address":"12111 W Heather Glen Ln",
    "sg:city":"Manhattan",
    "sg:classifiers":[
        {
            "category":"Professional",
            "type":"Services"
        }
    ],
    "sg:phone":"+1 815 478 3381",
    "sg:postcode":"60442",
    "sg:province":"IL",
    "wof:name":"K&M Services",
    "wof:placetype":"venue"
},
  "geometry": {"coordinates":[-87.906662,41.451812],"type":"Point"}
}