{
  "type": "Feature",
  "properties": {
    "addr:full":"1132 West Grand Ave Chicago IL 60642",
    "addr:housenumber":"1132",
    "addr:postcode":"60642",
    "addr:street":"West Grand Ave",
    "iso:country":"US",
    "sg:address":"1132 West Grand Ave",
    "sg:city":"Chicago",
    "sg:classifiers":[
        {
            "category":"Restaurant",
            "type":"Food & Drink"
        }
    ],
    "sg:phone":"+1 312 421 5547",
    "sg:postcode":"60642",
    "sg:province":"IL",
    "sg:website":"www.maystreetmarket.com",
    "wof:name":"May Street Market",
    "wof:placetype":"venue"
},
  "geometry": {"coordinates":[-87.656137,41.891336],"type":"Point"}
}