{
  "type": "Feature",
  "properties": {
    "addr:full":"3046 W Il Route 60 Mundelein IL 60060",
    "addr:housenumber":"3046",
    "addr:postcode":"60060",
    "addr:street":"W Il Route 60",
    "iso:country":"US",
    "sg:address":"3046 W Il Route 60",
    "sg:city":"Mundelein",
    "sg:classifiers":[
        {
            "category":"Restaurant",
            "type":"Food & Drink"
        }
    ],
    "sg:menulink":"http://www.allmenus.com/il/fremont/240855-white-castle/menu/",
    "sg:postcode":"60060",
    "sg:province":"IL",
    "sg:tags":[
        "burger",
        "american"
    ],
    "wof:name":"White Castle",
    "wof:placetype":"venue"
},
  "geometry": {"coordinates":[-88.045388,42.281792],"type":"Point"}
}