{
  "type": "Feature",
  "properties": {
    "addr:full":"14729 W US Hwy 24 Glasford IL 61533",
    "addr:housenumber":"14729",
    "addr:postcode":"61533",
    "addr:street":"W Us Hwy 24",
    "iso:country":"US",
    "sg:address":"14729 W US Hwy 24",
    "sg:city":"Glasford",
    "sg:classifiers":[
        {
            "category":"Shopping",
            "subcategory":"Used Merchandise",
            "type":"Retail Goods"
        }
    ],
    "sg:phone":"+1   ",
    "sg:postcode":"61533",
    "sg:province":"IL",
    "wof:name":"Summer Kitchen Antiques",
    "wof:placetype":"venue"
},
  "geometry": {"coordinates":[-89.824198,40.550881],"type":"Point"}
}