{
  "type": "Feature",
  "properties": {
    "iso:country":"US",
    "sg:address":"701 Devonshire Dr Ste C16",
    "sg:city":"Champaign",
    "sg:classifiers":[
        {
            "category":"Education",
            "subcategory":"Kindergarten",
            "type":"Public Place"
        }
    ],
    "sg:phone":"+1 217 398 6189",
    "sg:postcode":"61820",
    "sg:province":"IL",
    "sg:tags":[
        "school",
        "driving"
    ],
    "wof:name":"J R's Driving School",
    "wof:placetype":"venue"
},
  "geometry": {"coordinates":[-88.25299800000001,40.089401],"type":"Point"}
}