{
  "type": "Feature",
  "properties": {
    "iso:country":"US",
    "sg:address":"1400 Thelma Keller Ave",
    "sg:city":"Effingham",
    "sg:classifiers":[
        {
            "category":"Travel",
            "subcategory":"Hotels & Motels",
            "type":"Entertainment"
        }
    ],
    "sg:phone":"+1 217 342 6888",
    "sg:postcode":"62401",
    "sg:province":"IL",
    "sg:tags":[
        "operation"
    ],
    "wof:name":"Super 8 Motel",
    "wof:placetype":"venue"
},
  "geometry": {"coordinates":[-88.56460199999999,39.140622],"type":"Point"}
}