{
  "type": "Feature",
  "properties": {
    "addr:full":"7871 Levee Rd N Arenzville IL 62611",
    "addr:housenumber":"7871",
    "addr:postcode":"62611",
    "addr:street":"Levee Rd N",
    "iso:country":"US",
    "sg:address":"7871 Levee Rd N",
    "sg:city":"Arenzville",
    "sg:classifiers":[
        {
            "category":"Manufacturing",
            "subcategory":"Food",
            "type":"Manufacturing & Wholesale Goods"
        },
        {
            "category":"Farming",
            "subcategory":"Farm",
            "type":"Manufacturing & Wholesale Goods"
        }
    ],
    "sg:phone":"+1 217 997 2197",
    "sg:postcode":"62611",
    "sg:province":"IL",
    "sg:tags":[
        "corn",
        "product"
    ],
    "wof:name":"Jim Rolf Farm Co",
    "wof:placetype":"venue"
},
  "geometry": {"coordinates":[-90.42906499999999,39.90586],"type":"Point"}
}