{
  "type": "Feature",
  "properties": {
    "iso:country":"US",
    "sg:address":"6340 Blodgett Ave",
    "sg:city":"Downers Grove",
    "sg:classifiers":[
        {
            "category":"Building & Trades",
            "subcategory":"Construction",
            "type":"Services"
        }
    ],
    "sg:phone":"+1 630 971 8693",
    "sg:postcode":"60516",
    "sg:province":"IL",
    "sg:tags":[
        "marking",
        "maintenance",
        "parking"
    ],
    "wof:name":"Firemen Sealcoating",
    "wof:placetype":"venue"
},
  "geometry": {"coordinates":[-87.998834,41.771181],"type":"Point"}
}