{
  "type": "Feature",
  "properties": {
    "iso:country":"US",
    "sg:address":"2740 W Pratt Blvd",
    "sg:city":"Chicago",
    "sg:classifiers":[
        {
            "category":"Building & Trades",
            "subcategory":"Construction",
            "type":"Services"
        }
    ],
    "sg:phone":"+1 773 274 5320",
    "sg:postcode":"60645",
    "sg:province":"IL",
    "sg:tags":[
        "hanging",
        "contractor"
    ],
    "wof:name":"Omars Painting Incororated",
    "wof:placetype":"venue"
},
  "geometry": {"coordinates":[-87.697598,42.004964],"type":"Point"}
}