{
  "type": "Feature",
  "properties": {
    "iso:country":"US",
    "sg:address":"7601 S Kostner Ave",
    "sg:city":"Chicago",
    "sg:classifiers":[
        {
            "category":"Wholesale",
            "subcategory":"Office Equipment",
            "type":"Manufacturing & Wholesale Goods"
        }
    ],
    "sg:phone":"+1 773 585 2807",
    "sg:postcode":"60652",
    "sg:province":"IL",
    "sg:tags":[
        "machine",
        "duplicating",
        "copying"
    ],
    "wof:name":"Canon Business Solutions Inc",
    "wof:placetype":"venue"
},
  "geometry": {"coordinates":[-87.732309,41.755452],"type":"Point"}
}