{
  "type": "Feature",
  "properties": {
    "addr:full":"216 W Madison St Waukegan IL 60085",
    "addr:housenumber":"216",
    "addr:postcode":"60085",
    "addr:street":"W Madison St",
    "iso:country":"US",
    "sg:address":"216 W Madison St",
    "sg:city":"Waukegan",
    "sg:classifiers":[
        {
            "category":"Professional",
            "subcategory":"Lawyer & Legal Services",
            "type":"Services"
        }
    ],
    "sg:phone":"+1 847 336 8077",
    "sg:postcode":"60085",
    "sg:province":"IL",
    "sg:tags":[
        "attorney"
    ],
    "wof:name":"William Y Franks",
    "wof:placetype":"venue"
},
  "geometry": {"coordinates":[-87.83243299999999,42.361015],"type":"Point"}
}