{
  "type": "Feature",
  "properties": {
    "addr:full":"1505 N Rand Rd Palatine IL 60074",
    "addr:housenumber":"1505",
    "addr:postcode":"60074",
    "addr:street":"N Rand Rd",
    "iso:country":"US",
    "sg:address":"1505 N Rand Rd",
    "sg:city":"Palatine",
    "sg:classifiers":[
        {
            "category":"Retail",
            "subcategory":"Laundry & Dry Cleaning",
            "type":"Services"
        }
    ],
    "sg:phone":"+1 847 255 5598",
    "sg:postcode":"60074",
    "sg:province":"IL",
    "wof:name":"Courtney's Coin Laundry",
    "wof:placetype":"venue"
},
  "geometry": {"coordinates":[-88.019231,42.13727],"type":"Point"}
}