{
  "type": "Feature",
  "properties": {
    "iso:country":"US",
    "sg:address":"1020 E New York St",
    "sg:city":"Aurora",
    "sg:classifiers":[
        {
            "category":"Food & Beverages",
            "subcategory":"Groceries & Convenience Stores",
            "type":"Retail Goods"
        }
    ],
    "sg:phone":"+1 630 375 7897",
    "sg:postcode":"60505",
    "sg:province":"IL",
    "sg:tags":[
        "product"
    ],
    "wof:name":"Old Time Snackery",
    "wof:placetype":"venue"
},
  "geometry": {"coordinates":[-88.289157,41.754539],"type":"Point"}
}