{
  "type": "Feature",
  "properties": {
    "iso:country":"US",
    "sg:address":"15293 Wall St",
    "sg:city":"Carterville",
    "sg:classifiers":[
        {
            "category":"Building & Trades",
            "subcategory":"Plumbing",
            "type":"Services"
        }
    ],
    "sg:phone":"+1 618 987 2471",
    "sg:postcode":"62918",
    "sg:province":"IL",
    "wof:name":"Ellet Plumbing Backflow Prevention",
    "wof:placetype":"venue"
},
  "geometry": {"coordinates":[-89.126198,37.816101],"type":"Point"}
}