{
  "type": "Feature",
  "properties": {
    "addr:full":"1312 E Algonquin Rd Algonquin IL 60102",
    "addr:housenumber":"1312",
    "addr:postcode":"60102",
    "addr:street":"E Algonquin Rd",
    "iso:country":"US",
    "sg:address":"1312 E Algonquin Rd",
    "sg:city":"Algonquin",
    "sg:classifiers":[
        {
            "category":"Shopping",
            "subcategory":"Tobacco",
            "type":"Retail Goods"
        }
    ],
    "sg:phone":"+1 847 458 8644",
    "sg:postcode":"60102",
    "sg:province":"IL",
    "sg:tags":[
        "shop"
    ],
    "wof:name":"S T Cigars",
    "wof:placetype":"venue"
},
  "geometry": {"coordinates":[-88.2761,42.161098],"type":"Point"}
}