{
  "type": "Feature",
  "properties": {
    "addr:full":"83 N Cone St Farmington IL 61531",
    "addr:housenumber":"83",
    "addr:postcode":"61531",
    "addr:street":"N Cone St",
    "iso:country":"US",
    "sg:address":"83 N Cone St",
    "sg:city":"Farmington",
    "sg:classifiers":[
        {
            "category":"Organizations",
            "subcategory":"Religious Organization",
            "type":"Services"
        }
    ],
    "sg:phone":"+1 309 245 2914",
    "sg:postcode":"61531",
    "sg:province":"IL",
    "sg:tags":[
        "church"
    ],
    "wof:name":"First Presbyterian Church Inc",
    "wof:placetype":"venue"
},
  "geometry": {"coordinates":[-90.00312,40.698988],"type":"Point"}
}