{
  "type": "Feature",
  "properties": {
    "iso:country":"US",
    "sg:address":"12160 S Central Ave",
    "sg:city":"Alsip",
    "sg:classifiers":[
        {
            "category":"Food & Beverages",
            "subcategory":"Liquor & Beverages",
            "type":"Retail Goods"
        }
    ],
    "sg:phone":"+1 708 389 8200",
    "sg:postcode":"60803",
    "sg:province":"IL",
    "sg:tags":[
        "beer",
        "spirit",
        "wine"
    ],
    "wof:name":"Hayes Beer Distributing Co",
    "wof:placetype":"venue"
},
  "geometry": {"coordinates":[-87.758499,41.6716],"type":"Point"}
}