{
  "type": "Feature",
  "properties": {
    "iso:country":"US",
    "sg:address":"5 Bridle Ln",
    "sg:city":"Bannockburn",
    "sg:classifiers":[
        {
            "category":"Professional",
            "type":"Services"
        }
    ],
    "sg:phone":"+1 847 604 9700",
    "sg:postcode":"60015",
    "sg:province":"IL",
    "sg:tags":[
        "establishment"
    ],
    "wof:name":"W Nib",
    "wof:placetype":"venue"
},
  "geometry": {"coordinates":[-87.879613,42.202042],"type":"Point"}
}