{
  "type": "Feature",
  "properties": {
    "iso:country":"US",
    "sg:address":"5710 Kenosha St",
    "sg:city":"Richmond",
    "sg:classifiers":[
        {
            "category":"Building & Trades",
            "subcategory":"Electrical",
            "type":"Services"
        },
        {
            "category":"Utilities",
            "subcategory":"Natural Gas",
            "type":"Services"
        }
    ],
    "sg:phone":"+1 815 678 2211",
    "sg:postcode":"60071",
    "sg:province":"IL",
    "sg:tags":[
        "control",
        "regulator",
        "system",
        "controls",
        "thermocouple"
    ],
    "sg:website":"http://www.ceramicfiberheaters.com",
    "wof:name":"Watlow Richmond",
    "wof:placetype":"venue"
},
  "geometry": {"coordinates":[-88.30786500000001,42.479755],"type":"Point"}
}