{
  "type": "Feature",
  "properties": {
    "addr:full":"645 Carlyle Ave Belleville IL 62221",
    "addr:housenumber":"645",
    "addr:postcode":"62221",
    "addr:street":"Carlyle Ave",
    "iso:country":"US",
    "sg:address":"645 Carlyle Ave",
    "sg:city":"Belleville",
    "sg:classifiers":[
        {
            "category":"Restaurant",
            "type":"Food & Drink"
        }
    ],
    "sg:phone":"+1   ",
    "sg:postcode":"62221",
    "sg:province":"IL",
    "sg:tags":[
        "eating"
    ],
    "wof:name":"KFC",
    "wof:placetype":"venue"
},
  "geometry": {"coordinates":[-89.95409100000001,38.517045],"type":"Point"}
}