{
  "type": "Feature",
  "properties": {
    "addr:full":"639 York St Quincy IL 62301",
    "addr:housenumber":"639",
    "addr:postcode":"62301",
    "addr:street":"York St",
    "iso:country":"US",
    "sg:address":"639 York St",
    "sg:city":"Quincy",
    "sg:classifiers":[
        {
            "category":"Social Services",
            "type":"Services"
        }
    ],
    "sg:phone":"+1 217 592 3757",
    "sg:postcode":"62301",
    "sg:province":"IL",
    "sg:tags":[
        "care",
        "center",
        "day"
    ],
    "wof:name":"Adams County Adult Day Svc",
    "wof:placetype":"venue"
},
  "geometry": {"coordinates":[-91.40614600000001,39.929265],"type":"Point"}
}