{
  "type": "Feature",
  "properties": {
    "addr:full":"6378 Fulton Rd Fulton IL 61252",
    "addr:housenumber":"6378",
    "addr:postcode":"61252",
    "addr:street":"Fulton Rd",
    "iso:country":"US",
    "sg:address":"6378 Fulton Rd",
    "sg:city":"Fulton",
    "sg:classifiers":[
        {
            "category":"Professional",
            "subcategory":"Business Services",
            "type":"Services"
        }
    ],
    "sg:phone":"+1 815 589 3603",
    "sg:postcode":"61252",
    "sg:province":"IL",
    "wof:name":"Business of Adventure",
    "wof:placetype":"venue"
},
  "geometry": {"coordinates":[-90.122795,41.859635],"type":"Point"}
}