{
  "type": "Feature",
  "properties": {
    "iso:country":"US",
    "sg:address":"4500 16th St",
    "sg:city":"Moline",
    "sg:classifiers":[
        {
            "category":"Shopping",
            "subcategory":"Jewelry",
            "type":"Retail Goods"
        }
    ],
    "sg:phone":"+1 309 762 4200",
    "sg:postcode":"61265",
    "sg:province":"IL",
    "wof:name":"Fred Meyer Jewelers 67",
    "wof:placetype":"venue"
},
  "geometry": {"coordinates":[-90.506973,41.468117],"type":"Point"}
}