{
  "type": "Feature",
  "properties": {
    "iso:country":"US",
    "sg:address":"2411 Primrose Pl",
    "sg:city":"Rockford",
    "sg:classifiers":[
        {
            "category":"Wholesale",
            "subcategory":"Books, Periodicals, & Newspapers",
            "type":"Manufacturing & Wholesale Goods"
        }
    ],
    "sg:phone":"+1 815 398 0177",
    "sg:postcode":"61108",
    "sg:province":"IL",
    "sg:tags":[
        "publisher",
        "book"
    ],
    "wof:name":"Easton Publishing",
    "wof:placetype":"venue"
},
  "geometry": {"coordinates":[-88.994148,42.240852],"type":"Point"}
}