{
  "type": "Feature",
  "properties": {
    "addr:full":"2415 W Barry Avenue Chicago IL 60618",
    "addr:housenumber":"2415",
    "addr:postcode":"60618",
    "addr:street":"W Barry Avenue",
    "iso:country":"US",
    "sg:address":"2415 W Barry Avenue",
    "sg:city":"Chicago",
    "sg:classifiers":[
        {
            "category":"Home & Garden",
            "subcategory":"Carpets & Floor Coverings",
            "type":"Retail Goods"
        }
    ],
    "sg:phone":"+1 773 935 3400",
    "sg:postcode":"60618",
    "sg:province":"IL",
    "sg:tags":[
        "flooring"
    ],
    "wof:name":"North Branch Flooring Company",
    "wof:placetype":"venue"
},
  "geometry": {"coordinates":[-87.688275,41.937525],"type":"Point"}
}