{
  "type": "Feature",
  "properties": {
    "iso:country":"US",
    "sg:address":"2620 Washington Ave",
    "sg:city":"Alton",
    "sg:classifiers":[
        {
            "category":"Retail",
            "subcategory":"Auto Repair",
            "type":"Services"
        }
    ],
    "sg:phone":"+1 618 462 8778",
    "sg:postcode":"62002",
    "sg:province":"IL",
    "sg:tags":[
        "automobile",
        "lubrication"
    ],
    "wof:name":"Rapid Lube",
    "wof:placetype":"venue"
},
  "geometry": {"coordinates":[-90.150785,38.914091],"type":"Point"}
}