{
  "type": "Feature",
  "properties": {
    "addr:full":"358 W Army Trail Rd. Ste150 Bloomingdale IL 60108",
    "addr:housenumber":"358",
    "addr:postcode":"ste150;60108",
    "addr:street":"W Army Trail Rd.",
    "iso:country":"US",
    "sg:address":"358 W Army Trail Rd. Ste150",
    "sg:city":"Bloomingdale",
    "sg:classifiers":[
        {
            "category":"Wholesale",
            "subcategory":"Computers",
            "type":"Manufacturing & Wholesale Goods"
        }
    ],
    "sg:phone":"+1 630 893 6300",
    "sg:postcode":"60108",
    "sg:province":"IL",
    "sg:website":"cartridgeworldusa.com/store207",
    "wof:name":"Cartridge World-Bloomingdale",
    "wof:placetype":"venue"
},
  "geometry": {"coordinates":[-88.058273,41.935024],"type":"Point"}
}