{
  "type": "Feature",
  "properties": {
    "iso:country":"US",
    "sg:address":"1112 Parkwood Dr",
    "sg:city":"Joliet",
    "sg:classifiers":[
        {
            "category":"Real Estate",
            "subcategory":"Real Estate Operator",
            "type":"Services"
        }
    ],
    "sg:phone":"+1 815 727 1452",
    "sg:postcode":"60432",
    "sg:province":"IL",
    "sg:tags":[
        "apartment",
        "complex"
    ],
    "wof:name":"Pine Ridge Apartments",
    "wof:placetype":"venue"
},
  "geometry": {"coordinates":[-88.025567,41.545259],"type":"Point"}
}