{
  "type": "Feature",
  "properties": {
    "addr:full":"100 Southwoods Center Columbia IL 62236",
    "addr:housenumber":"100",
    "addr:postcode":"62236",
    "addr:street":"Southwoods Center",
    "iso:country":"US",
    "sg:address":"100 Southwoods Center",
    "sg:city":"Columbia",
    "sg:classifiers":[
        {
            "category":"Social Services",
            "subcategory":"Child Care",
            "type":"Services"
        }
    ],
    "sg:phone":"+1 618 281 8181",
    "sg:postcode":"62236",
    "sg:province":"IL",
    "sg:website":"www.lighthouselearning.net",
    "wof:name":"Lighthouse Learning Ctr",
    "wof:placetype":"venue"
},
  "geometry": {"coordinates":[-90.198877,38.436565],"type":"Point"}
}