{
  "type": "Feature",
  "properties": {
    "addr:full":"6600 W North Ave Chicago IL 60707",
    "addr:housenumber":"6600",
    "addr:postcode":"60707",
    "addr:street":"W North Ave",
    "iso:country":"US",
    "sg:address":"6600 W North Ave",
    "sg:city":"Chicago",
    "sg:classifiers":[
        {
            "category":"Retail",
            "subcategory":"Laundry & Dry Cleaning",
            "type":"Services"
        }
    ],
    "sg:phone":"+1 773 637 7837",
    "sg:postcode":"60707",
    "sg:province":"IL",
    "sg:website":"www.cdonepricecleaners.com",
    "wof:name":"CD One Price Cleaners",
    "wof:placetype":"venue"
},
  "geometry": {"coordinates":[-87.79047300000001,41.909313],"type":"Point"}
}