{
  "type": "Feature",
  "properties": {
    "addr:full":"6540 North Illinois Street Fairview Heights IL 62208",
    "addr:housenumber":"6540",
    "addr:postcode":"62208",
    "addr:street":"North Illinois Street",
    "iso:country":"US",
    "sg:address":"6540 North Illinois Street",
    "sg:city":"Fairview Heights",
    "sg:classifiers":[
        {
            "category":"Personal",
            "subcategory":"Day Spa",
            "type":"Services"
        }
    ],
    "sg:phone":"+1 618 628 7374",
    "sg:postcode":"62208",
    "sg:province":"IL",
    "sg:website":"www.purenatursalon.com/",
    "wof:name":"Pure Natur Aveda Salon",
    "wof:placetype":"venue"
},
  "geometry": {"coordinates":[-89.984801,38.593354],"type":"Point"}
}