{
  "type": "Feature",
  "properties": {
    "addr:full":"205 1/2 E Ohio Chicago IL 60611",
    "addr:housenumber":"205 1 / 2 e",
    "addr:postcode":"60611",
    "iso:country":"US",
    "sg:address":"205 1/2 E Ohio",
    "sg:city":"Chicago",
    "sg:classifiers":[
        {
            "category":"Personal",
            "type":"Services"
        },
        {
            "category":"Building & Trades",
            "subcategory":"Cleaning & Sanitation",
            "type":"Services"
        }
    ],
    "sg:phone":"+1 312 607 7930",
    "sg:postcode":"60611",
    "sg:province":"IL",
    "sg:tags":[
        "home",
        "mover"
    ],
    "sg:website":"lunamaidservices.com/",
    "wof:name":"Luna Maid Services",
    "wof:placetype":"venue"
},
  "geometry": {"coordinates":[-87.626919,41.892271],"type":"Point"}
}