{
  "type": "Feature",
  "properties": {
    "addr:full":"4229 N Lincoln Ave Chicago IL 60618",
    "addr:housenumber":"4229",
    "addr:postcode":"60618",
    "addr:street":"N Lincoln Ave",
    "iso:country":"US",
    "sg:address":"4229 N Lincoln Ave",
    "sg:city":"Chicago",
    "sg:classifiers":[
        {
            "category":"Restaurant",
            "type":"Food & Drink"
        }
    ],
    "sg:phone":"+1 773 868 4229",
    "sg:postcode":"60618",
    "sg:province":"IL",
    "sg:tags":[
        "korean",
        "japanese"
    ],
    "wof:name":"Choi's Roll Sushi",
    "wof:placetype":"venue"
},
  "geometry": {"coordinates":[-87.681825,41.958589],"type":"Point"}
}