{
  "type": "Feature",
  "properties": {
    "iso:country":"US",
    "sg:address":"1103 38th St",
    "sg:city":"Rock Island",
    "sg:classifiers":[
        {
            "category":"Arts & Performance",
            "subcategory":"Theater",
            "type":"Entertainment"
        }
    ],
    "sg:phone":"+1 309 786 2796",
    "sg:postcode":"61201",
    "sg:province":"IL",
    "sg:tags":[
        "group"
    ],
    "wof:name":"Music Masters",
    "wof:placetype":"venue"
},
  "geometry": {"coordinates":[-90.54754800000001,41.499185],"type":"Point"}
}