{
  "type": "Feature",
  "properties": {
    "iso:country":"US",
    "sg:address":"3140 Glenway Dr",
    "sg:city":"Northbrook",
    "sg:classifiers":[
        {
            "category":"Building & Trades",
            "subcategory":"Construction",
            "type":"Services"
        }
    ],
    "sg:phone":"+1 847 480 1585",
    "sg:postcode":"60062",
    "sg:province":"IL",
    "sg:tags":[
        "home",
        "remodeling",
        "commercial"
    ],
    "wof:name":"Steven Pick Construction Co",
    "wof:placetype":"venue"
},
  "geometry": {"coordinates":[-87.857665,42.101665],"type":"Point"}
}