{
  "type": "Feature",
  "properties": {
    "addr:full":"402 Buchanan St Belvidere IL 61008",
    "addr:housenumber":"402",
    "addr:postcode":"61008",
    "addr:street":"Buchanan St",
    "iso:country":"US",
    "sg:address":"402 Buchanan St",
    "sg:city":"Belvidere",
    "sg:classifiers":[
        {
            "category":"Home & Garden",
            "subcategory":"Household Appliances",
            "type":"Retail Goods"
        },
        {
            "category":"Building & Trades",
            "subcategory":"Construction",
            "type":"Services"
        }
    ],
    "sg:phone":"+1 815 544 4247",
    "sg:postcode":"61008",
    "sg:province":"IL",
    "sg:tags":[
        "purifying",
        "system",
        "specialty",
        "equipment",
        "heating",
        "cleaning",
        "contractor",
        "air conditioning"
    ],
    "sg:website":"http://www.flemingheating.com",
    "wof:name":"Fleming Heating And Air Conditioning, Inc",
    "wof:placetype":"venue"
},
  "geometry": {"coordinates":[-88.836642,42.257418],"type":"Point"}
}