{
  "type": "Feature",
  "properties": {
    "addr:full":"524 Morse Ave Schaumburg IL 60193",
    "addr:housenumber":"524",
    "addr:postcode":"60193",
    "addr:street":"Morse Ave",
    "iso:country":"US",
    "sg:address":"524 Morse Ave",
    "sg:city":"Schaumburg",
    "sg:classifiers":[
        {
            "category":"Wholesale",
            "subcategory":"Chemicals & Plastics",
            "type":"Manufacturing & Wholesale Goods"
        }
    ],
    "sg:phone":"+1 847 891 1625",
    "sg:postcode":"60193",
    "sg:province":"IL",
    "wof:name":"Reliable Solutions Inc",
    "wof:placetype":"venue"
},
  "geometry": {"coordinates":[-88.09934,42.000294],"type":"Point"}
}