{
  "type": "Feature",
  "properties": {
    "iso:country":"US",
    "sg:address":"2917 S Haynes Ct",
    "sg:city":"Chicago",
    "sg:classifiers":[
        {
            "category":"Building & Trades",
            "subcategory":"Plumbing",
            "type":"Services"
        }
    ],
    "sg:phone":"+1 773 742 8082",
    "sg:postcode":"60608",
    "sg:province":"IL",
    "sg:tags":[
        "pipe",
        "inspection"
    ],
    "wof:name":"Us Jack Inc.",
    "wof:placetype":"venue"
},
  "geometry": {"coordinates":[-87.658311,41.841005],"type":"Point"}
}