{
  "type": "Feature",
  "properties": {
    "iso:country":"US",
    "sg:address":"2816 Kinoka Rd",
    "sg:city":"Patoka",
    "sg:classifiers":[
        {
            "category":"Building & Trades",
            "subcategory":"Construction",
            "type":"Services"
        }
    ],
    "sg:phone":"+1 618 432 7371",
    "sg:postcode":"62875",
    "sg:province":"IL",
    "sg:tags":[
        "contractor"
    ],
    "wof:name":"Fru-Con Construction",
    "wof:placetype":"venue"
},
  "geometry": {"coordinates":[-89.011353,38.765128],"type":"Point"}
}