{
  "type": "Feature",
  "properties": {
    "iso:country":"US",
    "sg:address":"148 Clyde Ave",
    "sg:city":"Evanston",
    "sg:classifiers":[
        {
            "category":"Retail",
            "subcategory":"Repair Shop",
            "type":"Services"
        }
    ],
    "sg:phone":"+1 847 612 5260",
    "sg:postcode":"60202",
    "sg:province":"IL",
    "sg:tags":[
        "refrigeration"
    ],
    "wof:name":"Etek Refrigeration",
    "wof:placetype":"venue"
},
  "geometry": {"coordinates":[-87.678072,42.020327],"type":"Point"}
}