{
  "type": "Feature",
  "properties": {
    "addr:full":"1112 Lake St Oak Park IL 60301",
    "addr:housenumber":"1112",
    "addr:postcode":"60301",
    "addr:street":"Lake St",
    "iso:country":"US",
    "sg:address":"1112 Lake St",
    "sg:city":"Oak Park",
    "sg:classifiers":[
        {
            "category":"Health Services",
            "subcategory":"Health Practitioner",
            "type":"Services"
        }
    ],
    "sg:phone":"+1 708 445 0195",
    "sg:postcode":"60301",
    "sg:province":"IL",
    "sg:tags":[
        "nutritionist"
    ],
    "sg:website":"www.gnc.com",
    "wof:name":"Gnc",
    "wof:placetype":"venue"
},
  "geometry": {"coordinates":[-87.803082,41.888767],"type":"Point"}
}