{
  "type": "Feature",
  "properties": {
    "iso:country":"US",
    "sg:address":"13154 Cicero Ave",
    "sg:city":"Crestwood",
    "sg:classifiers":[
        {
            "category":"Wholesale",
            "subcategory":"Durable Goods & Equipment",
            "type":"Manufacturing & Wholesale Goods"
        }
    ],
    "sg:phone":"+1 708 371 7104",
    "sg:postcode":"60445",
    "sg:province":"IL",
    "sg:tags":[
        "merchandise-wholesale",
        "store",
        "variety"
    ],
    "wof:name":"Cigarettes Outlet",
    "wof:placetype":"venue"
},
  "geometry": {"coordinates":[-87.738287,41.652385],"type":"Point"}
}