{
  "type": "Feature",
  "properties": {
    "addr:full":"9321 Deer Run Ln Coulterville IL 62237",
    "addr:housenumber":"9321",
    "addr:postcode":"62237",
    "addr:street":"Deer Run Ln",
    "iso:country":"US",
    "sg:address":"9321 Deer Run Ln",
    "sg:city":"Coulterville",
    "sg:classifiers":[
        {
            "category":"Manufacturing",
            "subcategory":"Tools & Machinery",
            "type":"Manufacturing & Wholesale Goods"
        },
        {
            "category":"Autos & Motor Vehicles",
            "subcategory":"Auto Supplies",
            "type":"Retail Goods"
        }
    ],
    "sg:phone":"+1 618 758 2011",
    "sg:postcode":"62237",
    "sg:province":"IL",
    "sg:tags":[
        "battery",
        "mfg"
    ],
    "wof:name":"Larry's Better Built Batteries",
    "wof:placetype":"venue"
},
  "geometry": {"coordinates":[-89.638563,38.153278],"type":"Point"}
}