{
  "type": "Feature",
  "properties": {
    "iso:country":"US",
    "sg:address":"135 N 5th Ave",
    "sg:city":"Canton",
    "sg:classifiers":[
        {
            "category":"Restaurant",
            "type":"Food & Drink"
        }
    ],
    "sg:menulink":"http://www.allmenus.com/il/canton/88351-monicals-pizza/menu/",
    "sg:phone":"+1 309 647 1127",
    "sg:postcode":"61520",
    "sg:province":"IL",
    "sg:tags":[
        "american",
        "pizza"
    ],
    "wof:name":"Monicals Pizza",
    "wof:placetype":"venue"
},
  "geometry": {"coordinates":[-90.027311,40.557483],"type":"Point"}
}