{
  "type": "Feature",
  "properties": {
    "addr:full":"750 Deerrun Dr Deerfield IL 60015",
    "addr:housenumber":"750",
    "addr:postcode":"60015",
    "addr:street":"Deerrun Dr",
    "iso:country":"US",
    "sg:address":"750 Deerrun Dr",
    "sg:city":"Deerfield",
    "sg:classifiers":[
        {
            "category":"Arena",
            "subcategory":"Sports Club",
            "type":"Entertainment"
        }
    ],
    "sg:phone":"+1 847 267 9200",
    "sg:postcode":"60015",
    "sg:province":"IL",
    "wof:name":"Tsmgi",
    "wof:placetype":"venue"
},
  "geometry": {"coordinates":[-87.875714,42.167305],"type":"Point"}
}