{
  "type": "Feature",
  "properties": {
    "iso:country":"US",
    "sg:address":"1655 Clover Dr",
    "sg:city":"Palatine",
    "sg:classifiers":[
        {
            "category":"Professional",
            "subcategory":"Management & Consulting",
            "type":"Services"
        }
    ],
    "sg:phone":"+1 847 359 3804",
    "sg:postcode":"60067",
    "sg:province":"IL",
    "sg:tags":[
        "business"
    ],
    "wof:name":"C D Bowers Ltd",
    "wof:placetype":"venue"
},
  "geometry": {"coordinates":[-88.08098,42.098224],"type":"Point"}
}