{
  "type": "Feature",
  "properties": {
    "iso:country":"US",
    "sg:address":"75 E Wacker Dr",
    "sg:city":"Chicago",
    "sg:classifiers":[
        {
            "category":"Wholesale",
            "subcategory":"Books, Periodicals, & Newspapers",
            "type":"Manufacturing & Wholesale Goods"
        }
    ],
    "sg:phone":"+1 312 372 9310",
    "sg:postcode":"60601",
    "sg:province":"IL",
    "sg:tags":[
        "news",
        "dealers-wholesale"
    ],
    "wof:name":"Metro Newspaper Advertising",
    "wof:placetype":"venue"
},
  "geometry": {"coordinates":[-87.625693,41.887785],"type":"Point"}
}