{
  "type": "Feature",
  "properties": {
    "iso:country":"US",
    "sg:address":"36930 N Stanton Point Rd",
    "sg:city":"Ingleside",
    "sg:classifiers":[
        {
            "category":"Bars & Pubs",
            "type":"Food & Drink"
        }
    ],
    "sg:phone":"+1   ",
    "sg:postcode":"60041",
    "sg:province":"IL",
    "sg:tags":[
        "seasonal",
        "grill",
        "bar",
        "volleyball"
    ],
    "wof:name":"Costellos Pub & Grub",
    "wof:placetype":"venue"
},
  "geometry": {"coordinates":[-88.14746,42.394172],"type":"Point"}
}