{
  "type": "Feature",
  "properties": {
    "addr:full":"126 N Vermilion St Danville IL 61832",
    "addr:housenumber":"126",
    "addr:postcode":"61832",
    "addr:street":"N Vermilion St",
    "iso:country":"US",
    "sg:address":"126 N Vermilion St",
    "sg:city":"Danville",
    "sg:classifiers":[
        {
            "category":"Shopping",
            "subcategory":"Used Merchandise",
            "type":"Retail Goods"
        }
    ],
    "sg:phone":"+1 217 709 0331",
    "sg:postcode":"61832",
    "sg:province":"IL",
    "sg:tags":[
        "shop",
        "thrift"
    ],
    "wof:name":"Y's Buys",
    "wof:placetype":"venue"
},
  "geometry": {"coordinates":[-87.630047,40.127778],"type":"Point"}
}