{
  "type": "Feature",
  "properties": {
    "iso:country":"US",
    "sg:address":"3701 N Ravenswood Ave",
    "sg:city":"Chicago",
    "sg:classifiers":[
        {
            "category":"Communications",
            "subcategory":"Newspaper",
            "type":"Services"
        }
    ],
    "sg:phone":"+1 773 327 0728",
    "sg:postcode":"60686",
    "sg:province":"IL",
    "sg:tags":[
        "print",
        "medium"
    ],
    "sg:website":"www.mint-magazine.com",
    "wof:name":"Mint Magazine",
    "wof:placetype":"venue"
},
  "geometry": {"coordinates":[-87.67366800000001,41.948766],"type":"Point"}
}