{
  "type": "Feature",
  "properties": {
    "addr:full":"350 W Hubbard St Chicago IL 60610",
    "addr:housenumber":"350",
    "addr:postcode":"60610",
    "addr:street":"W Hubbard St",
    "iso:country":"US",
    "sg:address":"350 W Hubbard St",
    "sg:city":"Chicago",
    "sg:classifiers":[
        {
            "category":"Banks & Credit Unions",
            "subcategory":"Financial Services",
            "type":"Services"
        }
    ],
    "sg:phone":"+1 773 307 6313",
    "sg:postcode":"60610",
    "sg:province":"IL",
    "sg:tags":[
        "broker",
        "mortgage"
    ],
    "wof:name":"Chris Covalle Countrywide Home Loans",
    "wof:placetype":"venue"
},
  "geometry": {"coordinates":[-87.63811800000001,41.889936],"type":"Point"}
}