{
  "type": "Feature",
  "properties": {
    "addr:full":"1120 N Rand Rd Wauconda IL 60084",
    "addr:housenumber":"1120",
    "addr:postcode":"60084",
    "addr:street":"N Rand Rd",
    "iso:country":"US",
    "sg:address":"1120 N Rand Rd",
    "sg:city":"Wauconda",
    "sg:classifiers":[
        {
            "category":"Professional",
            "subcategory":"Lawyer & Legal Services",
            "type":"Services"
        }
    ],
    "sg:phone":"+1 847 526 2863",
    "sg:postcode":"60084",
    "sg:province":"IL",
    "wof:name":"Delaurentis Law",
    "wof:placetype":"venue"
},
  "geometry": {"coordinates":[-88.15449700000001,42.276409],"type":"Point"}
}