{
  "type": "Feature",
  "properties": {
    "addr:full":"1490 Douglas Dr Carbondale IL 62901",
    "addr:housenumber":"1490",
    "addr:postcode":"62901",
    "addr:street":"Douglas Dr",
    "iso:country":"US",
    "sg:address":"1490 Douglas Dr",
    "sg:city":"Carbondale",
    "sg:classifiers":[
        {
            "category":"Recreation",
            "type":"Entertainment"
        }
    ],
    "sg:phone":"+1 618 453 5341",
    "sg:postcode":"62901",
    "sg:province":"IL",
    "sg:tags":[
        "ticket"
    ],
    "wof:name":"S Iu Arena Special Events Tckt",
    "wof:placetype":"venue"
},
  "geometry": {"coordinates":[-89.22112,37.707376],"type":"Point"}
}