{
  "type": "Feature",
  "properties": {
    "iso:country":"US",
    "sg:address":"1443 7th St",
    "sg:city":"Charleston",
    "sg:classifiers":[
        {
            "category":"Shopping",
            "subcategory":"Books",
            "type":"Retail Goods"
        }
    ],
    "sg:phone":"+1   ",
    "sg:postcode":"61920",
    "sg:province":"IL",
    "wof:name":"7th & Glory Chrstn Bk Gift Str",
    "wof:placetype":"venue"
},
  "geometry": {"coordinates":[-88.173926,39.485249],"type":"Point"}
}