{
  "type": "Feature",
  "properties": {
    "iso:country":"US",
    "sg:address":"7923 Mansfield Ave",
    "sg:city":"Bedford Park",
    "sg:classifiers":[
        {
            "category":"Freight",
            "type":"Transportation"
        }
    ],
    "sg:phone":"+1 708 636 0116",
    "sg:postcode":"60459",
    "sg:province":"IL",
    "sg:tags":[
        "operator",
        "local",
        "trucking"
    ],
    "wof:name":"Ignacio Trucking Inc",
    "wof:placetype":"venue"
},
  "geometry": {"coordinates":[-87.766796,41.748622],"type":"Point"}
}