{
  "type": "Feature",
  "properties": {
    "addr:full":"845 Bonnie Ln Elk Grove Village IL 60007",
    "addr:housenumber":"845",
    "addr:postcode":"60007",
    "addr:street":"Bonnie Ln",
    "iso:country":"US",
    "sg:address":"845 Bonnie Ln",
    "sg:city":"Elk Grove Village",
    "sg:classifiers":[
        {
            "category":"Professional",
            "subcategory":"Advertising",
            "type":"Services"
        }
    ],
    "sg:phone":"+1 847 439 9897",
    "sg:postcode":"60007",
    "sg:province":"IL",
    "sg:tags":[
        "mail",
        "direct"
    ],
    "wof:name":"Xl Marketing Group Inc",
    "wof:placetype":"venue"
},
  "geometry": {"coordinates":[-87.971007,42.015089],"type":"Point"}
}