{
  "type": "Feature",
  "properties": {
    "iso:country":"US",
    "sg:address":"113 N Oak St",
    "sg:city":"Loraine",
    "sg:classifiers":[
        {
            "category":"Wholesale",
            "subcategory":"Construction Materials",
            "type":"Manufacturing & Wholesale Goods"
        }
    ],
    "sg:phone":"+1 217 938 4144",
    "sg:postcode":"62349",
    "sg:province":"IL",
    "sg:tags":[
        "granite"
    ],
    "wof:name":"Granite Casting",
    "wof:placetype":"venue"
},
  "geometry": {"coordinates":[-91.221781,40.155096],"type":"Point"}
}