{
  "type": "Feature",
  "properties": {
    "addr:full":"212 Prairie St Aurora IL 60506",
    "addr:housenumber":"212",
    "addr:postcode":"60506",
    "addr:street":"Prairie St",
    "iso:country":"US",
    "sg:address":"212 Prairie St",
    "sg:city":"Aurora",
    "sg:classifiers":[
        {
            "category":"Personal",
            "subcategory":"Barber",
            "type":"Services"
        }
    ],
    "sg:phone":"+1 630 859 9252",
    "sg:postcode":"60506",
    "sg:province":"IL",
    "sg:tags":[
        "shop"
    ],
    "wof:name":"Prairie Barber Shop",
    "wof:placetype":"venue"
},
  "geometry": {"coordinates":[-88.33014900000001,41.75235],"type":"Point"}
}