{
  "type": "Feature",
  "properties": {
    "iso:country":"US",
    "sg:address":"5531 S King Drive",
    "sg:city":"Chicago",
    "sg:classifiers":[
        {
            "category":"Sports & Exercise",
            "subcategory":"Sports Center",
            "type":"Entertainment"
        }
    ],
    "sg:phone":"+1 773 256 1248",
    "sg:postcode":"60637",
    "sg:province":"IL",
    "sg:tags":[
        "amateur",
        "team"
    ],
    "wof:name":"Chicago Park District",
    "wof:placetype":"venue"
},
  "geometry": {"coordinates":[-87.61572200000001,41.794001],"type":"Point"}
}