{
  "type": "Feature",
  "properties": {
    "addr:full":"3328 N Clark St Chicago IL 60657",
    "addr:housenumber":"3328",
    "addr:postcode":"60657",
    "addr:street":"N Clark St",
    "iso:country":"US",
    "sg:address":"3328 N Clark St",
    "sg:city":"Chicago",
    "sg:classifiers":[
        {
            "category":"Fast Food",
            "type":"Food & Drink"
        },
        {
            "category":"Food & Beverages",
            "subcategory":"Bakery",
            "type":"Retail Goods"
        },
        {
            "category":"Restaurant",
            "type":"Food & Drink"
        },
        {
            "category":"Food & Beverages",
            "subcategory":"Groceries & Convenience Stores",
            "type":"Retail Goods"
        }
    ],
    "sg:phone":"+1 773 244 9000",
    "sg:postcode":"60657",
    "sg:province":"IL",
    "sg:tags":[
        "shop",
        "sandwich",
        "take"
    ],
    "sg:website":"http://www.jimmyjohns.com",
    "wof:name":"Jimmy John's",
    "wof:placetype":"venue"
},
  "geometry": {"coordinates":[-87.65270200000001,41.942501],"type":"Point"}
}