{
  "type": "Feature",
  "properties": {
    "iso:country":"US",
    "sg:address":"1691 N Mannheim Rd",
    "sg:city":"Stone Park",
    "sg:classifiers":[
        {
            "category":"Restaurant",
            "type":"Food & Drink"
        }
    ],
    "sg:menulink":"http://www.allmenus.com/il/proviso/127522-subway/menu/",
    "sg:phone":"+1 708 410 2821",
    "sg:postcode":"60165",
    "sg:province":"IL",
    "sg:tags":[
        "american",
        "sandwich"
    ],
    "wof:name":"Subway",
    "wof:placetype":"venue"
},
  "geometry": {"coordinates":[-87.88367700000001,41.903166],"type":"Point"}
}