{
  "type": "Feature",
  "properties": {
    "addr:full":"127 S Roselle Rd Schaumburg IL 60193",
    "addr:housenumber":"127",
    "addr:postcode":"60193",
    "addr:street":"S Roselle Rd",
    "iso:country":"US",
    "sg:address":"127 S Roselle Rd",
    "sg:city":"Schaumburg",
    "sg:classifiers":[
        {
            "category":"Travel",
            "subcategory":"Travel Agent",
            "type":"Entertainment"
        }
    ],
    "sg:phone":"+1 847 534 1100",
    "sg:postcode":"60193",
    "sg:province":"IL",
    "sg:tags":[
        "operator",
        "tour",
        "agency"
    ],
    "wof:name":"Nutty Vacations & Cruises",
    "wof:placetype":"venue"
},
  "geometry": {"coordinates":[-88.07986200000001,42.02448],"type":"Point"}
}