{
  "type": "Feature",
  "properties": {
    "iso:country":"US",
    "sg:address":"1809 Walters Ave",
    "sg:city":"Northbrook",
    "sg:classifiers":[
        {
            "category":"Organizations",
            "subcategory":"Religious Organization",
            "type":"Services"
        }
    ],
    "sg:phone":"+1 847 272 3086",
    "sg:postcode":"60062",
    "sg:province":"IL",
    "wof:name":"Saint Nrbrts Rlgous Edcatn Off",
    "wof:placetype":"venue"
},
  "geometry": {"coordinates":[-87.826642,42.127347],"type":"Point"}
}