{
  "type": "Feature",
  "properties": {
    "addr:full":"2840 Clarissa Ln Aurora IL 60502",
    "addr:housenumber":"2840",
    "addr:postcode":"60502",
    "addr:street":"Clarissa Ln",
    "iso:country":"US",
    "sg:address":"2840 Clarissa Ln",
    "sg:city":"Aurora",
    "sg:classifiers":[
        {
            "category":"Utilities",
            "subcategory":"Mobile Phone",
            "type":"Services"
        }
    ],
    "sg:phone":"+1 630 692 1431",
    "sg:postcode":"60502",
    "sg:province":"IL",
    "sg:tags":[
        "sic",
        "marketing",
        "or",
        "interactive"
    ],
    "wof:name":"B 2 B Interactive Marketing",
    "wof:placetype":"venue"
},
  "geometry": {"coordinates":[-88.267126,41.813869],"type":"Point"}
}