{
  "type": "Feature",
  "properties": {
    "addr:full":"942 Busse Hwy Park Ridge IL 60068",
    "addr:housenumber":"942",
    "addr:postcode":"60068",
    "addr:street":"Busse Hwy",
    "iso:country":"US",
    "sg:address":"942 Busse Hwy",
    "sg:city":"Park Ridge",
    "sg:classifiers":[
        {
            "category":"Building & Trades",
            "subcategory":"Construction",
            "type":"Services"
        }
    ],
    "sg:phone":"+1 847 825 4497",
    "sg:postcode":"60068",
    "sg:province":"IL",
    "sg:tags":[
        "new",
        "remodeling",
        "co",
        "home"
    ],
    "wof:name":"Peter A Johnsen & Son Inc",
    "wof:placetype":"venue"
},
  "geometry": {"coordinates":[-87.85441400000001,42.023665],"type":"Point"}
}