{
  "type": "Feature",
  "properties": {
    "iso:country":"US",
    "sg:address":"3232 W 55th St",
    "sg:city":"Chicago",
    "sg:classifiers":[
        {
            "category":"Health Services",
            "subcategory":"Doctor",
            "type":"Services"
        }
    ],
    "sg:phone":"+1 773 471 3600",
    "sg:postcode":"60632",
    "sg:province":"IL",
    "sg:tags":[
        "medicine",
        "internal"
    ],
    "wof:name":"Sawyer Medical Center",
    "wof:placetype":"venue"
},
  "geometry": {"coordinates":[-87.704903,41.793499],"type":"Point"}
}