{
  "type": "Feature",
  "properties": {
    "iso:country":"US",
    "sg:address":"1116 Cannell Ct",
    "sg:city":"Rockton",
    "sg:classifiers":[
        {
            "category":"Insurance",
            "subcategory":"Insurance Agent",
            "type":"Services"
        }
    ],
    "sg:phone":"+1 815 324 2838",
    "sg:postcode":"61072",
    "sg:province":"IL",
    "wof:name":"Linda Hanson",
    "wof:placetype":"venue"
},
  "geometry": {"coordinates":[-89.06238500000001,42.465877],"type":"Point"}
}