{
  "type": "Feature",
  "properties": {
    "addr:full":"702 S 8th St Vandalia IL 62471",
    "addr:housenumber":"702",
    "addr:postcode":"62471",
    "addr:street":"S 8Th St",
    "iso:country":"US",
    "sg:address":"702 S 8th St",
    "sg:city":"Vandalia",
    "sg:classifiers":[
        {
            "category":"Retail",
            "subcategory":"Car Wash",
            "type":"Services"
        }
    ],
    "sg:phone":"+1 618 283 2597",
    "sg:postcode":"62471",
    "sg:province":"IL",
    "sg:tags":[
        "carwash",
        "building",
        "maintenance"
    ],
    "wof:name":"C C HI Pressure",
    "wof:placetype":"venue"
},
  "geometry": {"coordinates":[-89.10031600000001,38.95491],"type":"Point"}
}