{
  "type": "Feature",
  "properties": {
    "iso:country":"US",
    "sg:address":"421 Sycamore Dr",
    "sg:city":"Waterloo",
    "sg:classifiers":[
        {
            "category":"Banks & Credit Unions",
            "subcategory":"Investment Brokerage",
            "type":"Services"
        }
    ],
    "sg:phone":"+1 618 939 6053",
    "sg:postcode":"62298",
    "sg:province":"IL",
    "sg:tags":[
        "trust"
    ],
    "wof:name":"Krueger Land Trust",
    "wof:placetype":"venue"
},
  "geometry": {"coordinates":[-90.142932,38.330658],"type":"Point"}
}