{
  "type": "Feature",
  "properties": {
    "addr:full":"5757 South Cicero Ave Chicago IL 60638",
    "addr:housenumber":"5757",
    "addr:postcode":"60638",
    "addr:street":"South Cicero Ave",
    "iso:country":"US",
    "sg:address":"5757 South Cicero Ave",
    "sg:city":"Chicago",
    "sg:classifiers":[
        {
            "category":"Restaurant",
            "type":"Food & Drink"
        }
    ],
    "sg:phone":"+1 773 948 6300",
    "sg:postcode":"60638",
    "sg:province":"IL",
    "sg:tags":[
        "steakhouse"
    ],
    "sg:website":"www.harrycarays.com/seventh_inni...",
    "wof:name":"Harry Caray's Seventh Inning Stretch",
    "wof:placetype":"venue"
},
  "geometry": {"coordinates":[-87.74139099999999,41.78992],"type":"Point"}
}