{
  "type": "Feature",
  "properties": {
    "addr:full":"1331 E Business Center Dr Mount Prospect IL 60056",
    "addr:housenumber":"1331",
    "addr:postcode":"60056",
    "addr:street":"E Business Center Dr",
    "iso:country":"US",
    "sg:address":"1331 E Business Center Dr",
    "sg:city":"Mount Prospect",
    "sg:classifiers":[
        {
            "category":"Banks & Credit Unions",
            "subcategory":"Investment Brokerage",
            "type":"Services"
        }
    ],
    "sg:phone":"+1 847 391 6300",
    "sg:postcode":"60056",
    "sg:province":"IL",
    "sg:tags":[
        "security"
    ],
    "wof:name":"Pershing Securities",
    "wof:placetype":"venue"
},
  "geometry": {"coordinates":[-87.917868,42.078432],"type":"Point"}
}