{
  "type": "Feature",
  "properties": {
    "iso:country":"US",
    "sg:address":"4619 Luna Dr",
    "sg:city":"Machesney Park",
    "sg:classifiers":[
        {
            "category":"Shopping",
            "subcategory":"Catalog Store",
            "type":"Retail Goods"
        }
    ],
    "sg:phone":"+1   ",
    "sg:postcode":"61115",
    "sg:province":"IL",
    "sg:tags":[
        "house",
        "mail"
    ],
    "wof:name":"Wholesale Hennis J R",
    "wof:placetype":"venue"
},
  "geometry": {"coordinates":[-89.02479,42.350848],"type":"Point"}
}