{
  "type": "Feature",
  "properties": {
    "addr:city":"Fulton",
    "addr:full":"707 10Th Ave Fulton, Il 61252",
    "addr:house_number":"707",
    "addr:housenumber":"707",
    "addr:phone":"+1 815-589-3809",
    "addr:postcode":"61252",
    "addr:road":"10Th Ave",
    "addr:state":"IL",
    "addr:street":"10Th Ave",
    "iso:country":"US",
    "sg:address":"707 10th Ave",
    "sg:city":"Fulton",
    "sg:classifiers":[
        {
            "category":"Museum",
            "type":"Entertainment"
        }
    ],
    "sg:phone":"+1 815 589 2997",
    "sg:postcode":"61252",
    "sg:province":"IL",
    "wof:airports":[
        102526471
    ],
    "wof:name":"Martin House Museum",
    "wof:placetype":"venue"
},
  "geometry": {"coordinates":[-90.16135,41.86726],"type":"Point"}
}