{
  "type": "Feature",
  "properties": {
    "addr:full":"707 10th Ave Fulton IL 61252",
    "addr:housenumber":"707",
    "addr:postcode":"61252",
    "addr:street":"10Th Ave",
    "iso:country":"US",
    "sg:address":"707 10th Ave",
    "sg:city":"Fulton",
    "sg:classifiers":[
        {
            "category":"Museum",
            "type":"Entertainment"
        }
    ],
    "sg:phone":"+1 815 589 2997",
    "sg:postcode":"61252",
    "sg:province":"IL",
    "wof:name":"Martin House Museum",
    "wof:placetype":"venue"
},
  "geometry": {"coordinates":[-90.162274,41.867249],"type":"Point"}
}