{
  "type": "Feature",
  "properties": {
    "iso:country":"US",
    "sg:address":"2121 63rd St",
    "sg:city":"Downers Grove",
    "sg:classifiers":[
        {
            "category":"Education",
            "subcategory":"Dance Studio",
            "type":"Public Place"
        }
    ],
    "sg:phone":"+1 630 971 0603",
    "sg:postcode":"60516",
    "sg:province":"IL",
    "sg:tags":[
        "instruction",
        "dancing"
    ],
    "wof:name":"Spotlight Rhythm Machine",
    "wof:placetype":"venue"
},
  "geometry": {"coordinates":[-88.04827299999999,41.771611],"type":"Point"}
}