{
  "type": "Feature",
  "properties": {
    "addr:full":"884 Main St Antioch IL 60002",
    "addr:housenumber":"884",
    "addr:postcode":"60002",
    "addr:street":"Main St",
    "iso:country":"US",
    "sg:address":"884 Main St",
    "sg:city":"Antioch",
    "sg:classifiers":[
        {
            "category":"Government",
            "subcategory":"Office",
            "type":"Public Place"
        }
    ],
    "sg:phone":"+1 847 395 6342",
    "sg:postcode":"60002",
    "sg:province":"IL",
    "sg:tags":[
        "city",
        "planning",
        "dev"
    ],
    "wof:name":"Antioch Redevelopment Comm",
    "wof:placetype":"venue"
},
  "geometry": {"coordinates":[-88.09649,42.479192],"type":"Point"}
}