{
  "type": "Feature",
  "properties": {
    "iso:country":"US",
    "sg:address":"16036 Harlem Ave",
    "sg:city":"Tinley Park",
    "sg:classifiers":[
        {
            "category":"Shopping",
            "subcategory":"Computers & Home Electronics",
            "type":"Retail Goods"
        }
    ],
    "sg:phone":"+1   ",
    "sg:postcode":"60477",
    "sg:province":"IL",
    "sg:tags":[
        "consumer"
    ],
    "wof:name":"Radio Shack",
    "wof:placetype":"venue"
},
  "geometry": {"coordinates":[-87.794178,41.600959],"type":"Point"}
}