{
  "type": "Feature",
  "properties": {
    "iso:country":"US",
    "sg:address":"861 N Madison St",
    "sg:city":"Rockford",
    "sg:classifiers":[
        {
            "category":"Professional",
            "subcategory":"Management & Consulting",
            "type":"Services"
        }
    ],
    "sg:phone":"+1 815 962 7090",
    "sg:postcode":"61107",
    "sg:province":"IL",
    "wof:name":"Fetelli Advertising",
    "wof:placetype":"venue"
},
  "geometry": {"coordinates":[-89.082253,42.277637],"type":"Point"}
}