{
  "type": "Feature",
  "properties": {
    "iso:country":"US",
    "sg:address":"1614 Christina St",
    "sg:city":"Rockford",
    "sg:phone":"+1 815 965 8604",
    "sg:postcode":"61104",
    "sg:province":"IL",
    "wof:name":"Penguin Foods",
    "wof:placetype":"venue"
},
  "geometry": {"coordinates":[-89.09792400000001,42.250769],"type":"Point"}
}