{
  "type": "Feature",
  "properties": {
    "iso:country":"US",
    "sg:address":"4115 Progress Blvd",
    "sg:city":"Peru",
    "sg:classifiers":[
        {
            "category":"Home & Garden",
            "subcategory":"Building Materials",
            "type":"Retail Goods"
        },
        {
            "category":"Retail",
            "subcategory":"Auto Repair",
            "type":"Services"
        }
    ],
    "sg:phone":"+1 815 223 1060",
    "sg:postcode":"61354",
    "sg:province":"IL",
    "sg:tags":[
        "glass",
        "window",
        "plate",
        "replacement"
    ],
    "wof:name":"Glass Specialty Co",
    "wof:placetype":"venue"
},
  "geometry": {"coordinates":[-89.122035,41.357909],"type":"Point"}
}