{
  "type": "Feature",
  "properties": {
    "iso:country":"US",
    "sg:address":"30 Ash St",
    "sg:city":"Frankfort",
    "sg:classifiers":[
        {
            "category":"Insurance",
            "subcategory":"Hazard Insurance",
            "type":"Services"
        },
        {
            "category":"Insurance",
            "subcategory":"Insurance Agent",
            "type":"Services"
        },
        {
            "category":"Insurance",
            "subcategory":"Life Insurance",
            "type":"Services"
        },
        {
            "category":"Insurance",
            "subcategory":"Title Insurance",
            "type":"Services"
        }
    ],
    "sg:phone":"+1 815 464 0123",
    "sg:postcode":"60423",
    "sg:province":"IL",
    "sg:tags":[
        "auto",
        "commercial",
        "business",
        "homeowner"
    ],
    "sg:website":"http://www.countryfinancial.com/paul.malito",
    "wof:name":"COUNTRY Financial Paul Malito",
    "wof:placetype":"venue"
},
  "geometry": {"coordinates":[-87.849907,41.498252],"type":"Point"}
}