{
  "type": "Feature",
  "properties": {
    "iso:country":"US",
    "sg:address":"3110 N Sheffield Ave",
    "sg:city":"Chicago",
    "sg:classifiers":[
        {
            "category":"Community Center",
            "subcategory":"Social",
            "type":"Public Place"
        }
    ],
    "sg:phone":"+1 773 248 5900",
    "sg:postcode":"60657",
    "sg:province":"IL",
    "sg:tags":[
        "club"
    ],
    "wof:name":"Studio Be",
    "wof:placetype":"venue"
},
  "geometry": {"coordinates":[-87.654211,41.938367],"type":"Point"}
}