{
  "type": "Feature",
  "properties": {
    "addr:full":"822 W Waco St 2 Taylorville IL 62568",
    "addr:housenumber":"822;2",
    "addr:postcode":"62568",
    "addr:street":"W Waco St",
    "iso:country":"US",
    "sg:address":"822 W Waco St 2",
    "sg:city":"Taylorville",
    "sg:classifiers":[
        {
            "category":"Organizations",
            "subcategory":"Religious Organization",
            "type":"Services"
        }
    ],
    "sg:phone":"+1 217 824 5448",
    "sg:postcode":"62568",
    "sg:province":"IL",
    "wof:name":"Ensearch",
    "wof:placetype":"venue"
},
  "geometry": {"coordinates":[-89.304408,39.54163],"type":"Point"}
}