{
  "type": "Feature",
  "properties": {
    "iso:country":"US",
    "sg:address":"900 W Jefferson St",
    "sg:city":"Joliet",
    "sg:classifiers":[
        {
            "category":"Real Estate",
            "subcategory":"Architect",
            "type":"Services"
        }
    ],
    "sg:phone":"+1 815 744 8787",
    "sg:postcode":"60435",
    "sg:province":"IL",
    "sg:tags":[
        "architectural"
    ],
    "wof:name":"Russ + Carlson Architecture",
    "wof:placetype":"venue"
},
  "geometry": {"coordinates":[-88.104063,41.523202],"type":"Point"}
}