{
  "type": "Feature",
  "properties": {
    "iso:country":"US",
    "sg:address":"1927 Cedar St",
    "sg:city":"Jacksonville",
    "sg:classifiers":[
        {
            "category":"Personal",
            "subcategory":"Beauty Salon",
            "type":"Services"
        }
    ],
    "sg:phone":"+1 217 243 3116",
    "sg:postcode":"62650",
    "sg:province":"IL",
    "sg:tags":[
        "shop"
    ],
    "wof:name":"Shirlee's Salon Of Beauty",
    "wof:placetype":"venue"
},
  "geometry": {"coordinates":[-90.26739600000001,39.729557],"type":"Point"}
}