{
  "type": "Feature",
  "properties": {
    "addr:full":"2584 Prairie College Rd Jacksonville IL 62650",
    "addr:housenumber":"2584",
    "addr:postcode":"62650",
    "addr:street":"Prairie College Rd",
    "iso:country":"US",
    "sg:address":"2584 Prairie College Rd",
    "sg:city":"Jacksonville",
    "sg:classifiers":[
        {
            "category":"Building & Trades",
            "subcategory":"Plumbing",
            "type":"Services"
        }
    ],
    "sg:phone":"+1 217 245 6172",
    "sg:postcode":"62650",
    "sg:province":"IL",
    "sg:tags":[
        "conditioning",
        "air",
        "system",
        "contractor"
    ],
    "wof:name":"Taylor's Heating & Air Cond",
    "wof:placetype":"venue"
},
  "geometry": {"coordinates":[-90.13347400000001,39.716361],"type":"Point"}
}