{
  "type": "Feature",
  "properties": {
    "iso:country":"US",
    "sg:address":"15 S Wabash Ave",
    "sg:city":"Chicago",
    "sg:classifiers":[
        {
            "category":"Shopping",
            "subcategory":"Jewelry",
            "type":"Retail Goods"
        },
        {
            "category":"Manufacturing",
            "subcategory":"Jewelry",
            "type":"Manufacturing & Wholesale Goods"
        }
    ],
    "sg:phone":"+1 312 332 3133",
    "sg:postcode":"60603",
    "sg:province":"IL",
    "sg:tags":[
        "repairing",
        "designer",
        "jewelers-wholesale",
        "watch",
        "jeweler",
        "diamond",
        "appraiser",
        "manufacturer"
    ],
    "sg:website":"http://chicago.citysearch.com/profile/external/36752783/chicago_il/diamonds_on_wabash.html?publisher=yellowpages&reference_id=1&placement=ypwebsitemip",
    "wof:name":"Diamonds on Wabash",
    "wof:placetype":"venue"
},
  "geometry": {"coordinates":[-87.62594199999999,41.881615],"type":"Point"}
}