{
  "type": "Feature",
  "properties": {
    "iso:country":"US",
    "sg:address":"5540 N Long Ave",
    "sg:city":"Chicago",
    "sg:classifiers":[
        {
            "category":"Shopping",
            "subcategory":"Clothing, Apparel, & Fashions",
            "type":"Retail Goods"
        },
        {
            "category":"Home & Garden",
            "subcategory":"Home Furnishings",
            "type":"Retail Goods"
        },
        {
            "category":"Wholesale",
            "subcategory":"Home Furnishings",
            "type":"Manufacturing & Wholesale Goods"
        }
    ],
    "sg:phone":"+1 773 763 7695",
    "sg:postcode":"60630",
    "sg:province":"IL",
    "sg:tags":[
        "blind",
        "draperies",
        "women's",
        "window",
        "treatment",
        "shade",
        "shades-wholesale",
        "apparel",
        "curtain",
        "manufacturer"
    ],
    "wof:name":"Cut To Size",
    "wof:placetype":"venue"
},
  "geometry": {"coordinates":[-87.763199,41.9823],"type":"Point"}
}