{
  "type": "Feature",
  "properties": {
    "iso:country":"US",
    "sg:address":"5234 W 25th St",
    "sg:city":"Cicero",
    "sg:classifiers":[
        {
            "category":"Building & Trades",
            "subcategory":"Cleaning & Sanitation",
            "type":"Services"
        }
    ],
    "sg:phone":"+1 708 656 8300",
    "sg:postcode":"60804",
    "sg:province":"IL",
    "sg:tags":[
        "window",
        "janitorial"
    ],
    "wof:name":"A & R Janitorial Service Inc",
    "wof:placetype":"venue"
},
  "geometry": {"coordinates":[-87.75477100000001,41.845651],"type":"Point"}
}