{
  "type": "Feature",
  "properties": {
    "addr:full":"3924 W Devon Ave Lincolnwood IL 60712",
    "addr:housenumber":"3924",
    "addr:postcode":"60712",
    "addr:street":"W Devon Ave",
    "iso:country":"US",
    "sg:address":"3924 W Devon Ave",
    "sg:city":"Lincolnwood",
    "sg:classifiers":[
        {
            "category":"Shopping",
            "subcategory":"Gifts & Souvenirs",
            "type":"Retail Goods"
        },
        {
            "category":"Shopping",
            "subcategory":"Antiques",
            "type":"Retail Goods"
        }
    ],
    "sg:phone":"+1 847 933 1061",
    "sg:postcode":"60712",
    "sg:province":"IL",
    "sg:tags":[
        "dealers-wholesale"
    ],
    "wof:name":"The Postcard Factory",
    "wof:placetype":"venue"
},
  "geometry": {"coordinates":[-87.72734800000001,41.997261],"type":"Point"}
}