{
  "type": "Feature",
  "properties": {
    "addr:full":"17550 S Williamsburg Dr Plainfield IL 60586",
    "addr:housenumber":"17550",
    "addr:postcode":"60586",
    "addr:street":"S Williamsburg Dr",
    "iso:country":"US",
    "sg:address":"17550 S Williamsburg Dr",
    "sg:city":"Plainfield",
    "sg:classifiers":[
        {
            "category":"Building & Trades",
            "subcategory":"Construction",
            "type":"Services"
        }
    ],
    "sg:phone":"+1 815 230 2919",
    "sg:postcode":"60586",
    "sg:province":"IL",
    "sg:tags":[
        "altering",
        "remodeling",
        "contractor"
    ],
    "wof:name":"A Woman's Touch",
    "wof:placetype":"venue"
},
  "geometry": {"coordinates":[-88.243728,41.561959],"type":"Point"}
}