{
  "type": "Feature",
  "properties": {
    "addr:full":"327 5th St Lincoln IL 62656",
    "addr:housenumber":"327",
    "addr:postcode":"62656",
    "addr:street":"5Th St",
    "iso:country":"US",
    "sg:address":"327 5th St",
    "sg:city":"Lincoln",
    "sg:classifiers":[
        {
            "category":"Personal",
            "subcategory":"Beauty Salon",
            "type":"Services"
        }
    ],
    "sg:phone":"+1 217 732 2206",
    "sg:postcode":"62656",
    "sg:province":"IL",
    "sg:tags":[
        "shop"
    ],
    "wof:name":"Diana Pickett",
    "wof:placetype":"venue"
},
  "geometry": {"coordinates":[-89.371576,40.14688],"type":"Point"}
}