{
  "type": "Feature",
  "properties": {
    "iso:country":"US",
    "sg:address":"922 Dundee Ave",
    "sg:city":"Elgin",
    "sg:classifiers":[
        {
            "category":"Building & Trades",
            "subcategory":"Cleaning & Sanitation",
            "type":"Services"
        }
    ],
    "sg:phone":"+1 847 697 4455",
    "sg:postcode":"60120",
    "sg:province":"IL",
    "sg:tags":[
        "window"
    ],
    "wof:name":"All Window Cleaning",
    "wof:placetype":"venue"
},
  "geometry": {"coordinates":[-88.27016999999999,42.053496],"type":"Point"}
}