{
  "type": "Feature",
  "properties": {
    "addr:full":"4839 Cal Sag Rd Crestwood IL 60445",
    "addr:housenumber":"4839",
    "addr:postcode":"60445",
    "addr:street":"Cal Sag Rd",
    "iso:country":"US",
    "sg:address":"4839 Cal Sag Rd",
    "sg:city":"Crestwood",
    "sg:classifiers":[
        {
            "category":"Health Services",
            "subcategory":"Dentist",
            "type":"Services"
        }
    ],
    "sg:phone":"+1 708 597 9055",
    "sg:postcode":"60445",
    "sg:province":"IL",
    "sg:website":"www.searsdental.com",
    "wof:name":"Sears Dental",
    "wof:placetype":"venue"
},
  "geometry": {"coordinates":[-87.73960099999999,41.653801],"type":"Point"}
}