{
  "type": "Feature",
  "properties": {
    "iso:country":"US",
    "sg:address":"1753 S Cora St",
    "sg:city":"Des Plaines",
    "sg:classifiers":[
        {
            "category":"Wholesale",
            "subcategory":"Groceries",
            "type":"Manufacturing & Wholesale Goods"
        }
    ],
    "sg:phone":"+1 847 296 5333",
    "sg:postcode":"60018",
    "sg:province":"IL",
    "sg:tags":[
        "food",
        "product",
        "dist",
        "specialty"
    ],
    "wof:name":"Roadhouse Inc",
    "wof:placetype":"venue"
},
  "geometry": {"coordinates":[-87.885633,42.021542],"type":"Point"}
}