{
  "type": "Feature",
  "properties": {
    "iso:country":"US",
    "sg:address":"113 Neely Cir",
    "sg:city":"Carmi",
    "sg:classifiers":[
        {
            "category":"Personal",
            "subcategory":"Beauty Salon",
            "type":"Services"
        }
    ],
    "sg:phone":"+1 618 382 8922",
    "sg:postcode":"62821",
    "sg:province":"IL",
    "wof:name":"Lady Of Paris Beauty Salon",
    "wof:placetype":"venue"
},
  "geometry": {"coordinates":[-88.177238,38.07835],"type":"Point"}
}