{
  "type": "Feature",
  "properties": {
    "addr:full":"304 W Hubbard St Chicago IL 60654",
    "addr:housenumber":"304",
    "addr:postcode":"60654",
    "addr:street":"W Hubbard St",
    "iso:country":"US",
    "sg:address":"304 W Hubbard St",
    "sg:city":"Chicago",
    "sg:classifiers":[
        {
            "category":"Food & Beverages",
            "subcategory":"Bakery",
            "type":"Retail Goods"
        }
    ],
    "sg:phone":"+1 312 222 9899",
    "sg:postcode":"60654",
    "sg:province":"IL",
    "sg:tags":[
        "sandwich"
    ],
    "sg:website":"www.subway.com",
    "wof:name":"Subway",
    "wof:placetype":"venue"
},
  "geometry": {"coordinates":[-87.636792,41.889963],"type":"Point"}
}