{
  "type": "Feature",
  "properties": {
    "addr:full":"2827 W Catalpa Ave Chicago IL 60625",
    "addr:housenumber":"2827",
    "addr:postcode":"60625",
    "addr:street":"W Catalpa Ave",
    "iso:country":"US",
    "sg:address":"2827 W Catalpa Ave",
    "sg:city":"Chicago",
    "sg:classifiers":[
        {
            "category":"Social Services",
            "subcategory":"Job Training",
            "type":"Services"
        }
    ],
    "sg:phone":"+1 773 878 7178",
    "sg:postcode":"60625",
    "sg:province":"IL",
    "sg:tags":[
        "employment"
    ],
    "wof:name":"M K & A Corp",
    "wof:placetype":"venue"
},
  "geometry": {"coordinates":[-87.699748,41.981287],"type":"Point"}
}