{
  "type": "Feature",
  "properties": {
    "addr:full":"11141 Northwest Rd Palos Hills IL 60465",
    "addr:housenumber":"11141",
    "addr:postcode":"60465",
    "addr:street":"Northwest Rd",
    "iso:country":"US",
    "sg:address":"11141 Northwest Rd",
    "sg:city":"Palos Hills",
    "sg:classifiers":[
        {
            "category":"Organizations",
            "subcategory":"Religious Organization",
            "type":"Services"
        }
    ],
    "sg:phone":"+1 708 974 4220",
    "sg:postcode":"60465",
    "sg:province":"IL",
    "wof:name":"Chicago Catholic Women Inc",
    "wof:placetype":"venue"
},
  "geometry": {"coordinates":[-87.84400599999999,41.687582],"type":"Point"}
}