{
  "type": "Feature",
  "properties": {
    "iso:country":"US",
    "sg:address":"3206 N Cicero Ave",
    "sg:city":"Chicago",
    "sg:classifiers":[
        {
            "category":"Restaurant",
            "type":"Food & Drink"
        }
    ],
    "sg:phone":"+1 773 777 1615",
    "sg:postcode":"60641",
    "sg:province":"IL",
    "sg:tags":[
        "deli",
        "delicatessen"
    ],
    "wof:name":"Cicero Deli",
    "wof:placetype":"venue"
},
  "geometry": {"coordinates":[-87.746696,41.939201],"type":"Point"}
}