{
  "type": "Feature",
  "properties": {
    "addr:full":"20 N Michigan Ave Chicago IL 60602",
    "addr:housenumber":"20",
    "addr:postcode":"60602",
    "addr:street":"N Michigan Ave",
    "iso:country":"US",
    "sg:address":"20 N Michigan Ave",
    "sg:city":"Chicago",
    "sg:classifiers":[
        {
            "category":"Education",
            "subcategory":"Library",
            "type":"Public Place"
        }
    ],
    "sg:phone":"+1 312 201 9830",
    "sg:postcode":"60602",
    "sg:province":"IL",
    "wof:name":"Chicago Public Library Foundation",
    "wof:placetype":"venue"
},
  "geometry": {"coordinates":[-87.624487,41.88232],"type":"Point"}
}