{
  "type": "Feature",
  "properties": {
    "addr:full":"305 E Randolph St Pinckneyville IL 62274",
    "addr:housenumber":"305",
    "addr:postcode":"62274",
    "addr:street":"E Randolph St",
    "iso:country":"US",
    "sg:address":"305 E Randolph St",
    "sg:city":"Pinckneyville",
    "sg:classifiers":[
        {
            "category":"Health Services",
            "subcategory":"Dentist",
            "type":"Services"
        }
    ],
    "sg:phone":"+1 618 357 2446",
    "sg:postcode":"62274",
    "sg:province":"IL",
    "wof:name":"Herbert H Chapman Dds",
    "wof:placetype":"venue"
},
  "geometry": {"coordinates":[-89.377973,38.077498],"type":"Point"}
}