{
  "type": "Feature",
  "properties": {
    "addr:full":"1050 E Oakton St Des Plaines IL 60018",
    "addr:housenumber":"1050",
    "addr:postcode":"60018",
    "addr:street":"E Oakton St",
    "iso:country":"US",
    "sg:address":"1050 E Oakton St",
    "sg:city":"Des Plaines",
    "sg:classifiers":[
        {
            "category":"Restaurant",
            "type":"Food & Drink"
        }
    ],
    "sg:menulink":"http://www.allmenus.com/il/maine/21429-grazie!/menu/",
    "sg:phone":"+1 847 299 0011",
    "sg:postcode":"60018",
    "sg:province":"IL",
    "sg:tags":[
        "italian"
    ],
    "wof:name":"Grazie!",
    "wof:placetype":"venue"
},
  "geometry": {"coordinates":[-87.897294,42.023879],"type":"Point"}
}