{
  "type": "Feature",
  "properties": {
    "iso:country":"US",
    "sg:address":"1022 W Argyle St",
    "sg:city":"Chicago",
    "sg:classifiers":[
        {
            "category":"Real Estate",
            "subcategory":"Real Estate Agent",
            "type":"Services"
        }
    ],
    "sg:phone":"+1 773 271 4305",
    "sg:postcode":"60640",
    "sg:province":"IL",
    "sg:tags":[
        "agency"
    ],
    "wof:name":"Peoples Diversified Fincl Svcs",
    "wof:placetype":"venue"
},
  "geometry": {"coordinates":[-87.656184,41.97337],"type":"Point"}
}