{
  "type": "Feature",
  "properties": {
    "addr:full":"445 Harrison St Oak Park IL 60304",
    "addr:housenumber":"445",
    "addr:postcode":"60304",
    "addr:street":"Harrison St",
    "iso:country":"US",
    "sg:address":"445 Harrison St",
    "sg:city":"Oak Park",
    "sg:classifiers":[
        {
            "category":"Government",
            "subcategory":"Office",
            "type":"Public Place"
        }
    ],
    "sg:phone":"+1   ",
    "sg:postcode":"60304",
    "sg:province":"IL",
    "sg:tags":[
        "administration",
        "regulation",
        "program",
        "transportation"
    ],
    "wof:name":"Traffic System Center",
    "wof:placetype":"venue"
},
  "geometry": {"coordinates":[-87.788979,41.872478],"type":"Point"}
}