{
  "type": "Feature",
  "properties": {
    "addr:full":"10600 W 143rd St Orland Park IL 60462",
    "addr:housenumber":"10600",
    "addr:postcode":"60462",
    "addr:street":"W 143Rd St",
    "iso:country":"US",
    "sg:address":"10600 W 143rd St",
    "sg:city":"Orland Park",
    "sg:classifiers":[
        {
            "category":"Professional",
            "subcategory":"Lawyer & Legal Services",
            "type":"Services"
        }
    ],
    "sg:phone":"+1 708 460 4600",
    "sg:postcode":"60462",
    "sg:province":"IL",
    "wof:name":"Schreiber Mack & Postweiler",
    "wof:placetype":"venue"
},
  "geometry": {"coordinates":[-87.87781699999999,41.630067],"type":"Point"}
}