{
  "type": "Feature",
  "properties": {
    "iso:country":"US",
    "sg:address":"106 W Northwest Hwy",
    "sg:city":"Mount Prospect",
    "sg:classifiers":[
        {
            "category":"Restaurant",
            "type":"Food & Drink"
        }
    ],
    "sg:menulink":"http://www.allmenus.com/il/elk-grove/236027-pickermans-soup--sandwiches/menu/",
    "sg:phone":"+1 847 394 0333",
    "sg:postcode":"60056",
    "sg:province":"IL",
    "sg:tags":[
        "wrap",
        "soup",
        "american",
        "sandwich",
        "salad"
    ],
    "wof:name":"Pickerman's Soup & Sandwiches",
    "wof:placetype":"venue"
},
  "geometry": {"coordinates":[-87.938705,42.064524],"type":"Point"}
}