{
  "type": "Feature",
  "properties": {
    "iso:country":"US",
    "sg:address":"15009 Catlin Tilton Rd",
    "sg:city":"Danville",
    "sg:classifiers":[
        {
            "category":"Education",
            "subcategory":"School",
            "type":"Public Place"
        }
    ],
    "sg:phone":"+1 217 431 5547",
    "sg:postcode":"61834",
    "sg:province":"IL",
    "sg:tags":[
        "vocational"
    ],
    "wof:name":"Voted",
    "wof:placetype":"venue"
},
  "geometry": {"coordinates":[-87.662251,40.09938],"type":"Point"}
}