{
  "type": "Feature",
  "properties": {
    "addr:full":"101 Royce Rd Ste 4 Bolingbrook IL 60440",
    "addr:housenumber":"101",
    "addr:postcode":"60440",
    "addr:street":"Royce Rd Ste 4",
    "iso:country":"US",
    "sg:address":"101 Royce Rd Ste 4",
    "sg:city":"Bolingbrook",
    "sg:classifiers":[
        {
            "category":"Health Services",
            "subcategory":"Clinic",
            "type":"Services"
        },
        {
            "category":"Health Services",
            "subcategory":"Nursing And Care Facility",
            "type":"Services"
        },
        {
            "category":"Health Services",
            "subcategory":"Health Practitioner",
            "type":"Services"
        }
    ],
    "sg:phone":"+1 630 759 9640",
    "sg:postcode":"60440",
    "sg:province":"IL",
    "sg:tags":[
        "home",
        "medical",
        "eldercare-home"
    ],
    "wof:name":"Rainbow Health Care Services",
    "wof:placetype":"venue"
},
  "geometry": {"coordinates":[-88.068832,41.717548],"type":"Point"}
}