{
  "type": "Feature",
  "properties": {
    "addr:full":"8745 S Kedzie Ave Evergreen Park IL 60805",
    "addr:housenumber":"8745",
    "addr:postcode":"60805",
    "addr:street":"S Kedzie Ave",
    "iso:country":"US",
    "sg:address":"8745 S Kedzie Ave",
    "sg:city":"Evergreen Park",
    "sg:classifiers":[
        {
            "category":"Shopping",
            "type":"Retail Goods"
        }
    ],
    "sg:phone":"+1   ",
    "sg:postcode":"60805",
    "sg:province":"IL",
    "sg:tags":[
        "merchandise"
    ],
    "wof:name":"Cranley Awards Limited",
    "wof:placetype":"venue"
},
  "geometry": {"coordinates":[-87.702155,41.733763],"type":"Point"}
}