{
  "type": "Feature",
  "properties": {
    "iso:country":"US",
    "sg:address":"5140 N California Ave Ste 525",
    "sg:city":"Chicago",
    "sg:classifiers":[
        {
            "category":"Health Services",
            "subcategory":"Doctor",
            "type":"Services"
        }
    ],
    "sg:phone":"+1 773 769 1400",
    "sg:postcode":"60625",
    "sg:province":"IL",
    "wof:name":"Saporta Albert J MD",
    "wof:placetype":"venue"
},
  "geometry": {"coordinates":[-87.698898,41.975201],"type":"Point"}
}