{
  "type": "Feature",
  "properties": {
    "iso:country":"US",
    "sg:address":"4456 Montclair Rd",
    "sg:city":"Roscoe",
    "sg:classifiers":[
        {
            "category":"Sports & Exercise",
            "subcategory":"Race Track",
            "type":"Entertainment"
        }
    ],
    "sg:phone":"+1 815 624 7300",
    "sg:postcode":"61073",
    "sg:province":"IL",
    "sg:tags":[
        "equipment",
        "supply"
    ],
    "wof:name":"Adventure Interests LTD",
    "wof:placetype":"venue"
},
  "geometry": {"coordinates":[-89.030816,42.4458],"type":"Point"}
}