{
  "type": "Feature",
  "properties": {
    "iso:country":"US",
    "sg:address":"3616 James St",
    "sg:city":"Mc Henry",
    "sg:classifiers":[
        {
            "category":"Professional",
            "subcategory":"Computer Services",
            "type":"Services"
        },
        {
            "category":"Shopping",
            "subcategory":"Computers & Home Electronics",
            "type":"Retail Goods"
        }
    ],
    "sg:phone":"+1 815 385 1527",
    "sg:postcode":"60050",
    "sg:province":"IL",
    "sg:tags":[
        "prepackaged",
        "software",
        "custom"
    ],
    "wof:name":"Ranker Software",
    "wof:placetype":"venue"
},
  "geometry": {"coordinates":[-88.26761500000001,42.340398],"type":"Point"}
}