{
  "type": "Feature",
  "properties": {
    "iso:country":"US",
    "sg:address":"1607 W Ainslie St",
    "sg:city":"Chicago",
    "sg:classifiers":[
        {
            "category":"Professional",
            "subcategory":"Computer Services",
            "type":"Services"
        }
    ],
    "sg:phone":"+1 773 907 9101",
    "sg:postcode":"60640",
    "sg:province":"IL",
    "sg:tags":[
        "datum"
    ],
    "wof:name":"White Room Inc",
    "wof:placetype":"venue"
},
  "geometry": {"coordinates":[-87.670233,41.971767],"type":"Point"}
}