{
  "type": "Feature",
  "properties": {
    "iso:country":"US",
    "sg:address":"415 Summit St",
    "sg:city":"Elgin",
    "sg:classifiers":[
        {
            "category":"Restaurant",
            "type":"Food & Drink"
        }
    ],
    "sg:phone":"+1 847 888 9900",
    "sg:postcode":"60120",
    "sg:province":"IL",
    "wof:name":"Acapulco Restaurant of Elgin",
    "wof:placetype":"venue"
},
  "geometry": {"coordinates":[-88.275497,42.046398],"type":"Point"}
}