{
  "type": "Feature",
  "properties": {
    "iso:country":"US",
    "sg:address":"531 Mohican Rd",
    "sg:city":"Carol Stream",
    "sg:classifiers":[
        {
            "category":"Building & Trades",
            "subcategory":"Construction",
            "type":"Services"
        }
    ],
    "sg:phone":"+1 708 906 4718",
    "sg:postcode":"60188",
    "sg:province":"IL",
    "sg:tags":[
        "concrete",
        "contractor"
    ],
    "wof:name":"Benish & Barghs Cnstr Co",
    "wof:placetype":"venue"
},
  "geometry": {"coordinates":[-88.136964,41.920986],"type":"Point"}
}