{
  "type": "Feature",
  "properties": {
    "addr:full":"5312 W 123rd Pl Alsip IL 60803",
    "addr:housenumber":"5312",
    "addr:postcode":"60803",
    "addr:street":"W 123Rd Pl",
    "iso:country":"US",
    "sg:address":"5312 W 123rd Pl",
    "sg:city":"Alsip",
    "sg:classifiers":[
        {
            "category":"Wholesale",
            "subcategory":"Groceries",
            "type":"Manufacturing & Wholesale Goods"
        }
    ],
    "sg:phone":"+1 708 293 1634",
    "sg:postcode":"60803",
    "sg:province":"IL",
    "sg:tags":[
        "food",
        "to",
        "product"
    ],
    "wof:name":"Best Brand Chicago",
    "wof:placetype":"venue"
},
  "geometry": {"coordinates":[-87.74986199999999,41.668178],"type":"Point"}
}