{
  "type": "Feature",
  "properties": {
    "iso:country":"US",
    "sg:address":"1969 W Hart Rd",
    "sg:city":"Beloit",
    "sg:classifiers":[
        {
            "category":"Shopping",
            "subcategory":"Gifts & Souvenirs",
            "type":"Retail Goods"
        }
    ],
    "sg:phone":"+1 608 364 5163",
    "sg:postcode":"53511",
    "sg:province":"IL",
    "sg:tags":[
        "shop"
    ],
    "wof:name":"Gifts From The Hart",
    "wof:placetype":"venue"
},
  "geometry": {"coordinates":[-89.00670599999999,42.546741],"type":"Point"}
}