{
  "type": "Feature",
  "properties": {
    "addr:full":"120 E Northpoint Dr Streator IL 61364",
    "addr:housenumber":"120",
    "addr:postcode":"61364",
    "addr:street":"E Northpoint Dr",
    "iso:country":"US",
    "sg:address":"120 E Northpoint Dr",
    "sg:city":"Streator",
    "sg:classifiers":[
        {
            "category":"Banks & Credit Unions",
            "subcategory":"Bank",
            "type":"Services"
        },
        {
            "category":"Banks & Credit Unions",
            "subcategory":"Financial Services",
            "type":"Services"
        }
    ],
    "sg:phone":"+1 815 673 5577",
    "sg:postcode":"61364",
    "sg:province":"IL",
    "sg:tags":[
        "commercial",
        "loan",
        "saving"
    ],
    "sg:website":"http://www.streatoronized.org",
    "wof:name":"Streator Onized Credit Union",
    "wof:placetype":"venue"
},
  "geometry": {"coordinates":[-88.835266,41.14349],"type":"Point"}
}