{
  "type": "Feature",
  "properties": {
    "addr:full":"101 McHenry Rd Buffalo Grove IL 60089",
    "addr:housenumber":"101",
    "addr:postcode":"60089",
    "addr:street":"Mchenry Rd",
    "iso:country":"US",
    "sg:address":"101 McHenry Rd",
    "sg:city":"Buffalo Grove",
    "sg:classifiers":[
        {
            "category":"Shopping",
            "subcategory":"Gifts & Souvenirs",
            "type":"Retail Goods"
        }
    ],
    "sg:phone":"+1 847 520 0100",
    "sg:postcode":"60089",
    "sg:province":"IL",
    "sg:tags":[
        "party",
        "supply"
    ],
    "wof:name":"Card & Party Warehouse",
    "wof:placetype":"venue"
},
  "geometry": {"coordinates":[-87.95997,42.156805],"type":"Point"}
}