{
  "type": "Feature",
  "properties": {
    "iso:country":"US",
    "sg:address":"2404 Knox Road 2300 E",
    "sg:city":"La Fayette",
    "sg:classifiers":[
        {
            "category":"Farming",
            "subcategory":"Livestock Farm",
            "type":"Manufacturing & Wholesale Goods"
        }
    ],
    "sg:phone":"+1 309 995 3582",
    "sg:postcode":"61449",
    "sg:province":"IL",
    "sg:tags":[
        "beef",
        "feedlot",
        "cattle"
    ],
    "wof:name":"Alan J Harland",
    "wof:placetype":"venue"
},
  "geometry": {"coordinates":[-90.004138,41.063269],"type":"Point"}
}