{
  "type": "Feature",
  "properties": {
    "addr:full":"2445 N Lincoln Ave Chicago IL 60614",
    "addr:housenumber":"2445",
    "addr:postcode":"60614",
    "addr:street":"N Lincoln Ave",
    "iso:country":"US",
    "sg:address":"2445 N Lincoln Ave",
    "sg:city":"Chicago",
    "sg:classifiers":[
        {
            "category":"Banks & Credit Unions",
            "subcategory":"Financial Services",
            "type":"Services"
        }
    ],
    "sg:phone":"+1 773 325 9532",
    "sg:postcode":"60614",
    "sg:province":"IL",
    "sg:tags":[
        "broker",
        "mortgage"
    ],
    "wof:name":"Synergy Mortgage Company",
    "wof:placetype":"venue"
},
  "geometry": {"coordinates":[-87.650497,41.926601],"type":"Point"}
}