{
  "type": "Feature",
  "properties": {
    "addr:full":"811 W Main St Elmwood IL 61529",
    "addr:housenumber":"811",
    "addr:postcode":"61529",
    "addr:street":"W Main St",
    "iso:country":"US",
    "sg:address":"811 W Main St",
    "sg:city":"Elmwood",
    "sg:classifiers":[
        {
            "category":"Restaurant",
            "type":"Food & Drink"
        }
    ],
    "sg:phone":"+1 309 742 8888",
    "sg:postcode":"61529",
    "sg:province":"IL",
    "wof:name":"Casey's General Store",
    "wof:placetype":"venue"
},
  "geometry": {"coordinates":[-89.948819,40.777992],"type":"Point"}
}