{
  "type": "Feature",
  "properties": {
    "addr:full":"11110 S Western Ave Chicago IL 60643",
    "addr:housenumber":"11110",
    "addr:postcode":"60643",
    "addr:street":"S Western Ave",
    "iso:country":"US",
    "sg:address":"11110 S Western Ave",
    "sg:city":"Chicago",
    "sg:classifiers":[
        {
            "category":"Social Services",
            "type":"Services"
        },
        {
            "category":"Health Services",
            "subcategory":"Clinic",
            "type":"Services"
        }
    ],
    "sg:phone":"+1 773 905 5385",
    "sg:postcode":"60643",
    "sg:province":"IL",
    "sg:tags":[
        "mental"
    ],
    "sg:website":"http://www.mpichicago.com/index.php?mod=post&id=13",
    "wof:name":"Diversified Behavior Comprehensive Care",
    "wof:placetype":"venue"
},
  "geometry": {"coordinates":[-87.681152,41.691315],"type":"Point"}
}