{
  "type": "Feature",
  "properties": {
    "addr:full":"300 W Grand Avenue Chicago IL 60610",
    "addr:housenumber":"300",
    "addr:postcode":"60610",
    "addr:street":"W Grand Avenue",
    "iso:country":"US",
    "sg:address":"300 W Grand Avenue",
    "sg:city":"Chicago",
    "sg:classifiers":[
        {
            "category":"Real Estate",
            "subcategory":"Real Estate Operator",
            "type":"Services"
        }
    ],
    "sg:phone":"+1 312 527 6534",
    "sg:postcode":"60610",
    "sg:province":"IL",
    "sg:tags":[
        "apartment"
    ],
    "wof:name":"Wolin-Levin",
    "wof:placetype":"venue"
},
  "geometry": {"coordinates":[-87.635789,41.891621],"type":"Point"}
}