{
  "type": "Feature",
  "properties": {
    "iso:country":"US",
    "sg:address":"126 W Main St",
    "sg:city":"Urbana",
    "sg:classifiers":[
        {
            "category":"Shopping",
            "subcategory":"Florist",
            "type":"Retail Goods"
        }
    ],
    "sg:phone":"+1   ",
    "sg:postcode":"61801",
    "sg:province":"IL",
    "sg:tags":[
        "used",
        "merchandise"
    ],
    "wof:name":"Brash Flower Shop",
    "wof:placetype":"venue"
},
  "geometry": {"coordinates":[-88.208599,40.112517],"type":"Point"}
}