{
  "type": "Feature",
  "properties": {
    "addr:full":"55 E Jackson Blvd Suite 300 Chicago IL 60604",
    "addr:housenumber":"55",
    "addr:postcode":"60604",
    "addr:street":"E Jackson Blvd Suite 300",
    "iso:country":"US",
    "sg:address":"55 E Jackson Blvd Suite 300",
    "sg:city":"Chicago",
    "sg:classifiers":[
        {
            "category":"Education",
            "subcategory":"School",
            "type":"Public Place"
        }
    ],
    "sg:phone":"+1 800 694 5314",
    "sg:postcode":"60604",
    "sg:province":"IL",
    "sg:tags":[
        "massage"
    ],
    "sg:website":"www.soma.edu/",
    "wof:name":"Soma Institute",
    "wof:placetype":"venue"
},
  "geometry": {"coordinates":[-87.625623,41.878057],"type":"Point"}
}