{
  "type": "Feature",
  "properties": {
    "iso:country":"US",
    "sg:address":"413 N Weber Rd",
    "sg:city":"Romeoville",
    "sg:classifiers":[
        {
            "category":"Fast Food",
            "type":"Food & Drink"
        },
        {
            "category":"Restaurant",
            "type":"Food & Drink"
        }
    ],
    "sg:phone":"+1 815 886 7060",
    "sg:postcode":"60446",
    "sg:province":"IL",
    "sg:tags":[
        "mexican",
        "take"
    ],
    "wof:name":"Mr Taco",
    "wof:placetype":"venue"
},
  "geometry": {"coordinates":[-88.124557,41.642641],"type":"Point"}
}