{
  "type": "Feature",
  "properties": {
    "addr:full":"1907 N. Mendell St. 4th Fl Chicago IL 60642",
    "addr:housenumber":"1907",
    "addr:postcode":"60642",
    "addr:street":"N. Mendell St.",
    "iso:country":"US",
    "sg:address":"1907 N. Mendell St. 4th Fl",
    "sg:city":"Chicago",
    "sg:classifiers":[
        {
            "category":"Sports & Exercise",
            "subcategory":"Climbing Gym",
            "type":"Entertainment"
        },
        {
            "category":"Sports & Exercise",
            "subcategory":"Gym",
            "type":"Entertainment"
        }
    ],
    "sg:postcode":"60642",
    "sg:province":"IL",
    "sg:website":"chicagoelitefitness.com/",
    "wof:name":"Chicago Elite Fitness",
    "wof:placetype":"venue"
},
  "geometry": {"coordinates":[-87.66553399999999,41.917181],"type":"Point"}
}