{
  "type": "Feature",
  "properties": {
    "iso:country":"US",
    "sg:address":"7130 W Peotone Rd",
    "sg:city":"Peotone",
    "sg:phone":"+1 708 258 6922",
    "sg:postcode":"60468",
    "sg:province":"IL",
    "sg:tags":[
        "farm",
        "corn",
        "grain",
        "cash"
    ],
    "wof:name":"Lyle Wilke",
    "wof:placetype":"venue"
},
  "geometry": {"coordinates":[-87.783907,41.354073],"type":"Point"}
}