{
  "type": "Feature",
  "properties": {
    "iso:country":"US",
    "sg:address":"2829 Vail Ct",
    "sg:city":"Lisle",
    "sg:classifiers":[
        {
            "category":"Real Estate",
            "subcategory":"Real Estate Agent",
            "type":"Services"
        }
    ],
    "sg:phone":"+1 630 983 1118",
    "sg:postcode":"60532",
    "sg:province":"IL",
    "wof:name":"Andounian  Scheri",
    "wof:placetype":"venue"
},
  "geometry": {"coordinates":[-88.10505,41.762187],"type":"Point"}
}