{
  "type": "Feature",
  "properties": {
    "addr:full":"22840 Lake Cook Rd Barrington IL 60010",
    "addr:housenumber":"22840",
    "addr:postcode":"60010",
    "addr:street":"Lake Cook Rd",
    "iso:country":"US",
    "sg:address":"22840 Lake Cook Rd",
    "sg:city":"Barrington",
    "sg:classifiers":[
        {
            "category":"Wholesale",
            "subcategory":"Non-durable Goods",
            "type":"Manufacturing & Wholesale Goods"
        }
    ],
    "sg:phone":"+1 847 304 1644",
    "sg:postcode":"60010",
    "sg:province":"IL",
    "wof:name":"Ws Packaging",
    "wof:placetype":"venue"
},
  "geometry": {"coordinates":[-88.07736800000001,42.153907],"type":"Point"}
}