{
  "type": "Feature",
  "properties": {
    "addr:full":"110 N Main St Effingham IL 62401",
    "addr:housenumber":"110",
    "addr:postcode":"62401",
    "addr:street":"N Main St",
    "iso:country":"US",
    "sg:address":"110 N Main St",
    "sg:city":"Effingham",
    "sg:classifiers":[
        {
            "category":"Retail",
            "subcategory":"Auto Repair",
            "type":"Services"
        }
    ],
    "sg:phone":"+1   ",
    "sg:postcode":"62401",
    "sg:province":"IL",
    "sg:tags":[
        "automotive",
        "general"
    ],
    "wof:name":"Konrad Auto Repr Svc Kars",
    "wof:placetype":"venue"
},
  "geometry": {"coordinates":[-88.545922,39.122728],"type":"Point"}
}