{
  "type": "Feature",
  "properties": {
    "iso:country":"US",
    "sg:address":"510 W Frances St",
    "sg:city":"Chillicothe",
    "sg:classifiers":[
        {
            "category":"Organizations",
            "subcategory":"Religious Organization",
            "type":"Services"
        }
    ],
    "sg:phone":"+1 309 274 4419",
    "sg:postcode":"61523",
    "sg:province":"IL",
    "sg:tags":[
        "church"
    ],
    "sg:website":"www.chillicothechristian.net",
    "wof:name":"Chillicothe Christian Church",
    "wof:placetype":"venue"
},
  "geometry": {"coordinates":[-89.493955,40.911304],"type":"Point"}
}