{
  "type": "Feature",
  "properties": {
    "iso:country":"US",
    "sg:address":"1357 Washburn Way",
    "sg:city":"Lockport",
    "sg:classifiers":[
        {
            "category":"Building & Trades",
            "subcategory":"Landscaping Services",
            "type":"Services"
        }
    ],
    "sg:phone":"+1 815 834 1543",
    "sg:postcode":"60441",
    "sg:province":"IL",
    "wof:name":"Franks Lawn Maintenance",
    "wof:placetype":"venue"
},
  "geometry": {"coordinates":[-88.02680100000001,41.592419],"type":"Point"}
}