{
  "type": "Feature",
  "properties": {
    "iso:country":"US",
    "sg:address":"1460 Golf Rd",
    "sg:city":"Rolling Meadows",
    "sg:classifiers":[
        {
            "category":"Restaurant",
            "type":"Food & Drink"
        }
    ],
    "sg:menulink":"http://www.allmenus.com/il/elk-grove/127376-subway/menu/",
    "sg:phone":"+1 847 690 0100",
    "sg:postcode":"60008",
    "sg:province":"IL",
    "sg:tags":[
        "american",
        "sandwich"
    ],
    "wof:name":"Subway",
    "wof:placetype":"venue"
},
  "geometry": {"coordinates":[-87.998805,42.051336],"type":"Point"}
}