{
  "type": "Feature",
  "properties": {
    "addr:full":"558 Swain Ave Elmhurst IL 60126",
    "addr:housenumber":"558",
    "addr:postcode":"60126",
    "addr:street":"Swain Ave",
    "iso:country":"US",
    "sg:address":"558 Swain Ave",
    "sg:city":"Elmhurst",
    "sg:classifiers":[
        {
            "category":"Professional",
            "subcategory":"Management & Consulting",
            "type":"Services"
        }
    ],
    "sg:phone":"+1 630 516 0488",
    "sg:postcode":"60126",
    "sg:province":"IL",
    "wof:name":"Douglas C Heinen",
    "wof:placetype":"venue"
},
  "geometry": {"coordinates":[-87.94722299999999,41.884657],"type":"Point"}
}