{
  "type": "Feature",
  "properties": {
    "iso:country":"US",
    "sg:address":"100 W Blue Ave",
    "sg:city":"Creal Springs",
    "sg:classifiers":[
        {
            "category":"Insurance",
            "subcategory":"Insurance Agent",
            "type":"Services"
        }
    ],
    "sg:phone":"+1 618 996 2211",
    "sg:postcode":"62922",
    "sg:province":"IL",
    "wof:name":"Taylor Insurance",
    "wof:placetype":"venue"
},
  "geometry": {"coordinates":[-88.838983,37.619472],"type":"Point"}
}