{
  "type": "Feature",
  "properties": {
    "addr:full":"301 Main St Antioch IL 60002",
    "addr:housenumber":"301",
    "addr:postcode":"60002",
    "addr:street":"Main St",
    "iso:country":"US",
    "sg:address":"301 Main St",
    "sg:city":"Antioch",
    "sg:classifiers":[
        {
            "category":"Building & Trades",
            "subcategory":"Construction",
            "type":"Services"
        }
    ],
    "sg:phone":"+1 847 395 7762",
    "sg:postcode":"60002",
    "sg:province":"IL",
    "sg:tags":[
        "insulation",
        "heat",
        "contractor"
    ],
    "wof:name":"Rons Insulation",
    "wof:placetype":"venue"
},
  "geometry": {"coordinates":[-88.09434,42.493921],"type":"Point"}
}