{
  "type": "Feature",
  "properties": {
    "iso:country":"US",
    "sg:address":"520 E Madison Ave",
    "sg:city":"Chrisman",
    "sg:phone":"+1 217 269 2520",
    "sg:postcode":"61924",
    "sg:province":"IL",
    "sg:tags":[
        "real",
        "lessor",
        "farm",
        "corn",
        "soybean",
        "property"
    ],
    "wof:name":"Wayne and Sallie Sue Grissom",
    "wof:placetype":"venue"
},
  "geometry": {"coordinates":[-87.670986,39.804662],"type":"Point"}
}