{
  "type": "Feature",
  "properties": {
    "iso:country":"US",
    "sg:address":"7112 Cermak Rd Ste 2",
    "sg:city":"Berwyn",
    "sg:classifiers":[
        {
            "category":"Professional",
            "subcategory":"Lawyer & Legal Services",
            "type":"Services"
        }
    ],
    "sg:phone":"+1 708 788 1200",
    "sg:postcode":"60402",
    "sg:province":"IL",
    "wof:name":"Svec Milton A Associates Atty",
    "wof:placetype":"venue"
},
  "geometry": {"coordinates":[-87.8013,41.850201],"type":"Point"}
}