{
  "type": "Feature",
  "properties": {
    "addr:full":"300 W Roosevelt Rd Villa Park IL 60187",
    "addr:housenumber":"300",
    "addr:postcode":"60187",
    "addr:street":"W Roosevelt Rd",
    "iso:country":"US",
    "sg:address":"300 W Roosevelt Rd",
    "sg:city":"Villa Park",
    "sg:classifiers":[
        {
            "category":"Autos & Motor Vehicles",
            "subcategory":"Automobile Sales",
            "type":"Retail Goods"
        }
    ],
    "sg:phone":"+1 630 279 2000",
    "sg:postcode":"60187",
    "sg:province":"IL",
    "sg:tags":[
        "car",
        "dealer"
    ],
    "sg:website":"www.haggertygroup.com",
    "wof:name":"Haggerty Pontiac-GMC Inc",
    "wof:placetype":"venue"
},
  "geometry": {"coordinates":[-88.111451,41.858681],"type":"Point"}
}