{
  "type": "Feature",
  "properties": {
    "addr:full":"440 Bank Ln Highwood IL 60040",
    "addr:housenumber":"440",
    "addr:postcode":"60040",
    "addr:street":"Bank Ln",
    "iso:country":"US",
    "sg:address":"440 Bank Ln",
    "sg:city":"Highwood",
    "sg:classifiers":[
        {
            "category":"Organizations",
            "subcategory":"Community Association",
            "type":"Services"
        }
    ],
    "sg:phone":"+1 847 926 8118",
    "sg:postcode":"60040",
    "sg:province":"IL",
    "sg:tags":[
        "club"
    ],
    "wof:name":"Highwood Bocce Courts",
    "wof:placetype":"venue"
},
  "geometry": {"coordinates":[-87.81120300000001,42.204575],"type":"Point"}
}