{
  "type": "Feature",
  "properties": {
    "iso:country":"US",
    "sg:address":"5401 Cleveland St",
    "sg:city":"Morton Grove",
    "sg:classifiers":[
        {
            "category":"Shopping",
            "subcategory":"Pharmacy",
            "type":"Retail Goods"
        }
    ],
    "sg:phone":"+1   ",
    "sg:postcode":"60053",
    "sg:province":"IL",
    "wof:name":"Radha Pharmacy Inc",
    "wof:placetype":"venue"
},
  "geometry": {"coordinates":[-87.764054,42.030014],"type":"Point"}
}