{
  "type": "Feature",
  "properties": {
    "addr:full":"960 W Chicago Ave Chicago IL 60642",
    "addr:housenumber":"960",
    "addr:postcode":"60642",
    "addr:street":"W Chicago Ave",
    "iso:country":"US",
    "sg:address":"960 W Chicago Ave",
    "sg:city":"Chicago",
    "sg:classifiers":[
        {
            "category":"Retail",
            "subcategory":"Veterinary Services",
            "type":"Services"
        }
    ],
    "sg:phone":"+1 312 738 3322",
    "sg:postcode":"60642",
    "sg:province":"IL",
    "sg:tags":[
        "veterinarian",
        "specialty"
    ],
    "wof:name":"Houk Ray DVM",
    "wof:placetype":"venue"
},
  "geometry": {"coordinates":[-87.651978,41.896347],"type":"Point"}
}