{
  "type": "Feature",
  "properties": {
    "addr:full":"6603 Ammons Rd Bartelso IL 62218",
    "addr:housenumber":"6603",
    "addr:postcode":"62218",
    "addr:street":"Ammons Rd",
    "iso:country":"US",
    "sg:address":"6603 Ammons Rd",
    "sg:city":"Bartelso",
    "sg:classifiers":[
        {
            "category":"Farming",
            "subcategory":"Dairy Farm",
            "type":"Manufacturing & Wholesale Goods"
        }
    ],
    "sg:phone":"+1 618 523 4924",
    "sg:postcode":"62218",
    "sg:province":"IL",
    "wof:name":"Double A Dairy",
    "wof:placetype":"venue"
},
  "geometry": {"coordinates":[-89.516282,38.521073],"type":"Point"}
}