{
  "type": "Feature",
  "properties": {
    "addr:full":"1033 University Pl Evanston IL 60201",
    "addr:housenumber":"1033",
    "addr:postcode":"60201",
    "addr:street":"University Pl",
    "iso:country":"US",
    "sg:address":"1033 University Pl",
    "sg:city":"Evanston",
    "sg:classifiers":[
        {
            "category":"Government",
            "subcategory":"Office",
            "type":"Public Place"
        }
    ],
    "sg:phone":"+1   ",
    "sg:postcode":"60201",
    "sg:province":"IL",
    "sg:tags":[
        "forest"
    ],
    "wof:name":"Forest Service",
    "wof:placetype":"venue"
},
  "geometry": {"coordinates":[-87.68597699999999,42.051143],"type":"Point"}
}