{
  "type": "Feature",
  "properties": {
    "iso:country":"US",
    "sg:address":"19174 Cass County Line St",
    "sg:city":"Petersburg",
    "sg:classifiers":[
        {
            "category":"Professional",
            "subcategory":"Business Services",
            "type":"Services"
        }
    ],
    "sg:phone":"+1 217 634 4444",
    "sg:postcode":"62675",
    "sg:province":"IL",
    "sg:tags":[
        "auction"
    ],
    "wof:name":"Canterbury Auction",
    "wof:placetype":"venue"
},
  "geometry": {"coordinates":[-89.994957,40.038273],"type":"Point"}
}