{
  "type": "Feature",
  "properties": {
    "addr:full":"802 State St Quincy IL 62301",
    "addr:housenumber":"802",
    "addr:postcode":"62301",
    "addr:street":"State St",
    "iso:country":"US",
    "sg:address":"802 State St",
    "sg:city":"Quincy",
    "sg:classifiers":[
        {
            "category":"Wholesale",
            "subcategory":"Electrical",
            "type":"Manufacturing & Wholesale Goods"
        }
    ],
    "sg:phone":"+1 217 224 4940",
    "sg:postcode":"62301",
    "sg:province":"IL",
    "sg:tags":[
        "appliance"
    ],
    "wof:name":"A B Parts Today",
    "wof:placetype":"venue"
},
  "geometry": {"coordinates":[-91.40327600000001,39.926486],"type":"Point"}
}