{
  "type": "Feature",
  "properties": {
    "addr:full":"10065 Anderson Ave Chicago Ridge IL 60415",
    "addr:housenumber":"10065",
    "addr:postcode":"60415",
    "addr:street":"Anderson Ave",
    "iso:country":"US",
    "sg:address":"10065 Anderson Ave",
    "sg:city":"Chicago Ridge",
    "sg:classifiers":[
        {
            "category":"Home & Garden",
            "subcategory":"Furniture",
            "type":"Retail Goods"
        }
    ],
    "sg:phone":"+1 708 424 8126",
    "sg:postcode":"60415",
    "sg:province":"IL",
    "sg:tags":[
        "store"
    ],
    "wof:name":"Versatile Installations",
    "wof:placetype":"venue"
},
  "geometry": {"coordinates":[-87.78890199999999,41.709],"type":"Point"}
}