{
  "type": "Feature",
  "properties": {
    "iso:country":"US",
    "sg:address":"1975 E 73rd St",
    "sg:city":"Chicago",
    "sg:classifiers":[
        {
            "category":"Personal",
            "subcategory":"Barber",
            "type":"Services"
        }
    ],
    "sg:phone":"+1 773 288 4655",
    "sg:postcode":"60649",
    "sg:province":"IL",
    "wof:name":"Original Man's",
    "wof:placetype":"venue"
},
  "geometry": {"coordinates":[-87.576897,41.7626],"type":"Point"}
}