{
  "type": "Feature",
  "properties": {
    "iso:country":"US",
    "sg:address":"5151 N Lincoln Ave",
    "sg:city":"Chicago",
    "sg:classifiers":[
        {
            "category":"Health Services",
            "subcategory":"Health Practitioner",
            "type":"Services"
        }
    ],
    "sg:phone":"+1 773 754 8556",
    "sg:postcode":"60625",
    "sg:province":"IL",
    "sg:tags":[
        "therapy",
        "physical"
    ],
    "wof:name":"Lexington Phys Therapy",
    "wof:placetype":"venue"
},
  "geometry": {"coordinates":[-87.69211300000001,41.975168],"type":"Point"}
}