{
  "type": "Feature",
  "properties": {
    "iso:country":"US",
    "sg:address":"2093 W Station St",
    "sg:city":"Kankakee",
    "sg:classifiers":[
        {
            "category":"Autos & Motor Vehicles",
            "subcategory":"Auto Supplies",
            "type":"Retail Goods"
        }
    ],
    "sg:phone":"+1 815 937 9000",
    "sg:postcode":"60901",
    "sg:province":"IL",
    "sg:tags":[
        "automobile",
        "stereo",
        "radio"
    ],
    "wof:name":"Insured Dealer Svc",
    "wof:placetype":"venue"
},
  "geometry": {"coordinates":[-87.893167,41.118553],"type":"Point"}
}