{
  "type": "Feature",
  "properties": {
    "addr:full":"2233 Northwestern Ave Waukegan IL 60087",
    "addr:housenumber":"2233",
    "addr:postcode":"60087",
    "addr:street":"Northwestern Ave",
    "iso:country":"US",
    "sg:address":"2233 Northwestern Ave",
    "sg:city":"Waukegan",
    "sg:classifiers":[
        {
            "category":"Manufacturing",
            "subcategory":"Tools & Machinery",
            "type":"Manufacturing & Wholesale Goods"
        }
    ],
    "sg:phone":"+1 847 623 6327",
    "sg:postcode":"60087",
    "sg:province":"IL",
    "sg:tags":[
        "machine",
        "shop"
    ],
    "wof:name":"LCM",
    "wof:placetype":"venue"
},
  "geometry": {"coordinates":[-87.894458,42.393054],"type":"Point"}
}