{
  "type": "Feature",
  "properties": {
    "addr:full":"8220 Ulah Rd Cambridge IL 61238",
    "addr:housenumber":"8220",
    "addr:postcode":"61238",
    "addr:street":"Ulah Rd",
    "iso:country":"US",
    "sg:address":"8220 Ulah Rd",
    "sg:city":"Cambridge",
    "sg:classifiers":[
        {
            "category":"Shopping",
            "type":"Retail Goods"
        }
    ],
    "sg:phone":"+1 309 937 5591",
    "sg:postcode":"61238",
    "sg:province":"IL",
    "sg:tags":[
        "chemical"
    ],
    "sg:website":"www.michligag.com",
    "wof:name":"Michlig Agri Ctr Chemical Shed",
    "wof:placetype":"venue"
},
  "geometry": {"coordinates":[-90.146079,41.265783],"type":"Point"}
}