{
  "type": "Feature",
  "properties": {
    "iso:country":"US",
    "sg:address":"11212 S Harlem Ave",
    "sg:city":"Worth",
    "sg:classifiers":[
        {
            "category":"Professional",
            "subcategory":"Lawyer & Legal Services",
            "type":"Services"
        }
    ],
    "sg:phone":"+1 708 448 7063",
    "sg:postcode":"60482",
    "sg:province":"IL",
    "wof:name":"Ebersohl Jas L Atty",
    "wof:placetype":"venue"
},
  "geometry": {"coordinates":[-87.797501,41.687401],"type":"Point"}
}