{
  "type": "Feature",
  "properties": {
    "addr:full":"753 W US Highway 50 O Fallon IL 62269",
    "addr:housenumber":"753",
    "addr:postcode":"62269",
    "addr:street":"W Us Highway 50 O",
    "iso:country":"US",
    "sg:address":"753 W US Highway 50",
    "sg:city":"O Fallon",
    "sg:classifiers":[
        {
            "category":"Shopping",
            "subcategory":"Pharmacy",
            "type":"Retail Goods"
        }
    ],
    "sg:phone":"+1 618 624 3561",
    "sg:postcode":"62269",
    "sg:province":"IL",
    "sg:tags":[
        "drugstore"
    ],
    "wof:name":"Cvs/Pharmacy",
    "wof:placetype":"venue"
},
  "geometry": {"coordinates":[-89.930801,38.590099],"type":"Point"}
}