{
  "type": "Feature",
  "properties": {
    "iso:country":"US",
    "sg:address":"2425 Pan Am Blvd",
    "sg:city":"Elk Grove Village",
    "sg:classifiers":[
        {
            "category":"Building & Trades",
            "subcategory":"Construction",
            "type":"Services"
        }
    ],
    "sg:phone":"+1 847 766 5550",
    "sg:postcode":"60007",
    "sg:province":"IL",
    "sg:tags":[
        "concrete",
        "contractor"
    ],
    "wof:name":"Troch McNeil Paving Co Inc",
    "wof:placetype":"venue"
},
  "geometry": {"coordinates":[-87.943922,41.987401],"type":"Point"}
}