{
  "type": "Feature",
  "properties": {
    "iso:country":"US",
    "sg:address":"4939 W Van Buren Street",
    "sg:city":"Chicago",
    "sg:classifiers":[
        {
            "category":"Education",
            "subcategory":"School",
            "type":"Public Place"
        },
        {
            "category":"Organizations",
            "subcategory":"Community Association",
            "type":"Services"
        }
    ],
    "sg:phone":"+1 773 378 3262",
    "sg:postcode":"60644",
    "sg:province":"IL",
    "sg:tags":[
        "high",
        "elementary",
        "middle"
    ],
    "wof:name":"Family Academy",
    "wof:placetype":"venue"
},
  "geometry": {"coordinates":[-87.747793,41.874891],"type":"Point"}
}