{
  "type": "Feature",
  "properties": {
    "addr:full":"5537 County Farm Rd Hanover Park IL 60133",
    "addr:housenumber":"5537",
    "addr:postcode":"60133",
    "addr:street":"County Farm Rd",
    "iso:country":"US",
    "sg:address":"5537 County Farm Rd",
    "sg:city":"Hanover Park",
    "sg:classifiers":[
        {
            "category":"Health Services",
            "subcategory":"Dentist",
            "type":"Services"
        }
    ],
    "sg:phone":"+1 630 289 4840",
    "sg:postcode":"60133",
    "sg:province":"IL",
    "wof:name":"Gentle Dental Smile",
    "wof:placetype":"venue"
},
  "geometry": {"coordinates":[-88.151433,41.965943],"type":"Point"}
}