{
  "type": "Feature",
  "properties": {
    "iso:country":"US",
    "sg:address":"5140 S Hyde Park Blvd 5C",
    "sg:city":"Chicago",
    "sg:classifiers":[
        {
            "category":"Communications",
            "subcategory":"Film & Video Production",
            "type":"Services"
        }
    ],
    "sg:phone":"+1 773 510 6037",
    "sg:postcode":"60615",
    "sg:province":"IL",
    "sg:tags":[
        "picture",
        "companies-film",
        "tv",
        "motion",
        "radio"
    ],
    "wof:name":"In It To Win It Productions",
    "wof:placetype":"venue"
},
  "geometry": {"coordinates":[-87.584954,41.801922],"type":"Point"}
}