{
  "type": "Feature",
  "properties": {
    "iso:country":"US",
    "sg:address":"101 S Commercial St",
    "sg:city":"Woodson",
    "sg:classifiers":[
        {
            "category":"Bars & Pubs",
            "type":"Food & Drink"
        }
    ],
    "sg:phone":"+1 217 673 6841",
    "sg:postcode":"62695",
    "sg:province":"IL",
    "wof:name":"Midway Tavern",
    "wof:placetype":"venue"
},
  "geometry": {"coordinates":[-90.21971,39.628896],"type":"Point"}
}