{
  "type": "Feature",
  "properties": {
    "addr:full":"3452 N Cicero Ave Chicago IL 60641",
    "addr:housenumber":"3452",
    "addr:postcode":"60641",
    "addr:street":"N Cicero Ave",
    "iso:country":"US",
    "sg:address":"3452 N Cicero Ave",
    "sg:city":"Chicago",
    "sg:classifiers":[
        {
            "category":"Manufacturing",
            "subcategory":"Printing",
            "type":"Manufacturing & Wholesale Goods"
        }
    ],
    "sg:phone":"+1 773 725 5204",
    "sg:postcode":"60641",
    "sg:province":"IL",
    "sg:tags":[
        "printer"
    ],
    "wof:name":"C J's Printing",
    "wof:placetype":"venue"
},
  "geometry": {"coordinates":[-87.74708200000001,41.94406],"type":"Point"}
}