{
  "type": "Feature",
  "properties": {
    "addr:full":"640 Thornhill Ln Palatine IL 60074",
    "addr:housenumber":"640",
    "addr:postcode":"60074",
    "addr:street":"Thornhill Ln",
    "iso:country":"US",
    "sg:address":"640 Thornhill Ln",
    "sg:city":"Palatine",
    "sg:classifiers":[
        {
            "category":"Professional",
            "subcategory":"Computer Services",
            "type":"Services"
        }
    ],
    "sg:phone":"+1 847 981 9600",
    "sg:postcode":"60074",
    "sg:province":"IL",
    "sg:tags":[
        "agency",
        "employment",
        "programing",
        "custom"
    ],
    "wof:name":"Graf Consulting Inc",
    "wof:placetype":"venue"
},
  "geometry": {"coordinates":[-88.026472,42.135892],"type":"Point"}
}