{
  "type": "Feature",
  "properties": {
    "iso:country":"US",
    "sg:address":"1020 Mc Cameron Ave",
    "sg:city":"Lockport",
    "sg:classifiers":[
        {
            "category":"Building & Trades",
            "subcategory":"Construction",
            "type":"Services"
        }
    ],
    "sg:phone":"+1 815 588 1401",
    "sg:postcode":"60441",
    "sg:province":"IL",
    "sg:tags":[
        "roofing",
        "contractor",
        "commercial",
        "residential"
    ],
    "wof:name":"A Rose Roofing & Sheet Metal",
    "wof:placetype":"venue"
},
  "geometry": {"coordinates":[-88.037586,41.601412],"type":"Point"}
}