{
  "type": "Feature",
  "properties": {
    "iso:country":"US",
    "sg:address":"16139 Fairhaven Rd",
    "sg:city":"Thomson",
    "sg:phone":"+1 815 259 3483",
    "sg:postcode":"61285",
    "sg:province":"IL",
    "sg:tags":[
        "farm",
        "corn",
        "beef",
        "feedlot",
        "cattle"
    ],
    "wof:name":"Everett Appel",
    "wof:placetype":"venue"
},
  "geometry": {"coordinates":[-89.997108,41.945444],"type":"Point"}
}