{
  "type": "Feature",
  "properties": {
    "addr:full":"904 N Cedar Lake Rd Round Lake Beach IL 60073",
    "addr:housenumber":"904",
    "addr:postcode":"60073",
    "addr:street":"N Cedar Lake Rd Round Lake Beach",
    "iso:country":"US",
    "sg:address":"904 N Cedar Lake Rd",
    "sg:city":"Round Lake Beach",
    "sg:classifiers":[
        {
            "category":"Home & Garden",
            "subcategory":"Carpets & Floor Coverings",
            "type":"Retail Goods"
        }
    ],
    "sg:phone":"+1 847 546 6696",
    "sg:postcode":"60073",
    "sg:province":"IL",
    "sg:tags":[
        "dealer",
        "rug"
    ],
    "wof:name":"Franks Floors",
    "wof:placetype":"venue"
},
  "geometry": {"coordinates":[-88.089885,42.364549],"type":"Point"}
}