{
  "type": "Feature",
  "properties": {
    "addr:full":"2370 E Lincoln Hwy New Lenox IL 60451",
    "addr:housenumber":"2370",
    "addr:postcode":"60451",
    "addr:street":"E Lincoln Hwy",
    "iso:country":"US",
    "sg:address":"2370 E Lincoln Hwy",
    "sg:city":"New Lenox",
    "sg:classifiers":[
        {
            "category":"Coffee & Tea",
            "type":"Food & Drink"
        }
    ],
    "sg:menulink":"http://www.allmenus.com/il/new-lenox/112558-starbucks-coffee/menu/",
    "sg:phone":"+1 815 462 6001",
    "sg:postcode":"60451",
    "sg:province":"IL",
    "sg:tags":[
        "american"
    ],
    "wof:name":"Starbucks Coffee",
    "wof:placetype":"venue"
},
  "geometry": {"coordinates":[-87.92358400000001,41.50992],"type":"Point"}
}