{
  "type": "Feature",
  "properties": {
    "iso:country":"US",
    "sg:address":"15108 River Rd",
    "sg:city":"East Moline",
    "sg:classifiers":[
        {
            "category":"Professional",
            "subcategory":"Business Services",
            "type":"Services"
        }
    ],
    "sg:phone":"+1 309 792 4420",
    "sg:postcode":"61244",
    "sg:province":"IL",
    "sg:tags":[
        "fund",
        "promotion",
        "raising"
    ],
    "wof:name":"Premier Promotion",
    "wof:placetype":"venue"
},
  "geometry": {"coordinates":[-90.404523,41.47169],"type":"Point"}
}