{
  "type": "Feature",
  "properties": {
    "iso:country":"US",
    "sg:address":"1500 Ravinia Pl",
    "sg:city":"Orland Park",
    "sg:classifiers":[
        {
            "category":"Professional",
            "subcategory":"Lawyer & Legal Services",
            "type":"Services"
        }
    ],
    "sg:phone":"+1 708 460 7680",
    "sg:postcode":"60462",
    "sg:province":"IL",
    "sg:tags":[
        "attorney"
    ],
    "wof:name":"James Friel",
    "wof:placetype":"venue"
},
  "geometry": {"coordinates":[-87.85343899999999,41.615343],"type":"Point"}
}