{
  "type": "Feature",
  "properties": {
    "addr:full":"1 Tiffany Pt Bloomingdale IL 60108",
    "addr:housenumber":"1",
    "addr:postcode":"60108",
    "addr:street":"Tiffany Pt",
    "iso:country":"US",
    "sg:address":"1 Tiffany Pt",
    "sg:city":"Bloomingdale",
    "sg:classifiers":[
        {
            "category":"Personal",
            "subcategory":"Beauty Salon",
            "type":"Services"
        }
    ],
    "sg:phone":"+1 630 351 2222",
    "sg:postcode":"60108",
    "sg:province":"IL",
    "wof:name":"Meetings And Event Solutions",
    "wof:placetype":"venue"
},
  "geometry": {"coordinates":[-88.081017,41.954891],"type":"Point"}
}