{
  "type": "Feature",
  "properties": {
    "addr:full":"862 E Pleasant Hill Rd Carbondale IL 62902",
    "addr:housenumber":"862",
    "addr:postcode":"62902",
    "addr:street":"E Pleasant Hill Rd",
    "iso:country":"US",
    "sg:address":"862 E Pleasant Hill Rd",
    "sg:city":"Carbondale",
    "sg:classifiers":[
        {
            "category":"Professional",
            "subcategory":"Detective & Security Services",
            "type":"Services"
        }
    ],
    "sg:phone":"+1 618 351 0740",
    "sg:postcode":"62902",
    "sg:province":"IL",
    "sg:tags":[
        "investigator"
    ],
    "wof:name":"Zero Tolerance Drug Dogs",
    "wof:placetype":"venue"
},
  "geometry": {"coordinates":[-89.198874,37.700421],"type":"Point"}
}