{
  "type": "Feature",
  "properties": {
    "addr:full":"15 S Lincoln Ave Ste A Aurora IL 60505",
    "addr:housenumber":"15",
    "addr:postcode":"60505",
    "addr:street":"S Lincoln Ave Ste A",
    "iso:country":"US",
    "sg:address":"15 S Lincoln Ave Ste A",
    "sg:city":"Aurora",
    "sg:classifiers":[
        {
            "category":"Retail",
            "subcategory":"Laundry & Dry Cleaning",
            "type":"Services"
        }
    ],
    "sg:phone":"+1 630 897 2744",
    "sg:postcode":"60505",
    "sg:province":"IL",
    "sg:tags":[
        "laundries-self",
        "operated",
        "washer",
        "dryer",
        "coin"
    ],
    "sg:website":"http://www.superwash.com",
    "wof:name":"Superwash Coin Laundry Inc",
    "wof:placetype":"venue"
},
  "geometry": {"coordinates":[-88.31107799999999,41.755581],"type":"Point"}
}