{
  "type": "Feature",
  "properties": {
    "iso:country":"US",
    "sg:address":"40826 N State Rte 83",
    "sg:city":"Antioch",
    "sg:classifiers":[
        {
            "category":"Autos & Motor Vehicles",
            "subcategory":"Motorcycle Sales",
            "type":"Retail Goods"
        }
    ],
    "sg:phone":"+1 847 395 5300",
    "sg:postcode":"60002",
    "sg:province":"IL",
    "sg:tags":[
        "scooter"
    ],
    "wof:name":"Herb's Inc",
    "wof:placetype":"venue"
},
  "geometry": {"coordinates":[-88.091749,42.456678],"type":"Point"}
}