{
  "type": "Feature",
  "properties": {
    "addr:full":"198 W Laraway Rd Joliet IL 60436",
    "addr:housenumber":"198",
    "addr:postcode":"60436",
    "addr:street":"W Laraway Rd",
    "iso:country":"US",
    "sg:address":"198 W Laraway Rd",
    "sg:city":"Joliet",
    "sg:phone":"+1 815 723 3792",
    "sg:postcode":"60436",
    "sg:province":"IL",
    "sg:tags":[
        "farm"
    ],
    "wof:name":"Glasscock Farms",
    "wof:placetype":"venue"
},
  "geometry": {"coordinates":[-88.08367200000001,41.480691],"type":"Point"}
}