{
  "type": "Feature",
  "properties": {
    "iso:country":"US",
    "sg:address":"1271 W Galena Ave",
    "sg:city":"Freeport",
    "sg:classifiers":[
        {
            "category":"Shopping",
            "subcategory":"Department Store",
            "type":"Retail Goods"
        }
    ],
    "sg:phone":"+1 815 233 6133",
    "sg:postcode":"61032",
    "sg:province":"IL",
    "sg:tags":[
        "shop"
    ],
    "wof:name":"Big Lots",
    "wof:placetype":"venue"
},
  "geometry": {"coordinates":[-89.643709,42.301571],"type":"Point"}
}