{
  "type": "Feature",
  "properties": {
    "addr:full":"1330 N State Pkwy Chicago IL 60610",
    "addr:housenumber":"1330",
    "addr:postcode":"60610",
    "addr:street":"N State Pkwy",
    "iso:country":"US",
    "sg:address":"1330 N State Pkwy",
    "sg:city":"Chicago",
    "sg:classifiers":[
        {
            "category":"Communications",
            "subcategory":"Television Station",
            "type":"Services"
        }
    ],
    "sg:phone":"+1 312 280 8389",
    "sg:postcode":"60610",
    "sg:province":"IL",
    "sg:tags":[
        "commercials-radio"
    ],
    "wof:name":"Haboush Co Inc",
    "wof:placetype":"venue"
},
  "geometry": {"coordinates":[-87.62875200000001,41.906398],"type":"Point"}
}