{
  "type": "Feature",
  "properties": {
    "addr:full":"1156 Pine St Apt 4 Glenview IL 60025",
    "addr:housenumber":"1156;4",
    "addr:postcode":"60025",
    "addr:street":"Pine St Apt",
    "iso:country":"US",
    "sg:address":"1156 Pine St Apt 4",
    "sg:city":"Glenview",
    "sg:classifiers":[
        {
            "category":"Professional",
            "subcategory":"Art Services",
            "type":"Services"
        }
    ],
    "sg:phone":"+1 847 657 7623",
    "sg:postcode":"60025",
    "sg:province":"IL",
    "sg:tags":[
        "commercial",
        "artist"
    ],
    "wof:name":"Nancy R Halliday",
    "wof:placetype":"venue"
},
  "geometry": {"coordinates":[-87.803833,42.075678],"type":"Point"}
}