{
  "type": "Feature",
  "properties": {
    "iso:country":"US",
    "sg:address":"830 North Blvd Ste 2",
    "sg:city":"Oak Park",
    "sg:classifiers":[
        {
            "category":"Banks & Credit Unions",
            "subcategory":"Bank",
            "type":"Services"
        }
    ],
    "sg:phone":"+1 708 445 8491",
    "sg:postcode":"60301",
    "sg:province":"IL",
    "wof:name":"I Comm Consulting Inc",
    "wof:placetype":"venue"
},
  "geometry": {"coordinates":[-87.795097,41.887199],"type":"Point"}
}