{
  "type": "Feature",
  "properties": {
    "iso:country":"US",
    "sg:address":"505 N 7th St",
    "sg:city":"Saint Louis",
    "sg:classifiers":[
        {
            "category":"Professional",
            "subcategory":"Lawyer & Legal Services",
            "type":"Services"
        }
    ],
    "sg:phone":"+1 314 552 6057",
    "sg:postcode":"63101",
    "sg:province":"MO",
    "wof:name":"Goturi Milada R Atty",
    "wof:placetype":"venue"
},
  "geometry": {"coordinates":[-90.190625,38.630077],"type":"Point"}
}