{
  "type": "Feature",
  "properties": {
    "iso:country":"US",
    "sg:address":"7601 S 78th Ave",
    "sg:city":"Bridgeview",
    "sg:classifiers":[
        {
            "category":"Manufacturing",
            "subcategory":"Paper Products",
            "type":"Manufacturing & Wholesale Goods"
        }
    ],
    "sg:phone":"+1 708 458 8100",
    "sg:postcode":"60455",
    "sg:province":"IL",
    "sg:tags":[
        "box",
        "fiber",
        "metal",
        "mfg"
    ],
    "wof:name":"Smurfit Stone Container Corp",
    "wof:placetype":"venue"
},
  "geometry": {"coordinates":[-87.814425,41.751438],"type":"Point"}
}