{
  "type": "Feature",
  "properties": {
    "iso:country":"US",
    "sg:address":"562 Green Bay Rd",
    "sg:city":"Kenilworth",
    "sg:classifiers":[
        {
            "category":"Autos & Motor Vehicles",
            "subcategory":"Motorcycle Sales",
            "type":"Retail Goods"
        }
    ],
    "sg:phone":"+1   ",
    "sg:postcode":"60043",
    "sg:province":"IL",
    "wof:name":"R R B Cycles Ltd",
    "wof:placetype":"venue"
},
  "geometry": {"coordinates":[-87.719924,42.089261],"type":"Point"}
}