{
  "type": "Feature",
  "properties": {
    "addr:full":"14316 N 3100 E Rd Cullom IL 60929",
    "addr:housenumber":"14316;3100",
    "addr:postcode":"60929",
    "addr:street":"N;E Rd",
    "iso:country":"US",
    "sg:address":"14316 N 3100 E Rd",
    "sg:city":"Cullom",
    "sg:phone":"+1 815 689 2659",
    "sg:postcode":"60929",
    "sg:province":"IL",
    "sg:tags":[
        "farm",
        "corn",
        "soybean"
    ],
    "wof:name":"Haren Farms",
    "wof:placetype":"venue"
},
  "geometry": {"coordinates":[-88.33723500000001,40.847249],"type":"Point"}
}