{
  "type": "Feature",
  "properties": {
    "iso:country":"US",
    "sg:address":"115 N Main St",
    "sg:city":"Anna",
    "sg:classifiers":[
        {
            "category":"Real Estate",
            "subcategory":"Real Estate Services",
            "type":"Services"
        }
    ],
    "sg:phone":"+1 618 833 9797",
    "sg:postcode":"62906",
    "sg:province":"IL",
    "sg:tags":[
        "abstract",
        "title"
    ],
    "wof:name":"Anna-Jonesboro Title",
    "wof:placetype":"venue"
},
  "geometry": {"coordinates":[-89.24700300000001,37.460429],"type":"Point"}
}