{
  "type": "Feature",
  "properties": {
    "iso:country":"US",
    "sg:address":"1327 Casley Dr",
    "sg:city":"Hamilton",
    "sg:classifiers":[
        {
            "category":"Real Estate",
            "subcategory":"Real Estate Operator",
            "type":"Services"
        }
    ],
    "sg:phone":"+1 217 847 2251",
    "sg:postcode":"62341",
    "sg:province":"IL",
    "sg:tags":[
        "property",
        "lessor"
    ],
    "wof:name":"Esther McCartney",
    "wof:placetype":"venue"
},
  "geometry": {"coordinates":[-91.339983,40.397662],"type":"Point"}
}