{
  "type": "Feature",
  "properties": {
    "iso:country":"US",
    "sg:address":"633 Main St",
    "sg:city":"Peoria",
    "sg:classifiers":[
        {
            "category":"Restaurant",
            "type":"Food & Drink"
        }
    ],
    "sg:phone":"+1 309 676 7998",
    "sg:postcode":"61602",
    "sg:province":"IL",
    "sg:tags":[
        "house",
        "steak"
    ],
    "wof:name":"Anna's Steak House",
    "wof:placetype":"venue"
},
  "geometry": {"coordinates":[-89.593307,40.69537],"type":"Point"}
}