{
  "type": "Feature",
  "properties": {
    "addr:full":"473 W Wise Rd Schaumburg IL 60193",
    "addr:housenumber":"473",
    "addr:postcode":"60193",
    "addr:street":"W Wise Rd",
    "iso:country":"US",
    "sg:address":"473 W Wise Rd",
    "sg:city":"Schaumburg",
    "sg:classifiers":[
        {
            "category":"Personal",
            "subcategory":"Beauty Salon",
            "type":"Services"
        }
    ],
    "sg:phone":"+1 847 891 8133",
    "sg:postcode":"60193",
    "sg:province":"IL",
    "sg:tags":[
        "shop"
    ],
    "wof:name":"Perfect Impressions Inc",
    "wof:placetype":"venue"
},
  "geometry": {"coordinates":[-88.090518,42.004832],"type":"Point"}
}