{
  "type": "Feature",
  "properties": {
    "iso:country":"US",
    "sg:address":"1131 N Kenilworth Ave",
    "sg:city":"Oak Park",
    "sg:classifiers":[
        {
            "category":"Manufacturing",
            "subcategory":"Metals",
            "type":"Manufacturing & Wholesale Goods"
        }
    ],
    "sg:phone":"+1 708 383 8271",
    "sg:postcode":"60302",
    "sg:province":"IL",
    "sg:tags":[
        "plumbing",
        "fitting",
        "fixture",
        "mfg"
    ],
    "wof:name":"Kamco Representatives Inc",
    "wof:placetype":"venue"
},
  "geometry": {"coordinates":[-87.79825,41.906576],"type":"Point"}
}