{
  "type": "Feature",
  "properties": {
    "iso:country":"US",
    "sg:address":"4129 N Cicero Ave",
    "sg:city":"Chicago",
    "sg:classifiers":[
        {
            "category":"Building & Trades",
            "subcategory":"Electrical",
            "type":"Services"
        }
    ],
    "sg:phone":"+1 773 777 7454",
    "sg:postcode":"60641",
    "sg:province":"IL",
    "sg:tags":[
        "electrical",
        "contractor"
    ],
    "wof:name":"Bellmont Electric Company Inc",
    "wof:placetype":"venue"
},
  "geometry": {"coordinates":[-87.74730099999999,41.955836],"type":"Point"}
}