{
  "type": "Feature",
  "properties": {
    "addr:full":"10 E Chester St Champaign IL 61820",
    "addr:housenumber":"10",
    "addr:postcode":"61820",
    "addr:street":"E Chester St",
    "iso:country":"US",
    "sg:address":"10 E Chester St",
    "sg:city":"Champaign",
    "sg:classifiers":[
        {
            "category":"Real Estate",
            "subcategory":"Architect",
            "type":"Services"
        }
    ],
    "sg:phone":"+1 217 352 7696",
    "sg:postcode":"61820",
    "sg:province":"IL",
    "sg:website":"www.ratioarchitects.com",
    "wof:name":"Ratio Architects Inc",
    "wof:placetype":"venue"
},
  "geometry": {"coordinates":[-88.242171,40.116576],"type":"Point"}
}