{
  "type": "Feature",
  "properties": {
    "addr:full":"7020 West Cermak Rd Berwyn IL 60402",
    "addr:housenumber":"7020",
    "addr:postcode":"60402",
    "addr:street":"West Cermak Rd",
    "iso:country":"US",
    "sg:address":"7020 West Cermak Rd",
    "sg:city":"Berwyn",
    "sg:classifiers":[
        {
            "category":"Shopping",
            "subcategory":"Jewelry",
            "type":"Retail Goods"
        },
        {
            "category":"Manufacturing",
            "subcategory":"Jewelry",
            "type":"Manufacturing & Wholesale Goods"
        }
    ],
    "sg:phone":"+1 708 788 9200",
    "sg:postcode":"60402",
    "sg:province":"IL",
    "sg:tags":[
        "stone",
        "jewelers-wholesale",
        "watch",
        "jeweler",
        "precious",
        "semi-precious",
        "manufacturer"
    ],
    "sg:website":"www.jwjewelers.com",
    "wof:name":"James & Williams Jewelers",
    "wof:placetype":"venue"
},
  "geometry": {"coordinates":[-87.799407,41.850622],"type":"Point"}
}