{
  "type": "Feature",
  "properties": {
    "addr:full":"3011 Maine St Quincy IL 62301",
    "addr:housenumber":"3011",
    "addr:postcode":"62301",
    "addr:street":"Maine St",
    "iso:country":"US",
    "sg:address":"3011 Maine St",
    "sg:city":"Quincy",
    "sg:classifiers":[
        {
            "category":"Travel",
            "subcategory":"Travel Agent",
            "type":"Entertainment"
        }
    ],
    "sg:phone":"+1 217 222 0515",
    "sg:postcode":"62301",
    "sg:province":"IL",
    "sg:tags":[
        "agency"
    ],
    "wof:name":"Travel House of Quincy Inc",
    "wof:placetype":"venue"
},
  "geometry": {"coordinates":[-91.367704,39.931776],"type":"Point"}
}