{
  "type": "Feature",
  "properties": {
    "iso:country":"US",
    "sg:address":"917 Main St",
    "sg:city":"Highland",
    "sg:classifiers":[
        {
            "category":"Shopping",
            "subcategory":"Jewelry",
            "type":"Retail Goods"
        }
    ],
    "sg:phone":"+1 618 654 7464",
    "sg:postcode":"62249",
    "sg:province":"IL",
    "sg:tags":[
        "jeweler"
    ],
    "wof:name":"Becker Jewelers Inc",
    "wof:placetype":"venue"
},
  "geometry": {"coordinates":[-89.679228,38.740521],"type":"Point"}
}