{
  "type": "Feature",
  "properties": {
    "addr:full":"1926 N Halsted St Chicago IL 60614",
    "addr:housenumber":"1926",
    "addr:postcode":"60614",
    "addr:street":"N Halsted St",
    "iso:country":"US",
    "sg:address":"1926 N Halsted St",
    "sg:city":"Chicago",
    "sg:classifiers":[
        {
            "category":"Arts & Performance",
            "subcategory":"Art Gallery",
            "type":"Entertainment"
        }
    ],
    "sg:phone":"+1 773 929 2452",
    "sg:postcode":"60614",
    "sg:province":"IL",
    "sg:website":"www.saic.edu/webspaces/rogerbrow...",
    "wof:name":"Roger Brown Study Collection",
    "wof:placetype":"venue"
},
  "geometry": {"coordinates":[-87.648719,41.916822],"type":"Point"}
}