{
  "type": "Feature",
  "properties": {
    "iso:country":"US",
    "sg:address":"12427 Western Ave",
    "sg:city":"Blue Island",
    "sg:classifiers":[
        {
            "category":"Shopping",
            "subcategory":"Florist",
            "type":"Retail Goods"
        }
    ],
    "sg:phone":"+1 708 389 4401",
    "sg:postcode":"60406",
    "sg:province":"IL",
    "wof:name":"Pierres Flowers",
    "wof:placetype":"venue"
},
  "geometry": {"coordinates":[-87.68015699999999,41.667614],"type":"Point"}
}