{
  "type": "Feature",
  "properties": {
    "addr:full":"1284 N Milwaukee Ave Chicago IL 60622",
    "addr:housenumber":"1284",
    "addr:postcode":"60622",
    "addr:street":"N Milwaukee Ave",
    "iso:country":"US",
    "sg:address":"1284 N Milwaukee Ave",
    "sg:city":"Chicago",
    "sg:classifiers":[
        {
            "category":"Shopping",
            "subcategory":"Beauty & Cosmetics",
            "type":"Retail Goods"
        }
    ],
    "sg:phone":"+1 773 278 0332",
    "sg:postcode":"60622",
    "sg:province":"IL",
    "sg:tags":[
        "supply"
    ],
    "wof:name":"D & S Yo-Yo Milwaukee",
    "wof:placetype":"venue"
},
  "geometry": {"coordinates":[-87.668701,41.904701],"type":"Point"}
}