{
  "type": "Feature",
  "properties": {
    "iso:country":"US",
    "sg:address":"117 W 3rd St",
    "sg:city":"Alton",
    "sg:classifiers":[
        {
            "category":"Real Estate",
            "subcategory":"Real Estate Agent",
            "type":"Services"
        }
    ],
    "sg:phone":"+1 618 465 2966",
    "sg:postcode":"62002",
    "sg:province":"IL",
    "sg:website":"www.lauschkerealestate.com",
    "wof:name":"Paul R Lauschke & Assoc",
    "wof:placetype":"venue"
},
  "geometry": {"coordinates":[-90.187506,38.891119],"type":"Point"}
}