{
  "type": "Feature",
  "properties": {
    "iso:country":"US",
    "sg:address":"834 E 2nd St",
    "sg:city":"Gilman",
    "sg:classifiers":[
        {
            "category":"Manufacturing",
            "subcategory":"Buildings",
            "type":"Manufacturing & Wholesale Goods"
        },
        {
            "category":"Building & Trades",
            "subcategory":"Construction",
            "type":"Services"
        }
    ],
    "sg:phone":"+1 815 265 4322",
    "sg:postcode":"60938",
    "sg:province":"IL",
    "sg:tags":[
        "industrial",
        "excavation",
        "builder",
        "system",
        "specialty",
        "heating",
        "contractor",
        "contractors-commercial",
        "home",
        "air conditioning",
        "road"
    ],
    "wof:name":"Gray's Material Service",
    "wof:placetype":"venue"
},
  "geometry": {"coordinates":[-87.981746,40.768605],"type":"Point"}
}