{
  "type": "Feature",
  "properties": {
    "iso:country":"US",
    "sg:address":"823 N 2nd St",
    "sg:city":"Chillicothe",
    "sg:classifiers":[
        {
            "category":"Government",
            "subcategory":"Police Station",
            "type":"Public Place"
        }
    ],
    "sg:phone":"+1 309 274 2129",
    "sg:postcode":"61523",
    "sg:province":"IL",
    "sg:tags":[
        "department",
        "protection"
    ],
    "wof:name":"City Chillicothe Police Dept",
    "wof:placetype":"venue"
},
  "geometry": {"coordinates":[-89.485974,40.915923],"type":"Point"}
}