{
  "type": "Feature",
  "properties": {
    "iso:country":"US",
    "sg:address":"133 N Oak Park Ave",
    "sg:city":"Oak Park",
    "sg:classifiers":[
        {
            "category":"Food & Beverages",
            "subcategory":"Specialty",
            "type":"Retail Goods"
        }
    ],
    "sg:phone":"+1 708 848 4230",
    "sg:postcode":"60301",
    "sg:province":"IL",
    "sg:website":"www.oliveandwell.com",
    "wof:name":"Olive & Well, Inc.",
    "wof:placetype":"venue"
},
  "geometry": {"coordinates":[-87.794358,41.88822],"type":"Point"}
}