{
  "type": "Feature",
  "properties": {
    "iso:country":"US",
    "sg:address":"1440 Paddock Dr",
    "sg:city":"Northbrook",
    "sg:classifiers":[
        {
            "category":"Shopping",
            "subcategory":"Bicycles & Sporting Goods",
            "type":"Retail Goods"
        }
    ],
    "sg:phone":"+1 847 998 1000",
    "sg:postcode":"60062",
    "sg:province":"IL",
    "sg:tags":[
        "skating",
        "equipment",
        "supply"
    ],
    "sg:website":"http://www.rainbosports.com",
    "wof:name":"Rainbo Sports",
    "wof:placetype":"venue"
},
  "geometry": {"coordinates":[-87.81527199999999,42.104271],"type":"Point"}
}