{
  "type": "Feature",
  "properties": {
    "iso:country":"US",
    "sg:address":"8424 Skokie Blvd",
    "sg:city":"Skokie",
    "sg:classifiers":[
        {
            "category":"Social Services",
            "type":"Services"
        }
    ],
    "sg:phone":"+1 847 674 2020",
    "sg:postcode":"60077",
    "sg:province":"IL",
    "wof:name":"Physician Blling Solutions LLC",
    "wof:placetype":"venue"
},
  "geometry": {"coordinates":[-87.747295,42.033516],"type":"Point"}
}