{
  "type": "Feature",
  "properties": {
    "addr:full":"65 East Wacker Place Suite 600 Chicago IL 60601",
    "addr:housenumber":"65",
    "addr:postcode":"60601",
    "addr:street":"East Wacker Place Suite 600",
    "iso:country":"US",
    "sg:address":"65 East Wacker Place Suite 600",
    "sg:city":"Chicago",
    "sg:classifiers":[
        {
            "category":"Health Services",
            "subcategory":"Health Practitioner",
            "type":"Services"
        }
    ],
    "sg:phone":"+1 866 962 5689",
    "sg:postcode":"60601",
    "sg:province":"IL",
    "sg:tags":[
        "naturopathic/holistic"
    ],
    "sg:website":"www.bodylogicmd.com",
    "wof:name":"BodyLogicMD of Chicago",
    "wof:placetype":"venue"
},
  "geometry": {"coordinates":[-87.625604,41.886766],"type":"Point"}
}