{
  "type": "Feature",
  "properties": {
    "iso:country":"US",
    "sg:address":"105 E Vallette St",
    "sg:city":"Elmhurst",
    "sg:classifiers":[
        {
            "category":"Retail",
            "subcategory":"Photofinishing",
            "type":"Services"
        }
    ],
    "sg:phone":"+1 630 543 5891",
    "sg:postcode":"60126",
    "sg:province":"IL",
    "sg:tags":[
        "laboratory"
    ],
    "wof:name":"Iron Horse",
    "wof:placetype":"venue"
},
  "geometry": {"coordinates":[-87.938831,41.883648],"type":"Point"}
}