{
  "type": "Feature",
  "properties": {
    "iso:country":"US",
    "sg:address":"4925 W 95th St",
    "sg:city":"Oak Lawn",
    "sg:classifiers":[
        {
            "category":"Manufacturing",
            "subcategory":"Metals",
            "type":"Manufacturing & Wholesale Goods"
        }
    ],
    "sg:phone":"+1 708 425 2121",
    "sg:postcode":"60453",
    "sg:province":"IL",
    "sg:tags":[
        "product",
        "fabricated",
        "merchandise",
        "mfg"
    ],
    "wof:name":"All American Trophy King Inc",
    "wof:placetype":"venue"
},
  "geometry": {"coordinates":[-87.74407,41.719943],"type":"Point"}
}