{
  "type": "Feature",
  "properties": {
    "iso:country":"US",
    "sg:address":"3112 Ray Ave",
    "sg:city":"Alton",
    "sg:classifiers":[
        {
            "category":"Autos & Motor Vehicles",
            "subcategory":"Fuel & Gas Station",
            "type":"Retail Goods"
        }
    ],
    "sg:phone":"+1 618 463 0311",
    "sg:postcode":"62002",
    "sg:province":"IL",
    "sg:tags":[
        "oil"
    ],
    "wof:name":"Baker's Auto Repair",
    "wof:placetype":"venue"
},
  "geometry": {"coordinates":[-90.140158,38.908009],"type":"Point"}
}