{
  "type": "Feature",
  "properties": {
    "addr:full":"7058 S Washtenaw Avenue Chicago IL 60629",
    "addr:housenumber":"7058",
    "addr:postcode":"60629",
    "addr:street":"S Washtenaw Avenue",
    "iso:country":"US",
    "sg:address":"7058 S Washtenaw Avenue",
    "sg:city":"Chicago",
    "sg:classifiers":[
        {
            "category":"Education",
            "subcategory":"School",
            "type":"Public Place"
        }
    ],
    "sg:phone":"+1 773 535 9505",
    "sg:postcode":"60629",
    "sg:province":"IL",
    "sg:tags":[
        "high",
        "middle",
        "elementary"
    ],
    "wof:name":"Schools Public",
    "wof:placetype":"venue"
},
  "geometry": {"coordinates":[-87.69065999999999,41.765236],"type":"Point"}
}