{
  "type": "Feature",
  "properties": {
    "iso:country":"US",
    "sg:address":"124 N 9th St",
    "sg:city":"Rochelle",
    "sg:classifiers":[
        {
            "category":"Shopping",
            "subcategory":"Gifts & Souvenirs",
            "type":"Retail Goods"
        }
    ],
    "sg:phone":"+1 815 562 8107",
    "sg:postcode":"61068",
    "sg:province":"IL",
    "sg:tags":[
        "craft",
        "supply"
    ],
    "wof:name":"Rochelle Railroad Park",
    "wof:placetype":"venue"
},
  "geometry": {"coordinates":[-89.071116,41.920233],"type":"Point"}
}