{
  "type": "Feature",
  "properties": {
    "iso:country":"US",
    "sg:address":"75 S Stolp Ave",
    "sg:city":"Aurora",
    "sg:classifiers":[
        {
            "category":"Health Services",
            "subcategory":"Clinic",
            "type":"Services"
        }
    ],
    "sg:phone":"+1 630 892 9052",
    "sg:postcode":"60506",
    "sg:province":"IL",
    "sg:tags":[
        "home"
    ],
    "sg:website":"www.alphahomehealthcare.com",
    "wof:name":"Alpha Nursing Care",
    "wof:placetype":"venue"
},
  "geometry": {"coordinates":[-88.316712,41.757043],"type":"Point"}
}