{
  "type": "Feature",
  "properties": {
    "iso:country":"US",
    "sg:address":"22232 N Harmony Ln",
    "sg:city":"Texico",
    "sg:classifiers":[
        {
            "category":"Building & Trades",
            "subcategory":"Construction",
            "type":"Services"
        }
    ],
    "sg:phone":"+1 618 755 0049",
    "sg:postcode":"62889",
    "sg:province":"IL",
    "sg:tags":[
        "house"
    ],
    "wof:name":"Lusby Construction",
    "wof:placetype":"venue"
},
  "geometry": {"coordinates":[-88.792971,38.446228],"type":"Point"}
}