{
  "type": "Feature",
  "properties": {
    "iso:country":"US",
    "sg:address":"8409 S Stony Island Avenue",
    "sg:city":"Chicago",
    "sg:classifiers":[
        {
            "category":"Organizations",
            "subcategory":"Religious Organization",
            "type":"Services"
        }
    ],
    "sg:phone":"+1 773 721 5440",
    "sg:postcode":"60617",
    "sg:province":"IL",
    "wof:name":"God's House of All Nations",
    "wof:placetype":"venue"
},
  "geometry": {"coordinates":[-87.58510699999999,41.74207],"type":"Point"}
}