{
  "type": "Feature",
  "properties": {
    "iso:country":"US",
    "sg:address":"302 N Main St",
    "sg:city":"Toluca",
    "sg:classifiers":[
        {
            "category":"Restaurant",
            "type":"Food & Drink"
        }
    ],
    "sg:phone":"+1 815 452 2343",
    "sg:postcode":"61369",
    "sg:province":"IL",
    "sg:tags":[
        "style",
        "family",
        "italian"
    ],
    "wof:name":"Capponi's Restaurant",
    "wof:placetype":"venue"
},
  "geometry": {"coordinates":[-89.13400300000001,41.00395],"type":"Point"}
}