{
  "type": "Feature",
  "properties": {
    "iso:country":"US",
    "sg:address":"5100 Auburn St",
    "sg:city":"Rockford",
    "sg:classifiers":[
        {
            "category":"Organizations",
            "subcategory":"Non-profit Organization",
            "type":"Services"
        }
    ],
    "sg:phone":"+1 815 961 1152",
    "sg:postcode":"61101",
    "sg:province":"IL",
    "wof:name":"Rock River Valley Aviation",
    "wof:placetype":"venue"
},
  "geometry": {"coordinates":[-89.142277,42.288038],"type":"Point"}
}