{
  "type": "Feature",
  "properties": {
    "addr:full":"2628 N Sayre Ave Chicago IL 60707",
    "addr:housenumber":"2628",
    "addr:postcode":"60707",
    "addr:street":"N Sayre Ave",
    "iso:country":"US",
    "sg:address":"2628 N Sayre Ave",
    "sg:city":"Chicago",
    "sg:classifiers":[
        {
            "category":"Autos & Motor Vehicles",
            "subcategory":"Motorcycle Sales",
            "type":"Retail Goods"
        }
    ],
    "sg:phone":"+1 773 771 1875",
    "sg:postcode":"60707",
    "sg:province":"IL",
    "sg:tags":[
        "parts-wholesale",
        "scooters-supplies",
        "manufacturer"
    ],
    "wof:name":"Blue Steel Motorcycle Club, Chicago",
    "wof:placetype":"venue"
},
  "geometry": {"coordinates":[-87.800862,41.927698],"type":"Point"}
}