{
  "type": "Feature",
  "properties": {
    "addr:full":"504 East Pennsylvania Ave. Champaign IL 61820",
    "addr:housenumber":"504",
    "addr:postcode":"61820",
    "addr:street":"East Pennsylvania Ave.",
    "iso:country":"US",
    "sg:address":"504 East Pennsylvania Ave.",
    "sg:city":"Champaign",
    "sg:classifiers":[
        {
            "category":"Education",
            "subcategory":"University",
            "type":"Public Place"
        }
    ],
    "sg:phone":"+1 217 333 0931",
    "sg:postcode":"61820",
    "sg:province":"IL",
    "sg:tags":[
        "college"
    ],
    "sg:website":"www.law.uiuc.edu/",
    "wof:name":"University of Illinois College of Law",
    "wof:placetype":"venue"
},
  "geometry": {"coordinates":[-88.23226200000001,40.100517],"type":"Point"}
}