{
  "type": "Feature",
  "properties": {
    "iso:country":"US",
    "sg:address":"723 John St",
    "sg:city":"Joliet",
    "sg:classifiers":[
        {
            "category":"Building & Trades",
            "subcategory":"Cleaning & Sanitation",
            "type":"Services"
        }
    ],
    "sg:phone":"+1 815 723 8788",
    "sg:postcode":"60435",
    "sg:province":"IL",
    "sg:tags":[
        "maintenance"
    ],
    "wof:name":"Robert William Hurstik",
    "wof:placetype":"venue"
},
  "geometry": {"coordinates":[-88.100437,41.524269],"type":"Point"}
}