{
  "type": "Feature",
  "properties": {
    "addr:full":"2658 W Devon Ave Chicago IL 60659",
    "addr:housenumber":"2658",
    "addr:postcode":"60659",
    "addr:street":"W Devon Ave",
    "iso:country":"US",
    "sg:address":"2658 W Devon Ave",
    "sg:city":"Chicago",
    "sg:classifiers":[
        {
            "category":"Shopping",
            "subcategory":"Crafts & Fabrics",
            "type":"Retail Goods"
        }
    ],
    "sg:phone":"+1 773 338 9399",
    "sg:postcode":"60659",
    "sg:province":"IL",
    "sg:tags":[
        "shop",
        "material",
        "quilting",
        "supply"
    ],
    "wof:name":"Niketan",
    "wof:placetype":"venue"
},
  "geometry": {"coordinates":[-87.696466,41.997631],"type":"Point"}
}