{
  "type": "Feature",
  "properties": {
    "addr:full":"5452 S State St Chicago IL 60609",
    "addr:housenumber":"5452",
    "addr:postcode":"60609",
    "addr:street":"S State St",
    "iso:country":"US",
    "sg:address":"5452 S State St",
    "sg:city":"Chicago",
    "sg:classifiers":[
        {
            "category":"Place Of Worship",
            "subcategory":"Church",
            "type":"Public Place"
        }
    ],
    "sg:phone":"+1 773 924 5975",
    "sg:postcode":"60609",
    "sg:province":"IL",
    "wof:name":"New Philadelphia Church Baptist",
    "wof:placetype":"venue"
},
  "geometry": {"coordinates":[-87.625801,41.794899],"type":"Point"}
}