{
  "type": "Feature",
  "properties": {
    "iso:country":"US",
    "sg:address":"319 N 4th St Ste 400",
    "sg:city":"Saint Louis",
    "sg:classifiers":[
        {
            "category":"Professional",
            "subcategory":"Lawyer & Legal Services",
            "type":"Services"
        }
    ],
    "sg:phone":"+1 314 621 2005",
    "sg:postcode":"63102",
    "sg:province":"MO",
    "sg:tags":[
        "personal",
        "injury"
    ],
    "wof:name":"Weinstein Sheldon Atty",
    "wof:placetype":"venue"
},
  "geometry": {"coordinates":[-90.187401,38.628601],"type":"Point"}
}