{
  "type": "Feature",
  "properties": {
    "addr:full":"2406 Williamson County Pkwy Marion IL 62959",
    "addr:housenumber":"2406",
    "addr:postcode":"62959",
    "addr:street":"Williamson County Pkwy",
    "iso:country":"US",
    "sg:address":"2406 Williamson County Pkwy",
    "sg:city":"Marion",
    "sg:classifiers":[
        {
            "category":"Banks & Credit Unions",
            "subcategory":"Financial Services",
            "type":"Services"
        }
    ],
    "sg:phone":"+1 618 997 4542",
    "sg:postcode":"62959",
    "sg:province":"IL",
    "sg:tags":[
        "alternative",
        "loan",
        "payday"
    ],
    "sg:website":"http://www.cashstore.com/IL/Trademark/yp.com",
    "wof:name":"Cash Store",
    "wof:placetype":"venue"
},
  "geometry": {"coordinates":[-88.96937800000001,37.744132],"type":"Point"}
}