{
  "type": "Feature",
  "properties": {
    "iso:country":"US",
    "sg:address":"203 N Water St",
    "sg:city":"Wilmington",
    "sg:classifiers":[
        {
            "category":"Wholesale",
            "subcategory":"Vending Machines",
            "type":"Manufacturing & Wholesale Goods"
        }
    ],
    "sg:phone":"+1 815 476 7008",
    "sg:postcode":"60481",
    "sg:province":"IL",
    "sg:tags":[
        "operated",
        "phonograph"
    ],
    "sg:website":"www.camzretro.com",
    "wof:name":"CAMZRETRO.COM",
    "wof:placetype":"venue"
},
  "geometry": {"coordinates":[-88.147693,41.309517],"type":"Point"}
}