{
  "type": "Feature",
  "properties": {
    "iso:country":"US",
    "sg:address":"1409 W Stover St",
    "sg:city":"Freeport",
    "sg:classifiers":[
        {
            "category":"Building & Trades",
            "subcategory":"Construction",
            "type":"Services"
        }
    ],
    "sg:phone":"+1 815 235 3796",
    "sg:postcode":"61032",
    "sg:province":"IL",
    "sg:tags":[
        "residential"
    ],
    "wof:name":"Cannova Construction",
    "wof:placetype":"venue"
},
  "geometry": {"coordinates":[-89.646417,42.290435],"type":"Point"}
}