{
  "type": "Feature",
  "properties": {
    "iso:country":"US",
    "sg:address":"3140 W 111th St",
    "sg:city":"Chicago",
    "sg:classifiers":[
        {
            "category":"Government",
            "subcategory":"Fire Station",
            "type":"Public Place"
        }
    ],
    "sg:phone":"+1 312 747 5020",
    "sg:postcode":"60655",
    "sg:province":"IL",
    "sg:tags":[
        "consultant",
        "protection"
    ],
    "wof:name":"Chiocago Fire Department",
    "wof:placetype":"venue"
},
  "geometry": {"coordinates":[-87.69903600000001,41.691579],"type":"Point"}
}