{
  "type": "Feature",
  "properties": {
    "iso:country":"US",
    "sg:address":"733 W Blackhawk Dr",
    "sg:city":"Byron",
    "sg:classifiers":[
        {
            "category":"Restaurant",
            "type":"Food & Drink"
        }
    ],
    "sg:menulink":"http://www.allmenus.com/il/byron/226189-caseys-general-store/menu/",
    "sg:phone":"+1 815 234 4260",
    "sg:postcode":"61010",
    "sg:province":"IL",
    "sg:tags":[
        "american",
        "pizza"
    ],
    "wof:name":"Casey's General Store",
    "wof:placetype":"venue"
},
  "geometry": {"coordinates":[-89.26517699999999,42.125223],"type":"Point"}
}