{
  "type": "Feature",
  "properties": {
    "addr:full":"850 W Exchange Ave Chicago IL 60609",
    "addr:housenumber":"850",
    "addr:postcode":"60609",
    "addr:street":"W Exchange Ave",
    "iso:country":"US",
    "sg:address":"850 W Exchange Ave",
    "sg:city":"Chicago",
    "sg:classifiers":[
        {
            "category":"Landmark",
            "subcategory":"Historic",
            "type":"Public Place"
        },
        {
            "category":"Restaurant",
            "type":"Food & Drink"
        }
    ],
    "sg:postcode":"60609",
    "sg:province":"IL",
    "sg:tags":[
        "building",
        "flavor",
        "local",
        "historical"
    ],
    "wof:name":"Union Stockyards",
    "wof:placetype":"venue"
},
  "geometry": {"coordinates":[-87.647278,41.818737],"type":"Point"}
}