{
  "type": "Feature",
  "properties": {
    "iso:country":"US",
    "sg:address":"4615 Valley View Rd",
    "sg:city":"Crystal Lake",
    "sg:classifiers":[
        {
            "category":"Building & Trades",
            "subcategory":"Construction",
            "type":"Services"
        }
    ],
    "sg:phone":"+1 815 477 1742",
    "sg:postcode":"60012",
    "sg:province":"IL",
    "sg:tags":[
        "concrete",
        "contractor"
    ],
    "wof:name":"Covers Concrete Contractors",
    "wof:placetype":"venue"
},
  "geometry": {"coordinates":[-88.257659,42.270123],"type":"Point"}
}