{
  "type": "Feature",
  "properties": {
    "addr:full":"831 Jefferson Dr Lindenhurst IL 60046",
    "addr:housenumber":"831",
    "addr:postcode":"60046",
    "addr:street":"Jefferson Dr",
    "iso:country":"US",
    "sg:address":"831 Jefferson Dr",
    "sg:city":"Lindenhurst",
    "sg:classifiers":[
        {
            "category":"Wholesale",
            "subcategory":"Toys & Hobbies",
            "type":"Manufacturing & Wholesale Goods"
        },
        {
            "category":"Arts & Performance",
            "subcategory":"Theater",
            "type":"Entertainment"
        }
    ],
    "sg:phone":"+1 847 356 9035",
    "sg:postcode":"60046",
    "sg:province":"IL",
    "sg:tags":[
        "theatrical",
        "puppet",
        "marionette"
    ],
    "wof:name":"Polkadot Puppeteers",
    "wof:placetype":"venue"
},
  "geometry": {"coordinates":[-88.02448200000001,42.436581],"type":"Point"}
}