{
  "type": "Feature",
  "properties": {
    "addr:full":"200 S Wyman St Rockford IL 61101",
    "addr:housenumber":"200",
    "addr:postcode":"61101",
    "addr:street":"S Wyman St",
    "iso:country":"US",
    "sg:address":"200 S Wyman St",
    "sg:city":"Rockford",
    "sg:classifiers":[
        {
            "category":"Government",
            "subcategory":"Office",
            "type":"Public Place"
        }
    ],
    "sg:phone":"+1 815 987 7292",
    "sg:postcode":"61101",
    "sg:province":"IL",
    "sg:tags":[
        "administrative",
        "state",
        "program",
        "resource"
    ],
    "wof:name":"Illinois Industrial Commission",
    "wof:placetype":"venue"
},
  "geometry": {"coordinates":[-89.095106,42.269211],"type":"Point"}
}