{
  "type": "Feature",
  "properties": {
    "iso:country":"US",
    "sg:address":"12 W Main St",
    "sg:city":"Casey",
    "sg:classifiers":[
        {
            "category":"Personal",
            "subcategory":"Barber",
            "type":"Services"
        }
    ],
    "sg:phone":"+1 217 932 4611",
    "sg:postcode":"62420",
    "sg:province":"IL",
    "sg:tags":[
        "shop"
    ],
    "wof:name":"James Barber Shop",
    "wof:placetype":"venue"
},
  "geometry": {"coordinates":[-87.992943,39.299316],"type":"Point"}
}