{
  "type": "Feature",
  "properties": {
    "addr:full":"3055 183rd St Homewood IL 60430",
    "addr:housenumber":"3055",
    "addr:postcode":"60430",
    "addr:street":"183Rd St",
    "iso:country":"US",
    "sg:address":"3055 183rd St",
    "sg:city":"Homewood",
    "sg:classifiers":[
        {
            "category":"Shopping",
            "subcategory":"Department Store",
            "type":"Retail Goods"
        }
    ],
    "sg:phone":"+1 708 798 9511",
    "sg:postcode":"60430",
    "sg:province":"IL",
    "sg:tags":[
        "shop"
    ],
    "sg:website":"www.biglots.com",
    "wof:name":"Big Lots",
    "wof:placetype":"venue"
},
  "geometry": {"coordinates":[-87.692938,41.557095],"type":"Point"}
}