{
  "type": "Feature",
  "properties": {
    "addr:full":"134 W Main St Elizabeth IL 61028",
    "addr:housenumber":"134",
    "addr:postcode":"61028",
    "addr:street":"W Main St",
    "iso:country":"US",
    "sg:address":"134 W Main St",
    "sg:city":"Elizabeth",
    "sg:classifiers":[
        {
            "category":"Shopping",
            "subcategory":"Gifts & Souvenirs",
            "type":"Retail Goods"
        }
    ],
    "sg:phone":"+1 815 858 3749",
    "sg:postcode":"61028",
    "sg:province":"IL",
    "sg:tags":[
        "shop"
    ],
    "wof:name":"Heart-N-Hand",
    "wof:placetype":"venue"
},
  "geometry": {"coordinates":[-90.225809,42.319327],"type":"Point"}
}