{
  "type": "Feature",
  "properties": {
    "addr:full":"1569 Barclay Blvd Buffalo Grove IL 60089",
    "addr:housenumber":"1569",
    "addr:postcode":"60089",
    "addr:street":"Barclay Blvd",
    "iso:country":"US",
    "sg:address":"1569 Barclay Blvd",
    "sg:city":"Buffalo Grove",
    "sg:classifiers":[
        {
            "category":"Shopping",
            "type":"Retail Goods"
        }
    ],
    "sg:phone":"+1   ",
    "sg:postcode":"60089",
    "sg:province":"IL",
    "sg:tags":[
        "wholesale",
        "product",
        "nutrition"
    ],
    "wof:name":"Okun Enterprises",
    "wof:placetype":"venue"
},
  "geometry": {"coordinates":[-87.935368,42.179994],"type":"Point"}
}