{
  "type": "Feature",
  "properties": {
    "iso:country":"US",
    "sg:address":"4 E Elm St",
    "sg:city":"Albion",
    "sg:classifiers":[
        {
            "category":"Wholesale",
            "subcategory":"Farm Supplies",
            "type":"Manufacturing & Wholesale Goods"
        }
    ],
    "sg:phone":"+1 618 445 2613",
    "sg:postcode":"62806",
    "sg:province":"IL",
    "wof:name":"Wabash Valley Service Co",
    "wof:placetype":"venue"
},
  "geometry": {"coordinates":[-88.05724,38.378538],"type":"Point"}
}