{
  "type": "Feature",
  "properties": {
    "addr:full":"140 N Hemlock Ave Wood Dale IL 60191",
    "addr:housenumber":"140",
    "addr:postcode":"60191",
    "addr:street":"N Hemlock Ave",
    "iso:country":"US",
    "sg:address":"140 N Hemlock Ave",
    "sg:city":"Wood Dale",
    "sg:classifiers":[
        {
            "category":"Health Services",
            "subcategory":"Doctor",
            "type":"Services"
        }
    ],
    "sg:phone":"+1 630 616 9907",
    "sg:postcode":"60191",
    "sg:province":"IL",
    "sg:tags":[
        "medical"
    ],
    "wof:name":"Moreno Javier A MD",
    "wof:placetype":"venue"
},
  "geometry": {"coordinates":[-87.967612,41.959251],"type":"Point"}
}