{
  "type": "Feature",
  "properties": {
    "iso:country":"US",
    "sg:address":"3024 W Chase Ave",
    "sg:city":"Chicago",
    "sg:classifiers":[
        {
            "category":"Professional",
            "subcategory":"Lawyer & Legal Services",
            "type":"Services"
        }
    ],
    "sg:phone":"+1 773 262 6866",
    "sg:postcode":"60645",
    "sg:province":"IL",
    "wof:name":"George T Donoghue III",
    "wof:placetype":"venue"
},
  "geometry": {"coordinates":[-87.70623,42.013813],"type":"Point"}
}