{
  "type": "Feature",
  "properties": {
    "addr:full":"204 N Springfield Ave Rockford IL 61101",
    "addr:housenumber":"204",
    "addr:postcode":"61101",
    "addr:street":"N Springfield Ave",
    "iso:country":"US",
    "sg:address":"204 N Springfield Ave",
    "sg:city":"Rockford",
    "sg:classifiers":[
        {
            "category":"Shopping",
            "subcategory":"Bicycles & Sporting Goods",
            "type":"Retail Goods"
        }
    ],
    "sg:phone":"+1   ",
    "sg:postcode":"61101",
    "sg:province":"IL",
    "wof:name":"Sportsmens Den",
    "wof:placetype":"venue"
},
  "geometry": {"coordinates":[-89.145343,42.27933],"type":"Point"}
}