{
  "type": "Feature",
  "properties": {
    "addr:full":"12520 S Wood St Riverdale IL 60827",
    "addr:housenumber":"12520",
    "addr:postcode":"60827",
    "addr:street":"S Wood St",
    "iso:country":"US",
    "sg:address":"12520 S Wood St",
    "sg:city":"Riverdale",
    "sg:classifiers":[
        {
            "category":"Building & Trades",
            "subcategory":"Plumbing",
            "type":"Services"
        }
    ],
    "sg:phone":"+1 708 489 2045",
    "sg:postcode":"60827",
    "sg:province":"IL",
    "sg:tags":[
        "contractor"
    ],
    "wof:name":"Allen Montgomery",
    "wof:placetype":"venue"
},
  "geometry": {"coordinates":[-87.665907,41.665222],"type":"Point"}
}