{
  "type": "Feature",
  "properties": {
    "iso:country":"US",
    "sg:address":"22013 S Schoolhouse Rd",
    "sg:city":"New Lenox",
    "sg:classifiers":[
        {
            "category":"Building & Trades",
            "subcategory":"Landscaping Services",
            "type":"Services"
        }
    ],
    "sg:phone":"+1 708 349 7891",
    "sg:postcode":"60451",
    "sg:province":"IL",
    "sg:tags":[
        "designer",
        "landscape"
    ],
    "sg:website":"www.dutchbarnlandscaping.com",
    "wof:name":"Dutch Barn Landscaping",
    "wof:placetype":"venue"
},
  "geometry": {"coordinates":[-87.926345,41.488151],"type":"Point"}
}