{
  "type": "Feature",
  "properties": {
    "iso:country":"US",
    "sg:address":"12601 S Springfield Ave",
    "sg:city":"Alsip",
    "sg:classifiers":[
        {
            "category":"Education",
            "subcategory":"Special Training",
            "type":"Public Place"
        }
    ],
    "sg:phone":"+1 708 385 1325",
    "sg:postcode":"60803",
    "sg:province":"IL",
    "sg:tags":[
        "distribution",
        "safety"
    ],
    "wof:name":"Ots",
    "wof:placetype":"venue"
},
  "geometry": {"coordinates":[-87.716251,41.66391],"type":"Point"}
}