{
  "type": "Feature",
  "properties": {
    "addr:full":"426 S Milwaukee Ave Libertyville IL 60048",
    "addr:housenumber":"426",
    "addr:postcode":"60048",
    "addr:street":"S Milwaukee Ave",
    "iso:country":"US",
    "sg:address":"426 S Milwaukee Ave",
    "sg:city":"Libertyville",
    "sg:classifiers":[
        {
            "category":"Professional",
            "subcategory":"Research",
            "type":"Services"
        }
    ],
    "sg:phone":"+1 847 362 8290",
    "sg:postcode":"60048",
    "sg:province":"IL",
    "sg:tags":[
        "market",
        "analysis"
    ],
    "sg:website":"www.cmtamt.com",
    "wof:name":"College Marketing Technologies",
    "wof:placetype":"venue"
},
  "geometry": {"coordinates":[-87.952348,42.278519],"type":"Point"}
}