{
  "type": "Feature",
  "properties": {
    "iso:country":"US",
    "sg:address":"3005 Kishwaukee St",
    "sg:city":"Rockford",
    "sg:classifiers":[
        {
            "category":"Wholesale",
            "subcategory":"Hardware",
            "type":"Manufacturing & Wholesale Goods"
        }
    ],
    "sg:phone":"+1 815 229 2970",
    "sg:postcode":"61109",
    "sg:province":"IL",
    "sg:tags":[
        "beverage",
        "dispensing"
    ],
    "sg:website":"www.posi-pour.com",
    "wof:name":"Magnuson Industries",
    "wof:placetype":"venue"
},
  "geometry": {"coordinates":[-89.087009,42.229455],"type":"Point"}
}