{
  "type": "Feature",
  "properties": {
    "iso:country":"US",
    "sg:address":"420 W Maple St",
    "sg:city":"New Lenox",
    "sg:classifiers":[
        {
            "category":"Restaurant",
            "type":"Food & Drink"
        }
    ],
    "sg:menulink":"http://www.allmenus.com/il/new-lenox/199049-kfc---kentucky-fried-chicken/menu/",
    "sg:phone":"+1 815 462 0464",
    "sg:postcode":"60451",
    "sg:province":"IL",
    "sg:tags":[
        "american",
        "chicken"
    ],
    "wof:name":"KFC - Kentucky Fried Chicken",
    "wof:placetype":"venue"
},
  "geometry": {"coordinates":[-87.979827,41.517041],"type":"Point"}
}