{
  "type": "Feature",
  "properties": {
    "addr:full":"220 W Northwest Hwy Barrington IL 60010",
    "addr:housenumber":"220",
    "addr:postcode":"60010",
    "addr:street":"W Northwest Hwy",
    "iso:country":"US",
    "sg:address":"220 W Northwest Hwy",
    "sg:city":"Barrington",
    "sg:classifiers":[
        {
            "category":"Autos & Motor Vehicles",
            "subcategory":"Automobile Sales",
            "type":"Retail Goods"
        }
    ],
    "sg:phone":"+1 847 381 0250",
    "sg:postcode":"60010",
    "sg:province":"IL",
    "sg:tags":[
        "new",
        "repair"
    ],
    "wof:name":"Morrice & Heyse Motors Inc",
    "wof:placetype":"venue"
},
  "geometry": {"coordinates":[-88.139459,42.161549],"type":"Point"}
}