{
  "type": "Feature",
  "properties": {
    "addr:full":"517 Center St Cairo IL 62914",
    "addr:housenumber":"517",
    "addr:postcode":"62914",
    "addr:street":"Center St",
    "iso:country":"US",
    "sg:address":"517 Center St",
    "sg:city":"Cairo",
    "sg:classifiers":[
        {
            "category":"Organizations",
            "subcategory":"Labor Organization",
            "type":"Services"
        }
    ],
    "sg:phone":"+1 618 734 9506",
    "sg:postcode":"62914",
    "sg:province":"IL",
    "wof:name":"Laborers International Union",
    "wof:placetype":"venue"
},
  "geometry": {"coordinates":[-89.17730299999999,37.005362],"type":"Point"}
}