{
  "type": "Feature",
  "properties": {
    "iso:country":"US",
    "sg:address":"18062 Dixie Hwy",
    "sg:city":"Homewood",
    "sg:classifiers":[
        {
            "category":"Shopping",
            "subcategory":"Musical Instruments",
            "type":"Retail Goods"
        }
    ],
    "sg:phone":"+1 708 798 5500",
    "sg:postcode":"60430",
    "sg:province":"IL",
    "sg:tags":[
        "music",
        "sheet"
    ],
    "wof:name":"A Melody Mart Inc",
    "wof:placetype":"venue"
},
  "geometry": {"coordinates":[-87.66548,41.561001],"type":"Point"}
}