{
  "type": "Feature",
  "properties": {
    "addr:full":"105 E Wilson St Batavia IL 60510",
    "addr:housenumber":"105",
    "addr:postcode":"60510",
    "addr:street":"E Wilson St",
    "iso:country":"US",
    "sg:address":"105 E Wilson St",
    "sg:city":"Batavia",
    "sg:classifiers":[
        {
            "category":"Bars & Pubs",
            "type":"Food & Drink"
        }
    ],
    "sg:phone":"+1   ",
    "sg:postcode":"60510",
    "sg:province":"IL",
    "sg:tags":[
        "drinking"
    ],
    "wof:name":"Stop Lite Inn Inc",
    "wof:placetype":"venue"
},
  "geometry": {"coordinates":[-88.30487100000001,41.850095],"type":"Point"}
}