{
  "type": "Feature",
  "properties": {
    "iso:country":"US",
    "sg:address":"504 N Stanton St",
    "sg:city":"Davis",
    "sg:classifiers":[
        {
            "category":"Bars & Pubs",
            "type":"Food & Drink"
        }
    ],
    "sg:phone":"+1 815 865 5712",
    "sg:postcode":"61019",
    "sg:province":"IL",
    "wof:name":"Corner Tap",
    "wof:placetype":"venue"
},
  "geometry": {"coordinates":[-89.414025,42.423275],"type":"Point"}
}