{
  "type": "Feature",
  "properties": {
    "addr:full":"315 W 2nd St Rock Falls IL 61071",
    "addr:housenumber":"315",
    "addr:postcode":"61071",
    "addr:street":"W 2Nd St",
    "iso:country":"US",
    "sg:address":"315 W 2nd St",
    "sg:city":"Rock Falls",
    "sg:classifiers":[
        {
            "category":"Education",
            "subcategory":"Special Training",
            "type":"Public Place"
        }
    ],
    "sg:phone":"+1 815 622 4091",
    "sg:postcode":"61071",
    "sg:province":"IL",
    "sg:tags":[
        "instruct",
        "security",
        "firearm"
    ],
    "wof:name":"Illinois Axllary Spcial Police",
    "wof:placetype":"venue"
},
  "geometry": {"coordinates":[-89.693929,41.780908],"type":"Point"}
}