{
  "type": "Feature",
  "properties": {
    "addr:full":"7 Canna Dr Collinsville IL 62234",
    "addr:housenumber":"7",
    "addr:postcode":"62234",
    "addr:street":"Canna Dr",
    "iso:country":"US",
    "sg:address":"7 Canna Dr",
    "sg:city":"Collinsville",
    "sg:classifiers":[
        {
            "category":"Professional",
            "subcategory":"Accounting & Tax Preparation",
            "type":"Services"
        }
    ],
    "sg:phone":"+1 618 344 9248",
    "sg:postcode":"62234",
    "sg:province":"IL",
    "sg:tags":[
        "accountant"
    ],
    "wof:name":"Wilfong Stephen P CPA",
    "wof:placetype":"venue"
},
  "geometry": {"coordinates":[-90.013802,38.666698],"type":"Point"}
}