{
  "type": "Feature",
  "properties": {
    "iso:country":"US",
    "sg:address":"25W121 Argyle Ave",
    "sg:city":"Roselle",
    "sg:classifiers":[
        {
            "category":"Building & Trades",
            "subcategory":"Cleaning & Sanitation",
            "type":"Services"
        }
    ],
    "sg:phone":"+1 630 351 0169",
    "sg:postcode":"60172",
    "sg:province":"IL",
    "sg:tags":[
        "carpet"
    ],
    "wof:name":"Kathy's Professional Carpet & Upholstry Cleaning",
    "wof:placetype":"venue"
},
  "geometry": {"coordinates":[-88.115402,41.9641],"type":"Point"}
}