{
  "type": "Feature",
  "properties": {
    "iso:country":"US",
    "sg:address":"971 Harvest Cir",
    "sg:city":"Crystal Lake",
    "sg:classifiers":[
        {
            "category":"Shopping",
            "type":"Retail Goods"
        }
    ],
    "sg:phone":"+1   ",
    "sg:postcode":"60014",
    "sg:province":"IL",
    "sg:tags":[
        "merchandise"
    ],
    "wof:name":"Gillette",
    "wof:placetype":"venue"
},
  "geometry": {"coordinates":[-88.366175,42.214915],"type":"Point"}
}