{
  "type": "Feature",
  "properties": {
    "iso:country":"US",
    "sg:address":"3301 Logan Dr",
    "sg:city":"Herrin",
    "sg:classifiers":[
        {
            "category":"Health Services",
            "subcategory":"Doctor",
            "type":"Services"
        }
    ],
    "sg:phone":"+1 618 993 0444",
    "sg:postcode":"62948",
    "sg:province":"IL",
    "wof:name":"Neurology of Southern Illinois",
    "wof:placetype":"venue"
},
  "geometry": {"coordinates":[-89.028099,37.747299],"type":"Point"}
}