{
  "type": "Feature",
  "properties": {
    "iso:country":"US",
    "sg:address":"1417 W Schaumburg Rd",
    "sg:city":"Schaumburg",
    "sg:classifiers":[
        {
            "category":"Shopping",
            "subcategory":"Pets & Pet Supplies",
            "type":"Retail Goods"
        }
    ],
    "sg:phone":"+1 847 301 9600",
    "sg:postcode":"60194",
    "sg:province":"IL",
    "sg:tags":[
        "supplies-leasing",
        "store",
        "aquarium",
        "maintenance"
    ],
    "sg:website":"http://www.rainbowpetstore.com/",
    "wof:name":"Rainbow Pets",
    "wof:placetype":"venue"
},
  "geometry": {"coordinates":[-88.11525399999999,42.025985],"type":"Point"}
}