{
  "type": "Feature",
  "properties": {
    "addr:full":"22073 W Loon Dr Antioch IL 60002",
    "addr:housenumber":"22073",
    "addr:postcode":"60002",
    "addr:street":"W Loon Dr",
    "iso:country":"US",
    "sg:address":"22073 W Loon Dr",
    "sg:city":"Antioch",
    "sg:classifiers":[
        {
            "category":"Organizations",
            "subcategory":"Community Association",
            "type":"Services"
        }
    ],
    "sg:phone":"+1 847 395 0791",
    "sg:postcode":"60002",
    "sg:province":"IL",
    "wof:name":"East Loon Lk Shores Improvemnt",
    "wof:placetype":"venue"
},
  "geometry": {"coordinates":[-88.06390500000001,42.44892],"type":"Point"}
}