{
  "type": "Feature",
  "properties": {
    "addr:full":"6315 Pine St Loves Park IL 61111",
    "addr:housenumber":"6315",
    "addr:postcode":"61111",
    "addr:street":"Pine St",
    "iso:country":"US",
    "sg:address":"6315 Pine St",
    "sg:city":"Loves Park",
    "sg:classifiers":[
        {
            "category":"Building & Trades",
            "subcategory":"Plumbing",
            "type":"Services"
        }
    ],
    "sg:phone":"+1 815 633 6582",
    "sg:postcode":"61111",
    "sg:province":"IL",
    "sg:tags":[
        "air",
        "conditioning",
        "heating"
    ],
    "wof:name":"Professional Heating & AC",
    "wof:placetype":"venue"
},
  "geometry": {"coordinates":[-89.050636,42.323198],"type":"Point"}
}