{
  "type": "Feature",
  "properties": {
    "addr:full":"2910 Cottonwood Rd Eldorado IL 62930",
    "addr:housenumber":"2910",
    "addr:postcode":"62930",
    "addr:street":"Cottonwood Rd",
    "iso:country":"US",
    "sg:address":"2910 Cottonwood Rd",
    "sg:city":"Eldorado",
    "sg:classifiers":[
        {
            "category":"Shopping",
            "subcategory":"Bicycles & Sporting Goods",
            "type":"Retail Goods"
        }
    ],
    "sg:phone":"+1   ",
    "sg:postcode":"62930",
    "sg:province":"IL",
    "wof:name":"Portee Firearms Sales R",
    "wof:placetype":"venue"
},
  "geometry": {"coordinates":[-88.37417499999999,37.831022],"type":"Point"}
}