{
  "type": "Feature",
  "properties": {
    "addr:full":"1326 Niedringhaus Ave Granite City IL 62040",
    "addr:housenumber":"1326",
    "addr:postcode":"62040",
    "addr:street":"Niedringhaus Ave",
    "iso:country":"US",
    "sg:address":"1326 Niedringhaus Ave",
    "sg:city":"Granite City",
    "sg:classifiers":[
        {
            "category":"Professional",
            "subcategory":"Lawyer & Legal Services",
            "type":"Services"
        }
    ],
    "sg:phone":"+1 618 452 1323",
    "sg:postcode":"62040",
    "sg:province":"IL",
    "wof:name":"Papa John Atty",
    "wof:placetype":"venue"
},
  "geometry": {"coordinates":[-90.148499,38.701401],"type":"Point"}
}