{
  "type": "Feature",
  "properties": {
    "iso:country":"US",
    "sg:address":"118 W Main St",
    "sg:city":"Barrington",
    "sg:classifiers":[
        {
            "category":"Shopping",
            "subcategory":"Used Merchandise",
            "type":"Retail Goods"
        }
    ],
    "sg:phone":"+1 847 382 9988",
    "sg:postcode":"60010",
    "sg:province":"IL",
    "sg:tags":[
        "antique"
    ],
    "wof:name":"Kuwa Kollection",
    "wof:placetype":"venue"
},
  "geometry": {"coordinates":[-88.138381,42.154295],"type":"Point"}
}