{
  "type": "Feature",
  "properties": {
    "iso:country":"US",
    "sg:address":"8915 S Loomis St",
    "sg:city":"Chicago",
    "sg:classifiers":[
        {
            "category":"Real Estate",
            "subcategory":"Real Estate Operator",
            "type":"Services"
        }
    ],
    "sg:phone":"+1 773 429 1501",
    "sg:postcode":"60620",
    "sg:province":"IL",
    "sg:tags":[
        "apartment"
    ],
    "wof:name":"Brainerd Senior Center",
    "wof:placetype":"venue"
},
  "geometry": {"coordinates":[-87.658096,41.7318],"type":"Point"}
}