{
  "type": "Feature",
  "properties": {
    "iso:country":"US",
    "sg:address":"15551 S 71st Ct",
    "sg:city":"Orland Park",
    "sg:classifiers":[
        {
            "category":"Professional",
            "subcategory":"Business Services",
            "type":"Services"
        }
    ],
    "sg:phone":"+1 708 429 1770",
    "sg:postcode":"60462",
    "sg:province":"IL",
    "sg:tags":[
        "interior",
        "designer"
    ],
    "wof:name":"Van Kampen Janet Intr Design",
    "wof:placetype":"venue"
},
  "geometry": {"coordinates":[-87.79317899999999,41.607351],"type":"Point"}
}