{
  "type": "Feature",
  "properties": {
    "iso:country":"US",
    "sg:address":"2455 Wisconsin Ave",
    "sg:city":"Downers Grove",
    "sg:classifiers":[
        {
            "category":"Manufacturing",
            "subcategory":"Tools & Machinery",
            "type":"Manufacturing & Wholesale Goods"
        }
    ],
    "sg:phone":"+1 630 493 9860",
    "sg:postcode":"60515",
    "sg:province":"IL",
    "sg:tags":[
        "equipment",
        "material",
        "handling"
    ],
    "wof:name":"C F Clark Assoc",
    "wof:placetype":"venue"
},
  "geometry": {"coordinates":[-88.046852,41.789473],"type":"Point"}
}