{
  "type": "Feature",
  "properties": {
    "iso:country":"US",
    "sg:address":"300 W Briarcliff Rd",
    "sg:city":"Bolingbrook",
    "sg:classifiers":[
        {
            "category":"Education",
            "subcategory":"Library",
            "type":"Public Place"
        }
    ],
    "sg:phone":"+1 630 759 2102",
    "sg:postcode":"60440",
    "sg:province":"IL",
    "wof:name":"Fountaindale Public Lib Dst",
    "wof:placetype":"venue"
},
  "geometry": {"coordinates":[-88.079002,41.698309],"type":"Point"}
}