{
  "type": "Feature",
  "properties": {
    "iso:country":"US",
    "sg:address":"914 N Chicago St",
    "sg:city":"Geneseo",
    "sg:classifiers":[
        {
            "category":"Organizations",
            "subcategory":"Religious Organization",
            "type":"Services"
        }
    ],
    "sg:phone":"+1 309 944 4667",
    "sg:postcode":"61254",
    "sg:province":"IL",
    "sg:tags":[
        "church"
    ],
    "sg:website":"www.gefc.org",
    "wof:name":"Geneseo Evangelical Free Chr",
    "wof:placetype":"venue"
},
  "geometry": {"coordinates":[-90.143602,41.466478],"type":"Point"}
}