{
  "type": "Feature",
  "properties": {
    "addr:full":"6212 N Western Ave Chicago IL 60659",
    "addr:housenumber":"6212",
    "addr:postcode":"60659",
    "addr:street":"N Western Ave",
    "iso:country":"US",
    "sg:address":"6212 N Western Ave",
    "sg:city":"Chicago",
    "sg:classifiers":[
        {
            "category":"Professional",
            "subcategory":"Accounting & Tax Preparation",
            "type":"Services"
        },
        {
            "category":"Banks & Credit Unions",
            "subcategory":"Financial Services",
            "type":"Services"
        }
    ],
    "sg:phone":"+1 773 973 4288",
    "sg:postcode":"60659",
    "sg:province":"IL",
    "sg:tags":[
        "return",
        "preparation-business",
        "taxes-consultants",
        "loan",
        "reporting",
        "representative",
        "alternative",
        "bookkeeping"
    ],
    "sg:website":"http://www.hrblock.com",
    "wof:name":"H&R Block",
    "wof:placetype":"venue"
},
  "geometry": {"coordinates":[-87.68978199999999,41.994206],"type":"Point"}
}