{
  "type": "Feature",
  "properties": {
    "iso:country":"US",
    "sg:address":"4063 Hanover Rd",
    "sg:city":"Columbia",
    "sg:phone":"+1 618 939 8402",
    "sg:postcode":"62236",
    "sg:province":"IL",
    "sg:tags":[
        "farm",
        "corn",
        "soybean"
    ],
    "wof:name":"Chris Howell",
    "wof:placetype":"venue"
},
  "geometry": {"coordinates":[-90.166338,38.389388],"type":"Point"}
}