{
  "type": "Feature",
  "properties": {
    "addr:full":"100 S River St Aurora IL 60506",
    "addr:housenumber":"100",
    "addr:postcode":"60506",
    "addr:street":"S River St",
    "iso:country":"US",
    "sg:address":"100 S River St",
    "sg:city":"Aurora",
    "sg:classifiers":[
        {
            "category":"Retail",
            "subcategory":"Auto Rental",
            "type":"Services"
        }
    ],
    "sg:phone":"+1 630 264 3742",
    "sg:postcode":"60506",
    "sg:province":"IL",
    "sg:tags":[
        "renting",
        "truck",
        "leasing"
    ],
    "wof:name":"U-Haul Co",
    "wof:placetype":"venue"
},
  "geometry": {"coordinates":[-88.321612,41.755427],"type":"Point"}
}