{
  "type": "Feature",
  "properties": {
    "addr:full":"9230 S Pulaski Rd Oak Lawn IL 60453",
    "addr:housenumber":"9230",
    "addr:postcode":"60453",
    "addr:street":"S Pulaski Rd",
    "iso:country":"US",
    "sg:address":"9230 S Pulaski Rd",
    "sg:city":"Oak Lawn",
    "sg:classifiers":[
        {
            "category":"Organizations",
            "subcategory":"Religious Organization",
            "type":"Services"
        }
    ],
    "sg:phone":"+1 708 422 5111",
    "sg:postcode":"60453",
    "sg:province":"IL",
    "wof:name":"Trinity Evang Covenant Church",
    "wof:placetype":"venue"
},
  "geometry": {"coordinates":[-87.721603,41.7247],"type":"Point"}
}