{
  "type": "Feature",
  "properties": {
    "iso:country":"US",
    "sg:address":"269 S Alma Ave",
    "sg:city":"Kankakee",
    "sg:classifiers":[
        {
            "category":"Organizations",
            "subcategory":"Religious Organization",
            "type":"Services"
        }
    ],
    "sg:phone":"+1 815 933 0096",
    "sg:postcode":"60901",
    "sg:province":"IL",
    "sg:tags":[
        "church"
    ],
    "wof:name":"Christian Assembly In Kankakee",
    "wof:placetype":"venue"
},
  "geometry": {"coordinates":[-87.88306799999999,41.119597],"type":"Point"}
}