{
  "type": "Feature",
  "properties": {
    "iso:country":"US",
    "sg:address":"3630 S Lowe Ave",
    "sg:city":"Chicago",
    "sg:classifiers":[
        {
            "category":"Shopping",
            "type":"Retail Goods"
        }
    ],
    "sg:phone":"+1 773 523 1141",
    "sg:postcode":"60609",
    "sg:province":"IL",
    "sg:tags":[
        "merchandise"
    ],
    "wof:name":"Candy Store",
    "wof:placetype":"venue"
},
  "geometry": {"coordinates":[-87.642386,41.828414],"type":"Point"}
}