{
  "type": "Feature",
  "properties": {
    "iso:country":"US",
    "sg:address":"214 S Grand Ave W",
    "sg:city":"Springfield",
    "sg:classifiers":[
        {
            "category":"Real Estate",
            "subcategory":"Real Estate Services",
            "type":"Services"
        },
        {
            "category":"Real Estate",
            "subcategory":"Real Estate Agent",
            "type":"Services"
        }
    ],
    "sg:phone":"+1 217 528 4305",
    "sg:postcode":"62704",
    "sg:province":"IL",
    "sg:tags":[
        "management"
    ],
    "wof:name":"Reavy Real Estate",
    "wof:placetype":"venue"
},
  "geometry": {"coordinates":[-89.656346,39.787018],"type":"Point"}
}