{
  "type": "Feature",
  "properties": {
    "addr:full":"200 Old Chicago Dr Bolingbrook IL 60440",
    "addr:housenumber":"200",
    "addr:postcode":"60440",
    "addr:street":"Old Chicago Dr",
    "iso:country":"US",
    "sg:address":"200 Old Chicago Dr",
    "sg:city":"Bolingbrook",
    "sg:classifiers":[
        {
            "category":"Freight",
            "type":"Transportation"
        }
    ],
    "sg:phone":"+1 630 378 0858",
    "sg:postcode":"60440",
    "sg:province":"IL",
    "sg:tags":[
        "appraisal",
        "surveying"
    ],
    "wof:name":"I T S",
    "wof:placetype":"venue"
},
  "geometry": {"coordinates":[-88.071755,41.680384],"type":"Point"}
}