{
  "type": "Feature",
  "properties": {
    "addr:full":"7 E Park Blvd Villa Park IL 60181",
    "addr:housenumber":"7",
    "addr:postcode":"60181",
    "addr:street":"E Park Blvd",
    "iso:country":"US",
    "sg:address":"7 E Park Blvd",
    "sg:city":"Villa Park",
    "sg:classifiers":[
        {
            "category":"Shopping",
            "subcategory":"Used Merchandise",
            "type":"Retail Goods"
        }
    ],
    "sg:phone":"+1 630 832 9060",
    "sg:postcode":"60181",
    "sg:province":"IL",
    "sg:tags":[
        "antique"
    ],
    "sg:website":"www.dochensleys.com",
    "wof:name":"Doc Hensley's Antique Furn",
    "wof:placetype":"venue"
},
  "geometry": {"coordinates":[-87.97763999999999,41.883568],"type":"Point"}
}