{
  "type": "Feature",
  "properties": {
    "addr:full":"3539 Dempster St Skokie IL 60076",
    "addr:housenumber":"3539",
    "addr:postcode":"60076",
    "addr:street":"Dempster St",
    "iso:country":"US",
    "sg:address":"3539 Dempster St",
    "sg:city":"Skokie",
    "sg:classifiers":[
        {
            "category":"Personal",
            "subcategory":"Beauty Salon",
            "type":"Services"
        }
    ],
    "sg:phone":"+1 847 677 8889",
    "sg:postcode":"60076",
    "sg:province":"IL",
    "sg:tags":[
        "hair",
        "shop",
        "stylist"
    ],
    "sg:website":"http://www.supercuts.com/",
    "wof:name":"Supercuts",
    "wof:placetype":"venue"
},
  "geometry": {"coordinates":[-87.717016,42.040868],"type":"Point"}
}