{
  "type": "Feature",
  "properties": {
    "iso:country":"US",
    "sg:address":"8804 Summer Rd",
    "sg:city":"Columbia",
    "sg:classifiers":[
        {
            "category":"Building & Trades",
            "subcategory":"Plumbing",
            "type":"Services"
        }
    ],
    "sg:phone":"+1 618 939 9960",
    "sg:postcode":"62236",
    "sg:province":"IL",
    "sg:tags":[
        "plumbing",
        "contractor"
    ],
    "wof:name":"Cregger Co",
    "wof:placetype":"venue"
},
  "geometry": {"coordinates":[-90.16391,38.385889],"type":"Point"}
}