{
  "type": "Feature",
  "properties": {
    "iso:country":"US",
    "sg:address":"1625 E Riverside Blvd",
    "sg:city":"Rockford",
    "sg:classifiers":[
        {
            "category":"Freight",
            "type":"Transportation"
        }
    ],
    "sg:phone":"+1 815 986 2030",
    "sg:postcode":"61114",
    "sg:province":"IL",
    "wof:name":"All Pro Logistics LLC",
    "wof:placetype":"venue"
},
  "geometry": {"coordinates":[-89.03121,42.318132],"type":"Point"}
}