{
  "type": "Feature",
  "properties": {
    "iso:country":"US",
    "sg:address":"1491 W Roosevelt Road",
    "sg:city":"Chicago",
    "sg:classifiers":[
        {
            "category":"Autos & Motor Vehicles",
            "subcategory":"Fuel & Gas Station",
            "type":"Retail Goods"
        }
    ],
    "sg:phone":"+1 630 562 4618",
    "sg:postcode":"60608",
    "sg:province":"IL",
    "wof:name":"West Chicago Subway",
    "wof:placetype":"venue"
},
  "geometry": {"coordinates":[-87.66380100000001,41.866714],"type":"Point"}
}