{
  "type": "Feature",
  "properties": {
    "addr:full":"216 N 2nd St Peotone IL 60468",
    "addr:housenumber":"216",
    "addr:postcode":"60468",
    "addr:street":"N 2Nd St",
    "iso:country":"US",
    "sg:address":"216 N 2nd St",
    "sg:city":"Peotone",
    "sg:classifiers":[
        {
            "category":"Organizations",
            "subcategory":"Religious Organization",
            "type":"Services"
        }
    ],
    "sg:phone":"+1 708 258 3600",
    "sg:postcode":"60468",
    "sg:province":"IL",
    "sg:tags":[
        "church"
    ],
    "wof:name":"Christ Community Church",
    "wof:placetype":"venue"
},
  "geometry": {"coordinates":[-87.790918,41.335309],"type":"Point"}
}