{
  "type": "Feature",
  "properties": {
    "addr:full":"1212 S 23rd St Quincy IL 62301",
    "addr:housenumber":"1212",
    "addr:postcode":"62301",
    "addr:street":"S 23Rd St",
    "iso:country":"US",
    "sg:address":"1212 S 23rd St",
    "sg:city":"Quincy",
    "sg:classifiers":[
        {
            "category":"Building & Trades",
            "subcategory":"Construction",
            "type":"Services"
        }
    ],
    "sg:phone":"+1 217 228 1665",
    "sg:postcode":"62301",
    "sg:province":"IL",
    "sg:tags":[
        "general",
        "contractor"
    ],
    "wof:name":"Bainter Construction",
    "wof:placetype":"venue"
},
  "geometry": {"coordinates":[-91.379304,39.916831],"type":"Point"}
}