{
  "type": "Feature",
  "properties": {
    "iso:country":"US",
    "sg:address":"1352 S Milwaukee Ave",
    "sg:city":"Libertyville",
    "sg:classifiers":[
        {
            "category":"Shopping",
            "subcategory":"Books",
            "type":"Retail Goods"
        }
    ],
    "sg:phone":"+1   ",
    "sg:postcode":"60048",
    "sg:province":"IL",
    "sg:tags":[
        "educational",
        "toy"
    ],
    "wof:name":"Creative Fun Inc",
    "wof:placetype":"venue"
},
  "geometry": {"coordinates":[-87.948186,42.25977],"type":"Point"}
}