{
  "type": "Feature",
  "properties": {
    "iso:country":"US",
    "sg:address":"1966 N Henderson St",
    "sg:city":"Galesburg",
    "sg:classifiers":[
        {
            "category":"Restaurant",
            "type":"Food & Drink"
        }
    ],
    "sg:menulink":"http://www.allmenus.com/il/galesburg-city/88542-applebees/menu/",
    "sg:phone":"+1 309 344 7325",
    "sg:postcode":"61401",
    "sg:province":"IL",
    "sg:tags":[
        "burger",
        "american",
        "sandwich",
        "soup"
    ],
    "wof:name":"Applebee's",
    "wof:placetype":"venue"
},
  "geometry": {"coordinates":[-90.38314200000001,40.971584],"type":"Point"}
}