{
  "type": "Feature",
  "properties": {
    "addr:full":"828 Davis St Evanston IL 60201",
    "addr:housenumber":"828",
    "addr:postcode":"60201",
    "addr:street":"Davis St",
    "iso:country":"US",
    "sg:address":"828 Davis St",
    "sg:city":"Evanston",
    "sg:classifiers":[
        {
            "category":"Professional",
            "subcategory":"Computer Services",
            "type":"Services"
        }
    ],
    "sg:phone":"+1 847 864 7007",
    "sg:postcode":"60201",
    "sg:province":"IL",
    "sg:tags":[
        "software",
        "developer"
    ],
    "wof:name":"Infood Corporation",
    "wof:placetype":"venue"
},
  "geometry": {"coordinates":[-87.682475,42.046887],"type":"Point"}
}