{
  "type": "Feature",
  "properties": {
    "iso:country":"US",
    "sg:address":"2605 Stevenson Dr",
    "sg:city":"Springfield",
    "sg:classifiers":[
        {
            "category":"Restaurant",
            "type":"Food & Drink"
        }
    ],
    "sg:menulink":"http://www.allmenus.com/il/capital/83894-papa-johns-pizza/menu/",
    "sg:phone":"+1 217 529 7262",
    "sg:postcode":"62703",
    "sg:province":"IL",
    "sg:tags":[
        "american",
        "pizza"
    ],
    "wof:name":"Papa John's Pizza",
    "wof:placetype":"venue"
},
  "geometry": {"coordinates":[-89.61843,39.757989],"type":"Point"}
}