{
  "type": "Feature",
  "properties": {
    "addr:full":"106 N Main St Edwardsville IL 62025",
    "addr:housenumber":"106",
    "addr:postcode":"62025",
    "addr:street":"N Main St",
    "iso:country":"US",
    "sg:address":"106 N Main St",
    "sg:city":"Edwardsville",
    "sg:phone":"+1 618 656 9001",
    "sg:postcode":"62025",
    "sg:province":"IL",
    "sg:website":"http://www.fondfinedining.com/",
    "wof:name":"Fond - Illinois",
    "wof:placetype":"venue"
},
  "geometry": {"coordinates":[-89.955799,38.811372],"type":"Point"}
}