{
  "type": "Feature",
  "properties": {
    "addr:full":"3936 N Pulaski Road Chicago IL 60641",
    "addr:housenumber":"3936",
    "addr:postcode":"60641",
    "addr:street":"N Pulaski Road",
    "iso:country":"US",
    "sg:address":"3936 N Pulaski Road",
    "sg:city":"Chicago",
    "sg:classifiers":[
        {
            "category":"Shopping",
            "subcategory":"Mobile Phones",
            "type":"Retail Goods"
        }
    ],
    "sg:phone":"+1 773 427 8886",
    "sg:postcode":"60641",
    "sg:province":"IL",
    "wof:name":"International Business Platform",
    "wof:placetype":"venue"
},
  "geometry": {"coordinates":[-87.727311,41.953255],"type":"Point"}
}