{
  "type": "Feature",
  "properties": {
    "iso:country":"US",
    "sg:address":"15538 Cicero Ave",
    "sg:city":"Oak Forest",
    "sg:classifiers":[
        {
            "category":"Building & Trades",
            "subcategory":"Construction",
            "type":"Services"
        }
    ],
    "sg:phone":"+1 708 687 1664",
    "sg:postcode":"60452",
    "sg:province":"IL",
    "sg:tags":[
        "roofing",
        "contractor"
    ],
    "wof:name":"Anthony's Paving",
    "wof:placetype":"venue"
},
  "geometry": {"coordinates":[-87.736792,41.60945],"type":"Point"}
}