{
  "type": "Feature",
  "properties": {
    "iso:country":"US",
    "sg:address":"1035 E Main St",
    "sg:city":"Danville",
    "sg:classifiers":[
        {
            "category":"Banks & Credit Unions",
            "subcategory":"Bank",
            "type":"Services"
        }
    ],
    "sg:phone":"+1 217 477 4428",
    "sg:postcode":"61832",
    "sg:province":"IL",
    "wof:name":"Tee Pak Credit Union",
    "wof:placetype":"venue"
},
  "geometry": {"coordinates":[-87.60704,40.12822],"type":"Point"}
}