{
  "type": "Feature",
  "properties": {
    "iso:country":"US",
    "sg:address":"1700 Hill St",
    "sg:city":"Alton",
    "sg:classifiers":[
        {
            "category":"Building & Trades",
            "subcategory":"Construction",
            "type":"Services"
        }
    ],
    "sg:phone":"+1 618 462 4922",
    "sg:postcode":"62002",
    "sg:province":"IL",
    "sg:tags":[
        "product",
        "asphalt"
    ],
    "wof:name":"Jack & Sons Asphalt Paving",
    "wof:placetype":"venue"
},
  "geometry": {"coordinates":[-90.197231,38.902273],"type":"Point"}
}