{
  "type": "Feature",
  "properties": {
    "addr:full":"200 W 2nd St Rock Falls IL 61071",
    "addr:housenumber":"200",
    "addr:postcode":"61071",
    "addr:street":"W 2Nd St",
    "iso:country":"US",
    "sg:address":"200 W 2nd St",
    "sg:city":"Rock Falls",
    "sg:classifiers":[
        {
            "category":"Manufacturing",
            "subcategory":"Metals",
            "type":"Manufacturing & Wholesale Goods"
        }
    ],
    "sg:phone":"+1 815 625 8000",
    "sg:postcode":"61071",
    "sg:province":"IL",
    "sg:tags":[
        "die",
        "nonferrous",
        "casting",
        "alum"
    ],
    "sg:website":"www.microdiecast.com",
    "wof:name":"Micro Industries Inc",
    "wof:placetype":"venue"
},
  "geometry": {"coordinates":[-89.692712,41.781639],"type":"Point"}
}