{
  "type": "Feature",
  "properties": {
    "addr:full":"2024 S River Rd Des Plaines IL 60018",
    "addr:housenumber":"2024",
    "addr:postcode":"60018",
    "addr:street":"S River Rd Des",
    "iso:country":"US",
    "sg:address":"2024 S River Rd",
    "sg:city":"Des Plaines",
    "sg:classifiers":[
        {
            "category":"Retail",
            "subcategory":"Veterinary Services",
            "type":"Services"
        }
    ],
    "sg:phone":"+1 847 296 3112",
    "sg:postcode":"60018",
    "sg:province":"IL",
    "sg:tags":[
        "hospital",
        "animal"
    ],
    "wof:name":"Rudawsky George",
    "wof:placetype":"venue"
},
  "geometry": {"coordinates":[-87.87372000000001,42.016437],"type":"Point"}
}