{
  "type": "Feature",
  "properties": {
    "addr:full":"3340 Mall Loop Dr Joliet IL 60431",
    "addr:housenumber":"3340",
    "addr:postcode":"60431",
    "addr:street":"Mall Loop Dr",
    "iso:country":"US",
    "sg:address":"3340 Mall Loop Dr",
    "sg:city":"Joliet",
    "sg:classifiers":[
        {
            "category":"Restaurant",
            "type":"Food & Drink"
        }
    ],
    "sg:menulink":"http://www.allmenus.com/il/plainfield/196252-taco-bell/menu/",
    "sg:postcode":"60431",
    "sg:province":"IL",
    "sg:tags":[
        "mexican"
    ],
    "wof:name":"Taco Bell",
    "wof:placetype":"venue"
},
  "geometry": {"coordinates":[-88.165058,41.57939],"type":"Point"}
}