{
  "type": "Feature",
  "properties": {
    "iso:country":"US",
    "sg:address":"3202 Orchard Ln",
    "sg:city":"Carbon Cliff",
    "sg:classifiers":[
        {
            "category":"Professional",
            "type":"Services"
        }
    ],
    "sg:phone":"+1 309 755 4634",
    "sg:postcode":"61239",
    "sg:province":"IL",
    "sg:tags":[
        "establishment"
    ],
    "wof:name":"Daris Michaels",
    "wof:placetype":"venue"
},
  "geometry": {"coordinates":[-90.401385,41.483474],"type":"Point"}
}