{
  "type": "Feature",
  "properties": {
    "addr:full":"6172 US Hwy 20 Belvidere IL 61008",
    "addr:housenumber":"6172",
    "addr:postcode":"61008",
    "addr:street":"Us Hwy 20",
    "iso:country":"US",
    "sg:address":"6172 US Hwy 20",
    "sg:city":"Belvidere",
    "sg:classifiers":[
        {
            "category":"Freight",
            "type":"Transportation"
        }
    ],
    "sg:phone":"+1 815 544 4404",
    "sg:postcode":"61008",
    "sg:province":"IL",
    "sg:tags":[
        "trucking"
    ],
    "wof:name":"Freightways Inc",
    "wof:placetype":"venue"
},
  "geometry": {"coordinates":[-88.78521600000001,42.245298],"type":"Point"}
}