{
  "type": "Feature",
  "properties": {
    "addr:full":"6209 S Archer Rd Summit Argo IL 60501",
    "addr:housenumber":"6209",
    "addr:postcode":"60501",
    "addr:street":"S Archer Rd",
    "iso:country":"US",
    "sg:address":"6209 S Archer Rd",
    "sg:city":"Summit Argo",
    "sg:classifiers":[
        {
            "category":"Education",
            "subcategory":"Library",
            "type":"Public Place"
        }
    ],
    "sg:phone":"+1 708 458 1545",
    "sg:postcode":"60501",
    "sg:province":"IL",
    "wof:name":"Summit Public Library",
    "wof:placetype":"venue"
},
  "geometry": {"coordinates":[-87.813475,41.778147],"type":"Point"}
}