{
  "type": "Feature",
  "properties": {
    "iso:country":"US",
    "sg:address":"4401 N Belt W",
    "sg:city":"Belleville",
    "sg:classifiers":[
        {
            "category":"Manufacturing",
            "subcategory":"Tools & Machinery",
            "type":"Manufacturing & Wholesale Goods"
        }
    ],
    "sg:phone":"+1 618 257 7100",
    "sg:postcode":"62226",
    "sg:province":"IL",
    "sg:tags":[
        "manufacture",
        "recording",
        "product",
        "digital"
    ],
    "wof:name":"RTS Sentry",
    "wof:placetype":"venue"
},
  "geometry": {"coordinates":[-90.021019,38.541602],"type":"Point"}
}