{
  "type": "Feature",
  "properties": {
    "addr:full":"7005 North Ave Oak Park IL 60302",
    "addr:housenumber":"7005",
    "addr:postcode":"60302",
    "addr:street":"North Ave",
    "iso:country":"US",
    "sg:address":"7005 North Ave",
    "sg:city":"Oak Park",
    "sg:classifiers":[
        {
            "category":"Health Services",
            "subcategory":"Doctor",
            "type":"Services"
        },
        {
            "category":"Community Center",
            "type":"Public Place"
        }
    ],
    "sg:phone":"+1 708 383 8888",
    "sg:postcode":"60302",
    "sg:province":"IL",
    "sg:tags":[
        "medical"
    ],
    "wof:name":"Hung Sam MD",
    "wof:placetype":"venue"
},
  "geometry": {"coordinates":[-87.80135300000001,41.908771],"type":"Point"}
}