{
  "type": "Feature",
  "properties": {
    "iso:country":"US",
    "sg:address":"5050 W 127th St",
    "sg:city":"Alsip",
    "sg:classifiers":[
        {
            "category":"Retail",
            "subcategory":"Car Wash",
            "type":"Services"
        }
    ],
    "sg:phone":"+1 708 396 8777",
    "sg:postcode":"60803",
    "sg:province":"IL",
    "wof:name":"Delicate Touch Hand Car Wash",
    "wof:placetype":"venue"
},
  "geometry": {"coordinates":[-87.7444,41.661701],"type":"Point"}
}