{
  "type": "Feature",
  "properties": {
    "iso:country":"US",
    "sg:address":"3308 Veterans Dr",
    "sg:city":"Pekin",
    "sg:classifiers":[
        {
            "category":"Wholesale",
            "subcategory":"Apparel",
            "type":"Manufacturing & Wholesale Goods"
        },
        {
            "category":"Shopping",
            "subcategory":"Shoes",
            "type":"Retail Goods"
        }
    ],
    "sg:phone":"+1 309 346 0542",
    "sg:postcode":"61554",
    "sg:province":"IL",
    "sg:tags":[
        "shoes-wholesale",
        "store",
        "manufacturer"
    ],
    "wof:name":"Shoe Dept. The 1404",
    "wof:placetype":"venue"
},
  "geometry": {"coordinates":[-89.596819,40.540345],"type":"Point"}
}