{
  "type": "Feature",
  "properties": {
    "iso:country":"US",
    "sg:address":"1817 Speckman St",
    "sg:city":"Metropolis",
    "sg:classifiers":[
        {
            "category":"Professional",
            "subcategory":"Detective & Security Services",
            "type":"Services"
        }
    ],
    "sg:phone":"+1 618 524 9089",
    "sg:postcode":"62960",
    "sg:province":"IL",
    "sg:tags":[
        "information",
        "bureau"
    ],
    "wof:name":"Jlg Transcription Service",
    "wof:placetype":"venue"
},
  "geometry": {"coordinates":[-88.734532,37.161786],"type":"Point"}
}