{
  "type": "Feature",
  "properties": {
    "iso:country":"US",
    "sg:address":"523 Millersburg Rd",
    "sg:city":"Greenville",
    "sg:phone":"+1 618 664 4279",
    "sg:postcode":"62246",
    "sg:province":"IL",
    "sg:tags":[
        "farm",
        "corn"
    ],
    "wof:name":"Michael Suess",
    "wof:placetype":"venue"
},
  "geometry": {"coordinates":[-89.45615599999999,38.819421],"type":"Point"}
}