{
  "type": "Feature",
  "properties": {
    "iso:country":"US",
    "sg:address":"767 30th St",
    "sg:city":"Rock Island",
    "sg:classifiers":[
        {
            "category":"Social Services",
            "subcategory":"Job Training",
            "type":"Services"
        }
    ],
    "sg:phone":"+1 309 794 0534",
    "sg:postcode":"61201",
    "sg:province":"IL",
    "sg:tags":[
        "rehabilitation"
    ],
    "wof:name":"Aegis Therapies",
    "wof:placetype":"venue"
},
  "geometry": {"coordinates":[-90.55691299999999,41.5042],"type":"Point"}
}