{
  "type": "Feature",
  "properties": {
    "addr:full":"3120 State St East Saint Louis IL 62205",
    "addr:housenumber":"3120",
    "addr:postcode":"62205",
    "addr:street":"State St East",
    "iso:country":"US",
    "sg:address":"3120 State St",
    "sg:city":"East Saint Louis",
    "sg:classifiers":[
        {
            "category":"Health Services",
            "subcategory":"Doctor",
            "type":"Services"
        }
    ],
    "sg:phone":"+1 618 274 3036",
    "sg:postcode":"62205",
    "sg:province":"IL",
    "wof:name":"Davis Chas L Jr MD",
    "wof:placetype":"venue"
},
  "geometry": {"coordinates":[-90.121628,38.612831],"type":"Point"}
}