{
  "type": "Feature",
  "properties": {
    "addr:full":"1801 S Lumber St Chicago IL 60616",
    "addr:housenumber":"1801",
    "addr:postcode":"60616",
    "addr:street":"S Lumber St",
    "iso:country":"US",
    "sg:address":"1801 S Lumber St",
    "sg:city":"Chicago",
    "sg:classifiers":[
        {
            "category":"Professional",
            "subcategory":"Art Services",
            "type":"Services"
        }
    ],
    "sg:phone":"+1 312 279 5400",
    "sg:postcode":"60616",
    "sg:province":"IL",
    "sg:tags":[
        "graphic",
        "commercial",
        "designer",
        "artist"
    ],
    "wof:name":"Superior Digital Graphics",
    "wof:placetype":"venue"
},
  "geometry": {"coordinates":[-87.636551,41.8577],"type":"Point"}
}