{
  "type": "Feature",
  "properties": {
    "addr:full":"131 S Dearborn Ste 210 Chicago IL 60603",
    "addr:housenumber":"131",
    "addr:postcode":"60603",
    "addr:street":"S;Ste 210",
    "iso:country":"US",
    "sg:address":"131 S Dearborn Ste 210",
    "sg:city":"Chicago",
    "sg:classifiers":[
        {
            "category":"Coffee & Tea",
            "type":"Food & Drink"
        }
    ],
    "sg:phone":"+1 312 977 0018",
    "sg:postcode":"60603",
    "sg:province":"IL",
    "wof:name":"Starbucks",
    "wof:placetype":"venue"
},
  "geometry": {"coordinates":[-87.62939900000001,41.879802],"type":"Point"}
}