{
  "type": "Feature",
  "properties": {
    "addr:full":"210 N Ladd St Pontiac IL 61764",
    "addr:housenumber":"210",
    "addr:postcode":"61764",
    "addr:street":"N Ladd St",
    "iso:country":"US",
    "sg:address":"210 N Ladd St",
    "sg:city":"Pontiac",
    "sg:classifiers":[
        {
            "category":"Insurance",
            "subcategory":"Insurance Agent",
            "type":"Services"
        },
        {
            "category":"Insurance",
            "subcategory":"Hazard Insurance",
            "type":"Services"
        },
        {
            "category":"Insurance",
            "subcategory":"Title Insurance",
            "type":"Services"
        },
        {
            "category":"Insurance",
            "subcategory":"Life Insurance",
            "type":"Services"
        }
    ],
    "sg:phone":"+1 815 844 6821",
    "sg:postcode":"61764",
    "sg:province":"IL",
    "sg:tags":[
        "business",
        "auto",
        "commercial",
        "homeowner",
        "motorcycle",
        "renter"
    ],
    "wof:name":"Allstate Insurance Company - Corey Metz",
    "wof:placetype":"venue"
},
  "geometry": {"coordinates":[-88.638069,40.879442],"type":"Point"}
}