{
  "type": "Feature",
  "properties": {
    "iso:country":"US",
    "sg:address":"1430 Broadway",
    "sg:city":"Rockford",
    "sg:classifiers":[
        {
            "category":"Autos & Motor Vehicles",
            "subcategory":"Automobile Sales",
            "type":"Retail Goods"
        }
    ],
    "sg:phone":"+1   ",
    "sg:postcode":"61104",
    "sg:province":"IL",
    "sg:tags":[
        "car",
        "used",
        "dealer"
    ],
    "wof:name":"Crooks Brothers Motor Sales",
    "wof:placetype":"venue"
},
  "geometry": {"coordinates":[-89.07499,42.252475],"type":"Point"}
}