{
  "type": "Feature",
  "properties": {
    "iso:country":"US",
    "sg:address":"408 Fairview Blvd",
    "sg:city":"Rockford",
    "sg:classifiers":[
        {
            "category":"Shopping",
            "subcategory":"Computers & Home Electronics",
            "type":"Retail Goods"
        }
    ],
    "sg:phone":"+1   ",
    "sg:postcode":"61107",
    "sg:province":"IL",
    "wof:name":"Planetevo Computer Services",
    "wof:placetype":"venue"
},
  "geometry": {"coordinates":[-89.043039,42.271536],"type":"Point"}
}